{
  "type": "Feature",
  "properties": {
    "iso:country":"US",
    "sg:address":"14 Autumn St",
    "sg:city":"Windham",
    "sg:classifiers":[
        {
            "category":"Professional",
            "subcategory":"Management & Consulting",
            "type":"Services"
        }
    ],
    "sg:phone":"+1 603 880 7764",
    "sg:postcode":"03087",
    "sg:province":"NH",
    "sg:website":"www.quality-innovations.com",
    "wof:name":"Quality Innovations",
    "wof:placetype":"venue"
},
  "geometry": {"coordinates":[-71.349785,42.782981],"type":"Point"}
}