{
  "type": "Feature",
  "properties": {
    "iso:country":"US",
    "sg:address":"25 S River Rd",
    "sg:city":"Bedford",
    "sg:classifiers":[
        {
            "category":"Personal",
            "subcategory":"Beauty Salon",
            "type":"Services"
        }
    ],
    "sg:phone":"+1 603 627 9872",
    "sg:postcode":"03110",
    "sg:province":"NH",
    "sg:tags":[
        "shop"
    ],
    "wof:name":"Hair After",
    "wof:placetype":"venue"
},
  "geometry": {"coordinates":[-71.480146,42.963048],"type":"Point"}
}