{
  "type": "Feature",
  "properties": {
    "iso:country":"US",
    "sg:address":"53 Newton Rd",
    "sg:city":"Plaistow",
    "sg:classifiers":[
        {
            "category":"Autos & Motor Vehicles",
            "subcategory":"Automobile Sales",
            "type":"Retail Goods"
        }
    ],
    "sg:phone":"+1 603 382 7322",
    "sg:postcode":"03865",
    "sg:province":"NH",
    "sg:tags":[
        "dealers-used",
        "car",
        "used",
        "cars-wholesale"
    ],
    "sg:website":"http://www.plaistowautosales.com",
    "wof:name":"Plaistow Auto Sales",
    "wof:placetype":"venue"
},
  "geometry": {"coordinates":[-71.063554,42.816601],"type":"Point"}
}