{
  "type": "Feature",
  "properties": {
    "addr:full":"16 Commerce Way Milton NH 03833",
    "addr:housenumber":"16",
    "addr:postcode":"03833",
    "addr:street":"Commerce Way",
    "iso:country":"US",
    "sg:address":"16 Commerce Way",
    "sg:city":"Milton",
    "sg:classifiers":[
        {
            "category":"Personal",
            "subcategory":"Tanning Parlor",
            "type":"Services"
        }
    ],
    "sg:phone":"+1 603 652 0901",
    "sg:postcode":"03833",
    "sg:province":"NH",
    "sg:tags":[
        "salon"
    ],
    "wof:name":"Phoenix Nail & Tanning Salon",
    "wof:placetype":"venue"
},
  "geometry": {"coordinates":[-70.964955,42.994528],"type":"Point"}
}