{
  "type": "Feature",
  "properties": {
    "addr:full":"121 State St Portsmouth NH 03801",
    "addr:housenumber":"121",
    "addr:postcode":"03801",
    "addr:street":"State St",
    "iso:country":"US",
    "sg:address":"121 State St",
    "sg:city":"Portsmouth",
    "sg:classifiers":[
        {
            "category":"Food & Beverages",
            "subcategory":"Candy",
            "type":"Retail Goods"
        }
    ],
    "sg:phone":"+1 603 559 9778",
    "sg:postcode":"03801",
    "sg:province":"NH",
    "sg:tags":[
        "confectionery"
    ],
    "wof:name":"Byrne & Carlson Chocolatier",
    "wof:placetype":"venue"
},
  "geometry": {"coordinates":[-70.754519,43.077182],"type":"Point"}
}