{
  "type": "Feature",
  "properties": {
    "iso:country":"US",
    "sg:address":"100 Factory St",
    "sg:city":"Nashua",
    "sg:classifiers":[
        {
            "category":"Education",
            "subcategory":"Dance Studio",
            "type":"Public Place"
        }
    ],
    "sg:phone":"+1 603 886 7989",
    "sg:postcode":"03060",
    "sg:province":"NH",
    "sg:tags":[
        "instruction",
        "dancing"
    ],
    "wof:name":"Jeannine's Dance Stoppe",
    "wof:placetype":"venue"
},
  "geometry": {"coordinates":[-71.468745,42.760458],"type":"Point"}
}