{
  "type": "Feature",
  "properties": {
    "addr:full":"381 Main Dunstable Rd Nashua NH 03062",
    "addr:housenumber":"381",
    "addr:postcode":"03062",
    "addr:street":"Main Dunstable Rd",
    "iso:country":"US",
    "sg:address":"381 Main Dunstable Rd",
    "sg:city":"Nashua",
    "sg:classifiers":[
        {
            "category":"Retail",
            "subcategory":"Auto Repair",
            "type":"Services"
        }
    ],
    "sg:phone":"+1 603 883 1890",
    "sg:postcode":"03062",
    "sg:province":"NH",
    "sg:tags":[
        "body",
        "painting",
        "repairing",
        "automobile"
    ],
    "wof:name":"J P Jr's Auto Body",
    "wof:placetype":"venue"
},
  "geometry": {"coordinates":[-71.502792,42.72813],"type":"Point"}
}