{
  "type": "Feature",
  "properties": {
    "iso:country":"US",
    "sg:address":"54 Mill St",
    "sg:city":"Greenville",
    "sg:classifiers":[
        {
            "category":"Building & Trades",
            "subcategory":"Construction",
            "type":"Services"
        }
    ],
    "sg:phone":"+1 603 878 3725",
    "sg:postcode":"03048",
    "sg:province":"NH",
    "sg:tags":[
        "home",
        "improvement"
    ],
    "wof:name":"Gardeners Hauling & Odd Jobs",
    "wof:placetype":"venue"
},
  "geometry": {"coordinates":[-71.80786999999999,42.768619],"type":"Point"}
}