{
  "type": "Feature",
  "properties": {
    "iso:country":"US",
    "sg:address":"32 Rochester Ave",
    "sg:city":"Portsmouth",
    "sg:classifiers":[
        {
            "category":"Utilities",
            "subcategory":"Telephone",
            "type":"Services"
        }
    ],
    "sg:phone":"+1 603 334 0710",
    "sg:postcode":"03801",
    "sg:province":"NH",
    "sg:tags":[
        "communications",
        "retrieval",
        "information"
    ],
    "wof:name":"Si International Inc",
    "wof:placetype":"venue"
},
  "geometry": {"coordinates":[-70.809774,43.08042],"type":"Point"}
}