{
  "type": "Feature",
  "properties": {
    "addr:full":"7 McDaniels Dr Brookline NH 03033",
    "addr:housenumber":"7",
    "addr:postcode":"03033",
    "addr:street":"Mcdaniels Dr",
    "iso:country":"US",
    "sg:address":"7 McDaniels Dr",
    "sg:city":"Brookline",
    "sg:classifiers":[
        {
            "category":"Building & Trades",
            "subcategory":"Plumbing",
            "type":"Services"
        }
    ],
    "sg:phone":"+1 603 672 2735",
    "sg:postcode":"03033",
    "sg:province":"NH",
    "sg:tags":[
        "contractor"
    ],
    "wof:name":"Riverview Heating & AC",
    "wof:placetype":"venue"
},
  "geometry": {"coordinates":[-71.66266,42.764835],"type":"Point"}
}