{
  "type": "Feature",
  "properties": {
    "iso:country":"US",
    "sg:address":"130 Branch Rd",
    "sg:city":"Roxbury",
    "sg:classifiers":[
        {
            "category":"Retail",
            "subcategory":"Auto Repair",
            "type":"Services"
        }
    ],
    "sg:phone":"+1 603 352 8813",
    "sg:postcode":"03431",
    "sg:province":"NH",
    "sg:tags":[
        "automobile",
        "restoration",
        "classic"
    ],
    "wof:name":"Moons Classics",
    "wof:placetype":"venue"
},
  "geometry": {"coordinates":[-72.239042,42.924259],"type":"Point"}
}