{
  "type": "Feature",
  "properties": {
    "iso:country":"US",
    "sg:address":"9 Bennett Way",
    "sg:city":"Newmarket",
    "sg:classifiers":[
        {
            "category":"Professional",
            "subcategory":"Computer Services",
            "type":"Services"
        }
    ],
    "sg:phone":"+1 603 659 8428",
    "sg:postcode":"03857",
    "sg:province":"NH",
    "sg:tags":[
        "programing",
        "custom"
    ],
    "wof:name":"Poraiyan Rajesh Kannan",
    "wof:placetype":"venue"
},
  "geometry": {"coordinates":[-70.941446,43.070685],"type":"Point"}
}