{
  "type": "Feature",
  "properties": {
    "addr:full":"156 Harvey Rd Londonderry NH 03053",
    "addr:housenumber":"156",
    "addr:postcode":"03053",
    "addr:street":"Harvey Rd",
    "iso:country":"US",
    "sg:address":"156 Harvey Rd",
    "sg:city":"Londonderry",
    "sg:classifiers":[
        {
            "category":"Health Services",
            "subcategory":"Doctor",
            "type":"Services"
        }
    ],
    "sg:phone":"+1 603 644 3330",
    "sg:postcode":"03053",
    "sg:province":"NH",
    "sg:tags":[
        "medical"
    ],
    "wof:name":"Occuptonal Hlth Rehabilitation",
    "wof:placetype":"venue"
},
  "geometry": {"coordinates":[-71.424071,42.926038],"type":"Point"}
}