{
  "type": "Feature",
  "properties": {
    "addr:full":"114 Pleasant St Claremont NH 03743",
    "addr:housenumber":"114",
    "addr:postcode":"03743",
    "addr:street":"Pleasant St",
    "iso:country":"US",
    "sg:address":"114 Pleasant St",
    "sg:city":"Claremont",
    "sg:classifiers":[
        {
            "category":"Autos & Motor Vehicles",
            "subcategory":"Fuel & Gas Station",
            "type":"Retail Goods"
        }
    ],
    "sg:phone":"+1 603 542 2278",
    "sg:postcode":"03743",
    "sg:province":"NH",
    "sg:tags":[
        "oil"
    ],
    "wof:name":"Mobil",
    "wof:placetype":"venue"
},
  "geometry": {"coordinates":[-72.340001,43.368886],"type":"Point"}
}