{
  "type": "Feature",
  "properties": {
    "addr:full":"16 Post Pond Ln Lyme NH 03768",
    "addr:housenumber":"16",
    "addr:postcode":"03768",
    "addr:street":"Post Pond Ln",
    "iso:country":"US",
    "sg:address":"16 Post Pond Ln",
    "sg:city":"Lyme",
    "sg:classifiers":[
        {
            "category":"Building & Trades",
            "subcategory":"Cleaning & Sanitation",
            "type":"Services"
        }
    ],
    "sg:phone":"+1 603 795 4296",
    "sg:postcode":"03768",
    "sg:province":"NH",
    "sg:tags":[
        "maintenance"
    ],
    "wof:name":"Prime Property Maintenance",
    "wof:placetype":"venue"
},
  "geometry": {"coordinates":[-72.15097900000001,43.836949],"type":"Point"}
}