{
  "type": "Feature",
  "properties": {
    "iso:country":"US",
    "sg:address":"164 Endicott St N",
    "sg:city":"Laconia",
    "sg:classifiers":[
        {
            "category":"Building & Trades",
            "subcategory":"Construction",
            "type":"Services"
        }
    ],
    "sg:phone":"+1 603 366 5490",
    "sg:postcode":"03246",
    "sg:province":"NH",
    "sg:tags":[
        "nonresidential"
    ],
    "wof:name":"L G & L B Sitework",
    "wof:placetype":"venue"
},
  "geometry": {"coordinates":[-71.46326999999999,43.605413],"type":"Point"}
}