{
  "type": "Feature",
  "properties": {
    "addr:full":"38 Hubbard Pond Rd New Ipswich NH 03071",
    "addr:housenumber":"38",
    "addr:postcode":"03071",
    "addr:street":"Hubbard Pond Rd",
    "iso:country":"US",
    "sg:address":"38 Hubbard Pond Rd",
    "sg:city":"New Ipswich",
    "sg:classifiers":[
        {
            "category":"Banks & Credit Unions",
            "subcategory":"Financial Services",
            "type":"Services"
        }
    ],
    "sg:phone":"+1 603 878 1266",
    "sg:postcode":"03071",
    "sg:province":"NH",
    "sg:tags":[
        "company",
        "holding"
    ],
    "wof:name":"Dew Real Estate & Holdg Entps",
    "wof:placetype":"venue"
},
  "geometry": {"coordinates":[-71.929451,42.774259],"type":"Point"}
}