{
  "type": "Feature",
  "properties": {
    "addr:full":"2 Tracy Ln Hudson NH 03051",
    "addr:housenumber":"2",
    "addr:postcode":"03051",
    "addr:street":"Tracy Ln",
    "iso:country":"US",
    "sg:address":"2 Tracy Ln",
    "sg:city":"Hudson",
    "sg:classifiers":[
        {
            "category":"Food & Beverages",
            "subcategory":"Groceries & Convenience Stores",
            "type":"Retail Goods"
        }
    ],
    "sg:phone":"+1 603 595 7301",
    "sg:postcode":"03051",
    "sg:province":"NH",
    "wof:name":"Patriot Convenience",
    "wof:placetype":"venue"
},
  "geometry": {"coordinates":[-71.41169499999999,42.822303],"type":"Point"}
}