{
  "type": "Feature",
  "properties": {
    "addr:full":"360 Pleasant Valley Rd Wolfeboro NH 03894",
    "addr:housenumber":"360",
    "addr:postcode":"03894",
    "addr:street":"Pleasant Valley Rd",
    "iso:country":"US",
    "sg:address":"360 Pleasant Valley Rd",
    "sg:city":"Wolfeboro",
    "sg:classifiers":[
        {
            "category":"Building & Trades",
            "subcategory":"Construction",
            "type":"Services"
        },
        {
            "category":"Professional",
            "subcategory":"Accounting & Tax Preparation",
            "type":"Services"
        }
    ],
    "sg:phone":"+1 603 569 4781",
    "sg:postcode":"03894",
    "sg:province":"NH",
    "sg:tags":[
        "general",
        "return",
        "contractor"
    ],
    "sg:website":"www.fmblodget.com",
    "wof:name":"F M Blodget",
    "wof:placetype":"venue"
},
  "geometry": {"coordinates":[-71.159674,43.580228],"type":"Point"}
}