{
  "type": "Feature",
  "properties": {
    "iso:country":"US",
    "sg:address":"55 Essex Rd",
    "sg:city":"Bedford",
    "sg:classifiers":[
        {
            "category":"Building & Trades",
            "subcategory":"Cleaning & Sanitation",
            "type":"Services"
        }
    ],
    "sg:phone":"+1 603 471 9131",
    "sg:postcode":"03110",
    "sg:province":"NH",
    "sg:tags":[
        "janitorial"
    ],
    "wof:name":"Tbh Services Company",
    "wof:placetype":"venue"
},
  "geometry": {"coordinates":[-71.556682,42.967935],"type":"Point"}
}