{
  "type": "Feature",
  "properties": {
    "iso:country":"US",
    "sg:address":"58 Seaverns Bridge Rd",
    "sg:city":"Amherst",
    "sg:classifiers":[
        {
            "category":"Home & Garden",
            "subcategory":"Garden Supply",
            "type":"Retail Goods"
        }
    ],
    "sg:phone":"+1 603 424 2300",
    "sg:postcode":"03031",
    "sg:province":"NH",
    "wof:name":"Perennials From Susan",
    "wof:placetype":"venue"
},
  "geometry": {"coordinates":[-71.56183299999999,42.820705],"type":"Point"}
}