{
  "type": "Feature",
  "properties": {
    "iso:country":"US",
    "sg:address":"67 Ridgefield Dr",
    "sg:city":"Milford",
    "sg:classifiers":[
        {
            "category":"Banks & Credit Unions",
            "subcategory":"Investment Brokerage",
            "type":"Services"
        }
    ],
    "sg:phone":"+1 603 673 4448",
    "sg:postcode":"03055",
    "sg:province":"NH",
    "sg:tags":[
        "advisory"
    ],
    "wof:name":"Daudier Investments",
    "wof:placetype":"venue"
},
  "geometry": {"coordinates":[-71.674606,42.838348],"type":"Point"}
}