{
  "type": "Feature",
  "properties": {
    "iso:country":"US",
    "sg:address":"17 Wilder St",
    "sg:city":"Keene",
    "sg:classifiers":[
        {
            "category":"Professional",
            "subcategory":"Accounting & Tax Preparation",
            "type":"Services"
        }
    ],
    "sg:phone":"+1 603 352 2233",
    "sg:postcode":"03431",
    "sg:province":"NH",
    "sg:tags":[
        "accountant"
    ],
    "wof:name":"James A Hogancamp & Assoc",
    "wof:placetype":"venue"
},
  "geometry": {"coordinates":[-72.28433099999999,42.932789],"type":"Point"}
}