{
  "type": "Feature",
  "properties": {
    "addr:full":"10 Erin Ln Derry NH 03038",
    "addr:housenumber":"10",
    "addr:postcode":"03038",
    "addr:street":"Erin Ln",
    "iso:country":"US",
    "sg:address":"10 Erin Ln",
    "sg:city":"Derry",
    "sg:classifiers":[
        {
            "category":"Health Services",
            "subcategory":"Medical Lab",
            "type":"Services"
        }
    ],
    "sg:phone":"+1 603 437 0176",
    "sg:postcode":"03038",
    "sg:province":"NH",
    "sg:tags":[
        "laboratory"
    ],
    "wof:name":"Clinical Evidence Consulting",
    "wof:placetype":"venue"
},
  "geometry": {"coordinates":[-71.231264,42.900011],"type":"Point"}
}