{
  "type": "Feature",
  "properties": {
    "iso:country":"US",
    "sg:address":"542 Amherst Street Route 101A",
    "sg:city":"Nashua",
    "sg:classifiers":[
        {
            "category":"Professional",
            "subcategory":"Computer Services",
            "type":"Services"
        }
    ],
    "sg:phone":"+1 603 594 0249",
    "sg:postcode":"03063 ",
    "sg:province":"NH",
    "sg:website":"http://www.ektron.com/",
    "wof:name":"Ektron",
    "wof:placetype":"venue"
},
  "geometry": {"coordinates":[-71.528716,42.796065],"type":"Point"}
}