{
  "type": "Feature",
  "properties": {
    "addr:full":"2224 E Conway Rd North Conway NH 03813",
    "addr:housenumber":"2224",
    "addr:postcode":"03813",
    "addr:street":"E Conway Rd",
    "iso:country":"US",
    "sg:address":"2224 E Conway Rd",
    "sg:city":"North Conway",
    "sg:classifiers":[
        {
            "category":"Shopping",
            "subcategory":"Bicycles & Sporting Goods",
            "type":"Retail Goods"
        }
    ],
    "sg:phone":"+1 603 356 3133",
    "sg:postcode":"03813",
    "sg:province":"NH",
    "sg:tags":[
        "equipment",
        "skiing"
    ],
    "wof:name":"Sports Outlet",
    "wof:placetype":"venue"
},
  "geometry": {"coordinates":[-71.059583,44.011259],"type":"Point"}
}