{
  "type": "Feature",
  "properties": {
    "iso:country":"US",
    "sg:address":"237 Central Ave",
    "sg:city":"Dover",
    "sg:classifiers":[
        {
            "category":"Retail",
            "subcategory":"Car Wash",
            "type":"Services"
        }
    ],
    "sg:phone":"+1 603 742 0037",
    "sg:postcode":"03820",
    "sg:province":"NH",
    "sg:tags":[
        "polishing",
        "washing"
    ],
    "wof:name":"Southside Getty & Car Wash",
    "wof:placetype":"venue"
},
  "geometry": {"coordinates":[-70.87327999999999,43.19274],"type":"Point"}
}