{
  "type": "Feature",
  "properties": {
    "iso:country":"US",
    "sg:address":"2 1st St",
    "sg:city":"Plymouth",
    "sg:classifiers":[
        {
            "category":"Government",
            "subcategory":"Office",
            "type":"Public Place"
        }
    ],
    "sg:phone":"+1 603 536 2700",
    "sg:postcode":"03264",
    "sg:province":"NH",
    "sg:tags":[
        "executive"
    ],
    "wof:name":"Main Street Plymouth Inc",
    "wof:placetype":"venue"
},
  "geometry": {"coordinates":[-71.690456,43.752087],"type":"Point"}
}