{
  "type": "Feature",
  "properties": {
    "iso:country":"US",
    "sg:address":"311 Pako Ave",
    "sg:city":"Keene",
    "sg:classifiers":[
        {
            "category":"Professional",
            "subcategory":"Testing Lab",
            "type":"Services"
        }
    ],
    "sg:phone":"+1 603 352 5815",
    "sg:postcode":"03431",
    "sg:province":"NH",
    "sg:tags":[
        "correction",
        "radon"
    ],
    "wof:name":"Twin State Home Inspection",
    "wof:placetype":"venue"
},
  "geometry": {"coordinates":[-72.320138,42.959169],"type":"Point"}
}