{
  "type": "Feature",
  "properties": {
    "addr:full":"20 Worthley Rd Manchester NH 03102",
    "addr:housenumber":"20",
    "addr:postcode":"03102",
    "addr:street":"Worthley Rd",
    "iso:country":"US",
    "sg:address":"20 Worthley Rd",
    "sg:city":"Manchester",
    "sg:classifiers":[
        {
            "category":"Building & Trades",
            "subcategory":"Construction",
            "type":"Services"
        }
    ],
    "sg:phone":"+1 603 647 5948",
    "sg:postcode":"03102",
    "sg:province":"NH",
    "sg:tags":[
        "residential"
    ],
    "wof:name":"Flagstone Properties Inc",
    "wof:placetype":"venue"
},
  "geometry": {"coordinates":[-71.493155,42.979892],"type":"Point"}
}