{
  "type": "Feature",
  "properties": {
    "iso:country":"US",
    "sg:address":"46 Noyes Rd",
    "sg:city":"Londonderry",
    "sg:classifiers":[
        {
            "category":"Building & Trades",
            "subcategory":"Construction",
            "type":"Services"
        }
    ],
    "sg:phone":"+1 603 432 2589",
    "sg:postcode":"03053",
    "sg:province":"NH",
    "sg:tags":[
        "house",
        "nonresidential"
    ],
    "wof:name":"Bristol Construction LLC",
    "wof:placetype":"venue"
},
  "geometry": {"coordinates":[-71.383206,42.911961],"type":"Point"}
}