{
  "type": "Feature",
  "properties": {
    "addr:full":"1 Old Dover Rd Rochester NH 03867",
    "addr:housenumber":"1",
    "addr:postcode":"03867",
    "addr:street":"Old Dover Rd",
    "iso:country":"US",
    "sg:address":"1 Old Dover Rd",
    "sg:city":"Rochester",
    "sg:classifiers":[
        {
            "category":"Health Services",
            "subcategory":"Health Practitioner",
            "type":"Services"
        }
    ],
    "sg:phone":"+1 603 332 4447",
    "sg:postcode":"03867",
    "sg:province":"NH",
    "sg:tags":[
        "psychologist"
    ],
    "wof:name":"Solutions For Living LLC",
    "wof:placetype":"venue"
},
  "geometry": {"coordinates":[-70.974272,43.290108],"type":"Point"}
}