{
  "type": "Feature",
  "properties": {
    "addr:full":"33 Geremonty Dr Salem NH 03079",
    "addr:housenumber":"33",
    "addr:postcode":"03079",
    "addr:street":"Geremonty Dr",
    "iso:country":"US",
    "sg:address":"33 Geremonty Dr",
    "sg:city":"Salem",
    "sg:classifiers":[
        {
            "category":"Government",
            "subcategory":"Office",
            "type":"Public Place"
        }
    ],
    "sg:phone":"+1 603 890 2000",
    "sg:postcode":"03079",
    "sg:province":"NH",
    "sg:tags":[
        "town",
        "administration"
    ],
    "wof:name":"Town of Salem",
    "wof:placetype":"venue"
},
  "geometry": {"coordinates":[-71.210536,42.777688],"type":"Point"}
}