{
  "type": "Feature",
  "properties": {
    "addr:full":"340 Commercial St Manchester NH 03101",
    "addr:housenumber":"340",
    "addr:postcode":"03101",
    "addr:street":"Commercial St",
    "iso:country":"US",
    "sg:address":"340 Commercial St",
    "sg:city":"Manchester",
    "sg:classifiers":[
        {
            "category":"Wholesale",
            "subcategory":"Electrical",
            "type":"Manufacturing & Wholesale Goods"
        }
    ],
    "sg:phone":"+1 603 626 0701",
    "sg:postcode":"03101",
    "sg:province":"NH",
    "sg:tags":[
        "equipment"
    ],
    "wof:name":"Siemens Energy & Automation",
    "wof:placetype":"venue"
},
  "geometry": {"coordinates":[-71.46767199999999,42.991842],"type":"Point"}
}