{
  "type": "Feature",
  "properties": {
    "iso:country":"US",
    "sg:address":"13 Newton Junction Rd",
    "sg:city":"Kingston",
    "sg:classifiers":[
        {
            "category":"Building & Trades",
            "subcategory":"Plumbing",
            "type":"Services"
        }
    ],
    "sg:phone":"+1 603 642 7705",
    "sg:postcode":"03848",
    "sg:province":"NH",
    "sg:tags":[
        "plumbing",
        "contractor"
    ],
    "wof:name":"John Bartlett Jr Plbg & Htg",
    "wof:placetype":"venue"
},
  "geometry": {"coordinates":[-71.08015899999999,42.880155],"type":"Point"}
}