{
  "type": "Feature",
  "properties": {
    "iso:country":"US",
    "sg:address":"65 Chamberlain St",
    "sg:city":"Rochester",
    "sg:classifiers":[
        {
            "category":"Education",
            "subcategory":"School",
            "type":"Public Place"
        }
    ],
    "sg:phone":"+1 603 332 5258",
    "sg:postcode":"03867",
    "sg:province":"NH",
    "wof:name":"Chamberlain Street Elem Sch",
    "wof:placetype":"venue"
},
  "geometry": {"coordinates":[-70.94655899999999,43.299381],"type":"Point"}
}