{
  "type": "Feature",
  "properties": {
    "addr:full":"2 Rebel Rd Hudson NH 03051",
    "addr:housenumber":"2",
    "addr:postcode":"03051",
    "addr:street":"Rebel Rd",
    "iso:country":"US",
    "sg:address":"2 Rebel Rd",
    "sg:city":"Hudson",
    "sg:classifiers":[
        {
            "category":"Autos & Motor Vehicles",
            "subcategory":"Automobile Sales",
            "type":"Retail Goods"
        }
    ],
    "sg:phone":"+1 603 889 3433",
    "sg:postcode":"03051",
    "sg:province":"NH",
    "sg:tags":[
        "car",
        "dealer"
    ],
    "wof:name":"Auto Outlet",
    "wof:placetype":"venue"
},
  "geometry": {"coordinates":[-71.407467,42.822959],"type":"Point"}
}