{
  "type": "Feature",
  "properties": {
    "iso:country":"US",
    "sg:address":"231 Water St",
    "sg:city":"Exeter",
    "sg:classifiers":[
        {
            "category":"Real Estate",
            "subcategory":"Real Estate Agent",
            "type":"Services"
        }
    ],
    "sg:phone":"+1 603 778 0773",
    "sg:postcode":"03833",
    "sg:province":"NH",
    "sg:website":"www.milburyrealestate.com",
    "wof:name":"Milbury Associates Inc",
    "wof:placetype":"venue"
},
  "geometry": {"coordinates":[-70.949955,42.981859],"type":"Point"}
}