{
  "type": "Feature",
  "properties": {
    "iso:country":"US",
    "sg:address":"7 Brookside Ln",
    "sg:city":"Newton",
    "sg:classifiers":[
        {
            "category":"Building & Trades",
            "subcategory":"Plumbing",
            "type":"Services"
        }
    ],
    "sg:phone":"+1 603 382 4707",
    "sg:postcode":"03858",
    "sg:province":"NH",
    "sg:tags":[
        "contractor"
    ],
    "wof:name":"Bd Plumbing",
    "wof:placetype":"venue"
},
  "geometry": {"coordinates":[-71.010566,42.876787],"type":"Point"}
}