{
  "type": "Feature",
  "properties": {
    "addr:full":"54 Lesmerises Rd Loudon NH 03307",
    "addr:housenumber":"54",
    "addr:postcode":"03307",
    "addr:street":"Lesmerises Rd",
    "iso:country":"US",
    "sg:address":"54 Lesmerises Rd",
    "sg:city":"Loudon",
    "sg:classifiers":[
        {
            "category":"Building & Trades",
            "subcategory":"Construction",
            "type":"Services"
        }
    ],
    "sg:phone":"+1 603 783 4640",
    "sg:postcode":"03307",
    "sg:province":"NH",
    "sg:tags":[
        "painter"
    ],
    "wof:name":"Drake's Painting",
    "wof:placetype":"venue"
},
  "geometry": {"coordinates":[-71.47762400000001,43.308016],"type":"Point"}
}