{
  "type": "Feature",
  "properties": {
    "addr:full":"1264 Old Homestead Hwy Swanzey NH 03446",
    "addr:housenumber":"1264",
    "addr:postcode":"03446",
    "addr:street":"Old Homestead Hwy",
    "iso:country":"US",
    "sg:address":"1264 Old Homestead Hwy",
    "sg:city":"Swanzey",
    "sg:classifiers":[
        {
            "category":"Professional",
            "subcategory":"Engineering",
            "type":"Services"
        },
        {
            "category":"Wholesale",
            "subcategory":"Machinery & Supplies",
            "type":"Manufacturing & Wholesale Goods"
        },
        {
            "category":"Restaurant",
            "type":"Food & Drink"
        },
        {
            "category":"Building & Trades",
            "subcategory":"Construction",
            "type":"Services"
        },
        {
            "category":"Home & Garden",
            "subcategory":"Household Appliances",
            "type":"Retail Goods"
        }
    ],
    "sg:phone":"+1 603 352 9901",
    "sg:postcode":"03446",
    "sg:province":"NH",
    "sg:tags":[
        "equipment-commercial",
        "dishwashing",
        "supplies-refrigeration",
        "system",
        "contractor",
        "machine",
        "equipment",
        "industrial",
        "refrigeration",
        "air conditioning",
        "engineer"
    ],
    "wof:name":"Zitta Refrigeration & Air Conditioning Services",
    "wof:placetype":"venue"
},
  "geometry": {"coordinates":[-72.27298,42.828062],"type":"Point"}
}