{
  "type": "Feature",
  "properties": {
    "iso:country":"US",
    "sg:address":"1 Taylor River Ests",
    "sg:city":"Hampton",
    "sg:classifiers":[
        {
            "category":"Building & Trades",
            "subcategory":"Construction",
            "type":"Services"
        }
    ],
    "sg:phone":"+1 603 926 7724",
    "sg:postcode":"03842",
    "sg:province":"NH",
    "sg:tags":[
        "concrete",
        "contractor"
    ],
    "wof:name":"Perkins Al Concrete LLC",
    "wof:placetype":"venue"
},
  "geometry": {"coordinates":[-70.87065200000001,42.940203],"type":"Point"}
}