{
  "type": "Feature",
  "properties": {
    "iso:country":"US",
    "sg:address":"1 School St",
    "sg:city":"Amherst",
    "sg:classifiers":[
        {
            "category":"Education",
            "subcategory":"School",
            "type":"Public Place"
        }
    ],
    "sg:phone":"+1 603 673 2690",
    "sg:postcode":"03031",
    "sg:province":"NH",
    "wof:name":"Mont Vernon School Dept",
    "wof:placetype":"venue"
},
  "geometry": {"coordinates":[-71.626296,42.864107],"type":"Point"}
}