{
  "type": "Feature",
  "properties": {
    "addr:full":"69 Pike St Nashua NH 03060",
    "addr:housenumber":"69",
    "addr:postcode":"03060",
    "addr:street":"Pike St",
    "iso:country":"US",
    "sg:address":"69 Pike St",
    "sg:city":"Nashua",
    "sg:classifiers":[
        {
            "category":"Insurance",
            "subcategory":"Insurance Agent",
            "type":"Services"
        }
    ],
    "sg:phone":"+1 603 888 5896",
    "sg:postcode":"03060",
    "sg:province":"NH",
    "wof:name":"Porta Medic",
    "wof:placetype":"venue"
},
  "geometry": {"coordinates":[-71.452167,42.733829],"type":"Point"}
}