{
  "type": "Feature",
  "properties": {
    "addr:full":"53 E Pearl St Nashua NH 03060",
    "addr:housenumber":"53",
    "addr:postcode":"03060",
    "addr:street":"E Pearl St",
    "iso:country":"US",
    "sg:address":"53 E Pearl St",
    "sg:city":"Nashua",
    "sg:classifiers":[
        {
            "category":"Professional",
            "subcategory":"Lawyer & Legal Services",
            "type":"Services"
        }
    ],
    "sg:phone":"+1 603 883 3379",
    "sg:postcode":"03060",
    "sg:province":"NH",
    "sg:tags":[
        "attorney"
    ],
    "wof:name":"Clancy & O'Neill",
    "wof:placetype":"venue"
},
  "geometry": {"coordinates":[-71.464823,42.760352],"type":"Point"}
}