{
  "type": "Feature",
  "properties": {
    "iso:country":"US",
    "sg:address":"751 Portsmouth Ave",
    "sg:city":"Greenland",
    "sg:classifiers":[
        {
            "category":"Autos & Motor Vehicles",
            "subcategory":"Auto Supplies",
            "type":"Retail Goods"
        }
    ],
    "sg:phone":"+1 603 742 5666",
    "sg:postcode":"03840",
    "sg:province":"NH",
    "sg:tags":[
        "automobile",
        "stereo",
        "radio"
    ],
    "sg:website":"www.speedofsound.net",
    "wof:name":"At The Speed Of Sound",
    "wof:placetype":"venue"
},
  "geometry": {"coordinates":[-70.850607,43.035621],"type":"Point"}
}