{
  "type": "Feature",
  "properties": {
    "addr:full":"4 Hall St Concord NH 03301",
    "addr:housenumber":"4",
    "addr:postcode":"03301",
    "addr:street":"Hall St",
    "iso:country":"US",
    "sg:address":"4 Hall St",
    "sg:city":"Concord",
    "sg:classifiers":[
        {
            "category":"Shopping",
            "subcategory":"Computers & Home Electronics",
            "type":"Retail Goods"
        }
    ],
    "sg:phone":"+1 603 228 1641",
    "sg:postcode":"03301",
    "sg:province":"NH",
    "sg:tags":[
        "game",
        "video"
    ],
    "wof:name":"Game Zone",
    "wof:placetype":"venue"
},
  "geometry": {"coordinates":[-71.528059,43.194154],"type":"Point"}
}