{
  "type": "Feature",
  "properties": {
    "addr:full":"9 School St Peterborough NH 03458",
    "addr:housenumber":"9",
    "addr:postcode":"03458",
    "addr:street":"School St",
    "iso:country":"US",
    "sg:address":"9 School St",
    "sg:city":"Peterborough",
    "sg:classifiers":[
        {
            "category":"Shopping",
            "subcategory":"Jewelry",
            "type":"Retail Goods"
        }
    ],
    "sg:phone":"+1 603 924 0902",
    "sg:postcode":"03458",
    "sg:province":"NH",
    "sg:tags":[
        "designer"
    ],
    "wof:name":"Cullinan Seana Jewelry",
    "wof:placetype":"venue"
},
  "geometry": {"coordinates":[-71.949979,42.876525],"type":"Point"}
}