{
  "type": "Feature",
  "properties": {
    "iso:country":"US",
    "sg:address":"1529 E Conway Rd",
    "sg:city":"North Conway",
    "sg:classifiers":[
        {
            "category":"Home & Garden",
            "subcategory":"Household Appliances",
            "type":"Retail Goods"
        }
    ],
    "sg:phone":"+1 603 356 3434",
    "sg:postcode":"03813",
    "sg:province":"NH",
    "sg:tags":[
        "cleaners",
        "vacuum"
    ],
    "wof:name":"Due North Sew & Vac",
    "wof:placetype":"venue"
},
  "geometry": {"coordinates":[-71.035687,44.00068],"type":"Point"}
}