{
  "type": "Feature",
  "properties": {
    "addr:full":"19 Ralston St Keene NH 03431",
    "addr:housenumber":"19",
    "addr:postcode":"03431",
    "addr:street":"Ralston St",
    "iso:country":"US",
    "sg:address":"19 Ralston St",
    "sg:city":"Keene",
    "sg:classifiers":[
        {
            "category":"Manufacturing",
            "subcategory":"Printing",
            "type":"Manufacturing & Wholesale Goods"
        }
    ],
    "sg:phone":"+1 603 357 1513",
    "sg:postcode":"03431",
    "sg:province":"NH",
    "sg:tags":[
        "printer"
    ],
    "wof:name":"Braden Printing",
    "wof:placetype":"venue"
},
  "geometry": {"coordinates":[-72.28332,42.929736],"type":"Point"}
}