{
  "type": "Feature",
  "properties": {
    "iso:country":"US",
    "sg:address":"49 High St",
    "sg:city":"Exeter",
    "sg:classifiers":[
        {
            "category":"Personal",
            "subcategory":"Beauty Salon",
            "type":"Services"
        }
    ],
    "sg:phone":"+1 603 778 2111",
    "sg:postcode":"03833",
    "sg:province":"NH",
    "wof:name":"Be Free Hair Electrology",
    "wof:placetype":"venue"
},
  "geometry": {"coordinates":[-70.940946,42.980723],"type":"Point"}
}