{
  "type": "Feature",
  "properties": {
    "addr:full":"3 Main St Atkinson NH 03811",
    "addr:housenumber":"3",
    "addr:postcode":"03811",
    "addr:street":"Main St",
    "iso:country":"US",
    "sg:address":"3 Main St",
    "sg:city":"Atkinson",
    "sg:classifiers":[
        {
            "category":"Restaurant",
            "type":"Food & Drink"
        },
        {
            "category":"Wholesale",
            "subcategory":"Dairy",
            "type":"Manufacturing & Wholesale Goods"
        }
    ],
    "sg:phone":"+1 603 362 8223",
    "sg:postcode":"03811",
    "sg:province":"NH",
    "sg:tags":[
        "product",
        "parlor",
        "ice",
        "cream"
    ],
    "wof:name":"Stillwell's Ice Cream",
    "wof:placetype":"venue"
},
  "geometry": {"coordinates":[-71.116918,42.819488],"type":"Point"}
}