{
  "type": "Feature",
  "properties": {
    "iso:country":"US",
    "sg:address":"111 Pillsbury Rd",
    "sg:city":"Londonderry",
    "sg:classifiers":[
        {
            "category":"Building & Trades",
            "subcategory":"Construction",
            "type":"Services"
        }
    ],
    "sg:phone":"+1 603 434 8146",
    "sg:postcode":"03053",
    "sg:province":"NH",
    "sg:tags":[
        "house"
    ],
    "wof:name":"Woodys Home Repair & Imprv",
    "wof:placetype":"venue"
},
  "geometry": {"coordinates":[-71.36223099999999,42.87283],"type":"Point"}
}