{
  "type": "Feature",
  "properties": {
    "iso:country":"US",
    "sg:address":"18 Clinton Dr",
    "sg:city":"Hollis",
    "sg:classifiers":[
        {
            "category":"Wholesale",
            "subcategory":"Construction Materials",
            "type":"Manufacturing & Wholesale Goods"
        }
    ],
    "sg:phone":"+1 603 883 0500",
    "sg:postcode":"03049",
    "sg:province":"NH",
    "sg:tags":[
        "building",
        "insulation",
        "product"
    ],
    "wof:name":"Liberty Architectural Sales",
    "wof:placetype":"venue"
},
  "geometry": {"coordinates":[-71.553062,42.709186],"type":"Point"}
}