{
  "type": "Feature",
  "properties": {
    "addr:full":"510 Harvey Rd Manchester NH 03103",
    "addr:housenumber":"510",
    "addr:postcode":"03103",
    "addr:street":"Harvey Rd",
    "iso:country":"US",
    "sg:address":"510 Harvey Rd",
    "sg:city":"Manchester",
    "sg:classifiers":[
        {
            "category":"Restaurant",
            "type":"Food & Drink"
        }
    ],
    "sg:phone":"+1 603 641 3973",
    "sg:postcode":"03103",
    "sg:province":"NH",
    "wof:name":"Dunkin Donuts",
    "wof:placetype":"venue"
},
  "geometry": {"coordinates":[-71.42926,42.941994],"type":"Point"}
}