{
  "type": "Feature",
  "properties": {
    "addr:full":"14 Lilac Mall Rochester NH 03867",
    "addr:housenumber":"14",
    "addr:postcode":"03867",
    "addr:street":"Lilac Mall",
    "iso:country":"US",
    "sg:address":"14 Lilac Mall",
    "sg:city":"Rochester",
    "sg:classifiers":[
        {
            "category":"Restaurant",
            "type":"Food & Drink"
        }
    ],
    "sg:menulink":"http://www.allmenus.com/nh/rochester/129638-subway/menu/",
    "sg:phone":"+1 603 332 9666",
    "sg:postcode":"03867",
    "sg:province":"NH",
    "sg:tags":[
        "american",
        "sandwich"
    ],
    "wof:name":"Subway",
    "wof:placetype":"venue"
},
  "geometry": {"coordinates":[-70.975381,43.319432],"type":"Point"}
}