{
  "type": "Feature",
  "properties": {
    "addr:full":"31 Milton Rd Rochester NH 03868",
    "addr:housenumber":"31",
    "addr:postcode":"03868",
    "addr:street":"Milton Rd",
    "iso:country":"US",
    "sg:address":"31 Milton Rd",
    "sg:city":"Rochester",
    "sg:classifiers":[
        {
            "category":"Home & Garden",
            "subcategory":"Carpets & Floor Coverings",
            "type":"Retail Goods"
        }
    ],
    "sg:phone":"+1 603 332 0828",
    "sg:postcode":"03868",
    "sg:province":"NH",
    "sg:tags":[
        "dealer",
        "laying",
        "rug",
        "contractor"
    ],
    "wof:name":"Bourque's Flooring",
    "wof:placetype":"venue"
},
  "geometry": {"coordinates":[-70.975364,43.323206],"type":"Point"}
}