{
  "type": "Feature",
  "properties": {
    "iso:country":"US",
    "sg:address":"235 State Rte 115",
    "sg:city":"Carroll",
    "sg:classifiers":[
        {
            "category":"Manufacturing",
            "subcategory":"Aerospace",
            "type":"Manufacturing & Wholesale Goods"
        }
    ],
    "sg:phone":"+1 603 837 2627",
    "sg:postcode":"03598",
    "sg:province":"NH",
    "sg:tags":[
        "aircraft"
    ],
    "wof:name":"D Austin Aircraft",
    "wof:placetype":"venue"
},
  "geometry": {"coordinates":[-71.52752,44.311192],"type":"Point"}
}