{
  "type": "Feature",
  "properties": {
    "iso:country":"US",
    "sg:address":"47 Newport Rd",
    "sg:city":"New London",
    "sg:classifiers":[
        {
            "category":"Ice Cream",
            "type":"Food & Drink"
        }
    ],
    "sg:menulink":"http://www.allmenus.com/nh/new-london/209134-tcby/menu/",
    "sg:phone":"+1 603 526 9511",
    "sg:postcode":"03257",
    "sg:province":"NH",
    "sg:tags":[
        "smoothy",
        "juice",
        "american"
    ],
    "wof:name":"TCBY",
    "wof:placetype":"venue"
},
  "geometry": {"coordinates":[-72.00215300000001,43.423197],"type":"Point"}
}