{
  "type": "Feature",
  "properties": {
    "addr:full":"5 Varney St Manchester NH 03102",
    "addr:housenumber":"5",
    "addr:postcode":"03102",
    "addr:street":"Varney St",
    "iso:country":"US",
    "sg:address":"5 Varney St",
    "sg:city":"Manchester",
    "sg:classifiers":[
        {
            "category":"Retail",
            "subcategory":"Auto Repair",
            "type":"Services"
        }
    ],
    "sg:phone":"+1 603 622 0282",
    "sg:postcode":"03102",
    "sg:province":"NH",
    "sg:tags":[
        "van",
        "conversion",
        "truck",
        "accessory"
    ],
    "sg:website":"www.nekk.com",
    "wof:name":"Northeast Kustom Kreations",
    "wof:placetype":"venue"
},
  "geometry": {"coordinates":[-71.47877800000001,42.980749],"type":"Point"}
}