{
  "type": "Feature",
  "properties": {
    "iso:country":"US",
    "sg:address":"12 Ford Ln",
    "sg:city":"Rochester",
    "sg:classifiers":[
        {
            "category":"Building & Trades",
            "subcategory":"Construction",
            "type":"Services"
        }
    ],
    "sg:phone":"+1 603 332 7269",
    "sg:postcode":"03867",
    "sg:province":"NH",
    "sg:tags":[
        "contractor"
    ],
    "wof:name":"Atwood Carpentry",
    "wof:placetype":"venue"
},
  "geometry": {"coordinates":[-71.011214,43.322876],"type":"Point"}
}