{
  "type": "Feature",
  "properties": {
    "iso:country":"US",
    "sg:address":"4 Market St",
    "sg:city":"Portsmouth",
    "sg:classifiers":[
        {
            "category":"Professional",
            "subcategory":"Business Services",
            "type":"Services"
        }
    ],
    "sg:phone":"+1 603 430 7621",
    "sg:postcode":"03801",
    "sg:province":"NH",
    "wof:name":"Tobey Design",
    "wof:placetype":"venue"
},
  "geometry": {"coordinates":[-70.75762,43.077317],"type":"Point"}
}