{
  "type": "Feature",
  "properties": {
    "iso:country":"US",
    "sg:address":"264B N Broadway Ste 206",
    "sg:city":"Salem",
    "sg:classifiers":[
        {
            "category":"Professional",
            "subcategory":"Employment Agencies",
            "type":"Services"
        }
    ],
    "sg:phone":"+1 603 893 9486",
    "sg:postcode":"03079",
    "sg:province":"NH",
    "sg:tags":[
        "opportunity"
    ],
    "wof:name":"High Tech Opportunities Inc",
    "wof:placetype":"venue"
},
  "geometry": {"coordinates":[-71.23635400000001,42.79395],"type":"Point"}
}