{
  "type": "Feature",
  "properties": {
    "addr:full":"103 Amesbury Rd Newton NH 03858",
    "addr:housenumber":"103",
    "addr:postcode":"03858",
    "addr:street":"Amesbury Rd",
    "iso:country":"US",
    "sg:address":"103 Amesbury Rd",
    "sg:city":"Newton",
    "sg:classifiers":[
        {
            "category":"Shopping",
            "subcategory":"Bicycles & Sporting Goods",
            "type":"Retail Goods"
        }
    ],
    "sg:phone":"+1 603 394 7949",
    "sg:postcode":"03858",
    "sg:province":"NH",
    "sg:tags":[
        "durable"
    ],
    "wof:name":"Rays Gun Shop",
    "wof:placetype":"venue"
},
  "geometry": {"coordinates":[-71.00360999999999,42.868627],"type":"Point"}
}