{
  "type": "Feature",
  "properties": {
    "iso:country":"US",
    "sg:address":"33 Geremonty Dr",
    "sg:city":"Salem",
    "sg:classifiers":[
        {
            "category":"Government",
            "subcategory":"Office",
            "type":"Public Place"
        }
    ],
    "sg:phone":"+1 603 890 2120",
    "sg:postcode":"03079",
    "sg:province":"NH",
    "sg:tags":[
        "city"
    ],
    "wof:name":"Salem Town Manager",
    "wof:placetype":"venue"
},
  "geometry": {"coordinates":[-71.210536,42.777688],"type":"Point"}
}