{
  "type": "Feature",
  "properties": {
    "addr:full":"150 Lafayette Rd Rye NH 03870",
    "addr:housenumber":"150",
    "addr:postcode":"03870",
    "iso:country":"US",
    "sg:address":"150 Lafayette Rd",
    "sg:city":"Rye",
    "sg:classifiers":[
        {
            "category":"Sports & Exercise",
            "subcategory":"Gym",
            "type":"Entertainment"
        }
    ],
    "sg:phone":"+1 603 964 4420",
    "sg:postcode":"03870",
    "sg:province":"NH",
    "sg:tags":[
        "club",
        "health",
        "studio",
        "gymnasium"
    ],
    "wof:name":"Curves For Women",
    "wof:placetype":"venue"
},
  "geometry": {"coordinates":[-70.805317,43.009752],"type":"Point"}
}