{
  "type": "Feature",
  "properties": {
    "addr:full":"3 Barrell Ct Concord NH 03301",
    "addr:housenumber":"3",
    "addr:postcode":"03301",
    "addr:street":"Barrell Ct",
    "iso:country":"US",
    "sg:address":"3 Barrell Ct",
    "sg:city":"Concord",
    "sg:classifiers":[
        {
            "category":"Organizations",
            "subcategory":"Professional Association",
            "type":"Services"
        }
    ],
    "sg:phone":"+1 603 223 2302",
    "sg:postcode":"03301",
    "sg:province":"NH",
    "wof:name":"Campus Compact For New Hmpshr",
    "wof:placetype":"venue"
},
  "geometry": {"coordinates":[-71.498144,43.213399],"type":"Point"}
}