{
  "type": "Feature",
  "properties": {
    "addr:full":"91 Bisson Ave Laconia NH 03246",
    "addr:housenumber":"91",
    "addr:postcode":"03246",
    "addr:street":"Bisson Ave",
    "iso:country":"US",
    "sg:address":"91 Bisson Ave",
    "sg:city":"Laconia",
    "sg:classifiers":[
        {
            "category":"Building & Trades",
            "subcategory":"Construction",
            "type":"Services"
        }
    ],
    "sg:phone":"+1 603 524 3411",
    "sg:postcode":"03246",
    "sg:province":"NH",
    "sg:tags":[
        "general",
        "contractor"
    ],
    "wof:name":"Bonnette Page & Stone Corp",
    "wof:placetype":"venue"
},
  "geometry": {"coordinates":[-71.46566900000001,43.53486],"type":"Point"}
}