{
  "type": "Feature",
  "properties": {
    "addr:full":"26 Blueberry Hill Rd Amherst NH 03031",
    "addr:housenumber":"26",
    "addr:postcode":"03031",
    "addr:street":"Blueberry Hill Rd",
    "iso:country":"US",
    "sg:address":"26 Blueberry Hill Rd",
    "sg:city":"Amherst",
    "sg:classifiers":[
        {
            "category":"Manufacturing",
            "subcategory":"Printing",
            "type":"Manufacturing & Wholesale Goods"
        }
    ],
    "sg:phone":"+1 603 672 6628",
    "sg:postcode":"03031",
    "sg:province":"NH",
    "sg:tags":[
        "multimedia"
    ],
    "sg:website":"www.inflexion.com",
    "wof:name":"Inflexion",
    "wof:placetype":"venue"
},
  "geometry": {"coordinates":[-71.617784,42.870532],"type":"Point"}
}