{
  "type": "Feature",
  "properties": {
    "addr:full":"58 Turnpike St Allenstown NH 03275",
    "addr:housenumber":"58",
    "addr:postcode":"03275",
    "addr:street":"Turnpike St",
    "iso:country":"US",
    "sg:address":"58 Turnpike St",
    "sg:city":"Allenstown",
    "sg:classifiers":[
        {
            "category":"Building & Trades",
            "subcategory":"Plumbing",
            "type":"Services"
        }
    ],
    "sg:phone":"+1 603 485 6104",
    "sg:postcode":"03275",
    "sg:province":"NH",
    "sg:tags":[
        "plumbing",
        "contractor"
    ],
    "wof:name":"All In 1 Plumbing & Heating",
    "wof:placetype":"venue"
},
  "geometry": {"coordinates":[-71.447215,43.13185],"type":"Point"}
}