{
  "type": "Feature",
  "properties": {
    "iso:country":"US",
    "sg:address":"26 Commercial St",
    "sg:city":"Concord",
    "sg:classifiers":[
        {
            "category":"Real Estate",
            "subcategory":"Developer",
            "type":"Services"
        }
    ],
    "sg:phone":"+1 603 228 6160",
    "sg:postcode":"03301",
    "sg:province":"NH",
    "wof:name":"C & M Management Corp",
    "wof:placetype":"venue"
},
  "geometry": {"coordinates":[-71.539839,43.217596],"type":"Point"}
}