{
  "type": "Feature",
  "properties": {
    "iso:country":"US",
    "sg:address":"12 Pleasant St",
    "sg:city":"Concord",
    "sg:classifiers":[
        {
            "category":"Health Services",
            "subcategory":"Doctor",
            "type":"Services"
        }
    ],
    "sg:phone":"+1 603 228 7322",
    "sg:postcode":"03301",
    "sg:province":"NH",
    "sg:tags":[
        "medical"
    ],
    "wof:name":"Jarmoc Laura M",
    "wof:placetype":"venue"
},
  "geometry": {"coordinates":[-71.536344,43.204063],"type":"Point"}
}