{
  "type": "Feature",
  "properties": {
    "iso:country":"US",
    "sg:address":"45 B & B Ln",
    "sg:city":"Weare",
    "sg:classifiers":[
        {
            "category":"Professional",
            "subcategory":"Testing Lab",
            "type":"Services"
        }
    ],
    "sg:phone":"+1 603 529 6707",
    "sg:postcode":"03281",
    "sg:province":"NH",
    "sg:tags":[
        "correction",
        "radon"
    ],
    "wof:name":"MDM Water Svc",
    "wof:placetype":"venue"
},
  "geometry": {"coordinates":[-71.68735599999999,43.034917],"type":"Point"}
}