{
  "type": "Feature",
  "properties": {
    "addr:full":"81 Damren Rd Derry NH 03038",
    "addr:housenumber":"81",
    "addr:postcode":"03038",
    "addr:street":"Damren Rd",
    "iso:country":"US",
    "sg:address":"81 Damren Rd",
    "sg:city":"Derry",
    "sg:classifiers":[
        {
            "category":"Travel",
            "subcategory":"Campground",
            "type":"Entertainment"
        }
    ],
    "sg:phone":"+1 603 887 3767",
    "sg:postcode":"03038",
    "sg:province":"NH",
    "sg:tags":[
        "trailer"
    ],
    "wof:name":"Hidden Valley R V & Golf Park",
    "wof:placetype":"venue"
},
  "geometry": {"coordinates":[-71.239831,42.916905],"type":"Point"}
}