{
  "type": "Feature",
  "properties": {
    "addr:full":"8 Center St Ste 801 Exeter NH 03833",
    "addr:housenumber":"8",
    "addr:postcode":"03833",
    "addr:street":"Center St Ste 801",
    "iso:country":"US",
    "sg:address":"8 Center St Ste 801",
    "sg:city":"Exeter",
    "sg:classifiers":[
        {
            "category":"Real Estate",
            "subcategory":"Real Estate Services",
            "type":"Services"
        },
        {
            "category":"Professional",
            "subcategory":"Research",
            "type":"Services"
        },
        {
            "category":"Professional",
            "subcategory":"Lawyer & Legal Services",
            "type":"Services"
        },
        {
            "category":"Insurance",
            "subcategory":"Title Insurance",
            "type":"Services"
        }
    ],
    "sg:phone":"+1 603 778 1861",
    "sg:postcode":"03833",
    "sg:province":"NH",
    "sg:tags":[
        "abstracter",
        "plan"
    ],
    "wof:name":"Quality Title Company Inc",
    "wof:placetype":"venue"
},
  "geometry": {"coordinates":[-70.94834299999999,42.98112],"type":"Point"}
}