{
  "type": "Feature",
  "properties": {
    "iso:country":"US",
    "sg:address":"4 Aviation Dr",
    "sg:city":"Laconia",
    "sg:classifiers":[
        {
            "category":"Manufacturing",
            "subcategory":"Tools & Machinery",
            "type":"Manufacturing & Wholesale Goods"
        }
    ],
    "sg:phone":"+1 603 524 5101",
    "sg:postcode":"03249",
    "sg:province":"NH",
    "sg:tags":[
        "connector",
        "electrical",
        "barrier",
        "for",
        "manufacturer"
    ],
    "wof:name":"Molex Industrial Ventures Inc",
    "wof:placetype":"venue"
},
  "geometry": {"coordinates":[-71.431752,43.573234],"type":"Point"}
}