{
  "type": "Feature",
  "properties": {
    "iso:country":"US",
    "sg:address":"1361 Elm St",
    "sg:city":"Manchester",
    "sg:classifiers":[
        {
            "category":"Social Services",
            "type":"Services"
        }
    ],
    "sg:phone":"+1 603 622 5900",
    "sg:postcode":"03101",
    "sg:province":"NH",
    "wof:name":"Crotched Mountain Cmnty Svcs",
    "wof:placetype":"venue"
},
  "geometry": {"coordinates":[-71.46373,42.997209],"type":"Point"}
}