{
  "type": "Feature",
  "properties": {
    "addr:full":"377 Rimmon St Manchester NH 03102",
    "addr:housenumber":"377",
    "addr:postcode":"03102",
    "addr:street":"Rimmon St",
    "iso:country":"US",
    "sg:address":"377 Rimmon St",
    "sg:city":"Manchester",
    "sg:classifiers":[
        {
            "category":"Building & Trades",
            "subcategory":"Cleaning & Sanitation",
            "type":"Services"
        }
    ],
    "sg:phone":"+1 603 647 9331",
    "sg:postcode":"03102",
    "sg:province":"NH",
    "sg:tags":[
        "maintenance"
    ],
    "wof:name":"Pukka",
    "wof:placetype":"venue"
},
  "geometry": {"coordinates":[-71.47856299999999,42.992775],"type":"Point"}
}