{
  "type": "Feature",
  "properties": {
    "iso:country":"US",
    "sg:address":"16 N Main St",
    "sg:city":"Mont Vernon",
    "sg:classifiers":[
        {
            "category":"Home & Garden",
            "subcategory":"Building Materials",
            "type":"Retail Goods"
        }
    ],
    "sg:phone":"+1 603 673 4351",
    "sg:postcode":"03057",
    "sg:province":"NH",
    "wof:name":"Phoebe Flory Watercolor School",
    "wof:placetype":"venue"
},
  "geometry": {"coordinates":[-71.67635799999999,42.896013],"type":"Point"}
}