{
  "type": "Feature",
  "properties": {
    "iso:country":"US",
    "sg:address":"31 Rumford St",
    "sg:city":"Concord",
    "sg:classifiers":[
        {
            "category":"Building & Trades",
            "subcategory":"Construction",
            "type":"Services"
        }
    ],
    "sg:phone":"+1 603 848 4888",
    "sg:postcode":"03301",
    "sg:province":"NH",
    "sg:tags":[
        "contractor"
    ],
    "wof:name":"James Mark Stone Masonry",
    "wof:placetype":"venue"
},
  "geometry": {"coordinates":[-71.54255499999999,43.204082],"type":"Point"}
}