{
  "type": "Feature",
  "properties": {
    "iso:country":"US",
    "sg:address":"5 Juniper St",
    "sg:city":"Exeter",
    "sg:classifiers":[
        {
            "category":"Building & Trades",
            "subcategory":"Cleaning & Sanitation",
            "type":"Services"
        }
    ],
    "sg:phone":"+1 603 778 9392",
    "sg:postcode":"03833",
    "sg:province":"NH",
    "sg:tags":[
        "maintenance"
    ],
    "wof:name":"White Wolf Cleaning Service",
    "wof:placetype":"venue"
},
  "geometry": {"coordinates":[-70.97332400000001,42.965067],"type":"Point"}
}