{
  "type": "Feature",
  "properties": {
    "iso:country":"US",
    "sg:address":"339 Main St",
    "sg:city":"Nashua",
    "sg:classifiers":[
        {
            "category":"Professional",
            "subcategory":"Employment Agencies",
            "type":"Services"
        },
        {
            "category":"Health Services",
            "subcategory":"Nursing And Care Facility",
            "type":"Services"
        },
        {
            "category":"Health Services",
            "subcategory":"Health Practitioner",
            "type":"Services"
        }
    ],
    "sg:phone":"+1 603 589 6000",
    "sg:postcode":"03060",
    "sg:province":"NH",
    "sg:tags":[
        "physician",
        "assistant",
        "contractor",
        "home",
        "nurse",
        "eldercare-home"
    ],
    "wof:name":"Premier Medical Staffing",
    "wof:placetype":"venue"
},
  "geometry": {"coordinates":[-71.460426,42.749619],"type":"Point"}
}