{
  "type": "Feature",
  "properties": {
    "iso:country":"US",
    "sg:address":"74 Cortland Dr",
    "sg:city":"Bedford",
    "sg:classifiers":[
        {
            "category":"Professional",
            "subcategory":"Management & Consulting",
            "type":"Services"
        }
    ],
    "sg:phone":"+1 603 471 9107",
    "sg:postcode":"03110",
    "sg:province":"NH",
    "sg:tags":[
        "consultant",
        "telecommunication"
    ],
    "wof:name":"Merlin Communication Systems",
    "wof:placetype":"venue"
},
  "geometry": {"coordinates":[-71.59063999999999,42.949051],"type":"Point"}
}