{
  "type": "Feature",
  "properties": {
    "iso:country":"US",
    "sg:address":"218 Old Dover Rd",
    "sg:city":"Rochester",
    "sg:classifiers":[
        {
            "category":"Retail",
            "subcategory":"Repair Shop",
            "type":"Services"
        }
    ],
    "sg:phone":"+1 603 335 7880",
    "sg:postcode":"03867",
    "sg:province":"NH",
    "sg:tags":[
        "welding"
    ],
    "wof:name":"Murphy's Welding & Fabrication",
    "wof:placetype":"venue"
},
  "geometry": {"coordinates":[-70.94587300000001,43.269535],"type":"Point"}
}