{
  "type": "Feature",
  "properties": {
    "iso:country":"US",
    "sg:address":"80 Pine St",
    "sg:city":"Peterborough",
    "sg:classifiers":[
        {
            "category":"Organizations",
            "subcategory":"Non-profit Organization",
            "type":"Services"
        }
    ],
    "sg:phone":"+1 603 924 7006",
    "sg:postcode":"03458",
    "sg:province":"NH",
    "wof:name":"Associates In Career & Cmnty",
    "wof:placetype":"venue"
},
  "geometry": {"coordinates":[-71.945583,42.866171],"type":"Point"}
}