{
  "type": "Feature",
  "properties": {
    "iso:country":"US",
    "sg:address":"136 Storrs Hill Rd",
    "sg:city":"Lebanon",
    "sg:classifiers":[
        {
            "category":"Freight",
            "type":"Transportation"
        }
    ],
    "sg:phone":"+1 603 448 3920",
    "sg:postcode":"03766",
    "sg:province":"NH",
    "sg:tags":[
        "trucking"
    ],
    "wof:name":"Michael L Townsend Enterprises",
    "wof:placetype":"venue"
},
  "geometry": {"coordinates":[-72.253095,43.621322],"type":"Point"}
}