{
  "type": "Feature",
  "properties": {
    "iso:country":"US",
    "sg:address":"22 North St",
    "sg:city":"Jaffrey",
    "sg:classifiers":[
        {
            "category":"Health Services",
            "subcategory":"Doctor",
            "type":"Services"
        },
        {
            "category":"Social Services",
            "type":"Services"
        },
        {
            "category":"Personal",
            "type":"Services"
        },
        {
            "category":"Health Services",
            "subcategory":"Clinic",
            "type":"Services"
        }
    ],
    "sg:phone":"+1 603 532 4291",
    "sg:postcode":"03452",
    "sg:province":"NH",
    "sg:tags":[
        "information",
        "mental",
        "family",
        "counselors-licensed",
        "psychologist",
        "individual",
        "marriage",
        "child",
        "professional",
        "counselor"
    ],
    "sg:website":"http://www.mfs.org",
    "wof:name":"Monadnock Family Services Inc",
    "wof:placetype":"venue"
},
  "geometry": {"coordinates":[-72.02307,42.816064],"type":"Point"}
}