{
  "type": "Feature",
  "properties": {
    "iso:country":"US",
    "sg:address":"6 Christine Dr",
    "sg:city":"Atkinson",
    "sg:classifiers":[
        {
            "category":"Retail",
            "subcategory":"Repair Shop",
            "type":"Services"
        }
    ],
    "sg:phone":"+1 603 362 6224",
    "sg:postcode":"03811",
    "sg:province":"NH",
    "wof:name":"Very Good Cleaning Co A",
    "wof:placetype":"venue"
},
  "geometry": {"coordinates":[-71.16403200000001,42.826822],"type":"Point"}
}