{
  "type": "Feature",
  "properties": {
    "iso:country":"US",
    "sg:address":"16 Stone Rd",
    "sg:city":"Belmont",
    "sg:classifiers":[
        {
            "category":"Building & Trades",
            "subcategory":"Landscaping Services",
            "type":"Services"
        }
    ],
    "sg:phone":"+1 603 267 5900",
    "sg:postcode":"03220",
    "sg:province":"NH",
    "sg:tags":[
        "landscape",
        "contractor"
    ],
    "wof:name":"Greenplan LLC",
    "wof:placetype":"venue"
},
  "geometry": {"coordinates":[-71.46835900000001,43.431609],"type":"Point"}
}