{
  "type": "Feature",
  "properties": {
    "iso:country":"US",
    "sg:address":"9 Victor Ave",
    "sg:city":"Nashua",
    "sg:classifiers":[
        {
            "category":"Building & Trades",
            "subcategory":"Construction",
            "type":"Services"
        }
    ],
    "sg:phone":"+1 603 891 4392",
    "sg:postcode":"03060",
    "sg:province":"NH",
    "sg:tags":[
        "home",
        "improvement"
    ],
    "wof:name":"Tricia's Home Repair Svc",
    "wof:placetype":"venue"
},
  "geometry": {"coordinates":[-71.46618700000001,42.738011],"type":"Point"}
}