{
  "type": "Feature",
  "properties": {
    "iso:country":"US",
    "sg:address":"28 Chipmunk Ln",
    "sg:city":"Glmntn Iron Wks",
    "sg:classifiers":[
        {
            "category":"Wholesale",
            "subcategory":"Office Equipment",
            "type":"Manufacturing & Wholesale Goods"
        }
    ],
    "sg:phone":"+1 603 267 9885",
    "sg:postcode":"03835",
    "sg:province":"NH",
    "sg:tags":[
        "credit"
    ],
    "wof:name":"Nova Information Systems",
    "wof:placetype":"venue"
},
  "geometry": {"coordinates":[-71.098506,43.35931],"type":"Point"}
}