{
  "type": "Feature",
  "properties": {
    "iso:country":"US",
    "sg:address":"4 Tall Pines Dr",
    "sg:city":"Stratham",
    "sg:classifiers":[
        {
            "category":"Shopping",
            "subcategory":"Used Merchandise",
            "type":"Retail Goods"
        }
    ],
    "sg:phone":"+1 603 778 1885",
    "sg:postcode":"03885",
    "sg:province":"NH",
    "wof:name":"Actually Antiques",
    "wof:placetype":"venue"
},
  "geometry": {"coordinates":[-70.909066,43.006084],"type":"Point"}
}