{
  "type": "Feature",
  "properties": {
    "addr:full":"395 Daniel Webster Hwy Merrimack NH 03054",
    "addr:housenumber":"395",
    "addr:postcode":"03054",
    "addr:street":"Daniel Webster Hwy",
    "iso:country":"US",
    "sg:address":"395 Daniel Webster Hwy",
    "sg:city":"Merrimack",
    "sg:classifiers":[
        {
            "category":"Health Services",
            "subcategory":"Doctor",
            "type":"Services"
        }
    ],
    "sg:phone":"+1 603 424 0303",
    "sg:postcode":"03054",
    "sg:province":"NH",
    "sg:tags":[
        "dentist"
    ],
    "wof:name":"Mark N De Puy DDS",
    "wof:placetype":"venue"
},
  "geometry": {"coordinates":[-71.49135800000001,42.85616],"type":"Point"}
}