{
  "type": "Feature",
  "properties": {
    "iso:country":"US",
    "sg:address":"7 Pinard St",
    "sg:city":"Manchester",
    "sg:classifiers":[
        {
            "category":"Restaurant",
            "type":"Food & Drink"
        }
    ],
    "sg:phone":"+1 603 623 5222",
    "sg:postcode":"03102",
    "sg:province":"NH",
    "sg:tags":[
        "cafe",
        "catering"
    ],
    "wof:name":"Healthy Cameals",
    "wof:placetype":"venue"
},
  "geometry": {"coordinates":[-71.499742,42.990984],"type":"Point"}
}