{
  "type": "Feature",
  "properties": {
    "iso:country":"US",
    "sg:address":"20 Reservoir Rd",
    "sg:city":"Campton",
    "sg:classifiers":[
        {
            "category":"Organizations",
            "subcategory":"Professional Association",
            "type":"Services"
        }
    ],
    "sg:phone":"+1 603 726 2072",
    "sg:postcode":"03253",
    "sg:province":"NH",
    "wof:name":"Waterville Estates Assn",
    "wof:placetype":"venue"
},
  "geometry": {"coordinates":[-71.500781,43.641253],"type":"Point"}
}