{
  "type": "Feature",
  "properties": {
    "addr:full":"13 Court St Dover NH 03820",
    "addr:housenumber":"13",
    "addr:postcode":"03820",
    "addr:street":"Court St",
    "iso:country":"US",
    "sg:address":"13 Court St",
    "sg:city":"Dover",
    "sg:classifiers":[
        {
            "category":"Professional",
            "subcategory":"Secretarial Services",
            "type":"Services"
        }
    ],
    "sg:phone":"+1 603 749 5326",
    "sg:postcode":"03820",
    "sg:province":"NH",
    "sg:tags":[
        "reporting"
    ],
    "wof:name":"Hayes Reporting",
    "wof:placetype":"venue"
},
  "geometry": {"coordinates":[-70.873057,43.190562],"type":"Point"}
}