{
  "type": "Feature",
  "properties": {
    "iso:country":"US",
    "sg:address":"12 Pleasant St",
    "sg:city":"Colebrook",
    "sg:classifiers":[
        {
            "category":"Building & Trades",
            "subcategory":"Construction",
            "type":"Services"
        }
    ],
    "sg:phone":"+1 603 237 4454",
    "sg:postcode":"03576",
    "sg:province":"NH",
    "sg:tags":[
        "general",
        "contractor"
    ],
    "wof:name":"Daniel Hebert Inc",
    "wof:placetype":"venue"
},
  "geometry": {"coordinates":[-71.493949,44.893873],"type":"Point"}
}