{
  "type": "Feature",
  "properties": {
    "iso:country":"US",
    "sg:address":"11 Martha Dr",
    "sg:city":"Derry",
    "sg:classifiers":[
        {
            "category":"Building & Trades",
            "subcategory":"Landscaping Services",
            "type":"Services"
        }
    ],
    "sg:phone":"+1 603 425 6336",
    "sg:postcode":"03038",
    "sg:province":"NH",
    "wof:name":"Puzzo Brothers Lawn Care",
    "wof:placetype":"venue"
},
  "geometry": {"coordinates":[-71.306158,42.894037],"type":"Point"}
}