{
  "type": "Feature",
  "properties": {
    "iso:country":"US",
    "sg:address":"2 Highland St",
    "sg:city":"Rochester",
    "sg:classifiers":[
        {
            "category":"Food & Beverages",
            "subcategory":"Groceries & Convenience Stores",
            "type":"Retail Goods"
        }
    ],
    "sg:phone":"+1 603 332 5172",
    "sg:postcode":"03868",
    "sg:province":"NH",
    "wof:name":"Cumberland Farms 5406",
    "wof:placetype":"venue"
},
  "geometry": {"coordinates":[-70.940158,43.334781],"type":"Point"}
}