{
  "type": "Feature",
  "properties": {
    "iso:country":"US",
    "sg:address":"339 State Rte 125",
    "sg:city":"Barrington",
    "sg:classifiers":[
        {
            "category":"Restaurant",
            "type":"Food & Drink"
        }
    ],
    "sg:phone":"+1 603 664 9083",
    "sg:postcode":"03825",
    "sg:province":"NH",
    "wof:name":"Spring Garden",
    "wof:placetype":"venue"
},
  "geometry": {"coordinates":[-70.99250600000001,43.224633],"type":"Point"}
}