{
  "type": "Feature",
  "properties": {
    "iso:country":"US",
    "sg:address":"2035 Brown Ave",
    "sg:city":"Manchester",
    "sg:classifiers":[
        {
            "category":"Banks & Credit Unions",
            "subcategory":"Bank",
            "type":"Services"
        }
    ],
    "sg:phone":"+1 603 634 5751",
    "sg:postcode":"03103",
    "sg:province":"NH",
    "sg:tags":[
        "state",
        "commercial"
    ],
    "sg:website":"www.citizensbank.com",
    "wof:name":"Citizens Bank",
    "wof:placetype":"venue"
},
  "geometry": {"coordinates":[-71.453155,42.938808],"type":"Point"}
}