{
  "type": "Feature",
  "properties": {
    "iso:country":"US",
    "sg:address":"110 State Rte 101A",
    "sg:city":"Amherst",
    "sg:classifiers":[
        {
            "category":"Shopping",
            "subcategory":"Bicycles & Sporting Goods",
            "type":"Retail Goods"
        }
    ],
    "sg:phone":"+1 603 883 2221",
    "sg:postcode":"03031",
    "sg:province":"NH",
    "sg:tags":[
        "equipment",
        "equestrian",
        "supply"
    ],
    "wof:name":"Stone Pony Inc",
    "wof:placetype":"venue"
},
  "geometry": {"coordinates":[-71.57095,42.808444],"type":"Point"}
}