{
  "type": "Feature",
  "properties": {
    "addr:full":"57 Bay St Manchester NH 03104",
    "addr:housenumber":"57",
    "addr:postcode":"03104",
    "addr:street":"Bay St",
    "iso:country":"US",
    "sg:address":"57 Bay St",
    "sg:city":"Manchester",
    "sg:classifiers":[
        {
            "category":"Health Services",
            "subcategory":"Doctor",
            "type":"Services"
        }
    ],
    "sg:phone":"+1 603 669 0290",
    "sg:postcode":"03104",
    "sg:province":"NH",
    "sg:tags":[
        "physician"
    ],
    "wof:name":"Dr Peter PSC Plstc Srgry Cntr",
    "wof:placetype":"venue"
},
  "geometry": {"coordinates":[-71.463764,43.004507],"type":"Point"}
}