{
  "type": "Feature",
  "properties": {
    "iso:country":"US",
    "sg:address":"280 Main St",
    "sg:city":"Salem",
    "sg:classifiers":[
        {
            "category":"Professional",
            "type":"Services"
        },
        {
            "category":"Manufacturing",
            "subcategory":"Tools & Machinery",
            "type":"Manufacturing & Wholesale Goods"
        }
    ],
    "sg:phone":"+1 603 893 4751",
    "sg:postcode":"03079",
    "sg:province":"NH",
    "sg:tags":[
        "surgical",
        "establishment",
        "mfg"
    ],
    "wof:name":"Cairns Advanced Technologies",
    "wof:placetype":"venue"
},
  "geometry": {"coordinates":[-71.20335900000001,42.787454],"type":"Point"}
}