{
  "type": "Feature",
  "properties": {
    "addr:full":"296 Mittersill Rd Franconia NH 03580",
    "addr:housenumber":"296",
    "addr:postcode":"03580",
    "addr:street":"Mittersill Rd",
    "iso:country":"US",
    "sg:address":"296 Mittersill Rd",
    "sg:city":"Franconia",
    "sg:classifiers":[
        {
            "category":"Shopping",
            "subcategory":"Gifts & Souvenirs",
            "type":"Retail Goods"
        }
    ],
    "sg:phone":"+1 603 823 9907",
    "sg:postcode":"03580",
    "sg:province":"NH",
    "sg:tags":[
        "shop"
    ],
    "wof:name":"Amber Waves",
    "wof:placetype":"venue"
},
  "geometry": {"coordinates":[-71.71516099999999,44.179247],"type":"Point"}
}