{
  "type": "Feature",
  "properties": {
    "iso:country":"US",
    "sg:address":"20 Jana Ln",
    "sg:city":"Stratham",
    "sg:classifiers":[
        {
            "category":"Professional",
            "type":"Services"
        }
    ],
    "sg:phone":"+1 603 778 1191",
    "sg:postcode":"03885",
    "sg:province":"NH",
    "wof:name":"Marilyn Young Calligraphy",
    "wof:placetype":"venue"
},
  "geometry": {"coordinates":[-70.90280199999999,43.044092],"type":"Point"}
}