{
  "type": "Feature",
  "properties": {
    "addr:full":"498 Mont Vernon Rd New Boston NH 03070",
    "addr:housenumber":"498",
    "addr:postcode":"03070",
    "addr:street":"Mont Vernon Rd",
    "iso:country":"US",
    "sg:address":"498 Mont Vernon Rd",
    "sg:city":"New Boston",
    "sg:classifiers":[
        {
            "category":"Professional",
            "subcategory":"Computer Services",
            "type":"Services"
        }
    ],
    "sg:phone":"+1 603 497 8343",
    "sg:postcode":"03070",
    "sg:province":"NH",
    "sg:tags":[
        "resellers",
        "consultant"
    ],
    "wof:name":"C T G",
    "wof:placetype":"venue"
},
  "geometry": {"coordinates":[-71.67984199999999,42.935477],"type":"Point"}
}