{
  "type": "Feature",
  "properties": {
    "iso:country":"US",
    "sg:address":"221 S Main St",
    "sg:city":"Franklin",
    "sg:classifiers":[
        {
            "category":"Autos & Motor Vehicles",
            "subcategory":"Auto Supplies",
            "type":"Retail Goods"
        }
    ],
    "sg:phone":"+1 603 934 2715",
    "sg:postcode":"03235",
    "sg:province":"NH",
    "sg:tags":[
        "tire"
    ],
    "wof:name":"Prescott Tire Ctr",
    "wof:placetype":"venue"
},
  "geometry": {"coordinates":[-71.65517800000001,43.435378],"type":"Point"}
}