{
  "type": "Feature",
  "properties": {
    "iso:country":"US",
    "sg:address":"155 Lexington Dr",
    "sg:city":"Laconia",
    "sg:classifiers":[
        {
            "category":"Manufacturing",
            "subcategory":"Tools & Machinery",
            "type":"Manufacturing & Wholesale Goods"
        }
    ],
    "sg:phone":"+1 603 524 0004",
    "sg:postcode":"03246",
    "sg:province":"NH",
    "sg:tags":[
        "bearing",
        "furnace",
        "mfg",
        "foundry",
        "blast",
        "copper"
    ],
    "wof:name":"New Hampshire Ball Bearings",
    "wof:placetype":"venue"
},
  "geometry": {"coordinates":[-71.491316,43.544357],"type":"Point"}
}