{
  "type": "Feature",
  "properties": {
    "iso:country":"US",
    "sg:address":"150 Broad St",
    "sg:city":"Nashua",
    "sg:classifiers":[
        {
            "category":"Restaurant",
            "type":"Food & Drink"
        },
        {
            "category":"Food & Beverages",
            "subcategory":"Groceries & Convenience Stores",
            "type":"Retail Goods"
        }
    ],
    "sg:phone":"+1 603 204 5510",
    "sg:postcode":"03063",
    "sg:province":"NH",
    "sg:tags":[
        "shop",
        "style",
        "sandwich",
        "family",
        "pizza"
    ],
    "sg:website":"http://www.bellagiobestpizza.com",
    "wof:name":"Bellagio Pizza",
    "wof:placetype":"venue"
},
  "geometry": {"coordinates":[-71.49520099999999,42.768242],"type":"Point"}
}