{
  "type": "Feature",
  "properties": {
    "addr:full":"6 Gerry Ave Newmarket NH 03857",
    "addr:housenumber":"6",
    "addr:postcode":"03857",
    "addr:street":"Gerry Ave",
    "iso:country":"US",
    "sg:address":"6 Gerry Ave",
    "sg:city":"Newmarket",
    "sg:classifiers":[
        {
            "category":"Restaurant",
            "type":"Food & Drink"
        }
    ],
    "sg:phone":"+1 603 659 7777",
    "sg:postcode":"03857",
    "sg:province":"NH",
    "sg:tags":[
        "eating",
        "pizza"
    ],
    "wof:name":"Gepetto's Pizza",
    "wof:placetype":"venue"
},
  "geometry": {"coordinates":[-70.939239,43.07664],"type":"Point"}
}