{
  "type": "Feature",
  "properties": {
    "iso:country":"US",
    "sg:address":"428 Main St",
    "sg:city":"New London",
    "sg:classifiers":[
        {
            "category":"Shopping",
            "subcategory":"Crafts & Fabrics",
            "type":"Retail Goods"
        }
    ],
    "sg:phone":"+1 603 526 6923",
    "sg:postcode":"03257",
    "sg:province":"NH",
    "sg:tags":[
        "yarn"
    ],
    "wof:name":"Knit New London",
    "wof:placetype":"venue"
},
  "geometry": {"coordinates":[-72.059504,43.498976],"type":"Point"}
}