{
  "type": "Feature",
  "properties": {
    "iso:country":"US",
    "sg:address":"23 Homestead Ave",
    "sg:city":"Swanzey",
    "sg:classifiers":[
        {
            "category":"Professional",
            "subcategory":"Art Services",
            "type":"Services"
        }
    ],
    "sg:phone":"+1 603 358 5233",
    "sg:postcode":"03469",
    "sg:province":"NH",
    "sg:tags":[
        "photographer"
    ],
    "wof:name":"Gilmour Photography",
    "wof:placetype":"venue"
},
  "geometry": {"coordinates":[-72.32423799999999,42.868622],"type":"Point"}
}