{
  "type": "Feature",
  "properties": {
    "iso:country":"US",
    "sg:address":"1 Clocktower Pl",
    "sg:city":"Nashua",
    "sg:classifiers":[
        {
            "category":"Personal",
            "type":"Services"
        }
    ],
    "sg:phone":"+1 603 595 8884",
    "sg:postcode":"03060",
    "sg:province":"NH",
    "sg:tags":[
        "therapist",
        "massage"
    ],
    "wof:name":"Goldenglo Massage & Reiki",
    "wof:placetype":"venue"
},
  "geometry": {"coordinates":[-71.469155,42.760338],"type":"Point"}
}