{
  "type": "Feature",
  "properties": {
    "iso:country":"US",
    "sg:address":"58 Stinson Lake Rd",
    "sg:city":"Rumney",
    "sg:classifiers":[
        {
            "category":"Recreation",
            "type":"Entertainment"
        }
    ],
    "sg:phone":"+1 603 786 9943",
    "sg:postcode":"03266",
    "sg:province":"NH",
    "sg:tags":[
        "historical"
    ],
    "wof:name":"Mary Baker Eddy Historic House",
    "wof:placetype":"venue"
},
  "geometry": {"coordinates":[-71.811002,43.817864],"type":"Point"}
}