{
  "type": "Feature",
  "properties": {
    "addr:full":"8 Fales Ln Windham NH 03070",
    "addr:housenumber":"8",
    "addr:postcode":"03070",
    "addr:street":"Fales Ln",
    "iso:country":"US",
    "sg:address":"8 Fales Ln",
    "sg:city":"Windham",
    "sg:classifiers":[
        {
            "category":"Education",
            "subcategory":"Library",
            "type":"Public Place"
        }
    ],
    "sg:phone":"+1 603 432 7154",
    "sg:postcode":"03070",
    "sg:province":"NH",
    "wof:name":"Nesmith Library",
    "wof:placetype":"venue"
},
  "geometry": {"coordinates":[-71.630381,43.014316],"type":"Point"}
}