{
  "type": "Feature",
  "properties": {
    "addr:full":"15 Juniper Ln Nashua NH 03063",
    "addr:housenumber":"15",
    "addr:postcode":"03063",
    "addr:street":"Juniper Ln",
    "iso:country":"US",
    "sg:address":"15 Juniper Ln",
    "sg:city":"Nashua",
    "sg:classifiers":[
        {
            "category":"Professional",
            "subcategory":"Computer Services",
            "type":"Services"
        }
    ],
    "sg:phone":"+1 603 883 2175",
    "sg:postcode":"03063",
    "sg:province":"NH",
    "sg:tags":[
        "programing",
        "custom"
    ],
    "wof:name":"Hudnall Engineering",
    "wof:placetype":"venue"
},
  "geometry": {"coordinates":[-71.505668,42.773726],"type":"Point"}
}