{
  "type": "Feature",
  "properties": {
    "iso:country":"US",
    "sg:address":"549 Lafayette Rd",
    "sg:city":"Seabrook",
    "sg:classifiers":[
        {
            "category":"Health Services",
            "subcategory":"Chiropractor",
            "type":"Services"
        }
    ],
    "sg:phone":"+1 603 474 5400",
    "sg:postcode":"03874",
    "sg:province":"NH",
    "wof:name":"Fowler Chiropractic Office Inc",
    "wof:placetype":"venue"
},
  "geometry": {"coordinates":[-70.87201399999999,42.890768],"type":"Point"}
}