{
  "type": "Feature",
  "properties": {
    "addr:full":"116 S River Rd Bedford NH 03110",
    "addr:housenumber":"116",
    "addr:postcode":"03110",
    "addr:street":"S River Rd",
    "iso:country":"US",
    "sg:address":"116 S River Rd",
    "sg:city":"Bedford",
    "sg:classifiers":[
        {
            "category":"Professional",
            "subcategory":"Employment Agencies",
            "type":"Services"
        }
    ],
    "sg:phone":"+1 603 626 6777",
    "sg:postcode":"03110",
    "sg:province":"NH",
    "wof:name":"Snowden Associates",
    "wof:placetype":"venue"
},
  "geometry": {"coordinates":[-71.47803399999999,42.953694],"type":"Point"}
}