{
  "type": "Feature",
  "properties": {
    "iso:country":"US",
    "sg:address":"416 Lake Ave",
    "sg:city":"Manchester",
    "sg:classifiers":[
        {
            "category":"Parking",
            "type":"Transportation"
        }
    ],
    "sg:phone":"+1 603 622 5477",
    "sg:postcode":"03103",
    "sg:province":"NH",
    "sg:tags":[
        "garage"
    ],
    "wof:name":"Williams Garage",
    "wof:placetype":"venue"
},
  "geometry": {"coordinates":[-71.44722,42.987367],"type":"Point"}
}