{
  "type": "Feature",
  "properties": {
    "addr:full":"40 Walker Bungalow Rd Portsmouth NH 03801",
    "addr:housenumber":"40",
    "addr:postcode":"03801",
    "addr:street":"Walker Bungalow Rd",
    "iso:country":"US",
    "sg:address":"40 Walker Bungalow Rd",
    "sg:city":"Portsmouth",
    "sg:classifiers":[
        {
            "category":"Building & Trades",
            "subcategory":"Construction",
            "type":"Services"
        }
    ],
    "sg:phone":"+1 603 422 7750",
    "sg:postcode":"03801",
    "sg:province":"NH",
    "sg:tags":[
        "house"
    ],
    "wof:name":"Dintino Remodeling",
    "wof:placetype":"venue"
},
  "geometry": {"coordinates":[-70.749191,43.056967],"type":"Point"}
}