{
  "type": "Feature",
  "properties": {
    "iso:country":"US",
    "sg:address":"155 Dow St",
    "sg:city":"Manchester",
    "sg:classifiers":[
        {
            "category":"Restaurant",
            "type":"Food & Drink"
        }
    ],
    "sg:menulink":"http://www.allmenus.com/nh/manchester/39836-fratellos-ristorante-italiano/menu/",
    "sg:phone":"+1 603 624 2022",
    "sg:postcode":"03101",
    "sg:province":"NH",
    "sg:tags":[
        "italian"
    ],
    "wof:name":"Fratello's Ristorante Italiano",
    "wof:placetype":"venue"
},
  "geometry": {"coordinates":[-71.467393,42.997256],"type":"Point"}
}