{
  "type": "Feature",
  "properties": {
    "iso:country":"US",
    "sg:address":"6 Pine Rd",
    "sg:city":"Hampton",
    "sg:classifiers":[
        {
            "category":"Communications",
            "subcategory":"Film & Video Production",
            "type":"Services"
        }
    ],
    "sg:phone":"+1 603 529 7437",
    "sg:postcode":"03842",
    "sg:province":"NH",
    "sg:tags":[
        "motion"
    ],
    "wof:name":"Green Sky Productions",
    "wof:placetype":"venue"
},
  "geometry": {"coordinates":[-70.805278,42.939319],"type":"Point"}
}