{
  "type": "Feature",
  "properties": {
    "iso:country":"US",
    "sg:address":"504 State Rte 63",
    "sg:city":"Chesterfield",
    "sg:classifiers":[
        {
            "category":"Government",
            "subcategory":"Office",
            "type":"Public Place"
        }
    ],
    "sg:phone":"+1 603 363 4527",
    "sg:postcode":"03443",
    "sg:province":"NH",
    "sg:tags":[
        "city",
        "taxation"
    ],
    "wof:name":"Chesterfield Tax Collector",
    "wof:placetype":"venue"
},
  "geometry": {"coordinates":[-72.47059400000001,42.887427],"type":"Point"}
}