{
  "type": "Feature",
  "properties": {
    "iso:country":"US",
    "sg:address":"103 Cottage St",
    "sg:city":"Littleton",
    "sg:classifiers":[
        {
            "category":"Education",
            "subcategory":"School",
            "type":"Public Place"
        }
    ],
    "sg:phone":"+1 603 444 0226",
    "sg:postcode":"03561",
    "sg:province":"NH",
    "wof:name":"Littleton Home Based Head Strt",
    "wof:placetype":"venue"
},
  "geometry": {"coordinates":[-71.7693,44.302395],"type":"Point"}
}