{
  "type": "Feature",
  "properties": {
    "iso:country":"US",
    "sg:address":"787 Daniel Webster Hwy",
    "sg:city":"North Woodstock",
    "sg:classifiers":[
        {
            "category":"Wholesale",
            "subcategory":"Apparel",
            "type":"Manufacturing & Wholesale Goods"
        }
    ],
    "sg:phone":"+1 603 745 6277",
    "sg:postcode":"03262",
    "sg:province":"NH",
    "sg:tags":[
        "trim",
        "clothing",
        "mfg"
    ],
    "wof:name":"O D SILK SCREEN CO",
    "wof:placetype":"venue"
},
  "geometry": {"coordinates":[-71.685929,43.992047],"type":"Point"}
}