{
  "type": "Feature",
  "properties": {
    "iso:country":"US",
    "sg:address":"335 Pembroke Hill Rd",
    "sg:city":"Suncook",
    "sg:classifiers":[
        {
            "category":"Retail",
            "subcategory":"Portrait Studio",
            "type":"Services"
        }
    ],
    "sg:phone":"+1 603 485 5637",
    "sg:postcode":"03275",
    "sg:province":"NH",
    "sg:tags":[
        "motion",
        "photo",
        "picture"
    ],
    "wof:name":"J D Denham",
    "wof:placetype":"venue"
},
  "geometry": {"coordinates":[-71.45642700000001,43.163311],"type":"Point"}
}