{
  "type": "Feature",
  "properties": {
    "iso:country":"US",
    "sg:address":"40 Crystal Ave",
    "sg:city":"Derry",
    "sg:classifiers":[
        {
            "category":"Retail",
            "subcategory":"Animal Services",
            "type":"Services"
        }
    ],
    "sg:phone":"+1 603 437 7262",
    "sg:postcode":"03038",
    "sg:province":"NH",
    "sg:tags":[
        "merchandise"
    ],
    "wof:name":"Bark Ave Pet Salon",
    "wof:placetype":"venue"
},
  "geometry": {"coordinates":[-71.32684999999999,42.887366],"type":"Point"}
}