{
  "type": "Feature",
  "properties": {
    "iso:country":"US",
    "sg:address":"9 Bartlett Ave",
    "sg:city":"Somersworth",
    "sg:classifiers":[
        {
            "category":"Government",
            "subcategory":"Office",
            "type":"Public Place"
        }
    ],
    "sg:phone":"+1 603 692 4211",
    "sg:postcode":"03878",
    "sg:province":"ME",
    "wof:name":"County Nutrition Program",
    "wof:placetype":"venue"
},
  "geometry": {"coordinates":[-70.87403399999999,43.250189],"type":"Point"}
}