{
  "type": "Feature",
  "properties": {
    "iso:country":"US",
    "sg:address":"65 Trescott Rd",
    "sg:city":"Etna",
    "sg:classifiers":[
        {
            "category":"Professional",
            "subcategory":"Engineering",
            "type":"Services"
        }
    ],
    "sg:phone":"+1 603 643 2972",
    "sg:postcode":"03750",
    "sg:province":"NH",
    "wof:name":"W R B Assoc",
    "wof:placetype":"venue"
},
  "geometry": {"coordinates":[-72.23083699999999,43.706755],"type":"Point"}
}