{
  "type": "Feature",
  "properties": {
    "iso:country":"US",
    "sg:address":"629 Daniel Webster Hwy",
    "sg:city":"Merrimack",
    "sg:classifiers":[
        {
            "category":"Building & Trades",
            "subcategory":"Construction",
            "type":"Services"
        }
    ],
    "sg:phone":"+1 603 429 6389",
    "sg:postcode":"03054",
    "sg:province":"NH",
    "sg:tags":[
        "excavating",
        "contractor"
    ],
    "wof:name":"David Labrecque Quality Contr",
    "wof:placetype":"venue"
},
  "geometry": {"coordinates":[-71.474802,42.887481],"type":"Point"}
}