{
  "type": "Feature",
  "properties": {
    "iso:country":"US",
    "sg:address":"5 Woodward Ave",
    "sg:city":"Nashua",
    "sg:classifiers":[
        {
            "category":"Education",
            "subcategory":"College",
            "type":"Public Place"
        }
    ],
    "sg:phone":"+1 603 594 2567",
    "sg:postcode":"03060",
    "sg:province":"NH",
    "sg:tags":[
        "academic",
        "school"
    ],
    "sg:website":"www.stjosephhospital.com",
    "wof:name":"St Joseph Academic Ctr",
    "wof:placetype":"venue"
},
  "geometry": {"coordinates":[-71.47860300000001,42.750927],"type":"Point"}
}