{
  "type": "Feature",
  "properties": {
    "iso:country":"US",
    "sg:address":"1 Hampton Rd",
    "sg:city":"Exeter",
    "sg:classifiers":[
        {
            "category":"Retail",
            "subcategory":"Auto Rental",
            "type":"Services"
        }
    ],
    "sg:phone":"+1 603 926 9669",
    "sg:postcode":"03833",
    "sg:province":"NH",
    "sg:tags":[
        "truck"
    ],
    "wof:name":"Ryder",
    "wof:placetype":"venue"
},
  "geometry": {"coordinates":[-70.911447,42.976037],"type":"Point"}
}