{
  "type": "Feature",
  "properties": {
    "iso:country":"US",
    "sg:address":"RR 3",
    "sg:city":"Concord",
    "sg:classifiers":[
        {
            "category":"Home & Garden",
            "subcategory":"Garden Supply",
            "type":"Retail Goods"
        }
    ],
    "sg:phone":"+1 603 796 2756",
    "sg:postcode":"03303",
    "sg:province":"NH",
    "sg:tags":[
        "nursery",
        "gardening"
    ],
    "sg:website":"www.blackforestnursery.com",
    "wof:name":"Black Forest Nursery & Garden Center",
    "wof:placetype":"venue"
},
  "geometry": {"coordinates":[-71.59929700000001,43.282299],"type":"Point"}
}