{
  "type": "Feature",
  "properties": {
    "addr:full":"49 Bedford Rd Merrimack NH 03054",
    "addr:housenumber":"49",
    "addr:postcode":"03054",
    "addr:street":"Bedford Rd",
    "iso:country":"US",
    "sg:address":"49 Bedford Rd",
    "sg:city":"Merrimack",
    "sg:classifiers":[
        {
            "category":"Professional",
            "subcategory":"Art Services",
            "type":"Services"
        }
    ],
    "sg:phone":"+1 603 423 9848",
    "sg:postcode":"03054",
    "sg:province":"NH",
    "sg:tags":[
        "commercial",
        "design"
    ],
    "wof:name":"Nickis Notions",
    "wof:placetype":"venue"
},
  "geometry": {"coordinates":[-71.48485100000001,42.887974],"type":"Point"}
}