{
  "type": "Feature",
  "properties": {
    "iso:country":"US",
    "sg:address":"15 Fairhaven Rd",
    "sg:city":"Nashua",
    "sg:classifiers":[
        {
            "category":"Professional",
            "subcategory":"Business Services",
            "type":"Services"
        }
    ],
    "sg:phone":"+1 603 888 7132",
    "sg:postcode":"03060",
    "sg:province":"NH",
    "wof:name":"Klp Custom Interiors",
    "wof:placetype":"venue"
},
  "geometry": {"coordinates":[-71.444288,42.735931],"type":"Point"}
}