{
  "type": "Feature",
  "properties": {
    "addr:full":"2 Chapel St Newmarket NH 03857",
    "addr:housenumber":"2",
    "addr:postcode":"03857",
    "addr:street":"Chapel St",
    "iso:country":"US",
    "sg:address":"2 Chapel St",
    "sg:city":"Newmarket",
    "sg:classifiers":[
        {
            "category":"Building & Trades",
            "subcategory":"Electrical",
            "type":"Services"
        }
    ],
    "sg:phone":"+1 603 659 3140",
    "sg:postcode":"03857",
    "sg:province":"NH",
    "sg:tags":[
        "electrical",
        "contractor"
    ],
    "wof:name":"Great Bay Electrical Service",
    "wof:placetype":"venue"
},
  "geometry": {"coordinates":[-70.93680999999999,43.079073],"type":"Point"}
}