{
  "type": "Feature",
  "properties": {
    "addr:full":"737 South St Milford NH 03055",
    "addr:housenumber":"737",
    "addr:postcode":"03055",
    "addr:street":"South St",
    "iso:country":"US",
    "sg:address":"737 South St",
    "sg:city":"Milford",
    "sg:classifiers":[
        {
            "category":"Building & Trades",
            "subcategory":"Construction",
            "type":"Services"
        }
    ],
    "sg:phone":"+1 603 577 4739",
    "sg:postcode":"03055",
    "sg:province":"NH",
    "sg:tags":[
        "downspouts",
        "gutter"
    ],
    "wof:name":"Allpro Roofing",
    "wof:placetype":"venue"
},
  "geometry": {"coordinates":[-71.655372,42.795952],"type":"Point"}
}