{
  "type": "Feature",
  "properties": {
    "addr:full":"35 Rocky Shore Rd Wolfeboro NH 03894",
    "addr:housenumber":"35",
    "addr:postcode":"03894",
    "addr:street":"Rocky Shore Rd",
    "iso:country":"US",
    "sg:address":"35 Rocky Shore Rd",
    "sg:city":"Wolfeboro",
    "sg:classifiers":[
        {
            "category":"Food & Beverages",
            "subcategory":"Groceries & Convenience Stores",
            "type":"Retail Goods"
        }
    ],
    "sg:phone":"+1 603 569 6077",
    "sg:postcode":"03894",
    "sg:province":"NH",
    "wof:name":"Epping Fueling Center Inc",
    "wof:placetype":"venue"
},
  "geometry": {"coordinates":[-71.255038,43.578442],"type":"Point"}
}