{
  "type": "Feature",
  "properties": {
    "addr:full":"9 Walden Pond Dr Nashua NH 03064",
    "addr:housenumber":"9",
    "addr:postcode":"03064",
    "addr:street":"Walden Pond Dr",
    "iso:country":"US",
    "sg:address":"9 Walden Pond Dr",
    "sg:city":"Nashua",
    "sg:classifiers":[
        {
            "category":"Professional",
            "subcategory":"Business Services",
            "type":"Services"
        }
    ],
    "sg:phone":"+1 603 579 5430",
    "sg:postcode":"03064",
    "sg:province":"NH",
    "sg:tags":[
        "interior",
        "consultant",
        "design",
        "decorator"
    ],
    "wof:name":"Interior Solutions For Windows",
    "wof:placetype":"venue"
},
  "geometry": {"coordinates":[-71.450137,42.767119],"type":"Point"}
}