{
  "type": "Feature",
  "properties": {
    "iso:country":"US",
    "sg:address":"71 Langdale Dr",
    "sg:city":"Hampton",
    "sg:classifiers":[
        {
            "category":"Recreation",
            "subcategory":"Arcade",
            "type":"Entertainment"
        }
    ],
    "sg:phone":"+1 603 926 8839",
    "sg:postcode":"03842",
    "sg:province":"NH",
    "sg:tags":[
        "device",
        "operator",
        "amusement"
    ],
    "wof:name":"Strodes Rent A Box",
    "wof:placetype":"venue"
},
  "geometry": {"coordinates":[-70.848387,42.953398],"type":"Point"}
}