{
  "type": "Feature",
  "properties": {
    "iso:country":"US",
    "sg:address":"265 W Hill Rd",
    "sg:city":"Troy",
    "sg:classifiers":[
        {
            "category":"Home & Garden",
            "subcategory":"Hardware",
            "type":"Retail Goods"
        }
    ],
    "sg:phone":"+1 603 242 6413",
    "sg:postcode":"03465",
    "sg:province":"NH",
    "wof:name":"Savs Shyras A Value Syst",
    "wof:placetype":"venue"
},
  "geometry": {"coordinates":[-72.206175,42.840482],"type":"Point"}
}