{
  "type": "Feature",
  "properties": {
    "iso:country":"US",
    "sg:address":"3 Peabody Row",
    "sg:city":"Londonderry",
    "sg:classifiers":[
        {
            "category":"Organizations",
            "subcategory":"Religious Organization",
            "type":"Services"
        }
    ],
    "sg:phone":"+1 603 437 8333",
    "sg:postcode":"03053",
    "sg:province":"NH",
    "sg:tags":[
        "church"
    ],
    "sg:website":"www.forministry.com/03053spec",
    "wof:name":"St Peter S Episcopal Church",
    "wof:placetype":"venue"
},
  "geometry": {"coordinates":[-71.358361,42.855566],"type":"Point"}
}