{
  "type": "Feature",
  "properties": {
    "addr:full":"164 Main St Berlin NH 03570",
    "addr:housenumber":"164",
    "addr:postcode":"03570",
    "addr:street":"Main St",
    "iso:country":"US",
    "sg:address":"164 Main St",
    "sg:city":"Berlin",
    "sg:classifiers":[
        {
            "category":"Professional",
            "subcategory":"Management & Consulting",
            "type":"Services"
        }
    ],
    "sg:phone":"+1 603 752 6465",
    "sg:postcode":"03570",
    "sg:province":"NH",
    "sg:tags":[
        "consultant",
        "training"
    ],
    "wof:name":"Logger Rescue",
    "wof:placetype":"venue"
},
  "geometry": {"coordinates":[-71.180333,44.469832],"type":"Point"}
}