{
  "type": "Feature",
  "properties": {
    "iso:country":"US",
    "sg:address":"2 Palmer Dr",
    "sg:city":"Londonderry",
    "sg:classifiers":[
        {
            "category":"Building & Trades",
            "subcategory":"Cleaning & Sanitation",
            "type":"Services"
        }
    ],
    "sg:phone":"+1 603 425 0066",
    "sg:postcode":"03053",
    "sg:province":"NH",
    "sg:tags":[
        "maintenance"
    ],
    "wof:name":"Fish Window Cleaning",
    "wof:placetype":"venue"
},
  "geometry": {"coordinates":[-71.345882,42.865491],"type":"Point"}
}