{
  "type": "Feature",
  "properties": {
    "iso:country":"US",
    "sg:address":"200 Huse Rd",
    "sg:city":"Manchester",
    "sg:classifiers":[
        {
            "category":"Personal",
            "subcategory":"Barber",
            "type":"Services"
        }
    ],
    "sg:phone":"+1 603 623 9283",
    "sg:postcode":"03103",
    "sg:province":"NH",
    "sg:tags":[
        "shop"
    ],
    "wof:name":"Lr Brunette & Co",
    "wof:placetype":"venue"
},
  "geometry": {"coordinates":[-71.427137,42.970119],"type":"Point"}
}