{
  "type": "Feature",
  "properties": {
    "addr:full":"10 School St Allenstown NH 03275",
    "addr:housenumber":"10",
    "addr:postcode":"03275",
    "addr:street":"School St",
    "iso:country":"US",
    "sg:address":"10 School St",
    "sg:city":"Allenstown",
    "sg:classifiers":[
        {
            "category":"Organizations",
            "subcategory":"Religious Organization",
            "type":"Services"
        }
    ],
    "sg:phone":"+1 603 485 3113",
    "sg:postcode":"03275",
    "sg:province":"NH",
    "sg:tags":[
        "church"
    ],
    "sg:website":"www.sjbsuncook.com",
    "wof:name":"St John The Baptist Church",
    "wof:placetype":"venue"
},
  "geometry": {"coordinates":[-71.453486,43.127002],"type":"Point"}
}