{
  "type": "Feature",
  "properties": {
    "iso:country":"US",
    "sg:address":"7 Pentucket Dr",
    "sg:city":"Atkinson",
    "sg:classifiers":[
        {
            "category":"Retail",
            "subcategory":"Repair Shop",
            "type":"Services"
        }
    ],
    "sg:phone":"+1 603 362 5240",
    "sg:postcode":"03826",
    "sg:province":"NH",
    "sg:tags":[
        "equipment",
        "electrical"
    ],
    "wof:name":"S K Associates",
    "wof:placetype":"venue"
},
  "geometry": {"coordinates":[-71.127476,42.878057],"type":"Point"}
}