{
  "type": "Feature",
  "properties": {
    "addr:full":"47 Prospect St Jaffrey NH 03452",
    "addr:housenumber":"47",
    "addr:postcode":"03452",
    "addr:street":"Prospect St",
    "iso:country":"US",
    "sg:address":"47 Prospect St",
    "sg:city":"Jaffrey",
    "sg:classifiers":[
        {
            "category":"Professional",
            "subcategory":"Accounting & Tax Preparation",
            "type":"Services"
        }
    ],
    "sg:phone":"+1 603 532 4278",
    "sg:postcode":"03452",
    "sg:province":"NH",
    "sg:tags":[
        "return",
        "filing"
    ],
    "wof:name":"FTCCS",
    "wof:placetype":"venue"
},
  "geometry": {"coordinates":[-72.03284499999999,42.822771],"type":"Point"}
}