{
  "type": "Feature",
  "properties": {
    "iso:country":"US",
    "sg:address":"314 Londonderry Tpke",
    "sg:city":"Hooksett",
    "sg:classifiers":[
        {
            "category":"Sports & Exercise",
            "subcategory":"Gym",
            "type":"Entertainment"
        }
    ],
    "sg:phone":"+1 603 623 9083",
    "sg:postcode":"03106",
    "sg:province":"NH",
    "sg:tags":[
        "fitness",
        "physical",
        "association",
        "facility"
    ],
    "wof:name":"Deerhead Sportsmen Club Inc",
    "wof:placetype":"venue"
},
  "geometry": {"coordinates":[-71.432918,43.049238],"type":"Point"}
}