{
  "type": "Feature",
  "properties": {
    "iso:country":"US",
    "sg:address":"68 Stiles Rd",
    "sg:city":"Salem",
    "sg:classifiers":[
        {
            "category":"Wholesale",
            "subcategory":"Toys & Hobbies",
            "type":"Manufacturing & Wholesale Goods"
        },
        {
            "category":"Professional",
            "subcategory":"Management & Consulting",
            "type":"Services"
        }
    ],
    "sg:phone":"+1 603 893 5009",
    "sg:postcode":"03079",
    "sg:province":"NH",
    "sg:tags":[
        "wholesaler",
        "business"
    ],
    "wof:name":"Trade & Technology Intl",
    "wof:placetype":"venue"
},
  "geometry": {"coordinates":[-71.25022199999999,42.77331],"type":"Point"}
}