{
  "type": "Feature",
  "properties": {
    "addr:full":"28 Krzyzaniak Ln Contoocook NH 03229",
    "addr:housenumber":"28",
    "addr:postcode":"03229",
    "addr:street":"Krzyzaniak Ln",
    "iso:country":"US",
    "sg:address":"28 Krzyzaniak Ln",
    "sg:city":"Contoocook",
    "sg:classifiers":[
        {
            "category":"Building & Trades",
            "subcategory":"Construction",
            "type":"Services"
        }
    ],
    "sg:phone":"+1 603 746 5243",
    "sg:postcode":"03229",
    "sg:province":"NH",
    "sg:tags":[
        "hanging",
        "contractor"
    ],
    "wof:name":"L Menze Painting",
    "wof:placetype":"venue"
},
  "geometry": {"coordinates":[-71.728635,43.229559],"type":"Point"}
}