{
  "type": "Feature",
  "properties": {
    "iso:country":"US",
    "sg:address":"129 Exeter Rd",
    "sg:city":"Hampton",
    "sg:classifiers":[
        {
            "category":"Building & Trades",
            "subcategory":"Construction",
            "type":"Services"
        }
    ],
    "sg:phone":"+1 603 926 4736",
    "sg:postcode":"03842",
    "sg:province":"NH",
    "sg:tags":[
        "general",
        "contractor"
    ],
    "wof:name":"MGK Drywall/Plaster",
    "wof:placetype":"venue"
},
  "geometry": {"coordinates":[-70.842696,42.949261],"type":"Point"}
}