{
  "type": "Feature",
  "properties": {
    "iso:country":"US",
    "sg:address":"36 Nutter St",
    "sg:city":"Rochester",
    "sg:classifiers":[
        {
            "category":"Building & Trades",
            "subcategory":"Construction",
            "type":"Services"
        }
    ],
    "sg:phone":"+1 603 330 1970",
    "sg:postcode":"03867",
    "sg:province":"NH",
    "sg:tags":[
        "general",
        "contractor"
    ],
    "wof:name":"New England Roofing",
    "wof:placetype":"venue"
},
  "geometry": {"coordinates":[-70.962622,43.309631],"type":"Point"}
}