{
  "type": "Feature",
  "properties": {
    "iso:country":"US",
    "sg:address":"356 Daniel Webster Hwy",
    "sg:city":"Merrimack",
    "sg:classifiers":[
        {
            "category":"Professional",
            "subcategory":"Management & Consulting",
            "type":"Services"
        },
        {
            "category":"Food & Beverages",
            "subcategory":"Liquor & Beverages",
            "type":"Retail Goods"
        },
        {
            "category":"Government",
            "subcategory":"Office",
            "type":"Public Place"
        }
    ],
    "sg:phone":"+1 603 424 2521",
    "sg:postcode":"03054",
    "sg:province":"NH",
    "sg:tags":[
        "government-state",
        "store",
        "consultant"
    ],
    "wof:name":"State Liquor Store 59",
    "wof:placetype":"venue"
},
  "geometry": {"coordinates":[-71.493461,42.84775],"type":"Point"}
}