{
  "type": "Feature",
  "properties": {
    "iso:country":"US",
    "sg:address":"251 Joliette St",
    "sg:city":"Manchester",
    "sg:classifiers":[
        {
            "category":"Building & Trades",
            "subcategory":"Construction",
            "type":"Services"
        }
    ],
    "sg:phone":"+1 603 622 9059",
    "sg:postcode":"03102",
    "sg:province":"NH",
    "sg:tags":[
        "contractor"
    ],
    "wof:name":"Mark & Mike Siding",
    "wof:placetype":"venue"
},
  "geometry": {"coordinates":[-71.484758,42.996901],"type":"Point"}
}