{
  "type": "Feature",
  "properties": {
    "addr:full":"145 State Rte 108 Somersworth NH 03878",
    "addr:housenumber":"145",
    "addr:postcode":"03878",
    "addr:street":"State Rte 108",
    "iso:country":"US",
    "sg:address":"145 State Rte 108",
    "sg:city":"Somersworth",
    "sg:classifiers":[
        {
            "category":"Recreation",
            "type":"Entertainment"
        }
    ],
    "sg:phone":"+1 603 742 8068",
    "sg:postcode":"03878",
    "sg:province":"NH",
    "sg:tags":[
        "course",
        "golf"
    ],
    "wof:name":"Hilltop Fun Ctr",
    "wof:placetype":"venue"
},
  "geometry": {"coordinates":[-70.89834399999999,43.242541],"type":"Point"}
}