{
  "type": "Feature",
  "properties": {
    "iso:country":"US",
    "sg:address":"16 Pingree Hill Rd",
    "sg:city":"Derry",
    "sg:classifiers":[
        {
            "category":"Building & Trades",
            "subcategory":"Construction",
            "type":"Services"
        }
    ],
    "sg:phone":"+1 603 437 2509",
    "sg:postcode":"03038",
    "sg:province":"NH",
    "sg:tags":[
        "hanging",
        "contractor"
    ],
    "wof:name":"Sanrae Painting",
    "wof:placetype":"venue"
},
  "geometry": {"coordinates":[-71.308043,42.934273],"type":"Point"}
}