{
  "type": "Feature",
  "properties": {
    "iso:country":"US",
    "sg:address":"183 E Main St",
    "sg:city":"Warner",
    "sg:classifiers":[
        {
            "category":"Building & Trades",
            "subcategory":"Construction",
            "type":"Services"
        }
    ],
    "sg:phone":"+1 603 456 2225",
    "sg:postcode":"03278",
    "sg:province":"NH",
    "sg:tags":[
        "contractor"
    ],
    "wof:name":"Begin Homes LLC",
    "wof:placetype":"venue"
},
  "geometry": {"coordinates":[-71.80154899999999,43.274182],"type":"Point"}
}