{
  "type": "Feature",
  "properties": {
    "iso:country":"US",
    "sg:address":"571 State Rte 114",
    "sg:city":"Bradford",
    "sg:classifiers":[
        {
            "category":"Shopping",
            "type":"Retail Goods"
        }
    ],
    "sg:phone":"+1 603 927 1867",
    "sg:postcode":"03221",
    "sg:province":"NH",
    "sg:tags":[
        "pet",
        "food",
        "supply"
    ],
    "wof:name":"Pet Pantry",
    "wof:placetype":"venue"
},
  "geometry": {"coordinates":[-71.93404,43.317713],"type":"Point"}
}