{
  "type": "Feature",
  "properties": {
    "iso:country":"US",
    "sg:address":"46 Summer St",
    "sg:city":"Rochester",
    "sg:classifiers":[
        {
            "category":"Home & Garden",
            "subcategory":"Building Materials",
            "type":"Retail Goods"
        }
    ],
    "sg:phone":"+1 603 332 2548",
    "sg:postcode":"03867",
    "sg:province":"NH",
    "sg:tags":[
        "door",
        "gate",
        "operating",
        "devices"
    ],
    "wof:name":"Rochester Door Co",
    "wof:placetype":"venue"
},
  "geometry": {"coordinates":[-70.973749,43.307179],"type":"Point"}
}