{
  "type": "Feature",
  "properties": {
    "iso:country":"US",
    "sg:address":"789 Central Ave",
    "sg:city":"Dover",
    "sg:classifiers":[
        {
            "category":"Health Services",
            "subcategory":"Doctor",
            "type":"Services"
        }
    ],
    "sg:phone":"+1 603 742 2132",
    "sg:postcode":"03820",
    "sg:province":"NH",
    "sg:tags":[
        "physician",
        "surgeon"
    ],
    "wof:name":"Young Novis Professional Assn",
    "wof:placetype":"venue"
},
  "geometry": {"coordinates":[-70.87478,43.212069],"type":"Point"}
}