{
  "type": "Feature",
  "properties": {
    "iso:country":"US",
    "sg:address":"161 Corporate Dr",
    "sg:city":"Newington",
    "sg:classifiers":[
        {
            "category":"Health Services",
            "subcategory":"Doctor",
            "type":"Services"
        }
    ],
    "sg:phone":"+1 603 431 5154",
    "sg:postcode":"03801",
    "sg:province":"NH",
    "sg:tags":[
        "physician",
        "surgeon"
    ],
    "wof:name":"Martin's Point Health Care Ctr",
    "wof:placetype":"venue"
},
  "geometry": {"coordinates":[-70.800218,43.071547],"type":"Point"}
}