{
  "type": "Feature",
  "properties": {
    "addr:full":"1085 Mount Eustis Rd Littleton NH 03561",
    "addr:housenumber":"1085",
    "addr:postcode":"03561",
    "addr:street":"Mount Eustis Rd",
    "iso:country":"US",
    "sg:address":"1085 Mount Eustis Rd",
    "sg:city":"Littleton",
    "sg:classifiers":[
        {
            "category":"Shopping",
            "type":"Retail Goods"
        }
    ],
    "sg:phone":"+1 603 444 0178",
    "sg:postcode":"03561",
    "sg:province":"NH",
    "sg:tags":[
        "coin",
        "dealer",
        "supply"
    ],
    "wof:name":"Littleton Coin Co Inc",
    "wof:placetype":"venue"
},
  "geometry": {"coordinates":[-71.788326,44.289076],"type":"Point"}
}