{
  "type": "Feature",
  "properties": {
    "iso:country":"US",
    "sg:address":"28 Milford St",
    "sg:city":"Brookline",
    "sg:classifiers":[
        {
            "category":"Freight",
            "type":"Transportation"
        }
    ],
    "sg:phone":"+1 603 672 8891",
    "sg:postcode":"03033",
    "sg:province":"NH",
    "sg:tags":[
        "arrangement"
    ],
    "wof:name":"V & G Freight Brokers LLC",
    "wof:placetype":"venue"
},
  "geometry": {"coordinates":[-71.664338,42.740463],"type":"Point"}
}