{
  "type": "Feature",
  "properties": {
    "iso:country":"US",
    "sg:address":"108 Old Stage Rd",
    "sg:city":"Sanbornville",
    "sg:classifiers":[
        {
            "category":"Shopping",
            "subcategory":"Gifts & Souvenirs",
            "type":"Retail Goods"
        }
    ],
    "sg:phone":"+1 603 522 3079",
    "sg:postcode":"03872",
    "sg:province":"NH",
    "wof:name":"Impressive Presents",
    "wof:placetype":"venue"
},
  "geometry": {"coordinates":[-71.015863,43.538564],"type":"Point"}
}