{
  "type": "Feature",
  "properties": {
    "addr:full":"85 Manchester St Manchester NH 03101",
    "addr:housenumber":"85",
    "addr:postcode":"03101",
    "addr:street":"Manchester St",
    "iso:country":"US",
    "sg:address":"85 Manchester St",
    "sg:city":"Manchester",
    "sg:classifiers":[
        {
            "category":"Professional",
            "type":"Services"
        }
    ],
    "sg:phone":"+1 603 647 6910",
    "sg:postcode":"03101",
    "sg:province":"NH",
    "sg:tags":[
        "establishment"
    ],
    "wof:name":"SMJ Assoc",
    "wof:placetype":"venue"
},
  "geometry": {"coordinates":[-71.46095,42.990129],"type":"Point"}
}