{
  "type": "Feature",
  "properties": {
    "iso:country":"US",
    "sg:address":"121 Maple Ave",
    "sg:city":"Claremont",
    "sg:classifiers":[
        {
            "category":"Shopping",
            "subcategory":"Bicycles & Sporting Goods",
            "type":"Retail Goods"
        }
    ],
    "sg:phone":"+1 603 542 1988",
    "sg:postcode":"03743",
    "sg:province":"NH",
    "sg:tags":[
        "equipment",
        "archery",
        "supply"
    ],
    "wof:name":"F & L Archery",
    "wof:placetype":"venue"
},
  "geometry": {"coordinates":[-72.36046899999999,43.364795],"type":"Point"}
}