{
  "type": "Feature",
  "properties": {
    "iso:country":"US",
    "sg:address":"100 Autumn Dr",
    "sg:city":"Tilton",
    "sg:classifiers":[
        {
            "category":"Travel",
            "subcategory":"Hotels & Motels",
            "type":"Entertainment"
        }
    ],
    "sg:phone":"+1 603 524 3248",
    "sg:postcode":"03276",
    "sg:province":"NH",
    "sg:tags":[
        "cottage"
    ],
    "wof:name":"Anchorage The",
    "wof:placetype":"venue"
},
  "geometry": {"coordinates":[-71.545946,43.488836],"type":"Point"}
}