{
  "type": "Feature",
  "properties": {
    "addr:full":"50 State Rte 3a Hill NH 03243",
    "addr:housenumber":"50",
    "addr:postcode":"03243",
    "addr:street":"State Rte 3A Hill",
    "iso:country":"US",
    "sg:address":"50 State Rte 3a",
    "sg:city":"Hill",
    "sg:classifiers":[
        {
            "category":"Wholesale",
            "subcategory":"Toys & Hobbies",
            "type":"Manufacturing & Wholesale Goods"
        }
    ],
    "sg:phone":"+1 603 934 5563",
    "sg:postcode":"03243",
    "sg:province":"NH",
    "sg:tags":[
        "wholesaler"
    ],
    "wof:name":"Hill Design Group",
    "wof:placetype":"venue"
},
  "geometry": {"coordinates":[-71.701775,43.517838],"type":"Point"}
}