{
  "type": "Feature",
  "properties": {
    "addr:full":"220 Newmarket Rd Durham NH 03824",
    "addr:housenumber":"220",
    "addr:postcode":"03824",
    "addr:street":"Newmarket Rd",
    "iso:country":"US",
    "sg:address":"220 Newmarket Rd",
    "sg:city":"Durham",
    "sg:classifiers":[
        {
            "category":"Manufacturing",
            "subcategory":"Watercraft",
            "type":"Manufacturing & Wholesale Goods"
        }
    ],
    "sg:phone":"+1 603 659 7575",
    "sg:postcode":"03824",
    "sg:province":"NH",
    "sg:tags":[
        "boat"
    ],
    "sg:website":"www.durhamboat.com",
    "wof:name":"Durham Boat Co",
    "wof:placetype":"venue"
},
  "geometry": {"coordinates":[-70.929407,43.103594],"type":"Point"}
}