{
  "type": "Feature",
  "properties": {
    "iso:country":"US",
    "sg:address":"9 Winnwood St",
    "sg:city":"Nashua",
    "sg:classifiers":[
        {
            "category":"Professional",
            "subcategory":"Business Services",
            "type":"Services"
        }
    ],
    "sg:phone":"+1 603 889 7750",
    "sg:postcode":"03060",
    "sg:province":"NH",
    "sg:tags":[
        "interior",
        "consultant",
        "design",
        "decorator"
    ],
    "wof:name":"Terrence Lannan Interiors LLC",
    "wof:placetype":"venue"
},
  "geometry": {"coordinates":[-71.456711,42.745184],"type":"Point"}
}