{
  "type": "Feature",
  "properties": {
    "iso:country":"US",
    "sg:address":"75 Critchett Rd",
    "sg:city":"Candia",
    "sg:classifiers":[
        {
            "category":"Sports & Exercise",
            "subcategory":"Golf",
            "type":"Entertainment"
        }
    ],
    "sg:phone":"+1 603 483 5635",
    "sg:postcode":"03034",
    "sg:province":"NH",
    "wof:name":"All Courts Unlimited",
    "wof:placetype":"venue"
},
  "geometry": {"coordinates":[-71.270535,43.076983],"type":"Point"}
}