{
  "type": "Feature",
  "properties": {
    "addr:full":"101 Pleasant St Concord NH 03301",
    "addr:housenumber":"101",
    "addr:postcode":"03301",
    "addr:street":"Pleasant St",
    "iso:country":"US",
    "sg:address":"101 Pleasant St",
    "sg:city":"Concord",
    "sg:classifiers":[
        {
            "category":"Government",
            "subcategory":"Office",
            "type":"Public Place"
        }
    ],
    "sg:phone":"+1 603 271 3867",
    "sg:postcode":"03301",
    "sg:province":"NH",
    "sg:tags":[
        "career",
        "development"
    ],
    "wof:name":"Bureau of Career Development",
    "wof:placetype":"venue"
},
  "geometry": {"coordinates":[-71.544388,43.200453],"type":"Point"}
}