{
  "type": "Feature",
  "properties": {
    "iso:country":"US",
    "sg:address":"28 S Main St",
    "sg:city":"Concord",
    "sg:classifiers":[
        {
            "category":"Health Services",
            "subcategory":"Health Practitioner",
            "type":"Services"
        }
    ],
    "sg:phone":"+1 603 228 0057",
    "sg:postcode":"03301",
    "sg:province":"NH",
    "sg:tags":[
        "psychotherapist"
    ],
    "wof:name":"Tom Moore",
    "wof:placetype":"venue"
},
  "geometry": {"coordinates":[-71.535248,43.202853],"type":"Point"}
}