{
  "type": "Feature",
  "properties": {
    "iso:country":"US",
    "sg:address":"101 Water St",
    "sg:city":"Exeter",
    "sg:classifiers":[
        {
            "category":"Shopping",
            "subcategory":"Jewelry",
            "type":"Retail Goods"
        }
    ],
    "sg:phone":"+1 603 772 6414",
    "sg:postcode":"03833",
    "sg:province":"NH",
    "sg:tags":[
        "diamond"
    ],
    "wof:name":"Oro Verde",
    "wof:placetype":"venue"
},
  "geometry": {"coordinates":[-70.946676,42.981507],"type":"Point"}
}