{
  "type": "Feature",
  "properties": {
    "addr:full":"37 Manchester St Manchester NH 03101",
    "addr:housenumber":"37",
    "addr:postcode":"03101",
    "addr:street":"Manchester St",
    "iso:country":"US",
    "sg:address":"37 Manchester St",
    "sg:city":"Manchester",
    "sg:classifiers":[
        {
            "category":"Shopping",
            "subcategory":"Jewelry",
            "type":"Retail Goods"
        }
    ],
    "sg:phone":"+1 603 645 0034",
    "sg:postcode":"03101",
    "sg:province":"NH",
    "sg:tags":[
        "supply",
        "metaphysical",
        "gift",
        "handcrafted"
    ],
    "wof:name":"Ravens Nest Psychic Services",
    "wof:placetype":"venue"
},
  "geometry": {"coordinates":[-71.461766,42.990125],"type":"Point"}
}