{
  "type": "Feature",
  "properties": {
    "iso:country":"US",
    "sg:address":"8 Great Hollow Rd",
    "sg:city":"Hanover",
    "sg:classifiers":[
        {
            "category":"Building & Trades",
            "subcategory":"Construction",
            "type":"Services"
        }
    ],
    "sg:phone":"+1 603 643 4114",
    "sg:postcode":"03755",
    "sg:province":"NH",
    "sg:tags":[
        "general",
        "contractor"
    ],
    "wof:name":"Domus Inc",
    "wof:placetype":"venue"
},
  "geometry": {"coordinates":[-72.235213,43.680486],"type":"Point"}
}