{
  "type": "Feature",
  "properties": {
    "iso:country":"US",
    "sg:address":"165 Exeter Rd",
    "sg:city":"Hampton",
    "sg:classifiers":[
        {
            "category":"Health Services",
            "subcategory":"Doctor",
            "type":"Services"
        }
    ],
    "sg:phone":"+1 603 926 8031",
    "sg:postcode":"03842",
    "sg:province":"NH",
    "sg:tags":[
        "medical"
    ],
    "wof:name":"Dr Leonard K Walker",
    "wof:placetype":"venue"
},
  "geometry": {"coordinates":[-70.844084,42.951986],"type":"Point"}
}