{
  "type": "Feature",
  "properties": {
    "iso:country":"US",
    "sg:address":"1 Richardson St",
    "sg:city":"Rochester",
    "sg:classifiers":[
        {
            "category":"Personal",
            "subcategory":"Beauty Salon",
            "type":"Services"
        }
    ],
    "sg:phone":"+1 603 332 3333",
    "sg:postcode":"03867",
    "sg:province":"NH",
    "sg:tags":[
        "shop"
    ],
    "wof:name":"Lilac City Beauty Salon",
    "wof:placetype":"venue"
},
  "geometry": {"coordinates":[-70.965262,43.297258],"type":"Point"}
}