{
  "type": "Feature",
  "properties": {
    "addr:full":"17 Harvey Rd Deerfield NH 03037",
    "addr:housenumber":"17",
    "addr:postcode":"03037",
    "addr:street":"Harvey Rd",
    "iso:country":"US",
    "sg:address":"17 Harvey Rd",
    "sg:city":"Deerfield",
    "sg:classifiers":[
        {
            "category":"Building & Trades",
            "subcategory":"Electrical",
            "type":"Services"
        }
    ],
    "sg:phone":"+1 603 463 7229",
    "sg:postcode":"03037",
    "sg:province":"NH",
    "sg:tags":[
        "electrical",
        "contractor"
    ],
    "wof:name":"Stephen A Lafond Elec Svcs",
    "wof:placetype":"venue"
},
  "geometry": {"coordinates":[-71.21398000000001,43.158926],"type":"Point"}
}