{
  "type": "Feature",
  "properties": {
    "iso:country":"US",
    "sg:address":"161 State Rte 129",
    "sg:city":"Loudon",
    "sg:classifiers":[
        {
            "category":"Manufacturing",
            "subcategory":"Building Materials",
            "type":"Manufacturing & Wholesale Goods"
        }
    ],
    "sg:phone":"+1 603 798 5312",
    "sg:postcode":"03307",
    "sg:province":"NH",
    "wof:name":"Working Wood",
    "wof:placetype":"venue"
},
  "geometry": {"coordinates":[-71.54500899999999,43.291038],"type":"Point"}
}