{
  "type": "Feature",
  "properties": {
    "iso:country":"US",
    "sg:address":"80 Peterborough St",
    "sg:city":"Jaffrey",
    "sg:classifiers":[
        {
            "category":"Shopping",
            "subcategory":"Discount & Variety Stores",
            "type":"Retail Goods"
        },
        {
            "category":"Wholesale",
            "subcategory":"Non-durable Goods",
            "type":"Manufacturing & Wholesale Goods"
        }
    ],
    "sg:phone":"+1 603 532 8840",
    "sg:postcode":"03452",
    "sg:province":"NH",
    "sg:tags":[
        "merchandise"
    ],
    "wof:name":"Dollar Family Stores",
    "wof:placetype":"venue"
},
  "geometry": {"coordinates":[-72.020236,42.816488],"type":"Point"}
}