{
  "type": "Feature",
  "properties": {
    "iso:country":"US",
    "sg:address":"20 N Wentworth Ave",
    "sg:city":"Londonderry",
    "sg:classifiers":[
        {
            "category":"Shopping",
            "subcategory":"Catalog Store",
            "type":"Retail Goods"
        }
    ],
    "sg:phone":"+1 603 216 6000",
    "sg:postcode":"03053",
    "sg:province":"NH",
    "sg:tags":[
        "hardware",
        "computer",
        "software"
    ],
    "wof:name":"Digital Networks",
    "wof:placetype":"venue"
},
  "geometry": {"coordinates":[-71.426591,42.907304],"type":"Point"}
}