{
  "type": "Feature",
  "properties": {
    "addr:full":"2 Industrial Way Salem NH 03079",
    "addr:housenumber":"2",
    "addr:postcode":"03079",
    "addr:street":"Industrial Way",
    "iso:country":"US",
    "sg:address":"2 Industrial Way",
    "sg:city":"Salem",
    "sg:classifiers":[
        {
            "category":"Wholesale",
            "subcategory":"Machinery & Supplies",
            "type":"Manufacturing & Wholesale Goods"
        }
    ],
    "sg:phone":"+1 603 894 0003",
    "sg:postcode":"03079",
    "sg:province":"NH",
    "sg:tags":[
        "equipment",
        "screen",
        "printing"
    ],
    "wof:name":"Stentech",
    "wof:placetype":"venue"
},
  "geometry": {"coordinates":[-71.25122,42.780074],"type":"Point"}
}