{
  "type": "Feature",
  "properties": {
    "iso:country":"US",
    "sg:address":"156 Epping Rd",
    "sg:city":"Exeter",
    "sg:classifiers":[
        {
            "category":"Retail",
            "subcategory":"Auto Rental",
            "type":"Services"
        }
    ],
    "sg:phone":"+1 603 772 7145",
    "sg:postcode":"03833",
    "sg:province":"NH",
    "sg:tags":[
        "passenger",
        "car"
    ],
    "wof:name":"Enterprise Rent-A-Car",
    "wof:placetype":"venue"
},
  "geometry": {"coordinates":[-70.966928,42.988938],"type":"Point"}
}