{
  "type": "Feature",
  "properties": {
    "iso:country":"US",
    "sg:address":"254 Ridge Road Top",
    "sg:city":"New Durham",
    "sg:classifiers":[
        {
            "category":"Building & Trades",
            "subcategory":"Construction",
            "type":"Services"
        }
    ],
    "sg:phone":"+1 603 235 7885",
    "sg:postcode":"03855",
    "sg:province":"NH",
    "sg:tags":[
        "steel",
        "erectors"
    ],
    "wof:name":"Ridge Steel Inc",
    "wof:placetype":"venue"
},
  "geometry": {"coordinates":[-71.133045,43.397031],"type":"Point"}
}