{
  "type": "Feature",
  "properties": {
    "iso:country":"US",
    "sg:address":"147 Temple St",
    "sg:city":"Nashua",
    "sg:classifiers":[
        {
            "category":"Building & Trades",
            "subcategory":"Construction",
            "type":"Services"
        }
    ],
    "sg:phone":"+1 603 886 8236",
    "sg:postcode":"03060",
    "sg:province":"NH",
    "sg:tags":[
        "drywall",
        "contractor"
    ],
    "wof:name":"Wallworks LLC",
    "wof:placetype":"venue"
},
  "geometry": {"coordinates":[-71.453391,42.762084],"type":"Point"}
}