{
  "type": "Feature",
  "properties": {
    "iso:country":"US",
    "sg:address":"56 Kimball Hill Rd",
    "sg:city":"Hudson",
    "sg:classifiers":[
        {
            "category":"Organizations",
            "subcategory":"Labor Organization",
            "type":"Services"
        }
    ],
    "sg:phone":"+1 603 966 7900",
    "sg:postcode":"03051",
    "sg:province":"NH",
    "wof:name":"Dicarlo Wood Joiners",
    "wof:placetype":"venue"
},
  "geometry": {"coordinates":[-71.39326699999999,42.770213],"type":"Point"}
}