{
  "type": "Feature",
  "properties": {
    "iso:country":"US",
    "sg:address":"410 White Cedar Blvd",
    "sg:city":"Portsmouth",
    "sg:classifiers":[
        {
            "category":"Restaurant",
            "type":"Food & Drink"
        }
    ],
    "sg:phone":"+1 603 433 4414",
    "sg:postcode":"03801",
    "sg:province":"NH",
    "sg:tags":[
        "eating"
    ],
    "wof:name":"Stevens House of Pizza",
    "wof:placetype":"venue"
},
  "geometry": {"coordinates":[-70.784442,43.030883],"type":"Point"}
}