{
  "type": "Feature",
  "properties": {
    "addr:full":"11 E Broadway Derry NH 03038",
    "addr:housenumber":"11",
    "addr:postcode":"03038",
    "addr:street":"E Broadway",
    "iso:country":"US",
    "sg:address":"11 E Broadway",
    "sg:city":"Derry",
    "sg:classifiers":[
        {
            "category":"Personal",
            "subcategory":"Barber",
            "type":"Services"
        }
    ],
    "sg:phone":"+1 603 425 2499",
    "sg:postcode":"03038",
    "sg:province":"NH",
    "sg:tags":[
        "shop"
    ],
    "wof:name":"All American Barber Stylists",
    "wof:placetype":"venue"
},
  "geometry": {"coordinates":[-71.32523999999999,42.881406],"type":"Point"}
}