{
  "type": "Feature",
  "properties": {
    "addr:full":"278 Lafayette Rd Portsmouth NH 03801",
    "addr:housenumber":"278",
    "addr:postcode":"03801",
    "iso:country":"US",
    "sg:address":"278 Lafayette Rd",
    "sg:city":"Portsmouth",
    "sg:classifiers":[
        {
            "category":"Health Services",
            "subcategory":"Doctor",
            "type":"Services"
        }
    ],
    "sg:phone":"+1 603 436 3889",
    "sg:postcode":"03801",
    "sg:province":"NH",
    "wof:name":"Ananian Stephen",
    "wof:placetype":"venue"
},
  "geometry": {"coordinates":[-70.768958,43.061218],"type":"Point"}
}