{
  "type": "Feature",
  "properties": {
    "iso:country":"US",
    "sg:address":"10 Pilgrim Dr",
    "sg:city":"Bedford",
    "sg:classifiers":[
        {
            "category":"Wholesale",
            "subcategory":"Motor Vehicles",
            "type":"Manufacturing & Wholesale Goods"
        }
    ],
    "sg:phone":"+1 603 472 8000",
    "sg:postcode":"03110",
    "sg:province":"NH",
    "wof:name":"Ejd Auto",
    "wof:placetype":"venue"
},
  "geometry": {"coordinates":[-71.50861999999999,42.953426],"type":"Point"}
}