{
  "type": "Feature",
  "properties": {
    "addr:full":"211 2nd St Manchester NH 03102",
    "addr:housenumber":"211",
    "addr:postcode":"03102",
    "addr:street":"2Nd St",
    "iso:country":"US",
    "sg:address":"211 2nd St",
    "sg:city":"Manchester",
    "sg:classifiers":[
        {
            "category":"Retail",
            "subcategory":"Self-service Laundry",
            "type":"Services"
        }
    ],
    "sg:phone":"+1 603 669 8146",
    "sg:postcode":"03102",
    "sg:province":"NH",
    "sg:tags":[
        "coin"
    ],
    "wof:name":"Second Street Laundromat",
    "wof:placetype":"venue"
},
  "geometry": {"coordinates":[-71.471563,42.980782],"type":"Point"}
}