{
  "type": "Feature",
  "properties": {
    "iso:country":"US",
    "sg:address":"91 Bisson Ave",
    "sg:city":"Laconia",
    "sg:classifiers":[
        {
            "category":"Shopping",
            "type":"Retail Goods"
        }
    ],
    "sg:phone":"+1 603 528 4800",
    "sg:postcode":"03246",
    "sg:province":"NH",
    "sg:tags":[
        "medical",
        "apparatus",
        "supply"
    ],
    "wof:name":"Life Plus Medical",
    "wof:placetype":"venue"
},
  "geometry": {"coordinates":[-71.46566900000001,43.53486],"type":"Point"}
}