{
  "type": "Feature",
  "properties": {
    "iso:country":"US",
    "sg:address":"2 Main St",
    "sg:city":"Somersworth",
    "sg:classifiers":[
        {
            "category":"Restaurant",
            "type":"Food & Drink"
        }
    ],
    "sg:phone":"+1 603 692 5050",
    "sg:postcode":"03878",
    "sg:province":"NH",
    "sg:tags":[
        "caterer"
    ],
    "wof:name":"Station 319 Fine Food & Spirit",
    "wof:placetype":"venue"
},
  "geometry": {"coordinates":[-70.86351500000001,43.262853],"type":"Point"}
}