{
  "type": "Feature",
  "properties": {
    "iso:country":"US",
    "sg:address":"51 Pine St Exd",
    "sg:city":"Nashua",
    "sg:classifiers":[
        {
            "category":"Professional",
            "type":"Services"
        },
        {
            "category":"Shopping",
            "subcategory":"Catalog Store",
            "type":"Retail Goods"
        }
    ],
    "sg:phone":"+1 603 598 9990",
    "sg:postcode":"03060",
    "sg:province":"NH",
    "wof:name":"Pharmcheck Inc",
    "wof:placetype":"venue"
},
  "geometry": {"coordinates":[-71.474795,42.761737],"type":"Point"}
}