{
  "type": "Feature",
  "properties": {
    "iso:country":"US",
    "sg:address":"27 N Main St",
    "sg:city":"Rochester",
    "sg:classifiers":[
        {
            "category":"Professional",
            "subcategory":"Lawyer & Legal Services",
            "type":"Services"
        }
    ],
    "sg:phone":"+1 603 332 8499",
    "sg:postcode":"03867",
    "sg:province":"NH",
    "sg:tags":[
        "attorney"
    ],
    "wof:name":"Hanlon and Zubkus",
    "wof:placetype":"venue"
},
  "geometry": {"coordinates":[-70.977616,43.304666],"type":"Point"}
}