{
  "type": "Feature",
  "properties": {
    "iso:country":"US",
    "sg:address":"2724 E Conway Rd",
    "sg:city":"North Conway",
    "sg:classifiers":[
        {
            "category":"Shopping",
            "subcategory":"Gifts & Souvenirs",
            "type":"Retail Goods"
        }
    ],
    "sg:phone":"+1 603 356 6093",
    "sg:postcode":"03813",
    "sg:province":"ME",
    "sg:tags":[
        "shop"
    ],
    "wof:name":"Gilded Cottage",
    "wof:placetype":"venue"
},
  "geometry": {"coordinates":[-71.05962100000001,44.011238],"type":"Point"}
}