{
  "type": "Feature",
  "properties": {
    "iso:country":"US",
    "sg:address":"161 Main St",
    "sg:city":"Colebrook",
    "sg:classifiers":[
        {
            "category":"Personal",
            "subcategory":"Massage",
            "type":"Services"
        }
    ],
    "sg:phone":"+1 603 237 5007",
    "sg:postcode":"03576",
    "sg:province":"NH",
    "wof:name":"Bonsai Bodywork",
    "wof:placetype":"venue"
},
  "geometry": {"coordinates":[-71.496574,44.894205],"type":"Point"}
}