{
  "type": "Feature",
  "properties": {
    "iso:country":"US",
    "sg:address":"486 Union Ave",
    "sg:city":"Laconia",
    "sg:classifiers":[
        {
            "category":"Professional",
            "subcategory":"Lawyer & Legal Services",
            "type":"Services"
        }
    ],
    "sg:phone":"+1 603 524 4330",
    "sg:postcode":"03246",
    "sg:province":"NH",
    "sg:tags":[
        "attorney"
    ],
    "wof:name":"David H Bownes Law Office",
    "wof:placetype":"venue"
},
  "geometry": {"coordinates":[-71.46557300000001,43.539974],"type":"Point"}
}