{
  "type": "Feature",
  "properties": {
    "addr:full":"37 Union Sq Apt A Milford NH 03055",
    "addr:housenumber":"37",
    "addr:postcode":"03055",
    "addr:street":"Union Sq Apt A",
    "iso:country":"US",
    "sg:address":"37 Union Sq Apt A",
    "sg:city":"Milford",
    "sg:classifiers":[
        {
            "category":"Building & Trades",
            "subcategory":"Plumbing",
            "type":"Services"
        },
        {
            "category":"Building & Trades",
            "subcategory":"Construction",
            "type":"Services"
        }
    ],
    "sg:phone":"+1 603 673 1191",
    "sg:postcode":"03055",
    "sg:province":"NH",
    "sg:tags":[
        "plumber",
        "industrial",
        "system",
        "specialty",
        "heating",
        "contractors-commercial",
        "contractor",
        "air conditioning"
    ],
    "wof:name":"Wetherbee Plumbing & Heating",
    "wof:placetype":"venue"
},
  "geometry": {"coordinates":[-71.649348,42.835895],"type":"Point"}
}