{
  "type": "Feature",
  "properties": {
    "iso:country":"US",
    "sg:address":"27 Boulder Rd",
    "sg:city":"Madison",
    "sg:classifiers":[
        {
            "category":"Utilities",
            "subcategory":"Refuse",
            "type":"Services"
        }
    ],
    "sg:phone":"+1 603 367 8323",
    "sg:postcode":"03849",
    "sg:province":"NH",
    "sg:tags":[
        "garbage",
        "collection"
    ],
    "wof:name":"Madison Transfer Station",
    "wof:placetype":"venue"
},
  "geometry": {"coordinates":[-71.147835,43.928991],"type":"Point"}
}