{
  "type": "Feature",
  "properties": {
    "addr:full":"10 Susan Ln Rochester NH 03867",
    "addr:housenumber":"10",
    "addr:postcode":"03867",
    "addr:street":"Susan Ln",
    "iso:country":"US",
    "sg:address":"10 Susan Ln",
    "sg:city":"Rochester",
    "sg:classifiers":[
        {
            "category":"Manufacturing",
            "subcategory":"Tools & Machinery",
            "type":"Manufacturing & Wholesale Goods"
        }
    ],
    "sg:phone":"+1 603 332 7234",
    "sg:postcode":"03867",
    "sg:province":"NH",
    "sg:tags":[
        "industrial",
        "mfg"
    ],
    "wof:name":"Quality Fire Protection",
    "wof:placetype":"venue"
},
  "geometry": {"coordinates":[-70.96293799999999,43.280155],"type":"Point"}
}