{
  "type": "Feature",
  "properties": {
    "addr:full":"26 Depot St Andover NH 03216",
    "addr:housenumber":"26",
    "addr:postcode":"03216",
    "addr:street":"Depot St",
    "iso:country":"US",
    "sg:address":"26 Depot St",
    "sg:city":"Andover",
    "sg:classifiers":[
        {
            "category":"Restaurant",
            "type":"Food & Drink"
        }
    ],
    "sg:phone":"+1 603 735 5903",
    "sg:postcode":"03216",
    "sg:province":"NH",
    "sg:tags":[
        "caterer"
    ],
    "wof:name":"Depot Gourmet",
    "wof:placetype":"venue"
},
  "geometry": {"coordinates":[-71.857072,43.437114],"type":"Point"}
}