{
  "type": "Feature",
  "properties": {
    "iso:country":"US",
    "sg:address":"79 Central St",
    "sg:city":"Woodsville",
    "sg:classifiers":[
        {
            "category":"Professional",
            "subcategory":"Lawyer & Legal Services",
            "type":"Services"
        }
    ],
    "sg:phone":"+1 603 747 2338",
    "sg:postcode":"03785",
    "sg:province":"NH",
    "sg:tags":[
        "attorney"
    ],
    "wof:name":"Bernard J Wolfe Jr",
    "wof:placetype":"venue"
},
  "geometry": {"coordinates":[-72.036883,44.152199],"type":"Point"}
}