{
  "type": "Feature",
  "properties": {
    "addr:full":"45 Roxbury St Keene NH 03431",
    "addr:housenumber":"45",
    "addr:postcode":"03431",
    "addr:street":"Roxbury St",
    "iso:country":"US",
    "sg:address":"45 Roxbury St",
    "sg:city":"Keene",
    "sg:classifiers":[
        {
            "category":"Professional",
            "subcategory":"Lawyer & Legal Services",
            "type":"Services"
        }
    ],
    "sg:phone":"+1 603 352 0222",
    "sg:postcode":"03431",
    "sg:province":"NH",
    "sg:tags":[
        "attorney"
    ],
    "wof:name":"Goodnow Arwe Ayer Prigge",
    "wof:placetype":"venue"
},
  "geometry": {"coordinates":[-72.27795500000001,42.933617],"type":"Point"}
}