{
  "type": "Feature",
  "properties": {
    "iso:country":"US",
    "sg:address":"122 Cheney Rd",
    "sg:city":"Newbury",
    "sg:classifiers":[
        {
            "category":"Professional",
            "subcategory":"Management & Consulting",
            "type":"Services"
        }
    ],
    "sg:phone":"+1 603 938 5277",
    "sg:postcode":"03255",
    "sg:province":"NH",
    "sg:tags":[
        "business"
    ],
    "wof:name":"Tech Texc",
    "wof:placetype":"venue"
},
  "geometry": {"coordinates":[-71.996472,43.303982],"type":"Point"}
}