{
  "type": "Feature",
  "properties": {
    "iso:country":"US",
    "sg:address":"7 Langdon St",
    "sg:city":"Concord",
    "sg:classifiers":[
        {
            "category":"Bus Charters",
            "type":"Transportation"
        }
    ],
    "sg:phone":"+1 603 228 3300",
    "sg:postcode":"03301",
    "sg:province":"NH",
    "wof:name":"Dartmouth Trans Co",
    "wof:placetype":"venue"
},
  "geometry": {"coordinates":[-71.53192799999999,43.190824],"type":"Point"}
}