{
  "type": "Feature",
  "properties": {
    "iso:country":"US",
    "sg:address":"93 River Rd",
    "sg:city":"Hudson",
    "sg:classifiers":[
        {
            "category":"Restaurant",
            "type":"Food & Drink"
        }
    ],
    "sg:phone":"+1 603 882 7283",
    "sg:postcode":"03051",
    "sg:province":"NH",
    "sg:tags":[
        "pizza"
    ],
    "wof:name":"Pizza Man Of Hudson",
    "wof:placetype":"venue"
},
  "geometry": {"coordinates":[-71.42175400000001,42.70241],"type":"Point"}
}