{
  "type": "Feature",
  "properties": {
    "addr:full":"166 State Rte 27 Raymond NH 03077",
    "addr:housenumber":"166",
    "addr:postcode":"03077",
    "addr:street":"State Rte 27",
    "iso:country":"US",
    "sg:address":"166 State Rte 27",
    "sg:city":"Raymond",
    "sg:classifiers":[
        {
            "category":"Real Estate",
            "subcategory":"Real Estate Operator",
            "type":"Services"
        }
    ],
    "sg:phone":"+1 603 895 0376",
    "sg:postcode":"03077",
    "sg:province":"NH",
    "sg:tags":[
        "apartment"
    ],
    "wof:name":"Canterbury Commons Apartments",
    "wof:placetype":"venue"
},
  "geometry": {"coordinates":[-71.197619,43.039385],"type":"Point"}
}