{
  "type": "Feature",
  "properties": {
    "iso:country":"US",
    "sg:address":"164 Liberty Hill Rd",
    "sg:city":"Bedford",
    "sg:classifiers":[
        {
            "category":"Real Estate",
            "subcategory":"Real Estate Agent",
            "type":"Services"
        }
    ],
    "sg:phone":"+1 603 472 4008",
    "sg:postcode":"03110",
    "sg:province":"NH",
    "wof:name":"Briggs Appraisal Services",
    "wof:placetype":"venue"
},
  "geometry": {"coordinates":[-71.503462,42.932924],"type":"Point"}
}