{
  "type": "Feature",
  "properties": {
    "addr:full":"42 Sumner Dr Dover NH 03820",
    "addr:housenumber":"42",
    "addr:postcode":"03820",
    "addr:street":"Sumner Dr",
    "iso:country":"US",
    "sg:address":"42 Sumner Dr",
    "sg:city":"Dover",
    "sg:classifiers":[
        {
            "category":"Local Transit",
            "type":"Transportation"
        }
    ],
    "sg:phone":"+1 603 743 5777",
    "sg:postcode":"03820",
    "sg:province":"NH",
    "sg:tags":[
        "line"
    ],
    "sg:website":"www.coastbus.org",
    "wof:name":"Coast Public Transit",
    "wof:placetype":"venue"
},
  "geometry": {"coordinates":[-70.90079299999999,43.180588],"type":"Point"}
}