{
  "type": "Feature",
  "properties": {
    "iso:country":"US",
    "sg:address":"65 Chester Rd",
    "sg:city":"Raymond",
    "sg:classifiers":[
        {
            "category":"Wholesale",
            "subcategory":"Durable Goods & Equipment",
            "type":"Manufacturing & Wholesale Goods"
        }
    ],
    "sg:phone":"+1 603 895 4532",
    "sg:postcode":"03077",
    "sg:province":"NH",
    "wof:name":"Al Martin Antiques",
    "wof:placetype":"venue"
},
  "geometry": {"coordinates":[-71.17486100000001,43.002463],"type":"Point"}
}