{
  "type": "Feature",
  "properties": {
    "addr:full":"31 Baboosic Lake Rd Merrimack NH 03054",
    "addr:housenumber":"31",
    "addr:postcode":"03054",
    "addr:street":"Baboosic Lake Rd",
    "iso:country":"US",
    "sg:address":"31 Baboosic Lake Rd",
    "sg:city":"Merrimack",
    "sg:classifiers":[
        {
            "category":"Government",
            "subcategory":"Police Station",
            "type":"Public Place"
        }
    ],
    "sg:phone":"+1 603 424 2424",
    "sg:postcode":"03054",
    "sg:province":"NH",
    "sg:tags":[
        "department"
    ],
    "wof:name":"Merrimack Crime Line Inc",
    "wof:placetype":"venue"
},
  "geometry": {"coordinates":[-71.49932099999999,42.867809],"type":"Point"}
}