{
  "type": "Feature",
  "properties": {
    "iso:country":"US",
    "sg:address":"204 Pattee Hill Rd",
    "sg:city":"Goffstown",
    "sg:classifiers":[
        {
            "category":"Building & Trades",
            "subcategory":"Electrical",
            "type":"Services"
        }
    ],
    "sg:phone":"+1 603 497 8744",
    "sg:postcode":"03045",
    "sg:province":"NH",
    "sg:tags":[
        "electrical",
        "contractor"
    ],
    "wof:name":"Kimbrian Electrical Services",
    "wof:placetype":"venue"
},
  "geometry": {"coordinates":[-71.598316,43.037329],"type":"Point"}
}