{
  "type": "Feature",
  "properties": {
    "iso:country":"US",
    "sg:address":"8 Gordon Rd",
    "sg:city":"Bow",
    "sg:classifiers":[
        {
            "category":"Retail",
            "subcategory":"Auto Rental",
            "type":"Services"
        }
    ],
    "sg:phone":"+1 603 410 6440",
    "sg:postcode":"03304",
    "sg:province":"NH",
    "sg:tags":[
        "recreational",
        "leasing",
        "vehicle"
    ],
    "wof:name":"Northeast Rv Rentals LLC",
    "wof:placetype":"venue"
},
  "geometry": {"coordinates":[-71.490314,43.142956],"type":"Point"}
}