{
  "type": "Feature",
  "properties": {
    "iso:country":"US",
    "sg:address":"426 Bay Rd",
    "sg:city":"Farmington",
    "sg:classifiers":[
        {
            "category":"Autos & Motor Vehicles",
            "subcategory":"Auto Supplies",
            "type":"Retail Goods"
        }
    ],
    "sg:phone":"+1 603 859 2571",
    "sg:postcode":"03824",
    "sg:province":"NH",
    "sg:tags":[
        "tire"
    ],
    "wof:name":"Pappy's Auto & Truck Tire Svc",
    "wof:placetype":"venue"
},
  "geometry": {"coordinates":[-70.883708,43.095285],"type":"Point"}
}