{
  "type": "Feature",
  "properties": {
    "addr:full":"480 South St Littleton NH 03561",
    "addr:housenumber":"480",
    "addr:postcode":"03561",
    "addr:street":"South St",
    "iso:country":"US",
    "sg:address":"480 South St",
    "sg:city":"Littleton",
    "sg:classifiers":[
        {
            "category":"Building & Trades",
            "subcategory":"Construction",
            "type":"Services"
        }
    ],
    "sg:phone":"+1 603 444 4056",
    "sg:postcode":"03561",
    "sg:province":"NH",
    "sg:tags":[
        "excavation",
        "contractor"
    ],
    "wof:name":"Nute Excavating Inc",
    "wof:placetype":"venue"
},
  "geometry": {"coordinates":[-71.787886,44.304452],"type":"Point"}
}