{
  "type": "Feature",
  "properties": {
    "addr:full":"93 Lowell Rd Hudson NH 03051",
    "addr:housenumber":"93",
    "addr:postcode":"03051",
    "addr:street":"Lowell Rd",
    "iso:country":"US",
    "sg:address":"93 Lowell Rd",
    "sg:city":"Hudson",
    "sg:classifiers":[
        {
            "category":"Home & Garden",
            "subcategory":"Home Furnishings",
            "type":"Retail Goods"
        }
    ],
    "sg:phone":"+1 603 883 2907",
    "sg:postcode":"03051",
    "sg:province":"NH",
    "sg:tags":[
        "trade",
        "contractor"
    ],
    "wof:name":"Vertical Etc",
    "wof:placetype":"venue"
},
  "geometry": {"coordinates":[-71.429019,42.753334],"type":"Point"}
}