{
  "type": "Feature",
  "properties": {
    "iso:country":"US",
    "sg:address":"5 Garden Ln",
    "sg:city":"Londonderry",
    "sg:classifiers":[
        {
            "category":"Shopping",
            "subcategory":"Department Store",
            "type":"Retail Goods"
        }
    ],
    "sg:phone":"+1 603 437 2430",
    "sg:postcode":"03053",
    "sg:province":"NH",
    "wof:name":"Marshalls",
    "wof:placetype":"venue"
},
  "geometry": {"coordinates":[-71.34760799999999,42.867584],"type":"Point"}
}