{
  "type": "Feature",
  "properties": {
    "iso:country":"US",
    "sg:address":"61 Calef Hwy",
    "sg:city":"Rochester",
    "sg:classifiers":[
        {
            "category":"Wholesale",
            "subcategory":"Machinery & Supplies",
            "type":"Manufacturing & Wholesale Goods"
        }
    ],
    "sg:phone":"+1 603 335 9277",
    "sg:postcode":"03839",
    "sg:province":"NH",
    "sg:tags":[
        "industrial"
    ],
    "wof:name":"Hydraulic Hose New Hampshire",
    "wof:placetype":"venue"
},
  "geometry": {"coordinates":[-70.979209,43.254051],"type":"Point"}
}