{
  "type": "Feature",
  "properties": {
    "iso:country":"US",
    "sg:address":"1 Major Ln",
    "sg:city":"Plaistow",
    "sg:classifiers":[
        {
            "category":"Building & Trades",
            "subcategory":"Construction",
            "type":"Services"
        }
    ],
    "sg:phone":"+1 603 382 7537",
    "sg:postcode":"03865",
    "sg:province":"NH",
    "sg:tags":[
        "contractor"
    ],
    "wof:name":"TLC Construction",
    "wof:placetype":"venue"
},
  "geometry": {"coordinates":[-71.089342,42.84178],"type":"Point"}
}