{
  "type": "Feature",
  "properties": {
    "iso:country":"US",
    "sg:address":"16 Thompson Rd",
    "sg:city":"Westmoreland",
    "sg:classifiers":[
        {
            "category":"Building & Trades",
            "subcategory":"Construction",
            "type":"Services"
        }
    ],
    "sg:phone":"+1 603 399 4844",
    "sg:postcode":"03467",
    "sg:province":"NH",
    "sg:tags":[
        "resurfacing",
        "laying",
        "refinishing",
        "floor"
    ],
    "wof:name":"New Life Floor Sanding",
    "wof:placetype":"venue"
},
  "geometry": {"coordinates":[-72.39646399999999,42.989661],"type":"Point"}
}