{
  "type": "Feature",
  "properties": {
    "addr:full":"516 Laconia Rd Tilton NH 03276",
    "addr:housenumber":"516",
    "addr:postcode":"03276",
    "addr:street":"Laconia Rd",
    "iso:country":"US",
    "sg:address":"516 Laconia Rd",
    "sg:city":"Tilton",
    "sg:classifiers":[
        {
            "category":"Wholesale",
            "subcategory":"Construction Materials",
            "type":"Manufacturing & Wholesale Goods"
        }
    ],
    "sg:phone":"+1 603 524 0226",
    "sg:postcode":"03276",
    "sg:province":"NH",
    "sg:tags":[
        "fence"
    ],
    "wof:name":"Superior Fence Co",
    "wof:placetype":"venue"
},
  "geometry": {"coordinates":[-71.54192,43.477966],"type":"Point"}
}