{
  "type": "Feature",
  "properties": {
    "addr:full":"176 W High St Somersworth NH 03878",
    "addr:housenumber":"176",
    "addr:postcode":"03878",
    "addr:street":"W High St",
    "iso:country":"US",
    "sg:address":"176 W High St",
    "sg:city":"Somersworth",
    "sg:classifiers":[
        {
            "category":"Organizations",
            "subcategory":"Religious Organization",
            "type":"Services"
        }
    ],
    "sg:phone":"+1 603 692 2057",
    "sg:postcode":"03878",
    "sg:province":"NH",
    "sg:tags":[
        "church"
    ],
    "sg:website":"www.somersworthfirstparish.org",
    "wof:name":"First Parish United Church",
    "wof:placetype":"venue"
},
  "geometry": {"coordinates":[-70.898285,43.263095],"type":"Point"}
}