{
  "type": "Feature",
  "properties": {
    "iso:country":"US",
    "sg:address":"207 Stage Rd",
    "sg:city":"Hampstead",
    "sg:classifiers":[
        {
            "category":"Health Services",
            "subcategory":"Doctor",
            "type":"Services"
        }
    ],
    "sg:phone":"+1 603 329 4351",
    "sg:postcode":"03841",
    "sg:province":"NH",
    "sg:tags":[
        "physician",
        "surgeon"
    ],
    "wof:name":"Allergy Asthma & Immunology",
    "wof:placetype":"venue"
},
  "geometry": {"coordinates":[-71.173554,42.86266],"type":"Point"}
}