{
  "type": "Feature",
  "properties": {
    "iso:country":"US",
    "sg:address":"16 Church St",
    "sg:city":"Kingston",
    "sg:classifiers":[
        {
            "category":"Wholesale",
            "subcategory":"Durable Goods & Equipment",
            "type":"Manufacturing & Wholesale Goods"
        }
    ],
    "sg:phone":"+1 603 642 3304",
    "sg:postcode":"03848",
    "sg:province":"NH",
    "sg:tags":[
        "exporter"
    ],
    "sg:website":"www.abenakitimber.com",
    "wof:name":"Abenaki Timber Corp",
    "wof:placetype":"venue"
},
  "geometry": {"coordinates":[-71.055976,42.939669],"type":"Point"}
}