{
  "type": "Feature",
  "properties": {
    "addr:full":"270 Main St Tilton NH 03276",
    "addr:housenumber":"270",
    "addr:postcode":"03276",
    "addr:street":"Main St",
    "iso:country":"US",
    "sg:address":"270 Main St",
    "sg:city":"Tilton",
    "sg:classifiers":[
        {
            "category":"Home & Garden",
            "subcategory":"Hardware",
            "type":"Retail Goods"
        }
    ],
    "sg:phone":"+1 603 286 4322",
    "sg:postcode":"03276",
    "sg:province":"NH",
    "sg:tags":[
        "sporting"
    ],
    "wof:name":"Bryant & Lawrence Inc",
    "wof:placetype":"venue"
},
  "geometry": {"coordinates":[-71.589257,43.442167],"type":"Point"}
}