{
  "type": "Feature",
  "properties": {
    "addr:full":"183 Douglas St Manchester NH 03102",
    "addr:housenumber":"183",
    "addr:postcode":"03102",
    "addr:street":"Douglas St",
    "iso:country":"US",
    "sg:address":"183 Douglas St",
    "sg:city":"Manchester",
    "sg:classifiers":[
        {
            "category":"Organizations",
            "subcategory":"Community Association",
            "type":"Services"
        }
    ],
    "sg:phone":"+1 603 623 9035",
    "sg:postcode":"03102",
    "sg:province":"NH",
    "sg:tags":[
        "club"
    ],
    "wof:name":"Workmen's Relief Assn",
    "wof:placetype":"venue"
},
  "geometry": {"coordinates":[-71.47718999999999,42.984711],"type":"Point"}
}