{
  "type": "Feature",
  "properties": {
    "iso:country":"US",
    "sg:address":"75 Forest Park Dr",
    "sg:city":"Nashua",
    "sg:classifiers":[
        {
            "category":"Building & Trades",
            "subcategory":"Construction",
            "type":"Services"
        }
    ],
    "sg:phone":"+1 603 321 1267",
    "sg:postcode":"03060",
    "sg:province":"NH",
    "sg:tags":[
        "house"
    ],
    "wof:name":"Jmh Construction NH Sash",
    "wof:placetype":"venue"
},
  "geometry": {"coordinates":[-71.478441,42.7373],"type":"Point"}
}