{
  "type": "Feature",
  "properties": {
    "addr:full":"18 Sumac St Exeter NH 03833",
    "addr:housenumber":"18",
    "addr:postcode":"03833",
    "addr:street":"Sumac St",
    "iso:country":"US",
    "sg:address":"18 Sumac St",
    "sg:city":"Exeter",
    "sg:classifiers":[
        {
            "category":"Freight",
            "type":"Transportation"
        }
    ],
    "sg:phone":"+1 603 778 3832",
    "sg:postcode":"03833",
    "sg:province":"NH",
    "sg:tags":[
        "operator",
        "local",
        "trucking"
    ],
    "wof:name":"Lane Trucking and Leasing",
    "wof:placetype":"venue"
},
  "geometry": {"coordinates":[-70.970069,42.96579],"type":"Point"}
}