{
  "type": "Feature",
  "properties": {
    "addr:full":"542 S Mast Rd Goffstown NH 03045",
    "addr:housenumber":"542",
    "addr:postcode":"03045",
    "addr:street":"S Mast Rd",
    "iso:country":"US",
    "sg:address":"542 S Mast Rd",
    "sg:city":"Goffstown",
    "sg:classifiers":[
        {
            "category":"Personal",
            "subcategory":"Beauty Salon",
            "type":"Services"
        }
    ],
    "sg:phone":"+1 603 627 5455",
    "sg:postcode":"03045",
    "sg:province":"NH",
    "sg:tags":[
        "manicuring"
    ],
    "wof:name":"Crystal Nails",
    "wof:placetype":"venue"
},
  "geometry": {"coordinates":[-71.51777800000001,43.001532],"type":"Point"}
}