{
  "type": "Feature",
  "properties": {
    "iso:country":"US",
    "sg:address":"54 Maple St",
    "sg:city":"Center Sandwich",
    "sg:classifiers":[
        {
            "category":"Social Services",
            "subcategory":"Child Care",
            "type":"Services"
        }
    ],
    "sg:phone":"+1 603 284 7014",
    "sg:postcode":"03227",
    "sg:province":"NH",
    "sg:tags":[
        "day"
    ],
    "wof:name":"Sandwich Children Center",
    "wof:placetype":"venue"
},
  "geometry": {"coordinates":[-71.43468799999999,43.810945],"type":"Point"}
}