{
  "type": "Feature",
  "properties": {
    "iso:country":"US",
    "sg:address":"11 Eagle Ct",
    "sg:city":"Keene",
    "sg:classifiers":[
        {
            "category":"Utilities",
            "subcategory":"Cable",
            "type":"Services"
        }
    ],
    "sg:phone":"+1 603 352 6421",
    "sg:postcode":"03431",
    "sg:province":"NH",
    "sg:tags":[
        "television"
    ],
    "wof:name":"Time Warner Cable",
    "wof:placetype":"venue"
},
  "geometry": {"coordinates":[-72.277796,42.930897],"type":"Point"}
}