{
  "type": "Feature",
  "properties": {
    "addr:full":"113 MILTON RD ROCHESTER NH 03868",
    "addr:housenumber":"113",
    "addr:postcode":"03868",
    "addr:street":"Milton Rd",
    "iso:country":"US",
    "sg:address":"113 MILTON RD",
    "sg:city":"ROCHESTER",
    "sg:classifiers":[
        {
            "category":"Building & Trades",
            "subcategory":"Cleaning & Sanitation",
            "type":"Services"
        },
        {
            "category":"Building & Trades",
            "subcategory":"Construction",
            "type":"Services"
        }
    ],
    "sg:phone":"+1 603 509 4143",
    "sg:postcode":"03868",
    "sg:province":"NH",
    "sg:tags":[
        "system",
        "specialty",
        "duct",
        "heating",
        "contractor",
        "air conditioning"
    ],
    "sg:website":"http://www.tomtracker.com/redirect.cfm?bID=20757&hID=123132",
    "wof:name":"Strogen's Service Experts",
    "wof:placetype":"venue"
},
  "geometry": {"coordinates":[-70.97383499999999,43.343421],"type":"Point"}
}