{
  "type": "Feature",
  "properties": {
    "iso:country":"US",
    "sg:address":"3 Commerce Dr",
    "sg:city":"Atkinson",
    "sg:classifiers":[
        {
            "category":"Wholesale",
            "subcategory":"Durable Goods & Equipment",
            "type":"Manufacturing & Wholesale Goods"
        }
    ],
    "sg:phone":"+1 603 893 9566",
    "sg:postcode":"03811",
    "sg:province":"NH",
    "sg:tags":[
        "representative",
        "manufacturer"
    ],
    "sg:website":"www.intertechcorp.net",
    "wof:name":"Intertech Corp",
    "wof:placetype":"venue"
},
  "geometry": {"coordinates":[-71.195093,42.851207],"type":"Point"}
}