{
  "type": "Feature",
  "properties": {
    "addr:full":"1 Hancock St Rochester NH 03867",
    "addr:housenumber":"1",
    "addr:postcode":"03867",
    "addr:street":"Hancock St",
    "iso:country":"US",
    "sg:address":"1 Hancock St",
    "sg:city":"Rochester",
    "sg:classifiers":[
        {
            "category":"Food & Beverages",
            "subcategory":"Groceries & Convenience Stores",
            "type":"Retail Goods"
        }
    ],
    "sg:phone":"+1 603 332 5428",
    "sg:postcode":"03867",
    "sg:province":"NH",
    "sg:tags":[
        "grocer"
    ],
    "wof:name":"Arthur's Market",
    "wof:placetype":"venue"
},
  "geometry": {"coordinates":[-70.971079,43.296349],"type":"Point"}
}