{
  "type": "Feature",
  "properties": {
    "iso:country":"US",
    "sg:address":"83 Marlboro St",
    "sg:city":"Keene",
    "sg:classifiers":[
        {
            "category":"Personal",
            "subcategory":"Piercing",
            "type":"Services"
        }
    ],
    "sg:phone":"+1 603 355 0111",
    "sg:postcode":"03431",
    "sg:province":"NH",
    "sg:tags":[
        "body"
    ],
    "wof:name":"Pierce This 2",
    "wof:placetype":"venue"
},
  "geometry": {"coordinates":[-72.27483599999999,42.927754],"type":"Point"}
}