{
  "type": "Feature",
  "properties": {
    "addr:full":"70 Keene Rd Winchester NH 03470",
    "addr:housenumber":"70",
    "addr:postcode":"03470",
    "addr:street":"Keene Rd",
    "iso:country":"US",
    "sg:address":"70 Keene Rd",
    "sg:city":"Winchester",
    "sg:classifiers":[
        {
            "category":"Building & Trades",
            "subcategory":"Plumbing",
            "type":"Services"
        },
        {
            "category":"Building & Trades",
            "subcategory":"Cleaning & Sanitation",
            "type":"Services"
        }
    ],
    "sg:phone":"+1 603 239 4205",
    "sg:postcode":"03470",
    "sg:province":"NH",
    "sg:tags":[
        "cleaner",
        "repairer",
        "sewer",
        "plumbing-drain"
    ],
    "wof:name":"New England Sweeping Co",
    "wof:placetype":"venue"
},
  "geometry": {"coordinates":[-72.37862199999999,42.790622],"type":"Point"}
}