{
  "type": "Feature",
  "properties": {
    "addr:full":"112 Pleasant St Berlin NH 03570",
    "addr:housenumber":"112",
    "addr:postcode":"03570",
    "addr:street":"Pleasant St",
    "iso:country":"US",
    "sg:address":"112 Pleasant St",
    "sg:city":"Berlin",
    "sg:classifiers":[
        {
            "category":"Organizations",
            "subcategory":"Community Association",
            "type":"Services"
        }
    ],
    "sg:phone":"+1 603 752 6432",
    "sg:postcode":"03570",
    "sg:province":"NH",
    "sg:tags":[
        "military"
    ],
    "wof:name":"American Legion",
    "wof:placetype":"venue"
},
  "geometry": {"coordinates":[-71.18223,44.469558],"type":"Point"}
}