{
  "type": "Feature",
  "properties": {
    "iso:country":"US",
    "sg:address":"349 Turnpike Rd",
    "sg:city":"New Ipswich",
    "sg:classifiers":[
        {
            "category":"Autos & Motor Vehicles",
            "subcategory":"Fuel & Gas Station",
            "type":"Retail Goods"
        }
    ],
    "sg:phone":"+1 603 878 1328",
    "sg:postcode":"03071",
    "sg:province":"NH",
    "sg:tags":[
        "oil"
    ],
    "wof:name":"Ron's Citgo",
    "wof:placetype":"venue"
},
  "geometry": {"coordinates":[-71.828417,42.750502],"type":"Point"}
}