{
  "type": "Feature",
  "properties": {
    "addr:full":"18 East Rd Hampstead NH 03841",
    "addr:housenumber":"18",
    "addr:postcode":"03841",
    "addr:street":"East Rd",
    "iso:country":"US",
    "sg:address":"18 East Rd",
    "sg:city":"Hampstead",
    "sg:classifiers":[
        {
            "category":"Health Services",
            "subcategory":"Doctor",
            "type":"Services"
        }
    ],
    "sg:phone":"+1 603 329 4040",
    "sg:postcode":"03841",
    "sg:province":"NH",
    "sg:tags":[
        "physician",
        "surgeon"
    ],
    "wof:name":"Michael Romanowsky MD",
    "wof:placetype":"venue"
},
  "geometry": {"coordinates":[-71.16591099999999,42.875976],"type":"Point"}
}