{
  "type": "Feature",
  "properties": {
    "iso:country":"US",
    "sg:address":"10 Vose Farm Rd",
    "sg:city":"Peterborough",
    "sg:classifiers":[
        {
            "category":"Professional",
            "subcategory":"Advertising",
            "type":"Services"
        }
    ],
    "sg:phone":"+1 603 924 9262",
    "sg:postcode":"03458",
    "sg:province":"NH",
    "sg:tags":[
        "mailing",
        "list"
    ],
    "sg:website":"www.millard.com",
    "wof:name":"Millard Group Inc",
    "wof:placetype":"venue"
},
  "geometry": {"coordinates":[-71.934584,42.914406],"type":"Point"}
}