{
  "type": "Feature",
  "properties": {
    "iso:country":"US",
    "sg:address":"405 Critchett Rd",
    "sg:city":"Candia",
    "sg:classifiers":[
        {
            "category":"Wholesale",
            "subcategory":"Construction Materials",
            "type":"Manufacturing & Wholesale Goods"
        }
    ],
    "sg:phone":"+1 603 594 0782",
    "sg:postcode":"03034",
    "sg:province":"NH",
    "sg:tags":[
        "self",
        "storage"
    ],
    "wof:name":"Storage Solutions Wooden Sheds",
    "wof:placetype":"venue"
},
  "geometry": {"coordinates":[-71.242435,43.072456],"type":"Point"}
}