{
  "type": "Feature",
  "properties": {
    "iso:country":"US",
    "sg:address":"145 Temple St",
    "sg:city":"Nashua",
    "sg:classifiers":[
        {
            "category":"Home & Garden",
            "subcategory":"Building Materials",
            "type":"Retail Goods"
        }
    ],
    "sg:phone":"+1 603 883 7776",
    "sg:postcode":"03060",
    "sg:province":"NH",
    "sg:tags":[
        "lumber"
    ],
    "wof:name":"Moore's Lumber Yards & Bldg",
    "wof:placetype":"venue"
},
  "geometry": {"coordinates":[-71.453345,42.762209],"type":"Point"}
}