{
  "type": "Feature",
  "properties": {
    "iso:country":"US",
    "sg:address":"789 Union Ave",
    "sg:city":"Laconia",
    "sg:classifiers":[
        {
            "category":"Personal",
            "subcategory":"Beauty Salon",
            "type":"Services"
        }
    ],
    "sg:phone":"+1 603 524 3090",
    "sg:postcode":"03246",
    "sg:province":"NH",
    "sg:tags":[
        "manicuring"
    ],
    "wof:name":"M C Nails",
    "wof:placetype":"venue"
},
  "geometry": {"coordinates":[-71.46316400000001,43.545991],"type":"Point"}
}