{
  "type": "Feature",
  "properties": {
    "iso:country":"US",
    "sg:address":"102 Perimeter Rd",
    "sg:city":"Nashua",
    "sg:classifiers":[
        {
            "category":"Utilities",
            "subcategory":"Telephone",
            "type":"Services"
        }
    ],
    "sg:phone":"+1 603 883 4477",
    "sg:postcode":"03063",
    "sg:province":"NH",
    "sg:tags":[
        "communication",
        "datum"
    ],
    "wof:name":"CTC Communications Corp",
    "wof:placetype":"venue"
},
  "geometry": {"coordinates":[-71.52396,42.78231],"type":"Point"}
}