{
  "type": "Feature",
  "properties": {
    "iso:country":"US",
    "sg:address":"18 Kirriemuir Rd",
    "sg:city":"Stratham",
    "sg:classifiers":[
        {
            "category":"Professional",
            "subcategory":"Management & Consulting",
            "type":"Services"
        }
    ],
    "sg:phone":"+1 603 778 8197",
    "sg:postcode":"03885",
    "sg:province":"NH",
    "wof:name":"Online Marketing Strategies",
    "wof:placetype":"venue"
},
  "geometry": {"coordinates":[-70.899333,42.998665],"type":"Point"}
}