{
  "type": "Feature",
  "properties": {
    "addr:full":"330 Village St Concord NH 03303",
    "addr:housenumber":"330",
    "addr:postcode":"03303",
    "addr:street":"Village St",
    "iso:country":"US",
    "sg:address":"330 Village St",
    "sg:city":"Concord",
    "sg:classifiers":[
        {
            "category":"Restaurant",
            "type":"Food & Drink"
        }
    ],
    "sg:phone":"+1 603 753 8855",
    "sg:postcode":"03303",
    "sg:province":"NH",
    "sg:tags":[
        "chinese"
    ],
    "wof:name":"Seven Star",
    "wof:placetype":"venue"
},
  "geometry": {"coordinates":[-71.60072,43.281084],"type":"Point"}
}