{
  "type": "Feature",
  "properties": {
    "addr:full":"35 3rd St Dover NH 03820",
    "addr:housenumber":"35",
    "addr:postcode":"03820",
    "addr:street":"3Rd St",
    "iso:country":"US",
    "sg:address":"35 3rd St",
    "sg:city":"Dover",
    "sg:classifiers":[
        {
            "category":"Organizations",
            "subcategory":"Community Association",
            "type":"Services"
        }
    ],
    "sg:phone":"+1 603 742 6916",
    "sg:postcode":"03820",
    "sg:province":"NH",
    "sg:tags":[
        "club"
    ],
    "wof:name":"Dover Senior Ctr",
    "wof:placetype":"venue"
},
  "geometry": {"coordinates":[-70.87682,43.198687],"type":"Point"}
}