{
  "type": "Feature",
  "properties": {
    "addr:full":"1228 Elm St Manchester NH 03101",
    "addr:housenumber":"1228",
    "addr:postcode":"03101",
    "addr:street":"Elm St",
    "iso:country":"US",
    "sg:address":"1228 Elm St",
    "sg:city":"Manchester",
    "sg:classifiers":[
        {
            "category":"Social Services",
            "type":"Services"
        }
    ],
    "sg:phone":"+1 603 668 4111",
    "sg:postcode":"03101",
    "sg:province":"NH",
    "sg:tags":[
        "guidance",
        "child"
    ],
    "wof:name":"Child & Adolescent Counseling",
    "wof:placetype":"venue"
},
  "geometry": {"coordinates":[-71.463539,42.996148],"type":"Point"}
}