{
  "type": "Feature",
  "properties": {
    "iso:country":"US",
    "sg:address":"37 Autumn Pond Park",
    "sg:city":"Greenland",
    "sg:classifiers":[
        {
            "category":"Shopping",
            "subcategory":"Computers & Home Electronics",
            "type":"Retail Goods"
        }
    ],
    "sg:phone":"+1 603 433 0040",
    "sg:postcode":"03840",
    "sg:province":"NH",
    "sg:tags":[
        "equipment",
        "electronic",
        "supply"
    ],
    "wof:name":"Ocean Electronics",
    "wof:placetype":"venue"
},
  "geometry": {"coordinates":[-70.824641,43.040114],"type":"Point"}
}