{
  "type": "Feature",
  "properties": {
    "iso:country":"US",
    "sg:address":"210 Gonic Rd",
    "sg:city":"Rochester",
    "sg:classifiers":[
        {
            "category":"Retail",
            "subcategory":"Auto Repair",
            "type":"Services"
        }
    ],
    "sg:phone":"+1 603 335 0302",
    "sg:postcode":"03839",
    "sg:province":"NH",
    "sg:tags":[
        "scooter",
        "motorcycle",
        "motor"
    ],
    "wof:name":"Bonehead Designs",
    "wof:placetype":"venue"
},
  "geometry": {"coordinates":[-70.978972,43.260221],"type":"Point"}
}