{
  "type": "Feature",
  "properties": {
    "iso:country":"US",
    "sg:address":"546 Main St",
    "sg:city":"Laconia",
    "sg:classifiers":[
        {
            "category":"Restaurant",
            "type":"Food & Drink"
        }
    ],
    "sg:phone":"+1 603 527 0177",
    "sg:postcode":"03246",
    "sg:province":"NH",
    "wof:name":"Goodfellas Tavern & Grill",
    "wof:placetype":"venue"
},
  "geometry": {"coordinates":[-71.469825,43.527522],"type":"Point"}
}