{
  "type": "Feature",
  "properties": {
    "addr:full":"119 Walnut St Rochester NH 03867",
    "addr:housenumber":"119",
    "addr:postcode":"03867",
    "addr:street":"Walnut St",
    "iso:country":"US",
    "sg:address":"119 Walnut St",
    "sg:city":"Rochester",
    "sg:classifiers":[
        {
            "category":"Building & Trades",
            "subcategory":"Landscaping Services",
            "type":"Services"
        }
    ],
    "sg:phone":"+1 603 332 1246",
    "sg:postcode":"03867",
    "sg:province":"NH",
    "sg:tags":[
        "landscape",
        "contractor"
    ],
    "sg:website":"www.urbantreeservice.com",
    "wof:name":"Urban Tree Svc",
    "wof:placetype":"venue"
},
  "geometry": {"coordinates":[-70.995054,43.304959],"type":"Point"}
}