{
  "type": "Feature",
  "properties": {
    "addr:full":"76 Lower Pratt Pond Rd New Ipswich NH 03071",
    "addr:housenumber":"76",
    "addr:postcode":"03071",
    "addr:street":"Lower Pratt Pond Rd",
    "iso:country":"US",
    "sg:address":"76 Lower Pratt Pond Rd",
    "sg:city":"New Ipswich",
    "sg:classifiers":[
        {
            "category":"Shopping",
            "subcategory":"Gifts & Souvenirs",
            "type":"Retail Goods"
        }
    ],
    "sg:phone":"+1 603 878 0651",
    "sg:postcode":"03071",
    "sg:province":"NH",
    "wof:name":"Card Transport Inc",
    "wof:placetype":"venue"
},
  "geometry": {"coordinates":[-71.902761,42.7355],"type":"Point"}
}