{
  "type": "Feature",
  "properties": {
    "iso:country":"US",
    "sg:address":"7 Peabody Rd",
    "sg:city":"Derry",
    "sg:classifiers":[
        {
            "category":"Health Services",
            "subcategory":"Doctor",
            "type":"Services"
        }
    ],
    "sg:phone":"+1 603 434 4962",
    "sg:postcode":"03038",
    "sg:province":"NH",
    "sg:tags":[
        "dentist"
    ],
    "wof:name":"Derry Dental Assoc",
    "wof:placetype":"venue"
},
  "geometry": {"coordinates":[-71.322711,42.894276],"type":"Point"}
}