{
  "type": "Feature",
  "properties": {
    "addr:full":"99 Rockingham Park Blvd Salem NH 03079",
    "addr:housenumber":"99",
    "addr:postcode":"03079",
    "addr:street":"Rockingham Park Blvd",
    "iso:country":"US",
    "sg:address":"99 Rockingham Park Blvd",
    "sg:city":"Salem",
    "sg:classifiers":[
        {
            "category":"Restaurant",
            "type":"Food & Drink"
        }
    ],
    "sg:menulink":"http://www.allmenus.com/nh/salem/204926-taco-bell/menu/",
    "sg:phone":"+1 603 898 1335",
    "sg:postcode":"03079",
    "sg:province":"NH",
    "sg:tags":[
        "mexican"
    ],
    "wof:name":"Taco Bell",
    "wof:placetype":"venue"
},
  "geometry": {"coordinates":[-71.224903,42.767459],"type":"Point"}
}