{
  "type": "Feature",
  "properties": {
    "addr:full":"600 Farrington Corner Rd Contoocook NH 03229",
    "addr:housenumber":"600",
    "addr:postcode":"03229",
    "addr:street":"Farrington Corner Rd",
    "iso:country":"US",
    "sg:address":"600 Farrington Corner Rd",
    "sg:city":"Contoocook",
    "sg:classifiers":[
        {
            "category":"Building & Trades",
            "subcategory":"Construction",
            "type":"Services"
        }
    ],
    "sg:phone":"+1 603 224 2720",
    "sg:postcode":"03229",
    "sg:province":"NH",
    "wof:name":"GTS Construction",
    "wof:placetype":"venue"
},
  "geometry": {"coordinates":[-71.634263,43.176129],"type":"Point"}
}