{
  "type": "Feature",
  "properties": {
    "addr:full":"8 Moreau St Manchester NH 03102",
    "addr:housenumber":"8",
    "addr:postcode":"03102",
    "addr:street":"Moreau St",
    "iso:country":"US",
    "sg:address":"8 Moreau St",
    "sg:city":"Manchester",
    "sg:classifiers":[
        {
            "category":"Professional",
            "subcategory":"Computer Services",
            "type":"Services"
        }
    ],
    "sg:phone":"+1 603 624 9609",
    "sg:postcode":"03102",
    "sg:province":"NH",
    "wof:name":"Top Shelf PC",
    "wof:placetype":"venue"
},
  "geometry": {"coordinates":[-71.510655,42.996515],"type":"Point"}
}