{
  "type": "Feature",
  "properties": {
    "addr:full":"26 Country Acres Rd Sandown NH 03873",
    "addr:housenumber":"26",
    "addr:postcode":"03873",
    "addr:street":"Country Acres Rd",
    "iso:country":"US",
    "sg:address":"26 Country Acres Rd",
    "sg:city":"Sandown",
    "sg:classifiers":[
        {
            "category":"Shopping",
            "subcategory":"Computers & Home Electronics",
            "type":"Retail Goods"
        }
    ],
    "sg:phone":"+1 603 887 8058",
    "sg:postcode":"03873",
    "sg:province":"NH",
    "sg:tags":[
        "hardware",
        "integrated",
        "software"
    ],
    "wof:name":"Peach Computer Systems",
    "wof:placetype":"venue"
},
  "geometry": {"coordinates":[-71.21884799999999,42.953699],"type":"Point"}
}