{
  "type": "Feature",
  "properties": {
    "addr:full":"6 Patten Rd Merrimack NH 03054",
    "addr:housenumber":"6",
    "addr:postcode":"03054",
    "addr:street":"Patten Rd",
    "iso:country":"US",
    "sg:address":"6 Patten Rd",
    "sg:city":"Merrimack",
    "sg:classifiers":[
        {
            "category":"Manufacturing",
            "subcategory":"Metals",
            "type":"Manufacturing & Wholesale Goods"
        }
    ],
    "sg:phone":"+1 603 424 0923",
    "sg:postcode":"03054",
    "sg:province":"NH",
    "sg:tags":[
        "fire",
        "arms"
    ],
    "wof:name":"Triple Break Prodcuts",
    "wof:placetype":"venue"
},
  "geometry": {"coordinates":[-71.526072,42.873306],"type":"Point"}
}