{
  "type": "Feature",
  "properties": {
    "addr:full":"222 Daniel Webster Hwy Nashua NH 03060",
    "addr:housenumber":"222",
    "addr:postcode":"03060",
    "addr:street":"Daniel Webster Hwy",
    "iso:country":"US",
    "sg:address":"222 Daniel Webster Hwy",
    "sg:city":"Nashua",
    "sg:classifiers":[
        {
            "category":"Shopping",
            "subcategory":"Computers & Home Electronics",
            "type":"Retail Goods"
        }
    ],
    "sg:phone":"+1 603 888 3660",
    "sg:postcode":"03060",
    "sg:province":"NH",
    "sg:tags":[
        "equipment",
        "electronic",
        "supply"
    ],
    "wof:name":"Circuit City",
    "wof:placetype":"venue"
},
  "geometry": {"coordinates":[-71.442082,42.711638],"type":"Point"}
}