{
  "type": "Feature",
  "properties": {
    "iso:country":"US",
    "sg:address":"172 Main St",
    "sg:city":"Lancaster",
    "sg:classifiers":[
        {
            "category":"Building & Trades",
            "subcategory":"Construction",
            "type":"Services"
        }
    ],
    "sg:phone":"+1 603 788 2157",
    "sg:postcode":"03584",
    "sg:province":"NH",
    "sg:tags":[
        "contractor"
    ],
    "wof:name":"P & R Excavating Service Inc",
    "wof:placetype":"venue"
},
  "geometry": {"coordinates":[-71.57048399999999,44.491855],"type":"Point"}
}