{
  "type": "Feature",
  "properties": {
    "iso:country":"US",
    "sg:address":"66 N Main St",
    "sg:city":"Wolfeboro",
    "sg:classifiers":[
        {
            "category":"Real Estate",
            "subcategory":"Real Estate Agent",
            "type":"Services"
        }
    ],
    "sg:phone":"+1 603 569 2324",
    "sg:postcode":"03894",
    "sg:province":"NH",
    "wof:name":"Your Neighborhood Realty",
    "wof:placetype":"venue"
},
  "geometry": {"coordinates":[-71.216712,43.585271],"type":"Point"}
}