{
  "type": "Feature",
  "properties": {
    "addr:full":"318 South St Milford NH 03055",
    "addr:housenumber":"318",
    "addr:postcode":"03055",
    "addr:street":"South St",
    "iso:country":"US",
    "sg:address":"318 South St",
    "sg:city":"Milford",
    "sg:classifiers":[
        {
            "category":"Wholesale",
            "subcategory":"Electrical",
            "type":"Manufacturing & Wholesale Goods"
        }
    ],
    "sg:phone":"+1 603 672 1200",
    "sg:postcode":"03055",
    "sg:province":"NH",
    "sg:tags":[
        "equipment",
        "material"
    ],
    "wof:name":"Electrical Supply Of Milford",
    "wof:placetype":"venue"
},
  "geometry": {"coordinates":[-71.64712299999999,42.824862],"type":"Point"}
}