{
  "type": "Feature",
  "properties": {
    "iso:country":"US",
    "sg:address":"360 State Rte 101",
    "sg:city":"Bedford",
    "sg:classifiers":[
        {
            "category":"Professional",
            "subcategory":"Business Services",
            "type":"Services"
        }
    ],
    "sg:phone":"+1 603 471 9950",
    "sg:postcode":"03110",
    "sg:province":"NH",
    "wof:name":"Tattile USA",
    "wof:placetype":"venue"
},
  "geometry": {"coordinates":[-71.53888600000001,42.920907],"type":"Point"}
}