{
  "type": "Feature",
  "properties": {
    "addr:full":"98 Amherst St Amherst NH 03031",
    "addr:housenumber":"98",
    "addr:postcode":"03031",
    "addr:street":"Amherst St",
    "iso:country":"US",
    "sg:address":"98 Amherst St",
    "sg:city":"Amherst",
    "sg:classifiers":[
        {
            "category":"Retail",
            "subcategory":"Laundry & Dry Cleaning",
            "type":"Services"
        }
    ],
    "sg:phone":"+1 603 424 0316",
    "sg:postcode":"03031",
    "sg:province":"NH",
    "sg:tags":[
        "cleaners",
        "rug",
        "carpet"
    ],
    "wof:name":"Servicexperts",
    "wof:placetype":"venue"
},
  "geometry": {"coordinates":[-71.63526899999999,42.855154],"type":"Point"}
}