{
  "type": "Feature",
  "properties": {
    "iso:country":"US",
    "sg:address":"1602 Elm St",
    "sg:city":"Manchester",
    "sg:classifiers":[
        {
            "category":"Bakery",
            "type":"Food & Drink"
        },
        {
            "category":"Coffee & Tea",
            "type":"Food & Drink"
        },
        {
            "category":"Bagels",
            "type":"Food & Drink"
        },
        {
            "category":"Donuts",
            "type":"Food & Drink"
        }
    ],
    "sg:menulink":"http://www.allmenus.com/nh/manchester/149199-dunkin-donuts/menu/",
    "sg:phone":"+1 603 628 3681",
    "sg:postcode":"03101",
    "sg:province":"NH",
    "sg:tags":[
        "wrap",
        "american",
        "sandwich",
        "pastry"
    ],
    "wof:name":"Dunkin' Donuts",
    "wof:placetype":"venue"
},
  "geometry": {"coordinates":[-71.464482,43.001271],"type":"Point"}
}