{
  "type": "Feature",
  "properties": {
    "addr:full":"335 Washington St Dover NH 03820",
    "addr:housenumber":"335",
    "addr:postcode":"03820",
    "addr:street":"Washington St",
    "iso:country":"US",
    "sg:address":"335 Washington St",
    "sg:city":"Dover",
    "sg:classifiers":[
        {
            "category":"Real Estate",
            "subcategory":"Real Estate Agent",
            "type":"Services"
        }
    ],
    "sg:phone":"+1 603 749 2191",
    "sg:postcode":"03820",
    "sg:province":"NH",
    "wof:name":"Michael Ham Real Estate",
    "wof:placetype":"venue"
},
  "geometry": {"coordinates":[-70.890609,43.197637],"type":"Point"}
}