{
  "type": "Feature",
  "properties": {
    "iso:country":"US",
    "sg:address":"1 Wood St",
    "sg:city":"Nashua",
    "sg:classifiers":[
        {
            "category":"Professional",
            "subcategory":"Management & Consulting",
            "type":"Services"
        }
    ],
    "sg:phone":"+1 603 880 5436",
    "sg:postcode":"03064",
    "sg:province":"NH",
    "sg:tags":[
        "promotion",
        "sales"
    ],
    "wof:name":"Thomas Lizotte",
    "wof:placetype":"venue"
},
  "geometry": {"coordinates":[-71.460891,42.770803],"type":"Point"}
}