{
  "type": "Feature",
  "properties": {
    "iso:country":"US",
    "sg:address":"7 Perimeter Rd E",
    "sg:city":"Manchester",
    "sg:classifiers":[
        {
            "category":"Professional",
            "subcategory":"Computer Services",
            "type":"Services"
        }
    ],
    "sg:phone":"+1 603 668 1776",
    "sg:postcode":"03053",
    "sg:province":"NH",
    "sg:tags":[
        "consulting",
        "design",
        "network"
    ],
    "wof:name":"Ikon Office Solutions",
    "wof:placetype":"venue"
},
  "geometry": {"coordinates":[-71.431584,42.923066],"type":"Point"}
}