{
  "type": "Feature",
  "properties": {
    "iso:country":"US",
    "sg:address":"426 State St",
    "sg:city":"Portsmouth",
    "sg:classifiers":[
        {
            "category":"Social Services",
            "type":"Services"
        }
    ],
    "sg:phone":"+1 603 431 1191",
    "sg:postcode":"03801",
    "sg:province":"NH",
    "sg:tags":[
        "counselor",
        "marriage",
        "family"
    ],
    "wof:name":"Harbor Newmarket Cnslng Assoc",
    "wof:placetype":"venue"
},
  "geometry": {"coordinates":[-70.75964500000001,43.075049],"type":"Point"}
}