{
  "type": "Feature",
  "properties": {
    "iso:country":"US",
    "sg:address":"19 Northwood Dr",
    "sg:city":"Merrimack",
    "sg:classifiers":[
        {
            "category":"Professional",
            "type":"Services"
        }
    ],
    "sg:phone":"+1 603 234 5103",
    "sg:postcode":"03054",
    "sg:province":"NH",
    "sg:tags":[
        "establishment"
    ],
    "wof:name":"Inovoptics",
    "wof:placetype":"venue"
},
  "geometry": {"coordinates":[-71.51513,42.847933],"type":"Point"}
}