{
  "type": "Feature",
  "properties": {
    "iso:country":"US",
    "sg:address":"137 Mountain Base Rd",
    "sg:city":"Goffstown",
    "sg:classifiers":[
        {
            "category":"Manufacturing",
            "subcategory":"Food",
            "type":"Manufacturing & Wholesale Goods"
        }
    ],
    "sg:phone":"+1 603 497 4490",
    "sg:postcode":"03045",
    "sg:province":"NH",
    "sg:tags":[
        "corn",
        "chips",
        "potato"
    ],
    "wof:name":"Snack Aisle",
    "wof:placetype":"venue"
},
  "geometry": {"coordinates":[-71.5776,42.988217],"type":"Point"}
}