{
  "type": "Feature",
  "properties": {
    "iso:country":"US",
    "sg:address":"5 Depot St",
    "sg:city":"Hillsboro",
    "sg:classifiers":[
        {
            "category":"Real Estate",
            "subcategory":"Real Estate Agent",
            "type":"Services"
        }
    ],
    "sg:phone":"+1 603 464 4923",
    "sg:postcode":"03244",
    "sg:province":"NH",
    "wof:name":"R E Max Spirit Real Estate",
    "wof:placetype":"venue"
},
  "geometry": {"coordinates":[-71.891937,43.115213],"type":"Point"}
}