{
  "type": "Feature",
  "properties": {
    "iso:country":"US",
    "sg:address":"33 River Rd",
    "sg:city":"Sunapee",
    "sg:classifiers":[
        {
            "category":"Real Estate",
            "subcategory":"Real Estate Agent",
            "type":"Services"
        }
    ],
    "sg:phone":"+1 603 763 4433",
    "sg:postcode":"03782",
    "sg:province":"NH",
    "wof:name":"Colby Linehan Real Est",
    "wof:placetype":"venue"
},
  "geometry": {"coordinates":[-72.08121800000001,43.385161],"type":"Point"}
}