{
  "type": "Feature",
  "properties": {
    "iso:country":"US",
    "sg:address":"22 Leslie Ln",
    "sg:city":"Nashua",
    "sg:classifiers":[
        {
            "category":"Wholesale",
            "subcategory":"Jewelry",
            "type":"Manufacturing & Wholesale Goods"
        }
    ],
    "sg:phone":"+1 603 889 6800",
    "sg:postcode":"03062",
    "sg:province":"NH",
    "sg:tags":[
        "casting"
    ],
    "wof:name":"Replaform Corp",
    "wof:placetype":"venue"
},
  "geometry": {"coordinates":[-71.504521,42.738613],"type":"Point"}
}