{
  "type": "Feature",
  "properties": {
    "addr:full":"11 Johnson Dr Woodstock NH 03262",
    "addr:housenumber":"11",
    "addr:postcode":"03262",
    "addr:street":"Johnson Dr",
    "iso:country":"US",
    "sg:address":"11 Johnson Dr",
    "sg:city":"Woodstock",
    "sg:classifiers":[
        {
            "category":"Building & Trades",
            "subcategory":"Cleaning & Sanitation",
            "type":"Services"
        }
    ],
    "sg:phone":"+1 603 745 2701",
    "sg:postcode":"03262",
    "sg:province":"NH",
    "sg:tags":[
        "house"
    ],
    "wof:name":"J C Cleaning",
    "wof:placetype":"venue"
},
  "geometry": {"coordinates":[-71.68812200000001,44.036695],"type":"Point"}
}