{
  "type": "Feature",
  "properties": {
    "iso:country":"US",
    "sg:address":"24 Elm St",
    "sg:city":"Plaistow",
    "sg:classifiers":[
        {
            "category":"Autos & Motor Vehicles",
            "subcategory":"Auto Supplies",
            "type":"Retail Goods"
        }
    ],
    "sg:phone":"+1 603 378 0090",
    "sg:postcode":"03865",
    "sg:province":"NH",
    "sg:tags":[
        "automobile",
        "parts",
        "accessory",
        "part",
        "supplies-used",
        "accessories-wholesale",
        "rebuilt",
        "manufacturer"
    ],
    "sg:website":"http://www.flatlanderracing.com",
    "wof:name":"Flatlander Racing",
    "wof:placetype":"venue"
},
  "geometry": {"coordinates":[-71.09124799999999,42.839439],"type":"Point"}
}