{
  "type": "Feature",
  "properties": {
    "addr:full":"31 Garden Ln Durham NH 03824",
    "addr:housenumber":"31",
    "addr:postcode":"03824",
    "addr:street":"Garden Ln",
    "iso:country":"US",
    "sg:address":"31 Garden Ln",
    "sg:city":"Durham",
    "sg:classifiers":[
        {
            "category":"Arts & Performance",
            "subcategory":"Theater",
            "type":"Entertainment"
        }
    ],
    "sg:phone":"+1 603 868 1622",
    "sg:postcode":"03824",
    "sg:province":"NH",
    "sg:tags":[
        "educational"
    ],
    "wof:name":"Children and The Living Earth",
    "wof:placetype":"venue"
},
  "geometry": {"coordinates":[-70.93028200000001,43.128935],"type":"Point"}
}