{
  "type": "Feature",
  "properties": {
    "iso:country":"US",
    "sg:address":"152 N Main St",
    "sg:city":"Boscawen",
    "sg:classifiers":[
        {
            "category":"Shopping",
            "subcategory":"Gifts & Souvenirs",
            "type":"Retail Goods"
        }
    ],
    "sg:phone":"+1 603 753 4445",
    "sg:postcode":"03303",
    "sg:province":"NH",
    "sg:tags":[
        "shop"
    ],
    "wof:name":"Marshall's Flowers & Gifts",
    "wof:placetype":"venue"
},
  "geometry": {"coordinates":[-71.606286,43.297439],"type":"Point"}
}