{
  "type": "Feature",
  "properties": {
    "addr:full":"272 Hanover St Lebanon NH 03766",
    "addr:housenumber":"272",
    "addr:postcode":"03766",
    "addr:street":"Hanover St",
    "iso:country":"US",
    "sg:address":"272 Hanover St",
    "sg:city":"Lebanon",
    "sg:classifiers":[
        {
            "category":"Personal",
            "subcategory":"Beauty Salon",
            "type":"Services"
        }
    ],
    "sg:phone":"+1 603 448 2226",
    "sg:postcode":"03766",
    "sg:province":"NH",
    "wof:name":"Janz",
    "wof:placetype":"venue"
},
  "geometry": {"coordinates":[-72.251222,43.656775],"type":"Point"}
}