{
  "type": "Feature",
  "properties": {
    "addr:full":"93 Howard Rd Bristol NH 03222",
    "addr:housenumber":"93",
    "addr:postcode":"03222",
    "addr:street":"Howard Rd",
    "iso:country":"US",
    "sg:address":"93 Howard Rd",
    "sg:city":"Bristol",
    "sg:classifiers":[
        {
            "category":"Building & Trades",
            "subcategory":"Construction",
            "type":"Services"
        }
    ],
    "sg:phone":"+1 603 744 9334",
    "sg:postcode":"03222",
    "sg:province":"NH",
    "sg:tags":[
        "house"
    ],
    "wof:name":"Doucette Const Svc C",
    "wof:placetype":"venue"
},
  "geometry": {"coordinates":[-71.72765200000001,43.656301],"type":"Point"}
}