{
  "type": "Feature",
  "properties": {
    "iso:country":"US",
    "sg:address":"34 Tyler Hill Rd",
    "sg:city":"Jaffrey",
    "sg:classifiers":[
        {
            "category":"Building & Trades",
            "subcategory":"Landscaping Services",
            "type":"Services"
        },
        {
            "category":"Building & Trades",
            "subcategory":"Construction",
            "type":"Services"
        },
        {
            "category":"Manufacturing",
            "subcategory":"Paper Products",
            "type":"Manufacturing & Wholesale Goods"
        }
    ],
    "sg:phone":"+1 603 532 8886",
    "sg:postcode":"03452",
    "sg:province":"NH",
    "sg:tags":[
        "excavation",
        "arborist",
        "tree",
        "bamboo",
        "contractor"
    ],
    "wof:name":"Wright Tree Service",
    "wof:placetype":"venue"
},
  "geometry": {"coordinates":[-72.02705,42.812148],"type":"Point"}
}