{
  "type": "Feature",
  "properties": {
    "iso:country":"US",
    "sg:address":"11 Fitzgerald Dr",
    "sg:city":"Jaffrey",
    "sg:classifiers":[
        {
            "category":"Retail",
            "subcategory":"Auto Repair",
            "type":"Services"
        }
    ],
    "sg:phone":"+1 603 532 7215",
    "sg:postcode":"03451",
    "sg:province":"NH",
    "sg:tags":[
        "repairing",
        "automobile",
        "radiator"
    ],
    "wof:name":"Jaffrey Auto Svc",
    "wof:placetype":"venue"
},
  "geometry": {"coordinates":[-72.48396200000001,42.786944],"type":"Point"}
}