{
  "type": "Feature",
  "properties": {
    "addr:full":"97 Main St Colebrook NH 03576",
    "addr:housenumber":"97",
    "addr:postcode":"03576",
    "addr:street":"Main St",
    "iso:country":"US",
    "sg:address":"97 Main St",
    "sg:city":"Colebrook",
    "sg:classifiers":[
        {
            "category":"Restaurant",
            "type":"Food & Drink"
        }
    ],
    "sg:phone":"+1 603 237 4537",
    "sg:postcode":"03576",
    "sg:province":"NH",
    "sg:tags":[
        "sandwich"
    ],
    "wof:name":"Sub-Way",
    "wof:placetype":"venue"
},
  "geometry": {"coordinates":[-71.491606,44.911693],"type":"Point"}
}