{
  "type": "Feature",
  "properties": {
    "iso:country":"US",
    "sg:address":"20 Pear St",
    "sg:city":"Laconia",
    "sg:classifiers":[
        {
            "category":"Professional",
            "subcategory":"Business Services",
            "type":"Services"
        }
    ],
    "sg:phone":"+1 603 528 0597",
    "sg:postcode":"03246",
    "sg:province":"NH",
    "wof:name":"Wayne's Four Seasons Svc",
    "wof:placetype":"venue"
},
  "geometry": {"coordinates":[-71.46152600000001,43.545912],"type":"Point"}
}