{
  "type": "Feature",
  "properties": {
    "iso:country":"US",
    "sg:address":"202 W Main St",
    "sg:city":"Hillsboro",
    "sg:phone":"+1 603 464 2600",
    "sg:postcode":"03244",
    "sg:province":"NH",
    "sg:tags":[
        "gas"
    ],
    "wof:name":"Ameri Gas Inc",
    "wof:placetype":"venue"
},
  "geometry": {"coordinates":[-71.911361,43.111229],"type":"Point"}
}