{
  "type": "Feature",
  "properties": {
    "addr:full":"27 W Hill Rd Brookline NH 03033",
    "addr:housenumber":"27",
    "addr:postcode":"03033",
    "addr:street":"W Hill Rd",
    "iso:country":"US",
    "sg:address":"27 W Hill Rd",
    "sg:city":"Brookline",
    "sg:classifiers":[
        {
            "category":"Retail",
            "subcategory":"Repair Shop",
            "type":"Services"
        }
    ],
    "sg:phone":"+1 603 672 7174",
    "sg:postcode":"03033",
    "sg:province":"NH",
    "wof:name":"Harley Art Framing",
    "wof:placetype":"venue"
},
  "geometry": {"coordinates":[-71.699335,42.711657],"type":"Point"}
}