{
  "type": "Feature",
  "properties": {
    "addr:full":"178 State Rte 101 Bedford NH 03110",
    "addr:housenumber":"178",
    "addr:postcode":"03110",
    "addr:street":"State Rte 101",
    "iso:country":"US",
    "sg:address":"178 State Rte 101",
    "sg:city":"Bedford",
    "sg:classifiers":[
        {
            "category":"Insurance",
            "subcategory":"Insurance Agent",
            "type":"Services"
        }
    ],
    "sg:phone":"+1 603 471 9222",
    "sg:postcode":"03110",
    "sg:province":"NH",
    "wof:name":"Beals Insurance Agency",
    "wof:placetype":"venue"
},
  "geometry": {"coordinates":[-71.51899899999999,42.942003],"type":"Point"}
}