{
  "type": "Feature",
  "properties": {
    "addr:full":"2200 Front St Manchester NH 03102",
    "addr:housenumber":"2200",
    "addr:postcode":"03102",
    "addr:street":"Front St",
    "iso:country":"US",
    "sg:address":"2200 Front St",
    "sg:city":"Manchester",
    "sg:classifiers":[
        {
            "category":"Professional",
            "type":"Services"
        }
    ],
    "sg:phone":"+1 603 669 5131",
    "sg:postcode":"03102",
    "sg:province":"NH",
    "sg:tags":[
        "establishment"
    ],
    "wof:name":"Tracer Technologies",
    "wof:placetype":"venue"
},
  "geometry": {"coordinates":[-71.47793799999999,43.037546],"type":"Point"}
}