{
  "type": "Feature",
  "properties": {
    "iso:country":"US",
    "sg:address":"45 Meadow Rd",
    "sg:city":"Peterborough",
    "sg:classifiers":[
        {
            "category":"Retail",
            "subcategory":"Repair Shop",
            "type":"Services"
        }
    ],
    "sg:phone":"+1 603 563 8359",
    "sg:postcode":"03431",
    "sg:province":"NH",
    "sg:tags":[
        "industrial",
        "machinery",
        "mfg"
    ],
    "wof:name":"Monadnock Machine",
    "wof:placetype":"venue"
},
  "geometry": {"coordinates":[-72.29517199999999,42.92743],"type":"Point"}
}