{
  "type": "Feature",
  "properties": {
    "iso:country":"US",
    "sg:address":"47 Joanne Dr",
    "sg:city":"Hooksett",
    "sg:classifiers":[
        {
            "category":"Organizations",
            "subcategory":"Religious Organization",
            "type":"Services"
        }
    ],
    "sg:phone":"+1 603 644 8704",
    "sg:postcode":"03106",
    "sg:province":"NH",
    "wof:name":"NH Catholic Engaged Encou",
    "wof:placetype":"venue"
},
  "geometry": {"coordinates":[-71.410274,43.035524],"type":"Point"}
}