{
  "type": "Feature",
  "properties": {
    "addr:full":"10 Woodbury St Salem NH 03079",
    "addr:housenumber":"10",
    "addr:postcode":"03079",
    "addr:street":"Woodbury St",
    "iso:country":"US",
    "sg:address":"10 Woodbury St",
    "sg:city":"Salem",
    "sg:classifiers":[
        {
            "category":"Wholesale",
            "subcategory":"Office Equipment",
            "type":"Manufacturing & Wholesale Goods"
        }
    ],
    "sg:phone":"+1 603 898 4130",
    "sg:postcode":"03079",
    "sg:province":"NH",
    "sg:tags":[
        "furniture"
    ],
    "sg:website":"http://www.ctsnorth.com",
    "wof:name":"C T S North",
    "wof:placetype":"venue"
},
  "geometry": {"coordinates":[-71.189097,42.779484],"type":"Point"}
}