{
  "type": "Feature",
  "properties": {
    "iso:country":"US",
    "sg:address":"99 Old Dover Rd",
    "sg:city":"Portsmouth",
    "sg:classifiers":[
        {
            "category":"Communications",
            "subcategory":"News Services",
            "type":"Services"
        }
    ],
    "sg:phone":"+1 603 767 9679",
    "sg:postcode":"03801",
    "sg:province":"NH",
    "sg:tags":[
        "syndicate"
    ],
    "wof:name":"GE",
    "wof:placetype":"venue"
},
  "geometry": {"coordinates":[-70.805357,43.101169],"type":"Point"}
}