{
  "type": "Feature",
  "properties": {
    "addr:full":"77 Main St Keene NH 03431",
    "addr:housenumber":"77",
    "addr:postcode":"03431",
    "addr:street":"Main St",
    "iso:country":"US",
    "sg:address":"77 Main St",
    "sg:city":"Keene",
    "sg:classifiers":[
        {
            "category":"Restaurant",
            "type":"Food & Drink"
        }
    ],
    "sg:menulink":"http://www.allmenus.com/nh/keene/232154-margaritas/menu/",
    "sg:phone":"+1 603 357 4492",
    "sg:postcode":"03431",
    "sg:province":"NH",
    "sg:tags":[
        "mexican"
    ],
    "wof:name":"Margaritas",
    "wof:placetype":"venue"
},
  "geometry": {"coordinates":[-72.278369,42.932097],"type":"Point"}
}