{
  "type": "Feature",
  "properties": {
    "iso:country":"US",
    "sg:address":"35 Glen Rd",
    "sg:city":"West Lebanon",
    "sg:classifiers":[
        {
            "category":"Wholesale",
            "subcategory":"Construction Materials",
            "type":"Manufacturing & Wholesale Goods"
        }
    ],
    "sg:phone":"+1 603 298 5959",
    "sg:postcode":"03784",
    "sg:province":"NH",
    "sg:tags":[
        "brick",
        "common",
        "face"
    ],
    "sg:website":"www.arthurwhitcomb.com",
    "wof:name":"Arthur Whitcomb",
    "wof:placetype":"venue"
},
  "geometry": {"coordinates":[-72.31278399999999,43.633748],"type":"Point"}
}