{
  "type": "Feature",
  "properties": {
    "iso:country":"US",
    "sg:address":"54 Damren Rd",
    "sg:city":"Derry",
    "sg:classifiers":[
        {
            "category":"Shopping",
            "subcategory":"Hobbies, Toys, & Games",
            "type":"Retail Goods"
        }
    ],
    "sg:phone":"+1 603 425 1170",
    "sg:postcode":"03038",
    "sg:province":"NH",
    "wof:name":"Lsr Designs",
    "wof:placetype":"venue"
},
  "geometry": {"coordinates":[-71.239507,42.916189],"type":"Point"}
}