{
  "type": "Feature",
  "properties": {
    "iso:country":"US",
    "sg:address":"34 Grandview Dr",
    "sg:city":"Gilford",
    "sg:classifiers":[
        {
            "category":"Professional",
            "subcategory":"Management & Consulting",
            "type":"Services"
        }
    ],
    "sg:phone":"+1 603 293 8315",
    "sg:postcode":"03281",
    "sg:province":"NH",
    "sg:tags":[
        "training",
        "sales"
    ],
    "wof:name":"Sales & Telemarketing Resource",
    "wof:placetype":"venue"
},
  "geometry": {"coordinates":[-71.756315,43.103826],"type":"Point"}
}