{
  "type": "Feature",
  "properties": {
    "iso:country":"US",
    "sg:address":"232 E Main St",
    "sg:city":"East Hampstead",
    "sg:classifiers":[
        {
            "category":"Building & Trades",
            "subcategory":"Construction",
            "type":"Services"
        }
    ],
    "sg:phone":"+1 603 382 6829",
    "sg:postcode":"03826",
    "sg:province":"NH",
    "sg:tags":[
        "contractor"
    ],
    "wof:name":"C & G Construction",
    "wof:placetype":"venue"
},
  "geometry": {"coordinates":[-71.13852900000001,42.890534],"type":"Point"}
}