{
  "type": "Feature",
  "properties": {
    "iso:country":"US",
    "sg:address":"17 S Mast Rd",
    "sg:city":"Goffstown",
    "sg:classifiers":[
        {
            "category":"Retail",
            "subcategory":"Funeral Services",
            "type":"Services"
        }
    ],
    "sg:phone":"+1 603 497 4711",
    "sg:postcode":"03045",
    "sg:province":"NH",
    "sg:tags":[
        "home"
    ],
    "wof:name":"French & Rising Funeral Home",
    "wof:placetype":"venue"
},
  "geometry": {"coordinates":[-71.59773300000001,43.015972],"type":"Point"}
}