{
  "type": "Feature",
  "properties": {
    "iso:country":"US",
    "sg:address":"11 Willis Pl",
    "sg:city":"Gorham",
    "sg:classifiers":[
        {
            "category":"Building & Trades",
            "subcategory":"Construction",
            "type":"Services"
        }
    ],
    "sg:phone":"+1 603 466 2192",
    "sg:postcode":"03581",
    "sg:province":"NH",
    "sg:tags":[
        "house"
    ],
    "wof:name":"Lavigne Gen Contr Roland",
    "wof:placetype":"venue"
},
  "geometry": {"coordinates":[-71.175798,44.39158],"type":"Point"}
}