{
  "type": "Feature",
  "properties": {
    "addr:full":"1 Ledge Hill Rd Center Tuftonboro NH 03816",
    "addr:housenumber":"1",
    "addr:postcode":"03816",
    "addr:street":"Ledge Hill Rd",
    "iso:country":"US",
    "sg:address":"1 Ledge Hill Rd",
    "sg:city":"Center Tuftonboro",
    "sg:classifiers":[
        {
            "category":"Shopping",
            "subcategory":"Used Merchandise",
            "type":"Retail Goods"
        }
    ],
    "sg:phone":"+1 603 569 4048",
    "sg:postcode":"03816",
    "sg:province":"NH",
    "wof:name":"Log Cabin Antique Shop",
    "wof:placetype":"venue"
},
  "geometry": {"coordinates":[-71.253692,43.663528],"type":"Point"}
}