{
  "type": "Feature",
  "properties": {
    "iso:country":"US",
    "sg:address":"151 Wild Acres Rd",
    "sg:city":"Laconia",
    "sg:classifiers":[
        {
            "category":"Social Services",
            "subcategory":"Child Care",
            "type":"Services"
        }
    ],
    "sg:phone":"+1 603 524 0703",
    "sg:postcode":"03249",
    "sg:province":"NH",
    "sg:tags":[
        "day"
    ],
    "wof:name":"Animal Frm Day Care",
    "wof:placetype":"venue"
},
  "geometry": {"coordinates":[-71.407793,43.524954],"type":"Point"}
}