{
  "type": "Feature",
  "properties": {
    "iso:country":"US",
    "sg:address":"34 Putney Rd",
    "sg:city":"Andover",
    "sg:classifiers":[
        {
            "category":"Autos & Motor Vehicles",
            "subcategory":"Automobile Sales",
            "type":"Retail Goods"
        },
        {
            "category":"Retail",
            "subcategory":"Auto Repair",
            "type":"Services"
        }
    ],
    "sg:phone":"+1 603 735 5895",
    "sg:postcode":"03216",
    "sg:province":"NH",
    "sg:tags":[
        "body",
        "car",
        "dealer"
    ],
    "wof:name":"Haley's Auto",
    "wof:placetype":"venue"
},
  "geometry": {"coordinates":[-71.74101899999999,43.43611],"type":"Point"}
}