{
  "type": "Feature",
  "properties": {
    "iso:country":"US",
    "sg:address":"66 Ridgewood Cir",
    "sg:city":"Epsom",
    "sg:classifiers":[
        {
            "category":"Professional",
            "subcategory":"Detective & Security Services",
            "type":"Services"
        }
    ],
    "sg:phone":"+1 603 736 9689",
    "sg:postcode":"03234",
    "sg:province":"NH",
    "sg:tags":[
        "guard"
    ],
    "wof:name":"Richard Laframboise",
    "wof:placetype":"venue"
},
  "geometry": {"coordinates":[-71.341318,43.226063],"type":"Point"}
}