{
  "type": "Feature",
  "properties": {
    "addr:full":"9 Quinton Dr Nashua NH 03062",
    "addr:housenumber":"9",
    "addr:postcode":"03062",
    "addr:street":"Quinton Dr",
    "iso:country":"US",
    "sg:address":"9 Quinton Dr",
    "sg:city":"Nashua",
    "sg:classifiers":[
        {
            "category":"Banks & Credit Unions",
            "subcategory":"Investment Brokerage",
            "type":"Services"
        },
        {
            "category":"Banks & Credit Unions",
            "subcategory":"Financial Services",
            "type":"Services"
        }
    ],
    "sg:phone":"+1 603 881 8811",
    "sg:postcode":"03062",
    "sg:province":"NH",
    "sg:tags":[
        "advisory",
        "planner"
    ],
    "wof:name":"Kelley Safety First Financial Planners",
    "wof:placetype":"venue"
},
  "geometry": {"coordinates":[-71.49101,42.706882],"type":"Point"}
}