{
  "type": "Feature",
  "properties": {
    "iso:country":"US",
    "sg:address":"17 Aladdin Rd",
    "sg:city":"Windham",
    "sg:classifiers":[
        {
            "category":"Building & Trades",
            "subcategory":"Construction",
            "type":"Services"
        }
    ],
    "sg:phone":"+1 603 898 8045",
    "sg:postcode":"03087",
    "sg:province":"NH",
    "sg:tags":[
        "house"
    ],
    "wof:name":"Martin Gerald Construction",
    "wof:placetype":"venue"
},
  "geometry": {"coordinates":[-71.249019,42.82303],"type":"Point"}
}