{
  "type": "Feature",
  "properties": {
    "iso:country":"US",
    "sg:address":"28 Green St",
    "sg:city":"Somersworth",
    "sg:classifiers":[
        {
            "category":"Home & Garden",
            "subcategory":"Building Materials",
            "type":"Retail Goods"
        }
    ],
    "sg:phone":"+1 603 692 0163",
    "sg:postcode":"03878",
    "sg:province":"ME",
    "wof:name":"Antique Fence Co",
    "wof:placetype":"venue"
},
  "geometry": {"coordinates":[-70.863953,43.258376],"type":"Point"}
}