{
  "type": "Feature",
  "properties": {
    "addr:full":"10 Fieldstone Dr Hollis NH 03049",
    "addr:housenumber":"10",
    "addr:postcode":"03049",
    "addr:street":"Fieldstone Dr",
    "iso:country":"US",
    "sg:address":"10 Fieldstone Dr",
    "sg:city":"Hollis",
    "sg:classifiers":[
        {
            "category":"Education",
            "subcategory":"Special Training",
            "type":"Public Place"
        }
    ],
    "sg:phone":"+1 603 465 9514",
    "sg:postcode":"03049",
    "sg:province":"NH",
    "wof:name":"River Quest Kayak Instruction",
    "wof:placetype":"venue"
},
  "geometry": {"coordinates":[-71.57232399999999,42.724673],"type":"Point"}
}