{
  "type": "Feature",
  "properties": {
    "addr:full":"271 Mast Rd Durham NH 03824",
    "addr:housenumber":"271",
    "addr:postcode":"03824",
    "addr:street":"Mast Rd",
    "iso:country":"US",
    "sg:address":"271 Mast Rd",
    "sg:city":"Durham",
    "sg:classifiers":[
        {
            "category":"Manufacturing",
            "subcategory":"Lumber",
            "type":"Manufacturing & Wholesale Goods"
        }
    ],
    "sg:phone":"+1 603 868 7709",
    "sg:postcode":"03824",
    "sg:province":"NH",
    "sg:tags":[
        "government"
    ],
    "wof:name":"US Forestry Dept",
    "wof:placetype":"venue"
},
  "geometry": {"coordinates":[-70.957348,43.137293],"type":"Point"}
}