{
  "type": "Feature",
  "properties": {
    "iso:country":"US",
    "sg:address":"454 Old Street Rd",
    "sg:city":"Peterborough",
    "sg:classifiers":[
        {
            "category":"Health Services",
            "subcategory":"Doctor",
            "type":"Services"
        }
    ],
    "sg:phone":"+1 603 924 4680",
    "sg:postcode":"03458",
    "sg:province":"NH",
    "sg:tags":[
        "physician",
        "surgeon"
    ],
    "wof:name":"Peterborough Internal Medicine",
    "wof:placetype":"venue"
},
  "geometry": {"coordinates":[-71.936384,42.887555],"type":"Point"}
}