{
  "type": "Feature",
  "properties": {
    "iso:country":"US",
    "sg:address":"180 Main St",
    "sg:city":"Berlin",
    "sg:classifiers":[
        {
            "category":"Real Estate",
            "subcategory":"Real Estate Agent",
            "type":"Services"
        }
    ],
    "sg:phone":"+1 603 752 6003",
    "sg:postcode":"03570",
    "sg:province":"NH",
    "wof:name":"Androscoggin Appraisal Assoc",
    "wof:placetype":"venue"
},
  "geometry": {"coordinates":[-71.177888,44.471863],"type":"Point"}
}