{
  "type": "Feature",
  "properties": {
    "iso:country":"US",
    "sg:address":"1037 Elm St",
    "sg:city":"Manchester",
    "sg:classifiers":[
        {
            "category":"Professional",
            "type":"Services"
        }
    ],
    "sg:phone":"+1 603 647 2326",
    "sg:postcode":"03101",
    "sg:province":"NH",
    "sg:tags":[
        "establishment"
    ],
    "wof:name":"1037 Elm St",
    "wof:placetype":"venue"
},
  "geometry": {"coordinates":[-71.463016,42.993031],"type":"Point"}
}