{
  "type": "Feature",
  "properties": {
    "iso:country":"US",
    "sg:address":"584 W Main St",
    "sg:city":"Tilton",
    "sg:classifiers":[
        {
            "category":"Retail",
            "subcategory":"Funeral Services",
            "type":"Services"
        }
    ],
    "sg:phone":"+1 603 286 3132",
    "sg:postcode":"03276",
    "sg:province":"NH",
    "wof:name":"Smart Memorial Home",
    "wof:placetype":"venue"
},
  "geometry": {"coordinates":[-71.616259,43.44622],"type":"Point"}
}