{
  "type": "Feature",
  "properties": {
    "iso:country":"US",
    "sg:address":"22 Glasgow Cir",
    "sg:city":"Hudson",
    "sg:classifiers":[
        {
            "category":"Manufacturing",
            "subcategory":"Signs",
            "type":"Manufacturing & Wholesale Goods"
        }
    ],
    "sg:phone":"+1 603 882 2085",
    "sg:postcode":"03051",
    "sg:province":"NH",
    "sg:tags":[
        "specialty",
        "mfg"
    ],
    "wof:name":"A 1 Sign Design LLC",
    "wof:placetype":"venue"
},
  "geometry": {"coordinates":[-71.41864,42.784872],"type":"Point"}
}