{
  "type": "Feature",
  "properties": {
    "iso:country":"US",
    "sg:address":"17 Holman St",
    "sg:city":"Hillsborough",
    "sg:classifiers":[
        {
            "category":"Professional",
            "subcategory":"Business Services",
            "type":"Services"
        }
    ],
    "sg:phone":"+1 603 464 4648",
    "sg:postcode":"03244",
    "sg:province":"NH",
    "sg:tags":[
        "metalworking",
        "machinery",
        "mfg"
    ],
    "wof:name":"Blanchard Machine Dev LLC",
    "wof:placetype":"venue"
},
  "geometry": {"coordinates":[-71.891758,43.118553],"type":"Point"}
}