{
  "type": "Feature",
  "properties": {
    "iso:country":"US",
    "sg:address":"220 Great Hill Rd",
    "sg:city":"Tamworth",
    "sg:classifiers":[
        {
            "category":"Building & Trades",
            "subcategory":"Construction",
            "type":"Services"
        }
    ],
    "sg:phone":"+1 603 323 8191",
    "sg:postcode":"03886",
    "sg:province":"NH",
    "sg:tags":[
        "hanging",
        "contractor"
    ],
    "wof:name":"Jean L Chester",
    "wof:placetype":"venue"
},
  "geometry": {"coordinates":[-71.305713,43.877673],"type":"Point"}
}