{
  "type": "Feature",
  "properties": {
    "addr:full":"140 Lock St Nashua NH 03064",
    "addr:housenumber":"140",
    "addr:postcode":"03064",
    "addr:street":"Lock St",
    "iso:country":"US",
    "sg:address":"140 Lock St",
    "sg:city":"Nashua",
    "sg:classifiers":[
        {
            "category":"Recreation",
            "type":"Entertainment"
        }
    ],
    "sg:phone":"+1 603 883 0153",
    "sg:postcode":"03064",
    "sg:province":"NH",
    "sg:tags":[
        "tennis",
        "court"
    ],
    "sg:website":"www.nashuaswimandtennis.com",
    "wof:name":"Nashua Swim & Tennis Club",
    "wof:placetype":"venue"
},
  "geometry": {"coordinates":[-71.451483,42.768593],"type":"Point"}
}