{
  "type": "Feature",
  "properties": {
    "iso:country":"US",
    "sg:address":"221 Main St Ste 204",
    "sg:city":"Nashua",
    "sg:classifiers":[
        {
            "category":"Insurance",
            "subcategory":"Hazard Insurance",
            "type":"Services"
        }
    ],
    "sg:phone":"+1 603 888 5944",
    "sg:postcode":"03060",
    "sg:province":"NH",
    "sg:tags":[
        "commercial",
        "business"
    ],
    "wof:name":"Daniel A Tracy Iii",
    "wof:placetype":"venue"
},
  "geometry": {"coordinates":[-71.46449699999999,42.759],"type":"Point"}
}