{
  "type": "Feature",
  "properties": {
    "iso:country":"US",
    "sg:address":"119 Summer St",
    "sg:city":"Portsmouth",
    "sg:classifiers":[
        {
            "category":"Professional",
            "subcategory":"Management & Consulting",
            "type":"Services"
        }
    ],
    "sg:phone":"+1 603 436 1991",
    "sg:postcode":"03801",
    "sg:province":"NH",
    "sg:tags":[
        "marketing",
        "agency",
        "public",
        "relations",
        "advertising"
    ],
    "wof:name":"Wilson & Gould Associates",
    "wof:placetype":"venue"
},
  "geometry": {"coordinates":[-70.76322500000001,43.072664],"type":"Point"}
}