{
  "type": "Feature",
  "properties": {
    "addr:full":"22 Clover Ln East Wakefield NH 03801",
    "addr:housenumber":"22",
    "addr:postcode":"03801",
    "addr:street":"Clover Ln East",
    "iso:country":"US",
    "sg:address":"22 Clover Ln",
    "sg:city":"East Wakefield",
    "sg:classifiers":[
        {
            "category":"Professional",
            "subcategory":"Testing Lab",
            "type":"Services"
        }
    ],
    "sg:phone":"+1 603 522 8443",
    "sg:postcode":"03801",
    "sg:province":"NH",
    "sg:tags":[
        "laboratory"
    ],
    "wof:name":"Northeast Calibration",
    "wof:placetype":"venue"
},
  "geometry": {"coordinates":[-70.78407,43.07808],"type":"Point"}
}