{
  "type": "Feature",
  "properties": {
    "iso:country":"US",
    "sg:address":"200 Keller St",
    "sg:city":"Manchester",
    "sg:classifiers":[
        {
            "category":"Autos & Motor Vehicles",
            "subcategory":"Automobile Sales",
            "type":"Retail Goods"
        }
    ],
    "sg:phone":"+1 603 668 5700",
    "sg:postcode":"03103",
    "sg:province":"NH",
    "sg:tags":[
        "car",
        "dealer"
    ],
    "sg:website":"www.autofair.com",
    "wof:name":"Autofair Honda",
    "wof:placetype":"venue"
},
  "geometry": {"coordinates":[-71.440246,42.951219],"type":"Point"}
}