{
  "type": "Feature",
  "properties": {
    "addr:full":"4 Delta Dr Londonderry NH 03053",
    "addr:housenumber":"4",
    "addr:postcode":"03053",
    "addr:street":"Delta Dr",
    "iso:country":"US",
    "sg:address":"4 Delta Dr",
    "sg:city":"Londonderry",
    "sg:classifiers":[
        {
            "category":"Professional",
            "subcategory":"Research",
            "type":"Services"
        }
    ],
    "sg:phone":"+1 603 434 3004",
    "sg:postcode":"03053",
    "sg:province":"NH",
    "wof:name":"Delta Analytical Research",
    "wof:placetype":"venue"
},
  "geometry": {"coordinates":[-71.41773999999999,42.91297],"type":"Point"}
}