{
  "type": "Feature",
  "properties": {
    "addr:full":"1 Raynes Ave Portsmouth NH 03801",
    "addr:housenumber":"1",
    "addr:postcode":"03801",
    "addr:street":"Raynes Ave",
    "iso:country":"US",
    "sg:address":"1 Raynes Ave",
    "sg:city":"Portsmouth",
    "sg:classifiers":[
        {
            "category":"Recreation",
            "type":"Entertainment"
        }
    ],
    "sg:phone":"+1 603 436 5005",
    "sg:postcode":"03801",
    "sg:province":"NH",
    "sg:tags":[
        "range",
        "practice",
        "golf"
    ],
    "wof:name":"Swing In Golf",
    "wof:placetype":"venue"
},
  "geometry": {"coordinates":[-70.76431599999999,43.079498],"type":"Point"}
}