{
  "type": "Feature",
  "properties": {
    "addr:full":"41 Green St Plymouth NH 03264",
    "addr:housenumber":"41",
    "addr:postcode":"03264",
    "addr:street":"Green St",
    "iso:country":"US",
    "sg:address":"41 Green St",
    "sg:city":"Plymouth",
    "sg:classifiers":[
        {
            "category":"Social Services",
            "type":"Services"
        }
    ],
    "sg:phone":"+1 603 536 7631",
    "sg:postcode":"03264",
    "sg:province":"NH",
    "wof:name":"Pemi Bridge House",
    "wof:placetype":"venue"
},
  "geometry": {"coordinates":[-71.686469,43.758348],"type":"Point"}
}