{
  "type": "Feature",
  "properties": {
    "iso:country":"US",
    "sg:address":"18 Stanley Ln",
    "sg:city":"Nashua",
    "sg:classifiers":[
        {
            "category":"Professional",
            "subcategory":"Accounting & Tax Preparation",
            "type":"Services"
        }
    ],
    "sg:phone":"+1 603 888 9321",
    "sg:postcode":"03062",
    "sg:province":"NH",
    "sg:tags":[
        "accountant"
    ],
    "wof:name":"Jack Nelson & Assoc",
    "wof:placetype":"venue"
},
  "geometry": {"coordinates":[-71.47004800000001,42.729098],"type":"Point"}
}