{
  "type": "Feature",
  "properties": {
    "iso:country":"US",
    "sg:address":"1 Homestead Dr",
    "sg:city":"Derry",
    "sg:classifiers":[
        {
            "category":"Shopping",
            "subcategory":"Pets & Pet Supplies",
            "type":"Retail Goods"
        },
        {
            "category":"Retail",
            "subcategory":"Veterinary Services",
            "type":"Services"
        },
        {
            "category":"Retail",
            "subcategory":"Animal Services",
            "type":"Services"
        }
    ],
    "sg:phone":"+1 603 432 9085",
    "sg:postcode":"03038",
    "sg:province":"NH",
    "sg:tags":[
        "exercising",
        "specialty",
        "sitting"
    ],
    "wof:name":"All 4 Paws Petsitting",
    "wof:placetype":"venue"
},
  "geometry": {"coordinates":[-71.29097,42.856571],"type":"Point"}
}