{
  "type": "Feature",
  "properties": {
    "iso:country":"US",
    "sg:address":"222 Elm St",
    "sg:city":"Milford",
    "sg:classifiers":[
        {
            "category":"Restaurant",
            "type":"Food & Drink"
        }
    ],
    "sg:menulink":"http://www.allmenus.com/nh/milford/129587-subway/menu/",
    "sg:phone":"+1 603 673 9099",
    "sg:postcode":"03055",
    "sg:province":"NH",
    "sg:tags":[
        "american",
        "sandwich"
    ],
    "wof:name":"Subway",
    "wof:placetype":"venue"
},
  "geometry": {"coordinates":[-71.670682,42.838762],"type":"Point"}
}