{
  "type": "Feature",
  "properties": {
    "iso:country":"US",
    "sg:address":"780 N Main St",
    "sg:city":"Laconia",
    "sg:classifiers":[
        {
            "category":"Health Services",
            "subcategory":"Clinic",
            "type":"Services"
        }
    ],
    "sg:phone":"+1 603 524 8444",
    "sg:postcode":"03246",
    "sg:province":"NH",
    "sg:tags":[
        "family",
        "agency",
        "young",
        "p",
        "including",
        "hospice",
        "home"
    ],
    "sg:website":"www.chhnh.org",
    "wof:name":"Community Health & Hospice Inc",
    "wof:placetype":"venue"
},
  "geometry": {"coordinates":[-71.47310899999999,43.53214],"type":"Point"}
}