{
  "type": "Feature",
  "properties": {
    "iso:country":"US",
    "sg:address":"344 Orange St",
    "sg:city":"Manchester",
    "sg:classifiers":[
        {
            "category":"Shopping",
            "subcategory":"Books",
            "type":"Retail Goods"
        }
    ],
    "sg:phone":"+1 603 624 9707",
    "sg:postcode":"03104",
    "sg:province":"NH",
    "wof:name":"Powers Rare Books",
    "wof:placetype":"venue"
},
  "geometry": {"coordinates":[-71.448258,42.998068],"type":"Point"}
}