{
  "type": "Feature",
  "properties": {
    "iso:country":"US",
    "sg:address":"375 Keene Rd",
    "sg:city":"Antrim",
    "sg:classifiers":[
        {
            "category":"Manufacturing",
            "subcategory":"Glass & Minerals",
            "type":"Manufacturing & Wholesale Goods"
        }
    ],
    "sg:phone":"+1 603 588 4000",
    "sg:postcode":"03470",
    "sg:province":"NH",
    "sg:tags":[
        "h",
        "mfg"
    ],
    "sg:website":"www.ohgtile.com",
    "wof:name":"Old Hancock Glassworks",
    "wof:placetype":"venue"
},
  "geometry": {"coordinates":[-72.37687699999999,42.792032],"type":"Point"}
}