{
  "type": "Feature",
  "properties": {
    "iso:country":"US",
    "sg:address":"34 Hemlock Shore Dr",
    "sg:city":"Atkinson",
    "sg:classifiers":[
        {
            "category":"Building & Trades",
            "subcategory":"Construction",
            "type":"Services"
        }
    ],
    "sg:phone":"+1 603 329 6620",
    "sg:postcode":"03811",
    "sg:province":"NH",
    "sg:tags":[
        "hanging",
        "contractor"
    ],
    "wof:name":"BJ Donnelly Pntg Co Inc",
    "wof:placetype":"venue"
},
  "geometry": {"coordinates":[-71.200824,42.865496],"type":"Point"}
}