{
  "type": "Feature",
  "properties": {
    "iso:country":"US",
    "sg:address":"78 Main St",
    "sg:city":"Lincoln",
    "sg:classifiers":[
        {
            "category":"Professional",
            "subcategory":"Accounting & Tax Preparation",
            "type":"Services"
        }
    ],
    "sg:phone":"+1 603 745 3800",
    "sg:postcode":"03262",
    "sg:province":"NH",
    "sg:tags":[
        "accountant"
    ],
    "wof:name":"Driscoll & Co Pllc",
    "wof:placetype":"venue"
},
  "geometry": {"coordinates":[-71.68534099999999,44.028448],"type":"Point"}
}