{
  "type": "Feature",
  "properties": {
    "iso:country":"US",
    "sg:address":"41 Sargent Rd",
    "sg:city":"Sandown",
    "sg:classifiers":[
        {
            "category":"Real Estate",
            "subcategory":"Developer",
            "type":"Services"
        }
    ],
    "sg:phone":"+1 603 887 0330",
    "sg:postcode":"03873",
    "sg:province":"NH",
    "wof:name":"White Rock Realty Trust",
    "wof:placetype":"venue"
},
  "geometry": {"coordinates":[-71.186474,42.94862],"type":"Point"}
}