{
  "type": "Feature",
  "properties": {
    "iso:country":"US",
    "sg:address":"172 South St",
    "sg:city":"Milford",
    "sg:classifiers":[
        {
            "category":"Manufacturing",
            "subcategory":"Wood Products",
            "type":"Manufacturing & Wholesale Goods"
        }
    ],
    "sg:phone":"+1 603 673 2136",
    "sg:postcode":"03055",
    "sg:province":"NH",
    "sg:tags":[
        "mfg"
    ],
    "wof:name":"Expressions Gallery",
    "wof:placetype":"venue"
},
  "geometry": {"coordinates":[-71.64881200000001,42.832785],"type":"Point"}
}