{
  "type": "Feature",
  "properties": {
    "iso:country":"US",
    "sg:address":"548 High St",
    "sg:city":"Hampton",
    "sg:classifiers":[
        {
            "category":"Building & Trades",
            "subcategory":"Electrical",
            "type":"Services"
        }
    ],
    "sg:phone":"+1 603 926 4144",
    "sg:postcode":"03842",
    "sg:province":"NH",
    "sg:tags":[
        "electric",
        "contractor"
    ],
    "wof:name":"Robert R Charette & Co",
    "wof:placetype":"venue"
},
  "geometry": {"coordinates":[-70.797049,42.941522],"type":"Point"}
}