{
  "type": "Feature",
  "properties": {
    "addr:full":"30 Longwood Dr Keene NH 03431",
    "addr:housenumber":"30",
    "addr:postcode":"03431",
    "addr:street":"Longwood Dr",
    "iso:country":"US",
    "sg:address":"30 Longwood Dr",
    "sg:city":"Keene",
    "sg:classifiers":[
        {
            "category":"Professional",
            "subcategory":"Business Services",
            "type":"Services"
        }
    ],
    "sg:phone":"+1 603 352 2036",
    "sg:postcode":"03431",
    "sg:province":"NH",
    "wof:name":"Mlt Packaging Consultants",
    "wof:placetype":"venue"
},
  "geometry": {"coordinates":[-72.254704,42.907799],"type":"Point"}
}