{
  "type": "Feature",
  "properties": {
    "iso:country":"US",
    "sg:address":"11 Kelly St",
    "sg:city":"Nashua",
    "sg:classifiers":[
        {
            "category":"Real Estate",
            "subcategory":"Real Estate Agent",
            "type":"Services"
        }
    ],
    "sg:phone":"+1 603 888 7859",
    "sg:postcode":"03062",
    "sg:province":"NH",
    "wof:name":"Reality Netsoft Corp",
    "wof:placetype":"venue"
},
  "geometry": {"coordinates":[-71.467687,42.730612],"type":"Point"}
}