{
  "type": "Feature",
  "properties": {
    "iso:country":"US",
    "sg:address":"14 Chandler Rd",
    "sg:city":"Bedford",
    "sg:classifiers":[
        {
            "category":"Retail",
            "subcategory":"Portrait Studio",
            "type":"Services"
        }
    ],
    "sg:phone":"+1 603 471 1405",
    "sg:postcode":"03110",
    "sg:province":"NH",
    "sg:tags":[
        "photo"
    ],
    "wof:name":"Hartnett Photography",
    "wof:placetype":"venue"
},
  "geometry": {"coordinates":[-71.51835199999999,42.95054],"type":"Point"}
}