{
  "type": "Feature",
  "properties": {
    "iso:country":"US",
    "sg:address":"7 Dugout Rd",
    "sg:city":"Hudson",
    "sg:classifiers":[
        {
            "category":"Building & Trades",
            "subcategory":"Construction",
            "type":"Services"
        }
    ],
    "sg:phone":"+1 603 889 7417",
    "sg:postcode":"03051",
    "sg:province":"NH",
    "sg:tags":[
        "home",
        "contractor",
        "family",
        "general"
    ],
    "wof:name":"Marston Construction Company",
    "wof:placetype":"venue"
},
  "geometry": {"coordinates":[-71.388949,42.787054],"type":"Point"}
}