{
  "type": "Feature",
  "properties": {
    "iso:country":"US",
    "sg:address":"85 Dollard Rd",
    "sg:city":"Auburn",
    "sg:classifiers":[
        {
            "category":"Building & Trades",
            "subcategory":"Landscaping Services",
            "type":"Services"
        }
    ],
    "sg:phone":"+1 603 370 0699",
    "sg:postcode":"03032",
    "sg:province":"NH",
    "sg:tags":[
        "waterfall"
    ],
    "wof:name":"Raindance Waterfalls & Irrgtn",
    "wof:placetype":"venue"
},
  "geometry": {"coordinates":[-71.36458500000001,43.022348],"type":"Point"}
}