{
  "type": "Feature",
  "properties": {
    "addr:full":"44 Gleneagle Dr Nashua NH 03063",
    "addr:housenumber":"44",
    "addr:postcode":"03063",
    "addr:street":"Gleneagle Dr",
    "iso:country":"US",
    "sg:address":"44 Gleneagle Dr",
    "sg:city":"Nashua",
    "sg:classifiers":[
        {
            "category":"Building & Trades",
            "subcategory":"Construction",
            "type":"Services"
        }
    ],
    "sg:phone":"+1 603 882 5069",
    "sg:postcode":"03063",
    "sg:province":"NH",
    "sg:tags":[
        "contractor"
    ],
    "wof:name":"Sutton Drywall LLC",
    "wof:placetype":"venue"
},
  "geometry": {"coordinates":[-71.511121,42.790629],"type":"Point"}
}