{
  "type": "Feature",
  "properties": {
    "iso:country":"US",
    "sg:address":"1 Long Hill Rd",
    "sg:city":"Dover",
    "sg:classifiers":[
        {
            "category":"Autos & Motor Vehicles",
            "subcategory":"Fuel & Gas Station",
            "type":"Retail Goods"
        }
    ],
    "sg:phone":"+1 603 742 1476",
    "sg:postcode":"03820",
    "sg:province":"NH",
    "sg:tags":[
        "oil"
    ],
    "wof:name":"Dover Shell Station",
    "wof:placetype":"venue"
},
  "geometry": {"coordinates":[-70.8986,43.231604],"type":"Point"}
}