{
  "type": "Feature",
  "properties": {
    "iso:country":"US",
    "sg:address":"1 Harbour Pl",
    "sg:city":"Portsmouth",
    "sg:classifiers":[
        {
            "category":"Professional",
            "subcategory":"Computer Services",
            "type":"Services"
        }
    ],
    "sg:phone":"+1 603 427 0444",
    "sg:postcode":"03801",
    "sg:province":"NH",
    "sg:tags":[
        "product",
        "support",
        "system",
        "develops",
        "market",
        "software"
    ],
    "wof:name":"CA",
    "wof:placetype":"venue"
},
  "geometry": {"coordinates":[-70.753135,43.078088],"type":"Point"}
}