{
  "type": "Feature",
  "properties": {
    "iso:country":"US",
    "sg:address":"65 Catamount Hill Dr",
    "sg:city":"Allenstown",
    "sg:classifiers":[
        {
            "category":"Building & Trades",
            "subcategory":"Construction",
            "type":"Services"
        }
    ],
    "sg:phone":"+1 603 485 1182",
    "sg:postcode":"03275",
    "sg:province":"NH",
    "sg:tags":[
        "tile",
        "dealer",
        "contractor"
    ],
    "wof:name":"Bob Vaillancourt Installations",
    "wof:placetype":"venue"
},
  "geometry": {"coordinates":[-71.405196,43.150416],"type":"Point"}
}