{
  "type": "Feature",
  "properties": {
    "iso:country":"US",
    "sg:address":"33 School St",
    "sg:city":"Allenstown",
    "sg:classifiers":[
        {
            "category":"Social Services",
            "subcategory":"Child Care",
            "type":"Services"
        }
    ],
    "sg:phone":"+1 603 485 8595",
    "sg:postcode":"03275",
    "sg:province":"NH",
    "wof:name":"School Street Kindergarten Ctr",
    "wof:placetype":"venue"
},
  "geometry": {"coordinates":[-71.44943000000001,43.126871],"type":"Point"}
}