{
  "type": "Feature",
  "properties": {
    "addr:full":"37 Ffrost Dr Durham NH 03824",
    "addr:housenumber":"37",
    "addr:postcode":"03824",
    "addr:street":"Ffrost Dr",
    "iso:country":"US",
    "sg:address":"37 Ffrost Dr",
    "sg:city":"Durham",
    "sg:classifiers":[
        {
            "category":"Real Estate",
            "subcategory":"Architect",
            "type":"Services"
        }
    ],
    "sg:phone":"+1 603 868 3381",
    "sg:postcode":"03824",
    "sg:province":"NH",
    "sg:tags":[
        "architectural"
    ],
    "wof:name":"South Street Design",
    "wof:placetype":"venue"
},
  "geometry": {"coordinates":[-70.914492,43.114977],"type":"Point"}
}