{
  "type": "Feature",
  "properties": {
    "iso:country":"US",
    "sg:address":"1821 E Conway Rd",
    "sg:city":"North Conway",
    "sg:classifiers":[
        {
            "category":"Wholesale",
            "subcategory":"Hardware",
            "type":"Manufacturing & Wholesale Goods"
        }
    ],
    "sg:phone":"+1 603 356 7722",
    "sg:postcode":"03813",
    "sg:province":"NH",
    "sg:tags":[
        "tool"
    ],
    "wof:name":"Western Tool Supply",
    "wof:placetype":"venue"
},
  "geometry": {"coordinates":[-71.059551,44.011277],"type":"Point"}
}