{
  "type": "Feature",
  "properties": {
    "iso:country":"US",
    "sg:address":"45 Main St Ste 101",
    "sg:city":"Peterborough",
    "sg:classifiers":[
        {
            "category":"Health Services",
            "subcategory":"Doctor",
            "type":"Services"
        }
    ],
    "sg:phone":"+1 603 924 0804",
    "sg:postcode":"03458",
    "sg:province":"NH",
    "sg:tags":[
        "physician",
        "family",
        "practice",
        "surgeons",
        "medicine",
        "surgeon"
    ],
    "wof:name":"Teresa Mary Cadorette Md Pa",
    "wof:placetype":"venue"
},
  "geometry": {"coordinates":[-71.950333,42.87764],"type":"Point"}
}