{
  "type": "Feature",
  "properties": {
    "iso:country":"US",
    "sg:address":"273 S Broadway",
    "sg:city":"Salem",
    "sg:classifiers":[
        {
            "category":"Real Estate",
            "subcategory":"Real Estate Agent",
            "type":"Services"
        }
    ],
    "sg:phone":"+1 603 893 8990",
    "sg:postcode":"03079",
    "sg:province":"NH",
    "sg:tags":[
        "brokerage"
    ],
    "wof:name":"E R A Masiello Group",
    "wof:placetype":"venue"
},
  "geometry": {"coordinates":[-71.210646,42.756595],"type":"Point"}
}