{
  "type": "Feature",
  "properties": {
    "addr:full":"25 Danbury Cir Amherst NH 03031",
    "addr:housenumber":"25",
    "addr:postcode":"03031",
    "addr:street":"Danbury Cir",
    "iso:country":"US",
    "sg:address":"25 Danbury Cir",
    "sg:city":"Amherst",
    "sg:classifiers":[
        {
            "category":"Professional",
            "subcategory":"Computer Services",
            "type":"Services"
        }
    ],
    "sg:phone":"+1 603 673 0695",
    "sg:postcode":"03031",
    "sg:province":"NH",
    "sg:tags":[
        "programing",
        "custom"
    ],
    "wof:name":"Neweb Services",
    "wof:placetype":"venue"
},
  "geometry": {"coordinates":[-71.579331,42.836036],"type":"Point"}
}