{
  "type": "Feature",
  "properties": {
    "addr:full":"202 Cilley Rd Manchester NH 03103",
    "addr:housenumber":"202",
    "addr:postcode":"03103",
    "addr:street":"Cilley Rd",
    "iso:country":"US",
    "sg:address":"202 Cilley Rd",
    "sg:city":"Manchester",
    "sg:classifiers":[
        {
            "category":"Retail",
            "subcategory":"Portrait Studio",
            "type":"Services"
        }
    ],
    "sg:phone":"+1 603 566 7505",
    "sg:postcode":"03103",
    "sg:province":"NH",
    "sg:tags":[
        "photo"
    ],
    "wof:name":"Wayne Boucher",
    "wof:placetype":"venue"
},
  "geometry": {"coordinates":[-71.45080799999999,42.972968],"type":"Point"}
}