{
  "type": "Feature",
  "properties": {
    "iso:country":"US",
    "sg:address":"9 Meetinghouse Rd",
    "sg:city":"Hinsdale",
    "sg:classifiers":[
        {
            "category":"Building & Trades",
            "subcategory":"Construction",
            "type":"Services"
        }
    ],
    "sg:phone":"+1 603 256 8248",
    "sg:postcode":"03451",
    "sg:province":"NH",
    "sg:tags":[
        "roofing",
        "contractor"
    ],
    "wof:name":"BRI Roofing & Siding",
    "wof:placetype":"venue"
},
  "geometry": {"coordinates":[-72.520318,42.820306],"type":"Point"}
}