{
  "type": "Feature",
  "properties": {
    "iso:country":"US",
    "sg:address":"4 Progress Dr",
    "sg:city":"Dover",
    "sg:classifiers":[
        {
            "category":"Manufacturing",
            "subcategory":"Tools & Machinery",
            "type":"Manufacturing & Wholesale Goods"
        }
    ],
    "sg:phone":"+1 603 742 6247",
    "sg:postcode":"03820",
    "sg:province":"NH",
    "sg:tags":[
        "machine",
        "shop"
    ],
    "sg:website":"www.northeastproducts.com",
    "wof:name":"North East Products",
    "wof:placetype":"venue"
},
  "geometry": {"coordinates":[-70.904543,43.181131],"type":"Point"}
}