{
  "type": "Feature",
  "properties": {
    "addr:full":"129 Sunset Dr Monroe NH 03771",
    "addr:housenumber":"129",
    "addr:postcode":"03771",
    "addr:street":"Sunset Dr",
    "iso:country":"US",
    "sg:address":"129 Sunset Dr",
    "sg:city":"Monroe",
    "sg:classifiers":[
        {
            "category":"Professional",
            "subcategory":"Lawyer & Legal Services",
            "type":"Services"
        }
    ],
    "sg:phone":"+1 603 638 9360",
    "sg:postcode":"03771",
    "sg:province":"NH",
    "sg:tags":[
        "attorney",
        "practice"
    ],
    "wof:name":"Gillian Morrison Attorney At L",
    "wof:placetype":"venue"
},
  "geometry": {"coordinates":[-72.016628,44.299453],"type":"Point"}
}