{
  "type": "Feature",
  "properties": {
    "iso:country":"US",
    "sg:address":"1600 Woodbury Ave",
    "sg:city":"Portsmouth",
    "sg:classifiers":[
        {
            "category":"Banks & Credit Unions",
            "subcategory":"Bank",
            "type":"Services"
        }
    ],
    "sg:phone":"+1 603 430 3771",
    "sg:postcode":"03801",
    "sg:province":"NH",
    "wof:name":"Citizens Bank",
    "wof:placetype":"venue"
},
  "geometry": {"coordinates":[-70.791467,43.089905],"type":"Point"}
}