{
  "type": "Feature",
  "properties": {
    "iso:country":"US",
    "sg:address":"28 Webster St",
    "sg:city":"Manchester",
    "sg:classifiers":[
        {
            "category":"Professional",
            "subcategory":"Business Services",
            "type":"Services"
        }
    ],
    "sg:phone":"+1 603 626 7888",
    "sg:postcode":"03104",
    "sg:province":"NH",
    "sg:tags":[
        "security"
    ],
    "wof:name":"O'Brien-Rodgers-Kaise Inc",
    "wof:placetype":"venue"
},
  "geometry": {"coordinates":[-71.463733,43.006563],"type":"Point"}
}