{
  "type": "Feature",
  "properties": {
    "iso:country":"US",
    "sg:address":"180 Sand St",
    "sg:city":"Berlin",
    "sg:classifiers":[
        {
            "category":"Government",
            "subcategory":"Office",
            "type":"Public Place"
        }
    ],
    "sg:phone":"+1 603 752 3687",
    "sg:postcode":"03584",
    "sg:province":"NH",
    "sg:tags":[
        "village"
    ],
    "wof:name":"Berlin Water Filter Plant",
    "wof:placetype":"venue"
},
  "geometry": {"coordinates":[-71.567306,44.49618],"type":"Point"}
}