{
  "type": "Feature",
  "properties": {
    "addr:full":"168 Bremer St Manchester NH 03102",
    "addr:housenumber":"168",
    "addr:postcode":"03102",
    "addr:street":"Bremer St",
    "iso:country":"US",
    "sg:address":"168 Bremer St",
    "sg:city":"Manchester",
    "sg:classifiers":[
        {
            "category":"Arts & Performance",
            "subcategory":"Theater",
            "type":"Entertainment"
        }
    ],
    "sg:phone":"+1 603 623 2227",
    "sg:postcode":"03102",
    "sg:province":"NH",
    "sg:tags":[
        "group",
        "live",
        "music"
    ],
    "wof:name":"D J Dave Entertainment",
    "wof:placetype":"venue"
},
  "geometry": {"coordinates":[-71.482142,42.996727],"type":"Point"}
}