{
  "type": "Feature",
  "properties": {
    "iso:country":"US",
    "sg:address":"166 Cedar St",
    "sg:city":"Contoocook",
    "sg:classifiers":[
        {
            "category":"Education",
            "subcategory":"Special Training",
            "type":"Public Place"
        }
    ],
    "sg:phone":"+1 603 746 6704",
    "sg:postcode":"03229",
    "sg:province":"NH",
    "wof:name":"Contoocook Village Lrng Ctr",
    "wof:placetype":"venue"
},
  "geometry": {"coordinates":[-71.71299999999999,43.219424],"type":"Point"}
}