{
  "type": "Feature",
  "properties": {
    "iso:country":"US",
    "sg:address":"117 Federal Hill Rd",
    "sg:city":"Hollis",
    "sg:classifiers":[
        {
            "category":"Real Estate",
            "subcategory":"Real Estate Agent",
            "type":"Services"
        }
    ],
    "sg:phone":"+1 603 465 3990",
    "sg:postcode":"03049",
    "sg:province":"NH",
    "sg:tags":[
        "inspection"
    ],
    "wof:name":"Advisor Home Inspection",
    "wof:placetype":"venue"
},
  "geometry": {"coordinates":[-71.603341,42.762526],"type":"Point"}
}