{
  "type": "Feature",
  "properties": {
    "iso:country":"US",
    "sg:address":"320 Pork Hill Rd",
    "sg:city":"Wolfeboro",
    "sg:classifiers":[
        {
            "category":"Shopping",
            "subcategory":"Used Merchandise",
            "type":"Retail Goods"
        }
    ],
    "sg:phone":"+1 603 569 0000",
    "sg:postcode":"03894",
    "sg:province":"NH",
    "wof:name":"New England Events Management",
    "wof:placetype":"venue"
},
  "geometry": {"coordinates":[-71.150279,43.661243],"type":"Point"}
}