{
  "type": "Feature",
  "properties": {
    "addr:full":"104 Main St Colebrook NH 03576",
    "addr:housenumber":"104",
    "addr:postcode":"03576",
    "addr:street":"Main St",
    "iso:country":"US",
    "sg:address":"104 Main St",
    "sg:city":"Colebrook",
    "sg:classifiers":[
        {
            "category":"Banks & Credit Unions",
            "subcategory":"Bank",
            "type":"Services"
        }
    ],
    "sg:phone":"+1 603 237 5577",
    "sg:postcode":"03576",
    "sg:province":"NH",
    "wof:name":"Citizens Bank",
    "wof:placetype":"venue"
},
  "geometry": {"coordinates":[-71.491567,44.910982],"type":"Point"}
}