{
  "type": "Feature",
  "properties": {
    "iso:country":"US",
    "sg:address":"10 Vista Way",
    "sg:city":"Merrimack",
    "sg:classifiers":[
        {
            "category":"Professional",
            "subcategory":"Engineering",
            "type":"Services"
        }
    ],
    "sg:phone":"+1 603 424 4558",
    "sg:postcode":"03054",
    "sg:province":"NH",
    "sg:tags":[
        "engineer"
    ],
    "wof:name":"Sibley Consulting",
    "wof:placetype":"venue"
},
  "geometry": {"coordinates":[-71.487258,42.878886],"type":"Point"}
}