{
  "type": "Feature",
  "properties": {
    "iso:country":"US",
    "sg:address":"102 Perimeter Rd",
    "sg:city":"Nashua",
    "sg:classifiers":[
        {
            "category":"Banks & Credit Unions",
            "subcategory":"Investment Brokerage",
            "type":"Services"
        }
    ],
    "sg:phone":"+1 603 883 5190",
    "sg:postcode":"03063",
    "sg:province":"NH",
    "wof:name":"Hilltop Investments",
    "wof:placetype":"venue"
},
  "geometry": {"coordinates":[-71.52396,42.78231],"type":"Point"}
}