{
  "type": "Feature",
  "properties": {
    "iso:country":"US",
    "sg:address":"39 Dorchester Way",
    "sg:city":"Nashua",
    "sg:classifiers":[
        {
            "category":"Professional",
            "subcategory":"Business Services",
            "type":"Services"
        }
    ],
    "sg:phone":"+1 603 882 1863",
    "sg:postcode":"03064",
    "sg:province":"NH",
    "wof:name":"Cunningham S/Associates",
    "wof:placetype":"venue"
},
  "geometry": {"coordinates":[-71.485686,42.7833],"type":"Point"}
}