{
  "type": "Feature",
  "properties": {
    "iso:country":"US",
    "sg:address":"66 Chester St",
    "sg:city":"Chester",
    "sg:classifiers":[
        {
            "category":"Wholesale",
            "subcategory":"Toys & Hobbies",
            "type":"Manufacturing & Wholesale Goods"
        }
    ],
    "sg:phone":"+1 603 887 7432",
    "sg:postcode":"03036",
    "sg:province":"NH",
    "sg:tags":[
        "puppet",
        "marionette"
    ],
    "wof:name":"Palm Of The Hand Stories",
    "wof:placetype":"venue"
},
  "geometry": {"coordinates":[-71.260732,42.959562],"type":"Point"}
}