{
  "type": "Feature",
  "properties": {
    "addr:full":"3 Crestwood Dr Hollis NH 03049",
    "addr:housenumber":"3",
    "addr:postcode":"03049",
    "addr:street":"Crestwood Dr",
    "iso:country":"US",
    "sg:address":"3 Crestwood Dr",
    "sg:city":"Hollis",
    "sg:classifiers":[
        {
            "category":"Professional",
            "subcategory":"Advertising",
            "type":"Services"
        }
    ],
    "sg:phone":"+1 603 465 9358",
    "sg:postcode":"03049",
    "sg:province":"NH",
    "sg:tags":[
        "advertising-telephone",
        "fax",
        "telemarketing"
    ],
    "wof:name":"Jason Stringer",
    "wof:placetype":"venue"
},
  "geometry": {"coordinates":[-71.558634,42.742741],"type":"Point"}
}