{
  "type": "Feature",
  "properties": {
    "iso:country":"US",
    "sg:address":"495 Amherst St",
    "sg:city":"Nashua",
    "sg:classifiers":[
        {
            "category":"Retail",
            "subcategory":"Auto Rental",
            "type":"Services"
        }
    ],
    "sg:phone":"+1 603 886 9599",
    "sg:postcode":"03063",
    "sg:province":"NH",
    "sg:tags":[
        "passenger",
        "car"
    ],
    "wof:name":"Enterprise Rent-A-Car",
    "wof:placetype":"venue"
},
  "geometry": {"coordinates":[-71.518427,42.790547],"type":"Point"}
}