{
  "type": "Feature",
  "properties": {
    "addr:full":"22 Smith St Pittsfield NH 03263",
    "addr:housenumber":"22",
    "addr:postcode":"03263",
    "addr:street":"Smith St",
    "iso:country":"US",
    "sg:address":"22 Smith St",
    "sg:city":"Pittsfield",
    "sg:classifiers":[
        {
            "category":"Professional",
            "subcategory":"Management & Consulting",
            "type":"Services"
        }
    ],
    "sg:phone":"+1 603 435 5075",
    "sg:postcode":"03263",
    "sg:province":"NH",
    "sg:tags":[
        "consultant",
        "lighting"
    ],
    "wof:name":"Rainfall Irrigation",
    "wof:placetype":"venue"
},
  "geometry": {"coordinates":[-71.326882,43.308421],"type":"Point"}
}