{
  "type": "Feature",
  "properties": {
    "iso:country":"US",
    "sg:address":"3 Water St",
    "sg:city":"Hudson",
    "sg:classifiers":[
        {
            "category":"Building & Trades",
            "subcategory":"Construction",
            "type":"Services"
        }
    ],
    "sg:phone":"+1 603 883 2062",
    "sg:postcode":"03051",
    "sg:province":"NH",
    "sg:tags":[
        "contractor"
    ],
    "wof:name":"EZ Target Corp",
    "wof:placetype":"venue"
},
  "geometry": {"coordinates":[-71.43620799999999,42.764076],"type":"Point"}
}