{
  "type": "Feature",
  "properties": {
    "iso:country":"US",
    "sg:address":"27 Gary Ln",
    "sg:city":"Exeter",
    "sg:classifiers":[
        {
            "category":"Building & Trades",
            "subcategory":"Construction",
            "type":"Services"
        }
    ],
    "sg:phone":"+1 603 772 9545",
    "sg:postcode":"03833",
    "sg:province":"NH",
    "sg:tags":[
        "concrete",
        "contractor"
    ],
    "wof:name":"Sturgis Concrete Floors",
    "wof:placetype":"venue"
},
  "geometry": {"coordinates":[-70.95717,42.968041],"type":"Point"}
}