{
  "type": "Feature",
  "properties": {
    "iso:country":"US",
    "sg:address":"1015 Laconia Rd",
    "sg:city":"Tilton",
    "sg:classifiers":[
        {
            "category":"Real Estate",
            "subcategory":"Real Estate Agent",
            "type":"Services"
        }
    ],
    "sg:phone":"+1 603 524 9100",
    "sg:postcode":"03276",
    "sg:province":"NH",
    "wof:name":"Guyotte Realty Inc",
    "wof:placetype":"venue"
},
  "geometry": {"coordinates":[-71.514641,43.501453],"type":"Point"}
}