{
  "type": "Feature",
  "properties": {
    "iso:country":"US",
    "sg:address":"16 Kingston Rd",
    "sg:city":"Exeter",
    "sg:classifiers":[
        {
            "category":"Professional",
            "subcategory":"Printing & Photocopies",
            "type":"Services"
        },
        {
            "category":"Professional",
            "subcategory":"Computer Services",
            "type":"Services"
        }
    ],
    "sg:phone":"+1 603 772 2305",
    "sg:postcode":"03833",
    "sg:province":"NH",
    "sg:tags":[
        "processing",
        "datum",
        "duplicating",
        "copying"
    ],
    "wof:name":"Connor & Connor Inc",
    "wof:placetype":"venue"
},
  "geometry": {"coordinates":[-70.974406,42.974343],"type":"Point"}
}