{
  "type": "Feature",
  "properties": {
    "iso:country":"US",
    "sg:address":"17 Currier Dr",
    "sg:city":"Manchester",
    "sg:classifiers":[
        {
            "category":"Building & Trades",
            "subcategory":"Cleaning & Sanitation",
            "type":"Services"
        }
    ],
    "sg:phone":"+1 603 622 7392",
    "sg:postcode":"03104",
    "sg:province":"NH",
    "sg:tags":[
        "commercial"
    ],
    "wof:name":"W & D Cleaning Inc",
    "wof:placetype":"venue"
},
  "geometry": {"coordinates":[-71.41627,43.007711],"type":"Point"}
}