{
  "type": "Feature",
  "properties": {
    "addr:full":"1536 Candia Rd Manchester NH 03109",
    "addr:housenumber":"1536",
    "addr:postcode":"03109",
    "addr:street":"Candia Rd",
    "iso:country":"US",
    "sg:address":"1536 Candia Rd",
    "sg:city":"Manchester",
    "sg:classifiers":[
        {
            "category":"Food & Beverages",
            "subcategory":"Groceries & Convenience Stores",
            "type":"Retail Goods"
        }
    ],
    "sg:phone":"+1 603 623 6463",
    "sg:postcode":"03109",
    "sg:province":"NH",
    "wof:name":"Nickles Market",
    "wof:placetype":"venue"
},
  "geometry": {"coordinates":[-71.403346,42.994665],"type":"Point"}
}