{
  "type": "Feature",
  "properties": {
    "iso:country":"US",
    "sg:address":"649 2nd St",
    "sg:city":"Manchester",
    "sg:classifiers":[
        {
            "category":"Real Estate",
            "subcategory":"Real Estate Agent",
            "type":"Services"
        }
    ],
    "sg:phone":"+1 603 627 6508",
    "sg:postcode":"03102",
    "sg:province":"NH",
    "sg:tags":[
        "management",
        "property",
        "agency"
    ],
    "wof:name":"APM",
    "wof:placetype":"venue"
},
  "geometry": {"coordinates":[-71.47720099999999,42.972388],"type":"Point"}
}