{
  "type": "Feature",
  "properties": {
    "iso:country":"US",
    "sg:address":"10 Industrial Dr",
    "sg:city":"Windham",
    "sg:classifiers":[
        {
            "category":"Manufacturing",
            "subcategory":"Tools & Machinery",
            "type":"Manufacturing & Wholesale Goods"
        }
    ],
    "sg:phone":"+1 603 890 0455",
    "sg:postcode":"03087",
    "sg:province":"NH",
    "sg:tags":[
        "outdoor",
        "disaster",
        "mfg",
        "equipment",
        "preparedness",
        "safety"
    ],
    "wof:name":"M P I Outdoors",
    "wof:placetype":"venue"
},
  "geometry": {"coordinates":[-71.254114,42.809945],"type":"Point"}
}