{
  "type": "Feature",
  "properties": {
    "iso:country":"US",
    "sg:address":"4 S Park St",
    "sg:city":"Lebanon",
    "sg:classifiers":[
        {
            "category":"Health Services",
            "subcategory":"Doctor",
            "type":"Services"
        }
    ],
    "sg:phone":"+1 603 448 1717",
    "sg:postcode":"03766",
    "sg:province":"NH",
    "sg:tags":[
        "medical"
    ],
    "wof:name":"Myric W Wood Jr",
    "wof:placetype":"venue"
},
  "geometry": {"coordinates":[-72.251829,43.641869],"type":"Point"}
}