{
  "type": "Feature",
  "properties": {
    "iso:country":"US",
    "sg:address":"217 Fisherville Rd",
    "sg:city":"Concord",
    "sg:classifiers":[
        {
            "category":"Personal",
            "subcategory":"Beauty Salon",
            "type":"Services"
        }
    ],
    "sg:phone":"+1 603 753 4444",
    "sg:postcode":"03303",
    "sg:province":"NH",
    "wof:name":"Modern Look Salon",
    "wof:placetype":"venue"
},
  "geometry": {"coordinates":[-71.585581,43.264749],"type":"Point"}
}