{
  "type": "Feature",
  "properties": {
    "addr:full":"54 Maple St Whitefield NH 03598",
    "addr:housenumber":"54",
    "addr:postcode":"03598",
    "addr:street":"Maple St",
    "iso:country":"US",
    "sg:address":"54 Maple St",
    "sg:city":"Whitefield",
    "sg:classifiers":[
        {
            "category":"Arts & Performance",
            "subcategory":"Theater",
            "type":"Entertainment"
        }
    ],
    "sg:phone":"+1 603 837 9010",
    "sg:postcode":"03598",
    "sg:province":"NH",
    "wof:name":"Weathervane Theatre",
    "wof:placetype":"venue"
},
  "geometry": {"coordinates":[-71.606162,44.373114],"type":"Point"}
}