{
  "type": "Feature",
  "properties": {
    "iso:country":"US",
    "sg:address":"51 Howard Rd",
    "sg:city":"Bristol",
    "sg:classifiers":[
        {
            "category":"Freight",
            "type":"Transportation"
        }
    ],
    "sg:phone":"+1 603 744 2130",
    "sg:postcode":"03222",
    "sg:province":"NH",
    "sg:tags":[
        "operator",
        "local",
        "trucking"
    ],
    "wof:name":"Alumis Enterprises",
    "wof:placetype":"venue"
},
  "geometry": {"coordinates":[-71.728093,43.655158],"type":"Point"}
}