{
  "type": "Feature",
  "properties": {
    "addr:full":"160 Plaistow Rd Plaistow NH 03865",
    "addr:housenumber":"160",
    "addr:postcode":"03865",
    "addr:street":"Plaistow Rd",
    "iso:country":"US",
    "sg:address":"160 Plaistow Rd",
    "sg:city":"Plaistow",
    "sg:classifiers":[
        {
            "category":"Shopping",
            "subcategory":"Stationery & Office Supplies",
            "type":"Retail Goods"
        }
    ],
    "sg:phone":"+1 603 378 0672",
    "sg:postcode":"03865",
    "sg:province":"NH",
    "sg:tags":[
        "album",
        "scrapbook"
    ],
    "wof:name":"Picture Perfect Scrapbooking",
    "wof:placetype":"venue"
},
  "geometry": {"coordinates":[-71.102039,42.853091],"type":"Point"}
}