{
  "type": "Feature",
  "properties": {
    "iso:country":"US",
    "sg:address":"333 First New Hampshire Tpke",
    "sg:city":"Northwood",
    "sg:classifiers":[
        {
            "category":"Shopping",
            "type":"Retail Goods"
        }
    ],
    "sg:phone":"+1 603 942 7311",
    "sg:postcode":"03261",
    "sg:province":"NH",
    "sg:tags":[
        "monument"
    ],
    "wof:name":"Hall Monuments",
    "wof:placetype":"venue"
},
  "geometry": {"coordinates":[-71.16869,43.204527],"type":"Point"}
}