{
  "type": "Feature",
  "properties": {
    "iso:country":"US",
    "sg:address":"1 Eldridge St",
    "sg:city":"Nashua",
    "sg:classifiers":[
        {
            "category":"Wholesale",
            "subcategory":"Groceries",
            "type":"Manufacturing & Wholesale Goods"
        }
    ],
    "sg:phone":"+1 603 882 9343",
    "sg:postcode":"03060",
    "sg:province":"NH",
    "sg:tags":[
        "baker"
    ],
    "wof:name":"Bagel Alley",
    "wof:placetype":"venue"
},
  "geometry": {"coordinates":[-71.46287100000001,42.759274],"type":"Point"}
}