{
  "type": "Feature",
  "properties": {
    "iso:country":"US",
    "sg:address":"836 Candia Rd",
    "sg:city":"Manchester",
    "sg:classifiers":[
        {
            "category":"Manufacturing",
            "subcategory":"Printing",
            "type":"Manufacturing & Wholesale Goods"
        }
    ],
    "sg:phone":"+1 603 623 0802",
    "sg:postcode":"03109",
    "sg:province":"NH",
    "sg:tags":[
        "printer"
    ],
    "sg:website":"www.psquare.com",
    "wof:name":"Printers Square",
    "wof:placetype":"venue"
},
  "geometry": {"coordinates":[-71.41496600000001,42.984125],"type":"Point"}
}