{
  "type": "Feature",
  "properties": {
    "addr:full":"56 Bow Bog Rd Bow NH 03304",
    "addr:housenumber":"56",
    "addr:postcode":"03304",
    "addr:street":"Bow Bog Rd",
    "iso:country":"US",
    "sg:address":"56 Bow Bog Rd",
    "sg:city":"Bow",
    "sg:classifiers":[
        {
            "category":"Retail",
            "subcategory":"Repair Shop",
            "type":"Services"
        }
    ],
    "sg:phone":"+1 603 225 3909",
    "sg:postcode":"03304",
    "sg:province":"NH",
    "sg:tags":[
        "welding"
    ],
    "wof:name":"Leighton Welding",
    "wof:placetype":"venue"
},
  "geometry": {"coordinates":[-71.526062,43.128025],"type":"Point"}
}