{
  "type": "Feature",
  "properties": {
    "iso:country":"US",
    "sg:address":"228 Kensington Rd",
    "sg:city":"Hampton Falls",
    "sg:classifiers":[
        {
            "category":"Farming",
            "subcategory":"Fish & Marine Products",
            "type":"Manufacturing & Wholesale Goods"
        }
    ],
    "sg:phone":"+1 603 926 7177",
    "sg:postcode":"03844",
    "sg:province":"NH",
    "sg:tags":[
        "landscaping",
        "fisherman"
    ],
    "wof:name":"Caroline Murray",
    "wof:placetype":"venue"
},
  "geometry": {"coordinates":[-70.91780300000001,42.919538],"type":"Point"}
}