{
  "type": "Feature",
  "properties": {
    "iso:country":"US",
    "sg:address":"103 State Rte 101A",
    "sg:city":"Amherst",
    "sg:classifiers":[
        {
            "category":"Restaurant",
            "type":"Food & Drink"
        }
    ],
    "sg:phone":"+1 603 889 8022",
    "sg:postcode":"03031",
    "sg:province":"NH",
    "sg:tags":[
        "caterer"
    ],
    "wof:name":"Greenhouse Cafe Catering",
    "wof:placetype":"venue"
},
  "geometry": {"coordinates":[-71.57525,42.810234],"type":"Point"}
}