{
  "type": "Feature",
  "properties": {
    "iso:country":"US",
    "sg:address":"12 Oak St",
    "sg:city":"Dover",
    "sg:classifiers":[
        {
            "category":"Real Estate",
            "subcategory":"Real Estate Operator",
            "type":"Services"
        }
    ],
    "sg:phone":"+1 603 743 3400",
    "sg:postcode":"03820",
    "sg:province":"NH",
    "sg:tags":[
        "apartment"
    ],
    "wof:name":"Mc Quade Realty Inc",
    "wof:placetype":"venue"
},
  "geometry": {"coordinates":[-70.87364599999999,43.20736],"type":"Point"}
}