{
  "type": "Feature",
  "properties": {
    "iso:country":"US",
    "sg:address":"7 Myra Ave",
    "sg:city":"Lebanon",
    "sg:classifiers":[
        {
            "category":"Travel",
            "subcategory":"Travel Agent",
            "type":"Entertainment"
        }
    ],
    "sg:phone":"+1 603 448 4433",
    "sg:postcode":"03766",
    "sg:province":"NH",
    "sg:tags":[
        "agency"
    ],
    "wof:name":"Good Bye Travel Inc",
    "wof:placetype":"venue"
},
  "geometry": {"coordinates":[-72.26952199999999,43.641068],"type":"Point"}
}