{
  "type": "Feature",
  "properties": {
    "addr:full":"1 Hampton Rd Exeter NH 03833",
    "addr:housenumber":"1",
    "addr:postcode":"03833",
    "addr:street":"Hampton Rd",
    "iso:country":"US",
    "sg:address":"1 Hampton Rd",
    "sg:city":"Exeter",
    "sg:classifiers":[
        {
            "category":"Banks & Credit Unions",
            "subcategory":"Investment Brokerage",
            "type":"Services"
        }
    ],
    "sg:phone":"+1 603 778 7914",
    "sg:postcode":"03833",
    "sg:province":"NH",
    "sg:tags":[
        "consultant",
        "planning",
        "financial"
    ],
    "wof:name":"Professional Planning Svc",
    "wof:placetype":"venue"
},
  "geometry": {"coordinates":[-70.911447,42.976037],"type":"Point"}
}