{
  "type": "Feature",
  "properties": {
    "iso:country":"US",
    "sg:address":"367 Millstone Ave",
    "sg:city":"Manchester",
    "sg:classifiers":[
        {
            "category":"Professional",
            "subcategory":"Business Services",
            "type":"Services"
        }
    ],
    "sg:phone":"+1 603 624 4457",
    "sg:postcode":"03102",
    "sg:province":"NH",
    "wof:name":"Saul Associates LLC",
    "wof:placetype":"venue"
},
  "geometry": {"coordinates":[-71.49009700000001,43.04784],"type":"Point"}
}