{
  "type": "Feature",
  "properties": {
    "iso:country":"US",
    "sg:address":"91 N State St",
    "sg:city":"Concord",
    "sg:classifiers":[
        {
            "category":"Professional",
            "subcategory":"Lawyer & Legal Services",
            "type":"Services"
        }
    ],
    "sg:phone":"+1 603 225 9944",
    "sg:postcode":"03301",
    "sg:province":"NH",
    "wof:name":"Runge Law Offices",
    "wof:placetype":"venue"
},
  "geometry": {"coordinates":[-71.54016,43.209086],"type":"Point"}
}