{
  "type": "Feature",
  "properties": {
    "addr:full":"8 Sawyer Rd Hampstead NH 03841",
    "addr:housenumber":"8",
    "addr:postcode":"03841",
    "addr:street":"Sawyer Rd",
    "iso:country":"US",
    "sg:address":"8 Sawyer Rd",
    "sg:city":"Hampstead",
    "sg:classifiers":[
        {
            "category":"Manufacturing",
            "subcategory":"Metals",
            "type":"Manufacturing & Wholesale Goods"
        }
    ],
    "sg:phone":"+1 603 329 5624",
    "sg:postcode":"03841",
    "sg:province":"NH",
    "sg:tags":[
        "computer",
        "mfg"
    ],
    "wof:name":"American Rugged Enclosures",
    "wof:placetype":"venue"
},
  "geometry": {"coordinates":[-71.164033,42.887097],"type":"Point"}
}