{
  "type": "Feature",
  "properties": {
    "addr:full":"59 Warren St Concord NH 03301",
    "addr:housenumber":"59",
    "addr:postcode":"03301",
    "addr:street":"Warren St",
    "iso:country":"US",
    "sg:address":"59 Warren St",
    "sg:city":"Concord",
    "sg:classifiers":[
        {
            "category":"Professional",
            "subcategory":"Lawyer & Legal Services",
            "type":"Services"
        }
    ],
    "sg:phone":"+1 603 230 9999",
    "sg:postcode":"03301",
    "sg:province":"NH",
    "wof:name":"Penny Dean",
    "wof:placetype":"venue"
},
  "geometry": {"coordinates":[-71.54167099999999,43.203334],"type":"Point"}
}