{
  "type": "Feature",
  "properties": {
    "iso:country":"US",
    "sg:address":"719 Route 12 ",
    "sg:city":"Westmoreland",
    "sg:classifiers":[
        {
            "category":"Restaurant",
            "type":"Food & Drink"
        }
    ],
    "sg:menulink":"http://www.allmenus.com/nh/westmoreland/292538-summit-steak-house-and-tavern/menu/",
    "sg:phone":"+1 603 358 3331",
    "sg:postcode":"03467",
    "sg:province":"NH",
    "sg:tags":[
        "steakhouse"
    ],
    "wof:name":"Summit Steak House and Tavern",
    "wof:placetype":"venue"
},
  "geometry": {"coordinates":[-72.365578,42.981533],"type":"Point"}
}