{
  "type": "Feature",
  "properties": {
    "iso:country":"US",
    "sg:address":"11 Garden Rd",
    "sg:city":"Plaistow",
    "sg:classifiers":[
        {
            "category":"Retail",
            "subcategory":"Veterinary Services",
            "type":"Services"
        }
    ],
    "sg:phone":"+1 603 382 5819",
    "sg:postcode":"03865",
    "sg:province":"NH",
    "sg:tags":[
        "hospital",
        "animal"
    ],
    "wof:name":"Plaistow Animal Medical Center",
    "wof:placetype":"venue"
},
  "geometry": {"coordinates":[-71.103438,42.8222],"type":"Point"}
}