{
  "type": "Feature",
  "properties": {
    "iso:country":"US",
    "sg:address":"67 Sullivan Rd",
    "sg:city":"Hudson",
    "sg:classifiers":[
        {
            "category":"Arts & Performance",
            "subcategory":"Theater",
            "type":"Entertainment"
        }
    ],
    "sg:phone":"+1 603 886 7980",
    "sg:postcode":"03051",
    "sg:province":"NH",
    "sg:tags":[
        "group"
    ],
    "wof:name":"New Style Entertainment",
    "wof:placetype":"venue"
},
  "geometry": {"coordinates":[-71.373322,42.777124],"type":"Point"}
}