{
  "type": "Feature",
  "properties": {
    "iso:country":"US",
    "sg:address":"1 Batchelder Rd",
    "sg:city":"Seabrook",
    "sg:classifiers":[
        {
            "category":"Autos & Motor Vehicles",
            "subcategory":"Auto Supplies",
            "type":"Retail Goods"
        }
    ],
    "sg:phone":"+1 603 474 3023",
    "sg:postcode":"03874",
    "sg:province":"NH",
    "sg:tags":[
        "automobile",
        "parts"
    ],
    "wof:name":"Motortown Auto Part",
    "wof:placetype":"venue"
},
  "geometry": {"coordinates":[-70.887023,42.89476],"type":"Point"}
}