{
  "type": "Feature",
  "properties": {
    "addr:full":"125 Main St Newmarket NH 03857",
    "addr:housenumber":"125",
    "addr:postcode":"03857",
    "addr:street":"Main St",
    "iso:country":"US",
    "sg:address":"125 Main St",
    "sg:city":"Newmarket",
    "sg:classifiers":[
        {
            "category":"Professional",
            "subcategory":"Management & Consulting",
            "type":"Services"
        }
    ],
    "sg:phone":"+1 603 659 0342",
    "sg:postcode":"03857",
    "sg:province":"NH",
    "wof:name":"MBI",
    "wof:placetype":"venue"
},
  "geometry": {"coordinates":[-70.93628699999999,43.078759],"type":"Point"}
}