{
  "type": "Feature",
  "properties": {
    "iso:country":"US",
    "sg:address":"11124 S Willow St",
    "sg:city":"Manchester",
    "sg:classifiers":[
        {
            "category":"Manufacturing",
            "subcategory":"Metals",
            "type":"Manufacturing & Wholesale Goods"
        }
    ],
    "sg:phone":"+1 603 621 9957",
    "sg:postcode":"03103",
    "sg:province":"NH",
    "sg:tags":[
        "equipment",
        "cryogenic",
        "supply"
    ],
    "sg:website":"www.cryoindustries.com",
    "wof:name":"Cryo Industries",
    "wof:placetype":"venue"
},
  "geometry": {"coordinates":[-71.421722,42.939657],"type":"Point"}
}