{
  "type": "Feature",
  "properties": {
    "iso:country":"US",
    "sg:address":"300 Franklin St",
    "sg:city":"Manchester",
    "sg:classifiers":[
        {
            "category":"Banks & Credit Unions",
            "subcategory":"Bank",
            "type":"Services"
        }
    ],
    "sg:phone":"+1 603 695 3481",
    "sg:postcode":"03101",
    "sg:province":"NH",
    "wof:name":"Bank Of New Hampshire",
    "wof:placetype":"venue"
},
  "geometry": {"coordinates":[-71.46426599999999,42.989544],"type":"Point"}
}