{
  "type": "Feature",
  "properties": {
    "iso:country":"US",
    "sg:address":"175 Spring Hill Rd",
    "sg:city":"Peterborough",
    "sg:classifiers":[
        {
            "category":"Health Services",
            "subcategory":"Nursing And Care Facility",
            "type":"Services"
        }
    ],
    "sg:phone":"+1 603 924 9625",
    "sg:postcode":"03458",
    "sg:province":"NH",
    "sg:tags":[
        "skilled"
    ],
    "wof:name":"Harborside Health I Corp",
    "wof:placetype":"venue"
},
  "geometry": {"coordinates":[-71.96273100000001,42.829721],"type":"Point"}
}