{
  "type": "Feature",
  "properties": {
    "iso:country":"US",
    "sg:address":"650 2nd St",
    "sg:city":"Manchester",
    "sg:classifiers":[
        {
            "category":"Retail",
            "subcategory":"Auto Repair",
            "type":"Services"
        }
    ],
    "sg:phone":"+1 603 668 5545",
    "sg:postcode":"03102",
    "sg:province":"NH",
    "sg:tags":[
        "repairing",
        "automobile",
        "general"
    ],
    "wof:name":"Jack's Gulf",
    "wof:placetype":"venue"
},
  "geometry": {"coordinates":[-71.47709999999999,42.972248],"type":"Point"}
}