{
  "type": "Feature",
  "properties": {
    "iso:country":"US",
    "sg:address":"66 Union St",
    "sg:city":"Manchester",
    "sg:classifiers":[
        {
            "category":"Food & Beverages",
            "subcategory":"Groceries & Convenience Stores",
            "type":"Retail Goods"
        }
    ],
    "sg:phone":"+1 603 625 8755",
    "sg:postcode":"03103",
    "sg:province":"NH",
    "sg:tags":[
        "supermarket"
    ],
    "wof:name":"Golombs Market Inc",
    "wof:placetype":"venue"
},
  "geometry": {"coordinates":[-71.45742199999999,42.975812],"type":"Point"}
}