{
  "type": "Feature",
  "properties": {
    "iso:country":"US",
    "sg:address":"518 N State St",
    "sg:city":"Concord",
    "sg:classifiers":[
        {
            "category":"Real Estate",
            "subcategory":"Architect",
            "type":"Services"
        }
    ],
    "sg:phone":"+1 603 224 4132",
    "sg:postcode":"03301",
    "sg:province":"NH",
    "sg:tags":[
        "planner"
    ],
    "wof:name":"Brook Design Associates Inc",
    "wof:placetype":"venue"
},
  "geometry": {"coordinates":[-71.571538,43.246823],"type":"Point"}
}