{
  "type": "Feature",
  "properties": {
    "addr:full":"71 King Dr Plainfield NH 03781",
    "addr:housenumber":"71",
    "addr:postcode":"03781",
    "addr:street":"King Dr",
    "iso:country":"US",
    "sg:address":"71 King Dr",
    "sg:city":"Plainfield",
    "sg:classifiers":[
        {
            "category":"Organizations",
            "subcategory":"Religious Organization",
            "type":"Services"
        }
    ],
    "sg:phone":"+1 603 469 3236",
    "sg:postcode":"03781",
    "sg:province":"NH",
    "sg:tags":[
        "house",
        "retreat"
    ],
    "sg:website":"www.singinghills.net",
    "wof:name":"Singing Hills Christian Flwshp",
    "wof:placetype":"venue"
},
  "geometry": {"coordinates":[-72.29740099999999,43.533629],"type":"Point"}
}