{
  "type": "Feature",
  "properties": {
    "iso:country":"US",
    "sg:address":"160 Plaistow Rd",
    "sg:city":"Plaistow",
    "sg:classifiers":[
        {
            "category":"Social Services",
            "subcategory":"Job Training",
            "type":"Services"
        },
        {
            "category":"Shopping",
            "subcategory":"Hobbies, Toys, & Games",
            "type":"Retail Goods"
        }
    ],
    "sg:phone":"+1 603 382 3700",
    "sg:postcode":"03865",
    "sg:province":"NH",
    "sg:tags":[
        "repair",
        "video",
        "games-service"
    ],
    "sg:website":"http://www.vidgameexchange.com",
    "wof:name":"Video Game Exchange",
    "wof:placetype":"venue"
},
  "geometry": {"coordinates":[-71.104471,42.84899],"type":"Point"}
}