{
  "type": "Feature",
  "properties": {
    "iso:country":"US",
    "sg:address":"2 Walker St",
    "sg:city":"Derry",
    "sg:classifiers":[
        {
            "category":"Professional",
            "subcategory":"Computer Services",
            "type":"Services"
        }
    ],
    "sg:phone":"+1 603 537 1249",
    "sg:postcode":"03038",
    "sg:province":"NH",
    "sg:tags":[
        "datum"
    ],
    "wof:name":"Naes Design",
    "wof:placetype":"venue"
},
  "geometry": {"coordinates":[-71.323971,42.870179],"type":"Point"}
}