{
  "type": "Feature",
  "properties": {
    "iso:country":"US",
    "sg:address":"92 Irene Dr",
    "sg:city":"Hollis",
    "sg:classifiers":[
        {
            "category":"Professional",
            "subcategory":"Computer Services",
            "type":"Services"
        }
    ],
    "sg:phone":"+1 603 465 6567",
    "sg:postcode":"03049",
    "sg:province":"NH",
    "sg:tags":[
        "software"
    ],
    "wof:name":"Custom Computer Solutions",
    "wof:placetype":"venue"
},
  "geometry": {"coordinates":[-71.61972900000001,42.716218],"type":"Point"}
}