{
  "type": "Feature",
  "properties": {
    "addr:full":"66 Squamscott Rd Stratham NH 03885",
    "addr:housenumber":"66",
    "addr:postcode":"03885",
    "addr:street":"Squamscott Rd",
    "iso:country":"US",
    "sg:address":"66 Squamscott Rd",
    "sg:city":"Stratham",
    "sg:classifiers":[
        {
            "category":"Wholesale",
            "subcategory":"Poultry",
            "type":"Manufacturing & Wholesale Goods"
        }
    ],
    "sg:phone":"+1 603 778 8838",
    "sg:postcode":"03885",
    "sg:province":"NH",
    "sg:tags":[
        "butter",
        "frozen",
        "eggs",
        "berry"
    ],
    "wof:name":"Wiggins Egg Services Inc",
    "wof:placetype":"venue"
},
  "geometry": {"coordinates":[-70.91885499999999,43.037324],"type":"Point"}
}