{
  "type": "Feature",
  "properties": {
    "addr:full":"376 N Main St Wolfeboro NH 03894",
    "addr:housenumber":"376",
    "addr:postcode":"03894",
    "addr:street":"N Main St",
    "iso:country":"US",
    "sg:address":"376 N Main St",
    "sg:city":"Wolfeboro",
    "sg:classifiers":[
        {
            "category":"Health Services",
            "subcategory":"Doctor",
            "type":"Services"
        }
    ],
    "sg:phone":"+1 603 569 6318",
    "sg:postcode":"03894",
    "sg:province":"NH",
    "sg:tags":[
        "medical",
        "chiropractor"
    ],
    "sg:website":"www.healingfrontiers.com",
    "wof:name":"Healing Frontiers",
    "wof:placetype":"venue"
},
  "geometry": {"coordinates":[-71.23539700000001,43.5938],"type":"Point"}
}