{
  "type": "Feature",
  "properties": {
    "iso:country":"US",
    "sg:address":"78 River Rd",
    "sg:city":"Hudson",
    "sg:classifiers":[
        {
            "category":"Wholesale",
            "subcategory":"Durable Goods & Equipment",
            "type":"Manufacturing & Wholesale Goods"
        }
    ],
    "sg:phone":"+1 603 886 9500",
    "sg:postcode":"03051",
    "sg:province":"NH",
    "sg:tags":[
        "representative",
        "manufacturer"
    ],
    "wof:name":"Eastern Marketing Assoc Inc",
    "wof:placetype":"venue"
},
  "geometry": {"coordinates":[-71.421868,42.70357],"type":"Point"}
}