{
  "type": "Feature",
  "properties": {
    "addr:full":"17 Cambridge Dr Merrimack NH 03054",
    "addr:housenumber":"17",
    "addr:postcode":"03054",
    "addr:street":"Cambridge Dr",
    "iso:country":"US",
    "sg:address":"17 Cambridge Dr",
    "sg:city":"Merrimack",
    "sg:classifiers":[
        {
            "category":"Professional",
            "type":"Services"
        }
    ],
    "sg:phone":"+1 603 424 3710",
    "sg:postcode":"03054",
    "sg:province":"NH",
    "wof:name":"David Maskiewicz",
    "wof:placetype":"venue"
},
  "geometry": {"coordinates":[-71.517122,42.820864],"type":"Point"}
}