{
  "type": "Feature",
  "properties": {
    "iso:country":"US",
    "sg:address":"788 Elm St",
    "sg:city":"Manchester",
    "sg:classifiers":[
        {
            "category":"Recreation",
            "type":"Entertainment"
        }
    ],
    "sg:phone":"+1 603 668 8880",
    "sg:postcode":"03101",
    "sg:province":"NH",
    "sg:website":"www.fronttix.com",
    "wof:name":"Front Row Ticket Agency",
    "wof:placetype":"venue"
},
  "geometry": {"coordinates":[-71.46310099999999,42.990164],"type":"Point"}
}