{
  "type": "Feature",
  "properties": {
    "iso:country":"US",
    "sg:address":"240 Wheeler Rd",
    "sg:city":"Hollis",
    "sg:classifiers":[
        {
            "category":"Professional",
            "type":"Services"
        }
    ],
    "sg:phone":"+1 603 577 9771",
    "sg:postcode":"03049",
    "sg:province":"NH",
    "wof:name":"Brook Muddy Music",
    "wof:placetype":"venue"
},
  "geometry": {"coordinates":[-71.557368,42.769085],"type":"Point"}
}