{
  "type": "Feature",
  "properties": {
    "iso:country":"US",
    "sg:address":"20 Sutton Rd",
    "sg:city":"Newbury",
    "sg:classifiers":[
        {
            "category":"Government",
            "subcategory":"Office",
            "type":"Public Place"
        }
    ],
    "sg:phone":"+1 603 938 5494",
    "sg:postcode":"03255",
    "sg:province":"NH",
    "sg:tags":[
        "village"
    ],
    "wof:name":"Newbury Highway Garage",
    "wof:placetype":"venue"
},
  "geometry": {"coordinates":[-71.991292,43.295939],"type":"Point"}
}