{
  "type": "Feature",
  "properties": {
    "addr:full":"154 Harvey Rd Londonderry NH 03053",
    "addr:housenumber":"154",
    "addr:postcode":"03053",
    "addr:street":"Harvey Rd",
    "iso:country":"US",
    "sg:address":"154 Harvey Rd",
    "sg:city":"Londonderry",
    "sg:classifiers":[
        {
            "category":"Manufacturing",
            "subcategory":"Metals",
            "type":"Manufacturing & Wholesale Goods"
        }
    ],
    "sg:phone":"+1 603 644 2500",
    "sg:postcode":"03053",
    "sg:province":"NH",
    "sg:tags":[
        "product",
        "wire",
        "fabricated"
    ],
    "sg:website":"www.wirebelt.com",
    "wof:name":"Wire Belt Co Of America",
    "wof:placetype":"venue"
},
  "geometry": {"coordinates":[-71.423906,42.925618],"type":"Point"}
}