{
  "type": "Feature",
  "properties": {
    "addr:full":"180 Washington St Dover NH 03820",
    "addr:housenumber":"180",
    "addr:postcode":"03820",
    "addr:street":"Washington St",
    "iso:country":"US",
    "sg:address":"180 Washington St",
    "sg:city":"Dover",
    "sg:classifiers":[
        {
            "category":"Banks & Credit Unions",
            "subcategory":"Bank",
            "type":"Services"
        }
    ],
    "sg:phone":"+1 603 742 6737",
    "sg:postcode":"03820",
    "sg:province":"NH",
    "sg:tags":[
        "state",
        "commercial"
    ],
    "wof:name":"Fleet",
    "wof:placetype":"venue"
},
  "geometry": {"coordinates":[-70.878895,43.194402],"type":"Point"}
}