{
  "type": "Feature",
  "properties": {
    "iso:country":"US",
    "sg:address":"155 Pleasant St",
    "sg:city":"Epping",
    "sg:classifiers":[
        {
            "category":"Manufacturing",
            "subcategory":"Signs",
            "type":"Manufacturing & Wholesale Goods"
        }
    ],
    "sg:phone":"+1 603 679 2700",
    "sg:postcode":"03042",
    "sg:province":"NH",
    "wof:name":"D T Designs Graphics",
    "wof:placetype":"venue"
},
  "geometry": {"coordinates":[-71.08990900000001,43.037509],"type":"Point"}
}