{
  "type": "Feature",
  "properties": {
    "addr:full":"522 Amherst St Nashua NH 03063",
    "addr:housenumber":"522",
    "addr:postcode":"03063",
    "addr:street":"Amherst St",
    "iso:country":"US",
    "sg:address":"522 Amherst St",
    "sg:city":"Nashua",
    "sg:classifiers":[
        {
            "category":"Autos & Motor Vehicles",
            "subcategory":"Auto Supplies",
            "type":"Retail Goods"
        }
    ],
    "sg:phone":"+1 603 249 9595",
    "sg:postcode":"03063",
    "sg:province":"NH",
    "wof:name":"50 Pro-Shop",
    "wof:placetype":"venue"
},
  "geometry": {"coordinates":[-71.525963,42.794575],"type":"Point"}
}