{
  "type": "Feature",
  "properties": {
    "iso:country":"US",
    "sg:address":"7 Perimeter Rd",
    "sg:city":"Manchester",
    "sg:phone":"+1 603 647 1000",
    "sg:postcode":"03103",
    "sg:province":"NH",
    "sg:tags":[
        "video",
        "conferencing"
    ],
    "sg:website":"www.zydacron.com",
    "wof:name":"Zydacron Inc",
    "wof:placetype":"venue"
},
  "geometry": {"coordinates":[-71.448978,42.930534],"type":"Point"}
}