{
  "type": "Feature",
  "properties": {
    "addr:full":"9 Duck Pond Way Merrimack NH 03054",
    "addr:housenumber":"9",
    "addr:postcode":"03054",
    "addr:street":"Duck Pond Way",
    "iso:country":"US",
    "sg:address":"9 Duck Pond Way",
    "sg:city":"Merrimack",
    "sg:classifiers":[
        {
            "category":"Real Estate",
            "subcategory":"Architect",
            "type":"Services"
        }
    ],
    "sg:phone":"+1 603 883 6673",
    "sg:postcode":"03054",
    "sg:province":"NH",
    "sg:tags":[
        "model",
        "architectural"
    ],
    "wof:name":"Microform Models Inc",
    "wof:placetype":"venue"
},
  "geometry": {"coordinates":[-71.491489,42.798314],"type":"Point"}
}