{
  "type": "Feature",
  "properties": {
    "iso:country":"US",
    "sg:address":"18 Pelham Rd",
    "sg:city":"Salem",
    "sg:classifiers":[
        {
            "category":"Professional",
            "subcategory":"Employment Agencies",
            "type":"Services"
        }
    ],
    "sg:phone":"+1 603 898 3000",
    "sg:postcode":"03079",
    "sg:province":"NH",
    "sg:tags":[
        "help",
        "contractor"
    ],
    "sg:website":"www.techneeds.com",
    "wof:name":"Technical Needs",
    "wof:placetype":"venue"
},
  "geometry": {"coordinates":[-71.2457,42.777049],"type":"Point"}
}