{
  "type": "Feature",
  "properties": {
    "iso:country":"US",
    "sg:address":"80 Daniel St",
    "sg:city":"Portsmouth",
    "sg:classifiers":[
        {
            "category":"Building & Trades",
            "subcategory":"Electrical",
            "type":"Services"
        }
    ],
    "sg:phone":"+1 603 431 7769",
    "sg:postcode":"03801",
    "sg:province":"NH",
    "sg:tags":[
        "electric",
        "contractor"
    ],
    "wof:name":"Mattie & O'Brien Contracting",
    "wof:placetype":"venue"
},
  "geometry": {"coordinates":[-70.755201,43.077691],"type":"Point"}
}