{
  "type": "Feature",
  "properties": {
    "iso:country":"US",
    "sg:address":"5 Woodlawn Rd",
    "sg:city":"Rochester",
    "sg:classifiers":[
        {
            "category":"Building & Trades",
            "subcategory":"Construction",
            "type":"Services"
        }
    ],
    "sg:phone":"+1 603 332 1065",
    "sg:postcode":"03867",
    "sg:province":"NH",
    "sg:tags":[
        "paving",
        "contractor"
    ],
    "wof:name":"Lilac City Paving & Slctng",
    "wof:placetype":"venue"
},
  "geometry": {"coordinates":[-70.99239900000001,43.298552],"type":"Point"}
}