{
  "type": "Feature",
  "properties": {
    "iso:country":"US",
    "sg:address":"25 Old Fremont Rd",
    "sg:city":"Raymond",
    "sg:classifiers":[
        {
            "category":"Retail",
            "subcategory":"Auto Repair",
            "type":"Services"
        }
    ],
    "sg:phone":"+1 603 895 9486",
    "sg:postcode":"03077",
    "sg:province":"NH",
    "sg:tags":[
        "repairing",
        "automobile"
    ],
    "wof:name":"Steve's Auto Clinic",
    "wof:placetype":"venue"
},
  "geometry": {"coordinates":[-71.166803,43.018828],"type":"Point"}
}