{
  "type": "Feature",
  "properties": {
    "iso:country":"US",
    "sg:address":"136 Pleasant St",
    "sg:city":"Laconia",
    "sg:classifiers":[
        {
            "category":"Organizations",
            "subcategory":"Religious Organization",
            "type":"Services"
        }
    ],
    "sg:phone":"+1 603 524 7132",
    "sg:postcode":"03246",
    "sg:province":"NH",
    "sg:tags":[
        "church"
    ],
    "wof:name":"Christian Science Church",
    "wof:placetype":"venue"
},
  "geometry": {"coordinates":[-71.474141,43.528898],"type":"Point"}
}