{
  "type": "Feature",
  "properties": {
    "iso:country":"US",
    "sg:address":"18 Eastman St",
    "sg:city":"Concord",
    "sg:classifiers":[
        {
            "category":"Government",
            "subcategory":"Office",
            "type":"Public Place"
        }
    ],
    "sg:phone":"+1 603 228 8780",
    "sg:postcode":"03301",
    "sg:province":"NH",
    "sg:tags":[
        "village"
    ],
    "wof:name":"East Concord Community Ctr",
    "wof:placetype":"venue"
},
  "geometry": {"coordinates":[-71.535256,43.235202],"type":"Point"}
}