{
  "type": "Feature",
  "properties": {
    "addr:full":"110 Spit Brook Rd Nashua NH 03062",
    "addr:housenumber":"110",
    "addr:postcode":"03062",
    "addr:street":"Spit Brook Rd",
    "iso:country":"US",
    "sg:address":"110 Spit Brook Rd",
    "sg:city":"Nashua",
    "sg:classifiers":[
        {
            "category":"Structure",
            "subcategory":"Office Building",
            "type":"Public Place"
        }
    ],
    "sg:phone":"+1 603 884 2000",
    "sg:postcode":"03062",
    "sg:province":"NH",
    "sg:tags":[
        "park"
    ],
    "sg:website":"http://www.shopatcoloniecenter.com",
    "wof:name":"Jones Lang Lasalle Americas, Inc.",
    "wof:placetype":"venue"
},
  "geometry": {"coordinates":[-71.456551,42.707895],"type":"Point"}
}