{
  "type": "Feature",
  "properties": {
    "addr:full":"54 Woodrise Rd Charlestown NH 03603",
    "addr:housenumber":"54",
    "addr:postcode":"03603",
    "addr:street":"Woodrise Rd",
    "iso:country":"US",
    "sg:address":"54 Woodrise Rd",
    "sg:city":"Charlestown",
    "sg:classifiers":[
        {
            "category":"Education",
            "subcategory":"School",
            "type":"Public Place"
        }
    ],
    "sg:phone":"+1 603 826 4348",
    "sg:postcode":"03603",
    "sg:province":"NH",
    "wof:name":"Vase Collaberative School",
    "wof:placetype":"venue"
},
  "geometry": {"coordinates":[-72.415809,43.260551],"type":"Point"}
}