{
  "type": "Feature",
  "properties": {
    "iso:country":"US",
    "sg:address":"73 Locust St",
    "sg:city":"Dover",
    "sg:classifiers":[
        {
            "category":"Education",
            "subcategory":"Library",
            "type":"Public Place"
        }
    ],
    "sg:phone":"+1 603 516 6050",
    "sg:postcode":"03820",
    "sg:province":"NH",
    "sg:website":"www.dover.lib.nh.us",
    "wof:name":"Dover City Library",
    "wof:placetype":"venue"
},
  "geometry": {"coordinates":[-70.87553699999999,43.193237],"type":"Point"}
}