{
  "type": "Feature",
  "properties": {
    "iso:country":"US",
    "sg:address":"26 S Pine St",
    "sg:city":"Dover",
    "sg:classifiers":[
        {
            "category":"Building & Trades",
            "subcategory":"Construction",
            "type":"Services"
        }
    ],
    "sg:phone":"+1 603 742 2141",
    "sg:postcode":"03820",
    "sg:province":"NH",
    "sg:tags":[
        "floor",
        "laying",
        "contractor"
    ],
    "wof:name":"Affordable Builders",
    "wof:placetype":"venue"
},
  "geometry": {"coordinates":[-70.87269000000001,43.188452],"type":"Point"}
}