{
  "type": "Feature",
  "properties": {
    "addr:full":"5 Alumni Dr Exeter NH 03833",
    "addr:housenumber":"5",
    "addr:postcode":"03833",
    "addr:street":"Alumni Dr",
    "iso:country":"US",
    "sg:address":"5 Alumni Dr",
    "sg:city":"Exeter",
    "sg:classifiers":[
        {
            "category":"Health Services",
            "subcategory":"Doctor",
            "type":"Services"
        }
    ],
    "sg:phone":"+1 603 778 6608",
    "sg:postcode":"03833",
    "sg:province":"NH",
    "sg:tags":[
        "physician",
        "surgeon"
    ],
    "wof:name":"Exter Hospital Dept Radiology",
    "wof:placetype":"venue"
},
  "geometry": {"coordinates":[-70.93388299999999,42.982119],"type":"Point"}
}