{
  "type": "Feature",
  "properties": {
    "addr:full":"5 Harvest Dr Hooksett NH 03106",
    "addr:housenumber":"5",
    "addr:postcode":"03106",
    "addr:street":"Harvest Dr",
    "iso:country":"US",
    "sg:address":"5 Harvest Dr",
    "sg:city":"Hooksett",
    "sg:classifiers":[
        {
            "category":"Personal",
            "subcategory":"Beauty Salon",
            "type":"Services"
        }
    ],
    "sg:phone":"+1 603 627 7334",
    "sg:postcode":"03106",
    "sg:province":"NH",
    "sg:tags":[
        "shop"
    ],
    "wof:name":"Ultimate Man",
    "wof:placetype":"venue"
},
  "geometry": {"coordinates":[-71.432276,43.04244],"type":"Point"}
}