{
  "type": "Feature",
  "properties": {
    "iso:country":"US",
    "sg:address":"11 Dorchester Rd",
    "sg:city":"Lyme",
    "sg:classifiers":[
        {
            "category":"Communications",
            "subcategory":"Film & Video Production",
            "type":"Services"
        }
    ],
    "sg:phone":"+1 603 795 9424",
    "sg:postcode":"03768",
    "sg:province":"NH",
    "sg:tags":[
        "motion",
        "picture"
    ],
    "wof:name":"Hollywood Script Consultant",
    "wof:placetype":"venue"
},
  "geometry": {"coordinates":[-72.15270099999999,43.809332],"type":"Point"}
}