{
  "type": "Feature",
  "properties": {
    "iso:country":"US",
    "sg:address":"10 Weeks Rd",
    "sg:city":"Gilford",
    "sg:classifiers":[
        {
            "category":"Personal",
            "subcategory":"Tattoo Parlor",
            "type":"Services"
        }
    ],
    "sg:phone":"+1 603 366 4853",
    "sg:postcode":"03249",
    "sg:province":"NH",
    "sg:tags":[
        "tattooing"
    ],
    "wof:name":"Johnny Wacko Productions",
    "wof:placetype":"venue"
},
  "geometry": {"coordinates":[-71.392779,43.535633],"type":"Point"}
}