{
  "type": "Feature",
  "properties": {
    "addr:full":"34 Franklin St Nashua NH 03064",
    "addr:housenumber":"34",
    "addr:postcode":"03064",
    "addr:street":"Franklin St",
    "iso:country":"US",
    "sg:address":"34 Franklin St",
    "sg:city":"Nashua",
    "sg:classifiers":[
        {
            "category":"Organizations",
            "subcategory":"Non-profit Organization",
            "type":"Services"
        }
    ],
    "sg:phone":"+1 603 886 7147",
    "sg:postcode":"03064",
    "sg:province":"NH",
    "wof:name":"Gate City Cdc",
    "wof:placetype":"venue"
},
  "geometry": {"coordinates":[-71.468018,42.763805],"type":"Point"}
}