{
  "type": "Feature",
  "properties": {
    "addr:full":"84 Crestwood Dr Hollis NH 03049",
    "addr:housenumber":"84",
    "addr:postcode":"03049",
    "addr:street":"Crestwood Dr",
    "iso:country":"US",
    "sg:address":"84 Crestwood Dr",
    "sg:city":"Hollis",
    "sg:classifiers":[
        {
            "category":"Health Services",
            "subcategory":"Clinic",
            "type":"Services"
        }
    ],
    "sg:phone":"+1 603 465 6996",
    "sg:postcode":"03049",
    "sg:province":"NH",
    "sg:tags":[
        "organization",
        "medical",
        "surgical"
    ],
    "wof:name":"Lifeline Lap Tops",
    "wof:placetype":"venue"
},
  "geometry": {"coordinates":[-71.55736899999999,42.74724],"type":"Point"}
}