{
  "type": "Feature",
  "properties": {
    "iso:country":"US",
    "sg:address":"1 Kinsley St",
    "sg:city":"Nashua",
    "sg:classifiers":[
        {
            "category":"Home & Garden",
            "subcategory":"Furniture",
            "type":"Retail Goods"
        }
    ],
    "sg:phone":"+1 603 880 0754",
    "sg:postcode":"03060",
    "sg:province":"NH",
    "wof:name":"Mark's Furniture & Bedding",
    "wof:placetype":"venue"
},
  "geometry": {"coordinates":[-71.464771,42.75598],"type":"Point"}
}