{
  "type": "Feature",
  "properties": {
    "iso:country":"US",
    "sg:address":"1 Winter St",
    "sg:city":"Rochester",
    "sg:classifiers":[
        {
            "category":"Autos & Motor Vehicles",
            "subcategory":"Automobile Sales",
            "type":"Retail Goods"
        }
    ],
    "sg:phone":"+1 603 330 0311",
    "sg:postcode":"03867",
    "sg:province":"NH",
    "sg:tags":[
        "car",
        "dealer"
    ],
    "wof:name":"Backdoor Auto Sales",
    "wof:placetype":"venue"
},
  "geometry": {"coordinates":[-70.972341,43.301891],"type":"Point"}
}