{
  "type": "Feature",
  "properties": {
    "iso:country":"US",
    "sg:address":"18 Highland St",
    "sg:city":"Hooksett",
    "sg:classifiers":[
        {
            "category":"Personal",
            "subcategory":"Beauty Salon",
            "type":"Services"
        }
    ],
    "sg:phone":"+1 603 485 7275",
    "sg:postcode":"03106",
    "sg:province":"NH",
    "wof:name":"Hair Contempo",
    "wof:placetype":"venue"
},
  "geometry": {"coordinates":[-71.457877,43.09977],"type":"Point"}
}