{
  "type": "Feature",
  "properties": {
    "iso:country":"US",
    "sg:address":"100 E Sutton Rd",
    "sg:city":"Warner",
    "sg:classifiers":[
        {
            "category":"Education",
            "subcategory":"Vocational School",
            "type":"Public Place"
        }
    ],
    "sg:phone":"+1 603 456 6043",
    "sg:postcode":"03278",
    "sg:province":"NH",
    "sg:tags":[
        "training",
        "computer"
    ],
    "wof:name":"DRT Computer Training",
    "wof:placetype":"venue"
},
  "geometry": {"coordinates":[-71.85548300000001,43.29527],"type":"Point"}
}