{
  "type": "Feature",
  "properties": {
    "iso:country":"US",
    "sg:address":"143 Lake St",
    "sg:city":"Laconia",
    "sg:classifiers":[
        {
            "category":"Manufacturing",
            "subcategory":"Printing",
            "type":"Manufacturing & Wholesale Goods"
        }
    ],
    "sg:phone":"+1 603 524 5679",
    "sg:postcode":"03246",
    "sg:province":"NH",
    "sg:tags":[
        "commercial"
    ],
    "wof:name":"J & J Printing Inc",
    "wof:placetype":"venue"
},
  "geometry": {"coordinates":[-71.44805100000001,43.565676],"type":"Point"}
}