{
  "type": "Feature",
  "properties": {
    "addr:full":"109 Main St Salem NH 03079",
    "addr:housenumber":"109",
    "addr:postcode":"03079",
    "addr:street":"Main St",
    "iso:country":"US",
    "sg:address":"109 Main St",
    "sg:city":"Salem",
    "sg:classifiers":[
        {
            "category":"Shopping",
            "type":"Retail Goods"
        }
    ],
    "sg:phone":"+1 603 898 3355",
    "sg:postcode":"03079",
    "sg:province":"NH",
    "sg:tags":[
        "merchandise",
        "monument"
    ],
    "wof:name":"Gate City Monument Inc II",
    "wof:placetype":"venue"
},
  "geometry": {"coordinates":[-71.228359,42.782111],"type":"Point"}
}