{
  "type": "Feature",
  "properties": {
    "iso:country":"US",
    "sg:address":"186 River Rd",
    "sg:city":"Newington",
    "sg:classifiers":[
        {
            "category":"Shopping",
            "subcategory":"Computers & Home Electronics",
            "type":"Retail Goods"
        }
    ],
    "sg:phone":"+1 603 433 8405",
    "sg:postcode":"03801",
    "sg:province":"NH",
    "sg:tags":[
        "equipment",
        "dealer"
    ],
    "sg:website":"www.elitetechnicalsolutions.com",
    "wof:name":"Elite Computer Solutions",
    "wof:placetype":"venue"
},
  "geometry": {"coordinates":[-70.81815,43.113786],"type":"Point"}
}