{
  "type": "Feature",
  "properties": {
    "iso:country":"US",
    "sg:address":"65 Main St",
    "sg:city":"New Castle",
    "sg:classifiers":[
        {
            "category":"Organizations",
            "subcategory":"Religious Organization",
            "type":"Services"
        }
    ],
    "sg:phone":"+1 603 431 8672",
    "sg:postcode":"03854",
    "sg:province":"NH",
    "sg:tags":[
        "church"
    ],
    "wof:name":"New Castle Congregational Chr",
    "wof:placetype":"venue"
},
  "geometry": {"coordinates":[-70.716645,43.071376],"type":"Point"}
}