{
  "type": "Feature",
  "properties": {
    "addr:full":"1022 Union Ave Laconia NH 03246",
    "addr:housenumber":"1022",
    "addr:postcode":"03246",
    "addr:street":"Union Ave",
    "iso:country":"US",
    "sg:address":"1022 Union Ave",
    "sg:city":"Laconia",
    "sg:classifiers":[
        {
            "category":"Retail",
            "subcategory":"Auto Repair",
            "type":"Services"
        }
    ],
    "sg:phone":"+1 603 524 2240",
    "sg:postcode":"03246",
    "sg:province":"NH",
    "sg:tags":[
        "exhaust",
        "general",
        "automotive"
    ],
    "wof:name":"Midas Muffler",
    "wof:placetype":"venue"
},
  "geometry": {"coordinates":[-71.45667400000001,43.554316],"type":"Point"}
}