{
  "type": "Feature",
  "properties": {
    "iso:country":"US",
    "sg:address":"138 Green St",
    "sg:city":"Somersworth",
    "sg:classifiers":[
        {
            "category":"Professional",
            "type":"Services"
        }
    ],
    "sg:phone":"+1 603 692 5856",
    "sg:postcode":"03878",
    "sg:province":"NH",
    "wof:name":"Two Bears Internet Svc",
    "wof:placetype":"venue"
},
  "geometry": {"coordinates":[-70.863364,43.2549],"type":"Point"}
}