{
  "type": "Feature",
  "properties": {
    "iso:country":"US",
    "sg:address":"84 Sebbins Pond Dr",
    "sg:city":"Bedford",
    "sg:classifiers":[
        {
            "category":"Manufacturing",
            "subcategory":"Printing",
            "type":"Manufacturing & Wholesale Goods"
        }
    ],
    "sg:phone":"+1 603 623 5239",
    "sg:postcode":"03110",
    "sg:province":"NH",
    "sg:tags":[
        "lithographic",
        "commercial"
    ],
    "wof:name":"RB Assoc Printing Consultants",
    "wof:placetype":"venue"
},
  "geometry": {"coordinates":[-71.47605900000001,42.927344],"type":"Point"}
}