{
  "type": "Feature",
  "properties": {
    "iso:country":"US",
    "sg:address":"4 Main St",
    "sg:city":"New Durham",
    "sg:classifiers":[
        {
            "category":"Building & Trades",
            "subcategory":"Construction",
            "type":"Services"
        }
    ],
    "sg:phone":"+1 603 859 8000",
    "sg:postcode":"03855",
    "sg:province":"NH",
    "wof:name":"New Durham Highway Dept",
    "wof:placetype":"venue"
},
  "geometry": {"coordinates":[-71.167779,43.436659],"type":"Point"}
}