{
  "type": "Feature",
  "properties": {
    "iso:country":"US",
    "sg:address":"69 Portsmouth Ave",
    "sg:city":"Stratham",
    "sg:classifiers":[
        {
            "category":"Shopping",
            "subcategory":"Hobbies, Toys, & Games",
            "type":"Retail Goods"
        }
    ],
    "sg:phone":"+1 603 772 3062",
    "sg:postcode":"03885",
    "sg:province":"NH",
    "sg:tags":[
        "shop",
        "arts",
        "gift",
        "supply",
        "craft",
        "sc"
    ],
    "wof:name":"Creative Crickett",
    "wof:placetype":"venue"
},
  "geometry": {"coordinates":[-70.919631,43.006105],"type":"Point"}
}