{
  "type": "Feature",
  "properties": {
    "iso:country":"US",
    "sg:address":"151 Kimball Hill Rd",
    "sg:city":"Hudson",
    "sg:classifiers":[
        {
            "category":"Professional",
            "type":"Services"
        }
    ],
    "sg:phone":"+1 603 886 3281",
    "sg:postcode":"03051",
    "sg:province":"NH",
    "wof:name":"F & B Winter Services LLC",
    "wof:placetype":"venue"
},
  "geometry": {"coordinates":[-71.371786,42.770617],"type":"Point"}
}