{
  "type": "Feature",
  "properties": {
    "iso:country":"US",
    "sg:address":"111 Fairview Ave",
    "sg:city":"Nashua",
    "sg:classifiers":[
        {
            "category":"Professional",
            "subcategory":"Management & Consulting",
            "type":"Services"
        }
    ],
    "sg:phone":"+1 603 880 8220",
    "sg:postcode":"03060",
    "sg:province":"NH",
    "sg:tags":[
        "business"
    ],
    "wof:name":"Baez Consultant Services",
    "wof:placetype":"venue"
},
  "geometry": {"coordinates":[-71.47983600000001,42.742887],"type":"Point"}
}