{
  "type": "Feature",
  "properties": {
    "iso:country":"US",
    "sg:address":"167 Berry Farm Rd",
    "sg:city":"Bristol",
    "sg:classifiers":[
        {
            "category":"Building & Trades",
            "subcategory":"Construction",
            "type":"Services"
        }
    ],
    "sg:phone":"+1 603 744 2812",
    "sg:postcode":"03222",
    "sg:province":"NH",
    "sg:tags":[
        "contractor"
    ],
    "wof:name":"SM Waterproofing Services",
    "wof:placetype":"venue"
},
  "geometry": {"coordinates":[-71.763835,43.568434],"type":"Point"}
}