{
  "type": "Feature",
  "properties": {
    "iso:country":"US",
    "sg:address":"15 Parker St",
    "sg:city":"Winchester",
    "sg:classifiers":[
        {
            "category":"Building & Trades",
            "subcategory":"Construction",
            "type":"Services"
        }
    ],
    "sg:phone":"+1 603 239 6510",
    "sg:postcode":"03470",
    "sg:province":"NH",
    "sg:tags":[
        "general",
        "contractor"
    ],
    "wof:name":"Benson Renovation",
    "wof:placetype":"venue"
},
  "geometry": {"coordinates":[-72.383618,42.77178],"type":"Point"}
}