{
  "type": "Feature",
  "properties": {
    "iso:country":"US",
    "sg:address":"101 Mulberry St",
    "sg:city":"Claremont",
    "sg:classifiers":[
        {
            "category":"Wholesale",
            "subcategory":"Durable Goods & Equipment",
            "type":"Manufacturing & Wholesale Goods"
        }
    ],
    "sg:phone":"+1 603 543 0038",
    "sg:postcode":"03743",
    "sg:province":"NH",
    "sg:tags":[
        "laboratory",
        "supply"
    ],
    "wof:name":"Diversified Enterprises",
    "wof:placetype":"venue"
},
  "geometry": {"coordinates":[-72.344425,43.36917],"type":"Point"}
}