{
  "type": "Feature",
  "properties": {
    "addr:full":"376 S Willow St Manchester NH 03103",
    "addr:housenumber":"376",
    "addr:postcode":"03103",
    "addr:street":"S Willow St",
    "iso:country":"US",
    "sg:address":"376 S Willow St",
    "sg:city":"Manchester",
    "sg:classifiers":[
        {
            "category":"Shopping",
            "type":"Retail Goods"
        }
    ],
    "sg:phone":"+1 603 627 9954",
    "sg:postcode":"03103",
    "sg:province":"NH",
    "sg:tags":[
        "spa",
        "hot",
        "tub"
    ],
    "wof:name":"Plain N' Fancy Spas & Whrlpls",
    "wof:placetype":"venue"
},
  "geometry": {"coordinates":[-71.45269500000001,42.969056],"type":"Point"}
}