{
  "type": "Feature",
  "properties": {
    "addr:full":"14 Hale Ave Hooksett NH 03106",
    "addr:housenumber":"14",
    "addr:postcode":"03106",
    "addr:street":"Hale Ave",
    "iso:country":"US",
    "sg:address":"14 Hale Ave",
    "sg:city":"Hooksett",
    "sg:classifiers":[
        {
            "category":"Communications",
            "type":"Services"
        }
    ],
    "sg:phone":"+1 603 624 5901",
    "sg:postcode":"03106",
    "sg:province":"NH",
    "wof:name":"Alert Electrical",
    "wof:placetype":"venue"
},
  "geometry": {"coordinates":[-71.43941599999999,43.026007],"type":"Point"}
}