{
  "type": "Feature",
  "properties": {
    "iso:country":"US",
    "sg:address":"31 Century Ln",
    "sg:city":"Litchfield",
    "sg:classifiers":[
        {
            "category":"Utilities",
            "subcategory":"Telephone",
            "type":"Services"
        }
    ],
    "sg:phone":"+1 603 424 6511",
    "sg:postcode":"03052",
    "sg:province":"NH",
    "sg:tags":[
        "telecommunication"
    ],
    "wof:name":"Americom Inc Voice & Data Syst",
    "wof:placetype":"venue"
},
  "geometry": {"coordinates":[-71.457803,42.872508],"type":"Point"}
}