{
  "type": "Feature",
  "properties": {
    "iso:country":"US",
    "sg:address":"78 Wilson St",
    "sg:city":"Manchester",
    "sg:classifiers":[
        {
            "category":"Food & Beverages",
            "subcategory":"Groceries & Convenience Stores",
            "type":"Retail Goods"
        }
    ],
    "sg:phone":"+1 603 627 4124",
    "sg:postcode":"03103",
    "sg:province":"NH",
    "wof:name":"A Vif Store",
    "wof:placetype":"venue"
},
  "geometry": {"coordinates":[-71.448302,42.974479],"type":"Point"}
}