{
  "type": "Feature",
  "properties": {
    "iso:country":"US",
    "sg:address":"9 Church St",
    "sg:city":"Amherst",
    "sg:classifiers":[
        {
            "category":"Professional",
            "subcategory":"Management & Consulting",
            "type":"Services"
        }
    ],
    "sg:phone":"+1 603 672 4329",
    "sg:postcode":"03031",
    "sg:province":"NH",
    "sg:tags":[
        "business"
    ],
    "wof:name":"Reinsurance Consult",
    "wof:placetype":"venue"
},
  "geometry": {"coordinates":[-71.62570599999999,42.86465],"type":"Point"}
}