{
  "type": "Feature",
  "properties": {
    "iso:country":"US",
    "sg:address":"4110 Teneriffe Rd",
    "sg:city":"Milton",
    "sg:classifiers":[
        {
            "category":"Manufacturing",
            "subcategory":"Building Materials",
            "type":"Manufacturing & Wholesale Goods"
        }
    ],
    "sg:phone":"+1 603 652 9357",
    "sg:postcode":"03851",
    "sg:province":"NH",
    "wof:name":"Son G Woodworking",
    "wof:placetype":"venue"
},
  "geometry": {"coordinates":[-71.00726,43.438542],"type":"Point"}
}