{
  "type": "Feature",
  "properties": {
    "addr:full":"486 White Mountain Hwy Conway NH 03860",
    "addr:housenumber":"486",
    "addr:postcode":"03860",
    "addr:street":"White Mountain Hwy",
    "iso:country":"US",
    "sg:address":"486 White Mountain Hwy",
    "sg:city":"Conway",
    "sg:classifiers":[
        {
            "category":"Home & Garden",
            "subcategory":"Home Furnishings",
            "type":"Retail Goods"
        }
    ],
    "sg:phone":"+1 603 447 6361",
    "sg:postcode":"03860",
    "sg:province":"NH",
    "sg:tags":[
        "stove",
        "wood",
        "burning"
    ],
    "wof:name":"Country Hearth & Home",
    "wof:placetype":"venue"
},
  "geometry": {"coordinates":[-71.110674,43.991839],"type":"Point"}
}