{
  "type": "Feature",
  "properties": {
    "addr:full":"48 Pine Rd Brentwood NH 03833",
    "addr:housenumber":"48",
    "addr:postcode":"03833",
    "addr:street":"Pine Rd",
    "iso:country":"US",
    "sg:address":"48 Pine Rd",
    "sg:city":"Brentwood",
    "sg:phone":"+1 603 775 0350",
    "sg:postcode":"03833",
    "sg:province":"NH",
    "sg:tags":[
        "bulk",
        "gas"
    ],
    "sg:website":"www.skaffcryogenics.com",
    "wof:name":"Skaff Cryogenics Inc",
    "wof:placetype":"venue"
},
  "geometry": {"coordinates":[-71.014696,42.99576],"type":"Point"}
}