{
  "type": "Feature",
  "properties": {
    "iso:country":"US",
    "sg:address":"63 Epping St",
    "sg:city":"Raymond",
    "sg:classifiers":[
        {
            "category":"Autos & Motor Vehicles",
            "subcategory":"Automobile Sales",
            "type":"Retail Goods"
        },
        {
            "category":"Autos & Motor Vehicles",
            "subcategory":"Motorcycle Sales",
            "type":"Retail Goods"
        }
    ],
    "sg:phone":"+1 603 895 4028",
    "sg:postcode":"03077",
    "sg:province":"NH",
    "sg:tags":[
        "salvage"
    ],
    "sg:website":"http://www.argocycles.com",
    "wof:name":"Argo Cycles, Inc.",
    "wof:placetype":"venue"
},
  "geometry": {"coordinates":[-71.170721,43.040232],"type":"Point"}
}