{
  "type": "Feature",
  "properties": {
    "addr:full":"14 Echo Ave Nashua NH 03062",
    "addr:housenumber":"14",
    "addr:postcode":"03062",
    "addr:street":"Echo Ave",
    "iso:country":"US",
    "sg:address":"14 Echo Ave",
    "sg:city":"Nashua",
    "sg:classifiers":[
        {
            "category":"Building & Trades",
            "subcategory":"Construction",
            "type":"Services"
        }
    ],
    "sg:phone":"+1 978 667 0389",
    "sg:postcode":"03062",
    "sg:province":"NH",
    "sg:tags":[
        "general",
        "contractor"
    ],
    "wof:name":"Iannelli Contractors",
    "wof:placetype":"venue"
},
  "geometry": {"coordinates":[-71.50415099999999,42.730095],"type":"Point"}
}