{
  "type": "Feature",
  "properties": {
    "iso:country":"US",
    "sg:address":"11 Larry Ln",
    "sg:city":"Portsmouth",
    "sg:classifiers":[
        {
            "category":"Manufacturing",
            "subcategory":"Textiles",
            "type":"Manufacturing & Wholesale Goods"
        },
        {
            "category":"Professional",
            "subcategory":"Business Services",
            "type":"Services"
        }
    ],
    "sg:phone":"+1 603 433 2084",
    "sg:postcode":"03801",
    "sg:province":"NH",
    "sg:tags":[
        "mfg",
        "consultant",
        "reupholstery",
        "design",
        "drapery",
        "interior",
        "decorator"
    ],
    "wof:name":"Larrys Custom Interiors Inc",
    "wof:placetype":"venue"
},
  "geometry": {"coordinates":[-70.78395399999999,43.068968],"type":"Point"}
}