{
  "type": "Feature",
  "properties": {
    "iso:country":"US",
    "sg:address":"248 Worcester Rd",
    "sg:city":"Hollis",
    "sg:classifiers":[
        {
            "category":"Restaurant",
            "type":"Food & Drink"
        }
    ],
    "sg:phone":"+1 603 465 7040",
    "sg:postcode":"03049",
    "sg:province":"NH",
    "sg:tags":[
        "eating"
    ],
    "wof:name":"Hollis Country Kitchen",
    "wof:placetype":"venue"
},
  "geometry": {"coordinates":[-71.620514,42.707369],"type":"Point"}
}