{
  "type": "Feature",
  "properties": {
    "iso:country":"US",
    "sg:address":"61 Main St",
    "sg:city":"Plymouth",
    "sg:classifiers":[
        {
            "category":"Food & Beverages",
            "subcategory":"Bakery",
            "type":"Retail Goods"
        }
    ],
    "sg:phone":"+1 603 536 2669",
    "sg:postcode":"03264",
    "sg:province":"NH",
    "sg:tags":[
        "baker"
    ],
    "wof:name":"Anderson's Bakery",
    "wof:placetype":"venue"
},
  "geometry": {"coordinates":[-71.68733,43.759715],"type":"Point"}
}