{
  "type": "Feature",
  "properties": {
    "iso:country":"US",
    "sg:address":"186 Old Henniker St",
    "sg:city":"Hillsborough",
    "sg:classifiers":[
        {
            "category":"Farming",
            "subcategory":"Aquatic Farm",
            "type":"Manufacturing & Wholesale Goods"
        }
    ],
    "sg:phone":"+1 603 464 3026",
    "sg:postcode":"03244",
    "sg:province":"NH",
    "wof:name":"Hillsborough Trout Farm",
    "wof:placetype":"venue"
},
  "geometry": {"coordinates":[-71.885471,43.137421],"type":"Point"}
}