{
  "type": "Feature",
  "properties": {
    "addr:full":"36 Church St Kingston NH 03848",
    "addr:housenumber":"36",
    "addr:postcode":"03848",
    "addr:street":"Church St",
    "iso:country":"US",
    "sg:address":"36 Church St",
    "sg:city":"Kingston",
    "sg:classifiers":[
        {
            "category":"Organizations",
            "subcategory":"Community Association",
            "type":"Services"
        }
    ],
    "sg:phone":"+1 603 642 4168",
    "sg:postcode":"03848",
    "sg:province":"NH",
    "wof:name":"Kingston Veterans Club",
    "wof:placetype":"venue"
},
  "geometry": {"coordinates":[-71.057389,42.943287],"type":"Point"}
}