{
  "type": "Feature",
  "properties": {
    "iso:country":"US",
    "sg:address":"231 Shaker Street",
    "sg:city":"North Sutton",
    "sg:classifiers":[
        {
            "category":"Professional",
            "subcategory":"Computer Services",
            "type":"Services"
        }
    ],
    "sg:phone":"+1 603 927 4266",
    "sg:postcode":"03260",
    "sg:province":"NH",
    "sg:website":"http://www.labsphere.com",
    "wof:name":"Labsphere",
    "wof:placetype":"venue"
},
  "geometry": {"coordinates":[-71.930858,43.372606],"type":"Point"}
}