{
  "type": "Feature",
  "properties": {
    "addr:full":"176 Main St Plaistow NH 03865",
    "addr:housenumber":"176",
    "addr:postcode":"03865",
    "addr:street":"Main St",
    "iso:country":"US",
    "sg:address":"176 Main St",
    "sg:city":"Plaistow",
    "sg:classifiers":[
        {
            "category":"Organizations",
            "subcategory":"Community Association",
            "type":"Services"
        }
    ],
    "sg:phone":"+1 603 382 9777",
    "sg:postcode":"03865",
    "sg:province":"NH",
    "wof:name":"American Lgn-Carl Dvis Post 34",
    "wof:placetype":"venue"
},
  "geometry": {"coordinates":[-71.10119899999999,42.843762],"type":"Point"}
}