{
  "type": "Feature",
  "properties": {
    "iso:country":"US",
    "sg:address":"64 Breakfast Hill Rd",
    "sg:city":"Greenland",
    "sg:classifiers":[
        {
            "category":"Building & Trades",
            "subcategory":"Landscaping Services",
            "type":"Services"
        }
    ],
    "sg:phone":"+1 603 436 0626",
    "sg:postcode":"03840",
    "sg:province":"NH",
    "sg:tags":[
        "landscape",
        "contractor"
    ],
    "wof:name":"Little Harbor Landscape Dsgn",
    "wof:placetype":"venue"
},
  "geometry": {"coordinates":[-70.82884900000001,43.019914],"type":"Point"}
}