{
  "type": "Feature",
  "properties": {
    "addr:full":"68 New Hampshire Ave Portsmouth NH 03801",
    "addr:housenumber":"68",
    "addr:postcode":"03801",
    "addr:street":"New Hampshire Ave",
    "iso:country":"US",
    "sg:address":"68 New Hampshire Ave",
    "sg:city":"Portsmouth",
    "sg:classifiers":[
        {
            "category":"Wholesale",
            "subcategory":"Machinery & Supplies",
            "type":"Manufacturing & Wholesale Goods"
        }
    ],
    "sg:phone":"+1 603 766 3000",
    "sg:postcode":"03801",
    "sg:province":"NH",
    "sg:tags":[
        "engine",
        "aircraft",
        "parts",
        "sup"
    ],
    "wof:name":"Britannic Aviation",
    "wof:placetype":"venue"
},
  "geometry": {"coordinates":[-70.803528,43.075162],"type":"Point"}
}