{
  "type": "Feature",
  "properties": {
    "iso:country":"US",
    "sg:address":"11 Farrwood Ln",
    "sg:city":"Hooksett",
    "sg:classifiers":[
        {
            "category":"Professional",
            "subcategory":"Business Services",
            "type":"Services"
        }
    ],
    "sg:phone":"+1 603 624 5838",
    "sg:postcode":"03106",
    "sg:province":"NH",
    "wof:name":"JSM Marketing Group",
    "wof:placetype":"venue"
},
  "geometry": {"coordinates":[-71.403318,43.066833],"type":"Point"}
}