{
  "type": "Feature",
  "properties": {
    "iso:country":"US",
    "sg:address":"134 Newton Rd Unit 11",
    "sg:city":"Plaistow",
    "sg:classifiers":[
        {
            "category":"Personal",
            "subcategory":"Massage",
            "type":"Services"
        },
        {
            "category":"Health Services",
            "subcategory":"Clinic",
            "type":"Services"
        },
        {
            "category":"Health Services",
            "subcategory":"Health Practitioner",
            "type":"Services"
        },
        {
            "category":"Health Services",
            "subcategory":"Chiropractor",
            "type":"Services"
        }
    ],
    "sg:phone":"+1 603 382 1919",
    "sg:postcode":"03865",
    "sg:province":"NH",
    "sg:tags":[
        "chiropractic",
        "therapist",
        "therapy",
        "medicine",
        "alternative",
        "physical"
    ],
    "sg:website":"http://www.newlifechiropractic.net",
    "wof:name":"New Life Chiropractic",
    "wof:placetype":"venue"
},
  "geometry": {"coordinates":[-71.056372,42.833693],"type":"Point"}
}