{
  "type": "Feature",
  "properties": {
    "addr:full":"100 Saint Anselm Dr Manchester NH 03102",
    "addr:housenumber":"100",
    "addr:postcode":"03102",
    "addr:street":"Saint Anselm Dr",
    "iso:country":"US",
    "sg:address":"100 Saint Anselm Dr",
    "sg:city":"Manchester",
    "sg:classifiers":[
        {
            "category":"Organizations",
            "subcategory":"Religious Organization",
            "type":"Services"
        }
    ],
    "sg:phone":"+1 603 641 7770",
    "sg:postcode":"03102",
    "sg:province":"NH",
    "sg:tags":[
        "monastery",
        "convent"
    ],
    "wof:name":"Sister Of Joan Of Arc",
    "wof:placetype":"venue"
},
  "geometry": {"coordinates":[-71.507261,42.987751],"type":"Point"}
}