{
  "type": "Feature",
  "properties": {
    "iso:country":"US",
    "sg:address":"231 S Main St",
    "sg:city":"Concord",
    "sg:classifiers":[
        {
            "category":"Building & Trades",
            "subcategory":"Equipment Rental",
            "type":"Services"
        }
    ],
    "sg:phone":"+1 603 224 1931",
    "sg:postcode":"03301",
    "sg:province":"NH",
    "wof:name":"Party Plus",
    "wof:placetype":"venue"
},
  "geometry": {"coordinates":[-71.531211,43.19477],"type":"Point"}
}