{
  "type": "Feature",
  "properties": {
    "iso:country":"US",
    "sg:address":"25 Julia Dr",
    "sg:city":"Hooksett",
    "sg:classifiers":[
        {
            "category":"Professional",
            "subcategory":"Research",
            "type":"Services"
        }
    ],
    "sg:phone":"+1 603 512 4618",
    "sg:postcode":"03106",
    "sg:province":"NH",
    "sg:tags":[
        "environmental",
        "ecological"
    ],
    "wof:name":"Custom Environmental Equipment",
    "wof:placetype":"venue"
},
  "geometry": {"coordinates":[-71.438081,43.060507],"type":"Point"}
}