{
  "type": "Feature",
  "properties": {
    "iso:country":"US",
    "sg:address":"23 Julia Dr",
    "sg:city":"Hooksett",
    "sg:classifiers":[
        {
            "category":"Personal",
            "type":"Services"
        }
    ],
    "sg:phone":"+1 603 641 8855",
    "sg:postcode":"03106",
    "sg:province":"NH",
    "sg:tags":[
        "repair"
    ],
    "wof:name":"Robintons Repair & Renovation",
    "wof:placetype":"venue"
},
  "geometry": {"coordinates":[-71.438107,43.060621],"type":"Point"}
}