{
  "type": "Feature",
  "properties": {
    "iso:country":"US",
    "sg:address":"310 Daniel Webster Hwy",
    "sg:city":"Nashua",
    "sg:classifiers":[
        {
            "category":"Utilities",
            "subcategory":"Mobile Phone",
            "type":"Services"
        }
    ],
    "sg:phone":"+1 603 888 5561",
    "sg:postcode":"03060",
    "sg:province":"NH",
    "sg:tags":[
        "telephone",
        "cellular"
    ],
    "wof:name":"Nextel Communications Inc",
    "wof:placetype":"venue"
},
  "geometry": {"coordinates":[-71.440764,42.702758],"type":"Point"}
}