{
  "type": "Feature",
  "properties": {
    "iso:country":"US",
    "sg:address":"10 Epping St",
    "sg:city":"Raymond",
    "sg:classifiers":[
        {
            "category":"Shopping",
            "subcategory":"Gifts & Souvenirs",
            "type":"Retail Goods"
        }
    ],
    "sg:phone":"+1 603 895 3355",
    "sg:postcode":"03077",
    "sg:province":"NH",
    "sg:tags":[
        "collectible"
    ],
    "wof:name":"Bill & Chuck's Nascar Clctbls",
    "wof:placetype":"venue"
},
  "geometry": {"coordinates":[-71.181704,43.036086],"type":"Point"}
}