{
  "type": "Feature",
  "properties": {
    "iso:country":"US",
    "sg:address":"29 Kinsley St",
    "sg:city":"Nashua",
    "sg:classifiers":[
        {
            "category":"Professional",
            "type":"Services"
        }
    ],
    "sg:phone":"+1 603 598 2544",
    "sg:postcode":"03060",
    "sg:province":"NH",
    "sg:tags":[
        "establishment"
    ],
    "wof:name":"Nashua Family Shelter",
    "wof:placetype":"venue"
},
  "geometry": {"coordinates":[-71.46629299999999,42.755424],"type":"Point"}
}