{
  "type": "Feature",
  "properties": {
    "addr:full":"1 Harbour Place Suite 1100 Portsmouth NH 03801",
    "addr:housenumber":"1",
    "addr:postcode":"03801",
    "addr:street":"Harbour Place Suite 1100",
    "iso:country":"US",
    "sg:address":"1 Harbour Place Suite 1100",
    "sg:city":"Portsmouth",
    "sg:classifiers":[
        {
            "category":"Professional",
            "subcategory":"Computer Services",
            "type":"Services"
        }
    ],
    "sg:phone":"+1 603 766 1160",
    "sg:postcode":"03801",
    "sg:province":"NH",
    "sg:website":"http://www.trunity.com/",
    "wof:name":"Trunity",
    "wof:placetype":"venue"
},
  "geometry": {"coordinates":[-70.753687,43.078133],"type":"Point"}
}