{
  "type": "Feature",
  "properties": {
    "iso:country":"US",
    "sg:address":"9 Washington St",
    "sg:city":"Conway",
    "sg:classifiers":[
        {
            "category":"Food & Beverages",
            "subcategory":"Liquor & Beverages",
            "type":"Retail Goods"
        }
    ],
    "sg:phone":"+1 603 447 2782",
    "sg:postcode":"03818",
    "sg:province":"NH",
    "wof:name":"New Hampshire State Liquor",
    "wof:placetype":"venue"
},
  "geometry": {"coordinates":[-71.118447,43.978775],"type":"Point"}
}