{
  "type": "Feature",
  "properties": {
    "iso:country":"US",
    "sg:address":"69 Meadowbrook Dr",
    "sg:city":"Milford",
    "sg:classifiers":[
        {
            "category":"Manufacturing",
            "subcategory":"Metals",
            "type":"Manufacturing & Wholesale Goods"
        }
    ],
    "sg:phone":"+1 603 673 6183",
    "sg:postcode":"03055",
    "sg:province":"NH",
    "sg:tags":[
        "machine",
        "screw",
        "product",
        "mfg"
    ],
    "wof:name":"Kerk Motion Products Inc",
    "wof:placetype":"venue"
},
  "geometry": {"coordinates":[-71.703981,42.838777],"type":"Point"}
}