{
  "type": "Feature",
  "properties": {
    "iso:country":"US",
    "sg:address":"10 Knoll Ave",
    "sg:city":"Keene",
    "sg:classifiers":[
        {
            "category":"Insurance",
            "subcategory":"Insurance Agent",
            "type":"Services"
        }
    ],
    "sg:phone":"+1 603 352 9711",
    "sg:postcode":"03431",
    "sg:province":"NH",
    "sg:tags":[
        "consultant"
    ],
    "wof:name":"W J Cox Assocs Inc",
    "wof:placetype":"venue"
},
  "geometry": {"coordinates":[-72.289986,42.952254],"type":"Point"}
}