{
  "type": "Feature",
  "properties": {
    "iso:country":"US",
    "sg:address":"456 Laconia Rd",
    "sg:city":"Tilton",
    "sg:classifiers":[
        {
            "category":"Shopping",
            "subcategory":"Used Merchandise",
            "type":"Retail Goods"
        }
    ],
    "sg:phone":"+1 603 527 9444",
    "sg:postcode":"03276",
    "sg:province":"NH",
    "sg:tags":[
        "antique"
    ],
    "wof:name":"Belknap Antiques Marketplace",
    "wof:placetype":"venue"
},
  "geometry": {"coordinates":[-71.54309600000001,43.475271],"type":"Point"}
}