{
  "type": "Feature",
  "properties": {
    "addr:full":"294 Dover Point Rd Dover NH 03820",
    "addr:housenumber":"294",
    "addr:postcode":"03820",
    "addr:street":"Dover Point Rd",
    "iso:country":"US",
    "sg:address":"294 Dover Point Rd",
    "sg:city":"Dover",
    "sg:classifiers":[
        {
            "category":"Organizations",
            "subcategory":"Religious Organization",
            "type":"Services"
        }
    ],
    "sg:phone":"+1 603 749 3251",
    "sg:postcode":"03820",
    "sg:province":"NH",
    "sg:tags":[
        "church"
    ],
    "wof:name":"Christ The Healer Fellowship",
    "wof:placetype":"venue"
},
  "geometry": {"coordinates":[-70.83569,43.133922],"type":"Point"}
}