{
  "type": "Feature",
  "properties": {
    "addr:full":"198 Wakefield St Rochester NH 03867",
    "addr:housenumber":"198",
    "addr:postcode":"03867",
    "addr:street":"Wakefield St",
    "iso:country":"US",
    "sg:address":"198 Wakefield St",
    "sg:city":"Rochester",
    "sg:classifiers":[
        {
            "category":"Restaurant",
            "type":"Food & Drink"
        }
    ],
    "sg:menulink":"http://www.allmenus.com/nh/rochester/181639-wendys/menu/",
    "sg:phone":"+1 603 332 5975",
    "sg:postcode":"03867",
    "sg:province":"NH",
    "sg:tags":[
        "burger",
        "american",
        "soup"
    ],
    "wof:name":"Wendy's",
    "wof:placetype":"venue"
},
  "geometry": {"coordinates":[-70.977465,43.313224],"type":"Point"}
}