{
  "type": "Feature",
  "properties": {
    "iso:country":"US",
    "sg:address":"36 Carpenter St",
    "sg:city":"Keene",
    "sg:classifiers":[
        {
            "category":"Building & Trades",
            "subcategory":"Construction",
            "type":"Services"
        }
    ],
    "sg:phone":"+1 603 352 7243",
    "sg:postcode":"03431",
    "sg:province":"NH",
    "sg:tags":[
        "insulation",
        "heat",
        "contractor"
    ],
    "wof:name":"J A Jubb Co",
    "wof:placetype":"venue"
},
  "geometry": {"coordinates":[-72.270264,42.932462],"type":"Point"}
}