{
  "type": "Feature",
  "properties": {
    "iso:country":"US",
    "sg:address":"130 Spit Brook Rd",
    "sg:city":"Nashua",
    "sg:classifiers":[
        {
            "category":"Organizations",
            "subcategory":"Religious Organization",
            "type":"Services"
        }
    ],
    "sg:phone":"+1 603 888 7579",
    "sg:postcode":"03062",
    "sg:province":"NH",
    "sg:website":"www.glcmsnh.org",
    "wof:name":"Grace Lutheran Church",
    "wof:placetype":"venue"
},
  "geometry": {"coordinates":[-71.465397,42.708701],"type":"Point"}
}