{
  "type": "Feature",
  "properties": {
    "iso:country":"US",
    "sg:address":"1139 Bound Tree Rd",
    "sg:city":"Hopkinton",
    "sg:classifiers":[
        {
            "category":"Building & Trades",
            "subcategory":"Construction",
            "type":"Services"
        }
    ],
    "sg:phone":"+1 603 746 5851",
    "sg:postcode":"03229",
    "sg:province":"NH",
    "sg:tags":[
        "contractor"
    ],
    "wof:name":"Romeo R Dubreuil Builder",
    "wof:placetype":"venue"
},
  "geometry": {"coordinates":[-71.75532200000001,43.225265],"type":"Point"}
}