{
  "type": "Feature",
  "properties": {
    "iso:country":"US",
    "sg:address":"404 S Main St",
    "sg:city":"Wolfeboro",
    "sg:classifiers":[
        {
            "category":"Education",
            "subcategory":"School",
            "type":"Public Place"
        }
    ],
    "sg:phone":"+1 603 569 3689",
    "sg:postcode":"03894",
    "sg:province":"NH",
    "wof:name":"Kingswood Middle School",
    "wof:placetype":"venue"
},
  "geometry": {"coordinates":[-71.190428,43.574976],"type":"Point"}
}