{
  "type": "Feature",
  "properties": {
    "iso:country":"US",
    "sg:address":"165 Hampstead Rd",
    "sg:city":"Derry",
    "sg:classifiers":[
        {
            "category":"Real Estate",
            "subcategory":"Real Estate Services",
            "type":"Services"
        },
        {
            "category":"Home & Garden",
            "subcategory":"Hardware",
            "type":"Retail Goods"
        }
    ],
    "sg:phone":"+1 603 434 0574",
    "sg:postcode":"03038",
    "sg:province":"NH",
    "sg:tags":[
        "measuring",
        "device",
        "gage",
        "gauge"
    ],
    "sg:website":"http://www.visualeffectsconstruction.com",
    "wof:name":"Visual Effects Construction, LLC",
    "wof:placetype":"venue"
},
  "geometry": {"coordinates":[-71.261675,42.898842],"type":"Point"}
}