{
  "type": "Feature",
  "properties": {
    "iso:country":"US",
    "sg:address":"87 Hitching Post Ln",
    "sg:city":"Bedford",
    "sg:classifiers":[
        {
            "category":"Professional",
            "subcategory":"Management & Consulting",
            "type":"Services"
        }
    ],
    "sg:phone":"+1 603 472 4949",
    "sg:postcode":"03110",
    "sg:province":"NH",
    "sg:tags":[
        "business"
    ],
    "wof:name":"College Advisory Service",
    "wof:placetype":"venue"
},
  "geometry": {"coordinates":[-71.533629,42.937114],"type":"Point"}
}