{
  "type": "Feature",
  "properties": {
    "addr:full":"327 Broad St Hollis NH 03049",
    "addr:housenumber":"327",
    "addr:postcode":"03049",
    "addr:street":"Broad St",
    "iso:country":"US",
    "sg:address":"327 Broad St",
    "sg:city":"Hollis",
    "sg:classifiers":[
        {
            "category":"Building & Trades",
            "subcategory":"Landscaping Services",
            "type":"Services"
        }
    ],
    "sg:phone":"+1 603 598 5353",
    "sg:postcode":"03049",
    "sg:province":"NH",
    "sg:tags":[
        "lawn",
        "maintenance",
        "grounds"
    ],
    "wof:name":"Lawn Systems Inc",
    "wof:placetype":"venue"
},
  "geometry": {"coordinates":[-71.533686,42.745345],"type":"Point"}
}