{
  "type": "Feature",
  "properties": {
    "iso:country":"US",
    "sg:address":"13 Foxboro St",
    "sg:city":"Nashua",
    "sg:classifiers":[
        {
            "category":"Manufacturing",
            "subcategory":"Wood Products",
            "type":"Manufacturing & Wholesale Goods"
        }
    ],
    "sg:phone":"+1 603 883 1114",
    "sg:postcode":"03063",
    "sg:province":"NH",
    "sg:tags":[
        "millwork-wholesale",
        "millwork",
        "manufacturer"
    ],
    "wof:name":"Bt Woodworking",
    "wof:placetype":"venue"
},
  "geometry": {"coordinates":[-71.520309,42.745571],"type":"Point"}
}