{
  "type": "Feature",
  "properties": {
    "iso:country":"US",
    "sg:address":"252 Messer St",
    "sg:city":"Laconia",
    "sg:classifiers":[
        {
            "category":"Building & Trades",
            "subcategory":"Plumbing",
            "type":"Services"
        }
    ],
    "sg:phone":"+1 603 524 6700",
    "sg:postcode":"03246",
    "sg:province":"NH",
    "sg:tags":[
        "heating",
        "co",
        "system",
        "contractor",
        "warm",
        "conditioning",
        "air"
    ],
    "wof:name":"Dutile Refrigeration Co",
    "wof:placetype":"venue"
},
  "geometry": {"coordinates":[-71.46674,43.53776],"type":"Point"}
}