{
  "type": "Feature",
  "properties": {
    "addr:full":"9 Smoke St Nottingham NH 03290",
    "addr:housenumber":"9",
    "addr:postcode":"03290",
    "addr:street":"Smoke St",
    "iso:country":"US",
    "sg:address":"9 Smoke St",
    "sg:city":"Nottingham",
    "sg:classifiers":[
        {
            "category":"Manufacturing",
            "subcategory":"Tools & Machinery",
            "type":"Manufacturing & Wholesale Goods"
        }
    ],
    "sg:phone":"+1 603 679 5290",
    "sg:postcode":"03290",
    "sg:province":"NH",
    "sg:tags":[
        "shop",
        "job"
    ],
    "wof:name":"Dg Machine",
    "wof:placetype":"venue"
},
  "geometry": {"coordinates":[-71.05949699999999,43.119447],"type":"Point"}
}