{
  "type": "Feature",
  "properties": {
    "addr:full":"9 Old Lake Shore Rd Gilford NH 03249",
    "addr:housenumber":"9",
    "addr:postcode":"03249",
    "addr:street":"Old Lake Shore Rd",
    "iso:country":"US",
    "sg:address":"9 Old Lake Shore Rd",
    "sg:city":"Gilford",
    "sg:classifiers":[
        {
            "category":"Food & Beverages",
            "subcategory":"Liquor & Beverages",
            "type":"Retail Goods"
        }
    ],
    "sg:phone":"+1 603 524 6083",
    "sg:postcode":"03249",
    "sg:province":"NH",
    "wof:name":"Gilford Liquor Store 56",
    "wof:placetype":"venue"
},
  "geometry": {"coordinates":[-71.427993,43.566799],"type":"Point"}
}