{
  "type": "Feature",
  "properties": {
    "iso:country":"US",
    "sg:address":"85 Watts St",
    "sg:city":"Manchester",
    "sg:classifiers":[
        {
            "category":"Utilities",
            "subcategory":"Telephone",
            "type":"Services"
        }
    ],
    "sg:phone":"+1 603 627 1579",
    "sg:postcode":"03104",
    "sg:province":"NH",
    "sg:tags":[
        "telecommunication"
    ],
    "wof:name":"Ouellett Communication Inc",
    "wof:placetype":"venue"
},
  "geometry": {"coordinates":[-71.426924,42.99649],"type":"Point"}
}