{
  "type": "Feature",
  "properties": {
    "addr:full":"59 Deerfield Turn Laconia NH 03246",
    "addr:housenumber":"59",
    "addr:postcode":"03246",
    "addr:street":"Deerfield Turn",
    "iso:country":"US",
    "sg:address":"59 Deerfield Turn",
    "sg:city":"Laconia",
    "sg:classifiers":[
        {
            "category":"Building & Trades",
            "subcategory":"Landscaping Services",
            "type":"Services"
        }
    ],
    "sg:phone":"+1 603 524 0330",
    "sg:postcode":"03246",
    "sg:province":"NH",
    "sg:tags":[
        "landscape",
        "contractor"
    ],
    "wof:name":"Lakes Region Design Group",
    "wof:placetype":"venue"
},
  "geometry": {"coordinates":[-71.473353,43.58558],"type":"Point"}
}