{
  "type": "Feature",
  "properties": {
    "addr:full":"48 Shaker Rd Belmont NH 03220",
    "addr:housenumber":"48",
    "addr:postcode":"03220",
    "addr:street":"Shaker Rd",
    "iso:country":"US",
    "sg:address":"48 Shaker Rd",
    "sg:city":"Belmont",
    "sg:classifiers":[
        {
            "category":"Social Services",
            "subcategory":"Adult Care",
            "type":"Services"
        }
    ],
    "sg:phone":"+1 603 267 8801",
    "sg:postcode":"03220",
    "sg:province":"NH",
    "sg:tags":[
        "organization",
        "senior",
        "citizen"
    ],
    "wof:name":"Belmont Elderly Housing Inc",
    "wof:placetype":"venue"
},
  "geometry": {"coordinates":[-71.48599299999999,43.437802],"type":"Point"}
}