{
  "type": "Feature",
  "properties": {
    "iso:country":"US",
    "sg:address":"16 Hale St",
    "sg:city":"Guild",
    "sg:classifiers":[
        {
            "category":"Personal",
            "subcategory":"Barber",
            "type":"Services"
        }
    ],
    "sg:phone":"+1 603 863 5895",
    "sg:postcode":"03773",
    "sg:province":"NH",
    "sg:tags":[
        "shop"
    ],
    "wof:name":"Guild Family Haircuts",
    "wof:placetype":"venue"
},
  "geometry": {"coordinates":[-72.14012700000001,43.378085],"type":"Point"}
}