{
  "type": "Feature",
  "properties": {
    "addr:full":"346 Lakeshore Dr Franklin NH 03235",
    "addr:housenumber":"346",
    "addr:postcode":"03235",
    "addr:street":"Lakeshore Dr",
    "iso:country":"US",
    "sg:address":"346 Lakeshore Dr",
    "sg:city":"Franklin",
    "sg:classifiers":[
        {
            "category":"Building & Trades",
            "subcategory":"Construction",
            "type":"Services"
        }
    ],
    "sg:phone":"+1 603 934 3853",
    "sg:postcode":"03235",
    "sg:province":"NH",
    "sg:tags":[
        "excavation",
        "snowplowing",
        "contractor"
    ],
    "wof:name":"Victor Virgin Cnstr Corp",
    "wof:placetype":"venue"
},
  "geometry": {"coordinates":[-71.69959,43.473451],"type":"Point"}
}