{
  "type": "Feature",
  "properties": {
    "addr:full":"686 Washington Rd Goshen NH 03752",
    "addr:housenumber":"686",
    "addr:postcode":"03752",
    "addr:street":"Washington Rd",
    "iso:country":"US",
    "sg:address":"686 Washington Rd",
    "sg:city":"Goshen",
    "sg:classifiers":[
        {
            "category":"Travel",
            "subcategory":"Hotels & Motels",
            "type":"Entertainment"
        }
    ],
    "sg:phone":"+1 603 863 1019",
    "sg:postcode":"03752",
    "sg:province":"NH",
    "sg:tags":[
        "breakfast",
        "accommodation",
        "bed"
    ],
    "sg:website":"www.cuttersloft.com",
    "wof:name":"Cutter's Loft Bed & Breakfast",
    "wof:placetype":"venue"
},
  "geometry": {"coordinates":[-72.12363499999999,43.271711],"type":"Point"}
}