{
  "type": "Feature",
  "properties": {
    "iso:country":"US",
    "sg:address":"115 Main St",
    "sg:city":"Suncook",
    "sg:classifiers":[
        {
            "category":"Restaurant",
            "type":"Food & Drink"
        }
    ],
    "sg:phone":"+1 603 485 2818",
    "sg:postcode":"03275",
    "sg:province":"NH",
    "sg:tags":[
        "eating"
    ],
    "wof:name":"Golden Jade Inc",
    "wof:placetype":"venue"
},
  "geometry": {"coordinates":[-71.452913,43.130566],"type":"Point"}
}