{
  "type": "Feature",
  "properties": {
    "iso:country":"US",
    "sg:address":"456 Brackett Rd",
    "sg:city":"Sanbornville",
    "sg:classifiers":[
        {
            "category":"Building & Trades",
            "subcategory":"Construction",
            "type":"Services"
        }
    ],
    "sg:phone":"+1 603 522 8332",
    "sg:postcode":"03872",
    "sg:province":"NH",
    "sg:tags":[
        "house"
    ],
    "wof:name":"Marjen Construction Co Inc",
    "wof:placetype":"venue"
},
  "geometry": {"coordinates":[-70.99856699999999,43.546052],"type":"Point"}
}