{
  "type": "Feature",
  "properties": {
    "addr:full":"50 Reservoir Rd Meredith NH 03253",
    "addr:housenumber":"50",
    "addr:postcode":"03253",
    "addr:street":"Reservoir Rd",
    "iso:country":"US",
    "sg:address":"50 Reservoir Rd",
    "sg:city":"Meredith",
    "sg:classifiers":[
        {
            "category":"Shopping",
            "subcategory":"Hobbies, Toys, & Games",
            "type":"Retail Goods"
        }
    ],
    "sg:phone":"+1 603 279 6542",
    "sg:postcode":"03253",
    "sg:province":"NH",
    "sg:tags":[
        "doll"
    ],
    "sg:website":"www.annaleegiftshop.com",
    "wof:name":"Annalee's Doll Museum-Society",
    "wof:placetype":"venue"
},
  "geometry": {"coordinates":[-71.50045299999999,43.641332],"type":"Point"}
}