{
  "type": "Feature",
  "properties": {
    "iso:country":"US",
    "sg:address":"10 Bancroft Rd",
    "sg:city":"Newton",
    "sg:classifiers":[
        {
            "category":"Building & Trades",
            "subcategory":"Construction",
            "type":"Services"
        }
    ],
    "sg:phone":"+1 603 382 0380",
    "sg:postcode":"03858",
    "sg:province":"NH",
    "sg:tags":[
        "contractor"
    ],
    "wof:name":"Twisted 2 Stroke Winter Motors",
    "wof:placetype":"venue"
},
  "geometry": {"coordinates":[-71.019299,42.866687],"type":"Point"}
}