{
  "type": "Feature",
  "properties": {
    "iso:country":"US",
    "sg:address":"860 Lafayette Rd",
    "sg:city":"Hampton",
    "sg:classifiers":[
        {
            "category":"Personal",
            "subcategory":"Beauty Salon",
            "type":"Services"
        }
    ],
    "sg:phone":"+1 603 926 5467",
    "sg:postcode":"03842",
    "sg:province":"NH",
    "sg:tags":[
        "hair",
        "styling"
    ],
    "wof:name":"Shapely Shapers",
    "wof:placetype":"venue"
},
  "geometry": {"coordinates":[-70.833079,42.954072],"type":"Point"}
}