{
  "type": "Feature",
  "properties": {
    "iso:country":"US",
    "sg:address":"286 Portsmouth Ave",
    "sg:city":"Seabrook",
    "sg:classifiers":[
        {
            "category":"Building & Trades",
            "subcategory":"Construction",
            "type":"Services"
        }
    ],
    "sg:phone":"+1 603 474 1440",
    "sg:postcode":"03874",
    "sg:province":"NH",
    "sg:tags":[
        "contractor"
    ],
    "wof:name":"MCL Contracting Corp",
    "wof:placetype":"venue"
},
  "geometry": {"coordinates":[-70.817403,42.890197],"type":"Point"}
}