{
  "type": "Feature",
  "properties": {
    "iso:country":"US",
    "sg:address":"23 Forest Lake Rd",
    "sg:city":"Winchester",
    "sg:classifiers":[
        {
            "category":"Government",
            "subcategory":"Office",
            "type":"Public Place"
        }
    ],
    "sg:phone":"+1 603 239 8136",
    "sg:postcode":"03470",
    "sg:province":"NH",
    "sg:tags":[
        "village"
    ],
    "wof:name":"Winchester Landfill",
    "wof:placetype":"venue"
},
  "geometry": {"coordinates":[-72.37248700000001,42.769417],"type":"Point"}
}