{
  "type": "Feature",
  "properties": {
    "iso:country":"US",
    "sg:address":"175 Ledge St",
    "sg:city":"Nashua",
    "sg:classifiers":[
        {
            "category":"Manufacturing",
            "subcategory":"Tools & Machinery",
            "type":"Manufacturing & Wholesale Goods"
        }
    ],
    "sg:phone":"+1 603 889 5152",
    "sg:postcode":"03060",
    "sg:province":"NH",
    "sg:tags":[
        "equipment",
        "computer",
        "electronic",
        "calculating",
        "mfg"
    ],
    "wof:name":"Fasfax",
    "wof:placetype":"venue"
},
  "geometry": {"coordinates":[-71.485446,42.754522],"type":"Point"}
}