{
  "type": "Feature",
  "properties": {
    "addr:full":"822 Lafayette Rd Hampton NH 03842",
    "addr:housenumber":"822",
    "addr:postcode":"03842",
    "iso:country":"US",
    "sg:address":"822 Lafayette Rd",
    "sg:city":"Hampton",
    "sg:classifiers":[
        {
            "category":"Restaurant",
            "type":"Food & Drink"
        }
    ],
    "sg:phone":"+1 603 929 9966",
    "sg:postcode":"03842",
    "sg:province":"NH",
    "sg:tags":[
        "eating"
    ],
    "wof:name":"Ronz",
    "wof:placetype":"venue"
},
  "geometry": {"coordinates":[-70.832503,42.95184],"type":"Point"}
}