{
  "type": "Feature",
  "properties": {
    "iso:country":"US",
    "sg:address":"308 River Rd",
    "sg:city":"Weare",
    "sg:classifiers":[
        {
            "category":"Manufacturing",
            "subcategory":"Tools & Machinery",
            "type":"Manufacturing & Wholesale Goods"
        }
    ],
    "sg:phone":"+1 603 529 4695",
    "sg:postcode":"03281",
    "sg:province":"NH",
    "sg:tags":[
        "machine",
        "mfg",
        "accessory"
    ],
    "wof:name":"Easternson Machine",
    "wof:placetype":"venue"
},
  "geometry": {"coordinates":[-71.65079299999999,43.055291],"type":"Point"}
}