{
  "type": "Feature",
  "properties": {
    "iso:country":"US",
    "sg:address":"99 S Broadway",
    "sg:city":"Salem",
    "sg:classifiers":[
        {
            "category":"Personal",
            "subcategory":"Tattoo Parlor",
            "type":"Services"
        }
    ],
    "sg:phone":"+1 603 890 8779",
    "sg:postcode":"03079",
    "sg:province":"NH",
    "sg:tags":[
        "tattooing"
    ],
    "wof:name":"Brothers Too Tattoo Emporium",
    "wof:placetype":"venue"
},
  "geometry": {"coordinates":[-71.221065,42.770196],"type":"Point"}
}