{
  "type": "Feature",
  "properties": {
    "addr:full":"460 State Rte 101 Bedford NH 03110",
    "addr:housenumber":"460",
    "addr:postcode":"03110",
    "addr:street":"State Rte 101",
    "iso:country":"US",
    "sg:address":"460 State Rte 101",
    "sg:city":"Bedford",
    "sg:classifiers":[
        {
            "category":"Building & Trades",
            "subcategory":"Plumbing",
            "type":"Services"
        }
    ],
    "sg:phone":"+1 603 352 5254",
    "sg:postcode":"03110",
    "sg:province":"NH",
    "sg:tags":[
        "system",
        "heating",
        "air",
        "ventilation",
        "conditioning",
        "contractor"
    ],
    "sg:website":"www.precisiontempcontrol.com",
    "wof:name":"Precision Temperature Control",
    "wof:placetype":"venue"
},
  "geometry": {"coordinates":[-71.553606,42.912944],"type":"Point"}
}