{
  "type": "Feature",
  "properties": {
    "iso:country":"US",
    "sg:address":"66 Kings Hwy",
    "sg:city":"Middleton",
    "sg:classifiers":[
        {
            "category":"Retail",
            "subcategory":"Auto Repair",
            "type":"Services"
        }
    ],
    "sg:phone":"+1 603 473 2285",
    "sg:postcode":"03887",
    "sg:province":"NH",
    "sg:tags":[
        "body",
        "automobile",
        "painting"
    ],
    "wof:name":"Todd's Collision Repair",
    "wof:placetype":"venue"
},
  "geometry": {"coordinates":[-71.061491,43.470676],"type":"Point"}
}