{
  "type": "Feature",
  "properties": {
    "addr:full":"251 Concord Rd Northfield NH 03276",
    "addr:housenumber":"251",
    "addr:postcode":"03276",
    "addr:street":"Concord Rd",
    "iso:country":"US",
    "sg:address":"251 Concord Rd",
    "sg:city":"Northfield",
    "sg:classifiers":[
        {
            "category":"Building & Trades",
            "subcategory":"Cleaning & Sanitation",
            "type":"Services"
        }
    ],
    "sg:phone":"+1 603 286 3064",
    "sg:postcode":"03276",
    "sg:province":"NH",
    "sg:tags":[
        "carpet"
    ],
    "wof:name":"Rowe Daryl A",
    "wof:placetype":"venue"
},
  "geometry": {"coordinates":[-71.598099,43.4081],"type":"Point"}
}