{
  "type": "Feature",
  "properties": {
    "iso:country":"US",
    "sg:address":"4 Heritage Hill Rd",
    "sg:city":"Center Conway",
    "sg:classifiers":[
        {
            "category":"Building & Trades",
            "subcategory":"Construction",
            "type":"Services"
        }
    ],
    "sg:phone":"+1 603 939 2911",
    "sg:postcode":"03813",
    "sg:province":"NH",
    "sg:tags":[
        "contractor"
    ],
    "wof:name":"Heritage Services Building & Excavation",
    "wof:placetype":"venue"
},
  "geometry": {"coordinates":[-71.051804,44.0145],"type":"Point"}
}