{
  "type": "Feature",
  "properties": {
    "iso:country":"US",
    "sg:address":"4 Plaistow Rd",
    "sg:city":"Plaistow",
    "sg:classifiers":[
        {
            "category":"Banks & Credit Unions",
            "subcategory":"Bank",
            "type":"Services"
        }
    ],
    "sg:phone":"+1 603 382 8410",
    "sg:postcode":"03865",
    "sg:province":"NH",
    "sg:tags":[
        "loan"
    ],
    "wof:name":"Stateline Equity Partners",
    "wof:placetype":"venue"
},
  "geometry": {"coordinates":[-71.102779,42.814727],"type":"Point"}
}