{
  "type": "Feature",
  "properties": {
    "addr:full":"10 Dodge Hill Rd Henniker NH 03242",
    "addr:housenumber":"10",
    "addr:postcode":"03242",
    "addr:street":"Dodge Hill Rd",
    "iso:country":"US",
    "sg:address":"10 Dodge Hill Rd",
    "sg:city":"Henniker",
    "sg:classifiers":[
        {
            "category":"Manufacturing",
            "subcategory":"Metals",
            "type":"Manufacturing & Wholesale Goods"
        }
    ],
    "sg:phone":"+1 603 428 3505",
    "sg:postcode":"03242",
    "sg:province":"NH",
    "sg:tags":[
        "tool",
        "mfg"
    ],
    "wof:name":"A S Hadley & Co",
    "wof:placetype":"venue"
},
  "geometry": {"coordinates":[-71.7856,43.186465],"type":"Point"}
}