{
  "type": "Feature",
  "properties": {
    "iso:country":"US",
    "sg:address":"175 W Main St",
    "sg:city":"Conway",
    "sg:classifiers":[
        {
            "category":"Government",
            "subcategory":"Post Office",
            "type":"Public Place"
        }
    ],
    "sg:phone":"+1 603 447 5160",
    "sg:postcode":"03818",
    "sg:province":"NH",
    "wof:name":"US Post Office",
    "wof:placetype":"venue"
},
  "geometry": {"coordinates":[-71.13058700000001,43.976008],"type":"Point"}
}