{
  "type": "Feature",
  "properties": {
    "addr:full":"951 Islington St Portsmouth NH 03801",
    "addr:housenumber":"951",
    "addr:postcode":"03801",
    "addr:street":"Islington St",
    "iso:country":"US",
    "sg:address":"951 Islington St",
    "sg:city":"Portsmouth",
    "sg:classifiers":[
        {
            "category":"Shopping",
            "type":"Retail Goods"
        }
    ],
    "sg:phone":"+1 603 224 3507",
    "sg:postcode":"03801",
    "sg:province":"NH",
    "sg:tags":[
        "medical",
        "apparatus",
        "supply"
    ],
    "wof:name":"Lincare Inc",
    "wof:placetype":"venue"
},
  "geometry": {"coordinates":[-70.774314,43.06714],"type":"Point"}
}