{
  "type": "Feature",
  "properties": {
    "iso:country":"US",
    "sg:address":"34 Church St",
    "sg:city":"Concord",
    "sg:classifiers":[
        {
            "category":"Building & Trades",
            "subcategory":"Landscaping Services",
            "type":"Services"
        }
    ],
    "sg:phone":"+1 603 226 4929",
    "sg:postcode":"03301",
    "sg:province":"NH",
    "sg:tags":[
        "landscape",
        "contractor"
    ],
    "wof:name":"Eastern Valley Landscaping",
    "wof:placetype":"venue"
},
  "geometry": {"coordinates":[-71.54481699999999,43.213373],"type":"Point"}
}