{
  "type": "Feature",
  "properties": {
    "addr:full":"15 E Broadway Derry NH 03038",
    "addr:housenumber":"15",
    "addr:postcode":"03038",
    "addr:street":"E Broadway",
    "iso:country":"US",
    "sg:address":"15 E Broadway",
    "sg:city":"Derry",
    "sg:classifiers":[
        {
            "category":"Banks & Credit Unions",
            "subcategory":"Investment Brokerage",
            "type":"Services"
        },
        {
            "category":"Professional",
            "subcategory":"Research",
            "type":"Services"
        }
    ],
    "sg:phone":"+1 603 421 0229",
    "sg:postcode":"03038",
    "sg:province":"NH",
    "sg:tags":[
        "advisory",
        "financial",
        "commercial",
        "nonphysical"
    ],
    "wof:name":"Financial Destination Inc",
    "wof:placetype":"venue"
},
  "geometry": {"coordinates":[-71.32543699999999,42.881167],"type":"Point"}
}