{
  "type": "Feature",
  "properties": {
    "iso:country":"US",
    "sg:address":"34 Industrial Park Dr",
    "sg:city":"Hooksett",
    "sg:classifiers":[
        {
            "category":"Wholesale",
            "subcategory":"Scrap",
            "type":"Manufacturing & Wholesale Goods"
        }
    ],
    "sg:phone":"+1 603 669 2282",
    "sg:postcode":"03106",
    "sg:province":"NH",
    "sg:tags":[
        "recycling",
        "center"
    ],
    "wof:name":"Bfi Hooksett Recycling",
    "wof:placetype":"venue"
},
  "geometry": {"coordinates":[-71.446961,43.061323],"type":"Point"}
}