{
  "type": "Feature",
  "properties": {
    "iso:country":"US",
    "sg:address":"234 White Mountain Hwy Ste 1",
    "sg:city":"Conway",
    "sg:classifiers":[
        {
            "category":"Banks & Credit Unions",
            "subcategory":"Bank",
            "type":"Services"
        }
    ],
    "sg:phone":"+1 603 447 1600",
    "sg:postcode":"03818",
    "sg:province":"NH",
    "sg:website":"www.citizensbank.com",
    "wof:name":"Citizens Bank",
    "wof:placetype":"venue"
},
  "geometry": {"coordinates":[-71.130664,43.978663],"type":"Point"}
}