{
  "type": "Feature",
  "properties": {
    "iso:country":"US",
    "sg:address":"24 Kim Rd",
    "sg:city":"Salem",
    "sg:classifiers":[
        {
            "category":"Building & Trades",
            "subcategory":"Cleaning & Sanitation",
            "type":"Services"
        }
    ],
    "sg:phone":"+1 603 893 4492",
    "sg:postcode":"03079",
    "sg:province":"NH",
    "sg:tags":[
        "window"
    ],
    "wof:name":"American Cleaning Co",
    "wof:placetype":"venue"
},
  "geometry": {"coordinates":[-71.212898,42.788658],"type":"Point"}
}