{
  "type": "Feature",
  "properties": {
    "iso:country":"US",
    "sg:address":"577 State Rte 106",
    "sg:city":"Loudon",
    "sg:classifiers":[
        {
            "category":"Food & Beverages",
            "subcategory":"Groceries & Convenience Stores",
            "type":"Retail Goods"
        }
    ],
    "sg:phone":"+1 603 783 4305",
    "sg:postcode":"03307",
    "sg:province":"NH",
    "sg:tags":[
        "market"
    ],
    "wof:name":"Beanstalk",
    "wof:placetype":"venue"
},
  "geometry": {"coordinates":[-71.475459,43.311384],"type":"Point"}
}