{
  "type": "Feature",
  "properties": {
    "iso:country":"US",
    "sg:address":"3 Charles St",
    "sg:city":"Claremont",
    "sg:classifiers":[
        {
            "category":"Retail",
            "subcategory":"Auto Repair",
            "type":"Services"
        }
    ],
    "sg:phone":"+1 603 542 2179",
    "sg:postcode":"03743",
    "sg:province":"NH",
    "sg:tags":[
        "tire"
    ],
    "wof:name":"Asetex Tire & Auto",
    "wof:placetype":"venue"
},
  "geometry": {"coordinates":[-72.345316,43.363233],"type":"Point"}
}