{
  "type": "Feature",
  "properties": {
    "addr:full":"60 Shady Ln Hancock NH 03449",
    "addr:housenumber":"60",
    "addr:postcode":"03449",
    "addr:street":"Shady Ln",
    "iso:country":"US",
    "sg:address":"60 Shady Ln",
    "sg:city":"Hancock",
    "sg:classifiers":[
        {
            "category":"Mining & Drilling",
            "type":"Manufacturing & Wholesale Goods"
        }
    ],
    "sg:phone":"+1 603 525 9330",
    "sg:postcode":"03449",
    "sg:province":"NH",
    "sg:tags":[
        "field"
    ],
    "wof:name":"Daniel Johnston & Co Inc",
    "wof:placetype":"venue"
},
  "geometry": {"coordinates":[-71.97591,42.999818],"type":"Point"}
}