{
  "type": "Feature",
  "properties": {
    "iso:country":"US",
    "sg:address":"7 W Hill Rd",
    "sg:city":"Bath",
    "sg:classifiers":[
        {
            "category":"Shopping",
            "subcategory":"Used Merchandise",
            "type":"Retail Goods"
        }
    ],
    "sg:phone":"+1 603 747 4000",
    "sg:postcode":"03782",
    "sg:province":"NH",
    "sg:tags":[
        "antique"
    ],
    "wof:name":"Village Antiques",
    "wof:placetype":"venue"
},
  "geometry": {"coordinates":[-72.07472199999999,43.351908],"type":"Point"}
}