{
  "type": "Feature",
  "properties": {
    "addr:full":"4 Birch St Derry NH 03038",
    "addr:housenumber":"4",
    "addr:postcode":"03038",
    "addr:street":"Birch St",
    "iso:country":"US",
    "sg:address":"4 Birch St",
    "sg:city":"Derry",
    "sg:classifiers":[
        {
            "category":"Health Services",
            "subcategory":"Clinic",
            "type":"Services"
        },
        {
            "category":"Health Services",
            "subcategory":"Health Practitioner",
            "type":"Services"
        }
    ],
    "sg:phone":"+1 603 434 2535",
    "sg:postcode":"03038",
    "sg:province":"NH",
    "sg:tags":[
        "home",
        "nurse",
        "registry",
        "care"
    ],
    "wof:name":"Tender Care Home Nursing Svcs",
    "wof:placetype":"venue"
},
  "geometry": {"coordinates":[-71.322952,42.880821],"type":"Point"}
}