{
  "type": "Feature",
  "properties": {
    "addr:full":"23 W Webster St Manchester NH 03104",
    "addr:housenumber":"23",
    "addr:postcode":"03104",
    "addr:street":"W Webster St",
    "iso:country":"US",
    "sg:address":"23 W Webster St",
    "sg:city":"Manchester",
    "sg:classifiers":[
        {
            "category":"Professional",
            "subcategory":"Lawyer & Legal Services",
            "type":"Services"
        }
    ],
    "sg:phone":"+1 603 625 0042",
    "sg:postcode":"03104",
    "sg:province":"NH",
    "sg:tags":[
        "attorney"
    ],
    "wof:name":"Andrew J Harmon Law Offices",
    "wof:placetype":"venue"
},
  "geometry": {"coordinates":[-71.466072,43.006282],"type":"Point"}
}