{
  "type": "Feature",
  "properties": {
    "iso:country":"US",
    "sg:address":"146 Baboosic Lake Rd",
    "sg:city":"Merrimack",
    "sg:classifiers":[
        {
            "category":"Manufacturing",
            "subcategory":"Building Materials",
            "type":"Manufacturing & Wholesale Goods"
        }
    ],
    "sg:phone":"+1 603 429 0596",
    "sg:postcode":"03054",
    "sg:province":"NH",
    "sg:tags":[
        "mfg"
    ],
    "wof:name":"Srt Industries",
    "wof:placetype":"venue"
},
  "geometry": {"coordinates":[-71.529482,42.870506],"type":"Point"}
}