{
  "type": "Feature",
  "properties": {
    "iso:country":"US",
    "sg:address":"250 A St",
    "sg:city":"Portsmouth",
    "sg:classifiers":[
        {
            "category":"Banks & Credit Unions",
            "subcategory":"Investment Brokerage",
            "type":"Services"
        }
    ],
    "sg:phone":"+1 603 433 9502",
    "sg:postcode":"03818",
    "sg:province":"NH",
    "sg:tags":[
        "advisory",
        "financial"
    ],
    "sg:website":"www.belforti.org",
    "wof:name":"Belforti Investment Mgmt",
    "wof:placetype":"venue"
},
  "geometry": {"coordinates":[-71.13865800000001,43.964389],"type":"Point"}
}