{
  "type": "Feature",
  "properties": {
    "iso:country":"US",
    "sg:address":"1 Cobbler Ln",
    "sg:city":"Bedford",
    "sg:classifiers":[
        {
            "category":"Professional",
            "subcategory":"Management & Consulting",
            "type":"Services"
        }
    ],
    "sg:phone":"+1 603 472 5610",
    "sg:postcode":"03110",
    "sg:province":"NH",
    "wof:name":"Pappas Technology Mgt Inc",
    "wof:placetype":"venue"
},
  "geometry": {"coordinates":[-71.50275999999999,42.946307],"type":"Point"}
}