{
  "type": "Feature",
  "properties": {
    "iso:country":"US",
    "sg:address":"57 W Main St",
    "sg:city":"Bradford",
    "sg:classifiers":[
        {
            "category":"Building & Trades",
            "subcategory":"Equipment Rental",
            "type":"Services"
        }
    ],
    "sg:phone":"+1 603 938 2111",
    "sg:postcode":"03221",
    "sg:province":"NH",
    "sg:tags":[
        "player",
        "recorder",
        "video"
    ],
    "wof:name":"Video Pursuit Of Bradford",
    "wof:placetype":"venue"
},
  "geometry": {"coordinates":[-71.960821,43.269489],"type":"Point"}
}