{
  "type": "Feature",
  "properties": {
    "iso:country":"US",
    "sg:address":"264 N Broadway",
    "sg:city":"Salem",
    "sg:classifiers":[
        {
            "category":"Professional",
            "subcategory":"Lawyer & Legal Services",
            "type":"Services"
        }
    ],
    "sg:phone":"+1 603 898 9700",
    "sg:postcode":"03079",
    "sg:province":"NH",
    "sg:tags":[
        "attorney"
    ],
    "wof:name":"William R Mason",
    "wof:placetype":"venue"
},
  "geometry": {"coordinates":[-71.239566,42.798926],"type":"Point"}
}