{
  "type": "Feature",
  "properties": {
    "iso:country":"US",
    "sg:address":"40 Merrimack St",
    "sg:city":"Hooksett",
    "sg:classifiers":[
        {
            "category":"Professional",
            "subcategory":"Business Services",
            "type":"Services"
        }
    ],
    "sg:phone":"+1 603 485 4419",
    "sg:postcode":"03106",
    "sg:province":"NH",
    "wof:name":"Walshs Personal Services",
    "wof:placetype":"venue"
},
  "geometry": {"coordinates":[-71.460424,43.097091],"type":"Point"}
}