{
  "type": "Feature",
  "properties": {
    "addr:full":"547 Amherst St Nashua NH 03063",
    "addr:housenumber":"547",
    "addr:postcode":"03063",
    "addr:street":"Amherst St",
    "iso:country":"US",
    "sg:address":"547 Amherst St",
    "sg:city":"Nashua",
    "sg:classifiers":[
        {
            "category":"Insurance",
            "subcategory":"Insurance Agent",
            "type":"Services"
        }
    ],
    "sg:phone":"+1 603 889 3545",
    "sg:postcode":"03063",
    "sg:province":"NH",
    "wof:name":"Canada Maritime Agencies Ltd",
    "wof:placetype":"venue"
},
  "geometry": {"coordinates":[-71.529858,42.796862],"type":"Point"}
}