{
  "type": "Feature",
  "properties": {
    "addr:full":"830 Lafayette Rd Seabrook NH 03874",
    "addr:housenumber":"830",
    "addr:postcode":"03874",
    "iso:country":"US",
    "sg:address":"830 Lafayette Rd",
    "sg:city":"Seabrook",
    "sg:classifiers":[
        {
            "category":"Autos & Motor Vehicles",
            "subcategory":"Fuel & Gas Station",
            "type":"Retail Goods"
        }
    ],
    "sg:phone":"+1 603 474 3485",
    "sg:postcode":"03874",
    "sg:province":"NH",
    "sg:tags":[
        "oil"
    ],
    "wof:name":"Seabrook Plaza Prime",
    "wof:placetype":"venue"
},
  "geometry": {"coordinates":[-70.87043300000001,42.899733],"type":"Point"}
}