{
  "type": "Feature",
  "properties": {
    "iso:country":"US",
    "sg:address":"105 Middle Rd",
    "sg:city":"Portsmouth",
    "sg:classifiers":[
        {
            "category":"Professional",
            "subcategory":"Business Services",
            "type":"Services"
        }
    ],
    "sg:phone":"+1 603 591 2954",
    "sg:postcode":"03801",
    "sg:province":"NH",
    "wof:name":"Global Inventory Management",
    "wof:placetype":"venue"
},
  "geometry": {"coordinates":[-70.769611,43.063678],"type":"Point"}
}