{
  "type": "Feature",
  "properties": {
    "iso:country":"US",
    "sg:address":"225 Washington St",
    "sg:city":"Dover",
    "sg:classifiers":[
        {
            "category":"Communications",
            "type":"Services"
        }
    ],
    "sg:phone":"+1 603 766 3802",
    "sg:postcode":"03820",
    "sg:province":"NH",
    "wof:name":"Final Mile Communications",
    "wof:placetype":"venue"
},
  "geometry": {"coordinates":[-70.88185900000001,43.194053],"type":"Point"}
}