{
  "type": "Feature",
  "properties": {
    "iso:country":"US",
    "sg:address":"61 Elm St",
    "sg:city":"Manchester",
    "sg:classifiers":[
        {
            "category":"Personal",
            "type":"Services"
        }
    ],
    "sg:phone":"+1 603 540 1871",
    "sg:postcode":"03101",
    "sg:province":"NH",
    "sg:tags":[
        "therapist",
        "massage"
    ],
    "wof:name":"Jennifer Lupien Therapeutic",
    "wof:placetype":"venue"
},
  "geometry": {"coordinates":[-71.46301099999999,42.976042],"type":"Point"}
}