{
  "type": "Feature",
  "properties": {
    "iso:country":"US",
    "sg:address":"30 Margate Dr",
    "sg:city":"Auburn",
    "sg:classifiers":[
        {
            "category":"Home & Garden",
            "subcategory":"Building Materials",
            "type":"Retail Goods"
        },
        {
            "category":"Building & Trades",
            "subcategory":"Construction",
            "type":"Services"
        }
    ],
    "sg:phone":"+1 603 232 2176",
    "sg:postcode":"03032",
    "sg:province":"NH",
    "sg:tags":[
        "builder",
        "gazebo",
        "patio"
    ],
    "wof:name":"Robin Wilson",
    "wof:placetype":"venue"
},
  "geometry": {"coordinates":[-71.344055,42.962598],"type":"Point"}
}