{
  "type": "Feature",
  "properties": {
    "addr:full":"399 Jaffrey Rd Peterborough NH 03458",
    "addr:housenumber":"399",
    "addr:postcode":"03458",
    "addr:street":"Jaffrey Rd",
    "iso:country":"US",
    "sg:address":"399 Jaffrey Rd",
    "sg:city":"Peterborough",
    "sg:classifiers":[
        {
            "category":"Home & Garden",
            "subcategory":"Building Materials",
            "type":"Retail Goods"
        }
    ],
    "sg:phone":"+1 603 924 1999",
    "sg:postcode":"03458",
    "sg:province":"NH",
    "sg:tags":[
        "mixed",
        "concrete"
    ],
    "wof:name":"Carroll Concrete",
    "wof:placetype":"venue"
},
  "geometry": {"coordinates":[-71.970437,42.838195],"type":"Point"}
}