{
  "type": "Feature",
  "properties": {
    "iso:country":"US",
    "sg:address":"120 Prospect St Exn",
    "sg:city":"Lebanon",
    "sg:classifiers":[
        {
            "category":"Social Services",
            "subcategory":"Child Care",
            "type":"Services"
        }
    ],
    "sg:phone":"+1 603 448 1287",
    "sg:postcode":"03766",
    "sg:province":"NH",
    "sg:tags":[
        "day"
    ],
    "wof:name":"Grammy & Grandpa Service",
    "wof:placetype":"venue"
},
  "geometry": {"coordinates":[-72.22731400000001,43.635179],"type":"Point"}
}