{
  "type": "Feature",
  "properties": {
    "iso:country":"US",
    "sg:address":"67 Powwow River Ln",
    "sg:city":"East Kingston",
    "sg:classifiers":[
        {
            "category":"Professional",
            "subcategory":"Business Services",
            "type":"Services"
        }
    ],
    "sg:phone":"+1 603 642 5206",
    "sg:postcode":"03827",
    "sg:province":"NH",
    "wof:name":"Enchanting Homestead Interiors",
    "wof:placetype":"venue"
},
  "geometry": {"coordinates":[-71.02566299999999,42.913634],"type":"Point"}
}