{
  "type": "Feature",
  "properties": {
    "iso:country":"US",
    "sg:address":"491 Central Ave",
    "sg:city":"Dover",
    "sg:classifiers":[
        {
            "category":"Shopping",
            "subcategory":"Hobbies, Toys, & Games",
            "type":"Retail Goods"
        }
    ],
    "sg:phone":"+1 603 749 0840",
    "sg:postcode":"03820",
    "sg:province":"NH",
    "sg:tags":[
        "model",
        "supply"
    ],
    "wof:name":"Seacoast Hobbies",
    "wof:placetype":"venue"
},
  "geometry": {"coordinates":[-70.87414,43.198305],"type":"Point"}
}