{
  "type": "Feature",
  "properties": {
    "iso:country":"US",
    "sg:address":"6 Mill Pond Rd",
    "sg:city":"Epping",
    "sg:classifiers":[
        {
            "category":"Building & Trades",
            "subcategory":"Plumbing",
            "type":"Services"
        }
    ],
    "sg:phone":"+1 603 679 5061",
    "sg:postcode":"03042",
    "sg:province":"NH",
    "sg:tags":[
        "contractor"
    ],
    "wof:name":"Degrandpre Plumbing Heati",
    "wof:placetype":"venue"
},
  "geometry": {"coordinates":[-71.122834,43.032961],"type":"Point"}
}