{
  "type": "Feature",
  "properties": {
    "iso:country":"US",
    "sg:address":"22 Technology Way Fl 5",
    "sg:city":"Nashua",
    "sg:classifiers":[
        {
            "category":"Manufacturing",
            "subcategory":"Aerospace",
            "type":"Manufacturing & Wholesale Goods"
        },
        {
            "category":"Manufacturing",
            "subcategory":"Musical Instruments",
            "type":"Manufacturing & Wholesale Goods"
        }
    ],
    "sg:phone":"+1 603 598 8880",
    "sg:postcode":"03060",
    "sg:province":"NH",
    "sg:tags":[
        "aircraft",
        "avionics",
        "nautical"
    ],
    "sg:website":"http://www.phasedarray.com",
    "wof:name":"Paratek Microwave, Inc.",
    "wof:placetype":"venue"
},
  "geometry": {"coordinates":[-71.474711,42.761719],"type":"Point"}
}