{
  "type": "Feature",
  "properties": {
    "addr:full":"108 Carroll St Manchester NH 03102",
    "addr:housenumber":"108",
    "addr:postcode":"03102",
    "addr:street":"Carroll St",
    "iso:country":"US",
    "sg:address":"108 Carroll St",
    "sg:city":"Manchester",
    "sg:classifiers":[
        {
            "category":"Building & Trades",
            "subcategory":"Construction",
            "type":"Services"
        }
    ],
    "sg:phone":"+1 603 232 5962",
    "sg:postcode":"03102",
    "sg:province":"NH",
    "sg:tags":[
        "hanging",
        "contractor"
    ],
    "wof:name":"Currier Painting",
    "wof:placetype":"venue"
},
  "geometry": {"coordinates":[-71.484763,42.978747],"type":"Point"}
}