{
  "type": "Feature",
  "properties": {
    "iso:country":"US",
    "sg:address":"13 Kara Dr",
    "sg:city":"Chichester",
    "sg:classifiers":[
        {
            "category":"Banks & Credit Unions",
            "subcategory":"Bank",
            "type":"Services"
        }
    ],
    "sg:phone":"+1 603 798 4443",
    "sg:postcode":"03258",
    "sg:province":"NH",
    "sg:tags":[
        "financing"
    ],
    "wof:name":"Teddy Bear Fund",
    "wof:placetype":"venue"
},
  "geometry": {"coordinates":[-71.37552100000001,43.249242],"type":"Point"}
}