{
  "type": "Feature",
  "properties": {
    "iso:country":"US",
    "sg:address":"254 Main St",
    "sg:city":"Durham",
    "sg:classifiers":[
        {
            "category":"Home & Garden",
            "subcategory":"Building Materials",
            "type":"Retail Goods"
        }
    ],
    "sg:phone":"+1 603 868 7419",
    "sg:postcode":"03824",
    "sg:province":"NH",
    "sg:tags":[
        "mill"
    ],
    "wof:name":"Woodward Lumber Co",
    "wof:placetype":"venue"
},
  "geometry": {"coordinates":[-70.964187,43.147839],"type":"Point"}
}