{
  "type": "Feature",
  "properties": {
    "addr:full":"125 Main St Salem NH 03079",
    "addr:housenumber":"125",
    "addr:postcode":"03079",
    "addr:street":"Main St",
    "iso:country":"US",
    "sg:address":"125 Main St",
    "sg:city":"Salem",
    "sg:classifiers":[
        {
            "category":"Banks & Credit Unions",
            "subcategory":"Bank",
            "type":"Services"
        }
    ],
    "sg:phone":"+1 603 893 1655",
    "sg:postcode":"03079",
    "sg:province":"NH",
    "sg:tags":[
        "federal",
        "savings"
    ],
    "sg:website":"www.sovereignbank.com",
    "wof:name":"Sovereign Bank",
    "wof:placetype":"venue"
},
  "geometry": {"coordinates":[-71.225826,42.782199],"type":"Point"}
}