{
  "type": "Feature",
  "properties": {
    "iso:country":"US",
    "sg:address":"7 Monument Sq",
    "sg:city":"Hollis",
    "sg:classifiers":[
        {
            "category":"Government",
            "subcategory":"Office",
            "type":"Public Place"
        }
    ],
    "sg:phone":"+1 603 465 2209",
    "sg:postcode":"03049",
    "sg:province":"NH",
    "sg:tags":[
        "city"
    ],
    "wof:name":"Hollis Town Hall",
    "wof:placetype":"venue"
},
  "geometry": {"coordinates":[-71.58931699999999,42.739741],"type":"Point"}
}