{
  "type": "Feature",
  "properties": {
    "addr:full":"161 Dockham Shore Rd Laconia NH 03249",
    "addr:housenumber":"161",
    "addr:postcode":"03249",
    "addr:street":"Dockham Shore Rd",
    "iso:country":"US",
    "sg:address":"161 Dockham Shore Rd",
    "sg:city":"Laconia",
    "sg:classifiers":[
        {
            "category":"Building & Trades",
            "subcategory":"Construction",
            "type":"Services"
        }
    ],
    "sg:phone":"+1 603 293 0774",
    "sg:postcode":"03249",
    "sg:province":"NH",
    "sg:tags":[
        "house"
    ],
    "wof:name":"Bc Building & Remodeling LLC",
    "wof:placetype":"venue"
},
  "geometry": {"coordinates":[-71.413073,43.592177],"type":"Point"}
}