{
  "type": "Feature",
  "properties": {
    "iso:country":"US",
    "sg:address":"14 Danville Rd",
    "sg:city":"Plaistow",
    "sg:classifiers":[
        {
            "category":"Autos & Motor Vehicles",
            "subcategory":"Automobile Sales",
            "type":"Retail Goods"
        }
    ],
    "sg:phone":"+1 603 378 9300",
    "sg:postcode":"03865",
    "sg:province":"NH",
    "sg:tags":[
        "used"
    ],
    "wof:name":"McVees",
    "wof:placetype":"venue"
},
  "geometry": {"coordinates":[-71.108158,42.849139],"type":"Point"}
}