{
  "type": "Feature",
  "properties": {
    "addr:full":"187 Water St Exeter NH 03833",
    "addr:housenumber":"187",
    "addr:postcode":"03833",
    "addr:street":"Water St",
    "iso:country":"US",
    "sg:address":"187 Water St",
    "sg:city":"Exeter",
    "sg:classifiers":[
        {
            "category":"Real Estate",
            "subcategory":"Real Estate Services",
            "type":"Services"
        },
        {
            "category":"Real Estate",
            "subcategory":"Real Estate Agent",
            "type":"Services"
        }
    ],
    "sg:phone":"+1 603 772 4228",
    "sg:postcode":"03833",
    "sg:province":"NH",
    "sg:tags":[
        "buyer",
        "broker"
    ],
    "sg:website":"http://www.weichert.com",
    "wof:name":"Weichert Realtors",
    "wof:placetype":"venue"
},
  "geometry": {"coordinates":[-70.948791,42.982048],"type":"Point"}
}