{
  "type": "Feature",
  "properties": {
    "addr:full":"491 Nashua St Milford NH 03055",
    "addr:housenumber":"491",
    "addr:postcode":"03055",
    "addr:street":"Nashua St",
    "iso:country":"US",
    "sg:address":"491 Nashua St",
    "sg:city":"Milford",
    "sg:classifiers":[
        {
            "category":"Building & Trades",
            "subcategory":"Plumbing",
            "type":"Services"
        }
    ],
    "sg:phone":"+1 603 673 4820",
    "sg:postcode":"03055",
    "sg:province":"NH",
    "sg:tags":[
        "contractor"
    ],
    "wof:name":"Rdp Water Systems Plbg & Htg",
    "wof:placetype":"venue"
},
  "geometry": {"coordinates":[-71.63047899999999,42.825803],"type":"Point"}
}