{
  "type": "Feature",
  "properties": {
    "iso:country":"US",
    "sg:address":"175 Canal St",
    "sg:city":"Manchester",
    "sg:classifiers":[
        {
            "category":"Insurance",
            "subcategory":"Insurance Agent",
            "type":"Services"
        }
    ],
    "sg:phone":"+1 603 627 9583",
    "sg:postcode":"03101",
    "sg:province":"NH",
    "wof:name":"Dunlap Corp",
    "wof:placetype":"venue"
},
  "geometry": {"coordinates":[-71.46656,42.987964],"type":"Point"}
}