{
  "type": "Feature",
  "properties": {
    "iso:country":"US",
    "sg:address":"9 Storer Ct",
    "sg:city":"Derry",
    "sg:classifiers":[
        {
            "category":"Retail",
            "subcategory":"Repair Shop",
            "type":"Services"
        }
    ],
    "sg:phone":"+1 603 437 6853",
    "sg:postcode":"03038",
    "sg:province":"NH",
    "wof:name":"Reliant Small Engine Repair",
    "wof:placetype":"venue"
},
  "geometry": {"coordinates":[-71.327342,42.879273],"type":"Point"}
}