{
  "type": "Feature",
  "properties": {
    "iso:country":"US",
    "sg:address":"778 Woodbury Ave",
    "sg:city":"Portsmouth",
    "sg:classifiers":[
        {
            "category":"Professional",
            "subcategory":"Art Services",
            "type":"Services"
        }
    ],
    "sg:phone":"+1 603 430 8611",
    "sg:postcode":"03801",
    "sg:province":"NH",
    "sg:tags":[
        "photographer"
    ],
    "wof:name":"Haynes Images",
    "wof:placetype":"venue"
},
  "geometry": {"coordinates":[-70.781629,43.077773],"type":"Point"}
}