{
  "type": "Feature",
  "properties": {
    "iso:country":"US",
    "sg:address":"7 Elmwood Ave",
    "sg:city":"Manchester",
    "sg:classifiers":[
        {
            "category":"Building & Trades",
            "subcategory":"Landscaping Services",
            "type":"Services"
        }
    ],
    "sg:phone":"+1 603 365 6382",
    "sg:postcode":"03103",
    "sg:province":"NH",
    "wof:name":"Cbc Outdoor Services",
    "wof:placetype":"venue"
},
  "geometry": {"coordinates":[-71.460313,42.966215],"type":"Point"}
}