{
  "type": "Feature",
  "properties": {
    "iso:country":"US",
    "sg:address":"628 State Rte 3a",
    "sg:city":"Bow",
    "sg:classifiers":[
        {
            "category":"Professional",
            "type":"Services"
        }
    ],
    "sg:phone":"+1 603 228 9328",
    "sg:postcode":"03304",
    "sg:province":"NH",
    "sg:tags":[
        "establishment"
    ],
    "wof:name":"Clapp Ken Ent LLC",
    "wof:placetype":"venue"
},
  "geometry": {"coordinates":[-71.49534800000001,43.147405],"type":"Point"}
}