{
  "type": "Feature",
  "properties": {
    "addr:full":"103 Main St West Lebanon NH 03784",
    "addr:housenumber":"103",
    "addr:postcode":"03784",
    "addr:street":"Main St",
    "iso:country":"US",
    "sg:address":"103 Main St",
    "sg:city":"West Lebanon",
    "sg:classifiers":[
        {
            "category":"Personal",
            "type":"Services"
        }
    ],
    "sg:phone":"+1 603 298 6811",
    "sg:postcode":"03784",
    "sg:province":"NH",
    "sg:tags":[
        "therapist",
        "massage"
    ],
    "wof:name":"Paula Rossvall",
    "wof:placetype":"venue"
},
  "geometry": {"coordinates":[-72.31670200000001,43.634722],"type":"Point"}
}