{
  "type": "Feature",
  "properties": {
    "iso:country":"US",
    "sg:address":"48 Main St",
    "sg:city":"Meredith",
    "sg:classifiers":[
        {
            "category":"Restaurant",
            "type":"Food & Drink"
        }
    ],
    "sg:phone":"+1 603 279 5975",
    "sg:postcode":"03253",
    "sg:province":"NH",
    "sg:tags":[
        "shop",
        "coffee"
    ],
    "wof:name":"Village Perk Coffee Hse & Deli",
    "wof:placetype":"venue"
},
  "geometry": {"coordinates":[-71.501053,43.656688],"type":"Point"}
}