{
  "type": "Feature",
  "properties": {
    "addr:full":"351 Middle St Portsmouth NH 03801",
    "addr:housenumber":"351",
    "addr:postcode":"03801",
    "addr:street":"Middle St",
    "iso:country":"US",
    "sg:address":"351 Middle St",
    "sg:city":"Portsmouth",
    "sg:classifiers":[
        {
            "category":"Education",
            "subcategory":"Library",
            "type":"Public Place"
        }
    ],
    "sg:phone":"+1 603 436 3712",
    "sg:postcode":"03801",
    "sg:province":"NH",
    "sg:tags":[
        "special",
        "interest"
    ],
    "wof:name":"James E Whalley Museum & Libr",
    "wof:placetype":"venue"
},
  "geometry": {"coordinates":[-70.76544,43.068979],"type":"Point"}
}