{
  "type": "Feature",
  "properties": {
    "iso:country":"US",
    "sg:address":"10 Unity St",
    "sg:city":"Berlin",
    "sg:classifiers":[
        {
            "category":"Cinema",
            "subcategory":"Movie Theater",
            "type":"Entertainment"
        }
    ],
    "sg:phone":"+1 603 752 7137",
    "sg:postcode":"03570",
    "sg:province":"NH",
    "wof:name":"Depot Movies",
    "wof:placetype":"venue"
},
  "geometry": {"coordinates":[-71.17518800000001,44.469637],"type":"Point"}
}