{
  "type": "Feature",
  "properties": {
    "addr:full":"20 Library St Hudson NH 03051",
    "addr:housenumber":"20",
    "addr:postcode":"03051",
    "addr:street":"Library St",
    "iso:country":"US",
    "sg:address":"20 Library St",
    "sg:city":"Hudson",
    "sg:classifiers":[
        {
            "category":"Education",
            "subcategory":"School",
            "type":"Public Place"
        }
    ],
    "sg:phone":"+1 603 883 7765",
    "sg:postcode":"03051",
    "sg:province":"NH",
    "wof:name":"Hudson Superintendent-Schools",
    "wof:placetype":"venue"
},
  "geometry": {"coordinates":[-71.440096,42.766504],"type":"Point"}
}