{
  "type": "Feature",
  "properties": {
    "addr:full":"119 State Rte 101A Amherst NH 03031",
    "addr:housenumber":"119",
    "addr:postcode":"03031",
    "addr:street":"State Rte 101A",
    "iso:country":"US",
    "sg:address":"119 State Rte 101A",
    "sg:city":"Amherst",
    "sg:classifiers":[
        {
            "category":"Wholesale",
            "subcategory":"Machinery & Supplies",
            "type":"Manufacturing & Wholesale Goods"
        }
    ],
    "sg:phone":"+1 603 880 6404",
    "sg:postcode":"03031",
    "sg:province":"NH",
    "sg:tags":[
        "cleaning",
        "chimney"
    ],
    "wof:name":"Stove Barn Stove & Chimney",
    "wof:placetype":"venue"
},
  "geometry": {"coordinates":[-71.569137,42.807503],"type":"Point"}
}