{
  "type": "Feature",
  "properties": {
    "addr:full":"21 Taterboro Rd Center Sandwich NH 03227",
    "addr:housenumber":"21",
    "addr:postcode":"03227",
    "addr:street":"Taterboro Rd",
    "iso:country":"US",
    "sg:address":"21 Taterboro Rd",
    "sg:city":"Center Sandwich",
    "sg:classifiers":[
        {
            "category":"Manufacturing",
            "subcategory":"Lumber",
            "type":"Manufacturing & Wholesale Goods"
        }
    ],
    "sg:phone":"+1 603 284 7798",
    "sg:postcode":"03227",
    "sg:province":"NH",
    "sg:tags":[
        "mill"
    ],
    "wof:name":"Portable Sawmill Svc Sandwi",
    "wof:placetype":"venue"
},
  "geometry": {"coordinates":[-71.356216,43.804687],"type":"Point"}
}