{
  "type": "Feature",
  "properties": {
    "iso:country":"US",
    "sg:address":"75 Regional Dr",
    "sg:city":"Concord",
    "sg:classifiers":[
        {
            "category":"Utilities",
            "subcategory":"Fuel Oil & Lpg",
            "type":"Services"
        }
    ],
    "sg:phone":"+1 603 225 6660",
    "sg:postcode":"03301",
    "sg:province":"NH",
    "sg:tags":[
        "propane",
        "retail",
        "gas"
    ],
    "wof:name":"Energy North Propane Inc",
    "wof:placetype":"venue"
},
  "geometry": {"coordinates":[-71.489785,43.210018],"type":"Point"}
}