{
  "type": "Feature",
  "properties": {
    "iso:country":"US",
    "sg:address":"90 Harriman St",
    "sg:city":"Manchester",
    "sg:classifiers":[
        {
            "category":"Building & Trades",
            "subcategory":"Cleaning & Sanitation",
            "type":"Services"
        }
    ],
    "sg:phone":"+1 603 669 1088",
    "sg:postcode":"03102",
    "sg:province":"NH",
    "sg:tags":[
        "janitor",
        "maintenance"
    ],
    "wof:name":"Clean Look Cleaning Service",
    "wof:placetype":"venue"
},
  "geometry": {"coordinates":[-71.488269,42.966447],"type":"Point"}
}