{
  "type": "Feature",
  "properties": {
    "iso:country":"US",
    "sg:address":"RR 302",
    "sg:city":"Center Conway",
    "sg:classifiers":[
        {
            "category":"Home & Garden",
            "subcategory":"Garden Supply",
            "type":"Retail Goods"
        }
    ],
    "sg:phone":"+1 603 447 5442",
    "sg:postcode":"03813",
    "sg:province":"NH",
    "sg:tags":[
        "nursery",
        "gardening"
    ],
    "wof:name":"McSherry's Nursery & Garden Center",
    "wof:placetype":"venue"
},
  "geometry": {"coordinates":[-71.028198,43.996399],"type":"Point"}
}