{
  "type": "Feature",
  "properties": {
    "iso:country":"US",
    "sg:address":"1237 Elm St",
    "sg:city":"Manchester",
    "sg:classifiers":[
        {
            "category":"Retail",
            "subcategory":"Self-service Laundry",
            "type":"Services"
        }
    ],
    "sg:phone":"+1 603 623 9587",
    "sg:postcode":"03101",
    "sg:province":"NH",
    "wof:name":"North End Laundry & Drycleaner",
    "wof:placetype":"venue"
},
  "geometry": {"coordinates":[-71.463446,42.99599],"type":"Point"}
}