{
  "type": "Feature",
  "properties": {
    "iso:country":"US",
    "sg:address":"758 Meadow St",
    "sg:city":"Littleton",
    "sg:classifiers":[
        {
            "category":"Wholesale",
            "subcategory":"Hardware",
            "type":"Manufacturing & Wholesale Goods"
        }
    ],
    "sg:phone":"+1 603 444 6009",
    "sg:postcode":"03561",
    "sg:province":"NH",
    "sg:tags":[
        "tool"
    ],
    "wof:name":"Western Tool Supply",
    "wof:placetype":"venue"
},
  "geometry": {"coordinates":[-71.804822,44.300849],"type":"Point"}
}