{
  "type": "Feature",
  "properties": {
    "iso:country":"US",
    "sg:address":"199 Wakefield St",
    "sg:city":"Rochester",
    "sg:classifiers":[
        {
            "category":"Professional",
            "subcategory":"Art Services",
            "type":"Services"
        }
    ],
    "sg:phone":"+1 603 335 1273",
    "sg:postcode":"03867",
    "sg:province":"NH",
    "sg:tags":[
        "artist"
    ],
    "wof:name":"Artist In You",
    "wof:placetype":"venue"
},
  "geometry": {"coordinates":[-70.976167,43.317815],"type":"Point"}
}