{
  "type": "Feature",
  "properties": {
    "iso:country":"US",
    "sg:address":"591 White Mountain Hwy",
    "sg:city":"Conway",
    "sg:classifiers":[
        {
            "category":"Personal",
            "subcategory":"Barber",
            "type":"Services"
        }
    ],
    "sg:phone":"+1 603 447 4399",
    "sg:postcode":"03818",
    "sg:province":"NH",
    "wof:name":"Lei E' Bella Stylists",
    "wof:placetype":"venue"
},
  "geometry": {"coordinates":[-71.145065,43.968562],"type":"Point"}
}