{
  "type": "Feature",
  "properties": {
    "iso:country":"US",
    "sg:address":"255 State Rte 108",
    "sg:city":"Somersworth",
    "sg:classifiers":[
        {
            "category":"Health Services",
            "subcategory":"Doctor",
            "type":"Services"
        }
    ],
    "sg:phone":"+1 603 692 3166",
    "sg:postcode":"03878",
    "sg:province":"NH",
    "sg:tags":[
        "physician",
        "surgeon"
    ],
    "sg:website":"www.painmd.com",
    "wof:name":"Dr O'Connell's Paincare Ctr",
    "wof:placetype":"venue"
},
  "geometry": {"coordinates":[-70.89843999999999,43.25343],"type":"Point"}
}