{
  "type": "Feature",
  "properties": {
    "iso:country":"US",
    "sg:address":"232 Frontage Rd",
    "sg:city":"Manchester",
    "sg:classifiers":[
        {
            "category":"Wholesale",
            "subcategory":"Machinery & Supplies",
            "type":"Manufacturing & Wholesale Goods"
        }
    ],
    "sg:phone":"+1 603 625 6669",
    "sg:postcode":"03103",
    "sg:province":"NH",
    "sg:tags":[
        "truck"
    ],
    "sg:website":"www.mctrucks.com",
    "wof:name":"Independent Power Of America",
    "wof:placetype":"venue"
},
  "geometry": {"coordinates":[-71.447238,42.952541],"type":"Point"}
}