{
  "type": "Feature",
  "properties": {
    "addr:full":"149 Hanover St Manchester NH 03101",
    "addr:housenumber":"149",
    "addr:postcode":"03101",
    "addr:street":"Hanover St",
    "iso:country":"US",
    "sg:address":"149 Hanover St",
    "sg:city":"Manchester",
    "sg:classifiers":[
        {
            "category":"Restaurant",
            "type":"Food & Drink"
        }
    ],
    "sg:menulink":"http://www.allmenus.com/nh/manchester/39811-hanover-street-chophouse/menu/",
    "sg:phone":"+1 603 644 2467",
    "sg:postcode":"03101",
    "sg:province":"NH",
    "sg:tags":[
        "american",
        "steakhouse"
    ],
    "wof:name":"Hanover Street Chophouse",
    "wof:placetype":"venue"
},
  "geometry": {"coordinates":[-71.459639,42.990953],"type":"Point"}
}