{
  "type": "Feature",
  "properties": {
    "iso:country":"US",
    "sg:address":"5 Winding Brook Ln",
    "sg:city":"Merrimack",
    "sg:classifiers":[
        {
            "category":"Freight",
            "type":"Transportation"
        }
    ],
    "sg:phone":"+1 603 424 7322",
    "sg:postcode":"03054",
    "sg:province":"NH",
    "sg:tags":[
        "courier"
    ],
    "wof:name":"John Courier Service",
    "wof:placetype":"venue"
},
  "geometry": {"coordinates":[-71.491862,42.888192],"type":"Point"}
}