{
  "type": "Feature",
  "properties": {
    "addr:full":"309 Lincoln St Manchester NH 03103",
    "addr:housenumber":"309",
    "addr:postcode":"03103",
    "addr:street":"Lincoln St",
    "iso:country":"US",
    "sg:address":"309 Lincoln St",
    "sg:city":"Manchester",
    "sg:classifiers":[
        {
            "category":"Food & Beverages",
            "subcategory":"Liquor & Beverages",
            "type":"Retail Goods"
        }
    ],
    "sg:phone":"+1 603 626 0940",
    "sg:postcode":"03103",
    "sg:province":"NH",
    "wof:name":"State Liquor Store",
    "wof:placetype":"venue"
},
  "geometry": {"coordinates":[-71.45065700000001,42.984493],"type":"Point"}
}