{
  "type": "Feature",
  "properties": {
    "iso:country":"US",
    "sg:address":"380 S Broadway",
    "sg:city":"Salem",
    "sg:classifiers":[
        {
            "category":"Wholesale",
            "subcategory":"Construction Materials",
            "type":"Manufacturing & Wholesale Goods"
        }
    ],
    "sg:phone":"+1 603 894 6510",
    "sg:postcode":"03079",
    "sg:province":"NH",
    "sg:tags":[
        "brick",
        "common",
        "face"
    ],
    "wof:name":"Granite State Brick Face",
    "wof:placetype":"venue"
},
  "geometry": {"coordinates":[-71.20568799999999,42.751081],"type":"Point"}
}