{
  "type": "Feature",
  "properties": {
    "addr:full":"18 Juniper Ridge Rd Exeter NH 03833",
    "addr:housenumber":"18",
    "addr:postcode":"03833",
    "addr:street":"Juniper Ridge Rd",
    "iso:country":"US",
    "sg:address":"18 Juniper Ridge Rd",
    "sg:city":"Exeter",
    "sg:classifiers":[
        {
            "category":"Manufacturing",
            "subcategory":"Tools & Machinery",
            "type":"Manufacturing & Wholesale Goods"
        }
    ],
    "sg:phone":"+1 603 778 7929",
    "sg:postcode":"03833",
    "sg:province":"NH",
    "sg:tags":[
        "device",
        "medical"
    ],
    "wof:name":"FP Ventures",
    "wof:placetype":"venue"
},
  "geometry": {"coordinates":[-70.99026000000001,42.965268],"type":"Point"}
}