{
  "type": "Feature",
  "properties": {
    "iso:country":"US",
    "sg:address":"121 Middle St",
    "sg:city":"Manchester",
    "sg:classifiers":[
        {
            "category":"Health Services",
            "subcategory":"Health Practitioner",
            "type":"Services"
        }
    ],
    "sg:phone":"+1 603 665 9590",
    "sg:postcode":"03101",
    "sg:province":"NH",
    "sg:tags":[
        "psychotherapist"
    ],
    "wof:name":"Sheila Mc Donough",
    "wof:placetype":"venue"
},
  "geometry": {"coordinates":[-71.466025,42.990166],"type":"Point"}
}