{
  "type": "Feature",
  "properties": {
    "iso:country":"US",
    "sg:address":"554 US Hwy 202",
    "sg:city":"Rindge",
    "sg:classifiers":[
        {
            "category":"Organizations",
            "subcategory":"Religious Organization",
            "type":"Services"
        }
    ],
    "sg:phone":"+1 603 899 3095",
    "sg:postcode":"03461",
    "sg:province":"NH",
    "wof:name":"Advent Lutheran Church Elca",
    "wof:placetype":"venue"
},
  "geometry": {"coordinates":[-72.033737,42.789415],"type":"Point"}
}