{
  "type": "Feature",
  "properties": {
    "iso:country":"US",
    "sg:address":"56 Old Rte 11",
    "sg:city":"New Durham",
    "sg:classifiers":[
        {
            "category":"Government",
            "subcategory":"Office",
            "type":"Public Place"
        }
    ],
    "sg:phone":"+1 603 859 8080",
    "sg:postcode":"03855",
    "sg:province":"NH",
    "sg:tags":[
        "city",
        "program"
    ],
    "wof:name":"New Durham Solid Waste Dept",
    "wof:placetype":"venue"
},
  "geometry": {"coordinates":[-71.146795,43.424212],"type":"Point"}
}