{
  "type": "Feature",
  "properties": {
    "iso:country":"US",
    "sg:address":"7 Willow St",
    "sg:city":"Milford",
    "sg:classifiers":[
        {
            "category":"Building & Trades",
            "subcategory":"Construction",
            "type":"Services"
        }
    ],
    "sg:phone":"+1 603 672 2248",
    "sg:postcode":"03055",
    "sg:province":"NH",
    "sg:tags":[
        "hanging",
        "contractor"
    ],
    "wof:name":"A 1 Quality Painting",
    "wof:placetype":"venue"
},
  "geometry": {"coordinates":[-71.65123800000001,42.831166],"type":"Point"}
}