{
  "type": "Feature",
  "properties": {
    "iso:country":"US",
    "sg:address":"202 Main St # G2",
    "sg:city":"Salem",
    "sg:classifiers":[
        {
            "category":"Health Services",
            "subcategory":"Doctor",
            "type":"Services"
        },
        {
            "category":"Shopping",
            "subcategory":"Pharmacy",
            "type":"Retail Goods"
        }
    ],
    "sg:phone":"+1 603 894 0656",
    "sg:postcode":"03079",
    "sg:province":"NH",
    "sg:tags":[
        "physician",
        "immunology",
        "allergy",
        "surgeons",
        "treatment",
        "surgeon"
    ],
    "wof:name":"Advanced Allergy Treatment Centers of New England",
    "wof:placetype":"venue"
},
  "geometry": {"coordinates":[-71.21643400000001,42.783566],"type":"Point"}
}