{
  "type": "Feature",
  "properties": {
    "iso:country":"US",
    "sg:address":"52 Bush Hill Rd",
    "sg:city":"Hudson",
    "sg:classifiers":[
        {
            "category":"Retail",
            "subcategory":"Auto Repair",
            "type":"Services"
        }
    ],
    "sg:phone":"+1 603 883 9664",
    "sg:postcode":"03051",
    "sg:province":"NH",
    "sg:tags":[
        "wheel",
        "servicing-automotive",
        "balancing",
        "axle",
        "wheels-aligning",
        "alignment-frame"
    ],
    "wof:name":"Willy's Alignment & Brake Shop",
    "wof:placetype":"venue"
},
  "geometry": {"coordinates":[-71.398392,42.759029],"type":"Point"}
}