{
  "type": "Feature",
  "properties": {
    "iso:country":"US",
    "sg:address":"16 Woodland Dr",
    "sg:city":"Londonderry",
    "sg:classifiers":[
        {
            "category":"Building & Trades",
            "subcategory":"Construction",
            "type":"Services"
        }
    ],
    "sg:phone":"+1 603 883 6626",
    "sg:postcode":"03053",
    "sg:province":"NH",
    "sg:tags":[
        "house"
    ],
    "wof:name":"Mackinnon Construction",
    "wof:placetype":"venue"
},
  "geometry": {"coordinates":[-71.35857300000001,42.81424],"type":"Point"}
}