{
  "type": "Feature",
  "properties": {
    "iso:country":"US",
    "sg:address":"103 Hanover St",
    "sg:city":"Lebanon",
    "sg:classifiers":[
        {
            "category":"Communications",
            "subcategory":"Radio Station",
            "type":"Services"
        }
    ],
    "sg:phone":"+1 603 448 0500",
    "sg:postcode":"03766",
    "sg:province":"NH",
    "sg:tags":[
        "company",
        "broadcasting"
    ],
    "sg:website":"www.wntk.com",
    "wof:name":"WNTK",
    "wof:placetype":"venue"
},
  "geometry": {"coordinates":[-72.253542,43.647203],"type":"Point"}
}