{
  "type": "Feature",
  "properties": {
    "iso:country":"US",
    "sg:address":"5 Clement Rd",
    "sg:city":"Hanover",
    "sg:classifiers":[
        {
            "category":"Professional",
            "subcategory":"Management & Consulting",
            "type":"Services"
        }
    ],
    "sg:phone":"+1 603 643 6530",
    "sg:postcode":"03755",
    "sg:province":"NH",
    "sg:tags":[
        "business"
    ],
    "wof:name":"Hanover Partners Inc",
    "wof:placetype":"venue"
},
  "geometry": {"coordinates":[-72.289766,43.708533],"type":"Point"}
}