{
  "type": "Feature",
  "properties": {
    "addr:full":"775 Upper Straw Rd Contoocook NH 03229",
    "addr:housenumber":"775",
    "addr:postcode":"03229",
    "addr:street":"Upper Straw Rd",
    "iso:country":"US",
    "sg:address":"775 Upper Straw Rd",
    "sg:city":"Contoocook",
    "sg:classifiers":[
        {
            "category":"Building & Trades",
            "subcategory":"Construction",
            "type":"Services"
        }
    ],
    "sg:phone":"+1 603 225 9795",
    "sg:postcode":"03229",
    "sg:province":"NH",
    "sg:tags":[
        "contractor"
    ],
    "wof:name":"Olkonen Arthur Builder",
    "wof:placetype":"venue"
},
  "geometry": {"coordinates":[-71.62653899999999,43.181886],"type":"Point"}
}