{
  "type": "Feature",
  "properties": {
    "addr:full":"8 Lafayette St Rochester NH 03867",
    "addr:housenumber":"8",
    "addr:postcode":"03867",
    "addr:street":"Lafayette St",
    "iso:country":"US",
    "sg:address":"8 Lafayette St",
    "sg:city":"Rochester",
    "sg:classifiers":[
        {
            "category":"Building & Trades",
            "subcategory":"Construction",
            "type":"Services"
        }
    ],
    "sg:phone":"+1 603 335 1913",
    "sg:postcode":"03867",
    "sg:province":"NH",
    "sg:tags":[
        "roofing",
        "contractor"
    ],
    "wof:name":"C & G Roofing Home Improvement",
    "wof:placetype":"venue"
},
  "geometry": {"coordinates":[-70.981223,43.302411],"type":"Point"}
}