{
  "type": "Feature",
  "properties": {
    "addr:full":"736 Huse Rd Manchester NH 03103",
    "addr:housenumber":"736",
    "addr:postcode":"03103",
    "addr:street":"Huse Rd",
    "iso:country":"US",
    "sg:address":"736 Huse Rd",
    "sg:city":"Manchester",
    "sg:classifiers":[
        {
            "category":"Sports & Exercise",
            "subcategory":"Gym",
            "type":"Entertainment"
        }
    ],
    "sg:phone":"+1 603 621 9919",
    "sg:postcode":"03103",
    "sg:province":"NH",
    "sg:tags":[
        "club",
        "health",
        "studio",
        "gymnasium"
    ],
    "sg:website":"www.planetfitness.com",
    "wof:name":"Planet Fitness",
    "wof:placetype":"venue"
},
  "geometry": {"coordinates":[-71.43193100000001,42.950164],"type":"Point"}
}