{
  "type": "Feature",
  "properties": {
    "iso:country":"US",
    "sg:address":"367 Breed Rd",
    "sg:city":"Harrisville",
    "sg:classifiers":[
        {
            "category":"Professional",
            "subcategory":"Business Services",
            "type":"Services"
        }
    ],
    "sg:phone":"+1 603 827 3676",
    "sg:postcode":"03450",
    "sg:province":"NH",
    "wof:name":"Progressive Controls Inc",
    "wof:placetype":"venue"
},
  "geometry": {"coordinates":[-72.123464,42.967235],"type":"Point"}
}