{
  "type": "Feature",
  "properties": {
    "iso:country":"US",
    "sg:address":"21 Main St",
    "sg:city":"Jaffrey",
    "sg:classifiers":[
        {
            "category":"Professional",
            "subcategory":"Accounting & Tax Preparation",
            "type":"Services"
        }
    ],
    "sg:phone":"+1 603 532 7991",
    "sg:postcode":"03452",
    "sg:province":"NH",
    "sg:tags":[
        "accountant"
    ],
    "wof:name":"Carl C Little CPA",
    "wof:placetype":"venue"
},
  "geometry": {"coordinates":[-72.023622,42.814775],"type":"Point"}
}