{
  "type": "Feature",
  "properties": {
    "addr:full":"47 Laurel Hill Rd Hollis NH 03049",
    "addr:housenumber":"47",
    "addr:postcode":"03049",
    "addr:street":"Laurel Hill Rd",
    "iso:country":"US",
    "sg:address":"47 Laurel Hill Rd",
    "sg:city":"Hollis",
    "sg:classifiers":[
        {
            "category":"Professional",
            "subcategory":"Detective & Security Services",
            "type":"Services"
        }
    ],
    "sg:phone":"+1 603 465 6500",
    "sg:postcode":"03049",
    "sg:province":"NH",
    "sg:tags":[
        "investigator"
    ],
    "wof:name":"Stewart B Hannon & Assoc",
    "wof:placetype":"venue"
},
  "geometry": {"coordinates":[-71.602734,42.793308],"type":"Point"}
}