{
  "type": "Feature",
  "properties": {
    "iso:country":"US",
    "sg:address":"692 Lafayette Rd",
    "sg:city":"Seabrook",
    "sg:classifiers":[
        {
            "category":"Shopping",
            "subcategory":"Used Merchandise",
            "type":"Retail Goods"
        }
    ],
    "sg:phone":"+1 603 474 1100",
    "sg:postcode":"03874",
    "sg:province":"NH",
    "sg:tags":[
        "shop",
        "consignment"
    ],
    "wof:name":"Reflections Mirrors & Things",
    "wof:placetype":"venue"
},
  "geometry": {"coordinates":[-70.87117000000001,42.89516],"type":"Point"}
}