{
  "type": "Feature",
  "properties": {
    "iso:country":"US",
    "sg:address":"2 Manor Pkwy",
    "sg:city":"Salem",
    "sg:classifiers":[
        {
            "category":"Professional",
            "subcategory":"Accounting & Tax Preparation",
            "type":"Services"
        }
    ],
    "sg:phone":"+1 603 898 3322",
    "sg:postcode":"03079",
    "sg:province":"NH",
    "sg:tags":[
        "accountant"
    ],
    "wof:name":"Comolli & Company PC",
    "wof:placetype":"venue"
},
  "geometry": {"coordinates":[-71.24994599999999,42.775464],"type":"Point"}
}