{
  "type": "Feature",
  "properties": {
    "iso:country":"US",
    "sg:address":"45 S Summer St",
    "sg:city":"Nottingham",
    "sg:classifiers":[
        {
            "category":"Professional",
            "subcategory":"Business Services",
            "type":"Services"
        }
    ],
    "sg:phone":"+1 603 882 1400",
    "sg:postcode":"03290",
    "sg:province":"NH",
    "sg:tags":[
        "inspection"
    ],
    "wof:name":"Drougas Inspections LLC",
    "wof:placetype":"venue"
},
  "geometry": {"coordinates":[-71.077169,43.104889],"type":"Point"}
}