{
  "type": "Feature",
  "properties": {
    "addr:full":"5 Plaistow Rd Ste C47 Plaistow NH 03865",
    "addr:housenumber":"5",
    "addr:postcode":"03865",
    "addr:street":"Plaistow Rd Ste C47",
    "iso:country":"US",
    "sg:address":"5 Plaistow Rd Ste C47",
    "sg:city":"Plaistow",
    "sg:classifiers":[
        {
            "category":"Wholesale",
            "subcategory":"Office Equipment",
            "type":"Manufacturing & Wholesale Goods"
        },
        {
            "category":"Shopping",
            "subcategory":"Stationery & Office Supplies",
            "type":"Retail Goods"
        }
    ],
    "sg:phone":"+1 603 378 9465",
    "sg:postcode":"03865",
    "sg:province":"NH",
    "sg:tags":[
        "register",
        "autographic"
    ],
    "sg:website":"http://www.cartridgeworldusa.com",
    "wof:name":"Cartridge World USA",
    "wof:placetype":"venue"
},
  "geometry": {"coordinates":[-71.102903,42.815677],"type":"Point"}
}