{
  "type": "Feature",
  "properties": {
    "iso:country":"US",
    "sg:address":"9 Watson St",
    "sg:city":"Nashua",
    "sg:classifiers":[
        {
            "category":"Health Services",
            "subcategory":"Doctor",
            "type":"Services"
        },
        {
            "category":"Health Services",
            "subcategory":"Hospital",
            "type":"Services"
        }
    ],
    "sg:phone":"+1 603 889 1800",
    "sg:postcode":"03064",
    "sg:province":"NH",
    "sg:tags":[
        "consultant",
        "medical",
        "practice",
        "nursing",
        "home"
    ],
    "wof:name":"Lks Services",
    "wof:placetype":"venue"
},
  "geometry": {"coordinates":[-71.487968,42.774861],"type":"Point"}
}