{
  "type": "Feature",
  "properties": {
    "iso:country":"US",
    "sg:address":"256 Lafayette Rd",
    "sg:city":"Seabrook",
    "sg:classifiers":[
        {
            "category":"Personal",
            "subcategory":"Tattoo Parlor",
            "type":"Services"
        }
    ],
    "sg:phone":"+1 603 474 8754",
    "sg:postcode":"03874",
    "sg:province":"NH",
    "sg:tags":[
        "tattooing"
    ],
    "wof:name":"Jim's Tattoo Studio",
    "wof:placetype":"venue"
},
  "geometry": {"coordinates":[-70.867367,42.881345],"type":"Point"}
}