{
  "type": "Feature",
  "properties": {
    "addr:full":"21 F St Hampton NH 03842",
    "addr:housenumber":"21",
    "addr:postcode":"03842",
    "addr:street":"F St",
    "iso:country":"US",
    "sg:address":"21 F St",
    "sg:city":"Hampton",
    "sg:classifiers":[
        {
            "category":"Organizations",
            "subcategory":"Religious Organization",
            "type":"Services"
        }
    ],
    "sg:phone":"+1 603 926 2911",
    "sg:postcode":"03842",
    "sg:province":"NH",
    "wof:name":"Campus Crusade For Christ",
    "wof:placetype":"venue"
},
  "geometry": {"coordinates":[-70.811398,42.908798],"type":"Point"}
}