{
  "type": "Feature",
  "properties": {
    "iso:country":"US",
    "sg:address":"1095 Hanover St",
    "sg:city":"Manchester",
    "sg:classifiers":[
        {
            "category":"Autos & Motor Vehicles",
            "subcategory":"Fuel & Gas Station",
            "type":"Retail Goods"
        }
    ],
    "sg:phone":"+1 603 623 9350",
    "sg:postcode":"03104",
    "sg:province":"NH",
    "sg:tags":[
        "oil"
    ],
    "wof:name":"KWIK Stop-Mobile",
    "wof:placetype":"venue"
},
  "geometry": {"coordinates":[-71.41619900000001,42.987564],"type":"Point"}
}