{
  "type": "Feature",
  "properties": {
    "iso:country":"US",
    "sg:address":"6 Sawmill Rd",
    "sg:city":"Gilford",
    "sg:classifiers":[
        {
            "category":"Autos & Motor Vehicles",
            "subcategory":"Automobile Sales",
            "type":"Retail Goods"
        }
    ],
    "sg:phone":"+1 603 528 1944",
    "sg:postcode":"03249",
    "sg:province":"NH",
    "sg:tags":[
        "car",
        "dealer"
    ],
    "wof:name":"Lemay's Auto Sales",
    "wof:placetype":"venue"
},
  "geometry": {"coordinates":[-71.439567,43.532388],"type":"Point"}
}