{
  "type": "Feature",
  "properties": {
    "iso:country":"US",
    "sg:address":"31 Norton Rd",
    "sg:city":"Hillsboro",
    "sg:classifiers":[
        {
            "category":"Building & Trades",
            "subcategory":"Construction",
            "type":"Services"
        }
    ],
    "sg:phone":"+1 603 464 6400",
    "sg:postcode":"03244",
    "sg:province":"NH",
    "sg:tags":[
        "fabricator",
        "metal"
    ],
    "sg:website":"www.barettandgould.com",
    "wof:name":"Barett & Gould Inc",
    "wof:placetype":"venue"
},
  "geometry": {"coordinates":[-71.886297,43.117669],"type":"Point"}
}