{
  "type": "Feature",
  "properties": {
    "iso:country":"US",
    "sg:address":"957 Union Ave",
    "sg:city":"Laconia",
    "sg:classifiers":[
        {
            "category":"Real Estate",
            "subcategory":"Real Estate Agent",
            "type":"Services"
        }
    ],
    "sg:phone":"+1 603 524 9291",
    "sg:postcode":"03246",
    "sg:province":"NH",
    "wof:name":"Mid-Towne Realty",
    "wof:placetype":"venue"
},
  "geometry": {"coordinates":[-71.459425,43.551908],"type":"Point"}
}