{
  "type": "Feature",
  "properties": {
    "iso:country":"US",
    "sg:address":"312 Daniel Webster Hwy",
    "sg:city":"Meredith",
    "sg:classifiers":[
        {
            "category":"Food & Beverages",
            "subcategory":"Candy",
            "type":"Retail Goods"
        }
    ],
    "sg:phone":"+1 603 279 5175",
    "sg:postcode":"03253",
    "sg:province":"NH",
    "sg:tags":[
        "confectionery"
    ],
    "wof:name":"Lee's Candy Kitchen",
    "wof:placetype":"venue"
},
  "geometry": {"coordinates":[-71.500102,43.658287],"type":"Point"}
}