{
  "type": "Feature",
  "properties": {
    "addr:full":"35 Portsmouth Ave Stratham NH 03885",
    "addr:housenumber":"35",
    "addr:postcode":"03885",
    "addr:street":"Portsmouth Ave",
    "iso:country":"US",
    "sg:address":"35 Portsmouth Ave",
    "sg:city":"Stratham",
    "sg:classifiers":[
        {
            "category":"Autos & Motor Vehicles",
            "subcategory":"Auto Supplies",
            "type":"Retail Goods"
        }
    ],
    "sg:phone":"+1 603 778 0516",
    "sg:postcode":"03885",
    "sg:province":"NH",
    "wof:name":"Sullivan Tire Co Inc",
    "wof:placetype":"venue"
},
  "geometry": {"coordinates":[-70.920799,43.001064],"type":"Point"}
}