{
  "type": "Feature",
  "properties": {
    "iso:country":"US",
    "sg:address":"52 Ashworth Ave",
    "sg:city":"Hampton",
    "sg:classifiers":[
        {
            "category":"Travel",
            "subcategory":"Hotels & Motels",
            "type":"Entertainment"
        }
    ],
    "sg:phone":"+1 603 926 3925",
    "sg:postcode":"03842",
    "sg:province":"NH",
    "sg:tags":[
        "operation"
    ],
    "wof:name":"Janmere Motel",
    "wof:placetype":"venue"
},
  "geometry": {"coordinates":[-70.81241199999999,42.910399],"type":"Point"}
}