{
  "type": "Feature",
  "properties": {
    "iso:country":"US",
    "sg:address":"885 Londonderry Tpke",
    "sg:city":"Auburn",
    "sg:classifiers":[
        {
            "category":"Building & Trades",
            "subcategory":"Construction",
            "type":"Services"
        }
    ],
    "sg:phone":"+1 603 627 8995",
    "sg:postcode":"03032",
    "sg:province":"NH",
    "sg:tags":[
        "industrial"
    ],
    "wof:name":"Morton Buildings Inc",
    "wof:placetype":"venue"
},
  "geometry": {"coordinates":[-71.350364,42.947593],"type":"Point"}
}