{
  "type": "Feature",
  "properties": {
    "iso:country":"US",
    "sg:address":"683 5th Ave",
    "sg:city":"Berlin",
    "sg:classifiers":[
        {
            "category":"Retail",
            "subcategory":"Repair Shop",
            "type":"Services"
        }
    ],
    "sg:phone":"+1 603 752 0038",
    "sg:postcode":"03570",
    "sg:province":"NH",
    "wof:name":"Still Life Taxidermy",
    "wof:placetype":"venue"
},
  "geometry": {"coordinates":[-71.190321,44.471942],"type":"Point"}
}