{
  "type": "Feature",
  "properties": {
    "iso:country":"US",
    "sg:address":"173 Hanover St",
    "sg:city":"Lebanon",
    "sg:classifiers":[
        {
            "category":"Autos & Motor Vehicles",
            "subcategory":"Auto Supplies",
            "type":"Retail Goods"
        }
    ],
    "sg:phone":"+1 603 298 8708",
    "sg:postcode":"03766",
    "sg:province":"NH",
    "sg:tags":[
        "automobile",
        "parts"
    ],
    "wof:name":"Bailey Brothers",
    "wof:placetype":"venue"
},
  "geometry": {"coordinates":[-72.253289,43.651078],"type":"Point"}
}