{
  "type": "Feature",
  "properties": {
    "iso:country":"US",
    "sg:address":"75 Calef Hwy",
    "sg:city":"Epping",
    "sg:classifiers":[
        {
            "category":"Personal",
            "subcategory":"Beauty Salon",
            "type":"Services"
        }
    ],
    "sg:phone":"+1 603 679 3891",
    "sg:postcode":"03042",
    "sg:province":"NH",
    "wof:name":"Smart Style Family Hair Salon",
    "wof:placetype":"venue"
},
  "geometry": {"coordinates":[-71.073852,43.025189],"type":"Point"}
}