{
  "type": "Feature",
  "properties": {
    "iso:country":"US",
    "sg:address":"1164 Brownfield Rd",
    "sg:city":"Center Conway",
    "sg:classifiers":[
        {
            "category":"Real Estate",
            "subcategory":"Surveying",
            "type":"Services"
        }
    ],
    "sg:phone":"+1 603 447 2254",
    "sg:postcode":"03813",
    "sg:province":"NH",
    "sg:tags":[
        "surveyor"
    ],
    "wof:name":"Thaddeus Thorne-Surveys",
    "wof:placetype":"venue"
},
  "geometry": {"coordinates":[-71.029343,43.960768],"type":"Point"}
}