{
  "type": "Feature",
  "properties": {
    "iso:country":"US",
    "sg:address":"26 Academy St",
    "sg:city":"Laconia",
    "sg:classifiers":[
        {
            "category":"Government",
            "subcategory":"Court House",
            "type":"Public Place"
        }
    ],
    "sg:phone":"+1 603 524 4128",
    "sg:postcode":"03246",
    "sg:province":"NH",
    "sg:tags":[
        "city"
    ],
    "wof:name":"Laconia District Court",
    "wof:placetype":"venue"
},
  "geometry": {"coordinates":[-71.47001299999999,43.523993],"type":"Point"}
}