{
  "type": "Feature",
  "properties": {
    "iso:country":"US",
    "sg:address":"4 Aladdin Rd",
    "sg:city":"Windham",
    "sg:classifiers":[
        {
            "category":"Personal",
            "type":"Services"
        }
    ],
    "sg:phone":"+1 603 234 2188",
    "sg:postcode":"03087",
    "sg:province":"NH",
    "wof:name":"Gca Group Inc",
    "wof:placetype":"venue"
},
  "geometry": {"coordinates":[-71.252775,42.823442],"type":"Point"}
}