{
  "type": "Feature",
  "properties": {
    "iso:country":"US",
    "sg:address":"40 Meredith Center Rd",
    "sg:city":"Meredith",
    "sg:classifiers":[
        {
            "category":"Education",
            "subcategory":"School",
            "type":"Public Place"
        }
    ],
    "sg:phone":"+1 603 279 5680",
    "sg:postcode":"03253",
    "sg:province":"NH",
    "wof:name":"Lakeland School Inc",
    "wof:placetype":"venue"
},
  "geometry": {"coordinates":[-71.544949,43.621564],"type":"Point"}
}