{
  "type": "Feature",
  "properties": {
    "addr:full":"39 Newcastle Ave Portsmouth NH 03801",
    "addr:housenumber":"39",
    "addr:postcode":"03801",
    "addr:street":"Newcastle Ave",
    "iso:country":"US",
    "sg:address":"39 Newcastle Ave",
    "sg:city":"Portsmouth",
    "sg:classifiers":[
        {
            "category":"Building & Trades",
            "subcategory":"Plumbing",
            "type":"Services"
        }
    ],
    "sg:phone":"+1 603 430 3077",
    "sg:postcode":"03801",
    "sg:province":"NH",
    "sg:tags":[
        "plumbing",
        "contractor"
    ],
    "wof:name":"Viking Plumbing & Heating",
    "wof:placetype":"venue"
},
  "geometry": {"coordinates":[-70.752107,43.070276],"type":"Point"}
}