{
  "type": "Feature",
  "properties": {
    "iso:country":"US",
    "sg:address":"23 Pillsbury Rd",
    "sg:city":"Grantham",
    "sg:classifiers":[
        {
            "category":"Professional",
            "type":"Services"
        }
    ],
    "sg:phone":"+1 603 863 3506",
    "sg:postcode":"03753",
    "sg:province":"NH",
    "sg:tags":[
        "establishment"
    ],
    "wof:name":"Rempak",
    "wof:placetype":"venue"
},
  "geometry": {"coordinates":[-72.13675499999999,43.495176],"type":"Point"}
}