{
  "type": "Feature",
  "properties": {
    "iso:country":"US",
    "sg:address":"93 Church St",
    "sg:city":"Goffstown",
    "sg:classifiers":[
        {
            "category":"Government",
            "subcategory":"Office",
            "type":"Public Place"
        }
    ],
    "sg:phone":"+1 603 497 2471",
    "sg:postcode":"03045",
    "sg:province":"NH",
    "sg:tags":[
        "state",
        "program"
    ],
    "wof:name":"Transportation Dept-Patrol",
    "wof:placetype":"venue"
},
  "geometry": {"coordinates":[-71.60991199999999,43.022051],"type":"Point"}
}