{
  "type": "Feature",
  "properties": {
    "iso:country":"US",
    "sg:address":"472 Middle Winchendon Rd",
    "sg:city":"Rindge",
    "sg:classifiers":[
        {
            "category":"Professional",
            "subcategory":"Art Services",
            "type":"Services"
        }
    ],
    "sg:phone":"+1 603 899 6167",
    "sg:postcode":"03461",
    "sg:province":"NH",
    "sg:tags":[
        "designer",
        "display",
        "producer"
    ],
    "wof:name":"New Concepts Design & Fabrication",
    "wof:placetype":"venue"
},
  "geometry": {"coordinates":[-72.021856,42.737365],"type":"Point"}
}