{
  "type": "Feature",
  "properties": {
    "addr:full":"32 Elk Dr Bedford NH 03110",
    "addr:housenumber":"32",
    "addr:postcode":"03110",
    "addr:street":"Elk Dr",
    "iso:country":"US",
    "sg:address":"32 Elk Dr",
    "sg:city":"Bedford",
    "sg:classifiers":[
        {
            "category":"Real Estate",
            "subcategory":"Real Estate Agent",
            "type":"Services"
        }
    ],
    "sg:phone":"+1 603 472 3808",
    "sg:postcode":"03110",
    "sg:province":"NH",
    "wof:name":"Equity Alliance Corp",
    "wof:placetype":"venue"
},
  "geometry": {"coordinates":[-71.555111,42.916835],"type":"Point"}
}