{
  "type": "Feature",
  "properties": {
    "iso:country":"US",
    "sg:address":"490 Amherst St",
    "sg:city":"Manchester",
    "sg:classifiers":[
        {
            "category":"Professional",
            "subcategory":"Management & Consulting",
            "type":"Services"
        }
    ],
    "sg:phone":"+1 603 627 0000",
    "sg:postcode":"03104",
    "sg:province":"NH",
    "sg:tags":[
        "business"
    ],
    "wof:name":"Ne Leadership Counsel",
    "wof:placetype":"venue"
},
  "geometry": {"coordinates":[-71.444362,42.991989],"type":"Point"}
}