{
  "type": "Feature",
  "properties": {
    "addr:full":"35 Main St Peterborough NH 03458",
    "addr:housenumber":"35",
    "addr:postcode":"03458",
    "addr:street":"Main St",
    "iso:country":"US",
    "sg:address":"35 Main St",
    "sg:city":"Peterborough",
    "sg:classifiers":[
        {
            "category":"Professional",
            "subcategory":"Business Services",
            "type":"Services"
        }
    ],
    "sg:phone":"+1 603 532 4747",
    "sg:postcode":"03458",
    "sg:province":"NH",
    "sg:tags":[
        "transcribing",
        "disc"
    ],
    "wof:name":"Timberline Communications Inc",
    "wof:placetype":"venue"
},
  "geometry": {"coordinates":[-71.949361,42.877511],"type":"Point"}
}