{
  "type": "Feature",
  "properties": {
    "iso:country":"US",
    "sg:address":"401 South St",
    "sg:city":"Littleton",
    "sg:classifiers":[
        {
            "category":"Organizations",
            "subcategory":"Community Association",
            "type":"Services"
        }
    ],
    "sg:phone":"+1 603 444 8831",
    "sg:postcode":"03561",
    "sg:province":"NH",
    "wof:name":"Hinton Acdemic Special Prj LLC",
    "wof:placetype":"venue"
},
  "geometry": {"coordinates":[-71.786644,44.304853],"type":"Point"}
}