{
  "type": "Feature",
  "properties": {
    "addr:full":"64 Court St Laconia NH 03246",
    "addr:housenumber":"64",
    "addr:postcode":"03246",
    "addr:street":"Court St",
    "iso:country":"US",
    "sg:address":"64 Court St",
    "sg:city":"Laconia",
    "sg:classifiers":[
        {
            "category":"Government",
            "subcategory":"Fire Station",
            "type":"Public Place"
        }
    ],
    "sg:phone":"+1 603 000 1111",
    "sg:postcode":"03246",
    "sg:province":"NH",
    "sg:tags":[
        "department"
    ],
    "wof:name":"Franklin Fire Dept",
    "wof:placetype":"venue"
},
  "geometry": {"coordinates":[-71.469393,43.524916],"type":"Point"}
}