{
  "type": "Feature",
  "properties": {
    "iso:country":"US",
    "sg:address":"773 Portland St",
    "sg:city":"Rochester",
    "sg:classifiers":[
        {
            "category":"Education",
            "subcategory":"School",
            "type":"Public Place"
        }
    ],
    "sg:phone":"+1 603 332 2146",
    "sg:postcode":"03868",
    "sg:province":"NH",
    "wof:name":"East Rochester Elementary Schl",
    "wof:placetype":"venue"
},
  "geometry": {"coordinates":[-70.946665,43.322885],"type":"Point"}
}