{
  "type": "Feature",
  "properties": {
    "iso:country":"US",
    "sg:address":"24 Twin Birch Ln",
    "sg:city":"Sunapee",
    "sg:classifiers":[
        {
            "category":"Building & Trades",
            "subcategory":"Construction",
            "type":"Services"
        }
    ],
    "sg:phone":"+1 603 763 3443",
    "sg:postcode":"03782",
    "sg:province":"NH",
    "sg:tags":[
        "contractor"
    ],
    "wof:name":"Foremost Builders",
    "wof:placetype":"venue"
},
  "geometry": {"coordinates":[-72.115148,43.414641],"type":"Point"}
}