{
  "type": "Feature",
  "properties": {
    "addr:full":"30 Gigante Dr Hampstead NH 03841",
    "addr:housenumber":"30",
    "addr:postcode":"03841",
    "addr:street":"Gigante Dr",
    "iso:country":"US",
    "sg:address":"30 Gigante Dr",
    "sg:city":"Hampstead",
    "sg:classifiers":[
        {
            "category":"Manufacturing",
            "subcategory":"Wood Products",
            "type":"Manufacturing & Wholesale Goods"
        },
        {
            "category":"Building & Trades",
            "subcategory":"Construction",
            "type":"Services"
        }
    ],
    "sg:phone":"+1 603 329 6026",
    "sg:postcode":"03841",
    "sg:province":"NH",
    "sg:tags":[
        "millwork-wholesale",
        "manufacturer",
        "millwork",
        "carpenter"
    ],
    "wof:name":"Barlow Architectural Millwork",
    "wof:placetype":"venue"
},
  "geometry": {"coordinates":[-71.17461,42.8574],"type":"Point"}
}