{
  "type": "Feature",
  "properties": {
    "iso:country":"US",
    "sg:address":"825 Lake St",
    "sg:city":"Bristol",
    "sg:classifiers":[
        {
            "category":"Restaurant",
            "type":"Food & Drink"
        }
    ],
    "sg:phone":"+1 603 744 6886",
    "sg:postcode":"03222",
    "sg:province":"NH",
    "wof:name":"Village Pizza Of Bristol",
    "wof:placetype":"venue"
},
  "geometry": {"coordinates":[-71.74180699999999,43.609353],"type":"Point"}
}