{
  "type": "Feature",
  "properties": {
    "iso:country":"US",
    "sg:address":"446 Central Ave",
    "sg:city":"Dover",
    "sg:classifiers":[
        {
            "category":"Restaurant",
            "type":"Food & Drink"
        }
    ],
    "sg:phone":"+1 603 742 2522",
    "sg:postcode":"03820",
    "sg:province":"NH",
    "sg:tags":[
        "caterer"
    ],
    "wof:name":"Christopher David's",
    "wof:placetype":"venue"
},
  "geometry": {"coordinates":[-70.874104,43.197311],"type":"Point"}
}