{
  "type": "Feature",
  "properties": {
    "iso:country":"US",
    "sg:address":"15 Pine St",
    "sg:city":"Seabrook",
    "sg:classifiers":[
        {
            "category":"Recreation",
            "subcategory":"Amusement Park",
            "type":"Entertainment"
        }
    ],
    "sg:phone":"+1 603 474 5424",
    "sg:postcode":"03874",
    "sg:province":"NH",
    "wof:name":"Fiesta Shows",
    "wof:placetype":"venue"
},
  "geometry": {"coordinates":[-70.87273999999999,42.889213],"type":"Point"}
}