{
  "type": "Feature",
  "properties": {
    "addr:full":"13 Cyr Dr Hooksett NH 03106",
    "addr:housenumber":"13",
    "addr:postcode":"03106",
    "addr:street":"Cyr Dr",
    "iso:country":"US",
    "sg:address":"13 Cyr Dr",
    "sg:city":"Hooksett",
    "sg:classifiers":[
        {
            "category":"Professional",
            "subcategory":"Business Services",
            "type":"Services"
        }
    ],
    "sg:phone":"+1 603 485 8282",
    "sg:postcode":"03106",
    "sg:province":"NH",
    "wof:name":"R&S Enterprises",
    "wof:placetype":"venue"
},
  "geometry": {"coordinates":[-71.469381,43.093762],"type":"Point"}
}