{
  "type": "Feature",
  "properties": {
    "iso:country":"US",
    "sg:address":"36 Park St",
    "sg:city":"Wilton",
    "sg:classifiers":[
        {
            "category":"Professional",
            "type":"Services"
        }
    ],
    "sg:phone":"+1 603 673 1224",
    "sg:postcode":"03086",
    "sg:province":"NH",
    "sg:tags":[
        "establishment"
    ],
    "wof:name":"Haggerty D",
    "wof:placetype":"venue"
},
  "geometry": {"coordinates":[-71.736205,42.844118],"type":"Point"}
}