{
  "type": "Feature",
  "properties": {
    "addr:full":"11 Randolph Rd Concord NH 03301",
    "addr:housenumber":"11",
    "addr:postcode":"03301",
    "addr:street":"Randolph Rd",
    "iso:country":"US",
    "sg:address":"11 Randolph Rd",
    "sg:city":"Concord",
    "sg:classifiers":[
        {
            "category":"Communications",
            "subcategory":"Film & Video Production",
            "type":"Services"
        }
    ],
    "sg:phone":"+1 603 228 4637",
    "sg:postcode":"03301",
    "sg:province":"NH",
    "sg:tags":[
        "motion"
    ],
    "wof:name":"Capital Productions LLC",
    "wof:placetype":"venue"
},
  "geometry": {"coordinates":[-71.530477,43.240496],"type":"Point"}
}