{
  "type": "Feature",
  "properties": {
    "iso:country":"US",
    "sg:address":"268 Spruce St",
    "sg:city":"Manchester",
    "sg:classifiers":[
        {
            "category":"Professional",
            "subcategory":"Business Services",
            "type":"Services"
        }
    ],
    "sg:phone":"+1 603 656 9077",
    "sg:postcode":"03103",
    "sg:province":"NH",
    "wof:name":"Eureka Flight",
    "wof:placetype":"venue"
},
  "geometry": {"coordinates":[-71.45156,42.9866],"type":"Point"}
}