{
  "type": "Feature",
  "properties": {
    "iso:country":"US",
    "sg:address":"116 Perimeter Rd",
    "sg:city":"Nashua",
    "sg:classifiers":[
        {
            "category":"Professional",
            "subcategory":"Engineering",
            "type":"Services"
        },
        {
            "category":"Building & Trades",
            "subcategory":"Electrical",
            "type":"Services"
        },
        {
            "category":"Professional",
            "subcategory":"Computer Services",
            "type":"Services"
        }
    ],
    "sg:phone":"+1 603 880 4601",
    "sg:postcode":"03063",
    "sg:province":"NH",
    "sg:tags":[
        "designer",
        "electrician",
        "electric",
        "rooms-installation",
        "consultant",
        "system",
        "integration",
        "equipment",
        "industrial",
        "contractors-commercial",
        "engineer"
    ],
    "sg:website":"http://www.normaneday.com",
    "wof:name":"Norman E Day Inc",
    "wof:placetype":"venue"
},
  "geometry": {"coordinates":[-71.516946,42.778826],"type":"Point"}
}