{
  "type": "Feature",
  "properties": {
    "iso:country":"US",
    "sg:address":"1 Wire Rd",
    "sg:city":"Merrimack",
    "sg:classifiers":[
        {
            "category":"Insurance",
            "subcategory":"Insurance Agent",
            "type":"Services"
        },
        {
            "category":"Insurance",
            "subcategory":"Hazard Insurance",
            "type":"Services"
        },
        {
            "category":"Insurance",
            "subcategory":"Title Insurance",
            "type":"Services"
        },
        {
            "category":"Insurance",
            "subcategory":"Life Insurance",
            "type":"Services"
        }
    ],
    "sg:phone":"+1 603 429 8800",
    "sg:postcode":"03054",
    "sg:province":"NH",
    "sg:tags":[
        "business",
        "auto",
        "commercial",
        "homeowner",
        "motorcycle",
        "renter"
    ],
    "wof:name":"Allstate Insurance Company - James Parolin",
    "wof:placetype":"venue"
},
  "geometry": {"coordinates":[-71.49342300000001,42.869141],"type":"Point"}
}