{
  "type": "Feature",
  "properties": {
    "iso:country":"US",
    "sg:address":"4 Earle Dr",
    "sg:city":"Lee",
    "sg:classifiers":[
        {
            "category":"Professional",
            "subcategory":"Business Services",
            "type":"Services"
        }
    ],
    "sg:phone":"+1 603 659 2120",
    "sg:postcode":"03861",
    "sg:province":"NH",
    "sg:tags":[
        "water",
        "treatment"
    ],
    "wof:name":"Aquafax Inc",
    "wof:placetype":"venue"
},
  "geometry": {"coordinates":[-71.033964,43.092829],"type":"Point"}
}