{
  "type": "Feature",
  "properties": {
    "iso:country":"US",
    "sg:address":"631 Acton Ridge Rd",
    "sg:city":"East Wakefield",
    "sg:classifiers":[
        {
            "category":"Travel",
            "subcategory":"Campground",
            "type":"Entertainment"
        }
    ],
    "sg:phone":"+1 603 522 8824",
    "sg:postcode":"03830",
    "sg:province":"NH",
    "sg:tags":[
        "operation",
        "trailer"
    ],
    "wof:name":"Lake Ivanhoe Inn & Campsites",
    "wof:placetype":"venue"
},
  "geometry": {"coordinates":[-70.977087,43.603663],"type":"Point"}
}