{
  "type": "Feature",
  "properties": {
    "iso:country":"US",
    "sg:address":"160 Maryland Ave",
    "sg:city":"Manchester",
    "sg:classifiers":[
        {
            "category":"Retail",
            "subcategory":"Repair Shop",
            "type":"Services"
        }
    ],
    "sg:phone":"+1 603 623 5007",
    "sg:postcode":"03104",
    "sg:province":"NH",
    "sg:tags":[
        "player",
        "recorder",
        "video"
    ],
    "wof:name":"Bob Simard Radio & TV Repair",
    "wof:placetype":"venue"
},
  "geometry": {"coordinates":[-71.423469,42.991486],"type":"Point"}
}