{
  "type": "Feature",
  "properties": {
    "addr:full":"33 School St Concord NH 03301",
    "addr:housenumber":"33",
    "addr:postcode":"03301",
    "addr:street":"School St",
    "iso:country":"US",
    "sg:address":"33 School St",
    "sg:city":"Concord",
    "sg:classifiers":[
        {
            "category":"Organizations",
            "subcategory":"Religious Organization",
            "type":"Services"
        }
    ],
    "sg:phone":"+1 603 224 0818",
    "sg:postcode":"03301",
    "sg:province":"NH",
    "wof:name":"First Church Christ Scientist",
    "wof:placetype":"venue"
},
  "geometry": {"coordinates":[-71.537654,43.205868],"type":"Point"}
}