{
  "type": "Feature",
  "properties": {
    "addr:full":"900 Beech St Manchester NH 03104",
    "addr:housenumber":"900",
    "addr:postcode":"03104",
    "addr:street":"Beech St",
    "iso:country":"US",
    "sg:address":"900 Beech St",
    "sg:city":"Manchester",
    "sg:classifiers":[
        {
            "category":"Organizations",
            "subcategory":"Membership Organization",
            "type":"Services"
        }
    ],
    "sg:phone":"+1 603 647 1766",
    "sg:postcode":"03104",
    "sg:province":"NH",
    "sg:tags":[
        "athletic"
    ],
    "wof:name":"Manchester North Soccer League",
    "wof:placetype":"venue"
},
  "geometry": {"coordinates":[-71.457739,43.00597],"type":"Point"}
}