{
  "type": "Feature",
  "properties": {
    "addr:full":"403 Weirs Rd Gilford NH 03249",
    "addr:housenumber":"403",
    "addr:postcode":"03249",
    "addr:street":"Weirs Rd",
    "iso:country":"US",
    "sg:address":"403 Weirs Rd",
    "sg:city":"Gilford",
    "sg:classifiers":[
        {
            "category":"Building & Trades",
            "subcategory":"Electrical",
            "type":"Services"
        }
    ],
    "sg:phone":"+1 603 366 7300",
    "sg:postcode":"03249",
    "sg:province":"NH",
    "sg:tags":[
        "electrical",
        "electric",
        "contractor"
    ],
    "wof:name":"Electrical Systems & Controls",
    "wof:placetype":"venue"
},
  "geometry": {"coordinates":[-71.428111,43.59401],"type":"Point"}
}