{
  "type": "Feature",
  "properties": {
    "iso:country":"US",
    "sg:address":"84 Pleasant St",
    "sg:city":"Portsmouth",
    "sg:classifiers":[
        {
            "category":"Autos & Motor Vehicles",
            "subcategory":"Auto Supplies",
            "type":"Retail Goods"
        }
    ],
    "sg:phone":"+1 603 431 3112",
    "sg:postcode":"03801",
    "sg:province":"NH",
    "sg:tags":[
        "equipment",
        "racing",
        "car",
        "automobile"
    ],
    "wof:name":"Powerwerks",
    "wof:placetype":"venue"
},
  "geometry": {"coordinates":[-70.75705499999999,43.075836],"type":"Point"}
}