{
  "type": "Feature",
  "properties": {
    "iso:country":"US",
    "sg:address":"55 Milford St",
    "sg:city":"Brookline",
    "sg:classifiers":[
        {
            "category":"Building & Trades",
            "subcategory":"Plumbing",
            "type":"Services"
        },
        {
            "category":"Building & Trades",
            "subcategory":"Construction",
            "type":"Services"
        }
    ],
    "sg:phone":"+1 603 673 6178",
    "sg:postcode":"03033",
    "sg:province":"NH",
    "sg:tags":[
        "plumber",
        "industrial",
        "system",
        "specialty",
        "heating",
        "contractors-commercial",
        "contractor",
        "air conditioning"
    ],
    "wof:name":"Whitcomb Plumbing & Heating",
    "wof:placetype":"venue"
},
  "geometry": {"coordinates":[-71.665094,42.74548],"type":"Point"}
}