{
  "type": "Feature",
  "properties": {
    "iso:country":"US",
    "sg:address":"664 Portland St",
    "sg:city":"Rochester",
    "sg:classifiers":[
        {
            "category":"Building & Trades",
            "subcategory":"Construction",
            "type":"Services"
        }
    ],
    "sg:phone":"+1 603 335 7236",
    "sg:postcode":"03867",
    "sg:province":"NH",
    "sg:tags":[
        "carpentry",
        "contractor"
    ],
    "wof:name":"Mikes Carpentry",
    "wof:placetype":"venue"
},
  "geometry": {"coordinates":[-70.95249699999999,43.317971],"type":"Point"}
}