{
  "type": "Feature",
  "properties": {
    "iso:country":"US",
    "sg:address":"1 Walton Rd",
    "sg:city":"Seabrook",
    "sg:classifiers":[
        {
            "category":"Building & Trades",
            "subcategory":"Construction",
            "type":"Services"
        }
    ],
    "sg:phone":"+1 603 394 7040",
    "sg:postcode":"03874",
    "sg:province":"NH",
    "sg:tags":[
        "excavating",
        "contractor"
    ],
    "wof:name":"Plan It Excavation",
    "wof:placetype":"venue"
},
  "geometry": {"coordinates":[-70.87051099999999,42.876221],"type":"Point"}
}