{
  "type": "Feature",
  "properties": {
    "iso:country":"US",
    "sg:address":"308 Riverside Dr",
    "sg:city":"Littleton",
    "sg:classifiers":[
        {
            "category":"Utilities",
            "subcategory":"Fuel Oil & Lpg",
            "type":"Services"
        }
    ],
    "sg:phone":"+1 603 837 9395",
    "sg:postcode":"03561",
    "sg:province":"NH",
    "wof:name":"Stiles Fuel Co Inc",
    "wof:placetype":"venue"
},
  "geometry": {"coordinates":[-71.786761,44.306584],"type":"Point"}
}