{
  "type": "Feature",
  "properties": {
    "iso:country":"US",
    "sg:address":"8 Benrus St",
    "sg:city":"Nashua",
    "sg:classifiers":[
        {
            "category":"Building & Trades",
            "subcategory":"Equipment Rental",
            "type":"Services"
        }
    ],
    "sg:phone":"+1 603 860 2375",
    "sg:postcode":"03060",
    "sg:province":"NH",
    "wof:name":"Lehto Marylin Rental",
    "wof:placetype":"venue"
},
  "geometry": {"coordinates":[-71.440252,42.728741],"type":"Point"}
}