{
  "type": "Feature",
  "properties": {
    "iso:country":"US",
    "sg:address":"274 Newmarket Rd",
    "sg:city":"Durham",
    "sg:classifiers":[
        {
            "category":"Building & Trades",
            "subcategory":"Construction",
            "type":"Services"
        }
    ],
    "sg:phone":"+1 603 224 2550",
    "sg:postcode":"03824",
    "sg:province":"NH",
    "sg:tags":[
        "commercial",
        "contractor"
    ],
    "wof:name":"Esprit Corp",
    "wof:placetype":"venue"
},
  "geometry": {"coordinates":[-70.93289,43.095932],"type":"Point"}
}