{
  "type": "Feature",
  "properties": {
    "addr:full":"764 2nd St Manchester NH 03102",
    "addr:housenumber":"764",
    "addr:postcode":"03102",
    "addr:street":"2Nd St",
    "iso:country":"US",
    "sg:address":"764 2nd St",
    "sg:city":"Manchester",
    "sg:classifiers":[
        {
            "category":"Autos & Motor Vehicles",
            "subcategory":"Automobile Sales",
            "type":"Retail Goods"
        }
    ],
    "sg:phone":"+1 603 668 2411",
    "sg:postcode":"03102",
    "sg:province":"NH",
    "sg:tags":[
        "car",
        "dealer"
    ],
    "sg:website":"www.manchester.sne1.com",
    "wof:name":"Subaru Of Manchester",
    "wof:placetype":"venue"
},
  "geometry": {"coordinates":[-71.477295,42.97191],"type":"Point"}
}