{
  "type": "Feature",
  "properties": {
    "iso:country":"US",
    "sg:address":"42 Cody St",
    "sg:city":"Manchester",
    "sg:classifiers":[
        {
            "category":"Local Transit",
            "type":"Transportation"
        }
    ],
    "sg:phone":"+1 603 625 2999",
    "sg:postcode":"03109",
    "sg:province":"NH",
    "sg:tags":[
        "passenger"
    ],
    "wof:name":"Executive Limousines",
    "wof:placetype":"venue"
},
  "geometry": {"coordinates":[-71.421764,42.981432],"type":"Point"}
}