{
  "type": "Feature",
  "properties": {
    "addr:full":"284 Hedgerose Ln Contoocook NH 03229",
    "addr:housenumber":"284",
    "addr:postcode":"03229",
    "addr:street":"Hedgerose Ln",
    "iso:country":"US",
    "sg:address":"284 Hedgerose Ln",
    "sg:city":"Contoocook",
    "sg:classifiers":[
        {
            "category":"Professional",
            "subcategory":"Computer Services",
            "type":"Services"
        }
    ],
    "sg:phone":"+1 603 226 3889",
    "sg:postcode":"03229",
    "sg:province":"NH",
    "sg:tags":[
        "consultant",
        "designer",
        "programing",
        "custom"
    ],
    "wof:name":"P C Telecom Inc",
    "wof:placetype":"venue"
},
  "geometry": {"coordinates":[-71.619983,43.187895],"type":"Point"}
}