{
  "type": "Feature",
  "properties": {
    "addr:full":"209 Athol Rd Winchester NH 03470",
    "addr:housenumber":"209",
    "addr:postcode":"03470",
    "addr:street":"Athol Rd",
    "iso:country":"US",
    "sg:address":"209 Athol Rd",
    "sg:city":"Winchester",
    "sg:classifiers":[
        {
            "category":"Sports & Exercise",
            "subcategory":"Race Track",
            "type":"Entertainment"
        }
    ],
    "sg:phone":"+1 603 239 7217",
    "sg:postcode":"03470",
    "sg:province":"NH",
    "sg:tags":[
        "operation",
        "racing",
        "or"
    ],
    "wof:name":"A & L Racing",
    "wof:placetype":"venue"
},
  "geometry": {"coordinates":[-72.27132,42.747242],"type":"Point"}
}