{
  "type": "Feature",
  "properties": {
    "iso:country":"US",
    "sg:address":"144 Highland St",
    "sg:city":"Plymouth",
    "sg:classifiers":[
        {
            "category":"Health Services",
            "subcategory":"Doctor",
            "type":"Services"
        }
    ],
    "sg:phone":"+1 603 536 1441",
    "sg:postcode":"03264",
    "sg:province":"NH",
    "sg:tags":[
        "medical"
    ],
    "wof:name":"Drjohn Bentwood MD",
    "wof:placetype":"venue"
},
  "geometry": {"coordinates":[-71.709081,43.763489],"type":"Point"}
}