{
  "type": "Feature",
  "properties": {
    "addr:full":"2083 Dover Rd Epsom NH 03234",
    "addr:housenumber":"2083",
    "addr:postcode":"03234",
    "addr:street":"Dover Rd",
    "iso:country":"US",
    "sg:address":"2083 Dover Rd",
    "sg:city":"Epsom",
    "sg:phone":"+1 603 736 8148",
    "sg:postcode":"03234",
    "sg:province":"NH",
    "sg:tags":[
        "oil"
    ],
    "wof:name":"Johnson & Dix Oil & Propane",
    "wof:placetype":"venue"
},
  "geometry": {"coordinates":[-71.38168899999999,43.233688],"type":"Point"}
}