{
  "type": "Feature",
  "properties": {
    "iso:country":"US",
    "sg:address":"9 Horse Hill Rd",
    "sg:city":"Concord",
    "sg:classifiers":[
        {
            "category":"Recreation",
            "type":"Entertainment"
        }
    ],
    "sg:phone":"+1 603 753 9804",
    "sg:postcode":"03303",
    "sg:province":"NH",
    "sg:tags":[
        "charter",
        "boat"
    ],
    "wof:name":"Contoocook River Canoe Co",
    "wof:placetype":"venue"
},
  "geometry": {"coordinates":[-71.62523400000001,43.250442],"type":"Point"}
}