{
  "type": "Feature",
  "properties": {
    "addr:full":"17 Evergreen Dr Bow NH 03304",
    "addr:housenumber":"17",
    "addr:postcode":"03304",
    "addr:street":"Evergreen Dr",
    "iso:country":"US",
    "sg:address":"17 Evergreen Dr",
    "sg:city":"Bow",
    "sg:classifiers":[
        {
            "category":"Building & Trades",
            "subcategory":"Landscaping Services",
            "type":"Services"
        }
    ],
    "sg:phone":"+1 603 224 6605",
    "sg:postcode":"03304",
    "sg:province":"NH",
    "sg:tags":[
        "landscape",
        "contractor"
    ],
    "wof:name":"Capitol City Enterprises",
    "wof:placetype":"venue"
},
  "geometry": {"coordinates":[-71.61794,43.155194],"type":"Point"}
}