{
  "type": "Feature",
  "properties": {
    "addr:full":"15 Janet St Rochester NH 03867",
    "addr:housenumber":"15",
    "addr:postcode":"03867",
    "addr:street":"Janet St",
    "iso:country":"US",
    "sg:address":"15 Janet St",
    "sg:city":"Rochester",
    "sg:classifiers":[
        {
            "category":"Building & Trades",
            "subcategory":"Construction",
            "type":"Services"
        }
    ],
    "sg:phone":"+1 603 332 0246",
    "sg:postcode":"03867",
    "sg:province":"NH",
    "sg:tags":[
        "acoustical",
        "contractor"
    ],
    "wof:name":"John C Pratt Jr Acoustical",
    "wof:placetype":"venue"
},
  "geometry": {"coordinates":[-70.989211,43.296673],"type":"Point"}
}