{
  "type": "Feature",
  "properties": {
    "iso:country":"US",
    "sg:address":"30 Beacon St E",
    "sg:city":"Laconia",
    "sg:classifiers":[
        {
            "category":"Restaurant",
            "type":"Food & Drink"
        }
    ],
    "sg:phone":"+1 603 524 2366",
    "sg:postcode":"03246",
    "sg:province":"NH",
    "wof:name":"Soda Shoppe The",
    "wof:placetype":"venue"
},
  "geometry": {"coordinates":[-71.468829,43.527787],"type":"Point"}
}