{
  "type": "Feature",
  "properties": {
    "iso:country":"US",
    "sg:address":"18 School St",
    "sg:city":"Lebanon",
    "sg:classifiers":[
        {
            "category":"Organizations",
            "subcategory":"Religious Organization",
            "type":"Services"
        }
    ],
    "sg:phone":"+1 603 448 5478",
    "sg:postcode":"03766",
    "sg:province":"NH",
    "wof:name":"Methodist Church",
    "wof:placetype":"venue"
},
  "geometry": {"coordinates":[-72.25014299999999,43.640964],"type":"Point"}
}