{
  "type": "Feature",
  "properties": {
    "addr:full":"277 S Mast Rd Goffstown NH 03045",
    "addr:housenumber":"277",
    "addr:postcode":"03045",
    "addr:street":"S Mast Rd",
    "iso:country":"US",
    "sg:address":"277 S Mast Rd",
    "sg:city":"Goffstown",
    "sg:classifiers":[
        {
            "category":"Food & Beverages",
            "subcategory":"Groceries & Convenience Stores",
            "type":"Retail Goods"
        }
    ],
    "sg:phone":"+1 603 497 5860",
    "sg:postcode":"03045",
    "sg:province":"NH",
    "wof:name":"Goffstown Irving Mainway",
    "wof:placetype":"venue"
},
  "geometry": {"coordinates":[-71.542762,43.010369],"type":"Point"}
}