{
  "type": "Feature",
  "properties": {
    "addr:full":"132 Short Falls Rd Chichester NH 03258",
    "addr:housenumber":"132",
    "addr:postcode":"03258",
    "addr:street":"Short Falls Rd",
    "iso:country":"US",
    "sg:address":"132 Short Falls Rd",
    "sg:city":"Chichester",
    "sg:classifiers":[
        {
            "category":"Building & Trades",
            "subcategory":"Construction",
            "type":"Services"
        }
    ],
    "sg:phone":"+1 603 798 3075",
    "sg:postcode":"03258",
    "sg:province":"NH",
    "sg:tags":[
        "general",
        "contractor"
    ],
    "wof:name":"S Drew & Son",
    "wof:placetype":"venue"
},
  "geometry": {"coordinates":[-71.396649,43.218132],"type":"Point"}
}