{
  "type": "Feature",
  "properties": {
    "iso:country":"US",
    "sg:address":"111 Glendale Ave",
    "sg:city":"Manchester",
    "sg:classifiers":[
        {
            "category":"Building & Trades",
            "subcategory":"Pest Control",
            "type":"Services"
        }
    ],
    "sg:phone":"+1 603 623 2649",
    "sg:postcode":"03103",
    "sg:province":"NH",
    "wof:name":"Paramount Labs",
    "wof:placetype":"venue"
},
  "geometry": {"coordinates":[-71.435771,42.974677],"type":"Point"}
}