{
  "type": "Feature",
  "properties": {
    "iso:country":"US",
    "sg:address":"119 W Merrimack St",
    "sg:city":"Manchester",
    "sg:classifiers":[
        {
            "category":"Professional",
            "subcategory":"Lawyer & Legal Services",
            "type":"Services"
        }
    ],
    "sg:phone":"+1 603 622 7575",
    "sg:postcode":"03101",
    "sg:province":"NH",
    "sg:tags":[
        "attorney"
    ],
    "wof:name":"Joseph K Levasseur",
    "wof:placetype":"venue"
},
  "geometry": {"coordinates":[-71.466791,42.98944],"type":"Point"}
}