{
  "type": "Feature",
  "properties": {
    "addr:full":"13 Laconia Rd Belmont NH 03220",
    "addr:housenumber":"13",
    "addr:postcode":"03220",
    "addr:street":"Laconia Rd",
    "iso:country":"US",
    "sg:address":"13 Laconia Rd",
    "sg:city":"Belmont",
    "sg:classifiers":[
        {
            "category":"Retail",
            "subcategory":"Auto Rental",
            "type":"Services"
        }
    ],
    "sg:phone":"+1 603 527 1852",
    "sg:postcode":"03220",
    "sg:province":"NH",
    "sg:tags":[
        "truck"
    ],
    "wof:name":"U-Haul",
    "wof:placetype":"venue"
},
  "geometry": {"coordinates":[-71.502627,43.505687],"type":"Point"}
}