{
  "type": "Feature",
  "properties": {
    "iso:country":"US",
    "sg:address":"1547 White Mountain Hwy",
    "sg:city":"Tamworth",
    "sg:classifiers":[
        {
            "category":"Restaurant",
            "type":"Food & Drink"
        }
    ],
    "sg:phone":"+1 603 323 8611",
    "sg:postcode":"03886",
    "sg:province":"NH",
    "sg:tags":[
        "eating"
    ],
    "wof:name":"Rosie's Restaurant",
    "wof:placetype":"venue"
},
  "geometry": {"coordinates":[-71.20788400000001,43.839378],"type":"Point"}
}