{
  "type": "Feature",
  "properties": {
    "iso:country":"US",
    "sg:address":"72 High St",
    "sg:city":"Exeter",
    "sg:classifiers":[
        {
            "category":"Travel",
            "subcategory":"Hotels & Motels",
            "type":"Entertainment"
        }
    ],
    "sg:phone":"+1 603 778 0058",
    "sg:postcode":"03833",
    "sg:province":"NH",
    "sg:tags":[
        "operation"
    ],
    "wof:name":"Around Corner Bed & Breakfast",
    "wof:placetype":"venue"
},
  "geometry": {"coordinates":[-70.93887700000001,42.980746],"type":"Point"}
}