{
  "type": "Feature",
  "properties": {
    "iso:country":"US",
    "sg:address":"Ossipee Mountain Rd",
    "sg:city":"Moultonborough",
    "sg:classifiers":[
        {
            "category":"Retail",
            "subcategory":"Veterinary Services",
            "type":"Services"
        }
    ],
    "sg:phone":"+1 603 476 2396",
    "sg:postcode":"03254",
    "sg:province":"NH",
    "sg:tags":[
        "veterinarian"
    ],
    "wof:name":"Kraft Tevis DVM",
    "wof:placetype":"venue"
},
  "geometry": {"coordinates":[-71.324303,43.7159],"type":"Point"}
}