{
  "type": "Feature",
  "properties": {
    "iso:country":"US",
    "sg:address":"17 Woods Ave",
    "sg:city":"Londonderry",
    "sg:classifiers":[
        {
            "category":"Building & Trades",
            "subcategory":"Construction",
            "type":"Services"
        }
    ],
    "sg:phone":"+1 603 432 8040",
    "sg:postcode":"03053",
    "sg:province":"NH",
    "sg:tags":[
        "house"
    ],
    "wof:name":"Home S Fine By",
    "wof:placetype":"venue"
},
  "geometry": {"coordinates":[-71.36012700000001,42.921829],"type":"Point"}
}