{
  "type": "Feature",
  "properties": {
    "iso:country":"US",
    "sg:address":"70 Bridge St",
    "sg:city":"Pelham",
    "sg:classifiers":[
        {
            "category":"Real Estate",
            "subcategory":"Real Estate Agent",
            "type":"Services"
        }
    ],
    "sg:phone":"+1 603 635 9617",
    "sg:postcode":"03076",
    "sg:province":"NH",
    "sg:website":"www.sunliterealty.com",
    "wof:name":"Sunlite Realty",
    "wof:placetype":"venue"
},
  "geometry": {"coordinates":[-71.317116,42.71006],"type":"Point"}
}