{
  "type": "Feature",
  "properties": {
    "iso:country":"US",
    "sg:address":"185 Mills Shore Dr",
    "sg:city":"Hampstead",
    "sg:classifiers":[
        {
            "category":"Freight",
            "type":"Transportation"
        }
    ],
    "sg:phone":"+1 603 329 7839",
    "sg:postcode":"03841",
    "sg:province":"NH",
    "sg:tags":[
        "operator",
        "local",
        "trucking"
    ],
    "wof:name":"Dancause Enterprises",
    "wof:placetype":"venue"
},
  "geometry": {"coordinates":[-71.198745,42.874294],"type":"Point"}
}