{
  "type": "Feature",
  "properties": {
    "iso:country":"US",
    "sg:address":"61 Elm St",
    "sg:city":"Manchester",
    "sg:classifiers":[
        {
            "category":"Personal",
            "subcategory":"Beauty Salon",
            "type":"Services"
        },
        {
            "category":"Personal",
            "subcategory":"Barber",
            "type":"Services"
        }
    ],
    "sg:phone":"+1 603 626 3054",
    "sg:postcode":"03101",
    "sg:province":"NH",
    "sg:tags":[
        "shop"
    ],
    "wof:name":"Elm Street Studio 61",
    "wof:placetype":"venue"
},
  "geometry": {"coordinates":[-71.46301099999999,42.976042],"type":"Point"}
}