{
  "type": "Feature",
  "properties": {
    "iso:country":"US",
    "sg:address":"66 Eastern Ave",
    "sg:city":"Center Conway",
    "sg:classifiers":[
        {
            "category":"Manufacturing",
            "subcategory":"Tools & Machinery",
            "type":"Manufacturing & Wholesale Goods"
        }
    ],
    "sg:phone":"+1 603 356 6600",
    "sg:postcode":"03867",
    "sg:province":"NH",
    "sg:tags":[
        "machine",
        "shop"
    ],
    "wof:name":"Paradise Machine LLC",
    "wof:placetype":"venue"
},
  "geometry": {"coordinates":[-70.972628,43.309187],"type":"Point"}
}