{
  "type": "Feature",
  "properties": {
    "addr:full":"59 Kendall Pond Rd Derry NH 03038",
    "addr:housenumber":"59",
    "addr:postcode":"03038",
    "addr:street":"Kendall Pond Rd",
    "iso:country":"US",
    "sg:address":"59 Kendall Pond Rd",
    "sg:city":"Derry",
    "sg:classifiers":[
        {
            "category":"Building & Trades",
            "subcategory":"Construction",
            "type":"Services"
        }
    ],
    "sg:phone":"+1 603 432 7921",
    "sg:postcode":"03038",
    "sg:province":"NH",
    "sg:tags":[
        "road",
        "contractor"
    ],
    "wof:name":"Highway Maintenance Garage",
    "wof:placetype":"venue"
},
  "geometry": {"coordinates":[-71.331062,42.860211],"type":"Point"}
}