{
  "type": "Feature",
  "properties": {
    "iso:country":"US",
    "sg:address":"21 Merrimack St",
    "sg:city":"Penacook",
    "sg:classifiers":[
        {
            "category":"Organizations",
            "subcategory":"Religious Organization",
            "type":"Services"
        }
    ],
    "sg:phone":"+1 603 753 4072",
    "sg:postcode":"03303",
    "sg:province":"NH",
    "sg:tags":[
        "church"
    ],
    "sg:website":"www.ucp.bigstep.com",
    "wof:name":"United Church Of Penacook",
    "wof:placetype":"venue"
},
  "geometry": {"coordinates":[-71.59902099999999,43.281549],"type":"Point"}
}