{
  "type": "Feature",
  "properties": {
    "iso:country":"US",
    "sg:address":"51 Lindsay Rd",
    "sg:city":"Hooksett",
    "sg:classifiers":[
        {
            "category":"Arts & Performance",
            "subcategory":"Theater",
            "type":"Entertainment"
        }
    ],
    "sg:phone":"+1 603 624 5307",
    "sg:postcode":"03106",
    "sg:province":"NH",
    "sg:tags":[
        "group"
    ],
    "wof:name":"Kncucklehedz The Band",
    "wof:placetype":"venue"
},
  "geometry": {"coordinates":[-71.428856,43.060075],"type":"Point"}
}