{
  "type": "Feature",
  "properties": {
    "iso:country":"US",
    "sg:address":"201 Liberty Hill Rd",
    "sg:city":"Bedford",
    "sg:classifiers":[
        {
            "category":"Professional",
            "subcategory":"Computer Services",
            "type":"Services"
        }
    ],
    "sg:phone":"+1 603 471 2700",
    "sg:postcode":"03110",
    "sg:province":"NH",
    "sg:tags":[
        "internet"
    ],
    "sg:website":"www.ibg.com",
    "wof:name":"Internet Business Group",
    "wof:placetype":"venue"
},
  "geometry": {"coordinates":[-71.50093099999999,42.921168],"type":"Point"}
}