{
  "type": "Feature",
  "properties": {
    "addr:full":"36 Newburgh Rd Nashua NH 03062",
    "addr:housenumber":"36",
    "addr:postcode":"03062",
    "addr:street":"Newburgh Rd",
    "iso:country":"US",
    "sg:address":"36 Newburgh Rd",
    "sg:city":"Nashua",
    "sg:classifiers":[
        {
            "category":"Organizations",
            "subcategory":"Religious Organization",
            "type":"Services"
        }
    ],
    "sg:phone":"+1 603 888 4336",
    "sg:postcode":"03062",
    "sg:province":"NH",
    "sg:tags":[
        "clergy"
    ],
    "wof:name":"Soterios Alexopoulos",
    "wof:placetype":"venue"
},
  "geometry": {"coordinates":[-71.489929,42.71928],"type":"Point"}
}