{
  "type": "Feature",
  "properties": {
    "iso:country":"US",
    "sg:address":"21 Knight St",
    "sg:city":"Rochester",
    "sg:classifiers":[
        {
            "category":"Building & Trades",
            "subcategory":"Construction",
            "type":"Services"
        }
    ],
    "sg:phone":"+1 603 335 1726",
    "sg:postcode":"03867",
    "sg:province":"NH",
    "sg:tags":[
        "contractor"
    ],
    "wof:name":"Snl Vinyl Siding",
    "wof:placetype":"venue"
},
  "geometry": {"coordinates":[-70.973454,43.299767],"type":"Point"}
}