{
  "type": "Feature",
  "properties": {
    "iso:country":"US",
    "sg:address":"564 Central Ave",
    "sg:city":"Dover",
    "sg:classifiers":[
        {
            "category":"Personal",
            "subcategory":"Beauty Salon",
            "type":"Services"
        }
    ],
    "sg:phone":"+1 603 749 7192",
    "sg:postcode":"03820",
    "sg:province":"NH",
    "sg:tags":[
        "shop"
    ],
    "wof:name":"Shyloks",
    "wof:placetype":"venue"
},
  "geometry": {"coordinates":[-70.876013,43.202235],"type":"Point"}
}