{
  "type": "Feature",
  "properties": {
    "iso:country":"US",
    "sg:address":"198 Loudon Rd",
    "sg:city":"Concord",
    "sg:classifiers":[
        {
            "category":"Autos & Motor Vehicles",
            "subcategory":"Automobile Sales",
            "type":"Retail Goods"
        }
    ],
    "sg:phone":"+1 603 225 4777",
    "sg:postcode":"03301",
    "sg:province":"NH",
    "sg:tags":[
        "car",
        "dealer"
    ],
    "wof:name":"Dick Day Motors",
    "wof:placetype":"venue"
},
  "geometry": {"coordinates":[-71.498891,43.219892],"type":"Point"}
}