{
  "type": "Feature",
  "properties": {
    "addr:full":"54 Main St Meriden NH 03770",
    "addr:housenumber":"54",
    "addr:postcode":"03770",
    "addr:street":"Main St",
    "iso:country":"US",
    "sg:address":"54 Main St",
    "sg:city":"Meriden",
    "sg:classifiers":[
        {
            "category":"Government",
            "subcategory":"Post Office",
            "type":"Public Place"
        }
    ],
    "sg:phone":"+1 603 469 3265",
    "sg:postcode":"03770",
    "sg:province":"NH",
    "wof:name":"US Post Office",
    "wof:placetype":"venue"
},
  "geometry": {"coordinates":[-72.253703,43.544398],"type":"Point"}
}