{
  "type": "Feature",
  "properties": {
    "addr:full":"21 Highland St Plymouth NH 03264",
    "addr:housenumber":"21",
    "addr:postcode":"03264",
    "addr:street":"Highland St",
    "iso:country":"US",
    "sg:address":"21 Highland St",
    "sg:city":"Plymouth",
    "sg:classifiers":[
        {
            "category":"Health Services",
            "subcategory":"Doctor",
            "type":"Services"
        }
    ],
    "sg:phone":"+1 603 536 3710",
    "sg:postcode":"03264",
    "sg:province":"NH",
    "sg:tags":[
        "dentist"
    ],
    "wof:name":"Brian Goulet DDS",
    "wof:placetype":"venue"
},
  "geometry": {"coordinates":[-71.69156099999999,43.757948],"type":"Point"}
}