{
  "type": "Feature",
  "properties": {
    "iso:country":"US",
    "sg:address":"42 Windham Rd",
    "sg:city":"Derry",
    "sg:classifiers":[
        {
            "category":"Building & Trades",
            "subcategory":"Construction",
            "type":"Services"
        }
    ],
    "sg:phone":"+1 603 425 2210",
    "sg:postcode":"03038",
    "sg:province":"NH",
    "sg:tags":[
        "carpenter"
    ],
    "wof:name":"Level Headed Carpentry",
    "wof:placetype":"venue"
},
  "geometry": {"coordinates":[-71.310593,42.866937],"type":"Point"}
}