{
  "type": "Feature",
  "properties": {
    "iso:country":"US",
    "sg:address":"76 Main St",
    "sg:city":"Raymond",
    "sg:classifiers":[
        {
            "category":"Professional",
            "subcategory":"Advertising",
            "type":"Services"
        }
    ],
    "sg:phone":"+1 603 895 5363",
    "sg:postcode":"03077",
    "sg:province":"NH",
    "sg:tags":[
        "agency"
    ],
    "wof:name":"Set In Stone Advg Specialists",
    "wof:placetype":"venue"
},
  "geometry": {"coordinates":[-71.18152499999999,43.035325],"type":"Point"}
}