{
  "type": "Feature",
  "properties": {
    "iso:country":"US",
    "sg:address":"32 Pleasant St",
    "sg:city":"Goffstown",
    "sg:classifiers":[
        {
            "category":"Retail",
            "subcategory":"Repair Shop",
            "type":"Services"
        }
    ],
    "sg:phone":"+1 603 497 4505",
    "sg:postcode":"03045",
    "sg:province":"NH",
    "wof:name":"Ability Restoration & Repair",
    "wof:placetype":"venue"
},
  "geometry": {"coordinates":[-71.601916,43.015894],"type":"Point"}
}