{
  "type": "Feature",
  "properties": {
    "iso:country":"US",
    "sg:address":"8 Alexandra Dr",
    "sg:city":"Pelham",
    "sg:classifiers":[
        {
            "category":"Shopping",
            "subcategory":"Gifts & Souvenirs",
            "type":"Retail Goods"
        }
    ],
    "sg:phone":"+1 603 635 2393",
    "sg:postcode":"03076",
    "sg:province":"NH",
    "wof:name":"Cynthia Mastropiero",
    "wof:placetype":"venue"
},
  "geometry": {"coordinates":[-71.331774,42.735931],"type":"Point"}
}