{
  "type": "Feature",
  "properties": {
    "iso:country":"US",
    "sg:address":"3 Colonial Rd",
    "sg:city":"New London",
    "sg:classifiers":[
        {
            "category":"Shopping",
            "subcategory":"Optical Goods",
            "type":"Retail Goods"
        }
    ],
    "sg:phone":"+1 603 526 6990",
    "sg:postcode":"03246",
    "sg:province":"NH",
    "sg:tags":[
        "optician"
    ],
    "wof:name":"New London Opticians",
    "wof:placetype":"venue"
},
  "geometry": {"coordinates":[-71.44168500000001,43.600601],"type":"Point"}
}