{
  "type": "Feature",
  "properties": {
    "iso:country":"US",
    "sg:address":"1 Highlander Ct",
    "sg:city":"Litchfield",
    "sg:classifiers":[
        {
            "category":"Education",
            "subcategory":"School",
            "type":"Public Place"
        }
    ],
    "sg:phone":"+1 603 578 3570",
    "sg:postcode":"03052",
    "sg:province":"NH",
    "sg:website":"http://www.campbellhs.org",
    "wof:name":"Litchfield School District",
    "wof:placetype":"venue"
},
  "geometry": {"coordinates":[-71.446442,42.825859],"type":"Point"}
}