{
  "type": "Feature",
  "properties": {
    "iso:country":"US",
    "sg:address":"14 Main St",
    "sg:city":"Ashland",
    "sg:classifiers":[
        {
            "category":"Restaurant",
            "type":"Food & Drink"
        }
    ],
    "sg:phone":"+1 603 968 7089",
    "sg:postcode":"03217",
    "sg:province":"NH",
    "wof:name":"John's Restaurant",
    "wof:placetype":"venue"
},
  "geometry": {"coordinates":[-71.62970900000001,43.694263],"type":"Point"}
}