{
  "type": "Feature",
  "properties": {
    "iso:country":"US",
    "sg:address":"43 Atwood Rd",
    "sg:city":"Pelham",
    "sg:classifiers":[
        {
            "category":"Place Of Worship",
            "subcategory":"Church",
            "type":"Public Place"
        },
        {
            "category":"Place Of Worship",
            "type":"Public Place"
        }
    ],
    "sg:phone":"+1 603 635 1556",
    "sg:postcode":"03076",
    "sg:province":"NH",
    "sg:tags":[
        "churches-baptist-general",
        "churches-baptist"
    ],
    "wof:name":"Cross Roads Baptist Church",
    "wof:placetype":"venue"
},
  "geometry": {"coordinates":[-71.313019,42.727188],"type":"Point"}
}