{
  "type": "Feature",
  "properties": {
    "iso:country":"US",
    "sg:address":"7 Call Rd",
    "sg:city":"Concord",
    "sg:classifiers":[
        {
            "category":"Building & Trades",
            "subcategory":"Construction",
            "type":"Services"
        }
    ],
    "sg:phone":"+1 603 746 3615",
    "sg:postcode":"03303",
    "sg:province":"NH",
    "sg:tags":[
        "hanging",
        "contractor"
    ],
    "wof:name":"Not Just Paint & Paper",
    "wof:placetype":"venue"
},
  "geometry": {"coordinates":[-71.713685,43.300916],"type":"Point"}
}