{
  "type": "Feature",
  "properties": {
    "addr:full":"271 W Hollis St Nashua NH 03060",
    "addr:housenumber":"271",
    "addr:postcode":"03060",
    "addr:street":"W Hollis St",
    "iso:country":"US",
    "sg:address":"271 W Hollis St",
    "sg:city":"Nashua",
    "sg:classifiers":[
        {
            "category":"Retail",
            "subcategory":"Auto Repair",
            "type":"Services"
        }
    ],
    "sg:phone":"+1 603 883 7029",
    "sg:postcode":"03060",
    "sg:province":"NH",
    "sg:tags":[
        "repairing",
        "automobile"
    ],
    "wof:name":"Hanson's Automotive Svc",
    "wof:placetype":"venue"
},
  "geometry": {"coordinates":[-71.484364,42.751524],"type":"Point"}
}