{
  "type": "Feature",
  "properties": {
    "iso:country":"US",
    "sg:address":"410 W Main St",
    "sg:city":"Tilton",
    "sg:classifiers":[
        {
            "category":"Organizations",
            "subcategory":"Community Association",
            "type":"Services"
        }
    ],
    "sg:phone":"+1 603 286 2177",
    "sg:postcode":"03276",
    "sg:province":"NH",
    "sg:tags":[
        "fraternal"
    ],
    "wof:name":"Grand Chapter Of NH Order",
    "wof:placetype":"venue"
},
  "geometry": {"coordinates":[-71.60150299999999,43.44231],"type":"Point"}
}