{
  "type": "Feature",
  "properties": {
    "iso:country":"US",
    "sg:address":"18 Dorre Rd",
    "sg:city":"Kingston",
    "sg:classifiers":[
        {
            "category":"Mining & Drilling",
            "type":"Manufacturing & Wholesale Goods"
        }
    ],
    "sg:phone":"+1 603 642 5564",
    "sg:postcode":"03848",
    "sg:province":"NH",
    "sg:tags":[
        "stone"
    ],
    "wof:name":"Torromeo Trucking Inc",
    "wof:placetype":"venue"
},
  "geometry": {"coordinates":[-71.09751199999999,42.872352],"type":"Point"}
}