{
  "type": "Feature",
  "properties": {
    "addr:full":"245 Thaxter Rd Portsmouth NH 03801",
    "addr:housenumber":"245",
    "addr:postcode":"03801",
    "addr:street":"Thaxter Rd",
    "iso:country":"US",
    "sg:address":"245 Thaxter Rd",
    "sg:city":"Portsmouth",
    "sg:classifiers":[
        {
            "category":"Building & Trades",
            "subcategory":"Landscaping Services",
            "type":"Services"
        }
    ],
    "sg:phone":"+1 603 436 4759",
    "sg:postcode":"03801",
    "sg:province":"NH",
    "sg:tags":[
        "designer",
        "landscape"
    ],
    "wof:name":"Strawberry Banke Landscape",
    "wof:placetype":"venue"
},
  "geometry": {"coordinates":[-70.77125599999999,43.065918],"type":"Point"}
}