{
  "type": "Feature",
  "properties": {
    "addr:full":"85 Country Club Dr Atkinson NH 03811",
    "addr:housenumber":"85",
    "addr:postcode":"03811",
    "addr:street":"Country Club Dr",
    "iso:country":"US",
    "sg:address":"85 Country Club Dr",
    "sg:city":"Atkinson",
    "sg:classifiers":[
        {
            "category":"Sports & Exercise",
            "subcategory":"Golf",
            "type":"Entertainment"
        }
    ],
    "sg:phone":"+1 603 362 5681",
    "sg:postcode":"03811",
    "sg:province":"NH",
    "sg:tags":[
        "course"
    ],
    "wof:name":"Atkinson Country Club Golf",
    "wof:placetype":"venue"
},
  "geometry": {"coordinates":[-71.170945,42.821775],"type":"Point"}
}