{
  "type": "Feature",
  "properties": {
    "iso:country":"US",
    "sg:address":"10 Northern Blvd",
    "sg:city":"Amherst",
    "sg:classifiers":[
        {
            "category":"Professional",
            "subcategory":"Management & Consulting",
            "type":"Services"
        },
        {
            "category":"Education",
            "subcategory":"Special Training",
            "type":"Public Place"
        },
        {
            "category":"Communications",
            "type":"Services"
        }
    ],
    "sg:phone":"+1 603 769 4706",
    "sg:postcode":"03031",
    "sg:province":"NH",
    "sg:tags":[
        "consultant",
        "educational",
        "speech-language",
        "pathologist"
    ],
    "sg:website":"http://www.amhersttherapyconnections.com",
    "wof:name":"Amherst Therapy Connections Llc",
    "wof:placetype":"venue"
},
  "geometry": {"coordinates":[-71.582657,42.807629],"type":"Point"}
}