{
  "type": "Feature",
  "properties": {
    "addr:full":"171 Center Hill Rd Epsom NH 03234",
    "addr:housenumber":"171",
    "addr:postcode":"03234",
    "addr:street":"Center Hill Rd",
    "iso:country":"US",
    "sg:address":"171 Center Hill Rd",
    "sg:city":"Epsom",
    "sg:classifiers":[
        {
            "category":"Farming",
            "subcategory":"Dairy Farm",
            "type":"Manufacturing & Wholesale Goods"
        }
    ],
    "sg:phone":"+1 603 736 9075",
    "sg:postcode":"03234",
    "sg:province":"NH",
    "wof:name":"Spooky View Farm",
    "wof:placetype":"venue"
},
  "geometry": {"coordinates":[-71.31955000000001,43.217296],"type":"Point"}
}