{
  "type": "Feature",
  "properties": {
    "addr:full":"1343 State Rte 16 Albany NH 03818",
    "addr:housenumber":"1343",
    "addr:postcode":"03818",
    "addr:street":"State Rte 16",
    "iso:country":"US",
    "sg:address":"1343 State Rte 16",
    "sg:city":"Albany",
    "sg:classifiers":[
        {
            "category":"Home & Garden",
            "subcategory":"Home Furnishings",
            "type":"Retail Goods"
        }
    ],
    "sg:phone":"+1 603 447 4348",
    "sg:postcode":"03818",
    "sg:province":"NH",
    "sg:tags":[
        "weather",
        "vane"
    ],
    "wof:name":"Copper Tops",
    "wof:placetype":"venue"
},
  "geometry": {"coordinates":[-71.14582299999999,43.965606],"type":"Point"}
}