{
  "type": "Feature",
  "properties": {
    "addr:full":"169 Main St Kingston NH 03848",
    "addr:housenumber":"169",
    "addr:postcode":"03848",
    "addr:street":"Main St",
    "iso:country":"US",
    "sg:address":"169 Main St",
    "sg:city":"Kingston",
    "sg:classifiers":[
        {
            "category":"Education",
            "subcategory":"Library",
            "type":"Public Place"
        }
    ],
    "sg:phone":"+1 603 642 3521",
    "sg:postcode":"03848",
    "sg:province":"NH",
    "wof:name":"Kingston Public Library",
    "wof:placetype":"venue"
},
  "geometry": {"coordinates":[-71.05242200000001,42.938722],"type":"Point"}
}