{
  "type": "Feature",
  "properties": {
    "iso:country":"US",
    "sg:address":"37 Washington St",
    "sg:city":"Somersworth",
    "sg:classifiers":[
        {
            "category":"Autos & Motor Vehicles",
            "subcategory":"Auto Supplies",
            "type":"Retail Goods"
        }
    ],
    "sg:phone":"+1 603 692 5835",
    "sg:postcode":"03878",
    "sg:province":"NH",
    "sg:tags":[
        "automobile",
        "parts"
    ],
    "wof:name":"NAPA Auto Parts",
    "wof:placetype":"venue"
},
  "geometry": {"coordinates":[-70.864086,43.260464],"type":"Point"}
}