{
  "type": "Feature",
  "properties": {
    "iso:country":"US",
    "sg:address":"247 Hazen Rd",
    "sg:city":"Bethlehem",
    "sg:classifiers":[
        {
            "category":"Manufacturing",
            "subcategory":"Printing",
            "type":"Manufacturing & Wholesale Goods"
        }
    ],
    "sg:phone":"+1 603 869 6455",
    "sg:postcode":"03574",
    "sg:province":"NH",
    "sg:tags":[
        "commercial"
    ],
    "wof:name":"Kj Graphics",
    "wof:placetype":"venue"
},
  "geometry": {"coordinates":[-71.658357,44.310672],"type":"Point"}
}