{
  "type": "Feature",
  "properties": {
    "iso:country":"US",
    "sg:address":"48 Mountain Ave",
    "sg:city":"Northwood",
    "sg:classifiers":[
        {
            "category":"Freight",
            "type":"Transportation"
        }
    ],
    "sg:phone":"+1 603 942 8811",
    "sg:postcode":"03261",
    "sg:province":"NH",
    "sg:tags":[
        "trucking"
    ],
    "wof:name":"John Stilson Trucking",
    "wof:placetype":"venue"
},
  "geometry": {"coordinates":[-71.150233,43.192909],"type":"Point"}
}