{
  "type": "Feature",
  "properties": {
    "iso:country":"US",
    "sg:address":"14 Holly Ln",
    "sg:city":"Londonderry",
    "sg:classifiers":[
        {
            "category":"Wholesale",
            "subcategory":"Durable Goods & Equipment",
            "type":"Manufacturing & Wholesale Goods"
        }
    ],
    "sg:phone":"+1 603 437 1864",
    "sg:postcode":"03053",
    "sg:province":"NH",
    "sg:tags":[
        "representative",
        "manufacturer"
    ],
    "wof:name":"Three M",
    "wof:placetype":"venue"
},
  "geometry": {"coordinates":[-71.355127,42.84374],"type":"Point"}
}