{
  "type": "Feature",
  "properties": {
    "iso:country":"US",
    "sg:address":"86 River Rd",
    "sg:city":"New Boston",
    "sg:classifiers":[
        {
            "category":"Building & Trades",
            "subcategory":"Construction",
            "type":"Services"
        }
    ],
    "sg:phone":"+1 603 487 2709",
    "sg:postcode":"03070",
    "sg:province":"NH",
    "sg:tags":[
        "company"
    ],
    "wof:name":"Virgin Construction Corp",
    "wof:placetype":"venue"
},
  "geometry": {"coordinates":[-71.68876299999999,42.979773],"type":"Point"}
}