{
  "type": "Feature",
  "properties": {
    "iso:country":"US",
    "sg:address":"27 Penacook St",
    "sg:city":"Concord",
    "sg:classifiers":[
        {
            "category":"Travel",
            "subcategory":"Travel Agent",
            "type":"Entertainment"
        }
    ],
    "sg:phone":"+1 603 229 3244",
    "sg:postcode":"03301",
    "sg:province":"NH",
    "sg:tags":[
        "agency",
        "bureau"
    ],
    "wof:name":"Dream Destinations",
    "wof:placetype":"venue"
},
  "geometry": {"coordinates":[-71.54587600000001,43.216784],"type":"Point"}
}