{
  "type": "Feature",
  "properties": {
    "addr:full":"14 Clovercrest Dr Nashua NH 03062",
    "addr:housenumber":"14",
    "addr:postcode":"03062",
    "addr:street":"Clovercrest Dr",
    "iso:country":"US",
    "sg:address":"14 Clovercrest Dr",
    "sg:city":"Nashua",
    "sg:classifiers":[
        {
            "category":"Travel",
            "subcategory":"Travel Agent",
            "type":"Entertainment"
        }
    ],
    "sg:phone":"+1 603 881 3138",
    "sg:postcode":"03062",
    "sg:province":"NH",
    "sg:tags":[
        "agency",
        "bureau"
    ],
    "wof:name":"Holidays",
    "wof:placetype":"venue"
},
  "geometry": {"coordinates":[-71.530008,42.719521],"type":"Point"}
}