{
  "type": "Feature",
  "properties": {
    "addr:full":"294 Deering Rd Weare NH 03281",
    "addr:housenumber":"294",
    "addr:postcode":"03281",
    "addr:street":"Deering Rd",
    "iso:country":"US",
    "sg:address":"294 Deering Rd",
    "sg:city":"Weare",
    "sg:classifiers":[
        {
            "category":"Professional",
            "type":"Services"
        }
    ],
    "sg:phone":"+1 603 529 4934",
    "sg:postcode":"03281",
    "sg:province":"NH",
    "wof:name":"Quality Solutions",
    "wof:placetype":"venue"
},
  "geometry": {"coordinates":[-71.737033,43.049283],"type":"Point"}
}