{
  "type": "Feature",
  "properties": {
    "iso:country":"US",
    "sg:address":"173 Main St",
    "sg:city":"Charlestown",
    "sg:classifiers":[
        {
            "category":"Utilities",
            "subcategory":"Water",
            "type":"Services"
        }
    ],
    "sg:phone":"+1 603 826 5535",
    "sg:postcode":"03603",
    "sg:province":"NH",
    "sg:tags":[
        "company",
        "sewage"
    ],
    "wof:name":"Water Dept",
    "wof:placetype":"venue"
},
  "geometry": {"coordinates":[-72.42490599999999,43.237826],"type":"Point"}
}