{
  "type": "Feature",
  "properties": {
    "addr:full":"41 Gosling Rd Portsmouth NH 03801",
    "addr:housenumber":"41",
    "addr:postcode":"03801",
    "addr:street":"Gosling Rd",
    "iso:country":"US",
    "sg:address":"41 Gosling Rd",
    "sg:city":"Portsmouth",
    "sg:classifiers":[
        {
            "category":"Restaurant",
            "type":"Food & Drink"
        }
    ],
    "sg:menulink":"http://www.allmenus.com/nh/newington/98632-longhorn-steakhouse/menu/",
    "sg:phone":"+1 603 334 6533",
    "sg:postcode":"03801",
    "sg:province":"NH",
    "sg:tags":[
        "american",
        "steakhouse"
    ],
    "wof:name":"LongHorn Steakhouse",
    "wof:placetype":"venue"
},
  "geometry": {"coordinates":[-70.798699,43.092333],"type":"Point"}
}