{
  "type": "Feature",
  "properties": {
    "addr:full":"522 Ocean Blvd Hampton NH 03842",
    "addr:housenumber":"522",
    "addr:postcode":"03842",
    "addr:street":"Ocean Blvd",
    "iso:country":"US",
    "sg:address":"522 Ocean Blvd",
    "sg:city":"Hampton",
    "sg:classifiers":[
        {
            "category":"Taxi",
            "type":"Transportation"
        }
    ],
    "sg:phone":"+1 603 929 0077",
    "sg:postcode":"03842",
    "sg:province":"NH",
    "sg:tags":[
        "taxicab"
    ],
    "wof:name":"A 1 Vango-Taxi",
    "wof:placetype":"venue"
},
  "geometry": {"coordinates":[-70.799626,42.918724],"type":"Point"}
}