{
  "type": "Feature",
  "properties": {
    "addr:full":"7 South Dr Winchester NH 03470",
    "addr:housenumber":"7",
    "addr:postcode":"03470",
    "addr:street":"South Dr",
    "iso:country":"US",
    "sg:address":"7 South Dr",
    "sg:city":"Winchester",
    "sg:classifiers":[
        {
            "category":"Manufacturing",
            "subcategory":"Tools & Machinery",
            "type":"Manufacturing & Wholesale Goods"
        }
    ],
    "sg:phone":"+1 603 352 7940",
    "sg:postcode":"03470",
    "sg:province":"NH",
    "sg:tags":[
        "machine",
        "shop"
    ],
    "wof:name":"A & K Machine",
    "wof:placetype":"venue"
},
  "geometry": {"coordinates":[-72.362486,42.791422],"type":"Point"}
}