{
  "type": "Feature",
  "properties": {
    "iso:country":"US",
    "sg:address":"57 Wakefield St",
    "sg:city":"Rochester",
    "sg:classifiers":[
        {
            "category":"Education",
            "subcategory":"Special Training",
            "type":"Public Place"
        }
    ],
    "sg:phone":"+1 603 335 6200",
    "sg:postcode":"03867",
    "sg:province":"NH",
    "sg:tags":[
        "center"
    ],
    "wof:name":"Dover Adult Learning Ctr",
    "wof:placetype":"venue"
},
  "geometry": {"coordinates":[-70.976562,43.306672],"type":"Point"}
}