{
  "type": "Feature",
  "properties": {
    "iso:country":"US",
    "sg:address":"18 Bradford Rd",
    "sg:city":"Henniker",
    "sg:classifiers":[
        {
            "category":"Shopping",
            "subcategory":"Clothing, Apparel, & Fashions",
            "type":"Retail Goods"
        }
    ],
    "sg:phone":"+1 603 428 3255",
    "sg:postcode":"03242",
    "sg:province":"NH",
    "wof:name":"Henniker Farm & Country Store",
    "wof:placetype":"venue"
},
  "geometry": {"coordinates":[-71.847763,43.205461],"type":"Point"}
}