{
  "type": "Feature",
  "properties": {
    "iso:country":"US",
    "sg:address":"20 Nutting Hill Rd",
    "sg:city":"Greenville",
    "sg:classifiers":[
        {
            "category":"Retail",
            "subcategory":"Auto Repair",
            "type":"Services"
        }
    ],
    "sg:phone":"+1 603 878 1384",
    "sg:postcode":"03048",
    "sg:province":"NH",
    "sg:tags":[
        "general"
    ],
    "wof:name":"Larrys Auto",
    "wof:placetype":"venue"
},
  "geometry": {"coordinates":[-71.782082,42.77867],"type":"Point"}
}