{
  "type": "Feature",
  "properties": {
    "iso:country":"US",
    "sg:address":"286 Main St",
    "sg:city":"Claremont",
    "sg:phone":"+1 603 542 5175",
    "sg:postcode":"03743",
    "sg:province":"NH",
    "sg:tags":[
        "gas"
    ],
    "wof:name":"Limoges Oil & Propane Inc",
    "wof:placetype":"venue"
},
  "geometry": {"coordinates":[-72.352138,43.378778],"type":"Point"}
}