{
  "type": "Feature",
  "properties": {
    "iso:country":"US",
    "sg:address":"49 Town Line Rd",
    "sg:city":"Conway",
    "sg:classifiers":[
        {
            "category":"Shopping",
            "subcategory":"Books",
            "type":"Retail Goods"
        }
    ],
    "sg:phone":"+1 603 447 6286",
    "sg:postcode":"03849",
    "sg:province":"NH",
    "wof:name":"Bye The Book LLC",
    "wof:placetype":"venue"
},
  "geometry": {"coordinates":[-71.11236599999999,43.931351],"type":"Point"}
}