{
  "type": "Feature",
  "properties": {
    "iso:country":"US",
    "sg:address":"8 Raymond St",
    "sg:city":"Hudson",
    "sg:classifiers":[
        {
            "category":"Professional",
            "subcategory":"Management & Consulting",
            "type":"Services"
        }
    ],
    "sg:phone":"+1 603 882 7780",
    "sg:postcode":"03051",
    "sg:province":"NH",
    "sg:tags":[
        "business"
    ],
    "wof:name":"Demers Broadcast Consultants",
    "wof:placetype":"venue"
},
  "geometry": {"coordinates":[-71.432388,42.762849],"type":"Point"}
}