{
  "type": "Feature",
  "properties": {
    "iso:country":"US",
    "sg:address":"27 Hale Spring Rd",
    "sg:city":"Plaistow",
    "sg:classifiers":[
        {
            "category":"Manufacturing",
            "subcategory":"Retail Goods",
            "type":"Manufacturing & Wholesale Goods"
        }
    ],
    "sg:phone":"+1 603 382 3840",
    "sg:postcode":"03865",
    "sg:province":"NH",
    "sg:tags":[
        "assembly",
        "fabricating"
    ],
    "sg:website":"www.beckwood.com",
    "wof:name":"Beckwood Services",
    "wof:placetype":"venue"
},
  "geometry": {"coordinates":[-71.08841099999999,42.84398],"type":"Point"}
}