{
  "type": "Feature",
  "properties": {
    "iso:country":"US",
    "sg:address":"29 Crystal Ave",
    "sg:city":"Derry",
    "sg:classifiers":[
        {
            "category":"Restaurant",
            "type":"Food & Drink"
        }
    ],
    "sg:phone":"+1 603 434 6499",
    "sg:postcode":"03038",
    "sg:province":"NH",
    "sg:tags":[
        "eating"
    ],
    "wof:name":"Derry Diner",
    "wof:placetype":"venue"
},
  "geometry": {"coordinates":[-71.32684999999999,42.887366],"type":"Point"}
}