{
  "type": "Feature",
  "properties": {
    "iso:country":"US",
    "sg:address":"1359 Hooksett Rd",
    "sg:city":"Hooksett",
    "sg:classifiers":[
        {
            "category":"Building & Trades",
            "subcategory":"Construction",
            "type":"Services"
        }
    ],
    "sg:phone":"+1 603 626 4799",
    "sg:postcode":"03106",
    "sg:province":"NH",
    "sg:tags":[
        "general",
        "contractor"
    ],
    "wof:name":"Area Contractors",
    "wof:placetype":"venue"
},
  "geometry": {"coordinates":[-71.44251199999999,43.059084],"type":"Point"}
}