{
  "type": "Feature",
  "properties": {
    "iso:country":"US",
    "sg:address":"251 Westwood Dr",
    "sg:city":"Manchester",
    "sg:classifiers":[
        {
            "category":"Building & Trades",
            "subcategory":"Construction",
            "type":"Services"
        }
    ],
    "sg:phone":"+1 603 641 9577",
    "sg:postcode":"03103",
    "sg:province":"NH",
    "sg:tags":[
        "painter"
    ],
    "wof:name":"A-1 Electrostatic Refinishing",
    "wof:placetype":"venue"
},
  "geometry": {"coordinates":[-71.45044900000001,42.946964],"type":"Point"}
}