{
  "type": "Feature",
  "properties": {
    "iso:country":"US",
    "sg:address":"41 Old W Hopkinton Rd",
    "sg:city":"Henniker",
    "sg:classifiers":[
        {
            "category":"Travel",
            "subcategory":"Campground",
            "type":"Entertainment"
        }
    ],
    "sg:phone":"+1 603 428 7616",
    "sg:postcode":"03242",
    "sg:province":"NH",
    "sg:tags":[
        "trailer"
    ],
    "wof:name":"Mile-Away Campground",
    "wof:placetype":"venue"
},
  "geometry": {"coordinates":[-71.77323699999999,43.187276],"type":"Point"}
}