{
  "type": "Feature",
  "properties": {
    "addr:full":"125 Northeastern Blvd Nashua NH 03062",
    "addr:housenumber":"125",
    "addr:postcode":"03062",
    "addr:street":"Northeastern Blvd",
    "iso:country":"US",
    "sg:address":"125 Northeastern Blvd",
    "sg:city":"Nashua",
    "sg:classifiers":[
        {
            "category":"Professional",
            "subcategory":"Advertising",
            "type":"Services"
        }
    ],
    "sg:phone":"+1 603 889 4838",
    "sg:postcode":"03062",
    "sg:province":"NH",
    "sg:tags":[
        "mail",
        "direct",
        "photocopying"
    ],
    "sg:website":"www.majormail.com",
    "wof:name":"Major Mail Inc",
    "wof:placetype":"venue"
},
  "geometry": {"coordinates":[-71.49494900000001,42.740554],"type":"Point"}
}