{
  "type": "Feature",
  "properties": {
    "addr:full":"505 W Main St Tilton NH 03276",
    "addr:housenumber":"505",
    "addr:postcode":"03276",
    "addr:street":"W Main St",
    "iso:country":"US",
    "sg:address":"505 W Main St",
    "sg:city":"Tilton",
    "sg:classifiers":[
        {
            "category":"Home & Garden",
            "subcategory":"Building Materials",
            "type":"Retail Goods"
        }
    ],
    "sg:phone":"+1 603 286 9297",
    "sg:postcode":"03276",
    "sg:province":"NH",
    "sg:tags":[
        "glass",
        "window",
        "plate"
    ],
    "wof:name":"Glass America",
    "wof:placetype":"venue"
},
  "geometry": {"coordinates":[-71.61852500000001,43.447116],"type":"Point"}
}