{
  "type": "Feature",
  "properties": {
    "addr:full":"115 Gardners Grove Rd Belmont NH 03220",
    "addr:housenumber":"115",
    "addr:postcode":"03220",
    "addr:street":"Gardners Grove Rd",
    "iso:country":"US",
    "sg:address":"115 Gardners Grove Rd",
    "sg:city":"Belmont",
    "sg:classifiers":[
        {
            "category":"Food & Beverages",
            "subcategory":"Groceries & Convenience Stores",
            "type":"Retail Goods"
        }
    ],
    "sg:phone":"+1 603 524 1084",
    "sg:postcode":"03220",
    "sg:province":"NH",
    "wof:name":"Farmers Market",
    "wof:placetype":"venue"
},
  "geometry": {"coordinates":[-71.53628,43.45723],"type":"Point"}
}