{
  "type": "Feature",
  "properties": {
    "iso:country":"US",
    "sg:address":"15 Fox Meadow Ln",
    "sg:city":"Merrimack",
    "sg:classifiers":[
        {
            "category":"Education",
            "subcategory":"Special Training",
            "type":"Public Place"
        }
    ],
    "sg:phone":"+1 603 424 1744",
    "sg:postcode":"03054",
    "sg:province":"NH",
    "wof:name":"Masterful Design & Creati",
    "wof:placetype":"venue"
},
  "geometry": {"coordinates":[-71.520104,42.855337],"type":"Point"}
}