{
  "type": "Feature",
  "properties": {
    "addr:full":"187 East Rd Hampstead NH 03841",
    "addr:housenumber":"187",
    "addr:postcode":"03841",
    "addr:street":"East Rd",
    "iso:country":"US",
    "sg:address":"187 East Rd",
    "sg:city":"Hampstead",
    "sg:classifiers":[
        {
            "category":"Organizations",
            "subcategory":"Religious Organization",
            "type":"Services"
        }
    ],
    "sg:phone":"+1 603 329 4674",
    "sg:postcode":"03841",
    "sg:province":"NH",
    "wof:name":"Saint Chrstphers Epscpal Chrch",
    "wof:placetype":"venue"
},
  "geometry": {"coordinates":[-71.158395,42.869984],"type":"Point"}
}