{
  "type": "Feature",
  "properties": {
    "iso:country":"US",
    "sg:address":"16 Harrison St",
    "sg:city":"Keene",
    "sg:classifiers":[
        {
            "category":"Professional",
            "type":"Services"
        }
    ],
    "sg:phone":"+1 603 355 1498",
    "sg:postcode":"03431",
    "sg:province":"NH",
    "sg:tags":[
        "establishment"
    ],
    "wof:name":"Espmatik Inc",
    "wof:placetype":"venue"
},
  "geometry": {"coordinates":[-72.273453,42.934129],"type":"Point"}
}