{
  "type": "Feature",
  "properties": {
    "iso:country":"US",
    "sg:address":"46 Newport Rd",
    "sg:city":"New London",
    "sg:classifiers":[
        {
            "category":"Insurance",
            "subcategory":"Insurance Agent",
            "type":"Services"
        }
    ],
    "sg:phone":"+1 603 526 6700",
    "sg:postcode":"03257",
    "sg:province":"NH",
    "wof:name":"Beacon Financial Group",
    "wof:placetype":"venue"
},
  "geometry": {"coordinates":[-72.000506,43.424994],"type":"Point"}
}