{
  "type": "Feature",
  "properties": {
    "iso:country":"US",
    "sg:address":"311 Lafayette Rd",
    "sg:city":"Seabrook",
    "sg:classifiers":[
        {
            "category":"Social Services",
            "type":"Services"
        }
    ],
    "sg:phone":"+1 603 474 2139",
    "sg:postcode":"03874",
    "sg:province":"NH",
    "wof:name":"Rockingham Cnty Ntrtn Program",
    "wof:placetype":"venue"
},
  "geometry": {"coordinates":[-70.868194,42.883057],"type":"Point"}
}