{
  "type": "Feature",
  "properties": {
    "iso:country":"US",
    "sg:address":"286 Pleasant St",
    "sg:city":"Concord",
    "sg:classifiers":[
        {
            "category":"Retail",
            "subcategory":"Veterinary Services",
            "type":"Services"
        }
    ],
    "sg:phone":"+1 603 224 2361",
    "sg:postcode":"03301",
    "sg:province":"NH",
    "sg:tags":[
        "hospital",
        "veterinarian",
        "animal"
    ],
    "wof:name":"Russell Animal Hospital Pro",
    "wof:placetype":"venue"
},
  "geometry": {"coordinates":[-71.566219,43.197504],"type":"Point"}
}