{
  "type": "Feature",
  "properties": {
    "addr:full":"167 Main St Plaistow NH 03865",
    "addr:housenumber":"167",
    "addr:postcode":"03865",
    "addr:street":"Main St",
    "iso:country":"US",
    "sg:address":"167 Main St",
    "sg:city":"Plaistow",
    "sg:classifiers":[
        {
            "category":"Retail",
            "subcategory":"Auto Repair",
            "type":"Services"
        }
    ],
    "sg:phone":"+1 603 382 3594",
    "sg:postcode":"03865",
    "sg:province":"NH",
    "sg:tags":[
        "wrecker"
    ],
    "wof:name":"Plaistow Towing",
    "wof:placetype":"venue"
},
  "geometry": {"coordinates":[-71.098023,42.842098],"type":"Point"}
}