{
  "type": "Feature",
  "properties": {
    "iso:country":"US",
    "sg:address":"30 Charter St",
    "sg:city":"Exeter",
    "sg:classifiers":[
        {
            "category":"Professional",
            "subcategory":"Management & Consulting",
            "type":"Services"
        }
    ],
    "sg:phone":"+1 603 773 0252",
    "sg:postcode":"03833",
    "sg:province":"NH",
    "sg:tags":[
        "business"
    ],
    "wof:name":"Langhorst Consulting",
    "wof:placetype":"venue"
},
  "geometry": {"coordinates":[-70.96381,42.976699],"type":"Point"}
}