{
  "type": "Feature",
  "properties": {
    "iso:country":"US",
    "sg:address":"321 Calef Hill Rd",
    "sg:city":"Tilton",
    "sg:classifiers":[
        {
            "category":"Shopping",
            "subcategory":"Discount & Variety Stores",
            "type":"Retail Goods"
        }
    ],
    "sg:phone":"+1 603 473 8714",
    "sg:postcode":"03276",
    "sg:province":"NH",
    "sg:tags":[
        "merchandise",
        "general"
    ],
    "wof:name":"Victorian Merchant",
    "wof:placetype":"venue"
},
  "geometry": {"coordinates":[-71.603014,43.4659],"type":"Point"}
}