{
  "type": "Feature",
  "properties": {
    "addr:full":"76 Main St Keene NH 03431",
    "addr:housenumber":"76",
    "addr:postcode":"03431",
    "addr:street":"Main St",
    "iso:country":"US",
    "sg:address":"76 Main St",
    "sg:city":"Keene",
    "sg:classifiers":[
        {
            "category":"Education",
            "subcategory":"Special Training",
            "type":"Public Place"
        }
    ],
    "sg:phone":"+1 603 563 8300",
    "sg:postcode":"03431",
    "sg:province":"NH",
    "sg:tags":[
        "center"
    ],
    "wof:name":"Journeys In Education",
    "wof:placetype":"venue"
},
  "geometry": {"coordinates":[-72.278092,42.931987],"type":"Point"}
}