{
  "type": "Feature",
  "properties": {
    "addr:full":"21 Cross St Salem NH 03079",
    "addr:housenumber":"21",
    "addr:postcode":"03079",
    "addr:street":"Cross St",
    "iso:country":"US",
    "sg:address":"21 Cross St",
    "sg:city":"Salem",
    "sg:classifiers":[
        {
            "category":"Real Estate",
            "subcategory":"Real Estate Agent",
            "type":"Services"
        }
    ],
    "sg:phone":"+1 603 890 2180",
    "sg:postcode":"03079",
    "sg:province":"NH",
    "wof:name":"Salem Cemetery",
    "wof:placetype":"venue"
},
  "geometry": {"coordinates":[-71.225223,42.761125],"type":"Point"}
}