{
  "type": "Feature",
  "properties": {
    "iso:country":"US",
    "sg:address":"85 Lake St",
    "sg:city":"Bristol",
    "sg:classifiers":[
        {
            "category":"Government",
            "subcategory":"Fire Station",
            "type":"Public Place"
        }
    ],
    "sg:phone":"+1 603 744 2632",
    "sg:postcode":"03222",
    "sg:province":"NH",
    "sg:tags":[
        "department",
        "protection"
    ],
    "wof:name":"Bristol Fire Department",
    "wof:placetype":"venue"
},
  "geometry": {"coordinates":[-71.744953,43.595693],"type":"Point"}
}