{
  "type": "Feature",
  "properties": {
    "addr:full":"109 Daniel Webster Hwy Nashua NH 03060",
    "addr:housenumber":"109",
    "addr:postcode":"03060",
    "addr:street":"Daniel Webster Hwy",
    "iso:country":"US",
    "sg:address":"109 Daniel Webster Hwy",
    "sg:city":"Nashua",
    "sg:classifiers":[
        {
            "category":"Bakery",
            "type":"Food & Drink"
        },
        {
            "category":"Coffee & Tea",
            "type":"Food & Drink"
        },
        {
            "category":"Bagels",
            "type":"Food & Drink"
        },
        {
            "category":"Donuts",
            "type":"Food & Drink"
        }
    ],
    "sg:menulink":"http://www.allmenus.com/nh/nashua/149178-dunkin-donuts/menu/",
    "sg:phone":"+1 603 891 9674",
    "sg:postcode":"03060",
    "sg:province":"NH",
    "sg:tags":[
        "wrap",
        "american",
        "sandwich",
        "pastry"
    ],
    "wof:name":"Dunkin' Donuts",
    "wof:placetype":"venue"
},
  "geometry": {"coordinates":[-71.44803,42.728463],"type":"Point"}
}