{
  "type": "Feature",
  "properties": {
    "iso:country":"US",
    "sg:address":"2338 State Rte 16",
    "sg:city":"West Ossipee",
    "sg:classifiers":[
        {
            "category":"Organizations",
            "subcategory":"Professional Association",
            "type":"Services"
        }
    ],
    "sg:phone":"+1 603 539 5424",
    "sg:postcode":"03890",
    "sg:province":"NH",
    "sg:tags":[
        "chambers",
        "commerce"
    ],
    "wof:name":"Ossipee Area Chamber-Commerce",
    "wof:placetype":"venue"
},
  "geometry": {"coordinates":[-71.20231099999999,43.820543],"type":"Point"}
}