{
  "type": "Feature",
  "properties": {
    "iso:country":"US",
    "sg:address":"1701 Hooksett Rd Unit B",
    "sg:city":"Hooksett",
    "sg:classifiers":[
        {
            "category":"Education",
            "subcategory":"Library",
            "type":"Public Place"
        },
        {
            "category":"Government",
            "subcategory":"Office",
            "type":"Public Place"
        }
    ],
    "sg:phone":"+1 603 485 6092",
    "sg:postcode":"03106",
    "sg:province":"NH",
    "sg:tags":[
        "township",
        "government-city",
        "village"
    ],
    "wof:name":"Town Of Hooksett",
    "wof:placetype":"venue"
},
  "geometry": {"coordinates":[-71.45316800000001,43.093608],"type":"Point"}
}