{
  "type": "Feature",
  "properties": {
    "addr:full":"224 Main St Ste 2A Salem NH 03079",
    "addr:housenumber":"224",
    "addr:postcode":"03079",
    "addr:street":"Main St Ste 2A",
    "iso:country":"US",
    "sg:address":"224 Main St Ste 2A",
    "sg:city":"Salem",
    "sg:classifiers":[
        {
            "category":"Insurance",
            "subcategory":"Insurance Agent",
            "type":"Services"
        },
        {
            "category":"Insurance",
            "subcategory":"Hazard Insurance",
            "type":"Services"
        },
        {
            "category":"Banks & Credit Unions",
            "subcategory":"Financial Services",
            "type":"Services"
        }
    ],
    "sg:phone":"+1 877 669 6877",
    "sg:postcode":"03079",
    "sg:province":"NH",
    "sg:tags":[
        "sharing",
        "business",
        "profit",
        "auto",
        "commercial",
        "plan",
        "property",
        "casualty",
        "pension"
    ],
    "wof:name":"Nationwide Insurance",
    "wof:placetype":"venue"
},
  "geometry": {"coordinates":[-71.213356,42.783978],"type":"Point"}
}