{
  "type": "Feature",
  "properties": {
    "iso:country":"US",
    "sg:address":"14 Broad St",
    "sg:city":"Nashua",
    "sg:classifiers":[
        {
            "category":"Shopping",
            "subcategory":"Bicycles & Sporting Goods",
            "type":"Retail Goods"
        }
    ],
    "sg:phone":"+1 603 595 6466",
    "sg:postcode":"03064",
    "sg:province":"NH",
    "wof:name":"Goodale's Bike Shop",
    "wof:placetype":"venue"
},
  "geometry": {"coordinates":[-71.481129,42.769913],"type":"Point"}
}