{
  "type": "Feature",
  "properties": {
    "iso:country":"US",
    "sg:address":"328 Blakes Hill Rd",
    "sg:city":"Northwood",
    "sg:classifiers":[
        {
            "category":"Building & Trades",
            "subcategory":"Construction",
            "type":"Services"
        }
    ],
    "sg:phone":"+1 603 942 5317",
    "sg:postcode":"03261",
    "sg:province":"NH",
    "sg:tags":[
        "house"
    ],
    "wof:name":"Water View Construction",
    "wof:placetype":"venue"
},
  "geometry": {"coordinates":[-71.230527,43.206679],"type":"Point"}
}