{
  "type": "Feature",
  "properties": {
    "addr:full":"12 Park Ave Hudson NH 03051",
    "addr:housenumber":"12",
    "addr:postcode":"03051",
    "addr:street":"Park Ave",
    "iso:country":"US",
    "sg:address":"12 Park Ave",
    "sg:city":"Hudson",
    "sg:classifiers":[
        {
            "category":"Manufacturing",
            "subcategory":"Metals",
            "type":"Manufacturing & Wholesale Goods"
        }
    ],
    "sg:phone":"+1 603 889 2600",
    "sg:postcode":"03051",
    "sg:province":"NH",
    "sg:tags":[
        "plate",
        "medium",
        "precision",
        "fabrication"
    ],
    "wof:name":"Gilchrist Metal Fabricating Co",
    "wof:placetype":"venue"
},
  "geometry": {"coordinates":[-71.38141400000001,42.781352],"type":"Point"}
}