{
  "type": "Feature",
  "properties": {
    "iso:country":"US",
    "sg:address":"505 Sheffield Rd",
    "sg:city":"Manchester",
    "sg:classifiers":[
        {
            "category":"Recreation",
            "subcategory":"Dog Park",
            "type":"Entertainment"
        },
        {
            "category":"Animal Shelter",
            "type":"Public Place"
        },
        {
            "category":"Shopping",
            "subcategory":"Pets & Pet Supplies",
            "type":"Retail Goods"
        },
        {
            "category":"Retail",
            "subcategory":"Animal Services",
            "type":"Services"
        },
        {
            "category":"Retail",
            "subcategory":"Pet Boarding",
            "type":"Services"
        }
    ],
    "sg:phone":"+1 603 669 4644",
    "sg:postcode":"03103",
    "sg:province":"NH",
    "sg:tags":[
        "training",
        "grooming",
        "kennel",
        "cat"
    ],
    "sg:website":"http://www.alldogsgym.com",
    "wof:name":"All Dogs Gym & Inn",
    "wof:placetype":"venue"
},
  "geometry": {"coordinates":[-71.41843900000001,42.94157],"type":"Point"}
}