{
  "type": "Feature",
  "properties": {
    "iso:country":"US",
    "sg:address":"31 Court St",
    "sg:city":"Laconia",
    "sg:classifiers":[
        {
            "category":"Manufacturing",
            "subcategory":"Printing",
            "type":"Manufacturing & Wholesale Goods"
        }
    ],
    "sg:phone":"+1 603 524 2803",
    "sg:postcode":"03246",
    "sg:province":"NH",
    "sg:tags":[
        "lithographic",
        "commercial"
    ],
    "wof:name":"Winnisquam Printing & Copying",
    "wof:placetype":"venue"
},
  "geometry": {"coordinates":[-71.469037,43.525252],"type":"Point"}
}