{
  "type": "Feature",
  "properties": {
    "iso:country":"US",
    "sg:address":"164 State Rte 125",
    "sg:city":"Kingston",
    "sg:classifiers":[
        {
            "category":"Shopping",
            "type":"Retail Goods"
        }
    ],
    "sg:phone":"+1 603 642 6464",
    "sg:postcode":"03848",
    "sg:province":"NH",
    "sg:tags":[
        "merchandise"
    ],
    "wof:name":"Kingston Self Storage",
    "wof:placetype":"venue"
},
  "geometry": {"coordinates":[-71.053392,42.917187],"type":"Point"}
}