{
  "type": "Feature",
  "properties": {
    "addr:full":"391 Ten Rod Rd Farmington NH 03835",
    "addr:housenumber":"391",
    "addr:postcode":"03835",
    "addr:street":"Ten Rod Rd",
    "iso:country":"US",
    "sg:address":"391 Ten Rod Rd",
    "sg:city":"Farmington",
    "sg:classifiers":[
        {
            "category":"Building & Trades",
            "subcategory":"Construction",
            "type":"Services"
        }
    ],
    "sg:phone":"+1 603 335 4156",
    "sg:postcode":"03835",
    "sg:province":"NH",
    "sg:tags":[
        "siding",
        "contractor"
    ],
    "wof:name":"David Currier Siding & Windows",
    "wof:placetype":"venue"
},
  "geometry": {"coordinates":[-71.024339,43.329302],"type":"Point"}
}