{
  "type": "Feature",
  "properties": {
    "addr:full":"14 Coolidge St Jaffrey NH 03452",
    "addr:housenumber":"14",
    "addr:postcode":"03452",
    "addr:street":"Coolidge St",
    "iso:country":"US",
    "sg:address":"14 Coolidge St",
    "sg:city":"Jaffrey",
    "sg:classifiers":[
        {
            "category":"Organizations",
            "subcategory":"Membership Organization",
            "type":"Services"
        }
    ],
    "sg:phone":"+1 603 532 5752",
    "sg:postcode":"03452",
    "sg:province":"NH",
    "wof:name":"Monadnock Kitty Rescue & Adopt",
    "wof:placetype":"venue"
},
  "geometry": {"coordinates":[-72.019784,42.819896],"type":"Point"}
}