{
  "type": "Feature",
  "properties": {
    "iso:country":"US",
    "sg:address":"581 S Beech St",
    "sg:city":"Manchester",
    "sg:classifiers":[
        {
            "category":"Building & Trades",
            "subcategory":"Construction",
            "type":"Services"
        }
    ],
    "sg:phone":"+1 603 493 5792",
    "sg:postcode":"03103",
    "sg:province":"NH",
    "sg:tags":[
        "home",
        "builder"
    ],
    "wof:name":"Park Place Custom Home Bldrs",
    "wof:placetype":"venue"
},
  "geometry": {"coordinates":[-71.455484,42.962404],"type":"Point"}
}