{
  "type": "Feature",
  "properties": {
    "iso:country":"US",
    "sg:address":"11 Water St",
    "sg:city":"Bradford",
    "sg:classifiers":[
        {
            "category":"Real Estate",
            "subcategory":"Real Estate Operator",
            "type":"Services"
        }
    ],
    "sg:phone":"+1 603 938 2878",
    "sg:postcode":"03221",
    "sg:province":"NH",
    "sg:tags":[
        "building",
        "nonresidential"
    ],
    "wof:name":"Kearsarge Properties LLC",
    "wof:placetype":"venue"
},
  "geometry": {"coordinates":[-71.967625,43.269673],"type":"Point"}
}