{
  "type": "Feature",
  "properties": {
    "iso:country":"US",
    "sg:address":"64 Lowell Rd",
    "sg:city":"Windham",
    "sg:classifiers":[
        {
            "category":"Wholesale",
            "subcategory":"Durable Goods & Equipment",
            "type":"Manufacturing & Wholesale Goods"
        }
    ],
    "sg:phone":"+1 603 890 6564",
    "sg:postcode":"03087",
    "sg:province":"NH",
    "wof:name":"Windham Tree Service",
    "wof:placetype":"venue"
},
  "geometry": {"coordinates":[-71.307821,42.789617],"type":"Point"}
}