{
  "type": "Feature",
  "properties": {
    "addr:full":"9 Old Cathedral Rd Rindge NH 03461",
    "addr:housenumber":"9",
    "addr:postcode":"03461",
    "addr:street":"Old Cathedral Rd",
    "iso:country":"US",
    "sg:address":"9 Old Cathedral Rd",
    "sg:city":"Rindge",
    "sg:classifiers":[
        {
            "category":"Building & Trades",
            "subcategory":"Construction",
            "type":"Services"
        }
    ],
    "sg:phone":"+1 603 899 6358",
    "sg:postcode":"03461",
    "sg:province":"NH",
    "sg:tags":[
        "contractor"
    ],
    "wof:name":"Jewell Masonry",
    "wof:placetype":"venue"
},
  "geometry": {"coordinates":[-71.998048,42.765771],"type":"Point"}
}