{
  "type": "Feature",
  "properties": {
    "iso:country":"US",
    "sg:address":"106 Woodsville Rd",
    "sg:city":"Monroe",
    "sg:classifiers":[
        {
            "category":"Professional",
            "subcategory":"Accounting & Tax Preparation",
            "type":"Services"
        }
    ],
    "sg:phone":"+1 603 638 2130",
    "sg:postcode":"03771",
    "sg:province":"NH",
    "sg:tags":[
        "return"
    ],
    "wof:name":"Monroe Tax Service",
    "wof:placetype":"venue"
},
  "geometry": {"coordinates":[-72.05285000000001,44.258268],"type":"Point"}
}