{
  "type": "Feature",
  "properties": {
    "addr:full":"257 Bay Rd Sanbornton NH 03269",
    "addr:housenumber":"257",
    "addr:postcode":"03269",
    "addr:street":"Bay Rd",
    "iso:country":"US",
    "sg:address":"257 Bay Rd",
    "sg:city":"Sanbornton",
    "sg:classifiers":[
        {
            "category":"Building & Trades",
            "subcategory":"Landscaping Services",
            "type":"Services"
        }
    ],
    "sg:phone":"+1 603 528 2028",
    "sg:postcode":"03269",
    "sg:province":"NH",
    "sg:tags":[
        "landscape"
    ],
    "wof:name":"Landscaping Doctor From Little",
    "wof:placetype":"venue"
},
  "geometry": {"coordinates":[-71.51858,43.507965],"type":"Point"}
}