{
  "type": "Feature",
  "properties": {
    "iso:country":"US",
    "sg:address":"322 Hillhaven Rd",
    "sg:city":"Manchester",
    "sg:classifiers":[
        {
            "category":"Shopping",
            "subcategory":"Clothing, Apparel, & Fashions",
            "type":"Retail Goods"
        }
    ],
    "sg:phone":"+1 603 623 4575",
    "sg:postcode":"03104",
    "sg:province":"NH",
    "wof:name":"Merry Makers",
    "wof:placetype":"venue"
},
  "geometry": {"coordinates":[-71.44359300000001,43.013411],"type":"Point"}
}