{
  "type": "Feature",
  "properties": {
    "iso:country":"US",
    "sg:address":"33 Indian Rock Rd",
    "sg:city":"Windham",
    "sg:classifiers":[
        {
            "category":"Restaurant",
            "type":"Food & Drink"
        }
    ],
    "sg:menulink":"http://www.allmenus.com/nh/windham/281143-capri-pizza/menu/",
    "sg:phone":"+1 603 432 3600",
    "sg:postcode":"03087",
    "sg:province":"NH",
    "sg:tags":[
        "american",
        "pizza"
    ],
    "wof:name":"Capri Pizza",
    "wof:placetype":"venue"
},
  "geometry": {"coordinates":[-71.293487,42.806393],"type":"Point"}
}