{
  "type": "Feature",
  "properties": {
    "addr:full":"1 Orchard Dr Hollis NH 03049",
    "addr:housenumber":"1",
    "addr:postcode":"03049",
    "addr:street":"Orchard Dr",
    "iso:country":"US",
    "sg:address":"1 Orchard Dr",
    "sg:city":"Hollis",
    "sg:classifiers":[
        {
            "category":"Banks & Credit Unions",
            "subcategory":"Investment Brokerage",
            "type":"Services"
        }
    ],
    "sg:phone":"+1 603 465 2548",
    "sg:postcode":"03049",
    "sg:province":"NH",
    "sg:tags":[
        "security"
    ],
    "wof:name":"American Express",
    "wof:placetype":"venue"
},
  "geometry": {"coordinates":[-71.580905,42.732319],"type":"Point"}
}