{
  "type": "Feature",
  "properties": {
    "addr:full":"336 Salmon Falls Rd Rochester NH 03868",
    "addr:housenumber":"336",
    "addr:postcode":"03868",
    "addr:street":"Salmon Falls Rd",
    "iso:country":"US",
    "sg:address":"336 Salmon Falls Rd",
    "sg:city":"Rochester",
    "sg:classifiers":[
        {
            "category":"Organizations",
            "subcategory":"Religious Organization",
            "type":"Services"
        }
    ],
    "sg:phone":"+1 603 332 7193",
    "sg:postcode":"03868",
    "sg:province":"NH",
    "sg:tags":[
        "church"
    ],
    "wof:name":"Church Of Christ",
    "wof:placetype":"venue"
},
  "geometry": {"coordinates":[-70.940907,43.318231],"type":"Point"}
}