{
  "type": "Feature",
  "properties": {
    "iso:country":"US",
    "sg:address":"107 Main St",
    "sg:city":"West Lebanon",
    "sg:classifiers":[
        {
            "category":"Shopping",
            "type":"Retail Goods"
        }
    ],
    "sg:phone":"+1 603 298 7800",
    "sg:postcode":"03784",
    "sg:province":"NH",
    "sg:tags":[
        "hearing",
        "equipment",
        "supply",
        "merchandise",
        "impaired"
    ],
    "wof:name":"Dartmouth Hearing Aids",
    "wof:placetype":"venue"
},
  "geometry": {"coordinates":[-72.31674099999999,43.634672],"type":"Point"}
}