{
  "type": "Feature",
  "properties": {
    "addr:full":"69 Green St Somersworth ME 03878",
    "addr:housenumber":"69",
    "addr:postcode":"03878",
    "addr:street":"Green St",
    "iso:country":"US",
    "sg:address":"69 Green St",
    "sg:city":"Somersworth",
    "sg:classifiers":[
        {
            "category":"Building & Trades",
            "subcategory":"Construction",
            "type":"Services"
        }
    ],
    "sg:phone":"+1 603 692 6047",
    "sg:postcode":"03878",
    "sg:province":"ME",
    "sg:tags":[
        "contractor"
    ],
    "wof:name":"Murcon Construction",
    "wof:placetype":"venue"
},
  "geometry": {"coordinates":[-70.86375099999999,43.256469],"type":"Point"}
}