{
  "type": "Feature",
  "properties": {
    "iso:country":"US",
    "sg:address":"20 Washington Pl",
    "sg:city":"Bedford",
    "sg:classifiers":[
        {
            "category":"Health Services",
            "subcategory":"Doctor",
            "type":"Services"
        }
    ],
    "sg:phone":"+1 603 663 8060",
    "sg:postcode":"03110",
    "sg:province":"NH",
    "sg:tags":[
        "physician",
        "surgeon"
    ],
    "wof:name":"Willowbend Family Practice",
    "wof:placetype":"venue"
},
  "geometry": {"coordinates":[-71.478758,42.960664],"type":"Point"}
}