{
  "type": "Feature",
  "properties": {
    "addr:full":"8 Manhattan Drive Amherst NH 03031",
    "addr:housenumber":"8",
    "addr:postcode":"03031",
    "addr:street":"Manhattan Drive",
    "iso:country":"US",
    "sg:address":"8 Manhattan Drive",
    "sg:city":"Amherst",
    "sg:classifiers":[
        {
            "category":"Food & Beverages",
            "subcategory":"Bakery",
            "type":"Retail Goods"
        }
    ],
    "sg:phone":"+1 603 594 4000",
    "sg:postcode":"03031",
    "sg:province":"NH",
    "sg:tags":[
        "bakers-wholesale"
    ],
    "wof:name":"The Bread Chef",
    "wof:placetype":"venue"
},
  "geometry": {"coordinates":[-71.57507200000001,42.803527],"type":"Point"}
}