{
  "type": "Feature",
  "properties": {
    "addr:full":"493 Amherst St Nashua NH 03063",
    "addr:housenumber":"493",
    "addr:postcode":"03063",
    "addr:street":"Amherst St",
    "iso:country":"US",
    "sg:address":"493 Amherst St",
    "sg:city":"Nashua",
    "sg:classifiers":[
        {
            "category":"Home & Garden",
            "subcategory":"Home Furnishings",
            "type":"Retail Goods"
        }
    ],
    "sg:phone":"+1 603 882 1766",
    "sg:postcode":"03063",
    "sg:province":"NH",
    "sg:tags":[
        "curtain",
        "made",
        "drapery",
        "wallpaper",
        "carpet"
    ],
    "wof:name":"Drapery Cottage",
    "wof:placetype":"venue"
},
  "geometry": {"coordinates":[-71.518591,42.790651],"type":"Point"}
}