{
  "type": "Feature",
  "properties": {
    "iso:country":"US",
    "sg:address":"26 French Rd",
    "sg:city":"Henniker",
    "sg:classifiers":[
        {
            "category":"Building & Trades",
            "subcategory":"Construction",
            "type":"Services"
        }
    ],
    "sg:phone":"+1 603 428 6333",
    "sg:postcode":"03242",
    "sg:province":"NH",
    "sg:tags":[
        "boring",
        "drilling",
        "contractor"
    ],
    "sg:website":"www.hddbore.com",
    "wof:name":"Henniker Directional Drilling",
    "wof:placetype":"venue"
},
  "geometry": {"coordinates":[-71.779374,43.206062],"type":"Point"}
}