{
  "type": "Feature",
  "properties": {
    "iso:country":"US",
    "sg:address":"186 Bunker Hill Rd",
    "sg:city":"Auburn",
    "sg:classifiers":[
        {
            "category":"Communications",
            "subcategory":"Film & Video Production",
            "type":"Services"
        }
    ],
    "sg:phone":"+1 603 483 2673",
    "sg:postcode":"03032",
    "sg:province":"NH",
    "sg:tags":[
        "taping"
    ],
    "wof:name":"Reel Image Productions",
    "wof:placetype":"venue"
},
  "geometry": {"coordinates":[-71.326677,42.993421],"type":"Point"}
}