{
  "type": "Feature",
  "properties": {
    "iso:country":"US",
    "sg:address":"77 Pearl St",
    "sg:city":"Manchester",
    "sg:classifiers":[
        {
            "category":"Insurance",
            "subcategory":"Hazard Insurance",
            "type":"Services"
        },
        {
            "category":"Social Services",
            "type":"Services"
        }
    ],
    "sg:phone":"+1 603 647 5600",
    "sg:postcode":"03101",
    "sg:province":"NH",
    "sg:tags":[
        "profit",
        "sharing",
        "pension",
        "plan"
    ],
    "wof:name":"Retirement Alliance Inc",
    "wof:placetype":"venue"
},
  "geometry": {"coordinates":[-71.461302,42.995768],"type":"Point"}
}