{
  "type": "Feature",
  "properties": {
    "iso:country":"US",
    "sg:address":"47 Dutton Rd",
    "sg:city":"Pelham",
    "sg:classifiers":[
        {
            "category":"Personal",
            "type":"Services"
        },
        {
            "category":"Shopping",
            "subcategory":"Clothing, Apparel, & Fashions",
            "type":"Retail Goods"
        }
    ],
    "sg:phone":"+1 603 635 7396",
    "sg:postcode":"03076",
    "sg:province":"NH",
    "sg:tags":[
        "shop",
        "bridal"
    ],
    "wof:name":"Designs By Colleen",
    "wof:placetype":"venue"
},
  "geometry": {"coordinates":[-71.30346,42.719556],"type":"Point"}
}