{
  "type": "Feature",
  "properties": {
    "iso:country":"US",
    "sg:address":"8 Juniper Ridge Rd",
    "sg:city":"Exeter",
    "sg:classifiers":[
        {
            "category":"Professional",
            "subcategory":"Computer Services",
            "type":"Services"
        }
    ],
    "sg:phone":"+1 603 778 4236",
    "sg:postcode":"03833",
    "sg:province":"NH",
    "sg:tags":[
        "consultant",
        "designer"
    ],
    "wof:name":"Codeworks Software Systems",
    "wof:placetype":"venue"
},
  "geometry": {"coordinates":[-70.989389,42.965062],"type":"Point"}
}