{
  "type": "Feature",
  "properties": {
    "iso:country":"US",
    "sg:address":"33 Highland Ave",
    "sg:city":"Derry",
    "sg:classifiers":[
        {
            "category":"Freight",
            "type":"Transportation"
        }
    ],
    "sg:phone":"+1 603 437 8203",
    "sg:postcode":"03038",
    "sg:province":"NH",
    "sg:tags":[
        "a",
        "food",
        "delivery",
        "operates"
    ],
    "wof:name":"Ken Graves Provisions",
    "wof:placetype":"venue"
},
  "geometry": {"coordinates":[-71.326545,42.873966],"type":"Point"}
}