{
  "type": "Feature",
  "properties": {
    "iso:country":"US",
    "sg:address":"200 Main St",
    "sg:city":"Charlestown",
    "sg:classifiers":[
        {
            "category":"Food & Beverages",
            "subcategory":"Groceries & Convenience Stores",
            "type":"Retail Goods"
        }
    ],
    "sg:phone":"+1 603 826 9777",
    "sg:postcode":"03603",
    "sg:province":"NH",
    "sg:website":"www.jiffymartstores.com",
    "wof:name":"Charleston Jiffy Mart",
    "wof:placetype":"venue"
},
  "geometry": {"coordinates":[-72.424216,43.234572],"type":"Point"}
}