{
  "type": "Feature",
  "properties": {
    "iso:country":"US",
    "sg:address":"81 Portsmouth Ave",
    "sg:city":"Stratham",
    "sg:classifiers":[
        {
            "category":"Banks & Credit Unions",
            "subcategory":"Investment Brokerage",
            "type":"Services"
        }
    ],
    "sg:phone":"+1 603 773 0022",
    "sg:postcode":"03885",
    "sg:province":"NH",
    "sg:tags":[
        "security",
        "management",
        "consulting"
    ],
    "wof:name":"Commonwealth Financial Network",
    "wof:placetype":"venue"
},
  "geometry": {"coordinates":[-70.91963199999999,43.003094],"type":"Point"}
}