{
  "type": "Feature",
  "properties": {
    "addr:full":"2 Main St Hollis NH 03049",
    "addr:housenumber":"2",
    "addr:postcode":"03049",
    "addr:street":"Main St",
    "iso:country":"US",
    "sg:address":"2 Main St",
    "sg:city":"Hollis",
    "sg:classifiers":[
        {
            "category":"Real Estate",
            "subcategory":"Real Estate Agent",
            "type":"Services"
        }
    ],
    "sg:phone":"+1 603 465 9042",
    "sg:postcode":"03049",
    "sg:province":"NH",
    "sg:website":"www.masiello.com",
    "wof:name":"ERA Masiello Group",
    "wof:placetype":"venue"
},
  "geometry": {"coordinates":[-71.59074699999999,42.739762],"type":"Point"}
}