{
  "type": "Feature",
  "properties": {
    "iso:country":"US",
    "sg:address":"620 Lafayette Rd",
    "sg:city":"Seabrook",
    "sg:classifiers":[
        {
            "category":"Restaurant",
            "type":"Food & Drink"
        }
    ],
    "sg:phone":"+1 603 474 2355",
    "sg:postcode":"03874",
    "sg:province":"NH",
    "wof:name":"Breakwater Grill & Sports Bar",
    "wof:placetype":"venue"
},
  "geometry": {"coordinates":[-70.87241899999999,42.891965],"type":"Point"}
}