{
  "type": "Feature",
  "properties": {
    "iso:country":"US",
    "sg:address":"26 Andrews Ln",
    "sg:city":"East Kingston",
    "sg:classifiers":[
        {
            "category":"Retail",
            "subcategory":"Repair Shop",
            "type":"Services"
        }
    ],
    "sg:phone":"+1 603 642 8034",
    "sg:postcode":"03827",
    "sg:province":"NH",
    "wof:name":"Batal Blacksmith",
    "wof:placetype":"venue"
},
  "geometry": {"coordinates":[-70.990531,42.915582],"type":"Point"}
}