{
  "type": "Feature",
  "properties": {
    "iso:country":"US",
    "sg:address":"5 Hedman Ave",
    "sg:city":"Hampton",
    "sg:classifiers":[
        {
            "category":"Retail",
            "subcategory":"Portrait Studio",
            "type":"Services"
        }
    ],
    "sg:phone":"+1 603 926 5399",
    "sg:postcode":"03842",
    "sg:province":"NH",
    "sg:tags":[
        "photo"
    ],
    "wof:name":"Portrait Partners",
    "wof:placetype":"venue"
},
  "geometry": {"coordinates":[-70.814644,42.936738],"type":"Point"}
}