{
  "type": "Feature",
  "properties": {
    "addr:full":"1 Executive Park Dr Merrimack NH 03054",
    "addr:housenumber":"1",
    "addr:postcode":"03054",
    "addr:street":"Executive Park Dr",
    "iso:country":"US",
    "sg:address":"1 Executive Park Dr",
    "sg:city":"Merrimack",
    "sg:classifiers":[
        {
            "category":"Restaurant",
            "type":"Food & Drink"
        }
    ],
    "sg:menulink":"http://www.allmenus.com/nh/merrimack/91180-dangelo-sandwich-shops/menu/",
    "sg:phone":"+1 603 424 4499",
    "sg:postcode":"03054",
    "sg:province":"NH",
    "sg:tags":[
        "wrap",
        "soup",
        "american",
        "sandwich",
        "salad"
    ],
    "wof:name":"D'Angelo Sandwich Shops",
    "wof:placetype":"venue"
},
  "geometry": {"coordinates":[-71.495561,42.841111],"type":"Point"}
}