{
  "type": "Feature",
  "properties": {
    "iso:country":"US",
    "sg:address":"112 State St",
    "sg:city":"Portsmouth",
    "sg:classifiers":[
        {
            "category":"Shopping",
            "type":"Retail Goods"
        }
    ],
    "sg:phone":"+1 603 433 6002",
    "sg:postcode":"03801",
    "sg:province":"NH",
    "sg:tags":[
        "art",
        "gallery",
        "dealer"
    ],
    "wof:name":"Arte Toscana",
    "wof:placetype":"venue"
},
  "geometry": {"coordinates":[-70.754458,43.077044],"type":"Point"}
}