{
  "type": "Feature",
  "properties": {
    "iso:country":"US",
    "sg:address":"15 Tolles St",
    "sg:city":"Hudson",
    "sg:classifiers":[
        {
            "category":"Autos & Motor Vehicles",
            "subcategory":"Automobile Sales",
            "type":"Retail Goods"
        }
    ],
    "sg:phone":"+1 603 594 3101",
    "sg:postcode":"03051",
    "sg:province":"NH",
    "sg:tags":[
        "used"
    ],
    "wof:name":"Modern Auto Sales",
    "wof:placetype":"venue"
},
  "geometry": {"coordinates":[-71.447981,42.771569],"type":"Point"}
}