{
  "type": "Feature",
  "properties": {
    "iso:country":"US",
    "sg:address":"12 N Meadows Plz",
    "sg:city":"Walpole",
    "sg:classifiers":[
        {
            "category":"Shopping",
            "subcategory":"Gifts & Souvenirs",
            "type":"Retail Goods"
        }
    ],
    "sg:phone":"+1 603 756 9230",
    "sg:postcode":"03608",
    "sg:province":"NH",
    "wof:name":"Heidis Hallmark of Walpolk",
    "wof:placetype":"venue"
},
  "geometry": {"coordinates":[-72.423129,43.107076],"type":"Point"}
}