{
  "type": "Feature",
  "properties": {
    "iso:country":"US",
    "sg:address":"135 English Village Rd",
    "sg:city":"Manchester",
    "sg:classifiers":[
        {
            "category":"Real Estate",
            "subcategory":"Real Estate Operator",
            "type":"Services"
        }
    ],
    "sg:phone":"+1 603 624 1544",
    "sg:postcode":"03102",
    "sg:province":"NH",
    "sg:tags":[
        "apartment"
    ],
    "wof:name":"Pinewood Estates",
    "wof:placetype":"venue"
},
  "geometry": {"coordinates":[-71.485674,43.011048],"type":"Point"}
}