{
  "type": "Feature",
  "properties": {
    "iso:country":"US",
    "sg:address":"112 South Rd",
    "sg:city":"Brentwood",
    "sg:classifiers":[
        {
            "category":"Professional",
            "subcategory":"Management & Consulting",
            "type":"Services"
        },
        {
            "category":"Building & Trades",
            "subcategory":"Construction",
            "type":"Services"
        }
    ],
    "sg:phone":"+1 603 642 9254",
    "sg:postcode":"03833",
    "sg:province":"NH",
    "sg:tags":[
        "roofing",
        "contractor",
        "consultant"
    ],
    "wof:name":"Millenium Waterproofing Inc",
    "wof:placetype":"venue"
},
  "geometry": {"coordinates":[-71.02693600000001,42.961955],"type":"Point"}
}