{
  "type": "Feature",
  "properties": {
    "addr:full":"161 Main St Conway NH 03818",
    "addr:housenumber":"161",
    "addr:postcode":"03818",
    "addr:street":"Main St",
    "iso:country":"US",
    "sg:address":"161 Main St",
    "sg:city":"Conway",
    "sg:classifiers":[
        {
            "category":"Food & Beverages",
            "subcategory":"Groceries & Convenience Stores",
            "type":"Retail Goods"
        }
    ],
    "sg:phone":"+1 603 447 3117",
    "sg:postcode":"03818",
    "sg:province":"NH",
    "sg:website":"www.cumberlandfarms.com",
    "wof:name":"Cumberland Farms",
    "wof:placetype":"venue"
},
  "geometry": {"coordinates":[-71.126706,43.97884],"type":"Point"}
}