{
  "type": "Feature",
  "properties": {
    "addr:full":"27 Borough Rd Concord NH 03303",
    "addr:housenumber":"27",
    "addr:postcode":"03303",
    "addr:street":"Borough Rd",
    "iso:country":"US",
    "sg:address":"27 Borough Rd",
    "sg:city":"Concord",
    "sg:classifiers":[
        {
            "category":"Building & Trades",
            "subcategory":"Construction",
            "type":"Services"
        }
    ],
    "sg:phone":"+1 603 753 9127",
    "sg:postcode":"03303",
    "sg:province":"NH",
    "sg:tags":[
        "contractor"
    ],
    "wof:name":"Starter Building & Development",
    "wof:placetype":"venue"
},
  "geometry": {"coordinates":[-71.586601,43.2663],"type":"Point"}
}