{
  "type": "Feature",
  "properties": {
    "addr:full":"107 Old Denny Hill Rd Warner NH 03278",
    "addr:housenumber":"107",
    "addr:postcode":"03278",
    "addr:street":"Old Denny Hill Rd",
    "iso:country":"US",
    "sg:address":"107 Old Denny Hill Rd",
    "sg:city":"Warner",
    "sg:classifiers":[
        {
            "category":"Building & Trades",
            "subcategory":"Electrical",
            "type":"Services"
        }
    ],
    "sg:phone":"+1 603 456 3131",
    "sg:postcode":"03278",
    "sg:province":"NH",
    "sg:tags":[
        "electrical",
        "contractor"
    ],
    "wof:name":"Denny Hill Electric Inc",
    "wof:placetype":"venue"
},
  "geometry": {"coordinates":[-71.80452699999999,43.282355],"type":"Point"}
}