{
  "type": "Feature",
  "properties": {
    "addr:full":"325 Main St Gorham NH 03581",
    "addr:housenumber":"325",
    "addr:postcode":"03581",
    "addr:street":"Main St",
    "iso:country":"US",
    "sg:address":"325 Main St",
    "sg:city":"Gorham",
    "sg:classifiers":[
        {
            "category":"Shopping",
            "subcategory":"Shoes",
            "type":"Retail Goods"
        }
    ],
    "sg:phone":"+1 603 466 2441",
    "sg:postcode":"03581",
    "sg:province":"NH",
    "wof:name":"Sports Shoe Center",
    "wof:placetype":"venue"
},
  "geometry": {"coordinates":[-71.19414,44.39595],"type":"Point"}
}