{
  "type": "Feature",
  "properties": {
    "iso:country":"US",
    "sg:address":"5 Howard St",
    "sg:city":"Derry",
    "sg:classifiers":[
        {
            "category":"Shopping",
            "subcategory":"Computers & Home Electronics",
            "type":"Retail Goods"
        }
    ],
    "sg:phone":"+1 603 216 1577",
    "sg:postcode":"03038",
    "sg:province":"NH",
    "wof:name":"Pcs & More",
    "wof:placetype":"venue"
},
  "geometry": {"coordinates":[-71.32700199999999,42.886296],"type":"Point"}
}