{
  "type": "Feature",
  "properties": {
    "addr:full":"4 Hunters Rd Bedford NH 03110",
    "addr:housenumber":"4",
    "addr:postcode":"03110",
    "addr:street":"Hunters Rd",
    "iso:country":"US",
    "sg:address":"4 Hunters Rd",
    "sg:city":"Bedford",
    "sg:classifiers":[
        {
            "category":"Professional",
            "subcategory":"Secretarial Services",
            "type":"Services"
        }
    ],
    "sg:phone":"+1 603 472 8841",
    "sg:postcode":"03110",
    "sg:province":"NH",
    "sg:tags":[
        "convention",
        "court",
        "reporter"
    ],
    "wof:name":"Depositions Unlimited",
    "wof:placetype":"venue"
},
  "geometry": {"coordinates":[-71.545368,42.916445],"type":"Point"}
}