{
  "type": "Feature",
  "properties": {
    "iso:country":"US",
    "sg:address":"261 State Rte 25",
    "sg:city":"Rumney",
    "sg:classifiers":[
        {
            "category":"Restaurant",
            "type":"Food & Drink"
        }
    ],
    "sg:phone":"+1 603 536 1968",
    "sg:postcode":"03266",
    "sg:province":"NH",
    "sg:tags":[
        "eating"
    ],
    "wof:name":"Quonset Hut",
    "wof:placetype":"venue"
},
  "geometry": {"coordinates":[-71.84412399999999,43.795159],"type":"Point"}
}