{
  "type": "Feature",
  "properties": {
    "iso:country":"US",
    "sg:address":"17 Hilldale Ln",
    "sg:city":"New Boston",
    "sg:classifiers":[
        {
            "category":"Government",
            "subcategory":"Office",
            "type":"Public Place"
        }
    ],
    "sg:phone":"+1 603 487 3837",
    "sg:postcode":"03070",
    "sg:province":"NH",
    "sg:tags":[
        "county"
    ],
    "wof:name":"Hillsboro County 4H",
    "wof:placetype":"venue"
},
  "geometry": {"coordinates":[-71.682208,42.982644],"type":"Point"}
}