{
  "type": "Feature",
  "properties": {
    "iso:country":"US",
    "sg:address":"101 Fairgrounds Rd",
    "sg:city":"Plymouth",
    "sg:classifiers":[
        {
            "category":"Organizations",
            "subcategory":"Religious Organization",
            "type":"Services"
        }
    ],
    "sg:phone":"+1 603 536 8908",
    "sg:postcode":"03264",
    "sg:province":"NH",
    "sg:tags":[
        "church"
    ],
    "sg:website":"www.starrkingfellowship.org",
    "wof:name":"Starr King Unitarian Unvrslst",
    "wof:placetype":"venue"
},
  "geometry": {"coordinates":[-71.701809,43.77384],"type":"Point"}
}