{
  "type": "Feature",
  "properties": {
    "iso:country":"US",
    "sg:address":"875 Holt Ave",
    "sg:city":"Manchester",
    "sg:classifiers":[
        {
            "category":"Utilities",
            "subcategory":"Telephone",
            "type":"Services"
        }
    ],
    "sg:phone":"+1 603 695 5527",
    "sg:postcode":"03109",
    "sg:province":"NH",
    "sg:tags":[
        "communications"
    ],
    "wof:name":"Verizon",
    "wof:placetype":"venue"
},
  "geometry": {"coordinates":[-71.40825,42.978293],"type":"Point"}
}