{
  "type": "Feature",
  "properties": {
    "iso:country":"US",
    "sg:address":"9 Acorn Dr",
    "sg:city":"Kingston",
    "sg:classifiers":[
        {
            "category":"Real Estate",
            "subcategory":"Surveying",
            "type":"Services"
        }
    ],
    "sg:phone":"+1 603 642 4750",
    "sg:postcode":"03848",
    "sg:province":"NH",
    "sg:tags":[
        "surveyor"
    ],
    "wof:name":"Paul F Nichols Civil Engineers",
    "wof:placetype":"venue"
},
  "geometry": {"coordinates":[-71.081446,42.920313],"type":"Point"}
}