{
  "type": "Feature",
  "properties": {
    "iso:country":"US",
    "sg:address":"84 Stowell Rd",
    "sg:city":"New Ipswich",
    "sg:classifiers":[
        {
            "category":"Building & Trades",
            "subcategory":"Construction",
            "type":"Services"
        }
    ],
    "sg:phone":"+1 603 878 0798",
    "sg:postcode":"03071",
    "sg:province":"NH",
    "sg:tags":[
        "general",
        "contractor"
    ],
    "wof:name":"Maillet Construction",
    "wof:placetype":"venue"
},
  "geometry": {"coordinates":[-71.848175,42.777674],"type":"Point"}
}