{
  "type": "Feature",
  "properties": {
    "addr:full":"293 Calef Rd Manchester NH 03103",
    "addr:housenumber":"293",
    "addr:postcode":"03103",
    "addr:street":"Calef Rd",
    "iso:country":"US",
    "sg:address":"293 Calef Rd",
    "sg:city":"Manchester",
    "sg:classifiers":[
        {
            "category":"Building & Trades",
            "subcategory":"Construction",
            "type":"Services"
        }
    ],
    "sg:phone":"+1 603 626 9685",
    "sg:postcode":"03103",
    "sg:province":"NH",
    "sg:tags":[
        "home",
        "improvement"
    ],
    "wof:name":"Scott's Home Improvements",
    "wof:placetype":"venue"
},
  "geometry": {"coordinates":[-71.460272,42.96843],"type":"Point"}
}