{
  "type": "Feature",
  "properties": {
    "addr:full":"10 Lorden Dr Milford NH 03055",
    "addr:housenumber":"10",
    "addr:postcode":"03055",
    "addr:street":"Lorden Dr",
    "iso:country":"US",
    "sg:address":"10 Lorden Dr",
    "sg:city":"Milford",
    "sg:classifiers":[
        {
            "category":"Restaurant",
            "type":"Food & Drink"
        }
    ],
    "sg:menulink":"http://www.allmenus.com/nh/milford/91181-dangelo-sandwich-shops/menu/",
    "sg:phone":"+1 603 672 2700",
    "sg:postcode":"03055",
    "sg:province":"NH",
    "sg:tags":[
        "wrap",
        "soup",
        "american",
        "sandwich",
        "salad"
    ],
    "wof:name":"D'Angelo Sandwich Shops",
    "wof:placetype":"venue"
},
  "geometry": {"coordinates":[-71.696693,42.824592],"type":"Point"}
}