{
  "type": "Feature",
  "properties": {
    "iso:country":"US",
    "sg:address":"51 Harvard Ln",
    "sg:city":"Bedford",
    "sg:classifiers":[
        {
            "category":"Personal",
            "subcategory":"Massage",
            "type":"Services"
        }
    ],
    "sg:phone":"+1 603 472 9723",
    "sg:postcode":"03110",
    "sg:province":"NH",
    "wof:name":"Redfern Massage Therapy",
    "wof:placetype":"venue"
},
  "geometry": {"coordinates":[-71.542644,42.946912],"type":"Point"}
}