{
  "type": "Feature",
  "properties": {
    "iso:country":"US",
    "sg:address":"103 State Rte 13",
    "sg:city":"Brookline",
    "sg:classifiers":[
        {
            "category":"Autos & Motor Vehicles",
            "subcategory":"Fuel & Gas Station",
            "type":"Retail Goods"
        }
    ],
    "sg:phone":"+1 603 673 9861",
    "sg:postcode":"03033",
    "sg:province":"NH",
    "sg:tags":[
        "station",
        "gasoline"
    ],
    "wof:name":"Coreys Mobil Station",
    "wof:placetype":"venue"
},
  "geometry": {"coordinates":[-71.665696,42.731358],"type":"Point"}
}