{
  "type": "Feature",
  "properties": {
    "addr:full":"62 Patten Rd Merrimack NH 03054",
    "addr:housenumber":"62",
    "addr:postcode":"03054",
    "addr:street":"Patten Rd",
    "iso:country":"US",
    "sg:address":"62 Patten Rd",
    "sg:city":"Merrimack",
    "sg:classifiers":[
        {
            "category":"Professional",
            "subcategory":"Business Services",
            "type":"Services"
        }
    ],
    "sg:phone":"+1 603 429 2033",
    "sg:postcode":"03054",
    "sg:province":"NH",
    "wof:name":"Jr Interior Systems",
    "wof:placetype":"venue"
},
  "geometry": {"coordinates":[-71.519014,42.884506],"type":"Point"}
}