{
  "type": "Feature",
  "properties": {
    "iso:country":"US",
    "sg:address":"35 Old Auburn Rd",
    "sg:city":"Derry",
    "sg:classifiers":[
        {
            "category":"Professional",
            "subcategory":"Accounting & Tax Preparation",
            "type":"Services"
        }
    ],
    "sg:phone":"+1 603 434 4848",
    "sg:postcode":"03038",
    "sg:province":"NH",
    "sg:tags":[
        "return"
    ],
    "wof:name":"Douglas Connell Inc",
    "wof:placetype":"venue"
},
  "geometry": {"coordinates":[-71.28921699999999,42.926307],"type":"Point"}
}