{
  "type": "Feature",
  "properties": {
    "iso:country":"US",
    "sg:address":"28 Chestnut St",
    "sg:city":"Portsmouth",
    "sg:classifiers":[
        {
            "category":"Shopping",
            "subcategory":"Computers & Home Electronics",
            "type":"Retail Goods"
        }
    ],
    "sg:phone":"+1 603 431 0652",
    "sg:postcode":"03801",
    "sg:province":"NH",
    "sg:tags":[
        "equipment",
        "satellite",
        "system"
    ],
    "wof:name":"NBC Satellite Operations",
    "wof:placetype":"venue"
},
  "geometry": {"coordinates":[-70.75963,43.076162],"type":"Point"}
}