{
  "type": "Feature",
  "properties": {
    "iso:country":"US",
    "sg:address":"31 Gaita Dr",
    "sg:city":"Derry",
    "sg:classifiers":[
        {
            "category":"Professional",
            "subcategory":"Computer Services",
            "type":"Services"
        }
    ],
    "sg:phone":"+1 603 421 9514",
    "sg:postcode":"03038",
    "sg:province":"NH",
    "sg:tags":[
        "datum"
    ],
    "wof:name":"Duck Design Co",
    "wof:placetype":"venue"
},
  "geometry": {"coordinates":[-71.25310399999999,42.85758],"type":"Point"}
}