{
  "type": "Feature",
  "properties": {
    "iso:country":"US",
    "sg:address":"43 Windham Rd",
    "sg:city":"Derry",
    "sg:classifiers":[
        {
            "category":"Building & Trades",
            "subcategory":"Construction",
            "type":"Services"
        }
    ],
    "sg:phone":"+1 603 432 9845",
    "sg:postcode":"03038",
    "sg:province":"NH",
    "sg:tags":[
        "specializing",
        "sheet",
        "metal",
        "heating",
        "air",
        "co",
        "contractor"
    ],
    "wof:name":"R C Bonner Inc",
    "wof:placetype":"venue"
},
  "geometry": {"coordinates":[-71.310919,42.867164],"type":"Point"}
}