{
  "type": "Feature",
  "properties": {
    "iso:country":"US",
    "sg:address":"131 Daniel Webster Hwy",
    "sg:city":"Nashua",
    "sg:classifiers":[
        {
            "category":"Professional",
            "subcategory":"Accounting & Tax Preparation",
            "type":"Services"
        }
    ],
    "sg:phone":"+1 603 791 4732",
    "sg:postcode":"03060",
    "sg:province":"NH",
    "sg:tags":[
        "bookkeeping"
    ],
    "wof:name":"Sas 70 Specialists",
    "wof:placetype":"venue"
},
  "geometry": {"coordinates":[-71.446528,42.726369],"type":"Point"}
}