{
  "type": "Feature",
  "properties": {
    "addr:full":"48 Constitution Drive Bedford NH 03110",
    "addr:housenumber":"48",
    "addr:postcode":"03110",
    "addr:street":"Constitution Drive",
    "iso:country":"US",
    "sg:address":"48 Constitution Drive",
    "sg:city":"Bedford",
    "sg:classifiers":[
        {
            "category":"Professional",
            "subcategory":"Computer Services",
            "type":"Services"
        }
    ],
    "sg:phone":"+1 603 472 3519",
    "sg:postcode":"03110",
    "sg:province":"NH",
    "sg:website":"http://www.k-vest.com/",
    "wof:name":"K-MOTION Interactive",
    "wof:placetype":"venue"
},
  "geometry": {"coordinates":[-71.50090400000001,42.956301],"type":"Point"}
}