{
  "type": "Feature",
  "properties": {
    "iso:country":"US",
    "sg:address":"19 Winnepocket Rd",
    "sg:city":"Concord",
    "sg:classifiers":[
        {
            "category":"Recreation",
            "type":"Entertainment"
        }
    ],
    "sg:phone":"+1 603 746 4964",
    "sg:postcode":"03303",
    "sg:province":"NH",
    "sg:tags":[
        "club",
        "membership"
    ],
    "wof:name":"Yankee Miniature Horse Club",
    "wof:placetype":"venue"
},
  "geometry": {"coordinates":[-71.732979,43.291962],"type":"Point"}
}