{
  "type": "Feature",
  "properties": {
    "addr:full":"60 Whittier Hwy Center Harbor NH 03254",
    "addr:housenumber":"60",
    "addr:postcode":"03254",
    "addr:street":"Whittier Hwy",
    "iso:country":"US",
    "sg:address":"60 Whittier Hwy",
    "sg:city":"Center Harbor",
    "sg:classifiers":[
        {
            "category":"Health Services",
            "subcategory":"Doctor",
            "type":"Services"
        }
    ],
    "sg:phone":"+1 603 253 4363",
    "sg:postcode":"03254",
    "sg:province":"NH",
    "sg:tags":[
        "dentist"
    ],
    "wof:name":"Interlakes Family Dental Ctr",
    "wof:placetype":"venue"
},
  "geometry": {"coordinates":[-71.45990999999999,43.710034],"type":"Point"}
}