{
  "type": "Feature",
  "properties": {
    "addr:full":"37 Ashuelot St Keene NH 03431",
    "addr:housenumber":"37",
    "addr:postcode":"03431",
    "addr:street":"Ashuelot St",
    "iso:country":"US",
    "sg:address":"37 Ashuelot St",
    "sg:city":"Keene",
    "sg:classifiers":[
        {
            "category":"Health Services",
            "subcategory":"Health Practitioner",
            "type":"Services"
        }
    ],
    "sg:phone":"+1 603 352 6043",
    "sg:postcode":"03431",
    "sg:province":"NH",
    "sg:tags":[
        "therapist",
        "physical"
    ],
    "wof:name":"Healthsouth Sports Medicine",
    "wof:placetype":"venue"
},
  "geometry": {"coordinates":[-72.28604300000001,42.932585],"type":"Point"}
}