{
  "type": "Feature",
  "properties": {
    "addr:full":"767 Post Rd Greenland NH 03840",
    "addr:housenumber":"767",
    "addr:postcode":"03840",
    "addr:street":"Post Rd",
    "iso:country":"US",
    "sg:address":"767 Post Rd",
    "sg:city":"Greenland",
    "sg:classifiers":[
        {
            "category":"Building & Trades",
            "subcategory":"Construction",
            "type":"Services"
        }
    ],
    "sg:phone":"+1 603 433 3279",
    "sg:postcode":"03840",
    "sg:province":"NH",
    "sg:tags":[
        "general",
        "contractor"
    ],
    "wof:name":"Premiere Builders",
    "wof:placetype":"venue"
},
  "geometry": {"coordinates":[-70.83267600000001,43.036755],"type":"Point"}
}