{
  "type": "Feature",
  "properties": {
    "addr:full":"5 Cocheco Ave Rochester NH 03868",
    "addr:housenumber":"5",
    "addr:postcode":"03868",
    "addr:street":"Cocheco Ave",
    "iso:country":"US",
    "sg:address":"5 Cocheco Ave",
    "sg:city":"Rochester",
    "sg:classifiers":[
        {
            "category":"Education",
            "subcategory":"School",
            "type":"Public Place"
        }
    ],
    "sg:phone":"+1 603 332 6486",
    "sg:postcode":"03868",
    "sg:province":"NH",
    "wof:name":"East Rochester Primary Annex",
    "wof:placetype":"venue"
},
  "geometry": {"coordinates":[-70.936879,43.333302],"type":"Point"}
}