{
  "type": "Feature",
  "properties": {
    "iso:country":"US",
    "sg:address":"601 Islington St",
    "sg:city":"Portsmouth",
    "sg:classifiers":[
        {
            "category":"Personal",
            "subcategory":"Tanning Parlor",
            "type":"Services"
        }
    ],
    "sg:phone":"+1 603 431 0300",
    "sg:postcode":"03801",
    "sg:province":"NH",
    "sg:tags":[
        "salon"
    ],
    "wof:name":"24 Hour Tan",
    "wof:placetype":"venue"
},
  "geometry": {"coordinates":[-70.771305,43.070582],"type":"Point"}
}