{
  "type": "Feature",
  "properties": {
    "addr:full":"464 Central Ave Dover NH 03820",
    "addr:housenumber":"464",
    "addr:postcode":"03820",
    "addr:street":"Central Ave",
    "iso:country":"US",
    "sg:address":"464 Central Ave",
    "sg:city":"Dover",
    "sg:classifiers":[
        {
            "category":"Banks & Credit Unions",
            "subcategory":"Investment Brokerage",
            "type":"Services"
        }
    ],
    "sg:phone":"+1 603 749 1646",
    "sg:postcode":"03820",
    "sg:province":"NH",
    "sg:tags":[
        "security"
    ],
    "wof:name":"Edward D Jones & Co LP",
    "wof:placetype":"venue"
},
  "geometry": {"coordinates":[-70.874094,43.197859],"type":"Point"}
}