{
  "type": "Feature",
  "properties": {
    "iso:country":"US",
    "sg:address":"41 Sea Rd",
    "sg:city":"Rye Beach",
    "sg:classifiers":[
        {
            "category":"Professional",
            "subcategory":"Business Services",
            "type":"Services"
        }
    ],
    "sg:phone":"+1 603 964 8859",
    "sg:postcode":"03870",
    "sg:province":"NH",
    "wof:name":"Cynthia Barnes Interior D",
    "wof:placetype":"venue"
},
  "geometry": {"coordinates":[-70.770978,42.978508],"type":"Point"}
}