{
  "type": "Feature",
  "properties": {
    "addr:full":"22 Gosselin Rd Nashua NH 03062",
    "addr:housenumber":"22",
    "addr:postcode":"03062",
    "addr:street":"Gosselin Rd",
    "iso:country":"US",
    "sg:address":"22 Gosselin Rd",
    "sg:city":"Nashua",
    "sg:classifiers":[
        {
            "category":"Real Estate",
            "subcategory":"Real Estate Operator",
            "type":"Services"
        }
    ],
    "sg:phone":"+1 603 882 7508",
    "sg:postcode":"03062",
    "sg:province":"NH",
    "sg:tags":[
        "building",
        "apartment"
    ],
    "wof:name":"B&M Apts",
    "wof:placetype":"venue"
},
  "geometry": {"coordinates":[-71.506507,42.731195],"type":"Point"}
}