{
  "type": "Feature",
  "properties": {
    "iso:country":"US",
    "sg:address":"121 Lafayette Rd",
    "sg:city":"North Hampton",
    "sg:classifiers":[
        {
            "category":"Building & Trades",
            "subcategory":"Plumbing",
            "type":"Services"
        }
    ],
    "sg:phone":"+1 603 964 8065",
    "sg:postcode":"03862",
    "sg:province":"NH",
    "sg:tags":[
        "mechanical",
        "contractor"
    ],
    "wof:name":"Linnane Mechanical Contracting",
    "wof:placetype":"venue"
},
  "geometry": {"coordinates":[-70.834039,42.979072],"type":"Point"}
}