{
  "type": "Feature",
  "properties": {
    "iso:country":"US",
    "sg:address":"16 Harris Ave",
    "sg:city":"Merrimack",
    "sg:classifiers":[
        {
            "category":"Personal",
            "subcategory":"Beauty Salon",
            "type":"Services"
        }
    ],
    "sg:phone":"+1 603 886 1220",
    "sg:postcode":"03054",
    "sg:province":"NH",
    "sg:tags":[
        "shop"
    ],
    "wof:name":"Hairthurium",
    "wof:placetype":"venue"
},
  "geometry": {"coordinates":[-71.477358,42.883931],"type":"Point"}
}