{
  "type": "Feature",
  "properties": {
    "iso:country":"US",
    "sg:address":"830 S Willow St",
    "sg:city":"Manchester",
    "sg:classifiers":[
        {
            "category":"Personal",
            "type":"Services"
        },
        {
            "category":"Restaurant",
            "type":"Food & Drink"
        },
        {
            "category":"Retail",
            "subcategory":"Event Space",
            "type":"Services"
        }
    ],
    "sg:phone":"+1 603 625 5500",
    "sg:postcode":"03103",
    "sg:province":"NH",
    "sg:tags":[
        "style",
        "chinese",
        "family",
        "facility",
        "banquet",
        "planning",
        "asian",
        "reception",
        "party",
        "meeting",
        "hall",
        "pan"
    ],
    "wof:name":"New Yee Dynasty Banquet",
    "wof:placetype":"venue"
},
  "geometry": {"coordinates":[-71.44376200000001,42.963835],"type":"Point"}
}