{
  "type": "Feature",
  "properties": {
    "addr:full":"9 Derry Ln Hudson NH 03051",
    "addr:housenumber":"9",
    "addr:postcode":"03051",
    "addr:street":"Derry Ln",
    "iso:country":"US",
    "sg:address":"9 Derry Ln",
    "sg:city":"Hudson",
    "sg:classifiers":[
        {
            "category":"Health Services",
            "subcategory":"Health Practitioner",
            "type":"Services"
        }
    ],
    "sg:phone":"+1 603 882 4800",
    "sg:postcode":"03051",
    "sg:province":"NH",
    "sg:tags":[
        "acupuncture"
    ],
    "wof:name":"Advanced Health & Wellness Ctr",
    "wof:placetype":"venue"
},
  "geometry": {"coordinates":[-71.44342,42.786522],"type":"Point"}
}