{
  "type": "Feature",
  "properties": {
    "addr:full":"104 Grafton Dr Portsmouth NH 03801",
    "addr:housenumber":"104",
    "addr:postcode":"03801",
    "addr:street":"Grafton Dr",
    "iso:country":"US",
    "sg:address":"104 Grafton Dr",
    "sg:city":"Portsmouth",
    "sg:classifiers":[
        {
            "category":"Airport",
            "type":"Transportation"
        }
    ],
    "sg:phone":"+1 603 430 1199",
    "sg:postcode":"03801",
    "sg:province":"NH",
    "sg:tags":[
        "equipment"
    ],
    "wof:name":"Valley West Avionics",
    "wof:placetype":"venue"
},
  "geometry": {"coordinates":[-70.80572600000001,43.067446],"type":"Point"}
}