{
  "type": "Feature",
  "properties": {
    "iso:country":"US",
    "sg:address":"134 King Rd",
    "sg:city":"Bedford",
    "sg:classifiers":[
        {
            "category":"Organizations",
            "subcategory":"Community Association",
            "type":"Services"
        }
    ],
    "sg:phone":"+1 603 472 5094",
    "sg:postcode":"03110",
    "sg:province":"NH",
    "wof:name":"Bedford Senior Citizens",
    "wof:placetype":"venue"
},
  "geometry": {"coordinates":[-71.59459099999999,42.957642],"type":"Point"}
}