{
  "type": "Feature",
  "properties": {
    "iso:country":"US",
    "sg:address":"2 Continental Blvd",
    "sg:city":"Exeter",
    "sg:classifiers":[
        {
            "category":"Recreation",
            "type":"Entertainment"
        }
    ],
    "sg:phone":"+1 603 772 5811",
    "sg:postcode":"03867",
    "sg:province":"NH",
    "sg:tags":[
        "martial",
        "arts",
        "instruction"
    ],
    "wof:name":"New Hampshire Martial Arts",
    "wof:placetype":"venue"
},
  "geometry": {"coordinates":[-70.934145,43.283601],"type":"Point"}
}