{
  "type": "Feature",
  "properties": {
    "addr:full":"180 Amherst St Amherst NH 03031",
    "addr:housenumber":"180",
    "addr:postcode":"03031",
    "addr:street":"Amherst St",
    "iso:country":"US",
    "sg:address":"180 Amherst St",
    "sg:city":"Amherst",
    "sg:classifiers":[
        {
            "category":"Insurance",
            "subcategory":"Insurance Agent",
            "type":"Services"
        }
    ],
    "sg:phone":"+1 603 882 4190",
    "sg:postcode":"03031",
    "sg:province":"NH",
    "wof:name":"State Farm Insurance",
    "wof:placetype":"venue"
},
  "geometry": {"coordinates":[-71.61602600000001,42.865538],"type":"Point"}
}