{
  "type": "Feature",
  "properties": {
    "iso:country":"US",
    "sg:address":"8 Ridgewood Rd",
    "sg:city":"Plaistow",
    "sg:classifiers":[
        {
            "category":"Professional",
            "subcategory":"Management & Consulting",
            "type":"Services"
        }
    ],
    "sg:phone":"+1 603 378 0098",
    "sg:postcode":"03865",
    "sg:province":"NH",
    "sg:tags":[
        "business"
    ],
    "wof:name":"Bayside Consutants  The",
    "wof:placetype":"venue"
},
  "geometry": {"coordinates":[-71.06670699999999,42.838213],"type":"Point"}
}