{
  "type": "Feature",
  "properties": {
    "addr:full":"36 Swanzey Factory Rd Keene NH 03431",
    "addr:housenumber":"36",
    "addr:postcode":"03431",
    "addr:street":"Swanzey Factory Rd",
    "iso:country":"US",
    "sg:address":"36 Swanzey Factory Rd",
    "sg:city":"Keene",
    "sg:classifiers":[
        {
            "category":"Building & Trades",
            "subcategory":"Construction",
            "type":"Services"
        }
    ],
    "sg:phone":"+1 603 352 4510",
    "sg:postcode":"03431",
    "sg:province":"NH",
    "sg:tags":[
        "general",
        "contractor"
    ],
    "wof:name":"Arnold Fish Contracting",
    "wof:placetype":"venue"
},
  "geometry": {"coordinates":[-72.255747,42.909821],"type":"Point"}
}