{
  "type": "Feature",
  "properties": {
    "addr:full":"258 Dover Rd Chichester NH 03258",
    "addr:housenumber":"258",
    "addr:postcode":"03258",
    "addr:street":"Dover Rd",
    "iso:country":"US",
    "sg:address":"258 Dover Rd",
    "sg:city":"Chichester",
    "sg:classifiers":[
        {
            "category":"Autos & Motor Vehicles",
            "subcategory":"Auto Supplies",
            "type":"Retail Goods"
        }
    ],
    "sg:phone":"+1 603 798 5500",
    "sg:postcode":"03258",
    "sg:province":"NH",
    "sg:tags":[
        "body",
        "mfg"
    ],
    "sg:website":"www.landktruckbody.com",
    "wof:name":"L & K Equipment Inc",
    "wof:placetype":"venue"
},
  "geometry": {"coordinates":[-71.437273,43.24525],"type":"Point"}
}