{
  "type": "Feature",
  "properties": {
    "iso:country":"US",
    "sg:address":"12 Parmenter Rd",
    "sg:city":"Londonderry",
    "sg:classifiers":[
        {
            "category":"Professional",
            "subcategory":"Detective & Security Services",
            "type":"Services"
        }
    ],
    "sg:phone":"+1 603 437 9294",
    "sg:postcode":"03053",
    "sg:province":"NH",
    "sg:tags":[
        "car"
    ],
    "wof:name":"Case In Point Inc",
    "wof:placetype":"venue"
},
  "geometry": {"coordinates":[-71.393016,42.836465],"type":"Point"}
}