{
  "type": "Feature",
  "properties": {
    "addr:full":"239 Loudon Rd Concord NH 03301",
    "addr:housenumber":"239",
    "addr:postcode":"03301",
    "addr:street":"Loudon Rd",
    "iso:country":"US",
    "sg:address":"239 Loudon Rd",
    "sg:city":"Concord",
    "sg:classifiers":[
        {
            "category":"Insurance",
            "subcategory":"Insurance Agent",
            "type":"Services"
        },
        {
            "category":"Insurance",
            "subcategory":"Hazard Insurance",
            "type":"Services"
        },
        {
            "category":"Insurance",
            "subcategory":"Title Insurance",
            "type":"Services"
        },
        {
            "category":"Insurance",
            "subcategory":"Life Insurance",
            "type":"Services"
        }
    ],
    "sg:phone":"+1 603 224 7444",
    "sg:postcode":"03301",
    "sg:province":"NH",
    "sg:tags":[
        "business",
        "auto",
        "commercial",
        "homeowner",
        "motorcycle",
        "renter"
    ],
    "wof:name":"Allstate Insurance Company - George J Colt",
    "wof:placetype":"venue"
},
  "geometry": {"coordinates":[-71.49337,43.222469],"type":"Point"}
}