{
  "type": "Feature",
  "properties": {
    "iso:country":"US",
    "sg:address":"116 S Main St",
    "sg:city":"Manchester",
    "sg:classifiers":[
        {
            "category":"Autos & Motor Vehicles",
            "subcategory":"Auto Supplies",
            "type":"Retail Goods"
        }
    ],
    "sg:phone":"+1 603 644 2653",
    "sg:postcode":"03102",
    "sg:province":"NH",
    "sg:tags":[
        "used",
        "parts",
        "general"
    ],
    "wof:name":"Daves Auto Center",
    "wof:placetype":"venue"
},
  "geometry": {"coordinates":[-71.47507400000001,42.981879],"type":"Point"}
}