{
  "type": "Feature",
  "properties": {
    "addr:full":"1 Bell Rd Windham NH 03087",
    "addr:housenumber":"1",
    "addr:postcode":"03087",
    "addr:street":"Bell Rd",
    "iso:country":"US",
    "sg:address":"1 Bell Rd",
    "sg:city":"Windham",
    "sg:classifiers":[
        {
            "category":"Retail",
            "subcategory":"Animal Services",
            "type":"Services"
        }
    ],
    "sg:phone":"+1 603 894 4675",
    "sg:postcode":"03087",
    "sg:province":"NH",
    "sg:tags":[
        "pet",
        "boarding",
        "sitting"
    ],
    "wof:name":"Passtime Pet Svc",
    "wof:placetype":"venue"
},
  "geometry": {"coordinates":[-71.28160200000001,42.8066],"type":"Point"}
}