{
  "type": "Feature",
  "properties": {
    "iso:country":"US",
    "sg:address":"111 Union Sq",
    "sg:city":"Milford",
    "sg:classifiers":[
        {
            "category":"Personal",
            "subcategory":"Barber",
            "type":"Services"
        }
    ],
    "sg:phone":"+1 603 673 2222",
    "sg:postcode":"03055",
    "sg:province":"NH",
    "wof:name":"Joe's Political Parlour",
    "wof:placetype":"venue"
},
  "geometry": {"coordinates":[-71.649717,42.836069],"type":"Point"}
}