{
  "type": "Feature",
  "properties": {
    "addr:full":"67 Water St Laconia NH 03246",
    "addr:housenumber":"67",
    "addr:postcode":"03246",
    "addr:street":"Water St",
    "iso:country":"US",
    "sg:address":"67 Water St",
    "sg:city":"Laconia",
    "sg:classifiers":[
        {
            "category":"Social Services",
            "type":"Services"
        }
    ],
    "sg:phone":"+1 603 528 6086",
    "sg:postcode":"03246",
    "sg:province":"NH",
    "sg:tags":[
        "counselor",
        "marriage",
        "family"
    ],
    "wof:name":"Hammond F Brown",
    "wof:placetype":"venue"
},
  "geometry": {"coordinates":[-71.473202,43.526253],"type":"Point"}
}