{
  "type": "Feature",
  "properties": {
    "addr:full":"8 Vine St Peterborough NH 03458",
    "addr:housenumber":"8",
    "addr:postcode":"03458",
    "addr:street":"Vine St",
    "iso:country":"US",
    "sg:address":"8 Vine St",
    "sg:city":"Peterborough",
    "sg:classifiers":[
        {
            "category":"Professional",
            "subcategory":"Management & Consulting",
            "type":"Services"
        }
    ],
    "sg:phone":"+1 603 924 7983",
    "sg:postcode":"03458",
    "sg:province":"NH",
    "sg:tags":[
        "consultant",
        "safety"
    ],
    "wof:name":"System Safety Group",
    "wof:placetype":"venue"
},
  "geometry": {"coordinates":[-71.95308799999999,42.879152],"type":"Point"}
}