{
  "type": "Feature",
  "properties": {
    "iso:country":"US",
    "sg:address":"3 Lubern Ave",
    "sg:city":"Suncook",
    "sg:classifiers":[
        {
            "category":"Manufacturing",
            "subcategory":"Printing",
            "type":"Manufacturing & Wholesale Goods"
        }
    ],
    "sg:phone":"+1 603 485 7077",
    "sg:postcode":"03275",
    "sg:province":"NH",
    "sg:tags":[
        "newspaper"
    ],
    "wof:name":"New Hampshire Daily Dialogue",
    "wof:placetype":"venue"
},
  "geometry": {"coordinates":[-71.449454,43.119761],"type":"Point"}
}