{
  "type": "Feature",
  "properties": {
    "iso:country":"US",
    "sg:address":"8 Sullivan St",
    "sg:city":"Berwick",
    "sg:classifiers":[
        {
            "category":"Professional",
            "subcategory":"Business Services",
            "type":"Services"
        }
    ],
    "sg:phone":"+1 207 698 4444",
    "sg:postcode":"03878",
    "sg:province":"NH",
    "sg:tags":[
        "embroidery"
    ],
    "wof:name":"Deb & Duke Monogrammers",
    "wof:placetype":"venue"
},
  "geometry": {"coordinates":[-70.864282,43.26592],"type":"Point"}
}