{
  "type": "Feature",
  "properties": {
    "addr:full":"15 Marmon Dr Nashua NH 03060",
    "addr:housenumber":"15",
    "addr:postcode":"03060",
    "addr:street":"Marmon Dr",
    "iso:country":"US",
    "sg:address":"15 Marmon Dr",
    "sg:city":"Nashua",
    "sg:classifiers":[
        {
            "category":"Autos & Motor Vehicles",
            "subcategory":"Automobile Sales",
            "type":"Retail Goods"
        }
    ],
    "sg:phone":"+1 603 888 0200",
    "sg:postcode":"03060",
    "sg:province":"NH",
    "sg:tags":[
        "car",
        "dealer"
    ],
    "sg:website":"www.1400auto.com",
    "wof:name":"1400 Motors",
    "wof:placetype":"venue"
},
  "geometry": {"coordinates":[-71.446691,42.730195],"type":"Point"}
}