{
  "type": "Feature",
  "properties": {
    "iso:country":"US",
    "sg:address":"14 Front St",
    "sg:city":"Exeter",
    "sg:classifiers":[
        {
            "category":"Building & Trades",
            "subcategory":"Construction",
            "type":"Services"
        }
    ],
    "sg:phone":"+1 603 772 0690",
    "sg:postcode":"03833",
    "sg:province":"NH",
    "sg:tags":[
        "contractor"
    ],
    "wof:name":"Stock Framing",
    "wof:placetype":"venue"
},
  "geometry": {"coordinates":[-70.947114,42.980422],"type":"Point"}
}