{
  "type": "Feature",
  "properties": {
    "iso:country":"US",
    "sg:address":"700 Elm St",
    "sg:city":"Manchester",
    "sg:classifiers":[
        {
            "category":"Home & Garden",
            "subcategory":"Home Furnishings",
            "type":"Retail Goods"
        }
    ],
    "sg:phone":"+1 603 624 1545",
    "sg:postcode":"03101",
    "sg:province":"NH",
    "sg:tags":[
        "quilting"
    ],
    "wof:name":"Kingsmen Quilting",
    "wof:placetype":"venue"
},
  "geometry": {"coordinates":[-71.463126,42.988522],"type":"Point"}
}