{
  "type": "Feature",
  "properties": {
    "addr:full":"555 Main St Laconia NH 03246",
    "addr:housenumber":"555",
    "addr:postcode":"03246",
    "addr:street":"Main St",
    "iso:country":"US",
    "sg:address":"555 Main St",
    "sg:city":"Laconia",
    "sg:classifiers":[
        {
            "category":"Sports & Exercise",
            "subcategory":"Gym",
            "type":"Entertainment"
        }
    ],
    "sg:phone":"+1 603 528 0808",
    "sg:postcode":"03246",
    "sg:province":"NH",
    "sg:tags":[
        "club",
        "health",
        "studio",
        "gymnasium"
    ],
    "wof:name":"Curves For Women",
    "wof:placetype":"venue"
},
  "geometry": {"coordinates":[-71.469667,43.527544],"type":"Point"}
}