{
  "type": "Feature",
  "properties": {
    "addr:full":"211 Dowboro Rd Pittsfield NH 03263",
    "addr:housenumber":"211",
    "addr:postcode":"03263",
    "addr:street":"Dowboro Rd",
    "iso:country":"US",
    "sg:address":"211 Dowboro Rd",
    "sg:city":"Pittsfield",
    "sg:classifiers":[
        {
            "category":"Building & Trades",
            "subcategory":"Plumbing",
            "type":"Services"
        }
    ],
    "sg:phone":"+1 603 435 8828",
    "sg:postcode":"03263",
    "sg:province":"NH",
    "sg:tags":[
        "contractor"
    ],
    "wof:name":"B & S Trucking Cnstr & Septic",
    "wof:placetype":"venue"
},
  "geometry": {"coordinates":[-71.32864499999999,43.284268],"type":"Point"}
}