{
  "type": "Feature",
  "properties": {
    "iso:country":"US",
    "sg:address":"15 Spruce St",
    "sg:city":"Merrimack",
    "sg:classifiers":[
        {
            "category":"Building & Trades",
            "subcategory":"Construction",
            "type":"Services"
        }
    ],
    "sg:phone":"+1 603 424 9963",
    "sg:postcode":"03054",
    "sg:province":"NH",
    "sg:tags":[
        "product",
        "asphalt"
    ],
    "wof:name":"Chem Seal Asphalt Sealing",
    "wof:placetype":"venue"
},
  "geometry": {"coordinates":[-71.50685900000001,42.826163],"type":"Point"}
}