{
  "type": "Feature",
  "properties": {
    "iso:country":"US",
    "sg:address":"219 West St",
    "sg:city":"Keene",
    "sg:classifiers":[
        {
            "category":"Autos & Motor Vehicles",
            "subcategory":"Fuel & Gas Station",
            "type":"Retail Goods"
        }
    ],
    "sg:phone":"+1 603 357 0657",
    "sg:postcode":"03431",
    "sg:province":"NH",
    "sg:tags":[
        "station",
        "gasoline"
    ],
    "wof:name":"Texaco",
    "wof:placetype":"venue"
},
  "geometry": {"coordinates":[-72.286334,42.93246],"type":"Point"}
}