{
  "type": "Feature",
  "properties": {
    "iso:country":"US",
    "sg:address":"141 Fletcher Rd",
    "sg:city":"Croydon",
    "sg:classifiers":[
        {
            "category":"Building & Trades",
            "subcategory":"Construction",
            "type":"Services"
        }
    ],
    "sg:phone":"+1 603 863 8766",
    "sg:postcode":"03773",
    "sg:province":"NH",
    "sg:tags":[
        "concrete",
        "contractor"
    ],
    "wof:name":"Gardner & Son Construction",
    "wof:placetype":"venue"
},
  "geometry": {"coordinates":[-72.212283,43.391255],"type":"Point"}
}