{
  "type": "Feature",
  "properties": {
    "addr:full":"8 Higgins Rd Chichester NH 03258",
    "addr:housenumber":"8",
    "addr:postcode":"03258",
    "addr:street":"Higgins Rd",
    "iso:country":"US",
    "sg:address":"8 Higgins Rd",
    "sg:city":"Chichester",
    "sg:classifiers":[
        {
            "category":"Banks & Credit Unions",
            "subcategory":"Bank",
            "type":"Services"
        }
    ],
    "sg:phone":"+1 603 798 3885",
    "sg:postcode":"03258",
    "sg:province":"NH",
    "sg:tags":[
        "financing"
    ],
    "wof:name":"Granite Funding Resources",
    "wof:placetype":"venue"
},
  "geometry": {"coordinates":[-71.459254,43.234047],"type":"Point"}
}