{
  "type": "Feature",
  "properties": {
    "iso:country":"US",
    "sg:address":"472 Amherst St",
    "sg:city":"Nashua",
    "sg:classifiers":[
        {
            "category":"Professional",
            "subcategory":"Computer Services",
            "type":"Services"
        }
    ],
    "sg:phone":"+1 603 579 4777",
    "sg:postcode":"03063",
    "sg:province":"NH",
    "wof:name":"Analog Technology Center",
    "wof:placetype":"venue"
},
  "geometry": {"coordinates":[-71.521618,42.791915],"type":"Point"}
}