{
  "type": "Feature",
  "properties": {
    "addr:full":"26 Center View Rd Atkinson NH 03811",
    "addr:housenumber":"26",
    "addr:postcode":"03811",
    "addr:street":"Center View Rd",
    "iso:country":"US",
    "sg:address":"26 Center View Rd",
    "sg:city":"Atkinson",
    "sg:classifiers":[
        {
            "category":"Building & Trades",
            "subcategory":"Electrical",
            "type":"Services"
        }
    ],
    "sg:phone":"+1 603 362 8339",
    "sg:postcode":"03811",
    "sg:province":"NH",
    "sg:tags":[
        "electrical",
        "contractor"
    ],
    "wof:name":"Patriquin Electric Inc",
    "wof:placetype":"venue"
},
  "geometry": {"coordinates":[-71.15274100000001,42.83385],"type":"Point"}
}