{
  "type": "Feature",
  "properties": {
    "addr:full":"204 Main St Nashua NH 03060",
    "addr:housenumber":"204",
    "addr:postcode":"03060",
    "addr:street":"Main St",
    "iso:country":"US",
    "sg:address":"204 Main St",
    "sg:city":"Nashua",
    "sg:classifiers":[
        {
            "category":"Real Estate",
            "subcategory":"Real Estate Agent",
            "type":"Services"
        }
    ],
    "sg:phone":"+1 603 889 9151",
    "sg:postcode":"03060",
    "sg:province":"NH",
    "wof:name":"Damon Real Estate",
    "wof:placetype":"venue"
},
  "geometry": {"coordinates":[-71.464602,42.759502],"type":"Point"}
}