{
  "type": "Feature",
  "properties": {
    "iso:country":"US",
    "sg:address":"18 Union St",
    "sg:city":"Wolfeboro",
    "sg:classifiers":[
        {
            "category":"Professional",
            "subcategory":"Lawyer & Legal Services",
            "type":"Services"
        }
    ],
    "sg:phone":"+1 603 569 2447",
    "sg:postcode":"03894",
    "sg:province":"NH",
    "wof:name":"Martin Willard G Jr Atty",
    "wof:placetype":"venue"
},
  "geometry": {"coordinates":[-71.21060199999999,43.585899],"type":"Point"}
}