{
  "type": "Feature",
  "properties": {
    "iso:country":"US",
    "sg:address":"816 Elm St",
    "sg:city":"Manchester",
    "sg:classifiers":[
        {
            "category":"Professional",
            "subcategory":"Management & Consulting",
            "type":"Services"
        }
    ],
    "sg:phone":"+1 617 303 8711",
    "sg:postcode":"03101",
    "sg:province":"NH",
    "sg:tags":[
        "marketing"
    ],
    "wof:name":"Advantage Business Development",
    "wof:placetype":"venue"
},
  "geometry": {"coordinates":[-71.46310099999999,42.989726],"type":"Point"}
}