{
  "type": "Feature",
  "properties": {
    "iso:country":"US",
    "sg:address":"379 New Boston Rd",
    "sg:city":"Francestown",
    "sg:classifiers":[
        {
            "category":"Health Services",
            "subcategory":"Chiropractor",
            "type":"Services"
        }
    ],
    "sg:phone":"+1 603 547 2300",
    "sg:postcode":"03043",
    "sg:province":"NH",
    "wof:name":"Monadnock Family Chiropractic",
    "wof:placetype":"venue"
},
  "geometry": {"coordinates":[-71.79919700000001,42.985435],"type":"Point"}
}