{
  "type": "Feature",
  "properties": {
    "iso:country":"US",
    "sg:address":"4 Notre Dame St",
    "sg:city":"Nashua",
    "sg:classifiers":[
        {
            "category":"Professional",
            "subcategory":"Management & Consulting",
            "type":"Services"
        }
    ],
    "sg:phone":"+1 603 886 1081",
    "sg:postcode":"03060",
    "sg:province":"NH",
    "sg:tags":[
        "consultant",
        "business"
    ],
    "wof:name":"C Marquis Consultant",
    "wof:placetype":"venue"
},
  "geometry": {"coordinates":[-71.444214,42.754142],"type":"Point"}
}