{
  "type": "Feature",
  "properties": {
    "iso:country":"US",
    "sg:address":"330 Portsmouth Ave",
    "sg:city":"Greenland",
    "sg:classifiers":[
        {
            "category":"Personal",
            "type":"Services"
        }
    ],
    "sg:phone":"+1 603 433 5858",
    "sg:postcode":"03840",
    "sg:province":"NH",
    "sg:tags":[
        "therapist",
        "massage"
    ],
    "wof:name":"Jan Hummel Therapeutic Massage",
    "wof:placetype":"venue"
},
  "geometry": {"coordinates":[-70.82539199999999,43.041977],"type":"Point"}
}