{
  "type": "Feature",
  "properties": {
    "addr:full":"73 N Lowell Rd Windham NH 03087",
    "addr:housenumber":"73",
    "addr:postcode":"03087",
    "addr:street":"N Lowell Rd",
    "iso:country":"US",
    "sg:address":"73 N Lowell Rd",
    "sg:city":"Windham",
    "sg:classifiers":[
        {
            "category":"Professional",
            "subcategory":"Management & Consulting",
            "type":"Services"
        }
    ],
    "sg:phone":"+1 603 437 7500",
    "sg:postcode":"03087",
    "sg:province":"NH",
    "sg:tags":[
        "public",
        "relations"
    ],
    "wof:name":"Cleanline Promotions",
    "wof:placetype":"venue"
},
  "geometry": {"coordinates":[-71.300082,42.824152],"type":"Point"}
}