{
  "type": "Feature",
  "properties": {
    "addr:full":"30 Merrill Ave Salem NH 03079",
    "addr:housenumber":"30",
    "addr:postcode":"03079",
    "addr:street":"Merrill Ave",
    "iso:country":"US",
    "sg:address":"30 Merrill Ave",
    "sg:city":"Salem",
    "sg:classifiers":[
        {
            "category":"Professional",
            "type":"Services"
        }
    ],
    "sg:phone":"+1 603 894 1448",
    "sg:postcode":"03079",
    "sg:province":"NH",
    "wof:name":"Johnny TS",
    "wof:placetype":"venue"
},
  "geometry": {"coordinates":[-71.210514,42.790652],"type":"Point"}
}