{
  "type": "Feature",
  "properties": {
    "iso:country":"US",
    "sg:address":"86 Wood St",
    "sg:city":"Keene",
    "sg:classifiers":[
        {
            "category":"Social Services",
            "subcategory":"Child Care",
            "type":"Services"
        }
    ],
    "sg:phone":"+1 603 352 2129",
    "sg:postcode":"03431",
    "sg:province":"NH",
    "wof:name":"Keene Day Care Ctr",
    "wof:placetype":"venue"
},
  "geometry": {"coordinates":[-72.29133400000001,42.929613],"type":"Point"}
}