{
  "type": "Feature",
  "properties": {
    "iso:country":"US",
    "sg:address":"161 River Rd",
    "sg:city":"Manchester",
    "sg:classifiers":[
        {
            "category":"Real Estate",
            "subcategory":"Real Estate Agent",
            "type":"Services"
        }
    ],
    "sg:phone":"+1 603 625 5115",
    "sg:postcode":"03104",
    "sg:province":"NH",
    "sg:tags":[
        "management"
    ],
    "wof:name":"Peloquin Property Management",
    "wof:placetype":"venue"
},
  "geometry": {"coordinates":[-71.468362,43.00429],"type":"Point"}
}