{
  "type": "Feature",
  "properties": {
    "iso:country":"US",
    "sg:address":"3 Taschereau Dr",
    "sg:city":"Mont Vernon",
    "sg:classifiers":[
        {
            "category":"Retail",
            "subcategory":"Animal Services",
            "type":"Services"
        }
    ],
    "sg:phone":"+1 603 673 9508",
    "sg:postcode":"03057",
    "sg:province":"NH",
    "wof:name":"Doggie Depot",
    "wof:placetype":"venue"
},
  "geometry": {"coordinates":[-71.64980799999999,42.893671],"type":"Point"}
}