{
  "type": "Feature",
  "properties": {
    "addr:full":"4 Kingshaw Ave Plaistow NH 03865",
    "addr:housenumber":"4",
    "addr:postcode":"03865",
    "addr:street":"Kingshaw Ave",
    "iso:country":"US",
    "sg:address":"4 Kingshaw Ave",
    "sg:city":"Plaistow",
    "sg:classifiers":[
        {
            "category":"Building & Trades",
            "subcategory":"Electrical",
            "type":"Services"
        }
    ],
    "sg:phone":"+1 603 382 3993",
    "sg:postcode":"03865",
    "sg:province":"NH",
    "sg:tags":[
        "electric",
        "contractor"
    ],
    "wof:name":"Rigid Electrical Contr LLC",
    "wof:placetype":"venue"
},
  "geometry": {"coordinates":[-71.090841,42.824178],"type":"Point"}
}