{
  "type": "Feature",
  "properties": {
    "addr:full":"107 Main St West Lebanon NH 03784",
    "addr:housenumber":"107",
    "addr:postcode":"03784",
    "addr:street":"Main St",
    "iso:country":"US",
    "sg:address":"107 Main St",
    "sg:city":"West Lebanon",
    "sg:classifiers":[
        {
            "category":"Social Services",
            "type":"Services"
        }
    ],
    "sg:phone":"+1 603 523 7544",
    "sg:postcode":"03784",
    "sg:province":"NH",
    "sg:tags":[
        "counselor",
        "marriage",
        "family"
    ],
    "wof:name":"Janet Sullivan",
    "wof:placetype":"venue"
},
  "geometry": {"coordinates":[-72.31674099999999,43.634672],"type":"Point"}
}