{
  "type": "Feature",
  "properties": {
    "addr:full":"187 Day St Manchester NH 03104",
    "addr:housenumber":"187",
    "addr:postcode":"03104",
    "addr:street":"Day St",
    "iso:country":"US",
    "sg:address":"187 Day St",
    "sg:city":"Manchester",
    "sg:classifiers":[
        {
            "category":"Shopping",
            "subcategory":"Florist",
            "type":"Retail Goods"
        }
    ],
    "sg:phone":"+1 603 224 3200",
    "sg:postcode":"03104",
    "sg:province":"NH",
    "sg:tags":[
        "shop",
        "gift"
    ],
    "wof:name":"Square Rose Inc",
    "wof:placetype":"venue"
},
  "geometry": {"coordinates":[-71.44743099999999,43.017311],"type":"Point"}
}