{
  "type": "Feature",
  "properties": {
    "iso:country":"US",
    "sg:address":"131 Pine Rd",
    "sg:city":"Brentwood",
    "sg:classifiers":[
        {
            "category":"Autos & Motor Vehicles",
            "subcategory":"Automobile Sales",
            "type":"Retail Goods"
        }
    ],
    "sg:phone":"+1 603 772 2700",
    "sg:postcode":"03833",
    "sg:province":"NH",
    "sg:tags":[
        "truck"
    ],
    "wof:name":"B & E Truck Repair LLC",
    "wof:placetype":"venue"
},
  "geometry": {"coordinates":[-71.01012900000001,43.010172],"type":"Point"}
}