{
  "type": "Feature",
  "properties": {
    "iso:country":"US",
    "sg:address":"65 Old Portland Rd",
    "sg:city":"Freedom",
    "sg:classifiers":[
        {
            "category":"Shopping",
            "subcategory":"Used Merchandise",
            "type":"Retail Goods"
        }
    ],
    "sg:phone":"+1 603 539 7265",
    "sg:postcode":"03836",
    "sg:province":"NH",
    "sg:tags":[
        "book",
        "rare",
        "dealer"
    ],
    "wof:name":"Freedom Bookshop",
    "wof:placetype":"venue"
},
  "geometry": {"coordinates":[-71.029837,43.811783],"type":"Point"}
}