{
  "type": "Feature",
  "properties": {
    "iso:country":"US",
    "sg:address":"45 N Main St",
    "sg:city":"Concord",
    "sg:classifiers":[
        {
            "category":"Retail",
            "subcategory":"Auto Repair",
            "type":"Services"
        }
    ],
    "sg:phone":"+1 603 753 9383",
    "sg:postcode":"03303",
    "sg:province":"NH",
    "sg:tags":[
        "automotive",
        "used",
        "automobile"
    ],
    "wof:name":"Busters Serv Ctr",
    "wof:placetype":"venue"
},
  "geometry": {"coordinates":[-71.60308000000001,43.284425],"type":"Point"}
}