{
  "type": "Feature",
  "properties": {
    "iso:country":"US",
    "sg:address":"3 Elm St",
    "sg:city":"Peterborough",
    "sg:classifiers":[
        {
            "category":"Professional",
            "subcategory":"Research",
            "type":"Services"
        }
    ],
    "sg:phone":"+1 603 924 4405",
    "sg:postcode":"03458",
    "sg:province":"NH",
    "sg:tags":[
        "development",
        "energy",
        "solar"
    ],
    "wof:name":"Solar Access",
    "wof:placetype":"venue"
},
  "geometry": {"coordinates":[-71.95435999999999,42.878812],"type":"Point"}
}