{
  "type": "Feature",
  "properties": {
    "iso:country":"US",
    "sg:address":"110 Charlestown Rd",
    "sg:city":"Claremont",
    "sg:classifiers":[
        {
            "category":"Health Services",
            "subcategory":"Doctor",
            "type":"Services"
        }
    ],
    "sg:phone":"+1 603 542 8797",
    "sg:postcode":"03743",
    "sg:province":"NH",
    "sg:tags":[
        "dentist"
    ],
    "wof:name":"Thomas Hillebrand DDS",
    "wof:placetype":"venue"
},
  "geometry": {"coordinates":[-72.35842100000001,43.354708],"type":"Point"}
}