{
  "type": "Feature",
  "properties": {
    "iso:country":"US",
    "sg:address":"611 New London Rd",
    "sg:city":"West Springfield",
    "sg:classifiers":[
        {
            "category":"Manufacturing",
            "subcategory":"Pottery",
            "type":"Manufacturing & Wholesale Goods"
        }
    ],
    "sg:phone":"+1 603 763 8756",
    "sg:postcode":"03284",
    "sg:province":"NH",
    "sg:tags":[
        "product",
        "mfg"
    ],
    "wof:name":"Wellhouse Farm Pottery",
    "wof:placetype":"venue"
},
  "geometry": {"coordinates":[-72.042779,43.47314],"type":"Point"}
}