{
  "type": "Feature",
  "properties": {
    "addr:full":"36 Hemlock St Hampton NH 03842",
    "addr:housenumber":"36",
    "addr:postcode":"03842",
    "addr:street":"Hemlock St",
    "iso:country":"US",
    "sg:address":"36 Hemlock St",
    "sg:city":"Hampton",
    "sg:classifiers":[
        {
            "category":"Shopping",
            "subcategory":"Hobbies, Toys, & Games",
            "type":"Retail Goods"
        }
    ],
    "sg:phone":"+1 603 926 6119",
    "sg:postcode":"03842",
    "sg:province":"NH",
    "wof:name":"Cozy Nook Creations",
    "wof:placetype":"venue"
},
  "geometry": {"coordinates":[-70.804157,42.931068],"type":"Point"}
}