{
  "type": "Feature",
  "properties": {
    "iso:country":"US",
    "sg:address":"30 Spinnaker Way",
    "sg:city":"Portsmouth",
    "sg:classifiers":[
        {
            "category":"Recreation",
            "type":"Entertainment"
        }
    ],
    "sg:phone":"+1 603 766 1483",
    "sg:postcode":"03801",
    "sg:province":"NH",
    "wof:name":"Spinnker Pt Adult Rcration Ctr",
    "wof:placetype":"venue"
},
  "geometry": {"coordinates":[-70.776533,43.087549],"type":"Point"}
}