{
  "type": "Feature",
  "properties": {
    "iso:country":"US",
    "sg:address":"1 1st St",
    "sg:city":"Salem",
    "sg:classifiers":[
        {
            "category":"Shopping",
            "subcategory":"Bicycles & Sporting Goods",
            "type":"Retail Goods"
        }
    ],
    "sg:phone":"+1 603 890 3212",
    "sg:postcode":"03079",
    "sg:province":"NH",
    "sg:website":"www.mtn-bikes.com",
    "wof:name":"Cycles Etcetera Of Salem Inc",
    "wof:placetype":"venue"
},
  "geometry": {"coordinates":[-71.203389,42.824959],"type":"Point"}
}