{
  "type": "Feature",
  "properties": {
    "addr:full":"6 B St Derry NH 03038",
    "addr:housenumber":"6",
    "addr:postcode":"03038",
    "addr:street":"B St",
    "iso:country":"US",
    "sg:address":"6 B St",
    "sg:city":"Derry",
    "sg:classifiers":[
        {
            "category":"Home & Garden",
            "subcategory":"Garden Supply",
            "type":"Retail Goods"
        }
    ],
    "sg:phone":"+1 603 437 0407",
    "sg:postcode":"03038",
    "sg:province":"NH",
    "sg:tags":[
        "engine"
    ],
    "wof:name":"Eastern Equipment Inc",
    "wof:placetype":"venue"
},
  "geometry": {"coordinates":[-71.336738,42.892934],"type":"Point"}
}