{
  "type": "Feature",
  "properties": {
    "iso:country":"US",
    "sg:address":"37 Oak Hill Rd",
    "sg:city":"Brookline",
    "sg:classifiers":[
        {
            "category":"Manufacturing",
            "subcategory":"Tools & Machinery",
            "type":"Manufacturing & Wholesale Goods"
        }
    ],
    "sg:phone":"+1 603 672 5210",
    "sg:postcode":"03033",
    "sg:province":"NH",
    "sg:tags":[
        "industrial",
        "mfg"
    ],
    "wof:name":"Prb Technical Machining",
    "wof:placetype":"venue"
},
  "geometry": {"coordinates":[-71.64677399999999,42.714014],"type":"Point"}
}