{
  "type": "Feature",
  "properties": {
    "iso:country":"US",
    "sg:address":"167 Main St",
    "sg:city":"Kingston",
    "sg:classifiers":[
        {
            "category":"Food & Beverages",
            "subcategory":"Groceries & Convenience Stores",
            "type":"Retail Goods"
        }
    ],
    "sg:phone":"+1 603 642 4321",
    "sg:postcode":"03848",
    "sg:province":"NH",
    "sg:tags":[
        "grocer"
    ],
    "wof:name":"Kingston Village Market",
    "wof:placetype":"venue"
},
  "geometry": {"coordinates":[-71.053575,42.936164],"type":"Point"}
}