{
  "type": "Feature",
  "properties": {
    "iso:country":"US",
    "sg:address":"1 Severence Dr",
    "sg:city":"Londonderry",
    "sg:classifiers":[
        {
            "category":"Building & Trades",
            "subcategory":"Construction",
            "type":"Services"
        }
    ],
    "sg:phone":"+1 603 432 6187",
    "sg:postcode":"03053",
    "sg:province":"NH",
    "sg:tags":[
        "general",
        "contractor"
    ],
    "sg:website":"www.nutfieldbuilding.com",
    "wof:name":"Nutfield Building & Investment",
    "wof:placetype":"venue"
},
  "geometry": {"coordinates":[-71.397926,42.836377],"type":"Point"}
}