{
  "type": "Feature",
  "properties": {
    "addr:full":"5 Brookfield Rd Hudson NH 03051",
    "addr:housenumber":"5",
    "addr:postcode":"03051",
    "addr:street":"Brookfield Rd",
    "iso:country":"US",
    "sg:address":"5 Brookfield Rd",
    "sg:city":"Hudson",
    "sg:classifiers":[
        {
            "category":"Bus Charters",
            "type":"Transportation"
        }
    ],
    "sg:phone":"+1 603 897 1244",
    "sg:postcode":"03051",
    "sg:province":"NH",
    "sg:tags":[
        "rental"
    ],
    "wof:name":"Lessard Bus Co Inc",
    "wof:placetype":"venue"
},
  "geometry": {"coordinates":[-71.41067700000001,42.715256],"type":"Point"}
}