{
  "type": "Feature",
  "properties": {
    "iso:country":"US",
    "sg:address":"26 East Rd",
    "sg:city":"Atkinson",
    "sg:classifiers":[
        {
            "category":"Building & Trades",
            "subcategory":"Landscaping Services",
            "type":"Services"
        }
    ],
    "sg:phone":"+1 603 362 8845",
    "sg:postcode":"03811",
    "sg:province":"NH",
    "sg:tags":[
        "landscape",
        "contractor"
    ],
    "wof:name":"Earth Dynamics",
    "wof:placetype":"venue"
},
  "geometry": {"coordinates":[-71.124263,42.841732],"type":"Point"}
}