{
  "type": "Feature",
  "properties": {
    "iso:country":"US",
    "sg:address":"26 Norwich Rd",
    "sg:city":"Nashua",
    "sg:classifiers":[
        {
            "category":"Building & Trades",
            "subcategory":"Construction",
            "type":"Services"
        }
    ],
    "sg:phone":"+1 603 897 1915",
    "sg:postcode":"03062",
    "sg:province":"NH",
    "sg:tags":[
        "carpenter"
    ],
    "wof:name":"Select Carpentry",
    "wof:placetype":"venue"
},
  "geometry": {"coordinates":[-71.485029,42.720687],"type":"Point"}
}