{
  "type": "Feature",
  "properties": {
    "iso:country":"US",
    "sg:address":"55 Tenny Mountain Rd",
    "sg:city":"Plymouth",
    "sg:classifiers":[
        {
            "category":"Social Services",
            "subcategory":"Child Care",
            "type":"Services"
        }
    ],
    "sg:phone":"+1 603 536 4092",
    "sg:postcode":"03264",
    "sg:province":"NH",
    "sg:tags":[
        "day"
    ],
    "wof:name":"Toddle Town",
    "wof:placetype":"venue"
},
  "geometry": {"coordinates":[-71.753417,43.744066],"type":"Point"}
}