{
  "type": "Feature",
  "properties": {
    "iso:country":"US",
    "sg:address":"385 S Broadway",
    "sg:city":"Salem",
    "sg:classifiers":[
        {
            "category":"Personal",
            "subcategory":"Beauty Salon",
            "type":"Services"
        }
    ],
    "sg:phone":"+1 603 898 3880",
    "sg:postcode":"03079",
    "sg:province":"NH",
    "sg:tags":[
        "hair"
    ],
    "wof:name":"Haircuts II",
    "wof:placetype":"venue"
},
  "geometry": {"coordinates":[-71.205949,42.751841],"type":"Point"}
}