{
  "type": "Feature",
  "properties": {
    "iso:country":"US",
    "sg:address":"13 Pine St",
    "sg:city":"Jaffrey",
    "sg:classifiers":[
        {
            "category":"Social Services",
            "subcategory":"Child Care",
            "type":"Services"
        }
    ],
    "sg:phone":"+1 603 532 6774",
    "sg:postcode":"03452",
    "sg:province":"NH",
    "sg:tags":[
        "day"
    ],
    "wof:name":"Debbies Day Care",
    "wof:placetype":"venue"
},
  "geometry": {"coordinates":[-72.01555399999999,42.81444],"type":"Point"}
}