{
  "type": "Feature",
  "properties": {
    "addr:full":"15 Easton Hill Rd Stratham NH 03885",
    "addr:housenumber":"15",
    "addr:postcode":"03885",
    "addr:street":"Easton Hill Rd",
    "iso:country":"US",
    "sg:address":"15 Easton Hill Rd",
    "sg:city":"Stratham",
    "sg:classifiers":[
        {
            "category":"Shopping",
            "subcategory":"Jewelry",
            "type":"Retail Goods"
        }
    ],
    "sg:phone":"+1 603 772 8203",
    "sg:postcode":"03885",
    "sg:province":"NH",
    "wof:name":"N Jules Gems",
    "wof:placetype":"venue"
},
  "geometry": {"coordinates":[-70.878922,43.024376],"type":"Point"}
}