{
  "type": "Feature",
  "properties": {
    "iso:country":"US",
    "sg:address":"22 Old Coach Rd",
    "sg:city":"Nashua",
    "sg:classifiers":[
        {
            "category":"Building & Trades",
            "subcategory":"Construction",
            "type":"Services"
        }
    ],
    "sg:phone":"+1 603 595 5498",
    "sg:postcode":"03062",
    "sg:province":"NH",
    "sg:tags":[
        "contractor"
    ],
    "wof:name":"Yankee Drywall Inc",
    "wof:placetype":"venue"
},
  "geometry": {"coordinates":[-71.504108,42.736769],"type":"Point"}
}