{
  "type": "Feature",
  "properties": {
    "addr:full":"23 Fieldstone Cir Hampton NH 03842",
    "addr:housenumber":"23",
    "addr:postcode":"03842",
    "addr:street":"Fieldstone Cir",
    "iso:country":"US",
    "sg:address":"23 Fieldstone Cir",
    "sg:city":"Hampton",
    "sg:classifiers":[
        {
            "category":"Government",
            "subcategory":"Court House",
            "type":"Public Place"
        }
    ],
    "sg:phone":"+1 603 929 7673",
    "sg:postcode":"03842",
    "sg:province":"NH",
    "sg:tags":[
        "justice",
        "peace"
    ],
    "wof:name":"Suzanne Thompson",
    "wof:placetype":"venue"
},
  "geometry": {"coordinates":[-70.84433,42.958582],"type":"Point"}
}