{
  "type": "Feature",
  "properties": {
    "iso:country":"US",
    "sg:address":"3 Veterans Memorial Pkwy # 3",
    "sg:city":"Salem",
    "sg:classifiers":[
        {
            "category":"Restaurant",
            "type":"Food & Drink"
        }
    ],
    "sg:phone":"+1 603 893 9877",
    "sg:postcode":"03079",
    "sg:province":"NH",
    "sg:tags":[
        "style",
        "family"
    ],
    "wof:name":"Bickford's Grille 46",
    "wof:placetype":"venue"
},
  "geometry": {"coordinates":[-71.21983299999999,42.769299],"type":"Point"}
}