{
  "type": "Feature",
  "properties": {
    "iso:country":"US",
    "sg:address":"464 US Hwy 202",
    "sg:city":"Rindge",
    "sg:phone":"+1 603 899 6660",
    "sg:postcode":"03461",
    "sg:province":"NH",
    "sg:tags":[
        "gas"
    ],
    "wof:name":"Fogg Grill Gas Inc",
    "wof:placetype":"venue"
},
  "geometry": {"coordinates":[-72.03344199999999,42.779245],"type":"Point"}
}