{
  "type": "Feature",
  "properties": {
    "iso:country":"US",
    "sg:address":"40 Four Rod Rd",
    "sg:city":"Rochester",
    "sg:classifiers":[
        {
            "category":"Building & Trades",
            "subcategory":"Plumbing",
            "type":"Services"
        }
    ],
    "sg:phone":"+1 603 332 8940",
    "sg:postcode":"03867",
    "sg:province":"NH",
    "sg:tags":[
        "contractor"
    ],
    "wof:name":"Soley Thomas Plumbing & Htg",
    "wof:placetype":"venue"
},
  "geometry": {"coordinates":[-71.03371199999999,43.320894],"type":"Point"}
}