{
  "type": "Feature",
  "properties": {
    "addr:full":"43 Baboosic Lake Rd Merrimack NH 03054",
    "addr:housenumber":"43",
    "addr:postcode":"03054",
    "addr:street":"Baboosic Lake Rd",
    "iso:country":"US",
    "sg:address":"43 Baboosic Lake Rd",
    "sg:city":"Merrimack",
    "sg:classifiers":[
        {
            "category":"Organizations",
            "subcategory":"Community Association",
            "type":"Services"
        }
    ],
    "sg:phone":"+1 603 429 0343",
    "sg:postcode":"03054",
    "sg:province":"NH",
    "sg:tags":[
        "military"
    ],
    "wof:name":"American Legion",
    "wof:placetype":"venue"
},
  "geometry": {"coordinates":[-71.505207,42.868921],"type":"Point"}
}