{
  "type": "Feature",
  "properties": {
    "iso:country":"US",
    "sg:address":"7 Wall St Ste 101",
    "sg:city":"Windham",
    "sg:classifiers":[
        {
            "category":"Shopping",
            "subcategory":"Computers & Home Electronics",
            "type":"Retail Goods"
        }
    ],
    "sg:phone":"+1 603 552 1200",
    "sg:postcode":"03087",
    "sg:province":"NH",
    "sg:tags":[
        "hardware",
        "supply"
    ],
    "wof:name":"Emc Corp",
    "wof:placetype":"venue"
},
  "geometry": {"coordinates":[-71.288101,42.81131],"type":"Point"}
}