{
  "type": "Feature",
  "properties": {
    "iso:country":"US",
    "sg:address":"554 Maple St",
    "sg:city":"Hopkinton",
    "sg:classifiers":[
        {
            "category":"Wholesale",
            "subcategory":"Machinery & Supplies",
            "type":"Manufacturing & Wholesale Goods"
        }
    ],
    "sg:phone":"+1 603 746 4611",
    "sg:postcode":"03229",
    "sg:province":"NH",
    "sg:tags":[
        "contractor"
    ],
    "wof:name":"Milton Cat",
    "wof:placetype":"venue"
},
  "geometry": {"coordinates":[-71.708071,43.212809],"type":"Point"}
}