{
  "type": "Feature",
  "properties": {
    "iso:country":"US",
    "sg:address":"54 Pleasant St",
    "sg:city":"Claremont",
    "sg:classifiers":[
        {
            "category":"Shopping",
            "subcategory":"Used Merchandise",
            "type":"Retail Goods"
        },
        {
            "category":"Restaurant",
            "type":"Food & Drink"
        }
    ],
    "sg:phone":"+1 603 542 1218",
    "sg:postcode":"03743",
    "sg:province":"NH",
    "sg:tags":[
        "shop",
        "consignment",
        "eating"
    ],
    "wof:name":"Angelina's Closet",
    "wof:placetype":"venue"
},
  "geometry": {"coordinates":[-72.33867600000001,43.371335],"type":"Point"}
}