{
  "type": "Feature",
  "properties": {
    "addr:full":"9 Severance St Claremont NH 03743",
    "addr:housenumber":"9",
    "addr:postcode":"03743",
    "addr:street":"Severance St",
    "iso:country":"US",
    "sg:address":"9 Severance St",
    "sg:city":"Claremont",
    "sg:classifiers":[
        {
            "category":"Personal",
            "subcategory":"Beauty Salon",
            "type":"Services"
        }
    ],
    "sg:phone":"+1 603 543 3469",
    "sg:postcode":"03743",
    "sg:province":"NH",
    "sg:tags":[
        "shop"
    ],
    "wof:name":"Carols Hairstyling & Tan Salon",
    "wof:placetype":"venue"
},
  "geometry": {"coordinates":[-72.340096,43.365273],"type":"Point"}
}