{
  "type": "Feature",
  "properties": {
    "addr:full":"7 Village Ln Rochester NH 03867",
    "addr:housenumber":"7",
    "addr:postcode":"03867",
    "addr:street":"Village Ln",
    "iso:country":"US",
    "sg:address":"7 Village Ln",
    "sg:city":"Rochester",
    "sg:classifiers":[
        {
            "category":"Building & Trades",
            "subcategory":"Construction",
            "type":"Services"
        }
    ],
    "sg:phone":"+1 603 332 6661",
    "sg:postcode":"03867",
    "sg:province":"NH",
    "sg:tags":[
        "house"
    ],
    "wof:name":"Kinnisons A To Z Services",
    "wof:placetype":"venue"
},
  "geometry": {"coordinates":[-70.965288,43.317763],"type":"Point"}
}