{
  "type": "Feature",
  "properties": {
    "iso:country":"US",
    "sg:address":"194 N Main St",
    "sg:city":"Concord",
    "sg:classifiers":[
        {
            "category":"Professional",
            "subcategory":"Business Services",
            "type":"Services"
        }
    ],
    "sg:phone":"+1 603 224 3919",
    "sg:postcode":"03301",
    "sg:province":"NH",
    "sg:website":"www.customscoop.com",
    "wof:name":"Custom Scoop",
    "wof:placetype":"venue"
},
  "geometry": {"coordinates":[-71.53748299999999,43.209894],"type":"Point"}
}