{
  "type": "Feature",
  "properties": {
    "iso:country":"US",
    "sg:address":"48 Lebanon St",
    "sg:city":"Hanover",
    "sg:classifiers":[
        {
            "category":"Recreation",
            "type":"Entertainment"
        }
    ],
    "sg:phone":"+1 603 643 5315",
    "sg:postcode":"03755",
    "sg:province":"NH",
    "sg:tags":[
        "parks"
    ],
    "wof:name":"Hanover Recreation Dept",
    "wof:placetype":"venue"
},
  "geometry": {"coordinates":[-72.280804,43.697427],"type":"Point"}
}