{
  "type": "Feature",
  "properties": {
    "iso:country":"US",
    "sg:address":"200 Main St",
    "sg:city":"Lancaster",
    "sg:classifiers":[
        {
            "category":"Home & Garden",
            "subcategory":"Building Materials",
            "type":"Retail Goods"
        }
    ],
    "sg:phone":"+1 603 788 4445",
    "sg:postcode":"03584",
    "sg:province":"NH",
    "sg:tags":[
        "hardware",
        "sporting"
    ],
    "wof:name":"Lancaster Hardware",
    "wof:placetype":"venue"
},
  "geometry": {"coordinates":[-71.574946,44.495796],"type":"Point"}
}