{
  "type": "Feature",
  "properties": {
    "iso:country":"US",
    "sg:address":"176 Mountain Rd",
    "sg:city":"Pittsfield",
    "sg:classifiers":[
        {
            "category":"Building & Trades",
            "subcategory":"Landscaping Services",
            "type":"Services"
        }
    ],
    "sg:phone":"+1 603 435 7895",
    "sg:postcode":"03263",
    "sg:province":"NH",
    "sg:tags":[
        "landscape"
    ],
    "wof:name":"Landview Landscaping",
    "wof:placetype":"venue"
},
  "geometry": {"coordinates":[-71.31094,43.276241],"type":"Point"}
}