{
  "type": "Feature",
  "properties": {
    "addr:full":"5 Boutwell Rd Mont Vernon NH 03057",
    "addr:housenumber":"5",
    "addr:postcode":"03057",
    "addr:street":"Boutwell Rd",
    "iso:country":"US",
    "sg:address":"5 Boutwell Rd",
    "sg:city":"Mont Vernon",
    "sg:classifiers":[
        {
            "category":"Building & Trades",
            "subcategory":"Landscaping Services",
            "type":"Services"
        }
    ],
    "sg:phone":"+1 603 673 9996",
    "sg:postcode":"03057",
    "sg:province":"NH",
    "wof:name":"Tree Removal & Forestry",
    "wof:placetype":"venue"
},
  "geometry": {"coordinates":[-71.669507,42.893737],"type":"Point"}
}