{
  "type": "Feature",
  "properties": {
    "addr:full":"8 Union St Whitefield NH 03598",
    "addr:housenumber":"8",
    "addr:postcode":"03598",
    "addr:street":"Union St",
    "iso:country":"US",
    "sg:address":"8 Union St",
    "sg:city":"Whitefield",
    "sg:classifiers":[
        {
            "category":"Bakery",
            "type":"Food & Drink"
        },
        {
            "category":"Coffee & Tea",
            "type":"Food & Drink"
        },
        {
            "category":"Bagels",
            "type":"Food & Drink"
        },
        {
            "category":"Donuts",
            "type":"Food & Drink"
        }
    ],
    "sg:menulink":"http://www.allmenus.com/nh/whitefield/149275-dunkin-donuts/menu/",
    "sg:phone":"+1 603 837 8826",
    "sg:postcode":"03598",
    "sg:province":"NH",
    "sg:tags":[
        "wrap",
        "american",
        "sandwich",
        "pastry"
    ],
    "wof:name":"Dunkin' Donuts",
    "wof:placetype":"venue"
},
  "geometry": {"coordinates":[-71.611492,44.373503],"type":"Point"}
}