{
  "type": "Feature",
  "properties": {
    "iso:country":"US",
    "sg:address":"7 Sumner Dr",
    "sg:city":"Dover",
    "sg:classifiers":[
        {
            "category":"Manufacturing",
            "subcategory":"Food",
            "type":"Manufacturing & Wholesale Goods"
        }
    ],
    "sg:phone":"+1 603 740 4200",
    "sg:postcode":"03820",
    "sg:province":"NH",
    "sg:tags":[
        "tea",
        "coffee",
        "product"
    ],
    "sg:website":"www.piscataquacoffee.com",
    "wof:name":"Piscataqua Coffee Roasting Co",
    "wof:placetype":"venue"
},
  "geometry": {"coordinates":[-70.89928999999999,43.180659],"type":"Point"}
}