{
  "type": "Feature",
  "properties": {
    "iso:country":"US",
    "sg:address":"249 County Rd",
    "sg:city":"New London",
    "sg:classifiers":[
        {
            "category":"Health Services",
            "subcategory":"Doctor",
            "type":"Services"
        }
    ],
    "sg:phone":"+1 603 526 7575",
    "sg:postcode":"03257",
    "sg:province":"NH",
    "sg:tags":[
        "physician",
        "surgeon"
    ],
    "wof:name":"Womens Health Care",
    "wof:placetype":"venue"
},
  "geometry": {"coordinates":[-72.007256,43.414178],"type":"Point"}
}