{
  "type": "Feature",
  "properties": {
    "addr:full":"572 US Hwy 3 Lincoln NH 03262",
    "addr:housenumber":"572",
    "addr:postcode":"03262",
    "addr:street":"Us Hwy 3",
    "iso:country":"US",
    "sg:address":"572 US Hwy 3",
    "sg:city":"Lincoln",
    "sg:classifiers":[
        {
            "category":"Travel",
            "subcategory":"Hotels & Motels",
            "type":"Entertainment"
        }
    ],
    "sg:phone":"+1 603 745 2229",
    "sg:postcode":"03262",
    "sg:province":"NH",
    "sg:website":"www.franconianotch.com",
    "wof:name":"Franconia Notch Motel",
    "wof:placetype":"venue"
},
  "geometry": {"coordinates":[-71.686087,43.992436],"type":"Point"}
}