{
  "type": "Feature",
  "properties": {
    "addr:full":"43 Westminster St Walpole NH 03608",
    "addr:housenumber":"43",
    "addr:postcode":"03608",
    "addr:street":"Westminster St",
    "iso:country":"US",
    "sg:address":"43 Westminster St",
    "sg:city":"Walpole",
    "sg:classifiers":[
        {
            "category":"Farming",
            "subcategory":"Nursery",
            "type":"Manufacturing & Wholesale Goods"
        }
    ],
    "sg:phone":"+1 603 756 3395",
    "sg:postcode":"03608",
    "sg:province":"NH",
    "sg:tags":[
        "greenhouse"
    ],
    "wof:name":"Allen Brothers Inc",
    "wof:placetype":"venue"
},
  "geometry": {"coordinates":[-72.428117,43.079614],"type":"Point"}
}