{
  "type": "Feature",
  "properties": {
    "iso:country":"US",
    "sg:address":"292 Daniel Webster Hwy",
    "sg:city":"Meredith",
    "sg:classifiers":[
        {
            "category":"Shopping",
            "subcategory":"Florist",
            "type":"Retail Goods"
        }
    ],
    "sg:phone":"+1 603 279 1474",
    "sg:postcode":"03253",
    "sg:province":"NH",
    "wof:name":"Dockside Florist Garden Ctr",
    "wof:placetype":"venue"
},
  "geometry": {"coordinates":[-71.49787999999999,43.655165],"type":"Point"}
}