{
  "type": "Feature",
  "properties": {
    "iso:country":"US",
    "sg:address":"187 Wakefield St",
    "sg:city":"Rochester",
    "sg:classifiers":[
        {
            "category":"Shopping",
            "subcategory":"Gifts & Souvenirs",
            "type":"Retail Goods"
        }
    ],
    "sg:phone":"+1 603 335 4447",
    "sg:postcode":"03867",
    "sg:province":"NH",
    "sg:tags":[
        "party",
        "supply"
    ],
    "wof:name":"Confetti Express",
    "wof:placetype":"venue"
},
  "geometry": {"coordinates":[-70.976035,43.318283],"type":"Point"}
}