{
  "type": "Feature",
  "properties": {
    "iso:country":"US",
    "sg:address":"5 Tsienneto Rd",
    "sg:city":"Derry",
    "sg:classifiers":[
        {
            "category":"Wholesale",
            "subcategory":"Motor Vehicles",
            "type":"Manufacturing & Wholesale Goods"
        }
    ],
    "sg:phone":"+1 603 434 7234",
    "sg:postcode":"03038",
    "sg:province":"NH",
    "wof:name":"District Distributor Corp",
    "wof:placetype":"venue"
},
  "geometry": {"coordinates":[-71.32234,42.898583],"type":"Point"}
}