{
  "type": "Feature",
  "properties": {
    "iso:country":"US",
    "sg:address":"519 N State St",
    "sg:city":"Concord",
    "sg:classifiers":[
        {
            "category":"Professional",
            "subcategory":"Business Services",
            "type":"Services"
        }
    ],
    "sg:phone":"+1 603 224 4982",
    "sg:postcode":"03301",
    "sg:province":"NH",
    "wof:name":"A M Designs",
    "wof:placetype":"venue"
},
  "geometry": {"coordinates":[-71.571617,43.246972],"type":"Point"}
}