{
  "type": "Feature",
  "properties": {
    "iso:country":"US",
    "sg:address":"13 Manchester Rd",
    "sg:city":"Derry",
    "sg:classifiers":[
        {
            "category":"Restaurant",
            "type":"Food & Drink"
        }
    ],
    "sg:phone":"+1 603 425 6665",
    "sg:postcode":"03038",
    "sg:province":"NH",
    "wof:name":"Pinkerton Tavern",
    "wof:placetype":"venue"
},
  "geometry": {"coordinates":[-71.33077,42.89656],"type":"Point"}
}