{
  "type": "Feature",
  "properties": {
    "iso:country":"US",
    "sg:address":"27 Depot St",
    "sg:city":"Lancaster",
    "sg:classifiers":[
        {
            "category":"Food & Beverages",
            "subcategory":"Groceries & Convenience Stores",
            "type":"Retail Goods"
        }
    ],
    "sg:phone":"+1 603 788 2062",
    "sg:postcode":"03584",
    "sg:province":"NH",
    "wof:name":"North End Market",
    "wof:placetype":"venue"
},
  "geometry": {"coordinates":[-71.57094600000001,44.494721],"type":"Point"}
}