{
  "type": "Feature",
  "properties": {
    "iso:country":"US",
    "sg:address":"19 Morrison Ln",
    "sg:city":"Sandown",
    "sg:classifiers":[
        {
            "category":"Shopping",
            "subcategory":"Pets & Pet Supplies",
            "type":"Retail Goods"
        },
        {
            "category":"Retail",
            "subcategory":"Animal Services",
            "type":"Services"
        }
    ],
    "sg:phone":"+1 603 887 5000",
    "sg:postcode":"03873",
    "sg:province":"NH",
    "sg:tags":[
        "grooming",
        "dog",
        "cat"
    ],
    "wof:name":"The Grooming Clinic",
    "wof:placetype":"venue"
},
  "geometry": {"coordinates":[-71.149805,42.909494],"type":"Point"}
}