{
  "type": "Feature",
  "properties": {
    "iso:country":"US",
    "sg:address":"20 Kit St",
    "sg:city":"Keene",
    "sg:classifiers":[
        {
            "category":"Health Services",
            "subcategory":"Health Practitioner",
            "type":"Services"
        }
    ],
    "sg:phone":"+1 603 924 7462",
    "sg:postcode":"03431",
    "sg:province":"NH",
    "sg:tags":[
        "psychologist"
    ],
    "wof:name":"Bergman Crew Price & Assoc",
    "wof:placetype":"venue"
},
  "geometry": {"coordinates":[-72.29321,42.920923],"type":"Point"}
}