{
  "type": "Feature",
  "properties": {
    "iso:country":"US",
    "sg:address":"34 Mammoth Rd",
    "sg:city":"Pelham",
    "sg:classifiers":[
        {
            "category":"Building & Trades",
            "subcategory":"Construction",
            "type":"Services"
        }
    ],
    "sg:phone":"+1 603 635 2295",
    "sg:postcode":"03076",
    "sg:province":"NH",
    "wof:name":"F & F Asphalt Paving",
    "wof:placetype":"venue"
},
  "geometry": {"coordinates":[-71.352238,42.703344],"type":"Point"}
}