{
  "type": "Feature",
  "properties": {
    "addr:full":"20 Fairview Ave Henniker NH 03242",
    "addr:housenumber":"20",
    "addr:postcode":"03242",
    "addr:street":"Fairview Ave",
    "iso:country":"US",
    "sg:address":"20 Fairview Ave",
    "sg:city":"Henniker",
    "sg:classifiers":[
        {
            "category":"Manufacturing",
            "subcategory":"Lumber",
            "type":"Manufacturing & Wholesale Goods"
        }
    ],
    "sg:phone":"+1 603 428 7705",
    "sg:postcode":"03242",
    "sg:province":"NH",
    "sg:tags":[
        "forester"
    ],
    "wof:name":"Thomas J Ryan",
    "wof:placetype":"venue"
},
  "geometry": {"coordinates":[-71.83074999999999,43.181281],"type":"Point"}
}