{
  "type": "Feature",
  "properties": {
    "addr:full":"320 Sheep Davis Rd Concord NH 03301",
    "addr:housenumber":"320",
    "addr:postcode":"03301",
    "addr:street":"Sheep Davis Rd",
    "iso:country":"US",
    "sg:address":"320 Sheep Davis Rd",
    "sg:city":"Concord",
    "sg:classifiers":[
        {
            "category":"Wholesale",
            "subcategory":"Construction Materials",
            "type":"Manufacturing & Wholesale Goods"
        }
    ],
    "sg:phone":"+1 603 224 2146",
    "sg:postcode":"03301",
    "sg:province":"NH",
    "sg:tags":[
        "sand",
        "gravel"
    ],
    "wof:name":"Concord Sand & Gravel",
    "wof:placetype":"venue"
},
  "geometry": {"coordinates":[-71.472813,43.231606],"type":"Point"}
}