{
  "type": "Feature",
  "properties": {
    "iso:country":"US",
    "sg:address":"56 Ledge Rd",
    "sg:city":"Hudson",
    "sg:classifiers":[
        {
            "category":"Banks & Credit Unions",
            "subcategory":"Investment Brokerage",
            "type":"Services"
        }
    ],
    "sg:phone":"+1 603 886 4839",
    "sg:postcode":"03051",
    "sg:province":"NH",
    "sg:tags":[
        "trade",
        "barter",
        "exchange"
    ],
    "wof:name":"ITEX Barter Exchange",
    "wof:placetype":"venue"
},
  "geometry": {"coordinates":[-71.437352,42.776034],"type":"Point"}
}