{
  "type": "Feature",
  "properties": {
    "addr:full":"157 Loudon Rd Concord NH 03301",
    "addr:housenumber":"157",
    "addr:postcode":"03301",
    "addr:street":"Loudon Rd",
    "iso:country":"US",
    "sg:address":"157 Loudon Rd",
    "sg:city":"Concord",
    "sg:classifiers":[
        {
            "category":"Retail",
            "subcategory":"Auto Repair",
            "type":"Services"
        }
    ],
    "sg:phone":"+1 603 225 2244",
    "sg:postcode":"03301",
    "sg:province":"NH",
    "sg:tags":[
        "repairing",
        "automobile"
    ],
    "wof:name":"American Brake Svc Of Concord",
    "wof:placetype":"venue"
},
  "geometry": {"coordinates":[-71.506444,43.216448],"type":"Point"}
}