{
  "type": "Feature",
  "properties": {
    "iso:country":"US",
    "sg:address":"5 Arbor Dr",
    "sg:city":"Dover",
    "sg:classifiers":[
        {
            "category":"Building & Trades",
            "subcategory":"Construction",
            "type":"Services"
        }
    ],
    "sg:phone":"+1 603 516 3150",
    "sg:postcode":"03820",
    "sg:province":"NH",
    "sg:tags":[
        "resurfacing",
        "laying",
        "refinishing",
        "floor"
    ],
    "wof:name":"Kitchen Tune-Up",
    "wof:placetype":"venue"
},
  "geometry": {"coordinates":[-70.87030799999999,43.160709],"type":"Point"}
}