{
  "type": "Feature",
  "properties": {
    "iso:country":"US",
    "sg:address":"65 Central St",
    "sg:city":"Woodsville",
    "sg:classifiers":[
        {
            "category":"Shopping",
            "subcategory":"Crafts & Fabrics",
            "type":"Retail Goods"
        }
    ],
    "sg:phone":"+1 603 747 3054",
    "sg:postcode":"03785",
    "sg:province":"NH",
    "sg:tags":[
        "shop",
        "sewing"
    ],
    "wof:name":"Seams Sew Easy Fabric Shoppe",
    "wof:placetype":"venue"
},
  "geometry": {"coordinates":[-72.03736499999999,44.152526],"type":"Point"}
}