{
  "type": "Feature",
  "properties": {
    "iso:country":"US",
    "sg:address":"10 Hillcrest Ave",
    "sg:city":"Plaistow",
    "sg:classifiers":[
        {
            "category":"Building & Trades",
            "subcategory":"Construction",
            "type":"Services"
        }
    ],
    "sg:phone":"+1 603 382 1377",
    "sg:postcode":"03865",
    "sg:province":"NH",
    "sg:tags":[
        "house"
    ],
    "wof:name":"Shur Lock Homes",
    "wof:placetype":"venue"
},
  "geometry": {"coordinates":[-71.06649299999999,42.809607],"type":"Point"}
}