{
  "type": "Feature",
  "properties": {
    "iso:country":"US",
    "sg:address":"2800 Lafayette Rd",
    "sg:city":"Portsmouth",
    "sg:classifiers":[
        {
            "category":"Recreation",
            "type":"Entertainment"
        }
    ],
    "sg:phone":"+1 603 433 4304",
    "sg:postcode":"03801",
    "sg:province":"NH",
    "sg:tags":[
        "martial",
        "arts",
        "instruction"
    ],
    "wof:name":"East Coast Sport Karate Ctr",
    "wof:placetype":"venue"
},
  "geometry": {"coordinates":[-70.786912,43.031271],"type":"Point"}
}