{
  "type": "Feature",
  "properties": {
    "addr:full":"8 Algonquin Trl Hanover NH 03750",
    "addr:housenumber":"8",
    "addr:postcode":"03750",
    "addr:street":"Algonquin Trl",
    "iso:country":"US",
    "sg:address":"8 Algonquin Trl",
    "sg:city":"Hanover",
    "sg:classifiers":[
        {
            "category":"Recreation",
            "type":"Entertainment"
        }
    ],
    "sg:phone":"+1 603 643 2226",
    "sg:postcode":"03750",
    "sg:province":"NH",
    "sg:tags":[
        "instruction",
        "skiing"
    ],
    "wof:name":"Ford Sayer Ski Council",
    "wof:placetype":"venue"
},
  "geometry": {"coordinates":[-72.19608100000001,43.732528],"type":"Point"}
}