{
  "type": "Feature",
  "properties": {
    "iso:country":"US",
    "sg:address":"124 Congress St",
    "sg:city":"Portsmouth",
    "sg:classifiers":[
        {
            "category":"Education",
            "subcategory":"School",
            "type":"Public Place"
        }
    ],
    "sg:phone":"+1 603 436 4464",
    "sg:postcode":"03801",
    "sg:province":"NH",
    "wof:name":"Rose School Of Karate",
    "wof:placetype":"venue"
},
  "geometry": {"coordinates":[-70.76048900000001,43.075803],"type":"Point"}
}