{
  "type": "Feature",
  "properties": {
    "iso:country":"US",
    "sg:address":"14 Village St",
    "sg:city":"Concord",
    "sg:classifiers":[
        {
            "category":"Real Estate",
            "subcategory":"Real Estate Services",
            "type":"Services"
        }
    ],
    "sg:phone":"+1 603 224 8100",
    "sg:postcode":"03303",
    "sg:province":"NH",
    "sg:tags":[
        "home",
        "inspector"
    ],
    "wof:name":"Fedolfi's Pest-Free Management",
    "wof:placetype":"venue"
},
  "geometry": {"coordinates":[-71.58669999999999,43.2668],"type":"Point"}
}