{
  "type": "Feature",
  "properties": {
    "iso:country":"US",
    "sg:address":"139 Buttrick Rd",
    "sg:city":"Hampstead",
    "sg:classifiers":[
        {
            "category":"Real Estate",
            "subcategory":"Real Estate Agent",
            "type":"Services"
        }
    ],
    "sg:phone":"+1 603 329 5162",
    "sg:postcode":"03841",
    "sg:province":"NH",
    "wof:name":"Bar Harbor Realty Trust",
    "wof:placetype":"venue"
},
  "geometry": {"coordinates":[-71.171959,42.894678],"type":"Point"}
}