{
  "type": "Feature",
  "properties": {
    "iso:country":"US",
    "sg:address":"461 Mount Support Rd",
    "sg:city":"Lebanon",
    "sg:classifiers":[
        {
            "category":"Social Services",
            "type":"Services"
        }
    ],
    "sg:phone":"+1 603 643 2298",
    "sg:postcode":"03766",
    "sg:province":"NH",
    "sg:tags":[
        "organization",
        "welfare"
    ],
    "sg:website":"www.davids-house.org",
    "wof:name":"David's House",
    "wof:placetype":"venue"
},
  "geometry": {"coordinates":[-72.26680399999999,43.677778],"type":"Point"}
}