{
  "type": "Feature",
  "properties": {
    "iso:country":"US",
    "sg:address":"140 Brackett Rd",
    "sg:city":"Rye",
    "sg:classifiers":[
        {
            "category":"Marine",
            "type":"Transportation"
        }
    ],
    "sg:phone":"+1 603 433 7579",
    "sg:postcode":"03870",
    "sg:province":"NH",
    "sg:tags":[
        "surveyor"
    ],
    "wof:name":"John Mc Donough",
    "wof:placetype":"venue"
},
  "geometry": {"coordinates":[-70.734786,43.033654],"type":"Point"}
}