{
  "type": "Feature",
  "properties": {
    "addr:full":"15 Manchester Dr Lebanon NH 03766",
    "addr:housenumber":"15",
    "addr:postcode":"03766",
    "addr:street":"Manchester Dr",
    "iso:country":"US",
    "sg:address":"15 Manchester Dr",
    "sg:city":"Lebanon",
    "sg:classifiers":[
        {
            "category":"Building & Trades",
            "subcategory":"Construction",
            "type":"Services"
        }
    ],
    "sg:phone":"+1 603 448 9796",
    "sg:postcode":"03766",
    "sg:province":"NH",
    "sg:tags":[
        "foundation"
    ],
    "wof:name":"Central Nh Pressure Seal",
    "wof:placetype":"venue"
},
  "geometry": {"coordinates":[-72.18491299999999,43.647534],"type":"Point"}
}