{
  "type": "Feature",
  "properties": {
    "iso:country":"US",
    "sg:address":"1976 E Conway Rd",
    "sg:city":"North Conway",
    "sg:classifiers":[
        {
            "category":"Shopping",
            "subcategory":"Clothing, Apparel, & Fashions",
            "type":"Retail Goods"
        }
    ],
    "sg:phone":"+1 603 356 5483",
    "sg:postcode":"03813",
    "sg:province":"NH",
    "wof:name":"Aeropostale Inc",
    "wof:placetype":"venue"
},
  "geometry": {"coordinates":[-71.059563,44.01127],"type":"Point"}
}