{
  "type": "Feature",
  "properties": {
    "iso:country":"US",
    "sg:address":"14 Weaver Pl",
    "sg:city":"Weare",
    "sg:classifiers":[
        {
            "category":"Professional",
            "subcategory":"Management & Consulting",
            "type":"Services"
        }
    ],
    "sg:phone":"+1 603 529 1720",
    "sg:postcode":"03281",
    "sg:province":"NH",
    "sg:tags":[
        "business"
    ],
    "wof:name":"Arthur N Scarneo Consultng Ser",
    "wof:placetype":"venue"
},
  "geometry": {"coordinates":[-71.690196,43.135306],"type":"Point"}
}