{
  "type": "Feature",
  "properties": {
    "iso:country":"US",
    "sg:address":"45 Birch St",
    "sg:city":"Derry",
    "sg:classifiers":[
        {
            "category":"Retail",
            "subcategory":"Repair Shop",
            "type":"Services"
        }
    ],
    "sg:phone":"+1 603 434 3992",
    "sg:postcode":"03038",
    "sg:province":"NH",
    "wof:name":"Country Violin",
    "wof:placetype":"venue"
},
  "geometry": {"coordinates":[-71.321001,42.878344],"type":"Point"}
}