{
  "type": "Feature",
  "properties": {
    "iso:country":"US",
    "sg:address":"18 N Main St",
    "sg:city":"Concord",
    "sg:classifiers":[
        {
            "category":"Banks & Credit Unions",
            "subcategory":"Investment Brokerage",
            "type":"Services"
        }
    ],
    "sg:phone":"+1 603 227 9922",
    "sg:postcode":"03301",
    "sg:province":"NH",
    "sg:tags":[
        "advisory",
        "financial"
    ],
    "wof:name":"Alpine Financial Svc",
    "wof:placetype":"venue"
},
  "geometry": {"coordinates":[-71.535923,43.205213],"type":"Point"}
}