{
  "type": "Feature",
  "properties": {
    "addr:full":"185 Woodbound Rd Rindge NH 03461",
    "addr:housenumber":"185",
    "addr:postcode":"03461",
    "addr:street":"Woodbound Rd",
    "iso:country":"US",
    "sg:address":"185 Woodbound Rd",
    "sg:city":"Rindge",
    "sg:classifiers":[
        {
            "category":"Building & Trades",
            "subcategory":"Construction",
            "type":"Services"
        }
    ],
    "sg:phone":"+1 603 899 6920",
    "sg:postcode":"03461",
    "sg:province":"NH",
    "sg:tags":[
        "paving",
        "contractor"
    ],
    "wof:name":"Monadnock Seal Coating",
    "wof:placetype":"venue"
},
  "geometry": {"coordinates":[-72.022522,42.777948],"type":"Point"}
}