{
  "type": "Feature",
  "properties": {
    "addr:full":"121 Glenwood Ave Manchester NH 03102",
    "addr:housenumber":"121",
    "addr:postcode":"03102",
    "addr:street":"Glenwood Ave",
    "iso:country":"US",
    "sg:address":"121 Glenwood Ave",
    "sg:city":"Manchester",
    "sg:classifiers":[
        {
            "category":"Building & Trades",
            "subcategory":"Construction",
            "type":"Services"
        }
    ],
    "sg:phone":"+1 603 622 2236",
    "sg:postcode":"03102",
    "sg:province":"NH",
    "sg:tags":[
        "home",
        "improvement"
    ],
    "wof:name":"John Crain Jr",
    "wof:placetype":"venue"
},
  "geometry": {"coordinates":[-71.48928100000001,42.966334],"type":"Point"}
}