{
  "type": "Feature",
  "properties": {
    "addr:full":"219 W Main St Hillsboro NH 03244",
    "addr:housenumber":"219",
    "addr:postcode":"03244",
    "addr:street":"W Main St",
    "iso:country":"US",
    "sg:address":"219 W Main St",
    "sg:city":"Hillsboro",
    "sg:classifiers":[
        {
            "category":"Insurance",
            "subcategory":"Insurance Agent",
            "type":"Services"
        }
    ],
    "sg:phone":"+1 603 464 5882",
    "sg:postcode":"03244",
    "sg:province":"NH",
    "wof:name":"Amadio Insurance",
    "wof:placetype":"venue"
},
  "geometry": {"coordinates":[-71.912612,43.111433],"type":"Point"}
}