{
  "type": "Feature",
  "properties": {
    "iso:country":"US",
    "sg:address":"144 Wentworth Rd",
    "sg:city":"Walpole",
    "sg:classifiers":[
        {
            "category":"Autos & Motor Vehicles",
            "subcategory":"Automobile Sales",
            "type":"Retail Goods"
        }
    ],
    "sg:phone":"+1 603 756 9200",
    "sg:postcode":"03608",
    "sg:province":"NH",
    "wof:name":"Smart Recreational Parts",
    "wof:placetype":"venue"
},
  "geometry": {"coordinates":[-72.426785,43.073138],"type":"Point"}
}