{
  "type": "Feature",
  "properties": {
    "iso:country":"US",
    "sg:address":"15 Whittier Dr",
    "sg:city":"Seabrook",
    "sg:classifiers":[
        {
            "category":"Real Estate",
            "subcategory":"Real Estate Agent",
            "type":"Services"
        }
    ],
    "sg:phone":"+1 603 929 4279",
    "sg:postcode":"03874",
    "sg:province":"NH",
    "wof:name":"K L Properties",
    "wof:placetype":"venue"
},
  "geometry": {"coordinates":[-70.879617,42.888359],"type":"Point"}
}