{
  "type": "Feature",
  "properties": {
    "iso:country":"US",
    "sg:address":"500 State Rte 3a",
    "sg:city":"Bow",
    "sg:classifiers":[
        {
            "category":"Autos & Motor Vehicles",
            "subcategory":"Fuel & Gas Station",
            "type":"Retail Goods"
        }
    ],
    "sg:phone":"+1 603 228 6175",
    "sg:postcode":"03304",
    "sg:province":"NH",
    "sg:tags":[
        "convenience",
        "station",
        "gasoline",
        "store"
    ],
    "wof:name":"Irving Oil",
    "wof:placetype":"venue"
},
  "geometry": {"coordinates":[-71.529742,43.176216],"type":"Point"}
}