{
  "type": "Feature",
  "properties": {
    "addr:full":"27 Escumbuit Rd Derry NH 03038",
    "addr:housenumber":"27",
    "addr:postcode":"03038",
    "addr:street":"Escumbuit Rd",
    "iso:country":"US",
    "sg:address":"27 Escumbuit Rd",
    "sg:city":"Derry",
    "sg:classifiers":[
        {
            "category":"Building & Trades",
            "subcategory":"Plumbing",
            "type":"Services"
        }
    ],
    "sg:phone":"+1 603 893 8332",
    "sg:postcode":"03038",
    "sg:province":"NH",
    "sg:tags":[
        "contractor"
    ],
    "wof:name":"Faiella Plumbing & Heating Co",
    "wof:placetype":"venue"
},
  "geometry": {"coordinates":[-71.21238700000001,42.857375],"type":"Point"}
}