{
  "type": "Feature",
  "properties": {
    "addr:full":"72 S Pond Rd Colebrook NH 03582",
    "addr:housenumber":"72",
    "addr:postcode":"03582",
    "addr:street":"S Pond Rd",
    "iso:country":"US",
    "sg:address":"72 S Pond Rd",
    "sg:city":"Colebrook",
    "sg:classifiers":[
        {
            "category":"Shopping",
            "subcategory":"Florist",
            "type":"Retail Goods"
        }
    ],
    "sg:phone":"+1 603 237 4924",
    "sg:postcode":"03582",
    "sg:province":"NH",
    "wof:name":"Flowers By Helen",
    "wof:placetype":"venue"
},
  "geometry": {"coordinates":[-71.35552300000001,44.616333],"type":"Point"}
}