{
  "type": "Feature",
  "properties": {
    "addr:full":"197 Buck St Pembroke NH 03275",
    "addr:housenumber":"197",
    "addr:postcode":"03275",
    "addr:street":"Buck St",
    "iso:country":"US",
    "sg:address":"197 Buck St",
    "sg:city":"Pembroke",
    "sg:classifiers":[
        {
            "category":"Shopping",
            "type":"Retail Goods"
        }
    ],
    "sg:phone":"+1 603 485 4520",
    "sg:postcode":"03275",
    "sg:province":"NH",
    "sg:tags":[
        "coin",
        "dealer",
        "supply"
    ],
    "wof:name":"R & D Rarities",
    "wof:placetype":"venue"
},
  "geometry": {"coordinates":[-71.43718,43.137839],"type":"Point"}
}