{
  "type": "Feature",
  "properties": {
    "iso:country":"US",
    "sg:address":"80 Sharon Rd",
    "sg:city":"Peterborough",
    "sg:classifiers":[
        {
            "category":"Wholesale",
            "subcategory":"Construction Materials",
            "type":"Manufacturing & Wholesale Goods"
        }
    ],
    "sg:phone":"+1 603 924 6102",
    "sg:postcode":"03458",
    "sg:province":"NH",
    "sg:tags":[
        "sand",
        "gravel"
    ],
    "wof:name":"Mathewson Co Gravel",
    "wof:placetype":"venue"
},
  "geometry": {"coordinates":[-71.963446,42.847537],"type":"Point"}
}