{
  "type": "Feature",
  "properties": {
    "iso:country":"US",
    "sg:address":"3 Eagle Sq",
    "sg:city":"Concord",
    "sg:classifiers":[
        {
            "category":"Home & Garden",
            "subcategory":"Furniture",
            "type":"Retail Goods"
        }
    ],
    "sg:phone":"+1 603 225 7975",
    "sg:postcode":"03301",
    "sg:province":"NH",
    "wof:name":"Pompanoosuc Mills Corp",
    "wof:placetype":"venue"
},
  "geometry": {"coordinates":[-71.535687,43.206726],"type":"Point"}
}