{
  "type": "Feature",
  "properties": {
    "iso:country":"US",
    "sg:address":"117 Silver St",
    "sg:city":"Dover",
    "sg:classifiers":[
        {
            "category":"Professional",
            "subcategory":"Business Services",
            "type":"Services"
        }
    ],
    "sg:phone":"+1 603 740 0915",
    "sg:postcode":"03820",
    "sg:province":"NH",
    "wof:name":"Doverhaus LLC",
    "wof:placetype":"venue"
},
  "geometry": {"coordinates":[-70.88423299999999,43.19028],"type":"Point"}
}