{
  "type": "Feature",
  "properties": {
    "iso:country":"US",
    "sg:address":"319 State Rte 107",
    "sg:city":"Seabrook",
    "sg:classifiers":[
        {
            "category":"Local Transit",
            "type":"Transportation"
        }
    ],
    "sg:phone":"+1 603 474 7938",
    "sg:postcode":"03874",
    "sg:province":"NH",
    "sg:tags":[
        "bus",
        "line"
    ],
    "wof:name":"Yankee Greyhound",
    "wof:placetype":"venue"
},
  "geometry": {"coordinates":[-70.899996,42.897986],"type":"Point"}
}