{
  "type": "Feature",
  "properties": {
    "iso:country":"US",
    "sg:address":"21 W Auburn St",
    "sg:city":"Manchester",
    "sg:classifiers":[
        {
            "category":"Wholesale",
            "subcategory":"Durable Goods & Equipment",
            "type":"Manufacturing & Wholesale Goods"
        }
    ],
    "sg:phone":"+1 603 582 5648",
    "sg:postcode":"03101",
    "sg:province":"NH",
    "wof:name":"Protection Plus",
    "wof:placetype":"venue"
},
  "geometry": {"coordinates":[-71.46395800000001,42.985093],"type":"Point"}
}