{
  "type": "Feature",
  "properties": {
    "iso:country":"US",
    "sg:address":"163 Summer St",
    "sg:city":"Newport",
    "sg:classifiers":[
        {
            "category":"Health Services",
            "subcategory":"Hospital",
            "type":"Services"
        }
    ],
    "sg:phone":"+1 603 863 1785",
    "sg:postcode":"03773",
    "sg:province":"NH",
    "sg:tags":[
        "mental"
    ],
    "wof:name":"Arborview",
    "wof:placetype":"venue"
},
  "geometry": {"coordinates":[-72.168466,43.375176],"type":"Point"}
}