{
  "type": "Feature",
  "properties": {
    "iso:country":"US",
    "sg:address":"64 Hooksett Tpke",
    "sg:city":"Concord",
    "sg:classifiers":[
        {
            "category":"Professional",
            "subcategory":"Accounting & Tax Preparation",
            "type":"Services"
        }
    ],
    "sg:phone":"+1 603 224 6133",
    "sg:postcode":"03301",
    "sg:province":"NH",
    "sg:tags":[
        "accountant"
    ],
    "wof:name":"Brent W Washburn & Co",
    "wof:placetype":"venue"
},
  "geometry": {"coordinates":[-71.59514799999999,43.156087],"type":"Point"}
}