{
  "type": "Feature",
  "properties": {
    "iso:country":"US",
    "sg:address":"638 Somerville St",
    "sg:city":"Manchester",
    "sg:classifiers":[
        {
            "category":"Building & Trades",
            "subcategory":"Cleaning & Sanitation",
            "type":"Services"
        }
    ],
    "sg:phone":"+1 603 623 2478",
    "sg:postcode":"03103",
    "sg:province":"NH",
    "sg:tags":[
        "maintenance"
    ],
    "wof:name":"Harvey Cleaning",
    "wof:placetype":"venue"
},
  "geometry": {"coordinates":[-71.447714,42.976561],"type":"Point"}
}