{
  "type": "Feature",
  "properties": {
    "iso:country":"US",
    "sg:address":"48 Cabot Rd",
    "sg:city":"Harrisville",
    "sg:classifiers":[
        {
            "category":"Professional",
            "subcategory":"Engineering",
            "type":"Services"
        }
    ],
    "sg:phone":"+1 603 827 3672",
    "sg:postcode":"03450",
    "sg:province":"NH",
    "sg:tags":[
        "engineer"
    ],
    "wof:name":"Downing Engineering Pro Assn",
    "wof:placetype":"venue"
},
  "geometry": {"coordinates":[-72.106965,42.966948],"type":"Point"}
}