{
  "type": "Feature",
  "properties": {
    "addr:full":"98 Charlestown Rd Claremont NH 03743",
    "addr:housenumber":"98",
    "addr:postcode":"03743",
    "addr:street":"Charlestown Rd",
    "iso:country":"US",
    "sg:address":"98 Charlestown Rd",
    "sg:city":"Claremont",
    "sg:classifiers":[
        {
            "category":"Banks & Credit Unions",
            "subcategory":"Bank",
            "type":"Services"
        }
    ],
    "sg:phone":"+1 603 542 7781",
    "sg:postcode":"03743",
    "sg:province":"NH",
    "wof:name":"N H COMMUNITY Federal Cu",
    "wof:placetype":"venue"
},
  "geometry": {"coordinates":[-72.357795,43.355742],"type":"Point"}
}