{
  "type": "Feature",
  "properties": {
    "iso:country":"US",
    "sg:address":"4 Wilder St",
    "sg:city":"Nashua",
    "sg:classifiers":[
        {
            "category":"Organizations",
            "subcategory":"Religious Organization",
            "type":"Services"
        }
    ],
    "sg:phone":"+1 603 886 4247",
    "sg:postcode":"03060",
    "sg:province":"NH",
    "sg:tags":[
        "science",
        "christian",
        "practitioner"
    ],
    "wof:name":"Rita Smith",
    "wof:placetype":"venue"
},
  "geometry": {"coordinates":[-71.471476,42.754296],"type":"Point"}
}