{
  "type": "Feature",
  "properties": {
    "iso:country":"US",
    "sg:address":"735 E Industrial Park Dr",
    "sg:city":"Manchester",
    "sg:classifiers":[
        {
            "category":"Manufacturing",
            "subcategory":"Retail Goods",
            "type":"Manufacturing & Wholesale Goods"
        }
    ],
    "sg:phone":"+1 603 644 1118",
    "sg:postcode":"03109",
    "sg:province":"NH",
    "sg:tags":[
        "assembly",
        "fabricating"
    ],
    "wof:name":"QMS",
    "wof:placetype":"venue"
},
  "geometry": {"coordinates":[-71.408143,42.982449],"type":"Point"}
}