{
  "type": "Feature",
  "properties": {
    "iso:country":"US",
    "sg:address":"154 High St",
    "sg:city":"Somersworth",
    "sg:classifiers":[
        {
            "category":"Home & Garden",
            "subcategory":"Furniture",
            "type":"Retail Goods"
        }
    ],
    "sg:phone":"+1 603 692 0606",
    "sg:postcode":"03878",
    "sg:province":"ME",
    "wof:name":"Amesbury Furniture Outlet-Nh",
    "wof:placetype":"venue"
},
  "geometry": {"coordinates":[-70.866653,43.25961],"type":"Point"}
}