{
  "type": "Feature",
  "properties": {
    "addr:full":"74 Marblehead Rd Windham NH 03087",
    "addr:housenumber":"74",
    "addr:postcode":"03087",
    "addr:street":"Marblehead Rd",
    "iso:country":"US",
    "sg:address":"74 Marblehead Rd",
    "sg:city":"Windham",
    "sg:classifiers":[
        {
            "category":"Banks & Credit Unions",
            "subcategory":"Bank",
            "type":"Services"
        }
    ],
    "sg:phone":"+1 603 894 4422",
    "sg:postcode":"03087",
    "sg:province":"NH",
    "sg:tags":[
        "loan",
        "real estate"
    ],
    "wof:name":"Amerisource Mortgage",
    "wof:placetype":"venue"
},
  "geometry": {"coordinates":[-71.297528,42.762536],"type":"Point"}
}