{
  "type": "Feature",
  "properties": {
    "iso:country":"US",
    "sg:address":"19 Hazel Dr",
    "sg:city":"Hampstead",
    "sg:classifiers":[
        {
            "category":"Retail",
            "subcategory":"Auto Repair",
            "type":"Services"
        }
    ],
    "sg:phone":"+1 603 329 5810",
    "sg:postcode":"03841",
    "sg:province":"NH",
    "sg:tags":[
        "repairing",
        "automobile"
    ],
    "wof:name":"Revolution Tuning Svc",
    "wof:placetype":"venue"
},
  "geometry": {"coordinates":[-71.15186799999999,42.875331],"type":"Point"}
}