{
  "type": "Feature",
  "properties": {
    "iso:country":"US",
    "sg:address":"3 S Broadway",
    "sg:city":"Salem",
    "sg:classifiers":[
        {
            "category":"Professional",
            "type":"Services"
        }
    ],
    "sg:phone":"+1 603 890 0001",
    "sg:postcode":"03079",
    "sg:province":"NH",
    "sg:tags":[
        "establishment"
    ],
    "wof:name":"Telebanker",
    "wof:placetype":"venue"
},
  "geometry": {"coordinates":[-71.227017,42.778597],"type":"Point"}
}