{
  "type": "Feature",
  "properties": {
    "iso:country":"US",
    "sg:address":"70 Benjamin Wentworth Dr",
    "sg:city":"Chocorua",
    "sg:classifiers":[
        {
            "category":"Building & Trades",
            "subcategory":"Plumbing",
            "type":"Services"
        }
    ],
    "sg:phone":"+1 603 323 8830",
    "sg:postcode":"03817",
    "sg:province":"NH",
    "sg:tags":[
        "mechanical",
        "contractor"
    ],
    "wof:name":"Process Mechanical Inc",
    "wof:placetype":"venue"
},
  "geometry": {"coordinates":[-71.207571,43.881217],"type":"Point"}
}