{
  "type": "Feature",
  "properties": {
    "addr:full":"1395 Battle St Concord NH 03303",
    "addr:housenumber":"1395",
    "addr:postcode":"03303",
    "addr:street":"Battle St",
    "iso:country":"US",
    "sg:address":"1395 Battle St",
    "sg:city":"Concord",
    "sg:classifiers":[
        {
            "category":"Farming",
            "subcategory":"Dairy Farm",
            "type":"Manufacturing & Wholesale Goods"
        }
    ],
    "sg:phone":"+1 603 648 2520",
    "sg:postcode":"03303",
    "sg:province":"NH",
    "sg:tags":[
        "hog",
        "egg",
        "or",
        "feedlot"
    ],
    "wof:name":"Kathy Drown",
    "wof:placetype":"venue"
},
  "geometry": {"coordinates":[-71.722127,43.33607],"type":"Point"}
}