{
  "type": "Feature",
  "properties": {
    "addr:full":"39 Shady Ln Nashua NH 03062",
    "addr:housenumber":"39",
    "addr:postcode":"03062",
    "addr:street":"Shady Ln",
    "iso:country":"US",
    "sg:address":"39 Shady Ln",
    "sg:city":"Nashua",
    "sg:classifiers":[
        {
            "category":"Education",
            "subcategory":"School",
            "type":"Public Place"
        }
    ],
    "sg:phone":"+1 603 594 4409",
    "sg:postcode":"03062",
    "sg:province":"NH",
    "wof:name":"New Searles Elememntary School",
    "wof:placetype":"venue"
},
  "geometry": {"coordinates":[-71.478753,42.726215],"type":"Point"}
}