{
  "type": "Feature",
  "properties": {
    "iso:country":"US",
    "sg:address":"175 Main St",
    "sg:city":"Colebrook",
    "sg:classifiers":[
        {
            "category":"Shopping",
            "subcategory":"Department Store",
            "type":"Retail Goods"
        }
    ],
    "sg:phone":"+1 603 237 4200",
    "sg:postcode":"03576",
    "sg:province":"NH",
    "wof:name":"Hills Department Store",
    "wof:placetype":"venue"
},
  "geometry": {"coordinates":[-71.497299,44.892841],"type":"Point"}
}