{
  "type": "Feature",
  "properties": {
    "addr:full":"369 Hackett Hill Rd Hooksett NH 03106",
    "addr:housenumber":"369",
    "addr:postcode":"03106",
    "addr:street":"Hackett Hill Rd",
    "iso:country":"US",
    "sg:address":"369 Hackett Hill Rd",
    "sg:city":"Hooksett",
    "sg:classifiers":[
        {
            "category":"Building & Trades",
            "subcategory":"Construction",
            "type":"Services"
        }
    ],
    "sg:phone":"+1 603 647 8026",
    "sg:postcode":"03106",
    "sg:province":"NH",
    "sg:tags":[
        "contractor"
    ],
    "wof:name":"Ideal Masonry",
    "wof:placetype":"venue"
},
  "geometry": {"coordinates":[-71.485733,43.047117],"type":"Point"}
}