{
  "type": "Feature",
  "properties": {
    "addr:full":"361 Commerce Way Suncook NH 03275",
    "addr:housenumber":"361",
    "addr:postcode":"03275",
    "addr:street":"Commerce Way",
    "iso:country":"US",
    "sg:address":"361 Commerce Way",
    "sg:city":"Suncook",
    "sg:classifiers":[
        {
            "category":"Government",
            "subcategory":"Office",
            "type":"Public Place"
        }
    ],
    "sg:phone":"+1 603 226 7800",
    "sg:postcode":"03275",
    "sg:province":"NH",
    "sg:tags":[
        "water",
        "district"
    ],
    "wof:name":"Cost Center 2450-Nh/Vt",
    "wof:placetype":"venue"
},
  "geometry": {"coordinates":[-71.48032000000001,43.188145],"type":"Point"}
}