{
  "type": "Feature",
  "properties": {
    "iso:country":"US",
    "sg:address":"28 W River Rd",
    "sg:city":"Hooksett",
    "sg:classifiers":[
        {
            "category":"Autos & Motor Vehicles",
            "subcategory":"Fuel & Gas Station",
            "type":"Retail Goods"
        }
    ],
    "sg:phone":"+1 603 665 9316",
    "sg:postcode":"03106",
    "sg:province":"NH",
    "sg:tags":[
        "station",
        "gasoline"
    ],
    "wof:name":"Queen City Mobil 4",
    "wof:placetype":"venue"
},
  "geometry": {"coordinates":[-71.47140899999999,43.039983],"type":"Point"}
}