{
  "type": "Feature",
  "properties": {
    "iso:country":"US",
    "sg:address":"491 Main St",
    "sg:city":"Berlin",
    "sg:classifiers":[
        {
            "category":"Shopping",
            "subcategory":"Clothing, Apparel, & Fashions",
            "type":"Retail Goods"
        }
    ],
    "sg:phone":"+1 603 752 7219",
    "sg:postcode":"03570",
    "sg:province":"NH",
    "wof:name":"Poore Simon's #60",
    "wof:placetype":"venue"
},
  "geometry": {"coordinates":[-71.17615000000001,44.47295],"type":"Point"}
}