{
  "type": "Feature",
  "properties": {
    "iso:country":"US",
    "sg:address":"7 James Farm Rd",
    "sg:city":"Durham",
    "sg:classifiers":[
        {
            "category":"Professional",
            "subcategory":"Computer Services",
            "type":"Services"
        }
    ],
    "sg:phone":"+1 603 292 5016",
    "sg:postcode":"03861",
    "sg:province":"NH",
    "sg:tags":[
        "programing",
        "custom"
    ],
    "wof:name":"Metatak",
    "wof:placetype":"venue"
},
  "geometry": {"coordinates":[-70.992028,43.132117],"type":"Point"}
}