{
  "type": "Feature",
  "properties": {
    "iso:country":"US",
    "sg:address":"106 Hastings Ave",
    "sg:city":"Keene",
    "sg:classifiers":[
        {
            "category":"Government",
            "subcategory":"Office",
            "type":"Public Place"
        }
    ],
    "sg:phone":"+1 603 352 7021",
    "sg:postcode":"03431",
    "sg:province":"NH",
    "sg:tags":[
        "federal",
        "security"
    ],
    "wof:name":"US Army National Guard Recruit",
    "wof:placetype":"venue"
},
  "geometry": {"coordinates":[-72.324495,42.945836],"type":"Point"}
}