{
  "type": "Feature",
  "properties": {
    "iso:country":"US",
    "sg:address":"16 Putnam St",
    "sg:city":"Claremont",
    "sg:classifiers":[
        {
            "category":"Personal",
            "type":"Services"
        }
    ],
    "sg:phone":"+1 603 543 1265",
    "sg:postcode":"03743",
    "sg:province":"NH",
    "wof:name":"Lisa Strnger Massage Therapist",
    "wof:placetype":"venue"
},
  "geometry": {"coordinates":[-72.33604800000001,43.370271],"type":"Point"}
}