{
  "type": "Feature",
  "properties": {
    "iso:country":"US",
    "sg:address":"115 Gosling Rd",
    "sg:city":"Newington",
    "sg:classifiers":[
        {
            "category":"Government",
            "subcategory":"Office",
            "type":"Public Place"
        }
    ],
    "sg:phone":"+1 603 431 4111",
    "sg:postcode":"03801",
    "sg:province":"NH",
    "sg:tags":[
        "village"
    ],
    "wof:name":"Newington Waste Water Plant",
    "wof:placetype":"venue"
},
  "geometry": {"coordinates":[-70.796871,43.093084],"type":"Point"}
}