{
  "type": "Feature",
  "properties": {
    "iso:country":"US",
    "sg:address":"117 Brookdale Rd",
    "sg:city":"Salem",
    "sg:classifiers":[
        {
            "category":"Banks & Credit Unions",
            "subcategory":"Bank",
            "type":"Services"
        }
    ],
    "sg:phone":"+1 603 458 1217",
    "sg:postcode":"03079",
    "sg:province":"NH",
    "sg:tags":[
        "broker",
        "mortgage"
    ],
    "wof:name":"M & M Mortgage Consulting Inc",
    "wof:placetype":"venue"
},
  "geometry": {"coordinates":[-71.26348400000001,42.781243],"type":"Point"}
}