{
  "type": "Feature",
  "properties": {
    "iso:country":"US",
    "sg:address":"2164 Main St",
    "sg:city":"Bethlehem",
    "sg:classifiers":[
        {
            "category":"Food & Beverages",
            "subcategory":"Groceries & Convenience Stores",
            "type":"Retail Goods"
        }
    ],
    "sg:phone":"+1 603 869 3945",
    "sg:postcode":"03574",
    "sg:province":"NH",
    "wof:name":"Bethlehem Irving Mainway",
    "wof:placetype":"venue"
},
  "geometry": {"coordinates":[-71.673552,44.281335],"type":"Point"}
}