{
  "type": "Feature",
  "properties": {
    "iso:country":"US",
    "sg:address":"139 Oak Hill Ave",
    "sg:city":"Manchester",
    "sg:classifiers":[
        {
            "category":"Organizations",
            "subcategory":"Religious Organization",
            "type":"Services"
        }
    ],
    "sg:phone":"+1 603 669 7090",
    "sg:postcode":"03104",
    "sg:province":"NH",
    "wof:name":"Diane Trinity",
    "wof:placetype":"venue"
},
  "geometry": {"coordinates":[-71.43673099999999,43.000199],"type":"Point"}
}