{
  "type": "Feature",
  "properties": {
    "iso:country":"US",
    "sg:address":"5 Westside Dr",
    "sg:city":"Exeter",
    "sg:classifiers":[
        {
            "category":"Retail",
            "subcategory":"Repair Shop",
            "type":"Services"
        }
    ],
    "sg:phone":"+1 603 772 2552",
    "sg:postcode":"03833",
    "sg:province":"NH",
    "sg:tags":[
        "small",
        "engine"
    ],
    "wof:name":"Steeles Mowers Inc",
    "wof:placetype":"venue"
},
  "geometry": {"coordinates":[-70.96790300000001,42.976617],"type":"Point"}
}