{
  "type": "Feature",
  "properties": {
    "addr:full":"291 S Broadway Salem NH 03079",
    "addr:housenumber":"291",
    "addr:postcode":"03079",
    "addr:street":"S Broadway",
    "iso:country":"US",
    "sg:address":"291 S Broadway",
    "sg:city":"Salem",
    "sg:classifiers":[
        {
            "category":"Home & Garden",
            "subcategory":"Furniture",
            "type":"Retail Goods"
        }
    ],
    "sg:phone":"+1 603 870 0004",
    "sg:postcode":"03079",
    "sg:province":"NH",
    "wof:name":"Jennifer Convertibles Inc",
    "wof:placetype":"venue"
},
  "geometry": {"coordinates":[-71.210646,42.756595],"type":"Point"}
}