{
  "type": "Feature",
  "properties": {
    "addr:full":"33 Pleasant St Concord NH 03301",
    "addr:housenumber":"33",
    "addr:postcode":"03301",
    "addr:street":"Pleasant St",
    "iso:country":"US",
    "sg:address":"33 Pleasant St",
    "sg:city":"Concord",
    "sg:classifiers":[
        {
            "category":"Education",
            "subcategory":"School",
            "type":"Public Place"
        }
    ],
    "sg:phone":"+1 603 228 4209",
    "sg:postcode":"03301",
    "sg:province":"NH",
    "wof:name":"Parker Academy",
    "wof:placetype":"venue"
},
  "geometry": {"coordinates":[-71.538043,43.203149],"type":"Point"}
}