{
  "type": "Feature",
  "properties": {
    "iso:country":"US",
    "sg:address":"444 E Industrial Park Dr",
    "sg:city":"Manchester",
    "sg:classifiers":[
        {
            "category":"Retail",
            "subcategory":"Auto Repair",
            "type":"Services"
        }
    ],
    "sg:phone":"+1 603 625 1976",
    "sg:postcode":"03109",
    "sg:province":"NH",
    "sg:tags":[
        "repairing",
        "automobile",
        "radiator"
    ],
    "sg:website":"www.spi.com",
    "wof:name":"SPI",
    "wof:placetype":"venue"
},
  "geometry": {"coordinates":[-71.4091,42.9767],"type":"Point"}
}