{
  "type": "Feature",
  "properties": {
    "iso:country":"US",
    "sg:address":"8 Rockingham Rd",
    "sg:city":"Windham",
    "sg:classifiers":[
        {
            "category":"Home & Garden",
            "subcategory":"Furniture",
            "type":"Retail Goods"
        }
    ],
    "sg:phone":"+1 603 893 8434",
    "sg:postcode":"03087",
    "sg:province":"NH",
    "sg:tags":[
        "household"
    ],
    "wof:name":"Furniture World Clearance Ctr",
    "wof:placetype":"venue"
},
  "geometry": {"coordinates":[-71.249771,42.81458],"type":"Point"}
}