{
  "type": "Feature",
  "properties": {
    "iso:country":"US",
    "sg:address":"28 Center St",
    "sg:city":"Laconia",
    "sg:classifiers":[
        {
            "category":"Manufacturing",
            "subcategory":"Watercraft",
            "type":"Manufacturing & Wholesale Goods"
        }
    ],
    "sg:phone":"+1 603 528 3411",
    "sg:postcode":"03246",
    "sg:province":"NH",
    "sg:tags":[
        "rebuilt",
        "part",
        "boat"
    ],
    "wof:name":"New England Boat & Motor Inc",
    "wof:placetype":"venue"
},
  "geometry": {"coordinates":[-71.467499,43.521762],"type":"Point"}
}