{
  "type": "Feature",
  "properties": {
    "addr:full":"13 Cornwall St Exeter NH 03833",
    "addr:housenumber":"13",
    "addr:postcode":"03833",
    "addr:street":"Cornwall St",
    "iso:country":"US",
    "sg:address":"13 Cornwall St",
    "sg:city":"Exeter",
    "sg:classifiers":[
        {
            "category":"Building & Trades",
            "subcategory":"Landscaping Services",
            "type":"Services"
        }
    ],
    "sg:phone":"+1 603 580 1034",
    "sg:postcode":"03833",
    "sg:province":"NH",
    "sg:tags":[
        "landscape",
        "contractor"
    ],
    "wof:name":"Executive Landscape & Irgtn",
    "wof:placetype":"venue"
},
  "geometry": {"coordinates":[-70.96645700000001,42.967767],"type":"Point"}
}