{
  "type": "Feature",
  "properties": {
    "iso:country":"US",
    "sg:address":"130 Whittier Hwy",
    "sg:city":"Center Harbor",
    "sg:classifiers":[
        {
            "category":"Home & Garden",
            "subcategory":"Home Furnishings",
            "type":"Retail Goods"
        }
    ],
    "sg:phone":"+1 603 253 8731",
    "sg:postcode":"03226",
    "sg:province":"NH",
    "sg:tags":[
        "quilting"
    ],
    "wof:name":"Keepsake Quilting",
    "wof:placetype":"venue"
},
  "geometry": {"coordinates":[-71.460002,43.710051],"type":"Point"}
}