{
  "type": "Feature",
  "properties": {
    "iso:country":"US",
    "sg:address":"270 Pinewood Rd",
    "sg:city":"Allenstown",
    "sg:classifiers":[
        {
            "category":"Restaurant",
            "type":"Food & Drink"
        }
    ],
    "sg:phone":"+1 603 485 2717",
    "sg:postcode":"03275",
    "sg:province":"NH",
    "wof:name":"Suncock Deli",
    "wof:placetype":"venue"
},
  "geometry": {"coordinates":[-71.405984,43.159379],"type":"Point"}
}