{
  "type": "Feature",
  "properties": {
    "iso:country":"US",
    "sg:address":"1100 Hooksett Rd",
    "sg:city":"Hooksett",
    "sg:classifiers":[
        {
            "category":"Personal",
            "subcategory":"Tanning Parlor",
            "type":"Services"
        }
    ],
    "sg:phone":"+1 603 666 4555",
    "sg:postcode":"03106",
    "sg:province":"NH",
    "sg:tags":[
        "salon"
    ],
    "wof:name":"Gettin' Golden",
    "wof:placetype":"venue"
},
  "geometry": {"coordinates":[-71.439425,43.028364],"type":"Point"}
}