{
  "type": "Feature",
  "properties": {
    "iso:country":"US",
    "sg:address":"62 Peterborough St",
    "sg:city":"Jaffrey",
    "sg:classifiers":[
        {
            "category":"Banks & Credit Unions",
            "subcategory":"Bank",
            "type":"Services"
        }
    ],
    "sg:phone":"+1 603 532 4448",
    "sg:postcode":"03452",
    "sg:province":"NH",
    "wof:name":"Ocean National Bank",
    "wof:placetype":"venue"
},
  "geometry": {"coordinates":[-72.020236,42.816488],"type":"Point"}
}