{
  "type": "Feature",
  "properties": {
    "iso:country":"US",
    "sg:address":"91 Gold St",
    "sg:city":"Manchester",
    "sg:classifiers":[
        {
            "category":"Shopping",
            "subcategory":"Used Merchandise",
            "type":"Retail Goods"
        }
    ],
    "sg:phone":"+1 603 668 5229",
    "sg:postcode":"03103",
    "sg:province":"NH",
    "sg:tags":[
        "antique"
    ],
    "wof:name":"Postcards From The Past",
    "wof:placetype":"venue"
},
  "geometry": {"coordinates":[-71.46029,42.954984],"type":"Point"}
}