{
  "type": "Feature",
  "properties": {
    "iso:country":"US",
    "sg:address":"51 Wilton Rd",
    "sg:city":"Peterborough",
    "sg:classifiers":[
        {
            "category":"Building & Trades",
            "subcategory":"Construction",
            "type":"Services"
        }
    ],
    "sg:phone":"+1 603 924 6444",
    "sg:postcode":"03458",
    "sg:province":"NH",
    "sg:tags":[
        "residential",
        "general",
        "contractor"
    ],
    "wof:name":"Schaal Given Contracting Inc",
    "wof:placetype":"venue"
},
  "geometry": {"coordinates":[-71.95066199999999,42.870114],"type":"Point"}
}