{
  "type": "Feature",
  "properties": {
    "iso:country":"US",
    "sg:address":"70 Tebbets Rd",
    "sg:city":"Rochester",
    "sg:classifiers":[
        {
            "category":"Retail",
            "subcategory":"Auto Repair",
            "type":"Services"
        }
    ],
    "sg:phone":"+1 603 332 0440",
    "sg:postcode":"03867",
    "sg:province":"NH",
    "sg:tags":[
        "machine",
        "automobile",
        "shop",
        "automotive"
    ],
    "wof:name":"Flo Rite Machine Inc",
    "wof:placetype":"venue"
},
  "geometry": {"coordinates":[-70.946842,43.277674],"type":"Point"}
}