{
  "type": "Feature",
  "properties": {
    "iso:country":"US",
    "sg:address":"496 Main St",
    "sg:city":"Gorham",
    "sg:classifiers":[
        {
            "category":"Retail",
            "subcategory":"Portrait Studio",
            "type":"Services"
        }
    ],
    "sg:phone":"+1 603 752 6100",
    "sg:postcode":"03581",
    "sg:province":"NH",
    "sg:tags":[
        "photography"
    ],
    "wof:name":"NDP Photography",
    "wof:placetype":"venue"
},
  "geometry": {"coordinates":[-71.19326,44.424826],"type":"Point"}
}