{
  "type": "Feature",
  "properties": {
    "addr:full":"47 Amesbury Rd Kensington NH 03833",
    "addr:housenumber":"47",
    "addr:postcode":"03833",
    "addr:street":"Amesbury Rd",
    "iso:country":"US",
    "sg:address":"47 Amesbury Rd",
    "sg:city":"Kensington",
    "sg:classifiers":[
        {
            "category":"Building & Trades",
            "subcategory":"Construction",
            "type":"Services"
        }
    ],
    "sg:phone":"+1 603 775 0548",
    "sg:postcode":"03833",
    "sg:province":"NH",
    "sg:tags":[
        "designer",
        "dealer",
        "pool",
        "swimming"
    ],
    "wof:name":"Johnson Pools & Construction",
    "wof:placetype":"venue"
},
  "geometry": {"coordinates":[-70.95336399999999,42.944347],"type":"Point"}
}