{
  "type": "Feature",
  "properties": {
    "iso:country":"US",
    "sg:address":"14 King St",
    "sg:city":"Woodsville",
    "sg:classifiers":[
        {
            "category":"Freight",
            "type":"Transportation"
        }
    ],
    "sg:phone":"+1 603 747 2785",
    "sg:postcode":"03785",
    "sg:province":"NH",
    "sg:tags":[
        "trucking"
    ],
    "wof:name":"Copperhead Transport",
    "wof:placetype":"venue"
},
  "geometry": {"coordinates":[-72.03367299999999,44.145702],"type":"Point"}
}