{
  "type": "Feature",
  "properties": {
    "iso:country":"US",
    "sg:address":"1 Eagle Sq",
    "sg:city":"Concord",
    "sg:classifiers":[
        {
            "category":"Insurance",
            "subcategory":"Title Insurance",
            "type":"Services"
        }
    ],
    "sg:phone":"+1 603 224 3811",
    "sg:postcode":"03301",
    "sg:province":"NH",
    "sg:tags":[
        "company"
    ],
    "wof:name":"First American Title Insur Co",
    "wof:placetype":"venue"
},
  "geometry": {"coordinates":[-71.535622,43.206686],"type":"Point"}
}