{
  "type": "Feature",
  "properties": {
    "iso:country":"US",
    "sg:address":"200 Technology Dr",
    "sg:city":"Hooksett",
    "sg:classifiers":[
        {
            "category":"Health Services",
            "subcategory":"Doctor",
            "type":"Services"
        }
    ],
    "sg:phone":"+1 603 622 6484",
    "sg:postcode":"03106",
    "sg:province":"NH",
    "sg:tags":[
        "medical"
    ],
    "wof:name":"Chas H Catcher",
    "wof:placetype":"venue"
},
  "geometry": {"coordinates":[-71.46559600000001,43.047398],"type":"Point"}
}