{
  "type": "Feature",
  "properties": {
    "iso:country":"US",
    "sg:address":"23 Teloian Dr",
    "sg:city":"Hudson",
    "sg:classifiers":[
        {
            "category":"Manufacturing",
            "subcategory":"Tools & Machinery",
            "type":"Manufacturing & Wholesale Goods"
        }
    ],
    "sg:phone":"+1 603 315 4423",
    "sg:postcode":"03051",
    "sg:province":"NH",
    "sg:tags":[
        "erectors",
        "mover",
        "millwright"
    ],
    "wof:name":"Turbine Millwright",
    "wof:placetype":"venue"
},
  "geometry": {"coordinates":[-71.36705600000001,42.778119],"type":"Point"}
}