{
  "type": "Feature",
  "properties": {
    "iso:country":"US",
    "sg:address":"151 West St",
    "sg:city":"Keene",
    "sg:classifiers":[
        {
            "category":"Professional",
            "subcategory":"Business Services",
            "type":"Services"
        }
    ],
    "sg:phone":"+1 603 355 2287",
    "sg:postcode":"03431",
    "sg:province":"NH",
    "wof:name":"Lewis Thomas J Business",
    "wof:placetype":"venue"
},
  "geometry": {"coordinates":[-72.284342,42.932717],"type":"Point"}
}