{
  "type": "Feature",
  "properties": {
    "iso:country":"US",
    "sg:address":"8 Bridge St",
    "sg:city":"Hillsboro",
    "sg:classifiers":[
        {
            "category":"Shopping",
            "subcategory":"Used Merchandise",
            "type":"Retail Goods"
        }
    ],
    "sg:phone":"+1 603 464 5115",
    "sg:postcode":"03244",
    "sg:province":"NH",
    "sg:tags":[
        "second",
        "store",
        "hand"
    ],
    "wof:name":"Cast Away Treasures",
    "wof:placetype":"venue"
},
  "geometry": {"coordinates":[-71.894811,43.114433],"type":"Point"}
}