{
  "type": "Feature",
  "properties": {
    "iso:country":"US",
    "sg:address":"46 S Main St",
    "sg:city":"Concord",
    "sg:classifiers":[
        {
            "category":"Social Services",
            "type":"Services"
        }
    ],
    "sg:phone":"+1 603 224 2595",
    "sg:postcode":"03301",
    "sg:province":"NH",
    "sg:tags":[
        "organization",
        "welfare"
    ],
    "sg:website":"www.unitedwymc.org",
    "wof:name":"United Way",
    "wof:placetype":"venue"
},
  "geometry": {"coordinates":[-71.53417,43.201412],"type":"Point"}
}