{
  "type": "Feature",
  "properties": {
    "iso:country":"US",
    "sg:address":"13 Clover Ct",
    "sg:city":"Raymond",
    "sg:classifiers":[
        {
            "category":"Building & Trades",
            "subcategory":"Construction",
            "type":"Services"
        }
    ],
    "sg:phone":"+1 603 895 4040",
    "sg:postcode":"03077",
    "sg:province":"NH",
    "sg:tags":[
        "general",
        "contractor"
    ],
    "wof:name":"Munroe Builders",
    "wof:placetype":"venue"
},
  "geometry": {"coordinates":[-71.15935399999999,43.003638],"type":"Point"}
}