{
  "type": "Feature",
  "properties": {
    "iso:country":"US",
    "sg:address":"36 Exchange St",
    "sg:city":"Gorham",
    "sg:classifiers":[
        {
            "category":"Shopping",
            "subcategory":"Gifts & Souvenirs",
            "type":"Retail Goods"
        }
    ],
    "sg:phone":"+1 603 466 9900",
    "sg:postcode":"03581",
    "sg:province":"NH",
    "wof:name":"Gateway Gallery & Gifts",
    "wof:placetype":"venue"
},
  "geometry": {"coordinates":[-71.176596,44.388431],"type":"Point"}
}