{
  "type": "Feature",
  "properties": {
    "iso:country":"US",
    "sg:address":"191 Elm St",
    "sg:city":"Milford",
    "sg:classifiers":[
        {
            "category":"Personal",
            "type":"Services"
        }
    ],
    "sg:phone":"+1 603 672 9099",
    "sg:postcode":"03055",
    "sg:province":"NH",
    "sg:tags":[
        "program",
        "physical",
        "exercise",
        "fitness"
    ],
    "wof:name":"Fit Works",
    "wof:placetype":"venue"
},
  "geometry": {"coordinates":[-71.650164,42.835181],"type":"Point"}
}