{
  "type": "Feature",
  "properties": {
    "addr:full":"148 S Shore Dr Contoocook NH 03229",
    "addr:housenumber":"148",
    "addr:postcode":"03229",
    "addr:street":"S Shore Dr",
    "iso:country":"US",
    "sg:address":"148 S Shore Dr",
    "sg:city":"Contoocook",
    "sg:classifiers":[
        {
            "category":"Retail",
            "subcategory":"Repair Shop",
            "type":"Services"
        }
    ],
    "sg:phone":"+1 603 746 3877",
    "sg:postcode":"03229",
    "sg:province":"NH",
    "wof:name":"Masonworks Electronics",
    "wof:placetype":"venue"
},
  "geometry": {"coordinates":[-71.76397,43.212568],"type":"Point"}
}