{
  "type": "Feature",
  "properties": {
    "iso:country":"US",
    "sg:address":"20 Madbury Rd",
    "sg:city":"Durham",
    "sg:classifiers":[
        {
            "category":"Health Services",
            "subcategory":"Health Practitioner",
            "type":"Services"
        }
    ],
    "sg:phone":"+1 603 868 7275",
    "sg:postcode":"03824",
    "sg:province":"NH",
    "sg:tags":[
        "psychologist"
    ],
    "wof:name":"Liza Little",
    "wof:placetype":"venue"
},
  "geometry": {"coordinates":[-70.92533299999999,43.135748],"type":"Point"}
}