{
  "type": "Feature",
  "properties": {
    "addr:full":"30 Cottage St Milford NH 03055",
    "addr:housenumber":"30",
    "addr:postcode":"03055",
    "addr:street":"Cottage St",
    "iso:country":"US",
    "sg:address":"30 Cottage St",
    "sg:city":"Milford",
    "sg:classifiers":[
        {
            "category":"Building & Trades",
            "subcategory":"Construction",
            "type":"Services"
        }
    ],
    "sg:phone":"+1 603 672 5450",
    "sg:postcode":"03055",
    "sg:province":"NH",
    "sg:tags":[
        "house"
    ],
    "wof:name":"Abaid Home Repair",
    "wof:placetype":"venue"
},
  "geometry": {"coordinates":[-71.65392900000001,42.833172],"type":"Point"}
}