{
  "type": "Feature",
  "properties": {
    "iso:country":"US",
    "sg:address":"415 River Rd",
    "sg:city":"Manchester",
    "sg:classifiers":[
        {
            "category":"Professional",
            "subcategory":"Lawyer & Legal Services",
            "type":"Services"
        }
    ],
    "sg:phone":"+1 603 624 0997",
    "sg:postcode":"03104",
    "sg:province":"NH",
    "wof:name":"House Counsel",
    "wof:placetype":"venue"
},
  "geometry": {"coordinates":[-71.46798200000001,43.010483],"type":"Point"}
}