{
  "type": "Feature",
  "properties": {
    "addr:full":"1051 S Willow St Manchester NH 03103",
    "addr:housenumber":"1051",
    "addr:postcode":"03103",
    "addr:street":"S Willow St",
    "iso:country":"US",
    "sg:address":"1051 S Willow St",
    "sg:city":"Manchester",
    "sg:classifiers":[
        {
            "category":"Freight",
            "type":"Transportation"
        }
    ],
    "sg:phone":"+1 603 625 8971",
    "sg:postcode":"03103",
    "sg:province":"NH",
    "sg:tags":[
        "trucking"
    ],
    "wof:name":"St Johnsbury Trucking Co",
    "wof:placetype":"venue"
},
  "geometry": {"coordinates":[-71.437848,42.960529],"type":"Point"}
}