{
  "type": "Feature",
  "properties": {
    "addr:full":"127 Plaistow Rd Plaistow NH 03865",
    "addr:housenumber":"127",
    "addr:postcode":"03865",
    "addr:street":"Plaistow Rd",
    "iso:country":"US",
    "sg:address":"127 Plaistow Rd",
    "sg:city":"Plaistow",
    "sg:classifiers":[
        {
            "category":"Restaurant",
            "type":"Food & Drink"
        }
    ],
    "sg:phone":"+1 603 382 5063",
    "sg:postcode":"03865",
    "sg:province":"NH",
    "sg:tags":[
        "eating"
    ],
    "wof:name":"Eggies Diner",
    "wof:placetype":"venue"
},
  "geometry": {"coordinates":[-71.106647,42.844907],"type":"Point"}
}