{
  "type": "Feature",
  "properties": {
    "iso:country":"US",
    "sg:address":"276 Squantum Rd",
    "sg:city":"Jaffrey",
    "sg:classifiers":[
        {
            "category":"Professional",
            "subcategory":"Management & Consulting",
            "type":"Services"
        }
    ],
    "sg:phone":"+1 603 532 8858",
    "sg:postcode":"03452",
    "sg:province":"NH",
    "sg:tags":[
        "consultant"
    ],
    "wof:name":"Woodbury Hill Partners",
    "wof:placetype":"venue"
},
  "geometry": {"coordinates":[-71.99009700000001,42.791851],"type":"Point"}
}