{
  "type": "Feature",
  "properties": {
    "iso:country":"US",
    "sg:address":"139 Saltmarsh Pond Rd",
    "sg:city":"Gilford",
    "sg:classifiers":[
        {
            "category":"Retail",
            "subcategory":"Laundry & Dry Cleaning",
            "type":"Services"
        }
    ],
    "sg:phone":"+1 603 524 8264",
    "sg:postcode":"03249",
    "sg:province":"NH",
    "sg:tags":[
        "cleaners",
        "rug",
        "carpet"
    ],
    "wof:name":"New England Carpet & Uphl Clg",
    "wof:placetype":"venue"
},
  "geometry": {"coordinates":[-71.417778,43.530837],"type":"Point"}
}