{
  "type": "Feature",
  "properties": {
    "addr:full":"10 Quaker Rd New Durham NH 03855",
    "addr:housenumber":"10",
    "addr:postcode":"03855",
    "addr:street":"Quaker Rd",
    "iso:country":"US",
    "sg:address":"10 Quaker Rd",
    "sg:city":"New Durham",
    "sg:classifiers":[
        {
            "category":"Retail",
            "subcategory":"Repair Shop",
            "type":"Services"
        },
        {
            "category":"Building & Trades",
            "subcategory":"Construction",
            "type":"Services"
        }
    ],
    "sg:phone":"+1 603 859 2688",
    "sg:postcode":"03855",
    "sg:province":"NH",
    "sg:tags":[
        "welding",
        "contractor"
    ],
    "wof:name":"Benoit's Welding",
    "wof:placetype":"venue"
},
  "geometry": {"coordinates":[-71.12158100000001,43.401993],"type":"Point"}
}