{
  "type": "Feature",
  "properties": {
    "addr:full":"8 Love Ln Somersworth NH 03870",
    "addr:housenumber":"8",
    "addr:postcode":"03870",
    "addr:street":"Love Ln",
    "iso:country":"US",
    "sg:address":"8 Love Ln",
    "sg:city":"Somersworth",
    "sg:classifiers":[
        {
            "category":"Building & Trades",
            "subcategory":"Construction",
            "type":"Services"
        }
    ],
    "sg:phone":"+1 603 692 9444",
    "sg:postcode":"03870",
    "sg:province":"NH",
    "sg:tags":[
        "excavation",
        "contractor"
    ],
    "wof:name":"Oak Excavation",
    "wof:placetype":"venue"
},
  "geometry": {"coordinates":[-70.773382,42.988218],"type":"Point"}
}