{
  "type": "Feature",
  "properties": {
    "addr:full":"472 Lafayette Rd Seabrook NH 03874",
    "addr:housenumber":"472",
    "addr:postcode":"03874",
    "iso:country":"US",
    "sg:address":"472 Lafayette Rd",
    "sg:city":"Seabrook",
    "sg:classifiers":[
        {
            "category":"Manufacturing",
            "subcategory":"Food",
            "type":"Manufacturing & Wholesale Goods"
        }
    ],
    "sg:phone":"+1 603 474 8338",
    "sg:postcode":"03874",
    "sg:province":"NH",
    "sg:tags":[
        "product",
        "dairy"
    ],
    "wof:name":"Dean Northeast LLC",
    "wof:placetype":"venue"
},
  "geometry": {"coordinates":[-70.87136,42.888324],"type":"Point"}
}