{
  "type": "Feature",
  "properties": {
    "addr:full":"159 Hampstead Rd Derry NH 03038",
    "addr:housenumber":"159",
    "addr:postcode":"03038",
    "addr:street":"Hampstead Rd",
    "iso:country":"US",
    "sg:address":"159 Hampstead Rd",
    "sg:city":"Derry",
    "sg:classifiers":[
        {
            "category":"Recreation",
            "type":"Entertainment"
        }
    ],
    "sg:phone":"+1 603 434 8779",
    "sg:postcode":"03038",
    "sg:province":"NH",
    "sg:tags":[
        "stable"
    ],
    "wof:name":"High Gate Manor Farm",
    "wof:placetype":"venue"
},
  "geometry": {"coordinates":[-71.258788,42.899237],"type":"Point"}
}