{
  "type": "Feature",
  "properties": {
    "iso:country":"US",
    "sg:address":"1 Ivy Pointe Way",
    "sg:city":"Hanover",
    "sg:classifiers":[
        {
            "category":"Organizations",
            "subcategory":"Professional Association",
            "type":"Services"
        }
    ],
    "sg:phone":"+1 603 643 3276",
    "sg:postcode":"03755",
    "sg:province":"NH",
    "wof:name":"World Phenomenlogical Inst",
    "wof:placetype":"venue"
},
  "geometry": {"coordinates":[-72.28020600000001,43.708563],"type":"Point"}
}