{
  "type": "Feature",
  "properties": {
    "addr:full":"126 Stoney Brook Rd Lebanon NH 03766",
    "addr:housenumber":"126",
    "addr:postcode":"03766",
    "addr:street":"Stoney Brook Rd",
    "iso:country":"US",
    "sg:address":"126 Stoney Brook Rd",
    "sg:city":"Lebanon",
    "sg:classifiers":[
        {
            "category":"Manufacturing",
            "subcategory":"Watercraft",
            "type":"Manufacturing & Wholesale Goods"
        }
    ],
    "sg:phone":"+1 603 448 4568",
    "sg:postcode":"03766",
    "sg:province":"NH",
    "wof:name":"Connecticut River Boat Works",
    "wof:placetype":"venue"
},
  "geometry": {"coordinates":[-72.208524,43.634215],"type":"Point"}
}