{
  "type": "Feature",
  "properties": {
    "iso:country":"US",
    "sg:address":"575 State Rte 106",
    "sg:city":"Loudon",
    "sg:classifiers":[
        {
            "category":"Professional",
            "type":"Services"
        }
    ],
    "sg:phone":"+1 603 783 9555",
    "sg:postcode":"03307",
    "sg:province":"NH",
    "sg:tags":[
        "establishment"
    ],
    "wof:name":"National Power Sports Dist",
    "wof:placetype":"venue"
},
  "geometry": {"coordinates":[-71.475459,43.311384],"type":"Point"}
}