{
  "type": "Feature",
  "properties": {
    "addr:full":"522 Sagamore Rd Rye NH 03870",
    "addr:housenumber":"522",
    "addr:postcode":"03870",
    "addr:street":"Sagamore Rd",
    "iso:country":"US",
    "sg:address":"522 Sagamore Rd",
    "sg:city":"Rye",
    "sg:classifiers":[
        {
            "category":"Shopping",
            "subcategory":"Bicycles & Sporting Goods",
            "type":"Retail Goods"
        }
    ],
    "sg:phone":"+1 603 436 4443",
    "sg:postcode":"03870",
    "sg:province":"NH",
    "sg:tags":[
        "equipment",
        "diver",
        "supply"
    ],
    "wof:name":"Atlantic Aqua Sport",
    "wof:placetype":"venue"
},
  "geometry": {"coordinates":[-70.75476500000001,43.026026],"type":"Point"}
}