{
  "type": "Feature",
  "properties": {
    "addr:full":"132 State Rte 101A Amherst NH 03031",
    "addr:housenumber":"132",
    "addr:postcode":"03031",
    "addr:street":"State Rte 101A",
    "iso:country":"US",
    "sg:address":"132 State Rte 101A",
    "sg:city":"Amherst",
    "sg:classifiers":[
        {
            "category":"Shopping",
            "subcategory":"Hobbies, Toys, & Games",
            "type":"Retail Goods"
        }
    ],
    "sg:phone":"+1 603 579 9876",
    "sg:postcode":"03031",
    "sg:province":"NH",
    "sg:tags":[
        "shop",
        "model",
        "train",
        "supply"
    ],
    "wof:name":"Trains On Tracks Inc",
    "wof:placetype":"venue"
},
  "geometry": {"coordinates":[-71.564798,42.805851],"type":"Point"}
}