{
  "type": "Feature",
  "properties": {
    "iso:country":"US",
    "sg:address":"97 E Main St",
    "sg:city":"Conway",
    "sg:classifiers":[
        {
            "category":"Government",
            "subcategory":"Fire Station",
            "type":"Public Place"
        }
    ],
    "sg:phone":"+1 603 447 2681",
    "sg:postcode":"03818",
    "sg:province":"NH",
    "sg:tags":[
        "department"
    ],
    "wof:name":"Conway Fire Station",
    "wof:placetype":"venue"
},
  "geometry": {"coordinates":[-71.11647600000001,43.978929],"type":"Point"}
}