{
  "type": "Feature",
  "properties": {
    "iso:country":"US",
    "sg:address":"2 Broadway Ave",
    "sg:city":"Gorham",
    "sg:classifiers":[
        {
            "category":"Health Services",
            "subcategory":"Doctor",
            "type":"Services"
        }
    ],
    "sg:phone":"+1 603 466 2741",
    "sg:postcode":"03581",
    "sg:province":"NH",
    "sg:tags":[
        "physician",
        "surgeon"
    ],
    "wof:name":"Mountain Health Svc",
    "wof:placetype":"venue"
},
  "geometry": {"coordinates":[-71.189718,44.395326],"type":"Point"}
}