{
  "type": "Feature",
  "properties": {
    "iso:country":"US",
    "sg:address":"707 Lockehaven Rd",
    "sg:city":"Enfield",
    "sg:classifiers":[
        {
            "category":"Professional",
            "subcategory":"Accounting & Tax Preparation",
            "type":"Services"
        }
    ],
    "sg:phone":"+1 603 632 4780",
    "sg:postcode":"03748",
    "sg:province":"NH",
    "sg:tags":[
        "accountant"
    ],
    "wof:name":"Lynn Page Baker CPA",
    "wof:placetype":"venue"
},
  "geometry": {"coordinates":[-72.06662799999999,43.605048],"type":"Point"}
}