{
  "type": "Feature",
  "properties": {
    "iso:country":"US",
    "sg:address":"170 Warren St",
    "sg:city":"Concord",
    "sg:classifiers":[
        {
            "category":"Education",
            "subcategory":"School",
            "type":"Public Place"
        }
    ],
    "sg:phone":"+1 603 225 0804",
    "sg:postcode":"03301",
    "sg:province":"NH",
    "wof:name":"Concord Community Education",
    "wof:placetype":"venue"
},
  "geometry": {"coordinates":[-71.550319,43.199729],"type":"Point"}
}