{
  "type": "Feature",
  "properties": {
    "iso:country":"US",
    "sg:address":"2017 Main St",
    "sg:city":"Bethlehem",
    "sg:classifiers":[
        {
            "category":"Personal",
            "subcategory":"Beauty Salon",
            "type":"Services"
        }
    ],
    "sg:phone":"+1 603 869 3152",
    "sg:postcode":"03574",
    "sg:province":"NH",
    "wof:name":"Razzmatazz",
    "wof:placetype":"venue"
},
  "geometry": {"coordinates":[-71.69502,44.279752],"type":"Point"}
}