{
  "type": "Feature",
  "properties": {
    "iso:country":"US",
    "sg:address":"150 Congress St",
    "sg:city":"Portsmouth",
    "sg:classifiers":[
        {
            "category":"Shopping",
            "subcategory":"Books",
            "type":"Retail Goods"
        }
    ],
    "sg:phone":"+1 603 427 1323",
    "sg:postcode":"03801",
    "sg:province":"NH",
    "sg:tags":[
        "used",
        "merchandise"
    ],
    "wof:name":"Bobs Books Inc",
    "wof:placetype":"venue"
},
  "geometry": {"coordinates":[-70.760267,43.075926],"type":"Point"}
}