{
  "type": "Feature",
  "properties": {
    "addr:full":"23 S Main St Newton NH 03858",
    "addr:housenumber":"23",
    "addr:postcode":"03858",
    "addr:street":"S Main St",
    "iso:country":"US",
    "sg:address":"23 S Main St",
    "sg:city":"Newton",
    "sg:classifiers":[
        {
            "category":"Retail",
            "subcategory":"Repair Shop",
            "type":"Services"
        }
    ],
    "sg:phone":"+1 603 382 4667",
    "sg:postcode":"03858",
    "sg:province":"NH",
    "sg:tags":[
        "laboratory",
        "testing"
    ],
    "wof:name":"A/D Instruments",
    "wof:placetype":"venue"
},
  "geometry": {"coordinates":[-71.037739,42.86615],"type":"Point"}
}