{
  "type": "Feature",
  "properties": {
    "iso:country":"US",
    "sg:address":"8 Riverside St",
    "sg:city":"Nashua",
    "sg:classifiers":[
        {
            "category":"Shopping",
            "subcategory":"Bicycles & Sporting Goods",
            "type":"Retail Goods"
        }
    ],
    "sg:phone":"+1 603 595 6313",
    "sg:postcode":"03062",
    "sg:province":"NH",
    "sg:tags":[
        "equipment",
        "hockey"
    ],
    "wof:name":"Perfect Edge Pro Shop",
    "wof:placetype":"venue"
},
  "geometry": {"coordinates":[-71.50102200000001,42.747602],"type":"Point"}
}