{
  "type": "Feature",
  "properties": {
    "iso:country":"US",
    "sg:address":"15 Sagamore Rd",
    "sg:city":"Rye",
    "sg:classifiers":[
        {
            "category":"Shopping",
            "subcategory":"Crafts & Fabrics",
            "type":"Retail Goods"
        }
    ],
    "sg:phone":"+1 603 430 9276",
    "sg:postcode":"03870",
    "sg:province":"NH",
    "sg:tags":[
        "yarn"
    ],
    "wof:name":"Yarn For You",
    "wof:placetype":"venue"
},
  "geometry": {"coordinates":[-70.74750299999999,43.048513],"type":"Point"}
}