{
  "type": "Feature",
  "properties": {
    "iso:country":"US",
    "sg:address":"78 Glebe Rd",
    "sg:city":"Spofford",
    "sg:classifiers":[
        {
            "category":"Wholesale",
            "subcategory":"Hardware",
            "type":"Manufacturing & Wholesale Goods"
        }
    ],
    "sg:phone":"+1 603 363 9388",
    "sg:postcode":"03462",
    "sg:province":"NH",
    "sg:tags":[
        "tool"
    ],
    "wof:name":"J & J Discount Store",
    "wof:placetype":"venue"
},
  "geometry": {"coordinates":[-72.383515,42.92272],"type":"Point"}
}