{
  "type": "Feature",
  "properties": {
    "iso:country":"US",
    "sg:address":"77 Middleton Rd",
    "sg:city":"Wolfeboro",
    "sg:classifiers":[
        {
            "category":"Organizations",
            "subcategory":"Religious Organization",
            "type":"Services"
        }
    ],
    "sg:phone":"+1 603 569 3971",
    "sg:postcode":"03894",
    "sg:province":"NH",
    "wof:name":"Jehovahs Witnesses",
    "wof:placetype":"venue"
},
  "geometry": {"coordinates":[-71.17465799999999,43.56081],"type":"Point"}
}