{
  "type": "Feature",
  "properties": {
    "iso:country":"US",
    "sg:address":"27 Snow Ln",
    "sg:city":"Hollis",
    "sg:classifiers":[
        {
            "category":"Retail",
            "subcategory":"Repair Shop",
            "type":"Services"
        }
    ],
    "sg:phone":"+1 603 882 3867",
    "sg:postcode":"03049",
    "sg:province":"NH",
    "wof:name":"Beddard Jerry",
    "wof:placetype":"venue"
},
  "geometry": {"coordinates":[-71.543691,42.735895],"type":"Point"}
}