{
  "type": "Feature",
  "properties": {
    "iso:country":"US",
    "sg:address":"82 Washington St",
    "sg:city":"Keene",
    "sg:classifiers":[
        {
            "category":"Retail",
            "subcategory":"Laundry & Dry Cleaning",
            "type":"Services"
        },
        {
            "category":"Shopping",
            "subcategory":"Clothing, Apparel, & Fashions",
            "type":"Retail Goods"
        }
    ],
    "sg:phone":"+1 603 355 2409",
    "sg:postcode":"03431",
    "sg:province":"NH",
    "sg:tags":[
        "tailor"
    ],
    "wof:name":"Sew Perfect",
    "wof:placetype":"venue"
},
  "geometry": {"coordinates":[-72.277315,42.936322],"type":"Point"}
}