{
  "type": "Feature",
  "properties": {
    "iso:country":"US",
    "sg:address":"3 Durrell St",
    "sg:city":"Dover",
    "sg:classifiers":[
        {
            "category":"Professional",
            "type":"Services"
        }
    ],
    "sg:phone":"+1 603 742 6238",
    "sg:postcode":"03820",
    "sg:province":"NH",
    "wof:name":"Benjamin Cloutier Services",
    "wof:placetype":"venue"
},
  "geometry": {"coordinates":[-70.871758,43.199749],"type":"Point"}
}