{
  "type": "Feature",
  "properties": {
    "iso:country":"US",
    "sg:address":"762 S Mast Rd",
    "sg:city":"Manchester",
    "sg:classifiers":[
        {
            "category":"Home & Garden",
            "subcategory":"Hardware",
            "type":"Retail Goods"
        }
    ],
    "sg:phone":"+1 603 668 5533",
    "sg:postcode":"03045",
    "sg:province":"NH",
    "sg:tags":[
        "tool",
        "hand",
        "power",
        "general"
    ],
    "wof:name":"Aubin Hardware Inc",
    "wof:placetype":"venue"
},
  "geometry": {"coordinates":[-71.49906900000001,42.989934],"type":"Point"}
}