{
  "type": "Feature",
  "properties": {
    "iso:country":"US",
    "sg:address":"20 Central Sq",
    "sg:city":"Keene",
    "sg:classifiers":[
        {
            "category":"Professional",
            "type":"Services"
        },
        {
            "category":"Professional",
            "subcategory":"Management & Consulting",
            "type":"Services"
        }
    ],
    "sg:phone":"+1 603 357 0557",
    "sg:postcode":"03431",
    "sg:province":"NH",
    "sg:tags":[
        "commission",
        "regional",
        "planning",
        "establishment"
    ],
    "sg:website":"www.swrpc.org",
    "wof:name":"Southwest Region Planning Comm",
    "wof:placetype":"venue"
},
  "geometry": {"coordinates":[-72.27816900000001,42.934257],"type":"Point"}
}