{
  "type": "Feature",
  "properties": {
    "iso:country":"US",
    "sg:address":"123 Whipplewill Rd",
    "sg:city":"New Boston",
    "sg:classifiers":[
        {
            "category":"Retail",
            "subcategory":"Auto Repair",
            "type":"Services"
        }
    ],
    "sg:phone":"+1 603 497 4472",
    "sg:postcode":"03070",
    "sg:province":"NH",
    "sg:tags":[
        "general"
    ],
    "wof:name":"Cornerstone Auto Repair",
    "wof:placetype":"venue"
},
  "geometry": {"coordinates":[-71.63928199999999,43.023359],"type":"Point"}
}