{
  "type": "Feature",
  "properties": {
    "iso:country":"US",
    "sg:address":"478 Main St",
    "sg:city":"Hampstead",
    "sg:phone":"+1 603 329 6916",
    "sg:postcode":"03841",
    "sg:province":"NH",
    "sg:tags":[
        "oil"
    ],
    "wof:name":"Difeo Duston Oil Co",
    "wof:placetype":"venue"
},
  "geometry": {"coordinates":[-71.213814,42.896316],"type":"Point"}
}