{
  "type": "Feature",
  "properties": {
    "iso:country":"US",
    "sg:address":"292 Main St",
    "sg:city":"New London",
    "sg:classifiers":[
        {
            "category":"Shopping",
            "subcategory":"Computers & Home Electronics",
            "type":"Retail Goods"
        }
    ],
    "sg:phone":"+1 603 526 4358",
    "sg:postcode":"03257",
    "sg:province":"NH",
    "sg:tags":[
        "software"
    ],
    "sg:website":"www.ibshome.com",
    "wof:name":"Intelligent Banking Solutions",
    "wof:placetype":"venue"
},
  "geometry": {"coordinates":[-72.063288,43.499492],"type":"Point"}
}