{
  "type": "Feature",
  "properties": {
    "iso:country":"US",
    "sg:address":"71 Morrill St",
    "sg:city":"Laconia",
    "sg:classifiers":[
        {
            "category":"Building & Trades",
            "subcategory":"Landscaping Services",
            "type":"Services"
        }
    ],
    "sg:phone":"+1 603 528 5809",
    "sg:postcode":"03246",
    "sg:province":"NH",
    "sg:tags":[
        "landscape",
        "contractor"
    ],
    "wof:name":"James E Coffey & Son Ldscpg",
    "wof:placetype":"venue"
},
  "geometry": {"coordinates":[-71.45625,43.534614],"type":"Point"}
}