{
  "type": "Feature",
  "properties": {
    "iso:country":"US",
    "sg:address":"252 Daniel Webster Hwy",
    "sg:city":"Belmont",
    "sg:classifiers":[
        {
            "category":"Building & Trades",
            "subcategory":"Construction",
            "type":"Services"
        }
    ],
    "sg:phone":"+1 603 524 2000",
    "sg:postcode":"03220",
    "sg:province":"NH",
    "sg:tags":[
        "dock"
    ],
    "wof:name":"Lakes Region Dock Co",
    "wof:placetype":"venue"
},
  "geometry": {"coordinates":[-71.50042999999999,43.50776],"type":"Point"}
}