{
  "type": "Feature",
  "properties": {
    "iso:country":"US",
    "sg:address":"5 Woodbury Ave",
    "sg:city":"Pelham",
    "sg:classifiers":[
        {
            "category":"Manufacturing",
            "subcategory":"Tools & Machinery",
            "type":"Manufacturing & Wholesale Goods"
        }
    ],
    "sg:phone":"+1 603 635 7646",
    "sg:postcode":"03076",
    "sg:province":"NH",
    "sg:tags":[
        "machine",
        "shop"
    ],
    "wof:name":"M E Engineering Co",
    "wof:placetype":"venue"
},
  "geometry": {"coordinates":[-71.321614,42.733546],"type":"Point"}
}