{
  "type": "Feature",
  "properties": {
    "iso:country":"US",
    "sg:address":"155 E Main St",
    "sg:city":"Tilton",
    "sg:classifiers":[
        {
            "category":"Personal",
            "subcategory":"Beauty Salon",
            "type":"Services"
        }
    ],
    "sg:phone":"+1 603 823 4070",
    "sg:postcode":"03276",
    "sg:province":"NH",
    "sg:tags":[
        "shop"
    ],
    "wof:name":"Strand",
    "wof:placetype":"venue"
},
  "geometry": {"coordinates":[-71.581467,43.445747],"type":"Point"}
}