{
  "type": "Feature",
  "properties": {
    "addr:full":"673 Union Ave Laconia NH 03246",
    "addr:housenumber":"673",
    "addr:postcode":"03246",
    "addr:street":"Union Ave",
    "iso:country":"US",
    "sg:address":"673 Union Ave",
    "sg:city":"Laconia",
    "sg:classifiers":[
        {
            "category":"Personal",
            "subcategory":"Beauty Salon",
            "type":"Services"
        }
    ],
    "sg:phone":"+1 603 524 5444",
    "sg:postcode":"03246",
    "sg:province":"NH",
    "sg:tags":[
        "shop"
    ],
    "wof:name":"Tom's The Now Look",
    "wof:placetype":"venue"
},
  "geometry": {"coordinates":[-71.464485,43.54464],"type":"Point"}
}