{
  "type": "Feature",
  "properties": {
    "iso:country":"US",
    "sg:address":"329 S Mast Rd",
    "sg:city":"Goffstown",
    "sg:classifiers":[
        {
            "category":"Building & Trades",
            "subcategory":"Construction",
            "type":"Services"
        }
    ],
    "sg:phone":"+1 603 644 7881",
    "sg:postcode":"03045",
    "sg:province":"NH",
    "sg:tags":[
        "house",
        "nonresidential"
    ],
    "wof:name":"Enviro-Tech Post & Beam",
    "wof:placetype":"venue"
},
  "geometry": {"coordinates":[-71.540273,43.009897],"type":"Point"}
}