{
  "type": "Feature",
  "properties": {
    "iso:country":"US",
    "sg:address":"7 Ely St",
    "sg:city":"Littleton",
    "sg:classifiers":[
        {
            "category":"Professional",
            "subcategory":"Management & Consulting",
            "type":"Services"
        }
    ],
    "sg:phone":"+1 603 444 3337",
    "sg:postcode":"03561",
    "sg:province":"NH",
    "sg:tags":[
        "development",
        "business"
    ],
    "wof:name":"Osborn Business Development",
    "wof:placetype":"venue"
},
  "geometry": {"coordinates":[-71.75019500000001,44.307984],"type":"Point"}
}