{
  "type": "Feature",
  "properties": {
    "addr:full":"31 Oriole Dr Bedford NH 03110",
    "addr:housenumber":"31",
    "addr:postcode":"03110",
    "addr:street":"Oriole Dr",
    "iso:country":"US",
    "sg:address":"31 Oriole Dr",
    "sg:city":"Bedford",
    "sg:classifiers":[
        {
            "category":"Professional",
            "subcategory":"Business Services",
            "type":"Services"
        }
    ],
    "sg:phone":"+1 603 472 2417",
    "sg:postcode":"03110",
    "sg:province":"NH",
    "wof:name":"Pjm Communications",
    "wof:placetype":"venue"
},
  "geometry": {"coordinates":[-71.570734,42.957754],"type":"Point"}
}