{
  "type": "Feature",
  "properties": {
    "addr:full":"242 Amherst St Nashua NH 03063",
    "addr:housenumber":"242",
    "addr:postcode":"03063",
    "addr:street":"Amherst St",
    "iso:country":"US",
    "sg:address":"242 Amherst St",
    "sg:city":"Nashua",
    "sg:classifiers":[
        {
            "category":"Autos & Motor Vehicles",
            "subcategory":"Fuel & Gas Station",
            "type":"Retail Goods"
        }
    ],
    "sg:phone":"+1 603 883 0405",
    "sg:postcode":"03063",
    "sg:province":"NH",
    "sg:tags":[
        "oil"
    ],
    "wof:name":"Sell's Mobil",
    "wof:placetype":"venue"
},
  "geometry": {"coordinates":[-71.496443,42.778146],"type":"Point"}
}