{
  "type": "Feature",
  "properties": {
    "addr:full":"7 Monroe Dr Hudson NH 03051",
    "addr:housenumber":"7",
    "addr:postcode":"03051",
    "addr:street":"Monroe Dr",
    "iso:country":"US",
    "sg:address":"7 Monroe Dr",
    "sg:city":"Hudson",
    "sg:classifiers":[
        {
            "category":"Retail",
            "subcategory":"Auto Repair",
            "type":"Services"
        }
    ],
    "sg:phone":"+1 603 886 0742",
    "sg:postcode":"03051",
    "sg:province":"NH",
    "sg:tags":[
        "wrecker"
    ],
    "wof:name":"R & J Towing",
    "wof:placetype":"venue"
},
  "geometry": {"coordinates":[-71.41875,42.776397],"type":"Point"}
}