{
  "type": "Feature",
  "properties": {
    "iso:country":"US",
    "sg:address":"49 E Pearl St",
    "sg:city":"Nashua",
    "sg:classifiers":[
        {
            "category":"Personal",
            "subcategory":"Beauty Salon",
            "type":"Services"
        }
    ],
    "sg:phone":"+1 603 886 0413",
    "sg:postcode":"03060",
    "sg:province":"NH",
    "sg:tags":[
        "shop"
    ],
    "wof:name":"Nail Fetish Inc",
    "wof:placetype":"venue"
},
  "geometry": {"coordinates":[-71.46503800000001,42.760206],"type":"Point"}
}