{
  "type": "Feature",
  "properties": {
    "iso:country":"US",
    "sg:address":"1465 Woodbury Ave",
    "sg:city":"Portsmouth",
    "sg:classifiers":[
        {
            "category":"Retail",
            "subcategory":"Auto Repair",
            "type":"Services"
        }
    ],
    "sg:phone":"+1 603 431 5106",
    "sg:postcode":"03801",
    "sg:province":"NH",
    "sg:tags":[
        "body",
        "automobile",
        "painting"
    ],
    "wof:name":"Enviro Paint Group",
    "wof:placetype":"venue"
},
  "geometry": {"coordinates":[-70.788541,43.086932],"type":"Point"}
}