{
  "type": "Feature",
  "properties": {
    "iso:country":"US",
    "sg:address":"12 Wasserman Hts",
    "sg:city":"Merrimack",
    "sg:classifiers":[
        {
            "category":"Communications",
            "type":"Services"
        }
    ],
    "sg:phone":"+1 603 882 6987",
    "sg:postcode":"03054",
    "sg:province":"NH",
    "wof:name":"Communication Dynamics",
    "wof:placetype":"venue"
},
  "geometry": {"coordinates":[-71.531629,42.824815],"type":"Point"}
}