{
  "type": "Feature",
  "properties": {
    "addr:full":"193 Mittersill Rd Franconia NH 03580",
    "addr:housenumber":"193",
    "addr:postcode":"03580",
    "addr:street":"Mittersill Rd",
    "iso:country":"US",
    "sg:address":"193 Mittersill Rd",
    "sg:city":"Franconia",
    "sg:classifiers":[
        {
            "category":"Organizations",
            "subcategory":"Community Association",
            "type":"Services"
        }
    ],
    "sg:phone":"+1 603 823 5511",
    "sg:postcode":"03580",
    "sg:province":"NH",
    "sg:tags":[
        "owner",
        "resort"
    ],
    "wof:name":"Barons Restaurant & Lounge",
    "wof:placetype":"venue"
},
  "geometry": {"coordinates":[-71.71203800000001,44.180805],"type":"Point"}
}