{
  "type": "Feature",
  "properties": {
    "iso:country":"US",
    "sg:address":"38 Hemlock St",
    "sg:city":"Londonderry",
    "sg:classifiers":[
        {
            "category":"Building & Trades",
            "subcategory":"Construction",
            "type":"Services"
        }
    ],
    "sg:phone":"+1 603 674 5679",
    "sg:postcode":"03053",
    "sg:province":"NH",
    "sg:tags":[
        "house"
    ],
    "wof:name":"Jafra Development LLC",
    "wof:placetype":"venue"
},
  "geometry": {"coordinates":[-71.33445399999999,42.846142],"type":"Point"}
}