{
  "type": "Feature",
  "properties": {
    "iso:country":"US",
    "sg:address":"49 Main St",
    "sg:city":"Plaistow",
    "sg:classifiers":[
        {
            "category":"Shopping",
            "subcategory":"Florist",
            "type":"Retail Goods"
        }
    ],
    "sg:phone":"+1 603 382 8036",
    "sg:postcode":"03865",
    "sg:province":"NH",
    "wof:name":"Maplewood Florist LTD",
    "wof:placetype":"venue"
},
  "geometry": {"coordinates":[-71.09454100000001,42.820069],"type":"Point"}
}