{
  "type": "Feature",
  "properties": {
    "iso:country":"US",
    "sg:address":"34 Manchester Rd",
    "sg:city":"Derry",
    "sg:classifiers":[
        {
            "category":"Insurance",
            "subcategory":"Insurance Agent",
            "type":"Services"
        }
    ],
    "sg:phone":"+1 603 432 9521",
    "sg:postcode":"03038",
    "sg:province":"NH",
    "wof:name":"State Farm Insurance",
    "wof:placetype":"venue"
},
  "geometry": {"coordinates":[-71.33786499999999,42.89914],"type":"Point"}
}