{
  "type": "Feature",
  "properties": {
    "addr:full":"28 Lincoln St Milford NH 03055",
    "addr:housenumber":"28",
    "addr:postcode":"03055",
    "addr:street":"Lincoln St",
    "iso:country":"US",
    "sg:address":"28 Lincoln St",
    "sg:city":"Milford",
    "sg:classifiers":[
        {
            "category":"Shopping",
            "subcategory":"Computers & Home Electronics",
            "type":"Retail Goods"
        }
    ],
    "sg:phone":"+1 603 673 6134",
    "sg:postcode":"03055",
    "sg:province":"NH",
    "sg:tags":[
        "publishing"
    ],
    "wof:name":"Distinctive Creations Ink",
    "wof:placetype":"venue"
},
  "geometry": {"coordinates":[-71.652021,42.832511],"type":"Point"}
}