{
  "type": "Feature",
  "properties": {
    "addr:full":"19 Rand Hill Rd Alton Bay NH 03810",
    "addr:housenumber":"19",
    "addr:postcode":"03810",
    "addr:street":"Rand Hill Rd",
    "iso:country":"US",
    "sg:address":"19 Rand Hill Rd",
    "sg:city":"Alton Bay",
    "sg:classifiers":[
        {
            "category":"Building & Trades",
            "subcategory":"Landscaping Services",
            "type":"Services"
        }
    ],
    "sg:phone":"+1 603 875 2711",
    "sg:postcode":"03810",
    "sg:province":"NH",
    "sg:tags":[
        "landscape",
        "contractor"
    ],
    "wof:name":"R3J Landscapes",
    "wof:placetype":"venue"
},
  "geometry": {"coordinates":[-71.24516199999999,43.472498],"type":"Point"}
}