{
  "type": "Feature",
  "properties": {
    "iso:country":"US",
    "sg:address":"128 Oak St",
    "sg:city":"Newport",
    "sg:classifiers":[
        {
            "category":"Retail",
            "subcategory":"Repair Shop",
            "type":"Services"
        }
    ],
    "sg:phone":"+1 603 863 5514",
    "sg:postcode":"03773",
    "sg:province":"NH",
    "sg:tags":[
        "welding"
    ],
    "wof:name":"G K Stetson Blacksmith",
    "wof:placetype":"venue"
},
  "geometry": {"coordinates":[-72.181961,43.37213],"type":"Point"}
}