{
  "type": "Feature",
  "properties": {
    "iso:country":"US",
    "sg:address":"33 Hoyt Rd",
    "sg:city":"Gilford",
    "sg:classifiers":[
        {
            "category":"Building & Trades",
            "subcategory":"Construction",
            "type":"Services"
        }
    ],
    "sg:phone":"+1 603 524 5956",
    "sg:postcode":"03249",
    "sg:province":"NH",
    "sg:tags":[
        "excavation",
        "contractor",
        "general"
    ],
    "wof:name":"P D LA Bonte & Sons Inc",
    "wof:placetype":"venue"
},
  "geometry": {"coordinates":[-71.41586,43.541558],"type":"Point"}
}