{
  "type": "Feature",
  "properties": {
    "iso:country":"US",
    "sg:address":"5 Broadway",
    "sg:city":"Alton Bay",
    "sg:classifiers":[
        {
            "category":"Travel",
            "subcategory":"Campground",
            "type":"Entertainment"
        }
    ],
    "sg:phone":"+1 603 875 6161",
    "sg:postcode":"03820",
    "sg:province":"NH",
    "sg:website":"www.abccc.org",
    "wof:name":"Alton Bay Christian Conf Ctr",
    "wof:placetype":"venue"
},
  "geometry": {"coordinates":[-70.87337599999999,43.199109],"type":"Point"}
}