{
  "type": "Feature",
  "properties": {
    "iso:country":"US",
    "sg:address":"101 Cadogan Way",
    "sg:city":"Nashua",
    "sg:classifiers":[
        {
            "category":"Professional",
            "subcategory":"Business Services",
            "type":"Services"
        },
        {
            "category":"Professional",
            "subcategory":"Management & Consulting",
            "type":"Services"
        }
    ],
    "sg:phone":"+1 603 888 7777",
    "sg:postcode":"03062",
    "sg:province":"NH",
    "sg:tags":[
        "conference",
        "consultant",
        "meeting"
    ],
    "wof:name":"Corporate Meeting Planners Inc",
    "wof:placetype":"venue"
},
  "geometry": {"coordinates":[-71.484419,42.708421],"type":"Point"}
}