{
  "type": "Feature",
  "properties": {
    "addr:full":"60 W Hollis St Nashua NH 03060",
    "addr:housenumber":"60",
    "addr:postcode":"03060",
    "addr:street":"W Hollis St",
    "iso:country":"US",
    "sg:address":"60 W Hollis St",
    "sg:city":"Nashua",
    "sg:classifiers":[
        {
            "category":"Restaurant",
            "type":"Food & Drink"
        }
    ],
    "sg:phone":"+1 603 577 5505",
    "sg:postcode":"03060",
    "sg:province":"NH",
    "wof:name":"Caribbean Fast Food",
    "wof:placetype":"venue"
},
  "geometry": {"coordinates":[-71.469222,42.756469],"type":"Point"}
}