{
  "type": "Feature",
  "properties": {
    "addr:full":"206 Concord Rd Peterborough NH 03458",
    "addr:housenumber":"206",
    "addr:postcode":"03458",
    "addr:street":"Concord Rd",
    "iso:country":"US",
    "sg:address":"206 Concord Rd",
    "sg:city":"Peterborough",
    "sg:classifiers":[
        {
            "category":"Shopping",
            "subcategory":"Used Merchandise",
            "type":"Retail Goods"
        },
        {
            "category":"Home & Garden",
            "subcategory":"Furniture",
            "type":"Retail Goods"
        }
    ],
    "sg:phone":"+1 603 924 9247",
    "sg:postcode":"03458",
    "sg:province":"NH",
    "sg:tags":[
        "shop",
        "consignment"
    ],
    "wof:name":"Rebecca's Consignments",
    "wof:placetype":"venue"
},
  "geometry": {"coordinates":[-71.937894,42.909362],"type":"Point"}
}