{
  "type": "Feature",
  "properties": {
    "iso:country":"US",
    "sg:address":"13 River St",
    "sg:city":"Greenville",
    "sg:classifiers":[
        {
            "category":"Organizations",
            "subcategory":"Community Association",
            "type":"Services"
        }
    ],
    "sg:phone":"+1 603 878 2895",
    "sg:postcode":"03048",
    "sg:province":"NH",
    "sg:tags":[
        "military"
    ],
    "wof:name":"American Legion",
    "wof:placetype":"venue"
},
  "geometry": {"coordinates":[-71.812467,42.766423],"type":"Point"}
}