{
  "type": "Feature",
  "properties": {
    "addr:full":"85 Daniel Webster Hwy Boscawen NH 03303",
    "addr:housenumber":"85",
    "addr:postcode":"03303",
    "addr:street":"Daniel Webster Hwy",
    "iso:country":"US",
    "sg:address":"85 Daniel Webster Hwy",
    "sg:city":"Boscawen",
    "sg:classifiers":[
        {
            "category":"Retail",
            "subcategory":"Auto Rental",
            "type":"Services"
        }
    ],
    "sg:phone":"+1 603 796 6097",
    "sg:postcode":"03303",
    "sg:province":"NH",
    "sg:tags":[
        "renting",
        "truck",
        "leasing"
    ],
    "wof:name":"U-Haul Co Independent Dealers",
    "wof:placetype":"venue"
},
  "geometry": {"coordinates":[-71.63781899999999,43.335701],"type":"Point"}
}