{
  "type": "Feature",
  "properties": {
    "addr:full":"48 Chemung Rd Meredith NH 03253",
    "addr:housenumber":"48",
    "addr:postcode":"03253",
    "addr:street":"Chemung Rd",
    "iso:country":"US",
    "sg:address":"48 Chemung Rd",
    "sg:city":"Meredith",
    "sg:classifiers":[
        {
            "category":"Utilities",
            "subcategory":"Refuse",
            "type":"Services"
        }
    ],
    "sg:phone":"+1 603 279 8084",
    "sg:postcode":"03253",
    "sg:province":"NH",
    "sg:tags":[
        "garbage",
        "collection"
    ],
    "wof:name":"C & B Refuse Disposal",
    "wof:placetype":"venue"
},
  "geometry": {"coordinates":[-71.544984,43.608467],"type":"Point"}
}