{
  "type": "Feature",
  "properties": {
    "iso:country":"US",
    "sg:address":"156 High St",
    "sg:city":"Somersworth",
    "sg:classifiers":[
        {
            "category":"Personal",
            "subcategory":"Beauty Salon",
            "type":"Services"
        }
    ],
    "sg:phone":"+1 603 692 5299",
    "sg:postcode":"03878",
    "sg:province":"ME",
    "wof:name":"Evolutions",
    "wof:placetype":"venue"
},
  "geometry": {"coordinates":[-70.86662099999999,43.25969],"type":"Point"}
}