{
  "type": "Feature",
  "properties": {
    "iso:country":"US",
    "sg:address":"62 Grove St",
    "sg:city":"Peterborough",
    "sg:classifiers":[
        {
            "category":"Manufacturing",
            "subcategory":"Tools & Machinery",
            "type":"Manufacturing & Wholesale Goods"
        }
    ],
    "sg:phone":"+1 603 630 0925",
    "sg:postcode":"03458",
    "sg:province":"NH",
    "sg:tags":[
        "control",
        "mfg"
    ],
    "wof:name":"Engineered Advantage",
    "wof:placetype":"venue"
},
  "geometry": {"coordinates":[-71.950473,42.873886],"type":"Point"}
}