{
  "type": "Feature",
  "properties": {
    "addr:full":"129 Mason Rd New Ipswich NH 03071",
    "addr:housenumber":"129",
    "addr:postcode":"03071",
    "addr:street":"Mason Rd",
    "iso:country":"US",
    "sg:address":"129 Mason Rd",
    "sg:city":"New Ipswich",
    "sg:classifiers":[
        {
            "category":"Building & Trades",
            "subcategory":"Construction",
            "type":"Services"
        }
    ],
    "sg:phone":"+1 603 878 1975",
    "sg:postcode":"03071",
    "sg:province":"NH",
    "sg:tags":[
        "house"
    ],
    "wof:name":"Matson Homes Inc",
    "wof:placetype":"venue"
},
  "geometry": {"coordinates":[-71.82181,42.718917],"type":"Point"}
}