{
  "type": "Feature",
  "properties": {
    "iso:country":"US",
    "sg:address":"158 Union Ave",
    "sg:city":"Laconia",
    "sg:classifiers":[
        {
            "category":"Real Estate",
            "subcategory":"Real Estate Agent",
            "type":"Services"
        }
    ],
    "sg:phone":"+1 603 524 6169",
    "sg:postcode":"03246",
    "sg:province":"NH",
    "wof:name":"Reed Elwell Realtor",
    "wof:placetype":"venue"
},
  "geometry": {"coordinates":[-71.466386,43.528955],"type":"Point"}
}