{
  "type": "Feature",
  "properties": {
    "iso:country":"US",
    "sg:address":"354 Haines Hill Rd",
    "sg:city":"Wolfeboro",
    "sg:classifiers":[
        {
            "category":"Shopping",
            "subcategory":"Computers & Home Electronics",
            "type":"Retail Goods"
        }
    ],
    "sg:phone":"+1 603 569 3275",
    "sg:postcode":"03894",
    "sg:province":"NH",
    "sg:tags":[
        "equipment",
        "dealer"
    ],
    "wof:name":"Backbone Communications",
    "wof:placetype":"venue"
},
  "geometry": {"coordinates":[-71.138015,43.651615],"type":"Point"}
}