{
  "type": "Feature",
  "properties": {
    "iso:country":"US",
    "sg:address":"10 Shaw St",
    "sg:city":"Lebanon",
    "sg:classifiers":[
        {
            "category":"Professional",
            "subcategory":"Management & Consulting",
            "type":"Services"
        }
    ],
    "sg:phone":"+1 603 448 1726",
    "sg:postcode":"03766",
    "sg:province":"NH",
    "sg:tags":[
        "business"
    ],
    "wof:name":"Geo Co",
    "wof:placetype":"venue"
},
  "geometry": {"coordinates":[-72.245165,43.642506],"type":"Point"}
}