{
  "type": "Feature",
  "properties": {
    "addr:full":"49 King Rd New Ipswich NH 03071",
    "addr:housenumber":"49",
    "addr:postcode":"03071",
    "addr:street":"King Rd",
    "iso:country":"US",
    "sg:address":"49 King Rd",
    "sg:city":"New Ipswich",
    "sg:classifiers":[
        {
            "category":"Health Services",
            "subcategory":"Health Practitioner",
            "type":"Services"
        }
    ],
    "sg:phone":"+1 603 878 4221",
    "sg:postcode":"03071",
    "sg:province":"NH",
    "sg:tags":[
        "psychologist"
    ],
    "wof:name":"Charles Mobayed",
    "wof:placetype":"venue"
},
  "geometry": {"coordinates":[-71.851246,42.756217],"type":"Point"}
}