{
  "type": "Feature",
  "properties": {
    "addr:full":"114 Christian Hill Rd Amherst NH 03031",
    "addr:housenumber":"114",
    "addr:postcode":"03031",
    "addr:street":"Christian Hill Rd",
    "iso:country":"US",
    "sg:address":"114 Christian Hill Rd",
    "sg:city":"Amherst",
    "sg:classifiers":[
        {
            "category":"Building & Trades",
            "subcategory":"Construction",
            "type":"Services"
        }
    ],
    "sg:phone":"+1 603 673 8616",
    "sg:postcode":"03031",
    "sg:province":"NH",
    "sg:tags":[
        "general",
        "contractor"
    ],
    "wof:name":"Restore-It",
    "wof:placetype":"venue"
},
  "geometry": {"coordinates":[-71.663211,42.853711],"type":"Point"}
}