{
  "type": "Feature",
  "properties": {
    "addr:full":"143 W Swanzey Rd East Swanzey NH 03446",
    "addr:housenumber":"143",
    "addr:postcode":"03446",
    "addr:street":"W Swanzey Rd",
    "iso:country":"US",
    "sg:address":"143 W Swanzey Rd",
    "sg:city":"East Swanzey",
    "sg:classifiers":[
        {
            "category":"Building & Trades",
            "subcategory":"Construction",
            "type":"Services"
        }
    ],
    "sg:phone":"+1 603 352 1433",
    "sg:postcode":"03446",
    "sg:province":"NH",
    "wof:name":"H Price",
    "wof:placetype":"venue"
},
  "geometry": {"coordinates":[-72.302188,42.903073],"type":"Point"}
}