{
  "type": "Feature",
  "properties": {
    "iso:country":"US",
    "sg:address":"13 Standish Way",
    "sg:city":"Amherst",
    "sg:classifiers":[
        {
            "category":"Shopping",
            "subcategory":"Crafts & Fabrics",
            "type":"Retail Goods"
        },
        {
            "category":"Professional",
            "subcategory":"Art Services",
            "type":"Services"
        }
    ],
    "sg:phone":"+1 603 672 6639",
    "sg:postcode":"03031",
    "sg:province":"NH",
    "sg:tags":[
        "punching",
        "design",
        "embroidery"
    ],
    "wof:name":"Sewgood Creations",
    "wof:placetype":"venue"
},
  "geometry": {"coordinates":[-71.607587,42.819924],"type":"Point"}
}