{
  "type": "Feature",
  "properties": {
    "addr:full":"3 Overlook Dr Amherst NH 03031",
    "addr:housenumber":"3",
    "addr:postcode":"03031",
    "addr:street":"Overlook Dr",
    "iso:country":"US",
    "sg:address":"3 Overlook Dr",
    "sg:city":"Amherst",
    "sg:classifiers":[
        {
            "category":"Building & Trades",
            "subcategory":"Construction",
            "type":"Services"
        }
    ],
    "sg:phone":"+1 603 673 8217",
    "sg:postcode":"03031",
    "sg:province":"NH",
    "sg:tags":[
        "general",
        "residential",
        "industrial",
        "commercial",
        "contractor"
    ],
    "wof:name":"Goguen Construction Company",
    "wof:placetype":"venue"
},
  "geometry": {"coordinates":[-71.60800399999999,42.822703],"type":"Point"}
}