{
  "type": "Feature",
  "properties": {
    "iso:country":"US",
    "sg:address":"4 High St",
    "sg:city":"Stratham",
    "sg:classifiers":[
        {
            "category":"Building & Trades",
            "subcategory":"Construction",
            "type":"Services"
        }
    ],
    "sg:phone":"+1 978 465 2508",
    "sg:postcode":"03885",
    "sg:province":"NH",
    "sg:tags":[
        "house"
    ],
    "wof:name":"Dupere Builders",
    "wof:placetype":"venue"
},
  "geometry": {"coordinates":[-70.89699,43.023626],"type":"Point"}
}