{
  "type": "Feature",
  "properties": {
    "addr:full":"102 Potanipo Hill Ln Brookline NH 03033",
    "addr:housenumber":"102",
    "addr:postcode":"03033",
    "addr:street":"Potanipo Hill Ln",
    "iso:country":"US",
    "sg:address":"102 Potanipo Hill Ln",
    "sg:city":"Brookline",
    "sg:classifiers":[
        {
            "category":"Professional",
            "subcategory":"Business Services",
            "type":"Services"
        }
    ],
    "sg:phone":"+1 603 672 0130",
    "sg:postcode":"03033",
    "sg:province":"NH",
    "wof:name":"Graphic Resource Systems",
    "wof:placetype":"venue"
},
  "geometry": {"coordinates":[-71.669619,42.733051],"type":"Point"}
}