{
  "type": "Feature",
  "properties": {
    "iso:country":"US",
    "sg:address":"20 Gates Rd",
    "sg:city":"Marlborough",
    "sg:classifiers":[
        {
            "category":"Professional",
            "subcategory":"Management & Consulting",
            "type":"Services"
        }
    ],
    "sg:phone":"+1 603 876 3854",
    "sg:postcode":"03455",
    "sg:province":"NH",
    "sg:tags":[
        "marketing"
    ],
    "wof:name":"Direct Source Marketing",
    "wof:placetype":"venue"
},
  "geometry": {"coordinates":[-72.18738999999999,42.908713],"type":"Point"}
}