{
  "type": "Feature",
  "properties": {
    "addr:full":"44 S Main St Rochester NH 03867",
    "addr:housenumber":"44",
    "addr:postcode":"03867",
    "addr:street":"S Main St",
    "iso:country":"US",
    "sg:address":"44 S Main St",
    "sg:city":"Rochester",
    "sg:classifiers":[
        {
            "category":"Shopping",
            "subcategory":"Musical Instruments",
            "type":"Retail Goods"
        }
    ],
    "sg:phone":"+1 603 335 0037",
    "sg:postcode":"03867",
    "sg:province":"NH",
    "wof:name":"Michael Charles Music",
    "wof:placetype":"venue"
},
  "geometry": {"coordinates":[-70.974987,43.303366],"type":"Point"}
}