{
  "type": "Feature",
  "properties": {
    "addr:full":"420 Island Pond Rd Manchester NH 03109",
    "addr:housenumber":"420",
    "addr:postcode":"03109",
    "addr:street":"Island Pond Rd",
    "iso:country":"US",
    "sg:address":"420 Island Pond Rd",
    "sg:city":"Manchester",
    "sg:classifiers":[
        {
            "category":"Education",
            "subcategory":"School",
            "type":"Public Place"
        }
    ],
    "sg:phone":"+1 603 668 0510",
    "sg:postcode":"03109",
    "sg:province":"NH",
    "sg:tags":[
        "catholic"
    ],
    "wof:name":"Holy Cross Kindergarten",
    "wof:placetype":"venue"
},
  "geometry": {"coordinates":[-71.41521899999999,42.971392],"type":"Point"}
}