{
  "type": "Feature",
  "properties": {
    "iso:country":"US",
    "sg:address":"58 Range Rd",
    "sg:city":"Windham",
    "sg:classifiers":[
        {
            "category":"Personal",
            "subcategory":"Beauty Salon",
            "type":"Services"
        }
    ],
    "sg:phone":"+1 603 890 9455",
    "sg:postcode":"03087",
    "sg:province":"NH",
    "sg:tags":[
        "manicuring"
    ],
    "wof:name":"Fantasian Nails",
    "wof:placetype":"venue"
},
  "geometry": {"coordinates":[-71.26205299999999,42.806636],"type":"Point"}
}