{
  "type": "Feature",
  "properties": {
    "iso:country":"US",
    "sg:address":"140 Edmond Ave",
    "sg:city":"Portsmouth",
    "sg:classifiers":[
        {
            "category":"Health Services",
            "subcategory":"Chiropractor",
            "type":"Services"
        }
    ],
    "sg:phone":"+1 603 436 0237",
    "sg:postcode":"03801",
    "sg:province":"NH",
    "wof:name":"Advanced Chiropractic Hlth Ctr",
    "wof:placetype":"venue"
},
  "geometry": {"coordinates":[-70.777063,43.079028],"type":"Point"}
}