{
  "type": "Feature",
  "properties": {
    "iso:country":"US",
    "sg:address":"424 W Main St",
    "sg:city":"Hillsborough",
    "sg:classifiers":[
        {
            "category":"Building & Trades",
            "subcategory":"Construction",
            "type":"Services"
        }
    ],
    "sg:phone":"+1 603 478 1000",
    "sg:postcode":"03244",
    "sg:province":"NH",
    "sg:tags":[
        "contractor"
    ],
    "wof:name":"Russell & Karen Whitney",
    "wof:placetype":"venue"
},
  "geometry": {"coordinates":[-71.93686099999999,43.115445],"type":"Point"}
}