{
  "type": "Feature",
  "properties": {
    "iso:country":"US",
    "sg:address":"1007 State Rte 106",
    "sg:city":"Belmont",
    "sg:classifiers":[
        {
            "category":"Professional",
            "subcategory":"Computer Services",
            "type":"Services"
        }
    ],
    "sg:phone":"+1 603 286 3857",
    "sg:postcode":"03220",
    "sg:province":"NH",
    "sg:tags":[
        "design",
        "system"
    ],
    "wof:name":"Pro Form Technology",
    "wof:placetype":"venue"
},
  "geometry": {"coordinates":[-71.469736,43.452811],"type":"Point"}
}