{
  "type": "Feature",
  "properties": {
    "iso:country":"US",
    "sg:address":"1838 Elm St",
    "sg:city":"Manchester",
    "sg:classifiers":[
        {
            "category":"Banks & Credit Unions",
            "subcategory":"Investment Brokerage",
            "type":"Services"
        }
    ],
    "sg:phone":"+1 603 669 5038",
    "sg:postcode":"03104",
    "sg:province":"NH",
    "sg:tags":[
        "consultant",
        "planning",
        "financial"
    ],
    "wof:name":"Lodestone Financial Planning",
    "wof:placetype":"venue"
},
  "geometry": {"coordinates":[-71.46536,43.005334],"type":"Point"}
}