{
  "type": "Feature",
  "properties": {
    "iso:country":"US",
    "sg:address":"34 Ridge Rd",
    "sg:city":"Deerfield",
    "sg:classifiers":[
        {
            "category":"Health Services",
            "subcategory":"Nursing And Care Facility",
            "type":"Services"
        }
    ],
    "sg:phone":"+1 603 463 7002",
    "sg:postcode":"03037",
    "sg:province":"NH",
    "sg:tags":[
        "home",
        "retirement",
        "community"
    ],
    "wof:name":"Inn At Deerfield",
    "wof:placetype":"venue"
},
  "geometry": {"coordinates":[-71.257063,43.128118],"type":"Point"}
}