{
  "type": "Feature",
  "properties": {
    "iso:country":"US",
    "sg:address":"58 Crown St",
    "sg:city":"Nashua",
    "sg:classifiers":[
        {
            "category":"Wholesale",
            "subcategory":"Machinery & Supplies",
            "type":"Manufacturing & Wholesale Goods"
        }
    ],
    "sg:phone":"+1 603 881 4963",
    "sg:postcode":"03060",
    "sg:province":"NH",
    "sg:tags":[
        "equipment",
        "welding"
    ],
    "wof:name":"Danfor Technical Gases",
    "wof:placetype":"venue"
},
  "geometry": {"coordinates":[-71.444799,42.762195],"type":"Point"}
}