{
  "type": "Feature",
  "properties": {
    "iso:country":"US",
    "sg:address":"194 Stark St",
    "sg:city":"Gilford",
    "sg:classifiers":[
        {
            "category":"Manufacturing",
            "subcategory":"Printing",
            "type":"Manufacturing & Wholesale Goods"
        }
    ],
    "sg:phone":"+1 603 528 4088",
    "sg:postcode":"03249",
    "sg:province":"NH",
    "sg:tags":[
        "printer"
    ],
    "wof:name":"Johnson Printing",
    "wof:placetype":"venue"
},
  "geometry": {"coordinates":[-71.447467,43.549532],"type":"Point"}
}