{
  "type": "Feature",
  "properties": {
    "iso:country":"US",
    "sg:address":"41 Simon St Ste 1C",
    "sg:city":"Nashua",
    "sg:classifiers":[
        {
            "category":"Manufacturing",
            "subcategory":"Electronics",
            "type":"Manufacturing & Wholesale Goods"
        }
    ],
    "sg:phone":"+1 603 886 6460",
    "sg:postcode":"03060",
    "sg:province":"NH",
    "sg:tags":[
        "printed",
        "circuit",
        "etched"
    ],
    "sg:website":"http://www.massdesign.com",
    "wof:name":"Mass Design, Inc.",
    "wof:placetype":"venue"
},
  "geometry": {"coordinates":[-71.49054,42.756351],"type":"Point"}
}