{
  "type": "Feature",
  "properties": {
    "iso:country":"US",
    "sg:address":"477 Lane Rd",
    "sg:city":"Chester",
    "sg:classifiers":[
        {
            "category":"Retail",
            "subcategory":"Animal Services",
            "type":"Services"
        }
    ],
    "sg:phone":"+1 603 483 2050",
    "sg:postcode":"03036",
    "sg:province":"NH",
    "wof:name":"Royale Cocker Kennel",
    "wof:placetype":"venue"
},
  "geometry": {"coordinates":[-71.254608,42.997819],"type":"Point"}
}