{
  "type": "Feature",
  "properties": {
    "addr:full":"27 Loop Rd Merrimack NH 03054",
    "addr:housenumber":"27",
    "addr:postcode":"03054",
    "addr:street":"Loop Rd",
    "iso:country":"US",
    "sg:address":"27 Loop Rd",
    "sg:city":"Merrimack",
    "sg:classifiers":[
        {
            "category":"Health Services",
            "subcategory":"Doctor",
            "type":"Services"
        }
    ],
    "sg:phone":"+1 603 424 1199",
    "sg:postcode":"03054",
    "sg:province":"NH",
    "sg:tags":[
        "dentist"
    ],
    "wof:name":"Braces Plus",
    "wof:placetype":"venue"
},
  "geometry": {"coordinates":[-71.49284,42.864412],"type":"Point"}
}