{
  "type": "Feature",
  "properties": {
    "addr:full":"188 Concord Rd Peterborough NH 03458",
    "addr:housenumber":"188",
    "addr:postcode":"03458",
    "addr:street":"Concord Rd",
    "iso:country":"US",
    "sg:address":"188 Concord Rd",
    "sg:city":"Peterborough",
    "sg:classifiers":[
        {
            "category":"Home & Garden",
            "subcategory":"Building Materials",
            "type":"Retail Goods"
        }
    ],
    "sg:phone":"+1 603 924 9436",
    "sg:postcode":"03458",
    "sg:province":"NH",
    "sg:website":"www.belletetes.com",
    "wof:name":"Belletetes Inc",
    "wof:placetype":"venue"
},
  "geometry": {"coordinates":[-71.93799300000001,42.91004],"type":"Point"}
}