{
  "type": "Feature",
  "properties": {
    "iso:country":"US",
    "sg:address":"395 Daniel Webster Hwy",
    "sg:city":"Merrimack",
    "sg:classifiers":[
        {
            "category":"Shopping",
            "subcategory":"Computers & Home Electronics",
            "type":"Retail Goods"
        }
    ],
    "sg:phone":"+1 603 424 3117",
    "sg:postcode":"03054",
    "sg:province":"NH",
    "sg:tags":[
        "parts",
        "supply"
    ],
    "sg:website":"www.cejcomputer.com",
    "wof:name":"CEJ Computer Business System",
    "wof:placetype":"venue"
},
  "geometry": {"coordinates":[-71.49135800000001,42.85616],"type":"Point"}
}