{
  "type": "Feature",
  "properties": {
    "iso:country":"US",
    "sg:address":"14 Maylane Dr",
    "sg:city":"Salem",
    "sg:classifiers":[
        {
            "category":"Building & Trades",
            "subcategory":"Construction",
            "type":"Services"
        }
    ],
    "sg:phone":"+1 603 458 1641",
    "sg:postcode":"03079",
    "sg:province":"NH",
    "sg:tags":[
        "contractor"
    ],
    "wof:name":"Quiton Masonry",
    "wof:placetype":"venue"
},
  "geometry": {"coordinates":[-71.262506,42.782081],"type":"Point"}
}