{
  "type": "Feature",
  "properties": {
    "addr:full":"38 Old Dover Rd Portsmouth NH 03801",
    "addr:housenumber":"38",
    "addr:postcode":"03801",
    "addr:street":"Old Dover Rd",
    "iso:country":"US",
    "sg:address":"38 Old Dover Rd",
    "sg:city":"Portsmouth",
    "sg:classifiers":[
        {
            "category":"Building & Trades",
            "subcategory":"Landscaping Services",
            "type":"Services"
        }
    ],
    "sg:phone":"+1 603 427 2425",
    "sg:postcode":"03801",
    "sg:province":"NH",
    "wof:name":"Maritime Ldscp & Design LLC",
    "wof:placetype":"venue"
},
  "geometry": {"coordinates":[-70.804641,43.100842],"type":"Point"}
}