{
  "type": "Feature",
  "properties": {
    "iso:country":"US",
    "sg:address":"123 River Rd",
    "sg:city":"Canaan",
    "sg:classifiers":[
        {
            "category":"Shopping",
            "type":"Retail Goods"
        }
    ],
    "sg:phone":"+1 603 523 8346",
    "sg:postcode":"03768",
    "sg:province":"NH",
    "sg:tags":[
        "product",
        "wood"
    ],
    "wof:name":"S & W Wildfire",
    "wof:placetype":"venue"
},
  "geometry": {"coordinates":[-72.182907,43.802094],"type":"Point"}
}