{
  "type": "Feature",
  "properties": {
    "iso:country":"US",
    "sg:address":"154 Mountain Rd",
    "sg:city":"Salisbury",
    "sg:classifiers":[
        {
            "category":"Wholesale",
            "subcategory":"Machinery & Supplies",
            "type":"Manufacturing & Wholesale Goods"
        }
    ],
    "sg:phone":"+1 603 648 2737",
    "sg:postcode":"03268",
    "sg:province":"NH",
    "sg:tags":[
        "instrument",
        "surveying"
    ],
    "wof:name":"Trimble Engineering & Constr",
    "wof:placetype":"venue"
},
  "geometry": {"coordinates":[-71.751878,43.393963],"type":"Point"}
}