{
  "type": "Feature",
  "properties": {
    "iso:country":"US",
    "sg:address":"15 Daniel St",
    "sg:city":"Portsmouth",
    "sg:classifiers":[
        {
            "category":"Shopping",
            "subcategory":"Clothing, Apparel, & Fashions",
            "type":"Retail Goods"
        }
    ],
    "sg:phone":"+1 603 766 0520",
    "sg:postcode":"03801",
    "sg:province":"NH",
    "sg:tags":[
        "item",
        "boutique"
    ],
    "wof:name":"Caprice Boutique & Gift Shop",
    "wof:placetype":"venue"
},
  "geometry": {"coordinates":[-70.756514,43.077271],"type":"Point"}
}