{
  "type": "Feature",
  "properties": {
    "addr:full":"350 State Rte 108 Somersworth ME 03878",
    "addr:housenumber":"350",
    "addr:postcode":"03878",
    "addr:street":"State Rte 108",
    "iso:country":"US",
    "sg:address":"350 State Rte 108",
    "sg:city":"Somersworth",
    "sg:classifiers":[
        {
            "category":"Professional",
            "subcategory":"Engineering",
            "type":"Services"
        }
    ],
    "sg:phone":"+1 603 692 0088",
    "sg:postcode":"03878",
    "sg:province":"ME",
    "wof:name":"S W Cole Engineering Inc",
    "wof:placetype":"venue"
},
  "geometry": {"coordinates":[-70.905608,43.263808],"type":"Point"}
}