{
  "type": "Feature",
  "properties": {
    "addr:full":"468 Central Ave Dover NH 03820",
    "addr:housenumber":"468",
    "addr:postcode":"03820",
    "addr:street":"Central Ave",
    "iso:country":"US",
    "sg:address":"468 Central Ave",
    "sg:city":"Dover",
    "sg:classifiers":[
        {
            "category":"Real Estate",
            "subcategory":"Real Estate Agent",
            "type":"Services"
        }
    ],
    "sg:phone":"+1 603 749 9860",
    "sg:postcode":"03820",
    "sg:province":"NH",
    "wof:name":"Atrio Properties LLC",
    "wof:placetype":"venue"
},
  "geometry": {"coordinates":[-70.874008,43.197744],"type":"Point"}
}