{
  "type": "Feature",
  "properties": {
    "addr:full":"8 Karen St Rochester NH 03867",
    "addr:housenumber":"8",
    "addr:postcode":"03867",
    "addr:street":"Karen St",
    "iso:country":"US",
    "sg:address":"8 Karen St",
    "sg:city":"Rochester",
    "sg:classifiers":[
        {
            "category":"Autos & Motor Vehicles",
            "subcategory":"Automobile Sales",
            "type":"Retail Goods"
        }
    ],
    "sg:phone":"+1 603 335 3400",
    "sg:postcode":"03867",
    "sg:province":"NH",
    "sg:tags":[
        "car",
        "dealer"
    ],
    "sg:website":"www.graniteford.com",
    "wof:name":"Granite Ford",
    "wof:placetype":"venue"
},
  "geometry": {"coordinates":[-70.949051,43.268456],"type":"Point"}
}