{
  "type": "Feature",
  "properties": {
    "iso:country":"US",
    "sg:address":"376 Whittier Hwy",
    "sg:city":"Moultonborough",
    "sg:classifiers":[
        {
            "category":"Recreation",
            "subcategory":"Marina",
            "type":"Entertainment"
        }
    ],
    "sg:phone":"+1 603 253 3848",
    "sg:postcode":"03254",
    "sg:province":"NH",
    "sg:tags":[
        "repairing",
        "boat"
    ],
    "wof:name":"Unique Boat Restoration",
    "wof:placetype":"venue"
},
  "geometry": {"coordinates":[-71.43874099999999,43.716332],"type":"Point"}
}