{
  "type": "Feature",
  "properties": {
    "iso:country":"US",
    "sg:address":"20 High St",
    "sg:city":"Portsmouth",
    "sg:classifiers":[
        {
            "category":"Restaurant",
            "type":"Food & Drink"
        }
    ],
    "sg:phone":"+1 603 436 0521",
    "sg:postcode":"03801",
    "sg:province":"NH",
    "sg:tags":[
        "eating"
    ],
    "wof:name":"Metro Restaurant The",
    "wof:placetype":"venue"
},
  "geometry": {"coordinates":[-70.758399,43.077232],"type":"Point"}
}