{
  "type": "Feature",
  "properties": {
    "iso:country":"US",
    "sg:address":"725 2nd St",
    "sg:city":"Manchester",
    "sg:classifiers":[
        {
            "category":"Autos & Motor Vehicles",
            "subcategory":"Automobile Sales",
            "type":"Retail Goods"
        }
    ],
    "sg:phone":"+1 603 296 1010",
    "sg:postcode":"03102",
    "sg:province":"NH",
    "sg:tags":[
        "car",
        "dealer"
    ],
    "wof:name":"Millennium Auto Sales",
    "wof:placetype":"venue"
},
  "geometry": {"coordinates":[-71.478098,42.970991],"type":"Point"}
}