{
  "type": "Feature",
  "properties": {
    "iso:country":"US",
    "sg:address":"10 Ashford Rd",
    "sg:city":"Atkinson",
    "sg:classifiers":[
        {
            "category":"Building & Trades",
            "subcategory":"Plumbing",
            "type":"Services"
        }
    ],
    "sg:phone":"+1 603 362 4876",
    "sg:postcode":"03841",
    "sg:province":"NH",
    "sg:tags":[
        "contractor"
    ],
    "wof:name":"Ashford Plumbing & Heating",
    "wof:placetype":"venue"
},
  "geometry": {"coordinates":[-71.218345,42.910678],"type":"Point"}
}