{
  "type": "Feature",
  "properties": {
    "iso:country":"US",
    "sg:address":"121 Allds St",
    "sg:city":"Nashua",
    "sg:classifiers":[
        {
            "category":"Organizations",
            "subcategory":"Religious Organization",
            "type":"Services"
        }
    ],
    "sg:phone":"+1 603 598 2622",
    "sg:postcode":"03060",
    "sg:province":"NH",
    "sg:tags":[
        "church"
    ],
    "wof:name":"Infant Jesus Parish Brazilian",
    "wof:placetype":"venue"
},
  "geometry": {"coordinates":[-71.452967,42.759724],"type":"Point"}
}