{
  "type": "Feature",
  "properties": {
    "iso:country":"US",
    "sg:address":"12 Depot St",
    "sg:city":"Peterborough",
    "sg:classifiers":[
        {
            "category":"Professional",
            "subcategory":"Business Services",
            "type":"Services"
        }
    ],
    "sg:phone":"+1 603 563 9272",
    "sg:postcode":"03458",
    "sg:province":"NH",
    "wof:name":"Earthsound Studio",
    "wof:placetype":"venue"
},
  "geometry": {"coordinates":[-71.949287,42.877422],"type":"Point"}
}