{
  "type": "Feature",
  "properties": {
    "addr:full":"40 Magnolia Rd Manchester NH 03104",
    "addr:housenumber":"40",
    "addr:postcode":"03104",
    "addr:street":"Magnolia Rd",
    "iso:country":"US",
    "sg:address":"40 Magnolia Rd",
    "sg:city":"Manchester",
    "sg:classifiers":[
        {
            "category":"Building & Trades",
            "subcategory":"Construction",
            "type":"Services"
        }
    ],
    "sg:phone":"+1 603 668 2830",
    "sg:postcode":"03104",
    "sg:province":"NH",
    "sg:tags":[
        "painting",
        "painter",
        "contractor"
    ],
    "wof:name":"Decorative Concepts Inc",
    "wof:placetype":"venue"
},
  "geometry": {"coordinates":[-71.46359099999999,43.02537],"type":"Point"}
}