{
  "type": "Feature",
  "properties": {
    "iso:country":"US",
    "sg:address":"1260 Battle St",
    "sg:city":"Webster",
    "sg:classifiers":[
        {
            "category":"Wholesale",
            "subcategory":"Hardware",
            "type":"Manufacturing & Wholesale Goods"
        }
    ],
    "sg:phone":"+1 603 648 2121",
    "sg:postcode":"03303",
    "sg:province":"NH",
    "sg:tags":[
        "furnace"
    ],
    "sg:website":"www.mellencompany.com",
    "wof:name":"Mellen Co Inc",
    "wof:placetype":"venue"
},
  "geometry": {"coordinates":[-71.726212,43.343235],"type":"Point"}
}