{
  "type": "Feature",
  "properties": {
    "iso:country":"US",
    "sg:address":"14 Eayers Pond Rd",
    "sg:city":"Hudson",
    "sg:classifiers":[
        {
            "category":"Home & Garden",
            "subcategory":"Building Materials",
            "type":"Retail Goods"
        },
        {
            "category":"Building & Trades",
            "subcategory":"Construction",
            "type":"Services"
        }
    ],
    "sg:phone":"+1 603 880 5094",
    "sg:postcode":"03051",
    "sg:province":"NH",
    "sg:tags":[
        "windows",
        "house"
    ],
    "wof:name":"Lenzis Home Improvements",
    "wof:placetype":"venue"
},
  "geometry": {"coordinates":[-71.41624899999999,42.708121],"type":"Point"}
}