{
  "type": "Feature",
  "properties": {
    "addr:full":"223 Derry Rd Hudson NH 03051",
    "addr:housenumber":"223",
    "addr:postcode":"03051",
    "addr:street":"Derry Rd",
    "iso:country":"US",
    "sg:address":"223 Derry Rd",
    "sg:city":"Hudson",
    "sg:classifiers":[
        {
            "category":"Building & Trades",
            "subcategory":"Construction",
            "type":"Services"
        }
    ],
    "sg:phone":"+1 603 882 2986",
    "sg:postcode":"03051",
    "sg:province":"NH",
    "sg:tags":[
        "excavation",
        "contractor"
    ],
    "wof:name":"Dan Dubowik Excavation &",
    "wof:placetype":"venue"
},
  "geometry": {"coordinates":[-71.433161,42.79926],"type":"Point"}
}