{
  "type": "Feature",
  "properties": {
    "iso:country":"US",
    "sg:address":"579 Daniel Webster Hwy",
    "sg:city":"Merrimack",
    "sg:classifiers":[
        {
            "category":"Professional",
            "type":"Services"
        }
    ],
    "sg:phone":"+1 603 429 1426",
    "sg:postcode":"03054",
    "sg:province":"NH",
    "sg:tags":[
        "establishment"
    ],
    "wof:name":"Professional Firefighters",
    "wof:placetype":"venue"
},
  "geometry": {"coordinates":[-71.480867,42.880437],"type":"Point"}
}