{
  "type": "Feature",
  "properties": {
    "iso:country":"US",
    "sg:address":"75 Lafayette Rd",
    "sg:city":"Hampton",
    "sg:classifiers":[
        {
            "category":"Home & Garden",
            "subcategory":"Furniture",
            "type":"Retail Goods"
        }
    ],
    "sg:phone":"+1 603 929 0682",
    "sg:postcode":"03842",
    "sg:province":"NH",
    "wof:name":"New Traditions",
    "wof:placetype":"venue"
},
  "geometry": {"coordinates":[-70.85104800000001,42.925884],"type":"Point"}
}