{
  "type": "Feature",
  "properties": {
    "iso:country":"US",
    "sg:address":"173 State Rte 28",
    "sg:city":"Derry",
    "sg:classifiers":[
        {
            "category":"Retail",
            "subcategory":"Repair Shop",
            "type":"Services"
        }
    ],
    "sg:phone":"+1 603 216 1541",
    "sg:postcode":"03038",
    "sg:province":"NH",
    "wof:name":"Best Qualified Cleaning Inc",
    "wof:placetype":"venue"
},
  "geometry": {"coordinates":[-71.27609099999999,42.852778],"type":"Point"}
}