{
  "type": "Feature",
  "properties": {
    "iso:country":"US",
    "sg:address":"207 Main St",
    "sg:city":"New London",
    "sg:classifiers":[
        {
            "category":"Wholesale",
            "subcategory":"Jewelry",
            "type":"Manufacturing & Wholesale Goods"
        }
    ],
    "sg:phone":"+1 603 526 8902",
    "sg:postcode":"03257",
    "sg:province":"NH",
    "sg:tags":[
        "stone"
    ],
    "wof:name":"Vessels & Jewels",
    "wof:placetype":"venue"
},
  "geometry": {"coordinates":[-71.990335,43.418316],"type":"Point"}
}