{
  "type": "Feature",
  "properties": {
    "iso:country":"US",
    "sg:address":"5 Raymond St",
    "sg:city":"Nashua",
    "sg:classifiers":[
        {
            "category":"Organizations",
            "subcategory":"Religious Organization",
            "type":"Services"
        }
    ],
    "sg:phone":"+1 603 883 9844",
    "sg:postcode":"03064",
    "sg:province":"NH",
    "wof:name":"Temple Beth Abraham Religious",
    "wof:placetype":"venue"
},
  "geometry": {"coordinates":[-71.46201600000001,42.771541],"type":"Point"}
}