{
  "type": "Feature",
  "properties": {
    "iso:country":"US",
    "sg:address":"523 Abbot Hill Rd",
    "sg:city":"Wilton",
    "sg:classifiers":[
        {
            "category":"Professional",
            "type":"Services"
        }
    ],
    "sg:phone":"+1 603 654 5292",
    "sg:postcode":"03086",
    "sg:province":"NH",
    "sg:tags":[
        "establishment"
    ],
    "wof:name":"C L Guild Co",
    "wof:placetype":"venue"
},
  "geometry": {"coordinates":[-71.74657999999999,42.80855],"type":"Point"}
}