{
  "type": "Feature",
  "properties": {
    "iso:country":"US",
    "sg:address":"16 Richardson St",
    "sg:city":"Rochester",
    "sg:classifiers":[
        {
            "category":"Home & Garden",
            "subcategory":"Garden Supply",
            "type":"Retail Goods"
        }
    ],
    "sg:phone":"+1 603 332 8412",
    "sg:postcode":"03867",
    "sg:province":"NH",
    "sg:tags":[
        "repair",
        "lawn",
        "mower"
    ],
    "wof:name":"Tom's Fixit Shop",
    "wof:placetype":"venue"
},
  "geometry": {"coordinates":[-70.965262,43.297258],"type":"Point"}
}