{
  "type": "Feature",
  "properties": {
    "iso:country":"US",
    "sg:address":"583 Beacon St",
    "sg:city":"Manchester",
    "sg:classifiers":[
        {
            "category":"Education",
            "subcategory":"Vocational School",
            "type":"Public Place"
        }
    ],
    "sg:phone":"+1 603 436 7324",
    "sg:postcode":"03104",
    "sg:province":"NH",
    "sg:tags":[
        "training",
        "computer"
    ],
    "wof:name":"Micro C Training Ctr",
    "wof:placetype":"venue"
},
  "geometry": {"coordinates":[-71.443038,42.992046],"type":"Point"}
}