{
  "type": "Feature",
  "properties": {
    "iso:country":"US",
    "sg:address":"58 Merrimack Rd",
    "sg:city":"Amherst",
    "sg:classifiers":[
        {
            "category":"Organizations",
            "subcategory":"Religious Organization",
            "type":"Services"
        }
    ],
    "sg:phone":"+1 603 673 8292",
    "sg:postcode":"03031",
    "sg:province":"NH",
    "wof:name":"Christ Church of Amherst",
    "wof:placetype":"venue"
},
  "geometry": {"coordinates":[-71.621982,42.83716],"type":"Point"}
}