{
  "type": "Feature",
  "properties": {
    "iso:country":"US",
    "sg:address":"28 S Main St",
    "sg:city":"Derry",
    "sg:classifiers":[
        {
            "category":"Education",
            "subcategory":"School",
            "type":"Public Place"
        }
    ],
    "sg:phone":"+1 603 432 1233",
    "sg:postcode":"03038",
    "sg:province":"NH",
    "sg:tags":[
        "elementary"
    ],
    "sg:website":"http://www.derry.k12.nh.us",
    "wof:name":"Derry Village Elementry School",
    "wof:placetype":"venue"
},
  "geometry": {"coordinates":[-71.306839,42.885551],"type":"Point"}
}