{
  "type": "Feature",
  "properties": {
    "iso:country":"US",
    "sg:address":"19 Moonlight Rose Ln",
    "sg:city":"Bedford",
    "sg:classifiers":[
        {
            "category":"Manufacturing",
            "subcategory":"Food",
            "type":"Manufacturing & Wholesale Goods"
        }
    ],
    "sg:phone":"+1 603 641 6339",
    "sg:postcode":"03110",
    "sg:province":"NH",
    "sg:tags":[
        "mfg"
    ],
    "wof:name":"Richard R Jennings",
    "wof:placetype":"venue"
},
  "geometry": {"coordinates":[-71.494332,42.975256],"type":"Point"}
}