{
  "type": "Feature",
  "properties": {
    "addr:full":"40 Main St Pittsfield NH 03263",
    "addr:housenumber":"40",
    "addr:postcode":"03263",
    "addr:street":"Main St",
    "iso:country":"US",
    "sg:address":"40 Main St",
    "sg:city":"Pittsfield",
    "sg:classifiers":[
        {
            "category":"Shopping",
            "subcategory":"Used Merchandise",
            "type":"Retail Goods"
        }
    ],
    "sg:phone":"+1 603 435 5343",
    "sg:postcode":"03263",
    "sg:province":"NH",
    "sg:tags":[
        "furniture"
    ],
    "wof:name":"Pittsfield Used Furniture",
    "wof:placetype":"venue"
},
  "geometry": {"coordinates":[-71.32769399999999,43.304918],"type":"Point"}
}