{
  "type": "Feature",
  "properties": {
    "addr:full":"36 Oyster River Rd Durham NH 03824",
    "addr:housenumber":"36",
    "addr:postcode":"03824",
    "addr:street":"Oyster River Rd",
    "iso:country":"US",
    "sg:address":"36 Oyster River Rd",
    "sg:city":"Durham",
    "sg:classifiers":[
        {
            "category":"Professional",
            "subcategory":"Business Services",
            "type":"Services"
        }
    ],
    "sg:phone":"+1 603 868 9658",
    "sg:postcode":"03824",
    "sg:province":"NH",
    "sg:tags":[
        "interior",
        "consultant",
        "design",
        "decorator"
    ],
    "wof:name":"Annette Tischler Design",
    "wof:placetype":"venue"
},
  "geometry": {"coordinates":[-70.92911599999999,43.127747],"type":"Point"}
}