{
  "type": "Feature",
  "properties": {
    "addr:full":"500 Lafayette Rd Hampton NH 03842",
    "addr:housenumber":"500",
    "addr:postcode":"03842",
    "iso:country":"US",
    "sg:address":"500 Lafayette Rd",
    "sg:city":"Hampton",
    "sg:classifiers":[
        {
            "category":"Shopping",
            "subcategory":"Computers & Home Electronics",
            "type":"Retail Goods"
        }
    ],
    "sg:phone":"+1 603 926 9696",
    "sg:postcode":"03842",
    "sg:province":"NH",
    "sg:tags":[
        "software"
    ],
    "sg:website":"www.lillysoftware.com",
    "wof:name":"Infor Global Solutions",
    "wof:placetype":"venue"
},
  "geometry": {"coordinates":[-70.836618,42.943403],"type":"Point"}
}