{
  "type": "Feature",
  "properties": {
    "iso:country":"US",
    "sg:address":"1037 Lilac Ln",
    "sg:city":"Dover",
    "sg:classifiers":[
        {
            "category":"Building & Trades",
            "subcategory":"Construction",
            "type":"Services"
        }
    ],
    "sg:phone":"+1 603 749 6687",
    "sg:postcode":"03820",
    "sg:province":"NH",
    "sg:tags":[
        "residential"
    ],
    "wof:name":"Building Contractor",
    "wof:placetype":"venue"
},
  "geometry": {"coordinates":[-70.90030899999999,43.177718],"type":"Point"}
}