{
  "type": "Feature",
  "properties": {
    "iso:country":"US",
    "sg:address":"569 Concord Stage Rd",
    "sg:city":"Weare",
    "sg:classifiers":[
        {
            "category":"Freight",
            "type":"Transportation"
        }
    ],
    "sg:phone":"+1 603 529 4433",
    "sg:postcode":"03281",
    "sg:province":"NH",
    "sg:tags":[
        "commercial",
        "storage"
    ],
    "wof:name":"Look N2 Store Self Storage",
    "wof:placetype":"venue"
},
  "geometry": {"coordinates":[-71.713887,43.134908],"type":"Point"}
}