{
  "type": "Feature",
  "properties": {
    "iso:country":"US",
    "sg:address":"36 Granite St",
    "sg:city":"Allenstown",
    "sg:classifiers":[
        {
            "category":"Building & Trades",
            "subcategory":"Construction",
            "type":"Services"
        }
    ],
    "sg:phone":"+1 603 485 5460",
    "sg:postcode":"03275",
    "sg:province":"NH",
    "sg:tags":[
        "marking",
        "maintenance",
        "parking"
    ],
    "wof:name":"Highway Dept",
    "wof:placetype":"venue"
},
  "geometry": {"coordinates":[-71.449484,43.124573],"type":"Point"}
}