{
  "type": "Feature",
  "properties": {
    "addr:full":"777 Union St Manchester NH 03104",
    "addr:housenumber":"777",
    "addr:postcode":"03104",
    "addr:street":"Union St",
    "iso:country":"US",
    "sg:address":"777 Union St",
    "sg:city":"Manchester",
    "sg:phone":"+1 603 627 4645",
    "sg:postcode":"03104",
    "sg:province":"NH",
    "sg:tags":[
        "oil"
    ],
    "wof:name":"Absco Oil",
    "wof:placetype":"venue"
},
  "geometry": {"coordinates":[-71.45893599999999,43.00216],"type":"Point"}
}