{
  "type": "Feature",
  "properties": {
    "iso:country":"US",
    "sg:address":"7 Fullam Cir",
    "sg:city":"Suncook",
    "sg:classifiers":[
        {
            "category":"Building & Trades",
            "subcategory":"Cleaning & Sanitation",
            "type":"Services"
        }
    ],
    "sg:phone":"+1 603 210 1385",
    "sg:postcode":"03275",
    "sg:province":"NH",
    "sg:tags":[
        "maintenance"
    ],
    "wof:name":"Portuguese Cleaning Service",
    "wof:placetype":"venue"
},
  "geometry": {"coordinates":[-71.42425900000001,43.11722],"type":"Point"}
}