{
  "type": "Feature",
  "properties": {
    "addr:full":"8 Perrier Dr Belmont NH 03220",
    "addr:housenumber":"8",
    "addr:postcode":"03220",
    "addr:street":"Perrier Dr",
    "iso:country":"US",
    "sg:address":"8 Perrier Dr",
    "sg:city":"Belmont",
    "sg:classifiers":[
        {
            "category":"Building & Trades",
            "subcategory":"Construction",
            "type":"Services"
        }
    ],
    "sg:phone":"+1 603 528 4456",
    "sg:postcode":"03220",
    "sg:province":"NH",
    "sg:tags":[
        "masonry",
        "contractor"
    ],
    "wof:name":"Stone Mountain Masonry Inc",
    "wof:placetype":"venue"
},
  "geometry": {"coordinates":[-71.438412,43.459626],"type":"Point"}
}