{
  "type": "Feature",
  "properties": {
    "iso:country":"US",
    "sg:address":"286 Lane Rd",
    "sg:city":"Chester",
    "sg:classifiers":[
        {
            "category":"Cinema",
            "subcategory":"Movie Rental",
            "type":"Entertainment"
        }
    ],
    "sg:phone":"+1 603 887 6945",
    "sg:postcode":"03036",
    "sg:province":"NH",
    "sg:tags":[
        "motion",
        "video",
        "television",
        "station",
        "tape"
    ],
    "wof:name":"Mesa Video",
    "wof:placetype":"venue"
},
  "geometry": {"coordinates":[-71.238045,42.994761],"type":"Point"}
}