{
  "type": "Feature",
  "properties": {
    "iso:country":"US",
    "sg:address":"6 Sand Hill Rd",
    "sg:city":"Hudson",
    "sg:classifiers":[
        {
            "category":"Manufacturing",
            "subcategory":"Tools & Machinery",
            "type":"Manufacturing & Wholesale Goods"
        }
    ],
    "sg:phone":"+1 603 595 8954",
    "sg:postcode":"03051",
    "sg:province":"NH",
    "sg:tags":[
        "industrial",
        "mfg"
    ],
    "wof:name":"Swinimer Machine Shop",
    "wof:placetype":"venue"
},
  "geometry": {"coordinates":[-71.409609,42.71061],"type":"Point"}
}