{
  "type": "Feature",
  "properties": {
    "addr:full":"120 Haverhill Rd Windham NH 03087",
    "addr:housenumber":"120",
    "addr:postcode":"03087",
    "addr:street":"Haverhill Rd",
    "iso:country":"US",
    "sg:address":"120 Haverhill Rd",
    "sg:city":"Windham",
    "sg:classifiers":[
        {
            "category":"Retail",
            "subcategory":"Auto Repair",
            "type":"Services"
        }
    ],
    "sg:phone":"+1 603 598 2511",
    "sg:postcode":"03087",
    "sg:province":"NH",
    "sg:tags":[
        "automotive",
        "wrecker"
    ],
    "wof:name":"Bauchman's Towing Inc",
    "wof:placetype":"venue"
},
  "geometry": {"coordinates":[-71.336229,42.805872],"type":"Point"}
}