{
  "type": "Feature",
  "properties": {
    "addr:full":"55 Congress St Portsmouth NH 03801",
    "addr:housenumber":"55",
    "addr:postcode":"03801",
    "addr:street":"Congress St",
    "iso:country":"US",
    "sg:address":"55 Congress St",
    "sg:city":"Portsmouth",
    "sg:classifiers":[
        {
            "category":"Building & Trades",
            "subcategory":"Plumbing",
            "type":"Services"
        }
    ],
    "sg:phone":"+1 603 430 8666",
    "sg:postcode":"03801",
    "sg:province":"NH",
    "sg:tags":[
        "plumbing",
        "contractor"
    ],
    "wof:name":"Port City Plumbing & Heating",
    "wof:placetype":"venue"
},
  "geometry": {"coordinates":[-70.758258,43.07692],"type":"Point"}
}