{
  "type": "Feature",
  "properties": {
    "iso:country":"US",
    "sg:address":"11 Shaker Rd",
    "sg:city":"Concord",
    "sg:classifiers":[
        {
            "category":"Home & Garden",
            "subcategory":"Carpets & Floor Coverings",
            "type":"Retail Goods"
        }
    ],
    "sg:phone":"+1 603 783 4684",
    "sg:postcode":"03301",
    "sg:province":"NH",
    "sg:tags":[
        "laying",
        "contractor"
    ],
    "wof:name":"J JS Carpets",
    "wof:placetype":"venue"
},
  "geometry": {"coordinates":[-71.53664000000001,43.243296],"type":"Point"}
}