{
  "type": "Feature",
  "properties": {
    "addr:full":"67 Smith Corner Rd Newton NH 03858",
    "addr:housenumber":"67",
    "addr:postcode":"03858",
    "addr:street":"Smith Corner Rd",
    "iso:country":"US",
    "sg:address":"67 Smith Corner Rd",
    "sg:city":"Newton",
    "sg:classifiers":[
        {
            "category":"Communications",
            "type":"Services"
        },
        {
            "category":"Shopping",
            "subcategory":"Computers & Home Electronics",
            "type":"Retail Goods"
        }
    ],
    "sg:phone":"+1 603 382 1336",
    "sg:postcode":"03858",
    "sg:province":"NH",
    "sg:tags":[
        "sound",
        "television",
        "system",
        "equipment",
        "radio",
        "store"
    ],
    "wof:name":"Advance Projector & Home Theater Concepts",
    "wof:placetype":"venue"
},
  "geometry": {"coordinates":[-71.07034400000001,42.845589],"type":"Point"}
}