{
  "type": "Feature",
  "properties": {
    "iso:country":"US",
    "sg:address":"260 Cottage St",
    "sg:city":"Littleton",
    "sg:classifiers":[
        {
            "category":"Professional",
            "subcategory":"Lawyer & Legal Services",
            "type":"Services"
        }
    ],
    "sg:phone":"+1 603 444 0216",
    "sg:postcode":"03561",
    "sg:province":"NH",
    "sg:tags":[
        "attorney"
    ],
    "wof:name":"Downs Rachlin & Martin",
    "wof:placetype":"venue"
},
  "geometry": {"coordinates":[-71.768895,44.293205],"type":"Point"}
}