{
  "type": "Feature",
  "properties": {
    "iso:country":"US",
    "sg:address":"74 Fisherville Rd",
    "sg:city":"Concord",
    "sg:classifiers":[
        {
            "category":"Restaurant",
            "type":"Food & Drink"
        }
    ],
    "sg:phone":"+1 603 228 0579",
    "sg:postcode":"03303",
    "sg:province":"NH",
    "sg:tags":[
        "stand"
    ],
    "sg:website":"www.summerfreeze.com",
    "wof:name":"Summer Freeze",
    "wof:placetype":"venue"
},
  "geometry": {"coordinates":[-71.577051,43.255078],"type":"Point"}
}