{
  "type": "Feature",
  "properties": {
    "iso:country":"US",
    "sg:address":"104 State Rte 132",
    "sg:city":"New Hampton",
    "sg:classifiers":[
        {
            "category":"Manufacturing",
            "subcategory":"Tools & Machinery",
            "type":"Manufacturing & Wholesale Goods"
        }
    ],
    "sg:phone":"+1 603 744 3736",
    "sg:postcode":"03256",
    "sg:province":"NH",
    "sg:tags":[
        "machine",
        "shop"
    ],
    "wof:name":"Alan T Seeler Inc",
    "wof:placetype":"venue"
},
  "geometry": {"coordinates":[-71.64330200000001,43.61225],"type":"Point"}
}