{
  "type": "Feature",
  "properties": {
    "iso:country":"US",
    "sg:address":"136 Buckminster Way",
    "sg:city":"Portsmouth",
    "sg:classifiers":[
        {
            "category":"Personal",
            "type":"Services"
        }
    ],
    "sg:phone":"+1 603 234 8431",
    "sg:postcode":"03801",
    "sg:province":"NH",
    "wof:name":"Simcha Therapies Inc",
    "wof:placetype":"venue"
},
  "geometry": {"coordinates":[-70.808978,43.037837],"type":"Point"}
}