{
  "type": "Feature",
  "properties": {
    "iso:country":"US",
    "sg:address":"37 Mills Rd",
    "sg:city":"Lebanon",
    "sg:classifiers":[
        {
            "category":"Home & Garden",
            "subcategory":"Garden Supply",
            "type":"Retail Goods"
        }
    ],
    "sg:phone":"+1 207 457 1182",
    "sg:postcode":"04027",
    "sg:province":"ME",
    "sg:tags":[
        "sprinkler"
    ],
    "wof:name":"Miranda Renovation & Landscape",
    "wof:placetype":"venue"
},
  "geometry": {"coordinates":[-70.904714,43.369252],"type":"Point"}
}