{
  "type": "Feature",
  "properties": {
    "addr:full":"54 Bow Bog Rd Bow NH 03304",
    "addr:housenumber":"54",
    "addr:postcode":"03304",
    "addr:street":"Bow Bog Rd",
    "iso:country":"US",
    "sg:address":"54 Bow Bog Rd",
    "sg:city":"Bow",
    "sg:classifiers":[
        {
            "category":"Personal",
            "subcategory":"Beauty Salon",
            "type":"Services"
        }
    ],
    "sg:phone":"+1 603 225 4190",
    "sg:postcode":"03304",
    "sg:province":"NH",
    "sg:tags":[
        "shop"
    ],
    "wof:name":"Mirror Image Hair Salon",
    "wof:placetype":"venue"
},
  "geometry": {"coordinates":[-71.526201,43.128242],"type":"Point"}
}