{
  "type": "Feature",
  "properties": {
    "addr:full":"9 Partridge Run Center Conway NH 03813",
    "addr:housenumber":"9",
    "addr:postcode":"03813",
    "addr:street":"Partridge Run Center",
    "iso:country":"US",
    "sg:address":"9 Partridge Run",
    "sg:city":"Center Conway",
    "sg:classifiers":[
        {
            "category":"Building & Trades",
            "subcategory":"Construction",
            "type":"Services"
        }
    ],
    "sg:phone":"+1 603 356 0706",
    "sg:postcode":"03813",
    "sg:province":"NH",
    "sg:tags":[
        "excavating",
        "contractor"
    ],
    "wof:name":"Whitaker & Sons Excavating",
    "wof:placetype":"venue"
},
  "geometry": {"coordinates":[-71.038597,44.002567],"type":"Point"}
}