{
  "type": "Feature",
  "properties": {
    "iso:country":"US",
    "sg:address":"415 Millstone Ave",
    "sg:city":"Manchester",
    "sg:classifiers":[
        {
            "category":"Building & Trades",
            "subcategory":"Landscaping Services",
            "type":"Services"
        }
    ],
    "sg:phone":"+1 603 641 0279",
    "sg:postcode":"03102",
    "sg:province":"NH",
    "wof:name":"Firehouse Lawn Care",
    "wof:placetype":"venue"
},
  "geometry": {"coordinates":[-71.489932,43.048289],"type":"Point"}
}