{
  "type": "Feature",
  "properties": {
    "iso:country":"US",
    "sg:address":"15 McGrath Rd",
    "sg:city":"Pelham",
    "sg:classifiers":[
        {
            "category":"Retail",
            "subcategory":"Repair Shop",
            "type":"Services"
        }
    ],
    "sg:phone":"+1 603 635 2898",
    "sg:postcode":"03076",
    "sg:province":"NH",
    "sg:tags":[
        "refinishing",
        "furniture"
    ],
    "wof:name":"A-1 Touch Up & Refinishing",
    "wof:placetype":"venue"
},
  "geometry": {"coordinates":[-71.368706,42.702615],"type":"Point"}
}