{
  "type": "Feature",
  "properties": {
    "iso:country":"US",
    "sg:address":"7 Cabot Rd",
    "sg:city":"Merrimack",
    "sg:classifiers":[
        {
            "category":"Banks & Credit Unions",
            "subcategory":"Bank",
            "type":"Services"
        }
    ],
    "sg:phone":"+1 603 424 1460",
    "sg:postcode":"03054",
    "sg:province":"NH",
    "sg:tags":[
        "mortgage"
    ],
    "wof:name":"NH Family Mortgage",
    "wof:placetype":"venue"
},
  "geometry": {"coordinates":[-71.48648900000001,42.889927],"type":"Point"}
}