{
  "type": "Feature",
  "properties": {
    "iso:country":"US",
    "sg:address":"215 Manchester St",
    "sg:city":"Manchester",
    "sg:classifiers":[
        {
            "category":"Retail",
            "subcategory":"Auto Repair",
            "type":"Services"
        }
    ],
    "sg:phone":"+1 603 623 3386",
    "sg:postcode":"03103",
    "sg:province":"NH",
    "sg:tags":[
        "general"
    ],
    "wof:name":"Blue Line Garage",
    "wof:placetype":"venue"
},
  "geometry": {"coordinates":[-71.458467,42.990124],"type":"Point"}
}