{
  "type": "Feature",
  "properties": {
    "iso:country":"US",
    "sg:address":"229 Main St",
    "sg:city":"Nashua",
    "sg:classifiers":[
        {
            "category":"Government",
            "subcategory":"Office",
            "type":"Public Place"
        }
    ],
    "sg:phone":"+1 603 589 3000",
    "sg:postcode":"03060",
    "sg:province":"NH",
    "sg:tags":[
        "city"
    ],
    "wof:name":"Nashua City Hall Information",
    "wof:placetype":"venue"
},
  "geometry": {"coordinates":[-71.464354,42.758694],"type":"Point"}
}