{
  "type": "Feature",
  "properties": {
    "addr:full":"15 Meade St Nashua NH 03064",
    "addr:housenumber":"15",
    "addr:postcode":"03064",
    "addr:street":"Meade St",
    "iso:country":"US",
    "sg:address":"15 Meade St",
    "sg:city":"Nashua",
    "sg:classifiers":[
        {
            "category":"Retail",
            "subcategory":"Laundry & Dry Cleaning",
            "type":"Services"
        }
    ],
    "sg:phone":"+1 603 881 5732",
    "sg:postcode":"03064",
    "sg:province":"NH",
    "wof:name":"General Carpet Care Systems",
    "wof:placetype":"venue"
},
  "geometry": {"coordinates":[-71.481883,42.778451],"type":"Point"}
}