{
  "type": "Feature",
  "properties": {
    "addr:full":"7 Karen Ln Sandown NH 03873",
    "addr:housenumber":"7",
    "addr:postcode":"03873",
    "addr:street":"Karen Ln",
    "iso:country":"US",
    "sg:address":"7 Karen Ln",
    "sg:city":"Sandown",
    "sg:classifiers":[
        {
            "category":"Building & Trades",
            "subcategory":"Construction",
            "type":"Services"
        }
    ],
    "sg:phone":"+1 603 887 6623",
    "sg:postcode":"03873",
    "sg:province":"NH",
    "sg:tags":[
        "house"
    ],
    "wof:name":"Ko Construction",
    "wof:placetype":"venue"
},
  "geometry": {"coordinates":[-71.215446,42.925614],"type":"Point"}
}