{
  "type": "Feature",
  "properties": {
    "addr:full":"23 Oak Ter Dover NH 03820",
    "addr:housenumber":"23",
    "addr:postcode":"03820",
    "addr:street":"Oak Ter",
    "iso:country":"US",
    "sg:address":"23 Oak Ter",
    "sg:city":"Dover",
    "sg:classifiers":[
        {
            "category":"Retail",
            "subcategory":"Portrait Studio",
            "type":"Services"
        }
    ],
    "sg:phone":"+1 603 749 6223",
    "sg:postcode":"03820",
    "sg:province":"NH",
    "sg:tags":[
        "photo",
        "photography",
        "commercial"
    ],
    "wof:name":"Don Stehle Photography",
    "wof:placetype":"venue"
},
  "geometry": {"coordinates":[-70.873361,43.20899],"type":"Point"}
}