{
  "type": "Feature",
  "properties": {
    "iso:country":"US",
    "sg:address":"3 Webb Pl",
    "sg:city":"Dover",
    "sg:classifiers":[
        {
            "category":"Real Estate",
            "subcategory":"Real Estate Services",
            "type":"Services"
        }
    ],
    "sg:phone":"+1 603 749 4947",
    "sg:postcode":"03820",
    "sg:province":"NH",
    "sg:tags":[
        "company",
        "title"
    ],
    "wof:name":"Summit Metropolitan Title",
    "wof:placetype":"venue"
},
  "geometry": {"coordinates":[-70.888209,43.221119],"type":"Point"}
}