{
  "type": "Feature",
  "properties": {
    "iso:country":"US",
    "sg:address":"232 Frontage Rd",
    "sg:city":"Manchester",
    "sg:classifiers":[
        {
            "category":"Real Estate",
            "subcategory":"Real Estate Agent",
            "type":"Services"
        }
    ],
    "sg:phone":"+1 603 623 9030",
    "sg:postcode":"03103",
    "sg:province":"NH",
    "wof:name":"Winterhill Realty LLC",
    "wof:placetype":"venue"
},
  "geometry": {"coordinates":[-71.447238,42.952541],"type":"Point"}
}