{
  "type": "Feature",
  "properties": {
    "addr:full":"37 Maple St Manchester NH 03103",
    "addr:housenumber":"37",
    "addr:postcode":"03103",
    "addr:street":"Maple St",
    "iso:country":"US",
    "sg:address":"37 Maple St",
    "sg:city":"Manchester",
    "sg:classifiers":[
        {
            "category":"Retail",
            "subcategory":"Car Wash",
            "type":"Services"
        }
    ],
    "sg:phone":"+1 603 624 0090",
    "sg:postcode":"03103",
    "sg:province":"NH",
    "sg:tags":[
        "carwash",
        "automobile",
        "detail",
        "clean"
    ],
    "wof:name":"J R's Auto Reconditioning",
    "wof:placetype":"venue"
},
  "geometry": {"coordinates":[-71.452934,42.974141],"type":"Point"}
}