{
  "type": "Feature",
  "properties": {
    "iso:country":"US",
    "sg:address":"141 River Rd",
    "sg:city":"Plainfield",
    "sg:classifiers":[
        {
            "category":"Food & Beverages",
            "subcategory":"Fruits & Vegetables",
            "type":"Retail Goods"
        }
    ],
    "sg:phone":"+1 603 298 8519",
    "sg:postcode":"03781",
    "sg:province":"NH",
    "sg:website":"www.riverviewnh.com",
    "wof:name":"Riverview Farm",
    "wof:placetype":"venue"
},
  "geometry": {"coordinates":[-72.34941600000001,43.586129],"type":"Point"}
}