{
  "type": "Feature",
  "properties": {
    "iso:country":"US",
    "sg:address":"92 Old Dover Rd",
    "sg:city":"Rochester",
    "sg:classifiers":[
        {
            "category":"Manufacturing",
            "subcategory":"Soap",
            "type":"Manufacturing & Wholesale Goods"
        }
    ],
    "sg:phone":"+1 603 332 1832",
    "sg:postcode":"03867",
    "sg:province":"NH",
    "sg:tags":[
        "detergent",
        "mfg"
    ],
    "wof:name":"Peek A Boo Soap",
    "wof:placetype":"venue"
},
  "geometry": {"coordinates":[-70.96789099999999,43.279792],"type":"Point"}
}