{
  "type": "Feature",
  "properties": {
    "iso:country":"US",
    "sg:address":"103 Tolles St",
    "sg:city":"Nashua",
    "sg:classifiers":[
        {
            "category":"Building & Trades",
            "subcategory":"Construction",
            "type":"Services"
        }
    ],
    "sg:phone":"+1 603 594 0646",
    "sg:postcode":"03064",
    "sg:province":"NH",
    "sg:tags":[
        "hanging",
        "contractor"
    ],
    "wof:name":"Home Painters",
    "wof:placetype":"venue"
},
  "geometry": {"coordinates":[-71.460075,42.766244],"type":"Point"}
}