{
  "type": "Feature",
  "properties": {
    "iso:country":"US",
    "sg:address":"21 Knights Hill Rd",
    "sg:city":"New London",
    "sg:classifiers":[
        {
            "category":"Building & Trades",
            "subcategory":"Construction",
            "type":"Services"
        }
    ],
    "sg:phone":"+1 603 526 4797",
    "sg:postcode":"03257",
    "sg:province":"NH",
    "sg:tags":[
        "carpentry",
        "contractor"
    ],
    "wof:name":"P Harris & Martha P David",
    "wof:placetype":"venue"
},
  "geometry": {"coordinates":[-71.991422,43.406864],"type":"Point"}
}