{
  "type": "Feature",
  "properties": {
    "iso:country":"US",
    "sg:address":"300 Keller St",
    "sg:city":"Manchester",
    "sg:classifiers":[
        {
            "category":"Restaurant",
            "type":"Food & Drink"
        }
    ],
    "sg:menulink":"http://www.allmenus.com/nh/manchester/129595-subway/menu/",
    "sg:phone":"+1 603 222 2269",
    "sg:postcode":"03103",
    "sg:province":"NH",
    "sg:tags":[
        "american",
        "sandwich"
    ],
    "wof:name":"Subway",
    "wof:placetype":"venue"
},
  "geometry": {"coordinates":[-71.439629,42.951382],"type":"Point"}
}