{
  "type": "Feature",
  "properties": {
    "iso:country":"US",
    "sg:address":"255 West St",
    "sg:city":"Keene",
    "sg:classifiers":[
        {
            "category":"Food & Beverages",
            "subcategory":"Bakery",
            "type":"Retail Goods"
        }
    ],
    "sg:phone":"+1 603 355 8255",
    "sg:postcode":"03431",
    "sg:province":"NH",
    "sg:tags":[
        "bagel",
        "deli"
    ],
    "wof:name":"Elm City Bagels",
    "wof:placetype":"venue"
},
  "geometry": {"coordinates":[-72.28704399999999,42.932466],"type":"Point"}
}