{
  "type": "Feature",
  "properties": {
    "iso:country":"US",
    "sg:address":"10 Learned St",
    "sg:city":"Nashua",
    "sg:classifiers":[
        {
            "category":"Restaurant",
            "type":"Food & Drink"
        }
    ],
    "sg:phone":"+1 603 883 9998",
    "sg:postcode":"03060",
    "sg:province":"NH",
    "wof:name":"Ninety Nine Restaurant & Pub",
    "wof:placetype":"venue"
},
  "geometry": {"coordinates":[-71.46122200000001,42.738347],"type":"Point"}
}