{
  "type": "Feature",
  "properties": {
    "iso:country":"US",
    "sg:address":"66 Tuttle Ln",
    "sg:city":"Greenland",
    "sg:classifiers":[
        {
            "category":"Personal",
            "subcategory":"Beauty Salon",
            "type":"Services"
        }
    ],
    "sg:phone":"+1 603 431 2424",
    "sg:postcode":"03840",
    "sg:province":"NH",
    "sg:tags":[
        "shop"
    ],
    "wof:name":"Mnae Tamers",
    "wof:placetype":"venue"
},
  "geometry": {"coordinates":[-70.842876,43.033413],"type":"Point"}
}