{
  "type": "Feature",
  "properties": {
    "iso:country":"US",
    "sg:address":"63 Highland St",
    "sg:city":"Plymouth",
    "sg:classifiers":[
        {
            "category":"Health Services",
            "subcategory":"Podiatrist",
            "type":"Services"
        }
    ],
    "sg:phone":"+1 603 536 4563",
    "sg:postcode":"03264",
    "sg:province":"NH",
    "wof:name":"James S Scales DPM",
    "wof:placetype":"venue"
},
  "geometry": {"coordinates":[-71.695562,43.758758],"type":"Point"}
}