{
  "type": "Feature",
  "properties": {
    "addr:full":"55 High St Nashua NH 03060",
    "addr:housenumber":"55",
    "addr:postcode":"03060",
    "addr:street":"High St",
    "iso:country":"US",
    "sg:address":"55 High St",
    "sg:city":"Nashua",
    "sg:classifiers":[
        {
            "category":"Shopping",
            "subcategory":"Used Merchandise",
            "type":"Retail Goods"
        }
    ],
    "sg:phone":"+1 603 880 3568",
    "sg:postcode":"03060",
    "sg:province":"NH",
    "sg:tags":[
        "shop",
        "thrift"
    ],
    "wof:name":"Salvation Army Thirft Store",
    "wof:placetype":"venue"
},
  "geometry": {"coordinates":[-71.46683299999999,42.760607],"type":"Point"}
}