{
  "type": "Feature",
  "properties": {
    "addr:full":"915 Central Ave Dover NH 03820",
    "addr:housenumber":"915",
    "addr:postcode":"03820",
    "addr:street":"Central Ave",
    "iso:country":"US",
    "sg:address":"915 Central Ave",
    "sg:city":"Dover",
    "sg:classifiers":[
        {
            "category":"Restaurant",
            "type":"Food & Drink"
        }
    ],
    "sg:menulink":"http://www.allmenus.com/nh/dover/73548-pizza-hut/menu/",
    "sg:phone":"+1 603 742 3949",
    "sg:postcode":"03820",
    "sg:province":"NH",
    "sg:tags":[
        "american",
        "pizza"
    ],
    "wof:name":"Pizza Hut",
    "wof:placetype":"venue"
},
  "geometry": {"coordinates":[-70.88542700000001,43.220188],"type":"Point"}
}