{
  "type": "Feature",
  "properties": {
    "iso:country":"US",
    "sg:address":"54 Pollard Rd",
    "sg:city":"Goffstown",
    "sg:classifiers":[
        {
            "category":"Building & Trades",
            "subcategory":"Plumbing",
            "type":"Services"
        }
    ],
    "sg:phone":"+1 603 497 4111",
    "sg:postcode":"03045",
    "sg:province":"NH",
    "sg:tags":[
        "contractor"
    ],
    "wof:name":"Gas Works",
    "wof:placetype":"venue"
},
  "geometry": {"coordinates":[-71.51452399999999,43.039349],"type":"Point"}
}