{
  "type": "Feature",
  "properties": {
    "iso:country":"US",
    "sg:address":"21 Blake Rd",
    "sg:city":"Epping",
    "sg:classifiers":[
        {
            "category":"Personal",
            "subcategory":"Beauty Salon",
            "type":"Services"
        }
    ],
    "sg:phone":"+1 603 679 5572",
    "sg:postcode":"03042",
    "sg:province":"NH",
    "sg:tags":[
        "shop"
    ],
    "wof:name":"Lamprey Waves",
    "wof:placetype":"venue"
},
  "geometry": {"coordinates":[-71.122457,43.041167],"type":"Point"}
}