{
  "type": "Feature",
  "properties": {
    "iso:country":"US",
    "sg:address":"9 Button Dr",
    "sg:city":"Londonderry",
    "sg:classifiers":[
        {
            "category":"Building & Trades",
            "subcategory":"Construction",
            "type":"Services"
        }
    ],
    "sg:phone":"+1 603 432 9370",
    "sg:postcode":"03053",
    "sg:province":"NH",
    "sg:tags":[
        "dry wall",
        "contractor"
    ],
    "wof:name":"B & B Drywall",
    "wof:placetype":"venue"
},
  "geometry": {"coordinates":[-71.35544299999999,42.850833],"type":"Point"}
}