{
  "type": "Feature",
  "properties": {
    "addr:full":"163 Sawmill Rd Hillsboro NH 03244",
    "addr:housenumber":"163",
    "addr:postcode":"03244",
    "addr:street":"Sawmill Rd",
    "iso:country":"US",
    "sg:address":"163 Sawmill Rd",
    "sg:city":"Hillsboro",
    "sg:classifiers":[
        {
            "category":"Building & Trades",
            "subcategory":"Construction",
            "type":"Services"
        }
    ],
    "sg:phone":"+1 603 478 2300",
    "sg:postcode":"03244",
    "sg:province":"NH",
    "sg:tags":[
        "general",
        "contractor"
    ],
    "wof:name":"G Browning Construction",
    "wof:placetype":"venue"
},
  "geometry": {"coordinates":[-71.93983,43.113055],"type":"Point"}
}