{
  "type": "Feature",
  "properties": {
    "iso:country":"US",
    "sg:address":"2 Auburn St",
    "sg:city":"Nashua",
    "sg:classifiers":[
        {
            "category":"Professional",
            "subcategory":"Lawyer & Legal Services",
            "type":"Services"
        }
    ],
    "sg:phone":"+1 603 889 4200",
    "sg:postcode":"03064",
    "sg:province":"NH",
    "sg:tags":[
        "attorney"
    ],
    "wof:name":"Mazerolle & Frasca",
    "wof:placetype":"venue"
},
  "geometry": {"coordinates":[-71.469706,42.765277],"type":"Point"}
}