{
  "type": "Feature",
  "properties": {
    "iso:country":"US",
    "sg:address":"44 Irene Dr",
    "sg:city":"Pelham",
    "sg:classifiers":[
        {
            "category":"Organizations",
            "subcategory":"Membership Organization",
            "type":"Services"
        }
    ],
    "sg:phone":"+1 603 635 1324",
    "sg:postcode":"03076",
    "sg:province":"NH",
    "wof:name":"Boaf",
    "wof:placetype":"venue"
},
  "geometry": {"coordinates":[-71.348142,42.705047],"type":"Point"}
}