{
  "type": "Feature",
  "properties": {
    "addr:full":"129 Market St Portsmouth NH 03801",
    "addr:housenumber":"129",
    "addr:postcode":"03801",
    "addr:street":"Market St",
    "iso:country":"US",
    "sg:address":"129 Market St",
    "sg:city":"Portsmouth",
    "sg:classifiers":[
        {
            "category":"Shopping",
            "subcategory":"Clothing, Apparel, & Fashions",
            "type":"Retail Goods"
        }
    ],
    "sg:phone":"+1 603 431 1663",
    "sg:postcode":"03801",
    "sg:province":"NH",
    "sg:website":"www.fairskies.com",
    "wof:name":"Fair Skies",
    "wof:placetype":"venue"
},
  "geometry": {"coordinates":[-70.758505,43.079149],"type":"Point"}
}