{
  "type": "Feature",
  "properties": {
    "iso:country":"US",
    "sg:address":"209 Main St",
    "sg:city":"Charlestown",
    "sg:classifiers":[
        {
            "category":"Shopping",
            "subcategory":"Department Store",
            "type":"Retail Goods"
        }
    ],
    "sg:phone":"+1 603 826 5050",
    "sg:postcode":"03603",
    "sg:province":"NH",
    "sg:tags":[
        "shop"
    ],
    "wof:name":"Dan's Max Saver Store",
    "wof:placetype":"venue"
},
  "geometry": {"coordinates":[-72.42428200000001,43.234505],"type":"Point"}
}