{
  "type": "Feature",
  "properties": {
    "iso:country":"US",
    "sg:address":"85 Grove St",
    "sg:city":"Peterborough",
    "sg:classifiers":[
        {
            "category":"Shopping",
            "subcategory":"Computers & Home Electronics",
            "type":"Retail Goods"
        }
    ],
    "sg:phone":"+1 603 924 6079",
    "sg:postcode":"03458",
    "sg:province":"NH",
    "sg:tags":[
        "software"
    ],
    "sg:website":"www.appropriatesolutions.com",
    "wof:name":"Appropriate Solutions Inc",
    "wof:placetype":"venue"
},
  "geometry": {"coordinates":[-71.950582,42.871717],"type":"Point"}
}