{
  "type": "Feature",
  "properties": {
    "iso:country":"US",
    "sg:address":"315 Jarmany Hill Rd",
    "sg:city":"Sharon",
    "sg:classifiers":[
        {
            "category":"Professional",
            "type":"Services"
        }
    ],
    "sg:phone":"+1 603 924 4477",
    "sg:postcode":"03458",
    "sg:province":"NH",
    "sg:tags":[
        "technical",
        "preparation",
        "manual"
    ],
    "wof:name":"Roark Publications",
    "wof:placetype":"venue"
},
  "geometry": {"coordinates":[-71.92843499999999,42.805129],"type":"Point"}
}