{
  "type": "Feature",
  "properties": {
    "iso:country":"US",
    "sg:address":"27 Mary Batchelder Rd",
    "sg:city":"Hampton",
    "sg:classifiers":[
        {
            "category":"Banks & Credit Unions",
            "subcategory":"Investment Brokerage",
            "type":"Services"
        }
    ],
    "sg:phone":"+1 603 926 2118",
    "sg:postcode":"03842",
    "sg:province":"NH",
    "sg:tags":[
        "advisory",
        "financial"
    ],
    "wof:name":"L L Financial",
    "wof:placetype":"venue"
},
  "geometry": {"coordinates":[-70.861859,42.943693],"type":"Point"}
}