{
  "type": "Feature",
  "properties": {
    "iso:country":"US",
    "sg:address":"360 Amherst St",
    "sg:city":"Nashua",
    "sg:classifiers":[
        {
            "category":"Shopping",
            "subcategory":"Computers & Home Electronics",
            "type":"Retail Goods"
        }
    ],
    "sg:phone":"+1 603 598 2929",
    "sg:postcode":"03063",
    "sg:province":"NH",
    "sg:tags":[
        "software"
    ],
    "wof:name":"Hollis Interactive",
    "wof:placetype":"venue"
},
  "geometry": {"coordinates":[-71.504891,42.783138],"type":"Point"}
}