{
  "type": "Feature",
  "properties": {
    "addr:full":"130 Main St Salem NH 03079",
    "addr:housenumber":"130",
    "addr:postcode":"03079",
    "addr:street":"Main St",
    "iso:country":"US",
    "sg:address":"130 Main St",
    "sg:city":"Salem",
    "sg:classifiers":[
        {
            "category":"Professional",
            "subcategory":"Lawyer & Legal Services",
            "type":"Services"
        }
    ],
    "sg:phone":"+1 603 890 3888",
    "sg:postcode":"03079",
    "sg:province":"NH",
    "sg:tags":[
        "attorney"
    ],
    "wof:name":"Pamela J Khoury",
    "wof:placetype":"venue"
},
  "geometry": {"coordinates":[-71.226196,42.782102],"type":"Point"}
}