{
  "type": "Feature",
  "properties": {
    "iso:country":"US",
    "sg:address":"75 Gorham Rd",
    "sg:city":"Gorham",
    "sg:classifiers":[
        {
            "category":"Home & Garden",
            "subcategory":"Furniture",
            "type":"Retail Goods"
        }
    ],
    "sg:phone":"+1 603 752 5212",
    "sg:postcode":"03581",
    "sg:province":"NH",
    "sg:website":"www.top-furniture.com",
    "wof:name":"Top Furniture Inc",
    "wof:placetype":"venue"
},
  "geometry": {"coordinates":[-71.194709,44.422762],"type":"Point"}
}