{
  "type": "Feature",
  "properties": {
    "iso:country":"US",
    "sg:address":"73 Marsh Rd",
    "sg:city":"Pelham",
    "sg:classifiers":[
        {
            "category":"Professional",
            "type":"Services"
        }
    ],
    "sg:phone":"+1 603 635 7363",
    "sg:postcode":"03076",
    "sg:province":"NH",
    "sg:tags":[
        "establishment"
    ],
    "wof:name":"Ats",
    "wof:placetype":"venue"
},
  "geometry": {"coordinates":[-71.331019,42.724897],"type":"Point"}
}