{
  "type": "Feature",
  "properties": {
    "iso:country":"US",
    "sg:address":"1 Glass Ln",
    "sg:city":"Barrington",
    "sg:classifiers":[
        {
            "category":"Wholesale",
            "subcategory":"Machinery & Supplies",
            "type":"Manufacturing & Wholesale Goods"
        }
    ],
    "sg:phone":"+1 603 868 6691",
    "sg:postcode":"03825",
    "sg:province":"NH",
    "sg:tags":[
        "dyer",
        "cleaners",
        "equipment"
    ],
    "sg:website":"www.yankeeequipment.com",
    "wof:name":"Yankee Equipment Systems",
    "wof:placetype":"venue"
},
  "geometry": {"coordinates":[-71.03114600000001,43.150321],"type":"Point"}
}