{
  "type": "Feature",
  "properties": {
    "addr:full":"108 Hancock Rd Peterborough NH 03450",
    "addr:housenumber":"108",
    "addr:postcode":"03450",
    "addr:street":"Hancock Rd",
    "iso:country":"US",
    "sg:address":"108 Hancock Rd",
    "sg:city":"Peterborough",
    "sg:classifiers":[
        {
            "category":"Government",
            "subcategory":"Office",
            "type":"Public Place"
        }
    ],
    "sg:phone":"+1 603 924 7105",
    "sg:postcode":"03450",
    "sg:province":"NH",
    "sg:tags":[
        "school",
        "district"
    ],
    "wof:name":"South Meadow School",
    "wof:placetype":"venue"
},
  "geometry": {"coordinates":[-72.07893799999999,42.939824],"type":"Point"}
}