{
  "type": "Feature",
  "properties": {
    "iso:country":"US",
    "sg:address":"120 Main St",
    "sg:city":"West Lebanon",
    "sg:classifiers":[
        {
            "category":"Banks & Credit Unions",
            "subcategory":"Bank",
            "type":"Services"
        }
    ],
    "sg:phone":"+1 603 298 0228",
    "sg:postcode":"03784",
    "sg:province":"NH",
    "sg:tags":[
        "mortgage",
        "loan",
        "banker",
        "real estate"
    ],
    "wof:name":"Eastern Funding Inc",
    "wof:placetype":"venue"
},
  "geometry": {"coordinates":[-72.31692700000001,43.634651],"type":"Point"}
}