{
  "type": "Feature",
  "properties": {
    "addr:full":"11 Hampshire Dr Nashua NH 03063",
    "addr:housenumber":"11",
    "addr:postcode":"03063",
    "addr:street":"Hampshire Dr",
    "iso:country":"US",
    "sg:address":"11 Hampshire Dr",
    "sg:city":"Nashua",
    "sg:classifiers":[
        {
            "category":"Professional",
            "type":"Services"
        }
    ],
    "sg:phone":"+1 603 889 5205",
    "sg:postcode":"03063",
    "sg:province":"NH",
    "sg:tags":[
        "establishment"
    ],
    "wof:name":"JFC Auditors",
    "wof:placetype":"venue"
},
  "geometry": {"coordinates":[-71.497938,42.781151],"type":"Point"}
}