{
  "type": "Feature",
  "properties": {
    "iso:country":"US",
    "sg:address":"21 York Dr",
    "sg:city":"Lee",
    "sg:classifiers":[
        {
            "category":"Real Estate",
            "subcategory":"Architect",
            "type":"Services"
        }
    ],
    "sg:phone":"+1 603 659 8888",
    "sg:postcode":"03824",
    "sg:province":"NH",
    "wof:name":"Tambling Philp Arch",
    "wof:placetype":"venue"
},
  "geometry": {"coordinates":[-70.916618,43.123153],"type":"Point"}
}