{
  "type": "Feature",
  "properties": {
    "addr:full":"269 Harrison St Manchester NH 03104",
    "addr:housenumber":"269",
    "addr:postcode":"03104",
    "addr:street":"Harrison St",
    "iso:country":"US",
    "sg:address":"269 Harrison St",
    "sg:city":"Manchester",
    "sg:classifiers":[
        {
            "category":"Retail",
            "subcategory":"Laundry & Dry Cleaning",
            "type":"Services"
        }
    ],
    "sg:phone":"+1 603 232 3337",
    "sg:postcode":"03104",
    "sg:province":"NH",
    "wof:name":"Betsy Chicoine",
    "wof:placetype":"venue"
},
  "geometry": {"coordinates":[-71.447019,43.000302],"type":"Point"}
}