{
  "type": "Feature",
  "properties": {
    "iso:country":"US",
    "sg:address":"18 Danville Rd",
    "sg:city":"Plaistow",
    "sg:classifiers":[
        {
            "category":"Real Estate",
            "subcategory":"Real Estate Services",
            "type":"Services"
        }
    ],
    "sg:phone":"+1 603 382 2728",
    "sg:postcode":"03865",
    "sg:province":"NH",
    "sg:tags":[
        "consultant"
    ],
    "wof:name":"Diane Curley",
    "wof:placetype":"venue"
},
  "geometry": {"coordinates":[-71.107815,42.847385],"type":"Point"}
}