{
  "type": "Feature",
  "properties": {
    "iso:country":"US",
    "sg:address":"10 Main St",
    "sg:city":"Hampstead",
    "sg:classifiers":[
        {
            "category":"Restaurant",
            "type":"Food & Drink"
        }
    ],
    "sg:phone":"+1 603 329 9977",
    "sg:postcode":"03841",
    "sg:province":"NH",
    "wof:name":"Manos Brick Oven Pizza",
    "wof:placetype":"venue"
},
  "geometry": {"coordinates":[-71.18118699999999,42.874874],"type":"Point"}
}