{
  "type": "Feature",
  "properties": {
    "iso:country":"US",
    "sg:address":"25 Morningside Dr",
    "sg:city":"Dover",
    "sg:classifiers":[
        {
            "category":"Health Services",
            "subcategory":"Clinic",
            "type":"Services"
        }
    ],
    "sg:phone":"+1 603 740 1381",
    "sg:postcode":"03820",
    "sg:province":"NH",
    "sg:tags":[
        "specialty",
        "outpatient"
    ],
    "wof:name":"Vibrant Life Foundation Inc",
    "wof:placetype":"venue"
},
  "geometry": {"coordinates":[-70.87067,43.162217],"type":"Point"}
}