{
  "type": "Feature",
  "properties": {
    "iso:country":"US",
    "sg:address":"330 Main St",
    "sg:city":"Hopkinton",
    "sg:classifiers":[
        {
            "category":"Government",
            "subcategory":"Office",
            "type":"Public Place"
        }
    ],
    "sg:phone":"+1 603 746 5018",
    "sg:postcode":"03229",
    "sg:province":"NH",
    "sg:tags":[
        "village"
    ],
    "wof:name":"Hopkinton Assessor's Office",
    "wof:placetype":"venue"
},
  "geometry": {"coordinates":[-71.671919,43.190814],"type":"Point"}
}