{
  "type": "Feature",
  "properties": {
    "iso:country":"US",
    "sg:address":"357 Old College Rd",
    "sg:city":"Andover",
    "sg:classifiers":[
        {
            "category":"Building & Trades",
            "subcategory":"Cleaning & Sanitation",
            "type":"Services"
        }
    ],
    "sg:phone":"+1 603 735 5300",
    "sg:postcode":"03216",
    "sg:province":"NH",
    "sg:tags":[
        "maintenance"
    ],
    "wof:name":"Village Sweep",
    "wof:placetype":"venue"
},
  "geometry": {"coordinates":[-71.78056599999999,43.456898],"type":"Point"}
}