{
  "type": "Feature",
  "properties": {
    "iso:country":"US",
    "sg:address":"627 Sherwood Glenn",
    "sg:city":"Somersworth",
    "sg:classifiers":[
        {
            "category":"Professional",
            "subcategory":"Computer Services",
            "type":"Services"
        }
    ],
    "sg:phone":"+1 603 692 2651",
    "sg:postcode":"03878",
    "sg:province":"NH",
    "sg:tags":[
        "datum"
    ],
    "wof:name":"Radiospotcom",
    "wof:placetype":"venue"
},
  "geometry": {"coordinates":[-70.89078600000001,43.245919],"type":"Point"}
}