{
  "type": "Feature",
  "properties": {
    "iso:country":"US",
    "sg:address":"99 Main St",
    "sg:city":"Littleton",
    "sg:classifiers":[
        {
            "category":"Shopping",
            "subcategory":"Clothing, Apparel, & Fashions",
            "type":"Retail Goods"
        }
    ],
    "sg:phone":"+1 603 444 0915",
    "sg:postcode":"03561",
    "sg:province":"NH",
    "wof:name":"Lahout's North Face Patagonia",
    "wof:placetype":"venue"
},
  "geometry": {"coordinates":[-71.77344600000001,44.306821],"type":"Point"}
}