{
  "type": "Feature",
  "properties": {
    "iso:country":"US",
    "sg:address":"17 Executive Dr",
    "sg:city":"Hudson",
    "sg:classifiers":[
        {
            "category":"Manufacturing",
            "subcategory":"Printing",
            "type":"Manufacturing & Wholesale Goods"
        }
    ],
    "sg:phone":"+1 603 883 3150",
    "sg:postcode":"03051",
    "sg:province":"NH",
    "sg:tags":[
        "periodical"
    ],
    "wof:name":"New Hampshire Editions",
    "wof:placetype":"venue"
},
  "geometry": {"coordinates":[-71.43192999999999,42.737382],"type":"Point"}
}