{
  "type": "Feature",
  "properties": {
    "iso:country":"US",
    "sg:address":"6 Hunters Way",
    "sg:city":"Newton",
    "sg:classifiers":[
        {
            "category":"Professional",
            "subcategory":"Business Services",
            "type":"Services"
        }
    ],
    "sg:phone":"+1 603 382 4028",
    "sg:postcode":"03858",
    "sg:province":"NH",
    "sg:tags":[
        "interior",
        "stenciling"
    ],
    "wof:name":"Historic Borders",
    "wof:placetype":"venue"
},
  "geometry": {"coordinates":[-71.074752,42.85506],"type":"Point"}
}