{
  "type": "Feature",
  "properties": {
    "addr:full":"348 Dublin Rd Jaffrey NH 03452",
    "addr:housenumber":"348",
    "addr:postcode":"03452",
    "addr:street":"Dublin Rd",
    "iso:country":"US",
    "sg:address":"348 Dublin Rd",
    "sg:city":"Jaffrey",
    "sg:classifiers":[
        {
            "category":"Building & Trades",
            "subcategory":"Construction",
            "type":"Services"
        }
    ],
    "sg:phone":"+1 603 532 6966",
    "sg:postcode":"03452",
    "sg:province":"NH",
    "sg:tags":[
        "masonry",
        "contractor"
    ],
    "wof:name":"Edward Desmarais & Son Inc",
    "wof:placetype":"venue"
},
  "geometry": {"coordinates":[-72.073021,42.849493],"type":"Point"}
}