{
  "type": "Feature",
  "properties": {
    "iso:country":"US",
    "sg:address":"8 Raymond Rd",
    "sg:city":"Deerfield",
    "sg:classifiers":[
        {
            "category":"Wholesale",
            "subcategory":"Durable Goods & Equipment",
            "type":"Manufacturing & Wholesale Goods"
        }
    ],
    "sg:phone":"+1 603 463 7979",
    "sg:postcode":"03037",
    "sg:province":"NH",
    "sg:tags":[
        "exporter"
    ],
    "wof:name":"Bound To Finish",
    "wof:placetype":"venue"
},
  "geometry": {"coordinates":[-71.237567,43.129107],"type":"Point"}
}