{
  "type": "Feature",
  "properties": {
    "iso:country":"US",
    "sg:address":"599 Lafayette Rd",
    "sg:city":"Portsmouth",
    "sg:classifiers":[
        {
            "category":"Personal",
            "subcategory":"Beauty Salon",
            "type":"Services"
        }
    ],
    "sg:phone":"+1 603 431 7077",
    "sg:postcode":"03801",
    "sg:province":"NH",
    "wof:name":"Hair Excitement",
    "wof:placetype":"venue"
},
  "geometry": {"coordinates":[-70.769576,43.056736],"type":"Point"}
}