{
  "type": "Feature",
  "properties": {
    "iso:country":"US",
    "sg:address":"116 Central Ave",
    "sg:city":"Dover",
    "sg:classifiers":[
        {
            "category":"Restaurant",
            "type":"Food & Drink"
        }
    ],
    "sg:phone":"+1 603 749 9422",
    "sg:postcode":"03820",
    "sg:province":"NH",
    "sg:tags":[
        "pizza"
    ],
    "wof:name":"Strafford House Of Pizza Inc",
    "wof:placetype":"venue"
},
  "geometry": {"coordinates":[-70.873474,43.18489],"type":"Point"}
}