{
  "type": "Feature",
  "properties": {
    "iso:country":"US",
    "sg:address":"94 Seaverns Bridge Rd",
    "sg:city":"Amherst",
    "sg:classifiers":[
        {
            "category":"Wholesale",
            "subcategory":"Machinery & Supplies",
            "type":"Manufacturing & Wholesale Goods"
        }
    ],
    "sg:phone":"+1 603 424 5298",
    "sg:postcode":"03031",
    "sg:province":"NH",
    "sg:tags":[
        "glass",
        "tank",
        "plastic"
    ],
    "wof:name":"Chem Air Systems",
    "wof:placetype":"venue"
},
  "geometry": {"coordinates":[-71.563964,42.830993],"type":"Point"}
}