{
  "type": "Feature",
  "properties": {
    "iso:country":"US",
    "sg:address":"19 School Ln",
    "sg:city":"Woodsville",
    "sg:classifiers":[
        {
            "category":"Organizations",
            "subcategory":"Religious Organization",
            "type":"Services"
        }
    ],
    "sg:phone":"+1 603 747 2670",
    "sg:postcode":"03785",
    "sg:province":"NH",
    "sg:tags":[
        "church"
    ],
    "wof:name":"St Luke's Episcopal Church",
    "wof:placetype":"venue"
},
  "geometry": {"coordinates":[-72.037469,44.151033],"type":"Point"}
}