{
  "type": "Feature",
  "properties": {
    "addr:full":"451 Winchester St Keene NH 03431",
    "addr:housenumber":"451",
    "addr:postcode":"03431",
    "addr:street":"Winchester St",
    "iso:country":"US",
    "sg:address":"451 Winchester St",
    "sg:city":"Keene",
    "sg:classifiers":[
        {
            "category":"Autos & Motor Vehicles",
            "subcategory":"Auto Supplies",
            "type":"Retail Goods"
        }
    ],
    "sg:phone":"+1 603 357 7024",
    "sg:postcode":"03431",
    "sg:province":"NH",
    "wof:name":"Bumper To Bumper",
    "wof:placetype":"venue"
},
  "geometry": {"coordinates":[-72.292905,42.917717],"type":"Point"}
}