{
  "type": "Feature",
  "properties": {
    "addr:full":"33 Commercial St Manchester NH 03101",
    "addr:housenumber":"33",
    "addr:postcode":"03101",
    "addr:street":"Commercial St",
    "iso:country":"US",
    "sg:address":"33 Commercial St",
    "sg:city":"Manchester",
    "sg:classifiers":[
        {
            "category":"Real Estate",
            "subcategory":"Real Estate Agent",
            "type":"Services"
        }
    ],
    "sg:phone":"+1 603 641 0658",
    "sg:postcode":"03101",
    "sg:province":"NH",
    "sg:tags":[
        "loan",
        "broker"
    ],
    "wof:name":"SLM Financial",
    "wof:placetype":"venue"
},
  "geometry": {"coordinates":[-71.467917,42.986914],"type":"Point"}
}