{
  "type": "Feature",
  "properties": {
    "iso:country":"US",
    "sg:address":"140 US Hwy 4",
    "sg:city":"Portsmouth",
    "sg:classifiers":[
        {
            "category":"Manufacturing",
            "subcategory":"Apparel",
            "type":"Manufacturing & Wholesale Goods"
        }
    ],
    "sg:phone":"+1 603 433 7033",
    "sg:postcode":"03801",
    "sg:province":"NH",
    "sg:tags":[
        "outerwear",
        "mfg"
    ],
    "wof:name":"Randall Poquette",
    "wof:placetype":"venue"
},
  "geometry": {"coordinates":[-70.78292399999999,43.074691],"type":"Point"}
}