{
  "type": "Feature",
  "properties": {
    "addr:full":"52 Olde Canterbury Rd Northwood NH 03261",
    "addr:housenumber":"52",
    "addr:postcode":"03261",
    "addr:street":"Olde Canterbury Rd",
    "iso:country":"US",
    "sg:address":"52 Olde Canterbury Rd",
    "sg:city":"Northwood",
    "sg:classifiers":[
        {
            "category":"Retail",
            "subcategory":"Auto Repair",
            "type":"Services"
        }
    ],
    "sg:phone":"+1 603 942 8777",
    "sg:postcode":"03261",
    "sg:province":"NH",
    "sg:tags":[
        "repairing",
        "automobile"
    ],
    "wof:name":"Least Way Auto Sales & Svc",
    "wof:placetype":"venue"
},
  "geometry": {"coordinates":[-71.242029,43.224825],"type":"Point"}
}