{
  "type": "Feature",
  "properties": {
    "addr:full":"1261 Hooksett Rd Hooksett NH 03106",
    "addr:housenumber":"1261",
    "addr:postcode":"03106",
    "addr:street":"Hooksett Rd",
    "iso:country":"US",
    "sg:address":"1261 Hooksett Rd",
    "sg:city":"Hooksett",
    "sg:classifiers":[
        {
            "category":"Home & Garden",
            "subcategory":"Furniture",
            "type":"Retail Goods"
        }
    ],
    "sg:phone":"+1 603 296 2366",
    "sg:postcode":"03106",
    "sg:province":"NH",
    "sg:tags":[
        "cabinet"
    ],
    "wof:name":"Blair Cabinets Assoc",
    "wof:placetype":"venue"
},
  "geometry": {"coordinates":[-71.433949,43.039548],"type":"Point"}
}