{
  "type": "Feature",
  "properties": {
    "addr:full":"35 Conant Dr Concord NH 03301",
    "addr:housenumber":"35",
    "addr:postcode":"03301",
    "addr:street":"Conant Dr",
    "iso:country":"US",
    "sg:address":"35 Conant Dr",
    "sg:city":"Concord",
    "sg:classifiers":[
        {
            "category":"Organizations",
            "subcategory":"Religious Organization",
            "type":"Services"
        }
    ],
    "sg:phone":"+1 603 224 0675",
    "sg:postcode":"03301",
    "sg:province":"NH",
    "sg:tags":[
        "church"
    ],
    "wof:name":"United Methodist Church",
    "wof:placetype":"venue"
},
  "geometry": {"coordinates":[-71.54744599999999,43.187812],"type":"Point"}
}