{
  "type": "Feature",
  "properties": {
    "addr:full":"5 Gage St Concord NH 03303",
    "addr:housenumber":"5",
    "addr:postcode":"03303",
    "addr:street":"Gage St",
    "iso:country":"US",
    "sg:address":"5 Gage St",
    "sg:city":"Concord",
    "sg:classifiers":[
        {
            "category":"Health Services",
            "subcategory":"Health Practitioner",
            "type":"Services"
        }
    ],
    "sg:phone":"+1 603 340 0168",
    "sg:postcode":"03303",
    "sg:province":"NH",
    "sg:tags":[
        "dental",
        "hygienist"
    ],
    "wof:name":"Jean Magee",
    "wof:placetype":"venue"
},
  "geometry": {"coordinates":[-71.603011,43.291369],"type":"Point"}
}