{
  "type": "Feature",
  "properties": {
    "addr:full":"2013 Elm St Manchester NH 03104",
    "addr:housenumber":"2013",
    "addr:postcode":"03104",
    "addr:street":"Elm St",
    "iso:country":"US",
    "sg:address":"2013 Elm St",
    "sg:city":"Manchester",
    "sg:classifiers":[
        {
            "category":"Organizations",
            "subcategory":"Non-profit Organization",
            "type":"Services"
        },
        {
            "category":"Health Services",
            "subcategory":"Clinic",
            "type":"Services"
        }
    ],
    "sg:phone":"+1 603 627 2702",
    "sg:postcode":"03104",
    "sg:province":"NH",
    "sg:tags":[
        "counseling",
        "psychotherapy",
        "outpatient",
        "community"
    ],
    "wof:name":"Pastoral Counseling Services",
    "wof:placetype":"venue"
},
  "geometry": {"coordinates":[-71.465988,43.009676],"type":"Point"}
}