{
  "type": "Feature",
  "properties": {
    "iso:country":"US",
    "sg:address":"7 Hampshire St",
    "sg:city":"Salem",
    "sg:classifiers":[
        {
            "category":"Personal",
            "subcategory":"Beauty Salon",
            "type":"Services"
        }
    ],
    "sg:phone":"+1 603 893 6245",
    "sg:postcode":"03079",
    "sg:province":"NH",
    "sg:tags":[
        "shop",
        "manicuring"
    ],
    "wof:name":"A Touch of Joy",
    "wof:placetype":"venue"
},
  "geometry": {"coordinates":[-71.197264,42.742275],"type":"Point"}
}