{
  "type": "Feature",
  "properties": {
    "addr:full":"175 Pelham Rd Salem NH 03079",
    "addr:housenumber":"175",
    "addr:postcode":"03079",
    "addr:street":"Pelham Rd",
    "iso:country":"US",
    "sg:address":"175 Pelham Rd",
    "sg:city":"Salem",
    "sg:classifiers":[
        {
            "category":"Real Estate",
            "subcategory":"Real Estate Agent",
            "type":"Services"
        }
    ],
    "sg:phone":"+1 603 898 5400",
    "sg:postcode":"03079",
    "sg:province":"NH",
    "wof:name":"Ahomebuyercom",
    "wof:placetype":"venue"
},
  "geometry": {"coordinates":[-71.27332699999999,42.760186],"type":"Point"}
}