{
  "type": "Feature",
  "properties": {
    "iso:country":"US",
    "sg:address":"46 E Derry Rd",
    "sg:city":"Derry",
    "sg:classifiers":[
        {
            "category":"Personal",
            "subcategory":"Beauty Salon",
            "type":"Services"
        }
    ],
    "sg:phone":"+1 603 437 0115",
    "sg:postcode":"03038",
    "sg:province":"NH",
    "wof:name":"The Ultimate Attraction Hair Salon",
    "wof:placetype":"venue"
},
  "geometry": {"coordinates":[-71.295753,42.894255],"type":"Point"}
}