{
  "type": "Feature",
  "properties": {
    "addr:full":"15 Colleen Dr Salem NH 03079",
    "addr:housenumber":"15",
    "addr:postcode":"03079",
    "addr:street":"Colleen Dr",
    "iso:country":"US",
    "sg:address":"15 Colleen Dr",
    "sg:city":"Salem",
    "sg:classifiers":[
        {
            "category":"Wholesale",
            "subcategory":"Non-durable Goods",
            "type":"Manufacturing & Wholesale Goods"
        }
    ],
    "sg:phone":"+1 603 898 1389",
    "sg:postcode":"03079",
    "sg:province":"NH",
    "sg:tags":[
        "advertising"
    ],
    "wof:name":"P & E Advertising",
    "wof:placetype":"venue"
},
  "geometry": {"coordinates":[-71.192814,42.811925],"type":"Point"}
}