{
  "type": "Feature",
  "properties": {
    "iso:country":"US",
    "sg:address":"35 Camp Sargent Rd",
    "sg:city":"Merrimack",
    "sg:classifiers":[
        {
            "category":"Building & Trades",
            "subcategory":"Plumbing",
            "type":"Services"
        }
    ],
    "sg:phone":"+1 603 429 4249",
    "sg:postcode":"03054",
    "sg:province":"NH",
    "sg:tags":[
        "contractor"
    ],
    "wof:name":"Lortie Brothers Plumbing & Htg",
    "wof:placetype":"venue"
},
  "geometry": {"coordinates":[-71.503372,42.8323],"type":"Point"}
}