{
  "type": "Feature",
  "properties": {
    "iso:country":"US",
    "sg:address":"21 Kimball Rd",
    "sg:city":"Londonderry",
    "sg:classifiers":[
        {
            "category":"Professional",
            "subcategory":"Management & Consulting",
            "type":"Services"
        }
    ],
    "sg:phone":"+1 603 437 1465",
    "sg:postcode":"03053",
    "sg:province":"NH",
    "wof:name":"Money Concepts Fincl Plg Ctr",
    "wof:placetype":"venue"
},
  "geometry": {"coordinates":[-71.41631,42.89589],"type":"Point"}
}