{
  "type": "Feature",
  "properties": {
    "iso:country":"US",
    "sg:address":"301 Jaffrey Rd",
    "sg:city":"Peterborough",
    "sg:classifiers":[
        {
            "category":"Sports & Exercise",
            "subcategory":"Gym",
            "type":"Entertainment"
        }
    ],
    "sg:phone":"+1 603 924 9010",
    "sg:postcode":"03458",
    "sg:province":"NH",
    "sg:tags":[
        "fitness",
        "physical",
        "facility"
    ],
    "wof:name":"NH Sport and Fitness",
    "wof:placetype":"venue"
},
  "geometry": {"coordinates":[-71.966491,42.843388],"type":"Point"}
}