{
  "type": "Feature",
  "properties": {
    "addr:full":"1 S Hall St Manchester NH 03103",
    "addr:housenumber":"1",
    "addr:postcode":"03103",
    "addr:street":"S Hall St",
    "iso:country":"US",
    "sg:address":"1 S Hall St",
    "sg:city":"Manchester",
    "sg:classifiers":[
        {
            "category":"Professional",
            "subcategory":"Employment Agencies",
            "type":"Services"
        }
    ],
    "sg:phone":"+1 603 624 6543",
    "sg:postcode":"03103",
    "sg:province":"NH",
    "wof:name":"Human Resources",
    "wof:placetype":"venue"
},
  "geometry": {"coordinates":[-71.446343,42.972438],"type":"Point"}
}