{
  "type": "Feature",
  "properties": {
    "iso:country":"US",
    "sg:address":"1 2nd St",
    "sg:city":"Concord",
    "sg:classifiers":[
        {
            "category":"Professional",
            "subcategory":"Computer Services",
            "type":"Services"
        }
    ],
    "sg:phone":"+1 603 228 5836",
    "sg:postcode":"03301",
    "sg:province":"NH",
    "sg:tags":[
        "repair"
    ],
    "wof:name":"Rick & Son Computer Repairs",
    "wof:placetype":"venue"
},
  "geometry": {"coordinates":[-71.56894200000001,43.253834],"type":"Point"}
}