{
  "type": "Feature",
  "properties": {
    "addr:full":"39 Amherst St Milford NH 03055",
    "addr:housenumber":"39",
    "addr:postcode":"03055",
    "addr:street":"Amherst St",
    "iso:country":"US",
    "sg:address":"39 Amherst St",
    "sg:city":"Milford",
    "sg:classifiers":[
        {
            "category":"Retail",
            "subcategory":"Auto Repair",
            "type":"Services"
        }
    ],
    "sg:phone":"+1 603 249 9555",
    "sg:postcode":"03055",
    "sg:province":"NH",
    "sg:tags":[
        "repairing",
        "automobile"
    ],
    "wof:name":"K P's Automotive Repair",
    "wof:placetype":"venue"
},
  "geometry": {"coordinates":[-71.64634100000001,42.837569],"type":"Point"}
}