{
  "type": "Feature",
  "properties": {
    "iso:country":"US",
    "sg:address":"6 Cottonwood Dr",
    "sg:city":"Dover",
    "sg:classifiers":[
        {
            "category":"Professional",
            "subcategory":"Management & Consulting",
            "type":"Services"
        }
    ],
    "sg:phone":"+1 603 742 9544",
    "sg:postcode":"03820",
    "sg:province":"NH",
    "wof:name":"Burns Consulting Systems",
    "wof:placetype":"venue"
},
  "geometry": {"coordinates":[-70.92766,43.221102],"type":"Point"}
}