{
  "type": "Feature",
  "properties": {
    "iso:country":"US",
    "sg:address":"8 Eagle Dr",
    "sg:city":"Merrimack",
    "sg:classifiers":[
        {
            "category":"Manufacturing",
            "subcategory":"Textiles",
            "type":"Manufacturing & Wholesale Goods"
        }
    ],
    "sg:phone":"+1 603 429 2113",
    "sg:postcode":"03054",
    "sg:province":"NH",
    "sg:tags":[
        "mill",
        "fabric",
        "cotton"
    ],
    "wof:name":"Stencils By Denise",
    "wof:placetype":"venue"
},
  "geometry": {"coordinates":[-71.507538,42.88959],"type":"Point"}
}