{
  "type": "Feature",
  "properties": {
    "iso:country":"US",
    "sg:address":"175 N State St",
    "sg:city":"Concord",
    "sg:classifiers":[
        {
            "category":"Personal",
            "subcategory":"Beauty Salon",
            "type":"Services"
        }
    ],
    "sg:phone":"+1 603 225 0166",
    "sg:postcode":"03301",
    "sg:province":"NH",
    "sg:tags":[
        "shop"
    ],
    "wof:name":"Ultimate Looks By Dorina",
    "wof:placetype":"venue"
},
  "geometry": {"coordinates":[-71.548997,43.218708],"type":"Point"}
}