{
  "type": "Feature",
  "properties": {
    "iso:country":"US",
    "sg:address":"99 Clinton St",
    "sg:city":"Concord",
    "sg:classifiers":[
        {
            "category":"Building & Trades",
            "subcategory":"Construction",
            "type":"Services"
        }
    ],
    "sg:phone":"+1 603 228 2877",
    "sg:postcode":"03301",
    "sg:province":"NH",
    "sg:tags":[
        "paving",
        "contractor"
    ],
    "wof:name":"H W Dow Asphalt Surfacing",
    "wof:placetype":"venue"
},
  "geometry": {"coordinates":[-71.553961,43.188348],"type":"Point"}
}