{
  "type": "Feature",
  "properties": {
    "iso:country":"US",
    "sg:address":"206 N River Rd",
    "sg:city":"Durham",
    "sg:classifiers":[
        {
            "category":"Health Services",
            "subcategory":"Nursing And Care Facility",
            "type":"Services"
        }
    ],
    "sg:phone":"+1 603 659 6586",
    "sg:postcode":"03861",
    "sg:province":"NH",
    "sg:tags":[
        "home",
        "convalescent"
    ],
    "wof:name":"Kirkwood Corners",
    "wof:placetype":"venue"
},
  "geometry": {"coordinates":[-71.026352,43.089761],"type":"Point"}
}