{
  "type": "Feature",
  "properties": {
    "iso:country":"US",
    "sg:address":"9 Daigneau Dr",
    "sg:city":"Campton",
    "sg:classifiers":[
        {
            "category":"Professional",
            "type":"Services"
        }
    ],
    "sg:phone":"+1 603 512 5144",
    "sg:postcode":"03226",
    "sg:province":"NH",
    "sg:tags":[
        "journalism"
    ],
    "wof:name":"Shannon A Mullen",
    "wof:placetype":"venue"
},
  "geometry": {"coordinates":[-71.47587799999999,43.723169],"type":"Point"}
}