{
  "type": "Feature",
  "properties": {
    "addr:full":"3 Albany Ave Londonderry NH 03053",
    "addr:housenumber":"3",
    "addr:postcode":"03053",
    "addr:street":"Albany Ave",
    "iso:country":"US",
    "sg:address":"3 Albany Ave",
    "sg:city":"Londonderry",
    "sg:classifiers":[
        {
            "category":"Building & Trades",
            "subcategory":"Plumbing",
            "type":"Services"
        }
    ],
    "sg:phone":"+1 603 434 4641",
    "sg:postcode":"03053",
    "sg:province":"NH",
    "sg:tags":[
        "plumbing",
        "contractor"
    ],
    "wof:name":"James Michaels Plumbing & Htg",
    "wof:placetype":"venue"
},
  "geometry": {"coordinates":[-71.340121,42.864303],"type":"Point"}
}