{
  "type": "Feature",
  "properties": {
    "addr:full":"167 S Broadway Salem NH 03079",
    "addr:housenumber":"167",
    "addr:postcode":"03079",
    "addr:street":"S Broadway",
    "iso:country":"US",
    "sg:address":"167 S Broadway",
    "sg:city":"Salem",
    "sg:classifiers":[
        {
            "category":"Shopping",
            "subcategory":"Optical Goods",
            "type":"Retail Goods"
        }
    ],
    "sg:phone":"+1 603 893 5323",
    "sg:postcode":"03079",
    "sg:province":"NH",
    "wof:name":"Lens Crafters",
    "wof:placetype":"venue"
},
  "geometry": {"coordinates":[-71.219398,42.767898],"type":"Point"}
}