{
  "type": "Feature",
  "properties": {
    "iso:country":"US",
    "sg:address":"410 Amherst St",
    "sg:city":"Nashua",
    "sg:classifiers":[
        {
            "category":"Professional",
            "subcategory":"Computer Services",
            "type":"Services"
        },
        {
            "category":"Shopping",
            "subcategory":"Computers & Home Electronics",
            "type":"Retail Goods"
        }
    ],
    "sg:phone":"+1 603 882 1306",
    "sg:postcode":"03063",
    "sg:province":"NH",
    "sg:tags":[
        "prepackaged",
        "software"
    ],
    "wof:name":"Entegrity Solutions Corp",
    "wof:placetype":"venue"
},
  "geometry": {"coordinates":[-71.510049,42.785472],"type":"Point"}
}