{
  "type": "Feature",
  "properties": {
    "addr:full":"26 Bloody Brook Rd Amherst NH 03031",
    "addr:housenumber":"26",
    "addr:postcode":"03031",
    "addr:street":"Bloody Brook Rd",
    "iso:country":"US",
    "sg:address":"26 Bloody Brook Rd",
    "sg:city":"Amherst",
    "sg:classifiers":[
        {
            "category":"Professional",
            "subcategory":"Management & Consulting",
            "type":"Services"
        }
    ],
    "sg:phone":"+1 603 672 9514",
    "sg:postcode":"03031",
    "sg:province":"NH",
    "wof:name":"Ptak & Associates Inc",
    "wof:placetype":"venue"
},
  "geometry": {"coordinates":[-71.64344699999999,42.868553],"type":"Point"}
}