{
  "type": "Feature",
  "properties": {
    "iso:country":"US",
    "sg:address":"28 Industrial Way",
    "sg:city":"Rochester",
    "sg:phone":"+1 603 332 2080",
    "sg:postcode":"03867",
    "sg:province":"NH",
    "sg:tags":[
        "oil"
    ],
    "sg:website":"www.easternman.com",
    "wof:name":"Eastern Propane Gas Inc",
    "wof:placetype":"venue"
},
  "geometry": {"coordinates":[-71.000773,43.309607],"type":"Point"}
}