{
  "type": "Feature",
  "properties": {
    "iso:country":"US",
    "sg:address":"67 W Swanzey Rd",
    "sg:city":"East Swanzey",
    "sg:classifiers":[
        {
            "category":"Retail",
            "subcategory":"Auto Repair",
            "type":"Services"
        }
    ],
    "sg:phone":"+1 603 352 2161",
    "sg:postcode":"03446",
    "sg:province":"NH",
    "sg:tags":[
        "automotive"
    ],
    "wof:name":"Goodell A M Strters Altrnators",
    "wof:placetype":"venue"
},
  "geometry": {"coordinates":[-72.29726599999999,42.905856],"type":"Point"}
}