{
  "type": "Feature",
  "properties": {
    "iso:country":"US",
    "sg:address":"16 Swamscott St",
    "sg:city":"Newfields",
    "sg:classifiers":[
        {
            "category":"Shopping",
            "subcategory":"Used Merchandise",
            "type":"Retail Goods"
        }
    ],
    "sg:phone":"+1 603 772 7236",
    "sg:postcode":"03856",
    "sg:province":"NH",
    "sg:tags":[
        "sell",
        "buy",
        "computer",
        "refurnishes"
    ],
    "wof:name":"Brentwood Computer",
    "wof:placetype":"venue"
},
  "geometry": {"coordinates":[-70.939035,43.035751],"type":"Point"}
}