{
  "type": "Feature",
  "properties": {
    "iso:country":"US",
    "sg:address":"105 Hurricane Rd",
    "sg:city":"Belmont",
    "sg:classifiers":[
        {
            "category":"Building & Trades",
            "subcategory":"Construction",
            "type":"Services"
        }
    ],
    "sg:phone":"+1 603 524 0683",
    "sg:postcode":"03220",
    "sg:province":"NH",
    "sg:tags":[
        "home",
        "general",
        "family",
        "contractor"
    ],
    "wof:name":"Cartier Construction",
    "wof:placetype":"venue"
},
  "geometry": {"coordinates":[-71.499689,43.462731],"type":"Point"}
}