{
  "type": "Feature",
  "properties": {
    "iso:country":"US",
    "sg:address":"954 Whittier Hwy",
    "sg:city":"Moultonborough",
    "sg:classifiers":[
        {
            "category":"Building & Trades",
            "subcategory":"Plumbing",
            "type":"Services"
        }
    ],
    "sg:phone":"+1 603 476 2281",
    "sg:postcode":"03254",
    "sg:province":"NH",
    "sg:tags":[
        "tank",
        "septic"
    ],
    "wof:name":"Wilson Associates",
    "wof:placetype":"venue"
},
  "geometry": {"coordinates":[-71.39900299999999,43.752578],"type":"Point"}
}