{
  "type": "Feature",
  "properties": {
    "iso:country":"US",
    "sg:address":"388 North St",
    "sg:city":"Jaffrey",
    "sg:classifiers":[
        {
            "category":"Organizations",
            "subcategory":"Religious Organization",
            "type":"Services"
        }
    ],
    "sg:phone":"+1 603 532 6012",
    "sg:postcode":"03452",
    "sg:province":"NH",
    "sg:tags":[
        "church"
    ],
    "wof:name":"Pilgrim Baptist Church",
    "wof:placetype":"venue"
},
  "geometry": {"coordinates":[-72.02434,42.833329],"type":"Point"}
}