{
  "type": "Feature",
  "properties": {
    "iso:country":"US",
    "sg:address":"30 Alexis Ln",
    "sg:city":"Hampton Falls",
    "sg:classifiers":[
        {
            "category":"Professional",
            "subcategory":"Computer Services",
            "type":"Services"
        }
    ],
    "sg:phone":"+1 603 929 3635",
    "sg:postcode":"03844",
    "sg:province":"NH",
    "sg:tags":[
        "consultant",
        "designer",
        "datum",
        "system"
    ],
    "wof:name":"Bedrosian & Assoc",
    "wof:placetype":"venue"
},
  "geometry": {"coordinates":[-70.87660700000001,42.91658],"type":"Point"}
}