{
  "type": "Feature",
  "properties": {
    "iso:country":"US",
    "sg:address":"151 West St",
    "sg:city":"Keene",
    "sg:classifiers":[
        {
            "category":"Communications",
            "subcategory":"Radio Station",
            "type":"Services"
        }
    ],
    "sg:phone":"+1 603 357 4632",
    "sg:postcode":"03431",
    "sg:province":"NH",
    "sg:tags":[
        "company",
        "broadcasting"
    ],
    "wof:name":"Keene Christian Broadcasting",
    "wof:placetype":"venue"
},
  "geometry": {"coordinates":[-72.284342,42.932717],"type":"Point"}
}