{
  "type": "Feature",
  "properties": {
    "addr:full":"18 Sherwood Forest Rd Weare NH 03281",
    "addr:housenumber":"18",
    "addr:postcode":"03281",
    "addr:street":"Sherwood Forest Rd",
    "iso:country":"US",
    "sg:address":"18 Sherwood Forest Rd",
    "sg:city":"Weare",
    "sg:classifiers":[
        {
            "category":"Professional",
            "subcategory":"Computer Services",
            "type":"Services"
        }
    ],
    "sg:phone":"+1 603 529 6873",
    "sg:postcode":"03281",
    "sg:province":"NH",
    "sg:tags":[
        "datum"
    ],
    "wof:name":"Ynot Media",
    "wof:placetype":"venue"
},
  "geometry": {"coordinates":[-71.666175,43.137711],"type":"Point"}
}