{
  "type": "Feature",
  "properties": {
    "iso:country":"US",
    "sg:address":"60 Hallwood Dr",
    "sg:city":"Keene",
    "sg:classifiers":[
        {
            "category":"Building & Trades",
            "subcategory":"Electrical",
            "type":"Services"
        }
    ],
    "sg:phone":"+1 603 352 8439",
    "sg:postcode":"03431",
    "sg:province":"NH",
    "sg:tags":[
        "electrical",
        "contractor"
    ],
    "wof:name":"Andrew R Frink",
    "wof:placetype":"venue"
},
  "geometry": {"coordinates":[-72.33384700000001,42.997529],"type":"Point"}
}