{
  "type": "Feature",
  "properties": {
    "iso:country":"US",
    "sg:address":"95 Main St",
    "sg:city":"Raymond",
    "sg:classifiers":[
        {
            "category":"Professional",
            "subcategory":"Business Services",
            "type":"Services"
        }
    ],
    "sg:phone":"+1 603 895 3537",
    "sg:postcode":"03077",
    "sg:province":"NH",
    "wof:name":"N E Strength & Conditioning",
    "wof:placetype":"venue"
},
  "geometry": {"coordinates":[-71.17731499999999,43.032812],"type":"Point"}
}