{
  "type": "Feature",
  "properties": {
    "iso:country":"US",
    "sg:address":"344 Broad St",
    "sg:city":"Hollis",
    "sg:classifiers":[
        {
            "category":"Restaurant",
            "type":"Food & Drink"
        }
    ],
    "sg:phone":"+1 603 465 7188",
    "sg:postcode":"03049",
    "sg:province":"NH",
    "sg:tags":[
        "eating",
        "out"
    ],
    "wof:name":"Uniquely New England LLC",
    "wof:placetype":"venue"
},
  "geometry": {"coordinates":[-71.532146,42.745813],"type":"Point"}
}