{
  "type": "Feature",
  "properties": {
    "iso:country":"US",
    "sg:address":"1976 E Conway Rd",
    "sg:city":"North Conway",
    "sg:classifiers":[
        {
            "category":"Sports & Exercise",
            "subcategory":"Golf",
            "type":"Entertainment"
        }
    ],
    "sg:phone":"+1 603 356 5635",
    "sg:postcode":"03813",
    "sg:province":"ME",
    "sg:tags":[
        "course"
    ],
    "wof:name":"Jonathan's Golf",
    "wof:placetype":"venue"
},
  "geometry": {"coordinates":[-71.059563,44.01127],"type":"Point"}
}