{
  "type": "Feature",
  "properties": {
    "iso:country":"US",
    "sg:address":"17 Indian Fern Dr",
    "sg:city":"Nashua",
    "sg:classifiers":[
        {
            "category":"Shopping",
            "subcategory":"Gifts & Souvenirs",
            "type":"Retail Goods"
        }
    ],
    "sg:phone":"+1 603 888 7000",
    "sg:postcode":"03062",
    "sg:province":"NH",
    "sg:tags":[
        "party",
        "supply"
    ],
    "wof:name":"Ceremonies By Attorney Kate",
    "wof:placetype":"venue"
},
  "geometry": {"coordinates":[-71.480097,42.715324],"type":"Point"}
}