{
  "type": "Feature",
  "properties": {
    "iso:country":"US",
    "sg:address":"160 Emerald St",
    "sg:city":"Keene",
    "sg:classifiers":[
        {
            "category":"Shopping",
            "subcategory":"Computers & Home Electronics",
            "type":"Retail Goods"
        }
    ],
    "sg:phone":"+1 603 355 8007",
    "sg:postcode":"03431",
    "sg:province":"NH",
    "wof:name":"Cable Connection",
    "wof:placetype":"venue"
},
  "geometry": {"coordinates":[-72.28446599999999,42.930355],"type":"Point"}
}