{
  "type": "Feature",
  "properties": {
    "addr:full":"26 Sloan Rd Enfield NH 03748",
    "addr:housenumber":"26",
    "addr:postcode":"03748",
    "addr:street":"Sloan Rd",
    "iso:country":"US",
    "sg:address":"26 Sloan Rd",
    "sg:city":"Enfield",
    "sg:classifiers":[
        {
            "category":"Local Transit",
            "type":"Transportation"
        }
    ],
    "sg:phone":"+1 603 632 7570",
    "sg:postcode":"03748",
    "sg:province":"NH",
    "wof:name":"UVSScab Company",
    "wof:placetype":"venue"
},
  "geometry": {"coordinates":[-72.144012,43.61371],"type":"Point"}
}