{
  "type": "Feature",
  "properties": {
    "iso:country":"US",
    "sg:address":"340 Granite St",
    "sg:city":"Manchester",
    "sg:classifiers":[
        {
            "category":"Social Services",
            "subcategory":"Job Training",
            "type":"Services"
        }
    ],
    "sg:phone":"+1 603 624 2394",
    "sg:postcode":"03102",
    "sg:province":"NH",
    "sg:tags":[
        "rehabilitation"
    ],
    "wof:name":"Center For Physical Therapy",
    "wof:placetype":"venue"
},
  "geometry": {"coordinates":[-71.473919,42.983647],"type":"Point"}
}