{
  "type": "Feature",
  "properties": {
    "iso:country":"US",
    "sg:address":"S Main",
    "sg:city":"Wolfeboro",
    "sg:classifiers":[
        {
            "category":"Education",
            "subcategory":"School",
            "type":"Public Place"
        }
    ],
    "sg:phone":"+1 603 569 2055",
    "sg:postcode":"03894",
    "sg:province":"NH",
    "sg:tags":[
        "high",
        "middle"
    ],
    "wof:name":"Ossipee Central School",
    "wof:placetype":"venue"
},
  "geometry": {"coordinates":[-71.22020000000001,43.609402],"type":"Point"}
}