{
  "type": "Feature",
  "properties": {
    "iso:country":"US",
    "sg:address":"5 George Ave",
    "sg:city":"Londonderry",
    "sg:classifiers":[
        {
            "category":"Manufacturing",
            "subcategory":"Metals",
            "type":"Manufacturing & Wholesale Goods"
        }
    ],
    "sg:phone":"+1 603 641 2164",
    "sg:postcode":"03053",
    "sg:province":"NH",
    "sg:tags":[
        "finishing",
        "industrial",
        "shielding"
    ],
    "wof:name":"Finishield Corp",
    "wof:placetype":"venue"
},
  "geometry": {"coordinates":[-71.425872,42.932449],"type":"Point"}
}