{
  "type": "Feature",
  "properties": {
    "addr:full":"5 Cushing Rd Goffstown NH 03045",
    "addr:housenumber":"5",
    "addr:postcode":"03045",
    "addr:street":"Cushing Rd",
    "iso:country":"US",
    "sg:address":"5 Cushing Rd",
    "sg:city":"Goffstown",
    "sg:classifiers":[
        {
            "category":"Professional",
            "subcategory":"Accounting & Tax Preparation",
            "type":"Services"
        }
    ],
    "sg:phone":"+1 603 497 3691",
    "sg:postcode":"03045",
    "sg:province":"NH",
    "wof:name":"J C Hannemann Bookkeeping",
    "wof:placetype":"venue"
},
  "geometry": {"coordinates":[-71.615313,43.014487],"type":"Point"}
}