{
  "type": "Feature",
  "properties": {
    "iso:country":"US",
    "sg:address":"8 Quaker Ct",
    "sg:city":"Bedford",
    "sg:classifiers":[
        {
            "category":"Food & Beverages",
            "subcategory":"Specialty",
            "type":"Retail Goods"
        }
    ],
    "sg:phone":"+1 603 472 5520",
    "sg:postcode":"03110",
    "sg:province":"NH",
    "wof:name":"Quota Club International",
    "wof:placetype":"venue"
},
  "geometry": {"coordinates":[-71.499076,42.951412],"type":"Point"}
}