{
  "type": "Feature",
  "properties": {
    "iso:country":"US",
    "sg:address":"149 Rockstrain Dr",
    "sg:city":"Littleton",
    "sg:classifiers":[
        {
            "category":"Food & Beverages",
            "subcategory":"Bakery",
            "type":"Retail Goods"
        }
    ],
    "sg:phone":"+1 603 444 2924",
    "sg:postcode":"03561",
    "sg:province":"NH",
    "wof:name":"Deluxe Donuts & Pastry Shop",
    "wof:placetype":"venue"
},
  "geometry": {"coordinates":[-71.784171,44.314208],"type":"Point"}
}