{
  "type": "Feature",
  "properties": {
    "iso:country":"US",
    "sg:address":"60 Broad St",
    "sg:city":"Hollis",
    "sg:classifiers":[
        {
            "category":"Wholesale",
            "subcategory":"Farm Supplies",
            "type":"Manufacturing & Wholesale Goods"
        }
    ],
    "sg:phone":"+1 603 465 2583",
    "sg:postcode":"03049",
    "sg:province":"NH",
    "sg:tags":[
        "feed"
    ],
    "wof:name":"Hollis Grain & Hardware",
    "wof:placetype":"venue"
},
  "geometry": {"coordinates":[-71.578659,42.744113],"type":"Point"}
}