{
  "type": "Feature",
  "properties": {
    "iso:country":"US",
    "sg:address":"35 Concord Way",
    "sg:city":"Portsmouth",
    "sg:classifiers":[
        {
            "category":"Building & Trades",
            "subcategory":"Construction",
            "type":"Services"
        }
    ],
    "sg:phone":"+1 603 430 7660",
    "sg:postcode":"03801",
    "sg:province":"NH",
    "sg:tags":[
        "floor",
        "laying",
        "contractor"
    ],
    "wof:name":"Don Morse Flooring",
    "wof:placetype":"venue"
},
  "geometry": {"coordinates":[-70.770962,43.091256],"type":"Point"}
}