{
  "type": "Feature",
  "properties": {
    "iso:country":"US",
    "sg:address":"210 West Rd",
    "sg:city":"Portsmouth",
    "sg:classifiers":[
        {
            "category":"Wholesale",
            "subcategory":"Sporting Goods",
            "type":"Manufacturing & Wholesale Goods"
        }
    ],
    "sg:phone":"+1 603 436 0150",
    "sg:postcode":"03801",
    "sg:province":"NH",
    "sg:tags":[
        "recreational",
        "supply"
    ],
    "wof:name":"Henri Salaun Sports Inc",
    "wof:placetype":"venue"
},
  "geometry": {"coordinates":[-70.77751499999999,43.04284],"type":"Point"}
}