{
  "type": "Feature",
  "properties": {
    "iso:country":"US",
    "sg:address":"54 E Sutton Rd",
    "sg:city":"North Sutton",
    "sg:classifiers":[
        {
            "category":"Retail",
            "subcategory":"Repair Shop",
            "type":"Services"
        }
    ],
    "sg:phone":"+1 603 927 4362",
    "sg:postcode":"03278",
    "sg:province":"NH",
    "sg:tags":[
        "repairing",
        "piano",
        "refinishing"
    ],
    "wof:name":"Mountain View Piano",
    "wof:placetype":"venue"
},
  "geometry": {"coordinates":[-71.855969,43.298086],"type":"Point"}
}