{
  "type": "Feature",
  "properties": {
    "iso:country":"US",
    "sg:address":"891 N Mammoth Rd",
    "sg:city":"Manchester",
    "sg:classifiers":[
        {
            "category":"Professional",
            "subcategory":"Business Services",
            "type":"Services"
        }
    ],
    "sg:phone":"+1 603 634 4236",
    "sg:postcode":"03104",
    "sg:province":"NH",
    "wof:name":"Rock Mass Interiors",
    "wof:placetype":"venue"
},
  "geometry": {"coordinates":[-71.43590399999999,43.004074],"type":"Point"}
}