{
  "type": "Feature",
  "properties": {
    "addr:full":"28 Remle Rd Ossipee NH 03814",
    "addr:housenumber":"28",
    "addr:postcode":"03814",
    "addr:street":"Remle Rd",
    "iso:country":"US",
    "sg:address":"28 Remle Rd",
    "sg:city":"Ossipee",
    "sg:classifiers":[
        {
            "category":"Government",
            "subcategory":"Office",
            "type":"Public Place"
        }
    ],
    "sg:phone":"+1 603 539 4955",
    "sg:postcode":"03814",
    "sg:province":"NH",
    "sg:tags":[
        "village"
    ],
    "wof:name":"Ossipee Dog Officer",
    "wof:placetype":"venue"
},
  "geometry": {"coordinates":[-71.087564,43.791182],"type":"Point"}
}