{
  "type": "Feature",
  "properties": {
    "iso:country":"US",
    "sg:address":"32 Jady Hill Ave",
    "sg:city":"Exeter",
    "sg:classifiers":[
        {
            "category":"Health Services",
            "subcategory":"Clinic",
            "type":"Services"
        }
    ],
    "sg:phone":"+1 603 772 7704",
    "sg:postcode":"03833",
    "sg:province":"NH",
    "wof:name":"Katherine Rice Bsn",
    "wof:placetype":"venue"
},
  "geometry": {"coordinates":[-70.946054,42.985206],"type":"Point"}
}