{
  "type": "Feature",
  "properties": {
    "addr:full":"10 Ruddsboro Rd Lebanon NH 03766",
    "addr:housenumber":"10",
    "addr:postcode":"03766",
    "addr:street":"Ruddsboro Rd",
    "iso:country":"US",
    "sg:address":"10 Ruddsboro Rd",
    "sg:city":"Lebanon",
    "sg:classifiers":[
        {
            "category":"Organizations",
            "subcategory":"Religious Organization",
            "type":"Services"
        }
    ],
    "sg:phone":"+1 603 448 5401",
    "sg:postcode":"03766",
    "sg:province":"NH",
    "sg:tags":[
        "church"
    ],
    "wof:name":"New Beginnings Church Of God",
    "wof:placetype":"venue"
},
  "geometry": {"coordinates":[-72.17306000000001,43.651406],"type":"Point"}
}