{
  "type": "Feature",
  "properties": {
    "iso:country":"US",
    "sg:address":"21 Whitehall Rd",
    "sg:city":"Rochester",
    "sg:classifiers":[
        {
            "category":"Health Services",
            "subcategory":"Doctor",
            "type":"Services"
        }
    ],
    "sg:phone":"+1 603 335 0909",
    "sg:postcode":"03867",
    "sg:province":"NH",
    "sg:tags":[
        "physician",
        "surgeon"
    ],
    "wof:name":"Rochester Pulmonary Medicine",
    "wof:placetype":"venue"
},
  "geometry": {"coordinates":[-70.959818,43.298157],"type":"Point"}
}