{
  "type": "Feature",
  "properties": {
    "iso:country":"US",
    "sg:address":"7 Rainbow Dr",
    "sg:city":"Goffstown",
    "sg:classifiers":[
        {
            "category":"Shopping",
            "subcategory":"Florist",
            "type":"Retail Goods"
        }
    ],
    "sg:phone":"+1 603 497 3158",
    "sg:postcode":"03045",
    "sg:province":"NH",
    "wof:name":"Integrated Floral Svc",
    "wof:placetype":"venue"
},
  "geometry": {"coordinates":[-71.562153,43.000046],"type":"Point"}
}