{
  "type": "Feature",
  "properties": {
    "iso:country":"US",
    "sg:address":"10 Circle Dr",
    "sg:city":"Meredith",
    "sg:classifiers":[
        {
            "category":"Building & Trades",
            "subcategory":"Construction",
            "type":"Services"
        }
    ],
    "sg:phone":"+1 603 279 7937",
    "sg:postcode":"03253",
    "sg:province":"NH",
    "sg:tags":[
        "contractor"
    ],
    "wof:name":"Drywall Works",
    "wof:placetype":"venue"
},
  "geometry": {"coordinates":[-71.500758,43.667479],"type":"Point"}
}