{
  "type": "Feature",
  "properties": {
    "iso:country":"US",
    "sg:address":"2 Sawmill Rd",
    "sg:city":"Gilford",
    "sg:classifiers":[
        {
            "category":"Government",
            "subcategory":"Office",
            "type":"Public Place"
        }
    ],
    "sg:phone":"+1 603 744 8059",
    "sg:postcode":"03249",
    "sg:province":"NH",
    "sg:tags":[
        "state",
        "program",
        "transportation"
    ],
    "wof:name":"Transportation NH Dept",
    "wof:placetype":"venue"
},
  "geometry": {"coordinates":[-71.439701,43.531796],"type":"Point"}
}