{
  "type": "Feature",
  "properties": {
    "addr:full":"288 S River Rd Bedford NH 03110",
    "addr:housenumber":"288",
    "addr:postcode":"03110",
    "addr:street":"S River Rd",
    "iso:country":"US",
    "sg:address":"288 S River Rd",
    "sg:city":"Bedford",
    "sg:classifiers":[
        {
            "category":"Real Estate",
            "subcategory":"Developer",
            "type":"Services"
        }
    ],
    "sg:phone":"+1 603 668 9999",
    "sg:postcode":"03110",
    "sg:province":"NH",
    "sg:tags":[
        "development"
    ],
    "wof:name":"First New Hampshire Dev",
    "wof:placetype":"venue"
},
  "geometry": {"coordinates":[-71.465411,42.936504],"type":"Point"}
}