{
  "type": "Feature",
  "properties": {
    "iso:country":"US",
    "sg:address":"135 Commerce Way",
    "sg:city":"Portsmouth",
    "sg:classifiers":[
        {
            "category":"Real Estate",
            "subcategory":"Real Estate Services",
            "type":"Services"
        }
    ],
    "sg:phone":"+1 603 766 8877",
    "sg:postcode":"03801",
    "sg:province":"NH",
    "sg:tags":[
        "company",
        "title"
    ],
    "wof:name":"Warranty Title Co",
    "wof:placetype":"venue"
},
  "geometry": {"coordinates":[-70.785301,43.090501],"type":"Point"}
}