{
  "type": "Feature",
  "properties": {
    "iso:country":"US",
    "sg:address":"213 Forest Rd",
    "sg:city":"Hancock",
    "sg:classifiers":[
        {
            "category":"Professional",
            "type":"Services"
        }
    ],
    "sg:phone":"+1 603 525 3532",
    "sg:postcode":"03449",
    "sg:province":"NH",
    "sg:tags":[
        "establishment"
    ],
    "wof:name":"Pulfer & Williams",
    "wof:placetype":"venue"
},
  "geometry": {"coordinates":[-71.948351,42.962187],"type":"Point"}
}