{
  "type": "Feature",
  "properties": {
    "addr:full":"31 Charleston Ave Manchester NH 03102",
    "addr:housenumber":"31",
    "addr:postcode":"03102",
    "addr:street":"Charleston Ave",
    "iso:country":"US",
    "sg:address":"31 Charleston Ave",
    "sg:city":"Manchester",
    "sg:classifiers":[
        {
            "category":"Health Services",
            "subcategory":"Medical Lab",
            "type":"Services"
        }
    ],
    "sg:phone":"+1 603 421 9094",
    "sg:postcode":"03102",
    "sg:province":"NH",
    "sg:tags":[
        "laboratory",
        "dental"
    ],
    "wof:name":"Saturn Dental Lab Inc",
    "wof:placetype":"venue"
},
  "geometry": {"coordinates":[-71.487065,42.979586],"type":"Point"}
}