{
  "type": "Feature",
  "properties": {
    "iso:country":"US",
    "sg:address":"334 Raymond Rd",
    "sg:city":"Candia",
    "sg:classifiers":[
        {
            "category":"Education",
            "subcategory":"Special Training",
            "type":"Public Place"
        }
    ],
    "sg:phone":"+1 603 483 0158",
    "sg:postcode":"03034",
    "sg:province":"NH",
    "wof:name":"Susanna Bares",
    "wof:placetype":"venue"
},
  "geometry": {"coordinates":[-71.257116,43.056933],"type":"Point"}
}