{
  "type": "Feature",
  "properties": {
    "iso:country":"US",
    "sg:address":"257 Bridge St",
    "sg:city":"Manchester",
    "sg:classifiers":[
        {
            "category":"Manufacturing",
            "subcategory":"Motor Vehicles & Parts",
            "type":"Manufacturing & Wholesale Goods"
        }
    ],
    "sg:phone":"+1 603 623 8797",
    "sg:postcode":"03104",
    "sg:province":"NH",
    "sg:tags":[
        "radiator"
    ],
    "wof:name":"Plumbing & Heating Repair Co",
    "wof:placetype":"venue"
},
  "geometry": {"coordinates":[-71.451596,42.995523],"type":"Point"}
}