{
  "type": "Feature",
  "properties": {
    "addr:full":"240 Buckminster Way Portsmouth NH 03801",
    "addr:housenumber":"240",
    "addr:postcode":"03801",
    "addr:street":"Buckminster Way",
    "iso:country":"US",
    "sg:address":"240 Buckminster Way",
    "sg:city":"Portsmouth",
    "sg:classifiers":[
        {
            "category":"Professional",
            "subcategory":"Computer Services",
            "type":"Services"
        },
        {
            "category":"Shopping",
            "subcategory":"Computers & Home Electronics",
            "type":"Retail Goods"
        }
    ],
    "sg:phone":"+1 603 436 6239",
    "sg:postcode":"03801",
    "sg:province":"NH",
    "sg:tags":[
        "consultant",
        "software"
    ],
    "sg:website":"www.rivercitysoftware.com",
    "wof:name":"River City Software LLC",
    "wof:placetype":"venue"
},
  "geometry": {"coordinates":[-70.810017,43.039708],"type":"Point"}
}