{
  "type": "Feature",
  "properties": {
    "addr:full":"380 Lafayette Rd Seabrook NH 03874",
    "addr:housenumber":"380",
    "addr:postcode":"03874",
    "iso:country":"US",
    "sg:address":"380 Lafayette Rd",
    "sg:city":"Seabrook",
    "sg:classifiers":[
        {
            "category":"Food & Beverages",
            "subcategory":"Groceries & Convenience Stores",
            "type":"Retail Goods"
        }
    ],
    "sg:phone":"+1 603 474 9161",
    "sg:postcode":"03874",
    "sg:province":"NH",
    "sg:tags":[
        "grocer"
    ],
    "wof:name":"Market Basket Inc",
    "wof:placetype":"venue"
},
  "geometry": {"coordinates":[-70.869315,42.885234],"type":"Point"}
}