{
  "type": "Feature",
  "properties": {
    "addr:full":"5 Plaistow Rd Plaistow NH 03865",
    "addr:housenumber":"5",
    "addr:postcode":"03865",
    "addr:street":"Plaistow Rd",
    "iso:country":"US",
    "sg:address":"5 Plaistow Rd",
    "sg:city":"Plaistow",
    "sg:classifiers":[
        {
            "category":"Personal",
            "type":"Services"
        }
    ],
    "sg:phone":"+1 603 382 5300",
    "sg:postcode":"03865",
    "sg:province":"NH",
    "wof:name":"Pormarly Fifth Ave Tux",
    "wof:placetype":"venue"
},
  "geometry": {"coordinates":[-71.103116,42.816569],"type":"Point"}
}