{
  "type": "Feature",
  "properties": {
    "addr:full":"350 Winchester St Keene NH 03431",
    "addr:housenumber":"350",
    "addr:postcode":"03431",
    "addr:street":"Winchester St",
    "iso:country":"US",
    "sg:address":"350 Winchester St",
    "sg:city":"Keene",
    "sg:classifiers":[
        {
            "category":"Professional",
            "subcategory":"Accounting & Tax Preparation",
            "type":"Services"
        }
    ],
    "sg:phone":"+1 603 352 4065",
    "sg:postcode":"03431",
    "sg:province":"NH",
    "sg:tags":[
        "return",
        "filing"
    ],
    "wof:name":"H & R Block Tax Svc",
    "wof:placetype":"venue"
},
  "geometry": {"coordinates":[-72.290115,42.923638],"type":"Point"}
}