{
  "type": "Feature",
  "properties": {
    "addr:full":"161 Main Ave South Hampton NH 03827",
    "addr:housenumber":"161",
    "addr:postcode":"03827",
    "addr:street":"Main Ave South",
    "iso:country":"US",
    "sg:address":"161 Main Ave",
    "sg:city":"South Hampton",
    "sg:classifiers":[
        {
            "category":"Insurance",
            "subcategory":"Insurance Agent",
            "type":"Services"
        }
    ],
    "sg:phone":"+1 603 394 7008",
    "sg:postcode":"03827",
    "sg:province":"NH",
    "wof:name":"Blackadar Marine Insurance",
    "wof:placetype":"venue"
},
  "geometry": {"coordinates":[-70.968622,42.885371],"type":"Point"}
}