{
  "type": "Feature",
  "properties": {
    "iso:country":"US",
    "sg:address":"922 Elm St",
    "sg:city":"Manchester",
    "sg:classifiers":[
        {
            "category":"Education",
            "subcategory":"Special Training",
            "type":"Public Place"
        }
    ],
    "sg:phone":"+1 603 668 8418",
    "sg:postcode":"03101",
    "sg:province":"NH",
    "sg:tags":[
        "instruction",
        "music"
    ],
    "wof:name":"Peter Bridges",
    "wof:placetype":"venue"
},
  "geometry": {"coordinates":[-71.463149,42.991179],"type":"Point"}
}