{
  "type": "Feature",
  "properties": {
    "iso:country":"US",
    "sg:address":"1072 W Hollis St",
    "sg:city":"Nashua",
    "sg:classifiers":[
        {
            "category":"Wholesale",
            "subcategory":"Groceries",
            "type":"Manufacturing & Wholesale Goods"
        }
    ],
    "sg:phone":"+1 603 880 6494",
    "sg:postcode":"03062",
    "sg:province":"NH",
    "sg:tags":[
        "gourmet",
        "food",
        "product"
    ],
    "wof:name":"Bless Land Co",
    "wof:placetype":"venue"
},
  "geometry": {"coordinates":[-71.533916,42.719921],"type":"Point"}
}