{
  "type": "Feature",
  "properties": {
    "addr:full":"41 State Rte 104 Danbury NH 03230",
    "addr:housenumber":"41",
    "addr:postcode":"03230",
    "addr:street":"State Rte 104",
    "iso:country":"US",
    "sg:address":"41 State Rte 104",
    "sg:city":"Danbury",
    "sg:classifiers":[
        {
            "category":"Government",
            "subcategory":"Post Office",
            "type":"Public Place"
        }
    ],
    "sg:phone":"+1 603 768 3941",
    "sg:postcode":"03230",
    "sg:province":"NH",
    "wof:name":"US Post Office",
    "wof:placetype":"venue"
},
  "geometry": {"coordinates":[-71.838047,43.520267],"type":"Point"}
}