{
  "type": "Feature",
  "properties": {
    "addr:full":"54 Willow St Berlin NH 03570",
    "addr:housenumber":"54",
    "addr:postcode":"03570",
    "addr:street":"Willow St",
    "iso:country":"US",
    "sg:address":"54 Willow St",
    "sg:city":"Berlin",
    "sg:classifiers":[
        {
            "category":"Social Services",
            "type":"Services"
        }
    ],
    "sg:phone":"+1 603 752 4678",
    "sg:postcode":"03570",
    "sg:province":"NH",
    "sg:tags":[
        "pregnancy",
        "counseling",
        "information"
    ],
    "wof:name":"Coos County Family Health Svc",
    "wof:placetype":"venue"
},
  "geometry": {"coordinates":[-71.184454,44.472979],"type":"Point"}
}