{
  "type": "Feature",
  "properties": {
    "addr:full":"118 Hunters Village Way Manchester NH 03103",
    "addr:housenumber":"118",
    "addr:postcode":"03103",
    "addr:street":"Hunters Village Way",
    "iso:country":"US",
    "sg:address":"118 Hunters Village Way",
    "sg:city":"Manchester",
    "sg:classifiers":[
        {
            "category":"Professional",
            "subcategory":"Business Services",
            "type":"Services"
        }
    ],
    "sg:phone":"+1 603 666 0363",
    "sg:postcode":"03103",
    "sg:province":"NH",
    "sg:tags":[
        "merchandise",
        "general"
    ],
    "wof:name":"Simply Done",
    "wof:placetype":"venue"
},
  "geometry": {"coordinates":[-71.451161,42.955074],"type":"Point"}
}