{
  "type": "Feature",
  "properties": {
    "iso:country":"US",
    "sg:address":"911 Greenland Rd",
    "sg:city":"Portsmouth",
    "sg:classifiers":[
        {
            "category":"Retail",
            "subcategory":"Animal Services",
            "type":"Services"
        }
    ],
    "sg:phone":"+1 603 436 3818",
    "sg:postcode":"03801",
    "sg:province":"NH",
    "sg:tags":[
        "training",
        "dog"
    ],
    "wof:name":"Lucky Dogs Obedience Training",
    "wof:placetype":"venue"
},
  "geometry": {"coordinates":[-70.797935,43.058411],"type":"Point"}
}