{
  "type": "Feature",
  "properties": {
    "iso:country":"US",
    "sg:address":"8 Bittersweet Ln",
    "sg:city":"Atkinson",
    "sg:classifiers":[
        {
            "category":"Government",
            "subcategory":"Court House",
            "type":"Public Place"
        }
    ],
    "sg:phone":"+1 603 362 4535",
    "sg:postcode":"03811",
    "sg:province":"NH",
    "sg:tags":[
        "justice",
        "peace"
    ],
    "wof:name":"A Justice Of The Peace",
    "wof:placetype":"venue"
},
  "geometry": {"coordinates":[-71.158902,42.83886],"type":"Point"}
}