{
  "type": "Feature",
  "properties": {
    "iso:country":"US",
    "sg:address":"153 Gosling Rd",
    "sg:city":"Portsmouth",
    "sg:classifiers":[
        {
            "category":"Farming",
            "subcategory":"Aquatic Farm",
            "type":"Manufacturing & Wholesale Goods"
        },
        {
            "category":"Wholesale",
            "subcategory":"Seafood",
            "type":"Manufacturing & Wholesale Goods"
        }
    ],
    "sg:phone":"+1 603 430 8057",
    "sg:postcode":"03801",
    "sg:province":"NH",
    "sg:tags":[
        "hatchery",
        "fish",
        "marine"
    ],
    "wof:name":"Greatbay Aquaculture LLC",
    "wof:placetype":"venue"
},
  "geometry": {"coordinates":[-70.79442899999999,43.094189],"type":"Point"}
}