{
  "type": "Feature",
  "properties": {
    "iso:country":"US",
    "sg:address":"382 Bedford Rd",
    "sg:city":"New Boston",
    "sg:classifiers":[
        {
            "category":"Professional",
            "subcategory":"Advertising",
            "type":"Services"
        }
    ],
    "sg:phone":"+1 603 669 2985",
    "sg:postcode":"03070",
    "sg:province":"NH",
    "wof:name":"Beanie Boy Creative Inc",
    "wof:placetype":"venue"
},
  "geometry": {"coordinates":[-71.64088099999999,42.981163],"type":"Point"}
}