{
  "type": "Feature",
  "properties": {
    "iso:country":"US",
    "sg:address":"129 State Rte 125",
    "sg:city":"Kingston",
    "sg:classifiers":[
        {
            "category":"Professional",
            "subcategory":"Research",
            "type":"Services"
        }
    ],
    "sg:phone":"+1 603 642 8300",
    "sg:postcode":"03848",
    "sg:province":"NH",
    "sg:tags":[
        "consultant",
        "wetland"
    ],
    "wof:name":"Seekamp Environmental Cnsltng",
    "wof:placetype":"venue"
},
  "geometry": {"coordinates":[-71.073517,42.899716],"type":"Point"}
}