{
  "type": "Feature",
  "properties": {
    "addr:full":"99 Milton Rd Rochester NH 03868",
    "addr:housenumber":"99",
    "addr:postcode":"03868",
    "addr:street":"Milton Rd",
    "iso:country":"US",
    "sg:address":"99 Milton Rd",
    "sg:city":"Rochester",
    "sg:classifiers":[
        {
            "category":"Shopping",
            "subcategory":"Discount & Variety Stores",
            "type":"Retail Goods"
        }
    ],
    "sg:phone":"+1 603 332 2853",
    "sg:postcode":"03868",
    "sg:province":"NH",
    "wof:name":"Pete's Variety",
    "wof:placetype":"venue"
},
  "geometry": {"coordinates":[-70.97382399999999,43.342656],"type":"Point"}
}