{
  "type": "Feature",
  "properties": {
    "iso:country":"US",
    "sg:address":"579 Warwick Rd",
    "sg:city":"Winchester",
    "sg:classifiers":[
        {
            "category":"Autos & Motor Vehicles",
            "subcategory":"Motorcycle Sales",
            "type":"Retail Goods"
        }
    ],
    "sg:phone":"+1 603 239 4665",
    "sg:postcode":"03470",
    "sg:province":"NH",
    "wof:name":"CFR Cycles",
    "wof:placetype":"venue"
},
  "geometry": {"coordinates":[-72.365466,42.733387],"type":"Point"}
}