{
  "type": "Feature",
  "properties": {
    "addr:full":"20 Kipling St Nashua NH 03062",
    "addr:housenumber":"20",
    "addr:postcode":"03062",
    "addr:street":"Kipling St",
    "iso:country":"US",
    "sg:address":"20 Kipling St",
    "sg:city":"Nashua",
    "sg:classifiers":[
        {
            "category":"Professional",
            "subcategory":"Engineering",
            "type":"Services"
        }
    ],
    "sg:phone":"+1 603 888 1138",
    "sg:postcode":"03062",
    "sg:province":"NH",
    "wof:name":"Karl J Klarman",
    "wof:placetype":"venue"
},
  "geometry": {"coordinates":[-71.468576,42.720872],"type":"Point"}
}