{
  "type": "Feature",
  "properties": {
    "iso:country":"US",
    "sg:address":"2 Market Sq",
    "sg:city":"Portsmouth",
    "sg:classifiers":[
        {
            "category":"Shopping",
            "subcategory":"Gifts & Souvenirs",
            "type":"Retail Goods"
        }
    ],
    "sg:phone":"+1 603 431 6641",
    "sg:postcode":"03801",
    "sg:province":"NH",
    "sg:tags":[
        "shop"
    ],
    "wof:name":"Warner's Hallmark Shop",
    "wof:placetype":"venue"
},
  "geometry": {"coordinates":[-70.757823,43.077012],"type":"Point"}
}