{
  "type": "Feature",
  "properties": {
    "iso:country":"US",
    "sg:address":"65 Cooksville Rd",
    "sg:city":"Plymouth",
    "sg:classifiers":[
        {
            "category":"Building & Trades",
            "subcategory":"Construction",
            "type":"Services"
        }
    ],
    "sg:phone":"+1 603 536 1383",
    "sg:postcode":"03264",
    "sg:province":"NH",
    "sg:tags":[
        "nonresidential"
    ],
    "wof:name":"Golden Rule Construction Co",
    "wof:placetype":"venue"
},
  "geometry": {"coordinates":[-71.701543,43.772904],"type":"Point"}
}