{
  "type": "Feature",
  "properties": {
    "iso:country":"US",
    "sg:address":"5 Brier Ln",
    "sg:city":"Chester",
    "sg:classifiers":[
        {
            "category":"Wholesale",
            "subcategory":"Medical Equipment & Supplies",
            "type":"Manufacturing & Wholesale Goods"
        }
    ],
    "sg:phone":"+1 603 887 5082",
    "sg:postcode":"03038",
    "sg:province":"NH",
    "sg:tags":[
        "physician",
        "surgeon"
    ],
    "wof:name":"Biologic Systems Corp",
    "wof:placetype":"venue"
},
  "geometry": {"coordinates":[-71.259868,42.885285],"type":"Point"}
}