{
  "type": "Feature",
  "properties": {
    "iso:country":"US",
    "sg:address":"308 State Rte 125",
    "sg:city":"Barrington",
    "sg:classifiers":[
        {
            "category":"Professional",
            "subcategory":"Accounting & Tax Preparation",
            "type":"Services"
        }
    ],
    "sg:phone":"+1 603 664 9334",
    "sg:postcode":"03825",
    "sg:province":"NH",
    "sg:tags":[
        "accountant"
    ],
    "sg:website":"www.pdcpa.com",
    "wof:name":"Paul J Dibona CPA",
    "wof:placetype":"venue"
},
  "geometry": {"coordinates":[-70.992508,43.221857],"type":"Point"}
}