{
  "type": "Feature",
  "properties": {
    "addr:full":"650 Amherst St Nashua NH 03063",
    "addr:housenumber":"650",
    "addr:postcode":"03063",
    "addr:street":"Amherst St",
    "iso:country":"US",
    "sg:address":"650 Amherst St",
    "sg:city":"Nashua",
    "sg:classifiers":[
        {
            "category":"Restaurant",
            "type":"Food & Drink"
        }
    ],
    "sg:menulink":"http://www.allmenus.com/nh/nashua/31058-gogo-pizza,-roast-beef--more/menu/",
    "sg:phone":"+1 603 882 0766",
    "sg:postcode":"03063",
    "sg:province":"NH",
    "sg:tags":[
        "american",
        "pizza"
    ],
    "wof:name":"GoGo Pizza, Roast Beef & More",
    "wof:placetype":"venue"
},
  "geometry": {"coordinates":[-71.54054600000001,42.802784],"type":"Point"}
}