{
  "type": "Feature",
  "properties": {
    "iso:country":"US",
    "sg:address":"36 Lowell Rd",
    "sg:city":"Salem",
    "sg:classifiers":[
        {
            "category":"Bakery",
            "type":"Food & Drink"
        },
        {
            "category":"Coffee & Tea",
            "type":"Food & Drink"
        },
        {
            "category":"Bagels",
            "type":"Food & Drink"
        },
        {
            "category":"Donuts",
            "type":"Food & Drink"
        }
    ],
    "sg:menulink":"http://www.allmenus.com/nh/salem/149191-dunkin-donuts/menu/",
    "sg:phone":"+1 603 890 9130",
    "sg:postcode":"03079",
    "sg:province":"NH",
    "sg:tags":[
        "wrap",
        "american",
        "sandwich",
        "pastry"
    ],
    "wof:name":"Dunkin' Donuts",
    "wof:placetype":"venue"
},
  "geometry": {"coordinates":[-71.239852,42.765351],"type":"Point"}
}