{
  "type": "Feature",
  "properties": {
    "iso:country":"US",
    "sg:address":"9 Blossom Rd",
    "sg:city":"Plaistow",
    "sg:classifiers":[
        {
            "category":"Home & Garden",
            "subcategory":"Carpets & Floor Coverings",
            "type":"Retail Goods"
        }
    ],
    "sg:phone":"+1 603 382 5333",
    "sg:postcode":"03865",
    "sg:province":"NH",
    "sg:tags":[
        "dealer",
        "rug"
    ],
    "wof:name":"Kingdom Contract Flooring LLC",
    "wof:placetype":"venue"
},
  "geometry": {"coordinates":[-71.10901200000001,42.828154],"type":"Point"}
}