{
  "type": "Feature",
  "properties": {
    "iso:country":"US",
    "sg:address":"29 New Rd",
    "sg:city":"North Hampton",
    "sg:classifiers":[
        {
            "category":"Retail",
            "subcategory":"Repair Shop",
            "type":"Services"
        }
    ],
    "sg:phone":"+1 603 964 5109",
    "sg:postcode":"03862",
    "sg:province":"NH",
    "wof:name":"Croston Upholstery",
    "wof:placetype":"venue"
},
  "geometry": {"coordinates":[-70.839276,42.981373],"type":"Point"}
}