{
  "type": "Feature",
  "properties": {
    "iso:country":"US",
    "sg:address":"19 Bridge St",
    "sg:city":"Lancaster",
    "sg:classifiers":[
        {
            "category":"Autos & Motor Vehicles",
            "subcategory":"Automobile Sales",
            "type":"Retail Goods"
        }
    ],
    "sg:phone":"+1 603 788 2504",
    "sg:postcode":"03584",
    "sg:province":"NH",
    "sg:tags":[
        "truck"
    ],
    "wof:name":"Mc Devitt Trucks",
    "wof:placetype":"venue"
},
  "geometry": {"coordinates":[-71.579972,44.496631],"type":"Point"}
}