{
  "type": "Feature",
  "properties": {
    "iso:country":"US",
    "sg:address":"777 Union Ave",
    "sg:city":"Laconia",
    "sg:classifiers":[
        {
            "category":"Shopping",
            "subcategory":"Used Merchandise",
            "type":"Retail Goods"
        }
    ],
    "sg:phone":"+1 603 524 4114",
    "sg:postcode":"03246",
    "sg:province":"NH",
    "sg:tags":[
        "antique"
    ],
    "wof:name":"Liberty Antiques & Cllctbls",
    "wof:placetype":"venue"
},
  "geometry": {"coordinates":[-71.463071,43.54618],"type":"Point"}
}