{
  "type": "Feature",
  "properties": {
    "addr:full":"63 High St Somersworth ME 03878",
    "addr:housenumber":"63",
    "addr:postcode":"03878",
    "addr:street":"High St",
    "iso:country":"US",
    "sg:address":"63 High St",
    "sg:city":"Somersworth",
    "sg:classifiers":[
        {
            "category":"Shopping",
            "subcategory":"Clothing, Apparel, & Fashions",
            "type":"Retail Goods"
        }
    ],
    "sg:phone":"+1 603 692 2295",
    "sg:postcode":"03878",
    "sg:province":"ME",
    "sg:tags":[
        "tailor"
    ],
    "wof:name":"S I's Alterations & Gift Shop",
    "wof:placetype":"venue"
},
  "geometry": {"coordinates":[-70.864738,43.262771],"type":"Point"}
}