{
  "type": "Feature",
  "properties": {
    "iso:country":"US",
    "sg:address":"23 Dumaine Ave",
    "sg:city":"Nashua",
    "sg:classifiers":[
        {
            "category":"Manufacturing",
            "subcategory":"Paper Products",
            "type":"Manufacturing & Wholesale Goods"
        }
    ],
    "sg:phone":"+1 603 595 0700",
    "sg:postcode":"03063",
    "sg:province":"NH",
    "sg:tags":[
        "box",
        "mill",
        "paperboard",
        "setup",
        "mfg"
    ],
    "wof:name":"Lowell Paper Box Co Inc",
    "wof:placetype":"venue"
},
  "geometry": {"coordinates":[-71.526342,42.792734],"type":"Point"}
}