{
  "type": "Feature",
  "properties": {
    "iso:country":"US",
    "sg:address":"535 Jewett Rd",
    "sg:city":"Contoocook",
    "sg:classifiers":[
        {
            "category":"Retail",
            "subcategory":"Animal Services",
            "type":"Services"
        }
    ],
    "sg:phone":"+1 603 224 3406",
    "sg:postcode":"03229",
    "sg:province":"NH",
    "sg:tags":[
        "passenger"
    ],
    "wof:name":"Contoocook Valley Farm",
    "wof:placetype":"venue"
},
  "geometry": {"coordinates":[-71.64436600000001,43.172074],"type":"Point"}
}