{
  "type": "Feature",
  "properties": {
    "iso:country":"US",
    "sg:address":"696 Hanover St",
    "sg:city":"Manchester",
    "sg:classifiers":[
        {
            "category":"Real Estate",
            "subcategory":"Real Estate Agent",
            "type":"Services"
        }
    ],
    "sg:phone":"+1 603 668 5240",
    "sg:postcode":"03104",
    "sg:province":"NH",
    "wof:name":"Lee Realty",
    "wof:placetype":"venue"
},
  "geometry": {"coordinates":[-71.434466,42.989113],"type":"Point"}
}