{
  "type": "Feature",
  "properties": {
    "iso:country":"US",
    "sg:address":"4 Country Club Rd",
    "sg:city":"Gilford",
    "sg:classifiers":[
        {
            "category":"Personal",
            "subcategory":"Beauty Salon",
            "type":"Services"
        }
    ],
    "sg:phone":"+1 603 528 4282",
    "sg:postcode":"03249",
    "sg:province":"NH",
    "wof:name":"Lake City Reflections",
    "wof:placetype":"venue"
},
  "geometry": {"coordinates":[-71.440355,43.529415],"type":"Point"}
}