{
  "type": "Feature",
  "properties": {
    "iso:country":"US",
    "sg:address":"11 Jady Hill Cir",
    "sg:city":"Exeter",
    "sg:classifiers":[
        {
            "category":"Shopping",
            "type":"Retail Goods"
        }
    ],
    "sg:phone":"+1 603 772 4538",
    "sg:postcode":"03833",
    "sg:province":"NH",
    "sg:tags":[
        "picture",
        "frame"
    ],
    "sg:website":"www.decorantiques.com",
    "wof:name":"Decor Antiques",
    "wof:placetype":"venue"
},
  "geometry": {"coordinates":[-70.941524,42.984208],"type":"Point"}
}