{
  "type": "Feature",
  "properties": {
    "iso:country":"US",
    "sg:address":"3073 White Mountain Hwy",
    "sg:city":"North Conway",
    "sg:classifiers":[
        {
            "category":"Health Services",
            "subcategory":"Optometrist",
            "type":"Services"
        }
    ],
    "sg:phone":"+1 603 356 6045",
    "sg:postcode":"03860",
    "sg:province":"NH",
    "wof:name":"Kirwan Stephen J OD",
    "wof:placetype":"venue"
},
  "geometry": {"coordinates":[-71.138496,44.0602],"type":"Point"}
}