{
  "type": "Feature",
  "properties": {
    "addr:full":"94 Grove St Peterborough NH 03458",
    "addr:housenumber":"94",
    "addr:postcode":"03458",
    "addr:street":"Grove St",
    "iso:country":"US",
    "sg:address":"94 Grove St",
    "sg:city":"Peterborough",
    "sg:classifiers":[
        {
            "category":"Professional",
            "subcategory":"Advertising",
            "type":"Services"
        }
    ],
    "sg:phone":"+1 603 924 6383",
    "sg:postcode":"03458",
    "sg:province":"NH",
    "sg:tags":[
        "agency"
    ],
    "wof:name":"Fletcher Wilder Communications",
    "wof:placetype":"venue"
},
  "geometry": {"coordinates":[-71.95132099999999,42.870779],"type":"Point"}
}