{
  "type": "Feature",
  "properties": {
    "addr:full":"1500 S Willow St Manchester NH 03103",
    "addr:housenumber":"1500",
    "addr:postcode":"03103",
    "addr:street":"S Willow St",
    "iso:country":"US",
    "sg:address":"1500 S Willow St",
    "sg:city":"Manchester",
    "sg:classifiers":[
        {
            "category":"Shopping",
            "type":"Retail Goods"
        }
    ],
    "sg:phone":"+1 603 669 7510",
    "sg:postcode":"03103",
    "sg:province":"NH",
    "sg:tags":[
        "telephone",
        "cellular"
    ],
    "wof:name":"Mobile Solution Corp",
    "wof:placetype":"venue"
},
  "geometry": {"coordinates":[-71.435833,42.956489],"type":"Point"}
}