{
  "type": "Feature",
  "properties": {
    "iso:country":"US",
    "sg:address":"9 Linlew Dr",
    "sg:city":"Derry",
    "sg:classifiers":[
        {
            "category":"Professional",
            "subcategory":"Business Services",
            "type":"Services"
        }
    ],
    "sg:phone":"+1 603 432 1906",
    "sg:postcode":"03038",
    "sg:province":"NH",
    "wof:name":"Norton Collection Solutions LL",
    "wof:placetype":"venue"
},
  "geometry": {"coordinates":[-71.32121100000001,42.902997],"type":"Point"}
}