{
  "type": "Feature",
  "properties": {
    "iso:country":"US",
    "sg:address":"1635 Summer St",
    "sg:city":"Bristol",
    "sg:classifiers":[
        {
            "category":"Retail",
            "subcategory":"Auto Repair",
            "type":"Services"
        }
    ],
    "sg:phone":"+1 603 744 7840",
    "sg:postcode":"03222",
    "sg:province":"NH",
    "sg:tags":[
        "repairing",
        "automobile"
    ],
    "wof:name":"Hanser Auto",
    "wof:placetype":"venue"
},
  "geometry": {"coordinates":[-71.684472,43.59824],"type":"Point"}
}