{
  "type": "Feature",
  "properties": {
    "addr:full":"540 W Swanzey Rd East Swanzey NH 03446",
    "addr:housenumber":"540",
    "addr:postcode":"03446",
    "addr:street":"W Swanzey Rd",
    "iso:country":"US",
    "sg:address":"540 W Swanzey Rd",
    "sg:city":"East Swanzey",
    "sg:classifiers":[
        {
            "category":"Building & Trades",
            "subcategory":"Construction",
            "type":"Services"
        }
    ],
    "sg:phone":"+1 603 357 1510",
    "sg:postcode":"03446",
    "sg:province":"NH",
    "sg:tags":[
        "house"
    ],
    "wof:name":"Roy Ayotte Construction",
    "wof:placetype":"venue"
},
  "geometry": {"coordinates":[-72.308374,42.896618],"type":"Point"}
}