{
  "type": "Feature",
  "properties": {
    "iso:country":"US",
    "sg:address":"2 Lavender Ct",
    "sg:city":"Merrimack",
    "sg:classifiers":[
        {
            "category":"Organizations",
            "subcategory":"Religious Organization",
            "type":"Services"
        }
    ],
    "sg:phone":"+1 603 424 6806",
    "sg:postcode":"03054",
    "sg:province":"NH",
    "sg:tags":[
        "church"
    ],
    "wof:name":"Faith Episcopal Church",
    "wof:placetype":"venue"
},
  "geometry": {"coordinates":[-71.49096900000001,42.88793],"type":"Point"}
}