{
  "type": "Feature",
  "properties": {
    "iso:country":"US",
    "sg:address":"Exit 17 off I-93",
    "sg:city":"Boscawen",
    "sg:classifiers":[
        {
            "category":"Park",
            "type":"Public Place"
        }
    ],
    "sg:phone":"+1 603 485 2034",
    "sg:postcode":"03303",
    "sg:province":"NH",
    "sg:website":"www.nhparks.state.nh.us/ParksPag...",
    "wof:name":"Hannah Duston Memorial",
    "wof:placetype":"venue"
},
  "geometry": {"coordinates":[-71.63534,43.33097],"type":"Point"}
}