{
  "type": "Feature",
  "properties": {
    "iso:country":"US",
    "sg:address":"57 Mill St",
    "sg:city":"Wolfeboro",
    "sg:classifiers":[
        {
            "category":"Personal",
            "subcategory":"Beauty Salon",
            "type":"Services"
        }
    ],
    "sg:phone":"+1 603 569 2213",
    "sg:postcode":"03894",
    "sg:province":"NH",
    "wof:name":"Mirror Images",
    "wof:placetype":"venue"
},
  "geometry": {"coordinates":[-71.215264,43.586218],"type":"Point"}
}