{
  "type": "Feature",
  "properties": {
    "iso:country":"US",
    "sg:address":"117 Walnut Hill Rd",
    "sg:city":"Derry",
    "sg:classifiers":[
        {
            "category":"Wholesale",
            "subcategory":"Construction Materials",
            "type":"Manufacturing & Wholesale Goods"
        }
    ],
    "sg:phone":"+1 603 434 2982",
    "sg:postcode":"03038",
    "sg:province":"NH",
    "sg:tags":[
        "building"
    ],
    "wof:name":"Manchester Res & Dev Bldg Mtls",
    "wof:placetype":"venue"
},
  "geometry": {"coordinates":[-71.245864,42.914843],"type":"Point"}
}