{
  "type": "Feature",
  "properties": {
    "addr:full":"382 Union Ave Laconia NH 03246",
    "addr:housenumber":"382",
    "addr:postcode":"03246",
    "addr:street":"Union Ave",
    "iso:country":"US",
    "sg:address":"382 Union Ave",
    "sg:city":"Laconia",
    "sg:classifiers":[
        {
            "category":"Professional",
            "subcategory":"Advertising",
            "type":"Services"
        }
    ],
    "sg:phone":"+1 603 528 0101",
    "sg:postcode":"03246",
    "sg:province":"NH",
    "wof:name":"Rutter Media",
    "wof:placetype":"venue"
},
  "geometry": {"coordinates":[-71.463291,43.535699],"type":"Point"}
}