{
  "type": "Feature",
  "properties": {
    "addr:full":"67 Bow St Portsmouth NH 03801",
    "addr:housenumber":"67",
    "addr:postcode":"03801",
    "addr:street":"Bow St",
    "iso:country":"US",
    "sg:address":"67 Bow St",
    "sg:city":"Portsmouth",
    "sg:classifiers":[
        {
            "category":"Restaurant",
            "type":"Food & Drink"
        }
    ],
    "sg:phone":"+1 603 433 4441",
    "sg:postcode":"03801",
    "sg:province":"NH",
    "sg:tags":[
        "eating"
    ],
    "wof:name":"Harpoon Willy's",
    "wof:placetype":"venue"
},
  "geometry": {"coordinates":[-70.756681,43.078698],"type":"Point"}
}