{
  "type": "Feature",
  "properties": {
    "iso:country":"US",
    "sg:address":"633 Champlain St",
    "sg:city":"Berlin",
    "sg:classifiers":[
        {
            "category":"Retail",
            "subcategory":"Repair Shop",
            "type":"Services"
        }
    ],
    "sg:phone":"+1 603 752 6166",
    "sg:postcode":"03570",
    "sg:province":"NH",
    "sg:tags":[
        "television",
        "radio"
    ],
    "wof:name":"Steve's Electronics",
    "wof:placetype":"venue"
},
  "geometry": {"coordinates":[-71.174837,44.469501],"type":"Point"}
}