{
  "type": "Feature",
  "properties": {
    "addr:full":"7 Bloody Brook Road Hampstead NH 03841",
    "addr:housenumber":"7",
    "addr:postcode":"03841",
    "addr:street":"Bloody Brook Road",
    "iso:country":"US",
    "sg:address":"7 Bloody Brook Road",
    "sg:city":"Hampstead",
    "sg:classifiers":[
        {
            "category":"Professional",
            "subcategory":"Computer Services",
            "type":"Services"
        }
    ],
    "sg:phone":"+1 603 329 6293",
    "sg:postcode":"03841",
    "sg:province":"NH",
    "sg:tags":[
        "recommendations",
        "search",
        "reviews",
        "vendors",
        "b2b",
        "crowdsourcing",
        "networking",
        "business-networking",
        "trusted-vendor"
    ],
    "sg:website":"http://www.VendorCity.com",
    "wof:name":"VendorCity",
    "wof:placetype":"venue"
},
  "geometry": {"coordinates":[-71.170489,42.891721],"type":"Point"}
}