{
  "type": "Feature",
  "properties": {
    "iso:country":"US",
    "sg:address":"6 Tsienneto Rd",
    "sg:city":"Derry",
    "sg:classifiers":[
        {
            "category":"Health Services",
            "subcategory":"Doctor",
            "type":"Services"
        }
    ],
    "sg:phone":"+1 603 893 7185",
    "sg:postcode":"03038",
    "sg:province":"NH",
    "sg:tags":[
        "physician",
        "surgeon"
    ],
    "wof:name":"Edward Yourtee MD",
    "wof:placetype":"venue"
},
  "geometry": {"coordinates":[-71.32207099999999,42.898838],"type":"Point"}
}