{
  "type": "Feature",
  "properties": {
    "iso:country":"US",
    "sg:address":"1168 Concord St",
    "sg:city":"Antrim",
    "sg:classifiers":[
        {
            "category":"Retail",
            "subcategory":"Auto Repair",
            "type":"Services"
        }
    ],
    "sg:phone":"+1 603 464 5045",
    "sg:postcode":"03440",
    "sg:province":"NH",
    "sg:tags":[
        "repairing",
        "automobile"
    ],
    "wof:name":"Chuck's Auto Repair Of Antrim",
    "wof:placetype":"venue"
},
  "geometry": {"coordinates":[-71.91949099999999,43.089573],"type":"Point"}
}