{
  "type": "Feature",
  "properties": {
    "addr:full":"230 State Rte 103A New London NH 03257",
    "addr:housenumber":"230",
    "addr:postcode":"03257",
    "addr:street":"State Rte 103A",
    "iso:country":"US",
    "sg:address":"230 State Rte 103A",
    "sg:city":"New London",
    "sg:classifiers":[
        {
            "category":"Education",
            "subcategory":"Dance Studio",
            "type":"Public Place"
        }
    ],
    "sg:phone":"+1 603 763 2047",
    "sg:postcode":"03257",
    "sg:province":"NH",
    "sg:tags":[
        "instruction",
        "dancing"
    ],
    "wof:name":"Harrison School Of Dance",
    "wof:placetype":"venue"
},
  "geometry": {"coordinates":[-72.032526,43.402892],"type":"Point"}
}