{
  "type": "Feature",
  "properties": {
    "addr:full":"12 Pine Knoll Dr Atkinson NH 03811",
    "addr:housenumber":"12",
    "addr:postcode":"03811",
    "addr:street":"Pine Knoll Dr",
    "iso:country":"US",
    "sg:address":"12 Pine Knoll Dr",
    "sg:city":"Atkinson",
    "sg:classifiers":[
        {
            "category":"Professional",
            "subcategory":"Business Services",
            "type":"Services"
        }
    ],
    "sg:phone":"+1 603 362 5569",
    "sg:postcode":"03811",
    "sg:province":"NH",
    "sg:tags":[
        "interior",
        "consultant",
        "design",
        "decorator"
    ],
    "wof:name":"Cynthia J Vocell Assoc",
    "wof:placetype":"venue"
},
  "geometry": {"coordinates":[-71.132678,42.852537],"type":"Point"}
}