{
  "type": "Feature",
  "properties": {
    "iso:country":"US",
    "sg:address":"2 Buxton Industrial Dr",
    "sg:city":"Henniker",
    "sg:classifiers":[
        {
            "category":"Manufacturing",
            "subcategory":"Lumber",
            "type":"Manufacturing & Wholesale Goods"
        }
    ],
    "sg:phone":"+1 603 428 3298",
    "sg:postcode":"03242",
    "sg:province":"NH",
    "sg:tags":[
        "sawmill"
    ],
    "sg:website":"www.hhp-inc.com",
    "wof:name":"HHP Inc",
    "wof:placetype":"venue"
},
  "geometry": {"coordinates":[-71.770179,43.177512],"type":"Point"}
}