{
  "type": "Feature",
  "properties": {
    "iso:country":"US",
    "sg:address":"526 Meriden Rd",
    "sg:city":"Lebanon",
    "sg:classifiers":[
        {
            "category":"Manufacturing",
            "subcategory":"Lumber",
            "type":"Manufacturing & Wholesale Goods"
        }
    ],
    "sg:phone":"+1 603 448 5540",
    "sg:postcode":"03766",
    "sg:province":"NH",
    "sg:tags":[
        "sawmill"
    ],
    "wof:name":"G H Evarts & Co",
    "wof:placetype":"venue"
},
  "geometry": {"coordinates":[-72.219734,43.60895],"type":"Point"}
}