{
  "type": "Feature",
  "properties": {
    "iso:country":"US",
    "sg:address":"211 Peaked Hill Rd",
    "sg:city":"Bristol",
    "sg:classifiers":[
        {
            "category":"Home & Garden",
            "subcategory":"Household Appliances",
            "type":"Retail Goods"
        }
    ],
    "sg:phone":"+1 603 744 2000",
    "sg:postcode":"03222",
    "sg:province":"NH",
    "wof:name":"Alpine Appliance Repair Co",
    "wof:placetype":"venue"
},
  "geometry": {"coordinates":[-71.71123799999999,43.603716],"type":"Point"}
}