{
  "type": "Feature",
  "properties": {
    "iso:country":"US",
    "sg:address":"225 S Broadway",
    "sg:city":"Salem",
    "sg:classifiers":[
        {
            "category":"Restaurant",
            "type":"Food & Drink"
        }
    ],
    "sg:menulink":"http://www.allmenus.com/nh/salem/194516-mcdonalds/menu/",
    "sg:phone":"+1 603 685 6080",
    "sg:postcode":"03079",
    "sg:province":"NH",
    "sg:tags":[
        "burger",
        "american"
    ],
    "wof:name":"McDonald's",
    "wof:placetype":"venue"
},
  "geometry": {"coordinates":[-71.21570699999999,42.76294],"type":"Point"}
}