{
  "type": "Feature",
  "properties": {
    "iso:country":"US",
    "sg:address":"87 Morningside Dr",
    "sg:city":"Laconia",
    "sg:classifiers":[
        {
            "category":"Real Estate",
            "subcategory":"Real Estate Operator",
            "type":"Services"
        }
    ],
    "sg:phone":"+1 603 524 2029",
    "sg:postcode":"03246",
    "sg:province":"NH",
    "sg:tags":[
        "building",
        "nonresidential"
    ],
    "wof:name":"Medical Office Building Assn",
    "wof:placetype":"venue"
},
  "geometry": {"coordinates":[-71.47785500000001,43.544682],"type":"Point"}
}