{
  "type": "Feature",
  "properties": {
    "iso:country":"US",
    "sg:address":"20 Ash St",
    "sg:city":"Hollis",
    "sg:classifiers":[
        {
            "category":"Restaurant",
            "type":"Food & Drink"
        }
    ],
    "sg:phone":"+1 603 465 7200",
    "sg:postcode":"03049",
    "sg:province":"NH",
    "sg:tags":[
        "pizza"
    ],
    "wof:name":"Christophers Subs & Pizza",
    "wof:placetype":"venue"
},
  "geometry": {"coordinates":[-71.58762,42.742896],"type":"Point"}
}