{
  "type": "Feature",
  "properties": {
    "addr:full":"294 State Rte 101 Amherst NH 03031",
    "addr:housenumber":"294",
    "addr:postcode":"03031",
    "addr:street":"State Rte 101",
    "iso:country":"US",
    "sg:address":"294 State Rte 101",
    "sg:city":"Amherst",
    "sg:classifiers":[
        {
            "category":"Education",
            "subcategory":"Special Training",
            "type":"Public Place"
        }
    ],
    "sg:phone":"+1 603 672 4844",
    "sg:postcode":"03031",
    "sg:province":"NH",
    "sg:tags":[
        "instruction",
        "music"
    ],
    "wof:name":"Souhegan Piano Instruction",
    "wof:placetype":"venue"
},
  "geometry": {"coordinates":[-71.603223,42.897178],"type":"Point"}
}