{
  "type": "Feature",
  "properties": {
    "iso:country":"US",
    "sg:address":"6 Strawberry Hill Rd",
    "sg:city":"Derry",
    "sg:classifiers":[
        {
            "category":"Manufacturing",
            "subcategory":"Tools & Machinery",
            "type":"Manufacturing & Wholesale Goods"
        }
    ],
    "sg:phone":"+1 603 432 4172",
    "sg:postcode":"03038",
    "sg:province":"NH",
    "sg:tags":[
        "industrial",
        "mfg"
    ],
    "wof:name":"Affordable Stump Grinding",
    "wof:placetype":"venue"
},
  "geometry": {"coordinates":[-71.31209,42.866675],"type":"Point"}
}