{
  "type": "Feature",
  "properties": {
    "addr:full":"149 Main St Franconia NH 03580",
    "addr:housenumber":"149",
    "addr:postcode":"03580",
    "addr:street":"Main St",
    "iso:country":"US",
    "sg:address":"149 Main St",
    "sg:city":"Franconia",
    "sg:classifiers":[
        {
            "category":"Education",
            "subcategory":"School",
            "type":"Public Place"
        }
    ],
    "sg:phone":"+1 603 823 7741",
    "sg:postcode":"03580",
    "sg:province":"NH",
    "wof:name":"Lafayette Regional School",
    "wof:placetype":"venue"
},
  "geometry": {"coordinates":[-71.747953,44.227383],"type":"Point"}
}