{
  "type": "Feature",
  "properties": {
    "addr:full":"62 Littleworth Rd Dover NH 03820",
    "addr:housenumber":"62",
    "addr:postcode":"03820",
    "addr:street":"Littleworth Rd",
    "iso:country":"US",
    "sg:address":"62 Littleworth Rd",
    "sg:city":"Dover",
    "sg:classifiers":[
        {
            "category":"Shopping",
            "subcategory":"Stationery & Office Supplies",
            "type":"Retail Goods"
        }
    ],
    "sg:phone":"+1 603 742 4324",
    "sg:postcode":"03820",
    "sg:province":"NH",
    "sg:tags":[
        "furniture"
    ],
    "sg:website":"www.goodwinsoffice.com",
    "wof:name":"Goodwins Office Products LLC",
    "wof:placetype":"venue"
},
  "geometry": {"coordinates":[-70.913515,43.187813],"type":"Point"}
}