{
  "type": "Feature",
  "properties": {
    "addr:full":"14 Holman Way Chester NH 03036",
    "addr:housenumber":"14",
    "addr:postcode":"03036",
    "addr:street":"Holman Way",
    "iso:country":"US",
    "sg:address":"14 Holman Way",
    "sg:city":"Chester",
    "sg:classifiers":[
        {
            "category":"Professional",
            "subcategory":"Management & Consulting",
            "type":"Services"
        }
    ],
    "sg:phone":"+1 603 887 1762",
    "sg:postcode":"03036",
    "sg:province":"NH",
    "sg:tags":[
        "consultant"
    ],
    "wof:name":"Raven Gregg Consultant",
    "wof:placetype":"venue"
},
  "geometry": {"coordinates":[-71.17652,42.982107],"type":"Point"}
}