{
  "type": "Feature",
  "properties": {
    "addr:full":"2 Mundy Ln Merrimack NH 03038",
    "addr:housenumber":"2",
    "addr:postcode":"03038",
    "addr:street":"Mundy Ln",
    "iso:country":"US",
    "sg:address":"2 Mundy Ln",
    "sg:city":"Merrimack",
    "sg:classifiers":[
        {
            "category":"Shopping",
            "subcategory":"Computers & Home Electronics",
            "type":"Retail Goods"
        }
    ],
    "sg:phone":"+1 603 424 1088",
    "sg:postcode":"03038",
    "sg:province":"NH",
    "sg:tags":[
        "software"
    ],
    "wof:name":"Turcotte Consulting & Design",
    "wof:placetype":"venue"
},
  "geometry": {"coordinates":[-71.294287,42.911187],"type":"Point"}
}