{
  "type": "Feature",
  "properties": {
    "iso:country":"US",
    "sg:address":"5 Market Ln",
    "sg:city":"Concord",
    "sg:classifiers":[
        {
            "category":"Professional",
            "type":"Services"
        }
    ],
    "sg:phone":"+1 603 226 7516",
    "sg:postcode":"03301",
    "sg:province":"NH",
    "sg:tags":[
        "establishment"
    ],
    "wof:name":"Parent Child Ctr",
    "wof:placetype":"venue"
},
  "geometry": {"coordinates":[-71.536293,43.204603],"type":"Point"}
}