{
  "type": "Feature",
  "properties": {
    "addr:full":"7 Colby Ct Bedford NH 03110",
    "addr:housenumber":"7",
    "addr:postcode":"03110",
    "addr:street":"Colby Ct",
    "iso:country":"US",
    "sg:address":"7 Colby Ct",
    "sg:city":"Bedford",
    "sg:classifiers":[
        {
            "category":"Bakery",
            "type":"Food & Drink"
        }
    ],
    "sg:menulink":"http://www.allmenus.com/nh/bedford/105914-panera-bread/menu/",
    "sg:phone":"+1 603 641 0500",
    "sg:postcode":"03110",
    "sg:province":"NH",
    "sg:tags":[
        "american",
        "sandwich",
        "pastry"
    ],
    "wof:name":"Panera Bread",
    "wof:placetype":"venue"
},
  "geometry": {"coordinates":[-71.48207499999999,42.963414],"type":"Point"}
}