{
  "type": "Feature",
  "properties": {
    "iso:country":"US",
    "sg:address":"439 State Rte 108",
    "sg:city":"Somersworth",
    "sg:classifiers":[
        {
            "category":"Home & Garden",
            "subcategory":"Hardware",
            "type":"Retail Goods"
        }
    ],
    "sg:phone":"+1 603 335 2582",
    "sg:postcode":"03878",
    "sg:province":"NH",
    "sg:tags":[
        "saw"
    ],
    "wof:name":"Tri-City Tool Cribs",
    "wof:placetype":"venue"
},
  "geometry": {"coordinates":[-70.90774999999999,43.266407],"type":"Point"}
}