{
  "type": "Feature",
  "properties": {
    "addr:full":"185 Union St Littleton NH 03561",
    "addr:housenumber":"185",
    "addr:postcode":"03561",
    "addr:street":"Union St",
    "iso:country":"US",
    "sg:address":"185 Union St",
    "sg:city":"Littleton",
    "sg:classifiers":[
        {
            "category":"Shopping",
            "subcategory":"Clothing, Apparel, & Fashions",
            "type":"Retail Goods"
        }
    ],
    "sg:phone":"+1 603 444 0328",
    "sg:postcode":"03561",
    "sg:province":"NH",
    "sg:tags":[
        "sportswear"
    ],
    "wof:name":"Lahouts Discount Warehouse",
    "wof:placetype":"venue"
},
  "geometry": {"coordinates":[-71.761895,44.309236],"type":"Point"}
}