{
  "type": "Feature",
  "properties": {
    "iso:country":"US",
    "sg:address":"5 Forest St",
    "sg:city":"Atkinson",
    "sg:classifiers":[
        {
            "category":"Professional",
            "type":"Services"
        }
    ],
    "sg:phone":"+1 603 362 5188",
    "sg:postcode":"03811",
    "sg:province":"NH",
    "sg:tags":[
        "establishment"
    ],
    "wof:name":"Digital Entropy Inc",
    "wof:placetype":"venue"
},
  "geometry": {"coordinates":[-71.147063,42.821112],"type":"Point"}
}