{
  "type": "Feature",
  "properties": {
    "iso:country":"US",
    "sg:address":"506 Oak St",
    "sg:city":"Newport",
    "sg:classifiers":[
        {
            "category":"Building & Trades",
            "subcategory":"Construction",
            "type":"Services"
        },
        {
            "category":"Retail",
            "subcategory":"Auto Repair",
            "type":"Services"
        }
    ],
    "sg:phone":"+1 603 863 0658",
    "sg:postcode":"03773",
    "sg:province":"NH",
    "sg:tags":[
        "glass"
    ],
    "wof:name":"Northville Auto Glass Service",
    "wof:placetype":"venue"
},
  "geometry": {"coordinates":[-72.210168,43.387925],"type":"Point"}
}