{
  "type": "Feature",
  "properties": {
    "iso:country":"US",
    "sg:address":"8 Birch Wood Dr",
    "sg:city":"Londonderry",
    "sg:classifiers":[
        {
            "category":"Travel",
            "subcategory":"Travel Agent",
            "type":"Entertainment"
        }
    ],
    "sg:phone":"+1 603 432 2816",
    "sg:postcode":"03053",
    "sg:province":"NH",
    "sg:tags":[
        "tours",
        "promoter"
    ],
    "wof:name":"Jones Student Travel",
    "wof:placetype":"venue"
},
  "geometry": {"coordinates":[-71.351923,42.847236],"type":"Point"}
}