{
  "type": "Feature",
  "properties": {
    "iso:country":"US",
    "sg:address":"16 Hoyt Rd",
    "sg:city":"Goffstown",
    "sg:classifiers":[
        {
            "category":"Building & Trades",
            "subcategory":"Cleaning & Sanitation",
            "type":"Services"
        }
    ],
    "sg:phone":"+1 603 497 3787",
    "sg:postcode":"03045",
    "sg:province":"NH",
    "sg:tags":[
        "maintenance"
    ],
    "wof:name":"Storm Chasers",
    "wof:placetype":"venue"
},
  "geometry": {"coordinates":[-71.563599,43.053061],"type":"Point"}
}