{
  "type": "Feature",
  "properties": {
    "iso:country":"US",
    "sg:address":"545 Main St",
    "sg:city":"Gorham",
    "sg:classifiers":[
        {
            "category":"Autos & Motor Vehicles",
            "subcategory":"Automobile Sales",
            "type":"Retail Goods"
        }
    ],
    "sg:phone":"+1 603 752 3700",
    "sg:postcode":"03581",
    "sg:province":"NH",
    "sg:tags":[
        "car",
        "dealer"
    ],
    "wof:name":"Berlin City Chevrolet",
    "wof:placetype":"venue"
},
  "geometry": {"coordinates":[-71.19239399999999,44.429687],"type":"Point"}
}