{
  "type": "Feature",
  "properties": {
    "iso:country":"US",
    "sg:address":"7 Jeff Ln",
    "sg:city":"Litchfield",
    "sg:classifiers":[
        {
            "category":"Freight",
            "type":"Transportation"
        }
    ],
    "sg:phone":"+1 603 424 8606",
    "sg:postcode":"03052",
    "sg:province":"NH",
    "sg:tags":[
        "operator",
        "trucking"
    ],
    "wof:name":"Jrm Trucking & Leasing",
    "wof:placetype":"venue"
},
  "geometry": {"coordinates":[-71.45857599999999,42.875433],"type":"Point"}
}