{
  "type": "Feature",
  "properties": {
    "iso:country":"US",
    "sg:address":"836 Elm St",
    "sg:city":"Manchester",
    "sg:classifiers":[
        {
            "category":"Food & Beverages",
            "subcategory":"Bakery",
            "type":"Retail Goods"
        }
    ],
    "sg:phone":"+1 603 647 7100",
    "sg:postcode":"03101",
    "sg:province":"NH",
    "sg:tags":[
        "baker"
    ],
    "wof:name":"Lala's Hungarian Pastry",
    "wof:placetype":"venue"
},
  "geometry": {"coordinates":[-71.46310200000001,42.989414],"type":"Point"}
}