{
  "type": "Feature",
  "properties": {
    "addr:full":"264 Lafayette Rd Hampton NH 03842",
    "addr:housenumber":"264",
    "addr:postcode":"03842",
    "iso:country":"US",
    "sg:address":"264 Lafayette Rd",
    "sg:city":"Hampton",
    "sg:classifiers":[
        {
            "category":"Banks & Credit Unions",
            "subcategory":"Bank",
            "type":"Services"
        }
    ],
    "sg:phone":"+1 603 926 8894",
    "sg:postcode":"03842",
    "sg:province":"NH",
    "sg:tags":[
        "state",
        "commercial"
    ],
    "wof:name":"Fleet",
    "wof:placetype":"venue"
},
  "geometry": {"coordinates":[-70.83844000000001,42.935966],"type":"Point"}
}