{
  "type": "Feature",
  "properties": {
    "iso:country":"US",
    "sg:address":"17 Armory Rd",
    "sg:city":"Milford",
    "sg:classifiers":[
        {
            "category":"Utilities",
            "subcategory":"Electric",
            "type":"Services"
        }
    ],
    "sg:phone":"+1 603 672 1372",
    "sg:postcode":"03055",
    "sg:province":"NH",
    "wof:name":"Public Service Company NH",
    "wof:placetype":"venue"
},
  "geometry": {"coordinates":[-71.649142,42.816292],"type":"Point"}
}