{
  "type": "Feature",
  "properties": {
    "iso:country":"US",
    "sg:address":"99 Murphy St",
    "sg:city":"Manchester",
    "sg:classifiers":[
        {
            "category":"Retail",
            "subcategory":"Portrait Studio",
            "type":"Services"
        }
    ],
    "sg:phone":"+1 603 644 7873",
    "sg:postcode":"03103",
    "sg:province":"NH",
    "sg:tags":[
        "photography"
    ],
    "wof:name":"Studio 54 Inc",
    "wof:placetype":"venue"
},
  "geometry": {"coordinates":[-71.448606,42.95038],"type":"Point"}
}