{
  "type": "Feature",
  "properties": {
    "addr:full":"57 Olde Lantern Rd Bedford NH 03110",
    "addr:housenumber":"57",
    "addr:postcode":"03110",
    "addr:street":"Olde Lantern Rd",
    "iso:country":"US",
    "sg:address":"57 Olde Lantern Rd",
    "sg:city":"Bedford",
    "sg:classifiers":[
        {
            "category":"Home & Garden",
            "subcategory":"Hardware",
            "type":"Retail Goods"
        }
    ],
    "sg:phone":"+1 603 488 1869",
    "sg:postcode":"03110",
    "sg:province":"NH",
    "sg:tags":[
        "steel",
        "stainless",
        "tool"
    ],
    "wof:name":"TNT Toys Inc",
    "wof:placetype":"venue"
},
  "geometry": {"coordinates":[-71.563194,42.954172],"type":"Point"}
}