{
  "type": "Feature",
  "properties": {
    "addr:full":"883 Ocean Blvd Hampton NH 03842",
    "addr:housenumber":"883",
    "addr:postcode":"03842",
    "addr:street":"Ocean Blvd",
    "iso:country":"US",
    "sg:address":"883 Ocean Blvd",
    "sg:city":"Hampton",
    "sg:classifiers":[
        {
            "category":"Wholesale",
            "subcategory":"Books, Periodicals, & Newspapers",
            "type":"Manufacturing & Wholesale Goods"
        }
    ],
    "sg:phone":"+1 603 926 1084",
    "sg:postcode":"03842",
    "sg:province":"NH",
    "sg:tags":[
        "publishers-periodical"
    ],
    "sg:website":"http://www.penton.com",
    "wof:name":"Penton Media, Inc.",
    "wof:placetype":"venue"
},
  "geometry": {"coordinates":[-70.795513,42.938106],"type":"Point"}
}