{
  "type": "Feature",
  "properties": {
    "iso:country":"US",
    "sg:address":"209 First New Hampshire Tpke",
    "sg:city":"Northwood",
    "sg:classifiers":[
        {
            "category":"Professional",
            "subcategory":"Research",
            "type":"Services"
        }
    ],
    "sg:phone":"+1 603 942 7230",
    "sg:postcode":"03261",
    "sg:province":"NH",
    "sg:tags":[
        "environmental",
        "ecological"
    ],
    "wof:name":"North Ridge Environmental",
    "wof:placetype":"venue"
},
  "geometry": {"coordinates":[-71.158119,43.19851],"type":"Point"}
}