{
  "type": "Feature",
  "properties": {
    "iso:country":"US",
    "sg:address":"9 Mary Ave",
    "sg:city":"Raymond",
    "sg:classifiers":[
        {
            "category":"Shopping",
            "subcategory":"Crafts & Fabrics",
            "type":"Retail Goods"
        }
    ],
    "sg:phone":"+1 603 244 1098",
    "sg:postcode":"03077",
    "sg:province":"NH",
    "sg:tags":[
        "sewing",
        "machines-household"
    ],
    "wof:name":"Technico Sewing Machine",
    "wof:placetype":"venue"
},
  "geometry": {"coordinates":[-71.166267,43.002522],"type":"Point"}
}