{
  "type": "Feature",
  "properties": {
    "iso:country":"US",
    "sg:address":"72 Tallant Rd",
    "sg:city":"Pelham",
    "sg:classifiers":[
        {
            "category":"Building & Trades",
            "subcategory":"Electrical",
            "type":"Services"
        }
    ],
    "sg:phone":"+1 603 635 0400",
    "sg:postcode":"03076",
    "sg:province":"NH",
    "sg:tags":[
        "electric",
        "contractor"
    ],
    "wof:name":"Tek Electric",
    "wof:placetype":"venue"
},
  "geometry": {"coordinates":[-71.342479,42.7663],"type":"Point"}
}