{
  "type": "Feature",
  "properties": {
    "iso:country":"US",
    "sg:address":"121 Calef Hwy",
    "sg:city":"Epping",
    "sg:classifiers":[
        {
            "category":"Real Estate",
            "subcategory":"Real Estate Agent",
            "type":"Services"
        }
    ],
    "sg:phone":"+1 603 679 2300",
    "sg:postcode":"03042",
    "sg:province":"NH",
    "sg:website":"www.bridgerealty.com",
    "wof:name":"Century 21",
    "wof:placetype":"venue"
},
  "geometry": {"coordinates":[-71.07056799999999,43.03519],"type":"Point"}
}