{
  "type": "Feature",
  "properties": {
    "addr:full":"6 Mechanic St Alstead NH 03602",
    "addr:housenumber":"6",
    "addr:postcode":"03602",
    "addr:street":"Mechanic St",
    "iso:country":"US",
    "sg:address":"6 Mechanic St",
    "sg:city":"Alstead",
    "sg:classifiers":[
        {
            "category":"Real Estate",
            "subcategory":"Real Estate Agent",
            "type":"Services"
        }
    ],
    "sg:phone":"+1 603 835 6944",
    "sg:postcode":"03602",
    "sg:province":"NH",
    "wof:name":"Leslie Honey Real Estate",
    "wof:placetype":"venue"
},
  "geometry": {"coordinates":[-72.352321,43.150476],"type":"Point"}
}