{
  "type": "Feature",
  "properties": {
    "addr:full":"36 Crummet Hill Rd Barrington NH 03825",
    "addr:housenumber":"36",
    "addr:postcode":"03825",
    "addr:street":"Crummet Hill Rd",
    "iso:country":"US",
    "sg:address":"36 Crummet Hill Rd",
    "sg:city":"Barrington",
    "sg:classifiers":[
        {
            "category":"Building & Trades",
            "subcategory":"Landscaping Services",
            "type":"Services"
        }
    ],
    "sg:phone":"+1 603 868 7520",
    "sg:postcode":"03825",
    "sg:province":"NH",
    "sg:tags":[
        "landscape"
    ],
    "wof:name":"Rivet Landscaping",
    "wof:placetype":"venue"
},
  "geometry": {"coordinates":[-71.019998,43.146082],"type":"Point"}
}