{
  "type": "Feature",
  "properties": {
    "iso:country":"US",
    "sg:address":"311 Centre St",
    "sg:city":"Sullivan",
    "sg:classifiers":[
        {
            "category":"Government",
            "subcategory":"Post Office",
            "type":"Public Place"
        }
    ],
    "sg:phone":"+1 603 847 9720",
    "sg:postcode":"03445",
    "sg:province":"NH",
    "wof:name":"US Post Office",
    "wof:placetype":"venue"
},
  "geometry": {"coordinates":[-72.194947,42.993874],"type":"Point"}
}