{
  "type": "Feature",
  "properties": {
    "iso:country":"US",
    "sg:address":"54 Morways Park",
    "sg:city":"Charlestown",
    "sg:classifiers":[
        {
            "category":"Banks & Credit Unions",
            "subcategory":"Investment Brokerage",
            "type":"Services"
        }
    ],
    "sg:phone":"+1 603 826 5222",
    "sg:postcode":"03603",
    "sg:province":"NH",
    "sg:tags":[
        "advisory",
        "financial"
    ],
    "wof:name":"Carleton's Money Broker Svc",
    "wof:placetype":"venue"
},
  "geometry": {"coordinates":[-72.40945499999999,43.259243],"type":"Point"}
}