{
  "type": "Feature",
  "properties": {
    "iso:country":"US",
    "sg:address":"161 Court St",
    "sg:city":"Laconia",
    "sg:classifiers":[
        {
            "category":"Restaurant",
            "type":"Food & Drink"
        }
    ],
    "sg:menulink":"http://www.allmenus.com/nh/laconia/87132-little-caesars-pizza/menu/",
    "sg:phone":"+1 603 524 4111",
    "sg:postcode":"03246",
    "sg:province":"NH",
    "sg:tags":[
        "american",
        "pizza"
    ],
    "wof:name":"Little Caesar's Pizza",
    "wof:placetype":"venue"
},
  "geometry": {"coordinates":[-71.472883,43.522581],"type":"Point"}
}