{
  "type": "Feature",
  "properties": {
    "iso:country":"US",
    "sg:address":"28 Pleasant St",
    "sg:city":"Colebrook",
    "sg:classifiers":[
        {
            "category":"Organizations",
            "subcategory":"Religious Organization",
            "type":"Services"
        }
    ],
    "sg:phone":"+1 603 237 4342",
    "sg:postcode":"03576",
    "sg:province":"NH",
    "sg:tags":[
        "church"
    ],
    "wof:name":"St Brendan's Rectory",
    "wof:placetype":"venue"
},
  "geometry": {"coordinates":[-71.49242,44.893752],"type":"Point"}
}