{
  "type": "Feature",
  "properties": {
    "iso:country":"US",
    "sg:address":"9 Centerville Dr",
    "sg:city":"Salem",
    "sg:classifiers":[
        {
            "category":"Shopping",
            "subcategory":"Clothing, Apparel, & Fashions",
            "type":"Retail Goods"
        }
    ],
    "sg:phone":"+1 603 898 4455",
    "sg:postcode":"03079",
    "sg:province":"NH",
    "sg:tags":[
        "garment"
    ],
    "wof:name":"Bumpy Roads Apparel",
    "wof:placetype":"venue"
},
  "geometry": {"coordinates":[-71.21574099999999,42.783673],"type":"Point"}
}