{
  "type": "Feature",
  "properties": {
    "iso:country":"US",
    "sg:address":"292 State Rte 101",
    "sg:city":"Amherst",
    "sg:classifiers":[
        {
            "category":"Wholesale",
            "subcategory":"Home Furnishings",
            "type":"Manufacturing & Wholesale Goods"
        }
    ],
    "sg:phone":"+1 603 673 7498",
    "sg:postcode":"03031",
    "sg:province":"NH",
    "sg:tags":[
        "blind",
        "retail"
    ],
    "wof:name":"Budget Blinds Of Amherst",
    "wof:placetype":"venue"
},
  "geometry": {"coordinates":[-71.60238699999999,42.897642],"type":"Point"}
}