{
  "type": "Feature",
  "properties": {
    "addr:full":"40 Oak St Rochester NH 03839",
    "addr:housenumber":"40",
    "addr:postcode":"03839",
    "addr:street":"Oak St",
    "iso:country":"US",
    "sg:address":"40 Oak St",
    "sg:city":"Rochester",
    "sg:classifiers":[
        {
            "category":"Professional",
            "subcategory":"Business Services",
            "type":"Services"
        }
    ],
    "sg:phone":"+1 603 332 6406",
    "sg:postcode":"03839",
    "sg:province":"NH",
    "sg:tags":[
        "telemarketing"
    ],
    "wof:name":"Channel Business Development",
    "wof:placetype":"venue"
},
  "geometry": {"coordinates":[-70.98402900000001,43.275313],"type":"Point"}
}