{
  "type": "Feature",
  "properties": {
    "iso:country":"US",
    "sg:address":"281 Kearsarge Mountain Rd",
    "sg:city":"Warner",
    "sg:classifiers":[
        {
            "category":"Professional",
            "subcategory":"Business Services",
            "type":"Services"
        }
    ],
    "sg:phone":"+1 603 456 2246",
    "sg:postcode":"03278",
    "sg:province":"NH",
    "wof:name":"A Certain Style Interiors",
    "wof:placetype":"venue"
},
  "geometry": {"coordinates":[-71.832036,43.309215],"type":"Point"}
}