{
  "type": "Feature",
  "properties": {
    "iso:country":"US",
    "sg:address":"265 Proctor Hill Rd",
    "sg:city":"Hollis",
    "sg:classifiers":[
        {
            "category":"Manufacturing",
            "subcategory":"Chemicals & Compounds",
            "type":"Manufacturing & Wholesale Goods"
        }
    ],
    "sg:phone":"+1 603 465 7300",
    "sg:postcode":"03049",
    "sg:province":"NH",
    "sg:tags":[
        "manufacture",
        "polymer",
        "resin"
    ],
    "wof:name":"Aeroplas Corp International",
    "wof:placetype":"venue"
},
  "geometry": {"coordinates":[-71.604755,42.740237],"type":"Point"}
}