{
  "type": "Feature",
  "properties": {
    "addr:full":"753 Chestnut St Manchester NH 03104",
    "addr:housenumber":"753",
    "addr:postcode":"03104",
    "addr:street":"Chestnut St",
    "iso:country":"US",
    "sg:address":"753 Chestnut St",
    "sg:city":"Manchester",
    "sg:classifiers":[
        {
            "category":"Social Services",
            "type":"Services"
        }
    ],
    "sg:phone":"+1 603 668 0660",
    "sg:postcode":"03104",
    "sg:province":"NH",
    "sg:tags":[
        "counselor",
        "marriage",
        "family"
    ],
    "wof:name":"Kisonak & Souza",
    "wof:placetype":"venue"
},
  "geometry": {"coordinates":[-71.46295600000001,43.006509],"type":"Point"}
}