{
  "type": "Feature",
  "properties": {
    "addr:full":"9 Cascade Flat Gorham NH 03581",
    "addr:housenumber":"9;flat",
    "addr:postcode":"03581",
    "addr:street":"Cascade",
    "iso:country":"US",
    "sg:address":"9 Cascade Flat",
    "sg:city":"Gorham",
    "sg:classifiers":[
        {
            "category":"Restaurant",
            "type":"Food & Drink"
        }
    ],
    "sg:phone":"+1 603 752 6150",
    "sg:postcode":"03581",
    "sg:province":"NH",
    "sg:tags":[
        "eating"
    ],
    "wof:name":"Marys Pizza Inc",
    "wof:placetype":"venue"
},
  "geometry": {"coordinates":[-71.187701,44.442466],"type":"Point"}
}