{
  "type": "Feature",
  "properties": {
    "iso:country":"US",
    "sg:address":"153 S Main St",
    "sg:city":"Newton",
    "sg:classifiers":[
        {
            "category":"Wholesale",
            "subcategory":"Toys & Hobbies",
            "type":"Manufacturing & Wholesale Goods"
        }
    ],
    "sg:phone":"+1 603 382 3377",
    "sg:postcode":"03858",
    "sg:province":"NH",
    "wof:name":"Ravensburger FX Schmid USA",
    "wof:placetype":"venue"
},
  "geometry": {"coordinates":[-71.050511,42.842673],"type":"Point"}
}