{
  "type": "Feature",
  "properties": {
    "iso:country":"US",
    "sg:address":"123 Portsmouth St",
    "sg:city":"Concord",
    "sg:classifiers":[
        {
            "category":"Education",
            "subcategory":"School",
            "type":"Public Place"
        }
    ],
    "sg:phone":"+1 603 225 0855",
    "sg:postcode":"03301",
    "sg:province":"NH",
    "wof:name":"Broken Ground School",
    "wof:placetype":"venue"
},
  "geometry": {"coordinates":[-71.51436200000001,43.231724],"type":"Point"}
}