{
  "type": "Feature",
  "properties": {
    "iso:country":"US",
    "sg:address":"370 Meadow St",
    "sg:city":"Littleton",
    "sg:classifiers":[
        {
            "category":"Personal",
            "subcategory":"Beauty Salon",
            "type":"Services"
        }
    ],
    "sg:phone":"+1 603 444 7222",
    "sg:postcode":"03561",
    "sg:province":"NH",
    "sg:tags":[
        "manicuring"
    ],
    "wof:name":"Tip Top Nails",
    "wof:placetype":"venue"
},
  "geometry": {"coordinates":[-71.789483,44.309195],"type":"Point"}
}