{
  "type": "Feature",
  "properties": {
    "iso:country":"US",
    "sg:address":"164 Province Rd",
    "sg:city":"Barrington",
    "sg:classifiers":[
        {
            "category":"Arts & Performance",
            "subcategory":"Theater",
            "type":"Entertainment"
        }
    ],
    "sg:phone":"+1 603 664 3215",
    "sg:postcode":"03825",
    "sg:province":"NH",
    "sg:tags":[
        "group"
    ],
    "wof:name":"Pure Hearts",
    "wof:placetype":"venue"
},
  "geometry": {"coordinates":[-71.00797799999999,43.204556],"type":"Point"}
}