{
  "type": "Feature",
  "properties": {
    "iso:country":"US",
    "sg:address":"51 Beane Ln",
    "sg:city":"Newington",
    "sg:classifiers":[
        {
            "category":"Restaurant",
            "type":"Food & Drink"
        }
    ],
    "sg:phone":"+1 603 430 8565",
    "sg:postcode":"03801",
    "sg:province":"NH",
    "sg:tags":[
        "eating"
    ],
    "wof:name":"Currants Cafe & Grill",
    "wof:placetype":"venue"
},
  "geometry": {"coordinates":[-70.83528200000001,43.109824],"type":"Point"}
}