{
  "type": "Feature",
  "properties": {
    "addr:full":"295 W Mitchell St Manchester NH 03103",
    "addr:housenumber":"295",
    "addr:postcode":"03103",
    "addr:street":"W Mitchell St",
    "iso:country":"US",
    "sg:address":"295 W Mitchell St",
    "sg:city":"Manchester",
    "sg:classifiers":[
        {
            "category":"Building & Trades",
            "subcategory":"Plumbing",
            "type":"Services"
        }
    ],
    "sg:phone":"+1 603 627 7072",
    "sg:postcode":"03103",
    "sg:province":"NH",
    "sg:tags":[
        "plumber"
    ],
    "wof:name":"Raymond B Savoie",
    "wof:placetype":"venue"
},
  "geometry": {"coordinates":[-71.47001,42.96445],"type":"Point"}
}