{
  "type": "Feature",
  "properties": {
    "iso:country":"US",
    "sg:address":"111 Central Rd",
    "sg:city":"Rye",
    "sg:classifiers":[
        {
            "category":"Health Services",
            "subcategory":"Doctor",
            "type":"Services"
        }
    ],
    "sg:phone":"+1 603 430 8008",
    "sg:postcode":"03870",
    "sg:province":"NH",
    "sg:tags":[
        "physician",
        "surgeon"
    ],
    "wof:name":"Atlantic Pathology",
    "wof:placetype":"venue"
},
  "geometry": {"coordinates":[-70.77156100000001,43.006093],"type":"Point"}
}