{
  "type": "Feature",
  "properties": {
    "addr:full":"11 Muscovy Dr Litchfield NH 03052",
    "addr:housenumber":"11",
    "addr:postcode":"03052",
    "addr:street":"Muscovy Dr",
    "iso:country":"US",
    "sg:address":"11 Muscovy Dr",
    "sg:city":"Litchfield",
    "sg:classifiers":[
        {
            "category":"Professional",
            "subcategory":"Accounting & Tax Preparation",
            "type":"Services"
        }
    ],
    "sg:phone":"+1 603 429 1976",
    "sg:postcode":"03052",
    "sg:province":"NH",
    "sg:tags":[
        "bookkeeping",
        "general"
    ],
    "wof:name":"Books 'N' Ledgers",
    "wof:placetype":"venue"
},
  "geometry": {"coordinates":[-71.4554,42.849479],"type":"Point"}
}