{
  "type": "Feature",
  "properties": {
    "iso:country":"US",
    "sg:address":"16 Lehner St",
    "sg:city":"Wolfeboro",
    "sg:classifiers":[
        {
            "category":"Sports & Exercise",
            "subcategory":"Gym",
            "type":"Entertainment"
        }
    ],
    "sg:phone":"+1 603 569 6622",
    "sg:postcode":"03894",
    "sg:province":"NH",
    "wof:name":"New Beginnings Fitness Center",
    "wof:placetype":"venue"
},
  "geometry": {"coordinates":[-71.21169999999999,43.586498],"type":"Point"}
}