{
  "type": "Feature",
  "properties": {
    "addr:full":"13 Jenkins Ct Durham NH 03824",
    "addr:housenumber":"13",
    "addr:postcode":"03824",
    "addr:street":"Jenkins Ct",
    "iso:country":"US",
    "sg:address":"13 Jenkins Ct",
    "sg:city":"Durham",
    "sg:classifiers":[
        {
            "category":"Organizations",
            "subcategory":"Professional Association",
            "type":"Services"
        }
    ],
    "sg:phone":"+1 603 868 1123",
    "sg:postcode":"03824",
    "sg:province":"NH",
    "wof:name":"Durham Business Assn",
    "wof:placetype":"venue"
},
  "geometry": {"coordinates":[-70.92654899999999,43.134488],"type":"Point"}
}