{
  "type": "Feature",
  "properties": {
    "iso:country":"US",
    "sg:address":"23 Post Rd",
    "sg:city":"Hampton",
    "sg:classifiers":[
        {
            "category":"Health Services",
            "subcategory":"Doctor",
            "type":"Services"
        }
    ],
    "sg:phone":"+1 603 929 1194",
    "sg:postcode":"03862",
    "sg:province":"NH",
    "sg:tags":[
        "medical"
    ],
    "wof:name":"Obgyn",
    "wof:placetype":"venue"
},
  "geometry": {"coordinates":[-70.838482,42.962023],"type":"Point"}
}