{
  "type": "Feature",
  "properties": {
    "iso:country":"US",
    "sg:address":"10 Market St",
    "sg:city":"Somersworth",
    "sg:classifiers":[
        {
            "category":"Food & Beverages",
            "subcategory":"Groceries & Convenience Stores",
            "type":"Retail Goods"
        }
    ],
    "sg:phone":"+1 603 692 3022",
    "sg:postcode":"03878",
    "sg:province":"NH",
    "wof:name":"Borderline Beverages",
    "wof:placetype":"venue"
},
  "geometry": {"coordinates":[-70.864177,43.264805],"type":"Point"}
}