{
  "type": "Feature",
  "properties": {
    "addr:full":"83 Lafayette Rd Hampton Falls NH 03844",
    "addr:housenumber":"83",
    "addr:postcode":"03844",
    "iso:country":"US",
    "sg:address":"83 Lafayette Rd",
    "sg:city":"Hampton Falls",
    "sg:classifiers":[
        {
            "category":"Professional",
            "subcategory":"Lawyer & Legal Services",
            "type":"Services"
        }
    ],
    "sg:phone":"+1 603 624 7575",
    "sg:postcode":"03844",
    "sg:province":"NH",
    "sg:tags":[
        "attorney"
    ],
    "sg:website":"www.4injurylaw.com",
    "wof:name":"Jensen & Zumbado",
    "wof:placetype":"venue"
},
  "geometry": {"coordinates":[-70.864921,42.912813],"type":"Point"}
}