{
  "type": "Feature",
  "properties": {
    "addr:full":"13 Gettysburg Dr Nashua NH 03064",
    "addr:housenumber":"13",
    "addr:postcode":"03064",
    "addr:street":"Gettysburg Dr",
    "iso:country":"US",
    "sg:address":"13 Gettysburg Dr",
    "sg:city":"Nashua",
    "sg:classifiers":[
        {
            "category":"Retail",
            "subcategory":"Auto Repair",
            "type":"Services"
        }
    ],
    "sg:phone":"+1 603 594 4147",
    "sg:postcode":"03064",
    "sg:province":"NH",
    "sg:tags":[
        "engine",
        "rebuilding"
    ],
    "wof:name":"Tru Torque Engine Inc",
    "wof:placetype":"venue"
},
  "geometry": {"coordinates":[-71.467,42.787682],"type":"Point"}
}