{
  "type": "Feature",
  "properties": {
    "iso:country":"US",
    "sg:address":"14 Cross Rd",
    "sg:city":"Amherst",
    "sg:classifiers":[
        {
            "category":"Education",
            "subcategory":"School",
            "type":"Public Place"
        }
    ],
    "sg:phone":"+1 603 673 8944",
    "sg:postcode":"03031",
    "sg:province":"NH",
    "wof:name":"Amherst Middle School",
    "wof:placetype":"venue"
},
  "geometry": {"coordinates":[-71.57657399999999,42.82317],"type":"Point"}
}