{
  "type": "Feature",
  "properties": {
    "iso:country":"US",
    "sg:address":"13 Midway Park",
    "sg:city":"Somersworth",
    "sg:classifiers":[
        {
            "category":"Arts & Performance",
            "subcategory":"Theater",
            "type":"Entertainment"
        }
    ],
    "sg:phone":"+1 603 742 2435",
    "sg:postcode":"03878",
    "sg:province":"ME",
    "sg:tags":[
        "live",
        "music"
    ],
    "sg:website":"www.allhitsdjs.com",
    "wof:name":"All HITS Disc Jockeys & M C's",
    "wof:placetype":"venue"
},
  "geometry": {"coordinates":[-70.882423,43.233369],"type":"Point"}
}