{
  "type": "Feature",
  "properties": {
    "iso:country":"US",
    "sg:address":"7 Emerald St",
    "sg:city":"Keene",
    "sg:classifiers":[
        {
            "category":"Health Services",
            "subcategory":"Health Practitioner",
            "type":"Services"
        }
    ],
    "sg:phone":"+1 603 358 0035",
    "sg:postcode":"03431",
    "sg:province":"NH",
    "sg:tags":[
        "homeopath"
    ],
    "wof:name":"Julian Jonas",
    "wof:placetype":"venue"
},
  "geometry": {"coordinates":[-72.27819100000001,42.930851],"type":"Point"}
}