{
  "type": "Feature",
  "properties": {
    "iso:country":"US",
    "sg:address":"10 Daniel Dr",
    "sg:city":"Epping",
    "sg:classifiers":[
        {
            "category":"Autos & Motor Vehicles",
            "subcategory":"Motorcycle Sales",
            "type":"Retail Goods"
        }
    ],
    "sg:phone":"+1 603 679 5134",
    "sg:postcode":"03042",
    "sg:province":"NH",
    "sg:tags":[
        "car",
        "golf",
        "cart"
    ],
    "wof:name":"B & H Sales & Svc",
    "wof:placetype":"venue"
},
  "geometry": {"coordinates":[-71.06051100000001,43.059697],"type":"Point"}
}