{
  "type": "Feature",
  "properties": {
    "addr:full":"77 South St Concord NH 03301",
    "addr:housenumber":"77",
    "addr:postcode":"03301",
    "addr:street":"South St",
    "iso:country":"US",
    "sg:address":"77 South St",
    "sg:city":"Concord",
    "sg:classifiers":[
        {
            "category":"Personal",
            "subcategory":"Beauty Salon",
            "type":"Services"
        }
    ],
    "sg:phone":"+1 603 225 2223",
    "sg:postcode":"03301",
    "sg:province":"NH",
    "sg:tags":[
        "shop"
    ],
    "wof:name":"Townhouse Coiffures By Phillip",
    "wof:placetype":"venue"
},
  "geometry": {"coordinates":[-71.539405,43.195178],"type":"Point"}
}