{
  "type": "Feature",
  "properties": {
    "iso:country":"US",
    "sg:address":"2800 Lafayette Rd",
    "sg:city":"Portsmouth",
    "sg:classifiers":[
        {
            "category":"Shopping",
            "subcategory":"Books",
            "type":"Retail Goods"
        }
    ],
    "sg:phone":"+1 603 430 0222",
    "sg:postcode":"03801",
    "sg:province":"NH",
    "sg:tags":[
        "comic"
    ],
    "sg:website":"www.jumpgatelink.com",
    "wof:name":"Jumpgate Science Fiction",
    "wof:placetype":"venue"
},
  "geometry": {"coordinates":[-70.786912,43.031271],"type":"Point"}
}