{
  "type": "Feature",
  "properties": {
    "addr:full":"180 Greenleaf Ave Portsmouth NH 03801",
    "addr:housenumber":"180",
    "addr:postcode":"03801",
    "addr:street":"Greenleaf Ave",
    "iso:country":"US",
    "sg:address":"180 Greenleaf Ave",
    "sg:city":"Portsmouth",
    "sg:classifiers":[
        {
            "category":"Utilities",
            "subcategory":"Cable",
            "type":"Services"
        }
    ],
    "sg:phone":"+1 603 436 7161",
    "sg:postcode":"03801",
    "sg:province":"NH",
    "wof:name":"Comcast Cable Holdings LLC",
    "wof:placetype":"venue"
},
  "geometry": {"coordinates":[-70.770197,43.059116],"type":"Point"}
}