{
  "type": "Feature",
  "properties": {
    "iso:country":"US",
    "sg:address":"169 Main St",
    "sg:city":"Gorham",
    "sg:classifiers":[
        {
            "category":"Education",
            "subcategory":"School",
            "type":"Public Place"
        }
    ],
    "sg:phone":"+1 603 466 3334",
    "sg:postcode":"03581",
    "sg:province":"NH",
    "sg:website":"www.sau20.org",
    "wof:name":"Edward Fenn Elementary School",
    "wof:placetype":"venue"
},
  "geometry": {"coordinates":[-71.18333199999999,44.390936],"type":"Point"}
}