{
  "type": "Feature",
  "properties": {
    "iso:country":"US",
    "sg:address":"156 Lowell Rd",
    "sg:city":"Hudson",
    "sg:classifiers":[
        {
            "category":"Retail",
            "subcategory":"Auto Repair",
            "type":"Services"
        }
    ],
    "sg:phone":"+1 603 882 1444",
    "sg:postcode":"03051",
    "sg:province":"NH",
    "sg:tags":[
        "shop",
        "automotive",
        "transmission"
    ],
    "wof:name":"Freddies Transmission Service",
    "wof:placetype":"venue"
},
  "geometry": {"coordinates":[-71.425951,42.746824],"type":"Point"}
}