{
  "type": "Feature",
  "properties": {
    "iso:country":"US",
    "sg:address":"46 Lane Rd",
    "sg:city":"Chester",
    "sg:classifiers":[
        {
            "category":"Professional",
            "subcategory":"Management & Consulting",
            "type":"Services"
        }
    ],
    "sg:phone":"+1 603 887 5408",
    "sg:postcode":"03036",
    "sg:province":"NH",
    "wof:name":"Chesterlane Co",
    "wof:placetype":"venue"
},
  "geometry": {"coordinates":[-71.228302,42.983944],"type":"Point"}
}