{
  "type": "Feature",
  "properties": {
    "iso:country":"US",
    "sg:address":"112 Granite St",
    "sg:city":"Allenstown",
    "sg:classifiers":[
        {
            "category":"Home & Garden",
            "subcategory":"Building Materials",
            "type":"Retail Goods"
        }
    ],
    "sg:phone":"+1 603 485 8344",
    "sg:postcode":"03275",
    "sg:province":"NH",
    "sg:tags":[
        "glass",
        "leaded"
    ],
    "sg:website":"www.cdvkiln.com",
    "wof:name":"Centre De Verre",
    "wof:placetype":"venue"
},
  "geometry": {"coordinates":[-71.435976,43.124606],"type":"Point"}
}