{
  "type": "Feature",
  "properties": {
    "iso:country":"US",
    "sg:address":"8 Dunlin Way",
    "sg:city":"Portsmouth",
    "sg:classifiers":[
        {
            "category":"Wholesale",
            "subcategory":"Machinery & Supplies",
            "type":"Manufacturing & Wholesale Goods"
        }
    ],
    "sg:phone":"+1 603 431 2494",
    "sg:postcode":"03801",
    "sg:province":"NH",
    "sg:tags":[
        "industrial",
        "mfg"
    ],
    "wof:name":"Sutherland Industrial Sales",
    "wof:placetype":"venue"
},
  "geometry": {"coordinates":[-70.777468,43.090744],"type":"Point"}
}