{
  "type": "Feature",
  "properties": {
    "iso:country":"US",
    "sg:address":"183 Pembroke Rd",
    "sg:city":"Concord",
    "sg:classifiers":[
        {
            "category":"Building & Trades",
            "subcategory":"Construction",
            "type":"Services"
        }
    ],
    "sg:phone":"+1 603 225 0211",
    "sg:postcode":"03301",
    "sg:province":"NH",
    "sg:tags":[
        "steel",
        "rep",
        "product"
    ],
    "wof:name":"Leonard Charles Cnstr Co",
    "wof:placetype":"venue"
},
  "geometry": {"coordinates":[-71.48757999999999,43.214536],"type":"Point"}
}