{
  "type": "Feature",
  "properties": {
    "iso:country":"US",
    "sg:address":"65 Depot Rd",
    "sg:city":"Kingston",
    "sg:classifiers":[
        {
            "category":"Sports & Exercise",
            "subcategory":"Golf",
            "type":"Entertainment"
        }
    ],
    "sg:phone":"+1 603 642 7722",
    "sg:postcode":"03848",
    "sg:province":"NH",
    "sg:tags":[
        "course",
        "courses-private"
    ],
    "wof:name":"Kingston Fairways Golf Club",
    "wof:placetype":"venue"
},
  "geometry": {"coordinates":[-71.03560299999999,42.93016],"type":"Point"}
}