{
  "type": "Feature",
  "properties": {
    "addr:full":"2 Scobie Pond Rd Derry NH 03038",
    "addr:housenumber":"2",
    "addr:postcode":"03038",
    "addr:street":"Scobie Pond Rd",
    "iso:country":"US",
    "sg:address":"2 Scobie Pond Rd",
    "sg:city":"Derry",
    "sg:classifiers":[
        {
            "category":"Freight",
            "type":"Transportation"
        }
    ],
    "sg:phone":"+1 603 432 8993",
    "sg:postcode":"03038",
    "sg:province":"NH",
    "sg:tags":[
        "commercial",
        "storage"
    ],
    "wof:name":"Extra Space Storage",
    "wof:placetype":"venue"
},
  "geometry": {"coordinates":[-71.33787100000001,42.9036],"type":"Point"}
}