{
  "type": "Feature",
  "properties": {
    "addr:full":"40 Main St Durham NH 03824",
    "addr:housenumber":"40",
    "addr:postcode":"03824",
    "addr:street":"Main St",
    "iso:country":"US",
    "sg:address":"40 Main St",
    "sg:city":"Durham",
    "sg:classifiers":[
        {
            "category":"Restaurant",
            "type":"Food & Drink"
        }
    ],
    "sg:menulink":"http://www.allmenus.com/nh/durham/17742-dominos-pizza/menu/",
    "sg:phone":"+1 603 868 6230",
    "sg:postcode":"03824",
    "sg:province":"NH",
    "sg:tags":[
        "american",
        "wing",
        "pizza"
    ],
    "wof:name":"Domino's Pizza",
    "wof:placetype":"venue"
},
  "geometry": {"coordinates":[-70.925748,43.133996],"type":"Point"}
}