{
  "type": "Feature",
  "properties": {
    "iso:country":"US",
    "sg:address":"1500 S Willow St",
    "sg:city":"Manchester",
    "sg:classifiers":[
        {
            "category":"Bakery",
            "type":"Food & Drink"
        }
    ],
    "sg:menulink":"http://www.allmenus.com/nh/manchester/220036-auntie-annes-pretzels/menu/",
    "sg:phone":"+1 603 641 6550",
    "sg:postcode":"03103",
    "sg:province":"NH",
    "sg:tags":[
        "american",
        "pastry"
    ],
    "wof:name":"Auntie Anne's Pretzels",
    "wof:placetype":"venue"
},
  "geometry": {"coordinates":[-71.43059599999999,42.957119],"type":"Point"}
}