{
  "type": "Feature",
  "properties": {
    "iso:country":"US",
    "sg:address":"108 W Hollis St",
    "sg:city":"Nashua",
    "sg:classifiers":[
        {
            "category":"Shopping",
            "subcategory":"Hobbies, Toys, & Games",
            "type":"Retail Goods"
        }
    ],
    "sg:phone":"+1 603 598 9280",
    "sg:postcode":"03060",
    "sg:province":"NH",
    "sg:website":"www.thebeadroom.com",
    "wof:name":"Bead Room",
    "wof:placetype":"venue"
},
  "geometry": {"coordinates":[-71.47421199999999,42.754877],"type":"Point"}
}