{
  "type": "Feature",
  "properties": {
    "iso:country":"US",
    "sg:address":"133 Mystic St",
    "sg:city":"Manchester",
    "sg:classifiers":[
        {
            "category":"Manufacturing",
            "subcategory":"Tools & Machinery",
            "type":"Manufacturing & Wholesale Goods"
        }
    ],
    "sg:phone":"+1 603 627 3145",
    "sg:postcode":"03103",
    "sg:province":"NH",
    "sg:tags":[
        "cutting"
    ],
    "wof:name":"Technology Grinding Co",
    "wof:placetype":"venue"
},
  "geometry": {"coordinates":[-71.460668,42.962143],"type":"Point"}
}