{
  "type": "Feature",
  "properties": {
    "addr:full":"178 Emerald St Keene NH 03431",
    "addr:housenumber":"178",
    "addr:postcode":"03431",
    "addr:street":"Emerald St",
    "iso:country":"US",
    "sg:address":"178 Emerald St",
    "sg:city":"Keene",
    "sg:classifiers":[
        {
            "category":"Home & Garden",
            "subcategory":"Carpets & Floor Coverings",
            "type":"Retail Goods"
        }
    ],
    "sg:phone":"+1 603 358 3934",
    "sg:postcode":"03431",
    "sg:province":"NH",
    "sg:website":"www.carpet-clearance.com",
    "wof:name":"Carpet Clearance Warehouse",
    "wof:placetype":"venue"
},
  "geometry": {"coordinates":[-72.284677,42.930253],"type":"Point"}
}