{
  "type": "Feature",
  "properties": {
    "addr:full":"58 Optical Ave Keene NH 03431",
    "addr:postcode":"03431",
    "addr:street":"Ave",
    "iso:country":"US",
    "sg:address":"58 Optical Ave",
    "sg:city":"Keene",
    "sg:classifiers":[
        {
            "category":"Manufacturing",
            "subcategory":"Tools & Machinery",
            "type":"Manufacturing & Wholesale Goods"
        }
    ],
    "sg:phone":"+1 603 355 2246",
    "sg:postcode":"03431",
    "sg:province":"NH",
    "sg:tags":[
        "die",
        "maker"
    ],
    "sg:website":"www.sunsettoolinc.com",
    "wof:name":"Sunset Tool Inc",
    "wof:placetype":"venue"
},
  "geometry": {"coordinates":[-72.261684,42.916644],"type":"Point"}
}