{
  "type": "Feature",
  "properties": {
    "addr:full":"38 Boyd Rd Londonderry NH 03053",
    "addr:housenumber":"38",
    "addr:postcode":"03053",
    "addr:street":"Boyd Rd",
    "iso:country":"US",
    "sg:address":"38 Boyd Rd",
    "sg:city":"Londonderry",
    "sg:classifiers":[
        {
            "category":"Professional",
            "subcategory":"Computer Services",
            "type":"Services"
        }
    ],
    "sg:phone":"+1 603 432 1603",
    "sg:postcode":"03053",
    "sg:province":"NH",
    "wof:name":"Mlans Inc",
    "wof:placetype":"venue"
},
  "geometry": {"coordinates":[-71.38686199999999,42.823406],"type":"Point"}
}