{
  "type": "Feature",
  "properties": {
    "iso:country":"US",
    "sg:address":"10 Water St",
    "sg:city":"Antrim",
    "sg:classifiers":[
        {
            "category":"Manufacturing",
            "subcategory":"Rubber & Plastics",
            "type":"Manufacturing & Wholesale Goods"
        }
    ],
    "sg:phone":"+1 603 588 7234",
    "sg:postcode":"03465",
    "sg:province":"NH",
    "sg:tags":[
        "museum",
        "gift",
        "reproduction",
        "manufacturer"
    ],
    "wof:name":"Artek",
    "wof:placetype":"venue"
},
  "geometry": {"coordinates":[-72.183088,42.824712],"type":"Point"}
}