{
  "type": "Feature",
  "properties": {
    "iso:country":"US",
    "sg:address":"38 Portsmouth Ave",
    "sg:city":"Stratham",
    "sg:classifiers":[
        {
            "category":"Banks & Credit Unions",
            "subcategory":"Bank",
            "type":"Services"
        }
    ],
    "sg:phone":"+1 603 773 2500",
    "sg:postcode":"03885",
    "sg:province":"NH",
    "sg:tags":[
        "state",
        "commercial"
    ],
    "wof:name":"Citizens Bank",
    "wof:placetype":"venue"
},
  "geometry": {"coordinates":[-70.922416,42.999206],"type":"Point"}
}