{
  "type": "Feature",
  "properties": {
    "addr:full":"5 State Rte 101A Amherst NH 03031",
    "addr:housenumber":"5",
    "addr:postcode":"03031",
    "addr:street":"State Rte 101A",
    "iso:country":"US",
    "sg:address":"5 State Rte 101A",
    "sg:city":"Amherst",
    "sg:classifiers":[
        {
            "category":"Shopping",
            "subcategory":"Musical Instruments",
            "type":"Retail Goods"
        }
    ],
    "sg:phone":"+1 603 672 9224",
    "sg:postcode":"03031",
    "sg:province":"NH",
    "wof:name":"Guitar Gallery Of New England",
    "wof:placetype":"venue"
},
  "geometry": {"coordinates":[-71.61216,42.823801],"type":"Point"}
}