{
  "type": "Feature",
  "properties": {
    "iso:country":"US",
    "sg:address":"18 Chagnon St",
    "sg:city":"Manchester",
    "sg:classifiers":[
        {
            "category":"Shopping",
            "subcategory":"Used Merchandise",
            "type":"Retail Goods"
        },
        {
            "category":"Wholesale",
            "subcategory":"Scrap",
            "type":"Manufacturing & Wholesale Goods"
        }
    ],
    "sg:phone":"+1 603 623 0342",
    "sg:postcode":"03102",
    "sg:province":"NH",
    "sg:tags":[
        "junk",
        "material"
    ],
    "wof:name":"B Rovner & Co",
    "wof:placetype":"venue"
},
  "geometry": {"coordinates":[-71.47196599999999,42.990153],"type":"Point"}
}