{
  "type": "Feature",
  "properties": {
    "iso:country":"US",
    "sg:address":"113 Cottage St",
    "sg:city":"Littleton",
    "sg:classifiers":[
        {
            "category":"Professional",
            "subcategory":"Employment Agencies",
            "type":"Services"
        }
    ],
    "sg:phone":"+1 603 444 1100",
    "sg:postcode":"03561",
    "sg:province":"NH",
    "sg:tags":[
        "help",
        "supply"
    ],
    "wof:name":"New Dimensions Personnel Svcs",
    "wof:placetype":"venue"
},
  "geometry": {"coordinates":[-71.76924,44.302252],"type":"Point"}
}