{
  "type": "Feature",
  "properties": {
    "addr:full":"7 N River Rd Epping NH 03042",
    "addr:housenumber":"7",
    "addr:postcode":"03042",
    "addr:street":"N River Rd",
    "iso:country":"US",
    "sg:address":"7 N River Rd",
    "sg:city":"Epping",
    "sg:classifiers":[
        {
            "category":"Restaurant",
            "type":"Food & Drink"
        }
    ],
    "sg:menulink":"http://www.allmenus.com/nh/epping/53399-applebees/menu/",
    "sg:phone":"+1 603 679 2327",
    "sg:postcode":"03042",
    "sg:province":"NH",
    "sg:tags":[
        "burger",
        "american",
        "sandwich",
        "soup"
    ],
    "wof:name":"Applebee's",
    "wof:placetype":"venue"
},
  "geometry": {"coordinates":[-71.070668,43.048397],"type":"Point"}
}