{
  "type": "Feature",
  "properties": {
    "addr:full":"41 Mill Rd Durham NH 03824",
    "addr:housenumber":"41",
    "addr:postcode":"03824",
    "addr:street":"Mill Rd",
    "iso:country":"US",
    "sg:address":"41 Mill Rd",
    "sg:city":"Durham",
    "sg:classifiers":[
        {
            "category":"Banks & Credit Unions",
            "subcategory":"Bank",
            "type":"Services"
        }
    ],
    "sg:phone":"+1 603 868 1111",
    "sg:postcode":"03824",
    "sg:province":"NH",
    "wof:name":"Federal Savings Bank",
    "wof:placetype":"venue"
},
  "geometry": {"coordinates":[-70.93190800000001,43.130576],"type":"Point"}
}