{
  "type": "Feature",
  "properties": {
    "addr:full":"333 Tasker Hill Rd Conway NH 03818",
    "addr:housenumber":"333",
    "addr:postcode":"03818",
    "addr:street":"Tasker Hill Rd",
    "iso:country":"US",
    "sg:address":"333 Tasker Hill Rd",
    "sg:city":"Conway",
    "sg:classifiers":[
        {
            "category":"Manufacturing",
            "subcategory":"Printing",
            "type":"Manufacturing & Wholesale Goods"
        }
    ],
    "sg:phone":"+1 603 447 4251",
    "sg:postcode":"03818",
    "sg:province":"NH",
    "sg:tags":[
        "newspaper"
    ],
    "wof:name":"Racin' Paper",
    "wof:placetype":"venue"
},
  "geometry": {"coordinates":[-71.118781,43.963399],"type":"Point"}
}