{
  "type": "Feature",
  "properties": {
    "iso:country":"US",
    "sg:address":"309 Main St",
    "sg:city":"Salem",
    "sg:classifiers":[
        {
            "category":"Building & Trades",
            "subcategory":"Construction",
            "type":"Services"
        }
    ],
    "sg:phone":"+1 617 638 3230",
    "sg:postcode":"03079",
    "sg:province":"NH",
    "sg:tags":[
        "contractor",
        "fence-sales"
    ],
    "wof:name":"Kelly S Underground Dog Gr",
    "wof:placetype":"venue"
},
  "geometry": {"coordinates":[-71.20027899999999,42.789354],"type":"Point"}
}