{
  "type": "Feature",
  "properties": {
    "iso:country":"US",
    "sg:address":"66 Main St",
    "sg:city":"Enfield",
    "sg:classifiers":[
        {
            "category":"Food & Beverages",
            "subcategory":"Groceries & Convenience Stores",
            "type":"Retail Goods"
        }
    ],
    "sg:phone":"+1 603 632 7443",
    "sg:postcode":"03748",
    "sg:province":"NH",
    "wof:name":"Georges Supervalue LLC",
    "wof:placetype":"venue"
},
  "geometry": {"coordinates":[-72.147268,43.641143],"type":"Point"}
}