{
  "type": "Feature",
  "properties": {
    "addr:full":"286 Commercial St Manchester NH 03101",
    "addr:housenumber":"286",
    "addr:postcode":"03101",
    "addr:street":"Commercial St",
    "iso:country":"US",
    "sg:address":"286 Commercial St",
    "sg:city":"Manchester",
    "sg:classifiers":[
        {
            "category":"Professional",
            "type":"Services"
        }
    ],
    "sg:phone":"+1 603 622 9122",
    "sg:postcode":"03101",
    "sg:province":"NH",
    "sg:tags":[
        "establishment"
    ],
    "wof:name":"Elite Prodproducers Group",
    "wof:placetype":"venue"
},
  "geometry": {"coordinates":[-71.46777299999999,42.991467],"type":"Point"}
}