{
  "type": "Feature",
  "properties": {
    "addr:full":"30 Dugout Rd Hudson NH 03051",
    "addr:housenumber":"30",
    "addr:postcode":"03051",
    "addr:street":"Dugout Rd",
    "iso:country":"US",
    "sg:address":"30 Dugout Rd",
    "sg:city":"Hudson",
    "sg:classifiers":[
        {
            "category":"Manufacturing",
            "subcategory":"Printing",
            "type":"Manufacturing & Wholesale Goods"
        }
    ],
    "sg:phone":"+1 603 880 9096",
    "sg:postcode":"03051",
    "sg:province":"NH",
    "sg:tags":[
        "multimedia"
    ],
    "wof:name":"MMG Media LLC",
    "wof:placetype":"venue"
},
  "geometry": {"coordinates":[-71.38424000000001,42.788084],"type":"Point"}
}