{
  "type": "Feature",
  "properties": {
    "iso:country":"US",
    "sg:address":"16 State Rte 111",
    "sg:city":"Derry",
    "sg:classifiers":[
        {
            "category":"Social Services",
            "type":"Services"
        }
    ],
    "sg:phone":"+1 603 898 6770",
    "sg:postcode":"03038",
    "sg:province":"NH",
    "sg:tags":[
        "organization",
        "welfare"
    ],
    "sg:website":"www.crotchedmountain.org",
    "wof:name":"Crotched Mountain Residential",
    "wof:placetype":"venue"
},
  "geometry": {"coordinates":[-71.206811,42.853545],"type":"Point"}
}