{
  "type": "Feature",
  "properties": {
    "addr:full":"34 Chatel Rd Goffstown NH 03045",
    "addr:postcode":"03045",
    "addr:street":"Chatel Rd",
    "iso:country":"US",
    "sg:address":"34 Chatel Rd",
    "sg:city":"Goffstown",
    "sg:classifiers":[
        {
            "category":"Shopping",
            "subcategory":"Catalog Store",
            "type":"Retail Goods"
        }
    ],
    "sg:phone":"+1 603 623 5988",
    "sg:postcode":"03045",
    "sg:province":"NH",
    "sg:tags":[
        "mail",
        "order"
    ],
    "wof:name":"UNC",
    "wof:placetype":"venue"
},
  "geometry": {"coordinates":[-71.521754,43.010532],"type":"Point"}
}