{
  "type": "Feature",
  "properties": {
    "iso:country":"US",
    "sg:address":"465 Tibbetts Hill Rd",
    "sg:city":"Goffstown",
    "sg:classifiers":[
        {
            "category":"Professional",
            "subcategory":"Art Services",
            "type":"Services"
        }
    ],
    "sg:phone":"+1 603 774 6278",
    "sg:postcode":"03045",
    "sg:province":"NH",
    "sg:tags":[
        "commercial",
        "design"
    ],
    "wof:name":"Menz Wor Graphics",
    "wof:placetype":"venue"
},
  "geometry": {"coordinates":[-71.572875,43.056679],"type":"Point"}
}