{
  "type": "Feature",
  "properties": {
    "iso:country":"US",
    "sg:address":"2 Old Nashua Rd",
    "sg:city":"Londonderry",
    "sg:classifiers":[
        {
            "category":"Retail",
            "subcategory":"Portrait Studio",
            "type":"Services"
        }
    ],
    "sg:phone":"+1 603 434 9383",
    "sg:postcode":"03053",
    "sg:province":"NH",
    "sg:tags":[
        "photography"
    ],
    "sg:website":"www.marklawrencephotographers.com",
    "wof:name":"Mark Lawrence Photographers",
    "wof:placetype":"venue"
},
  "geometry": {"coordinates":[-71.393181,42.833076],"type":"Point"}
}