{
  "type": "Feature",
  "properties": {
    "iso:country":"US",
    "sg:address":"129 Mechanic St",
    "sg:city":"Lebanon",
    "sg:classifiers":[
        {
            "category":"Health Services",
            "subcategory":"Doctor",
            "type":"Services"
        }
    ],
    "sg:phone":"+1 603 448 1071",
    "sg:postcode":"03766",
    "sg:province":"NH",
    "sg:tags":[
        "physician",
        "surgeon"
    ],
    "wof:name":"Skin Care Ctr",
    "wof:placetype":"venue"
},
  "geometry": {"coordinates":[-72.26109599999999,43.638357],"type":"Point"}
}