{
  "type": "Feature",
  "properties": {
    "iso:country":"US",
    "sg:address":"160 Jennifer Dr",
    "sg:city":"Chester",
    "sg:classifiers":[
        {
            "category":"Wholesale",
            "subcategory":"Construction Materials",
            "type":"Manufacturing & Wholesale Goods"
        }
    ],
    "sg:phone":"+1 603 887 8588",
    "sg:postcode":"03036",
    "sg:province":"NH",
    "sg:tags":[
        "fence"
    ],
    "wof:name":"Sturdy Fence Co",
    "wof:placetype":"venue"
},
  "geometry": {"coordinates":[-71.17858699999999,42.981827],"type":"Point"}
}