{
  "type": "Feature",
  "properties": {
    "iso:country":"US",
    "sg:address":"5 Pond Rd",
    "sg:city":"Mont Vernon",
    "sg:classifiers":[
        {
            "category":"Health Services",
            "subcategory":"Doctor",
            "type":"Services"
        }
    ],
    "sg:phone":"+1 603 672 7592",
    "sg:postcode":"03057",
    "sg:province":"NH",
    "sg:tags":[
        "medical",
        "agency",
        "employment"
    ],
    "wof:name":"Harrison Business Grp",
    "wof:placetype":"venue"
},
  "geometry": {"coordinates":[-71.681146,42.907269],"type":"Point"}
}