{
  "type": "Feature",
  "properties": {
    "addr:full":"130 Pleasant St Claremont NH 03743",
    "addr:housenumber":"130",
    "addr:postcode":"03743",
    "addr:street":"Pleasant St",
    "iso:country":"US",
    "sg:address":"130 Pleasant St",
    "sg:city":"Claremont",
    "sg:classifiers":[
        {
            "category":"Real Estate",
            "subcategory":"Real Estate Services",
            "type":"Services"
        }
    ],
    "sg:phone":"+1 603 542 4117",
    "sg:postcode":"03743",
    "sg:province":"NH",
    "sg:tags":[
        "company",
        "title"
    ],
    "wof:name":"Accurate Title",
    "wof:placetype":"venue"
},
  "geometry": {"coordinates":[-72.34038099999999,43.368234],"type":"Point"}
}