{
  "type": "Feature",
  "properties": {
    "addr:full":"19 Sanborn Rd Londonderry NH 03053",
    "addr:housenumber":"19",
    "addr:postcode":"03053",
    "addr:street":"Sanborn Rd",
    "iso:country":"US",
    "sg:address":"19 Sanborn Rd",
    "sg:city":"Londonderry",
    "sg:classifiers":[
        {
            "category":"Education",
            "subcategory":"School",
            "type":"Public Place"
        }
    ],
    "sg:phone":"+1 603 432 6933",
    "sg:postcode":"03053",
    "sg:province":"NH",
    "wof:name":"North Londonderry School",
    "wof:placetype":"venue"
},
  "geometry": {"coordinates":[-71.390169,42.921617],"type":"Point"}
}