{
  "type": "Feature",
  "properties": {
    "iso:country":"US",
    "sg:address":"435 Lake St",
    "sg:city":"Bristol",
    "sg:classifiers":[
        {
            "category":"Banks & Credit Unions",
            "subcategory":"Bank",
            "type":"Services"
        }
    ],
    "sg:phone":"+1 603 744 0000",
    "sg:postcode":"03222",
    "sg:province":"NH",
    "sg:tags":[
        "financing"
    ],
    "wof:name":"Group East Financial Svc Inc",
    "wof:placetype":"venue"
},
  "geometry": {"coordinates":[-71.74379399999999,43.604567],"type":"Point"}
}