{
  "type": "Feature",
  "properties": {
    "iso:country":"US",
    "sg:address":"159 1st New Hampshire Tpke",
    "sg:city":"Northwood",
    "sg:classifiers":[
        {
            "category":"Restaurant",
            "type":"Food & Drink"
        }
    ],
    "sg:phone":"+1 603 942 5862",
    "sg:postcode":"03261",
    "sg:province":"NH",
    "sg:tags":[
        "vegetarian"
    ],
    "sg:website":"sustysnorthwood.com/",
    "wof:name":"Susty's Cafe",
    "wof:placetype":"venue"
},
  "geometry": {"coordinates":[-71.15679,43.197707],"type":"Point"}
}