{
  "type": "Feature",
  "properties": {
    "iso:country":"US",
    "sg:address":"1000 Elm St Ste 121",
    "sg:city":"Manchester",
    "sg:classifiers":[
        {
            "category":"Coffee & Tea",
            "type":"Food & Drink"
        }
    ],
    "sg:phone":"+1 603 622 7944",
    "sg:postcode":"03101",
    "sg:province":"NH",
    "wof:name":"J Dubs Coffee House",
    "wof:placetype":"venue"
},
  "geometry": {"coordinates":[-71.46307400000001,42.993004],"type":"Point"}
}