{
  "type": "Feature",
  "properties": {
    "addr:full":"1803 Riverside Dr Berlin NH 03570",
    "addr:housenumber":"1803",
    "addr:postcode":"03570",
    "addr:street":"Riverside Dr",
    "iso:country":"US",
    "sg:address":"1803 Riverside Dr",
    "sg:city":"Berlin",
    "sg:classifiers":[
        {
            "category":"Building & Trades",
            "subcategory":"Construction",
            "type":"Services"
        }
    ],
    "sg:phone":"+1 603 752 4622",
    "sg:postcode":"03570",
    "sg:province":"NH",
    "sg:tags":[
        "warehouse",
        "industrial",
        "commercial",
        "general",
        "contractor"
    ],
    "wof:name":"A R Couture Construction Corp",
    "wof:placetype":"venue"
},
  "geometry": {"coordinates":[-71.162947,44.493742],"type":"Point"}
}