{
  "type": "Feature",
  "properties": {
    "iso:country":"US",
    "sg:address":"45 S Village Rd",
    "sg:city":"Loudon",
    "sg:classifiers":[
        {
            "category":"Real Estate",
            "subcategory":"Real Estate Agent",
            "type":"Services"
        }
    ],
    "sg:phone":"+1 603 798 3719",
    "sg:postcode":"03307",
    "sg:province":"NH",
    "wof:name":"Blue Diamond Realty",
    "wof:placetype":"venue"
},
  "geometry": {"coordinates":[-71.465953,43.283418],"type":"Point"}
}