{
  "type": "Feature",
  "properties": {
    "addr:full":"53 Church St Concord NH 03301",
    "addr:housenumber":"53",
    "addr:postcode":"03301",
    "addr:street":"Church St",
    "iso:country":"US",
    "sg:address":"53 Church St",
    "sg:city":"Concord",
    "sg:classifiers":[
        {
            "category":"Professional",
            "subcategory":"Business Services",
            "type":"Services"
        }
    ],
    "sg:phone":"+1 603 225 5195",
    "sg:postcode":"03301",
    "sg:province":"NH",
    "sg:tags":[
        "water",
        "treatment"
    ],
    "wof:name":"Allied Clearwater",
    "wof:placetype":"venue"
},
  "geometry": {"coordinates":[-71.54708599999999,43.212482],"type":"Point"}
}