{
  "type": "Feature",
  "properties": {
    "addr:full":"692 Lafayette Rd Seabrook NH 03874",
    "addr:housenumber":"692",
    "addr:postcode":"03874",
    "iso:country":"US",
    "sg:address":"692 Lafayette Rd",
    "sg:city":"Seabrook",
    "sg:classifiers":[
        {
            "category":"Banks & Credit Unions",
            "subcategory":"Bank",
            "type":"Services"
        }
    ],
    "sg:phone":"+1 603 474 9685",
    "sg:postcode":"03874",
    "sg:province":"NH",
    "sg:tags":[
        "cashing",
        "check"
    ],
    "wof:name":"Advance America",
    "wof:placetype":"venue"
},
  "geometry": {"coordinates":[-70.87117000000001,42.89516],"type":"Point"}
}