{
  "type": "Feature",
  "properties": {
    "iso:country":"US",
    "sg:address":"364 State Rte 108",
    "sg:city":"Somersworth",
    "sg:classifiers":[
        {
            "category":"Manufacturing",
            "subcategory":"Leather Goods",
            "type":"Manufacturing & Wholesale Goods"
        }
    ],
    "sg:phone":"+1 603 332 2283",
    "sg:postcode":"03878",
    "sg:province":"ME",
    "sg:tags":[
        "athletic",
        "mfg",
        "except",
        "footwear"
    ],
    "wof:name":"Colby Footwear Inc",
    "wof:placetype":"venue"
},
  "geometry": {"coordinates":[-70.905001,43.261727],"type":"Point"}
}