{
  "type": "Feature",
  "properties": {
    "iso:country":"US",
    "sg:address":"229 Queen City Ave",
    "sg:city":"Manchester",
    "sg:classifiers":[
        {
            "category":"Retail",
            "subcategory":"Auto Repair",
            "type":"Services"
        }
    ],
    "sg:phone":"+1 603 666 4644",
    "sg:postcode":"03103",
    "sg:province":"NH",
    "sg:tags":[
        "repairing",
        "automobile",
        "pump",
        "parts",
        "gasoline"
    ],
    "wof:name":"Nazar Queen City Sunoco",
    "wof:placetype":"venue"
},
  "geometry": {"coordinates":[-71.466157,42.973597],"type":"Point"}
}