{
  "type": "Feature",
  "properties": {
    "iso:country":"US",
    "sg:address":"160 Ossipee Mountain Rd",
    "sg:city":"Center Ossipee",
    "sg:classifiers":[
        {
            "category":"Building & Trades",
            "subcategory":"Construction",
            "type":"Services"
        }
    ],
    "sg:phone":"+1 603 662 9095",
    "sg:postcode":"03814",
    "sg:province":"NH",
    "sg:tags":[
        "house"
    ],
    "wof:name":"Skill Builders",
    "wof:placetype":"venue"
},
  "geometry": {"coordinates":[-71.18297,43.762521],"type":"Point"}
}