{
  "type": "Feature",
  "properties": {
    "addr:full":"500 Kearsarge Way Portsmouth NH 03801",
    "addr:housenumber":"500",
    "addr:postcode":"03801",
    "addr:street":"Kearsarge Way",
    "iso:country":"US",
    "sg:address":"500 Kearsarge Way",
    "sg:city":"Portsmouth",
    "sg:classifiers":[
        {
            "category":"Building & Trades",
            "subcategory":"Construction",
            "type":"Services"
        }
    ],
    "sg:phone":"+1 603 431 3374",
    "sg:postcode":"03801",
    "sg:province":"NH",
    "sg:tags":[
        "painter"
    ],
    "wof:name":"Paint New England",
    "wof:placetype":"venue"
},
  "geometry": {"coordinates":[-70.772312,43.090173],"type":"Point"}
}