{
  "type": "Feature",
  "properties": {
    "addr:full":"47 Sanborn Rd Londonderry NH 03053",
    "addr:housenumber":"47",
    "addr:postcode":"03053",
    "addr:street":"Sanborn Rd",
    "iso:country":"US",
    "sg:address":"47 Sanborn Rd",
    "sg:city":"Londonderry",
    "sg:classifiers":[
        {
            "category":"Wholesale",
            "subcategory":"Electrical",
            "type":"Manufacturing & Wholesale Goods"
        }
    ],
    "sg:phone":"+1 603 425 2671",
    "sg:postcode":"03053",
    "sg:province":"NH",
    "sg:tags":[
        "disposal",
        "garbage"
    ],
    "wof:name":"Tri-State Waste Svc",
    "wof:placetype":"venue"
},
  "geometry": {"coordinates":[-71.393878,42.919843],"type":"Point"}
}