{
  "type": "Feature",
  "properties": {
    "iso:country":"US",
    "sg:address":"13 Drummer Trl",
    "sg:city":"Laconia",
    "sg:classifiers":[
        {
            "category":"Building & Trades",
            "subcategory":"Plumbing",
            "type":"Services"
        }
    ],
    "sg:phone":"+1 603 524 7353",
    "sg:postcode":"03246",
    "sg:province":"NH",
    "sg:tags":[
        "air",
        "heating",
        "conditioning",
        "contractor"
    ],
    "wof:name":"Timothy J Plante",
    "wof:placetype":"venue"
},
  "geometry": {"coordinates":[-71.47089200000001,43.571816],"type":"Point"}
}