{
  "type": "Feature",
  "properties": {
    "iso:country":"US",
    "sg:address":"12 Rideout Ln",
    "sg:city":"Brookline",
    "sg:classifiers":[
        {
            "category":"Professional",
            "subcategory":"Engineering",
            "type":"Services"
        }
    ],
    "sg:phone":"+1 603 673 9733",
    "sg:postcode":"03033",
    "sg:province":"NH",
    "sg:tags":[
        "engineer"
    ],
    "wof:name":"LA Bombard Engineering",
    "wof:placetype":"venue"
},
  "geometry": {"coordinates":[-71.652868,42.744532],"type":"Point"}
}