{
  "type": "Feature",
  "properties": {
    "addr:full":"500 Jones Ave Portsmouth NH 03801",
    "addr:housenumber":"500",
    "addr:postcode":"03801",
    "addr:street":"Jones Ave",
    "iso:country":"US",
    "sg:address":"500 Jones Ave",
    "sg:city":"Portsmouth",
    "sg:classifiers":[
        {
            "category":"Restaurant",
            "type":"Food & Drink"
        }
    ],
    "sg:phone":"+1 603 431 2510",
    "sg:postcode":"03801",
    "sg:province":"NH",
    "sg:tags":[
        "banquet",
        "rooms"
    ],
    "wof:name":"Elks Lodge",
    "wof:placetype":"venue"
},
  "geometry": {"coordinates":[-70.75974100000001,43.059224],"type":"Point"}
}