{
  "type": "Feature",
  "properties": {
    "addr:full":"61 Royal Cir Salem NH 03079",
    "addr:housenumber":"61",
    "addr:postcode":"03079",
    "addr:street":"Royal Cir",
    "iso:country":"US",
    "sg:address":"61 Royal Cir",
    "sg:city":"Salem",
    "sg:classifiers":[
        {
            "category":"Building & Trades",
            "subcategory":"Plumbing",
            "type":"Services"
        }
    ],
    "sg:phone":"+1 603 894 0020",
    "sg:postcode":"03079",
    "sg:province":"NH",
    "sg:tags":[
        "plumbing",
        "contractor"
    ],
    "wof:name":"Bob's Plumbing & Heating",
    "wof:placetype":"venue"
},
  "geometry": {"coordinates":[-71.216814,42.78913],"type":"Point"}
}