{
  "type": "Feature",
  "properties": {
    "addr:full":"1 Overlook Dr Amherst NH 03031",
    "addr:housenumber":"1",
    "addr:postcode":"03031",
    "addr:street":"Overlook Dr",
    "iso:country":"US",
    "sg:address":"1 Overlook Dr",
    "sg:city":"Amherst",
    "sg:classifiers":[
        {
            "category":"Professional",
            "subcategory":"Accounting & Tax Preparation",
            "type":"Services"
        }
    ],
    "sg:phone":"+1 603 673 0336",
    "sg:postcode":"03031",
    "sg:province":"NH",
    "wof:name":"Christopher Rogers CPA",
    "wof:placetype":"venue"
},
  "geometry": {"coordinates":[-71.60800399999999,42.822703],"type":"Point"}
}