{
  "type": "Feature",
  "properties": {
    "iso:country":"US",
    "sg:address":"87 State Rte 132",
    "sg:city":"New Hampton",
    "sg:classifiers":[
        {
            "category":"Manufacturing",
            "subcategory":"Electronics",
            "type":"Manufacturing & Wholesale Goods"
        }
    ],
    "sg:phone":"+1 603 744 9177",
    "sg:postcode":"03256",
    "sg:province":"NH",
    "sg:tags":[
        "connector",
        "electronic"
    ],
    "wof:name":"Mar-Cam",
    "wof:placetype":"venue"
},
  "geometry": {"coordinates":[-71.647983,43.608231],"type":"Point"}
}