{
  "type": "Feature",
  "properties": {
    "iso:country":"US",
    "sg:address":"3 West Rd",
    "sg:city":"Hampstead",
    "sg:classifiers":[
        {
            "category":"Building & Trades",
            "subcategory":"Landscaping Services",
            "type":"Services"
        }
    ],
    "sg:phone":"+1 603 329 4254",
    "sg:postcode":"03841",
    "sg:province":"NH",
    "sg:tags":[
        "landscape",
        "contractor"
    ],
    "wof:name":"Auger Property Maintenance",
    "wof:placetype":"venue"
},
  "geometry": {"coordinates":[-71.19225900000001,42.868357],"type":"Point"}
}