{
  "type": "Feature",
  "properties": {
    "iso:country":"US",
    "sg:address":"27 Ridge Rd",
    "sg:city":"Holderness",
    "sg:classifiers":[
        {
            "category":"Building & Trades",
            "subcategory":"Construction",
            "type":"Services"
        }
    ],
    "sg:phone":"+1 603 968 9018",
    "sg:postcode":"03276",
    "sg:province":"NH",
    "wof:name":"Keeney Construction",
    "wof:placetype":"venue"
},
  "geometry": {"coordinates":[-71.55714399999999,43.479309],"type":"Point"}
}