{
  "type": "Feature",
  "properties": {
    "iso:country":"US",
    "sg:address":"160 Farmington Rd",
    "sg:city":"Rochester",
    "sg:classifiers":[
        {
            "category":"Autos & Motor Vehicles",
            "subcategory":"Automobile Sales",
            "type":"Retail Goods"
        }
    ],
    "sg:phone":"+1 603 822 1010",
    "sg:postcode":"03867",
    "sg:province":"NH",
    "sg:tags":[
        "car",
        "dealer"
    ],
    "wof:name":"Automart Of New England",
    "wof:placetype":"venue"
},
  "geometry": {"coordinates":[-71.015135,43.338805],"type":"Point"}
}