{
  "type": "Feature",
  "properties": {
    "iso:country":"US",
    "sg:address":"5 Patterson St",
    "sg:city":"Manchester",
    "sg:classifiers":[
        {
            "category":"Professional",
            "subcategory":"Business Services",
            "type":"Services"
        }
    ],
    "sg:phone":"+1 603 622 7111",
    "sg:postcode":"03102",
    "sg:province":"NH",
    "wof:name":"Structural Consultant NH",
    "wof:placetype":"venue"
},
  "geometry": {"coordinates":[-71.488066,42.967845],"type":"Point"}
}