{
  "type": "Feature",
  "properties": {
    "addr:full":"265 Maple St Manchester NH 03103",
    "addr:housenumber":"265",
    "addr:postcode":"03103",
    "addr:street":"Maple St",
    "iso:country":"US",
    "sg:address":"265 Maple St",
    "sg:city":"Manchester",
    "sg:classifiers":[
        {
            "category":"Organizations",
            "subcategory":"Religious Organization",
            "type":"Services"
        }
    ],
    "sg:phone":"+1 603 668 8106",
    "sg:postcode":"03103",
    "sg:province":"NH",
    "sg:tags":[
        "church"
    ],
    "wof:name":"Pentecostal Missonary Church",
    "wof:placetype":"venue"
},
  "geometry": {"coordinates":[-71.452907,42.982795],"type":"Point"}
}