{
  "type": "Feature",
  "properties": {
    "iso:country":"US",
    "sg:address":"7 Tinkham Ave",
    "sg:city":"Derry",
    "sg:classifiers":[
        {
            "category":"Banks & Credit Unions",
            "subcategory":"Investment Brokerage",
            "type":"Services"
        },
        {
            "category":"Professional",
            "subcategory":"Business Services",
            "type":"Services"
        }
    ],
    "sg:phone":"+1 603 437 3308",
    "sg:postcode":"03038",
    "sg:province":"NH",
    "sg:tags":[
        "broker",
        "commodity"
    ],
    "wof:name":"Aquila Services Corp",
    "wof:placetype":"venue"
},
  "geometry": {"coordinates":[-71.330736,42.893295],"type":"Point"}
}