{
  "type": "Feature",
  "properties": {
    "iso:country":"US",
    "sg:address":"246 W Main St",
    "sg:city":"Hillsboro",
    "sg:classifiers":[
        {
            "category":"Real Estate",
            "subcategory":"Real Estate Agent",
            "type":"Services"
        }
    ],
    "sg:phone":"+1 603 464 4036",
    "sg:postcode":"03244",
    "sg:province":"NH",
    "sg:website":"www.c21redcoat.com",
    "wof:name":"RED Coat Realty",
    "wof:placetype":"venue"
},
  "geometry": {"coordinates":[-71.914693,43.111398],"type":"Point"}
}