{
  "type": "Feature",
  "properties": {
    "addr:full":"113 Rockland Ave Manchester NH 03102",
    "addr:housenumber":"113",
    "addr:postcode":"03102",
    "addr:street":"Rockland Ave",
    "iso:country":"US",
    "sg:address":"113 Rockland Ave",
    "sg:city":"Manchester",
    "sg:classifiers":[
        {
            "category":"Building & Trades",
            "subcategory":"Construction",
            "type":"Services"
        }
    ],
    "sg:phone":"+1 603 627 7339",
    "sg:postcode":"03102",
    "sg:province":"NH",
    "sg:tags":[
        "general",
        "contractor"
    ],
    "wof:name":"A-1 Roofing",
    "wof:placetype":"venue"
},
  "geometry": {"coordinates":[-71.493143,42.981563],"type":"Point"}
}