{
  "type": "Feature",
  "properties": {
    "iso:country":"US",
    "sg:address":"18 Frost Rd",
    "sg:city":"Hill",
    "sg:classifiers":[
        {
            "category":"Retail",
            "subcategory":"Laundry & Dry Cleaning",
            "type":"Services"
        }
    ],
    "sg:phone":"+1 603 934 4986",
    "sg:postcode":"03243",
    "sg:province":"NH",
    "sg:tags":[
        "cleaners",
        "rug",
        "carpet"
    ],
    "wof:name":"Soot Busters",
    "wof:placetype":"venue"
},
  "geometry": {"coordinates":[-71.737377,43.531385],"type":"Point"}
}