{
  "type": "Feature",
  "properties": {
    "iso:country":"US",
    "sg:address":"31 Parkersville Ln",
    "sg:city":"Seabrook",
    "sg:classifiers":[
        {
            "category":"Arts & Performance",
            "subcategory":"Theater",
            "type":"Entertainment"
        }
    ],
    "sg:phone":"+1 603 474 7365",
    "sg:postcode":"03874",
    "sg:province":"NH",
    "sg:tags":[
        "entertainer"
    ],
    "wof:name":"Northeast Disc Jockey Assn",
    "wof:placetype":"venue"
},
  "geometry": {"coordinates":[-70.851708,42.86584],"type":"Point"}
}