{
  "type": "Feature",
  "properties": {
    "iso:country":"US",
    "sg:address":"91 Page Hill Rd",
    "sg:city":"New Ipswich",
    "sg:classifiers":[
        {
            "category":"Building & Trades",
            "subcategory":"Construction",
            "type":"Services"
        }
    ],
    "sg:phone":"+1 603 878 3259",
    "sg:postcode":"03071",
    "sg:province":"NH",
    "sg:tags":[
        "house"
    ],
    "wof:name":"Maillet Siding & Home Imprv",
    "wof:placetype":"venue"
},
  "geometry": {"coordinates":[-71.87593200000001,42.730974],"type":"Point"}
}