{
  "type": "Feature",
  "properties": {
    "iso:country":"US",
    "sg:address":"81 Fitzgerald Rd",
    "sg:city":"Rindge",
    "sg:classifiers":[
        {
            "category":"Building & Trades",
            "subcategory":"Construction",
            "type":"Services"
        }
    ],
    "sg:phone":"+1 603 899 5100",
    "sg:postcode":"03461",
    "sg:province":"NH",
    "sg:tags":[
        "contractor"
    ],
    "wof:name":"Gauthier Construction",
    "wof:placetype":"venue"
},
  "geometry": {"coordinates":[-72.007803,42.760757],"type":"Point"}
}