{
  "type": "Feature",
  "properties": {
    "addr:full":"4 Portsmouth Ave Exeter NH 03833",
    "addr:housenumber":"4",
    "addr:postcode":"03833",
    "addr:street":"Portsmouth Ave",
    "iso:country":"US",
    "sg:address":"4 Portsmouth Ave",
    "sg:city":"Exeter",
    "sg:classifiers":[
        {
            "category":"Shopping",
            "subcategory":"Bicycles & Sporting Goods",
            "type":"Retail Goods"
        }
    ],
    "sg:phone":"+1 603 778 2331",
    "sg:postcode":"03833",
    "sg:province":"NH",
    "sg:tags":[
        "repair"
    ],
    "wof:name":"Exeter Cycles",
    "wof:placetype":"venue"
},
  "geometry": {"coordinates":[-70.941462,42.981244],"type":"Point"}
}