{
  "type": "Feature",
  "properties": {
    "iso:country":"US",
    "sg:address":"4 Pawnee Ln",
    "sg:city":"Epping",
    "sg:classifiers":[
        {
            "category":"Wholesale",
            "subcategory":"Medical Equipment & Supplies",
            "type":"Manufacturing & Wholesale Goods"
        }
    ],
    "sg:phone":"+1 603 679 5629",
    "sg:postcode":"03042",
    "sg:province":"NH",
    "sg:tags":[
        "furniture"
    ],
    "wof:name":"Vine Healthcare Inc",
    "wof:placetype":"venue"
},
  "geometry": {"coordinates":[-71.092646,43.044245],"type":"Point"}
}