{
  "type": "Feature",
  "properties": {
    "addr:full":"168 Seamans Rd New London NH 03257",
    "addr:housenumber":"168",
    "addr:postcode":"03257",
    "addr:street":"Seamans Rd",
    "iso:country":"US",
    "sg:address":"168 Seamans Rd",
    "sg:city":"New London",
    "sg:classifiers":[
        {
            "category":"Real Estate",
            "subcategory":"Real Estate Agent",
            "type":"Services"
        }
    ],
    "sg:phone":"+1 603 526 4601",
    "sg:postcode":"03257",
    "sg:province":"NH",
    "wof:name":"Messer Real Estate Services",
    "wof:placetype":"venue"
},
  "geometry": {"coordinates":[-71.966887,43.412022],"type":"Point"}
}