{
  "type": "Feature",
  "properties": {
    "iso:country":"US",
    "sg:address":"1 Noble Dr",
    "sg:city":"Concord",
    "sg:classifiers":[
        {
            "category":"Government",
            "subcategory":"Office",
            "type":"Public Place"
        }
    ],
    "sg:phone":"+1 603 271 3751",
    "sg:postcode":"03301",
    "sg:province":"NH",
    "wof:name":"Honorable John T Broderick Jr",
    "wof:placetype":"venue"
},
  "geometry": {"coordinates":[-71.52047899999999,43.212876],"type":"Point"}
}