{
  "type": "Feature",
  "properties": {
    "addr:full":"39 Partridge Green Rochester NH 03867",
    "addr:housenumber":"39",
    "addr:postcode":"03867",
    "addr:street":"Partridge",
    "iso:country":"US",
    "sg:address":"39 Partridge Green",
    "sg:city":"Rochester",
    "sg:classifiers":[
        {
            "category":"Real Estate",
            "subcategory":"Real Estate Operator",
            "type":"Services"
        }
    ],
    "sg:phone":"+1 603 332 8852",
    "sg:postcode":"03867",
    "sg:province":"NH",
    "sg:tags":[
        "apartment"
    ],
    "wof:name":"Partridge Green Apartments",
    "wof:placetype":"venue"
},
  "geometry": {"coordinates":[-70.974632,43.287848],"type":"Point"}
}