{
  "type": "Feature",
  "properties": {
    "iso:country":"US",
    "sg:address":"92 Old New Ipswich Rd",
    "sg:city":"Rindge",
    "sg:classifiers":[
        {
            "category":"Freight",
            "type":"Transportation"
        }
    ],
    "sg:phone":"+1 603 899 6741",
    "sg:postcode":"03461",
    "sg:province":"NH",
    "wof:name":"Movin Up Movers",
    "wof:placetype":"venue"
},
  "geometry": {"coordinates":[-71.97765,42.765911],"type":"Point"}
}