{
  "type": "Feature",
  "properties": {
    "addr:full":"4 Kilton Rd Bedford NH 03110",
    "addr:housenumber":"4",
    "addr:postcode":"03110",
    "addr:street":"Kilton Rd",
    "iso:country":"US",
    "sg:address":"4 Kilton Rd",
    "sg:city":"Bedford",
    "sg:classifiers":[
        {
            "category":"Government",
            "subcategory":"Post Office",
            "type":"Public Place"
        }
    ],
    "sg:phone":"+1 603 668 3323",
    "sg:postcode":"03110",
    "sg:province":"NH",
    "wof:name":"US Post Office",
    "wof:placetype":"venue"
},
  "geometry": {"coordinates":[-71.47909900000001,42.956748],"type":"Point"}
}