{
  "type": "Feature",
  "properties": {
    "iso:country":"US",
    "sg:address":"24 Fitch Rd",
    "sg:city":"Dover",
    "sg:classifiers":[
        {
            "category":"Freight",
            "type":"Transportation"
        },
        {
            "category":"Real Estate",
            "subcategory":"Real Estate Agent",
            "type":"Services"
        }
    ],
    "sg:phone":"+1 603 742 3087",
    "sg:postcode":"03823",
    "sg:province":"NH",
    "sg:tags":[
        "operator",
        "local",
        "cooperative",
        "trucking"
    ],
    "wof:name":"Lamprey Regional Co Operative",
    "wof:placetype":"venue"
},
  "geometry": {"coordinates":[-70.93770499999999,43.185604],"type":"Point"}
}