{
  "type": "Feature",
  "properties": {
    "iso:country":"US",
    "sg:address":"20 Norway Ave",
    "sg:city":"Keene",
    "sg:classifiers":[
        {
            "category":"Professional",
            "subcategory":"Research",
            "type":"Services"
        }
    ],
    "sg:phone":"+1 603 357 1922",
    "sg:postcode":"03431",
    "sg:province":"NH",
    "sg:tags":[
        "organization",
        "noncommercial"
    ],
    "wof:name":"Monadock Collaborative",
    "wof:placetype":"venue"
},
  "geometry": {"coordinates":[-72.27494799999999,42.934049],"type":"Point"}
}