{
  "type": "Feature",
  "properties": {
    "iso:country":"US",
    "sg:address":"9 Manor View Dr",
    "sg:city":"Raymond",
    "sg:classifiers":[
        {
            "category":"Professional",
            "subcategory":"Management & Consulting",
            "type":"Services"
        }
    ],
    "sg:phone":"+1 603 895 4837",
    "sg:postcode":"03077",
    "sg:province":"NH",
    "sg:tags":[
        "business"
    ],
    "wof:name":"Ken Cameron",
    "wof:placetype":"venue"
},
  "geometry": {"coordinates":[-71.209153,43.044224],"type":"Point"}
}