{
  "type": "Feature",
  "properties": {
    "iso:country":"US",
    "sg:address":"66 S State St",
    "sg:city":"Concord",
    "sg:classifiers":[
        {
            "category":"Insurance",
            "subcategory":"Insurance Agent",
            "type":"Services"
        }
    ],
    "sg:phone":"+1 603 225 7597",
    "sg:postcode":"03301",
    "sg:province":"NH",
    "sg:tags":[
        "agency",
        "general"
    ],
    "wof:name":"Shamrock Insurance Inc",
    "wof:placetype":"venue"
},
  "geometry": {"coordinates":[-71.534255,43.198718],"type":"Point"}
}