{
  "type": "Feature",
  "properties": {
    "iso:country":"US",
    "sg:address":"12 Hawkview Rd",
    "sg:city":"Hudson",
    "sg:classifiers":[
        {
            "category":"Shopping",
            "type":"Retail Goods"
        }
    ],
    "sg:phone":"+1 603 886 5859",
    "sg:postcode":"03051",
    "sg:province":"NH",
    "sg:tags":[
        "merchandise"
    ],
    "wof:name":"Society Neng Artist Assn",
    "wof:placetype":"venue"
},
  "geometry": {"coordinates":[-71.369608,42.765764],"type":"Point"}
}