{
  "type": "Feature",
  "properties": {
    "iso:country":"US",
    "sg:address":"35 Pembroke Rd",
    "sg:city":"Concord",
    "sg:classifiers":[
        {
            "category":"Real Estate",
            "subcategory":"Real Estate Operator",
            "type":"Services"
        }
    ],
    "sg:phone":"+1 603 228 1315",
    "sg:postcode":"03301",
    "sg:province":"NH",
    "sg:tags":[
        "building",
        "nonresidential"
    ],
    "wof:name":"Ahern Property",
    "wof:placetype":"venue"
},
  "geometry": {"coordinates":[-71.510729,43.212502],"type":"Point"}
}