{
  "type": "Feature",
  "properties": {
    "iso:country":"US",
    "sg:address":"161 Londonderry Tpke",
    "sg:city":"Hooksett",
    "sg:classifiers":[
        {
            "category":"Organizations",
            "subcategory":"Labor Organization",
            "type":"Services"
        }
    ],
    "sg:phone":"+1 603 623 7302",
    "sg:postcode":"03106",
    "sg:province":"NH",
    "wof:name":"Nhaflcio",
    "wof:placetype":"venue"
},
  "geometry": {"coordinates":[-71.41406600000001,43.036276],"type":"Point"}
}