{
  "type": "Feature",
  "properties": {
    "addr:full":"660 Central Ave Dover NH 03820",
    "addr:housenumber":"660",
    "addr:postcode":"03820",
    "addr:street":"Central Ave",
    "iso:country":"US",
    "sg:address":"660 Central Ave",
    "sg:city":"Dover",
    "sg:classifiers":[
        {
            "category":"Organizations",
            "subcategory":"Religious Organization",
            "type":"Services"
        }
    ],
    "sg:phone":"+1 603 742 8210",
    "sg:postcode":"03820",
    "sg:province":"NH",
    "sg:tags":[
        "church"
    ],
    "wof:name":"Church Of Christ",
    "wof:placetype":"venue"
},
  "geometry": {"coordinates":[-70.875439,43.206239],"type":"Point"}
}