{
  "type": "Feature",
  "properties": {
    "iso:country":"US",
    "sg:address":"966 Hurricane Hill Rd",
    "sg:city":"Greenville",
    "sg:classifiers":[
        {
            "category":"Social Services",
            "subcategory":"Child Care",
            "type":"Services"
        },
        {
            "category":"Education",
            "subcategory":"Special Training",
            "type":"Public Place"
        }
    ],
    "sg:phone":"+1 603 878 6006",
    "sg:postcode":"03048",
    "sg:province":"NH",
    "sg:tags":[
        "tutoring",
        "day"
    ],
    "wof:name":"Creative Learning Solutions",
    "wof:placetype":"venue"
},
  "geometry": {"coordinates":[-71.728308,42.72868],"type":"Point"}
}