{
  "type": "Feature",
  "properties": {
    "iso:country":"US",
    "sg:address":"25 Black Brook Rd",
    "sg:city":"Goffstown",
    "sg:classifiers":[
        {
            "category":"Building & Trades",
            "subcategory":"Construction",
            "type":"Services"
        }
    ],
    "sg:phone":"+1 603 497 3235",
    "sg:postcode":"03045",
    "sg:province":"NH",
    "sg:tags":[
        "house"
    ],
    "wof:name":"Hallix Builders",
    "wof:placetype":"venue"
},
  "geometry": {"coordinates":[-71.513767,43.035641],"type":"Point"}
}