{
  "type": "Feature",
  "properties": {
    "iso:country":"US",
    "sg:address":"12 School St",
    "sg:city":"Hudson",
    "sg:classifiers":[
        {
            "category":"Government",
            "subcategory":"Office",
            "type":"Public Place"
        }
    ],
    "sg:phone":"+1 603 886 6003",
    "sg:postcode":"03051",
    "sg:province":"NH",
    "sg:tags":[
        "city"
    ],
    "wof:name":"Hudson Town Clerk",
    "wof:placetype":"venue"
},
  "geometry": {"coordinates":[-71.440517,42.763431],"type":"Point"}
}