{
  "type": "Feature",
  "properties": {
    "iso:country":"US",
    "sg:address":"95 Ledge Rd",
    "sg:city":"Seabrook",
    "sg:classifiers":[
        {
            "category":"Professional",
            "subcategory":"Computer Services",
            "type":"Services"
        }
    ],
    "sg:phone":"+1 603 418 8334",
    "sg:postcode":"03874",
    "sg:province":"NH",
    "sg:tags":[
        "internet"
    ],
    "wof:name":"Cortex LLC",
    "wof:placetype":"venue"
},
  "geometry": {"coordinates":[-70.89049199999999,42.890302],"type":"Point"}
}