{
  "type": "Feature",
  "properties": {
    "addr:full":"85 Dartmouth College Rd Lyme NH 03765",
    "addr:housenumber":"85",
    "addr:postcode":"03765",
    "addr:street":"Dartmouth College Rd",
    "iso:country":"US",
    "sg:address":"85 Dartmouth College Rd",
    "sg:city":"Lyme",
    "sg:classifiers":[
        {
            "category":"Real Estate",
            "subcategory":"Real Estate Agent",
            "type":"Services"
        }
    ],
    "sg:phone":"+1 603 795 4438",
    "sg:postcode":"03765",
    "sg:province":"NH",
    "wof:name":"Technology Appraisals",
    "wof:placetype":"venue"
},
  "geometry": {"coordinates":[-72.068658,44.026776],"type":"Point"}
}