{
  "type": "Feature",
  "properties": {
    "iso:country":"US",
    "sg:address":"1 Ledgewood Dr",
    "sg:city":"Derry",
    "sg:classifiers":[
        {
            "category":"Professional",
            "subcategory":"Management & Consulting",
            "type":"Services"
        }
    ],
    "sg:phone":"+1 603 434 2775",
    "sg:postcode":"03038",
    "sg:province":"NH",
    "sg:tags":[
        "consultant"
    ],
    "wof:name":"Total Quality Solutions Inc",
    "wof:placetype":"venue"
},
  "geometry": {"coordinates":[-71.314814,42.930538],"type":"Point"}
}