{
  "type": "Feature",
  "properties": {
    "iso:country":"US",
    "sg:address":"132 Whig Hill Rd",
    "sg:city":"Strafford",
    "sg:classifiers":[
        {
            "category":"Building & Trades",
            "subcategory":"Construction",
            "type":"Services"
        }
    ],
    "sg:phone":"+1 603 817 3666",
    "sg:postcode":"03884",
    "sg:province":"NH",
    "sg:tags":[
        "nonresidential"
    ],
    "wof:name":"Linco Co",
    "wof:placetype":"venue"
},
  "geometry": {"coordinates":[-71.15019100000001,43.225968],"type":"Point"}
}