{
  "type": "Feature",
  "properties": {
    "addr:full":"28 Railroad Sq Nashua NH 03064",
    "addr:housenumber":"28",
    "addr:postcode":"03064",
    "addr:street":"Railroad Sq",
    "iso:country":"US",
    "sg:address":"28 Railroad Sq",
    "sg:city":"Nashua",
    "sg:classifiers":[
        {
            "category":"Personal",
            "subcategory":"Beauty Salon",
            "type":"Services"
        }
    ],
    "sg:phone":"+1 603 882 3900",
    "sg:postcode":"03064",
    "sg:province":"NH",
    "sg:tags":[
        "shop"
    ],
    "wof:name":"Pretty Nails of Nashua",
    "wof:placetype":"venue"
},
  "geometry": {"coordinates":[-71.46621399999999,42.764732],"type":"Point"}
}