{
  "type": "Feature",
  "properties": {
    "addr:full":"44 Pinkham Rd Durham NH 03861",
    "addr:housenumber":"44",
    "addr:postcode":"03861",
    "addr:street":"Pinkham Rd",
    "iso:country":"US",
    "sg:address":"44 Pinkham Rd",
    "sg:city":"Durham",
    "sg:classifiers":[
        {
            "category":"Professional",
            "subcategory":"Management & Consulting",
            "type":"Services"
        }
    ],
    "sg:phone":"+1 603 969 9390",
    "sg:postcode":"03861",
    "sg:province":"NH",
    "sg:tags":[
        "consultant",
        "training",
        "education"
    ],
    "wof:name":"Dory Educational and Training",
    "wof:placetype":"venue"
},
  "geometry": {"coordinates":[-70.99303,43.158428],"type":"Point"}
}