{
  "type": "Feature",
  "properties": {
    "addr:full":"348 Daniel Webster Hwy Merrimack NH 03054",
    "addr:housenumber":"348",
    "addr:postcode":"03054",
    "addr:street":"Daniel Webster Hwy",
    "iso:country":"US",
    "sg:address":"348 Daniel Webster Hwy",
    "sg:city":"Merrimack",
    "sg:classifiers":[
        {
            "category":"Retail",
            "subcategory":"Auto Repair",
            "type":"Services"
        }
    ],
    "sg:phone":"+1 603 424 1432",
    "sg:postcode":"03054",
    "sg:province":"NH",
    "sg:tags":[
        "repairing",
        "automobile"
    ],
    "wof:name":"Monro Muffler Brake & Svc",
    "wof:placetype":"venue"
},
  "geometry": {"coordinates":[-71.493506,42.848048],"type":"Point"}
}