{
  "type": "Feature",
  "properties": {
    "iso:country":"US",
    "sg:address":"187 Main Dunstable Rd",
    "sg:city":"Nashua",
    "sg:classifiers":[
        {
            "category":"Shopping",
            "subcategory":"Bicycles & Sporting Goods",
            "type":"Retail Goods"
        }
    ],
    "sg:phone":"+1 603 882 2929",
    "sg:postcode":"03060",
    "sg:province":"NH",
    "sg:tags":[
        "snowboard"
    ],
    "wof:name":"Boarder's Edge",
    "wof:placetype":"venue"
},
  "geometry": {"coordinates":[-71.489914,42.746123],"type":"Point"}
}