{
  "type": "Feature",
  "properties": {
    "iso:country":"US",
    "sg:address":"170 Emerald St",
    "sg:city":"Keene",
    "sg:classifiers":[
        {
            "category":"Manufacturing",
            "subcategory":"Printing",
            "type":"Manufacturing & Wholesale Goods"
        }
    ],
    "sg:phone":"+1 603 357 7060",
    "sg:postcode":"03431",
    "sg:province":"NH",
    "sg:tags":[
        "organization",
        "publishing",
        "labor"
    ],
    "wof:name":"Your Local Directory",
    "wof:placetype":"venue"
},
  "geometry": {"coordinates":[-72.28457899999999,42.930265],"type":"Point"}
}