{
  "type": "Feature",
  "properties": {
    "iso:country":"US",
    "sg:address":"210 Henniker St",
    "sg:city":"Hillsborough",
    "sg:classifiers":[
        {
            "category":"Restaurant",
            "type":"Food & Drink"
        }
    ],
    "sg:phone":"+1 603 464 6314",
    "sg:postcode":"03244",
    "sg:province":"NH",
    "sg:tags":[
        "eating"
    ],
    "wof:name":"Brunchys Restaurant LLC",
    "wof:placetype":"venue"
},
  "geometry": {"coordinates":[-71.886279,43.125353],"type":"Point"}
}