{
  "type": "Feature",
  "properties": {
    "iso:country":"US",
    "sg:address":"40 Winchester Dr",
    "sg:city":"Center Barnstead",
    "sg:classifiers":[
        {
            "category":"Building & Trades",
            "subcategory":"Construction",
            "type":"Services"
        }
    ],
    "sg:phone":"+1 603 776 0611",
    "sg:postcode":"03225",
    "sg:province":"NH",
    "sg:tags":[
        "contractor"
    ],
    "wof:name":"Howe Home Improvement",
    "wof:placetype":"venue"
},
  "geometry": {"coordinates":[-71.233653,43.377309],"type":"Point"}
}