{
  "type": "Feature",
  "properties": {
    "iso:country":"US",
    "sg:address":"1 Nashua St",
    "sg:city":"Milford",
    "sg:classifiers":[
        {
            "category":"Personal",
            "subcategory":"Barber",
            "type":"Services"
        }
    ],
    "sg:phone":"+1 603 672 8337",
    "sg:postcode":"03055",
    "sg:province":"NH",
    "sg:tags":[
        "shop"
    ],
    "wof:name":"Gentlemens Weekly",
    "wof:placetype":"venue"
},
  "geometry": {"coordinates":[-71.649075,42.835496],"type":"Point"}
}