{
  "type": "Feature",
  "properties": {
    "addr:full":"20 Checkerberry Rd East Hampstead NH 03826",
    "addr:housenumber":"20",
    "addr:postcode":"03826",
    "addr:street":"Checkerberry Rd",
    "iso:country":"US",
    "sg:address":"20 Checkerberry Rd",
    "sg:city":"East Hampstead",
    "sg:classifiers":[
        {
            "category":"Professional",
            "subcategory":"Accounting & Tax Preparation",
            "type":"Services"
        }
    ],
    "sg:phone":"+1 603 382 2234",
    "sg:postcode":"03826",
    "sg:province":"NH",
    "wof:name":"Greene S & Co",
    "wof:placetype":"venue"
},
  "geometry": {"coordinates":[-71.124442,42.892684],"type":"Point"}
}