{
  "type": "Feature",
  "properties": {
    "iso:country":"US",
    "sg:address":"43 Bunker St",
    "sg:city":"Farmington",
    "sg:classifiers":[
        {
            "category":"Retail",
            "subcategory":"Auto Repair",
            "type":"Services"
        }
    ],
    "sg:phone":"+1 603 755 2590",
    "sg:postcode":"03835",
    "sg:province":"NH",
    "sg:tags":[
        "repairing",
        "automobile"
    ],
    "wof:name":"Bob's Garage",
    "wof:placetype":"venue"
},
  "geometry": {"coordinates":[-71.06040900000001,43.395869],"type":"Point"}
}