{
  "type": "Feature",
  "properties": {
    "addr:full":"6A Dover Point Rd Dover NH 03820",
    "addr:housenumber":"6a",
    "addr:postcode":"03820",
    "addr:street":"Dover Point Rd",
    "iso:country":"US",
    "sg:address":"6A Dover Point Rd",
    "sg:city":"Dover",
    "sg:classifiers":[
        {
            "category":"Professional",
            "subcategory":"Employment Agencies",
            "type":"Services"
        }
    ],
    "sg:phone":"+1 603 617 4319",
    "sg:postcode":"03820",
    "sg:province":"NH",
    "sg:tags":[
        "temporary",
        "contractor"
    ],
    "sg:website":"http://portsmouth.citysearch.com/profile/external/6566934/dover_nh/manpower.html?publisher=yellowpages&reference_id=1&placement=ypwebsitemip",
    "wof:name":"Manpower",
    "wof:placetype":"venue"
},
  "geometry": {"coordinates":[-70.867164,43.176313],"type":"Point"}
}