{
  "type": "Feature",
  "properties": {
    "iso:country":"US",
    "sg:address":"6 Greenleaf Woods Dr",
    "sg:city":"Portsmouth",
    "sg:classifiers":[
        {
            "category":"Professional",
            "subcategory":"Employment Agencies",
            "type":"Services"
        }
    ],
    "sg:phone":"+1 603 436 4283",
    "sg:postcode":"03801",
    "sg:province":"NH",
    "wof:name":"Cft",
    "wof:placetype":"venue"
},
  "geometry": {"coordinates":[-70.776028,43.054523],"type":"Point"}
}