{
  "type": "Feature",
  "properties": {
    "addr:full":"46 Patton St Rochester NH 03867",
    "addr:housenumber":"46",
    "addr:postcode":"03867",
    "addr:street":"Patton St",
    "iso:country":"US",
    "sg:address":"46 Patton St",
    "sg:city":"Rochester",
    "sg:classifiers":[
        {
            "category":"Arena",
            "subcategory":"Sports Club",
            "type":"Entertainment"
        }
    ],
    "sg:phone":"+1 603 332 8857",
    "sg:postcode":"03867",
    "sg:province":"NH",
    "wof:name":"RC United Soccer Club",
    "wof:placetype":"venue"
},
  "geometry": {"coordinates":[-70.987104,43.313512],"type":"Point"}
}