{
  "type": "Feature",
  "properties": {
    "iso:country":"US",
    "sg:address":"12 Madison Ave",
    "sg:city":"Hooksett",
    "sg:classifiers":[
        {
            "category":"Organizations",
            "subcategory":"Community Association",
            "type":"Services"
        }
    ],
    "sg:phone":"+1 603 668 8035",
    "sg:postcode":"03106",
    "sg:province":"NH",
    "wof:name":"Free & Accepted Masons of",
    "wof:placetype":"venue"
},
  "geometry": {"coordinates":[-71.430486,43.045457],"type":"Point"}
}