{
  "type": "Feature",
  "properties": {
    "addr:full":"29 Goodell Rd Antrim NH 03440",
    "addr:housenumber":"29",
    "addr:postcode":"03440",
    "addr:street":"Goodell Rd",
    "iso:country":"US",
    "sg:address":"29 Goodell Rd",
    "sg:city":"Antrim",
    "sg:classifiers":[
        {
            "category":"Education",
            "subcategory":"Library",
            "type":"Public Place"
        }
    ],
    "sg:phone":"+1 603 588 2338",
    "sg:postcode":"03440",
    "sg:province":"NH",
    "wof:name":"North Branch Refrigeration",
    "wof:placetype":"venue"
},
  "geometry": {"coordinates":[-71.93828000000001,43.042604],"type":"Point"}
}