{
  "type": "Feature",
  "properties": {
    "iso:country":"US",
    "sg:address":"270 Amory St",
    "sg:city":"Manchester",
    "sg:classifiers":[
        {
            "category":"Building & Trades",
            "subcategory":"Construction",
            "type":"Services"
        }
    ],
    "sg:phone":"+1 603 622 7278",
    "sg:postcode":"03102",
    "sg:province":"NH",
    "sg:tags":[
        "ceiling",
        "work",
        "contractor",
        "acoustical",
        "home",
        "remodeling"
    ],
    "wof:name":"Acoustic Boucher Contractor",
    "wof:placetype":"venue"
},
  "geometry": {"coordinates":[-71.480512,42.993287],"type":"Point"}
}