{
  "type": "Feature",
  "properties": {
    "iso:country":"US",
    "sg:address":"819 2nd St",
    "sg:city":"Manchester",
    "sg:classifiers":[
        {
            "category":"Shopping",
            "subcategory":"Computers & Home Electronics",
            "type":"Retail Goods"
        }
    ],
    "sg:phone":"+1 603 472 9704",
    "sg:postcode":"03102",
    "sg:province":"NH",
    "sg:tags":[
        "parts",
        "supply"
    ],
    "wof:name":"N H Recharge Svc Co",
    "wof:placetype":"venue"
},
  "geometry": {"coordinates":[-71.478326,42.970586],"type":"Point"}
}