{
  "type": "Feature",
  "properties": {
    "addr:full":"333 Central Ave Dover NH 03820",
    "addr:housenumber":"333",
    "addr:postcode":"03820",
    "addr:street":"Central Ave",
    "iso:country":"US",
    "sg:address":"333 Central Ave",
    "sg:city":"Dover",
    "sg:classifiers":[
        {
            "category":"Manufacturing",
            "subcategory":"Printing",
            "type":"Manufacturing & Wholesale Goods"
        }
    ],
    "sg:phone":"+1 603 742 4455",
    "sg:postcode":"03820",
    "sg:province":"NH",
    "sg:tags":[
        "newspaper"
    ],
    "sg:website":"www.fosters.com",
    "wof:name":"Foster's Daily Democrat",
    "wof:placetype":"venue"
},
  "geometry": {"coordinates":[-70.874639,43.194989],"type":"Point"}
}