{
  "type": "Feature",
  "properties": {
    "iso:country":"US",
    "sg:address":"516 State Rte 11",
    "sg:city":"Farmington",
    "sg:classifiers":[
        {
            "category":"Home & Garden",
            "subcategory":"Building Materials",
            "type":"Retail Goods"
        }
    ],
    "sg:phone":"+1 603 755 2422",
    "sg:postcode":"03835",
    "sg:province":"NH",
    "sg:tags":[
        "glass",
        "window",
        "plate"
    ],
    "wof:name":"Farmington Glass",
    "wof:placetype":"venue"
},
  "geometry": {"coordinates":[-71.06039,43.375598],"type":"Point"}
}