{
  "type": "Feature",
  "properties": {
    "iso:country":"US",
    "sg:address":"837 W Hollis St",
    "sg:city":"Nashua",
    "sg:classifiers":[
        {
            "category":"Real Estate",
            "subcategory":"Real Estate Operator",
            "type":"Services"
        }
    ],
    "sg:phone":"+1 603 882 3285",
    "sg:postcode":"03062",
    "sg:province":"NH",
    "sg:tags":[
        "mobile",
        "home",
        "community"
    ],
    "wof:name":"Rodgers Mobile Homes Park Inc",
    "wof:placetype":"venue"
},
  "geometry": {"coordinates":[-71.523543,42.734629],"type":"Point"}
}