{
  "type": "Feature",
  "properties": {
    "iso:country":"US",
    "sg:address":"30 N Sandwich Rd",
    "sg:city":"Center Sandwich",
    "sg:classifiers":[
        {
            "category":"Professional",
            "type":"Services"
        }
    ],
    "sg:phone":"+1 603 284 6400",
    "sg:postcode":"03227",
    "sg:province":"NH",
    "wof:name":"Wendy Vandepoll",
    "wof:placetype":"venue"
},
  "geometry": {"coordinates":[-71.432132,43.812739],"type":"Point"}
}