{
  "type": "Feature",
  "properties": {
    "iso:country":"US",
    "sg:address":"16 Main St",
    "sg:city":"Goffstown",
    "sg:classifiers":[
        {
            "category":"Government",
            "subcategory":"Office",
            "type":"Public Place"
        }
    ],
    "sg:phone":"+1 603 497 3615",
    "sg:postcode":"03045",
    "sg:province":"NH",
    "sg:tags":[
        "village"
    ],
    "wof:name":"Goffstown Accounting Dept",
    "wof:placetype":"venue"
},
  "geometry": {"coordinates":[-71.59995000000001,43.01938],"type":"Point"}
}