{
  "type": "Feature",
  "properties": {
    "addr:full":"2 S Mast Rd Goffstown NH 03045",
    "addr:housenumber":"2",
    "addr:postcode":"03045",
    "addr:street":"S Mast Rd",
    "iso:country":"US",
    "sg:address":"2 S Mast Rd",
    "sg:city":"Goffstown",
    "sg:classifiers":[
        {
            "category":"Food & Beverages",
            "subcategory":"Bakery",
            "type":"Retail Goods"
        }
    ],
    "sg:phone":"+1 603 497 5338",
    "sg:postcode":"03045",
    "sg:province":"NH",
    "sg:tags":[
        "doughnut"
    ],
    "wof:name":"Dunkin Donuts",
    "wof:placetype":"venue"
},
  "geometry": {"coordinates":[-71.59684300000001,43.015497],"type":"Point"}
}