{
  "type": "Feature",
  "properties": {
    "iso:country":"US",
    "sg:address":"26 Glance Rd",
    "sg:city":"Windham",
    "sg:classifiers":[
        {
            "category":"Personal",
            "subcategory":"Beauty Salon",
            "type":"Services"
        }
    ],
    "sg:phone":"+1 603 883 9062",
    "sg:postcode":"03087",
    "sg:province":"NH",
    "wof:name":"Cutting Co I",
    "wof:placetype":"venue"
},
  "geometry": {"coordinates":[-71.341945,42.789863],"type":"Point"}
}