{
  "type": "Feature",
  "properties": {
    "iso:country":"US",
    "sg:address":"23 School St",
    "sg:city":"Laconia",
    "sg:classifiers":[
        {
            "category":"Building & Trades",
            "subcategory":"Cleaning & Sanitation",
            "type":"Services"
        }
    ],
    "sg:phone":"+1 603 528 0702",
    "sg:postcode":"03246",
    "sg:province":"NH",
    "sg:tags":[
        "maintenance"
    ],
    "wof:name":"ServiceMaster",
    "wof:placetype":"venue"
},
  "geometry": {"coordinates":[-71.469672,43.551343],"type":"Point"}
}