{
  "type": "Feature",
  "properties": {
    "addr:full":"76 Lyme Rd Hanover NH 03755",
    "addr:housenumber":"76",
    "addr:postcode":"03755",
    "addr:street":"Lyme Rd",
    "iso:country":"US",
    "sg:address":"76 Lyme Rd",
    "sg:city":"Hanover",
    "sg:classifiers":[
        {
            "category":"Building & Trades",
            "subcategory":"Construction",
            "type":"Services"
        }
    ],
    "sg:phone":"+1 603 643 4295",
    "sg:postcode":"03755",
    "sg:province":"NH",
    "sg:tags":[
        "general",
        "contractor"
    ],
    "wof:name":"L & M Svc Contractors",
    "wof:placetype":"venue"
},
  "geometry": {"coordinates":[-72.269203,43.726682],"type":"Point"}
}