{
  "type": "Feature",
  "properties": {
    "addr:full":"120 Church St North Walpole NH 03609",
    "addr:housenumber":"120",
    "addr:postcode":"03609",
    "addr:street":"Church St",
    "iso:country":"US",
    "sg:address":"120 Church St",
    "sg:city":"North Walpole",
    "sg:classifiers":[
        {
            "category":"Autos & Motor Vehicles",
            "subcategory":"Auto Supplies",
            "type":"Retail Goods"
        }
    ],
    "sg:phone":"+1 603 445 2102",
    "sg:postcode":"03609",
    "sg:province":"NH",
    "sg:tags":[
        "automobile",
        "parts"
    ],
    "wof:name":"Fast Auto Works",
    "wof:placetype":"venue"
},
  "geometry": {"coordinates":[-72.451421,43.146506],"type":"Point"}
}