{
  "type": "Feature",
  "properties": {
    "iso:country":"US",
    "sg:address":"15 Roulston Rd",
    "sg:city":"Windham",
    "sg:classifiers":[
        {
            "category":"Wholesale",
            "subcategory":"Machinery & Supplies",
            "type":"Manufacturing & Wholesale Goods"
        }
    ],
    "sg:phone":"+1 603 898 5738",
    "sg:postcode":"03087",
    "sg:province":"NH",
    "sg:tags":[
        "carpet",
        "cleaning",
        "rug"
    ],
    "wof:name":"Accredited Environmental Svc",
    "wof:placetype":"venue"
},
  "geometry": {"coordinates":[-71.25741499999999,42.813417],"type":"Point"}
}