{
  "type": "Feature",
  "properties": {
    "iso:country":"US",
    "sg:address":"23 Lucille Ave",
    "sg:city":"Salem",
    "sg:classifiers":[
        {
            "category":"Retail",
            "subcategory":"Laundry & Dry Cleaning",
            "type":"Services"
        }
    ],
    "sg:phone":"+1 603 893 7660",
    "sg:postcode":"03079",
    "sg:province":"NH",
    "wof:name":"Special Touch",
    "wof:placetype":"venue"
},
  "geometry": {"coordinates":[-71.239102,42.787793],"type":"Point"}
}