{
  "type": "Feature",
  "properties": {
    "iso:country":"US",
    "sg:address":"41 Barnet Rd",
    "sg:city":"Monroe",
    "sg:classifiers":[
        {
            "category":"Retail",
            "subcategory":"Veterinary Services",
            "type":"Services"
        }
    ],
    "sg:phone":"+1 603 638 2679",
    "sg:postcode":"03771",
    "sg:province":"NH",
    "sg:tags":[
        "clinic"
    ],
    "wof:name":"Dairy Veterinary Services PA",
    "wof:placetype":"venue"
},
  "geometry": {"coordinates":[-72.05406499999999,44.285346],"type":"Point"}
}