{
  "type": "Feature",
  "properties": {
    "iso:country":"US",
    "sg:address":"700 Marlboro St",
    "sg:city":"Keene",
    "sg:classifiers":[
        {
            "category":"Retail",
            "subcategory":"Animal Services",
            "type":"Services"
        }
    ],
    "sg:phone":"+1 603 357 7387",
    "sg:postcode":"03431",
    "sg:province":"NH",
    "wof:name":"Glad Wags Grooming",
    "wof:placetype":"venue"
},
  "geometry": {"coordinates":[-72.243788,42.914703],"type":"Point"}
}