{
  "type": "Feature",
  "properties": {
    "iso:country":"US",
    "sg:address":"57 Harvey Rd",
    "sg:city":"Londonderry",
    "sg:phone":"+1 603 537 9816",
    "sg:postcode":"03053",
    "sg:province":"NH",
    "sg:tags":[
        "irrigation",
        "system"
    ],
    "wof:name":"Castle Springs",
    "wof:placetype":"venue"
},
  "geometry": {"coordinates":[-71.420563,42.909517],"type":"Point"}
}