{
  "type": "Feature",
  "properties": {
    "iso:country":"US",
    "sg:address":"155 Portland Ave",
    "sg:city":"Dover",
    "sg:classifiers":[
        {
            "category":"Shopping",
            "subcategory":"Florist",
            "type":"Retail Goods"
        }
    ],
    "sg:phone":"+1 603 742 1165",
    "sg:postcode":"03820",
    "sg:province":"NH",
    "sg:tags":[
        "shop",
        "gift"
    ],
    "wof:name":"Sweet Meadows Flower & Gift Sp",
    "wof:placetype":"venue"
},
  "geometry": {"coordinates":[-70.85947299999999,43.205225],"type":"Point"}
}