{
  "type": "Feature",
  "properties": {
    "iso:country":"US",
    "sg:address":"84 S Broadway",
    "sg:city":"Salem",
    "sg:classifiers":[
        {
            "category":"Retail",
            "subcategory":"Auto Rental",
            "type":"Services"
        }
    ],
    "sg:phone":"+1 603 894 0022",
    "sg:postcode":"03079",
    "sg:province":"NH",
    "sg:tags":[
        "renting",
        "automobile"
    ],
    "wof:name":"Circle Rent A Car",
    "wof:placetype":"venue"
},
  "geometry": {"coordinates":[-71.221065,42.770196],"type":"Point"}
}