{
  "type": "Feature",
  "properties": {
    "addr:full":"297 Mayhew Tpke Bristol NH 03222",
    "addr:housenumber":"297",
    "addr:postcode":"03222",
    "addr:street":"Mayhew Tpke",
    "iso:country":"US",
    "sg:address":"297 Mayhew Tpke",
    "sg:city":"Bristol",
    "sg:classifiers":[
        {
            "category":"Government",
            "subcategory":"Office",
            "type":"Public Place"
        }
    ],
    "sg:phone":"+1 603 744 5055",
    "sg:postcode":"03222",
    "sg:province":"NH",
    "sg:tags":[
        "village"
    ],
    "wof:name":"Bridgewater Selectmen's Office",
    "wof:placetype":"venue"
},
  "geometry": {"coordinates":[-71.73560500000001,43.639888],"type":"Point"}
}