{
  "type": "Feature",
  "properties": {
    "iso:country":"US",
    "sg:address":"404 State Rte 125",
    "sg:city":"Exeter",
    "sg:classifiers":[
        {
            "category":"Wholesale",
            "subcategory":"Construction Materials",
            "type":"Manufacturing & Wholesale Goods"
        }
    ],
    "sg:phone":"+1 603 772 6355",
    "sg:postcode":"03833",
    "sg:province":"NH",
    "sg:tags":[
        "building"
    ],
    "wof:name":"Shorts Supply Company Inc",
    "wof:placetype":"venue"
},
  "geometry": {"coordinates":[-71.07559500000001,43.009135],"type":"Point"}
}