{
  "type": "Feature",
  "properties": {
    "addr:full":"2 Ingalls Ter Plaistow NH 03865",
    "addr:housenumber":"2",
    "addr:postcode":"03865",
    "addr:street":"Ingalls Ter",
    "iso:country":"US",
    "sg:address":"2 Ingalls Ter",
    "sg:city":"Plaistow",
    "sg:classifiers":[
        {
            "category":"Local Transit",
            "type":"Transportation"
        }
    ],
    "sg:phone":"+1 603 382 7610",
    "sg:postcode":"03865",
    "sg:province":"NH",
    "sg:tags":[
        "shuttle",
        "passenger"
    ],
    "wof:name":"Andover Coach",
    "wof:placetype":"venue"
},
  "geometry": {"coordinates":[-71.097992,42.842121],"type":"Point"}
}