{
  "type": "Feature",
  "properties": {
    "iso:country":"US",
    "sg:address":"119 Turner St",
    "sg:city":"Bethlehem",
    "sg:classifiers":[
        {
            "category":"Home & Garden",
            "subcategory":"Household Appliances",
            "type":"Retail Goods"
        }
    ],
    "sg:phone":"+1 603 869 2169",
    "sg:postcode":"03574",
    "sg:province":"NH",
    "wof:name":"Profile Appliance Svc Ctr",
    "wof:placetype":"venue"
},
  "geometry": {"coordinates":[-71.678653,44.2797],"type":"Point"}
}