{
  "type": "Feature",
  "properties": {
    "addr:full":"370 Harvey Rd Manchester NH 03103",
    "addr:housenumber":"370",
    "addr:postcode":"03103",
    "addr:street":"Harvey Rd",
    "iso:country":"US",
    "sg:address":"370 Harvey Rd",
    "sg:city":"Manchester",
    "sg:classifiers":[
        {
            "category":"Professional",
            "subcategory":"Employment Agencies",
            "type":"Services"
        }
    ],
    "sg:phone":"+1 603 606 7177",
    "sg:postcode":"03103",
    "sg:province":"NH",
    "sg:tags":[
        "opportunity"
    ],
    "wof:name":"Express Personnel Svc",
    "wof:placetype":"venue"
},
  "geometry": {"coordinates":[-71.429483,42.940933],"type":"Point"}
}