{
  "type": "Feature",
  "properties": {
    "iso:country":"US",
    "sg:address":"27 Sunset Dr",
    "sg:city":"Littleton",
    "sg:classifiers":[
        {
            "category":"Building & Trades",
            "subcategory":"Construction",
            "type":"Services"
        }
    ],
    "sg:phone":"+1 603 444 5052",
    "sg:postcode":"03561",
    "sg:province":"NH",
    "sg:tags":[
        "painter"
    ],
    "wof:name":"Littleton Pre-Stain Co",
    "wof:placetype":"venue"
},
  "geometry": {"coordinates":[-71.783725,44.311799],"type":"Point"}
}