{
  "type": "Feature",
  "properties": {
    "addr:full":"4 Coliseum Ave Nashua NH 03063",
    "addr:housenumber":"4",
    "addr:postcode":"03063",
    "addr:street":"Coliseum Ave",
    "iso:country":"US",
    "sg:address":"4 Coliseum Ave",
    "sg:city":"Nashua",
    "sg:classifiers":[
        {
            "category":"Shopping",
            "subcategory":"Gifts & Souvenirs",
            "type":"Retail Goods"
        }
    ],
    "sg:phone":"+1 603 598 5240",
    "sg:postcode":"03063",
    "sg:province":"NH",
    "sg:tags":[
        "shop"
    ],
    "wof:name":"Irish Cottage Inc",
    "wof:placetype":"venue"
},
  "geometry": {"coordinates":[-71.497615,42.7661],"type":"Point"}
}