{
  "type": "Feature",
  "properties": {
    "iso:country":"US",
    "sg:address":"603 Center St",
    "sg:city":"Wolfeboro",
    "sg:classifiers":[
        {
            "category":"Home & Garden",
            "subcategory":"Building Materials",
            "type":"Retail Goods"
        }
    ],
    "sg:phone":"+1 603 569 4311",
    "sg:postcode":"03894",
    "sg:province":"NH",
    "sg:tags":[
        "glass",
        "window",
        "plate"
    ],
    "wof:name":"Carroll County Glass",
    "wof:placetype":"venue"
},
  "geometry": {"coordinates":[-71.176517,43.612844],"type":"Point"}
}