{
  "type": "Feature",
  "properties": {
    "addr:full":"12 Winkley Pond Rd Barrington NH 03825",
    "addr:housenumber":"12",
    "addr:postcode":"03825",
    "addr:street":"Winkley Pond Rd",
    "iso:country":"US",
    "sg:address":"12 Winkley Pond Rd",
    "sg:city":"Barrington",
    "sg:classifiers":[
        {
            "category":"Travel",
            "subcategory":"Bed & Breakfast",
            "type":"Entertainment"
        }
    ],
    "sg:phone":"+1 603 664 7346",
    "sg:postcode":"03825",
    "sg:province":"NH",
    "sg:tags":[
        "house"
    ],
    "wof:name":"Noels Inn",
    "wof:placetype":"venue"
},
  "geometry": {"coordinates":[-70.998425,43.190917],"type":"Point"}
}