{
  "type": "Feature",
  "properties": {
    "iso:country":"US",
    "sg:address":"1061 Union Ave",
    "sg:city":"Laconia",
    "sg:classifiers":[
        {
            "category":"Retail",
            "subcategory":"Funeral Services",
            "type":"Services"
        }
    ],
    "sg:phone":"+1 603 524 5742",
    "sg:postcode":"03246",
    "sg:province":"NH",
    "sg:tags":[
        "director"
    ],
    "wof:name":"Dewhirst Funeral Home",
    "wof:placetype":"venue"
},
  "geometry": {"coordinates":[-71.457364,43.553268],"type":"Point"}
}