{
  "type": "Feature",
  "properties": {
    "addr:full":"2064 Woodbury Ave Portsmouth NH 03801",
    "addr:housenumber":"2064",
    "addr:postcode":"03801",
    "addr:street":"Woodbury Ave",
    "iso:country":"US",
    "sg:address":"2064 Woodbury Ave",
    "sg:city":"Portsmouth",
    "sg:classifiers":[
        {
            "category":"Shopping",
            "subcategory":"Crafts & Fabrics",
            "type":"Retail Goods"
        }
    ],
    "sg:phone":"+1 603 436 1936",
    "sg:postcode":"03801",
    "sg:province":"NH",
    "sg:tags":[
        "sewing",
        "supply"
    ],
    "wof:name":"Jo-Ann Fabrics & Crafts",
    "wof:placetype":"venue"
},
  "geometry": {"coordinates":[-70.798517,43.097317],"type":"Point"}
}