{
  "type": "Feature",
  "properties": {
    "addr:full":"56 Prospect St Keene NH 03431",
    "addr:housenumber":"56",
    "addr:postcode":"03431",
    "addr:street":"Prospect St",
    "iso:country":"US",
    "sg:address":"56 Prospect St",
    "sg:city":"Keene",
    "sg:classifiers":[
        {
            "category":"Building & Trades",
            "subcategory":"Electrical",
            "type":"Services"
        }
    ],
    "sg:phone":"+1 603 352 5800",
    "sg:postcode":"03431",
    "sg:province":"NH",
    "sg:tags":[
        "electrical",
        "contractor"
    ],
    "wof:name":"Electric Services By Ken Dicey",
    "wof:placetype":"venue"
},
  "geometry": {"coordinates":[-72.282454,42.94388],"type":"Point"}
}