{
  "type": "Feature",
  "properties": {
    "iso:country":"US",
    "sg:address":"43 King St",
    "sg:city":"Wolfeboro",
    "sg:classifiers":[
        {
            "category":"Retail",
            "subcategory":"Auto Repair",
            "type":"Services"
        }
    ],
    "sg:phone":"+1 603 569 3364",
    "sg:postcode":"03896",
    "sg:province":"NH",
    "sg:tags":[
        "repairing",
        "automobile"
    ],
    "wof:name":"Wagonwerks Bay",
    "wof:placetype":"venue"
},
  "geometry": {"coordinates":[-71.21585899999999,43.589337],"type":"Point"}
}