{
  "type": "Feature",
  "properties": {
    "iso:country":"US",
    "sg:address":"85 Center St",
    "sg:city":"Wolfeboro",
    "sg:classifiers":[
        {
            "category":"Shopping",
            "subcategory":"Used Merchandise",
            "type":"Retail Goods"
        }
    ],
    "sg:phone":"+1 603 569 0000",
    "sg:postcode":"03894",
    "sg:province":"NH",
    "sg:tags":[
        "antique"
    ],
    "wof:name":"Antiquebug",
    "wof:placetype":"venue"
},
  "geometry": {"coordinates":[-71.205724,43.588695],"type":"Point"}
}