{
  "type": "Feature",
  "properties": {
    "iso:country":"US",
    "sg:address":"47 Lawrence Rd",
    "sg:city":"Salem",
    "sg:classifiers":[
        {
            "category":"Autos & Motor Vehicles",
            "subcategory":"Auto Supplies",
            "type":"Retail Goods"
        }
    ],
    "sg:phone":"+1 603 894 7117",
    "sg:postcode":"03079",
    "sg:province":"NH",
    "sg:tags":[
        "equipment",
        "racing",
        "car",
        "automobile"
    ],
    "wof:name":"Tricked Out Motor Sports",
    "wof:placetype":"venue"
},
  "geometry": {"coordinates":[-71.20371,42.784087],"type":"Point"}
}