{
  "type": "Feature",
  "properties": {
    "iso:country":"US",
    "sg:address":"81 S State St",
    "sg:city":"Concord",
    "sg:classifiers":[
        {
            "category":"Professional",
            "subcategory":"Lawyer & Legal Services",
            "type":"Services"
        }
    ],
    "sg:phone":"+1 603 224 2100",
    "sg:postcode":"03301",
    "sg:province":"NH",
    "wof:name":"Raymond J Dilucci PA",
    "wof:placetype":"venue"
},
  "geometry": {"coordinates":[-71.533641,43.197668],"type":"Point"}
}