{
  "type": "Feature",
  "properties": {
    "addr:full":"792 Page St Manchester NH 03109",
    "addr:housenumber":"792",
    "addr:postcode":"03109",
    "addr:street":"Page St",
    "iso:country":"US",
    "sg:address":"792 Page St",
    "sg:city":"Manchester",
    "sg:classifiers":[
        {
            "category":"Freight",
            "type":"Transportation"
        }
    ],
    "sg:phone":"+1 603 231 2837",
    "sg:postcode":"03109",
    "sg:province":"NH",
    "sg:tags":[
        "operator",
        "trucking"
    ],
    "wof:name":"Petico Trucking",
    "wof:placetype":"venue"
},
  "geometry": {"coordinates":[-71.41959,42.983664],"type":"Point"}
}