{
  "type": "Feature",
  "properties": {
    "iso:country":"US",
    "sg:address":"7 Raymond Ave",
    "sg:city":"Salem",
    "sg:classifiers":[
        {
            "category":"Wholesale",
            "subcategory":"Stationery",
            "type":"Manufacturing & Wholesale Goods"
        },
        {
            "category":"Wholesale",
            "subcategory":"Non-durable Goods",
            "type":"Manufacturing & Wholesale Goods"
        }
    ],
    "sg:phone":"+1 603 898 4750",
    "sg:postcode":"03079",
    "sg:province":"NH",
    "sg:tags":[
        "packaging",
        "equipment",
        "material",
        "industrial"
    ],
    "sg:website":"www.hillpackaging.com",
    "wof:name":"Hill Packaging Inc",
    "wof:placetype":"venue"
},
  "geometry": {"coordinates":[-71.23905000000001,42.775537],"type":"Point"}
}