{
  "type": "Feature",
  "properties": {
    "iso:country":"US",
    "sg:address":"28 Weirs Rd",
    "sg:city":"Gilford",
    "sg:classifiers":[
        {
            "category":"Real Estate",
            "subcategory":"Real Estate Agent",
            "type":"Services"
        }
    ],
    "sg:phone":"+1 603 293 8300",
    "sg:postcode":"03249",
    "sg:province":"NH",
    "wof:name":"Assist 2 Sell Buyers & Sellers",
    "wof:placetype":"venue"
},
  "geometry": {"coordinates":[-71.40274599999999,43.57817],"type":"Point"}
}