{
  "type": "Feature",
  "properties": {
    "addr:full":"90 E Hollis St Nashua NH 03060",
    "addr:housenumber":"90",
    "addr:postcode":"03060",
    "addr:street":"E Hollis St",
    "iso:country":"US",
    "sg:address":"90 E Hollis St",
    "sg:city":"Nashua",
    "sg:classifiers":[
        {
            "category":"Wholesale",
            "subcategory":"Construction Materials",
            "type":"Manufacturing & Wholesale Goods"
        }
    ],
    "sg:phone":"+1 603 889 7401",
    "sg:postcode":"03060",
    "sg:province":"NH",
    "sg:tags":[
        "marble"
    ],
    "wof:name":"Primero Inc",
    "wof:placetype":"venue"
},
  "geometry": {"coordinates":[-71.45313899999999,42.7602],"type":"Point"}
}