{
  "type": "Feature",
  "properties": {
    "addr:full":"81 Brickyard Rd Littleton NH 03561",
    "addr:housenumber":"81",
    "addr:postcode":"03561",
    "addr:street":"Brickyard Rd",
    "iso:country":"US",
    "sg:address":"81 Brickyard Rd",
    "sg:city":"Littleton",
    "sg:classifiers":[
        {
            "category":"Professional",
            "subcategory":"Art Services",
            "type":"Services"
        }
    ],
    "sg:phone":"+1 603 444 0324",
    "sg:postcode":"03561",
    "sg:province":"NH",
    "sg:tags":[
        "photographer"
    ],
    "wof:name":"Garnet Hill Photo Studio",
    "wof:placetype":"venue"
},
  "geometry": {"coordinates":[-71.795585,44.316345],"type":"Point"}
}