{
  "type": "Feature",
  "properties": {
    "iso:country":"US",
    "sg:address":"180 South Rd",
    "sg:city":"Canaan",
    "sg:classifiers":[
        {
            "category":"Wholesale",
            "subcategory":"Machinery & Supplies",
            "type":"Manufacturing & Wholesale Goods"
        }
    ],
    "sg:phone":"+1 603 632 7707",
    "sg:postcode":"03741",
    "sg:province":"NH",
    "sg:tags":[
        "machine",
        "industrial",
        "parts"
    ],
    "wof:name":"Precision Products",
    "wof:placetype":"venue"
},
  "geometry": {"coordinates":[-72.087508,43.641839],"type":"Point"}
}