{
  "type": "Feature",
  "properties": {
    "addr:full":"43 North Rd Ste 207 Deerfield NH 03037",
    "addr:housenumber":"43",
    "addr:postcode":"03037",
    "addr:street":"North Rd Ste 207",
    "iso:country":"US",
    "sg:address":"43 North Rd Ste 207",
    "sg:city":"Deerfield",
    "sg:classifiers":[
        {
            "category":"Personal",
            "subcategory":"Nail Salon",
            "type":"Services"
        }
    ],
    "sg:phone":"+1 603 463 7575",
    "sg:postcode":"03037",
    "sg:province":"NH",
    "wof:name":"Fancy Nail Spa",
    "wof:placetype":"venue"
},
  "geometry": {"coordinates":[-71.235135,43.140788],"type":"Point"}
}