{
  "type": "Feature",
  "properties": {
    "iso:country":"US",
    "sg:address":"404 Chestnut St",
    "sg:city":"Manchester",
    "sg:classifiers":[
        {
            "category":"Professional",
            "subcategory":"Management & Consulting",
            "type":"Services"
        }
    ],
    "sg:phone":"+1 603 625 0887",
    "sg:postcode":"03101",
    "sg:province":"NH",
    "sg:tags":[
        "encyclopedia"
    ],
    "wof:name":"Encyclopaedia Britannica Inc",
    "wof:placetype":"venue"
},
  "geometry": {"coordinates":[-71.460717,42.991262],"type":"Point"}
}