{
  "type": "Feature",
  "properties": {
    "iso:country":"US",
    "sg:address":"712 Jarmany Hill Rd",
    "sg:city":"Sharon",
    "sg:classifiers":[
        {
            "category":"Manufacturing",
            "subcategory":"Printing",
            "type":"Manufacturing & Wholesale Goods"
        }
    ],
    "sg:phone":"+1 603 924 8886",
    "sg:postcode":"03458",
    "sg:province":"NH",
    "sg:tags":[
        "publisher"
    ],
    "wof:name":"Laurin Publishing",
    "wof:placetype":"venue"
},
  "geometry": {"coordinates":[-71.95916699999999,42.816214],"type":"Point"}
}