{
  "type": "Feature",
  "properties": {
    "iso:country":"US",
    "sg:address":"125 Silver St",
    "sg:city":"Dover",
    "sg:classifiers":[
        {
            "category":"Recreation",
            "type":"Entertainment"
        }
    ],
    "sg:phone":"+1 603 743 6957",
    "sg:postcode":"03820",
    "sg:province":"NH",
    "wof:name":"Jump & Tumble Tumblebus",
    "wof:placetype":"venue"
},
  "geometry": {"coordinates":[-70.88372200000001,43.19058],"type":"Point"}
}