{
  "type": "Feature",
  "properties": {
    "iso:country":"US",
    "sg:address":"8 Marsh Rd",
    "sg:city":"Union",
    "sg:classifiers":[
        {
            "category":"Building & Trades",
            "subcategory":"Cleaning & Sanitation",
            "type":"Services"
        }
    ],
    "sg:phone":"+1 603 473 8284",
    "sg:postcode":"03887",
    "sg:province":"NH",
    "sg:tags":[
        "maintenance"
    ],
    "wof:name":"Rapid Cleaning Service & Sply",
    "wof:placetype":"venue"
},
  "geometry": {"coordinates":[-71.023567,43.52148],"type":"Point"}
}