{
  "type": "Feature",
  "properties": {
    "iso:country":"US",
    "sg:address":"20 Main St",
    "sg:city":"Hanover",
    "sg:classifiers":[
        {
            "category":"Shopping",
            "subcategory":"Clothing, Apparel, & Fashions",
            "type":"Retail Goods"
        }
    ],
    "sg:phone":"+1 603 643 6733",
    "sg:postcode":"03755",
    "sg:province":"NH",
    "wof:name":"Gap",
    "wof:placetype":"venue"
},
  "geometry": {"coordinates":[-72.28947599999999,43.704117],"type":"Point"}
}