{
  "type": "Feature",
  "properties": {
    "iso:country":"US",
    "sg:address":"2 Pine Rd",
    "sg:city":"Hampton",
    "sg:classifiers":[
        {
            "category":"Real Estate",
            "subcategory":"Real Estate Operator",
            "type":"Services"
        }
    ],
    "sg:phone":"+1 603 929 9254",
    "sg:postcode":"03842",
    "sg:province":"NH",
    "sg:tags":[
        "building",
        "apartment"
    ],
    "wof:name":"Maher Atlantic Properties",
    "wof:placetype":"venue"
},
  "geometry": {"coordinates":[-70.805415,42.939572],"type":"Point"}
}