{
  "type": "Feature",
  "properties": {
    "iso:country":"US",
    "sg:address":"588 Main St",
    "sg:city":"Laconia",
    "sg:classifiers":[
        {
            "category":"Banks & Credit Unions",
            "subcategory":"Investment Brokerage",
            "type":"Services"
        }
    ],
    "sg:phone":"+1 603 524 4533",
    "sg:postcode":"03246",
    "sg:province":"NH",
    "sg:tags":[
        "security"
    ],
    "wof:name":"Edward Jones Co",
    "wof:placetype":"venue"
},
  "geometry": {"coordinates":[-71.469984,43.527733],"type":"Point"}
}