{
  "type": "Feature",
  "properties": {
    "addr:full":"241 Governor John Wentworth Hwy Mirror Lake NH 03853",
    "addr:housenumber":"241",
    "addr:postcode":"03853",
    "addr:street":"Governor John Wentworth Hwy",
    "iso:country":"US",
    "sg:address":"241 Governor John Wentworth Hwy",
    "sg:city":"Mirror Lake",
    "sg:classifiers":[
        {
            "category":"Travel",
            "subcategory":"Travel Agent",
            "type":"Entertainment"
        }
    ],
    "sg:phone":"+1 603 569 2743",
    "sg:postcode":"03853",
    "sg:province":"NH",
    "sg:tags":[
        "agency",
        "bureau"
    ],
    "wof:name":"Eva's Travel",
    "wof:placetype":"venue"
},
  "geometry": {"coordinates":[-71.278346,43.652483],"type":"Point"}
}