{
  "type": "Feature",
  "properties": {
    "addr:full":"49 Granite St Marlborough NH 03455",
    "addr:housenumber":"49",
    "addr:postcode":"03455",
    "addr:street":"Granite St",
    "iso:country":"US",
    "sg:address":"49 Granite St",
    "sg:city":"Marlborough",
    "sg:classifiers":[
        {
            "category":"Manufacturing",
            "subcategory":"Apparel",
            "type":"Manufacturing & Wholesale Goods"
        }
    ],
    "sg:phone":"+1 603 876 3525",
    "sg:postcode":"03455",
    "sg:province":"NH",
    "sg:tags":[
        "sewing",
        "contractor"
    ],
    "wof:name":"TAM Assoc",
    "wof:placetype":"venue"
},
  "geometry": {"coordinates":[-72.207459,42.904089],"type":"Point"}
}