{
  "type": "Feature",
  "properties": {
    "addr:full":"46 Donovan St Concord NH 03301",
    "addr:housenumber":"46",
    "addr:postcode":"03301",
    "addr:street":"Donovan St",
    "iso:country":"US",
    "sg:address":"46 Donovan St",
    "sg:city":"Concord",
    "sg:classifiers":[
        {
            "category":"Insurance",
            "subcategory":"Insurance Agent",
            "type":"Services"
        }
    ],
    "sg:phone":"+1 603 225 2841",
    "sg:postcode":"03301",
    "sg:province":"NH",
    "wof:name":"Primex",
    "wof:placetype":"venue"
},
  "geometry": {"coordinates":[-71.533727,43.179559],"type":"Point"}
}