{
  "type": "Feature",
  "properties": {
    "iso:country":"US",
    "sg:address":"11 Shore Dr",
    "sg:city":"Henniker",
    "sg:classifiers":[
        {
            "category":"Professional",
            "subcategory":"Management & Consulting",
            "type":"Services"
        }
    ],
    "sg:phone":"+1 603 428 3167",
    "sg:postcode":"03242",
    "sg:province":"NH",
    "wof:name":"Panetta Property Management",
    "wof:placetype":"venue"
},
  "geometry": {"coordinates":[-71.810523,43.200179],"type":"Point"}
}