{
  "type": "Feature",
  "properties": {
    "iso:country":"US",
    "sg:address":"1 Exchange St",
    "sg:city":"Gorham",
    "sg:classifiers":[
        {
            "category":"Personal",
            "subcategory":"Tattoo Parlor",
            "type":"Services"
        }
    ],
    "sg:phone":"+1 603 466 2233",
    "sg:postcode":"03581",
    "sg:province":"NH",
    "sg:tags":[
        "tattooing"
    ],
    "wof:name":"Drigger's Tattoo",
    "wof:placetype":"venue"
},
  "geometry": {"coordinates":[-71.176408,44.388921],"type":"Point"}
}