{
  "type": "Feature",
  "properties": {
    "addr:full":"177 Main St Colebrook NH 03576",
    "addr:housenumber":"177",
    "addr:postcode":"03576",
    "addr:street":"Main St",
    "iso:country":"US",
    "sg:address":"177 Main St",
    "sg:city":"Colebrook",
    "sg:classifiers":[
        {
            "category":"Shopping",
            "subcategory":"Clothing, Apparel, & Fashions",
            "type":"Retail Goods"
        }
    ],
    "sg:phone":"+1 603 237 4101",
    "sg:postcode":"03576",
    "sg:province":"NH",
    "wof:name":"Jaime's Boutique",
    "wof:placetype":"venue"
},
  "geometry": {"coordinates":[-71.497299,44.892841],"type":"Point"}
}