{
  "type": "Feature",
  "properties": {
    "iso:country":"US",
    "sg:address":"23 Rockwood Ct",
    "sg:city":"Bedford",
    "sg:classifiers":[
        {
            "category":"Building & Trades",
            "subcategory":"Plumbing",
            "type":"Services"
        }
    ],
    "sg:phone":"+1 603 533 9867",
    "sg:postcode":"03110",
    "sg:province":"NH",
    "sg:tags":[
        "contractor"
    ],
    "wof:name":"Adr Mechanical LLC",
    "wof:placetype":"venue"
},
  "geometry": {"coordinates":[-71.535625,42.940766],"type":"Point"}
}