{
  "type": "Feature",
  "properties": {
    "iso:country":"US",
    "sg:address":"107 W Glenwood St",
    "sg:city":"Nashua",
    "sg:classifiers":[
        {
            "category":"Retail",
            "subcategory":"Repair Shop",
            "type":"Services"
        },
        {
            "category":"Building & Trades",
            "subcategory":"Construction",
            "type":"Services"
        }
    ],
    "sg:phone":"+1 603 897 0951",
    "sg:postcode":"03060",
    "sg:province":"NH",
    "sg:tags":[
        "welding",
        "contractor"
    ],
    "wof:name":"Sam's Metal Crafting",
    "wof:placetype":"venue"
},
  "geometry": {"coordinates":[-71.45066799999999,42.731693],"type":"Point"}
}