{
  "type": "Feature",
  "properties": {
    "addr:full":"37 Park Ave Keene NH 03431",
    "addr:housenumber":"37",
    "addr:postcode":"03431",
    "addr:street":"Park Ave",
    "iso:country":"US",
    "sg:address":"37 Park Ave",
    "sg:city":"Keene",
    "sg:classifiers":[
        {
            "category":"Home & Garden",
            "subcategory":"Hardware",
            "type":"Retail Goods"
        }
    ],
    "sg:phone":"+1 603 352 1517",
    "sg:postcode":"03431",
    "sg:province":"NH",
    "sg:tags":[
        "store"
    ],
    "wof:name":"True Value",
    "wof:placetype":"venue"
},
  "geometry": {"coordinates":[-72.302943,42.936612],"type":"Point"}
}