{
  "type": "Feature",
  "properties": {
    "iso:country":"US",
    "sg:address":"143 Campbell Rd",
    "sg:city":"Bedford",
    "sg:classifiers":[
        {
            "category":"Building & Trades",
            "subcategory":"Construction",
            "type":"Services"
        }
    ],
    "sg:phone":"+1 603 472 2636",
    "sg:postcode":"03110",
    "sg:province":"NH",
    "sg:tags":[
        "general",
        "contractor"
    ],
    "wof:name":"Oaktree Building Service LLC",
    "wof:placetype":"venue"
},
  "geometry": {"coordinates":[-71.561487,42.946222],"type":"Point"}
}