{
  "type": "Feature",
  "properties": {
    "addr:full":"456 Daniel Webster Hwy Merrimack NH 03054",
    "addr:housenumber":"456",
    "addr:postcode":"03054",
    "addr:street":"Daniel Webster Hwy",
    "iso:country":"US",
    "sg:address":"456 Daniel Webster Hwy",
    "sg:city":"Merrimack",
    "sg:classifiers":[
        {
            "category":"Health Services",
            "subcategory":"Doctor",
            "type":"Services"
        },
        {
            "category":"Health Services",
            "subcategory":"Clinic",
            "type":"Services"
        }
    ],
    "sg:phone":"+1 603 424 8120",
    "sg:postcode":"03054",
    "sg:province":"NH",
    "sg:tags":[
        "physician",
        "family",
        "practice",
        "surgeons",
        "medicine",
        "surgeon"
    ],
    "wof:name":"Merrimack Vlg Fmly Practice",
    "wof:placetype":"venue"
},
  "geometry": {"coordinates":[-71.493465,42.864765],"type":"Point"}
}