{
  "type": "Feature",
  "properties": {
    "addr:full":"12 High St Lancaster NH 03584",
    "addr:housenumber":"12",
    "addr:postcode":"03584",
    "addr:street":"High St",
    "iso:country":"US",
    "sg:address":"12 High St",
    "sg:city":"Lancaster",
    "sg:classifiers":[
        {
            "category":"Building & Trades",
            "subcategory":"Plumbing",
            "type":"Services"
        }
    ],
    "sg:phone":"+1 603 788 4376",
    "sg:postcode":"03584",
    "sg:province":"NH",
    "sg:tags":[
        "contractor"
    ],
    "wof:name":"Plumbing More",
    "wof:placetype":"venue"
},
  "geometry": {"coordinates":[-71.56846,44.490899],"type":"Point"}
}