{
  "type": "Feature",
  "properties": {
    "addr:full":"2 Northwestern Dr Salem NH 03079",
    "addr:housenumber":"2",
    "addr:postcode":"03079",
    "addr:street":"Northwestern Dr",
    "iso:country":"US",
    "sg:address":"2 Northwestern Dr",
    "sg:city":"Salem",
    "sg:classifiers":[
        {
            "category":"Building & Trades",
            "subcategory":"Construction",
            "type":"Services"
        }
    ],
    "sg:phone":"+1 603 898 1268",
    "sg:postcode":"03079",
    "sg:province":"NH",
    "sg:tags":[
        "repair",
        "sheet",
        "mfg",
        "contractor",
        "meta",
        "welding"
    ],
    "wof:name":"Ken-Mar Inc",
    "wof:placetype":"venue"
},
  "geometry": {"coordinates":[-71.258619,42.775011],"type":"Point"}
}