{
  "type": "Feature",
  "properties": {
    "iso:country":"US",
    "sg:address":"270 Exeter Rd",
    "sg:city":"Epping",
    "sg:classifiers":[
        {
            "category":"Wholesale",
            "subcategory":"Scrap",
            "type":"Manufacturing & Wholesale Goods"
        }
    ],
    "sg:phone":"+1 603 679 2626",
    "sg:postcode":"03042",
    "sg:province":"NH",
    "sg:tags":[
        "recycling",
        "center"
    ],
    "sg:website":"www.errco.com",
    "wof:name":"ERRCO Construction Recycle",
    "wof:placetype":"venue"
},
  "geometry": {"coordinates":[-71.033689,43.020781],"type":"Point"}
}