{
  "type": "Feature",
  "properties": {
    "addr:full":"1022 Dover Rd Epsom NH 03234",
    "addr:housenumber":"1022",
    "addr:postcode":"03234",
    "addr:street":"Dover Rd",
    "iso:country":"US",
    "sg:address":"1022 Dover Rd",
    "sg:city":"Epsom",
    "sg:classifiers":[
        {
            "category":"Shopping",
            "subcategory":"Stationery & Office Supplies",
            "type":"Retail Goods"
        }
    ],
    "sg:phone":"+1 603 736 5550",
    "sg:postcode":"03234",
    "sg:province":"NH",
    "sg:tags":[
        "educational",
        "material"
    ],
    "wof:name":"Teaching Trends",
    "wof:placetype":"venue"
},
  "geometry": {"coordinates":[-71.362526,43.228498],"type":"Point"}
}