{
  "type": "Feature",
  "properties": {
    "iso:country":"US",
    "sg:address":"174 Loudon Rd",
    "sg:city":"Concord",
    "sg:classifiers":[
        {
            "category":"Retail",
            "subcategory":"Auto Repair",
            "type":"Services"
        }
    ],
    "sg:phone":"+1 603 228 4824",
    "sg:postcode":"03301",
    "sg:province":"NH",
    "sg:tags":[
        "automotive"
    ],
    "wof:name":"Alstart Inc",
    "wof:placetype":"venue"
},
  "geometry": {"coordinates":[-71.502501,43.218146],"type":"Point"}
}