{
  "type": "Feature",
  "properties": {
    "addr:full":"28 Thompson Rd Hanover NH 03755",
    "addr:housenumber":"28",
    "addr:postcode":"03755",
    "addr:street":"Thompson Rd",
    "iso:country":"US",
    "sg:address":"28 Thompson Rd",
    "sg:city":"Hanover",
    "sg:classifiers":[
        {
            "category":"Organizations",
            "subcategory":"Labor Organization",
            "type":"Services"
        }
    ],
    "sg:phone":"+1 603 643 6430",
    "sg:postcode":"03755",
    "sg:province":"NH",
    "wof:name":"Carpenters Analytical",
    "wof:placetype":"venue"
},
  "geometry": {"coordinates":[-72.165689,43.751933],"type":"Point"}
}