{
  "type": "Feature",
  "properties": {
    "iso:country":"US",
    "sg:address":"89 Main St",
    "sg:city":"Plaistow",
    "sg:classifiers":[
        {
            "category":"Real Estate",
            "subcategory":"Real Estate Agent",
            "type":"Services"
        }
    ],
    "sg:phone":"+1 603 382 8089",
    "sg:postcode":"03865",
    "sg:province":"NH",
    "wof:name":"Staple Realty LLC",
    "wof:placetype":"venue"
},
  "geometry": {"coordinates":[-71.09307099999999,42.828528],"type":"Point"}
}