{
  "type": "Feature",
  "properties": {
    "addr:full":"46 School St Lisbon NH 03585",
    "addr:housenumber":"46",
    "addr:postcode":"03585",
    "addr:street":"School St",
    "iso:country":"US",
    "sg:address":"46 School St",
    "sg:city":"Lisbon",
    "sg:classifiers":[
        {
            "category":"Government",
            "subcategory":"Office",
            "type":"Public Place"
        }
    ],
    "sg:phone":"+1 603 838 2862",
    "sg:postcode":"03585",
    "sg:province":"NH",
    "sg:tags":[
        "city"
    ],
    "wof:name":"Town Clerk",
    "wof:placetype":"venue"
},
  "geometry": {"coordinates":[-71.911356,44.214642],"type":"Point"}
}