{
  "type": "Feature",
  "properties": {
    "iso:country":"US",
    "sg:address":"98 Ridge Road Top",
    "sg:city":"New Durham",
    "sg:classifiers":[
        {
            "category":"Professional",
            "subcategory":"Employment Agencies",
            "type":"Services"
        }
    ],
    "sg:phone":"+1 603 859 2200",
    "sg:postcode":"03855",
    "sg:province":"NH",
    "sg:tags":[
        "installation",
        "sales"
    ],
    "wof:name":"Green Mountain Mfg",
    "wof:placetype":"venue"
},
  "geometry": {"coordinates":[-71.151595,43.399193],"type":"Point"}
}