{
  "type": "Feature",
  "properties": {
    "addr:full":"197 W Main St Conway NH 03818",
    "addr:housenumber":"197",
    "addr:postcode":"03818",
    "addr:street":"W Main St",
    "iso:country":"US",
    "sg:address":"197 W Main St",
    "sg:city":"Conway",
    "sg:classifiers":[
        {
            "category":"Food & Beverages",
            "subcategory":"Meat & Fish",
            "type":"Retail Goods"
        }
    ],
    "sg:phone":"+1 603 447 6756",
    "sg:postcode":"03818",
    "sg:province":"NH",
    "sg:tags":[
        "lobster"
    ],
    "wof:name":"Northland Lobster Co",
    "wof:placetype":"venue"
},
  "geometry": {"coordinates":[-71.13124999999999,43.975829],"type":"Point"}
}