{
  "type": "Feature",
  "properties": {
    "addr:full":"738 Eastman Rd Center Conway NH 03813",
    "addr:housenumber":"738",
    "addr:postcode":"03813",
    "addr:street":"Eastman Rd",
    "iso:country":"US",
    "sg:address":"738 Eastman Rd",
    "sg:city":"Center Conway",
    "sg:classifiers":[
        {
            "category":"Professional",
            "type":"Services"
        }
    ],
    "sg:phone":"+1 603 356 6669",
    "sg:postcode":"03813",
    "sg:province":"NH",
    "sg:tags":[
        "establishment"
    ],
    "wof:name":"Spaceman Enterprises",
    "wof:placetype":"venue"
},
  "geometry": {"coordinates":[-71.08895,44.005369],"type":"Point"}
}