{
  "type": "Feature",
  "properties": {
    "addr:full":"30 Leighton Ave N Laconia NH 03246",
    "addr:housenumber":"30",
    "addr:postcode":"03246",
    "addr:street":"Leighton Ave N",
    "iso:country":"US",
    "sg:address":"30 Leighton Ave N",
    "sg:city":"Laconia",
    "sg:classifiers":[
        {
            "category":"Manufacturing",
            "subcategory":"Glass & Minerals",
            "type":"Manufacturing & Wholesale Goods"
        }
    ],
    "sg:phone":"+1 603 527 0466",
    "sg:postcode":"03246",
    "sg:province":"NH",
    "wof:name":"ASGS",
    "wof:placetype":"venue"
},
  "geometry": {"coordinates":[-71.529533,43.584374],"type":"Point"}
}