{
  "type": "Feature",
  "properties": {
    "iso:country":"US",
    "sg:address":"27A Roulston Rd",
    "sg:city":"Windham",
    "sg:classifiers":[
        {
            "category":"Wholesale",
            "subcategory":"Machinery & Supplies",
            "type":"Manufacturing & Wholesale Goods"
        }
    ],
    "sg:phone":"+1 603 894 6100",
    "sg:postcode":"03087",
    "sg:province":"NH",
    "sg:tags":[
        "designed",
        "specially"
    ],
    "sg:website":"http://www.cettechnology.com",
    "wof:name":"Cet Technology",
    "wof:placetype":"venue"
},
  "geometry": {"coordinates":[-71.254471,42.815708],"type":"Point"}
}