{
  "type": "Feature",
  "properties": {
    "addr:full":"240 Hanover Center Rd Etna NH 03750",
    "addr:housenumber":"240",
    "addr:postcode":"03750",
    "addr:street":"Hanover Center Rd",
    "iso:country":"US",
    "sg:address":"240 Hanover Center Rd",
    "sg:city":"Etna",
    "sg:classifiers":[
        {
            "category":"Manufacturing",
            "subcategory":"Tools & Machinery",
            "type":"Manufacturing & Wholesale Goods"
        }
    ],
    "sg:phone":"+1 603 643 0199",
    "sg:postcode":"03750",
    "sg:province":"NH",
    "sg:tags":[
        "control",
        "mfg"
    ],
    "wof:name":"Summing Junction Pllc",
    "wof:placetype":"venue"
},
  "geometry": {"coordinates":[-72.210911,43.705946],"type":"Point"}
}