{
  "type": "Feature",
  "properties": {
    "addr:full":"1 Independence Dr Dover NH 03820",
    "addr:housenumber":"1",
    "addr:postcode":"03820",
    "addr:street":"Independence Dr",
    "iso:country":"US",
    "sg:address":"1 Independence Dr",
    "sg:city":"Dover",
    "sg:classifiers":[
        {
            "category":"Manufacturing",
            "subcategory":"Tools & Machinery",
            "type":"Manufacturing & Wholesale Goods"
        }
    ],
    "sg:phone":"+1 603 750 7525",
    "sg:postcode":"03820",
    "sg:province":"NH",
    "sg:tags":[
        "pattern",
        "industrial",
        "mfg"
    ],
    "wof:name":"Berry Pattern",
    "wof:placetype":"venue"
},
  "geometry": {"coordinates":[-70.852435,43.172669],"type":"Point"}
}