{
  "type": "Feature",
  "properties": {
    "iso:country":"US",
    "sg:address":"3 Ridgecrest Dr",
    "sg:city":"Hudson",
    "sg:classifiers":[
        {
            "category":"Building & Trades",
            "subcategory":"Construction",
            "type":"Services"
        }
    ],
    "sg:phone":"+1 603 883 1958",
    "sg:postcode":"03051",
    "sg:province":"NH",
    "sg:tags":[
        "company"
    ],
    "wof:name":"Peter Mc Carthy Construction",
    "wof:placetype":"venue"
},
  "geometry": {"coordinates":[-71.41507300000001,42.727426],"type":"Point"}
}