{
  "type": "Feature",
  "properties": {
    "iso:country":"US",
    "sg:address":"642 Marlboro St",
    "sg:city":"Keene",
    "sg:classifiers":[
        {
            "category":"Building & Trades",
            "subcategory":"Construction",
            "type":"Services"
        }
    ],
    "sg:phone":"+1 603 352 1960",
    "sg:postcode":"03431",
    "sg:province":"NH",
    "sg:tags":[
        "hanging",
        "contractor"
    ],
    "wof:name":"Stebbins Spectacular Painting",
    "wof:placetype":"venue"
},
  "geometry": {"coordinates":[-72.25386399999999,42.914835],"type":"Point"}
}