{
  "type": "Feature",
  "properties": {
    "iso:country":"US",
    "sg:address":"2 Winter St",
    "sg:city":"Claremont",
    "sg:classifiers":[
        {
            "category":"Organizations",
            "subcategory":"Religious Organization",
            "type":"Services"
        }
    ],
    "sg:phone":"+1 603 543 1452",
    "sg:postcode":"03743",
    "sg:province":"NH",
    "wof:name":"LDS Missionaries",
    "wof:placetype":"venue"
},
  "geometry": {"coordinates":[-72.333201,43.376892],"type":"Point"}
}