{
  "type": "Feature",
  "properties": {
    "addr:full":"5 Johnson Rd Bow NH 03304",
    "addr:housenumber":"5",
    "addr:postcode":"03304",
    "addr:street":"Johnson Rd",
    "iso:country":"US",
    "sg:address":"5 Johnson Rd",
    "sg:city":"Bow",
    "sg:classifiers":[
        {
            "category":"Manufacturing",
            "subcategory":"Metals",
            "type":"Manufacturing & Wholesale Goods"
        }
    ],
    "sg:phone":"+1 603 429 8448",
    "sg:postcode":"03304",
    "sg:province":"NH",
    "sg:tags":[
        "steel"
    ],
    "sg:website":"www.powerfab.com",
    "wof:name":"Powerfab",
    "wof:placetype":"venue"
},
  "geometry": {"coordinates":[-71.46967600000001,43.125143],"type":"Point"}
}