{
  "type": "Feature",
  "properties": {
    "iso:country":"US",
    "sg:address":"125 Stage Rd",
    "sg:city":"W Chesterfield",
    "sg:classifiers":[
        {
            "category":"Building & Trades",
            "subcategory":"Construction",
            "type":"Services"
        }
    ],
    "sg:phone":"+1 603 256 8900",
    "sg:postcode":"03466",
    "sg:province":"NH",
    "sg:tags":[
        "painter"
    ],
    "wof:name":"Bogar Painting",
    "wof:placetype":"venue"
},
  "geometry": {"coordinates":[-72.491671,42.882096],"type":"Point"}
}