{
  "type": "Feature",
  "properties": {
    "iso:country":"US",
    "sg:address":"616 Portland St",
    "sg:city":"Rochester",
    "sg:classifiers":[
        {
            "category":"Real Estate",
            "subcategory":"Real Estate Operator",
            "type":"Services"
        }
    ],
    "sg:phone":"+1 603 332 7287",
    "sg:postcode":"03867",
    "sg:province":"NH",
    "sg:tags":[
        "building",
        "apartment"
    ],
    "wof:name":"Woodlands Apartments",
    "wof:placetype":"venue"
},
  "geometry": {"coordinates":[-70.95082499999999,43.3195],"type":"Point"}
}