{
  "type": "Feature",
  "properties": {
    "addr:full":"8 Cooper St Loudon NH 03307",
    "addr:housenumber":"8",
    "addr:postcode":"03307",
    "addr:street":"Cooper St",
    "iso:country":"US",
    "sg:address":"8 Cooper St",
    "sg:city":"Loudon",
    "sg:classifiers":[
        {
            "category":"Government",
            "subcategory":"Police Station",
            "type":"Public Place"
        }
    ],
    "sg:phone":"+1 603 798 5585",
    "sg:postcode":"03307",
    "sg:province":"NH",
    "sg:tags":[
        "department"
    ],
    "sg:website":"www.loudonpolice.com",
    "wof:name":"Loudon Police Assn",
    "wof:placetype":"venue"
},
  "geometry": {"coordinates":[-71.466075,43.286566],"type":"Point"}
}