{
  "type": "Feature",
  "properties": {
    "addr:full":"76 Bridge St Pelham NH 03076",
    "addr:housenumber":"76",
    "addr:postcode":"03076",
    "addr:street":"Bridge St",
    "iso:country":"US",
    "sg:address":"76 Bridge St",
    "sg:city":"Pelham",
    "sg:classifiers":[
        {
            "category":"Manufacturing",
            "subcategory":"Paper Products",
            "type":"Manufacturing & Wholesale Goods"
        }
    ],
    "sg:phone":"+1 603 635 2400",
    "sg:postcode":"03076",
    "sg:province":"NH",
    "sg:tags":[
        "bamboo"
    ],
    "wof:name":"Acre's Edge Earth Products, Inc.",
    "wof:placetype":"venue"
},
  "geometry": {"coordinates":[-71.31800800000001,42.713001],"type":"Point"}
}