{
  "type": "Feature",
  "properties": {
    "addr:full":"170 Knox Mountain Rd Sanbornton NH 03269",
    "addr:housenumber":"170",
    "addr:postcode":"03269",
    "addr:street":"Knox Mountain Rd",
    "iso:country":"US",
    "sg:address":"170 Knox Mountain Rd",
    "sg:city":"Sanbornton",
    "sg:classifiers":[
        {
            "category":"Manufacturing",
            "subcategory":"Textiles",
            "type":"Manufacturing & Wholesale Goods"
        }
    ],
    "sg:phone":"+1 603 934 5228",
    "sg:postcode":"03269",
    "sg:province":"NH",
    "sg:tags":[
        "mill",
        "knit",
        "outerwear"
    ],
    "wof:name":"Another Mother Mouse",
    "wof:placetype":"venue"
},
  "geometry": {"coordinates":[-71.675145,43.526897],"type":"Point"}
}