{
  "type": "Feature",
  "properties": {
    "iso:country":"US",
    "sg:address":"9 Matthew Dr",
    "sg:city":"Merrimack",
    "sg:classifiers":[
        {
            "category":"Wholesale",
            "subcategory":"Medical Equipment & Supplies",
            "type":"Manufacturing & Wholesale Goods"
        }
    ],
    "sg:phone":"+1 603 424 1368",
    "sg:postcode":"03054",
    "sg:province":"NH",
    "sg:tags":[
        "therapy",
        "physical"
    ],
    "wof:name":"Patriot Therapy Equipment",
    "wof:placetype":"venue"
},
  "geometry": {"coordinates":[-71.482544,42.893111],"type":"Point"}
}