{
  "type": "Feature",
  "properties": {
    "iso:country":"US",
    "sg:address":"455 Pine St",
    "sg:city":"Manchester",
    "sg:classifiers":[
        {
            "category":"Travel",
            "subcategory":"Bed & Breakfast",
            "type":"Entertainment"
        }
    ],
    "sg:phone":"+1 603 668 8709",
    "sg:postcode":"03104",
    "sg:province":"NH",
    "sg:tags":[
        "house"
    ],
    "wof:name":"Duparin Enterprises",
    "wof:placetype":"venue"
},
  "geometry": {"coordinates":[-71.45932000000001,42.994158],"type":"Point"}
}