{
  "type": "Feature",
  "properties": {
    "iso:country":"US",
    "sg:address":"141 State Rte 101A",
    "sg:city":"Amherst",
    "sg:classifiers":[
        {
            "category":"Home & Garden",
            "subcategory":"Carpets & Floor Coverings",
            "type":"Retail Goods"
        }
    ],
    "sg:phone":"+1 603 883 9677",
    "sg:postcode":"03031",
    "sg:province":"NH",
    "sg:tags":[
        "dealer",
        "rug"
    ],
    "wof:name":"Mahfuz & Sons Rug Gallery",
    "wof:placetype":"venue"
},
  "geometry": {"coordinates":[-71.56344199999999,42.805055],"type":"Point"}
}