{
  "type": "Feature",
  "properties": {
    "addr:full":"22 Craig Dr Merrimack NH 03054",
    "addr:housenumber":"22",
    "addr:postcode":"03054",
    "addr:street":"Craig Dr",
    "iso:country":"US",
    "sg:address":"22 Craig Dr",
    "sg:city":"Merrimack",
    "sg:classifiers":[
        {
            "category":"Building & Trades",
            "subcategory":"Construction",
            "type":"Services"
        }
    ],
    "sg:phone":"+1 603 429 0926",
    "sg:postcode":"03054",
    "sg:province":"NH",
    "sg:tags":[
        "installation",
        "cabinet"
    ],
    "wof:name":"Steven Mayo Corporation",
    "wof:placetype":"venue"
},
  "geometry": {"coordinates":[-71.516564,42.852806],"type":"Point"}
}