{
  "type": "Feature",
  "properties": {
    "iso:country":"US",
    "sg:address":"21 Country Club Rd",
    "sg:city":"Franklin",
    "sg:classifiers":[
        {
            "category":"Education",
            "subcategory":"School",
            "type":"Public Place"
        }
    ],
    "sg:phone":"+1 603 934 0216",
    "sg:postcode":"03249",
    "sg:province":"NH",
    "sg:tags":[
        "charter"
    ],
    "wof:name":"Franklin Career Academy",
    "wof:placetype":"venue"
},
  "geometry": {"coordinates":[-71.440541,43.528976],"type":"Point"}
}