{
  "type": "Feature",
  "properties": {
    "iso:country":"US",
    "sg:address":"11 Surry Coach Ln",
    "sg:city":"Bow",
    "sg:classifiers":[
        {
            "category":"Wholesale",
            "subcategory":"Durable Goods & Equipment",
            "type":"Manufacturing & Wholesale Goods"
        }
    ],
    "sg:phone":"+1 603 223 9696",
    "sg:postcode":"03304",
    "sg:province":"NH",
    "sg:tags":[
        "toy",
        "novelty",
        "sundries"
    ],
    "wof:name":"Mr Checkout Ltd",
    "wof:placetype":"venue"
},
  "geometry": {"coordinates":[-71.561347,43.153496],"type":"Point"}
}