{
  "type": "Feature",
  "properties": {
    "iso:country":"US",
    "sg:address":"80 Livingston Lodge Rd",
    "sg:city":"Enfield",
    "sg:classifiers":[
        {
            "category":"Shopping",
            "type":"Retail Goods"
        }
    ],
    "sg:phone":"+1 603 526 4904",
    "sg:postcode":"03748",
    "sg:province":"NH",
    "sg:tags":[
        "art",
        "gallery",
        "dealer"
    ],
    "wof:name":"Livingstone Lodge",
    "wof:placetype":"venue"
},
  "geometry": {"coordinates":[-72.139735,43.63454],"type":"Point"}
}