{
  "type": "Feature",
  "properties": {
    "iso:country":"US",
    "sg:address":"172 Pembroke Rd",
    "sg:city":"Concord",
    "sg:classifiers":[
        {
            "category":"Manufacturing",
            "subcategory":"Tools & Machinery",
            "type":"Manufacturing & Wholesale Goods"
        }
    ],
    "sg:phone":"+1 603 228 5222",
    "sg:postcode":"03301",
    "sg:province":"NH",
    "sg:tags":[
        "x",
        "industry",
        "apparatus",
        "mfg"
    ],
    "sg:website":"www.wmi.com",
    "wof:name":"White Mountain Imaging Inc",
    "wof:placetype":"venue"
},
  "geometry": {"coordinates":[-71.490115,43.214734],"type":"Point"}
}