{
  "type": "Feature",
  "properties": {
    "addr:full":"13 Meadowbrook Ln Litchfield NH 03052",
    "addr:housenumber":"13",
    "addr:postcode":"03052",
    "addr:street":"Meadowbrook Ln",
    "iso:country":"US",
    "sg:address":"13 Meadowbrook Ln",
    "sg:city":"Litchfield",
    "sg:classifiers":[
        {
            "category":"Recreation",
            "type":"Entertainment"
        }
    ],
    "sg:phone":"+1 603 429 1823",
    "sg:postcode":"03052",
    "sg:province":"NH",
    "wof:name":"Kumiuchi Ryu of New Hmpsh",
    "wof:placetype":"venue"
},
  "geometry": {"coordinates":[-71.45579499999999,42.852477],"type":"Point"}
}