{
  "type": "Feature",
  "properties": {
    "addr:full":"4 Academy Rd New Ipswich NH 03071",
    "addr:housenumber":"4",
    "addr:postcode":"03071",
    "addr:street":"Academy Rd",
    "iso:country":"US",
    "sg:address":"4 Academy Rd",
    "sg:city":"New Ipswich",
    "sg:classifiers":[
        {
            "category":"Health Services",
            "subcategory":"Health Practitioner",
            "type":"Services"
        }
    ],
    "sg:phone":"+1 603 878 2900",
    "sg:postcode":"03071",
    "sg:province":"NH",
    "sg:tags":[
        "midwife"
    ],
    "wof:name":"Birth Cottage",
    "wof:placetype":"venue"
},
  "geometry": {"coordinates":[-71.85705299999999,42.757863],"type":"Point"}
}