{
  "type": "Feature",
  "properties": {
    "addr:full":"78 Main St Gorham NH 03581",
    "addr:housenumber":"78",
    "addr:postcode":"03581",
    "addr:street":"Main St",
    "iso:country":"US",
    "sg:address":"78 Main St",
    "sg:city":"Gorham",
    "sg:classifiers":[
        {
            "category":"Food & Beverages",
            "subcategory":"Groceries & Convenience Stores",
            "type":"Retail Goods"
        }
    ],
    "sg:phone":"+1 603 466 5003",
    "sg:postcode":"03581",
    "sg:province":"NH",
    "wof:name":"Gorham Deli Mart",
    "wof:placetype":"venue"
},
  "geometry": {"coordinates":[-71.175329,44.38869],"type":"Point"}
}