{
  "type": "Feature",
  "properties": {
    "addr:full":"2 Keller St Manchester NH 03103",
    "addr:postcode":"03103",
    "addr:street":"St",
    "iso:country":"US",
    "sg:address":"2 Keller St",
    "sg:city":"Manchester",
    "sg:classifiers":[
        {
            "category":"Shopping",
            "subcategory":"Hobbies, Toys, & Games",
            "type":"Retail Goods"
        }
    ],
    "sg:phone":"+1 603 623 8077",
    "sg:postcode":"03103",
    "sg:province":"NH",
    "wof:name":"Toys R Us",
    "wof:placetype":"venue"
},
  "geometry": {"coordinates":[-71.44111599999999,42.954392],"type":"Point"}
}