{
  "type": "Feature",
  "properties": {
    "iso:country":"US",
    "sg:address":"311 Highlander Way",
    "sg:city":"Manchester",
    "sg:classifiers":[
        {
            "category":"Health Services",
            "subcategory":"Doctor",
            "type":"Services"
        }
    ],
    "sg:phone":"+1 603 626 0966",
    "sg:postcode":"03103",
    "sg:province":"NH",
    "sg:tags":[
        "medical"
    ],
    "wof:name":"Mart Eric MD",
    "wof:placetype":"venue"
},
  "geometry": {"coordinates":[-71.449512,42.925408],"type":"Point"}
}