{
  "type": "Feature",
  "properties": {
    "addr:full":"100 Lawrence Rd Derry NH 03038",
    "addr:housenumber":"100",
    "addr:postcode":"03038",
    "addr:street":"Lawrence Rd",
    "iso:country":"US",
    "sg:address":"100 Lawrence Rd",
    "sg:city":"Derry",
    "sg:classifiers":[
        {
            "category":"Real Estate",
            "subcategory":"Real Estate Agent",
            "type":"Services"
        }
    ],
    "sg:phone":"+1 603 432 2963",
    "sg:postcode":"03038",
    "sg:province":"NH",
    "sg:tags":[
        "operator"
    ],
    "wof:name":"William and Barbara Blunt",
    "wof:placetype":"venue"
},
  "geometry": {"coordinates":[-71.27916500000001,42.873936],"type":"Point"}
}