{
  "type": "Feature",
  "properties": {
    "iso:country":"US",
    "sg:address":"21 Lebanon St",
    "sg:city":"West Lebanon",
    "sg:classifiers":[
        {
            "category":"Recreation",
            "type":"Entertainment"
        }
    ],
    "sg:phone":"+1 603 298 7877",
    "sg:postcode":"03755",
    "sg:province":"NH",
    "sg:tags":[
        "installs",
        "lift",
        "ski"
    ],
    "wof:name":"Leitner-Poma America Inc",
    "wof:placetype":"venue"
},
  "geometry": {"coordinates":[-72.285872,43.700946],"type":"Point"}
}