{
  "type": "Feature",
  "properties": {
    "iso:country":"US",
    "sg:address":"19 Perkins Landing Rd",
    "sg:city":"Littleton",
    "sg:classifiers":[
        {
            "category":"Building & Trades",
            "subcategory":"Construction",
            "type":"Services"
        }
    ],
    "sg:phone":"+1 603 444 2693",
    "sg:postcode":"03561",
    "sg:province":"NH",
    "sg:tags":[
        "contractor"
    ],
    "wof:name":"Bacon Contracting & Building",
    "wof:placetype":"venue"
},
  "geometry": {"coordinates":[-71.804311,44.36696],"type":"Point"}
}