{
  "type": "Feature",
  "properties": {
    "iso:country":"US",
    "sg:address":"1130 E Conway Rd",
    "sg:city":"North Conway",
    "sg:classifiers":[
        {
            "category":"Shopping",
            "subcategory":"Crafts & Fabrics",
            "type":"Retail Goods"
        }
    ],
    "sg:phone":"+1 603 356 5500",
    "sg:postcode":"03813",
    "sg:province":"NH",
    "sg:tags":[
        "shop"
    ],
    "wof:name":"Fabric Stash",
    "wof:placetype":"venue"
},
  "geometry": {"coordinates":[-71.05949699999999,44.011307],"type":"Point"}
}