{
  "type": "Feature",
  "properties": {
    "addr:full":"24 Tremont St Claremont NH 03743",
    "addr:housenumber":"24",
    "addr:postcode":"03743",
    "addr:street":"Tremont St",
    "iso:country":"US",
    "sg:address":"24 Tremont St",
    "sg:city":"Claremont",
    "sg:classifiers":[
        {
            "category":"Professional",
            "subcategory":"Lawyer & Legal Services",
            "type":"Services"
        }
    ],
    "sg:phone":"+1 603 542 8795",
    "sg:postcode":"03743",
    "sg:province":"NH",
    "wof:name":"New Hampshire Legal Aid",
    "wof:placetype":"venue"
},
  "geometry": {"coordinates":[-72.33770199999999,43.372944],"type":"Point"}
}