{
  "type": "Feature",
  "properties": {
    "iso:country":"US",
    "sg:address":"12 Fillmore Rd",
    "sg:city":"Portsmouth",
    "sg:classifiers":[
        {
            "category":"Professional",
            "subcategory":"Management & Consulting",
            "type":"Services"
        }
    ],
    "sg:phone":"+1 603 433 8900",
    "sg:postcode":"03801",
    "sg:province":"NH",
    "sg:tags":[
        "business"
    ],
    "wof:name":"Rozek Business Consultants",
    "wof:placetype":"venue"
},
  "geometry": {"coordinates":[-70.766087,43.038782],"type":"Point"}
}