{
  "type": "Feature",
  "properties": {
    "addr:full":"101 Giles Rd East Kingston NH 03827",
    "addr:housenumber":"101",
    "addr:postcode":"03827",
    "addr:street":"Giles Rd",
    "iso:country":"US",
    "sg:address":"101 Giles Rd",
    "sg:city":"East Kingston",
    "sg:classifiers":[
        {
            "category":"Professional",
            "subcategory":"Advertising",
            "type":"Services"
        }
    ],
    "sg:phone":"+1 603 772 0800",
    "sg:postcode":"03827",
    "sg:province":"NH",
    "sg:tags":[
        "counselor"
    ],
    "wof:name":"Tyrrell Creative Svc",
    "wof:placetype":"venue"
},
  "geometry": {"coordinates":[-70.99628300000001,42.950596],"type":"Point"}
}