{
  "type": "Feature",
  "properties": {
    "iso:country":"US",
    "sg:address":"6 Hazen Dr",
    "sg:city":"Concord",
    "sg:classifiers":[
        {
            "category":"Professional",
            "subcategory":"Research",
            "type":"Services"
        }
    ],
    "sg:phone":"+1 603 271 5173",
    "sg:postcode":"03301",
    "sg:province":"NH",
    "sg:tags":[
        "organization",
        "noncommercial"
    ],
    "wof:name":"Diabetes Education",
    "wof:placetype":"venue"
},
  "geometry": {"coordinates":[-71.517297,43.213083],"type":"Point"}
}