{
  "type": "Feature",
  "properties": {
    "iso:country":"US",
    "sg:address":"11 Welch Ln",
    "sg:city":"Goffstown",
    "sg:classifiers":[
        {
            "category":"Farming",
            "subcategory":"Farm",
            "type":"Manufacturing & Wholesale Goods"
        }
    ],
    "sg:phone":"+1 603 497 2004",
    "sg:postcode":"03045",
    "sg:province":"NH",
    "wof:name":"Welch Farms",
    "wof:placetype":"venue"
},
  "geometry": {"coordinates":[-71.562686,42.987334],"type":"Point"}
}