{
  "type": "Feature",
  "properties": {
    "addr:full":"24 Main St Peterborough NH 03458",
    "addr:housenumber":"24",
    "addr:postcode":"03458",
    "addr:street":"Main St",
    "iso:country":"US",
    "sg:address":"24 Main St",
    "sg:city":"Peterborough",
    "sg:classifiers":[
        {
            "category":"Organizations",
            "subcategory":"Professional Association",
            "type":"Services"
        }
    ],
    "sg:phone":"+1 603 924 9449",
    "sg:postcode":"03458",
    "sg:province":"NH",
    "sg:website":"www.awane.com",
    "wof:name":"Awane",
    "wof:placetype":"venue"
},
  "geometry": {"coordinates":[-71.94848399999999,42.877476],"type":"Point"}
}