{
  "type": "Feature",
  "properties": {
    "addr:full":"37 Technology Dr Nashua NH 03053",
    "addr:housenumber":"37",
    "addr:postcode":"03053",
    "addr:street":"Technology Dr",
    "iso:country":"US",
    "sg:address":"37 Technology Dr",
    "sg:city":"Nashua",
    "sg:classifiers":[
        {
            "category":"Travel",
            "subcategory":"Travel Agent",
            "type":"Entertainment"
        }
    ],
    "sg:phone":"+1 603 889 9133",
    "sg:postcode":"03053",
    "sg:province":"NH",
    "sg:tags":[
        "agency"
    ],
    "wof:name":"Carlson Wagonlit Travel",
    "wof:placetype":"venue"
},
  "geometry": {"coordinates":[-71.42399500000001,42.932849],"type":"Point"}
}