{
  "type": "Feature",
  "properties": {
    "iso:country":"US",
    "sg:address":"32 Executive Dr",
    "sg:city":"Hudson",
    "sg:classifiers":[
        {
            "category":"Real Estate",
            "subcategory":"Developer",
            "type":"Services"
        }
    ],
    "sg:phone":"+1 603 889 1330",
    "sg:postcode":"03051",
    "sg:province":"NH",
    "wof:name":"N P V Development",
    "wof:placetype":"venue"
},
  "geometry": {"coordinates":[-71.43285400000001,42.736679],"type":"Point"}
}