{
  "type": "Feature",
  "properties": {
    "iso:country":"US",
    "sg:address":"70 Orford Rd",
    "sg:city":"Lyme",
    "sg:classifiers":[
        {
            "category":"Travel",
            "subcategory":"Hotels & Motels",
            "type":"Entertainment"
        }
    ],
    "sg:phone":"+1 603 795 2141",
    "sg:postcode":"03768",
    "sg:province":"NH",
    "sg:tags":[
        "breakfast",
        "court",
        "accommodation",
        "bed",
        "tourist"
    ],
    "sg:website":"www.lochlymelodge.com",
    "wof:name":"Loch Lyme Lodge Inc",
    "wof:placetype":"venue"
},
  "geometry": {"coordinates":[-72.149924,43.816038],"type":"Point"}
}