{
  "type": "Feature",
  "properties": {
    "iso:country":"US",
    "sg:address":"82 Manor Rd",
    "sg:city":"Concord",
    "sg:classifiers":[
        {
            "category":"Retail",
            "subcategory":"Laundry & Dry Cleaning",
            "type":"Services"
        }
    ],
    "sg:phone":"+1 603 225 6538",
    "sg:postcode":"03303",
    "sg:province":"NH",
    "sg:tags":[
        "upholstery",
        "carpet"
    ],
    "wof:name":"Dearborn Carpet Cleaning",
    "wof:placetype":"venue"
},
  "geometry": {"coordinates":[-71.57678799999999,43.264638],"type":"Point"}
}