{
  "type": "Feature",
  "properties": {
    "iso:country":"US",
    "sg:address":"5 Main St",
    "sg:city":"Plaistow",
    "sg:classifiers":[
        {
            "category":"Social Services",
            "subcategory":"Adult Care",
            "type":"Services"
        }
    ],
    "sg:phone":"+1 603 382 2244",
    "sg:postcode":"03865",
    "sg:province":"NH",
    "sg:tags":[
        "centers-adult",
        "day"
    ],
    "wof:name":"Life Visions",
    "wof:placetype":"venue"
},
  "geometry": {"coordinates":[-71.101007,42.815343],"type":"Point"}
}