{
  "type": "Feature",
  "properties": {
    "addr:full":"5 Arch Rd Claremont NH 03743",
    "addr:housenumber":"5",
    "addr:postcode":"03743",
    "addr:street":"Arch Rd",
    "iso:country":"US",
    "sg:address":"5 Arch Rd",
    "sg:city":"Claremont",
    "sg:classifiers":[
        {
            "category":"Social Services",
            "type":"Services"
        }
    ],
    "sg:phone":"+1 603 543 5998",
    "sg:postcode":"03743",
    "sg:province":"NH",
    "wof:name":"Claremont Senior Center Inc",
    "wof:placetype":"venue"
},
  "geometry": {"coordinates":[-72.357632,43.357259],"type":"Point"}
}