{
  "type": "Feature",
  "properties": {
    "addr:full":"2 Iris Ct Nashua NH 03062",
    "addr:housenumber":"2",
    "addr:postcode":"03062",
    "addr:street":"Iris Ct",
    "iso:country":"US",
    "sg:address":"2 Iris Ct",
    "sg:city":"Nashua",
    "sg:classifiers":[
        {
            "category":"Professional",
            "subcategory":"Business Services",
            "type":"Services"
        }
    ],
    "sg:phone":"+1 603 883 7412",
    "sg:postcode":"03062",
    "sg:province":"NH",
    "wof:name":"Walls and Spaces",
    "wof:placetype":"venue"
},
  "geometry": {"coordinates":[-71.50914899999999,42.737995],"type":"Point"}
}