{
  "type": "Feature",
  "properties": {
    "iso:country":"US",
    "sg:address":"55 Dodge Rd",
    "sg:city":"Amherst",
    "sg:classifiers":[
        {
            "category":"Insurance",
            "subcategory":"Insurance Agent",
            "type":"Services"
        }
    ],
    "sg:phone":"+1 603 673 0111",
    "sg:postcode":"03031",
    "sg:province":"NH",
    "wof:name":"John Walega & Co",
    "wof:placetype":"venue"
},
  "geometry": {"coordinates":[-71.615837,42.8888],"type":"Point"}
}