{
  "type": "Feature",
  "properties": {
    "iso:country":"US",
    "sg:address":"26 Holmgren Rd",
    "sg:city":"Stratham",
    "sg:classifiers":[
        {
            "category":"Wholesale",
            "subcategory":"Electrical",
            "type":"Manufacturing & Wholesale Goods"
        }
    ],
    "sg:phone":"+1 603 772 1540",
    "sg:postcode":"03885",
    "sg:province":"NH",
    "sg:tags":[
        "control"
    ],
    "wof:name":"RTP Corp",
    "wof:placetype":"venue"
},
  "geometry": {"coordinates":[-70.889512,42.995001],"type":"Point"}
}