{
  "type": "Feature",
  "properties": {
    "addr:full":"80 Rumford St Concord NH 03301",
    "addr:housenumber":"80",
    "addr:postcode":"03301",
    "addr:street":"Rumford St",
    "iso:country":"US",
    "sg:address":"80 Rumford St",
    "sg:city":"Concord",
    "sg:classifiers":[
        {
            "category":"Retail",
            "subcategory":"Portrait Studio",
            "type":"Services"
        }
    ],
    "sg:phone":"+1 603 225 3789",
    "sg:postcode":"03301",
    "sg:province":"NH",
    "sg:tags":[
        "photographer"
    ],
    "wof:name":"Mike Round's Photography Svc",
    "wof:placetype":"venue"
},
  "geometry": {"coordinates":[-71.543815,43.207797],"type":"Point"}
}