{
  "type": "Feature",
  "properties": {
    "iso:country":"US",
    "sg:address":"30 Exchange St",
    "sg:city":"Berlin",
    "sg:classifiers":[
        {
            "category":"Social Services",
            "type":"Services"
        }
    ],
    "sg:phone":"+1 603 752 1872",
    "sg:postcode":"03570",
    "sg:province":"NH",
    "wof:name":"Youth Alternatives",
    "wof:placetype":"venue"
},
  "geometry": {"coordinates":[-71.183965,44.46777],"type":"Point"}
}