{
  "type": "Feature",
  "properties": {
    "addr:full":"5 Harold Dr Nashua NH 03060",
    "addr:housenumber":"5",
    "addr:postcode":"03060",
    "addr:street":"Harold Dr",
    "iso:country":"US",
    "sg:address":"5 Harold Dr",
    "sg:city":"Nashua",
    "sg:classifiers":[
        {
            "category":"Government",
            "subcategory":"Post Office",
            "type":"Public Place"
        }
    ],
    "sg:phone":"+1 603 888 5411",
    "sg:postcode":"03060",
    "sg:province":"NH",
    "wof:name":"US Post Office",
    "wof:placetype":"venue"
},
  "geometry": {"coordinates":[-71.441981,42.708939],"type":"Point"}
}