{
  "type": "Feature",
  "properties": {
    "iso:country":"US",
    "sg:address":"8 Stiles Rd",
    "sg:city":"Salem",
    "sg:classifiers":[
        {
            "category":"Professional",
            "subcategory":"Accounting & Tax Preparation",
            "type":"Services"
        }
    ],
    "sg:phone":"+1 603 890 6633",
    "sg:postcode":"03079",
    "sg:province":"NH",
    "sg:tags":[
        "accountant"
    ],
    "wof:name":"R A Hall & Co",
    "wof:placetype":"venue"
},
  "geometry": {"coordinates":[-71.249135,42.768644],"type":"Point"}
}