{
  "type": "Feature",
  "properties": {
    "iso:country":"US",
    "sg:address":"99 Elm St",
    "sg:city":"Manchester",
    "sg:classifiers":[
        {
            "category":"Education",
            "subcategory":"Dance Studio",
            "type":"Public Place"
        }
    ],
    "sg:phone":"+1 603 624 6857",
    "sg:postcode":"03101",
    "sg:province":"NH",
    "sg:tags":[
        "latin",
        "ballroom",
        "offering",
        "social"
    ],
    "wof:name":"Arthur Murray Dance Studio",
    "wof:placetype":"venue"
},
  "geometry": {"coordinates":[-71.46290999999999,42.977731],"type":"Point"}
}