{
  "type": "Feature",
  "properties": {
    "iso:country":"US",
    "sg:address":"57 Sherburne Rd",
    "sg:city":"Pelham",
    "sg:classifiers":[
        {
            "category":"Building & Trades",
            "subcategory":"Electrical",
            "type":"Services"
        }
    ],
    "sg:phone":"+1 603 635 7565",
    "sg:postcode":"03076",
    "sg:province":"NH",
    "sg:tags":[
        "electrical",
        "contractor"
    ],
    "wof:name":"Andrew J Dow Electrical",
    "wof:placetype":"venue"
},
  "geometry": {"coordinates":[-71.37088900000001,42.70457],"type":"Point"}
}