{
  "type": "Feature",
  "properties": {
    "iso:country":"US",
    "sg:address":"2200 Front St",
    "sg:city":"Manchester",
    "sg:classifiers":[
        {
            "category":"Real Estate",
            "subcategory":"Real Estate Agent",
            "type":"Services"
        }
    ],
    "sg:phone":"+1 603 668 1889",
    "sg:postcode":"03102",
    "sg:province":"NH",
    "wof:name":"Letendre Richard P Realty & M",
    "wof:placetype":"venue"
},
  "geometry": {"coordinates":[-71.47793799999999,43.037546],"type":"Point"}
}