{
  "type": "Feature",
  "properties": {
    "iso:country":"US",
    "sg:address":"45 Reed Rd",
    "sg:city":"Colebrook",
    "sg:classifiers":[
        {
            "category":"Retail",
            "subcategory":"Repair Shop",
            "type":"Services"
        }
    ],
    "sg:phone":"+1 603 237 5517",
    "sg:postcode":"03584",
    "sg:province":"NH",
    "sg:tags":[
        "lock",
        "locksmith"
    ],
    "wof:name":"Zizza Lock & Safe",
    "wof:placetype":"venue"
},
  "geometry": {"coordinates":[-71.568354,44.461768],"type":"Point"}
}