{
  "type": "Feature",
  "properties": {
    "iso:country":"US",
    "sg:address":"29 Armory Rd Ste 1",
    "sg:city":"Milford",
    "sg:classifiers":[
        {
            "category":"Real Estate",
            "subcategory":"Real Estate Services",
            "type":"Services"
        },
        {
            "category":"Real Estate",
            "subcategory":"Real Estate Agent",
            "type":"Services"
        }
    ],
    "sg:phone":"+1 603 672 0300",
    "sg:postcode":"03055",
    "sg:province":"NH",
    "sg:tags":[
        "management"
    ],
    "wof:name":"R. J. Finlay & Co.",
    "wof:placetype":"venue"
},
  "geometry": {"coordinates":[-71.649109,42.81628],"type":"Point"}
}