{
  "type": "Feature",
  "properties": {
    "addr:full":"198 US Hwy 4 Enfield NH 03748",
    "addr:housenumber":"198",
    "addr:postcode":"03748",
    "addr:street":"Us Hwy 4",
    "iso:country":"US",
    "sg:address":"198 US Hwy 4",
    "sg:city":"Enfield",
    "sg:classifiers":[
        {
            "category":"Real Estate",
            "subcategory":"Real Estate Agent",
            "type":"Services"
        }
    ],
    "sg:phone":"+1 603 632 7955",
    "sg:postcode":"03748",
    "sg:province":"NH",
    "wof:name":"Cantlin Associates Realtors",
    "wof:placetype":"venue"
},
  "geometry": {"coordinates":[-72.148764,43.642615],"type":"Point"}
}