{
  "type": "Feature",
  "properties": {
    "addr:full":"65 Pine Island Rd Manchester NH 03103",
    "addr:housenumber":"65",
    "addr:postcode":"03103",
    "addr:street":"Pine Island Rd",
    "iso:country":"US",
    "sg:address":"65 Pine Island Rd",
    "sg:city":"Manchester",
    "sg:classifiers":[
        {
            "category":"Building & Trades",
            "subcategory":"Construction",
            "type":"Services"
        }
    ],
    "sg:phone":"+1 603 669 5020",
    "sg:postcode":"03103",
    "sg:province":"NH",
    "sg:tags":[
        "siding",
        "contractor"
    ],
    "wof:name":"Dependable J M R",
    "wof:placetype":"venue"
},
  "geometry": {"coordinates":[-71.453484,42.938755],"type":"Point"}
}