{
  "type": "Feature",
  "properties": {
    "addr:full":"649 E Industrial Park Dr Manchester NH 03109",
    "addr:housenumber":"649",
    "addr:postcode":"03109",
    "addr:street":"E Industrial Park Dr",
    "iso:country":"US",
    "sg:address":"649 E Industrial Park Dr",
    "sg:city":"Manchester",
    "sg:classifiers":[
        {
            "category":"Restaurant",
            "type":"Food & Drink"
        }
    ],
    "sg:phone":"+1 603 641 2993",
    "sg:postcode":"03109",
    "sg:province":"NH",
    "sg:tags":[
        "eating"
    ],
    "wof:name":"Moe Joe Country Diner",
    "wof:placetype":"venue"
},
  "geometry": {"coordinates":[-71.408384,42.980561],"type":"Point"}
}