{
  "type": "Feature",
  "properties": {
    "iso:country":"US",
    "sg:address":"214 Washington St",
    "sg:city":"Keene",
    "sg:classifiers":[
        {
            "category":"Professional",
            "subcategory":"Advertising",
            "type":"Services"
        }
    ],
    "sg:phone":"+1 603 352 4410",
    "sg:postcode":"03431",
    "sg:province":"NH",
    "sg:tags":[
        "counselor"
    ],
    "wof:name":"Sterling Design & Comms",
    "wof:placetype":"venue"
},
  "geometry": {"coordinates":[-72.27666000000001,42.939792],"type":"Point"}
}