{
  "type": "Feature",
  "properties": {
    "iso:country":"US",
    "sg:address":"59 Old Rochester Rd",
    "sg:city":"Dover",
    "sg:classifiers":[
        {
            "category":"Building & Trades",
            "subcategory":"Plumbing",
            "type":"Services"
        }
    ],
    "sg:phone":"+1 603 742 4141",
    "sg:postcode":"03820",
    "sg:province":"NH",
    "sg:tags":[
        "plumbing",
        "contractor"
    ],
    "wof:name":"Martel Plumbing & Heating Inc",
    "wof:placetype":"venue"
},
  "geometry": {"coordinates":[-70.89714600000001,43.230011],"type":"Point"}
}