{
  "type": "Feature",
  "properties": {
    "iso:country":"US",
    "sg:address":"122 Fitzwilliam Rd",
    "sg:city":"Richmond",
    "sg:classifiers":[
        {
            "category":"Shopping",
            "subcategory":"Used Merchandise",
            "type":"Retail Goods"
        }
    ],
    "sg:phone":"+1 603 239 4188",
    "sg:postcode":"03470",
    "sg:province":"NH",
    "sg:tags":[
        "antique"
    ],
    "wof:name":"Yankee Smuggler Antiques",
    "wof:placetype":"venue"
},
  "geometry": {"coordinates":[-72.25927799999999,42.754785],"type":"Point"}
}