{
  "type": "Feature",
  "properties": {
    "addr:full":"20 Spencer St Lebanon NH 03766",
    "addr:housenumber":"20",
    "addr:postcode":"03766",
    "addr:street":"Spencer St",
    "iso:country":"US",
    "sg:address":"20 Spencer St",
    "sg:city":"Lebanon",
    "sg:classifiers":[
        {
            "category":"Government",
            "subcategory":"Office",
            "type":"Public Place"
        }
    ],
    "sg:phone":"+1 603 448 3112",
    "sg:postcode":"03766",
    "sg:province":"NH",
    "sg:tags":[
        "village"
    ],
    "sg:website":"www.lebcity.com",
    "wof:name":"Highway Garage",
    "wof:placetype":"venue"
},
  "geometry": {"coordinates":[-72.249641,43.644735],"type":"Point"}
}