{
  "type": "Feature",
  "properties": {
    "iso:country":"US",
    "sg:address":"935 Ocean Blvd",
    "sg:city":"Hampton",
    "sg:classifiers":[
        {
            "category":"Travel",
            "subcategory":"Hotels & Motels",
            "type":"Entertainment"
        }
    ],
    "sg:phone":"+1 603 926 2500",
    "sg:postcode":"03842",
    "sg:province":"NH",
    "sg:tags":[
        "operation"
    ],
    "wof:name":"Windjammer Motel",
    "wof:placetype":"venue"
},
  "geometry": {"coordinates":[-70.79374900000001,42.941799],"type":"Point"}
}