{
  "type": "Feature",
  "properties": {
    "addr:full":"166 Woodland Rd Hampton NH 03842",
    "addr:housenumber":"166",
    "addr:postcode":"03842",
    "addr:street":"Woodland Rd",
    "iso:country":"US",
    "sg:address":"166 Woodland Rd",
    "sg:city":"Hampton",
    "sg:classifiers":[
        {
            "category":"Building & Trades",
            "subcategory":"Landscaping Services",
            "type":"Services"
        }
    ],
    "sg:phone":"+1 603 926 9852",
    "sg:postcode":"03842",
    "sg:province":"NH",
    "sg:tags":[
        "landscape",
        "contractor"
    ],
    "wof:name":"Greater North Landscaping",
    "wof:placetype":"venue"
},
  "geometry": {"coordinates":[-70.805505,42.949445],"type":"Point"}
}