{
  "type": "Feature",
  "properties": {
    "iso:country":"US",
    "sg:address":"52 Dexter St",
    "sg:city":"Nashua",
    "sg:classifiers":[
        {
            "category":"Building & Trades",
            "subcategory":"Cleaning & Sanitation",
            "type":"Services"
        }
    ],
    "sg:phone":"+1 603 598 3183",
    "sg:postcode":"03060",
    "sg:province":"NH",
    "sg:tags":[
        "maintenance"
    ],
    "wof:name":"AAA NH House Cleaning Service",
    "wof:placetype":"venue"
},
  "geometry": {"coordinates":[-71.472775,42.747085],"type":"Point"}
}