{
  "type": "Feature",
  "properties": {
    "iso:country":"US",
    "sg:address":"18 Winding Brook Rd",
    "sg:city":"Goffstown",
    "sg:classifiers":[
        {
            "category":"Professional",
            "subcategory":"Business Services",
            "type":"Services"
        }
    ],
    "sg:phone":"+1 603 624 1436",
    "sg:postcode":"03045",
    "sg:province":"NH",
    "wof:name":"Leistner Group LLC",
    "wof:placetype":"venue"
},
  "geometry": {"coordinates":[-71.528047,42.992191],"type":"Point"}
}