{
  "type": "Feature",
  "properties": {
    "iso:country":"US",
    "sg:address":"955 Ocean Blvd",
    "sg:city":"Hampton",
    "sg:classifiers":[
        {
            "category":"Travel",
            "subcategory":"Hotels & Motels",
            "type":"Entertainment"
        }
    ],
    "sg:phone":"+1 603 926 1750",
    "sg:postcode":"03842",
    "sg:province":"NH",
    "wof:name":"Seascape Inn",
    "wof:placetype":"venue"
},
  "geometry": {"coordinates":[-70.791173,42.943174],"type":"Point"}
}