{
  "type": "Feature",
  "properties": {
    "addr:full":"143 Kennard Rd Nottingham NH 03290",
    "addr:housenumber":"143",
    "addr:postcode":"03290",
    "addr:street":"Kennard Rd",
    "iso:country":"US",
    "sg:address":"143 Kennard Rd",
    "sg:city":"Nottingham",
    "sg:classifiers":[
        {
            "category":"Manufacturing",
            "subcategory":"Apparel",
            "type":"Manufacturing & Wholesale Goods"
        }
    ],
    "sg:phone":"+1 603 868 6161",
    "sg:postcode":"03290",
    "sg:province":"NH",
    "sg:tags":[
        "textile",
        "product",
        "fabricated",
        "mfg"
    ],
    "wof:name":"Horse Creations",
    "wof:placetype":"venue"
},
  "geometry": {"coordinates":[-71.06663500000001,43.151672],"type":"Point"}
}