{
  "type": "Feature",
  "properties": {
    "addr:full":"210 Daniel Webster Hwy Nashua NH 03060",
    "addr:housenumber":"210",
    "addr:postcode":"03060",
    "addr:street":"Daniel Webster Hwy",
    "iso:country":"US",
    "sg:address":"210 Daniel Webster Hwy",
    "sg:city":"Nashua",
    "sg:classifiers":[
        {
            "category":"Professional",
            "subcategory":"Management & Consulting",
            "type":"Services"
        }
    ],
    "sg:phone":"+1 603 595 4646",
    "sg:postcode":"03060",
    "sg:province":"NH",
    "wof:name":"Sara Lee Knit Products",
    "wof:placetype":"venue"
},
  "geometry": {"coordinates":[-71.442679,42.715191],"type":"Point"}
}