{
  "type": "Feature",
  "properties": {
    "iso:country":"US",
    "sg:address":"91 Norton Ave",
    "sg:city":"Manchester",
    "sg:classifiers":[
        {
            "category":"Restaurant",
            "type":"Food & Drink"
        }
    ],
    "sg:phone":"+1 603 624 4413",
    "sg:postcode":"03109",
    "sg:province":"NH",
    "sg:tags":[
        "eating"
    ],
    "wof:name":"Kikis Home Cookin Catering",
    "wof:placetype":"venue"
},
  "geometry": {"coordinates":[-71.42865999999999,42.982092],"type":"Point"}
}