{
  "type": "Feature",
  "properties": {
    "iso:country":"US",
    "sg:address":"5 Hampstead Rd",
    "sg:city":"East Hampstead",
    "sg:classifiers":[
        {
            "category":"Manufacturing",
            "subcategory":"Printing",
            "type":"Manufacturing & Wholesale Goods"
        }
    ],
    "sg:phone":"+1 603 382 7045",
    "sg:postcode":"03819",
    "sg:province":"NH",
    "sg:tags":[
        "printer"
    ],
    "sg:website":"www.ramprinting.com",
    "wof:name":"Ram Printing Inc",
    "wof:placetype":"venue"
},
  "geometry": {"coordinates":[-71.127644,42.900088],"type":"Point"}
}