{
  "type": "Feature",
  "properties": {
    "iso:country":"US",
    "sg:address":"36 Salisbury Rd",
    "sg:city":"Lyndeborough",
    "sg:classifiers":[
        {
            "category":"Wholesale",
            "subcategory":"Machinery & Supplies",
            "type":"Manufacturing & Wholesale Goods"
        }
    ],
    "sg:phone":"+1 603 654 5798",
    "sg:postcode":"03057",
    "sg:province":"NH",
    "wof:name":"Hanson & Hanson",
    "wof:placetype":"venue"
},
  "geometry": {"coordinates":[-71.72899700000001,42.900745],"type":"Point"}
}