{
  "type": "Feature",
  "properties": {
    "iso:country":"US",
    "sg:address":"1857 E Conway Rd",
    "sg:city":"North Conway",
    "sg:classifiers":[
        {
            "category":"Professional",
            "subcategory":"Advertising",
            "type":"Services"
        }
    ],
    "sg:phone":"+1 603 356 4881",
    "sg:postcode":"03813",
    "sg:province":"NH",
    "sg:tags":[
        "mailing",
        "shipping"
    ],
    "wof:name":"UPS Store",
    "wof:placetype":"venue"
},
  "geometry": {"coordinates":[-71.05955400000001,44.011275],"type":"Point"}
}