{
  "type": "Feature",
  "properties": {
    "addr:full":"132 Bunker Hill Rd Auburn NH 03032",
    "addr:housenumber":"132",
    "addr:postcode":"03032",
    "addr:street":"Bunker Hill Rd",
    "iso:country":"US",
    "sg:address":"132 Bunker Hill Rd",
    "sg:city":"Auburn",
    "sg:classifiers":[
        {
            "category":"Building & Trades",
            "subcategory":"Construction",
            "type":"Services"
        }
    ],
    "sg:phone":"+1 603 483 8577",
    "sg:postcode":"03032",
    "sg:province":"NH",
    "sg:tags":[
        "house"
    ],
    "wof:name":"Rolfe Builders",
    "wof:placetype":"venue"
},
  "geometry": {"coordinates":[-71.33295699999999,42.994173],"type":"Point"}
}