{
  "type": "Feature",
  "properties": {
    "addr:full":"81 Four Rod Rd Rochester NH 03867",
    "addr:housenumber":"81",
    "addr:postcode":"03867",
    "addr:street":"Four Rod Rd",
    "iso:country":"US",
    "sg:address":"81 Four Rod Rd",
    "sg:city":"Rochester",
    "sg:classifiers":[
        {
            "category":"Retail",
            "subcategory":"Auto Repair",
            "type":"Services"
        }
    ],
    "sg:phone":"+1 603 332 9726",
    "sg:postcode":"03867",
    "sg:province":"NH",
    "sg:tags":[
        "repairing",
        "automobile"
    ],
    "wof:name":"Timmers Automotive",
    "wof:placetype":"venue"
},
  "geometry": {"coordinates":[-71.035597,43.318858],"type":"Point"}
}