{
  "type": "Feature",
  "properties": {
    "iso:country":"US",
    "sg:address":"43 Gilford East Dr",
    "sg:city":"Gilford",
    "sg:classifiers":[
        {
            "category":"Home & Garden",
            "subcategory":"Building Materials",
            "type":"Retail Goods"
        },
        {
            "category":"Home & Garden",
            "subcategory":"Furniture",
            "type":"Retail Goods"
        }
    ],
    "sg:phone":"+1 603 527 0453",
    "sg:postcode":"03249",
    "sg:province":"NH",
    "sg:tags":[
        "installs",
        "equipment",
        "kitchen",
        "cabinet"
    ],
    "wof:name":"Kitchen Encounters",
    "wof:placetype":"venue"
},
  "geometry": {"coordinates":[-71.42501799999999,43.566528],"type":"Point"}
}