{
  "type": "Feature",
  "properties": {
    "iso:country":"US",
    "sg:address":"5 Pine St Exd",
    "sg:city":"Nashua",
    "sg:classifiers":[
        {
            "category":"Social Services",
            "type":"Services"
        }
    ],
    "sg:phone":"+1 603 881 4848",
    "sg:postcode":"03060",
    "sg:province":"NH",
    "sg:tags":[
        "program",
        "administrative"
    ],
    "sg:website":"www.keystonehall.org",
    "wof:name":"Keystone Hall",
    "wof:placetype":"venue"
},
  "geometry": {"coordinates":[-71.475207,42.762607],"type":"Point"}
}