{
  "type": "Feature",
  "properties": {
    "addr:full":"39 Cove St Goffstown NH 03045",
    "addr:housenumber":"39",
    "addr:postcode":"03045",
    "addr:street":"Cove St",
    "iso:country":"US",
    "sg:address":"39 Cove St",
    "sg:city":"Goffstown",
    "sg:classifiers":[
        {
            "category":"Building & Trades",
            "subcategory":"Plumbing",
            "type":"Services"
        }
    ],
    "sg:phone":"+1 603 625 1691",
    "sg:postcode":"03045",
    "sg:province":"NH",
    "sg:tags":[
        "plumbing",
        "heating",
        "contractor"
    ],
    "wof:name":"A Better Value Plbg & Htg Co",
    "wof:placetype":"venue"
},
  "geometry": {"coordinates":[-71.517042,43.006927],"type":"Point"}
}