{
  "type": "Feature",
  "properties": {
    "iso:country":"US",
    "sg:address":"125 Daniel Webster Hwy",
    "sg:city":"Merrimack",
    "sg:classifiers":[
        {
            "category":"Insurance",
            "subcategory":"Insurance Agent",
            "type":"Services"
        }
    ],
    "sg:phone":"+1 603 889 6963",
    "sg:postcode":"03054",
    "sg:province":"NH",
    "wof:name":"Gahan Associates",
    "wof:placetype":"venue"
},
  "geometry": {"coordinates":[-71.48569000000001,42.813533],"type":"Point"}
}