{
  "type": "Feature",
  "properties": {
    "addr:full":"253 Wilson St Manchester NH 03103",
    "addr:housenumber":"253",
    "addr:postcode":"03103",
    "addr:street":"Wilson St",
    "iso:country":"US",
    "sg:address":"253 Wilson St",
    "sg:city":"Manchester",
    "sg:classifiers":[
        {
            "category":"Restaurant",
            "type":"Food & Drink"
        }
    ],
    "sg:phone":"+1 603 626 5866",
    "sg:postcode":"03103",
    "sg:province":"NH",
    "wof:name":"On The Rocks",
    "wof:placetype":"venue"
},
  "geometry": {"coordinates":[-71.44820300000001,42.980616],"type":"Point"}
}