{
  "type": "Feature",
  "properties": {
    "addr:full":"10 Church St W Stewartstown NH 03584",
    "addr:housenumber":"10",
    "addr:postcode":"03584",
    "addr:street":"Church St W Stewartstown",
    "iso:country":"US",
    "sg:address":"10 Church St",
    "sg:city":"W Stewartstown",
    "sg:classifiers":[
        {
            "category":"Organizations",
            "subcategory":"Religious Organization",
            "type":"Services"
        }
    ],
    "sg:phone":"+1 603 246 8829",
    "sg:postcode":"03584",
    "sg:province":"NH",
    "sg:tags":[
        "church"
    ],
    "wof:name":"St Albert's Rectory",
    "wof:placetype":"venue"
},
  "geometry": {"coordinates":[-71.56958400000001,44.49169],"type":"Point"}
}