{
  "type": "Feature",
  "properties": {
    "iso:country":"US",
    "sg:address":"555 Canal St",
    "sg:city":"Manchester",
    "sg:classifiers":[
        {
            "category":"Health Services",
            "subcategory":"Chiropractor",
            "type":"Services"
        }
    ],
    "sg:phone":"+1 603 641 2227",
    "sg:postcode":"03101",
    "sg:province":"NH",
    "wof:name":"Janine Brown DC",
    "wof:placetype":"venue"
},
  "geometry": {"coordinates":[-71.465959,42.994443],"type":"Point"}
}