{
  "type": "Feature",
  "properties": {
    "addr:full":"65 Industrial Park Rd Dover NH 03820",
    "addr:housenumber":"65",
    "addr:postcode":"03820",
    "addr:street":"Industrial Park Rd",
    "iso:country":"US",
    "sg:address":"65 Industrial Park Rd",
    "sg:city":"Dover",
    "sg:classifiers":[
        {
            "category":"Building & Trades",
            "subcategory":"Electrical",
            "type":"Services"
        }
    ],
    "sg:phone":"+1 603 742 0677",
    "sg:postcode":"03820",
    "sg:province":"NH",
    "sg:tags":[
        "general",
        "electrical",
        "contractor"
    ],
    "wof:name":"Ray Martineau Elec Contrs",
    "wof:placetype":"venue"
},
  "geometry": {"coordinates":[-70.906138,43.18635],"type":"Point"}
}