{
  "type": "Feature",
  "properties": {
    "iso:country":"US",
    "sg:address":"628 Old Homestead Hwy",
    "sg:city":"Swanzey",
    "sg:classifiers":[
        {
            "category":"Education",
            "subcategory":"Library",
            "type":"Public Place"
        }
    ],
    "sg:phone":"+1 603 357 0456",
    "sg:postcode":"03446",
    "sg:province":"NH",
    "wof:name":"Mt Caesar Union Library",
    "wof:placetype":"venue"
},
  "geometry": {"coordinates":[-72.281113,42.874349],"type":"Point"}
}