{
  "type": "Feature",
  "properties": {
    "iso:country":"US",
    "sg:address":"448 Donald St",
    "sg:city":"Bedford",
    "sg:classifiers":[
        {
            "category":"Real Estate",
            "subcategory":"Developer",
            "type":"Services"
        }
    ],
    "sg:phone":"+1 603 622 9522",
    "sg:postcode":"03110",
    "sg:province":"NH",
    "sg:tags":[
        "cemetery"
    ],
    "wof:name":"St Josephs Cemetery",
    "wof:placetype":"venue"
},
  "geometry": {"coordinates":[-71.498767,42.969691],"type":"Point"}
}