{
  "type": "Feature",
  "properties": {
    "addr:full":"290 Burns Hill Rd Wilton NH 03086",
    "addr:housenumber":"290",
    "addr:postcode":"03086",
    "addr:street":"Burns Hill Rd",
    "iso:country":"US",
    "sg:address":"290 Burns Hill Rd",
    "sg:city":"Wilton",
    "sg:classifiers":[
        {
            "category":"Organizations",
            "subcategory":"Community Association",
            "type":"Services"
        }
    ],
    "sg:phone":"+1 603 654 2460",
    "sg:postcode":"03086",
    "sg:province":"NH",
    "wof:name":"Media Moose",
    "wof:placetype":"venue"
},
  "geometry": {"coordinates":[-71.764081,42.839759],"type":"Point"}
}