{
  "type": "Feature",
  "properties": {
    "iso:country":"US",
    "sg:address":"43 N Main St",
    "sg:city":"Concord",
    "sg:classifiers":[
        {
            "category":"Professional",
            "subcategory":"Lawyer & Legal Services",
            "type":"Services"
        }
    ],
    "sg:phone":"+1 603 225 4334",
    "sg:postcode":"03301",
    "sg:province":"NH",
    "sg:tags":[
        "attorney"
    ],
    "sg:website":"www.haslaw.com",
    "wof:name":"Hinckley Allen & Snyder",
    "wof:placetype":"venue"
},
  "geometry": {"coordinates":[-71.536328,43.206346],"type":"Point"}
}