{
  "type": "Feature",
  "properties": {
    "addr:full":"163 Old Warner Rd Bradford NH 03221",
    "addr:housenumber":"163",
    "addr:postcode":"03221",
    "addr:street":"Old Warner Rd",
    "iso:country":"US",
    "sg:address":"163 Old Warner Rd",
    "sg:city":"Bradford",
    "sg:classifiers":[
        {
            "category":"Education",
            "subcategory":"School",
            "type":"Public Place"
        }
    ],
    "sg:phone":"+1 603 938 2538",
    "sg:postcode":"03221",
    "sg:province":"NH",
    "wof:name":"Bradford School",
    "wof:placetype":"venue"
},
  "geometry": {"coordinates":[-71.946038,43.267047],"type":"Point"}
}