{
  "type": "Feature",
  "properties": {
    "iso:country":"US",
    "sg:address":"134 Plaistow Rd",
    "sg:city":"Plaistow",
    "sg:classifiers":[
        {
            "category":"Autos & Motor Vehicles",
            "subcategory":"Automobile Sales",
            "type":"Retail Goods"
        },
        {
            "category":"Retail",
            "subcategory":"Auto Repair",
            "type":"Services"
        }
    ],
    "sg:phone":"+1 603 382 3222",
    "sg:postcode":"03865",
    "sg:province":"NH",
    "sg:tags":[
        "dealers-used",
        "car",
        "used",
        "cars-wholesale"
    ],
    "wof:name":"Wally S Auto World",
    "wof:placetype":"venue"
},
  "geometry": {"coordinates":[-71.10701,42.84425],"type":"Point"}
}