{
  "type": "Feature",
  "properties": {
    "iso:country":"US",
    "sg:address":"40 Lebanon St",
    "sg:city":"West Lebanon",
    "sg:classifiers":[
        {
            "category":"Wholesale",
            "subcategory":"Machinery & Supplies",
            "type":"Manufacturing & Wholesale Goods"
        }
    ],
    "sg:phone":"+1 603 298 5275",
    "sg:postcode":"03755",
    "sg:province":"NH",
    "sg:tags":[
        "industrial"
    ],
    "wof:name":"Red Hed Supply Inc",
    "wof:placetype":"venue"
},
  "geometry": {"coordinates":[-72.283063,43.69927],"type":"Point"}
}