{
  "type": "Feature",
  "properties": {
    "iso:country":"US",
    "sg:address":"363 Shaker Rd",
    "sg:city":"Canterbury",
    "sg:classifiers":[
        {
            "category":"Professional",
            "subcategory":"Management & Consulting",
            "type":"Services"
        }
    ],
    "sg:phone":"+1 603 783 4681",
    "sg:postcode":"03224",
    "sg:province":"NH",
    "wof:name":"Tory Dodge Assoc Schools",
    "wof:placetype":"venue"
},
  "geometry": {"coordinates":[-71.490765,43.36008],"type":"Point"}
}