{
  "type": "Feature",
  "properties": {
    "iso:country":"US",
    "sg:address":"6 2nd St",
    "sg:city":"Exeter",
    "sg:classifiers":[
        {
            "category":"Building & Trades",
            "subcategory":"Cleaning & Sanitation",
            "type":"Services"
        }
    ],
    "sg:phone":"+1 603 778 7788",
    "sg:postcode":"03833",
    "sg:province":"NH",
    "sg:tags":[
        "maintenance"
    ],
    "wof:name":"Healys Helping Hand Clg Svcs",
    "wof:placetype":"venue"
},
  "geometry": {"coordinates":[-70.90314499999999,42.970613],"type":"Point"}
}