{
  "type": "Feature",
  "properties": {
    "iso:country":"US",
    "sg:address":"1618 E Conway Rd",
    "sg:city":"North Conway",
    "sg:classifiers":[
        {
            "category":"Wholesale",
            "subcategory":"Toys & Hobbies",
            "type":"Manufacturing & Wholesale Goods"
        }
    ],
    "sg:phone":"+1 603 356 3369",
    "sg:postcode":"03813",
    "sg:province":"ME",
    "sg:tags":[
        "wholesaler"
    ],
    "wof:name":"Lochcarron Of Scotland",
    "wof:placetype":"venue"
},
  "geometry": {"coordinates":[-71.059535,44.011285],"type":"Point"}
}