{
  "type": "Feature",
  "properties": {
    "addr:full":"3 S Broadway Salem NH 03079",
    "addr:housenumber":"3",
    "addr:postcode":"03079",
    "addr:street":"S Broadway",
    "iso:country":"US",
    "sg:address":"3 S Broadway",
    "sg:city":"Salem",
    "sg:classifiers":[
        {
            "category":"Banks & Credit Unions",
            "subcategory":"Bank",
            "type":"Services"
        }
    ],
    "sg:phone":"+1 603 898 2153",
    "sg:postcode":"03079",
    "sg:province":"NH",
    "wof:name":"Salem Co-Operative Bank",
    "wof:placetype":"venue"
},
  "geometry": {"coordinates":[-71.227017,42.778597],"type":"Point"}
}