{
  "type": "Feature",
  "properties": {
    "iso:country":"US",
    "sg:address":"170 Bedford Rd",
    "sg:city":"Merrimack",
    "sg:classifiers":[
        {
            "category":"Professional",
            "subcategory":"Business Services",
            "type":"Services"
        }
    ],
    "sg:phone":"+1 603 424 8027",
    "sg:postcode":"03054",
    "sg:province":"NH",
    "sg:tags":[
        "interior",
        "decorating"
    ],
    "wof:name":"Visions Interiors",
    "wof:placetype":"venue"
},
  "geometry": {"coordinates":[-71.51661799999999,42.896716],"type":"Point"}
}