{
  "type": "Feature",
  "properties": {
    "addr:full":"32 Twin Fawn Run Chester NH 03036",
    "addr:housenumber":"32",
    "addr:postcode":"03036",
    "addr:street":"Twin Fawn Run",
    "iso:country":"US",
    "sg:address":"32 Twin Fawn Run",
    "sg:city":"Chester",
    "sg:classifiers":[
        {
            "category":"Shopping",
            "subcategory":"Catalog Store",
            "type":"Retail Goods"
        }
    ],
    "sg:phone":"+1 603 887 3695",
    "sg:postcode":"03036",
    "sg:province":"NH",
    "sg:tags":[
        "mail",
        "house"
    ],
    "wof:name":"Past Presence Antiques",
    "wof:placetype":"venue"
},
  "geometry": {"coordinates":[-71.202112,42.980396],"type":"Point"}
}