{
  "type": "Feature",
  "properties": {
    "iso:country":"US",
    "sg:address":"4 Elliot Way",
    "sg:city":"Manchester",
    "sg:classifiers":[
        {
            "category":"Health Services",
            "subcategory":"Doctor",
            "type":"Services"
        }
    ],
    "sg:phone":"+1 603 623 3836",
    "sg:postcode":"03103",
    "sg:province":"NH",
    "sg:tags":[
        "medical"
    ],
    "wof:name":"Marc S Rubenson MD",
    "wof:placetype":"venue"
},
  "geometry": {"coordinates":[-71.436634,42.983428],"type":"Point"}
}