{
  "type": "Feature",
  "properties": {
    "iso:country":"US",
    "sg:address":"38 Adam Dr",
    "sg:city":"Hudson",
    "sg:classifiers":[
        {
            "category":"Professional",
            "subcategory":"Management & Consulting",
            "type":"Services"
        }
    ],
    "sg:phone":"+1 603 595 7929",
    "sg:postcode":"03051",
    "sg:province":"NH",
    "wof:name":"Greenwood Distributors",
    "wof:placetype":"venue"
},
  "geometry": {"coordinates":[-71.451193,42.797647],"type":"Point"}
}