{
  "type": "Feature",
  "properties": {
    "iso:country":"US",
    "sg:address":"20 State Rte 102",
    "sg:city":"Nashua",
    "sg:classifiers":[
        {
            "category":"Professional",
            "type":"Services"
        }
    ],
    "sg:phone":"+1 603 429 4300",
    "sg:postcode":"03036",
    "sg:province":"NH",
    "wof:name":"Merchant Express",
    "wof:placetype":"venue"
},
  "geometry": {"coordinates":[-71.255359,42.959572],"type":"Point"}
}