{
  "type": "Feature",
  "properties": {
    "addr:full":"37 Great Bay Dr E Greenland NH 03840",
    "addr:housenumber":"37",
    "addr:postcode":"03840",
    "addr:street":"Great Bay Dr E",
    "iso:country":"US",
    "sg:address":"37 Great Bay Dr E",
    "sg:city":"Greenland",
    "sg:classifiers":[
        {
            "category":"Building & Trades",
            "subcategory":"Construction",
            "type":"Services"
        }
    ],
    "sg:phone":"+1 603 502 4183",
    "sg:postcode":"03840",
    "sg:province":"NH",
    "sg:tags":[
        "contractor"
    ],
    "wof:name":"Perry Johnson",
    "wof:placetype":"venue"
},
  "geometry": {"coordinates":[-70.87994399999999,43.058627],"type":"Point"}
}