{
  "type": "Feature",
  "properties": {
    "addr:full":"8 Faneuil Hall Marketplace Boston NH 02109",
    "addr:housenumber":"8",
    "addr:postcode":"02109",
    "addr:street":"Faneuil Hall Marketplace",
    "iso:country":"US",
    "sg:address":"8 Faneuil Hall Marketplace",
    "sg:city":"Boston",
    "sg:classifiers":[
        {
            "category":"Professional",
            "subcategory":"Computer Services",
            "type":"Services"
        }
    ],
    "sg:phone":"+1 617 401 8733",
    "sg:postcode":"02109",
    "sg:province":"NH",
    "sg:tags":[
        "university-scheduling",
        "online-scheduling",
        "employee-scheduling",
        "web-based-scheduling",
        "lifeguard-scheduling",
        "recreation-scheduling",
        "college-scheduling",
        "student-worker-scheduling"
    ],
    "sg:website":"http://www.subitup.com",
    "wof:name":"SubItUp",
    "wof:placetype":"venue"
},
  "geometry": {"coordinates":[-71.15121499999999,42.355278],"type":"Point"}
}