{
  "type": "Feature",
  "properties": {
    "addr:full":"11 Pine Echo Rd New Boston NH 03070",
    "addr:housenumber":"11",
    "addr:postcode":"03070",
    "addr:street":"Pine Echo Rd",
    "iso:country":"US",
    "sg:address":"11 Pine Echo Rd",
    "sg:city":"New Boston",
    "sg:classifiers":[
        {
            "category":"Building & Trades",
            "subcategory":"Landscaping Services",
            "type":"Services"
        }
    ],
    "sg:phone":"+1 603 487 5114",
    "sg:postcode":"03070",
    "sg:province":"NH",
    "sg:tags":[
        "landscape"
    ],
    "wof:name":"Country Landscapes & Garden",
    "wof:placetype":"venue"
},
  "geometry": {"coordinates":[-71.710948,42.993217],"type":"Point"}
}