{
  "type": "Feature",
  "properties": {
    "addr:full":"8 Jacqueline Dr Goffstown NH 03046",
    "addr:housenumber":"8",
    "addr:postcode":"03046",
    "addr:street":"Jacqueline Dr",
    "iso:country":"US",
    "sg:address":"8 Jacqueline Dr",
    "sg:city":"Goffstown",
    "sg:classifiers":[
        {
            "category":"Building & Trades",
            "subcategory":"Plumbing",
            "type":"Services"
        }
    ],
    "sg:phone":"+1 603 774 8175",
    "sg:postcode":"03046",
    "sg:province":"NH",
    "sg:tags":[
        "contractor"
    ],
    "wof:name":"Jays Plumbing & Heating",
    "wof:placetype":"venue"
},
  "geometry": {"coordinates":[-71.56881,43.106242],"type":"Point"}
}