{
  "type": "Feature",
  "properties": {
    "iso:country":"US",
    "sg:address":"27 Main St",
    "sg:city":"Hancock",
    "sg:classifiers":[
        {
            "category":"Insurance",
            "subcategory":"Insurance Agent",
            "type":"Services"
        }
    ],
    "sg:phone":"+1 603 525 3342",
    "sg:postcode":"03449",
    "sg:province":"NH",
    "wof:name":"Bellows-Nichols Agency",
    "wof:placetype":"venue"
},
  "geometry": {"coordinates":[-71.987201,42.973432],"type":"Point"}
}