{
  "type": "Feature",
  "properties": {
    "iso:country":"US",
    "sg:address":"136 Old Sharon Rd",
    "sg:city":"Jaffrey",
    "sg:classifiers":[
        {
            "category":"Wholesale",
            "subcategory":"Toys & Hobbies",
            "type":"Manufacturing & Wholesale Goods"
        }
    ],
    "sg:phone":"+1 603 532 9540",
    "sg:postcode":"03452",
    "sg:province":"NH",
    "sg:tags":[
        "firework"
    ],
    "wof:name":"Nighthawk Firing Systems",
    "wof:placetype":"venue"
},
  "geometry": {"coordinates":[-71.991739,42.82096],"type":"Point"}
}