{
  "type": "Feature",
  "properties": {
    "addr:full":"20 Court St Exeter NH 03833",
    "addr:housenumber":"20",
    "addr:postcode":"03833",
    "addr:street":"Court St",
    "iso:country":"US",
    "sg:address":"20 Court St",
    "sg:city":"Exeter",
    "sg:classifiers":[
        {
            "category":"Building & Trades",
            "subcategory":"Plumbing",
            "type":"Services"
        }
    ],
    "sg:phone":"+1 603 778 9097",
    "sg:postcode":"03833",
    "sg:province":"NH",
    "sg:tags":[
        "product",
        "management",
        "energy",
        "system"
    ],
    "wof:name":"FPL Energy Seabrook LLC",
    "wof:placetype":"venue"
},
  "geometry": {"coordinates":[-70.946853,42.979617],"type":"Point"}
}