{
  "type": "Feature",
  "properties": {
    "iso:country":"US",
    "sg:address":"10 Lakeview Dr",
    "sg:city":"Meredith",
    "sg:classifiers":[
        {
            "category":"Shopping",
            "type":"Retail Goods"
        }
    ],
    "sg:phone":"+1 603 279 5486",
    "sg:postcode":"03253",
    "sg:province":"NH",
    "sg:tags":[
        "merchandise"
    ],
    "wof:name":"Roys Cheap Store",
    "wof:placetype":"venue"
},
  "geometry": {"coordinates":[-71.505475,43.648335],"type":"Point"}
}