{
  "type": "Feature",
  "properties": {
    "iso:country":"US",
    "sg:address":"127 Helena Dr",
    "sg:city":"New Boston",
    "sg:classifiers":[
        {
            "category":"Manufacturing",
            "subcategory":"Lumber",
            "type":"Manufacturing & Wholesale Goods"
        }
    ],
    "sg:phone":"+1 603 529 2544",
    "sg:postcode":"03070",
    "sg:province":"NH",
    "sg:tags":[
        "company",
        "logging"
    ],
    "wof:name":"Trimbur Forestry Logging",
    "wof:placetype":"venue"
},
  "geometry": {"coordinates":[-71.668828,43.025193],"type":"Point"}
}