{
  "type": "Feature",
  "properties": {
    "iso:country":"US",
    "sg:address":"11 Pleasant St",
    "sg:city":"New London",
    "sg:classifiers":[
        {
            "category":"Organizations",
            "subcategory":"Community Association",
            "type":"Services"
        }
    ],
    "sg:phone":"+1 603 526 6555",
    "sg:postcode":"03257",
    "sg:province":"NH",
    "sg:tags":[
        "environmental",
        "org"
    ],
    "sg:website":"www.ausbonsargent.org",
    "wof:name":"Ausbon Sargent Land Trust",
    "wof:placetype":"venue"
},
  "geometry": {"coordinates":[-71.98014499999999,43.419792],"type":"Point"}
}