{
  "type": "Feature",
  "properties": {
    "addr:full":"18 Russell St Nashua NH 03060",
    "addr:housenumber":"18",
    "addr:postcode":"03060",
    "addr:street":"Russell St",
    "iso:country":"US",
    "sg:address":"18 Russell St",
    "sg:city":"Nashua",
    "sg:classifiers":[
        {
            "category":"Building & Trades",
            "subcategory":"Cleaning & Sanitation",
            "type":"Services"
        }
    ],
    "sg:phone":"+1 603 880 3363",
    "sg:postcode":"03060",
    "sg:province":"NH",
    "sg:tags":[
        "maintenance"
    ],
    "wof:name":"Commercial Cleaning Co",
    "wof:placetype":"venue"
},
  "geometry": {"coordinates":[-71.474132,42.748373],"type":"Point"}
}