{
  "type": "Feature",
  "properties": {
    "iso:country":"US",
    "sg:address":"116 Crosby Rd",
    "sg:city":"Dover",
    "sg:classifiers":[
        {
            "category":"Professional",
            "subcategory":"Business Services",
            "type":"Services"
        },
        {
            "category":"Professional",
            "subcategory":"Management & Consulting",
            "type":"Services"
        }
    ],
    "sg:phone":"+1 603 742 1160",
    "sg:postcode":"03820",
    "sg:province":"NH",
    "sg:tags":[
        "instrument",
        "product",
        "musical",
        "consultant"
    ],
    "wof:name":"Poly Tech Co",
    "wof:placetype":"venue"
},
  "geometry": {"coordinates":[-70.91668900000001,43.178997],"type":"Point"}
}