{
  "type": "Feature",
  "properties": {
    "iso:country":"US",
    "sg:address":"293 Main St",
    "sg:city":"Tilton",
    "sg:classifiers":[
        {
            "category":"Insurance",
            "subcategory":"Insurance Agent",
            "type":"Services"
        }
    ],
    "sg:phone":"+1 603 286 3508",
    "sg:postcode":"03276",
    "sg:province":"NH",
    "sg:website":"www.preferredriskins.com",
    "wof:name":"Salisbury Insurance Inc",
    "wof:placetype":"venue"
},
  "geometry": {"coordinates":[-71.59045399999999,43.442743],"type":"Point"}
}