{
  "type": "Feature",
  "properties": {
    "iso:country":"US",
    "sg:address":"415 Emerson Ave",
    "sg:city":"Hampstead",
    "sg:classifiers":[
        {
            "category":"Autos & Motor Vehicles",
            "subcategory":"Automobile Sales",
            "type":"Retail Goods"
        }
    ],
    "sg:phone":"+1 603 329 4999",
    "sg:postcode":"03841",
    "sg:province":"NH",
    "sg:tags":[
        "car",
        "dealer"
    ],
    "wof:name":"AMK Auto Wholesale Brokers",
    "wof:placetype":"venue"
},
  "geometry": {"coordinates":[-71.149259,42.88706],"type":"Point"}
}