{
  "type": "Feature",
  "properties": {
    "addr:full":"30 Barretts Hill Rd Hudson NH 03051",
    "addr:housenumber":"30",
    "addr:postcode":"03051",
    "addr:street":"Barretts Hill Rd",
    "iso:country":"US",
    "sg:address":"30 Barretts Hill Rd",
    "sg:city":"Hudson",
    "sg:classifiers":[
        {
            "category":"Professional",
            "subcategory":"Business Services",
            "type":"Services"
        }
    ],
    "sg:phone":"+1 603 881 8960",
    "sg:postcode":"03051",
    "sg:province":"NH",
    "wof:name":"Tony Lekas",
    "wof:placetype":"venue"
},
  "geometry": {"coordinates":[-71.407061,42.78361],"type":"Point"}
}