{
  "type": "Feature",
  "properties": {
    "iso:country":"US",
    "sg:address":"151 Main St",
    "sg:city":"Nashua",
    "sg:classifiers":[
        {
            "category":"Organizations",
            "subcategory":"Non-profit Organization",
            "type":"Services"
        }
    ],
    "sg:phone":"+1 603 883 5700",
    "sg:postcode":"03060",
    "sg:province":"NH",
    "wof:name":"Great American Downtown",
    "wof:placetype":"venue"
},
  "geometry": {"coordinates":[-71.46548,42.76109],"type":"Point"}
}