{
  "type": "Feature",
  "properties": {
    "iso:country":"US",
    "sg:address":"12 Custer Cir",
    "sg:city":"Nashua",
    "sg:classifiers":[
        {
            "category":"Shopping",
            "subcategory":"Computers & Home Electronics",
            "type":"Retail Goods"
        }
    ],
    "sg:phone":"+1 603 883 7511",
    "sg:postcode":"03062",
    "sg:province":"NH",
    "sg:tags":[
        "parts",
        "supply"
    ],
    "wof:name":"GHA Technologies Inc",
    "wof:placetype":"venue"
},
  "geometry": {"coordinates":[-71.510446,42.736266],"type":"Point"}
}