{
  "type": "Feature",
  "properties": {
    "iso:country":"US",
    "sg:address":"111 Church St",
    "sg:city":"Laconia",
    "sg:classifiers":[
        {
            "category":"Health Services",
            "subcategory":"Doctor",
            "type":"Services"
        }
    ],
    "sg:phone":"+1 603 524 4430",
    "sg:postcode":"03246",
    "sg:province":"NH",
    "sg:tags":[
        "medical"
    ],
    "wof:name":"Lakes Region Pediatrics",
    "wof:placetype":"venue"
},
  "geometry": {"coordinates":[-71.465509,43.53129],"type":"Point"}
}