{
  "type": "Feature",
  "properties": {
    "addr:full":"569 New Hampton Rd Sanbornton NH 03269",
    "addr:housenumber":"569",
    "addr:postcode":"03269",
    "addr:street":"New Hampton Rd",
    "iso:country":"US",
    "sg:address":"569 New Hampton Rd",
    "sg:city":"Sanbornton",
    "sg:classifiers":[
        {
            "category":"Museum",
            "type":"Entertainment"
        }
    ],
    "sg:phone":"+1 603 934 3738",
    "sg:postcode":"03269",
    "sg:province":"NH",
    "sg:tags":[
        "gallery"
    ],
    "wof:name":"Sanbornton Historical Doc",
    "wof:placetype":"venue"
},
  "geometry": {"coordinates":[-71.631204,43.497267],"type":"Point"}
}