{
  "type": "Feature",
  "properties": {
    "iso:country":"US",
    "sg:address":"170 Commerce Way",
    "sg:city":"Portsmouth",
    "sg:classifiers":[
        {
            "category":"Manufacturing",
            "subcategory":"Tools & Machinery",
            "type":"Manufacturing & Wholesale Goods"
        }
    ],
    "sg:phone":"+1 603 431 1718",
    "sg:postcode":"03801",
    "sg:province":"NH",
    "sg:tags":[
        "conductive",
        "wiring",
        "devices",
        "mfg"
    ],
    "wof:name":"Schneider Electric",
    "wof:placetype":"venue"
},
  "geometry": {"coordinates":[-70.786124,43.090923],"type":"Point"}
}