{
  "type": "Feature",
  "properties": {
    "iso:country":"US",
    "sg:address":"2393 Lake Shore Rd",
    "sg:city":"Laconia",
    "sg:classifiers":[
        {
            "category":"Wholesale",
            "subcategory":"Home Furnishings",
            "type":"Manufacturing & Wholesale Goods"
        }
    ],
    "sg:phone":"+1 877 365 2920",
    "sg:postcode":"03249",
    "sg:province":"NH",
    "sg:tags":[
        "mat",
        "floor"
    ],
    "wof:name":"Genimex Inc",
    "wof:placetype":"venue"
},
  "geometry": {"coordinates":[-71.372084,43.579149],"type":"Point"}
}