{
  "type": "Feature",
  "properties": {
    "iso:country":"US",
    "sg:address":"215 Rochester Hill Rd",
    "sg:city":"Rochester",
    "sg:classifiers":[
        {
            "category":"Health Services",
            "subcategory":"Clinic",
            "type":"Services"
        }
    ],
    "sg:phone":"+1 603 335 1770",
    "sg:postcode":"03867",
    "sg:province":"NH",
    "sg:tags":[
        "home",
        "care"
    ],
    "sg:website":"www.thehomemakers.org",
    "wof:name":"Homemakers Of Strafford County",
    "wof:placetype":"venue"
},
  "geometry": {"coordinates":[-70.925353,43.279633],"type":"Point"}
}