{
  "type": "Feature",
  "properties": {
    "addr:full":"14 Main St West Lebanon NH 03784",
    "addr:housenumber":"14",
    "addr:postcode":"03784",
    "addr:street":"Main St",
    "iso:country":"US",
    "sg:address":"14 Main St",
    "sg:city":"West Lebanon",
    "sg:classifiers":[
        {
            "category":"Home & Garden",
            "subcategory":"Furniture",
            "type":"Retail Goods"
        }
    ],
    "sg:phone":"+1 603 298 9580",
    "sg:postcode":"03784",
    "sg:province":"NH",
    "sg:tags":[
        "mattress"
    ],
    "wof:name":"Defelice Mattress Ctr",
    "wof:placetype":"venue"
},
  "geometry": {"coordinates":[-72.309405,43.64488],"type":"Point"}
}