{
  "type": "Feature",
  "properties": {
    "iso:country":"US",
    "sg:address":"28 S Broadway",
    "sg:city":"Salem",
    "sg:classifiers":[
        {
            "category":"Personal",
            "type":"Services"
        }
    ],
    "sg:phone":"+1 603 894 4870",
    "sg:postcode":"03079",
    "sg:province":"NH",
    "sg:tags":[
        "palmist"
    ],
    "wof:name":"Readings By Mrs Marsh",
    "wof:placetype":"venue"
},
  "geometry": {"coordinates":[-71.226632,42.777902],"type":"Point"}
}