{
  "type": "Feature",
  "properties": {
    "iso:country":"US",
    "sg:address":"500 Chestnut St",
    "sg:city":"Manchester",
    "sg:classifiers":[
        {
            "category":"Travel",
            "subcategory":"Hotels & Motels",
            "type":"Entertainment"
        }
    ],
    "sg:phone":"+1 603 624 2223",
    "sg:postcode":"03101",
    "sg:province":"NH",
    "wof:name":"Cadillac Motel",
    "wof:placetype":"venue"
},
  "geometry": {"coordinates":[-71.460925,42.995014],"type":"Point"}
}