{
  "type": "Feature",
  "properties": {
    "iso:country":"US",
    "sg:address":"43 Birch St Ste B",
    "sg:city":"Derry",
    "sg:classifiers":[
        {
            "category":"Health Services",
            "subcategory":"Doctor",
            "type":"Services"
        }
    ],
    "sg:phone":"+1 603 434 0327",
    "sg:postcode":"03038",
    "sg:province":"NH",
    "sg:tags":[
        "physician",
        "pediatrics-emergency",
        "pediatrics",
        "family",
        "practice",
        "surgeons",
        "medicine",
        "surgeon"
    ],
    "sg:website":"http://www.derrypediatrics.com",
    "wof:name":"Derry Pediatrics Pro Assoc",
    "wof:placetype":"venue"
},
  "geometry": {"coordinates":[-71.32028200000001,42.877209],"type":"Point"}
}