{
  "type": "Feature",
  "properties": {
    "addr:full":"680 Central Ave Dover NH 03820",
    "addr:housenumber":"680",
    "addr:postcode":"03820",
    "addr:street":"Central Ave",
    "iso:country":"US",
    "sg:address":"680 Central Ave",
    "sg:city":"Dover",
    "sg:classifiers":[
        {
            "category":"Professional",
            "subcategory":"Business Services",
            "type":"Services"
        },
        {
            "category":"Insurance",
            "subcategory":"Insurance Agent",
            "type":"Services"
        }
    ],
    "sg:phone":"+1 603 743 6488",
    "sg:postcode":"03820",
    "sg:province":"NH",
    "wof:name":"Michael F Le Barge",
    "wof:placetype":"venue"
},
  "geometry": {"coordinates":[-70.875525,43.20553],"type":"Point"}
}