{
  "type": "Feature",
  "properties": {
    "iso:country":"US",
    "sg:address":"80 N Main St",
    "sg:city":"Franklin",
    "sg:classifiers":[
        {
            "category":"Autos & Motor Vehicles",
            "subcategory":"Fuel & Gas Station",
            "type":"Retail Goods"
        }
    ],
    "sg:phone":"+1 603 934 2606",
    "sg:postcode":"03235",
    "sg:province":"NH",
    "sg:tags":[
        "station",
        "gasoline"
    ],
    "wof:name":"Franklin Citgo",
    "wof:placetype":"venue"
},
  "geometry": {"coordinates":[-71.660342,43.443602],"type":"Point"}
}