{
  "type": "Feature",
  "properties": {
    "addr:full":"18 Main St Pittsfield NH 03263",
    "addr:housenumber":"18",
    "addr:postcode":"03263",
    "addr:street":"Main St",
    "iso:country":"US",
    "sg:address":"18 Main St",
    "sg:city":"Pittsfield",
    "sg:classifiers":[
        {
            "category":"Shopping",
            "subcategory":"Stationery & Office Supplies",
            "type":"Retail Goods"
        }
    ],
    "sg:phone":"+1 603 435 8500",
    "sg:postcode":"03263",
    "sg:province":"NH",
    "sg:tags":[
        "rubber",
        "stamp",
        "plastic"
    ],
    "wof:name":"Simply Stamps",
    "wof:placetype":"venue"
},
  "geometry": {"coordinates":[-71.329848,43.305459],"type":"Point"}
}