{
  "type": "Feature",
  "properties": {
    "iso:country":"US",
    "sg:address":"5 Hurd Hill Rd",
    "sg:city":"Lisbon",
    "sg:classifiers":[
        {
            "category":"Government",
            "subcategory":"Office",
            "type":"Public Place"
        }
    ],
    "sg:phone":"+1 603 838 0017",
    "sg:postcode":"03585",
    "sg:province":"NH",
    "sg:tags":[
        "housing",
        "program"
    ],
    "wof:name":"Tinkerville Arts Pond Hous",
    "wof:placetype":"venue"
},
  "geometry": {"coordinates":[-71.92394299999999,44.277966],"type":"Point"}
}