{
  "type": "Feature",
  "properties": {
    "iso:country":"US",
    "sg:address":"12 Integra Dr",
    "sg:city":"Concord",
    "sg:classifiers":[
        {
            "category":"Retail",
            "subcategory":"Repair Shop",
            "type":"Services"
        }
    ],
    "sg:phone":"+1 603 225 6266",
    "sg:postcode":"03301",
    "sg:province":"NH",
    "sg:tags":[
        "lock",
        "locksmith"
    ],
    "wof:name":"John's Auto Lock-Out Svc",
    "wof:placetype":"venue"
},
  "geometry": {"coordinates":[-71.502909,43.185069],"type":"Point"}
}