{
  "type": "Feature",
  "properties": {
    "addr:full":"97 Eddy Rd Manchester NH 03102",
    "addr:housenumber":"97",
    "addr:postcode":"03102",
    "addr:street":"Eddy Rd",
    "iso:country":"US",
    "sg:address":"97 Eddy Rd",
    "sg:city":"Manchester",
    "sg:classifiers":[
        {
            "category":"Bars & Pubs",
            "type":"Food & Drink"
        }
    ],
    "sg:phone":"+1 603 647 8465",
    "sg:postcode":"03102",
    "sg:province":"NH",
    "sg:tags":[
        "drinking"
    ],
    "wof:name":"TN 21s Bomb Shelter",
    "wof:placetype":"venue"
},
  "geometry": {"coordinates":[-71.474656,42.996659],"type":"Point"}
}