{
  "type": "Feature",
  "properties": {
    "iso:country":"US",
    "sg:address":"26 Scobie Pond Rd",
    "sg:city":"Derry",
    "sg:phone":"+1 603 432 7800",
    "sg:postcode":"03038",
    "sg:province":"NH",
    "wof:name":"Green Cab Co",
    "wof:placetype":"venue"
},
  "geometry": {"coordinates":[-71.337891,42.903568],"type":"Point"}
}