{
  "type": "Feature",
  "properties": {
    "iso:country":"US",
    "sg:address":"6 Finch St",
    "sg:city":"Keene",
    "sg:classifiers":[
        {
            "category":"Building & Trades",
            "subcategory":"Cleaning & Sanitation",
            "type":"Services"
        }
    ],
    "sg:phone":"+1 603 358 3423",
    "sg:postcode":"03431",
    "sg:province":"NH",
    "sg:tags":[
        "maintenance"
    ],
    "wof:name":"Cheshire Maintenance",
    "wof:placetype":"venue"
},
  "geometry": {"coordinates":[-72.306006,42.959328],"type":"Point"}
}