{
  "type": "Feature",
  "properties": {
    "addr:full":"100 Diamond Pl Laconia NH 03246",
    "addr:housenumber":"100",
    "addr:postcode":"03246",
    "addr:street":"Diamond Pl",
    "iso:country":"US",
    "sg:address":"100 Diamond Pl",
    "sg:city":"Laconia",
    "sg:classifiers":[
        {
            "category":"Building & Trades",
            "subcategory":"Construction",
            "type":"Services"
        }
    ],
    "sg:phone":"+1 603 524 6889",
    "sg:postcode":"03246",
    "sg:province":"NH",
    "sg:tags":[
        "excavation",
        "contractor"
    ],
    "wof:name":"Province Sand & Gravel Inc",
    "wof:placetype":"venue"
},
  "geometry": {"coordinates":[-71.456727,43.504828],"type":"Point"}
}