{
  "type": "Feature",
  "properties": {
    "iso:country":"US",
    "sg:address":"11 Freedom Acres Dr",
    "sg:city":"Concord",
    "sg:classifiers":[
        {
            "category":"Building & Trades",
            "subcategory":"Construction",
            "type":"Services"
        }
    ],
    "sg:phone":"+1 603 228 4369",
    "sg:postcode":"03301",
    "sg:province":"NH",
    "sg:tags":[
        "carpentry",
        "carpenter",
        "contractor"
    ],
    "wof:name":"Robbins Quality Carpentary",
    "wof:placetype":"venue"
},
  "geometry": {"coordinates":[-71.56129,43.286214],"type":"Point"}
}