{
  "type": "Feature",
  "properties": {
    "addr:full":"836 Candia Rd Manchester NH 03109",
    "addr:housenumber":"836",
    "addr:postcode":"03109",
    "addr:street":"Candia Rd",
    "iso:country":"US",
    "sg:address":"836 Candia Rd",
    "sg:city":"Manchester",
    "sg:classifiers":[
        {
            "category":"Retail",
            "subcategory":"Auto Repair",
            "type":"Services"
        }
    ],
    "sg:phone":"+1 603 626 4423",
    "sg:postcode":"03109",
    "sg:province":"NH",
    "sg:tags":[
        "repairing",
        "automobile"
    ],
    "wof:name":"Reynolds Auto",
    "wof:placetype":"venue"
},
  "geometry": {"coordinates":[-71.41496600000001,42.984125],"type":"Point"}
}