{
  "type": "Feature",
  "properties": {
    "iso:country":"US",
    "sg:address":"775 Lafayette Rd",
    "sg:city":"Portsmouth",
    "sg:classifiers":[
        {
            "category":"Shopping",
            "subcategory":"Gifts & Souvenirs",
            "type":"Retail Goods"
        }
    ],
    "sg:phone":"+1 603 431 9438",
    "sg:postcode":"03801",
    "sg:province":"NH",
    "sg:tags":[
        "party",
        "supply"
    ],
    "wof:name":"Party People",
    "wof:placetype":"venue"
},
  "geometry": {"coordinates":[-70.77031599999999,43.052793],"type":"Point"}
}