{
  "type": "Feature",
  "properties": {
    "addr:full":"294 S River Rd Bedford NH 03110",
    "addr:housenumber":"294",
    "addr:postcode":"03110",
    "addr:street":"S River Rd",
    "iso:country":"US",
    "sg:address":"294 S River Rd",
    "sg:city":"Bedford",
    "sg:classifiers":[
        {
            "category":"Home & Garden",
            "subcategory":"Furniture",
            "type":"Retail Goods"
        }
    ],
    "sg:phone":"+1 603 625 5795",
    "sg:postcode":"03110",
    "sg:province":"NH",
    "wof:name":"A A Mooney Furniture Co",
    "wof:placetype":"venue"
},
  "geometry": {"coordinates":[-71.46397399999999,42.933811],"type":"Point"}
}