{
  "type": "Feature",
  "properties": {
    "addr:full":"137 Westgate Rd Plainfield NH 03781",
    "addr:housenumber":"137",
    "addr:postcode":"03781",
    "addr:street":"Westgate Rd",
    "iso:country":"US",
    "sg:address":"137 Westgate Rd",
    "sg:city":"Plainfield",
    "sg:classifiers":[
        {
            "category":"Home & Garden",
            "subcategory":"Carpets & Floor Coverings",
            "type":"Retail Goods"
        }
    ],
    "sg:phone":"+1 603 675 2832",
    "sg:postcode":"03781",
    "sg:province":"NH",
    "wof:name":"Floor Coverings International",
    "wof:placetype":"venue"
},
  "geometry": {"coordinates":[-72.34391100000001,43.527623],"type":"Point"}
}