{
  "type": "Feature",
  "properties": {
    "iso:country":"US",
    "sg:address":"67 Main St",
    "sg:city":"Keene",
    "sg:classifiers":[
        {
            "category":"Shopping",
            "subcategory":"News",
            "type":"Retail Goods"
        }
    ],
    "sg:phone":"+1 603 357 4696",
    "sg:postcode":"03431",
    "sg:province":"NH",
    "wof:name":"Corner News",
    "wof:placetype":"venue"
},
  "geometry": {"coordinates":[-72.278244,42.93199],"type":"Point"}
}