{
  "type": "Feature",
  "properties": {
    "iso:country":"US",
    "sg:address":"1 Mill St",
    "sg:city":"Exeter",
    "sg:classifiers":[
        {
            "category":"Building & Trades",
            "subcategory":"Construction",
            "type":"Services"
        }
    ],
    "sg:phone":"+1 603 772 1998",
    "sg:postcode":"03833",
    "sg:province":"NH",
    "sg:tags":[
        "painter"
    ],
    "wof:name":"Pizzano Designs",
    "wof:placetype":"venue"
},
  "geometry": {"coordinates":[-70.960825,42.978581],"type":"Point"}
}