{
  "type": "Feature",
  "properties": {
    "iso:country":"US",
    "sg:address":"68 Maple St",
    "sg:city":"Henniker",
    "sg:classifiers":[
        {
            "category":"Restaurant",
            "type":"Food & Drink"
        }
    ],
    "sg:phone":"+1 603 428 7007",
    "sg:postcode":"03242",
    "sg:province":"NH",
    "wof:name":"Country Spirit Restaurant",
    "wof:placetype":"venue"
},
  "geometry": {"coordinates":[-71.824867,43.18403],"type":"Point"}
}