{
  "type": "Feature",
  "properties": {
    "addr:full":"48 Riverview St Milford NH 03055",
    "addr:housenumber":"48",
    "addr:postcode":"03055",
    "addr:street":"Riverview St",
    "iso:country":"US",
    "sg:address":"48 Riverview St",
    "sg:city":"Milford",
    "sg:classifiers":[
        {
            "category":"Retail",
            "subcategory":"Auto Repair",
            "type":"Services"
        }
    ],
    "sg:phone":"+1 603 673 1300",
    "sg:postcode":"03055",
    "sg:province":"NH",
    "sg:tags":[
        "general"
    ],
    "wof:name":"Riverside Garage",
    "wof:placetype":"venue"
},
  "geometry": {"coordinates":[-71.634092,42.830979],"type":"Point"}
}