{
  "type": "Feature",
  "properties": {
    "iso:country":"US",
    "sg:address":"4 Front St",
    "sg:city":"Exeter",
    "sg:classifiers":[
        {
            "category":"Travel",
            "subcategory":"Hotels & Motels",
            "type":"Entertainment"
        }
    ],
    "sg:phone":"+1 603 772 6352",
    "sg:postcode":"03833",
    "sg:province":"NH",
    "sg:tags":[
        "breakfast",
        "accommodation",
        "bed"
    ],
    "wof:name":"Inn By The Bandstand",
    "wof:placetype":"venue"
},
  "geometry": {"coordinates":[-70.946654,42.980833],"type":"Point"}
}