{
  "type": "Feature",
  "properties": {
    "iso:country":"US",
    "sg:address":"16 Bloody Brook Rd",
    "sg:city":"Amherst",
    "sg:classifiers":[
        {
            "category":"Real Estate",
            "subcategory":"Real Estate Agent",
            "type":"Services"
        }
    ],
    "sg:phone":"+1 603 673 9483",
    "sg:postcode":"03031",
    "sg:province":"NH",
    "wof:name":"Barrett Neumann Realty Trust",
    "wof:placetype":"venue"
},
  "geometry": {"coordinates":[-71.641373,42.869538],"type":"Point"}
}