{
  "type": "Feature",
  "properties": {
    "iso:country":"US",
    "sg:address":"95 Plaistow Rd",
    "sg:city":"Plaistow",
    "sg:classifiers":[
        {
            "category":"Health Services",
            "subcategory":"Doctor",
            "type":"Services"
        }
    ],
    "sg:phone":"+1 603 382 1585",
    "sg:postcode":"03865",
    "sg:province":"NH",
    "sg:tags":[
        "dentist"
    ],
    "wof:name":"Leonard E Di Paolo DDS",
    "wof:placetype":"venue"
},
  "geometry": {"coordinates":[-71.107764,42.83253],"type":"Point"}
}