{
  "type": "Feature",
  "properties": {
    "iso:country":"US",
    "sg:address":"1151 Suncook Valley Hwy S",
    "sg:city":"Epsom",
    "sg:classifiers":[
        {
            "category":"Autos & Motor Vehicles",
            "subcategory":"Automobile Sales",
            "type":"Retail Goods"
        }
    ],
    "sg:phone":"+1 603 736 9323",
    "sg:postcode":"03234",
    "sg:province":"NH",
    "sg:tags":[
        "car",
        "dealer"
    ],
    "sg:website":"www.m-mford.com",
    "wof:name":"M & M Ford",
    "wof:placetype":"venue"
},
  "geometry": {"coordinates":[-71.368149,43.244775],"type":"Point"}
}