{
  "type": "Feature",
  "properties": {
    "addr:full":"415 Oak St Manchester NH 03104",
    "addr:housenumber":"415",
    "addr:postcode":"03104",
    "addr:street":"Oak St",
    "iso:country":"US",
    "sg:address":"415 Oak St",
    "sg:city":"Manchester",
    "sg:classifiers":[
        {
            "category":"Personal",
            "subcategory":"Beauty Salon",
            "type":"Services"
        }
    ],
    "sg:phone":"+1 603 625 2040",
    "sg:postcode":"03104",
    "sg:province":"NH",
    "sg:tags":[
        "shop"
    ],
    "wof:name":"Now & Then Beauty Salon",
    "wof:placetype":"venue"
},
  "geometry": {"coordinates":[-71.454649,43.008927],"type":"Point"}
}