{
  "type": "Feature",
  "properties": {
    "iso:country":"US",
    "sg:address":"40 Primrose Dr N",
    "sg:city":"Laconia",
    "sg:classifiers":[
        {
            "category":"Food & Beverages",
            "subcategory":"Dairy",
            "type":"Retail Goods"
        }
    ],
    "sg:phone":"+1 603 366 9323",
    "sg:postcode":"03246",
    "sg:province":"NH",
    "sg:tags":[
        "product"
    ],
    "wof:name":"Liliuokalanis",
    "wof:placetype":"venue"
},
  "geometry": {"coordinates":[-71.490714,43.54592],"type":"Point"}
}