{
  "type": "Feature",
  "properties": {
    "addr:full":"1400 Lake Shore Rd Gilford NH 03249",
    "addr:housenumber":"1400",
    "addr:postcode":"03249",
    "addr:street":"Lake Shore Rd",
    "iso:country":"US",
    "sg:address":"1400 Lake Shore Rd",
    "sg:city":"Gilford",
    "sg:classifiers":[
        {
            "category":"Bakery",
            "type":"Food & Drink"
        },
        {
            "category":"Coffee & Tea",
            "type":"Food & Drink"
        },
        {
            "category":"Bagels",
            "type":"Food & Drink"
        },
        {
            "category":"Donuts",
            "type":"Food & Drink"
        }
    ],
    "sg:menulink":"http://www.allmenus.com/nh/gilford/149235-dunkin-donuts/menu/",
    "sg:phone":"+1 603 528 1751",
    "sg:postcode":"03249",
    "sg:province":"NH",
    "sg:tags":[
        "wrap",
        "american",
        "sandwich",
        "pastry"
    ],
    "wof:name":"Dunkin' Donuts",
    "wof:placetype":"venue"
},
  "geometry": {"coordinates":[-71.444872,43.562949],"type":"Point"}
}