{
  "type": "Feature",
  "properties": {
    "iso:country":"US",
    "sg:address":"50 Smith St",
    "sg:city":"Woodsville",
    "sg:classifiers":[
        {
            "category":"Food & Beverages",
            "subcategory":"Specialty",
            "type":"Retail Goods"
        }
    ],
    "sg:phone":"+1 603 747 8222",
    "sg:postcode":"03785",
    "sg:province":"NH",
    "sg:tags":[
        "health",
        "diet"
    ],
    "wof:name":"Back To Nature",
    "wof:placetype":"venue"
},
  "geometry": {"coordinates":[-72.032437,44.144226],"type":"Point"}
}