{
  "type": "Feature",
  "properties": {
    "iso:country":"US",
    "sg:address":"336 E Mountain Rd",
    "sg:city":"Newport",
    "sg:classifiers":[
        {
            "category":"Farming",
            "subcategory":"Dairy Farm",
            "type":"Manufacturing & Wholesale Goods"
        }
    ],
    "sg:phone":"+1 603 542 7712",
    "sg:postcode":"03773",
    "sg:province":"NH",
    "wof:name":"Edward Macglaflin",
    "wof:placetype":"venue"
},
  "geometry": {"coordinates":[-72.14203500000001,43.337664],"type":"Point"}
}