{
  "type": "Feature",
  "properties": {
    "addr:full":"75 Gilcreast Rd Londonderry NH 03053",
    "addr:housenumber":"75",
    "addr:postcode":"03053",
    "addr:street":"Gilcreast Rd",
    "iso:country":"US",
    "sg:address":"75 Gilcreast Rd",
    "sg:city":"Londonderry",
    "sg:classifiers":[
        {
            "category":"Professional",
            "subcategory":"Lawyer & Legal Services",
            "type":"Services"
        }
    ],
    "sg:phone":"+1 603 425 1974",
    "sg:postcode":"03053",
    "sg:province":"NH",
    "sg:tags":[
        "attorney"
    ],
    "wof:name":"Odonnell Law",
    "wof:placetype":"venue"
},
  "geometry": {"coordinates":[-71.349985,42.865791],"type":"Point"}
}