{
  "type": "Feature",
  "properties": {
    "iso:country":"US",
    "sg:address":"10 Diamond Dr",
    "sg:city":"Derry",
    "sg:classifiers":[
        {
            "category":"Professional",
            "subcategory":"Testing Lab",
            "type":"Services"
        }
    ],
    "sg:phone":"+1 603 434 5245",
    "sg:postcode":"03038",
    "sg:province":"NH",
    "sg:tags":[
        "asbestos"
    ],
    "wof:name":"Axiom Partners",
    "wof:placetype":"venue"
},
  "geometry": {"coordinates":[-71.32693999999999,42.851406],"type":"Point"}
}