{
  "type": "Feature",
  "properties": {
    "addr:full":"109 Beech Hill Rd Mont Vernon NH 03057",
    "addr:housenumber":"109",
    "addr:postcode":"03057",
    "addr:street":"Beech Hill Rd",
    "iso:country":"US",
    "sg:address":"109 Beech Hill Rd",
    "sg:city":"Mont Vernon",
    "sg:classifiers":[
        {
            "category":"Building & Trades",
            "subcategory":"Landscaping Services",
            "type":"Services"
        }
    ],
    "sg:phone":"+1 603 654 5900",
    "sg:postcode":"03057",
    "sg:province":"NH",
    "sg:tags":[
        "landscape",
        "contractor"
    ],
    "wof:name":"C & L Drilling & Blasting",
    "wof:placetype":"venue"
},
  "geometry": {"coordinates":[-71.71647900000001,42.89907],"type":"Point"}
}