{
  "type": "Feature",
  "properties": {
    "addr:full":"34 Plaistow Rd Plaistow NH 03865",
    "addr:housenumber":"34",
    "addr:postcode":"03865",
    "addr:street":"Plaistow Rd",
    "iso:country":"US",
    "sg:address":"34 Plaistow Rd",
    "sg:city":"Plaistow",
    "sg:classifiers":[
        {
            "category":"Shopping",
            "subcategory":"Pharmacy",
            "type":"Retail Goods"
        }
    ],
    "sg:phone":"+1 603 382 9216",
    "sg:postcode":"03865",
    "sg:province":"NH",
    "wof:name":"Brooks Pharmacy",
    "wof:placetype":"venue"
},
  "geometry": {"coordinates":[-71.104984,42.824161],"type":"Point"}
}