{
  "type": "Feature",
  "properties": {
    "iso:country":"US",
    "sg:address":"10 Sherman St",
    "sg:city":"Elkins",
    "sg:classifiers":[
        {
            "category":"Building & Trades",
            "subcategory":"Construction",
            "type":"Services"
        }
    ],
    "sg:phone":"+1 603 526 6499",
    "sg:postcode":"03233",
    "sg:province":"NH",
    "sg:tags":[
        "contractor"
    ],
    "wof:name":"Hayes & Hayes",
    "wof:placetype":"venue"
},
  "geometry": {"coordinates":[-71.935819,43.420263],"type":"Point"}
}