{
  "type": "Feature",
  "properties": {
    "iso:country":"US",
    "sg:address":"191 S Stark Hwy",
    "sg:city":"Weare",
    "sg:classifiers":[
        {
            "category":"Professional",
            "subcategory":"Management & Consulting",
            "type":"Services"
        }
    ],
    "sg:phone":"+1 603 529 2866",
    "sg:postcode":"03281",
    "sg:province":"NH",
    "sg:tags":[
        "home",
        "demonstration"
    ],
    "wof:name":"Princess House Home Parties",
    "wof:placetype":"venue"
},
  "geometry": {"coordinates":[-71.662755,43.038675],"type":"Point"}
}