{
  "type": "Feature",
  "properties": {
    "iso:country":"US",
    "sg:address":"772 State Rte 63",
    "sg:city":"Westmoreland",
    "sg:classifiers":[
        {
            "category":"Government",
            "subcategory":"Fire Station",
            "type":"Public Place"
        }
    ],
    "sg:phone":"+1 603 399 9993",
    "sg:postcode":"03467",
    "sg:province":"NH",
    "sg:tags":[
        "department"
    ],
    "wof:name":"Westmoreland Fire Dept",
    "wof:placetype":"venue"
},
  "geometry": {"coordinates":[-72.44431899999999,42.950707],"type":"Point"}
}