{
  "type": "Feature",
  "properties": {
    "addr:full":"207 Meetinghouse Rd Bedford NH 03110",
    "addr:housenumber":"207",
    "addr:postcode":"03110",
    "addr:street":"Meetinghouse Rd",
    "iso:country":"US",
    "sg:address":"207 Meetinghouse Rd",
    "sg:city":"Bedford",
    "sg:classifiers":[
        {
            "category":"Health Services",
            "subcategory":"Optometrist",
            "type":"Services"
        }
    ],
    "sg:phone":"+1 603 668 2771",
    "sg:postcode":"03110",
    "sg:province":"NH",
    "wof:name":"McKay Vision Center LLC",
    "wof:placetype":"venue"
},
  "geometry": {"coordinates":[-71.47897,42.949987],"type":"Point"}
}