{
  "type": "Feature",
  "properties": {
    "iso:country":"US",
    "sg:address":"Mount Washington Vly",
    "sg:city":"North Conway",
    "sg:classifiers":[
        {
            "category":"Health Services",
            "subcategory":"Doctor",
            "type":"Services"
        }
    ],
    "sg:phone":"+1 603 356 7061",
    "sg:postcode":"03860",
    "sg:province":"NH",
    "wof:name":"Conway Orthopedic PA",
    "wof:placetype":"venue"
},
  "geometry": {"coordinates":[-71.11869900000001,44.027299],"type":"Point"}
}