{
  "type": "Feature",
  "properties": {
    "addr:full":"102 Marsh Rd Pelham NH 03076",
    "addr:housenumber":"102",
    "addr:postcode":"03076",
    "addr:street":"Marsh Rd",
    "iso:country":"US",
    "sg:address":"102 Marsh Rd",
    "sg:city":"Pelham",
    "sg:classifiers":[
        {
            "category":"Retail",
            "subcategory":"Auto Repair",
            "type":"Services"
        }
    ],
    "sg:phone":"+1 603 635 3050",
    "sg:postcode":"03076",
    "sg:province":"NH",
    "sg:tags":[
        "automotive",
        "general"
    ],
    "wof:name":"Steves Garage",
    "wof:placetype":"venue"
},
  "geometry": {"coordinates":[-71.332993,42.723095],"type":"Point"}
}