{
  "type": "Feature",
  "properties": {
    "iso:country":"US",
    "sg:address":"162 Lowell Rd",
    "sg:city":"Hudson",
    "sg:classifiers":[
        {
            "category":"Retail",
            "subcategory":"Auto Repair",
            "type":"Services"
        }
    ],
    "sg:phone":"+1 603 882 1037",
    "sg:postcode":"03051",
    "sg:province":"NH",
    "sg:tags":[
        "windshield"
    ],
    "sg:website":"http://www.safelite.com",
    "wof:name":"Safelite AutoGlass",
    "wof:placetype":"venue"
},
  "geometry": {"coordinates":[-71.42673000000001,42.744],"type":"Point"}
}