{
  "type": "Feature",
  "properties": {
    "iso:country":"US",
    "sg:address":"77 Newfields Rd",
    "sg:city":"Exeter",
    "sg:classifiers":[
        {
            "category":"Building & Trades",
            "subcategory":"Construction",
            "type":"Services"
        }
    ],
    "sg:phone":"+1 603 773 2900",
    "sg:postcode":"03833",
    "sg:province":"NH",
    "sg:tags":[
        "painter"
    ],
    "wof:name":"Caprioli Painting Inc",
    "wof:placetype":"venue"
},
  "geometry": {"coordinates":[-70.94143800000001,43.021119],"type":"Point"}
}