{
  "type": "Feature",
  "properties": {
    "addr:full":"429 Brackett Rd Rye NH 03870",
    "addr:housenumber":"429",
    "addr:postcode":"03870",
    "addr:street":"Brackett Rd",
    "iso:country":"US",
    "sg:address":"429 Brackett Rd",
    "sg:city":"Rye",
    "sg:classifiers":[
        {
            "category":"Professional",
            "subcategory":"Computer Services",
            "type":"Services"
        }
    ],
    "sg:phone":"+1 603 431 2403",
    "sg:postcode":"03870",
    "sg:province":"NH",
    "sg:tags":[
        "datum"
    ],
    "wof:name":"New Market Websites",
    "wof:placetype":"venue"
},
  "geometry": {"coordinates":[-70.742339,43.026718],"type":"Point"}
}