{
  "type": "Feature",
  "properties": {
    "iso:country":"US",
    "sg:address":"9 South Ave",
    "sg:city":"Derry",
    "sg:classifiers":[
        {
            "category":"Utilities",
            "subcategory":"Refuse",
            "type":"Services"
        }
    ],
    "sg:phone":"+1 603 437 1352",
    "sg:postcode":"03038",
    "sg:province":"NH",
    "sg:tags":[
        "disposal",
        "waste"
    ],
    "wof:name":"Draghi Environmental Svc Inc",
    "wof:placetype":"venue"
},
  "geometry": {"coordinates":[-71.32229599999999,42.879982],"type":"Point"}
}