{
  "type": "Feature",
  "properties": {
    "iso:country":"US",
    "sg:address":"174 S Mammoth Rd",
    "sg:city":"Manchester",
    "sg:classifiers":[
        {
            "category":"Professional",
            "subcategory":"Business Services",
            "type":"Services"
        }
    ],
    "sg:phone":"+1 603 493 4419",
    "sg:postcode":"03109",
    "sg:province":"NH",
    "sg:tags":[
        "drafting"
    ],
    "wof:name":"Designed",
    "wof:placetype":"venue"
},
  "geometry": {"coordinates":[-71.422178,42.966905],"type":"Point"}
}