{
  "type": "Feature",
  "properties": {
    "iso:country":"US",
    "sg:address":"29 Anvil Dr",
    "sg:city":"Nashua",
    "sg:classifiers":[
        {
            "category":"Building & Trades",
            "subcategory":"Construction",
            "type":"Services"
        }
    ],
    "sg:phone":"+1 603 882 1348",
    "sg:postcode":"03060",
    "sg:province":"NH",
    "sg:tags":[
        "nonresidential"
    ],
    "wof:name":"Construction Concepts",
    "wof:placetype":"venue"
},
  "geometry": {"coordinates":[-71.483616,42.742255],"type":"Point"}
}