{
  "type": "Feature",
  "properties": {
    "addr:full":"143 State Rte 113 Madison NH 03849",
    "addr:housenumber":"143",
    "addr:postcode":"03849",
    "addr:street":"State Rte 113",
    "iso:country":"US",
    "sg:address":"143 State Rte 113",
    "sg:city":"Madison",
    "sg:classifiers":[
        {
            "category":"Manufacturing",
            "subcategory":"Glass & Minerals",
            "type":"Manufacturing & Wholesale Goods"
        },
        {
            "category":"Building & Trades",
            "subcategory":"Construction",
            "type":"Services"
        }
    ],
    "sg:phone":"+1 603 447 5700",
    "sg:postcode":"03849",
    "sg:province":"NH",
    "sg:tags":[
        "ready",
        "concrete",
        "pumping",
        "mfg"
    ],
    "wof:name":"Coleman Concrete Inc",
    "wof:placetype":"venue"
},
  "geometry": {"coordinates":[-71.183713,43.887817],"type":"Point"}
}