{
  "type": "Feature",
  "properties": {
    "addr:full":"1 Cider Ln Nashua NH 03063",
    "addr:housenumber":"1",
    "addr:postcode":"03063",
    "addr:street":"Cider Ln",
    "iso:country":"US",
    "sg:address":"1 Cider Ln",
    "sg:city":"Nashua",
    "sg:classifiers":[
        {
            "category":"Professional",
            "subcategory":"Advertising",
            "type":"Services"
        }
    ],
    "sg:phone":"+1 603 886 9545",
    "sg:postcode":"03063",
    "sg:province":"NH",
    "sg:tags":[
        "consulting",
        "agency",
        "business"
    ],
    "wof:name":"Decision Analysts Inc",
    "wof:placetype":"venue"
},
  "geometry": {"coordinates":[-71.522952,42.757909],"type":"Point"}
}