{
  "type": "Feature",
  "properties": {
    "iso:country":"US",
    "sg:address":"3352 N Littleton Rd",
    "sg:city":"Littleton",
    "sg:classifiers":[
        {
            "category":"Building & Trades",
            "subcategory":"Electrical",
            "type":"Services"
        }
    ],
    "sg:phone":"+1 603 444 0957",
    "sg:postcode":"03561",
    "sg:province":"NH",
    "sg:tags":[
        "electric",
        "contractor"
    ],
    "wof:name":"Littleton Electric Solutions",
    "wof:placetype":"venue"
},
  "geometry": {"coordinates":[-71.768097,44.391292],"type":"Point"}
}