{
  "type": "Feature",
  "properties": {
    "addr:full":"58 Powder Hill Rd Bedford NH 03110",
    "addr:housenumber":"58",
    "addr:postcode":"03110",
    "addr:street":"Powder Hill Rd",
    "iso:country":"US",
    "sg:address":"58 Powder Hill Rd",
    "sg:city":"Bedford",
    "sg:classifiers":[
        {
            "category":"Manufacturing",
            "subcategory":"Tools & Machinery",
            "type":"Manufacturing & Wholesale Goods"
        }
    ],
    "sg:phone":"+1 603 472 6909",
    "sg:postcode":"03110",
    "sg:province":"NH",
    "sg:tags":[
        "industry",
        "mfg"
    ],
    "wof:name":"Mark Ilaria",
    "wof:placetype":"venue"
},
  "geometry": {"coordinates":[-71.557346,42.953057],"type":"Point"}
}