{
  "type": "Feature",
  "properties": {
    "iso:country":"US",
    "sg:address":"39 Averill Rd",
    "sg:city":"Brookline",
    "sg:classifiers":[
        {
            "category":"Professional",
            "subcategory":"Computer Services",
            "type":"Services"
        }
    ],
    "sg:phone":"+1 603 672 4769",
    "sg:postcode":"03033",
    "sg:province":"NH",
    "sg:tags":[
        "prepackaged",
        "software"
    ],
    "wof:name":"Butterpup Software",
    "wof:placetype":"venue"
},
  "geometry": {"coordinates":[-71.677421,42.709763],"type":"Point"}
}