{
  "type": "Feature",
  "properties": {
    "addr:full":"715 Main St Berlin NH 03570",
    "addr:housenumber":"715",
    "addr:postcode":"03570",
    "addr:street":"Main St",
    "iso:country":"US",
    "sg:address":"715 Main St",
    "sg:city":"Berlin",
    "sg:classifiers":[
        {
            "category":"Restaurant",
            "type":"Food & Drink"
        }
    ],
    "sg:phone":"+1 603 752 8100",
    "sg:postcode":"03570",
    "sg:province":"NH",
    "sg:tags":[
        "eating"
    ],
    "wof:name":"Lams Kitchen",
    "wof:placetype":"venue"
},
  "geometry": {"coordinates":[-71.172085,44.474521],"type":"Point"}
}