{
  "type": "Feature",
  "properties": {
    "addr:full":"24 Production Ave Keene NH 03431",
    "addr:housenumber":"24",
    "addr:postcode":"03431",
    "addr:street":"Production Ave",
    "iso:country":"US",
    "sg:address":"24 Production Ave",
    "sg:city":"Keene",
    "sg:classifiers":[
        {
            "category":"Wholesale",
            "subcategory":"Hardware",
            "type":"Manufacturing & Wholesale Goods"
        }
    ],
    "sg:phone":"+1 603 357 8458",
    "sg:postcode":"03431",
    "sg:province":"NH",
    "sg:tags":[
        "fastener"
    ],
    "wof:name":"Fastenal Co",
    "wof:placetype":"venue"
},
  "geometry": {"coordinates":[-72.30607500000001,42.923187],"type":"Point"}
}