{
  "type": "Feature",
  "properties": {
    "iso:country":"US",
    "sg:address":"65 Temple St",
    "sg:city":"Nashua",
    "sg:classifiers":[
        {
            "category":"Professional",
            "subcategory":"Lawyer & Legal Services",
            "type":"Services"
        }
    ],
    "sg:phone":"+1 603 594 4242",
    "sg:postcode":"03060",
    "sg:province":"NH",
    "sg:tags":[
        "attorney"
    ],
    "wof:name":"Ellen S Friedman",
    "wof:placetype":"venue"
},
  "geometry": {"coordinates":[-71.460668,42.761793],"type":"Point"}
}