{
  "type": "Feature",
  "properties": {
    "iso:country":"US",
    "sg:address":"168 Lincoln Ave",
    "sg:city":"Portsmouth",
    "sg:classifiers":[
        {
            "category":"Personal",
            "subcategory":"Beauty Salon",
            "type":"Services"
        }
    ],
    "sg:phone":"+1 603 436 8038",
    "sg:postcode":"03801",
    "sg:province":"NH",
    "sg:tags":[
        "shop"
    ],
    "wof:name":"Gleeful Color Inc",
    "wof:placetype":"venue"
},
  "geometry": {"coordinates":[-70.758219,43.069095],"type":"Point"}
}