{
  "type": "Feature",
  "properties": {
    "iso:country":"US",
    "sg:address":"127 Winnacunnet Rd",
    "sg:city":"Hampton",
    "sg:classifiers":[
        {
            "category":"Organizations",
            "subcategory":"Religious Organization",
            "type":"Services"
        }
    ],
    "sg:phone":"+1 603 926 2837",
    "sg:postcode":"03842",
    "sg:province":"NH",
    "wof:name":"First Congregational Church",
    "wof:placetype":"venue"
},
  "geometry": {"coordinates":[-70.830679,42.93694],"type":"Point"}
}