{
  "type": "Feature",
  "properties": {
    "iso:country":"US",
    "sg:address":"501 Washington Rd",
    "sg:city":"Rye",
    "sg:classifiers":[
        {
            "category":"Education",
            "subcategory":"School",
            "type":"Public Place"
        }
    ],
    "sg:phone":"+1 603 964 5591",
    "sg:postcode":"03870",
    "sg:province":"NH",
    "wof:name":"Rye Junior High School",
    "wof:placetype":"venue"
},
  "geometry": {"coordinates":[-70.769874,43.014409],"type":"Point"}
}