{
  "type": "Feature",
  "properties": {
    "iso:country":"US",
    "sg:address":"263 Peverly Hill Rd",
    "sg:city":"Portsmouth",
    "sg:classifiers":[
        {
            "category":"Organizations",
            "subcategory":"Religious Organization",
            "type":"Services"
        }
    ],
    "sg:phone":"+1 603 431 7310",
    "sg:postcode":"03801",
    "sg:province":"NH",
    "sg:tags":[
        "church"
    ],
    "wof:name":"New Hope Baptist Church",
    "wof:placetype":"venue"
},
  "geometry": {"coordinates":[-70.781104,43.056023],"type":"Point"}
}