{
  "type": "Feature",
  "properties": {
    "iso:country":"US",
    "sg:address":"1042 W Swanzey Rd",
    "sg:city":"Swanzey",
    "sg:classifiers":[
        {
            "category":"Wholesale",
            "subcategory":"Auto Parts",
            "type":"Manufacturing & Wholesale Goods"
        }
    ],
    "sg:phone":"+1 603 358 3306",
    "sg:postcode":"03446",
    "sg:province":"NH",
    "sg:tags":[
        "tire"
    ],
    "wof:name":"Tire Warehouse Distribution",
    "wof:placetype":"venue"
},
  "geometry": {"coordinates":[-72.34873399999999,42.845302],"type":"Point"}
}