{
  "type": "Feature",
  "properties": {
    "iso:country":"US",
    "sg:address":"281 Baboosic Lake Rd",
    "sg:city":"Merrimack",
    "sg:classifiers":[
        {
            "category":"Building & Trades",
            "subcategory":"Construction",
            "type":"Services"
        }
    ],
    "sg:phone":"+1 603 424 9551",
    "sg:postcode":"03054",
    "sg:province":"NH",
    "sg:tags":[
        "excavation",
        "contractor"
    ],
    "wof:name":"M J F Excavation",
    "wof:placetype":"venue"
},
  "geometry": {"coordinates":[-71.566906,42.885299],"type":"Point"}
}