{
  "type": "Feature",
  "properties": {
    "addr:full":"1632 Main St Pittsburg NH 03574",
    "addr:housenumber":"1632",
    "addr:postcode":"03574",
    "addr:street":"Main St",
    "iso:country":"US",
    "sg:address":"1632 Main St",
    "sg:city":"Pittsburg",
    "sg:classifiers":[
        {
            "category":"Autos & Motor Vehicles",
            "subcategory":"Automobile Sales",
            "type":"Retail Goods"
        }
    ],
    "sg:phone":"+1 603 538 5001",
    "sg:postcode":"03574",
    "sg:province":"NH",
    "sg:tags":[
        "snowmobile"
    ],
    "wof:name":"Trailside Snowmobile Parts",
    "wof:placetype":"venue"
},
  "geometry": {"coordinates":[-71.698038,44.279627],"type":"Point"}
}