{
  "type": "Feature",
  "properties": {
    "iso:country":"US",
    "sg:address":"413 Cedar St",
    "sg:city":"Manchester",
    "sg:classifiers":[
        {
            "category":"Food & Beverages",
            "subcategory":"Bakery",
            "type":"Retail Goods"
        }
    ],
    "sg:phone":"+1 603 625 4987",
    "sg:postcode":"03103",
    "sg:province":"NH",
    "wof:name":"Thomas R Larochelle",
    "wof:placetype":"venue"
},
  "geometry": {"coordinates":[-71.45164800000001,42.98571],"type":"Point"}
}