{
  "type": "Feature",
  "properties": {
    "addr:full":"4 King George Dr Londonderry NH 03053",
    "addr:housenumber":"4",
    "addr:postcode":"03053",
    "addr:street":"King George Dr",
    "iso:country":"US",
    "sg:address":"4 King George Dr",
    "sg:city":"Londonderry",
    "sg:classifiers":[
        {
            "category":"Manufacturing",
            "subcategory":"Metals",
            "type":"Manufacturing & Wholesale Goods"
        }
    ],
    "sg:phone":"+1 603 434 8826",
    "sg:postcode":"03053",
    "sg:province":"NH",
    "sg:tags":[
        "plumbing",
        "represent",
        "industry",
        "heating",
        "mfg"
    ],
    "wof:name":"Acme Sales",
    "wof:placetype":"venue"
},
  "geometry": {"coordinates":[-71.364948,42.875255],"type":"Point"}
}