{
  "type": "Feature",
  "properties": {
    "iso:country":"US",
    "sg:address":"111 South St",
    "sg:city":"Claremont",
    "sg:classifiers":[
        {
            "category":"Education",
            "subcategory":"Junior College",
            "type":"Public Place"
        }
    ],
    "sg:phone":"+1 603 543 4291",
    "sg:postcode":"03743",
    "sg:province":"NH",
    "sg:tags":[
        "technical",
        "institute"
    ],
    "wof:name":"Sugar River Vly Regl Technical",
    "wof:placetype":"venue"
},
  "geometry": {"coordinates":[-72.33145399999999,43.365261],"type":"Point"}
}