{
  "type": "Feature",
  "properties": {
    "iso:country":"US",
    "sg:address":"148 Concord St",
    "sg:city":"Manchester",
    "sg:classifiers":[
        {
            "category":"Education",
            "subcategory":"Junior College",
            "type":"Public Place"
        }
    ],
    "sg:phone":"+1 603 669 2731",
    "sg:postcode":"03104",
    "sg:province":"NH",
    "sg:tags":[
        "technical",
        "institute"
    ],
    "wof:name":"Manchester Institute Of Arts",
    "wof:placetype":"venue"
},
  "geometry": {"coordinates":[-71.458716,42.992814],"type":"Point"}
}