{
  "type": "Feature",
  "properties": {
    "iso:country":"US",
    "sg:address":"95 S River Rd",
    "sg:city":"Bedford",
    "sg:classifiers":[
        {
            "category":"Shopping",
            "subcategory":"Clothing, Apparel, & Fashions",
            "type":"Retail Goods"
        }
    ],
    "sg:phone":"+1 603 624 3832",
    "sg:postcode":"03110",
    "sg:province":"NH",
    "sg:tags":[
        "furnishing"
    ],
    "wof:name":"Bob's Stores",
    "wof:placetype":"venue"
},
  "geometry": {"coordinates":[-71.478641,42.956922],"type":"Point"}
}