{
  "type": "Feature",
  "properties": {
    "iso:country":"US",
    "sg:address":"36 Joseph Rd",
    "sg:city":"Salem",
    "sg:classifiers":[
        {
            "category":"Retail",
            "subcategory":"Repair Shop",
            "type":"Services"
        }
    ],
    "sg:phone":"+1 603 893 5984",
    "sg:postcode":"03079",
    "sg:province":"NH",
    "wof:name":"Tic-Toc Clock Shop",
    "wof:placetype":"venue"
},
  "geometry": {"coordinates":[-71.238086,42.788753],"type":"Point"}
}