{
  "type": "Feature",
  "properties": {
    "iso:country":"US",
    "sg:address":"101 Adams Hill Rd",
    "sg:city":"Greenville",
    "sg:classifiers":[
        {
            "category":"Autos & Motor Vehicles",
            "subcategory":"Fuel & Gas Station",
            "type":"Retail Goods"
        }
    ],
    "sg:phone":"+1 603 878 1470",
    "sg:postcode":"03048",
    "sg:province":"NH",
    "sg:tags":[
        "color",
        "pigment"
    ],
    "wof:name":"Approved Color",
    "wof:placetype":"venue"
},
  "geometry": {"coordinates":[-71.79472699999999,42.768396],"type":"Point"}
}