{
  "type": "Feature",
  "properties": {
    "iso:country":"US",
    "sg:address":"37 Calef Rd",
    "sg:city":"Auburn",
    "sg:classifiers":[
        {
            "category":"Professional",
            "subcategory":"Management & Consulting",
            "type":"Services"
        }
    ],
    "sg:phone":"+1 603 483 8912",
    "sg:postcode":"03032",
    "sg:province":"NH",
    "sg:tags":[
        "consultant"
    ],
    "wof:name":"Phelan Marketing Svc",
    "wof:placetype":"venue"
},
  "geometry": {"coordinates":[-71.32171200000001,42.969095],"type":"Point"}
}