{
  "type": "Feature",
  "properties": {
    "addr:full":"38 Elm St Milford NH 03055",
    "addr:housenumber":"38",
    "addr:postcode":"03055",
    "addr:street":"Elm St",
    "iso:country":"US",
    "sg:address":"38 Elm St",
    "sg:city":"Milford",
    "sg:classifiers":[
        {
            "category":"Food & Beverages",
            "subcategory":"Groceries & Convenience Stores",
            "type":"Retail Goods"
        }
    ],
    "sg:phone":"+1 603 673 5102",
    "sg:postcode":"03055",
    "sg:province":"NH",
    "wof:name":"Amhurst Mobile",
    "wof:placetype":"venue"
},
  "geometry": {"coordinates":[-71.654659,42.835219],"type":"Point"}
}