{
  "type": "Feature",
  "properties": {
    "addr:full":"2724 Main St North Conway NH 03860",
    "addr:housenumber":"2724",
    "addr:postcode":"03860",
    "addr:street":"Main St",
    "iso:country":"US",
    "sg:address":"2724 Main St",
    "sg:city":"North Conway",
    "sg:classifiers":[
        {
            "category":"Professional",
            "type":"Services"
        }
    ],
    "sg:phone":"+1 603 356 4747",
    "sg:postcode":"03860",
    "sg:province":"NH",
    "sg:tags":[
        "caterer"
    ],
    "wof:name":"Chef's Market of North Conway the",
    "wof:placetype":"venue"
},
  "geometry": {"coordinates":[-71.13001800000001,44.055481],"type":"Point"}
}