{
  "type": "Feature",
  "properties": {
    "iso:country":"US",
    "sg:address":"89 Bridge St",
    "sg:city":"Manchester",
    "sg:classifiers":[
        {
            "category":"Autos & Motor Vehicles",
            "subcategory":"Fuel & Gas Station",
            "type":"Retail Goods"
        }
    ],
    "sg:phone":"+1 603 627 4731",
    "sg:postcode":"03101",
    "sg:province":"NH",
    "sg:tags":[
        "oil"
    ],
    "sg:website":"www.hess.com",
    "wof:name":"Hess",
    "wof:placetype":"venue"
},
  "geometry": {"coordinates":[-71.45982600000001,42.995038],"type":"Point"}
}