{
  "type": "Feature",
  "properties": {
    "iso:country":"US",
    "sg:address":"150 Lafayette Rd",
    "sg:city":"Rye",
    "sg:classifiers":[
        {
            "category":"Shopping",
            "subcategory":"Computers & Home Electronics",
            "type":"Retail Goods"
        }
    ],
    "sg:phone":"+1 603 436 6373",
    "sg:postcode":"03870",
    "sg:province":"NH",
    "sg:tags":[
        "equipment",
        "dealer"
    ],
    "wof:name":"Personal Nerd",
    "wof:placetype":"venue"
},
  "geometry": {"coordinates":[-70.805317,43.009752],"type":"Point"}
}