{
  "type": "Feature",
  "properties": {
    "addr:full":"44 Cliff Rd Portsmouth NH 03801",
    "addr:housenumber":"44",
    "addr:postcode":"03801",
    "addr:street":"Cliff Rd",
    "iso:country":"US",
    "sg:address":"44 Cliff Rd",
    "sg:city":"Portsmouth",
    "sg:classifiers":[
        {
            "category":"Wholesale",
            "subcategory":"Home Furnishings",
            "type":"Manufacturing & Wholesale Goods"
        }
    ],
    "sg:phone":"+1 603 559 9775",
    "sg:postcode":"03801",
    "sg:province":"NH",
    "wof:name":"Voice of Clay",
    "wof:placetype":"venue"
},
  "geometry": {"coordinates":[-70.750856,43.057848],"type":"Point"}
}