{
  "type": "Feature",
  "properties": {
    "iso:country":"US",
    "sg:address":"187 Webster St",
    "sg:city":"Hudson",
    "sg:classifiers":[
        {
            "category":"Shopping",
            "type":"Retail Goods"
        }
    ],
    "sg:phone":"+1 603 889 3441",
    "sg:postcode":"03051",
    "sg:province":"NH",
    "sg:tags":[
        "merchandise"
    ],
    "wof:name":"D & G Country Store",
    "wof:placetype":"venue"
},
  "geometry": {"coordinates":[-71.452883,42.789461],"type":"Point"}
}