{
  "type": "Feature",
  "properties": {
    "addr:full":"128 Narrows Rd Center Barnstead NH 03225",
    "addr:housenumber":"128",
    "addr:postcode":"03225",
    "addr:street":"Narrows Rd",
    "iso:country":"US",
    "sg:address":"128 Narrows Rd",
    "sg:city":"Center Barnstead",
    "sg:classifiers":[
        {
            "category":"Home & Garden",
            "subcategory":"Garden Supply",
            "type":"Retail Goods"
        }
    ],
    "sg:phone":"+1 603 269 7769",
    "sg:postcode":"03225",
    "sg:province":"NH",
    "sg:tags":[
        "center"
    ],
    "wof:name":"Crary Waterfalls & Aquatic Nur",
    "wof:placetype":"venue"
},
  "geometry": {"coordinates":[-71.279701,43.376968],"type":"Point"}
}