{
  "type": "Feature",
  "properties": {
    "iso:country":"US",
    "sg:address":"26 Madbury Rd",
    "sg:city":"Durham",
    "sg:classifiers":[
        {
            "category":"Organizations",
            "subcategory":"Community Association",
            "type":"Services"
        }
    ],
    "sg:phone":"+1 603 868 9723",
    "sg:postcode":"03824",
    "sg:province":"NH",
    "sg:website":"www.sigmabeta.com",
    "wof:name":"Sigma Beta",
    "wof:placetype":"venue"
},
  "geometry": {"coordinates":[-70.925561,43.136493],"type":"Point"}
}