{
  "type": "Feature",
  "properties": {
    "iso:country":"US",
    "sg:address":"10 State Rte 101",
    "sg:city":"Peterborough",
    "sg:classifiers":[
        {
            "category":"Wholesale",
            "subcategory":"Durable Goods & Equipment",
            "type":"Manufacturing & Wholesale Goods"
        }
    ],
    "sg:phone":"+1 603 924 7211",
    "sg:postcode":"03458",
    "sg:province":"NH",
    "sg:tags":[
        "exporter"
    ],
    "wof:name":"Tri-Med Inc",
    "wof:placetype":"venue"
},
  "geometry": {"coordinates":[-71.950919,42.870284],"type":"Point"}
}