{
  "type": "Feature",
  "properties": {
    "iso:country":"US",
    "sg:address":"52 Hall St",
    "sg:city":"Concord",
    "sg:classifiers":[
        {
            "category":"Building & Trades",
            "subcategory":"Construction",
            "type":"Services"
        }
    ],
    "sg:phone":"+1 603 226 0212",
    "sg:postcode":"03301",
    "sg:province":"NH",
    "sg:tags":[
        "general",
        "contractor"
    ],
    "wof:name":"Gulf Brook Renovations",
    "wof:placetype":"venue"
},
  "geometry": {"coordinates":[-71.526186,43.18952],"type":"Point"}
}