{
  "type": "Feature",
  "properties": {
    "addr:full":"55 Park Ave Salem NH 03079",
    "addr:housenumber":"55",
    "addr:postcode":"03079",
    "addr:street":"Park Ave",
    "iso:country":"US",
    "sg:address":"55 Park Ave",
    "sg:city":"Salem",
    "sg:classifiers":[
        {
            "category":"Wholesale",
            "subcategory":"Auto Parts",
            "type":"Manufacturing & Wholesale Goods"
        }
    ],
    "sg:phone":"+1 603 893 4600",
    "sg:postcode":"03079",
    "sg:province":"NH",
    "sg:tags":[
        "used"
    ],
    "wof:name":"Green Point of Salem Inc",
    "wof:placetype":"venue"
},
  "geometry": {"coordinates":[-71.220189,42.77597],"type":"Point"}
}