{
  "type": "Feature",
  "properties": {
    "addr:full":"24 Granite St Lebanon NH 03766",
    "addr:housenumber":"24",
    "addr:postcode":"03766",
    "addr:street":"Granite St",
    "iso:country":"US",
    "sg:address":"24 Granite St",
    "sg:city":"Lebanon",
    "sg:classifiers":[
        {
            "category":"Retail",
            "subcategory":"Auto Repair",
            "type":"Services"
        }
    ],
    "sg:phone":"+1 603 352 0560",
    "sg:postcode":"03766",
    "sg:province":"NH",
    "sg:tags":[
        "general"
    ],
    "wof:name":"Paladin Automotive LLC",
    "wof:placetype":"venue"
},
  "geometry": {"coordinates":[-72.257532,43.642668],"type":"Point"}
}