{
  "type": "Feature",
  "properties": {
    "addr:full":"92 Court St Laconia NH 03246",
    "addr:housenumber":"92",
    "addr:postcode":"03246",
    "addr:street":"Court St",
    "iso:country":"US",
    "sg:address":"92 Court St",
    "sg:city":"Laconia",
    "sg:classifiers":[
        {
            "category":"Retail",
            "subcategory":"Auto Repair",
            "type":"Services"
        }
    ],
    "sg:phone":"+1 603 524 9833",
    "sg:postcode":"03246",
    "sg:province":"NH",
    "sg:tags":[
        "repairing",
        "automobile"
    ],
    "wof:name":"Fred Lamere's Svc Ctr",
    "wof:placetype":"venue"
},
  "geometry": {"coordinates":[-71.470128,43.524395],"type":"Point"}
}