{
  "type": "Feature",
  "properties": {
    "addr:full":"59 S Main St Newport NH 03773",
    "addr:housenumber":"59",
    "addr:postcode":"03773",
    "addr:street":"S Main St",
    "iso:country":"US",
    "sg:address":"59 S Main St",
    "sg:city":"Newport",
    "sg:classifiers":[
        {
            "category":"Government",
            "subcategory":"Police Station",
            "type":"Public Place"
        }
    ],
    "sg:phone":"+1 603 863 3232",
    "sg:postcode":"03773",
    "sg:province":"NH",
    "sg:tags":[
        "department",
        "protection"
    ],
    "wof:name":"Newport Police Department",
    "wof:placetype":"venue"
},
  "geometry": {"coordinates":[-72.17097,43.360918],"type":"Point"}
}