{
  "type": "Feature",
  "properties": {
    "iso:country":"US",
    "sg:address":"8 Reeds Mill Rd",
    "sg:city":"Newport",
    "sg:classifiers":[
        {
            "category":"Manufacturing",
            "subcategory":"Glass & Minerals",
            "type":"Manufacturing & Wholesale Goods"
        }
    ],
    "sg:phone":"+1 603 863 1000",
    "sg:postcode":"03773",
    "sg:province":"NH",
    "sg:tags":[
        "ready"
    ],
    "sg:website":"www.carrollconcrete.com",
    "wof:name":"Carroll Concrete Co",
    "wof:placetype":"venue"
},
  "geometry": {"coordinates":[-72.136239,43.409568],"type":"Point"}
}