{
  "type": "Feature",
  "properties": {
    "addr:full":"31 Old Nashua Rd Amherst NH 03031",
    "addr:housenumber":"31",
    "addr:postcode":"03031",
    "addr:street":"Old Nashua Rd",
    "iso:country":"US",
    "sg:address":"31 Old Nashua Rd",
    "sg:city":"Amherst",
    "sg:classifiers":[
        {
            "category":"Building & Trades",
            "subcategory":"Construction",
            "type":"Services"
        }
    ],
    "sg:phone":"+1 603 673 4886",
    "sg:postcode":"03031",
    "sg:province":"NH",
    "sg:tags":[
        "swimming",
        "designer",
        "dealer",
        "pool",
        "contractor"
    ],
    "wof:name":"A-2-Z Pools",
    "wof:placetype":"venue"
},
  "geometry": {"coordinates":[-71.593906,42.812606],"type":"Point"}
}