{
  "type": "Feature",
  "properties": {
    "addr:full":"20 Grove St Peterborough NH 03458",
    "addr:housenumber":"20",
    "addr:postcode":"03458",
    "addr:street":"Grove St",
    "iso:country":"US",
    "sg:address":"20 Grove St",
    "sg:city":"Peterborough",
    "sg:classifiers":[
        {
            "category":"Internet Cafe",
            "subcategory":"None",
            "type":"Food & Drink"
        },
        {
            "category":"Professional",
            "subcategory":"Art Services",
            "type":"Services"
        },
        {
            "category":"Professional",
            "subcategory":"Computer Services",
            "type":"Services"
        }
    ],
    "sg:phone":"+1 603 924 4084",
    "sg:postcode":"03458",
    "sg:province":"NH",
    "sg:tags":[
        "publisher",
        "product",
        "designer",
        "consultant",
        "isp",
        "system",
        "graphic",
        "provider",
        "developer",
        "software"
    ],
    "sg:website":"http://www.consensus-technology.com",
    "wof:name":"Consensus Technology",
    "wof:placetype":"venue"
},
  "geometry": {"coordinates":[-71.950699,42.87674],"type":"Point"}
}