{
  "type": "Feature",
  "properties": {
    "iso:country":"US",
    "sg:address":"28 Technology Way",
    "sg:city":"Nashua",
    "sg:classifiers":[
        {
            "category":"Professional",
            "subcategory":"Engineering",
            "type":"Services"
        }
    ],
    "sg:phone":"+1 603 883 1071",
    "sg:postcode":"03060",
    "sg:province":"NH",
    "sg:tags":[
        "consulting",
        "engineer"
    ],
    "wof:name":"Jump Start Manufacturing",
    "wof:placetype":"venue"
},
  "geometry": {"coordinates":[-71.474842,42.761741],"type":"Point"}
}