{
  "type": "Feature",
  "properties": {
    "addr:full":"2 Christine Dr Hudson NH 03051",
    "addr:housenumber":"2",
    "addr:postcode":"03051",
    "addr:street":"Christine Dr",
    "iso:country":"US",
    "sg:address":"2 Christine Dr",
    "sg:city":"Hudson",
    "sg:classifiers":[
        {
            "category":"Professional",
            "subcategory":"Computer Services",
            "type":"Services"
        }
    ],
    "sg:phone":"+1 603 595 0850",
    "sg:postcode":"03051",
    "sg:province":"NH",
    "sg:tags":[
        "consultant",
        "designer"
    ],
    "wof:name":"Computer Management Consultant",
    "wof:placetype":"venue"
},
  "geometry": {"coordinates":[-71.41340099999999,42.818762],"type":"Point"}
}