{
  "type": "Feature",
  "properties": {
    "iso:country":"US",
    "sg:address":"74 Jaffrey Rd",
    "sg:city":"Peterborough",
    "sg:classifiers":[
        {
            "category":"Autos & Motor Vehicles",
            "subcategory":"Auto Supplies",
            "type":"Retail Goods"
        }
    ],
    "sg:phone":"+1 603 924 4366",
    "sg:postcode":"03458",
    "sg:province":"NH",
    "sg:tags":[
        "tire"
    ],
    "wof:name":"Tires Unlimited",
    "wof:placetype":"venue"
},
  "geometry": {"coordinates":[-72.126007,42.793951],"type":"Point"}
}