{
  "type": "Feature",
  "properties": {
    "iso:country":"US",
    "sg:address":"8 Baileys Green",
    "sg:city":"Bedford",
    "sg:classifiers":[
        {
            "category":"Social Services",
            "subcategory":"Child Care",
            "type":"Services"
        }
    ],
    "sg:phone":"+1 603 488 2122",
    "sg:postcode":"03110",
    "sg:province":"NH",
    "sg:tags":[
        "day"
    ],
    "wof:name":"Pre Construction Service",
    "wof:placetype":"venue"
},
  "geometry": {"coordinates":[-71.49831,42.906165],"type":"Point"}
}