{
  "type": "Feature",
  "properties": {
    "iso:country":"US",
    "sg:address":"285 W Hollis St",
    "sg:city":"Nashua",
    "sg:classifiers":[
        {
            "category":"Real Estate",
            "subcategory":"Real Estate Agent",
            "type":"Services"
        }
    ],
    "sg:phone":"+1 603 594 4114",
    "sg:postcode":"03060",
    "sg:province":"NH",
    "wof:name":"Blackwood Properties",
    "wof:placetype":"venue"
},
  "geometry": {"coordinates":[-71.486407,42.750837],"type":"Point"}
}