{
  "type": "Feature",
  "properties": {
    "iso:country":"US",
    "sg:address":"17 Main St",
    "sg:city":"Temple",
    "sg:classifiers":[
        {
            "category":"Organizations",
            "subcategory":"Religious Organization",
            "type":"Services"
        }
    ],
    "sg:phone":"+1 603 878 4177",
    "sg:postcode":"03086",
    "sg:province":"NH",
    "sg:tags":[
        "church"
    ],
    "wof:name":"Congreational Church Of Temple",
    "wof:placetype":"venue"
},
  "geometry": {"coordinates":[-71.736868,42.842531],"type":"Point"}
}