{
  "type": "Feature",
  "properties": {
    "iso:country":"US",
    "sg:address":"65 State Rte 27",
    "sg:city":"Raymond",
    "sg:classifiers":[
        {
            "category":"Retail",
            "subcategory":"Auto Repair",
            "type":"Services"
        }
    ],
    "sg:phone":"+1 603 895 9284",
    "sg:postcode":"03077",
    "sg:province":"NH",
    "sg:tags":[
        "repairing",
        "automobile"
    ],
    "wof:name":"J & C Auto & Truck Repair",
    "wof:placetype":"venue"
},
  "geometry": {"coordinates":[-71.168419,43.040191],"type":"Point"}
}