{
  "type": "Feature",
  "properties": {
    "iso:country":"US",
    "sg:address":"21 Main St",
    "sg:city":"New Durham",
    "sg:classifiers":[
        {
            "category":"Building & Trades",
            "subcategory":"Electrical",
            "type":"Services"
        }
    ],
    "sg:phone":"+1 603 859 5631",
    "sg:postcode":"03855",
    "sg:province":"NH",
    "sg:tags":[
        "electric",
        "contractor"
    ],
    "sg:website":"www.rineselectric.com",
    "wof:name":"Rines Electric",
    "wof:placetype":"venue"
},
  "geometry": {"coordinates":[-71.165835,43.43588],"type":"Point"}
}