{
  "type": "Feature",
  "properties": {
    "iso:country":"US",
    "sg:address":"24 Canney Rd",
    "sg:city":"Durham",
    "sg:classifiers":[
        {
            "category":"Building & Trades",
            "subcategory":"Construction",
            "type":"Services"
        }
    ],
    "sg:phone":"+1 603 868 7462",
    "sg:postcode":"03824",
    "sg:province":"NH",
    "sg:tags":[
        "house"
    ],
    "wof:name":"Agora Fine Homes",
    "wof:placetype":"venue"
},
  "geometry": {"coordinates":[-70.912178,43.143922],"type":"Point"}
}