{
  "type": "Feature",
  "properties": {
    "addr:full":"322 Main St Marlborough NH 03455",
    "addr:housenumber":"322",
    "addr:postcode":"03455",
    "addr:street":"Main St",
    "iso:country":"US",
    "sg:address":"322 Main St",
    "sg:city":"Marlborough",
    "sg:classifiers":[
        {
            "category":"Shopping",
            "subcategory":"Gifts & Souvenirs",
            "type":"Retail Goods"
        }
    ],
    "sg:phone":"+1 603 876 4877",
    "sg:postcode":"03455",
    "sg:province":"NH",
    "wof:name":"Princess of Little Pleasures",
    "wof:placetype":"venue"
},
  "geometry": {"coordinates":[-72.19461,42.906455],"type":"Point"}
}