{
  "type": "Feature",
  "properties": {
    "iso:country":"US",
    "sg:address":"171 Middle St",
    "sg:city":"Portsmouth",
    "sg:classifiers":[
        {
            "category":"Professional",
            "subcategory":"Lawyer & Legal Services",
            "type":"Services"
        }
    ],
    "sg:phone":"+1 603 431 4271",
    "sg:postcode":"03801",
    "sg:province":"NH",
    "sg:tags":[
        "attorney",
        "criminal",
        "law"
    ],
    "sg:website":"http://www.starbranchlaw.com",
    "wof:name":"Jeffco Starbranch",
    "wof:placetype":"venue"
},
  "geometry": {"coordinates":[-70.761304,43.073354],"type":"Point"}
}