{
  "type": "Feature",
  "properties": {
    "iso:country":"US",
    "sg:address":"18 Lovewell St",
    "sg:city":"Nashua",
    "sg:classifiers":[
        {
            "category":"Building & Trades",
            "subcategory":"Construction",
            "type":"Services"
        }
    ],
    "sg:phone":"+1 603 883 2591",
    "sg:postcode":"03060",
    "sg:province":"NH",
    "sg:tags":[
        "house"
    ],
    "wof:name":"Richards Home Improvement",
    "wof:placetype":"venue"
},
  "geometry": {"coordinates":[-71.47091,42.751283],"type":"Point"}
}