{
  "type": "Feature",
  "properties": {
    "iso:country":"US",
    "sg:address":"15 Exeter Rd",
    "sg:city":"Kingston",
    "sg:classifiers":[
        {
            "category":"Professional",
            "subcategory":"Business Services",
            "type":"Services"
        }
    ],
    "sg:phone":"+1 603 642 8493",
    "sg:postcode":"03848",
    "sg:province":"NH",
    "sg:tags":[
        "recording",
        "studio"
    ],
    "wof:name":"Kingston Records & Talent",
    "wof:placetype":"venue"
},
  "geometry": {"coordinates":[-71.04814399999999,42.944175],"type":"Point"}
}