{
  "type": "Feature",
  "properties": {
    "addr:full":"103 Main St Atkinson NH 03811",
    "addr:housenumber":"103",
    "addr:postcode":"03811",
    "addr:street":"Main St",
    "iso:country":"US",
    "sg:address":"103 Main St",
    "sg:city":"Atkinson",
    "sg:classifiers":[
        {
            "category":"Building & Trades",
            "subcategory":"Construction",
            "type":"Services"
        }
    ],
    "sg:phone":"+1 603 362 4784",
    "sg:postcode":"03811",
    "sg:province":"NH",
    "sg:tags":[
        "house"
    ],
    "wof:name":"Linda Fredrickson",
    "wof:placetype":"venue"
},
  "geometry": {"coordinates":[-71.149404,42.836922],"type":"Point"}
}