{
  "type": "Feature",
  "properties": {
    "iso:country":"US",
    "sg:address":"305 Sandown Rd",
    "sg:city":"East Hampstead",
    "sg:classifiers":[
        {
            "category":"Food & Beverages",
            "subcategory":"Groceries & Convenience Stores",
            "type":"Retail Goods"
        }
    ],
    "sg:phone":"+1 603 329 0182",
    "sg:postcode":"03826",
    "sg:province":"NH",
    "sg:tags":[
        "grocer"
    ],
    "wof:name":"Hannaford",
    "wof:placetype":"venue"
},
  "geometry": {"coordinates":[-71.14333999999999,42.892682],"type":"Point"}
}