{
  "type": "Feature",
  "properties": {
    "iso:country":"US",
    "sg:address":"900 Elm St",
    "sg:city":"Manchester",
    "sg:classifiers":[
        {
            "category":"Organizations",
            "subcategory":"Community Association",
            "type":"Services"
        }
    ],
    "sg:phone":"+1 603 645 2666",
    "sg:postcode":"03101",
    "sg:province":"NH",
    "wof:name":"Telecompioneers",
    "wof:placetype":"venue"
},
  "geometry": {"coordinates":[-71.463103,42.990211],"type":"Point"}
}