{
  "type": "Feature",
  "properties": {
    "iso:country":"US",
    "sg:address":"28 French Rd",
    "sg:city":"Henniker",
    "sg:classifiers":[
        {
            "category":"Retail",
            "subcategory":"Portrait Studio",
            "type":"Services"
        }
    ],
    "sg:phone":"+1 603 428 8746",
    "sg:postcode":"03242",
    "sg:province":"NH",
    "sg:tags":[
        "identification",
        "card"
    ],
    "wof:name":"Safe Kids Identifications",
    "wof:placetype":"venue"
},
  "geometry": {"coordinates":[-71.779116,43.205513],"type":"Point"}
}