{
  "type": "Feature",
  "properties": {
    "addr:full":"10 Autumn Pond Park Greenland NH 03840",
    "addr:housenumber":"10",
    "addr:postcode":"03840",
    "addr:street":"Autumn Pond Park",
    "iso:country":"US",
    "sg:address":"10 Autumn Pond Park",
    "sg:city":"Greenland",
    "sg:classifiers":[
        {
            "category":"Building & Trades",
            "subcategory":"Electrical",
            "type":"Services"
        }
    ],
    "sg:phone":"+1 603 436 9860",
    "sg:postcode":"03840",
    "sg:province":"NH",
    "sg:tags":[
        "electric",
        "contractor"
    ],
    "wof:name":"Stalker Electric Inc",
    "wof:placetype":"venue"
},
  "geometry": {"coordinates":[-70.824844,43.040458],"type":"Point"}
}