{
  "type": "Feature",
  "properties": {
    "iso:country":"US",
    "sg:address":"174 Court St",
    "sg:city":"Laconia",
    "sg:classifiers":[
        {
            "category":"Real Estate",
            "subcategory":"Real Estate Agent",
            "type":"Services"
        }
    ],
    "sg:phone":"+1 603 524 4693",
    "sg:postcode":"03246",
    "sg:province":"NH",
    "wof:name":"R E Reed & Co",
    "wof:placetype":"venue"
},
  "geometry": {"coordinates":[-71.47292899999999,43.522376],"type":"Point"}
}