{
  "type": "Feature",
  "properties": {
    "addr:full":"725 Laconia Rd Tilton NH 03276",
    "addr:housenumber":"725",
    "addr:postcode":"03276",
    "addr:street":"Laconia Rd",
    "iso:country":"US",
    "sg:address":"725 Laconia Rd",
    "sg:city":"Tilton",
    "sg:classifiers":[
        {
            "category":"Travel",
            "subcategory":"Hotels & Motels",
            "type":"Entertainment"
        }
    ],
    "sg:phone":"+1 603 524 3248",
    "sg:postcode":"03276",
    "sg:province":"NH",
    "sg:tags":[
        "cottage",
        "cabin"
    ],
    "wof:name":"Anchorage On Lake Winnisquam",
    "wof:placetype":"venue"
},
  "geometry": {"coordinates":[-71.518433,43.498864],"type":"Point"}
}