{
  "type": "Feature",
  "properties": {
    "iso:country":"US",
    "sg:address":"42 Ely St",
    "sg:city":"Littleton",
    "sg:classifiers":[
        {
            "category":"Social Services",
            "subcategory":"Child Care",
            "type":"Services"
        }
    ],
    "sg:phone":"+1 603 444 2174",
    "sg:postcode":"03561",
    "sg:province":"NH",
    "sg:tags":[
        "day"
    ],
    "wof:name":"Margaret Hampson",
    "wof:placetype":"venue"
},
  "geometry": {"coordinates":[-71.749607,44.306981],"type":"Point"}
}