{
  "type": "Feature",
  "properties": {
    "iso:country":"US",
    "sg:address":"104 N State St",
    "sg:city":"Concord",
    "sg:classifiers":[
        {
            "category":"Professional",
            "subcategory":"Management & Consulting",
            "type":"Services"
        }
    ],
    "sg:phone":"+1 603 228 1178",
    "sg:postcode":"03301",
    "sg:province":"NH",
    "wof:name":"Alan W Summers",
    "wof:placetype":"venue"
},
  "geometry": {"coordinates":[-71.542633,43.213951],"type":"Point"}
}