{
  "type": "Feature",
  "properties": {
    "iso:country":"US",
    "sg:address":"1 Depot St",
    "sg:city":"Pittsfield",
    "sg:classifiers":[
        {
            "category":"Retail",
            "subcategory":"Self-service Laundry",
            "type":"Services"
        },
        {
            "category":"Food & Beverages",
            "subcategory":"Groceries & Convenience Stores",
            "type":"Retail Goods"
        }
    ],
    "sg:phone":"+1 603 435 6777",
    "sg:postcode":"03263",
    "sg:province":"NH",
    "sg:tags":[
        "coin"
    ],
    "wof:name":"Bell Brothers",
    "wof:placetype":"venue"
},
  "geometry": {"coordinates":[-71.326599,43.306],"type":"Point"}
}