{
  "type": "Feature",
  "properties": {
    "iso:country":"US",
    "sg:address":"863 Easton Rd",
    "sg:city":"Franconia",
    "sg:classifiers":[
        {
            "category":"Building & Trades",
            "subcategory":"Construction",
            "type":"Services"
        }
    ],
    "sg:phone":"+1 603 823 8032",
    "sg:postcode":"03580",
    "sg:province":"NH",
    "sg:tags":[
        "concrete",
        "contractor"
    ],
    "wof:name":"White Mountain Concrete Form",
    "wof:placetype":"venue"
},
  "geometry": {"coordinates":[-71.778126,44.157963],"type":"Point"}
}