{
  "type": "Feature",
  "properties": {
    "addr:full":"318 Knox Marsh Rd Madbury NH 03823",
    "addr:housenumber":"318",
    "addr:postcode":"03823",
    "addr:street":"Knox Marsh Rd",
    "iso:country":"US",
    "sg:address":"318 Knox Marsh Rd",
    "sg:city":"Madbury",
    "sg:classifiers":[
        {
            "category":"Personal",
            "type":"Services"
        }
    ],
    "sg:phone":"+1 603 742 2169",
    "sg:postcode":"03823",
    "sg:province":"NH",
    "sg:tags":[
        "consultant",
        "wedding"
    ],
    "sg:website":"www.elliottrose.com",
    "wof:name":"Elliott Rose Co-Madbury Inc",
    "wof:placetype":"venue"
},
  "geometry": {"coordinates":[-70.91320399999999,43.176663],"type":"Point"}
}