{
  "type": "Feature",
  "properties": {
    "iso:country":"US",
    "sg:address":"12 Lake Rd",
    "sg:city":"Concord",
    "sg:classifiers":[
        {
            "category":"Manufacturing",
            "subcategory":"Retail Goods",
            "type":"Manufacturing & Wholesale Goods"
        }
    ],
    "sg:phone":"+1 603 648 6614",
    "sg:postcode":"03303",
    "sg:province":"NH",
    "sg:tags":[
        "product",
        "mfg"
    ],
    "wof:name":"Simply Divine",
    "wof:placetype":"venue"
},
  "geometry": {"coordinates":[-71.747957,43.316921],"type":"Point"}
}