{
  "type": "Feature",
  "properties": {
    "iso:country":"US",
    "sg:address":"7 Emerald Dr",
    "sg:city":"Barrington",
    "sg:classifiers":[
        {
            "category":"Building & Trades",
            "subcategory":"Construction",
            "type":"Services"
        }
    ],
    "sg:phone":"+1 603 868 1992",
    "sg:postcode":"03825",
    "sg:province":"NH",
    "sg:tags":[
        "contractor"
    ],
    "wof:name":"Gary Womack Contractors",
    "wof:placetype":"venue"
},
  "geometry": {"coordinates":[-71.02076,43.151129],"type":"Point"}
}