{
  "type": "Feature",
  "properties": {
    "iso:country":"US",
    "sg:address":"62 Farmington Rd",
    "sg:city":"Nashua",
    "sg:classifiers":[
        {
            "category":"Professional",
            "type":"Services"
        }
    ],
    "sg:phone":"+1 603 888 1046",
    "sg:postcode":"03060",
    "sg:province":"NH",
    "sg:tags":[
        "establishment"
    ],
    "wof:name":"Wunnegen Enterprises Inc",
    "wof:placetype":"venue"
},
  "geometry": {"coordinates":[-71.440789,42.73807],"type":"Point"}
}