{
  "type": "Feature",
  "properties": {
    "iso:country":"US",
    "sg:address":"90 W Swanzey Rd",
    "sg:city":"East Swanzey",
    "sg:classifiers":[
        {
            "category":"Retail",
            "subcategory":"Auto Repair",
            "type":"Services"
        }
    ],
    "sg:phone":"+1 603 352 7665",
    "sg:postcode":"03446",
    "sg:province":"NH",
    "sg:tags":[
        "general"
    ],
    "wof:name":"Bobs Auto Service",
    "wof:placetype":"venue"
},
  "geometry": {"coordinates":[-72.298642,42.904843],"type":"Point"}
}