{
  "type": "Feature",
  "properties": {
    "iso:country":"US",
    "sg:address":"117 Perimeter Rd",
    "sg:city":"Nashua",
    "sg:classifiers":[
        {
            "category":"Professional",
            "subcategory":"Management & Consulting",
            "type":"Services"
        }
    ],
    "sg:phone":"+1 603 595 6655",
    "sg:postcode":"03063",
    "sg:province":"NH",
    "wof:name":"Kellogg Krivsky & Buttler Inc",
    "wof:placetype":"venue"
},
  "geometry": {"coordinates":[-71.522705,42.781956],"type":"Point"}
}