{
  "type": "Feature",
  "properties": {
    "addr:full":"29 Middle St Lancaster NH 03584",
    "addr:housenumber":"29",
    "addr:postcode":"03584",
    "addr:street":"Middle St",
    "iso:country":"US",
    "sg:address":"29 Middle St",
    "sg:city":"Lancaster",
    "sg:classifiers":[
        {
            "category":"Autos & Motor Vehicles",
            "subcategory":"Automobile Sales",
            "type":"Retail Goods"
        }
    ],
    "sg:phone":"+1 603 788 2311",
    "sg:postcode":"03584",
    "sg:province":"NH",
    "sg:tags":[
        "car",
        "dealer"
    ],
    "sg:website":"www.northcountrymotors.com",
    "wof:name":"North Country Ford Motor Sales",
    "wof:placetype":"venue"
},
  "geometry": {"coordinates":[-71.567148,44.488409],"type":"Point"}
}