{
  "type": "Feature",
  "properties": {
    "iso:country":"US",
    "sg:address":"85 Main St",
    "sg:city":"Plaistow",
    "sg:classifiers":[
        {
            "category":"Education",
            "subcategory":"Library",
            "type":"Public Place"
        }
    ],
    "sg:phone":"+1 603 382 6011",
    "sg:postcode":"03865",
    "sg:province":"NH",
    "wof:name":"Plaistow Public Library",
    "wof:placetype":"venue"
},
  "geometry": {"coordinates":[-71.09350499999999,42.829481],"type":"Point"}
}