{
  "type": "Feature",
  "properties": {
    "addr:full":"395 Main St Salem NH 03079",
    "addr:housenumber":"395",
    "addr:postcode":"03079",
    "addr:street":"Main St",
    "iso:country":"US",
    "sg:address":"395 Main St",
    "sg:city":"Salem",
    "sg:classifiers":[
        {
            "category":"Wholesale",
            "subcategory":"Electrical",
            "type":"Manufacturing & Wholesale Goods"
        }
    ],
    "sg:phone":"+1 603 894 9897",
    "sg:postcode":"03079",
    "sg:province":"NH",
    "sg:tags":[
        "electronics"
    ],
    "wof:name":"Progressive Power Products LLC",
    "wof:placetype":"venue"
},
  "geometry": {"coordinates":[-71.188588,42.793095],"type":"Point"}
}