{
  "type": "Feature",
  "properties": {
    "iso:country":"US",
    "sg:address":"984 White Mountain Hwy",
    "sg:city":"Conway",
    "sg:classifiers":[
        {
            "category":"Personal",
            "type":"Services"
        }
    ],
    "sg:phone":"+1 603 447 8878",
    "sg:postcode":"03818",
    "sg:province":"NH",
    "sg:tags":[
        "planning",
        "wedding"
    ],
    "wof:name":"Ruthie's Flower Shop",
    "wof:placetype":"venue"
},
  "geometry": {"coordinates":[-71.14422999999999,43.970076],"type":"Point"}
}