{
  "type": "Feature",
  "properties": {
    "iso:country":"US",
    "sg:address":"18 Holly Ln",
    "sg:city":"Milford",
    "sg:classifiers":[
        {
            "category":"Wholesale",
            "subcategory":"Groceries",
            "type":"Manufacturing & Wholesale Goods"
        }
    ],
    "sg:phone":"+1 603 672 4464",
    "sg:postcode":"03055",
    "sg:province":"NH",
    "sg:tags":[
        "food",
        "product"
    ],
    "wof:name":"Tri-State Malted Waffles",
    "wof:placetype":"venue"
},
  "geometry": {"coordinates":[-71.672472,42.834974],"type":"Point"}
}