{
  "type": "Feature",
  "properties": {
    "iso:country":"US",
    "sg:address":"910 Main St",
    "sg:city":"Contoocook",
    "sg:classifiers":[
        {
            "category":"Professional",
            "subcategory":"Lawyer & Legal Services",
            "type":"Services"
        }
    ],
    "sg:phone":"+1 603 746 4185",
    "sg:postcode":"03229",
    "sg:province":"NH",
    "sg:tags":[
        "attorney"
    ],
    "wof:name":"Charles E Dibble",
    "wof:placetype":"venue"
},
  "geometry": {"coordinates":[-71.71074400000001,43.221865],"type":"Point"}
}