{
  "type": "Feature",
  "properties": {
    "iso:country":"US",
    "sg:address":"201 State Rte 28",
    "sg:city":"Derry",
    "sg:classifiers":[
        {
            "category":"Building & Trades",
            "subcategory":"Construction",
            "type":"Services"
        }
    ],
    "sg:phone":"+1 603 434 3500",
    "sg:postcode":"03038",
    "sg:province":"NH",
    "sg:tags":[
        "paving",
        "contractor"
    ],
    "wof:name":"A Pittore Brothers Paving",
    "wof:placetype":"venue"
},
  "geometry": {"coordinates":[-71.284032,42.858958],"type":"Point"}
}