{
  "type": "Feature",
  "properties": {
    "iso:country":"US",
    "sg:address":"440 S Broadway",
    "sg:city":"Salem",
    "sg:classifiers":[
        {
            "category":"Retail",
            "subcategory":"Car Wash",
            "type":"Services"
        }
    ],
    "sg:phone":"+1 603 893 4444",
    "sg:postcode":"03079",
    "sg:province":"NH",
    "sg:tags":[
        "polishing",
        "washing"
    ],
    "wof:name":"Haffner's Car Wash",
    "wof:placetype":"venue"
},
  "geometry": {"coordinates":[-71.20067899999999,42.744534],"type":"Point"}
}