{
  "type": "Feature",
  "properties": {
    "iso:country":"US",
    "sg:address":"3 Academy St",
    "sg:city":"Colebrook",
    "sg:classifiers":[
        {
            "category":"Education",
            "subcategory":"School",
            "type":"Public Place"
        }
    ],
    "sg:phone":"+1 603 237 5571",
    "sg:postcode":"03576",
    "sg:province":"NH",
    "sg:tags":[
        "board"
    ],
    "wof:name":"Colel Brook Dist 7",
    "wof:placetype":"venue"
},
  "geometry": {"coordinates":[-71.495357,44.895472],"type":"Point"}
}