{
  "type": "Feature",
  "properties": {
    "iso:country":"US",
    "sg:address":"7 Greenleaf Woods Dr",
    "sg:city":"Portsmouth",
    "sg:classifiers":[
        {
            "category":"Freight",
            "type":"Transportation"
        },
        {
            "category":"Government",
            "subcategory":"Office",
            "type":"Public Place"
        }
    ],
    "sg:phone":"+1 603 427 1366",
    "sg:postcode":"03801",
    "sg:province":"NH",
    "sg:tags":[
        "dry",
        "distance",
        "product",
        "long",
        "trucking",
        "refrigerated",
        "authorities"
    ],
    "wof:name":"Gentry Transportation Services",
    "wof:placetype":"venue"
},
  "geometry": {"coordinates":[-70.77592199999999,43.054411],"type":"Point"}
}