{
  "type": "Feature",
  "properties": {
    "iso:country":"US",
    "sg:address":"893 Lafayette Rd",
    "sg:city":"Hampton",
    "sg:classifiers":[
        {
            "category":"Food & Beverages",
            "subcategory":"Candy",
            "type":"Retail Goods"
        }
    ],
    "sg:phone":"+1 603 926 3933",
    "sg:postcode":"03842",
    "sg:province":"NH",
    "sg:tags":[
        "confectionery"
    ],
    "wof:name":"Elements Of Taste",
    "wof:placetype":"venue"
},
  "geometry": {"coordinates":[-70.83348100000001,42.956774],"type":"Point"}
}