{
  "type": "Feature",
  "properties": {
    "iso:country":"US",
    "sg:address":"23 Goodrich Rd",
    "sg:city":"Wolfeboro",
    "sg:classifiers":[
        {
            "category":"Travel",
            "subcategory":"Hotels & Motels",
            "type":"Entertainment"
        },
        {
            "category":"Travel",
            "subcategory":"Bed & Breakfast",
            "type":"Entertainment"
        }
    ],
    "sg:phone":"+1 603 569 2204",
    "sg:postcode":"03894",
    "sg:province":"NH",
    "wof:name":"Alicia's of Wolfeboro",
    "wof:placetype":"venue"
},
  "geometry": {"coordinates":[-71.202904,43.579899],"type":"Point"}
}