{
  "type": "Feature",
  "properties": {
    "iso:country":"US",
    "sg:address":"50 Smith St",
    "sg:city":"Woodsville",
    "sg:classifiers":[
        {
            "category":"Restaurant",
            "type":"Food & Drink"
        }
    ],
    "sg:menulink":"http://www.allmenus.com/nh/haverhill/129626-subway/menu/",
    "sg:phone":"+1 603 747 2700",
    "sg:postcode":"03785",
    "sg:province":"NH",
    "sg:tags":[
        "american",
        "sandwich"
    ],
    "wof:name":"Subway",
    "wof:placetype":"venue"
},
  "geometry": {"coordinates":[-72.033672,44.14557],"type":"Point"}
}