{
  "type": "Feature",
  "properties": {
    "addr:full":"121 Water St Exeter NH 03833",
    "addr:housenumber":"121",
    "addr:postcode":"03833",
    "addr:street":"Water St",
    "iso:country":"US",
    "sg:address":"121 Water St",
    "sg:city":"Exeter",
    "sg:classifiers":[
        {
            "category":"Professional",
            "subcategory":"Management & Consulting",
            "type":"Services"
        }
    ],
    "sg:phone":"+1 603 772 8302",
    "sg:postcode":"03833",
    "sg:province":"NH",
    "sg:tags":[
        "business"
    ],
    "wof:name":"Joni Praded",
    "wof:placetype":"venue"
},
  "geometry": {"coordinates":[-70.947225,42.981561],"type":"Point"}
}