{
  "type": "Feature",
  "properties": {
    "iso:country":"US",
    "sg:address":"614 Laconia Rd",
    "sg:city":"Tilton",
    "sg:classifiers":[
        {
            "category":"Building & Trades",
            "subcategory":"Construction",
            "type":"Services"
        }
    ],
    "sg:phone":"+1 603 524 7152",
    "sg:postcode":"03276",
    "sg:province":"NH",
    "sg:tags":[
        "home",
        "improvement"
    ],
    "wof:name":"Granite State Home Improvement",
    "wof:placetype":"venue"
},
  "geometry": {"coordinates":[-71.529062,43.487289],"type":"Point"}
}