{
  "type": "Feature",
  "properties": {
    "iso:country":"US",
    "sg:address":"121 Eastside Rd",
    "sg:city":"North Woodstock",
    "sg:classifiers":[
        {
            "category":"Building & Trades",
            "subcategory":"Electrical",
            "type":"Services"
        }
    ],
    "sg:phone":"+1 603 745 4868",
    "sg:postcode":"03262",
    "sg:province":"NH",
    "sg:tags":[
        "electric",
        "contractor"
    ],
    "wof:name":"Sabourn Electric Inc",
    "wof:placetype":"venue"
},
  "geometry": {"coordinates":[-71.67709000000001,44.014487],"type":"Point"}
}