{
  "type": "Feature",
  "properties": {
    "addr:full":"49 W Main St Bradford NH 03221",
    "addr:housenumber":"49",
    "addr:postcode":"03221",
    "addr:street":"W Main St",
    "iso:country":"US",
    "sg:address":"49 W Main St",
    "sg:city":"Bradford",
    "sg:classifiers":[
        {
            "category":"Social Services",
            "subcategory":"Child Care",
            "type":"Services"
        }
    ],
    "sg:phone":"+1 603 938 5596",
    "sg:postcode":"03221",
    "sg:province":"NH",
    "sg:tags":[
        "day"
    ],
    "wof:name":"Marges Child Care",
    "wof:placetype":"venue"
},
  "geometry": {"coordinates":[-71.960904,43.269489],"type":"Point"}
}