{
  "type": "Feature",
  "properties": {
    "iso:country":"US",
    "sg:address":"70 Zachary Rd",
    "sg:city":"Manchester",
    "sg:classifiers":[
        {
            "category":"Wholesale",
            "subcategory":"Machinery & Supplies",
            "type":"Manufacturing & Wholesale Goods"
        }
    ],
    "sg:phone":"+1 603 627 6300",
    "sg:postcode":"03109",
    "sg:province":"NH",
    "sg:tags":[
        "industrial",
        "marine"
    ],
    "wof:name":"K L Jack & Co",
    "wof:placetype":"venue"
},
  "geometry": {"coordinates":[-71.404713,42.982624],"type":"Point"}
}