{
  "type": "Feature",
  "properties": {
    "iso:country":"US",
    "sg:address":"9 Trafalgar Sq",
    "sg:city":"Nashua",
    "sg:classifiers":[
        {
            "category":"Wholesale",
            "subcategory":"Computers",
            "type":"Manufacturing & Wholesale Goods"
        },
        {
            "category":"Professional",
            "subcategory":"Computer Services",
            "type":"Services"
        }
    ],
    "sg:phone":"+1 603 578 1870",
    "sg:postcode":"03063",
    "sg:province":"NH",
    "sg:tags":[
        "information",
        "recovery",
        "processing",
        "system",
        "equipment",
        "data",
        "retrieval"
    ],
    "sg:website":"http://www.hiawathaislandsoftware.net",
    "wof:name":"Hisoftware Inc",
    "wof:placetype":"venue"
},
  "geometry": {"coordinates":[-71.505234,42.787016],"type":"Point"}
}