{
  "type": "Feature",
  "properties": {
    "addr:full":"9 Gale Village Rd Newton NH 03858",
    "addr:housenumber":"9",
    "addr:postcode":"03858",
    "addr:street":"Gale Village Rd",
    "iso:country":"US",
    "sg:address":"9 Gale Village Rd",
    "sg:city":"Newton",
    "sg:classifiers":[
        {
            "category":"Shopping",
            "subcategory":"Bicycles & Sporting Goods",
            "type":"Retail Goods"
        }
    ],
    "sg:phone":"+1 603 382 2939",
    "sg:postcode":"03858",
    "sg:province":"NH",
    "wof:name":"Gilchrist Custom Firearms",
    "wof:placetype":"venue"
},
  "geometry": {"coordinates":[-71.02255599999999,42.889759],"type":"Point"}
}