{
  "type": "Feature",
  "properties": {
    "iso:country":"US",
    "sg:address":"750 Central Ave",
    "sg:city":"Dover",
    "sg:classifiers":[
        {
            "category":"Health Services",
            "subcategory":"Doctor",
            "type":"Services"
        }
    ],
    "sg:phone":"+1 603 742 6030",
    "sg:postcode":"03820",
    "sg:province":"NH",
    "sg:tags":[
        "physician",
        "surgeon"
    ],
    "wof:name":"Atlantic Family Practice",
    "wof:placetype":"venue"
},
  "geometry": {"coordinates":[-70.874959,43.209622],"type":"Point"}
}