{
  "type": "Feature",
  "properties": {
    "iso:country":"US",
    "sg:address":"20 Jackson St",
    "sg:city":"Rochester",
    "sg:classifiers":[
        {
            "category":"Building & Trades",
            "subcategory":"Electrical",
            "type":"Services"
        }
    ],
    "sg:phone":"+1 603 335 1182",
    "sg:postcode":"03867",
    "sg:province":"NH",
    "sg:tags":[
        "electric",
        "contractor"
    ],
    "wof:name":"Vaughan Electric",
    "wof:placetype":"venue"
},
  "geometry": {"coordinates":[-70.984639,43.304131],"type":"Point"}
}