{
  "type": "Feature",
  "properties": {
    "addr:full":"112 Grandview Dr Weare NH 03281",
    "addr:housenumber":"112",
    "addr:postcode":"03281",
    "addr:street":"Grandview Dr",
    "iso:country":"US",
    "sg:address":"112 Grandview Dr",
    "sg:city":"Weare",
    "sg:classifiers":[
        {
            "category":"Building & Trades",
            "subcategory":"Construction",
            "type":"Services"
        }
    ],
    "sg:phone":"+1 603 529 1258",
    "sg:postcode":"03281",
    "sg:province":"NH",
    "sg:tags":[
        "excavation",
        "contractor"
    ],
    "wof:name":"Townes Excavating Corporation",
    "wof:placetype":"venue"
},
  "geometry": {"coordinates":[-71.75513599999999,43.109846],"type":"Point"}
}