{
  "type": "Feature",
  "properties": {
    "iso:country":"US",
    "sg:address":"69 Mercier Ave",
    "sg:city":"Manchester",
    "sg:classifiers":[
        {
            "category":"Personal",
            "subcategory":"Beauty Salon",
            "type":"Services"
        }
    ],
    "sg:phone":"+1 603 627 2043",
    "sg:postcode":"03102",
    "sg:province":"NH",
    "sg:tags":[
        "shop"
    ],
    "wof:name":"Lady Dis Unisex Salon",
    "wof:placetype":"venue"
},
  "geometry": {"coordinates":[-71.49200500000001,42.994065],"type":"Point"}
}