{
  "type": "Feature",
  "properties": {
    "iso:country":"US",
    "sg:address":"17 Signal St",
    "sg:city":"Rochester",
    "sg:classifiers":[
        {
            "category":"Home & Garden",
            "subcategory":"Garden Supply",
            "type":"Retail Goods"
        }
    ],
    "sg:phone":"+1 603 335 1597",
    "sg:postcode":"03867",
    "sg:province":"NH",
    "sg:tags":[
        "lawn",
        "mower"
    ],
    "wof:name":"Colbath Equipment Inc",
    "wof:placetype":"venue"
},
  "geometry": {"coordinates":[-70.974074,43.306802],"type":"Point"}
}