{
  "type": "Feature",
  "properties": {
    "iso:country":"US",
    "sg:address":"245 Hooksett Rd ",
    "sg:city":"Manchester",
    "sg:classifiers":[
        {
            "category":"Restaurant",
            "type":"Food & Drink"
        }
    ],
    "sg:menulink":"http://www.allmenus.com/nh/manchester/39831-puritan-backroom/menu/",
    "sg:phone":"+1 603 669 6890",
    "sg:postcode":"03104",
    "sg:province":"NH",
    "sg:tags":[
        "american"
    ],
    "wof:name":"Puritan Backroom",
    "wof:placetype":"venue"
},
  "geometry": {"coordinates":[-71.454414,43.010682],"type":"Point"}
}