{
  "type": "Feature",
  "properties": {
    "iso:country":"US",
    "sg:address":"191 Lafayette Rd",
    "sg:city":"Seabrook",
    "sg:classifiers":[
        {
            "category":"Building & Trades",
            "subcategory":"Equipment Rental",
            "type":"Services"
        }
    ],
    "sg:phone":"+1 603 474 5742",
    "sg:postcode":"03874",
    "sg:province":"NH",
    "sg:tags":[
        "yard"
    ],
    "wof:name":"Syvinski's Seacoast Equipment",
    "wof:placetype":"venue"
},
  "geometry": {"coordinates":[-70.868008,42.879676],"type":"Point"}
}