{
  "type": "Feature",
  "properties": {
    "iso:country":"US",
    "sg:address":"92 Cluff Crossing Rd Ste 3",
    "sg:city":"Salem",
    "sg:classifiers":[
        {
            "category":"Shopping",
            "subcategory":"Pets & Pet Supplies",
            "type":"Retail Goods"
        },
        {
            "category":"Retail",
            "subcategory":"Animal Services",
            "type":"Services"
        },
        {
            "category":"Museum",
            "subcategory":"Aquarium",
            "type":"Entertainment"
        }
    ],
    "sg:phone":"+1 603 890 6922",
    "sg:postcode":"03079",
    "sg:province":"NH",
    "sg:tags":[
        "food",
        "dog",
        "cat",
        "furnishing",
        "grooming",
        "store"
    ],
    "sg:website":"http://www.petco.com",
    "wof:name":"PETCO",
    "wof:placetype":"venue"
},
  "geometry": {"coordinates":[-71.218468,42.765331],"type":"Point"}
}