{
  "type": "Feature",
  "properties": {
    "addr:full":"132 Titus Ave Manchester NH 03103",
    "addr:housenumber":"132",
    "addr:postcode":"03103",
    "addr:street":"Titus Ave",
    "iso:country":"US",
    "sg:address":"132 Titus Ave",
    "sg:city":"Manchester",
    "sg:classifiers":[
        {
            "category":"Social Services",
            "type":"Services"
        }
    ],
    "sg:phone":"+1 603 668 5423",
    "sg:postcode":"03103",
    "sg:province":"NH",
    "sg:tags":[
        "organization",
        "welfare"
    ],
    "sg:website":"www.moorecenter.org",
    "wof:name":"Moore Center Svc Inc",
    "wof:placetype":"venue"
},
  "geometry": {"coordinates":[-71.457864,42.9608],"type":"Point"}
}