{
  "type": "Feature",
  "properties": {
    "addr:full":"652 Lafayette Rd Hampton NH 03842",
    "addr:housenumber":"652",
    "addr:postcode":"03842",
    "iso:country":"US",
    "sg:address":"652 Lafayette Rd",
    "sg:city":"Hampton",
    "sg:classifiers":[
        {
            "category":"Recreation",
            "type":"Entertainment"
        }
    ],
    "sg:phone":"+1 603 929 0303",
    "sg:postcode":"03842",
    "sg:province":"NH",
    "sg:tags":[
        "instruction",
        "yoga"
    ],
    "wof:name":"Institute For Personal Dev Inc",
    "wof:placetype":"venue"
},
  "geometry": {"coordinates":[-70.833608,42.945728],"type":"Point"}
}