{
  "type": "Feature",
  "properties": {
    "addr:full":"45 Joliet St Laconia NH 03246",
    "addr:housenumber":"45",
    "addr:postcode":"03246",
    "addr:street":"Joliet St",
    "iso:country":"US",
    "sg:address":"45 Joliet St",
    "sg:city":"Laconia",
    "sg:classifiers":[
        {
            "category":"Manufacturing",
            "subcategory":"Tools & Machinery",
            "type":"Manufacturing & Wholesale Goods"
        }
    ],
    "sg:phone":"+1 603 528 8058",
    "sg:postcode":"03246",
    "sg:province":"NH",
    "sg:tags":[
        "woodworking",
        "mfg"
    ],
    "wof:name":"Granite State Woodworks",
    "wof:placetype":"venue"
},
  "geometry": {"coordinates":[-71.465418,43.521673],"type":"Point"}
}