{
  "type": "Feature",
  "properties": {
    "addr:full":"134 Main St West Lebanon NH 03784",
    "addr:housenumber":"134",
    "addr:postcode":"03784",
    "addr:street":"Main St",
    "iso:country":"US",
    "sg:address":"134 Main St",
    "sg:city":"West Lebanon",
    "sg:classifiers":[
        {
            "category":"Retail",
            "subcategory":"Auto Repair",
            "type":"Services"
        }
    ],
    "sg:phone":"+1 603 298 5019",
    "sg:postcode":"03784",
    "sg:province":"NH",
    "sg:tags":[
        "lubricating"
    ],
    "sg:website":"www.jiffylube.com",
    "wof:name":"Jiffy Lube",
    "wof:placetype":"venue"
},
  "geometry": {"coordinates":[-72.310057,43.651835],"type":"Point"}
}