{
  "type": "Feature",
  "properties": {
    "addr:full":"1811 Hopkinton Rd Contoocook NH 03229",
    "addr:housenumber":"1811",
    "addr:postcode":"03229",
    "addr:street":"Hopkinton Rd",
    "iso:country":"US",
    "sg:address":"1811 Hopkinton Rd",
    "sg:city":"Contoocook",
    "sg:classifiers":[
        {
            "category":"Building & Trades",
            "subcategory":"Construction",
            "type":"Services"
        }
    ],
    "sg:phone":"+1 603 746 5851",
    "sg:postcode":"03229",
    "sg:province":"NH",
    "sg:tags":[
        "contractor"
    ],
    "wof:name":"Romeo R Dubreuil Builder",
    "wof:placetype":"venue"
},
  "geometry": {"coordinates":[-71.680904,43.197965],"type":"Point"}
}