{
  "type": "Feature",
  "properties": {
    "addr:full":"269 Pinewood Rd Allenstown NH 03275",
    "addr:housenumber":"269",
    "addr:postcode":"03275",
    "addr:street":"Pinewood Rd",
    "iso:country":"US",
    "sg:address":"269 Pinewood Rd",
    "sg:city":"Allenstown",
    "sg:classifiers":[
        {
            "category":"Shopping",
            "subcategory":"Used Merchandise",
            "type":"Retail Goods"
        }
    ],
    "sg:phone":"+1 603 485 9611",
    "sg:postcode":"03275",
    "sg:province":"NH",
    "sg:tags":[
        "furniture"
    ],
    "wof:name":"D Art's Town Line Consignment",
    "wof:placetype":"venue"
},
  "geometry": {"coordinates":[-71.406339,43.152726],"type":"Point"}
}