{
  "type": "Feature",
  "properties": {
    "iso:country":"US",
    "sg:address":"36 Endicott St E",
    "sg:city":"Laconia",
    "sg:classifiers":[
        {
            "category":"Professional",
            "subcategory":"Management & Consulting",
            "type":"Services"
        }
    ],
    "sg:phone":"+1 603 366 5403",
    "sg:postcode":"03246",
    "sg:province":"NH",
    "sg:tags":[
        "fuel"
    ],
    "wof:name":"Moore Food Management",
    "wof:placetype":"venue"
},
  "geometry": {"coordinates":[-71.454853,43.603426],"type":"Point"}
}