{
  "type": "Feature",
  "properties": {
    "iso:country":"US",
    "sg:address":"117 W Milan Rd",
    "sg:city":"Berlin",
    "sg:classifiers":[
        {
            "category":"Food & Beverages",
            "subcategory":"Groceries & Convenience Stores",
            "type":"Retail Goods"
        }
    ],
    "sg:phone":"+1 603 752 6691",
    "sg:postcode":"03570",
    "sg:province":"NH",
    "sg:tags":[
        "oil"
    ],
    "wof:name":"Community Co Op Oil",
    "wof:placetype":"venue"
},
  "geometry": {"coordinates":[-71.248926,44.518419],"type":"Point"}
}