{
  "type": "Feature",
  "properties": {
    "iso:country":"US",
    "sg:address":"1367 Union Ave",
    "sg:city":"Laconia",
    "sg:classifiers":[
        {
            "category":"Restaurant",
            "type":"Food & Drink"
        }
    ],
    "sg:phone":"+1 603 527 9111",
    "sg:postcode":"03246",
    "sg:province":"NH",
    "sg:tags":[
        "delicatessen"
    ],
    "wof:name":"Jon's Roast Beef & Deli",
    "wof:placetype":"venue"
},
  "geometry": {"coordinates":[-71.44956999999999,43.562458],"type":"Point"}
}