{
  "type": "Feature",
  "properties": {
    "iso:country":"US",
    "sg:address":"34 Church St",
    "sg:city":"Kingston",
    "sg:classifiers":[
        {
            "category":"Restaurant",
            "type":"Food & Drink"
        }
    ],
    "sg:phone":"+1 603 642 3777",
    "sg:postcode":"03848",
    "sg:province":"NH",
    "wof:name":"Fremont Pizzeria II",
    "wof:placetype":"venue"
},
  "geometry": {"coordinates":[-71.057408,42.943045],"type":"Point"}
}