{
  "type": "Feature",
  "properties": {
    "iso:country":"US",
    "sg:address":"8 Beaudoin St",
    "sg:city":"Bedford",
    "sg:classifiers":[
        {
            "category":"Building & Trades",
            "subcategory":"Landscaping Services",
            "type":"Services"
        }
    ],
    "sg:phone":"+1 603 645 6199",
    "sg:postcode":"03110",
    "sg:province":"NH",
    "sg:tags":[
        "repair"
    ],
    "wof:name":"Yard Machine",
    "wof:placetype":"venue"
},
  "geometry": {"coordinates":[-71.477262,42.961789],"type":"Point"}
}