{
  "type": "Feature",
  "properties": {
    "iso:country":"US",
    "sg:address":"49 Mount Delight Rd",
    "sg:city":"Epsom",
    "sg:classifiers":[
        {
            "category":"Manufacturing",
            "subcategory":"Lumber",
            "type":"Manufacturing & Wholesale Goods"
        }
    ],
    "sg:phone":"+1 603 736 8099",
    "sg:postcode":"03234",
    "sg:province":"NH",
    "sg:tags":[
        "logging"
    ],
    "wof:name":"Birons Logging",
    "wof:placetype":"venue"
},
  "geometry": {"coordinates":[-71.333015,43.173043],"type":"Point"}
}