{
  "type": "Feature",
  "properties": {
    "iso:country":"US",
    "sg:address":"250 S Main St",
    "sg:city":"Laconia",
    "sg:classifiers":[
        {
            "category":"Restaurant",
            "type":"Food & Drink"
        }
    ],
    "sg:phone":"+1 603 536 2260",
    "sg:postcode":"03246",
    "sg:province":"NH",
    "sg:tags":[
        "drinking",
        "eating"
    ],
    "wof:name":"Bier Haus",
    "wof:placetype":"venue"
},
  "geometry": {"coordinates":[-71.464889,43.519278],"type":"Point"}
}