{
  "type": "Feature",
  "properties": {
    "addr:full":"30 Birch Ln Pelham NH 03076",
    "addr:housenumber":"30",
    "addr:postcode":"03076",
    "addr:street":"Birch Ln",
    "iso:country":"US",
    "sg:address":"30 Birch Ln",
    "sg:city":"Pelham",
    "sg:classifiers":[
        {
            "category":"Retail",
            "subcategory":"Repair Shop",
            "type":"Services"
        }
    ],
    "sg:phone":"+1 603 635 3000",
    "sg:postcode":"03076",
    "sg:province":"NH",
    "sg:tags":[
        "cleaners",
        "parts",
        "vacuum"
    ],
    "wof:name":"Drac Vax Vacuums & Supplies",
    "wof:placetype":"venue"
},
  "geometry": {"coordinates":[-71.300359,42.714008],"type":"Point"}
}