{
  "type": "Feature",
  "properties": {
    "iso:country":"US",
    "sg:address":"189 Elm St",
    "sg:city":"Milford",
    "sg:classifiers":[
        {
            "category":"Building & Trades",
            "subcategory":"Equipment Rental",
            "type":"Services"
        }
    ],
    "sg:phone":"+1 603 672 6948",
    "sg:postcode":"03055",
    "sg:province":"NH",
    "sg:tags":[
        "leasing",
        "furniture"
    ],
    "wof:name":"Rent-One-Plus",
    "wof:placetype":"venue"
},
  "geometry": {"coordinates":[-71.650155,42.835189],"type":"Point"}
}