{
  "type": "Feature",
  "properties": {
    "iso:country":"US",
    "sg:address":"800 Turnpike Rd",
    "sg:city":"New Ipswich",
    "sg:classifiers":[
        {
            "category":"Wholesale",
            "subcategory":"Construction Materials",
            "type":"Manufacturing & Wholesale Goods"
        }
    ],
    "sg:phone":"+1 603 878 3385",
    "sg:postcode":"03071",
    "sg:province":"NH",
    "sg:tags":[
        "mobile",
        "home"
    ],
    "wof:name":"Karen Carnivale Real Estate",
    "wof:placetype":"venue"
},
  "geometry": {"coordinates":[-71.875034,42.760651],"type":"Point"}
}