{
  "type": "Feature",
  "properties": {
    "iso:country":"US",
    "sg:address":"501 Islington St",
    "sg:city":"Portsmouth",
    "sg:classifiers":[
        {
            "category":"Insurance",
            "subcategory":"Insurance Agent",
            "type":"Services"
        }
    ],
    "sg:phone":"+1 603 226 3517",
    "sg:postcode":"03801",
    "sg:province":"NH",
    "wof:name":"Chittenden Insurance Group",
    "wof:placetype":"venue"
},
  "geometry": {"coordinates":[-70.769786,43.071766],"type":"Point"}
}