{
  "type": "Feature",
  "properties": {
    "iso:country":"US",
    "sg:address":"20 Elm St",
    "sg:city":"Wolfeboro",
    "sg:classifiers":[
        {
            "category":"Personal",
            "subcategory":"Beauty Salon",
            "type":"Services"
        }
    ],
    "sg:phone":"+1 603 569 1446",
    "sg:postcode":"03894",
    "sg:province":"NH",
    "wof:name":"Idle-Hour Beauty Shop",
    "wof:placetype":"venue"
},
  "geometry": {"coordinates":[-71.204635,43.592646],"type":"Point"}
}