{
  "type": "Feature",
  "properties": {
    "iso:country":"US",
    "sg:address":"204 Dartmouth College Rd",
    "sg:city":"Lyme",
    "sg:classifiers":[
        {
            "category":"Health Services",
            "subcategory":"Health Practitioner",
            "type":"Services"
        }
    ],
    "sg:phone":"+1 603 795 2509",
    "sg:postcode":"03779",
    "sg:province":"NH",
    "sg:tags":[
        "psychotherapist"
    ],
    "wof:name":"Mindbody Psychotherapy Assoc",
    "wof:placetype":"venue"
},
  "geometry": {"coordinates":[-72.078934,43.971989],"type":"Point"}
}