{
  "type": "Feature",
  "properties": {
    "iso:country":"US",
    "sg:address":"22 Brian St",
    "sg:city":"Sandown",
    "sg:classifiers":[
        {
            "category":"Food & Beverages",
            "subcategory":"Candy",
            "type":"Retail Goods"
        }
    ],
    "sg:phone":"+1 603 887 2473",
    "sg:postcode":"03873",
    "sg:province":"NH",
    "wof:name":"Tim Richards",
    "wof:placetype":"venue"
},
  "geometry": {"coordinates":[-71.21369300000001,42.958735],"type":"Point"}
}