{
  "type": "Feature",
  "properties": {
    "iso:country":"US",
    "sg:address":"96 Portsmouth Ave",
    "sg:city":"Exeter",
    "sg:classifiers":[
        {
            "category":"Retail",
            "subcategory":"Auto Repair",
            "type":"Services"
        }
    ],
    "sg:phone":"+1 603 772 9274",
    "sg:postcode":"03833",
    "sg:province":"NH",
    "sg:tags":[
        "automotive"
    ],
    "wof:name":"Kerners Quick Lube Detail Ctr",
    "wof:placetype":"venue"
},
  "geometry": {"coordinates":[-70.93365799999999,42.988319],"type":"Point"}
}