{
  "type": "Feature",
  "properties": {
    "addr:full":"21 Victoria Ct Keene NH 03431",
    "addr:housenumber":"21",
    "addr:postcode":"03431",
    "addr:street":"Victoria Ct",
    "iso:country":"US",
    "sg:address":"21 Victoria Ct",
    "sg:city":"Keene",
    "sg:classifiers":[
        {
            "category":"Wholesale",
            "subcategory":"Hardware",
            "type":"Manufacturing & Wholesale Goods"
        }
    ],
    "sg:phone":"+1 603 357 0350",
    "sg:postcode":"03431",
    "sg:province":"NH",
    "sg:tags":[
        "plumbing",
        "fixture",
        "supply"
    ],
    "sg:website":"www.thegranitegroup.com",
    "wof:name":"Granite Group",
    "wof:placetype":"venue"
},
  "geometry": {"coordinates":[-72.26608299999999,42.92916],"type":"Point"}
}