{
  "type": "Feature",
  "properties": {
    "iso:country":"US",
    "sg:address":"401 Wilson St",
    "sg:city":"Manchester",
    "sg:classifiers":[
        {
            "category":"Social Services",
            "type":"Services"
        }
    ],
    "sg:phone":"+1 603 669 3499",
    "sg:postcode":"03103",
    "sg:province":"NH",
    "sg:tags":[
        "organization",
        "welfare"
    ],
    "wof:name":"YMCA-You Wilson",
    "wof:placetype":"venue"
},
  "geometry": {"coordinates":[-71.44821899999999,42.985786],"type":"Point"}
}