{
  "type": "Feature",
  "properties": {
    "addr:full":"126 Daniel St Portsmouth NH 03801",
    "addr:housenumber":"126",
    "addr:postcode":"03801",
    "addr:street":"Daniel St",
    "iso:country":"US",
    "sg:address":"126 Daniel St",
    "sg:city":"Portsmouth",
    "sg:classifiers":[
        {
            "category":"Building & Trades",
            "subcategory":"Construction",
            "type":"Services"
        }
    ],
    "sg:phone":"+1 603 436 1054",
    "sg:postcode":"03801",
    "sg:province":"NH",
    "sg:tags":[
        "industrial",
        "designer"
    ],
    "wof:name":"Daniel Richard Design",
    "wof:placetype":"venue"
},
  "geometry": {"coordinates":[-70.755201,43.077691],"type":"Point"}
}