{
  "type": "Feature",
  "properties": {
    "iso:country":"US",
    "sg:address":"35 Newton Junction Rd",
    "sg:city":"Kingston",
    "sg:classifiers":[
        {
            "category":"Government",
            "subcategory":"Office",
            "type":"Public Place"
        }
    ],
    "sg:phone":"+1 603 382 8014",
    "sg:postcode":"03848",
    "sg:province":"NH",
    "wof:name":"New Hampshire Maintenance Dept",
    "wof:placetype":"venue"
},
  "geometry": {"coordinates":[-71.07312,42.873726],"type":"Point"}
}