{
  "type": "Feature",
  "properties": {
    "iso:country":"US",
    "sg:address":"118 Portsmouth Ave",
    "sg:city":"Stratham",
    "sg:classifiers":[
        {
            "category":"Health Services",
            "subcategory":"Health Practitioner",
            "type":"Services"
        }
    ],
    "sg:phone":"+1 603 772 8222",
    "sg:postcode":"03885",
    "sg:province":"NH",
    "sg:tags":[
        "therapist",
        "physical"
    ],
    "wof:name":"Stratham Physical Therapy",
    "wof:placetype":"venue"
},
  "geometry": {"coordinates":[-70.916507,43.017753],"type":"Point"}
}