{
  "type": "Feature",
  "properties": {
    "addr:full":"16 Pond Rd Derry NH 03038",
    "addr:housenumber":"16",
    "addr:postcode":"03038",
    "addr:street":"Pond Rd",
    "iso:country":"US",
    "sg:address":"16 Pond Rd",
    "sg:city":"Derry",
    "sg:classifiers":[
        {
            "category":"Arts & Performance",
            "subcategory":"Theater",
            "type":"Entertainment"
        }
    ],
    "sg:phone":"+1 603 432 4414",
    "sg:postcode":"03038",
    "sg:province":"NH",
    "sg:tags":[
        "group"
    ],
    "wof:name":"Bob Riordan Magic & Comedy",
    "wof:placetype":"venue"
},
  "geometry": {"coordinates":[-71.297038,42.897191],"type":"Point"}
}