{
  "type": "Feature",
  "properties": {
    "iso:country":"US",
    "sg:address":"11 Gauthier Dr",
    "sg:city":"Pelham",
    "sg:classifiers":[
        {
            "category":"Professional",
            "subcategory":"Computer Services",
            "type":"Services"
        }
    ],
    "sg:phone":"+1 603 635 2992",
    "sg:postcode":"03054",
    "sg:province":"NH",
    "sg:tags":[
        "related"
    ],
    "wof:name":"Mirror Image",
    "wof:placetype":"venue"
},
  "geometry": {"coordinates":[-71.54621400000001,42.829089],"type":"Point"}
}