{
  "type": "Feature",
  "properties": {
    "iso:country":"US",
    "sg:address":"16 Main St",
    "sg:city":"Gilsum",
    "sg:classifiers":[
        {
            "category":"Professional",
            "subcategory":"Business Services",
            "type":"Services"
        }
    ],
    "sg:phone":"+1 603 355 2242",
    "sg:postcode":"03448",
    "sg:province":"NH",
    "wof:name":"Village Auctions",
    "wof:placetype":"venue"
},
  "geometry": {"coordinates":[-72.263515,43.047892],"type":"Point"}
}