{
  "type": "Feature",
  "properties": {
    "addr:full":"12 Amesbury Rd Newton NH 03858",
    "addr:housenumber":"12",
    "addr:postcode":"03858",
    "addr:street":"Amesbury Rd",
    "iso:country":"US",
    "sg:address":"12 Amesbury Rd",
    "sg:city":"Newton",
    "sg:classifiers":[
        {
            "category":"Place Of Worship",
            "type":"Public Place"
        }
    ],
    "sg:phone":"+1 603 382 6566",
    "sg:postcode":"03858",
    "sg:province":"NH",
    "sg:tags":[
        "church"
    ],
    "sg:website":"http://www.diopitt.org",
    "wof:name":"Mary Mother Of The Church",
    "wof:placetype":"venue"
},
  "geometry": {"coordinates":[-71.021629,42.87286],"type":"Point"}
}