{
  "type": "Feature",
  "properties": {
    "iso:country":"US",
    "sg:address":"379 State St",
    "sg:city":"Portsmouth",
    "sg:classifiers":[
        {
            "category":"Insurance",
            "subcategory":"Insurance Agent",
            "type":"Services"
        }
    ],
    "sg:phone":"+1 603 427 1932",
    "sg:postcode":"03801",
    "sg:province":"NH",
    "wof:name":"National Life Insurance Co",
    "wof:placetype":"venue"
},
  "geometry": {"coordinates":[-70.760291,43.074948],"type":"Point"}
}