{
  "type": "Feature",
  "properties": {
    "iso:country":"US",
    "sg:address":"15 Roby Rd",
    "sg:city":"New Boston",
    "sg:classifiers":[
        {
            "category":"Building & Trades",
            "subcategory":"Construction",
            "type":"Services"
        }
    ],
    "sg:phone":"+1 603 487 3081",
    "sg:postcode":"03070",
    "sg:province":"NH",
    "sg:tags":[
        "contractor"
    ],
    "wof:name":"Allen Masonry 15 Ro",
    "wof:placetype":"venue"
},
  "geometry": {"coordinates":[-71.621923,42.974641],"type":"Point"}
}