{
  "type": "Feature",
  "properties": {
    "iso:country":"US",
    "sg:address":"2 Garfield St",
    "sg:city":"Farmington",
    "sg:classifiers":[
        {
            "category":"Utilities",
            "subcategory":"Refuse",
            "type":"Services"
        }
    ],
    "sg:phone":"+1 603 755 2762",
    "sg:postcode":"03835",
    "sg:province":"NH",
    "sg:tags":[
        "system"
    ],
    "wof:name":"New Direction Recycling",
    "wof:placetype":"venue"
},
  "geometry": {"coordinates":[-71.061459,43.389811],"type":"Point"}
}