{
  "type": "Feature",
  "properties": {
    "iso:country":"US",
    "sg:address":"6 Forest St",
    "sg:city":"Derry",
    "sg:classifiers":[
        {
            "category":"Building & Trades",
            "subcategory":"Construction",
            "type":"Services"
        }
    ],
    "sg:phone":"+1 603 434 8383",
    "sg:postcode":"03038",
    "sg:province":"NH",
    "sg:tags":[
        "general",
        "contractor"
    ],
    "wof:name":"Jim Ferrante Building Contr",
    "wof:placetype":"venue"
},
  "geometry": {"coordinates":[-71.33745999999999,42.927382],"type":"Point"}
}