{
  "type": "Feature",
  "properties": {
    "addr:full":"38 Highland Dr Henniker NH 03242",
    "addr:housenumber":"38",
    "addr:postcode":"03242",
    "addr:street":"Highland Dr",
    "iso:country":"US",
    "sg:address":"38 Highland Dr",
    "sg:city":"Henniker",
    "sg:classifiers":[
        {
            "category":"Professional",
            "subcategory":"Management & Consulting",
            "type":"Services"
        }
    ],
    "sg:phone":"+1 603 428 3651",
    "sg:postcode":"03242",
    "sg:province":"NH",
    "sg:tags":[
        "business"
    ],
    "wof:name":"Compettive Dynamics Consulting",
    "wof:placetype":"venue"
},
  "geometry": {"coordinates":[-71.761358,43.185496],"type":"Point"}
}