{
  "type": "Feature",
  "properties": {
    "addr:full":"1 Middle St Salem NH 03079",
    "addr:housenumber":"1",
    "addr:postcode":"03079",
    "addr:street":"Middle St",
    "iso:country":"US",
    "sg:address":"1 Middle St",
    "sg:city":"Salem",
    "sg:classifiers":[
        {
            "category":"Building & Trades",
            "subcategory":"Plumbing",
            "type":"Services"
        }
    ],
    "sg:phone":"+1 603 894 5817",
    "sg:postcode":"03079",
    "sg:province":"NH",
    "sg:tags":[
        "plumbing",
        "contractor"
    ],
    "wof:name":"Rudy's Plumbing & Heating",
    "wof:placetype":"venue"
},
  "geometry": {"coordinates":[-71.23036999999999,42.781302],"type":"Point"}
}