{
  "type": "Feature",
  "properties": {
    "addr:full":"217 Ragged Mountain Club Rd Andover NH 03216",
    "addr:housenumber":"217",
    "addr:postcode":"03216",
    "addr:street":"Ragged;Club Rd",
    "iso:country":"US",
    "sg:address":"217 Ragged Mountain Club Rd",
    "sg:city":"Andover",
    "sg:classifiers":[
        {
            "category":"Organizations",
            "subcategory":"Professional Association",
            "type":"Services"
        }
    ],
    "sg:phone":"+1 603 735 5361",
    "sg:postcode":"03216",
    "sg:province":"NH",
    "wof:name":"Ragged Mountain Fish & Game",
    "wof:placetype":"venue"
},
  "geometry": {"coordinates":[-71.85319800000001,43.45198],"type":"Point"}
}