{
  "type": "Feature",
  "properties": {
    "iso:country":"US",
    "sg:address":"53 Silver St",
    "sg:city":"Dover",
    "sg:classifiers":[
        {
            "category":"Building & Trades",
            "subcategory":"Construction",
            "type":"Services"
        }
    ],
    "sg:phone":"+1 603 742 4454",
    "sg:postcode":"03820",
    "sg:province":"NH",
    "sg:tags":[
        "contractor"
    ],
    "wof:name":"All-Pro Roofing",
    "wof:placetype":"venue"
},
  "geometry": {"coordinates":[-70.87568400000001,43.190415],"type":"Point"}
}