{
  "type": "Feature",
  "properties": {
    "addr:full":"13 Chase Island Atkinson NH 03811",
    "addr:housenumber":"13",
    "addr:postcode":"03811",
    "addr:street":"Chase Island",
    "iso:country":"US",
    "sg:address":"13 Chase Island",
    "sg:city":"Atkinson",
    "sg:classifiers":[
        {
            "category":"Professional",
            "type":"Services"
        }
    ],
    "sg:phone":"+1 603 898 0570",
    "sg:postcode":"03811",
    "sg:province":"NH",
    "sg:tags":[
        "establishment"
    ],
    "wof:name":"Engineered System Solutions",
    "wof:placetype":"venue"
},
  "geometry": {"coordinates":[-71.203338,42.86151],"type":"Point"}
}