{
  "type": "Feature",
  "properties": {
    "addr:full":"62 March Ave Manchester NH 03103",
    "addr:housenumber":"62",
    "addr:postcode":"03103",
    "addr:street":"March Ave",
    "iso:country":"US",
    "sg:address":"62 March Ave",
    "sg:city":"Manchester",
    "sg:classifiers":[
        {
            "category":"Shopping",
            "subcategory":"Gifts & Souvenirs",
            "type":"Retail Goods"
        }
    ],
    "sg:phone":"+1 603 668 5665",
    "sg:postcode":"03103",
    "sg:province":"NH",
    "sg:tags":[
        "shop"
    ],
    "wof:name":"John's Hallmark Shop",
    "wof:placetype":"venue"
},
  "geometry": {"coordinates":[-71.441661,42.962779],"type":"Point"}
}