{
  "type": "Feature",
  "properties": {
    "addr:full":"220 Derry Rd Hudson NH 03051",
    "addr:housenumber":"220",
    "addr:postcode":"03051",
    "addr:street":"Derry Rd",
    "iso:country":"US",
    "sg:address":"220 Derry Rd",
    "sg:city":"Hudson",
    "sg:classifiers":[
        {
            "category":"Building & Trades",
            "subcategory":"Construction",
            "type":"Services"
        }
    ],
    "sg:phone":"+1 603 883 8783",
    "sg:postcode":"03051",
    "sg:province":"NH",
    "sg:tags":[
        "general",
        "contractor"
    ],
    "wof:name":"Lee Jenna Homes Inc",
    "wof:placetype":"venue"
},
  "geometry": {"coordinates":[-71.433211,42.799561],"type":"Point"}
}