{
  "type": "Feature",
  "properties": {
    "iso:country":"US",
    "sg:address":"9 Partridge Ln",
    "sg:city":"Derry",
    "sg:classifiers":[
        {
            "category":"Professional",
            "subcategory":"Business Services",
            "type":"Services"
        }
    ],
    "sg:phone":"+1 603 432 2188",
    "sg:postcode":"03038",
    "sg:province":"NH",
    "sg:tags":[
        "broker",
        "merchandise"
    ],
    "wof:name":"John Morgan Assoc",
    "wof:placetype":"venue"
},
  "geometry": {"coordinates":[-71.26594,42.909716],"type":"Point"}
}