{
  "type": "Feature",
  "properties": {
    "addr:full":"628 Daniel Webster Hwy Merrimack NH 03054",
    "addr:housenumber":"628",
    "addr:postcode":"03054",
    "addr:street":"Daniel Webster Hwy",
    "iso:country":"US",
    "sg:address":"628 Daniel Webster Hwy",
    "sg:city":"Merrimack",
    "sg:classifiers":[
        {
            "category":"Social Services",
            "subcategory":"Child Care",
            "type":"Services"
        }
    ],
    "sg:phone":"+1 603 424 6000",
    "sg:postcode":"03054",
    "sg:province":"NH",
    "sg:tags":[
        "day"
    ],
    "wof:name":"Kids Inn Early Running Center",
    "wof:placetype":"venue"
},
  "geometry": {"coordinates":[-71.474802,42.887481],"type":"Point"}
}