{
  "type": "Feature",
  "properties": {
    "iso:country":"US",
    "sg:address":"25 S River Rd",
    "sg:city":"Bedford",
    "sg:classifiers":[
        {
            "category":"Health Services",
            "subcategory":"Doctor",
            "type":"Services"
        }
    ],
    "sg:phone":"+1 603 626 4392",
    "sg:postcode":"03110",
    "sg:province":"NH",
    "sg:tags":[
        "physician",
        "medical",
        "surgeon"
    ],
    "wof:name":"Family Practice Assoc Bedford",
    "wof:placetype":"venue"
},
  "geometry": {"coordinates":[-71.480146,42.963048],"type":"Point"}
}