{
  "type": "Feature",
  "properties": {
    "iso:country":"US",
    "sg:address":"274 Foster Pond Rd",
    "sg:city":"Bristol",
    "sg:classifiers":[
        {
            "category":"Building & Trades",
            "subcategory":"Landscaping Services",
            "type":"Services"
        }
    ],
    "sg:phone":"+1 603 744 3208",
    "sg:postcode":"03222",
    "sg:province":"NH",
    "wof:name":"R & R Homers Tree Service",
    "wof:placetype":"venue"
},
  "geometry": {"coordinates":[-71.784054,43.583126],"type":"Point"}
}