{
  "type": "Feature",
  "properties": {
    "iso:country":"US",
    "sg:address":"4 Country Club Rd",
    "sg:city":"Gilford",
    "sg:classifiers":[
        {
            "category":"Government",
            "subcategory":"Post Office",
            "type":"Public Place"
        }
    ],
    "sg:phone":"+1 603 524 7257",
    "sg:postcode":"03249",
    "sg:province":"NH",
    "wof:name":"US Post Office",
    "wof:placetype":"venue"
},
  "geometry": {"coordinates":[-71.440355,43.529415],"type":"Point"}
}