{
  "type": "Feature",
  "properties": {
    "iso:country":"US",
    "sg:address":"273 S Broadway",
    "sg:city":"Salem",
    "sg:classifiers":[
        {
            "category":"Real Estate",
            "subcategory":"Real Estate Agent",
            "type":"Services"
        }
    ],
    "sg:phone":"+1 603 890 0110",
    "sg:postcode":"03079",
    "sg:province":"NH",
    "wof:name":"Real Estate Specialists",
    "wof:placetype":"venue"
},
  "geometry": {"coordinates":[-71.210646,42.756595],"type":"Point"}
}