{
  "type": "Feature",
  "properties": {
    "iso:country":"US",
    "sg:address":"295 Old County Rd",
    "sg:city":"Haverhill",
    "sg:classifiers":[
        {
            "category":"Building & Trades",
            "subcategory":"Construction",
            "type":"Services"
        }
    ],
    "sg:phone":"+1 603 989 5170",
    "sg:postcode":"03781",
    "sg:province":"NH",
    "sg:tags":[
        "home",
        "improvement"
    ],
    "wof:name":"Haverhill Home Improvement",
    "wof:placetype":"venue"
},
  "geometry": {"coordinates":[-72.33506300000001,43.579405],"type":"Point"}
}