{
  "type": "Feature",
  "properties": {
    "iso:country":"US",
    "sg:address":"70 Palomino Ln",
    "sg:city":"Bedford",
    "sg:classifiers":[
        {
            "category":"Professional",
            "type":"Services"
        }
    ],
    "sg:phone":"+1 603 644 5673",
    "sg:postcode":"03110",
    "sg:province":"NH",
    "wof:name":"Jeff Beland",
    "wof:placetype":"venue"
},
  "geometry": {"coordinates":[-71.48312199999999,42.961055],"type":"Point"}
}