{
  "type": "Feature",
  "properties": {
    "iso:country":"US",
    "sg:address":"206 North St",
    "sg:city":"Manchester",
    "sg:classifiers":[
        {
            "category":"Education",
            "subcategory":"School",
            "type":"Public Place"
        }
    ],
    "sg:phone":"+1 603 622 1711",
    "sg:postcode":"03104",
    "sg:province":"NH",
    "wof:name":"St Catherine School",
    "wof:placetype":"venue"
},
  "geometry": {"coordinates":[-71.453024,43.005858],"type":"Point"}
}