{
  "type": "Feature",
  "properties": {
    "iso:country":"US",
    "sg:address":"1 Thornton Ferry Road I",
    "sg:city":"Amherst",
    "sg:classifiers":[
        {
            "category":"Building & Trades",
            "subcategory":"Plumbing",
            "type":"Services"
        }
    ],
    "sg:phone":"+1 603 672 2400",
    "sg:postcode":"03031",
    "sg:province":"NH",
    "sg:tags":[
        "contractor"
    ],
    "wof:name":"J T Art & Frame",
    "wof:placetype":"venue"
},
  "geometry": {"coordinates":[-71.616146,42.858883],"type":"Point"}
}