{
  "type": "Feature",
  "properties": {
    "iso:country":"US",
    "sg:address":"320 Blevens Dr",
    "sg:city":"Manchester",
    "sg:classifiers":[
        {
            "category":"Real Estate",
            "subcategory":"Real Estate Operator",
            "type":"Services"
        }
    ],
    "sg:phone":"+1 603 626 5984",
    "sg:postcode":"03104",
    "sg:province":"NH",
    "sg:tags":[
        "building",
        "apartment"
    ],
    "wof:name":"Raybar LLC",
    "wof:placetype":"venue"
},
  "geometry": {"coordinates":[-71.441418,43.016585],"type":"Point"}
}