{
  "type": "Feature",
  "properties": {
    "iso:country":"US",
    "sg:address":"183 Mill St",
    "sg:city":"Center Conway",
    "sg:classifiers":[
        {
            "category":"Education",
            "subcategory":"School",
            "type":"Public Place"
        }
    ],
    "sg:phone":"+1 603 356 7800",
    "sg:postcode":"03813",
    "sg:province":"NH",
    "wof:name":"Conway School District",
    "wof:placetype":"venue"
},
  "geometry": {"coordinates":[-71.057051,43.991895],"type":"Point"}
}