{
  "type": "Feature",
  "properties": {
    "addr:full":"2 Commerce Dr Bedford NH 03110",
    "addr:housenumber":"2",
    "addr:postcode":"03110",
    "addr:street":"Commerce Dr",
    "iso:country":"US",
    "sg:address":"2 Commerce Dr",
    "sg:city":"Bedford",
    "sg:classifiers":[
        {
            "category":"Manufacturing",
            "subcategory":"Tools & Machinery",
            "type":"Manufacturing & Wholesale Goods"
        },
        {
            "category":"Professional",
            "subcategory":"Computer Services",
            "type":"Services"
        }
    ],
    "sg:phone":"+1 603 669 3330",
    "sg:postcode":"03110",
    "sg:province":"NH",
    "sg:tags":[
        "po",
        "sales"
    ],
    "sg:website":"www.netspos.com",
    "wof:name":"Nets Electronics Inc",
    "wof:placetype":"venue"
},
  "geometry": {"coordinates":[-71.461175,42.925079],"type":"Point"}
}