{
  "type": "Feature",
  "properties": {
    "iso:country":"US",
    "sg:address":"49 Kinsley St",
    "sg:city":"Nashua",
    "sg:classifiers":[
        {
            "category":"Shopping",
            "subcategory":"Hobbies, Toys, & Games",
            "type":"Retail Goods"
        }
    ],
    "sg:phone":"+1 603 594 0521",
    "sg:postcode":"03060",
    "sg:province":"NH",
    "sg:tags":[
        "model",
        "supply"
    ],
    "wof:name":"Wizard's Tower",
    "wof:placetype":"venue"
},
  "geometry": {"coordinates":[-71.46790799999999,42.754833],"type":"Point"}
}