{
  "type": "Feature",
  "properties": {
    "iso:country":"US",
    "sg:address":"29 Lil Nor Ave",
    "sg:city":"Somersworth",
    "sg:classifiers":[
        {
            "category":"Social Services",
            "subcategory":"Child Care",
            "type":"Services"
        }
    ],
    "sg:phone":"+1 603 692 4706",
    "sg:postcode":"03878",
    "sg:province":"ME",
    "sg:tags":[
        "kindergarten",
        "academic",
        "school"
    ],
    "wof:name":"Little Folks Kindergarten",
    "wof:placetype":"venue"
},
  "geometry": {"coordinates":[-70.885719,43.257211],"type":"Point"}
}