{
  "type": "Feature",
  "properties": {
    "iso:country":"US",
    "sg:address":"117 Main St",
    "sg:city":"Lincoln",
    "sg:classifiers":[
        {
            "category":"Restaurant",
            "type":"Food & Drink"
        }
    ],
    "sg:phone":"+1 603 745 4395",
    "sg:postcode":"03251",
    "sg:province":"NH",
    "wof:name":"Gypsy Cafe",
    "wof:placetype":"venue"
},
  "geometry": {"coordinates":[-71.667794,44.044913],"type":"Point"}
}