{
  "type": "Feature",
  "properties": {
    "iso:country":"US",
    "sg:address":"379 Amherst St",
    "sg:city":"Nashua",
    "sg:classifiers":[
        {
            "category":"Professional",
            "subcategory":"Advertising",
            "type":"Services"
        }
    ],
    "sg:phone":"+1 603 882 6245",
    "sg:postcode":"03063",
    "sg:province":"NH",
    "sg:tags":[
        "mailing",
        "shipping"
    ],
    "wof:name":"Postal Center USA",
    "wof:placetype":"venue"
},
  "geometry": {"coordinates":[-71.508342,42.784891],"type":"Point"}
}