{
  "type": "Feature",
  "properties": {
    "iso:country":"US",
    "sg:address":"353 Central Ave",
    "sg:city":"Dover",
    "sg:classifiers":[
        {
            "category":"Banks & Credit Unions",
            "subcategory":"Bank",
            "type":"Services"
        }
    ],
    "sg:phone":"+1 603 740 8025",
    "sg:postcode":"03820",
    "sg:province":"NH",
    "sg:website":"www.banknh.com",
    "wof:name":"Bank Of New Hampshire",
    "wof:placetype":"venue"
},
  "geometry": {"coordinates":[-70.874477,43.195157],"type":"Point"}
}