{
  "type": "Feature",
  "properties": {
    "addr:full":"42 W River Rd Hooksett NH 03106",
    "addr:housenumber":"42",
    "addr:postcode":"03106",
    "addr:street":"W River Rd",
    "iso:country":"US",
    "sg:address":"42 W River Rd",
    "sg:city":"Hooksett",
    "sg:classifiers":[
        {
            "category":"Manufacturing",
            "subcategory":"Tools & Machinery",
            "type":"Manufacturing & Wholesale Goods"
        }
    ],
    "sg:phone":"+1 603 625 5900",
    "sg:postcode":"03106",
    "sg:province":"NH",
    "sg:tags":[
        "wheel",
        "aligning",
        "measuring",
        "devices"
    ],
    "wof:name":"Wheelamatic LLC",
    "wof:placetype":"venue"
},
  "geometry": {"coordinates":[-71.46956299999999,43.04072],"type":"Point"}
}