{
  "type": "Feature",
  "properties": {
    "addr:full":"288 State Rte 101 Bedford NH 03110",
    "addr:housenumber":"288",
    "addr:postcode":"03110",
    "addr:street":"State Rte 101",
    "iso:country":"US",
    "sg:address":"288 State Rte 101",
    "sg:city":"Bedford",
    "sg:classifiers":[
        {
            "category":"Real Estate",
            "subcategory":"Real Estate Agent",
            "type":"Services"
        }
    ],
    "sg:phone":"+1 603 472 4400",
    "sg:postcode":"03110",
    "sg:province":"NH",
    "sg:website":"www.c21shakra.com",
    "wof:name":"Shakra Realty Group",
    "wof:placetype":"venue"
},
  "geometry": {"coordinates":[-71.533108,42.928102],"type":"Point"}
}