{
  "type": "Feature",
  "properties": {
    "iso:country":"US",
    "sg:address":"545 Hooksett Rd",
    "sg:city":"Manchester",
    "sg:classifiers":[
        {
            "category":"Personal",
            "subcategory":"Tanning Parlor",
            "type":"Services"
        }
    ],
    "sg:phone":"+1 603 641 0098",
    "sg:postcode":"03104",
    "sg:province":"NH",
    "sg:tags":[
        "salon"
    ],
    "wof:name":"Suntana",
    "wof:placetype":"venue"
},
  "geometry": {"coordinates":[-71.45288600000001,43.012705],"type":"Point"}
}