{
  "type": "Feature",
  "properties": {
    "iso:country":"US",
    "sg:address":"62 Colin Rd",
    "sg:city":"Manchester",
    "sg:classifiers":[
        {
            "category":"Wholesale",
            "subcategory":"Electrical",
            "type":"Manufacturing & Wholesale Goods"
        }
    ],
    "sg:phone":"+1 603 624 9090",
    "sg:postcode":"03103",
    "sg:province":"NH",
    "sg:tags":[
        "equipment"
    ],
    "wof:name":"Sentry Battery Corp",
    "wof:placetype":"venue"
},
  "geometry": {"coordinates":[-71.425597,42.937497],"type":"Point"}
}