{
  "type": "Feature",
  "properties": {
    "addr:full":"5 Commerce Way Barrington NH 03833",
    "addr:housenumber":"5",
    "addr:postcode":"03833",
    "addr:street":"Commerce Way",
    "iso:country":"US",
    "sg:address":"5 Commerce Way",
    "sg:city":"Barrington",
    "sg:classifiers":[
        {
            "category":"Wholesale",
            "subcategory":"Groceries",
            "type":"Manufacturing & Wholesale Goods"
        }
    ],
    "sg:phone":"+1 603 664 5656",
    "sg:postcode":"03833",
    "sg:province":"NH",
    "sg:tags":[
        "food",
        "product"
    ],
    "sg:website":"www.associatedbuyers.com",
    "wof:name":"Associated Buyers",
    "wof:placetype":"venue"
},
  "geometry": {"coordinates":[-70.964899,42.994275],"type":"Point"}
}