{
  "type": "Feature",
  "properties": {
    "iso:country":"US",
    "sg:address":"121 Railroad St",
    "sg:city":"Keene",
    "sg:classifiers":[
        {
            "category":"Organizations",
            "subcategory":"Non-profit Organization",
            "type":"Services"
        },
        {
            "category":"Social Services",
            "type":"Services"
        }
    ],
    "sg:phone":"+1 603 352 1304",
    "sg:postcode":"03431",
    "sg:province":"NH",
    "sg:tags":[
        "to",
        "agency",
        "human",
        "providing"
    ],
    "sg:website":"www.mds-nh.org",
    "wof:name":"Monadnock Developmental Svcs",
    "wof:placetype":"venue"
},
  "geometry": {"coordinates":[-72.27377799999999,42.932345],"type":"Point"}
}