{
  "type": "Feature",
  "properties": {
    "iso:country":"US",
    "sg:address":"38 Main St",
    "sg:city":"Conway",
    "sg:classifiers":[
        {
            "category":"Shopping",
            "subcategory":"Jewelry",
            "type":"Retail Goods"
        }
    ],
    "sg:phone":"+1 603 447 3723",
    "sg:postcode":"03818",
    "sg:province":"NH",
    "wof:name":"Lonestar Jewelers",
    "wof:placetype":"venue"
},
  "geometry": {"coordinates":[-71.120002,43.978539],"type":"Point"}
}