{
  "type": "Feature",
  "properties": {
    "iso:country":"US",
    "sg:address":"455 South Rd",
    "sg:city":"Newbury",
    "sg:classifiers":[
        {
            "category":"Building & Trades",
            "subcategory":"Construction",
            "type":"Services"
        }
    ],
    "sg:phone":"+1 603 938 2248",
    "sg:postcode":"03255",
    "sg:province":"NH",
    "sg:tags":[
        "house"
    ],
    "wof:name":"Paddock Construction Co Inc",
    "wof:placetype":"venue"
},
  "geometry": {"coordinates":[-72.01406299999999,43.267187],"type":"Point"}
}