{
  "type": "Feature",
  "properties": {
    "addr:full":"25 Park St Concord NH 03301",
    "addr:housenumber":"25",
    "addr:postcode":"03301",
    "addr:street":"Park St",
    "iso:country":"US",
    "sg:address":"25 Park St",
    "sg:city":"Concord",
    "sg:classifiers":[
        {
            "category":"Organizations",
            "subcategory":"Professional Association",
            "type":"Services"
        }
    ],
    "sg:phone":"+1 603 224 7447",
    "sg:postcode":"03301",
    "sg:province":"NH",
    "sg:website":"www.nhlgc.org",
    "wof:name":"Nh Local Government Ctr",
    "wof:placetype":"venue"
},
  "geometry": {"coordinates":[-71.538961,43.207031],"type":"Point"}
}