{
  "type": "Feature",
  "properties": {
    "iso:country":"US",
    "sg:address":"116 Bay St",
    "sg:city":"Wolfeboro",
    "sg:classifiers":[
        {
            "category":"Recreation",
            "subcategory":"Marina",
            "type":"Entertainment"
        }
    ],
    "sg:phone":"+1 603 569 5038",
    "sg:postcode":"03896",
    "sg:province":"NH",
    "sg:tags":[
        "repairing",
        "boat"
    ],
    "wof:name":"Lakes Region Restorations",
    "wof:placetype":"venue"
},
  "geometry": {"coordinates":[-71.21133399999999,43.591358],"type":"Point"}
}