{
  "type": "Feature",
  "properties": {
    "iso:country":"US",
    "sg:address":"112 Crawley Falls Rd",
    "sg:city":"Brentwood",
    "sg:classifiers":[
        {
            "category":"Shopping",
            "subcategory":"Computers & Home Electronics",
            "type":"Retail Goods"
        }
    ],
    "sg:phone":"+1 603 642 6899",
    "sg:postcode":"03833",
    "sg:province":"NH",
    "sg:tags":[
        "equipment",
        "dealer"
    ],
    "sg:website":"www.msrcco.com",
    "wof:name":"MSRC",
    "wof:placetype":"venue"
},
  "geometry": {"coordinates":[-71.068073,42.974033],"type":"Point"}
}