{
  "type": "Feature",
  "properties": {
    "addr:full":"216 Loudon Rd Concord NH 03301",
    "addr:housenumber":"216",
    "addr:postcode":"03301",
    "addr:street":"Loudon Rd",
    "iso:country":"US",
    "sg:address":"216 Loudon Rd",
    "sg:city":"Concord",
    "sg:classifiers":[
        {
            "category":"Retail",
            "subcategory":"Auto Repair",
            "type":"Services"
        }
    ],
    "sg:phone":"+1 603 224 8144",
    "sg:postcode":"03301",
    "sg:province":"NH",
    "sg:tags":[
        "repairing",
        "automobile"
    ],
    "wof:name":"Meineke Car Care Ctr",
    "wof:placetype":"venue"
},
  "geometry": {"coordinates":[-71.49265,43.222714],"type":"Point"}
}