{
  "type": "Feature",
  "properties": {
    "iso:country":"US",
    "sg:address":"1 Main St",
    "sg:city":"Hooksett",
    "sg:classifiers":[
        {
            "category":"Professional",
            "subcategory":"Management & Consulting",
            "type":"Services"
        }
    ],
    "sg:phone":"+1 603 485 2742",
    "sg:postcode":"03106",
    "sg:province":"NH",
    "wof:name":"Productive Systems New England",
    "wof:placetype":"venue"
},
  "geometry": {"coordinates":[-71.46566799999999,43.097622],"type":"Point"}
}