{
  "type": "Feature",
  "properties": {
    "iso:country":"US",
    "sg:address":"25 Raleigh Dr",
    "sg:city":"Nashua",
    "sg:classifiers":[
        {
            "category":"Social Services",
            "subcategory":"Child Care",
            "type":"Services"
        }
    ],
    "sg:phone":"+1 603 880 7583",
    "sg:postcode":"03062",
    "sg:province":"NH",
    "wof:name":"Nashua Kinder Kastle Inc",
    "wof:placetype":"venue"
},
  "geometry": {"coordinates":[-71.47147699999999,42.725949],"type":"Point"}
}