{
  "type": "Feature",
  "properties": {
    "iso:country":"US",
    "sg:address":"93 Stiles Rd",
    "sg:city":"Salem",
    "sg:classifiers":[
        {
            "category":"Wholesale",
            "subcategory":"Electrical",
            "type":"Manufacturing & Wholesale Goods"
        }
    ],
    "sg:phone":"+1 603 893 8484",
    "sg:postcode":"03079",
    "sg:province":"NH",
    "sg:tags":[
        "equipment",
        "electronic"
    ],
    "wof:name":"Ricoh Corporation",
    "wof:placetype":"venue"
},
  "geometry": {"coordinates":[-71.249821,42.775321],"type":"Point"}
}