{
  "type": "Feature",
  "properties": {
    "iso:country":"US",
    "sg:address":"690 Wellington Hill Rd",
    "sg:city":"Manchester",
    "sg:classifiers":[
        {
            "category":"Shopping",
            "subcategory":"Used Merchandise",
            "type":"Retail Goods"
        }
    ],
    "sg:phone":"+1 603 622 8429",
    "sg:postcode":"03104",
    "sg:province":"NH",
    "sg:tags":[
        "furniture"
    ],
    "wof:name":"Dh Consignment Furniture Acces",
    "wof:placetype":"venue"
},
  "geometry": {"coordinates":[-71.430499,43.005641],"type":"Point"}
}