{
  "type": "Feature",
  "properties": {
    "addr:full":"1200 Old N Main St Laconia NH 03246",
    "addr:housenumber":"1200",
    "addr:postcode":"03246",
    "addr:street":"Old N Main St",
    "iso:country":"US",
    "sg:address":"1200 Old N Main St",
    "sg:city":"Laconia",
    "sg:classifiers":[
        {
            "category":"Building & Trades",
            "subcategory":"Landscaping Services",
            "type":"Services"
        }
    ],
    "sg:phone":"+1 603 524 6494",
    "sg:postcode":"03246",
    "sg:province":"NH",
    "sg:tags":[
        "landscape",
        "contractor"
    ],
    "wof:name":"Muller's Lawn & Landscape Inc",
    "wof:placetype":"venue"
},
  "geometry": {"coordinates":[-71.487695,43.556527],"type":"Point"}
}