{
  "type": "Feature",
  "properties": {
    "iso:country":"US",
    "sg:address":"10 Folsom Rd",
    "sg:city":"Derry",
    "sg:classifiers":[
        {
            "category":"Shopping",
            "subcategory":"Clothing, Apparel, & Fashions",
            "type":"Retail Goods"
        }
    ],
    "sg:phone":"+1 603 432 2770",
    "sg:postcode":"03038",
    "sg:province":"NH",
    "sg:tags":[
        "custom",
        "printing",
        "t",
        "shirt"
    ],
    "wof:name":"Mark-All Industries Inc",
    "wof:placetype":"venue"
},
  "geometry": {"coordinates":[-71.330094,42.890625],"type":"Point"}
}