{
  "type": "Feature",
  "properties": {
    "iso:country":"US",
    "sg:address":"161 Portland Ave",
    "sg:city":"Dover",
    "sg:classifiers":[
        {
            "category":"Shopping",
            "subcategory":"Bicycles & Sporting Goods",
            "type":"Retail Goods"
        }
    ],
    "sg:phone":"+1 603 742 8781",
    "sg:postcode":"03820",
    "sg:province":"NH",
    "sg:website":"www.philbricksports.com",
    "wof:name":"Philbrick's Sports Ctr",
    "wof:placetype":"venue"
},
  "geometry": {"coordinates":[-70.85976599999999,43.204886],"type":"Point"}
}