{
  "type": "Feature",
  "properties": {
    "addr:full":"33 Gooseberry Cir Rochester NH 03867",
    "addr:housenumber":"33",
    "addr:postcode":"03867",
    "addr:street":"Gooseberry Cir",
    "iso:country":"US",
    "sg:address":"33 Gooseberry Cir",
    "sg:city":"Rochester",
    "sg:classifiers":[
        {
            "category":"Building & Trades",
            "subcategory":"Construction",
            "type":"Services"
        }
    ],
    "sg:phone":"+1 603 767 9658",
    "sg:postcode":"03867",
    "sg:province":"NH",
    "sg:tags":[
        "system",
        "specialty",
        "heating",
        "contractor",
        "air conditioning"
    ],
    "wof:name":"R & B Heating & Air Conditioning",
    "wof:placetype":"venue"
},
  "geometry": {"coordinates":[-70.954407,43.267632],"type":"Point"}
}