{
  "type": "Feature",
  "properties": {
    "iso:country":"US",
    "sg:address":"392 Mount Israel Rd",
    "sg:city":"Center Sandwich",
    "sg:classifiers":[
        {
            "category":"Professional",
            "subcategory":"Employment Agencies",
            "type":"Services"
        }
    ],
    "sg:phone":"+1 603 284 6308",
    "sg:postcode":"03227",
    "sg:province":"NH",
    "wof:name":"US Machine Innovations",
    "wof:placetype":"venue"
},
  "geometry": {"coordinates":[-71.45258200000001,43.824468],"type":"Point"}
}