{
  "type": "Feature",
  "properties": {
    "addr:full":"292 Walnut St Rochester NH 03867",
    "addr:housenumber":"292",
    "addr:postcode":"03867",
    "addr:street":"Walnut St",
    "iso:country":"US",
    "sg:address":"292 Walnut St",
    "sg:city":"Rochester",
    "sg:classifiers":[
        {
            "category":"Shopping",
            "type":"Retail Goods"
        }
    ],
    "sg:phone":"+1 603 332 2766",
    "sg:postcode":"03867",
    "sg:province":"NH",
    "sg:tags":[
        "pet",
        "food",
        "supply"
    ],
    "wof:name":"Horse Hill Feeds",
    "wof:placetype":"venue"
},
  "geometry": {"coordinates":[-71.021968,43.302094],"type":"Point"}
}