{
  "type": "Feature",
  "properties": {
    "iso:country":"US",
    "sg:address":"105 Main St",
    "sg:city":"Berlin",
    "sg:classifiers":[
        {
            "category":"Restaurant",
            "type":"Food & Drink"
        }
    ],
    "sg:phone":"+1 603 752 4419",
    "sg:postcode":"03570",
    "sg:province":"NH",
    "sg:tags":[
        "eating"
    ],
    "wof:name":"Melissas Country Kitchen",
    "wof:placetype":"venue"
},
  "geometry": {"coordinates":[-71.18148600000001,44.469346],"type":"Point"}
}