{
  "type": "Feature",
  "properties": {
    "iso:country":"US",
    "sg:address":"116 Key Rd",
    "sg:city":"Keene",
    "sg:classifiers":[
        {
            "category":"Home & Garden",
            "subcategory":"Building Materials",
            "type":"Retail Goods"
        }
    ],
    "sg:phone":"+1 603 352 2039",
    "sg:postcode":"03431",
    "sg:province":"NH",
    "sg:tags":[
        "paint"
    ],
    "wof:name":"Perkins Paint Ctr",
    "wof:placetype":"venue"
},
  "geometry": {"coordinates":[-72.29647799999999,42.924531],"type":"Point"}
}