{
  "type": "Feature",
  "properties": {
    "iso:country":"US",
    "sg:address":"325 Ward St",
    "sg:city":"Manchester",
    "sg:classifiers":[
        {
            "category":"Professional",
            "subcategory":"Business Services",
            "type":"Services"
        }
    ],
    "sg:phone":"+1 603 622 4712",
    "sg:postcode":"03104",
    "sg:province":"NH",
    "sg:tags":[
        "event"
    ],
    "wof:name":"Voices Nh Community Events",
    "wof:placetype":"venue"
},
  "geometry": {"coordinates":[-71.477711,43.025402],"type":"Point"}
}