{
  "type": "Feature",
  "properties": {
    "addr:full":"44 Cricket Ln Manchester NH 03104",
    "addr:housenumber":"44",
    "addr:postcode":"03104",
    "addr:street":"Cricket Ln",
    "iso:country":"US",
    "sg:address":"44 Cricket Ln",
    "sg:city":"Manchester",
    "sg:classifiers":[
        {
            "category":"Building & Trades",
            "subcategory":"Construction",
            "type":"Services"
        }
    ],
    "sg:phone":"+1 603 626 0277",
    "sg:postcode":"03104",
    "sg:province":"NH",
    "sg:tags":[
        "siding",
        "contractor"
    ],
    "wof:name":"C Gosselin Siding LLC",
    "wof:placetype":"venue"
},
  "geometry": {"coordinates":[-71.45800300000001,43.018112],"type":"Point"}
}