{
  "type": "Feature",
  "properties": {
    "iso:country":"US",
    "sg:address":"45 Kimball Rd",
    "sg:city":"Exeter",
    "sg:classifiers":[
        {
            "category":"Building & Trades",
            "subcategory":"Construction",
            "type":"Services"
        },
        {
            "category":"Restaurant",
            "type":"Food & Drink"
        }
    ],
    "sg:phone":"+1 603 778 1773",
    "sg:postcode":"03833",
    "sg:province":"NH",
    "sg:tags":[
        "masonry",
        "eating",
        "contractor"
    ],
    "wof:name":"Gallant Masonry",
    "wof:placetype":"venue"
},
  "geometry": {"coordinates":[-70.97253499999999,42.956363],"type":"Point"}
}