{
  "type": "Feature",
  "properties": {
    "iso:country":"US",
    "sg:address":"25 Woodcrest Heights Dr",
    "sg:city":"Concord",
    "sg:classifiers":[
        {
            "category":"Organizations",
            "subcategory":"Membership Organization",
            "type":"Services"
        }
    ],
    "sg:phone":"+1 603 226 3862",
    "sg:postcode":"03301",
    "sg:province":"NH",
    "sg:tags":[
        "athletic"
    ],
    "wof:name":"Baseball & Softball Academy",
    "wof:placetype":"venue"
},
  "geometry": {"coordinates":[-71.499764,43.22186],"type":"Point"}
}