{
  "type": "Feature",
  "properties": {
    "addr:full":"49 Lawndale Ave Franklin NH 03235",
    "addr:housenumber":"49",
    "addr:postcode":"03235",
    "addr:street":"Lawndale Ave",
    "iso:country":"US",
    "sg:address":"49 Lawndale Ave",
    "sg:city":"Franklin",
    "sg:classifiers":[
        {
            "category":"Retail",
            "subcategory":"Repair Shop",
            "type":"Services"
        },
        {
            "category":"Building & Trades",
            "subcategory":"Plumbing",
            "type":"Services"
        }
    ],
    "sg:phone":"+1 603 934 3113",
    "sg:postcode":"03235",
    "sg:province":"NH",
    "sg:tags":[
        "tank",
        "septic"
    ],
    "wof:name":"Hinds Septic Design Svcs",
    "wof:placetype":"venue"
},
  "geometry": {"coordinates":[-71.66556199999999,43.452294],"type":"Point"}
}