{
  "type": "Feature",
  "properties": {
    "addr:full":"17 Clydesdale Dr Danville NH 03819",
    "addr:housenumber":"17",
    "addr:postcode":"03819",
    "addr:street":"Clydesdale Dr",
    "iso:country":"US",
    "sg:address":"17 Clydesdale Dr",
    "sg:city":"Danville",
    "sg:classifiers":[
        {
            "category":"Building & Trades",
            "subcategory":"Electrical",
            "type":"Services"
        }
    ],
    "sg:phone":"+1 603 382 9115",
    "sg:postcode":"03819",
    "sg:province":"NH",
    "sg:tags":[
        "electrical",
        "contractor"
    ],
    "wof:name":"Drl Electric",
    "wof:placetype":"venue"
},
  "geometry": {"coordinates":[-71.118369,42.91781],"type":"Point"}
}