{
  "type": "Feature",
  "properties": {
    "addr:full":"43 Lebanon St Hanover NH 03755",
    "addr:housenumber":"43",
    "addr:postcode":"03755",
    "addr:street":"Lebanon St",
    "iso:country":"US",
    "sg:address":"43 Lebanon St",
    "sg:city":"Hanover",
    "sg:classifiers":[
        {
            "category":"Professional",
            "subcategory":"Business Services",
            "type":"Services"
        }
    ],
    "sg:phone":"+1 603 643 3186",
    "sg:postcode":"03755",
    "sg:province":"NH",
    "wof:name":"Rhea M McKay",
    "wof:placetype":"venue"
},
  "geometry": {"coordinates":[-72.280326,43.69647],"type":"Point"}
}