{
  "type": "Feature",
  "properties": {
    "iso:country":"US",
    "sg:address":"69 Willard St",
    "sg:city":"Berlin",
    "sg:classifiers":[
        {
            "category":"Social Services",
            "type":"Services"
        }
    ],
    "sg:phone":"+1 603 466 9010",
    "sg:postcode":"03570",
    "sg:province":"NH",
    "sg:tags":[
        "organization",
        "welfare"
    ],
    "wof:name":"Family Support Svc",
    "wof:placetype":"venue"
},
  "geometry": {"coordinates":[-71.18033699999999,44.471816],"type":"Point"}
}