{
  "type": "Feature",
  "properties": {
    "addr:full":"95 Farmington Rd Rochester NH 03867",
    "addr:housenumber":"95",
    "addr:postcode":"03867",
    "addr:street":"Farmington Rd",
    "iso:country":"US",
    "sg:address":"95 Farmington Rd",
    "sg:city":"Rochester",
    "sg:classifiers":[
        {
            "category":"Autos & Motor Vehicles",
            "subcategory":"Fuel & Gas Station",
            "type":"Retail Goods"
        }
    ],
    "sg:phone":"+1 603 332 4101",
    "sg:postcode":"03867",
    "sg:province":"NH",
    "sg:tags":[
        "oil"
    ],
    "wof:name":"Farmington Rd Shell",
    "wof:placetype":"venue"
},
  "geometry": {"coordinates":[-71.006317,43.330751],"type":"Point"}
}