{
  "type": "Feature",
  "properties": {
    "addr:full":"70 Plaistow Rd Plaistow NH 03865",
    "addr:housenumber":"70",
    "addr:postcode":"03865",
    "addr:street":"Plaistow Rd",
    "iso:country":"US",
    "sg:address":"70 Plaistow Rd",
    "sg:city":"Plaistow",
    "sg:classifiers":[
        {
            "category":"Autos & Motor Vehicles",
            "subcategory":"Fuel & Gas Station",
            "type":"Retail Goods"
        }
    ],
    "sg:phone":"+1 603 382 7774",
    "sg:postcode":"03865",
    "sg:province":"NH",
    "sg:tags":[
        "oil"
    ],
    "wof:name":"Getty Auto Ctr",
    "wof:placetype":"venue"
},
  "geometry": {"coordinates":[-71.107789,42.830624],"type":"Point"}
}