{
  "type": "Feature",
  "properties": {
    "iso:country":"US",
    "sg:address":"74 Main St",
    "sg:city":"Gorham",
    "sg:classifiers":[
        {
            "category":"Professional",
            "subcategory":"Lawyer & Legal Services",
            "type":"Services"
        }
    ],
    "sg:phone":"+1 603 466 3378",
    "sg:postcode":"03581",
    "sg:province":"NH",
    "sg:tags":[
        "attorney"
    ],
    "wof:name":"Thomas Cote Law Offices",
    "wof:placetype":"venue"
},
  "geometry": {"coordinates":[-71.17543000000001,44.388729],"type":"Point"}
}