{
  "type": "Feature",
  "properties": {
    "iso:country":"US",
    "sg:address":"27 Washington St",
    "sg:city":"Conway",
    "sg:classifiers":[
        {
            "category":"Health Services",
            "subcategory":"Dentist",
            "type":"Services"
        }
    ],
    "sg:phone":"+1 603 447 3888",
    "sg:postcode":"03818",
    "sg:province":"NH",
    "sg:tags":[
        "cosmetic"
    ],
    "sg:website":"conwayfamilydentalcare.com/",
    "wof:name":"Conway Family Dental Care",
    "wof:placetype":"venue"
},
  "geometry": {"coordinates":[-71.118364,43.979413],"type":"Point"}
}