{
  "type": "Feature",
  "properties": {
    "iso:country":"US",
    "sg:address":"5 Edward St",
    "sg:city":"Lebanon",
    "sg:classifiers":[
        {
            "category":"Building & Trades",
            "subcategory":"Cleaning & Sanitation",
            "type":"Services"
        }
    ],
    "sg:phone":"+1 603 448 4906",
    "sg:postcode":"03766",
    "sg:province":"NH",
    "sg:tags":[
        "janitor"
    ],
    "wof:name":"Aslan's Maintenance",
    "wof:placetype":"venue"
},
  "geometry": {"coordinates":[-72.244412,43.649116],"type":"Point"}
}