{
  "type": "Feature",
  "properties": {
    "addr:full":"14 Integra Dr Concord NH 03301",
    "addr:housenumber":"14",
    "addr:postcode":"03301",
    "addr:street":"Integra Dr",
    "iso:country":"US",
    "sg:address":"14 Integra Dr",
    "sg:city":"Concord",
    "sg:classifiers":[
        {
            "category":"Government",
            "subcategory":"Office",
            "type":"Public Place"
        }
    ],
    "sg:phone":"+1 603 271 3391",
    "sg:postcode":"03301",
    "sg:province":"NH",
    "sg:website":"www.nhlottery.org",
    "wof:name":"Sweepstakes Commission",
    "wof:placetype":"venue"
},
  "geometry": {"coordinates":[-71.50263099999999,43.185114],"type":"Point"}
}