{
  "type": "Feature",
  "properties": {
    "addr:full":"65 S Main St Concord NH 03301",
    "addr:housenumber":"65",
    "addr:postcode":"03301",
    "addr:street":"S Main St",
    "iso:country":"US",
    "sg:address":"65 S Main St",
    "sg:city":"Concord",
    "sg:classifiers":[
        {
            "category":"Shopping",
            "type":"Retail Goods"
        }
    ],
    "sg:phone":"+1 603 225 9580",
    "sg:postcode":"03301",
    "sg:province":"NH",
    "sg:tags":[
        "enforcement",
        "law",
        "supply"
    ],
    "wof:name":"N H Insignia",
    "wof:placetype":"venue"
},
  "geometry": {"coordinates":[-71.533355,43.200515],"type":"Point"}
}