{
  "type": "Feature",
  "properties": {
    "iso:country":"US",
    "sg:address":"134 Glen Rd",
    "sg:city":"Gorham",
    "sg:classifiers":[
        {
            "category":"Manufacturing",
            "subcategory":"Tools & Machinery",
            "type":"Manufacturing & Wholesale Goods"
        }
    ],
    "sg:phone":"+1 603 466 5203",
    "sg:postcode":"03581",
    "sg:province":"NH",
    "sg:tags":[
        "machining"
    ],
    "wof:name":"Moonlight Machining",
    "wof:placetype":"venue"
},
  "geometry": {"coordinates":[-71.17326300000001,44.381921],"type":"Point"}
}