{
  "type": "Feature",
  "properties": {
    "iso:country":"US",
    "sg:address":"2 Depot St",
    "sg:city":"Pittsfield",
    "sg:classifiers":[
        {
            "category":"Education",
            "subcategory":"Preschool",
            "type":"Public Place"
        },
        {
            "category":"Education",
            "subcategory":"School",
            "type":"Public Place"
        }
    ],
    "sg:phone":"+1 603 435 6618",
    "sg:postcode":"03263",
    "sg:province":"NH",
    "sg:tags":[
        "elementary"
    ],
    "wof:name":"Head Start-Pittsfield",
    "wof:placetype":"venue"
},
  "geometry": {"coordinates":[-71.326599,43.306],"type":"Point"}
}