{
  "type": "Feature",
  "properties": {
    "iso:country":"US",
    "sg:address":"99 Meadow St",
    "sg:city":"Littleton",
    "sg:classifiers":[
        {
            "category":"Shopping",
            "subcategory":"Shoes",
            "type":"Retail Goods"
        }
    ],
    "sg:phone":"+1 603 444 6834",
    "sg:postcode":"03561",
    "sg:province":"NH",
    "wof:name":"Dexter Shoe",
    "wof:placetype":"venue"
},
  "geometry": {"coordinates":[-71.787104,44.308937],"type":"Point"}
}