{
  "type": "Feature",
  "properties": {
    "addr:full":"6 Old Mill Ln Nashua NH 03064",
    "addr:housenumber":"6",
    "addr:postcode":"03064",
    "addr:street":"Old Mill Ln",
    "iso:country":"US",
    "sg:address":"6 Old Mill Ln",
    "sg:city":"Nashua",
    "sg:classifiers":[
        {
            "category":"Professional",
            "subcategory":"Management & Consulting",
            "type":"Services"
        }
    ],
    "sg:phone":"+1 603 930 9173",
    "sg:postcode":"03064",
    "sg:province":"NH",
    "sg:tags":[
        "consultant",
        "resource",
        "human"
    ],
    "wof:name":"Advanced HR LTD",
    "wof:placetype":"venue"
},
  "geometry": {"coordinates":[-71.47581,42.782966],"type":"Point"}
}