{
  "type": "Feature",
  "properties": {
    "iso:country":"US",
    "sg:address":"6 Fogg Ln",
    "sg:city":"Hampton",
    "sg:classifiers":[
        {
            "category":"Building & Trades",
            "subcategory":"Plumbing",
            "type":"Services"
        }
    ],
    "sg:phone":"+1 603 926 0693",
    "sg:postcode":"03842",
    "sg:province":"NH",
    "sg:tags":[
        "plumbing"
    ],
    "wof:name":"Gary P Dupuis",
    "wof:placetype":"venue"
},
  "geometry": {"coordinates":[-70.831767,42.925356],"type":"Point"}
}