{
  "type": "Feature",
  "properties": {
    "addr:full":"182 Main St Salem NH 03079",
    "addr:housenumber":"182",
    "addr:postcode":"03079",
    "addr:street":"Main St",
    "iso:country":"US",
    "sg:address":"182 Main St",
    "sg:city":"Salem",
    "sg:classifiers":[
        {
            "category":"Professional",
            "subcategory":"Computer Services",
            "type":"Services"
        }
    ],
    "sg:phone":"+1 603 893 4185",
    "sg:postcode":"03079",
    "sg:province":"NH",
    "sg:tags":[
        "consultant",
        "designer"
    ],
    "sg:website":"www.polymorf.com",
    "wof:name":"Polymorph Corp",
    "wof:placetype":"venue"
},
  "geometry": {"coordinates":[-71.219712,42.783069],"type":"Point"}
}