{
  "type": "Feature",
  "properties": {
    "iso:country":"US",
    "sg:address":"1932 Wellington Rd",
    "sg:city":"Manchester",
    "sg:classifiers":[
        {
            "category":"Bagels",
            "type":"Food & Drink"
        },
        {
            "category":"Coffee & Tea",
            "type":"Food & Drink"
        },
        {
            "category":"Food & Beverages",
            "subcategory":"Bakery",
            "type":"Retail Goods"
        },
        {
            "category":"Bakery",
            "type":"Food & Drink"
        },
        {
            "category":"Donuts",
            "type":"Food & Drink"
        }
    ],
    "sg:menulink":"http://www.allmenus.com/nh/manchester/149216-dunkin-donuts/menu/",
    "sg:phone":"+1 603 647 9268",
    "sg:postcode":"03104",
    "sg:province":"NH",
    "sg:tags":[
        "coffee",
        "sandwich",
        "tea",
        "american",
        "bagel",
        "bakery",
        "pastry",
        "wrap"
    ],
    "wof:name":"Dunkin' Donuts",
    "wof:placetype":"venue"
},
  "geometry": {"coordinates":[-71.39704500000001,43.008388],"type":"Point"}
}