{
  "type": "Feature",
  "properties": {
    "addr:full":"30 Main St Meredith NH 03253",
    "addr:housenumber":"30",
    "addr:postcode":"03253",
    "addr:street":"Main St",
    "iso:country":"US",
    "sg:address":"30 Main St",
    "sg:city":"Meredith",
    "sg:classifiers":[
        {
            "category":"Personal",
            "subcategory":"Beauty Salon",
            "type":"Services"
        }
    ],
    "sg:phone":"+1 603 279 9940",
    "sg:postcode":"03253",
    "sg:province":"NH",
    "wof:name":"N J's Tangles",
    "wof:placetype":"venue"
},
  "geometry": {"coordinates":[-71.501192,43.656766],"type":"Point"}
}