{
  "type": "Feature",
  "properties": {
    "iso:country":"US",
    "sg:address":"134 Newton Rd",
    "sg:city":"Plaistow",
    "sg:classifiers":[
        {
            "category":"Professional",
            "subcategory":"Accounting & Tax Preparation",
            "type":"Services"
        }
    ],
    "sg:phone":"+1 603 382 0382",
    "sg:postcode":"03865",
    "sg:province":"NH",
    "sg:tags":[
        "consultant"
    ],
    "wof:name":"Larson Tax Svc",
    "wof:placetype":"venue"
},
  "geometry": {"coordinates":[-71.056785,42.832111],"type":"Point"}
}