{
  "type": "Feature",
  "properties": {
    "iso:country":"US",
    "sg:address":"100 Main St",
    "sg:city":"Dover",
    "sg:classifiers":[
        {
            "category":"Shopping",
            "subcategory":"Computers & Home Electronics",
            "type":"Retail Goods"
        }
    ],
    "sg:phone":"+1 603 749 7900",
    "sg:postcode":"03820",
    "sg:province":"NH",
    "sg:tags":[
        "a",
        "e",
        "retailer",
        "operates",
        "as",
        "software"
    ],
    "wof:name":"Centerfield Group LLC",
    "wof:placetype":"venue"
},
  "geometry": {"coordinates":[-70.873783,43.198079],"type":"Point"}
}