{
  "type": "Feature",
  "properties": {
    "iso:country":"US",
    "sg:address":"6 Evergreen Cir",
    "sg:city":"Litchfield",
    "sg:classifiers":[
        {
            "category":"Professional",
            "subcategory":"Secretarial Services",
            "type":"Services"
        }
    ],
    "sg:phone":"+1 603 432 9855",
    "sg:postcode":"03052",
    "sg:province":"NH",
    "sg:tags":[
        "medical"
    ],
    "wof:name":"MD Inc",
    "wof:placetype":"venue"
},
  "geometry": {"coordinates":[-71.434815,42.846013],"type":"Point"}
}