{
  "type": "Feature",
  "properties": {
    "iso:country":"US",
    "sg:address":"38 3rd St",
    "sg:city":"Berlin",
    "sg:classifiers":[
        {
            "category":"Manufacturing",
            "subcategory":"Lumber",
            "type":"Manufacturing & Wholesale Goods"
        }
    ],
    "sg:phone":"+1 603 752 3549",
    "sg:postcode":"03570",
    "sg:province":"NH",
    "sg:tags":[
        "logging"
    ],
    "wof:name":"Corbeil Logging",
    "wof:placetype":"venue"
},
  "geometry": {"coordinates":[-71.171395,44.476235],"type":"Point"}
}