{
  "type": "Feature",
  "properties": {
    "addr:full":"41 Dupaw Gould Rd Brookline NH 03033",
    "addr:housenumber":"41",
    "addr:postcode":"03033",
    "addr:street":"Dupaw Gould Rd",
    "iso:country":"US",
    "sg:address":"41 Dupaw Gould Rd",
    "sg:city":"Brookline",
    "sg:classifiers":[
        {
            "category":"Manufacturing",
            "subcategory":"Metals",
            "type":"Manufacturing & Wholesale Goods"
        }
    ],
    "sg:phone":"+1 603 765 4393",
    "sg:postcode":"03033",
    "sg:province":"NH",
    "sg:tags":[
        "network"
    ],
    "wof:name":"Ie Data",
    "wof:placetype":"venue"
},
  "geometry": {"coordinates":[-71.690788,42.7491],"type":"Point"}
}