{
  "type": "Feature",
  "properties": {
    "iso:country":"US",
    "sg:address":"100 Market St",
    "sg:city":"Portsmouth",
    "sg:classifiers":[
        {
            "category":"Shopping",
            "subcategory":"Jewelry",
            "type":"Retail Goods"
        }
    ],
    "sg:phone":"+1 603 431 8418",
    "sg:postcode":"03801",
    "sg:province":"NH",
    "sg:tags":[
        "jeweler"
    ],
    "sg:website":"www.springersjewelers.com",
    "wof:name":"Springer's Jewelers",
    "wof:placetype":"venue"
},
  "geometry": {"coordinates":[-70.75890200000001,43.079312],"type":"Point"}
}