{
  "type": "Feature",
  "properties": {
    "iso:country":"US",
    "sg:address":"64 Epping St",
    "sg:city":"Raymond",
    "sg:classifiers":[
        {
            "category":"Retail",
            "subcategory":"Auto Repair",
            "type":"Services"
        }
    ],
    "sg:phone":"+1 603 895 6155",
    "sg:postcode":"03077",
    "sg:province":"NH",
    "sg:tags":[
        "repairing",
        "automobile"
    ],
    "wof:name":"Raymond Foreign Auto",
    "wof:placetype":"venue"
},
  "geometry": {"coordinates":[-71.169284,43.04032],"type":"Point"}
}