{
  "type": "Feature",
  "properties": {
    "iso:country":"US",
    "sg:address":"34 S Main St",
    "sg:city":"Rochester",
    "sg:classifiers":[
        {
            "category":"Social Services",
            "subcategory":"Child Care",
            "type":"Services"
        },
        {
            "category":"Organizations",
            "subcategory":"Religious Organization",
            "type":"Services"
        }
    ],
    "sg:phone":"+1 603 332 4170",
    "sg:postcode":"03867",
    "sg:province":"NH",
    "sg:tags":[
        "day",
        "church"
    ],
    "wof:name":"First United Methodist Church",
    "wof:placetype":"venue"
},
  "geometry": {"coordinates":[-70.97484799999999,43.303055],"type":"Point"}
}