{
  "type": "Feature",
  "properties": {
    "addr:full":"9 Village St Penacook NH 03303",
    "addr:housenumber":"9",
    "addr:postcode":"03303",
    "addr:street":"Village St",
    "iso:country":"US",
    "sg:address":"9 Village St",
    "sg:city":"Penacook",
    "sg:classifiers":[
        {
            "category":"Food & Beverages",
            "subcategory":"Groceries & Convenience Stores",
            "type":"Retail Goods"
        }
    ],
    "sg:phone":"+1 603 753 6306",
    "sg:postcode":"03303",
    "sg:province":"NH",
    "sg:tags":[
        "market"
    ],
    "wof:name":"Thirty Pines Market",
    "wof:placetype":"venue"
},
  "geometry": {"coordinates":[-71.586657,43.266399],"type":"Point"}
}