{
  "type": "Feature",
  "properties": {
    "iso:country":"US",
    "sg:address":"1 Sargent Hill Rd",
    "sg:city":"W Chesterfield",
    "sg:classifiers":[
        {
            "category":"Shopping",
            "subcategory":"Clothing, Apparel, & Fashions",
            "type":"Retail Goods"
        }
    ],
    "sg:phone":"+1 603 256 6006",
    "sg:postcode":"03443",
    "sg:province":"NH",
    "sg:tags":[
        "riding",
        "equipment"
    ],
    "sg:website":"www.saddlebrooktack.com",
    "wof:name":"Saddlebrook Tack",
    "wof:placetype":"venue"
},
  "geometry": {"coordinates":[-72.51136099999999,42.895841],"type":"Point"}
}