{
  "type": "Feature",
  "properties": {
    "iso:country":"US",
    "sg:address":"429 River Rd",
    "sg:city":"Lyme",
    "sg:classifiers":[
        {
            "category":"Health Services",
            "subcategory":"Health Practitioner",
            "type":"Services"
        }
    ],
    "sg:phone":"+1 603 795 2130",
    "sg:postcode":"03768",
    "sg:province":"NH",
    "wof:name":"Young Alethea",
    "wof:placetype":"venue"
},
  "geometry": {"coordinates":[-72.177251,43.856859],"type":"Point"}
}