{
  "type": "Feature",
  "properties": {
    "iso:country":"US",
    "sg:address":"23 Grove St",
    "sg:city":"Peterborough",
    "sg:classifiers":[
        {
            "category":"Government",
            "subcategory":"Post Office",
            "type":"Public Place"
        }
    ],
    "sg:phone":"+1 800 275 8777",
    "sg:postcode":"03458",
    "sg:province":"NH",
    "sg:website":"http://www.usps.com",
    "wof:name":"USPS - United States Post Office - Peterborough Main Office",
    "wof:placetype":"venue"
},
  "geometry": {"coordinates":[-71.950942,42.876217],"type":"Point"}
}