{
  "type": "Feature",
  "properties": {
    "iso:country":"US",
    "sg:address":"30 High St",
    "sg:city":"Pembroke",
    "sg:classifiers":[
        {
            "category":"Education",
            "subcategory":"School",
            "type":"Public Place"
        }
    ],
    "sg:phone":"+1 603 485 1807",
    "sg:postcode":"03275",
    "sg:province":"NH",
    "sg:website":"www.sau53.org",
    "wof:name":"Pembroke Village School",
    "wof:placetype":"venue"
},
  "geometry": {"coordinates":[-71.45561600000001,43.133812],"type":"Point"}
}