{
  "type": "Feature",
  "properties": {
    "addr:full":"588 Charles Bancroft Hwy Litchfield NH 03052",
    "addr:housenumber":"588",
    "addr:postcode":"03052",
    "addr:street":"Charles Bancroft Hwy",
    "iso:country":"US",
    "sg:address":"588 Charles Bancroft Hwy",
    "sg:city":"Litchfield",
    "sg:classifiers":[
        {
            "category":"Manufacturing",
            "subcategory":"Tools & Machinery",
            "type":"Manufacturing & Wholesale Goods"
        }
    ],
    "sg:phone":"+1 603 424 7707",
    "sg:postcode":"03052",
    "sg:province":"NH",
    "sg:tags":[
        "machine",
        "shop"
    ],
    "wof:name":"N & B Machine",
    "wof:placetype":"venue"
},
  "geometry": {"coordinates":[-71.452821,42.901643],"type":"Point"}
}