{
  "type": "Feature",
  "properties": {
    "iso:country":"US",
    "sg:address":"17 Dunbar St",
    "sg:city":"Keene",
    "sg:classifiers":[
        {
            "category":"Real Estate",
            "subcategory":"Real Estate Agent",
            "type":"Services"
        }
    ],
    "sg:phone":"+1 603 352 6030",
    "sg:postcode":"03431",
    "sg:province":"NH",
    "sg:website":"www.hksassoc.com",
    "wof:name":"HKS Assoc Inc",
    "wof:placetype":"venue"
},
  "geometry": {"coordinates":[-72.275308,42.930521],"type":"Point"}
}