{
  "type": "Feature",
  "properties": {
    "iso:country":"US",
    "sg:address":"40 Meadows Edge Rd",
    "sg:city":"Center Barnstead",
    "sg:classifiers":[
        {
            "category":"Banks & Credit Unions",
            "subcategory":"Investment Brokerage",
            "type":"Services"
        }
    ],
    "sg:phone":"+1 603 226 0674",
    "sg:postcode":"03225",
    "sg:province":"NH",
    "wof:name":"Westlake & Westlake",
    "wof:placetype":"venue"
},
  "geometry": {"coordinates":[-71.271519,43.38412],"type":"Point"}
}