{
  "type": "Feature",
  "properties": {
    "iso:country":"US",
    "sg:address":"32 Clinton St",
    "sg:city":"Concord",
    "sg:classifiers":[
        {
            "category":"Government",
            "subcategory":"Court House",
            "type":"Public Place"
        }
    ],
    "sg:phone":"+1 603 271 6400",
    "sg:postcode":"03301",
    "sg:province":"NH",
    "sg:tags":[
        "county"
    ],
    "wof:name":"Concord District Court",
    "wof:placetype":"venue"
},
  "geometry": {"coordinates":[-71.54379900000001,43.193174],"type":"Point"}
}