{
  "type": "Feature",
  "properties": {
    "addr:full":"452 Winchester St Keene NH 03431",
    "addr:housenumber":"452",
    "addr:postcode":"03431",
    "addr:street":"Winchester St",
    "iso:country":"US",
    "sg:address":"452 Winchester St",
    "sg:city":"Keene",
    "sg:phone":"+1 603 352 5240",
    "sg:postcode":"03431",
    "sg:province":"NH",
    "sg:tags":[
        "oil"
    ],
    "wof:name":"Webber Energy Fuels",
    "wof:placetype":"venue"
},
  "geometry": {"coordinates":[-72.29275800000001,42.917688],"type":"Point"}
}