{
  "type": "Feature",
  "properties": {
    "iso:country":"US",
    "sg:address":"105 State Rte 101A",
    "sg:city":"Amherst",
    "sg:classifiers":[
        {
            "category":"Professional",
            "type":"Services"
        },
        {
            "category":"Manufacturing",
            "subcategory":"Tools & Machinery",
            "type":"Manufacturing & Wholesale Goods"
        }
    ],
    "sg:phone":"+1 603 546 0100",
    "sg:postcode":"03031",
    "sg:province":"NH",
    "sg:tags":[
        "manufacture",
        "ergonomic",
        "equipment",
        "stand",
        "establishment",
        "check"
    ],
    "sg:website":"www.seamarkinternational.com",
    "wof:name":"Seamark International LLC",
    "wof:placetype":"venue"
},
  "geometry": {"coordinates":[-71.574589,42.809959],"type":"Point"}
}