{
  "type": "Feature",
  "properties": {
    "iso:country":"US",
    "sg:address":"5 Angus Way",
    "sg:city":"Pelham",
    "sg:classifiers":[
        {
            "category":"Shopping",
            "subcategory":"Hobbies, Toys, & Games",
            "type":"Retail Goods"
        }
    ],
    "sg:phone":"+1 603 635 2565",
    "sg:postcode":"03076",
    "sg:province":"NH",
    "wof:name":"Just A Little Somethin",
    "wof:placetype":"venue"
},
  "geometry": {"coordinates":[-71.337807,42.761346],"type":"Point"}
}