{
  "type": "Feature",
  "properties": {
    "addr:full":"128 Estes Rd Rochester NH 03867",
    "addr:housenumber":"128",
    "addr:postcode":"03867",
    "addr:street":"Estes Rd",
    "iso:country":"US",
    "sg:address":"128 Estes Rd",
    "sg:city":"Rochester",
    "sg:classifiers":[
        {
            "category":"Professional",
            "subcategory":"Business Services",
            "type":"Services"
        }
    ],
    "sg:phone":"+1 603 332 1635",
    "sg:postcode":"03867",
    "sg:province":"NH",
    "wof:name":"Mc Grail Detailing",
    "wof:placetype":"venue"
},
  "geometry": {"coordinates":[-71.0172,43.290865],"type":"Point"}
}