{
  "type": "Feature",
  "properties": {
    "addr:full":"5 Lebanon St West Lebanon NH 03755",
    "addr:housenumber":"5",
    "addr:postcode":"03755",
    "addr:street":"Lebanon St",
    "iso:country":"US",
    "sg:address":"5 Lebanon St",
    "sg:city":"West Lebanon",
    "sg:classifiers":[
        {
            "category":"Retail",
            "subcategory":"Auto Rental",
            "type":"Services"
        }
    ],
    "sg:phone":"+1 603 298 5701",
    "sg:postcode":"03755",
    "sg:province":"NH",
    "sg:tags":[
        "renting",
        "automobile"
    ],
    "wof:name":"National Car Rental",
    "wof:placetype":"venue"
},
  "geometry": {"coordinates":[-72.287491,43.700956],"type":"Point"}
}