{
  "type": "Feature",
  "properties": {
    "iso:country":"US",
    "sg:address":"624 Cross Country Rd",
    "sg:city":"Suncook",
    "sg:classifiers":[
        {
            "category":"Building & Trades",
            "subcategory":"Construction",
            "type":"Services"
        }
    ],
    "sg:phone":"+1 603 228 0725",
    "sg:postcode":"03275",
    "sg:province":"NH",
    "sg:tags":[
        "excavation",
        "contractor"
    ],
    "wof:name":"Pembroke Excavation & Ldscpg",
    "wof:placetype":"venue"
},
  "geometry": {"coordinates":[-71.442481,43.192679],"type":"Point"}
}