{
  "type": "Feature",
  "properties": {
    "iso:country":"US",
    "sg:address":"1 Andrea Cir",
    "sg:city":"Merrimack",
    "sg:classifiers":[
        {
            "category":"Professional",
            "type":"Services"
        }
    ],
    "sg:phone":"+1 603 424 7223",
    "sg:postcode":"03054",
    "sg:province":"NH",
    "sg:tags":[
        "establishment"
    ],
    "wof:name":"GMS",
    "wof:placetype":"venue"
},
  "geometry": {"coordinates":[-71.472645,42.905702],"type":"Point"}
}