{
  "type": "Feature",
  "properties": {
    "addr:full":"120 Amherst St Nashua NH 03064",
    "addr:housenumber":"120",
    "addr:postcode":"03064",
    "addr:street":"Amherst St",
    "iso:country":"US",
    "sg:address":"120 Amherst St",
    "sg:city":"Nashua",
    "sg:classifiers":[
        {
            "category":"Restaurant",
            "type":"Food & Drink"
        }
    ],
    "sg:menulink":"http://www.allmenus.com/nh/nashua/26336-pan-asia/menu/",
    "sg:phone":"+1 603 880 5136",
    "sg:postcode":"03064",
    "sg:province":"NH",
    "sg:tags":[
        "asian",
        "chinese"
    ],
    "wof:name":"Pan Asia",
    "wof:placetype":"venue"
},
  "geometry": {"coordinates":[-71.480485,42.77044],"type":"Point"}
}