{
  "type": "Feature",
  "properties": {
    "iso:country":"US",
    "sg:address":"265 Packers Falls Rd",
    "sg:city":"Durham",
    "sg:classifiers":[
        {
            "category":"Building & Trades",
            "subcategory":"Equipment Rental",
            "type":"Services"
        }
    ],
    "sg:phone":"+1 603 659 2301",
    "sg:postcode":"03824",
    "sg:province":"NH",
    "sg:tags":[
        "crane"
    ],
    "wof:name":"Carlisle Construction Co",
    "wof:placetype":"venue"
},
  "geometry": {"coordinates":[-70.958462,43.109066],"type":"Point"}
}