{
  "type": "Feature",
  "properties": {
    "iso:country":"US",
    "sg:address":"9 Sunridge Rd",
    "sg:city":"Windham",
    "sg:classifiers":[
        {
            "category":"Professional",
            "subcategory":"Computer Services",
            "type":"Services"
        }
    ],
    "sg:phone":"+1 603 889 6344",
    "sg:postcode":"03087",
    "sg:province":"NH",
    "sg:tags":[
        "programing",
        "custom"
    ],
    "wof:name":"David Searles",
    "wof:placetype":"venue"
},
  "geometry": {"coordinates":[-71.34707299999999,42.791058],"type":"Point"}
}