{
  "type": "Feature",
  "properties": {
    "iso:country":"US",
    "sg:address":"114 Locust St",
    "sg:city":"Dover",
    "sg:classifiers":[
        {
            "category":"Professional",
            "type":"Services"
        }
    ],
    "sg:phone":"+1 603 750 7310",
    "sg:postcode":"03820",
    "sg:province":"NH",
    "sg:tags":[
        "establishment"
    ],
    "wof:name":"Work Opportunities Unltd Inc",
    "wof:placetype":"venue"
},
  "geometry": {"coordinates":[-70.875609,43.190509],"type":"Point"}
}