{
  "type": "Feature",
  "properties": {
    "iso:country":"US",
    "sg:address":"90 Badger St",
    "sg:city":"Littleton",
    "sg:classifiers":[
        {
            "category":"Professional",
            "subcategory":"Detective & Security Services",
            "type":"Services"
        }
    ],
    "sg:phone":"+1 603 444 0780",
    "sg:postcode":"03561",
    "sg:province":"NH",
    "sg:tags":[
        "system"
    ],
    "wof:name":"L R C LLC",
    "wof:placetype":"venue"
},
  "geometry": {"coordinates":[-71.763555,44.294818],"type":"Point"}
}