{
  "type": "Feature",
  "properties": {
    "iso:country":"US",
    "sg:address":"702 Smithfield Rd",
    "sg:city":"Suncook",
    "sg:classifiers":[
        {
            "category":"Building & Trades",
            "subcategory":"Landscaping Services",
            "type":"Services"
        }
    ],
    "sg:phone":"+1 603 485 4761",
    "sg:postcode":"03229",
    "sg:province":"NH",
    "sg:tags":[
        "tree"
    ],
    "wof:name":"Collins Tree Svc",
    "wof:placetype":"venue"
},
  "geometry": {"coordinates":[-71.70602700000001,43.220752],"type":"Point"}
}