{
  "type": "Feature",
  "properties": {
    "addr:full":"347 Main St Gorham NH 03581",
    "addr:housenumber":"347",
    "addr:postcode":"03581",
    "addr:street":"Main St",
    "iso:country":"US",
    "sg:address":"347 Main St",
    "sg:city":"Gorham",
    "sg:classifiers":[
        {
            "category":"Local Transit",
            "type":"Transportation"
        }
    ],
    "sg:phone":"+1 603 466 5611",
    "sg:postcode":"03581",
    "sg:province":"NH",
    "sg:tags":[
        "ambulance"
    ],
    "sg:website":"www.gorhamems.org",
    "wof:name":"Gorham Ambulance",
    "wof:placetype":"venue"
},
  "geometry": {"coordinates":[-71.19413,44.396181],"type":"Point"}
}