{
  "type": "Feature",
  "properties": {
    "iso:country":"US",
    "sg:address":"42 Cottage St",
    "sg:city":"Littleton",
    "sg:classifiers":[
        {
            "category":"Health Services",
            "subcategory":"Doctor",
            "type":"Services"
        }
    ],
    "sg:phone":"+1 603 444 0860",
    "sg:postcode":"03561",
    "sg:province":"NH",
    "sg:tags":[
        "medical"
    ],
    "wof:name":"Carol F Lidstrom",
    "wof:placetype":"venue"
},
  "geometry": {"coordinates":[-71.769718,44.304387],"type":"Point"}
}