{
  "type": "Feature",
  "properties": {
    "iso:country":"US",
    "sg:address":"301 Union St",
    "sg:city":"Peterborough",
    "sg:classifiers":[
        {
            "category":"Government",
            "subcategory":"Post Office",
            "type":"Public Place"
        }
    ],
    "sg:phone":"+1 603 924 6126",
    "sg:postcode":"03458",
    "sg:province":"NH",
    "sg:tags":[
        "postal",
        "us"
    ],
    "wof:name":"US Post Office",
    "wof:placetype":"venue"
},
  "geometry": {"coordinates":[-71.977722,42.888487],"type":"Point"}
}