{
  "type": "Feature",
  "properties": {
    "iso:country":"US",
    "sg:address":"1 Mill Plz",
    "sg:city":"Laconia",
    "sg:classifiers":[
        {
            "category":"Real Estate",
            "subcategory":"Architect",
            "type":"Services"
        }
    ],
    "sg:phone":"+1 603 527 1617",
    "sg:postcode":"03246",
    "sg:province":"NH",
    "wof:name":"Misiaszek & Turpin LLC",
    "wof:placetype":"venue"
},
  "geometry": {"coordinates":[-71.46750900000001,43.526552],"type":"Point"}
}