{
  "type": "Feature",
  "properties": {
    "addr:full":"58 New Rochester Rd Dover NH 03820",
    "addr:housenumber":"58",
    "addr:postcode":"03820",
    "addr:street":"New Rochester Rd",
    "iso:country":"US",
    "sg:address":"58 New Rochester Rd",
    "sg:city":"Dover",
    "sg:classifiers":[
        {
            "category":"Restaurant",
            "type":"Food & Drink"
        }
    ],
    "sg:phone":"+1 603 742 7012",
    "sg:postcode":"03820",
    "sg:province":"NH",
    "sg:website":"http://www.straffordfarms.com",
    "wof:name":"Strafford Farms Restaurant",
    "wof:placetype":"venue"
},
  "geometry": {"coordinates":[-70.89587400000001,43.228619],"type":"Point"}
}