{
  "type": "Feature",
  "properties": {
    "addr:full":"5 Depot Rd Sandown NH 03873",
    "addr:housenumber":"5",
    "addr:postcode":"03873",
    "addr:street":"Depot Rd",
    "iso:country":"US",
    "sg:address":"5 Depot Rd",
    "sg:city":"Sandown",
    "sg:classifiers":[
        {
            "category":"Building & Trades",
            "subcategory":"Construction",
            "type":"Services"
        }
    ],
    "sg:phone":"+1 603 887 3968",
    "sg:postcode":"03873",
    "sg:province":"NH",
    "sg:tags":[
        "dry wall",
        "contractor"
    ],
    "wof:name":"Scott's Drywall",
    "wof:placetype":"venue"
},
  "geometry": {"coordinates":[-71.183532,42.929372],"type":"Point"}
}