{
  "type": "Feature",
  "properties": {
    "iso:country":"US",
    "sg:address":"859 Hanover St",
    "sg:city":"Manchester",
    "sg:classifiers":[
        {
            "category":"Food & Beverages",
            "subcategory":"Groceries & Convenience Stores",
            "type":"Retail Goods"
        }
    ],
    "sg:phone":"+1 603 627 4354",
    "sg:postcode":"03104",
    "sg:province":"NH",
    "sg:tags":[
        "grocer"
    ],
    "wof:name":"Hannaford Supermarkets",
    "wof:placetype":"venue"
},
  "geometry": {"coordinates":[-71.42834000000001,42.98769],"type":"Point"}
}