{
  "type": "Feature",
  "properties": {
    "iso:country":"US",
    "sg:address":"3 Alumni Dr",
    "sg:city":"Exeter",
    "sg:classifiers":[
        {
            "category":"Health Services",
            "subcategory":"Doctor",
            "type":"Services"
        }
    ],
    "sg:phone":"+1 603 773 9904",
    "sg:postcode":"03833",
    "sg:province":"NH",
    "sg:tags":[
        "physician",
        "surgeon"
    ],
    "sg:website":"www.drmarble.com",
    "wof:name":"Core Health Svc",
    "wof:placetype":"venue"
},
  "geometry": {"coordinates":[-70.93770499999999,42.985068],"type":"Point"}
}