{
  "type": "Feature",
  "properties": {
    "iso:country":"US",
    "sg:address":"936 Battle St",
    "sg:city":"Concord",
    "sg:classifiers":[
        {
            "category":"Education",
            "subcategory":"School",
            "type":"Public Place"
        }
    ],
    "sg:phone":"+1 603 648 2467",
    "sg:postcode":"03303",
    "sg:province":"NH",
    "wof:name":"Webster Elementary School",
    "wof:placetype":"venue"
},
  "geometry": {"coordinates":[-71.717832,43.308247],"type":"Point"}
}