{
  "type": "Feature",
  "properties": {
    "addr:full":"11 Andrews Rd Somersworth NH 03878",
    "addr:housenumber":"11",
    "addr:postcode":"03878",
    "addr:street":"Andrews Rd",
    "iso:country":"US",
    "sg:address":"11 Andrews Rd",
    "sg:city":"Somersworth",
    "sg:classifiers":[
        {
            "category":"Utilities",
            "subcategory":"Mobile Phone",
            "type":"Services"
        },
        {
            "category":"Coffee & Tea",
            "type":"Food & Drink"
        }
    ],
    "sg:phone":"+1 603 692 6750",
    "sg:postcode":"03878",
    "sg:province":"NH",
    "sg:tags":[
        "shop",
        "restaurant",
        "espresso",
        "hotspot",
        "wi-fi"
    ],
    "sg:website":"http://www.starbuckscoffee.com",
    "wof:name":"Starbucks Coffee",
    "wof:placetype":"venue"
},
  "geometry": {"coordinates":[-70.88282599999999,43.234634],"type":"Point"}
}