{
  "type": "Feature",
  "properties": {
    "iso:country":"US",
    "sg:address":"120 State Rte 101A",
    "sg:city":"Amherst",
    "sg:classifiers":[
        {
            "category":"Shopping",
            "type":"Retail Goods"
        }
    ],
    "sg:phone":"+1 603 883 9535",
    "sg:postcode":"03031",
    "sg:province":"NH",
    "sg:tags":[
        "sport",
        "merchandise",
        "furniture"
    ],
    "wof:name":"Seasonal Specialty Stores",
    "wof:placetype":"venue"
},
  "geometry": {"coordinates":[-71.568493,42.807317],"type":"Point"}
}