{
  "type": "Feature",
  "properties": {
    "addr:full":"68 Highland St Plymouth NH 03264",
    "addr:housenumber":"68",
    "addr:postcode":"03264",
    "addr:street":"Highland St",
    "iso:country":"US",
    "sg:address":"68 Highland St",
    "sg:city":"Plymouth",
    "sg:classifiers":[
        {
            "category":"Personal",
            "subcategory":"Beauty Salon",
            "type":"Services"
        }
    ],
    "sg:phone":"+1 603 536 9844",
    "sg:postcode":"03264",
    "sg:province":"NH",
    "sg:tags":[
        "shop"
    ],
    "wof:name":"Curl Up & Dye Hair Salon",
    "wof:placetype":"venue"
},
  "geometry": {"coordinates":[-71.694766,43.758789],"type":"Point"}
}