{
  "type": "Feature",
  "properties": {
    "iso:country":"US",
    "sg:address":"54 Baboosic Lake Rd",
    "sg:city":"Merrimack",
    "sg:classifiers":[
        {
            "category":"Personal",
            "type":"Services"
        },
        {
            "category":"Wholesale",
            "subcategory":"Scrap",
            "type":"Manufacturing & Wholesale Goods"
        },
        {
            "category":"Shopping",
            "subcategory":"Discount & Variety Stores",
            "type":"Retail Goods"
        },
        {
            "category":"Wholesale",
            "subcategory":"Auto Parts",
            "type":"Manufacturing & Wholesale Goods"
        },
        {
            "category":"Autos & Motor Vehicles",
            "subcategory":"Auto Supplies",
            "type":"Retail Goods"
        }
    ],
    "sg:phone":"+1 603 424 3376",
    "sg:postcode":"03054",
    "sg:province":"NH",
    "sg:tags":[
        "surplus",
        "wrecking",
        "automobile",
        "accessory",
        "rebuilt-wholesale",
        "truck",
        "towing",
        "supplies-used",
        "rebuilt",
        "salvage",
        "merchandise",
        "manufacturer"
    ],
    "wof:name":"Matt's Salvage",
    "wof:placetype":"venue"
},
  "geometry": {"coordinates":[-71.504362,42.868647],"type":"Point"}
}