{
  "type": "Feature",
  "properties": {
    "iso:country":"US",
    "sg:address":"4 Coopers Grove Rd",
    "sg:city":"Kingston",
    "sg:classifiers":[
        {
            "category":"Wholesale",
            "subcategory":"Construction Materials",
            "type":"Manufacturing & Wholesale Goods"
        }
    ],
    "sg:phone":"+1 603 642 7457",
    "sg:postcode":"03848",
    "sg:province":"NH",
    "sg:tags":[
        "fence"
    ],
    "wof:name":"Nelco Fence Builders",
    "wof:placetype":"venue"
},
  "geometry": {"coordinates":[-71.03725300000001,42.908344],"type":"Point"}
}