{
  "type": "Feature",
  "properties": {
    "iso:country":"US",
    "sg:address":"184 Mammoth Rd",
    "sg:city":"Londonderry",
    "sg:classifiers":[
        {
            "category":"Banks & Credit Unions",
            "subcategory":"Bank",
            "type":"Services"
        }
    ],
    "sg:phone":"+1 603 437 5959",
    "sg:postcode":"03053",
    "sg:province":"NH",
    "sg:tags":[
        "loan",
        "real estate"
    ],
    "wof:name":"Ne Merchants Corp Londonberry",
    "wof:placetype":"venue"
},
  "geometry": {"coordinates":[-71.36202400000001,42.837257],"type":"Point"}
}