{
  "type": "Feature",
  "properties": {
    "addr:full":"4 Crescent St Derry NH 03038",
    "addr:housenumber":"4",
    "addr:postcode":"03038",
    "addr:street":"Crescent St",
    "iso:country":"US",
    "sg:address":"4 Crescent St",
    "sg:city":"Derry",
    "sg:classifiers":[
        {
            "category":"Building & Trades",
            "subcategory":"Construction",
            "type":"Services"
        }
    ],
    "sg:phone":"+1 603 759 9289",
    "sg:postcode":"03038",
    "sg:province":"NH",
    "sg:tags":[
        "repair",
        "renovation"
    ],
    "wof:name":"Bobroff Homebuilders",
    "wof:placetype":"venue"
},
  "geometry": {"coordinates":[-71.313188,42.891521],"type":"Point"}
}