{
  "type": "Feature",
  "properties": {
    "iso:country":"US",
    "sg:address":"1 Wood Ave",
    "sg:city":"Derry",
    "sg:classifiers":[
        {
            "category":"Manufacturing",
            "subcategory":"Electronics",
            "type":"Manufacturing & Wholesale Goods"
        }
    ],
    "sg:phone":"+1 603 216 1490",
    "sg:postcode":"03038",
    "sg:province":"NH",
    "sg:tags":[
        "business"
    ],
    "wof:name":"Assembly Plus Inc",
    "wof:placetype":"venue"
},
  "geometry": {"coordinates":[-71.327101,42.866988],"type":"Point"}
}