{
  "type": "Feature",
  "properties": {
    "iso:country":"US",
    "sg:address":"114 Londonderry Tpke",
    "sg:city":"Manchester",
    "sg:classifiers":[
        {
            "category":"Shopping",
            "type":"Retail Goods"
        }
    ],
    "sg:phone":"+1 603 627 1808",
    "sg:postcode":"03104",
    "sg:province":"NH",
    "sg:tags":[
        "merchandise"
    ],
    "wof:name":"Eatons Cake & Candy Supplies",
    "wof:placetype":"venue"
},
  "geometry": {"coordinates":[-71.393486,43.004755],"type":"Point"}
}