{
  "type": "Feature",
  "properties": {
    "iso:country":"US",
    "sg:address":"41 Congress St",
    "sg:city":"Portsmouth",
    "sg:classifiers":[
        {
            "category":"Restaurant",
            "type":"Food & Drink"
        }
    ],
    "sg:phone":"+1 603 427 2504",
    "sg:postcode":"03801",
    "sg:province":"NH",
    "sg:website":"www.bellepeppers.com",
    "wof:name":"Belle Peppers",
    "wof:placetype":"venue"
},
  "geometry": {"coordinates":[-70.758411,43.076812],"type":"Point"}
}