{
  "type": "Feature",
  "properties": {
    "iso:country":"US",
    "sg:address":"62 Market St",
    "sg:city":"Portsmouth",
    "sg:classifiers":[
        {
            "category":"Personal",
            "subcategory":"Tanning Parlor",
            "type":"Services"
        }
    ],
    "sg:phone":"+1 603 431 8827",
    "sg:postcode":"03801",
    "sg:province":"NH",
    "sg:tags":[
        "salon"
    ],
    "wof:name":"Market Street Tub Shop",
    "wof:placetype":"venue"
},
  "geometry": {"coordinates":[-70.757559,43.077637],"type":"Point"}
}