{
  "type": "Feature",
  "properties": {
    "iso:country":"US",
    "sg:address":"302 N Main St",
    "sg:city":"Rochester",
    "sg:classifiers":[
        {
            "category":"Restaurant",
            "type":"Food & Drink"
        }
    ],
    "sg:phone":"+1 603 332 6633",
    "sg:postcode":"03867",
    "sg:province":"NH",
    "wof:name":"Pizza Hut",
    "wof:placetype":"venue"
},
  "geometry": {"coordinates":[-70.994445,43.317676],"type":"Point"}
}