{
  "type": "Feature",
  "properties": {
    "addr:full":"20 Tater St Mont Vernon NH 03057",
    "addr:housenumber":"20",
    "addr:postcode":"03057",
    "addr:street":"Tater St",
    "iso:country":"US",
    "sg:address":"20 Tater St",
    "sg:city":"Mont Vernon",
    "sg:classifiers":[
        {
            "category":"Organizations",
            "subcategory":"Non-profit Organization",
            "type":"Services"
        }
    ],
    "sg:phone":"+1 603 249 9553",
    "sg:postcode":"03057",
    "sg:province":"NH",
    "wof:name":"Institute Of Professional",
    "wof:placetype":"venue"
},
  "geometry": {"coordinates":[-71.666754,42.928485],"type":"Point"}
}