{
  "type": "Feature",
  "properties": {
    "iso:country":"US",
    "sg:address":"157 Portland Ave",
    "sg:city":"Dover",
    "sg:classifiers":[
        {
            "category":"Health Services",
            "subcategory":"Chiropractor",
            "type":"Services"
        }
    ],
    "sg:phone":"+1 603 740 4332",
    "sg:postcode":"03820",
    "sg:province":"NH",
    "wof:name":"Forbes Family Chiropractic",
    "wof:placetype":"venue"
},
  "geometry": {"coordinates":[-70.859539,43.205074],"type":"Point"}
}