{
  "type": "Feature",
  "properties": {
    "addr:full":"24 Shady Ln Plaistow NH 03865",
    "addr:housenumber":"24",
    "addr:postcode":"03865",
    "addr:street":"Shady Ln",
    "iso:country":"US",
    "sg:address":"24 Shady Ln",
    "sg:city":"Plaistow",
    "sg:classifiers":[
        {
            "category":"Insurance",
            "subcategory":"Insurance Agent",
            "type":"Services"
        }
    ],
    "sg:phone":"+1 603 382 1959",
    "sg:postcode":"03865",
    "sg:province":"NH",
    "wof:name":"Insurance Solutions Corp",
    "wof:placetype":"venue"
},
  "geometry": {"coordinates":[-71.105994,42.852101],"type":"Point"}
}