{
  "type": "Feature",
  "properties": {
    "iso:country":"US",
    "sg:address":"43 Melvin Mills Rd",
    "sg:city":"Warner",
    "sg:classifiers":[
        {
            "category":"Manufacturing",
            "subcategory":"Tools & Machinery",
            "type":"Manufacturing & Wholesale Goods"
        }
    ],
    "sg:phone":"+1 603 456 3456",
    "sg:postcode":"03278",
    "sg:province":"NH",
    "sg:tags":[
        "machine",
        "shop"
    ],
    "wof:name":"Techni Cut Inc",
    "wof:placetype":"venue"
},
  "geometry": {"coordinates":[-71.912975,43.268969],"type":"Point"}
}