{
  "type": "Feature",
  "properties": {
    "iso:country":"US",
    "sg:address":"130 Etna Rd",
    "sg:city":"Hanover",
    "sg:classifiers":[
        {
            "category":"Government",
            "subcategory":"Office",
            "type":"Public Place"
        }
    ],
    "sg:phone":"+1 603 643 5269",
    "sg:postcode":"03766",
    "sg:province":"NH",
    "sg:tags":[
        "village"
    ],
    "wof:name":"Hanover Town Office",
    "wof:placetype":"venue"
},
  "geometry": {"coordinates":[-72.23703399999999,43.676849],"type":"Point"}
}