{
  "type": "Feature",
  "properties": {
    "iso:country":"US",
    "sg:address":"143 Fern Ave",
    "sg:city":"Rye",
    "sg:classifiers":[
        {
            "category":"Wholesale",
            "subcategory":"Non-durable Goods",
            "type":"Manufacturing & Wholesale Goods"
        }
    ],
    "sg:phone":"+1 603 964 6868",
    "sg:postcode":"03870",
    "sg:province":"NH",
    "sg:tags":[
        "advertising"
    ],
    "wof:name":"Classic Signature",
    "wof:placetype":"venue"
},
  "geometry": {"coordinates":[-70.781283,42.998627],"type":"Point"}
}