{
  "type": "Feature",
  "properties": {
    "iso:country":"US",
    "sg:address":"150 Greenleaf Ave",
    "sg:city":"Portsmouth",
    "sg:classifiers":[
        {
            "category":"Real Estate",
            "subcategory":"Surveying",
            "type":"Services"
        }
    ],
    "sg:phone":"+1 603 433 1352",
    "sg:postcode":"03801",
    "sg:province":"NH",
    "wof:name":"Cuoco & Cormier Engrg Assoc",
    "wof:placetype":"venue"
},
  "geometry": {"coordinates":[-70.77047899999999,43.05894],"type":"Point"}
}