{
  "type": "Feature",
  "properties": {
    "iso:country":"US",
    "sg:address":"151 Central Ave",
    "sg:city":"Dover",
    "sg:classifiers":[
        {
            "category":"Shopping",
            "subcategory":"Hobbies, Toys, & Games",
            "type":"Retail Goods"
        }
    ],
    "sg:phone":"+1 603 749 5208",
    "sg:postcode":"03820",
    "sg:province":"NH",
    "wof:name":"Wise Woman Wares",
    "wof:placetype":"venue"
},
  "geometry": {"coordinates":[-70.874039,43.188009],"type":"Point"}
}