{
  "type": "Feature",
  "properties": {
    "iso:country":"US",
    "sg:address":"4 Concord Dr",
    "sg:city":"Atkinson",
    "sg:classifiers":[
        {
            "category":"Building & Trades",
            "subcategory":"Construction",
            "type":"Services"
        }
    ],
    "sg:phone":"+1 603 362 8989",
    "sg:postcode":"03811",
    "sg:province":"NH",
    "sg:tags":[
        "nonresidential"
    ],
    "wof:name":"Gigante Constrution",
    "wof:placetype":"venue"
},
  "geometry": {"coordinates":[-71.174014,42.847668],"type":"Point"}
}