{
  "type": "Feature",
  "properties": {
    "iso:country":"US",
    "sg:address":"80 N Main St",
    "sg:city":"Lisbon",
    "sg:classifiers":[
        {
            "category":"Government",
            "subcategory":"Post Office",
            "type":"Public Place"
        }
    ],
    "sg:phone":"+1 603 838 2881",
    "sg:postcode":"03584",
    "sg:province":"NH",
    "sg:tags":[
        "postal",
        "us"
    ],
    "wof:name":"US Post Office",
    "wof:placetype":"venue"
},
  "geometry": {"coordinates":[-71.57585899999999,44.497346],"type":"Point"}
}