{
  "type": "Feature",
  "properties": {
    "iso:country":"US",
    "sg:address":"1 Elm St",
    "sg:city":"Milford",
    "sg:classifiers":[
        {
            "category":"Professional",
            "type":"Services"
        }
    ],
    "sg:phone":"+1 603 249 9403",
    "sg:postcode":"03055",
    "sg:province":"NH",
    "sg:tags":[
        "establishment"
    ],
    "wof:name":"KVS Inc",
    "wof:placetype":"venue"
},
  "geometry": {"coordinates":[-71.654859,42.835324],"type":"Point"}
}