{
  "type": "Feature",
  "properties": {
    "iso:country":"US",
    "sg:address":"9A Warwick Rd",
    "sg:city":"Winchester",
    "sg:classifiers":[
        {
            "category":"Retail",
            "subcategory":"Auto Repair",
            "type":"Services"
        }
    ],
    "sg:phone":"+1 603 239 9991",
    "sg:postcode":"03470",
    "sg:province":"NH",
    "sg:tags":[
        "machine",
        "automobile",
        "shop"
    ],
    "wof:name":"Sekor Machine & Fabricating",
    "wof:placetype":"venue"
},
  "geometry": {"coordinates":[-72.38891700000001,42.766545],"type":"Point"}
}