{
  "type": "Feature",
  "properties": {
    "iso:country":"US",
    "sg:address":"10 Birch Rd",
    "sg:city":"North Hampton",
    "sg:classifiers":[
        {
            "category":"Social Services",
            "type":"Services"
        }
    ],
    "sg:phone":"+1 603 964 1647",
    "sg:postcode":"03862",
    "sg:province":"NH",
    "sg:tags":[
        "youth",
        "organization",
        "center"
    ],
    "wof:name":"North Hampton Youth Assoc",
    "wof:placetype":"venue"
},
  "geometry": {"coordinates":[-70.833291,42.984686],"type":"Point"}
}