{
  "type": "Feature",
  "properties": {
    "iso:country":"US",
    "sg:address":"27 Hill Rd",
    "sg:city":"Franklin",
    "sg:classifiers":[
        {
            "category":"Wholesale",
            "subcategory":"Office Equipment",
            "type":"Manufacturing & Wholesale Goods"
        }
    ],
    "sg:phone":"+1 603 934 1944",
    "sg:postcode":"03235",
    "sg:province":"NH",
    "sg:tags":[
        "machine",
        "duplicating",
        "copying"
    ],
    "wof:name":"Jenorm's Office Machines",
    "wof:placetype":"venue"
},
  "geometry": {"coordinates":[-71.66062700000001,43.460833],"type":"Point"}
}