{
  "type": "Feature",
  "properties": {
    "iso:country":"US",
    "sg:address":"1 Pine St Exd",
    "sg:city":"Nashua",
    "sg:classifiers":[
        {
            "category":"Manufacturing",
            "subcategory":"Tools & Machinery",
            "type":"Manufacturing & Wholesale Goods"
        }
    ],
    "sg:phone":"+1 603 882 8174",
    "sg:postcode":"03060",
    "sg:province":"NH",
    "sg:tags":[
        "shop",
        "repair",
        "industrial",
        "sheet",
        "mfg",
        "metal",
        "machine",
        "welding"
    ],
    "sg:website":"www.nimconet.com",
    "wof:name":"Ultima Nashua Industrial Corp",
    "wof:placetype":"venue"
},
  "geometry": {"coordinates":[-71.475173,42.762713],"type":"Point"}
}