{
  "type": "Feature",
  "properties": {
    "addr:full":"365 Union St Littleton NH 03561",
    "addr:housenumber":"365",
    "addr:postcode":"03561",
    "addr:street":"Union St",
    "iso:country":"US",
    "sg:address":"365 Union St",
    "sg:city":"Littleton",
    "sg:classifiers":[
        {
            "category":"Manufacturing",
            "subcategory":"Printing",
            "type":"Manufacturing & Wholesale Goods"
        }
    ],
    "sg:phone":"+1 603 444 6552",
    "sg:postcode":"03561",
    "sg:province":"NH",
    "sg:tags":[
        "printer"
    ],
    "sg:website":"www.sherwindodgeprinters.com",
    "wof:name":"Sherwin Dodge Printers",
    "wof:placetype":"venue"
},
  "geometry": {"coordinates":[-71.758948,44.30869],"type":"Point"}
}