{
  "type": "Feature",
  "properties": {
    "iso:country":"US",
    "sg:address":"8 Lilac Mall Rd",
    "sg:city":"Rochester",
    "sg:classifiers":[
        {
            "category":"Health Services",
            "subcategory":"Optometrist",
            "type":"Services"
        }
    ],
    "sg:phone":"+1 603 335 6666",
    "sg:postcode":"03867",
    "sg:province":"NH",
    "wof:name":"Jordan Family Eye Care",
    "wof:placetype":"venue"
},
  "geometry": {"coordinates":[-70.975306,43.319406],"type":"Point"}
}