{
  "type": "Feature",
  "properties": {
    "addr:full":"1732 E Conway Rd North Conway NH 03813",
    "addr:housenumber":"1732",
    "addr:postcode":"03813",
    "addr:street":"E Conway Rd",
    "iso:country":"US",
    "sg:address":"1732 E Conway Rd",
    "sg:city":"North Conway",
    "sg:classifiers":[
        {
            "category":"Travel",
            "subcategory":"Hotels & Motels",
            "type":"Entertainment"
        }
    ],
    "sg:phone":"+1 603 356 2551",
    "sg:postcode":"03813",
    "sg:province":"NH",
    "wof:name":"Holiday Inn Express N Conway",
    "wof:placetype":"venue"
},
  "geometry": {"coordinates":[-71.059544,44.011281],"type":"Point"}
}