{
  "type": "Feature",
  "properties": {
    "addr:full":"297 Derry Rd Hudson NH 03051",
    "addr:housenumber":"297",
    "addr:postcode":"03051",
    "addr:street":"Derry Rd",
    "iso:country":"US",
    "sg:address":"297 Derry Rd",
    "sg:city":"Hudson",
    "sg:classifiers":[
        {
            "category":"Restaurant",
            "type":"Food & Drink"
        }
    ],
    "sg:phone":"+1 603 886 9422",
    "sg:postcode":"03051",
    "sg:province":"NH",
    "sg:tags":[
        "shop",
        "fountain",
        "soda"
    ],
    "wof:name":"Findeisen's Ice Cream",
    "wof:placetype":"venue"
},
  "geometry": {"coordinates":[-71.417855,42.815422],"type":"Point"}
}