{
  "type": "Feature",
  "properties": {
    "iso:country":"US",
    "sg:address":"5 Bowers St",
    "sg:city":"Merrimack",
    "sg:classifiers":[
        {
            "category":"Building & Trades",
            "subcategory":"Construction",
            "type":"Services"
        }
    ],
    "sg:phone":"+1 603 883 2132",
    "sg:postcode":"03060",
    "sg:province":"NH",
    "sg:tags":[
        "steel",
        "erection",
        "structural"
    ],
    "wof:name":"Alistair L Wattam",
    "wof:placetype":"venue"
},
  "geometry": {"coordinates":[-71.461157,42.755229],"type":"Point"}
}