{
  "type": "Feature",
  "properties": {
    "iso:country":"US",
    "sg:address":"10 Phillips Dr",
    "sg:city":"Hudson",
    "sg:classifiers":[
        {
            "category":"Shopping",
            "subcategory":"Used Merchandise",
            "type":"Retail Goods"
        }
    ],
    "sg:phone":"+1 603 880 7201",
    "sg:postcode":"03051",
    "sg:province":"NH",
    "wof:name":"Thoughtful Things Inc",
    "wof:placetype":"venue"
},
  "geometry": {"coordinates":[-71.444315,42.778318],"type":"Point"}
}