{
  "type": "Feature",
  "properties": {
    "iso:country":"US",
    "sg:address":"13 Northwestern Dr",
    "sg:city":"Salem",
    "sg:classifiers":[
        {
            "category":"Wholesale",
            "subcategory":"Machinery & Supplies",
            "type":"Manufacturing & Wholesale Goods"
        }
    ],
    "sg:phone":"+1 603 870 9334",
    "sg:postcode":"03079",
    "sg:province":"NH",
    "sg:tags":[
        "equipment",
        "welding"
    ],
    "wof:name":"Airgas",
    "wof:placetype":"venue"
},
  "geometry": {"coordinates":[-71.260407,42.774381],"type":"Point"}
}