{
  "type": "Feature",
  "properties": {
    "iso:country":"US",
    "sg:address":"2 Rock Pond Rd",
    "sg:city":"Windham",
    "sg:classifiers":[
        {
            "category":"Building & Trades",
            "subcategory":"Electrical",
            "type":"Services"
        }
    ],
    "sg:phone":"+1 603 890 8562",
    "sg:postcode":"03087",
    "sg:province":"NH",
    "sg:tags":[
        "electrical",
        "contractor"
    ],
    "wof:name":"Pesaturo Electric",
    "wof:placetype":"venue"
},
  "geometry": {"coordinates":[-71.31809199999999,42.769424],"type":"Point"}
}