{
  "type": "Feature",
  "properties": {
    "addr:full":"920 Lovell Lake Rd Sanbornville NH 03872",
    "addr:housenumber":"920",
    "addr:postcode":"03872",
    "addr:street":"Lovell Lake Rd",
    "iso:country":"US",
    "sg:address":"920 Lovell Lake Rd",
    "sg:city":"Sanbornville",
    "sg:classifiers":[
        {
            "category":"Shopping",
            "subcategory":"Discount & Variety Stores",
            "type":"Retail Goods"
        }
    ],
    "sg:phone":"+1 603 522 6502",
    "sg:postcode":"03872",
    "sg:province":"NH",
    "sg:tags":[
        "merchandise",
        "general"
    ],
    "wof:name":"PR Promotionromotions",
    "wof:placetype":"venue"
},
  "geometry": {"coordinates":[-71.006274,43.538542],"type":"Point"}
}