{
  "type": "Feature",
  "properties": {
    "addr:full":"22 Greeley St Merrimack NH 03054",
    "addr:housenumber":"22",
    "addr:postcode":"03054",
    "addr:street":"Greeley St",
    "iso:country":"US",
    "sg:address":"22 Greeley St",
    "sg:city":"Merrimack",
    "sg:classifiers":[
        {
            "category":"Professional",
            "subcategory":"Engineering",
            "type":"Services"
        }
    ],
    "sg:phone":"+1 603 429 3313",
    "sg:postcode":"03054",
    "sg:province":"NH",
    "sg:tags":[
        "engineer"
    ],
    "wof:name":"SMR Engineering",
    "wof:placetype":"venue"
},
  "geometry": {"coordinates":[-71.48878499999999,42.839896],"type":"Point"}
}