{
  "type": "Feature",
  "properties": {
    "addr:full":"459 Winchester St Keene NH 03431",
    "addr:housenumber":"459",
    "addr:postcode":"03431",
    "addr:street":"Winchester St",
    "iso:country":"US",
    "sg:address":"459 Winchester St",
    "sg:city":"Keene",
    "sg:classifiers":[
        {
            "category":"Organizations",
            "subcategory":"Community Association",
            "type":"Services"
        }
    ],
    "sg:phone":"+1 603 357 0149",
    "sg:postcode":"03431",
    "sg:province":"NH",
    "sg:tags":[
        "club"
    ],
    "wof:name":"Veterans Of Foreign Wars",
    "wof:placetype":"venue"
},
  "geometry": {"coordinates":[-72.292992,42.917406],"type":"Point"}
}