{
  "type": "Feature",
  "properties": {
    "iso:country":"US",
    "sg:address":"137 Laconia Rd",
    "sg:city":"Belmont",
    "sg:classifiers":[
        {
            "category":"Retail",
            "subcategory":"Repair Shop",
            "type":"Services"
        },
        {
            "category":"Autos & Motor Vehicles",
            "subcategory":"Motorcycle Sales",
            "type":"Retail Goods"
        }
    ],
    "sg:phone":"+1 603 528 4118",
    "sg:postcode":"03220",
    "sg:province":"NH",
    "sg:tags":[
        "scooter"
    ],
    "wof:name":"American Cycle Inc",
    "wof:placetype":"venue"
},
  "geometry": {"coordinates":[-71.462515,43.486647],"type":"Point"}
}