{
  "type": "Feature",
  "properties": {
    "iso:country":"US",
    "sg:address":"3 Sanborn Rd",
    "sg:city":"Londonderry",
    "sg:classifiers":[
        {
            "category":"Building & Trades",
            "subcategory":"Construction",
            "type":"Services"
        }
    ],
    "sg:phone":"+1 603 434 8684",
    "sg:postcode":"03053",
    "sg:province":"NH",
    "sg:tags":[
        "general",
        "contractor"
    ],
    "sg:website":"www.mandmengineering.com",
    "wof:name":"M & M Engineering",
    "wof:placetype":"venue"
},
  "geometry": {"coordinates":[-71.38768399999999,42.922123],"type":"Point"}
}