{
  "type": "Feature",
  "properties": {
    "iso:country":"US",
    "sg:address":"51 Tilton Rd",
    "sg:city":"Tilton",
    "sg:classifiers":[
        {
            "category":"Wholesale",
            "subcategory":"Groceries",
            "type":"Manufacturing & Wholesale Goods"
        }
    ],
    "sg:phone":"+1 603 286 7102",
    "sg:postcode":"03276",
    "sg:province":"NH",
    "sg:tags":[
        "baker"
    ],
    "wof:name":"John J Nissen Baking Co",
    "wof:placetype":"venue"
},
  "geometry": {"coordinates":[-71.564863,43.453198],"type":"Point"}
}