{
  "type": "Feature",
  "properties": {
    "iso:country":"US",
    "sg:address":"110 River Rd",
    "sg:city":"Epsom",
    "sg:classifiers":[
        {
            "category":"Building & Trades",
            "subcategory":"Pest Control",
            "type":"Services"
        }
    ],
    "sg:phone":"+1 603 736 4663",
    "sg:postcode":"03234",
    "sg:province":"NH",
    "wof:name":"Bat & Wildlife Ctrl Specialist",
    "wof:placetype":"venue"
},
  "geometry": {"coordinates":[-71.38004100000001,43.187126],"type":"Point"}
}