{
  "type": "Feature",
  "properties": {
    "iso:country":"US",
    "sg:address":"69 Manchester St",
    "sg:city":"Concord",
    "sg:classifiers":[
        {
            "category":"Professional",
            "type":"Services"
        }
    ],
    "sg:phone":"+1 603 226 3586",
    "sg:postcode":"03301",
    "sg:province":"NH",
    "sg:tags":[
        "establishment"
    ],
    "wof:name":"New England Ornamental Metals",
    "wof:placetype":"venue"
},
  "geometry": {"coordinates":[-71.51311699999999,43.191092],"type":"Point"}
}