{
  "type": "Feature",
  "properties": {
    "iso:country":"US",
    "sg:address":"41 Pleasant St",
    "sg:city":"Claremont",
    "sg:classifiers":[
        {
            "category":"Personal",
            "subcategory":"Beauty Salon",
            "type":"Services"
        }
    ],
    "sg:phone":"+1 603 542 5363",
    "sg:postcode":"03743",
    "sg:province":"NH",
    "wof:name":"Shear Expressions Hair Design",
    "wof:placetype":"venue"
},
  "geometry": {"coordinates":[-72.338702,43.371689],"type":"Point"}
}