{
  "type": "Feature",
  "properties": {
    "addr:full":"31 State Rte 3a Plymouth NH 03264",
    "addr:housenumber":"31",
    "addr:postcode":"03264",
    "addr:street":"State Rte 3A",
    "iso:country":"US",
    "sg:address":"31 State Rte 3a",
    "sg:city":"Plymouth",
    "sg:classifiers":[
        {
            "category":"Professional",
            "subcategory":"Art Services",
            "type":"Services"
        }
    ],
    "sg:phone":"+1 603 536 2966",
    "sg:postcode":"03264",
    "sg:province":"NH",
    "sg:tags":[
        "graphic",
        "designer"
    ],
    "sg:website":"www.preseps.com",
    "wof:name":"Preseps Limited",
    "wof:placetype":"venue"
},
  "geometry": {"coordinates":[-71.724193,43.771045],"type":"Point"}
}