{
  "type": "Feature",
  "properties": {
    "iso:country":"US",
    "sg:address":"71 Packers Falls Rd",
    "sg:city":"Newmarket",
    "sg:classifiers":[
        {
            "category":"Retail",
            "subcategory":"Repair Shop",
            "type":"Services"
        }
    ],
    "sg:phone":"+1 603 817 1374",
    "sg:postcode":"03857",
    "sg:province":"NH",
    "sg:tags":[
        "lock",
        "locksmith"
    ],
    "wof:name":"Scotty's Lock",
    "wof:placetype":"venue"
},
  "geometry": {"coordinates":[-70.948087,43.083921],"type":"Point"}
}