{
  "type": "Feature",
  "properties": {
    "addr:full":"3 Crestwood Dr Hollis NH 03049",
    "addr:housenumber":"3",
    "addr:postcode":"03049",
    "addr:street":"Crestwood Dr",
    "iso:country":"US",
    "sg:address":"3 Crestwood Dr",
    "sg:city":"Hollis",
    "sg:classifiers":[
        {
            "category":"Shopping",
            "type":"Retail Goods"
        }
    ],
    "sg:phone":"+1 603 465 2045",
    "sg:postcode":"03049",
    "sg:province":"NH",
    "sg:tags":[
        "equipment",
        "telephone",
        "supply"
    ],
    "wof:name":"Niman's Inc",
    "wof:placetype":"venue"
},
  "geometry": {"coordinates":[-71.558536,42.742746],"type":"Point"}
}