{
  "type": "Feature",
  "properties": {
    "iso:country":"US",
    "sg:address":"30 Main St",
    "sg:city":"Henniker",
    "sg:classifiers":[
        {
            "category":"Restaurant",
            "type":"Food & Drink"
        }
    ],
    "sg:phone":"+1 603 428 7621",
    "sg:postcode":"03242",
    "sg:province":"NH",
    "sg:tags":[
        "banquet",
        "rooms"
    ],
    "sg:website":"www.danielsofhenniker.com",
    "wof:name":"Daniel's Restaurant & Pub",
    "wof:placetype":"venue"
},
  "geometry": {"coordinates":[-71.819445,43.179808],"type":"Point"}
}