{
  "type": "Feature",
  "properties": {
    "iso:country":"US",
    "sg:address":"130 State Rte 10",
    "sg:city":"Piermont",
    "sg:classifiers":[
        {
            "category":"Government",
            "subcategory":"Office",
            "type":"Public Place"
        }
    ],
    "sg:phone":"+1 603 272 4840",
    "sg:postcode":"03779",
    "sg:province":"NH",
    "sg:tags":[
        "village"
    ],
    "wof:name":"Selectmen Office",
    "wof:placetype":"venue"
},
  "geometry": {"coordinates":[-72.080805,43.967805],"type":"Point"}
}