{
  "type": "Feature",
  "properties": {
    "iso:country":"US",
    "sg:address":"100 McGregor St",
    "sg:city":"Manchester",
    "sg:classifiers":[
        {
            "category":"Health Services",
            "subcategory":"Hospital",
            "type":"Services"
        }
    ],
    "sg:phone":"+1 603 663 6170",
    "sg:postcode":"03102",
    "sg:province":"NH",
    "sg:tags":[
        "mental"
    ],
    "wof:name":"Psychiatric Institute-Optima",
    "wof:placetype":"venue"
},
  "geometry": {"coordinates":[-71.47297399999999,42.993007],"type":"Point"}
}