{
  "type": "Feature",
  "properties": {
    "addr:full":"102 Main St Keene NH 03431",
    "addr:housenumber":"102",
    "addr:postcode":"03431",
    "addr:street":"Main St",
    "iso:country":"US",
    "sg:address":"102 Main St",
    "sg:city":"Keene",
    "sg:classifiers":[
        {
            "category":"Insurance",
            "subcategory":"Insurance Agent",
            "type":"Services"
        }
    ],
    "sg:phone":"+1 603 352 2121",
    "sg:postcode":"03431",
    "sg:province":"NH",
    "sg:website":"www.clark-mortenson.com",
    "wof:name":"Clark-Mortenson Agency Inc",
    "wof:placetype":"venue"
},
  "geometry": {"coordinates":[-72.27812900000001,42.931788],"type":"Point"}
}