{
  "type": "Feature",
  "properties": {
    "addr:full":"12 Union St Rochester NH 03867",
    "addr:housenumber":"12",
    "addr:postcode":"03867",
    "addr:street":"Union St",
    "iso:country":"US",
    "sg:address":"12 Union St",
    "sg:city":"Rochester",
    "sg:classifiers":[
        {
            "category":"Restaurant",
            "type":"Food & Drink"
        }
    ],
    "sg:phone":"+1 603 335 3388",
    "sg:postcode":"03867",
    "sg:province":"NH",
    "wof:name":"Main Moon Chinese Restaurant",
    "wof:placetype":"venue"
},
  "geometry": {"coordinates":[-70.978004,43.305349],"type":"Point"}
}