{
  "type": "Feature",
  "properties": {
    "iso:country":"US",
    "sg:address":"303 Great Rd",
    "sg:city":"Jaffrey",
    "sg:classifiers":[
        {
            "category":"Professional",
            "subcategory":"Computer Services",
            "type":"Services"
        }
    ],
    "sg:phone":"+1 603 532 4286",
    "sg:postcode":"03452",
    "sg:province":"NH",
    "sg:tags":[
        "related"
    ],
    "wof:name":"E S B C Consulting",
    "wof:placetype":"venue"
},
  "geometry": {"coordinates":[-72.087202,42.814832],"type":"Point"}
}