{
  "type": "Feature",
  "properties": {
    "addr:full":"69 Pinkham Rd Durham NH 03861",
    "addr:housenumber":"69",
    "addr:postcode":"03861",
    "addr:street":"Pinkham Rd",
    "iso:country":"US",
    "sg:address":"69 Pinkham Rd",
    "sg:city":"Durham",
    "sg:classifiers":[
        {
            "category":"Building & Trades",
            "subcategory":"Construction",
            "type":"Services"
        }
    ],
    "sg:phone":"+1 603 868 7302",
    "sg:postcode":"03861",
    "sg:province":"NH",
    "sg:tags":[
        "house",
        "general",
        "contractor"
    ],
    "wof:name":"ADC Builders",
    "wof:placetype":"venue"
},
  "geometry": {"coordinates":[-70.992734,43.158317],"type":"Point"}
}