{
  "type": "Feature",
  "properties": {
    "addr:full":"15 Hudson Park Dr Hudson NH 03051",
    "addr:housenumber":"15",
    "addr:postcode":"03051",
    "addr:street":"Hudson Park Dr",
    "iso:country":"US",
    "sg:address":"15 Hudson Park Dr",
    "sg:city":"Hudson",
    "sg:classifiers":[
        {
            "category":"Manufacturing",
            "subcategory":"Electronics",
            "type":"Manufacturing & Wholesale Goods"
        }
    ],
    "sg:phone":"+1 603 879 3000",
    "sg:postcode":"03051",
    "sg:province":"NH",
    "sg:tags":[
        "telecom",
        "electronic"
    ],
    "wof:name":"Teradyne Inc",
    "wof:placetype":"venue"
},
  "geometry": {"coordinates":[-71.394659,42.77688],"type":"Point"}
}