{
  "type": "Feature",
  "properties": {
    "iso:country":"US",
    "sg:address":"53 Davis Pl",
    "sg:city":"Laconia",
    "sg:classifiers":[
        {
            "category":"Wholesale",
            "subcategory":"Machinery & Supplies",
            "type":"Manufacturing & Wholesale Goods"
        },
        {
            "category":"Manufacturing",
            "subcategory":"Tools & Machinery",
            "type":"Manufacturing & Wholesale Goods"
        }
    ],
    "sg:phone":"+1 603 524 6766",
    "sg:postcode":"03246",
    "sg:province":"NH",
    "sg:tags":[
        "shop",
        "jobbing",
        "wire",
        "repair",
        "precision",
        "machine"
    ],
    "wof:name":"Levasseur Precision Inc",
    "wof:placetype":"venue"
},
  "geometry": {"coordinates":[-71.465722,43.532817],"type":"Point"}
}