{
  "type": "Feature",
  "properties": {
    "addr:full":"17 Newport Rd New London NH 03257",
    "addr:housenumber":"17",
    "addr:postcode":"03257",
    "addr:street":"Newport Rd",
    "iso:country":"US",
    "sg:address":"17 Newport Rd",
    "sg:city":"New London",
    "sg:classifiers":[
        {
            "category":"Health Services",
            "subcategory":"Health Practitioner",
            "type":"Services"
        }
    ],
    "sg:phone":"+1 603 526 2781",
    "sg:postcode":"03257",
    "sg:province":"NH",
    "sg:tags":[
        "therapist",
        "physical"
    ],
    "wof:name":"Therapy Works",
    "wof:placetype":"venue"
},
  "geometry": {"coordinates":[-71.993071,43.421142],"type":"Point"}
}