{
  "type": "Feature",
  "properties": {
    "iso:country":"US",
    "sg:address":"33 Harriman Rd",
    "sg:city":"Whitefield",
    "sg:classifiers":[
        {
            "category":"Personal",
            "subcategory":"Beauty Salon",
            "type":"Services"
        }
    ],
    "sg:phone":"+1 603 444 2059",
    "sg:postcode":"03598",
    "sg:province":"NH",
    "sg:tags":[
        "shop"
    ],
    "wof:name":"Hair Creations",
    "wof:placetype":"venue"
},
  "geometry": {"coordinates":[-71.728487,44.383454],"type":"Point"}
}