{
  "type": "Feature",
  "properties": {
    "iso:country":"US",
    "sg:address":"114 N Main St",
    "sg:city":"Concord",
    "sg:classifiers":[
        {
            "category":"Wholesale",
            "subcategory":"Computers",
            "type":"Manufacturing & Wholesale Goods"
        }
    ],
    "sg:phone":"+1 603 226 4480",
    "sg:postcode":"03301",
    "sg:province":"NH",
    "sg:tags":[
        "software"
    ],
    "wof:name":"Handmark Inc",
    "wof:placetype":"venue"
},
  "geometry": {"coordinates":[-71.536394,43.20657],"type":"Point"}
}