{
  "type": "Feature",
  "properties": {
    "addr:city":"Meredith",
    "addr:full":"28 Lang St Meredith, Nh 03253",
    "addr:house_number":"28",
    "addr:housenumber":"28",
    "addr:phone":"+1 603-279-6307",
    "addr:postcode":"03253",
    "addr:road":"Lang St",
    "addr:state":"NH",
    "addr:street":"Lang St",
    "iso:country":"US",
    "sg:address":"28 Lang St",
    "sg:city":"Meredith",
    "sg:classifiers":[
        {
            "category":"Museum",
            "type":"Entertainment"
        }
    ],
    "sg:phone":"+1 603 279 6307",
    "sg:postcode":"03253",
    "sg:province":"NH",
    "sg:website":"www.thezeeum.com",
    "wof:name":"Children'S Museum-Meredith",
    "wof:placetype":"venue"
},
  "geometry": {"coordinates":[-71.49892,43.65441],"type":"Point"}
}