{
  "type": "Feature",
  "properties": {
    "addr:full":"28 Lang St Meredith NH 03253",
    "addr:housenumber":"28",
    "addr:postcode":"03253",
    "addr:street":"Lang St",
    "iso:country":"US",
    "sg:address":"28 Lang St",
    "sg:city":"Meredith",
    "sg:classifiers":[
        {
            "category":"Museum",
            "type":"Entertainment"
        }
    ],
    "sg:phone":"+1 603 279 6307",
    "sg:postcode":"03253",
    "sg:province":"NH",
    "sg:website":"www.thezeeum.com",
    "wof:name":"Children's Museum Meredith",
    "wof:placetype":"venue"
},
  "geometry": {"coordinates":[-71.499177,43.652947],"type":"Point"}
}