{
  "type": "Feature",
  "properties": {
    "addr:full":"92 King Rd Bedford NH 03110",
    "addr:housenumber":"92",
    "addr:postcode":"03110",
    "addr:street":"King Rd",
    "iso:country":"US",
    "sg:address":"92 King Rd",
    "sg:city":"Bedford",
    "sg:classifiers":[
        {
            "category":"Professional",
            "subcategory":"Management & Consulting",
            "type":"Services"
        }
    ],
    "sg:phone":"+1 603 471 0330",
    "sg:postcode":"03110",
    "sg:province":"NH",
    "wof:name":"Brown Performance Group Inc",
    "wof:placetype":"venue"
},
  "geometry": {"coordinates":[-71.59262200000001,42.953097],"type":"Point"}
}