{
  "type": "Feature",
  "properties": {
    "iso:country":"US",
    "sg:address":"10 Highland Ave",
    "sg:city":"Gorham",
    "sg:classifiers":[
        {
            "category":"Organizations",
            "subcategory":"Religious Organization",
            "type":"Services"
        }
    ],
    "sg:phone":"+1 603 466 2325",
    "sg:postcode":"03581",
    "sg:province":"NH",
    "sg:tags":[
        "church"
    ],
    "wof:name":"Community Baptist Church Rctry",
    "wof:placetype":"venue"
},
  "geometry": {"coordinates":[-71.190977,44.394096],"type":"Point"}
}