{
  "type": "Feature",
  "properties": {
    "iso:country":"US",
    "sg:address":"495 Center St",
    "sg:city":"Wolfeboro",
    "sg:classifiers":[
        {
            "category":"Building & Trades",
            "subcategory":"Plumbing",
            "type":"Services"
        }
    ],
    "sg:phone":"+1 603 569 9952",
    "sg:postcode":"03894",
    "sg:province":"NH",
    "sg:tags":[
        "conditioning",
        "air",
        "system",
        "contractor"
    ],
    "wof:name":"Warren's Heating & Cooling",
    "wof:placetype":"venue"
},
  "geometry": {"coordinates":[-71.186106,43.607147],"type":"Point"}
}