{
  "type": "Feature",
  "properties": {
    "iso:country":"US",
    "sg:address":"281 Lincoln St",
    "sg:city":"Manchester",
    "sg:classifiers":[
        {
            "category":"Utilities",
            "subcategory":"Water",
            "type":"Services"
        }
    ],
    "sg:phone":"+1 603 624 6494",
    "sg:postcode":"03103",
    "sg:province":"NH",
    "sg:tags":[
        "company",
        "sewage"
    ],
    "wof:name":"Manchester Water Dept",
    "wof:placetype":"venue"
},
  "geometry": {"coordinates":[-71.45067400000001,42.980442],"type":"Point"}
}