{
  "type": "Feature",
  "properties": {
    "iso:country":"US",
    "sg:address":"417 Adams Hill Rd",
    "sg:city":"Greenville",
    "sg:classifiers":[
        {
            "category":"Personal",
            "subcategory":"Shoe Repair & Shine",
            "type":"Services"
        }
    ],
    "sg:phone":"+1 603 878 3347",
    "sg:postcode":"03048",
    "sg:province":"NH",
    "sg:tags":[
        "repairing",
        "boot"
    ],
    "wof:name":"Gary's Boot'n Shoe Repair",
    "wof:placetype":"venue"
},
  "geometry": {"coordinates":[-71.803327,42.782498],"type":"Point"}
}