{
  "type": "Feature",
  "properties": {
    "iso:country":"US",
    "sg:address":"15 Field Rd",
    "sg:city":"Windham",
    "sg:classifiers":[
        {
            "category":"Professional",
            "subcategory":"Computer Services",
            "type":"Services"
        }
    ],
    "sg:phone":"+1 603 595 4585",
    "sg:postcode":"03087",
    "sg:province":"NH",
    "sg:tags":[
        "programing",
        "custom"
    ],
    "wof:name":"Heynow Software",
    "wof:placetype":"venue"
},
  "geometry": {"coordinates":[-71.347587,42.773924],"type":"Point"}
}