{
  "type": "Feature",
  "properties": {
    "iso:country":"US",
    "sg:address":"65 Coburn Woods",
    "sg:city":"Nashua",
    "sg:classifiers":[
        {
            "category":"Professional",
            "subcategory":"Business Services",
            "type":"Services"
        }
    ],
    "sg:phone":"+1 603 595 4505",
    "sg:postcode":"03063",
    "sg:province":"NH",
    "wof:name":"Rohmann Technology Inc",
    "wof:placetype":"venue"
},
  "geometry": {"coordinates":[-71.517111,42.767888],"type":"Point"}
}