{
  "type": "Feature",
  "properties": {
    "addr:full":"134 S Main St Seabrook NH 03874",
    "addr:housenumber":"134",
    "addr:postcode":"03874",
    "addr:street":"S Main St",
    "iso:country":"US",
    "sg:address":"134 S Main St",
    "sg:city":"Seabrook",
    "sg:classifiers":[
        {
            "category":"Organizations",
            "subcategory":"Religious Organization",
            "type":"Services"
        }
    ],
    "sg:phone":"+1 603 474 2703",
    "sg:postcode":"03874",
    "sg:province":"NH",
    "sg:tags":[
        "church"
    ],
    "wof:name":"Rand Memorial Congrgtnal Chr",
    "wof:placetype":"venue"
},
  "geometry": {"coordinates":[-70.850268,42.866783],"type":"Point"}
}