{
  "type": "Feature",
  "properties": {
    "addr:full":"75 Woodward Rd Merrimack NH 03054",
    "addr:housenumber":"75",
    "addr:postcode":"03054",
    "addr:street":"Woodward Rd",
    "iso:country":"US",
    "sg:address":"75 Woodward Rd",
    "sg:city":"Merrimack",
    "sg:classifiers":[
        {
            "category":"Real Estate",
            "subcategory":"Real Estate Agent",
            "type":"Services"
        }
    ],
    "sg:phone":"+1 603 424 3359",
    "sg:postcode":"03054",
    "sg:province":"NH",
    "sg:tags":[
        "inspection"
    ],
    "wof:name":"Homestead Inspections Of NH",
    "wof:placetype":"venue"
},
  "geometry": {"coordinates":[-71.555396,42.898113],"type":"Point"}
}