{
  "type": "Feature",
  "properties": {
    "iso:country":"US",
    "sg:address":"55 Main St",
    "sg:city":"Antrim",
    "sg:classifiers":[
        {
            "category":"Social Services",
            "type":"Services"
        }
    ],
    "sg:phone":"+1 603 588 3124",
    "sg:postcode":"03440",
    "sg:province":"NH",
    "sg:tags":[
        "organization",
        "welfare"
    ],
    "wof:name":"Lutheran Social Svc",
    "wof:placetype":"venue"
},
  "geometry": {"coordinates":[-71.93777300000001,43.027827],"type":"Point"}
}