{
  "type": "Feature",
  "properties": {
    "iso:country":"US",
    "sg:address":"5 George Ave",
    "sg:city":"Londonderry",
    "sg:classifiers":[
        {
            "category":"Professional",
            "subcategory":"Art Services",
            "type":"Services"
        }
    ],
    "sg:phone":"+1 603 623 9190",
    "sg:postcode":"03053",
    "sg:province":"NH",
    "sg:tags":[
        "screen",
        "silk"
    ],
    "wof:name":"Superior Silk Screen Inc",
    "wof:placetype":"venue"
},
  "geometry": {"coordinates":[-71.425872,42.932449],"type":"Point"}
}