{
  "type": "Feature",
  "properties": {
    "iso:country":"US",
    "sg:address":"16 Fox Point Rd",
    "sg:city":"Newington",
    "sg:classifiers":[
        {
            "category":"Wholesale",
            "subcategory":"Furniture",
            "type":"Manufacturing & Wholesale Goods"
        },
        {
            "category":"Home & Garden",
            "subcategory":"Furniture",
            "type":"Retail Goods"
        }
    ],
    "sg:phone":"+1 603 430 8443",
    "sg:postcode":"03801",
    "sg:province":"NH",
    "sg:tags":[
        "store",
        "furniture-wholesale",
        "manufacturer"
    ],
    "wof:name":"Link Sales & Mktg",
    "wof:placetype":"venue"
},
  "geometry": {"coordinates":[-70.823027,43.103726],"type":"Point"}
}