{
  "type": "Feature",
  "properties": {
    "iso:country":"US",
    "sg:address":"104 Lily Pond Rd",
    "sg:city":"Gilford",
    "sg:classifiers":[
        {
            "category":"Building & Trades",
            "subcategory":"Construction",
            "type":"Services"
        }
    ],
    "sg:phone":"+1 603 524 3128",
    "sg:postcode":"03249",
    "sg:province":"NH",
    "sg:tags":[
        "general",
        "contractor"
    ],
    "sg:website":"www.woodandclay.com",
    "wof:name":"Wood & Clay Inc",
    "wof:placetype":"venue"
},
  "geometry": {"coordinates":[-71.43249,43.57307],"type":"Point"}
}