{
  "type": "Feature",
  "properties": {
    "iso:country":"US",
    "sg:address":"79 Pleasant St",
    "sg:city":"Concord",
    "sg:classifiers":[
        {
            "category":"Social Services",
            "type":"Services"
        }
    ],
    "sg:phone":"+1 603 228 1686",
    "sg:postcode":"03301",
    "sg:province":"NH",
    "sg:tags":[
        "a",
        "as",
        "individual",
        "specifically",
        "family"
    ],
    "wof:name":"Group Home",
    "wof:placetype":"venue"
},
  "geometry": {"coordinates":[-71.541845,43.201522],"type":"Point"}
}