{
  "type": "Feature",
  "properties": {
    "iso:country":"US",
    "sg:address":"53 Wadleigh Point Rd",
    "sg:city":"Kingston",
    "sg:classifiers":[
        {
            "category":"Retail",
            "subcategory":"Animal Services",
            "type":"Services"
        }
    ],
    "sg:phone":"+1 603 642 3673",
    "sg:postcode":"03848",
    "sg:province":"NH",
    "wof:name":"Heckman Kennels",
    "wof:placetype":"venue"
},
  "geometry": {"coordinates":[-71.067763,42.912416],"type":"Point"}
}