{
  "type": "Feature",
  "properties": {
    "addr:full":"6 Bailey Ave Claremont NH 03743",
    "addr:housenumber":"6",
    "addr:postcode":"03743",
    "addr:street":"Bailey Ave",
    "iso:country":"US",
    "sg:address":"6 Bailey Ave",
    "sg:city":"Claremont",
    "sg:classifiers":[
        {
            "category":"Real Estate",
            "subcategory":"Real Estate Operator",
            "type":"Services"
        }
    ],
    "sg:phone":"+1 603 542 0002",
    "sg:postcode":"03743",
    "sg:province":"NH",
    "sg:tags":[
        "apartment"
    ],
    "wof:name":"Claremont Real Estate Mgnt",
    "wof:placetype":"venue"
},
  "geometry": {"coordinates":[-72.33465200000001,43.369602],"type":"Point"}
}