{
  "type": "Feature",
  "properties": {
    "addr:full":"320 Main St Sandown NH 03873",
    "addr:housenumber":"320",
    "addr:postcode":"03873",
    "addr:street":"Main St",
    "iso:country":"US",
    "sg:address":"320 Main St",
    "sg:city":"Sandown",
    "sg:classifiers":[
        {
            "category":"Government",
            "subcategory":"Office",
            "type":"Public Place"
        }
    ],
    "sg:phone":"+1 603 887 4870",
    "sg:postcode":"03873",
    "sg:province":"NH",
    "sg:tags":[
        "city"
    ],
    "wof:name":"Sandown Town Clerk",
    "wof:placetype":"venue"
},
  "geometry": {"coordinates":[-71.187,42.927122],"type":"Point"}
}