{
  "type": "Feature",
  "properties": {
    "iso:country":"US",
    "sg:address":"615 Ocean Blvd",
    "sg:city":"Hampton",
    "sg:classifiers":[
        {
            "category":"Real Estate",
            "subcategory":"Real Estate Services",
            "type":"Services"
        }
    ],
    "sg:phone":"+1 603 929 1500",
    "sg:postcode":"03842",
    "sg:province":"NH",
    "sg:tags":[
        "vacancy",
        "rental",
        "listing"
    ],
    "wof:name":"Holiday Shore Condo Rental",
    "wof:placetype":"venue"
},
  "geometry": {"coordinates":[-70.799177,42.925337],"type":"Point"}
}