{
  "type": "Feature",
  "properties": {
    "iso:country":"US",
    "sg:address":"39 Ceres St",
    "sg:city":"Portsmouth",
    "sg:classifiers":[
        {
            "category":"Professional",
            "subcategory":"Art Services",
            "type":"Services"
        }
    ],
    "sg:phone":"+1 603 433 4131",
    "sg:postcode":"03801",
    "sg:province":"NH",
    "sg:tags":[
        "commercial",
        "design"
    ],
    "wof:name":"Tara Peck",
    "wof:placetype":"venue"
},
  "geometry": {"coordinates":[-70.75831700000001,43.079283],"type":"Point"}
}