{
  "type": "Feature",
  "properties": {
    "iso:country":"US",
    "sg:address":"4 Merrit Pkwy",
    "sg:city":"Nashua",
    "sg:classifiers":[
        {
            "category":"Social Services",
            "subcategory":"Child Care",
            "type":"Services"
        }
    ],
    "sg:phone":"+1 603 881 4815",
    "sg:postcode":"03062",
    "sg:province":"NH",
    "sg:tags":[
        "day"
    ],
    "sg:website":"www.tnotlc.com",
    "wof:name":"Nature Of Things",
    "wof:placetype":"venue"
},
  "geometry": {"coordinates":[-71.50492300000001,42.716679],"type":"Point"}
}