{
  "type": "Feature",
  "properties": {
    "iso:country":"US",
    "sg:address":"453 2nd St",
    "sg:city":"Manchester",
    "sg:classifiers":[
        {
            "category":"Insurance",
            "subcategory":"Insurance Agent",
            "type":"Services"
        }
    ],
    "sg:phone":"+1 603 666 3202",
    "sg:postcode":"03102",
    "sg:province":"NH",
    "wof:name":"Connie Cantin Agency",
    "wof:placetype":"venue"
},
  "geometry": {"coordinates":[-71.47468499999999,42.976056],"type":"Point"}
}