{
  "type": "Feature",
  "properties": {
    "addr:full":"11 Lone Birch Trl Tamworth NH 03817",
    "addr:housenumber":"11",
    "addr:postcode":"03817",
    "addr:street":"Lone Birch Trl",
    "iso:country":"US",
    "sg:address":"11 Lone Birch Trl",
    "sg:city":"Tamworth",
    "sg:classifiers":[
        {
            "category":"Building & Trades",
            "subcategory":"Cleaning & Sanitation",
            "type":"Services"
        }
    ],
    "sg:phone":"+1 603 323 7441",
    "sg:postcode":"03817",
    "sg:province":"NH",
    "sg:tags":[
        "fireplace",
        "chimney"
    ],
    "wof:name":"Ossipee Valley Chimney Sweep",
    "wof:placetype":"venue"
},
  "geometry": {"coordinates":[-71.212397,43.841393],"type":"Point"}
}