{
  "type": "Feature",
  "properties": {
    "iso:country":"US",
    "sg:address":"195 McGregor St",
    "sg:city":"Manchester",
    "sg:classifiers":[
        {
            "category":"Health Services",
            "subcategory":"Clinic",
            "type":"Services"
        },
        {
            "category":"Health Services",
            "subcategory":"Doctor",
            "type":"Services"
        }
    ],
    "sg:phone":"+1 603 647 9325",
    "sg:postcode":"03102",
    "sg:province":"NH",
    "sg:tags":[
        "medical"
    ],
    "wof:name":"Anesthesia Care Group PC",
    "wof:placetype":"venue"
},
  "geometry": {"coordinates":[-71.473793,42.991219],"type":"Point"}
}