{
  "type": "Feature",
  "properties": {
    "iso:country":"US",
    "sg:address":"72 Yeaton Rd",
    "sg:city":"Plymouth",
    "sg:classifiers":[
        {
            "category":"Personal",
            "type":"Services"
        }
    ],
    "sg:phone":"+1 603 536 7288",
    "sg:postcode":"03264",
    "sg:province":"NH",
    "wof:name":"MBC Co",
    "wof:placetype":"venue"
},
  "geometry": {"coordinates":[-71.75345,43.766634],"type":"Point"}
}