{
  "type": "Feature",
  "properties": {
    "addr:full":"276 State Rte 9 Barrington NH 03825",
    "addr:housenumber":"276",
    "addr:postcode":"03825",
    "addr:street":"State Rte 9",
    "iso:country":"US",
    "sg:address":"276 State Rte 9",
    "sg:city":"Barrington",
    "sg:classifiers":[
        {
            "category":"Retail",
            "subcategory":"Repair Shop",
            "type":"Services"
        }
    ],
    "sg:phone":"+1 603 664 8911",
    "sg:postcode":"03825",
    "sg:province":"NH",
    "wof:name":"Saving Memories Taxidermy",
    "wof:placetype":"venue"
},
  "geometry": {"coordinates":[-71.024016,43.216116],"type":"Point"}
}