{
  "type": "Feature",
  "properties": {
    "iso:country":"US",
    "sg:address":"15 Elm St",
    "sg:city":"Goffstown",
    "sg:classifiers":[
        {
            "category":"Retail",
            "subcategory":"Veterinary Services",
            "type":"Services"
        }
    ],
    "sg:phone":"+1 603 497 4113",
    "sg:postcode":"03045",
    "sg:province":"NH",
    "sg:tags":[
        "veterinarian"
    ],
    "wof:name":"Glen Lake Animal Hospital",
    "wof:placetype":"venue"
},
  "geometry": {"coordinates":[-71.59749600000001,43.020188],"type":"Point"}
}