{
  "type": "Feature",
  "properties": {
    "iso:country":"US",
    "sg:address":"79 Manchester St",
    "sg:city":"Concord",
    "sg:classifiers":[
        {
            "category":"Autos & Motor Vehicles",
            "subcategory":"Recreational Vehicle Sales",
            "type":"Retail Goods"
        }
    ],
    "sg:phone":"+1 603 228 8600",
    "sg:postcode":"03301",
    "sg:province":"NH",
    "sg:website":"www.outdoorsportscenter.net",
    "wof:name":"Outdoor Sports Center Inc",
    "wof:placetype":"venue"
},
  "geometry": {"coordinates":[-71.51112000000001,43.190588],"type":"Point"}
}