{
  "type": "Feature",
  "properties": {
    "iso:country":"US",
    "sg:address":"16 Lawrence Rd",
    "sg:city":"Salem",
    "sg:classifiers":[
        {
            "category":"Building & Trades",
            "subcategory":"Construction",
            "type":"Services"
        }
    ],
    "sg:phone":"+1 603 893 1213",
    "sg:postcode":"03079",
    "sg:province":"NH",
    "sg:tags":[
        "contractor"
    ],
    "wof:name":"Richard Keyes & Sons",
    "wof:placetype":"venue"
},
  "geometry": {"coordinates":[-71.203377,42.785952],"type":"Point"}
}