{
  "type": "Feature",
  "properties": {
    "iso:country":"US",
    "sg:address":"1263 Winona Rd",
    "sg:city":"New Hampton",
    "sg:classifiers":[
        {
            "category":"Professional",
            "subcategory":"Employment Agencies",
            "type":"Services"
        }
    ],
    "sg:phone":"+1 603 968 7167",
    "sg:postcode":"03256",
    "sg:province":"NH",
    "sg:tags":[
        "supply",
        "cleaning",
        "help"
    ],
    "wof:name":"Chandler Enterprises",
    "wof:placetype":"venue"
},
  "geometry": {"coordinates":[-71.59686000000001,43.688485],"type":"Point"}
}