{
  "type": "Feature",
  "properties": {
    "iso:country":"US",
    "sg:address":"1855 Woodbury Ave",
    "sg:city":"Portsmouth",
    "sg:classifiers":[
        {
            "category":"Restaurant",
            "type":"Food & Drink"
        }
    ],
    "sg:phone":"+1 603 431 7577",
    "sg:postcode":"03801",
    "sg:province":"NH",
    "sg:tags":[
        "eating",
        "pizza"
    ],
    "sg:website":"http://www.pizzahut.com",
    "wof:name":"Pizza Hut",
    "wof:placetype":"venue"
},
  "geometry": {"coordinates":[-70.792877,43.0924],"type":"Point"}
}