{
  "type": "Feature",
  "properties": {
    "iso:country":"US",
    "sg:address":"36 Mill St",
    "sg:city":"Wolfeboro",
    "sg:classifiers":[
        {
            "category":"Shopping",
            "subcategory":"Used Merchandise",
            "type":"Retail Goods"
        }
    ],
    "sg:phone":"+1 603 569 1113",
    "sg:postcode":"03894",
    "sg:province":"NH",
    "sg:tags":[
        "shop",
        "consignment"
    ],
    "wof:name":"Re Threads Resale Clothing",
    "wof:placetype":"venue"
},
  "geometry": {"coordinates":[-71.215112,43.585472],"type":"Point"}
}