{
  "type": "Feature",
  "properties": {
    "addr:full":"18 Pearl St Keene NH 03431",
    "addr:housenumber":"18",
    "addr:postcode":"03431",
    "addr:street":"Pearl St",
    "iso:country":"US",
    "sg:address":"18 Pearl St",
    "sg:city":"Keene",
    "sg:classifiers":[
        {
            "category":"Building & Trades",
            "subcategory":"Construction",
            "type":"Services"
        }
    ],
    "sg:phone":"+1 603 358 6897",
    "sg:postcode":"03431",
    "sg:province":"NH",
    "sg:tags":[
        "house"
    ],
    "wof:name":"JAS Realty Improvements",
    "wof:placetype":"venue"
},
  "geometry": {"coordinates":[-72.291944,42.932485],"type":"Point"}
}