{
  "type": "Feature",
  "properties": {
    "iso:country":"US",
    "sg:address":"195 Portsmouth Ave",
    "sg:city":"Greenland",
    "sg:classifiers":[
        {
            "category":"Retail",
            "subcategory":"Animal Services",
            "type":"Services"
        }
    ],
    "sg:phone":"+1 603 433 1229",
    "sg:postcode":"03840",
    "sg:province":"NH",
    "wof:name":"Catspaw Feline Boarding",
    "wof:placetype":"venue"
},
  "geometry": {"coordinates":[-70.82458699999999,43.046811],"type":"Point"}
}