{
  "type": "Feature",
  "properties": {
    "iso:country":"US",
    "sg:address":"30 Hammond Rd",
    "sg:city":"Milford",
    "sg:classifiers":[
        {
            "category":"Home & Garden",
            "subcategory":"Furniture",
            "type":"Retail Goods"
        }
    ],
    "sg:phone":"+1 603 673 7972",
    "sg:postcode":"03055",
    "sg:province":"NH",
    "sg:tags":[
        "store"
    ],
    "sg:website":"http://www.willettefurniture.com",
    "wof:name":"Willette Fine Furniture",
    "wof:placetype":"venue"
},
  "geometry": {"coordinates":[-71.64496800000001,42.81887],"type":"Point"}
}