{
  "type": "Feature",
  "properties": {
    "addr:full":"34 W Bow St Franklin NH 03235",
    "addr:housenumber":"34",
    "addr:postcode":"03235",
    "addr:street":"W Bow St",
    "iso:country":"US",
    "sg:address":"34 W Bow St",
    "sg:city":"Franklin",
    "sg:classifiers":[
        {
            "category":"Building & Trades",
            "subcategory":"Construction",
            "type":"Services"
        }
    ],
    "sg:phone":"+1 603 934 7164",
    "sg:postcode":"03235",
    "sg:province":"NH",
    "sg:tags":[
        "carpentry",
        "contractor"
    ],
    "wof:name":"Jimmy Yank",
    "wof:placetype":"venue"
},
  "geometry": {"coordinates":[-71.652006,43.447258],"type":"Point"}
}