{
  "type": "Feature",
  "properties": {
    "iso:country":"US",
    "sg:address":"160 Emerald St",
    "sg:city":"Keene",
    "sg:classifiers":[
        {
            "category":"Professional",
            "subcategory":"Management & Consulting",
            "type":"Services"
        }
    ],
    "sg:phone":"+1 603 352 3691",
    "sg:postcode":"03431",
    "sg:province":"NH",
    "sg:tags":[
        "consultant",
        "business"
    ],
    "wof:name":"Close Communications",
    "wof:placetype":"venue"
},
  "geometry": {"coordinates":[-72.28446599999999,42.930355],"type":"Point"}
}