{
  "type": "Feature",
  "properties": {
    "iso:country":"US",
    "sg:address":"140 F W Hartford Dr",
    "sg:city":"Portsmouth",
    "sg:classifiers":[
        {
            "category":"Building & Trades",
            "subcategory":"Construction",
            "type":"Services"
        }
    ],
    "sg:phone":"+1 603 436 2150",
    "sg:postcode":"03801",
    "sg:province":"NH",
    "sg:tags":[
        "house"
    ],
    "wof:name":"Hancock Builders",
    "wof:placetype":"venue"
},
  "geometry": {"coordinates":[-70.772507,43.035578],"type":"Point"}
}