{
  "type": "Feature",
  "properties": {
    "iso:country":"US",
    "sg:address":"21 Clement St",
    "sg:city":"Nashua",
    "sg:classifiers":[
        {
            "category":"Wholesale",
            "subcategory":"Machinery & Supplies",
            "type":"Manufacturing & Wholesale Goods"
        }
    ],
    "sg:phone":"+1 603 883 7372",
    "sg:postcode":"03060",
    "sg:province":"NH",
    "wof:name":"Joseph Deluca",
    "wof:placetype":"venue"
},
  "geometry": {"coordinates":[-71.45728699999999,42.742754],"type":"Point"}
}