{
  "type": "Feature",
  "properties": {
    "iso:country":"US",
    "sg:address":"49 State Rte 16B",
    "sg:city":"Jackson",
    "sg:classifiers":[
        {
            "category":"Building & Trades",
            "subcategory":"Construction",
            "type":"Services"
        }
    ],
    "sg:phone":"+1 603 383 9233",
    "sg:postcode":"03814",
    "sg:province":"NH",
    "sg:tags":[
        "general",
        "contractor"
    ],
    "wof:name":"Mallett Co",
    "wof:placetype":"venue"
},
  "geometry": {"coordinates":[-71.141831,43.754158],"type":"Point"}
}