{
  "type": "Feature",
  "properties": {
    "addr:full":"125 Ocean Rd Greenland NH 03840",
    "addr:housenumber":"125",
    "addr:postcode":"03840",
    "addr:street":"Ocean Rd",
    "iso:country":"US",
    "sg:address":"125 Ocean Rd",
    "sg:city":"Greenland",
    "sg:classifiers":[
        {
            "category":"Building & Trades",
            "subcategory":"Construction",
            "type":"Services"
        }
    ],
    "sg:phone":"+1 603 436 6350",
    "sg:postcode":"03840",
    "sg:province":"NH",
    "sg:tags":[
        "general",
        "contractor"
    ],
    "wof:name":"H L Patten Construction Inc",
    "wof:placetype":"venue"
},
  "geometry": {"coordinates":[-70.81841799999999,43.043896],"type":"Point"}
}