{
  "type": "Feature",
  "properties": {
    "iso:country":"US",
    "sg:address":"963 Mason Rd",
    "sg:city":"Wilton",
    "sg:classifiers":[
        {
            "category":"Professional",
            "type":"Services"
        }
    ],
    "sg:phone":"+1 603 654 2107",
    "sg:postcode":"03086",
    "sg:province":"NH",
    "sg:tags":[
        "establishment"
    ],
    "wof:name":"Migneault & Migneault",
    "wof:placetype":"venue"
},
  "geometry": {"coordinates":[-71.737056,42.802901],"type":"Point"}
}