{
  "type": "Feature",
  "properties": {
    "iso:country":"US",
    "sg:address":"10 Hampshire Ln",
    "sg:city":"Londonderry",
    "sg:classifiers":[
        {
            "category":"Insurance",
            "subcategory":"Insurance Agent",
            "type":"Services"
        }
    ],
    "sg:phone":"+1 603 434 1966",
    "sg:postcode":"03053",
    "sg:province":"NH",
    "sg:tags":[
        "medical"
    ],
    "wof:name":"Clifton Associates",
    "wof:placetype":"venue"
},
  "geometry": {"coordinates":[-71.378681,42.855788],"type":"Point"}
}