{
  "type": "Feature",
  "properties": {
    "iso:country":"US",
    "sg:address":"339 S Broadway",
    "sg:city":"Salem",
    "sg:classifiers":[
        {
            "category":"Restaurant",
            "type":"Food & Drink"
        }
    ],
    "sg:phone":"+1 603 898 8888",
    "sg:postcode":"03079",
    "sg:province":"NH",
    "sg:tags":[
        "chinese"
    ],
    "sg:website":"http://www.newgarden.com",
    "wof:name":"New Garden",
    "wof:placetype":"venue"
},
  "geometry": {"coordinates":[-71.208275,42.754498],"type":"Point"}
}