{
  "type": "Feature",
  "properties": {
    "iso:country":"US",
    "sg:address":"751 S Mast Rd",
    "sg:city":"Manchester",
    "sg:classifiers":[
        {
            "category":"Sports & Exercise",
            "subcategory":"Bowling",
            "type":"Entertainment"
        }
    ],
    "sg:phone":"+1 603 623 9215",
    "sg:postcode":"03102",
    "sg:province":"NH",
    "sg:tags":[
        "center"
    ],
    "sg:website":"www.kinglanes.com",
    "wof:name":"King's Bowling Lanes",
    "wof:placetype":"venue"
},
  "geometry": {"coordinates":[-71.500176,42.990776],"type":"Point"}
}