{
  "type": "Feature",
  "properties": {
    "iso:country":"US",
    "sg:address":"45 Forest St",
    "sg:city":"Bradford",
    "sg:classifiers":[
        {
            "category":"Manufacturing",
            "subcategory":"Printing",
            "type":"Manufacturing & Wholesale Goods"
        }
    ],
    "sg:phone":"+1 603 938 2829",
    "sg:postcode":"03221",
    "sg:province":"NH",
    "sg:tags":[
        "newspaper"
    ],
    "sg:website":"www.thesmartadvertiser.com",
    "wof:name":"Smart Advertiser",
    "wof:placetype":"venue"
},
  "geometry": {"coordinates":[-71.923333,43.236916],"type":"Point"}
}