{
  "type": "Feature",
  "properties": {
    "addr:full":"87 Factory St Nashua NH 03060",
    "addr:housenumber":"87",
    "addr:postcode":"03060",
    "addr:street":"Factory St",
    "iso:country":"US",
    "sg:address":"87 Factory St",
    "sg:city":"Nashua",
    "sg:classifiers":[
        {
            "category":"Professional",
            "type":"Services"
        }
    ],
    "sg:phone":"+1 603 883 0601",
    "sg:postcode":"03060",
    "sg:province":"NH",
    "sg:tags":[
        "establishment"
    ],
    "wof:name":"Clocktower Place",
    "wof:placetype":"venue"
},
  "geometry": {"coordinates":[-71.46911799999999,42.760132],"type":"Point"}
}