{
  "type": "Feature",
  "properties": {
    "iso:country":"US",
    "sg:address":"74 Litchfield Rd",
    "sg:city":"Londonderry",
    "sg:classifiers":[
        {
            "category":"Building & Trades",
            "subcategory":"Landscaping Services",
            "type":"Services"
        }
    ],
    "sg:phone":"+1 603 437 1104",
    "sg:postcode":"03053",
    "sg:province":"NH",
    "sg:tags":[
        "landscape"
    ],
    "wof:name":"Fieldstone Nursery",
    "wof:placetype":"venue"
},
  "geometry": {"coordinates":[-71.40725399999999,42.896463],"type":"Point"}
}