{
  "type": "Feature",
  "properties": {
    "addr:full":"7 Graham Dr Nashua NH 03060",
    "addr:housenumber":"7",
    "addr:postcode":"03060",
    "addr:street":"Graham Dr",
    "iso:country":"US",
    "sg:address":"7 Graham Dr",
    "sg:city":"Nashua",
    "sg:classifiers":[
        {
            "category":"Utilities",
            "subcategory":"Mobile Phone",
            "type":"Services"
        },
        {
            "category":"Utilities",
            "subcategory":"Telephone",
            "type":"Services"
        },
        {
            "category":"Communications",
            "type":"Services"
        },
        {
            "category":"Professional",
            "subcategory":"Computer Services",
            "type":"Services"
        }
    ],
    "sg:phone":"+1 603 888 3540",
    "sg:postcode":"03060",
    "sg:province":"NH",
    "sg:tags":[
        "telecommunication",
        "cellular"
    ],
    "sg:website":"http://www.verizonwireless.com",
    "wof:name":"Verizon Wireless",
    "wof:placetype":"venue"
},
  "geometry": {"coordinates":[-71.44871000000001,42.729724],"type":"Point"}
}