{
  "type": "Feature",
  "properties": {
    "iso:country":"US",
    "sg:address":"1130 Eastman Rd",
    "sg:city":"North Conway",
    "sg:classifiers":[
        {
            "category":"Wholesale",
            "subcategory":"Computers",
            "type":"Manufacturing & Wholesale Goods"
        },
        {
            "category":"Professional",
            "subcategory":"Computer Services",
            "type":"Services"
        }
    ],
    "sg:phone":"+1 603 356 7161",
    "sg:postcode":"03860",
    "sg:province":"NH",
    "sg:tags":[
        "repair"
    ],
    "wof:name":"Computer Port",
    "wof:placetype":"venue"
},
  "geometry": {"coordinates":[-71.088246,44.001555],"type":"Point"}
}