{
  "type": "Feature",
  "properties": {
    "iso:country":"US",
    "sg:address":"317 Elm St",
    "sg:city":"Manchester",
    "sg:classifiers":[
        {
            "category":"Shopping",
            "type":"Retail Goods"
        }
    ],
    "sg:phone":"+1 603 668 1100",
    "sg:postcode":"03101",
    "sg:province":"NH",
    "sg:tags":[
        "home",
        "medical",
        "rental"
    ],
    "wof:name":"American Homecare Supply LLC",
    "wof:placetype":"venue"
},
  "geometry": {"coordinates":[-71.462998,42.982538],"type":"Point"}
}