{
  "type": "Feature",
  "properties": {
    "iso:country":"US",
    "sg:address":"77 Elwyn Ave",
    "sg:city":"Portsmouth",
    "sg:classifiers":[
        {
            "category":"Real Estate",
            "subcategory":"Real Estate Agent",
            "type":"Services"
        }
    ],
    "sg:phone":"+1 603 427 1770",
    "sg:postcode":"03801",
    "sg:province":"NH",
    "wof:name":"B N & A Realty Corp",
    "wof:placetype":"venue"
},
  "geometry": {"coordinates":[-70.757161,43.070508],"type":"Point"}
}