{
  "type": "Feature",
  "properties": {
    "iso:country":"US",
    "sg:address":"56 Middle St",
    "sg:city":"Portsmouth",
    "sg:classifiers":[
        {
            "category":"Professional",
            "subcategory":"Lawyer & Legal Services",
            "type":"Services"
        }
    ],
    "sg:phone":"+1 603 433 1830",
    "sg:postcode":"03801",
    "sg:province":"NH",
    "sg:tags":[
        "attorney"
    ],
    "wof:name":"Griffin Pudloski & Jenkins",
    "wof:placetype":"venue"
},
  "geometry": {"coordinates":[-70.767054,43.065832],"type":"Point"}
}