{
  "type": "Feature",
  "properties": {
    "iso:country":"US",
    "sg:address":"434 Stockdale Cir",
    "sg:city":"Rollinsford",
    "sg:classifiers":[
        {
            "category":"Building & Trades",
            "subcategory":"Electrical",
            "type":"Services"
        }
    ],
    "sg:phone":"+1 603 742 1456",
    "sg:postcode":"03869",
    "sg:province":"NH",
    "sg:tags":[
        "electric",
        "contractor"
    ],
    "wof:name":"Bunker Electric",
    "wof:placetype":"venue"
},
  "geometry": {"coordinates":[-70.829325,43.231838],"type":"Point"}
}