{
  "type": "Feature",
  "properties": {
    "addr:full":"1094 State Rte 12 Plainfield NH 03781",
    "addr:housenumber":"1094",
    "addr:postcode":"03781",
    "addr:street":"State Rte 12",
    "iso:country":"US",
    "sg:address":"1094 State Rte 12",
    "sg:city":"Plainfield",
    "sg:classifiers":[
        {
            "category":"Organizations",
            "subcategory":"Religious Organization",
            "type":"Services"
        }
    ],
    "sg:phone":"+1 603 675 6510",
    "sg:postcode":"03781",
    "sg:province":"NH",
    "sg:tags":[
        "church"
    ],
    "wof:name":"Community Baptist Church",
    "wof:placetype":"venue"
},
  "geometry": {"coordinates":[-72.355647,43.535343],"type":"Point"}
}