{
  "type": "Feature",
  "properties": {
    "iso:country":"US",
    "sg:address":"6 Kingston Rd",
    "sg:city":"East Kingston",
    "sg:classifiers":[
        {
            "category":"Wholesale",
            "subcategory":"Non-durable Goods",
            "type":"Manufacturing & Wholesale Goods"
        }
    ],
    "sg:phone":"+1 603 775 9800",
    "sg:postcode":"03865",
    "sg:province":"NH",
    "sg:tags":[
        "advertising"
    ],
    "wof:name":"Yankee Clipper Specialties",
    "wof:placetype":"venue"
},
  "geometry": {"coordinates":[-71.090339,42.840164],"type":"Point"}
}