{
  "type": "Feature",
  "properties": {
    "iso:country":"US",
    "sg:address":"2005 Dover Rd",
    "sg:city":"Epsom",
    "sg:classifiers":[
        {
            "category":"Building & Trades",
            "subcategory":"Construction",
            "type":"Services"
        }
    ],
    "sg:phone":"+1 603 736 4406",
    "sg:postcode":"03234",
    "sg:province":"NH",
    "sg:tags":[
        "carpentry",
        "contractor"
    ],
    "wof:name":"Graton Woods",
    "wof:placetype":"venue"
},
  "geometry": {"coordinates":[-71.37232,43.230837],"type":"Point"}
}