{
  "type": "Feature",
  "properties": {
    "iso:country":"US",
    "sg:address":"3 Lamb Rd",
    "sg:city":"Nashua",
    "sg:classifiers":[
        {
            "category":"Restaurant",
            "type":"Food & Drink"
        }
    ],
    "sg:phone":"+1 603 943 5042",
    "sg:postcode":"03062",
    "sg:province":"NH",
    "wof:name":"Synergy Dining Group",
    "wof:placetype":"venue"
},
  "geometry": {"coordinates":[-71.47370100000001,42.712444],"type":"Point"}
}