{
  "type": "Feature",
  "properties": {
    "addr:full":"4 Epping St Raymond NH 03077",
    "addr:housenumber":"4",
    "addr:postcode":"03077",
    "addr:street":"Epping St",
    "iso:country":"US",
    "sg:address":"4 Epping St",
    "sg:city":"Raymond",
    "sg:classifiers":[
        {
            "category":"Utilities",
            "subcategory":"Water",
            "type":"Services"
        }
    ],
    "sg:phone":"+1 603 895 4657",
    "sg:postcode":"03077",
    "sg:province":"NH",
    "sg:tags":[
        "company",
        "sewage"
    ],
    "wof:name":"Raymond Water Dept",
    "wof:placetype":"venue"
},
  "geometry": {"coordinates":[-71.18261099999999,43.036785],"type":"Point"}
}