{
  "type": "Feature",
  "properties": {
    "iso:country":"US",
    "sg:address":"192 Loudon Rd",
    "sg:city":"Concord",
    "sg:classifiers":[
        {
            "category":"Cinema",
            "subcategory":"Movie Theater",
            "type":"Entertainment"
        }
    ],
    "sg:phone":"+1 603 228 3265",
    "sg:postcode":"03301",
    "sg:province":"NH",
    "wof:name":"Entertainment Cinemas",
    "wof:placetype":"venue"
},
  "geometry": {"coordinates":[-71.500168,43.219202],"type":"Point"}
}