{
  "type": "Feature",
  "properties": {
    "iso:country":"US",
    "sg:address":"16 Birch Dr",
    "sg:city":"Newmarket",
    "sg:classifiers":[
        {
            "category":"Professional",
            "subcategory":"Art Services",
            "type":"Services"
        },
        {
            "category":"Professional",
            "subcategory":"Advertising",
            "type":"Services"
        }
    ],
    "sg:phone":"+1 603 659 7056",
    "sg:postcode":"03857",
    "sg:province":"NH",
    "sg:tags":[
        "commercial",
        "counselor",
        "design"
    ],
    "wof:name":"Fourae Graphic & Design Co",
    "wof:placetype":"venue"
},
  "geometry": {"coordinates":[-70.92737099999999,43.071534],"type":"Point"}
}