{
  "type": "Feature",
  "properties": {
    "iso:country":"US",
    "sg:address":"2075 Lafayette Rd",
    "sg:city":"Portsmouth",
    "sg:classifiers":[
        {
            "category":"Organizations",
            "subcategory":"Religious Organization",
            "type":"Services"
        }
    ],
    "sg:phone":"+1 603 436 4555",
    "sg:postcode":"03801",
    "sg:province":"NH",
    "wof:name":"Saint James Church",
    "wof:placetype":"venue"
},
  "geometry": {"coordinates":[-70.782005,43.033902],"type":"Point"}
}