{
  "type": "Feature",
  "properties": {
    "iso:country":"US",
    "sg:address":"39 Simon St",
    "sg:city":"Nashua",
    "sg:classifiers":[
        {
            "category":"Banks & Credit Unions",
            "subcategory":"Bank",
            "type":"Services"
        }
    ],
    "sg:phone":"+1 603 880 9797",
    "sg:postcode":"03060",
    "sg:province":"NH",
    "sg:tags":[
        "loan",
        "real estate"
    ],
    "wof:name":"American Heritage Mortgage",
    "wof:placetype":"venue"
},
  "geometry": {"coordinates":[-71.48728699999999,42.757397],"type":"Point"}
}