{
  "type": "Feature",
  "properties": {
    "addr:full":"20 Canal St Laconia NH 03246",
    "addr:housenumber":"20",
    "addr:postcode":"03246",
    "addr:street":"Canal St",
    "iso:country":"US",
    "sg:address":"20 Canal St",
    "sg:city":"Laconia",
    "sg:classifiers":[
        {
            "category":"Restaurant",
            "type":"Food & Drink"
        }
    ],
    "sg:phone":"+1 603 524 2610",
    "sg:postcode":"03246",
    "sg:province":"NH",
    "sg:tags":[
        "eating"
    ],
    "wof:name":"Giggles & Grins",
    "wof:placetype":"venue"
},
  "geometry": {"coordinates":[-71.469605,43.529099],"type":"Point"}
}