{
  "type": "Feature",
  "properties": {
    "iso:country":"US",
    "sg:address":"25 Mountain Dr",
    "sg:city":"Gilford",
    "sg:classifiers":[
        {
            "category":"Shopping",
            "subcategory":"Clothing, Apparel, & Fashions",
            "type":"Retail Goods"
        }
    ],
    "sg:phone":"+1 603 745 2408",
    "sg:postcode":"03249",
    "sg:province":"NH",
    "sg:tags":[
        "t"
    ],
    "wof:name":"Original Design Silk Screen Co",
    "wof:placetype":"venue"
},
  "geometry": {"coordinates":[-71.36099900000001,43.55494],"type":"Point"}
}