{
  "type": "Feature",
  "properties": {
    "iso:country":"US",
    "sg:address":"5 Garvins Falls Rd",
    "sg:city":"Concord",
    "sg:classifiers":[
        {
            "category":"Retail",
            "subcategory":"Repair Shop",
            "type":"Services"
        }
    ],
    "sg:phone":"+1 603 225 6737",
    "sg:postcode":"03301",
    "sg:province":"NH",
    "wof:name":"Edge Sharpening Service",
    "wof:placetype":"venue"
},
  "geometry": {"coordinates":[-71.512978,43.190581],"type":"Point"}
}