{
  "type": "Feature",
  "properties": {
    "iso:country":"US",
    "sg:address":"9 Woodbine Ln",
    "sg:city":"Amherst",
    "sg:classifiers":[
        {
            "category":"Professional",
            "subcategory":"Business Services",
            "type":"Services"
        }
    ],
    "sg:phone":"+1 603 424 7996",
    "sg:postcode":"03031",
    "sg:province":"NH",
    "wof:name":"Fishing Horizon Inc",
    "wof:placetype":"venue"
},
  "geometry": {"coordinates":[-71.563554,42.822581],"type":"Point"}
}