{
  "type": "Feature",
  "properties": {
    "iso:country":"US",
    "sg:address":"252 W Main St",
    "sg:city":"Conway",
    "sg:classifiers":[
        {
            "category":"Retail",
            "subcategory":"Auto Repair",
            "type":"Services"
        }
    ],
    "sg:phone":"+1 603 447 2528",
    "sg:postcode":"03818",
    "sg:province":"NH",
    "sg:tags":[
        "transmission"
    ],
    "wof:name":"Kennett Transmission Co Inc",
    "wof:placetype":"venue"
},
  "geometry": {"coordinates":[-71.13444,43.975063],"type":"Point"}
}