{
  "type": "Feature",
  "properties": {
    "iso:country":"US",
    "sg:address":"166 Stevens Rd",
    "sg:city":"Lebanon",
    "sg:classifiers":[
        {
            "category":"Manufacturing",
            "subcategory":"Metals",
            "type":"Manufacturing & Wholesale Goods"
        }
    ],
    "sg:phone":"+1 603 448 4246",
    "sg:postcode":"03766",
    "sg:province":"NH",
    "sg:tags":[
        "fabrication",
        "structural"
    ],
    "wof:name":"Windrow Forge",
    "wof:placetype":"venue"
},
  "geometry": {"coordinates":[-72.22230399999999,43.671312],"type":"Point"}
}