{
  "type": "Feature",
  "properties": {
    "iso:country":"US",
    "sg:address":"24 Greenbriar Ln",
    "sg:city":"Amherst",
    "sg:classifiers":[
        {
            "category":"Professional",
            "subcategory":"Management & Consulting",
            "type":"Services"
        }
    ],
    "sg:phone":"+1 603 673 7333",
    "sg:postcode":"03031",
    "sg:province":"NH",
    "sg:tags":[
        "business"
    ],
    "wof:name":"OReilly Environmental Svcs",
    "wof:placetype":"venue"
},
  "geometry": {"coordinates":[-71.583873,42.914631],"type":"Point"}
}