{
  "type": "Feature",
  "properties": {
    "addr:full":"5 Mill Rd Durham NH 03824",
    "addr:housenumber":"5",
    "addr:postcode":"03824",
    "addr:street":"Mill Rd",
    "iso:country":"US",
    "sg:address":"5 Mill Rd",
    "sg:city":"Durham",
    "sg:classifiers":[
        {
            "category":"Shopping",
            "subcategory":"Pharmacy",
            "type":"Retail Goods"
        }
    ],
    "sg:phone":"+1 603 868 2003",
    "sg:postcode":"03824",
    "sg:province":"NH",
    "sg:website":"www.brooksrx.com",
    "wof:name":"Brooks Pharmacy",
    "wof:placetype":"venue"
},
  "geometry": {"coordinates":[-70.92767499999999,43.133021],"type":"Point"}
}