{
  "type": "Feature",
  "properties": {
    "addr:full":"54 Conant Rd Nashua NH 03062",
    "addr:housenumber":"54",
    "addr:postcode":"03062",
    "addr:street":"Conant Rd",
    "iso:country":"US",
    "sg:address":"54 Conant Rd",
    "sg:city":"Nashua",
    "sg:classifiers":[
        {
            "category":"Manufacturing",
            "subcategory":"Metals",
            "type":"Manufacturing & Wholesale Goods"
        }
    ],
    "sg:phone":"+1 603 882 0000",
    "sg:postcode":"03062",
    "sg:province":"NH",
    "sg:tags":[
        "steel"
    ],
    "wof:name":"Aavic's Fabrications",
    "wof:placetype":"venue"
},
  "geometry": {"coordinates":[-71.497863,42.729261],"type":"Point"}
}