{
  "type": "Feature",
  "properties": {
    "addr:full":"21 Seavey St Conway NH 03842",
    "addr:housenumber":"21",
    "addr:postcode":"03842",
    "addr:street":"Seavey St",
    "iso:country":"US",
    "sg:address":"21 Seavey St",
    "sg:city":"Conway",
    "sg:classifiers":[
        {
            "category":"Retail",
            "subcategory":"Repair Shop",
            "type":"Services"
        }
    ],
    "sg:phone":"+1 603 356 6970",
    "sg:postcode":"03842",
    "sg:province":"NH",
    "sg:tags":[
        "jewelry"
    ],
    "wof:name":"Shalian Jewelers",
    "wof:placetype":"venue"
},
  "geometry": {"coordinates":[-70.842189,42.951732],"type":"Point"}
}