{
  "type": "Feature",
  "properties": {
    "iso:country":"US",
    "sg:address":"7 Pleasant Ln",
    "sg:city":"Amherst",
    "sg:classifiers":[
        {
            "category":"Professional",
            "subcategory":"Business Services",
            "type":"Services"
        }
    ],
    "sg:phone":"+1 603 672 2339",
    "sg:postcode":"03031",
    "sg:province":"NH",
    "wof:name":"Massa Technologies",
    "wof:placetype":"venue"
},
  "geometry": {"coordinates":[-71.575979,42.818167],"type":"Point"}
}