{
  "type": "Feature",
  "properties": {
    "addr:full":"196 Nottingham Rd Deerfield NH 03037",
    "addr:housenumber":"196",
    "addr:postcode":"03037",
    "addr:street":"Nottingham Rd",
    "iso:country":"US",
    "sg:address":"196 Nottingham Rd",
    "sg:city":"Deerfield",
    "sg:classifiers":[
        {
            "category":"Retail",
            "subcategory":"Repair Shop",
            "type":"Services"
        }
    ],
    "sg:phone":"+1 603 463 7923",
    "sg:postcode":"03037",
    "sg:province":"NH",
    "wof:name":"Rsb Enterprises",
    "wof:placetype":"venue"
},
  "geometry": {"coordinates":[-71.181028,43.131978],"type":"Point"}
}