{
  "type": "Feature",
  "properties": {
    "iso:country":"US",
    "sg:address":"15 Western Ave",
    "sg:city":"Henniker",
    "sg:classifiers":[
        {
            "category":"Education",
            "subcategory":"School",
            "type":"Public Place"
        }
    ],
    "sg:phone":"+1 603 428 3476",
    "sg:postcode":"03242",
    "sg:province":"NH",
    "sg:website":"www.henniker.k12.nh.us",
    "wof:name":"Henniker Community School",
    "wof:placetype":"venue"
},
  "geometry": {"coordinates":[-71.82397,43.179756],"type":"Point"}
}