{
  "type": "Feature",
  "properties": {
    "addr:full":"24 Alden Ave Greenland NH 03840",
    "addr:housenumber":"24",
    "addr:postcode":"03840",
    "addr:street":"Alden Ave",
    "iso:country":"US",
    "sg:address":"24 Alden Ave",
    "sg:city":"Greenland",
    "sg:classifiers":[
        {
            "category":"Wholesale",
            "subcategory":"Machinery & Supplies",
            "type":"Manufacturing & Wholesale Goods"
        }
    ],
    "sg:phone":"+1 603 433 1151",
    "sg:postcode":"03840",
    "sg:province":"NH",
    "sg:tags":[
        "equipment",
        "industrial"
    ],
    "wof:name":"Motive Marketing",
    "wof:placetype":"venue"
},
  "geometry": {"coordinates":[-70.824816,43.04027],"type":"Point"}
}