{
  "type": "Feature",
  "properties": {
    "iso:country":"US",
    "sg:address":"86 Chosen Vale Ln",
    "sg:city":"Enfield",
    "sg:classifiers":[
        {
            "category":"Professional",
            "subcategory":"Accounting & Tax Preparation",
            "type":"Services"
        }
    ],
    "sg:phone":"+1 603 632 9090",
    "sg:postcode":"03748",
    "sg:province":"NH",
    "sg:tags":[
        "bookkeeping",
        "general"
    ],
    "wof:name":"Opus",
    "wof:placetype":"venue"
},
  "geometry": {"coordinates":[-72.14388,43.619144],"type":"Point"}
}