{
  "type": "Feature",
  "properties": {
    "addr:full":"263 Grafton Rd Alexandria NH 03222",
    "addr:housenumber":"263",
    "addr:postcode":"03222",
    "addr:street":"Grafton Rd",
    "iso:country":"US",
    "sg:address":"263 Grafton Rd",
    "sg:city":"Alexandria",
    "sg:classifiers":[
        {
            "category":"Shopping",
            "type":"Retail Goods"
        }
    ],
    "sg:phone":"+1 603 744 5255",
    "sg:postcode":"03222",
    "sg:province":"NH",
    "sg:tags":[
        "wood",
        "carving"
    ],
    "wof:name":"Gilly's Pond Wildlife Art",
    "wof:placetype":"venue"
},
  "geometry": {"coordinates":[-71.880281,43.60265],"type":"Point"}
}