{
  "type": "Feature",
  "properties": {
    "iso:country":"US",
    "sg:address":"4 Sentry Way",
    "sg:city":"Merrimack",
    "sg:classifiers":[
        {
            "category":"Professional",
            "subcategory":"Management & Consulting",
            "type":"Services"
        }
    ],
    "sg:phone":"+1 603 424 9491",
    "sg:postcode":"03054",
    "sg:province":"NH",
    "sg:tags":[
        "consultant",
        "publishing"
    ],
    "wof:name":"Options Publishing Inc",
    "wof:placetype":"venue"
},
  "geometry": {"coordinates":[-71.491596,42.83534],"type":"Point"}
}