{
  "type": "Feature",
  "properties": {
    "iso:country":"US",
    "sg:address":"18 S Main St",
    "sg:city":"Derry",
    "sg:classifiers":[
        {
            "category":"Education",
            "subcategory":"School",
            "type":"Public Place"
        }
    ],
    "sg:phone":"+1 603 432 1210",
    "sg:postcode":"03038",
    "sg:province":"NH",
    "wof:name":"Derry Superintendent-Schools",
    "wof:placetype":"venue"
},
  "geometry": {"coordinates":[-71.308153,42.887337],"type":"Point"}
}