{
  "type": "Feature",
  "properties": {
    "iso:country":"US",
    "sg:address":"326 S Broadway",
    "sg:city":"Salem",
    "sg:classifiers":[
        {
            "category":"Shopping",
            "subcategory":"Books",
            "type":"Retail Goods"
        }
    ],
    "sg:phone":"+1 603 893 8202",
    "sg:postcode":"03079",
    "sg:province":"NH",
    "sg:tags":[
        "used",
        "dealer",
        "merchandise"
    ],
    "wof:name":"Annie's Book Stop",
    "wof:placetype":"venue"
},
  "geometry": {"coordinates":[-71.20854300000001,42.754579],"type":"Point"}
}