{
  "type": "Feature",
  "properties": {
    "addr:full":"664 US Hwy 3 Lincoln NH 03262",
    "addr:housenumber":"664",
    "addr:postcode":"03262",
    "addr:street":"Us Hwy 3",
    "iso:country":"US",
    "sg:address":"664 US Hwy 3",
    "sg:city":"Lincoln",
    "sg:classifiers":[
        {
            "category":"Travel",
            "subcategory":"Hotels & Motels",
            "type":"Entertainment"
        }
    ],
    "sg:phone":"+1 603 745 6000",
    "sg:postcode":"03262",
    "sg:province":"NH",
    "sg:tags":[
        "operation"
    ],
    "wof:name":"Indaian Head Resort",
    "wof:placetype":"venue"
},
  "geometry": {"coordinates":[-71.68594400000001,43.99218],"type":"Point"}
}