{
  "type": "Feature",
  "properties": {
    "iso:country":"US",
    "sg:address":"27 Old Kings Rd",
    "sg:city":"Merrimack",
    "sg:classifiers":[
        {
            "category":"Restaurant",
            "type":"Food & Drink"
        }
    ],
    "sg:phone":"+1 603 883 2485",
    "sg:postcode":"03054",
    "sg:province":"NH",
    "sg:tags":[
        "management"
    ],
    "wof:name":"Concepts Of New England Inc",
    "wof:placetype":"venue"
},
  "geometry": {"coordinates":[-71.534003,42.829549],"type":"Point"}
}