{
  "type": "Feature",
  "properties": {
    "addr:full":"158 Main St Andover NH 03216",
    "addr:housenumber":"158",
    "addr:postcode":"03216",
    "addr:street":"Main St",
    "iso:country":"US",
    "sg:address":"158 Main St",
    "sg:city":"Andover",
    "sg:classifiers":[
        {
            "category":"Restaurant",
            "type":"Food & Drink"
        }
    ],
    "sg:phone":"+1 603 968 9083",
    "sg:postcode":"03216",
    "sg:province":"NH",
    "sg:tags":[
        "shop",
        "coffee"
    ],
    "wof:name":"Dunkin Donuts",
    "wof:placetype":"venue"
},
  "geometry": {"coordinates":[-71.821623,43.436718],"type":"Point"}
}