{
  "type": "Feature",
  "properties": {
    "addr:full":"172 State Rte 101 Bedford NH 03110",
    "addr:housenumber":"172",
    "addr:postcode":"03110",
    "addr:street":"State Rte 101",
    "iso:country":"US",
    "sg:address":"172 State Rte 101",
    "sg:city":"Bedford",
    "sg:classifiers":[
        {
            "category":"Retail",
            "subcategory":"Funeral Services",
            "type":"Services"
        }
    ],
    "sg:phone":"+1 603 472 9205",
    "sg:postcode":"03110",
    "sg:province":"NH",
    "sg:tags":[
        "director"
    ],
    "wof:name":"Phaneuf Funeral Homes",
    "wof:placetype":"venue"
},
  "geometry": {"coordinates":[-71.519752,42.941526],"type":"Point"}
}