{
  "type": "Feature",
  "properties": {
    "iso:country":"US",
    "sg:address":"246 Derry Rd",
    "sg:city":"Litchfield",
    "sg:classifiers":[
        {
            "category":"Wholesale",
            "subcategory":"Vending Machines",
            "type":"Manufacturing & Wholesale Goods"
        }
    ],
    "sg:phone":"+1 603 882 7054",
    "sg:postcode":"03052",
    "sg:province":"NH",
    "wof:name":"Snack-King",
    "wof:placetype":"venue"
},
  "geometry": {"coordinates":[-71.43065799999999,42.804946],"type":"Point"}
}