{
  "type": "Feature",
  "properties": {
    "iso:country":"US",
    "sg:address":"41 School St",
    "sg:city":"Keene",
    "sg:classifiers":[
        {
            "category":"Professional",
            "subcategory":"Lawyer & Legal Services",
            "type":"Services"
        }
    ],
    "sg:phone":"+1 603 352 9030",
    "sg:postcode":"03431",
    "sg:province":"NH",
    "sg:tags":[
        "attorney"
    ],
    "wof:name":"Thomas R Hanna Law Office",
    "wof:placetype":"venue"
},
  "geometry": {"coordinates":[-72.282832,42.93515],"type":"Point"}
}