{
  "type": "Feature",
  "properties": {
    "iso:country":"US",
    "sg:address":"16 Butter Rd",
    "sg:city":"Henniker",
    "sg:classifiers":[
        {
            "category":"Building & Trades",
            "subcategory":"Construction",
            "type":"Services"
        }
    ],
    "sg:phone":"+1 603 428 7564",
    "sg:postcode":"03242",
    "sg:province":"NH",
    "sg:tags":[
        "water",
        "well",
        "drilling"
    ],
    "wof:name":"Gould & Son Artesian Well Co",
    "wof:placetype":"venue"
},
  "geometry": {"coordinates":[-71.819975,43.154814],"type":"Point"}
}