{
  "type": "Feature",
  "properties": {
    "iso:country":"US",
    "sg:address":"35 Manchester Rd",
    "sg:city":"Derry",
    "sg:classifiers":[
        {
            "category":"Personal",
            "type":"Services"
        }
    ],
    "sg:phone":"+1 603 425 6813",
    "sg:postcode":"03038",
    "sg:province":"NH",
    "sg:tags":[
        "control",
        "weight"
    ],
    "wof:name":"Cellulite Solutions",
    "wof:placetype":"venue"
},
  "geometry": {"coordinates":[-71.33792099999999,42.899295],"type":"Point"}
}