{
  "type": "Feature",
  "properties": {
    "addr:full":"135 Daniel St Portsmouth NH 03801",
    "addr:housenumber":"135",
    "addr:postcode":"03801",
    "addr:street":"Daniel St",
    "iso:country":"US",
    "sg:address":"135 Daniel St",
    "sg:city":"Portsmouth",
    "sg:classifiers":[
        {
            "category":"Museum",
            "type":"Entertainment"
        }
    ],
    "sg:phone":"+1 603 433 4278",
    "sg:postcode":"03801",
    "sg:province":"NH",
    "sg:tags":[
        "organization",
        "arts",
        "information"
    ],
    "wof:name":"Artists In Residence",
    "wof:placetype":"venue"
},
  "geometry": {"coordinates":[-70.756202,43.077337],"type":"Point"}
}