{
  "type": "Feature",
  "properties": {
    "iso:country":"US",
    "sg:address":"779 Lafayette Rd",
    "sg:city":"Seabrook",
    "sg:classifiers":[
        {
            "category":"Utilities",
            "subcategory":"Cable",
            "type":"Services"
        }
    ],
    "sg:phone":"+1 603 474 7301",
    "sg:postcode":"03874",
    "sg:province":"NH",
    "sg:tags":[
        "television"
    ],
    "wof:name":"All Around Tele Communications",
    "wof:placetype":"venue"
},
  "geometry": {"coordinates":[-70.870621,42.897792],"type":"Point"}
}