{
  "type": "Feature",
  "properties": {
    "iso:country":"US",
    "sg:address":"258 Pleasant St",
    "sg:city":"Franklin",
    "sg:classifiers":[
        {
            "category":"Building & Trades",
            "subcategory":"Construction",
            "type":"Services"
        }
    ],
    "sg:phone":"+1 603 934 9944",
    "sg:postcode":"03235",
    "sg:province":"NH",
    "sg:tags":[
        "painter"
    ],
    "wof:name":"New England Painting",
    "wof:placetype":"venue"
},
  "geometry": {"coordinates":[-71.630864,43.435404],"type":"Point"}
}