{
  "type": "Feature",
  "properties": {
    "addr:full":"48 Litchfield Rd Londonderry NH 03053",
    "addr:housenumber":"48",
    "addr:postcode":"03053",
    "addr:street":"Litchfield Rd",
    "iso:country":"US",
    "sg:address":"48 Litchfield Rd",
    "sg:city":"Londonderry",
    "sg:classifiers":[
        {
            "category":"Wholesale",
            "subcategory":"Machinery & Supplies",
            "type":"Manufacturing & Wholesale Goods"
        }
    ],
    "sg:phone":"+1 603 437 0018",
    "sg:postcode":"03053",
    "sg:province":"NH",
    "sg:tags":[
        "repairing"
    ],
    "wof:name":"Bcp Trilogy",
    "wof:placetype":"venue"
},
  "geometry": {"coordinates":[-71.39982500000001,42.896235],"type":"Point"}
}