{
  "type": "Feature",
  "properties": {
    "iso:country":"US",
    "sg:address":"28 Lowell Rd",
    "sg:city":"Hudson",
    "sg:classifiers":[
        {
            "category":"Professional",
            "subcategory":"Business Services",
            "type":"Services"
        }
    ],
    "sg:phone":"+1 800 275 8777",
    "sg:postcode":"03051",
    "sg:province":"NH",
    "sg:tags":[
        "mail",
        "shipping"
    ],
    "sg:website":"http://www.usps.com",
    "wof:name":"United States Postal Service",
    "wof:placetype":"venue"
},
  "geometry": {"coordinates":[-71.431549,42.759472],"type":"Point"}
}