{
  "type": "Feature",
  "properties": {
    "iso:country":"US",
    "sg:address":"300 Washington St",
    "sg:city":"Claremont",
    "sg:classifiers":[
        {
            "category":"Home & Garden",
            "subcategory":"Household Appliances",
            "type":"Retail Goods"
        }
    ],
    "sg:phone":"+1 603 542 7113",
    "sg:postcode":"03743",
    "sg:province":"NH",
    "sg:tags":[
        "cleaners",
        "vacuum"
    ],
    "wof:name":"Pinard's Sew & Vac",
    "wof:placetype":"venue"
},
  "geometry": {"coordinates":[-72.31647100000001,43.363409],"type":"Point"}
}