{
  "type": "Feature",
  "properties": {
    "iso:country":"US",
    "sg:address":"142 Main St",
    "sg:city":"Salem",
    "sg:classifiers":[
        {
            "category":"Building & Trades",
            "subcategory":"Construction",
            "type":"Services"
        }
    ],
    "sg:phone":"+1 603 952 4532",
    "sg:postcode":"03079",
    "sg:province":"NH",
    "sg:tags":[
        "demolition",
        "contractor"
    ],
    "wof:name":"Nh Demolition",
    "wof:placetype":"venue"
},
  "geometry": {"coordinates":[-71.226372,42.782159],"type":"Point"}
}