{
  "type": "Feature",
  "properties": {
    "addr:full":"21 Moultonville Rd Center Ossipee NH 03814",
    "addr:housenumber":"21",
    "addr:postcode":"03814",
    "addr:street":"Moultonville Rd",
    "iso:country":"US",
    "sg:address":"21 Moultonville Rd",
    "sg:city":"Center Ossipee",
    "sg:classifiers":[
        {
            "category":"Shopping",
            "subcategory":"Crafts & Fabrics",
            "type":"Retail Goods"
        }
    ],
    "sg:phone":"+1 603 539 4397",
    "sg:postcode":"03814",
    "sg:province":"NH",
    "sg:tags":[
        "yarn"
    ],
    "wof:name":"Yarn Express",
    "wof:placetype":"venue"
},
  "geometry": {"coordinates":[-71.163591,43.755936],"type":"Point"}
}