{
  "type": "Feature",
  "properties": {
    "addr:full":"631 State Rte 12 Surry NH 03431",
    "addr:housenumber":"631",
    "addr:postcode":"03431",
    "addr:street":"State Rte 12 Surry",
    "iso:country":"US",
    "sg:address":"631 State Rte 12",
    "sg:city":"Surry",
    "sg:classifiers":[
        {
            "category":"Building & Trades",
            "subcategory":"Construction",
            "type":"Services"
        }
    ],
    "sg:phone":"+1 603 352 8866",
    "sg:postcode":"03431",
    "sg:province":"NH",
    "sg:tags":[
        "well",
        "drilling"
    ],
    "wof:name":"Cushing & Sons Well Drilling",
    "wof:placetype":"venue"
},
  "geometry": {"coordinates":[-72.26965800000001,42.914633],"type":"Point"}
}