{
  "type": "Feature",
  "properties": {
    "iso:country":"US",
    "sg:address":"80 Hanover St",
    "sg:city":"Portsmouth",
    "sg:classifiers":[
        {
            "category":"Restaurant",
            "type":"Food & Drink"
        }
    ],
    "sg:phone":"+1 603 427 2959",
    "sg:postcode":"03801",
    "sg:province":"NH",
    "wof:name":"Shalimar India Restaurant",
    "wof:placetype":"venue"
},
  "geometry": {"coordinates":[-70.75795599999999,43.078291],"type":"Point"}
}