{
  "type": "Feature",
  "properties": {
    "iso:country":"US",
    "sg:address":"295 Sheep Davis Rd",
    "sg:city":"Concord",
    "sg:classifiers":[
        {
            "category":"Organizations",
            "subcategory":"Non-profit Organization",
            "type":"Services"
        }
    ],
    "sg:phone":"+1 603 224 1934",
    "sg:postcode":"03301",
    "sg:province":"NH",
    "wof:name":"New Hampshire Farm Bureau",
    "wof:placetype":"venue"
},
  "geometry": {"coordinates":[-71.47814700000001,43.226585],"type":"Point"}
}