{
  "type": "Feature",
  "properties": {
    "addr:full":"124 S River Rd Bedford NH 03110",
    "addr:housenumber":"124",
    "addr:postcode":"03110",
    "addr:street":"S River Rd",
    "iso:country":"US",
    "sg:address":"124 S River Rd",
    "sg:city":"Bedford",
    "sg:classifiers":[
        {
            "category":"Banks & Credit Unions",
            "subcategory":"Bank",
            "type":"Services"
        }
    ],
    "sg:phone":"+1 603 625 9751",
    "sg:postcode":"03110",
    "sg:province":"NH",
    "sg:tags":[
        "financing"
    ],
    "wof:name":"Citi Financial",
    "wof:placetype":"venue"
},
  "geometry": {"coordinates":[-71.478168,42.954588],"type":"Point"}
}