{
  "type": "Feature",
  "properties": {
    "addr:full":"306 Lafayette Rd Seabrook NH 03874",
    "addr:housenumber":"306",
    "addr:postcode":"03874",
    "iso:country":"US",
    "sg:address":"306 Lafayette Rd",
    "sg:city":"Seabrook",
    "sg:classifiers":[
        {
            "category":"Restaurant",
            "type":"Food & Drink"
        }
    ],
    "sg:menulink":"http://www.allmenus.com/nh/seabrook/183531-kfc---kentucky-fried-chicken/menu/",
    "sg:phone":"+1 603 474 5101",
    "sg:postcode":"03874",
    "sg:province":"NH",
    "sg:tags":[
        "american",
        "chicken"
    ],
    "wof:name":"KFC - Kentucky Fried Chicken",
    "wof:placetype":"venue"
},
  "geometry": {"coordinates":[-70.868736,42.884055],"type":"Point"}
}