{
  "type": "Feature",
  "properties": {
    "iso:country":"US",
    "sg:address":"10 Stratham Heights Rd",
    "sg:city":"Stratham",
    "sg:classifiers":[
        {
            "category":"Professional",
            "subcategory":"Lawyer & Legal Services",
            "type":"Services"
        }
    ],
    "sg:phone":"+1 603 772 4225",
    "sg:postcode":"03885",
    "sg:province":"NH",
    "wof:name":"Elizabeth Bassett",
    "wof:placetype":"venue"
},
  "geometry": {"coordinates":[-70.923951,42.993786],"type":"Point"}
}