{
  "type": "Feature",
  "properties": {
    "addr:full":"191 Sherwood Dr Manchester NH 03103",
    "addr:housenumber":"191",
    "addr:postcode":"03103",
    "addr:street":"Sherwood Dr",
    "iso:country":"US",
    "sg:address":"191 Sherwood Dr",
    "sg:city":"Manchester",
    "sg:classifiers":[
        {
            "category":"Autos & Motor Vehicles",
            "subcategory":"Automobile Sales",
            "type":"Retail Goods"
        }
    ],
    "sg:phone":"+1 603 622 4663",
    "sg:postcode":"03103",
    "sg:province":"NH",
    "sg:tags":[
        "used"
    ],
    "wof:name":"Best Buy Auto",
    "wof:placetype":"venue"
},
  "geometry": {"coordinates":[-71.450298,42.946091],"type":"Point"}
}