{
  "type": "Feature",
  "properties": {
    "addr:full":"33 Londonderry Rd Londonderry NH 03053",
    "addr:housenumber":"33",
    "addr:postcode":"03053",
    "addr:street":"Londonderry Rd",
    "iso:country":"US",
    "sg:address":"33 Londonderry Rd",
    "sg:city":"Londonderry",
    "sg:classifiers":[
        {
            "category":"Manufacturing",
            "subcategory":"Tools & Machinery",
            "type":"Manufacturing & Wholesale Goods"
        }
    ],
    "sg:phone":"+1 603 425 7417",
    "sg:postcode":"03053",
    "sg:province":"NH",
    "sg:tags":[
        "machine",
        "shop"
    ],
    "wof:name":"Advanced Machine Technology",
    "wof:placetype":"venue"
},
  "geometry": {"coordinates":[-71.338865,42.875577],"type":"Point"}
}