{
  "type": "Feature",
  "properties": {
    "iso:country":"US",
    "sg:address":"633 2nd St",
    "sg:city":"Manchester",
    "sg:classifiers":[
        {
            "category":"Professional",
            "subcategory":"Lawyer & Legal Services",
            "type":"Services"
        }
    ],
    "sg:phone":"+1 603 668 2027",
    "sg:postcode":"03102",
    "sg:province":"NH",
    "wof:name":"Mitchell P Utell",
    "wof:placetype":"venue"
},
  "geometry": {"coordinates":[-71.477289,42.972021],"type":"Point"}
}