{
  "type": "Feature",
  "properties": {
    "addr:full":"51 Whitehall Rd Rochester NH 03867",
    "addr:housenumber":"51",
    "addr:postcode":"03867",
    "addr:street":"Whitehall Rd",
    "iso:country":"US",
    "sg:address":"51 Whitehall Rd",
    "sg:city":"Rochester",
    "sg:classifiers":[
        {
            "category":"Building & Trades",
            "subcategory":"Electrical",
            "type":"Services"
        }
    ],
    "sg:phone":"+1 603 332 4595",
    "sg:postcode":"03867",
    "sg:province":"NH",
    "sg:tags":[
        "electrical",
        "contractor"
    ],
    "wof:name":"R & R Electric",
    "wof:placetype":"venue"
},
  "geometry": {"coordinates":[-70.952367,43.298378],"type":"Point"}
}