{
  "type": "Feature",
  "properties": {
    "iso:country":"US",
    "sg:address":"10 Canobie Ave",
    "sg:city":"Salem",
    "sg:classifiers":[
        {
            "category":"Building & Trades",
            "subcategory":"Construction",
            "type":"Services"
        }
    ],
    "sg:phone":"+1 603 894 1270",
    "sg:postcode":"03079",
    "sg:province":"NH",
    "sg:tags":[
        "general",
        "contractor"
    ],
    "wof:name":"KIRK Mac Donald Construction",
    "wof:placetype":"venue"
},
  "geometry": {"coordinates":[-71.25111699999999,42.790259],"type":"Point"}
}