{
  "type": "Feature",
  "properties": {
    "iso:country":"US",
    "sg:address":"282 Paige Hill Rd",
    "sg:city":"Goffstown",
    "sg:classifiers":[
        {
            "category":"Shopping",
            "subcategory":"Jewelry",
            "type":"Retail Goods"
        }
    ],
    "sg:phone":"+1 603 497 3557",
    "sg:postcode":"03045",
    "sg:province":"NH",
    "sg:tags":[
        "jeweler"
    ],
    "wof:name":"Sunset Creations",
    "wof:placetype":"venue"
},
  "geometry": {"coordinates":[-71.58107699999999,43.03934],"type":"Point"}
}