{
  "type": "Feature",
  "properties": {
    "iso:country":"US",
    "sg:address":"147 Lake St",
    "sg:city":"Nashua",
    "sg:classifiers":[
        {
            "category":"Food & Beverages",
            "subcategory":"Groceries & Convenience Stores",
            "type":"Retail Goods"
        }
    ],
    "sg:phone":"+1 603 886 3860",
    "sg:postcode":"03060",
    "sg:province":"NH",
    "wof:name":"Kozy Korner Variety Inc",
    "wof:placetype":"venue"
},
  "geometry": {"coordinates":[-71.473443,42.748131],"type":"Point"}
}