{
  "type": "Feature",
  "properties": {
    "iso:country":"US",
    "sg:address":"242 Messer St",
    "sg:city":"Laconia",
    "sg:classifiers":[
        {
            "category":"Utilities",
            "subcategory":"Fuel Oil & Lpg",
            "type":"Services"
        }
    ],
    "sg:phone":"+1 603 524 5217",
    "sg:postcode":"03246",
    "sg:province":"NH",
    "sg:tags":[
        "coal"
    ],
    "wof:name":"Dutile & Sons Inc",
    "wof:placetype":"venue"
},
  "geometry": {"coordinates":[-71.46655199999999,43.53818],"type":"Point"}
}