{
  "type": "Feature",
  "properties": {
    "addr:full":"6 Raymond Ave Salem NH 03079",
    "addr:housenumber":"6",
    "addr:postcode":"03079",
    "addr:street":"Raymond Ave",
    "iso:country":"US",
    "sg:address":"6 Raymond Ave",
    "sg:city":"Salem",
    "sg:classifiers":[
        {
            "category":"Manufacturing",
            "subcategory":"Signs",
            "type":"Manufacturing & Wholesale Goods"
        }
    ],
    "sg:phone":"+1 603 898 6882",
    "sg:postcode":"03079",
    "sg:province":"NH",
    "sg:tags":[
        "specialty",
        "mfg"
    ],
    "wof:name":"Brothers Sign Company",
    "wof:placetype":"venue"
},
  "geometry": {"coordinates":[-71.23903,42.775691],"type":"Point"}
}