{
  "type": "Feature",
  "properties": {
    "iso:country":"US",
    "sg:address":"129 State Rte 27",
    "sg:city":"Raymond",
    "sg:classifiers":[
        {
            "category":"Social Services",
            "subcategory":"Child Care",
            "type":"Services"
        }
    ],
    "sg:phone":"+1 603 895 5323",
    "sg:postcode":"03077",
    "sg:province":"NH",
    "sg:tags":[
        "day"
    ],
    "wof:name":"Blocks To Books Children's Ctr",
    "wof:placetype":"venue"
},
  "geometry": {"coordinates":[-71.186987,43.041865],"type":"Point"}
}