{
  "type": "Feature",
  "properties": {
    "addr:full":"5 Meghan Cir Salem NH 03079",
    "addr:housenumber":"5",
    "addr:postcode":"03079",
    "addr:street":"Meghan Cir",
    "iso:country":"US",
    "sg:address":"5 Meghan Cir",
    "sg:city":"Salem",
    "sg:classifiers":[
        {
            "category":"Building & Trades",
            "subcategory":"Plumbing",
            "type":"Services"
        }
    ],
    "sg:phone":"+1 603 898 6987",
    "sg:postcode":"03079",
    "sg:province":"NH",
    "sg:tags":[
        "contractor"
    ],
    "wof:name":"Correct Temp Inc",
    "wof:placetype":"venue"
},
  "geometry": {"coordinates":[-71.178437,42.79968],"type":"Point"}
}