{
  "type": "Feature",
  "properties": {
    "iso:country":"US",
    "sg:address":"20 Dublin Rd",
    "sg:city":"Peterborough",
    "sg:classifiers":[
        {
            "category":"Building & Trades",
            "subcategory":"Construction",
            "type":"Services"
        }
    ],
    "sg:phone":"+1 603 924 3676",
    "sg:postcode":"03458",
    "sg:province":"NH",
    "sg:tags":[
        "contractor"
    ],
    "wof:name":"David A Blanchette Inc",
    "wof:placetype":"venue"
},
  "geometry": {"coordinates":[-71.959165,42.872887],"type":"Point"}
}