{
  "type": "Feature",
  "properties": {
    "iso:country":"US",
    "sg:address":"7 Kelsey Dr",
    "sg:city":"Lee",
    "sg:classifiers":[
        {
            "category":"Shopping",
            "subcategory":"Computers & Home Electronics",
            "type":"Retail Goods"
        }
    ],
    "sg:phone":"+1 603 659 5335",
    "sg:postcode":"03824",
    "sg:province":"NH",
    "sg:tags":[
        "equipment",
        "electronic",
        "supply"
    ],
    "wof:name":"LRS Electronics",
    "wof:placetype":"venue"
},
  "geometry": {"coordinates":[-70.969838,43.085467],"type":"Point"}
}