{
  "type": "Feature",
  "properties": {
    "addr:full":"470 S Mast Rd Goffstown NH 03045",
    "addr:housenumber":"470",
    "addr:postcode":"03045",
    "addr:street":"S Mast Rd",
    "iso:country":"US",
    "sg:address":"470 S Mast Rd",
    "sg:city":"Goffstown",
    "sg:classifiers":[
        {
            "category":"Real Estate",
            "subcategory":"Real Estate Agent",
            "type":"Services"
        }
    ],
    "sg:phone":"+1 603 624 9424",
    "sg:postcode":"03045",
    "sg:province":"NH",
    "sg:website":"www.northernacres.com",
    "wof:name":"J W Powers Realty Co",
    "wof:placetype":"venue"
},
  "geometry": {"coordinates":[-71.523191,43.005599],"type":"Point"}
}