{
  "type": "Feature",
  "properties": {
    "addr:full":"8 Whipplewill Rd New Boston NH 03070",
    "addr:housenumber":"8",
    "addr:postcode":"03070",
    "addr:street":"Whipplewill Rd",
    "iso:country":"US",
    "sg:address":"8 Whipplewill Rd",
    "sg:city":"New Boston",
    "sg:classifiers":[
        {
            "category":"Building & Trades",
            "subcategory":"Construction",
            "type":"Services"
        }
    ],
    "sg:phone":"+1 603 497 8154",
    "sg:postcode":"03070",
    "sg:province":"NH",
    "sg:tags":[
        "excavation",
        "contractor"
    ],
    "wof:name":"John E Neville Excavating",
    "wof:placetype":"venue"
},
  "geometry": {"coordinates":[-71.636567,43.022558],"type":"Point"}
}