{
  "type": "Feature",
  "properties": {
    "addr:full":"124 W Pearl St Nashua NH 03060",
    "addr:housenumber":"124",
    "addr:postcode":"03060",
    "addr:street":"W Pearl St",
    "iso:country":"US",
    "sg:address":"124 W Pearl St",
    "sg:city":"Nashua",
    "sg:classifiers":[
        {
            "category":"Freight",
            "type":"Transportation"
        }
    ],
    "sg:phone":"+1 603 880 5055",
    "sg:postcode":"03060",
    "sg:province":"NH",
    "sg:tags":[
        "mover",
        "trucking"
    ],
    "wof:name":"Ferrick Transport",
    "wof:placetype":"venue"
},
  "geometry": {"coordinates":[-71.46682,42.759715],"type":"Point"}
}