{
  "type": "Feature",
  "properties": {
    "iso:country":"US",
    "sg:address":"12 Sacred Heart Dr",
    "sg:city":"Nashua",
    "sg:classifiers":[
        {
            "category":"Professional",
            "subcategory":"Business Services",
            "type":"Services"
        }
    ],
    "sg:phone":"+1 603 886 9433",
    "sg:postcode":"03060",
    "sg:province":"NH",
    "wof:name":"Shebas Drafters",
    "wof:placetype":"venue"
},
  "geometry": {"coordinates":[-71.47131,42.748739],"type":"Point"}
}