{
  "type": "Feature",
  "properties": {
    "addr:full":"1260 Elm St Manchester NH 03101",
    "addr:housenumber":"1260",
    "addr:postcode":"03101",
    "addr:street":"Elm St",
    "iso:country":"US",
    "sg:address":"1260 Elm St",
    "sg:city":"Manchester",
    "sg:classifiers":[
        {
            "category":"Education",
            "subcategory":"College",
            "type":"Public Place"
        }
    ],
    "sg:phone":"+1 603 314 0210",
    "sg:postcode":"03101",
    "sg:province":"NH",
    "wof:name":"Manchester Campus",
    "wof:placetype":"venue"
},
  "geometry": {"coordinates":[-71.46366399999999,42.996391],"type":"Point"}
}