{
  "type": "Feature",
  "properties": {
    "iso:country":"US",
    "sg:address":"110 Main St",
    "sg:city":"Atkinson",
    "sg:classifiers":[
        {
            "category":"Food & Beverages",
            "subcategory":"Groceries & Convenience Stores",
            "type":"Retail Goods"
        }
    ],
    "sg:phone":"+1 603 362 5898",
    "sg:postcode":"03811",
    "sg:province":"NH",
    "sg:website":"http://www.atkinsonhistoricalsociety.org",
    "wof:name":"Atkinson Village Store",
    "wof:placetype":"venue"
},
  "geometry": {"coordinates":[-71.151443,42.838009],"type":"Point"}
}