{
  "type": "Feature",
  "properties": {
    "addr:full":"229 Wilson St Manchester NH 03103",
    "addr:housenumber":"229",
    "addr:postcode":"03103",
    "addr:street":"Wilson St",
    "iso:country":"US",
    "sg:address":"229 Wilson St",
    "sg:city":"Manchester",
    "sg:classifiers":[
        {
            "category":"Shopping",
            "subcategory":"Pets & Pet Supplies",
            "type":"Retail Goods"
        },
        {
            "category":"Retail",
            "subcategory":"Animal Services",
            "type":"Services"
        }
    ],
    "sg:phone":"+1 603 669 1955",
    "sg:postcode":"03103",
    "sg:province":"NH",
    "sg:tags":[
        "grooming",
        "furnishing",
        "dog",
        "store",
        "cat"
    ],
    "sg:website":"http://www.rufftofluff.com",
    "wof:name":"Ruff To Fluff Dog Grooming",
    "wof:placetype":"venue"
},
  "geometry": {"coordinates":[-71.44817399999999,42.979245],"type":"Point"}
}