{
  "type": "Feature",
  "properties": {
    "iso:country":"US",
    "sg:address":"121 Lafayette Rd",
    "sg:city":"North Hampton",
    "sg:classifiers":[
        {
            "category":"Professional",
            "subcategory":"Business Services",
            "type":"Services"
        }
    ],
    "sg:phone":"+1 603 964 5800",
    "sg:postcode":"03862",
    "sg:province":"NH",
    "sg:tags":[
        "water",
        "treatment"
    ],
    "wof:name":"Water Treatment Technology",
    "wof:placetype":"venue"
},
  "geometry": {"coordinates":[-70.834039,42.979072],"type":"Point"}
}