{
  "type": "Feature",
  "properties": {
    "iso:country":"US",
    "sg:address":"64 Pleasant St",
    "sg:city":"Claremont",
    "sg:classifiers":[
        {
            "category":"Shopping",
            "subcategory":"Used Merchandise",
            "type":"Retail Goods"
        }
    ],
    "sg:phone":"+1 603 542 4391",
    "sg:postcode":"03743",
    "sg:province":"NH",
    "sg:tags":[
        "flea",
        "market"
    ],
    "wof:name":"Nana's Collectables & Trsrs",
    "wof:placetype":"venue"
},
  "geometry": {"coordinates":[-72.33893,43.371085],"type":"Point"}
}