{
  "type": "Feature",
  "properties": {
    "iso:country":"US",
    "sg:address":"4 Birch St",
    "sg:city":"Derry",
    "sg:classifiers":[
        {
            "category":"Professional",
            "subcategory":"Accounting & Tax Preparation",
            "type":"Services"
        }
    ],
    "sg:phone":"+1 603 434 2722",
    "sg:postcode":"03038",
    "sg:province":"NH",
    "wof:name":"AP Lane & Co",
    "wof:placetype":"venue"
},
  "geometry": {"coordinates":[-71.322952,42.880821],"type":"Point"}
}