{
  "type": "Feature",
  "properties": {
    "addr:full":"326 Buck St Suncook NH 03275",
    "addr:housenumber":"326",
    "addr:postcode":"03275",
    "addr:street":"Buck St",
    "iso:country":"US",
    "sg:address":"326 Buck St",
    "sg:city":"Suncook",
    "sg:phone":"+1 603 485 4211",
    "sg:postcode":"03275",
    "sg:province":"NH",
    "sg:tags":[
        "farm",
        "hay",
        "corn",
        "snowplowing"
    ],
    "wof:name":"Green Gold Farm LLC",
    "wof:placetype":"venue"
},
  "geometry": {"coordinates":[-71.43173,43.146402],"type":"Point"}
}