{
  "type": "Feature",
  "properties": {
    "addr:full":"121 Pembroke St Pembroke NH 03275",
    "addr:housenumber":"121",
    "addr:postcode":"03275",
    "addr:street":"Pembroke St",
    "iso:country":"US",
    "sg:address":"121 Pembroke St",
    "sg:city":"Pembroke",
    "sg:classifiers":[
        {
            "category":"Health Services",
            "subcategory":"Doctor",
            "type":"Services"
        }
    ],
    "sg:phone":"+1 603 485 8441",
    "sg:postcode":"03275",
    "sg:province":"NH",
    "sg:tags":[
        "physician",
        "surgeon"
    ],
    "wof:name":"Family Physicians Of Pembroke",
    "wof:placetype":"venue"
},
  "geometry": {"coordinates":[-71.449535,43.137748],"type":"Point"}
}