{
  "type": "Feature",
  "properties": {
    "iso:country":"US",
    "sg:address":"30 River St",
    "sg:city":"Exeter",
    "sg:classifiers":[
        {
            "category":"Professional",
            "subcategory":"Accounting & Tax Preparation",
            "type":"Services"
        }
    ],
    "sg:phone":"+1 603 775 7015",
    "sg:postcode":"03833",
    "sg:province":"NH",
    "sg:tags":[
        "bookkeeping",
        "general"
    ],
    "wof:name":"ADZ Up Inc",
    "wof:placetype":"venue"
},
  "geometry": {"coordinates":[-70.94465599999999,42.978365],"type":"Point"}
}