{
  "type": "Feature",
  "properties": {
    "iso:country":"US",
    "sg:address":"223 E Main St",
    "sg:city":"Conway",
    "sg:classifiers":[
        {
            "category":"Retail",
            "subcategory":"Animal Services",
            "type":"Services"
        }
    ],
    "sg:phone":"+1 603 447 5955",
    "sg:postcode":"03818",
    "sg:province":"NH",
    "sg:tags":[
        "pet",
        "shelter",
        "store"
    ],
    "sg:website":"www.conwayshelter.org",
    "wof:name":"Conway Area Humane Society",
    "wof:placetype":"venue"
},
  "geometry": {"coordinates":[-71.114998,43.978802],"type":"Point"}
}