{
  "type": "Feature",
  "properties": {
    "iso:country":"US",
    "sg:address":"101 Elm Ave",
    "sg:city":"Antrim",
    "sg:classifiers":[
        {
            "category":"Health Services",
            "subcategory":"Doctor",
            "type":"Services"
        }
    ],
    "sg:phone":"+1 603 588 4042",
    "sg:postcode":"03440",
    "sg:province":"NH",
    "sg:tags":[
        "clinic"
    ],
    "wof:name":"AAU Medical Legal Consulting",
    "wof:placetype":"venue"
},
  "geometry": {"coordinates":[-71.93303899999999,43.064772],"type":"Point"}
}