{
  "type": "Feature",
  "properties": {
    "iso:country":"US",
    "sg:address":"4 Main St",
    "sg:city":"Hollis",
    "sg:classifiers":[
        {
            "category":"Personal",
            "subcategory":"Beauty Salon",
            "type":"Services"
        }
    ],
    "sg:phone":"+1 603 321 8899",
    "sg:postcode":"03049",
    "sg:province":"NH",
    "sg:tags":[
        "treatment",
        "skin"
    ],
    "wof:name":"Skin Is In",
    "wof:placetype":"venue"
},
  "geometry": {"coordinates":[-71.590728,42.740101],"type":"Point"}
}