{
  "type": "Feature",
  "properties": {
    "iso:country":"US",
    "sg:address":"4 Elmview Cir",
    "sg:city":"Dover",
    "sg:classifiers":[
        {
            "category":"Restaurant",
            "type":"Food & Drink"
        }
    ],
    "sg:phone":"+1 603 742 6540",
    "sg:postcode":"03820",
    "sg:province":"NH",
    "sg:tags":[
        "eating"
    ],
    "wof:name":"Leas Lunch and More",
    "wof:placetype":"venue"
},
  "geometry": {"coordinates":[-70.86630599999999,43.187565],"type":"Point"}
}