{
  "type": "Feature",
  "properties": {
    "iso:country":"US",
    "sg:address":"542 Pembroke St",
    "sg:city":"Pembroke",
    "sg:classifiers":[
        {
            "category":"Organizations",
            "subcategory":"Religious Organization",
            "type":"Services"
        }
    ],
    "sg:phone":"+1 603 415 4040",
    "sg:postcode":"03275",
    "sg:province":"NH",
    "sg:tags":[
        "church"
    ],
    "wof:name":"Northern New England",
    "wof:placetype":"venue"
},
  "geometry": {"coordinates":[-71.479866,43.169757],"type":"Point"}
}