{
  "type": "Feature",
  "properties": {
    "iso:country":"US",
    "sg:address":"358 County Rd",
    "sg:city":"Hillsboro",
    "sg:classifiers":[
        {
            "category":"Manufacturing",
            "subcategory":"Tools & Machinery",
            "type":"Manufacturing & Wholesale Goods"
        }
    ],
    "sg:phone":"+1 603 464 4310",
    "sg:postcode":"03244",
    "sg:province":"NH",
    "sg:tags":[
        "machine",
        "shop"
    ],
    "wof:name":"Utopia Machine Works",
    "wof:placetype":"venue"
},
  "geometry": {"coordinates":[-71.96044999999999,43.185739],"type":"Point"}
}