{
  "type": "Feature",
  "properties": {
    "addr:full":"19 Surrey Ln Hampton Falls NH 03844",
    "addr:housenumber":"19",
    "addr:postcode":"03844",
    "addr:street":"Surrey Ln",
    "iso:country":"US",
    "sg:address":"19 Surrey Ln",
    "sg:city":"Hampton Falls",
    "sg:classifiers":[
        {
            "category":"Manufacturing",
            "subcategory":"Printing",
            "type":"Manufacturing & Wholesale Goods"
        }
    ],
    "sg:phone":"+1 603 778 7191",
    "sg:postcode":"03844",
    "sg:province":"NH",
    "sg:tags":[
        "publisher"
    ],
    "sg:website":"www.grantbooks.com",
    "wof:name":"Donald M Grant Publisher Inc",
    "wof:placetype":"venue"
},
  "geometry": {"coordinates":[-70.89758500000001,42.938976],"type":"Point"}
}