{
  "type": "Feature",
  "properties": {
    "iso:country":"US",
    "sg:address":"106 Deerwood Dr",
    "sg:city":"Nashua",
    "sg:classifiers":[
        {
            "category":"Shopping",
            "subcategory":"Hobbies, Toys, & Games",
            "type":"Retail Goods"
        },
        {
            "category":"Wholesale",
            "subcategory":"Toys & Hobbies",
            "type":"Manufacturing & Wholesale Goods"
        }
    ],
    "sg:phone":"+1 603 591 1734",
    "sg:postcode":"03063",
    "sg:province":"NH",
    "sg:tags":[
        "shop",
        "model",
        "supplies-wholesale",
        "manufacturer"
    ],
    "wof:name":"Gemini Rockets",
    "wof:placetype":"venue"
},
  "geometry": {"coordinates":[-71.530033,42.784056],"type":"Point"}
}