{
  "type": "Feature",
  "properties": {
    "iso:country":"US",
    "sg:address":"61 Russell Hill Rd",
    "sg:city":"Brookline",
    "sg:classifiers":[
        {
            "category":"Shopping",
            "subcategory":"Computers & Home Electronics",
            "type":"Retail Goods"
        }
    ],
    "sg:phone":"+1 603 673 2808",
    "sg:postcode":"03033",
    "sg:province":"NH",
    "sg:tags":[
        "software"
    ],
    "wof:name":"Northern Horizons Inc",
    "wof:placetype":"venue"
},
  "geometry": {"coordinates":[-71.699799,42.73497],"type":"Point"}
}