{
  "type": "Feature",
  "properties": {
    "addr:full":"2 Wellman Ave Nashua NH 03064",
    "addr:housenumber":"2",
    "addr:postcode":"03064",
    "addr:street":"Wellman Ave",
    "iso:country":"US",
    "sg:address":"2 Wellman Ave",
    "sg:city":"Nashua",
    "sg:classifiers":[
        {
            "category":"Health Services",
            "subcategory":"Health Practitioner",
            "type":"Services"
        }
    ],
    "sg:phone":"+1 603 881 3993",
    "sg:postcode":"03064",
    "sg:province":"NH",
    "sg:tags":[
        "acupuncture"
    ],
    "wof:name":"Southern New Hampshire",
    "wof:placetype":"venue"
},
  "geometry": {"coordinates":[-71.48517099999999,42.776919],"type":"Point"}
}