{
  "type": "Feature",
  "properties": {
    "iso:country":"US",
    "sg:address":"75 Webster St",
    "sg:city":"Manchester",
    "sg:classifiers":[
        {
            "category":"Food & Beverages",
            "subcategory":"Groceries & Convenience Stores",
            "type":"Retail Goods"
        }
    ],
    "sg:phone":"+1 603 622 5080",
    "sg:postcode":"03104",
    "sg:province":"NH",
    "sg:tags":[
        "market"
    ],
    "wof:name":"Bunny's Superette",
    "wof:placetype":"venue"
},
  "geometry": {"coordinates":[-71.46137899999999,43.006695],"type":"Point"}
}