{
  "type": "Feature",
  "properties": {
    "iso:country":"US",
    "sg:address":"15 Rush Rd",
    "sg:city":"Henniker",
    "sg:classifiers":[
        {
            "category":"Shopping",
            "subcategory":"Music",
            "type":"Retail Goods"
        }
    ],
    "sg:phone":"+1 603 428 7699",
    "sg:postcode":"03242",
    "sg:province":"NH",
    "sg:tags":[
        "video",
        "disc",
        "tape",
        "cassette"
    ],
    "wof:name":"Cabin Fever Video",
    "wof:placetype":"venue"
},
  "geometry": {"coordinates":[-71.822002,43.179691],"type":"Point"}
}