{
  "type": "Feature",
  "properties": {
    "addr:full":"852 Lafayette Rd Hampton NH 03842",
    "addr:housenumber":"852",
    "addr:postcode":"03842",
    "iso:country":"US",
    "sg:address":"852 Lafayette Rd",
    "sg:city":"Hampton",
    "sg:classifiers":[
        {
            "category":"Autos & Motor Vehicles",
            "subcategory":"Auto Supplies",
            "type":"Retail Goods"
        }
    ],
    "sg:phone":"+1 603 926 1133",
    "sg:postcode":"03842",
    "sg:province":"NH",
    "sg:tags":[
        "automotive",
        "parts"
    ],
    "wof:name":"Motor Manuals",
    "wof:placetype":"venue"
},
  "geometry": {"coordinates":[-70.83295099999999,42.953549],"type":"Point"}
}