{
  "type": "Feature",
  "properties": {
    "iso:country":"US",
    "sg:address":"11 Railroad Ave",
    "sg:city":"Seabrook",
    "sg:classifiers":[
        {
            "category":"Social Services",
            "type":"Services"
        }
    ],
    "sg:phone":"+1 603 474 6099",
    "sg:postcode":"03874",
    "sg:province":"NH",
    "sg:tags":[
        "care",
        "center",
        "day"
    ],
    "wof:name":"Cousins Adult Day Care Ctr",
    "wof:placetype":"venue"
},
  "geometry": {"coordinates":[-70.869598,42.888489],"type":"Point"}
}