{
  "type": "Feature",
  "properties": {
    "iso:country":"US",
    "sg:address":"230 E Conway Rd",
    "sg:city":"Conway",
    "sg:classifiers":[
        {
            "category":"Retail",
            "subcategory":"Auto Repair",
            "type":"Services"
        }
    ],
    "sg:phone":"+1 603 356 6801",
    "sg:postcode":"03818",
    "sg:province":"NH",
    "sg:tags":[
        "repairing",
        "automobile"
    ],
    "wof:name":"Ken Williams Automotive Svc",
    "wof:placetype":"venue"
},
  "geometry": {"coordinates":[-71.045867,44.003572],"type":"Point"}
}