{
  "type": "Feature",
  "properties": {
    "addr:full":"12 Depot St Peterborough NH 03458",
    "addr:housenumber":"12",
    "addr:postcode":"03458",
    "addr:street":"Depot St",
    "iso:country":"US",
    "sg:address":"12 Depot St",
    "sg:city":"Peterborough",
    "sg:classifiers":[
        {
            "category":"Shopping",
            "subcategory":"Computers & Home Electronics",
            "type":"Retail Goods"
        }
    ],
    "sg:phone":"+1 603 924 7664",
    "sg:postcode":"03458",
    "sg:province":"NH",
    "sg:tags":[
        "equipment",
        "dealer"
    ],
    "sg:website":"www.abilities.com",
    "wof:name":"Compucare Inc",
    "wof:placetype":"venue"
},
  "geometry": {"coordinates":[-71.949287,42.877422],"type":"Point"}
}