{
  "type": "Feature",
  "properties": {
    "iso:country":"US",
    "sg:address":"241 Mast Rd",
    "sg:city":"Dover",
    "sg:classifiers":[
        {
            "category":"Building & Trades",
            "subcategory":"Construction",
            "type":"Services"
        }
    ],
    "sg:phone":"+1 603 742 2092",
    "sg:postcode":"03820",
    "sg:province":"NH",
    "sg:tags":[
        "excavating",
        "contractor"
    ],
    "wof:name":"Garrison Land Corp",
    "wof:placetype":"venue"
},
  "geometry": {"coordinates":[-70.892915,43.168582],"type":"Point"}
}