{
  "type": "Feature",
  "properties": {
    "iso:country":"US",
    "sg:address":"24 Main St",
    "sg:city":"Pittsfield",
    "sg:classifiers":[
        {
            "category":"Organizations",
            "subcategory":"Religious Organization",
            "type":"Services"
        }
    ],
    "sg:phone":"+1 603 435 7471",
    "sg:postcode":"03263",
    "sg:province":"NH",
    "sg:tags":[
        "church"
    ],
    "wof:name":"Congregational Church",
    "wof:placetype":"venue"
},
  "geometry": {"coordinates":[-71.328484,43.305426],"type":"Point"}
}