{
  "type": "Feature",
  "properties": {
    "iso:country":"US",
    "sg:address":"61 Crystal Ave",
    "sg:city":"Derry",
    "sg:classifiers":[
        {
            "category":"Cinema",
            "subcategory":"Movie Rental",
            "type":"Entertainment"
        }
    ],
    "sg:phone":"+1 603 432 1879",
    "sg:postcode":"03038",
    "sg:province":"NH",
    "sg:tags":[
        "leasing",
        "video",
        "disc",
        "tape"
    ],
    "sg:website":"www.myvideostore.com",
    "wof:name":"Movie Scene",
    "wof:placetype":"venue"
},
  "geometry": {"coordinates":[-71.32710400000001,42.890729],"type":"Point"}
}