{
  "type": "Feature",
  "properties": {
    "iso:country":"US",
    "sg:address":"51 Main St",
    "sg:city":"West Lebanon",
    "sg:classifiers":[
        {
            "category":"Government",
            "subcategory":"Post Office",
            "type":"Public Place"
        }
    ],
    "sg:phone":"+1 603 298 8440",
    "sg:postcode":"03784",
    "sg:province":"NH",
    "wof:name":"US Post Office",
    "wof:placetype":"venue"
},
  "geometry": {"coordinates":[-72.31020599999999,43.646998],"type":"Point"}
}