{
  "type": "Feature",
  "properties": {
    "addr:full":"120 Walnut Hill Rd Derry NH 03038",
    "addr:housenumber":"120",
    "addr:postcode":"03038",
    "addr:street":"Walnut Hill Rd",
    "iso:country":"US",
    "sg:address":"120 Walnut Hill Rd",
    "sg:city":"Derry",
    "sg:classifiers":[
        {
            "category":"Building & Trades",
            "subcategory":"Construction",
            "type":"Services"
        }
    ],
    "sg:phone":"+1 603 434 6777",
    "sg:postcode":"03038",
    "sg:province":"NH",
    "sg:tags":[
        "contractor"
    ],
    "wof:name":"Boutot All Star Drywall",
    "wof:placetype":"venue"
},
  "geometry": {"coordinates":[-71.249067,42.914455],"type":"Point"}
}