{
  "type": "Feature",
  "properties": {
    "addr:full":"27 River Rd Tilton NH 03276",
    "addr:housenumber":"27",
    "addr:postcode":"03276",
    "addr:street":"River Rd",
    "iso:country":"US",
    "sg:address":"27 River Rd",
    "sg:city":"Tilton",
    "sg:classifiers":[
        {
            "category":"Manufacturing",
            "subcategory":"Tools & Machinery",
            "type":"Manufacturing & Wholesale Goods"
        }
    ],
    "sg:phone":"+1 603 528 0042",
    "sg:postcode":"03276",
    "sg:province":"NH",
    "sg:tags":[
        "industrial",
        "mfg"
    ],
    "wof:name":"Stillwater Tech",
    "wof:placetype":"venue"
},
  "geometry": {"coordinates":[-71.535079,43.474386],"type":"Point"}
}