{
  "type": "Feature",
  "properties": {
    "iso:country":"US",
    "sg:address":"192 W Main St",
    "sg:city":"Hillsboro",
    "sg:classifiers":[
        {
            "category":"Food & Beverages",
            "subcategory":"Groceries & Convenience Stores",
            "type":"Retail Goods"
        }
    ],
    "sg:phone":"+1 603 464 3330",
    "sg:postcode":"03244",
    "sg:province":"NH",
    "sg:tags":[
        "grocer"
    ],
    "wof:name":"West Main Market",
    "wof:placetype":"venue"
},
  "geometry": {"coordinates":[-71.910813,43.111188],"type":"Point"}
}