{
  "type": "Feature",
  "properties": {
    "iso:country":"US",
    "sg:address":"43 Smith Corner Rd",
    "sg:city":"Newton",
    "sg:classifiers":[
        {
            "category":"Building & Trades",
            "subcategory":"Landscaping Services",
            "type":"Services"
        }
    ],
    "sg:phone":"+1 603 382 1221",
    "sg:postcode":"03858",
    "sg:province":"NH",
    "sg:tags":[
        "tree"
    ],
    "wof:name":"Kma Tree Service",
    "wof:placetype":"venue"
},
  "geometry": {"coordinates":[-71.06567800000001,42.847666],"type":"Point"}
}