{
  "type": "Feature",
  "properties": {
    "addr:full":"128 Jasper St Berlin NH 03570",
    "addr:housenumber":"128",
    "addr:postcode":"03570",
    "addr:street":"Jasper St",
    "iso:country":"US",
    "sg:address":"128 Jasper St",
    "sg:city":"Berlin",
    "sg:classifiers":[
        {
            "category":"Building & Trades",
            "subcategory":"Electrical",
            "type":"Services"
        }
    ],
    "sg:phone":"+1 603 752 5541",
    "sg:postcode":"03570",
    "sg:province":"NH",
    "sg:tags":[
        "electric",
        "contractor"
    ],
    "wof:name":"Vaillancourt's Electric",
    "wof:placetype":"venue"
},
  "geometry": {"coordinates":[-71.18608399999999,44.480337],"type":"Point"}
}