{
  "type": "Feature",
  "properties": {
    "iso:country":"US",
    "sg:address":"41 Avon St",
    "sg:city":"Keene",
    "sg:classifiers":[
        {
            "category":"Insurance",
            "subcategory":"Insurance Agent",
            "type":"Services"
        }
    ],
    "sg:phone":"+1 603 352 8615",
    "sg:postcode":"03431",
    "sg:province":"NH",
    "wof:name":"Insurance Adjustment Service",
    "wof:placetype":"venue"
},
  "geometry": {"coordinates":[-72.29396300000001,42.932737],"type":"Point"}
}