{
  "type": "Feature",
  "properties": {
    "iso:country":"US",
    "sg:address":"53 Jug City Rd",
    "sg:city":"Epsom",
    "sg:classifiers":[
        {
            "category":"Freight",
            "type":"Transportation"
        }
    ],
    "sg:phone":"+1 603 736 8041",
    "sg:postcode":"03234",
    "sg:province":"NH",
    "sg:tags":[
        "operator",
        "local",
        "trucking"
    ],
    "wof:name":"Al Stephens Trucking",
    "wof:placetype":"venue"
},
  "geometry": {"coordinates":[-71.395449,43.18968],"type":"Point"}
}