{
  "type": "Feature",
  "properties": {
    "iso:country":"US",
    "sg:address":"79 September Dr",
    "sg:city":"Greenland",
    "sg:classifiers":[
        {
            "category":"Education",
            "subcategory":"Music School",
            "type":"Public Place"
        }
    ],
    "sg:phone":"+1 603 431 3033",
    "sg:postcode":"03840",
    "sg:province":"NH",
    "wof:name":"Midi Schoolhouse",
    "wof:placetype":"venue"
},
  "geometry": {"coordinates":[-70.830477,43.017051],"type":"Point"}
}