{
  "type": "Feature",
  "properties": {
    "iso:country":"US",
    "sg:address":"9 Rush Rd",
    "sg:city":"Henniker",
    "sg:classifiers":[
        {
            "category":"Health Services",
            "subcategory":"Health Practitioner",
            "type":"Services"
        }
    ],
    "sg:phone":"+1 603 428 8386",
    "sg:postcode":"03242",
    "sg:province":"NH",
    "sg:tags":[
        "therapist",
        "physical"
    ],
    "wof:name":"Henniker Physical Therapy",
    "wof:placetype":"venue"
},
  "geometry": {"coordinates":[-71.820013,43.20859],"type":"Point"}
}