{
  "type": "Feature",
  "properties": {
    "addr:full":"984 2nd St Manchester NH 03102",
    "addr:housenumber":"984",
    "addr:postcode":"03102",
    "addr:street":"2Nd St",
    "iso:country":"US",
    "sg:address":"984 2nd St",
    "sg:city":"Manchester",
    "sg:classifiers":[
        {
            "category":"Wholesale",
            "subcategory":"Motor Vehicles",
            "type":"Manufacturing & Wholesale Goods"
        }
    ],
    "sg:phone":"+1 603 625 1215",
    "sg:postcode":"03102",
    "sg:province":"NH",
    "sg:tags":[
        "automobile",
        "dealer"
    ],
    "wof:name":"KMS Wholesale",
    "wof:placetype":"venue"
},
  "geometry": {"coordinates":[-71.481138,42.966013],"type":"Point"}
}