{
  "type": "Feature",
  "properties": {
    "iso:country":"US",
    "sg:address":"44 Roby Rd",
    "sg:city":"New Boston",
    "sg:classifiers":[
        {
            "category":"Building & Trades",
            "subcategory":"Construction",
            "type":"Services"
        }
    ],
    "sg:phone":"+1 603 497 2290",
    "sg:postcode":"03070",
    "sg:province":"NH",
    "sg:tags":[
        "home",
        "improvement"
    ],
    "wof:name":"Superior Architectural",
    "wof:placetype":"venue"
},
  "geometry": {"coordinates":[-71.61862000000001,42.974171],"type":"Point"}
}