{
  "type": "Feature",
  "properties": {
    "addr:full":"98 Spit Brook Road, Suite 100 Nashua NH 03062 ",
    "addr:housenumber":"98",
    "addr:postcode":"03062",
    "addr:street":"Spit Brook Road Suite 100",
    "iso:country":"US",
    "sg:address":"98 Spit Brook Road, Suite 100",
    "sg:city":"Nashua",
    "sg:classifiers":[
        {
            "category":"Professional",
            "subcategory":"Research",
            "type":"Services"
        }
    ],
    "sg:phone":"+1 603 882 5200",
    "sg:postcode":"03062 ",
    "sg:province":"NH",
    "sg:website":"http://www.icadmed.com",
    "wof:name":"iCAD",
    "wof:placetype":"venue"
},
  "geometry": {"coordinates":[-71.452941,42.707941],"type":"Point"}
}