{
  "type": "Feature",
  "properties": {
    "addr:full":"92 Old Chester Rd Derry NH 03038",
    "addr:housenumber":"92",
    "addr:postcode":"03038",
    "addr:street":"Old Chester Rd",
    "iso:country":"US",
    "sg:address":"92 Old Chester Rd",
    "sg:city":"Derry",
    "sg:classifiers":[
        {
            "category":"Building & Trades",
            "subcategory":"Construction",
            "type":"Services"
        }
    ],
    "sg:phone":"+1 603 432 0090",
    "sg:postcode":"03038",
    "sg:province":"NH",
    "sg:tags":[
        "contractor"
    ],
    "wof:name":"Center Line Fence",
    "wof:placetype":"venue"
},
  "geometry": {"coordinates":[-71.281507,42.908324],"type":"Point"}
}