{
  "type": "Feature",
  "properties": {
    "iso:country":"US",
    "sg:address":"405 S Main St",
    "sg:city":"Landaff",
    "sg:classifiers":[
        {
            "category":"Manufacturing",
            "subcategory":"Lumber",
            "type":"Manufacturing & Wholesale Goods"
        }
    ],
    "sg:phone":"+1 603 838 5111",
    "sg:postcode":"03576",
    "sg:province":"NH",
    "sg:tags":[
        "company",
        "logging"
    ],
    "wof:name":"Stockley Trucking Inc",
    "wof:placetype":"venue"
},
  "geometry": {"coordinates":[-71.50709000000001,44.880868],"type":"Point"}
}