{
  "type": "Feature",
  "properties": {
    "addr:full":"10 Hooksett Tpke Bow NH 03304",
    "addr:housenumber":"10",
    "addr:postcode":"03304",
    "addr:street":"Hooksett Tpke",
    "iso:country":"US",
    "sg:address":"10 Hooksett Tpke",
    "sg:city":"Bow",
    "sg:classifiers":[
        {
            "category":"Building & Trades",
            "subcategory":"Construction",
            "type":"Services"
        }
    ],
    "sg:phone":"+1 603 226 4242",
    "sg:postcode":"03304",
    "sg:province":"NH",
    "sg:tags":[
        "painter"
    ],
    "wof:name":"Tuxedo Painting",
    "wof:placetype":"venue"
},
  "geometry": {"coordinates":[-71.584287,43.15079],"type":"Point"}
}