{
  "type": "Feature",
  "properties": {
    "iso:country":"US",
    "sg:address":"801 McGee Dr",
    "sg:city":"Portsmouth",
    "sg:classifiers":[
        {
            "category":"Government",
            "subcategory":"Office",
            "type":"Public Place"
        }
    ],
    "sg:phone":"+1 603 436 7426",
    "sg:postcode":"03801",
    "sg:province":"NH",
    "sg:tags":[
        "federal",
        "security"
    ],
    "wof:name":"US Army National Guard Recruit",
    "wof:placetype":"venue"
},
  "geometry": {"coordinates":[-70.78081,43.082768],"type":"Point"}
}