{
  "type": "Feature",
  "properties": {
    "addr:full":"2315 Columbia Cir Merrimack NH 03054",
    "addr:housenumber":"2315",
    "addr:postcode":"03054",
    "addr:street":"Columbia Cir",
    "iso:country":"US",
    "sg:address":"2315 Columbia Cir",
    "sg:city":"Merrimack",
    "sg:classifiers":[
        {
            "category":"Wholesale",
            "subcategory":"Non-durable Goods",
            "type":"Manufacturing & Wholesale Goods"
        }
    ],
    "sg:phone":"+1 603 424 7438",
    "sg:postcode":"03054",
    "sg:province":"NH",
    "sg:tags":[
        "candle"
    ],
    "wof:name":"Old English Lights Candle Co",
    "wof:placetype":"venue"
},
  "geometry": {"coordinates":[-71.493482,42.853308],"type":"Point"}
}