{
  "type": "Feature",
  "properties": {
    "iso:country":"US",
    "sg:address":"1 Bayside Rd Ste 11",
    "sg:city":"Greenland",
    "sg:phone":"+1 603 431 8311",
    "sg:postcode":"03840",
    "sg:province":"NH",
    "wof:name":"Diamond King Sports",
    "wof:placetype":"venue"
},
  "geometry": {"coordinates":[-70.84899900000001,43.035999],"type":"Point"}
}