{
  "type": "Feature",
  "properties": {
    "addr:full":"26 Artisan Ct Gilford NH 03249",
    "addr:housenumber":"26",
    "addr:postcode":"03249",
    "addr:street":"Artisan Ct",
    "iso:country":"US",
    "sg:address":"26 Artisan Ct",
    "sg:city":"Gilford",
    "sg:classifiers":[
        {
            "category":"Retail",
            "subcategory":"Auto Repair",
            "type":"Services"
        }
    ],
    "sg:phone":"+1 603 528 4323",
    "sg:postcode":"03249",
    "sg:province":"NH",
    "sg:tags":[
        "body",
        "automobile",
        "painting"
    ],
    "wof:name":"Bayview Auto Body",
    "wof:placetype":"venue"
},
  "geometry": {"coordinates":[-71.433623,43.577335],"type":"Point"}
}