{
  "type": "Feature",
  "properties": {
    "addr:full":"16 Henniker St Hillsboro NH 03244",
    "addr:postcode":"03244",
    "addr:street":"Henniker St",
    "iso:country":"US",
    "sg:address":"16 Henniker St",
    "sg:city":"Hillsboro",
    "sg:classifiers":[
        {
            "category":"Organizations",
            "subcategory":"Religious Organization",
            "type":"Services"
        }
    ],
    "sg:phone":"+1 603 464 3056",
    "sg:postcode":"03244",
    "sg:province":"NH",
    "sg:tags":[
        "church"
    ],
    "wof:name":"United Methodist Church",
    "wof:placetype":"venue"
},
  "geometry": {"coordinates":[-71.893787,43.115753],"type":"Point"}
}