{
  "type": "Feature",
  "properties": {
    "addr:full":"23 Glenridge Way Laconia NH 03249",
    "addr:housenumber":"23",
    "addr:postcode":"03249",
    "addr:street":"Glenridge Way",
    "iso:country":"US",
    "sg:address":"23 Glenridge Way",
    "sg:city":"Laconia",
    "sg:classifiers":[
        {
            "category":"Freight",
            "type":"Transportation"
        }
    ],
    "sg:phone":"+1 603 524 0600",
    "sg:postcode":"03249",
    "sg:province":"NH",
    "sg:tags":[
        "operator",
        "local",
        "trucking"
    ],
    "wof:name":"Errands Unlimited",
    "wof:placetype":"venue"
},
  "geometry": {"coordinates":[-71.451393,43.535605],"type":"Point"}
}