{
  "type": "Feature",
  "properties": {
    "iso:country":"US",
    "sg:address":"1 E Pearl St",
    "sg:city":"Nashua",
    "sg:classifiers":[
        {
            "category":"Shopping",
            "subcategory":"Gifts & Souvenirs",
            "type":"Retail Goods"
        }
    ],
    "sg:phone":"+1 603 889 7447",
    "sg:postcode":"03060",
    "sg:province":"NH",
    "sg:tags":[
        "basket",
        "parcel"
    ],
    "wof:name":"Gift In A Basket",
    "wof:placetype":"venue"
},
  "geometry": {"coordinates":[-71.459659,42.761678],"type":"Point"}
}