{
  "type": "Feature",
  "properties": {
    "iso:country":"US",
    "sg:address":"3 Maureen Ln",
    "sg:city":"Hudson",
    "sg:classifiers":[
        {
            "category":"Professional",
            "subcategory":"Computer Services",
            "type":"Services"
        }
    ],
    "sg:phone":"+1 603 886 3822",
    "sg:postcode":"03051",
    "sg:province":"NH",
    "sg:tags":[
        "consultant",
        "designer"
    ],
    "wof:name":"Bang! Software Solutions",
    "wof:placetype":"venue"
},
  "geometry": {"coordinates":[-71.39706700000001,42.806075],"type":"Point"}
}