{
  "type": "Feature",
  "properties": {
    "addr:full":"327 River Rd Piermont NH 03779",
    "addr:housenumber":"327",
    "addr:postcode":"03779",
    "addr:street":"River Rd",
    "iso:country":"US",
    "sg:address":"327 River Rd",
    "sg:city":"Piermont",
    "sg:classifiers":[
        {
            "category":"Farming",
            "subcategory":"Dairy Farm",
            "type":"Manufacturing & Wholesale Goods"
        }
    ],
    "sg:phone":"+1 603 272 9132",
    "sg:postcode":"03779",
    "sg:province":"NH",
    "wof:name":"Moonstruck Farm",
    "wof:placetype":"venue"
},
  "geometry": {"coordinates":[-72.07010699999999,44.02159],"type":"Point"}
}