{
  "type": "Feature",
  "properties": {
    "iso:country":"US",
    "sg:address":"44 Old Wilton Rd",
    "sg:city":"New Ipswich",
    "sg:classifiers":[
        {
            "category":"Retail",
            "subcategory":"Portrait Studio",
            "type":"Services"
        }
    ],
    "sg:phone":"+1 603 878 9028",
    "sg:postcode":"03071",
    "sg:province":"NH",
    "sg:tags":[
        "photo"
    ],
    "wof:name":"Babbling Brook Photography",
    "wof:placetype":"venue"
},
  "geometry": {"coordinates":[-71.82576400000001,42.775893],"type":"Point"}
}