{
  "type": "Feature",
  "properties": {
    "iso:country":"US",
    "sg:address":"77 Forrest St",
    "sg:city":"Plaistow",
    "sg:classifiers":[
        {
            "category":"Freight",
            "type":"Transportation"
        }
    ],
    "sg:phone":"+1 603 382 5376",
    "sg:postcode":"03865",
    "sg:province":"NH",
    "sg:tags":[
        "operator",
        "local",
        "trucking"
    ],
    "wof:name":"Ordway Trucking",
    "wof:placetype":"venue"
},
  "geometry": {"coordinates":[-71.07322600000001,42.820208],"type":"Point"}
}