{
  "type": "Feature",
  "properties": {
    "addr:full":"70 Shirley Hill Rd Goffstown NH 03045",
    "addr:housenumber":"70",
    "addr:postcode":"03045",
    "addr:street":"Shirley Hill Rd",
    "iso:country":"US",
    "sg:address":"70 Shirley Hill Rd",
    "sg:city":"Goffstown",
    "sg:classifiers":[
        {
            "category":"Freight",
            "type":"Transportation"
        }
    ],
    "sg:phone":"+1 603 497 2204",
    "sg:postcode":"03045",
    "sg:province":"NH",
    "sg:tags":[
        "operator",
        "trucking"
    ],
    "wof:name":"HP Welch Trucking",
    "wof:placetype":"venue"
},
  "geometry": {"coordinates":[-71.56397,42.987803],"type":"Point"}
}