{
  "type": "Feature",
  "properties": {
    "iso:country":"US",
    "sg:address":"136 Bedford Center Rd",
    "sg:city":"Bedford",
    "sg:classifiers":[
        {
            "category":"Shopping",
            "subcategory":"Florist",
            "type":"Retail Goods"
        }
    ],
    "sg:phone":"+1 603 472 3264",
    "sg:postcode":"03110",
    "sg:province":"NH",
    "wof:name":"Blue Goose",
    "wof:placetype":"venue"
},
  "geometry": {"coordinates":[-71.524689,42.939013],"type":"Point"}
}