{
  "type": "Feature",
  "properties": {
    "iso:country":"US",
    "sg:address":"143 Fairview Ave",
    "sg:city":"Conway",
    "sg:classifiers":[
        {
            "category":"Building & Trades",
            "subcategory":"Plumbing",
            "type":"Services"
        }
    ],
    "sg:phone":"+1 603 447 3497",
    "sg:postcode":"03818",
    "sg:province":"NH",
    "wof:name":"Alpine Plumbing & Heating",
    "wof:placetype":"venue"
},
  "geometry": {"coordinates":[-71.139397,43.976898],"type":"Point"}
}