{
  "type": "Feature",
  "properties": {
    "iso:country":"US",
    "sg:address":"207 Baldwin St",
    "sg:city":"Laconia",
    "sg:classifiers":[
        {
            "category":"Real Estate",
            "subcategory":"Architect",
            "type":"Services"
        }
    ],
    "sg:phone":"+1 603 528 8511",
    "sg:postcode":"03246",
    "sg:province":"NH",
    "sg:tags":[
        "specification",
        "architectural"
    ],
    "wof:name":"Arc-Spec Consulting",
    "wof:placetype":"venue"
},
  "geometry": {"coordinates":[-71.46136199999999,43.522161],"type":"Point"}
}