{
  "type": "Feature",
  "properties": {
    "iso:country":"US",
    "sg:address":"73 Brady Ave",
    "sg:city":"Salem",
    "sg:classifiers":[
        {
            "category":"Farming",
            "subcategory":"Farm",
            "type":"Manufacturing & Wholesale Goods"
        }
    ],
    "sg:phone":"+1 603 898 1906",
    "sg:postcode":"03079",
    "sg:province":"NH",
    "wof:name":"Midland Farms Inc",
    "wof:placetype":"venue"
},
  "geometry": {"coordinates":[-71.24341699999999,42.755713],"type":"Point"}
}