{
  "type": "Feature",
  "properties": {
    "iso:country":"US",
    "sg:address":"64 Harvey Rd",
    "sg:city":"Londonderry",
    "sg:classifiers":[
        {
            "category":"Retail",
            "subcategory":"Repair Shop",
            "type":"Services"
        }
    ],
    "sg:phone":"+1 603 432 5065",
    "sg:postcode":"03053",
    "sg:province":"NH",
    "sg:tags":[
        "clocks",
        "parts"
    ],
    "wof:name":"Northern Ne Employment Svc",
    "wof:placetype":"venue"
},
  "geometry": {"coordinates":[-71.420793,42.910291],"type":"Point"}
}