{
  "type": "Feature",
  "properties": {
    "addr:full":"158 Wilton Rd Peterborough NH 03458",
    "addr:housenumber":"158",
    "addr:postcode":"03458",
    "addr:street":"Wilton Rd",
    "iso:country":"US",
    "sg:address":"158 Wilton Rd",
    "sg:city":"Peterborough",
    "sg:classifiers":[
        {
            "category":"Professional",
            "subcategory":"Business Services",
            "type":"Services"
        }
    ],
    "sg:phone":"+1 603 924 6867",
    "sg:postcode":"03458",
    "sg:province":"NH",
    "sg:tags":[
        "embroidery"
    ],
    "wof:name":"Buttercup Embroidery",
    "wof:placetype":"venue"
},
  "geometry": {"coordinates":[-71.940968,42.865024],"type":"Point"}
}