{
  "type": "Feature",
  "properties": {
    "addr:full":"134 River Rd Bow NH 03304",
    "addr:housenumber":"134",
    "addr:postcode":"03304",
    "addr:street":"River Rd",
    "iso:country":"US",
    "sg:address":"134 River Rd",
    "sg:city":"Bow",
    "sg:classifiers":[
        {
            "category":"Autos & Motor Vehicles",
            "subcategory":"Auto Supplies",
            "type":"Retail Goods"
        }
    ],
    "sg:phone":"+1 603 223 0609",
    "sg:postcode":"03304",
    "sg:province":"NH",
    "sg:tags":[
        "tire"
    ],
    "wof:name":"New England Truck Tire Ctr",
    "wof:placetype":"venue"
},
  "geometry": {"coordinates":[-71.46631499999999,43.127933],"type":"Point"}
}