{
  "type": "Feature",
  "properties": {
    "iso:country":"US",
    "sg:address":"38 Berry Rd",
    "sg:city":"Derry",
    "sg:classifiers":[
        {
            "category":"Freight",
            "type":"Transportation"
        }
    ],
    "sg:phone":"+1 603 432 7158",
    "sg:postcode":"03038",
    "sg:province":"NH",
    "wof:name":"McCullough Transport",
    "wof:placetype":"venue"
},
  "geometry": {"coordinates":[-71.30238199999999,42.862735],"type":"Point"}
}