{
  "type": "Feature",
  "properties": {
    "iso:country":"US",
    "sg:address":"189 Meaderboro Rd",
    "sg:city":"Farmington",
    "sg:classifiers":[
        {
            "category":"Farming",
            "subcategory":"Dairy Farm",
            "type":"Manufacturing & Wholesale Goods"
        }
    ],
    "sg:phone":"+1 603 332 1130",
    "sg:postcode":"03835",
    "sg:province":"NH",
    "wof:name":"Scruton's Dairy",
    "wof:placetype":"venue"
},
  "geometry": {"coordinates":[-71.060563,43.317751],"type":"Point"}
}