{
  "type": "Feature",
  "properties": {
    "iso:country":"US",
    "sg:address":"62 Durham St",
    "sg:city":"Portsmouth",
    "sg:classifiers":[
        {
            "category":"Airport",
            "type":"Transportation"
        }
    ],
    "sg:phone":"+1 603 427 0350",
    "sg:postcode":"03801",
    "sg:province":"NH",
    "sg:tags":[
        "aircraft",
        "maintenance"
    ],
    "wof:name":"Pan AM Svc",
    "wof:placetype":"venue"
},
  "geometry": {"coordinates":[-70.806431,43.072055],"type":"Point"}
}