{
  "type": "Feature",
  "properties": {
    "addr:full":"304 Sheep Davis Rd Concord NH 03301",
    "addr:housenumber":"304",
    "addr:postcode":"03301",
    "addr:street":"Sheep Davis Rd",
    "iso:country":"US",
    "sg:address":"304 Sheep Davis Rd",
    "sg:city":"Concord",
    "sg:classifiers":[
        {
            "category":"Utilities",
            "subcategory":"Mobile Phone",
            "type":"Services"
        }
    ],
    "sg:phone":"+1 603 228 5286",
    "sg:postcode":"03301",
    "sg:province":"NH",
    "sg:tags":[
        "telephone",
        "cellular"
    ],
    "wof:name":"Wireless Retail Inc",
    "wof:placetype":"venue"
},
  "geometry": {"coordinates":[-71.476173,43.228445],"type":"Point"}
}