{
  "type": "Feature",
  "properties": {
    "iso:country":"US",
    "sg:address":"42 Garnet St",
    "sg:city":"Sunapee",
    "sg:classifiers":[
        {
            "category":"Building & Trades",
            "subcategory":"Construction",
            "type":"Services"
        }
    ],
    "sg:phone":"+1 603 763 2263",
    "sg:postcode":"03782",
    "sg:province":"NH",
    "sg:tags":[
        "company"
    ],
    "wof:name":"Currier Construction Co Site",
    "wof:placetype":"venue"
},
  "geometry": {"coordinates":[-72.08179800000001,43.395126],"type":"Point"}
}