{
  "type": "Feature",
  "properties": {
    "iso:country":"US",
    "sg:address":"44 Denmark Dr",
    "sg:city":"Northwood",
    "sg:classifiers":[
        {
            "category":"Building & Trades",
            "subcategory":"Plumbing",
            "type":"Services"
        }
    ],
    "sg:phone":"+1 603 942 7377",
    "sg:postcode":"03261",
    "sg:province":"NH",
    "sg:tags":[
        "plumbing",
        "contractor"
    ],
    "wof:name":"Rescue Plumbing and Heating",
    "wof:placetype":"venue"
},
  "geometry": {"coordinates":[-71.24776900000001,43.216491],"type":"Point"}
}