{
  "type": "Feature",
  "properties": {
    "addr:full":"801 Central Ave Dover NH 03820",
    "addr:housenumber":"801",
    "addr:postcode":"03820",
    "addr:street":"Central Ave",
    "iso:country":"US",
    "sg:address":"801 Central Ave",
    "sg:city":"Dover",
    "sg:classifiers":[
        {
            "category":"Health Services",
            "subcategory":"Doctor",
            "type":"Services"
        }
    ],
    "sg:phone":"+1 603 749 2224",
    "sg:postcode":"03820",
    "sg:province":"NH",
    "sg:tags":[
        "surgery",
        "oral"
    ],
    "wof:name":"Gregory L Shaker DDS",
    "wof:placetype":"venue"
},
  "geometry": {"coordinates":[-70.87876,43.21528],"type":"Point"}
}