{
  "type": "Feature",
  "properties": {
    "addr:full":"21 Westview Rd Brookline NH 03033",
    "addr:housenumber":"21",
    "addr:postcode":"03033",
    "addr:street":"Westview Rd",
    "iso:country":"US",
    "sg:address":"21 Westview Rd",
    "sg:city":"Brookline",
    "sg:classifiers":[
        {
            "category":"Shopping",
            "subcategory":"Computers & Home Electronics",
            "type":"Retail Goods"
        }
    ],
    "sg:phone":"+1 603 672 8112",
    "sg:postcode":"03033",
    "sg:province":"NH",
    "sg:tags":[
        "software"
    ],
    "wof:name":"Penta Ware Inc",
    "wof:placetype":"venue"
},
  "geometry": {"coordinates":[-71.64497900000001,42.770937],"type":"Point"}
}