{
  "type": "Feature",
  "properties": {
    "iso:country":"US",
    "sg:address":"49 Forest Dr",
    "sg:city":"Hollis",
    "sg:classifiers":[
        {
            "category":"Professional",
            "subcategory":"Computer Services",
            "type":"Services"
        }
    ],
    "sg:phone":"+1 603 465 6672",
    "sg:postcode":"03032",
    "sg:province":"NH",
    "sg:tags":[
        "design",
        "system"
    ],
    "wof:name":"Oaktree Peak Software",
    "wof:placetype":"venue"
},
  "geometry": {"coordinates":[-71.354748,43.013734],"type":"Point"}
}