{
  "type": "Feature",
  "properties": {
    "addr:full":"480 Center St Wolfeboro NH 03894",
    "addr:housenumber":"480",
    "addr:postcode":"03894",
    "addr:street":"Center St",
    "iso:country":"US",
    "sg:address":"480 Center St",
    "sg:city":"Wolfeboro",
    "sg:classifiers":[
        {
            "category":"Building & Trades",
            "subcategory":"Construction",
            "type":"Services"
        }
    ],
    "sg:phone":"+1 603 569 2864",
    "sg:postcode":"03894",
    "sg:province":"NH",
    "sg:tags":[
        "contractor"
    ],
    "wof:name":"Albee Contractors",
    "wof:placetype":"venue"
},
  "geometry": {"coordinates":[-71.200897,43.593601],"type":"Point"}
}