{
  "type": "Feature",
  "properties": {
    "iso:country":"US",
    "sg:address":"4 Linwood Ave",
    "sg:city":"Derry",
    "sg:classifiers":[
        {
            "category":"Personal",
            "subcategory":"Beauty Salon",
            "type":"Services"
        }
    ],
    "sg:phone":"+1 603 434 2293",
    "sg:postcode":"03038",
    "sg:province":"NH",
    "sg:tags":[
        "shop"
    ],
    "wof:name":"Richard E Boulette",
    "wof:placetype":"venue"
},
  "geometry": {"coordinates":[-71.335576,42.876236],"type":"Point"}
}