{
  "type": "Feature",
  "properties": {
    "addr:full":"297 S Broadway Salem NH 03079",
    "addr:housenumber":"297",
    "addr:postcode":"03079",
    "addr:street":"S Broadway",
    "iso:country":"US",
    "sg:address":"297 S Broadway",
    "sg:city":"Salem",
    "sg:classifiers":[
        {
            "category":"Restaurant",
            "type":"Food & Drink"
        }
    ],
    "sg:menulink":"http://www.allmenus.com/nh/salem/110375-chilis/menu/",
    "sg:phone":"+1 603 890 1777",
    "sg:postcode":"03079",
    "sg:province":"NH",
    "sg:tags":[
        "burger",
        "american",
        "sandwich",
        "tex-mex",
        "soup"
    ],
    "wof:name":"Chili's",
    "wof:placetype":"venue"
},
  "geometry": {"coordinates":[-71.211923,42.757959],"type":"Point"}
}