{
  "type": "Feature",
  "properties": {
    "iso:country":"US",
    "sg:address":"34 Portsmouth Ave",
    "sg:city":"Exeter",
    "sg:classifiers":[
        {
            "category":"Retail",
            "subcategory":"Repair Shop",
            "type":"Services"
        }
    ],
    "sg:phone":"+1 603 772 2233",
    "sg:postcode":"03833",
    "sg:province":"NH",
    "sg:tags":[
        "television",
        "radio"
    ],
    "wof:name":"Exeter Television Svc",
    "wof:placetype":"venue"
},
  "geometry": {"coordinates":[-70.93966500000001,42.983327],"type":"Point"}
}