{
  "type": "Feature",
  "properties": {
    "iso:country":"US",
    "sg:address":"225 Daniel Webster Hwy",
    "sg:city":"Nashua",
    "sg:classifiers":[
        {
            "category":"Personal",
            "subcategory":"Beauty Salon",
            "type":"Services"
        }
    ],
    "sg:phone":"+1 603 888 3300",
    "sg:postcode":"03060",
    "sg:province":"NH",
    "sg:tags":[
        "shop"
    ],
    "sg:website":"www.cassandrasalon.com",
    "wof:name":"Cassandra Appearance Domain",
    "wof:placetype":"venue"
},
  "geometry": {"coordinates":[-71.442617,42.712645],"type":"Point"}
}