{
  "type": "Feature",
  "properties": {
    "iso:country":"US",
    "sg:address":"355 Middle Rd",
    "sg:city":"Brentwood",
    "sg:classifiers":[
        {
            "category":"Health Services",
            "subcategory":"Health Practitioner",
            "type":"Services"
        }
    ],
    "sg:phone":"+1 603 775 7777",
    "sg:postcode":"03833",
    "sg:province":"NH",
    "sg:tags":[
        "psychotherapist"
    ],
    "wof:name":"Monika Ostroff",
    "wof:placetype":"venue"
},
  "geometry": {"coordinates":[-71.064762,42.984456],"type":"Point"}
}