{
  "type": "Feature",
  "properties": {
    "addr:full":"546 First New Hampshire Tpke Northwood NH 03261",
    "addr:housenumber":"546",
    "addr:postcode":"03261",
    "addr:street":"First New;Tpke",
    "iso:country":"US",
    "sg:address":"546 First New Hampshire Tpke",
    "sg:city":"Northwood",
    "sg:classifiers":[
        {
            "category":"Shopping",
            "subcategory":"Discount & Variety Stores",
            "type":"Retail Goods"
        }
    ],
    "sg:phone":"+1 603 942 8898",
    "sg:postcode":"03261",
    "sg:province":"NH",
    "sg:tags":[
        "merchandise",
        "general"
    ],
    "wof:name":"No Limits",
    "wof:placetype":"venue"
},
  "geometry": {"coordinates":[-71.189345,43.210498],"type":"Point"}
}