{
  "type": "Feature",
  "properties": {
    "iso:country":"US",
    "sg:address":"22 School St",
    "sg:city":"Hanover",
    "sg:classifiers":[
        {
            "category":"Professional",
            "subcategory":"Management & Consulting",
            "type":"Services"
        }
    ],
    "sg:phone":"+1 603 643 2181",
    "sg:postcode":"03755",
    "sg:province":"NH",
    "sg:tags":[
        "business"
    ],
    "wof:name":"Henry Clews Consulting",
    "wof:placetype":"venue"
},
  "geometry": {"coordinates":[-72.291456,43.699597],"type":"Point"}
}