{
  "type": "Feature",
  "properties": {
    "addr:full":"6 W Broadway Derry NH 03038",
    "addr:housenumber":"6",
    "addr:postcode":"03038",
    "addr:street":"W Broadway",
    "iso:country":"US",
    "sg:address":"6 W Broadway",
    "sg:city":"Derry",
    "sg:classifiers":[
        {
            "category":"Food & Beverages",
            "subcategory":"Specialty",
            "type":"Retail Goods"
        }
    ],
    "sg:phone":"+1 603 425 1117",
    "sg:postcode":"03038",
    "sg:province":"NH",
    "sg:tags":[
        "health",
        "diet"
    ],
    "wof:name":"Herbal Life Independent Distr",
    "wof:placetype":"venue"
},
  "geometry": {"coordinates":[-71.326712,42.880503],"type":"Point"}
}