{
  "type": "Feature",
  "properties": {
    "iso:country":"US",
    "sg:address":"382 Ray Rd",
    "sg:city":"Henniker",
    "sg:classifiers":[
        {
            "category":"Recreation",
            "subcategory":"Campground",
            "type":"Entertainment"
        }
    ],
    "sg:phone":"+1 603 428 7213",
    "sg:postcode":"03242",
    "sg:province":"NH",
    "sg:tags":[
        "recreational",
        "park",
        "vehicle"
    ],
    "wof:name":"Rock'n'birch Campground",
    "wof:placetype":"venue"
},
  "geometry": {"coordinates":[-71.79693399999999,43.202003],"type":"Point"}
}