{
  "type": "Feature",
  "properties": {
    "iso:country":"US",
    "sg:address":"86 N Main St",
    "sg:city":"Newport",
    "sg:classifiers":[
        {
            "category":"Education",
            "subcategory":"School",
            "type":"Public Place"
        }
    ],
    "sg:phone":"+1 603 863 2050",
    "sg:postcode":"03773",
    "sg:province":"NH",
    "wof:name":"Goshen-Lempster Co-Op SD 43",
    "wof:placetype":"venue"
},
  "geometry": {"coordinates":[-72.175774,43.367315],"type":"Point"}
}