{
  "type": "Feature",
  "properties": {
    "iso:country":"US",
    "sg:address":"243 Crown Point Rd",
    "sg:city":"Rochester",
    "sg:classifiers":[
        {
            "category":"Professional",
            "type":"Services"
        }
    ],
    "sg:phone":"+1 603 332 8540",
    "sg:postcode":"03867",
    "sg:province":"NH",
    "wof:name":"C/O Cheryl Hastings",
    "wof:placetype":"venue"
},
  "geometry": {"coordinates":[-71.067098,43.296296],"type":"Point"}
}