{
  "type": "Feature",
  "properties": {
    "iso:country":"US",
    "sg:address":"1857 E Conway Rd",
    "sg:city":"North Conway",
    "sg:classifiers":[
        {
            "category":"Shopping",
            "subcategory":"Discount & Variety Stores",
            "type":"Retail Goods"
        }
    ],
    "sg:phone":"+1 603 356 3616",
    "sg:postcode":"03813",
    "sg:province":"NH",
    "wof:name":"Wardo's",
    "wof:placetype":"venue"
},
  "geometry": {"coordinates":[-71.05955400000001,44.011275],"type":"Point"}
}