{
  "type": "Feature",
  "properties": {
    "addr:full":"182 Tamworth Rd Tamworth NH 03886",
    "addr:housenumber":"182",
    "addr:postcode":"03886",
    "addr:street":"Tamworth Rd",
    "iso:country":"US",
    "sg:address":"182 Tamworth Rd",
    "sg:city":"Tamworth",
    "sg:classifiers":[
        {
            "category":"Government",
            "subcategory":"Post Office",
            "type":"Public Place"
        }
    ],
    "sg:phone":"+1 603 323 8708",
    "sg:postcode":"03886",
    "sg:province":"NH",
    "wof:name":"US Post Office",
    "wof:placetype":"venue"
},
  "geometry": {"coordinates":[-71.264318,43.848557],"type":"Point"}
}