{
  "type": "Feature",
  "properties": {
    "addr:full":"64 Pine Hill Rd Wolfeboro NH 03894",
    "addr:housenumber":"64",
    "addr:postcode":"03894",
    "addr:street":"Pine Hill Rd",
    "iso:country":"US",
    "sg:address":"64 Pine Hill Rd",
    "sg:city":"Wolfeboro",
    "sg:classifiers":[
        {
            "category":"Professional",
            "subcategory":"Secretarial Services",
            "type":"Services"
        }
    ],
    "sg:phone":"+1 603 569 0300",
    "sg:postcode":"03894",
    "sg:province":"NH",
    "sg:tags":[
        "reporting"
    ],
    "wof:name":"New England Transcription Inc",
    "wof:placetype":"venue"
},
  "geometry": {"coordinates":[-71.21461600000001,43.608524],"type":"Point"}
}