{
  "type": "Feature",
  "properties": {
    "addr:full":"4 Peters Brook Dr Hooksett NH 03106",
    "addr:housenumber":"4",
    "addr:postcode":"03106",
    "addr:street":"Peters Brook Dr",
    "iso:country":"US",
    "sg:address":"4 Peters Brook Dr",
    "sg:city":"Hooksett",
    "sg:classifiers":[
        {
            "category":"Manufacturing",
            "subcategory":"Printing",
            "type":"Manufacturing & Wholesale Goods"
        }
    ],
    "sg:phone":"+1 603 625 6901",
    "sg:postcode":"03106",
    "sg:province":"NH",
    "sg:tags":[
        "printer"
    ],
    "sg:website":"www.cummingsprinting.com",
    "wof:name":"Cummings Printing Co",
    "wof:placetype":"venue"
},
  "geometry": {"coordinates":[-71.447373,43.059662],"type":"Point"}
}