{
  "type": "Feature",
  "properties": {
    "iso:country":"US",
    "sg:address":"1471 Main St",
    "sg:city":"Berlin",
    "sg:classifiers":[
        {
            "category":"Building & Trades",
            "subcategory":"Electrical",
            "type":"Services"
        }
    ],
    "sg:phone":"+1 603 752 4383",
    "sg:postcode":"03570",
    "sg:province":"NH",
    "sg:tags":[
        "electrical",
        "contractor"
    ],
    "wof:name":"Boyz Electric",
    "wof:placetype":"venue"
},
  "geometry": {"coordinates":[-71.167508,44.48492],"type":"Point"}
}