{
  "type": "Feature",
  "properties": {
    "iso:country":"US",
    "sg:address":"5 Bedford Farms",
    "sg:city":"Bedford",
    "sg:classifiers":[
        {
            "category":"Banks & Credit Unions",
            "subcategory":"Investment Brokerage",
            "type":"Services"
        }
    ],
    "sg:phone":"+1 603 668 1273",
    "sg:postcode":"03110",
    "sg:province":"NH",
    "sg:tags":[
        "consultant",
        "planning",
        "financial"
    ],
    "wof:name":"American Express Financial Adv",
    "wof:placetype":"venue"
},
  "geometry": {"coordinates":[-71.481319,42.956074],"type":"Point"}
}