{
  "type": "Feature",
  "properties": {
    "iso:country":"US",
    "sg:address":"100 Loudon Rd",
    "sg:city":"Concord",
    "sg:classifiers":[
        {
            "category":"Banks & Credit Unions",
            "subcategory":"Bank",
            "type":"Services"
        }
    ],
    "sg:phone":"+1 603 224 7719",
    "sg:postcode":"03301",
    "sg:province":"NH",
    "sg:tags":[
        "state",
        "commercial"
    ],
    "wof:name":"Fleet",
    "wof:placetype":"venue"
},
  "geometry": {"coordinates":[-71.513189,43.213008],"type":"Point"}
}