{
  "type": "Feature",
  "properties": {
    "iso:country":"US",
    "sg:address":"280 County Rd",
    "sg:city":"New London",
    "sg:classifiers":[
        {
            "category":"Health Services",
            "subcategory":"Doctor",
            "type":"Services"
        }
    ],
    "sg:phone":"+1 603 526 5260",
    "sg:postcode":"03257",
    "sg:province":"NH",
    "sg:tags":[
        "physician",
        "surgeon"
    ],
    "wof:name":"Associates In Surgery",
    "wof:placetype":"venue"
},
  "geometry": {"coordinates":[-72.000755,43.421345],"type":"Point"}
}