{
  "type": "Feature",
  "properties": {
    "addr:full":"169 Curtis Farm Rd Wilton NH 03086",
    "addr:housenumber":"169",
    "addr:postcode":"03086",
    "addr:street":"Curtis Farm Rd",
    "iso:country":"US",
    "sg:address":"169 Curtis Farm Rd",
    "sg:city":"Wilton",
    "sg:classifiers":[
        {
            "category":"Building & Trades",
            "subcategory":"Construction",
            "type":"Services"
        }
    ],
    "sg:phone":"+1 603 654 5620",
    "sg:postcode":"03086",
    "sg:province":"NH",
    "sg:tags":[
        "carpentry",
        "contractor"
    ],
    "wof:name":"Matt Audette & Sons Carpentry",
    "wof:placetype":"venue"
},
  "geometry": {"coordinates":[-71.744202,42.855241],"type":"Point"}
}