{
  "type": "Feature",
  "properties": {
    "addr:full":"17 Progress Ave Nashua NH 03062",
    "addr:housenumber":"17",
    "addr:postcode":"03062",
    "addr:street":"Progress Ave",
    "iso:country":"US",
    "sg:address":"17 Progress Ave",
    "sg:city":"Nashua",
    "sg:classifiers":[
        {
            "category":"Retail",
            "subcategory":"Auto Repair",
            "type":"Services"
        }
    ],
    "sg:phone":"+1 603 882 0037",
    "sg:postcode":"03062",
    "sg:province":"NH",
    "sg:tags":[
        "repairing",
        "automobile"
    ],
    "wof:name":"Cambray's Automotive Svc",
    "wof:placetype":"venue"
},
  "geometry": {"coordinates":[-71.48944400000001,42.739894],"type":"Point"}
}