{
  "type": "Feature",
  "properties": {
    "iso:country":"US",
    "sg:address":"56 Knox Pasture Rd",
    "sg:city":"Wolfeboro",
    "sg:classifiers":[
        {
            "category":"Autos & Motor Vehicles",
            "subcategory":"Automobile Sales",
            "type":"Retail Goods"
        },
        {
            "category":"Taxi",
            "type":"Transportation"
        },
        {
            "category":"Airline",
            "type":"Transportation"
        }
    ],
    "sg:phone":"+1 603 569 3189",
    "sg:postcode":"03894",
    "sg:province":"NH",
    "sg:tags":[
        "shuttle",
        "airport",
        "limo"
    ],
    "wof:name":"Winnipesaukee Livery Llc",
    "wof:placetype":"venue"
},
  "geometry": {"coordinates":[-71.186542,43.624791],"type":"Point"}
}