{
  "type": "Feature",
  "properties": {
    "addr:full":"165 Rosedale Ave Manchester NH 03103",
    "addr:housenumber":"165",
    "addr:postcode":"03103",
    "addr:street":"Rosedale Ave",
    "iso:country":"US",
    "sg:address":"165 Rosedale Ave",
    "sg:city":"Manchester",
    "sg:classifiers":[
        {
            "category":"Retail",
            "subcategory":"Auto Repair",
            "type":"Services"
        }
    ],
    "sg:phone":"+1 603 625 1720",
    "sg:postcode":"03103",
    "sg:province":"NH",
    "sg:tags":[
        "wrecker"
    ],
    "wof:name":"Admiral Towing LLC",
    "wof:placetype":"venue"
},
  "geometry": {"coordinates":[-71.45848700000001,42.969104],"type":"Point"}
}