{
  "type": "Feature",
  "properties": {
    "iso:country":"US",
    "sg:address":"585 State Rte 4a",
    "sg:city":"Enfield",
    "sg:classifiers":[
        {
            "category":"Home & Garden",
            "subcategory":"Garden Supply",
            "type":"Retail Goods"
        }
    ],
    "sg:phone":"+1 603 632 4070",
    "sg:postcode":"03748",
    "sg:province":"NH",
    "wof:name":"Upper Valley Kioti & Equipment",
    "wof:placetype":"venue"
},
  "geometry": {"coordinates":[-72.141561,43.612023],"type":"Point"}
}