{
  "type": "Feature",
  "properties": {
    "addr:full":"145 Peele Rd Nashua NH 03062",
    "addr:housenumber":"145",
    "addr:postcode":"03062",
    "addr:street":"Peele Rd",
    "iso:country":"US",
    "sg:address":"145 Peele Rd",
    "sg:city":"Nashua",
    "sg:classifiers":[
        {
            "category":"Professional",
            "subcategory":"Management & Consulting",
            "type":"Services"
        }
    ],
    "sg:phone":"+1 603 888 6450",
    "sg:postcode":"03062",
    "sg:province":"NH",
    "sg:tags":[
        "fuel"
    ],
    "wof:name":"O'Connell Management Co",
    "wof:placetype":"venue"
},
  "geometry": {"coordinates":[-71.46373199999999,42.718901],"type":"Point"}
}