{
  "type": "Feature",
  "properties": {
    "iso:country":"US",
    "sg:address":"67 S River Rd",
    "sg:city":"Bedford",
    "sg:classifiers":[
        {
            "category":"Wholesale",
            "subcategory":"Plants",
            "type":"Manufacturing & Wholesale Goods"
        }
    ],
    "sg:phone":"+1 603 668 6048",
    "sg:postcode":"03110",
    "sg:province":"NH",
    "sg:tags":[
        "florist"
    ],
    "wof:name":"John R Mc Gilvary & Sons",
    "wof:placetype":"venue"
},
  "geometry": {"coordinates":[-71.47892899999999,42.95825],"type":"Point"}
}