{
  "type": "Feature",
  "properties": {
    "iso:country":"US",
    "sg:address":"97 Paradise Dr",
    "sg:city":"Bennington",
    "sg:classifiers":[
        {
            "category":"Building & Trades",
            "subcategory":"Construction",
            "type":"Services"
        }
    ],
    "sg:phone":"+1 603 588 3765",
    "sg:postcode":"03442",
    "sg:province":"NH",
    "sg:tags":[
        "carpenter"
    ],
    "wof:name":"Gallant Systems Svc",
    "wof:placetype":"venue"
},
  "geometry": {"coordinates":[-71.918358,42.988754],"type":"Point"}
}