{
  "type": "Feature",
  "properties": {
    "addr:full":"1 Integra Dr Concord NH 03301",
    "addr:housenumber":"1",
    "addr:postcode":"03301",
    "addr:street":"Integra Dr",
    "iso:country":"US",
    "sg:address":"1 Integra Dr",
    "sg:city":"Concord",
    "sg:classifiers":[
        {
            "category":"Banks & Credit Unions",
            "subcategory":"Bank",
            "type":"Services"
        }
    ],
    "sg:phone":"+1 603 225 2793",
    "sg:postcode":"03301",
    "sg:province":"NH",
    "wof:name":"Merrimack County Savings Bank",
    "wof:placetype":"venue"
},
  "geometry": {"coordinates":[-71.50332299999999,43.184778],"type":"Point"}
}