{
  "type": "Feature",
  "properties": {
    "addr:full":"930 Easton Rd Franconia NH 03580",
    "addr:housenumber":"930",
    "addr:postcode":"03580",
    "addr:street":"Easton Rd",
    "iso:country":"US",
    "sg:address":"930 Easton Rd",
    "sg:city":"Franconia",
    "sg:classifiers":[
        {
            "category":"Building & Trades",
            "subcategory":"Plumbing",
            "type":"Services"
        }
    ],
    "sg:phone":"+1 603 823 5327",
    "sg:postcode":"03580",
    "sg:province":"NH",
    "sg:tags":[
        "plumbing",
        "contractor"
    ],
    "wof:name":"J C Plumbing & Heating Co",
    "wof:placetype":"venue"
},
  "geometry": {"coordinates":[-71.77834199999999,44.157818],"type":"Point"}
}