{
  "type": "Feature",
  "properties": {
    "iso:country":"US",
    "sg:address":"406 S Main St",
    "sg:city":"Concord",
    "sg:classifiers":[
        {
            "category":"Travel",
            "subcategory":"Hotels & Motels",
            "type":"Entertainment"
        }
    ],
    "sg:phone":"+1 603 224 2511",
    "sg:postcode":"03301",
    "sg:province":"NH",
    "wof:name":"Days Inn",
    "wof:placetype":"venue"
},
  "geometry": {"coordinates":[-71.53086999999999,43.179099],"type":"Point"}
}