{
  "type": "Feature",
  "properties": {
    "addr:full":"3 Stonehedge Rd Windham NH 03087",
    "addr:housenumber":"3",
    "addr:postcode":"03087",
    "addr:street":"Stonehedge Rd",
    "iso:country":"US",
    "sg:address":"3 Stonehedge Rd",
    "sg:city":"Windham",
    "sg:classifiers":[
        {
            "category":"Food & Beverages",
            "subcategory":"Liquor & Beverages",
            "type":"Retail Goods"
        }
    ],
    "sg:phone":"+1 603 870 9420",
    "sg:postcode":"03087",
    "sg:province":"NH",
    "sg:tags":[
        "alcoholic"
    ],
    "wof:name":"Windham Wine Cellars",
    "wof:placetype":"venue"
},
  "geometry": {"coordinates":[-71.260895,42.816278],"type":"Point"}
}