{
  "type": "Feature",
  "properties": {
    "addr:full":"14 Lafayette Rd North Hampton NH 03862",
    "addr:housenumber":"14",
    "addr:postcode":"03862",
    "iso:country":"US",
    "sg:address":"14 Lafayette Rd",
    "sg:city":"North Hampton",
    "sg:classifiers":[
        {
            "category":"Social Services",
            "subcategory":"Child Care",
            "type":"Services"
        },
        {
            "category":"Education",
            "subcategory":"Special Training",
            "type":"Public Place"
        }
    ],
    "sg:phone":"+1 603 964 2230",
    "sg:postcode":"03862",
    "sg:province":"NH",
    "sg:tags":[
        "day"
    ],
    "wof:name":"Imprint's Day School",
    "wof:placetype":"venue"
},
  "geometry": {"coordinates":[-70.83422299999999,42.960486],"type":"Point"}
}