{
  "type": "Feature",
  "properties": {
    "iso:country":"US",
    "sg:address":"521 Lost River Rd",
    "sg:city":"North Woodstock",
    "sg:classifiers":[
        {
            "category":"Restaurant",
            "type":"Food & Drink"
        }
    ],
    "sg:phone":"+1 603 745 6620",
    "sg:postcode":"03262",
    "sg:province":"NH",
    "wof:name":"Govoni's Italian Restaurant",
    "wof:placetype":"venue"
},
  "geometry": {"coordinates":[-71.702555,44.030798],"type":"Point"}
}