{
  "type": "Feature",
  "properties": {
    "iso:country":"US",
    "sg:address":"46 River Rd",
    "sg:city":"Hudson",
    "sg:classifiers":[
        {
            "category":"Professional",
            "subcategory":"Research",
            "type":"Services"
        }
    ],
    "sg:phone":"+1 603 889 3653",
    "sg:postcode":"03051",
    "sg:province":"NH",
    "wof:name":"AGFA Corporation",
    "wof:placetype":"venue"
},
  "geometry": {"coordinates":[-71.41991,42.715158],"type":"Point"}
}