{
  "type": "Feature",
  "properties": {
    "addr:full":"3507 Claremont Rd Charlestown NH 03603",
    "addr:housenumber":"3507",
    "addr:postcode":"03603",
    "addr:street":"Claremont Rd",
    "iso:country":"US",
    "sg:address":"3507 Claremont Rd",
    "sg:city":"Charlestown",
    "sg:classifiers":[
        {
            "category":"Freight",
            "type":"Transportation"
        }
    ],
    "sg:phone":"+1 603 542 2500",
    "sg:postcode":"03603",
    "sg:province":"NH",
    "sg:tags":[
        "building",
        "operator",
        "apartment",
        "general"
    ],
    "wof:name":"Mitza Family Trust",
    "wof:placetype":"venue"
},
  "geometry": {"coordinates":[-72.378029,43.32167],"type":"Point"}
}