{
  "type": "Feature",
  "properties": {
    "iso:country":"US",
    "sg:address":"750 Lafayette Rd",
    "sg:city":"Hampton",
    "sg:classifiers":[
        {
            "category":"Professional",
            "subcategory":"Accounting & Tax Preparation",
            "type":"Services"
        }
    ],
    "sg:phone":"+1 603 926 6644",
    "sg:postcode":"03842",
    "sg:province":"NH",
    "sg:tags":[
        "accountant"
    ],
    "wof:name":"Krieger & Co",
    "wof:placetype":"venue"
},
  "geometry": {"coordinates":[-70.832415,42.948343],"type":"Point"}
}