{
  "type": "Feature",
  "properties": {
    "iso:country":"US",
    "sg:address":"81 Cross Rd",
    "sg:city":"Hooksett",
    "sg:classifiers":[
        {
            "category":"Retail",
            "subcategory":"Portrait Studio",
            "type":"Services"
        }
    ],
    "sg:phone":"+1 603 625 6011",
    "sg:postcode":"03106",
    "sg:province":"NH",
    "sg:tags":[
        "photography"
    ],
    "wof:name":"Thomas Roy",
    "wof:placetype":"venue"
},
  "geometry": {"coordinates":[-71.481633,43.073001],"type":"Point"}
}