{
  "type": "Feature",
  "properties": {
    "addr:full":"134 State Rte 25 Meredith NH 03253",
    "addr:housenumber":"134",
    "addr:postcode":"03253",
    "addr:street":"State Rte 25",
    "iso:country":"US",
    "sg:address":"134 State Rte 25",
    "sg:city":"Meredith",
    "sg:classifiers":[
        {
            "category":"Recreation",
            "type":"Entertainment"
        }
    ],
    "sg:phone":"+1 603 279 0287",
    "sg:postcode":"03253",
    "sg:province":"NH",
    "wof:name":"Lakes Region Riding Academy",
    "wof:placetype":"venue"
},
  "geometry": {"coordinates":[-71.49108,43.664121],"type":"Point"}
}