{
  "type": "Feature",
  "properties": {
    "addr:full":"10 Cotton Rd Nashua NH 03063",
    "addr:housenumber":"10",
    "addr:postcode":"03063",
    "addr:street":"Cotton Rd",
    "iso:country":"US",
    "sg:address":"10 Cotton Rd",
    "sg:city":"Nashua",
    "sg:classifiers":[
        {
            "category":"Building & Trades",
            "subcategory":"Plumbing",
            "type":"Services"
        }
    ],
    "sg:phone":"+1 603 882 2021",
    "sg:postcode":"03063",
    "sg:province":"NH",
    "sg:tags":[
        "conditioning",
        "air",
        "system",
        "contractor"
    ],
    "sg:website":"www.jlawrencehall.com",
    "wof:name":"J Lawrence Hall Co",
    "wof:placetype":"venue"
},
  "geometry": {"coordinates":[-71.511098,42.78455],"type":"Point"}
}