{
  "type": "Feature",
  "properties": {
    "addr:full":"199 Pepsi Rd Manchester NH 03109",
    "addr:housenumber":"199",
    "addr:postcode":"03109",
    "addr:street":"Pepsi Rd",
    "iso:country":"US",
    "sg:address":"199 Pepsi Rd",
    "sg:city":"Manchester",
    "sg:classifiers":[
        {
            "category":"Manufacturing",
            "subcategory":"Food",
            "type":"Manufacturing & Wholesale Goods"
        }
    ],
    "sg:phone":"+1 603 622 0996",
    "sg:postcode":"03109",
    "sg:province":"NH",
    "sg:tags":[
        "bakery",
        "prod",
        "cookie"
    ],
    "wof:name":"Country Kitchen-Le Page Bakery",
    "wof:placetype":"venue"
},
  "geometry": {"coordinates":[-71.402843,42.974102],"type":"Point"}
}