{
  "type": "Feature",
  "properties": {
    "iso:country":"US",
    "sg:address":"120 E Dunstable Rd",
    "sg:city":"Nashua",
    "sg:classifiers":[
        {
            "category":"Retail",
            "subcategory":"Laundry & Dry Cleaning",
            "type":"Services"
        }
    ],
    "sg:phone":"+1 603 888 3341",
    "sg:postcode":"03062",
    "sg:province":"NH",
    "sg:tags":[
        "cleaners"
    ],
    "wof:name":"Benjamin's Dry Cleaning",
    "wof:placetype":"venue"
},
  "geometry": {"coordinates":[-71.471217,42.731041],"type":"Point"}
}