{
  "type": "Feature",
  "properties": {
    "iso:country":"US",
    "sg:address":"5 Flagstone Dr",
    "sg:city":"Hudson",
    "sg:classifiers":[
        {
            "category":"Building & Trades",
            "subcategory":"Construction",
            "type":"Services"
        }
    ],
    "sg:phone":"+1 603 883 0097",
    "sg:postcode":"03051",
    "sg:province":"NH",
    "sg:tags":[
        "steel",
        "fabrication",
        "welding"
    ],
    "wof:name":"Integrated Dynamics",
    "wof:placetype":"venue"
},
  "geometry": {"coordinates":[-71.42959999999999,42.731389],"type":"Point"}
}