{
  "type": "Feature",
  "properties": {
    "iso:country":"US",
    "sg:address":"1 Park Ave",
    "sg:city":"Hampton",
    "sg:classifiers":[
        {
            "category":"Building & Trades",
            "subcategory":"Construction",
            "type":"Services"
        }
    ],
    "sg:phone":"+1 603 926 4200",
    "sg:postcode":"03842",
    "sg:province":"NH",
    "sg:tags":[
        "general",
        "contractor"
    ],
    "wof:name":"Drakes Appleton Corp",
    "wof:placetype":"venue"
},
  "geometry": {"coordinates":[-70.835852,42.93362],"type":"Point"}
}