{
  "type": "Feature",
  "properties": {
    "addr:full":"200 Zachary Rd Manchester NH 03109",
    "addr:housenumber":"200",
    "addr:postcode":"03109",
    "addr:street":"Zachary Rd",
    "iso:country":"US",
    "sg:address":"200 Zachary Rd",
    "sg:city":"Manchester",
    "sg:classifiers":[
        {
            "category":"Social Services",
            "type":"Services"
        }
    ],
    "sg:phone":"+1 603 624 9761",
    "sg:postcode":"03109",
    "sg:province":"NH",
    "sg:tags":[
        "charitable"
    ],
    "wof:name":"Easter Seal Industrial Svcs",
    "wof:placetype":"venue"
},
  "geometry": {"coordinates":[-71.406147,42.982746],"type":"Point"}
}