{
  "type": "Feature",
  "properties": {
    "addr:full":"9 Hubbard Rd Amherst NH 03031",
    "addr:housenumber":"9",
    "addr:postcode":"03031",
    "addr:street":"Hubbard Rd",
    "iso:country":"US",
    "sg:address":"9 Hubbard Rd",
    "sg:city":"Amherst",
    "sg:classifiers":[
        {
            "category":"Retail",
            "subcategory":"Photofinishing",
            "type":"Services"
        }
    ],
    "sg:phone":"+1 603 672 7007",
    "sg:postcode":"03031",
    "sg:province":"NH",
    "sg:tags":[
        "photography"
    ],
    "wof:name":"Global Images",
    "wof:placetype":"venue"
},
  "geometry": {"coordinates":[-71.634974,42.90832],"type":"Point"}
}