{
  "type": "Feature",
  "properties": {
    "addr:full":"10 Beech St Loudon NH 03307",
    "addr:housenumber":"10",
    "addr:postcode":"03307",
    "addr:street":"Beech St",
    "iso:country":"US",
    "sg:address":"10 Beech St",
    "sg:city":"Loudon",
    "sg:classifiers":[
        {
            "category":"Building & Trades",
            "subcategory":"Construction",
            "type":"Services"
        }
    ],
    "sg:phone":"+1 603 228 8017",
    "sg:postcode":"03307",
    "sg:province":"NH",
    "sg:tags":[
        "house"
    ],
    "wof:name":"Teekay Construction",
    "wof:placetype":"venue"
},
  "geometry": {"coordinates":[-71.459878,43.256747],"type":"Point"}
}