{
  "type": "Feature",
  "properties": {
    "addr:full":"7 Hamilton Ln Lyme NH 03768",
    "addr:housenumber":"7",
    "addr:postcode":"03768",
    "addr:street":"Hamilton Ln",
    "iso:country":"US",
    "sg:address":"7 Hamilton Ln",
    "sg:city":"Lyme",
    "sg:classifiers":[
        {
            "category":"Shopping",
            "subcategory":"Used Merchandise",
            "type":"Retail Goods"
        }
    ],
    "sg:phone":"+1 603 795 4628",
    "sg:postcode":"03768",
    "sg:province":"NH",
    "wof:name":"Frog Pond Books",
    "wof:placetype":"venue"
},
  "geometry": {"coordinates":[-72.160802,43.811636],"type":"Point"}
}