{
  "type": "Feature",
  "properties": {
    "iso:country":"US",
    "sg:address":"148 Monadnock Hwy",
    "sg:city":"Swanzey",
    "sg:classifiers":[
        {
            "category":"Retail",
            "subcategory":"Repair Shop",
            "type":"Services"
        }
    ],
    "sg:phone":"+1 603 357 0519",
    "sg:postcode":"03446",
    "sg:province":"NH",
    "sg:tags":[
        "clocks",
        "parts"
    ],
    "wof:name":"Sheldons Clocks",
    "wof:placetype":"venue"
},
  "geometry": {"coordinates":[-72.252076,42.898963],"type":"Point"}
}