{
  "type": "Feature",
  "properties": {
    "iso:country":"US",
    "sg:address":"81 Fieldstone Ln",
    "sg:city":"Candia",
    "sg:classifiers":[
        {
            "category":"Banks & Credit Unions",
            "subcategory":"Financial Services",
            "type":"Services"
        }
    ],
    "sg:phone":"+1 603 587 0205",
    "sg:postcode":"03034",
    "sg:province":"NH",
    "sg:tags":[
        "company",
        "holding"
    ],
    "wof:name":"Amber Cauge Holdings LLC",
    "wof:placetype":"venue"
},
  "geometry": {"coordinates":[-71.31408500000001,43.045937],"type":"Point"}
}