{
  "type": "Feature",
  "properties": {
    "iso:country":"US",
    "sg:address":"14 Shearwater St",
    "sg:city":"Durham",
    "sg:classifiers":[
        {
            "category":"Professional",
            "subcategory":"Management & Consulting",
            "type":"Services"
        }
    ],
    "sg:phone":"+1 603 868 2253",
    "sg:postcode":"03824",
    "sg:province":"NH",
    "wof:name":"Lathrop Associates",
    "wof:placetype":"venue"
},
  "geometry": {"coordinates":[-70.892248,43.136874],"type":"Point"}
}