{
  "type": "Feature",
  "properties": {
    "addr:full":"780 State Rte 63 Westmoreland NH 03467",
    "addr:housenumber":"780",
    "addr:postcode":"03467",
    "addr:street":"State Rte 63",
    "iso:country":"US",
    "sg:address":"780 State Rte 63",
    "sg:city":"Westmoreland",
    "sg:classifiers":[
        {
            "category":"Government",
            "subcategory":"Office",
            "type":"Public Place"
        }
    ],
    "sg:phone":"+1 603 399 4471",
    "sg:postcode":"03467",
    "sg:province":"NH",
    "sg:tags":[
        "village"
    ],
    "wof:name":"Westmoreland Town Selectmen",
    "wof:placetype":"venue"
},
  "geometry": {"coordinates":[-72.444339,42.950622],"type":"Point"}
}