{
  "type": "Feature",
  "properties": {
    "iso:country":"US",
    "sg:address":"39 Main St",
    "sg:city":"Hollis",
    "sg:classifiers":[
        {
            "category":"Professional",
            "type":"Services"
        }
    ],
    "sg:phone":"+1 603 465 7247",
    "sg:postcode":"03049",
    "sg:province":"NH",
    "sg:tags":[
        "establishment"
    ],
    "wof:name":"Solar Decisions Inc",
    "wof:placetype":"venue"
},
  "geometry": {"coordinates":[-71.59038099999999,42.738224],"type":"Point"}
}