{
  "type": "Feature",
  "properties": {
    "addr:full":"423 Union St Littleton NH 03561",
    "addr:housenumber":"423",
    "addr:postcode":"03561",
    "addr:street":"Union St",
    "iso:country":"US",
    "sg:address":"423 Union St",
    "sg:city":"Littleton",
    "sg:classifiers":[
        {
            "category":"Professional",
            "subcategory":"Accounting & Tax Preparation",
            "type":"Services"
        }
    ],
    "sg:phone":"+1 603 444 5306",
    "sg:postcode":"03561",
    "sg:province":"NH",
    "sg:tags":[
        "accountant"
    ],
    "wof:name":"Martin & Thomas",
    "wof:placetype":"venue"
},
  "geometry": {"coordinates":[-71.755,44.308038],"type":"Point"}
}