{
  "type": "Feature",
  "properties": {
    "iso:country":"US",
    "sg:address":"14 Evergreen Cir",
    "sg:city":"Henniker",
    "sg:classifiers":[
        {
            "category":"Retail",
            "subcategory":"Repair Shop",
            "type":"Services"
        }
    ],
    "sg:phone":"+1 603 428 7358",
    "sg:postcode":"03242",
    "sg:province":"NH",
    "sg:tags":[
        "instrument",
        "musical"
    ],
    "wof:name":"Horn Fixer",
    "wof:placetype":"venue"
},
  "geometry": {"coordinates":[-71.80815,43.199053],"type":"Point"}
}