{
  "type": "Feature",
  "properties": {
    "iso:country":"US",
    "sg:address":"1 Manor Pkwy",
    "sg:city":"Salem",
    "sg:classifiers":[
        {
            "category":"Real Estate",
            "subcategory":"Real Estate Agent",
            "type":"Services"
        }
    ],
    "sg:phone":"+1 603 893 9500",
    "sg:postcode":"03079",
    "sg:province":"NH",
    "sg:website":"www.lindarobertsrealty.com",
    "wof:name":"Linda Roberts Realty",
    "wof:placetype":"venue"
},
  "geometry": {"coordinates":[-71.24994599999999,42.775464],"type":"Point"}
}