{
  "type": "Feature",
  "properties": {
    "addr:full":"505 Amherst St Nashua NH 03063",
    "addr:housenumber":"505",
    "addr:postcode":"03063",
    "addr:street":"Amherst St",
    "iso:country":"US",
    "sg:address":"505 Amherst St",
    "sg:city":"Nashua",
    "sg:classifiers":[
        {
            "category":"Shopping",
            "subcategory":"Books",
            "type":"Retail Goods"
        }
    ],
    "sg:phone":"+1 603 880 7083",
    "sg:postcode":"03063",
    "sg:province":"NH",
    "sg:tags":[
        "dealer"
    ],
    "wof:name":"Campus Stores Of Ma Inc",
    "wof:placetype":"venue"
},
  "geometry": {"coordinates":[-71.52408,42.793637],"type":"Point"}
}