{
  "type": "Feature",
  "properties": {
    "iso:country":"US",
    "sg:address":"614 Laconia Rd",
    "sg:city":"Tilton",
    "sg:classifiers":[
        {
            "category":"Personal",
            "subcategory":"Beauty Salon",
            "type":"Services"
        }
    ],
    "sg:phone":"+1 603 528 1947",
    "sg:postcode":"03276",
    "sg:province":"NH",
    "wof:name":"Salon 3",
    "wof:placetype":"venue"
},
  "geometry": {"coordinates":[-71.529062,43.487289],"type":"Point"}
}