{
  "type": "Feature",
  "properties": {
    "addr:full":"55 Bay St Laconia NH 03246",
    "addr:housenumber":"55",
    "addr:postcode":"03246",
    "addr:street":"Bay St",
    "iso:country":"US",
    "sg:address":"55 Bay St",
    "sg:city":"Laconia",
    "sg:classifiers":[
        {
            "category":"Utilities",
            "subcategory":"Fuel Oil & Lpg",
            "type":"Services"
        }
    ],
    "sg:phone":"+1 603 524 5063",
    "sg:postcode":"03246",
    "sg:province":"NH",
    "sg:tags":[
        "repair",
        "dealer"
    ],
    "wof:name":"Fuller Oil",
    "wof:placetype":"venue"
},
  "geometry": {"coordinates":[-71.476401,43.523036],"type":"Point"}
}