{
  "type": "Feature",
  "properties": {
    "addr:full":"19 Ashram Rd Sanbornton NH 03269",
    "addr:housenumber":"19",
    "addr:postcode":"03269",
    "addr:street":"Ashram Rd",
    "iso:country":"US",
    "sg:address":"19 Ashram Rd",
    "sg:city":"Sanbornton",
    "sg:classifiers":[
        {
            "category":"Education",
            "subcategory":"School",
            "type":"Public Place"
        }
    ],
    "sg:phone":"+1 603 934 4240",
    "sg:postcode":"03269",
    "sg:province":"NH",
    "sg:website":"www.santbani.k12.nh.us",
    "wof:name":"Sant Bani School",
    "wof:placetype":"venue"
},
  "geometry": {"coordinates":[-71.65390600000001,43.524548],"type":"Point"}
}