{
  "type": "Feature",
  "properties": {
    "addr:full":"98 Blanford Pl Bedford NH 03110",
    "addr:housenumber":"98",
    "addr:postcode":"03110",
    "addr:street":"Blanford Pl",
    "iso:country":"US",
    "sg:address":"98 Blanford Pl",
    "sg:city":"Bedford",
    "sg:classifiers":[
        {
            "category":"Shopping",
            "subcategory":"Clothing, Apparel, & Fashions",
            "type":"Retail Goods"
        }
    ],
    "sg:phone":"+1 603 471 1641",
    "sg:postcode":"03110",
    "sg:province":"NH",
    "wof:name":"Prints Charming",
    "wof:placetype":"venue"
},
  "geometry": {"coordinates":[-71.562078,42.923683],"type":"Point"}
}