{
  "type": "Feature",
  "properties": {
    "addr:full":"431 Maple St Manchester NH 03103",
    "addr:housenumber":"431",
    "addr:postcode":"03103",
    "addr:street":"Maple St",
    "iso:country":"US",
    "sg:address":"431 Maple St",
    "sg:city":"Manchester",
    "sg:classifiers":[
        {
            "category":"Wholesale",
            "subcategory":"Plants",
            "type":"Manufacturing & Wholesale Goods"
        }
    ],
    "sg:phone":"+1 603 627 2114",
    "sg:postcode":"03103",
    "sg:province":"NH",
    "sg:tags":[
        "supply"
    ],
    "wof:name":"Barrett Wholesalers LLC",
    "wof:placetype":"venue"
},
  "geometry": {"coordinates":[-71.453002,42.990196],"type":"Point"}
}