{
  "type": "Feature",
  "properties": {
    "iso:country":"US",
    "sg:address":"42 Reservoir St",
    "sg:city":"Keene",
    "sg:classifiers":[
        {
            "category":"Building & Trades",
            "subcategory":"Cleaning & Sanitation",
            "type":"Services"
        }
    ],
    "sg:phone":"+1 603 357 1255",
    "sg:postcode":"03431",
    "sg:province":"NH",
    "sg:tags":[
        "maintenance"
    ],
    "wof:name":"Conrads Cleaning Service",
    "wof:placetype":"venue"
},
  "geometry": {"coordinates":[-72.265407,42.936331],"type":"Point"}
}