{
  "type": "Feature",
  "properties": {
    "addr:full":"3 Riverside Dr Greenland NH 03840",
    "addr:housenumber":"3",
    "addr:postcode":"03840",
    "addr:street":"Riverside Dr",
    "iso:country":"US",
    "sg:address":"3 Riverside Dr",
    "sg:city":"Greenland",
    "sg:classifiers":[
        {
            "category":"Building & Trades",
            "subcategory":"Construction",
            "type":"Services"
        }
    ],
    "sg:phone":"+1 603 436 4456",
    "sg:postcode":"03840",
    "sg:province":"NH",
    "sg:tags":[
        "contractor"
    ],
    "wof:name":"AGS Building & Remodeling",
    "wof:placetype":"venue"
},
  "geometry": {"coordinates":[-70.846138,43.03608],"type":"Point"}
}