{
  "type": "Feature",
  "properties": {
    "iso:country":"US",
    "sg:address":"800 Park Ave",
    "sg:city":"Keene",
    "sg:classifiers":[
        {
            "category":"Home & Garden",
            "subcategory":"Building Materials",
            "type":"Retail Goods"
        }
    ],
    "sg:phone":"+1 603 357 7544",
    "sg:postcode":"03431",
    "sg:province":"NH",
    "sg:tags":[
        "door"
    ],
    "wof:name":"Salem Door & Hardware Inc",
    "wof:placetype":"venue"
},
  "geometry": {"coordinates":[-72.321209,42.949711],"type":"Point"}
}