{
  "type": "Feature",
  "properties": {
    "iso:country":"US",
    "sg:address":"333 Birch Hill Rd",
    "sg:city":"New Durham",
    "sg:classifiers":[
        {
            "category":"Travel",
            "subcategory":"Campground",
            "type":"Entertainment"
        }
    ],
    "sg:phone":"+1 603 859 1955",
    "sg:postcode":"03855",
    "sg:province":"NH",
    "sg:tags":[
        "youth",
        "camp"
    ],
    "wof:name":"Birch Hill Summer Camp",
    "wof:placetype":"venue"
},
  "geometry": {"coordinates":[-71.132452,43.462683],"type":"Point"}
}