{
  "type": "Feature",
  "properties": {
    "iso:country":"US",
    "sg:address":"140 Sanborn St",
    "sg:city":"Franklin",
    "sg:classifiers":[
        {
            "category":"Education",
            "subcategory":"School",
            "type":"Public Place"
        }
    ],
    "sg:phone":"+1 603 934 5939",
    "sg:postcode":"03235",
    "sg:province":"NH",
    "wof:name":"Shark Unified Technologies",
    "wof:placetype":"venue"
},
  "geometry": {"coordinates":[-71.64049900000001,43.450945],"type":"Point"}
}