{
  "type": "Feature",
  "properties": {
    "iso:country":"US",
    "sg:address":"944 Laconia Rd",
    "sg:city":"Tilton",
    "sg:classifiers":[
        {
            "category":"Health Services",
            "subcategory":"Doctor",
            "type":"Services"
        }
    ],
    "sg:phone":"+1 603 528 1212",
    "sg:postcode":"03276",
    "sg:province":"NH",
    "sg:tags":[
        "dentist"
    ],
    "wof:name":"Winnisquam Dental PA",
    "wof:placetype":"venue"
},
  "geometry": {"coordinates":[-71.517263,43.500198],"type":"Point"}
}