{
  "type": "Feature",
  "properties": {
    "iso:country":"US",
    "sg:address":"18 Glance Rd",
    "sg:city":"Windham",
    "sg:classifiers":[
        {
            "category":"Retail",
            "subcategory":"Repair Shop",
            "type":"Services"
        }
    ],
    "sg:phone":"+1 603 882 4845",
    "sg:postcode":"03087",
    "sg:province":"NH",
    "sg:tags":[
        "water",
        "maintenance",
        "for",
        "treatment"
    ],
    "wof:name":"Interstate Wtr Wstwter Spclsts",
    "wof:placetype":"venue"
},
  "geometry": {"coordinates":[-71.34661699999999,42.787796],"type":"Point"}
}