{
  "type": "Feature",
  "properties": {
    "addr:full":"54 Manchester St Concord NH 03301",
    "addr:housenumber":"54",
    "addr:postcode":"03301",
    "addr:street":"Manchester St",
    "iso:country":"US",
    "sg:address":"54 Manchester St",
    "sg:city":"Concord",
    "sg:classifiers":[
        {
            "category":"Autos & Motor Vehicles",
            "subcategory":"Automobile Sales",
            "type":"Retail Goods"
        }
    ],
    "sg:phone":"+1 603 224 2519",
    "sg:postcode":"03301",
    "sg:province":"NH",
    "wof:name":"Banks Tracy Saabaa",
    "wof:placetype":"venue"
},
  "geometry": {"coordinates":[-71.51373599999999,43.191247],"type":"Point"}
}