{
  "type": "Feature",
  "properties": {
    "iso:country":"US",
    "sg:address":"150 Greenleaf Ave",
    "sg:city":"Portsmouth",
    "sg:classifiers":[
        {
            "category":"Personal",
            "type":"Services"
        }
    ],
    "sg:phone":"+1 603 427 0657",
    "sg:postcode":"03801",
    "sg:province":"NH",
    "sg:tags":[
        "consultant",
        "program",
        "health",
        "fitness"
    ],
    "wof:name":"Physical Advantage Personal",
    "wof:placetype":"venue"
},
  "geometry": {"coordinates":[-70.77047899999999,43.05894],"type":"Point"}
}