{
  "type": "Feature",
  "properties": {
    "iso:country":"US",
    "sg:address":"211 Fisherville Rd",
    "sg:city":"Concord",
    "sg:classifiers":[
        {
            "category":"Cinema",
            "subcategory":"Movie Rental",
            "type":"Entertainment"
        }
    ],
    "sg:phone":"+1 603 753 1044",
    "sg:postcode":"03303",
    "sg:province":"NH",
    "sg:tags":[
        "game",
        "video"
    ],
    "sg:website":"www.moviegallery.com",
    "wof:name":"Movie Gallery",
    "wof:placetype":"venue"
},
  "geometry": {"coordinates":[-71.584621,43.263869],"type":"Point"}
}