{
  "type": "Feature",
  "properties": {
    "addr:full":"115 Church St North Walpole NH 03609",
    "addr:housenumber":"115",
    "addr:postcode":"03609",
    "addr:street":"Church St",
    "iso:country":"US",
    "sg:address":"115 Church St",
    "sg:city":"North Walpole",
    "sg:classifiers":[
        {
            "category":"Food & Beverages",
            "subcategory":"Groceries & Convenience Stores",
            "type":"Retail Goods"
        }
    ],
    "sg:phone":"+1 603 445 5317",
    "sg:postcode":"03609",
    "sg:province":"NH",
    "sg:tags":[
        "grocer"
    ],
    "wof:name":"Discount Food Warehouse",
    "wof:placetype":"venue"
},
  "geometry": {"coordinates":[-72.451325,43.146477],"type":"Point"}
}