{
  "type": "Feature",
  "properties": {
    "addr:full":"17 Alder Ave Rye NH 03870",
    "addr:housenumber":"17",
    "addr:postcode":"03870",
    "addr:street":"Alder Ave",
    "iso:country":"US",
    "sg:address":"17 Alder Ave",
    "sg:city":"Rye",
    "sg:classifiers":[
        {
            "category":"Building & Trades",
            "subcategory":"Construction",
            "type":"Services"
        }
    ],
    "sg:phone":"+1 603 964 9892",
    "sg:postcode":"03870",
    "sg:province":"NH",
    "sg:tags":[
        "house"
    ],
    "wof:name":"Ender Bldr Richard",
    "wof:placetype":"venue"
},
  "geometry": {"coordinates":[-70.765401,42.98996],"type":"Point"}
}