{
  "type": "Feature",
  "properties": {
    "iso:country":"US",
    "sg:address":"210 N State St",
    "sg:city":"Concord",
    "sg:classifiers":[
        {
            "category":"Real Estate",
            "subcategory":"Real Estate Agent",
            "type":"Services"
        }
    ],
    "sg:phone":"+1 603 415 0130",
    "sg:postcode":"03301",
    "sg:province":"NH",
    "sg:tags":[
        "appraiser"
    ],
    "wof:name":"Cross Country Appraisal Group",
    "wof:placetype":"venue"
},
  "geometry": {"coordinates":[-71.550656,43.219889],"type":"Point"}
}