{
  "type": "Feature",
  "properties": {
    "addr:full":"244 N Main St Concord NH 03301",
    "addr:housenumber":"244",
    "addr:postcode":"03301",
    "addr:street":"N Main St",
    "iso:country":"US",
    "sg:address":"244 N Main St",
    "sg:city":"Concord",
    "sg:classifiers":[
        {
            "category":"Government",
            "subcategory":"Office",
            "type":"Public Place"
        }
    ],
    "sg:phone":"+1 603 271 2158",
    "sg:postcode":"03301",
    "sg:province":"NH",
    "sg:tags":[
        "greyhound",
        "horse",
        "racing"
    ],
    "wof:name":"Greyhound & Horse Racing",
    "wof:placetype":"venue"
},
  "geometry": {"coordinates":[-71.540605,43.214397],"type":"Point"}
}