{
  "type": "Feature",
  "properties": {
    "addr:full":"17 Skylark Dr Derry NH 03038",
    "addr:housenumber":"17",
    "addr:postcode":"03038",
    "addr:street":"Skylark Dr",
    "iso:country":"US",
    "sg:address":"17 Skylark Dr",
    "sg:city":"Derry",
    "sg:classifiers":[
        {
            "category":"Social Services",
            "type":"Services"
        }
    ],
    "sg:phone":"+1 603 548 9469",
    "sg:postcode":"03038",
    "sg:province":"NH",
    "sg:tags":[
        "aid",
        "first"
    ],
    "wof:name":"New England Cpr and First Aid",
    "wof:placetype":"venue"
},
  "geometry": {"coordinates":[-71.28758999999999,42.856886],"type":"Point"}
}