{
  "type": "Feature",
  "properties": {
    "iso:country":"US",
    "sg:address":"152 Middle Rd",
    "sg:city":"Ctr Tuftonboro",
    "sg:classifiers":[
        {
            "category":"Retail",
            "subcategory":"Auto Repair",
            "type":"Services"
        }
    ],
    "sg:phone":"+1 603 569 9133",
    "sg:postcode":"03816",
    "sg:province":"NH",
    "sg:tags":[
        "repairing",
        "automobile",
        "automotive"
    ],
    "wof:name":"Tuftonboro Repair",
    "wof:placetype":"venue"
},
  "geometry": {"coordinates":[-71.250047,43.657272],"type":"Point"}
}