{
  "type": "Feature",
  "properties": {
    "iso:country":"US",
    "sg:address":"14 Pierce St",
    "sg:city":"Dover",
    "sg:classifiers":[
        {
            "category":"Manufacturing",
            "subcategory":"Tools & Machinery",
            "type":"Manufacturing & Wholesale Goods"
        }
    ],
    "sg:phone":"+1 603 740 6363",
    "sg:postcode":"03820",
    "sg:province":"NH",
    "sg:tags":[
        "adhesive",
        "gluing",
        "equipment"
    ],
    "wof:name":"Valco Cincinnati",
    "wof:placetype":"venue"
},
  "geometry": {"coordinates":[-70.872767,43.200379],"type":"Point"}
}