{
  "type": "Feature",
  "properties": {
    "iso:country":"US",
    "sg:address":"110 Perimeter Rd",
    "sg:city":"Nashua",
    "sg:classifiers":[
        {
            "category":"Home & Garden",
            "subcategory":"Building Materials",
            "type":"Retail Goods"
        },
        {
            "category":"Professional",
            "subcategory":"Printing & Photocopies",
            "type":"Services"
        },
        {
            "category":"Manufacturing",
            "subcategory":"Building Materials",
            "type":"Manufacturing & Wholesale Goods"
        },
        {
            "category":"Building & Trades",
            "subcategory":"Locksmith",
            "type":"Services"
        }
    ],
    "sg:phone":"+1 503 661 2730",
    "sg:postcode":"03063",
    "sg:province":"NH",
    "sg:tags":[
        "repair",
        "industrial-sales",
        "door-overhead",
        "doors-commercial",
        "device",
        "door",
        "type",
        "doors-operating"
    ],
    "sg:website":"http://wayne-dalton.com/",
    "wof:name":"Quality Insulation",
    "wof:placetype":"venue"
},
  "geometry": {"coordinates":[-71.516266,42.778649],"type":"Point"}
}