{
  "type": "Feature",
  "properties": {
    "addr:full":"130 Knowlton St Manchester NH 03103",
    "addr:housenumber":"130",
    "addr:postcode":"03103",
    "addr:street":"Knowlton St",
    "iso:country":"US",
    "sg:address":"130 Knowlton St",
    "sg:city":"Manchester",
    "sg:classifiers":[
        {
            "category":"Manufacturing",
            "subcategory":"Retail Goods",
            "type":"Manufacturing & Wholesale Goods"
        }
    ],
    "sg:phone":"+1 603 627 9718",
    "sg:postcode":"03103",
    "sg:province":"NH",
    "sg:tags":[
        "product",
        "mfg"
    ],
    "wof:name":"Duct Wear",
    "wof:placetype":"venue"
},
  "geometry": {"coordinates":[-71.43248,42.976415],"type":"Point"}
}