{
  "type": "Feature",
  "properties": {
    "iso:country":"US",
    "sg:address":"1 Webb Pl",
    "sg:city":"Dover",
    "sg:classifiers":[
        {
            "category":"Health Services",
            "subcategory":"Clinic",
            "type":"Services"
        },
        {
            "category":"Health Services",
            "subcategory":"Doctor",
            "type":"Services"
        }
    ],
    "sg:phone":"+1 603 749 7979",
    "sg:postcode":"03820",
    "sg:province":"NH",
    "sg:tags":[
        "physician",
        "surgeon"
    ],
    "wof:name":"Peter Richards MD",
    "wof:placetype":"venue"
},
  "geometry": {"coordinates":[-70.888288,43.221099],"type":"Point"}
}