{
  "type": "Feature",
  "properties": {
    "addr:full":"660 Chestnut St Manchester NH 03104",
    "addr:housenumber":"660",
    "addr:postcode":"03104",
    "addr:street":"Chestnut St",
    "iso:country":"US",
    "sg:address":"660 Chestnut St",
    "sg:city":"Manchester",
    "sg:classifiers":[
        {
            "category":"Professional",
            "subcategory":"Accounting & Tax Preparation",
            "type":"Services"
        }
    ],
    "sg:phone":"+1 603 627 3838",
    "sg:postcode":"03104",
    "sg:province":"NH",
    "sg:tags":[
        "accountant",
        "public",
        "certified"
    ],
    "sg:website":"www.hrhcpa.com",
    "wof:name":"Howe Riley & Howe Prof",
    "wof:placetype":"venue"
},
  "geometry": {"coordinates":[-71.462107,43.001023],"type":"Point"}
}