{
  "type": "Feature",
  "properties": {
    "iso:country":"US",
    "sg:address":"223 Winchester St",
    "sg:city":"Keene",
    "sg:classifiers":[
        {
            "category":"Shopping",
            "subcategory":"Clothing, Apparel, & Fashions",
            "type":"Retail Goods"
        }
    ],
    "sg:phone":"+1 603 358 3001",
    "sg:postcode":"03431",
    "sg:province":"NH",
    "sg:tags":[
        "riding",
        "equipment"
    ],
    "sg:website":"www.cheshirehorse.com",
    "wof:name":"Cheshire Horse",
    "wof:placetype":"venue"
},
  "geometry": {"coordinates":[-72.28684699999999,42.92703],"type":"Point"}
}