{
  "type": "Feature",
  "properties": {
    "addr:full":"41 Bridge St Nashua NH 03060",
    "addr:housenumber":"41",
    "addr:postcode":"03060",
    "addr:street":"Bridge St",
    "iso:country":"US",
    "sg:address":"41 Bridge St",
    "sg:city":"Nashua",
    "sg:classifiers":[
        {
            "category":"Retail",
            "subcategory":"Auto Repair",
            "type":"Services"
        }
    ],
    "sg:phone":"+1 603 883 4593",
    "sg:postcode":"03060",
    "sg:province":"NH",
    "sg:tags":[
        "repairing",
        "automobile",
        "general"
    ],
    "wof:name":"Beebie's Auto",
    "wof:placetype":"venue"
},
  "geometry": {"coordinates":[-71.45005999999999,42.763543],"type":"Point"}
}