{
  "type": "Feature",
  "properties": {
    "iso:country":"US",
    "sg:address":"14 Manning Hill Rd",
    "sg:city":"Winchester",
    "sg:classifiers":[
        {
            "category":"Shopping",
            "subcategory":"Discount & Variety Stores",
            "type":"Retail Goods"
        }
    ],
    "sg:phone":"+1 603 239 7559",
    "sg:postcode":"03470",
    "sg:province":"NH",
    "sg:tags":[
        "merchandise",
        "general"
    ],
    "wof:name":"Katie's Dollar & Up",
    "wof:placetype":"venue"
},
  "geometry": {"coordinates":[-72.389746,42.766511],"type":"Point"}
}