{
  "type": "Feature",
  "properties": {
    "iso:country":"US",
    "sg:address":"15 Main St",
    "sg:city":"Keene",
    "sg:classifiers":[
        {
            "category":"Banks & Credit Unions",
            "subcategory":"Bank",
            "type":"Services"
        }
    ],
    "sg:phone":"+1 603 352 5050",
    "sg:postcode":"03431",
    "sg:province":"NH",
    "wof:name":"Citizens Bank",
    "wof:placetype":"venue"
},
  "geometry": {"coordinates":[-72.27855599999999,42.933183],"type":"Point"}
}