{
  "type": "Feature",
  "properties": {
    "addr:full":"101 E Industrial Park Dr Manchester NH 03109",
    "addr:housenumber":"101",
    "addr:postcode":"03109",
    "addr:street":"E Industrial Park Dr",
    "iso:country":"US",
    "sg:address":"101 E Industrial Park Dr",
    "sg:city":"Manchester",
    "sg:classifiers":[
        {
            "category":"Wholesale",
            "subcategory":"Durable Goods & Equipment",
            "type":"Manufacturing & Wholesale Goods"
        }
    ],
    "sg:phone":"+1 603 626 1909",
    "sg:postcode":"03109",
    "sg:province":"NH",
    "sg:tags":[
        "representative",
        "manufacturer"
    ],
    "sg:website":"www.jandksales.com",
    "wof:name":"J & K Sales Assoc",
    "wof:placetype":"venue"
},
  "geometry": {"coordinates":[-71.40983300000001,42.970591],"type":"Point"}
}