{
  "type": "Feature",
  "properties": {
    "iso:country":"US",
    "sg:address":"14 River Rd",
    "sg:city":"New Boston",
    "sg:classifiers":[
        {
            "category":"Building & Trades",
            "subcategory":"Construction",
            "type":"Services"
        }
    ],
    "sg:phone":"+1 603 487 5142",
    "sg:postcode":"03070",
    "sg:province":"NH",
    "sg:tags":[
        "house"
    ],
    "wof:name":"Strausbaugh Building & Rmdlg",
    "wof:placetype":"venue"
},
  "geometry": {"coordinates":[-71.690502,42.977829],"type":"Point"}
}