{
  "type": "Feature",
  "properties": {
    "iso:country":"US",
    "sg:address":"25 Pleasant St",
    "sg:city":"Berlin",
    "sg:classifiers":[
        {
            "category":"Travel",
            "subcategory":"Hotels & Motels",
            "type":"Entertainment"
        }
    ],
    "sg:phone":"+1 603 752 1551",
    "sg:postcode":"03570",
    "sg:province":"NH",
    "sg:tags":[
        "operation"
    ],
    "wof:name":"J S K LLC",
    "wof:placetype":"venue"
},
  "geometry": {"coordinates":[-71.185608,44.464806],"type":"Point"}
}