{
  "type": "Feature",
  "properties": {
    "iso:country":"US",
    "sg:address":"445 US Hwy 1 Byp",
    "sg:city":"Portsmouth",
    "sg:classifiers":[
        {
            "category":"Real Estate",
            "subcategory":"Surveying",
            "type":"Services"
        }
    ],
    "sg:phone":"+1 603 436 3557",
    "sg:postcode":"03801",
    "sg:province":"NH",
    "sg:tags":[
        "surveyor",
        "land"
    ],
    "wof:name":"Verra James & Assoc Inc",
    "wof:placetype":"venue"
},
  "geometry": {"coordinates":[-70.77876500000001,43.069873],"type":"Point"}
}