{
  "type": "Feature",
  "properties": {
    "iso:country":"US",
    "sg:address":"26 Wright Ave",
    "sg:city":"Merrimack",
    "sg:classifiers":[
        {
            "category":"Building & Trades",
            "subcategory":"Construction",
            "type":"Services"
        }
    ],
    "sg:phone":"+1 603 424 4731",
    "sg:postcode":"03054",
    "sg:province":"NH",
    "sg:tags":[
        "contractor"
    ],
    "wof:name":"J & S Patterson",
    "wof:placetype":"venue"
},
  "geometry": {"coordinates":[-71.48782199999999,42.854296],"type":"Point"}
}