{
  "type": "Feature",
  "properties": {
    "iso:country":"US",
    "sg:address":"46 Main St",
    "sg:city":"Exeter",
    "sg:classifiers":[
        {
            "category":"Retail",
            "subcategory":"Auto Repair",
            "type":"Services"
        }
    ],
    "sg:phone":"+1 603 778 1111",
    "sg:postcode":"03833",
    "sg:province":"NH",
    "sg:tags":[
        "repairing",
        "automobile",
        "radiator"
    ],
    "wof:name":"Exeter Main St Mobile",
    "wof:placetype":"venue"
},
  "geometry": {"coordinates":[-70.954125,42.98213],"type":"Point"}
}