{
  "type": "Feature",
  "properties": {
    "addr:full":"193 Rockingham Rd Derry NH 03038",
    "addr:housenumber":"193",
    "addr:postcode":"03038",
    "addr:street":"Rockingham Rd",
    "iso:country":"US",
    "sg:address":"193 Rockingham Rd",
    "sg:city":"Derry",
    "sg:classifiers":[
        {
            "category":"Professional",
            "subcategory":"Business Services",
            "type":"Services"
        }
    ],
    "sg:phone":"+1 603 425 6860",
    "sg:postcode":"03038",
    "sg:province":"NH",
    "wof:name":"Recovery Solutions",
    "wof:placetype":"venue"
},
  "geometry": {"coordinates":[-71.281812,42.857073],"type":"Point"}
}