{
  "type": "Feature",
  "properties": {
    "iso:country":"US",
    "sg:address":"266 Fremont Rd",
    "sg:city":"Sandown",
    "sg:classifiers":[
        {
            "category":"Building & Trades",
            "subcategory":"Construction",
            "type":"Services"
        }
    ],
    "sg:phone":"+1 603 887 2648",
    "sg:postcode":"03873",
    "sg:province":"NH",
    "sg:tags":[
        "contractor"
    ],
    "wof:name":"NW Albee Enterprises",
    "wof:placetype":"venue"
},
  "geometry": {"coordinates":[-71.159024,42.952141],"type":"Point"}
}