{
  "type": "Feature",
  "properties": {
    "iso:country":"US",
    "sg:address":"40 Canal St",
    "sg:city":"Nashua",
    "sg:classifiers":[
        {
            "category":"Restaurant",
            "type":"Food & Drink"
        }
    ],
    "sg:phone":"+1 603 886 8998",
    "sg:postcode":"03064",
    "sg:province":"NH",
    "wof:name":"Julie's Boutique",
    "wof:placetype":"venue"
},
  "geometry": {"coordinates":[-71.46095200000001,42.764304],"type":"Point"}
}