{
  "type": "Feature",
  "properties": {
    "iso:country":"US",
    "sg:address":"76 Allds St",
    "sg:city":"Nashua",
    "sg:classifiers":[
        {
            "category":"Health Services",
            "subcategory":"Doctor",
            "type":"Services"
        },
        {
            "category":"Personal",
            "subcategory":"Hair Removal",
            "type":"Services"
        },
        {
            "category":"Personal",
            "subcategory":"Skin Care",
            "type":"Services"
        }
    ],
    "sg:phone":"+1 603 889 4149",
    "sg:postcode":"03060",
    "sg:province":"NH",
    "sg:tags":[
        "dermatology",
        "physician",
        "surgeon",
        "surgeons"
    ],
    "sg:website":"http://www.nhskin.com",
    "wof:name":"Dermatology Associates of Southern New Hampshire",
    "wof:placetype":"venue"
},
  "geometry": {"coordinates":[-71.45378100000001,42.754421],"type":"Point"}
}