{
  "type": "Feature",
  "properties": {
    "iso:country":"US",
    "sg:address":"66 Prospect St",
    "sg:city":"Rochester",
    "sg:classifiers":[
        {
            "category":"Health Services",
            "subcategory":"Chiropractor",
            "type":"Services"
        }
    ],
    "sg:phone":"+1 603 335 3580",
    "sg:postcode":"03867",
    "sg:province":"NH",
    "wof:name":"Latella Rene",
    "wof:placetype":"venue"
},
  "geometry": {"coordinates":[-70.964968,43.308587],"type":"Point"}
}