{
  "type": "Feature",
  "properties": {
    "iso:country":"US",
    "sg:address":"20 Commercial Ct",
    "sg:city":"Auburn",
    "sg:classifiers":[
        {
            "category":"Retail",
            "subcategory":"Auto Repair",
            "type":"Services"
        }
    ],
    "sg:phone":"+1 603 622 4999",
    "sg:postcode":"03032",
    "sg:province":"NH",
    "sg:tags":[
        "automotive"
    ],
    "wof:name":"Southern NH Wrecker",
    "wof:placetype":"venue"
},
  "geometry": {"coordinates":[-71.354778,42.957952],"type":"Point"}
}