{
  "type": "Feature",
  "properties": {
    "addr:full":"206 Washington St Keene NH 03431",
    "addr:housenumber":"206",
    "addr:postcode":"03431",
    "addr:street":"Washington St",
    "iso:country":"US",
    "sg:address":"206 Washington St",
    "sg:city":"Keene",
    "sg:classifiers":[
        {
            "category":"Professional",
            "subcategory":"Management & Consulting",
            "type":"Services"
        }
    ],
    "sg:phone":"+1 603 357 5118",
    "sg:postcode":"03431",
    "sg:province":"NH",
    "wof:name":"Valic",
    "wof:placetype":"venue"
},
  "geometry": {"coordinates":[-72.276625,42.940037],"type":"Point"}
}