{
  "type": "Feature",
  "properties": {
    "addr:full":"393 Laconia Rd Belmont NH 03220",
    "addr:housenumber":"393",
    "addr:postcode":"03220",
    "addr:street":"Laconia Rd",
    "iso:country":"US",
    "sg:address":"393 Laconia Rd",
    "sg:city":"Belmont",
    "sg:classifiers":[
        {
            "category":"Freight",
            "type":"Transportation"
        }
    ],
    "sg:phone":"+1 603 527 9229",
    "sg:postcode":"03220",
    "sg:province":"NH",
    "sg:tags":[
        "commercial",
        "storage"
    ],
    "wof:name":"Belmont Self Storage",
    "wof:placetype":"venue"
},
  "geometry": {"coordinates":[-71.509922,43.501655],"type":"Point"}
}